Workbook

Sheet README
A1: Tokenomics v15.0 — Block 1＋2＋3＋4＋5＋6＋第 0 層 Source：機架規格、每 GW 成本、各層級產出與每 token 成本、訓練與研發計畫、理論營收與單價前緣、harness 與每成功任務成本、研發與服務算力配置（Alloc）、L1 常用推算值、Interface 下游介面
A2: 第 0 層規格來源。理論營收為理想上限；實際營收在下游模型。
A4: 用途 | B4: 回答：每 1 GW IT 電力，各世代可容納多少機架、資本支出與持有成本（Block 1）；各層級 SLO 下的產出與依『世代 × 層級 × token 類型』的每 M token 成本（Block 2）；各層級代表模型的訓練與研發計畫需要多少 GPU 小時、成本與 1 GW 年，其中後訓練占多少（Block 3）；每 GW 的理論營收（理想上限）、含中國廠商的單價前緣、訓練攤提、快取儲存與 1 GW 參考機隊（Block 4）；harness 對每個成功任務的 token、成本與成功率的影響（Block 5）。實際營收（需求、市占、訂閱方案）在下游。
A5: 版本 | B5: 20261017_Tokenomics_v15.0（主版：工作單 docs/workorders/20261017_v14.3_稽核結案.md（r1）——O13 推論支出區間（Alloc Q 節、RNG_Dem004_*、Checks RG4）；O14 L1 外部對照換算同一單位；O15 B11 守衛 IF_FrontSuccVRQual、B20 口徑、Y9 敏感度端點、F16 註記；O9 V16 改標恆等式（驗證計數 22 → 21）；O6 SRC_Index 哨兵列；O20 κ 推導區塊；O5 SRC_PERF_060 來源登錄更正（556 為 NVIDIA 自測、非 MLCommons 結果）；O4 VR200 批次倍數區間（12 個名稱）；Decisions SL46-*）。以下為 v14.2（次版：工作單 docs/workorders/20261017_v14.2修補.md——S1 L1_MFleet_P25Lo／P25Hi（Cap_In 第 285、286 列）各欄比照 v14.1 R1 截在同欄同單價下限（MAX(點估計, 營收 ÷（第 118 列 × 該列單價)）；低端欄 P25Lo 0.3535 → 0.4141、P25Hi 0.1066 → 0.1249，L1_MFleet 三端與其他名稱不變）；S2 Har_In 第 20、32 列 A、B 標籤清空；S3 工程小項；Decisions SL45-*）。以下為 v14.1（次版：工作單 docs/workorders/20261017_v14.1修補.md——R1 機隊 m 低端改用同欄下限（Cap_In 第 119 列各欄＝MAX(點估計, 第 121 列同欄)；L1_MFleet_Lo 0.184 → 0.215，基準與高端不變）；R2 Checks V23、V24 標恆等式（驗證計數 24／16／7／1 → 22／14／7／1）；R3 Har_In 第 20、32 列供應商旗標清空；R4 v14.0 刪除列的 A、B 標籤清空；R5 Cap_In 24 格清空；R6 v14.0 獨立查核小項（GM629 註記、三筆用途更正、過時錨點文字）；Decisions SL44-*）。以下為 v14.0（主版：工作單 docs/workorders/20261017_4-3B.md——4-3 B 段依 A 段建議執行瘦身：刪除 73 列未接線的計算格（509＋5 格）與兩個無人使用的名稱；新增 18 個契約名稱（Interface M 節 IF_TaskTokMult、IF_TrainFLOP_／IF_TrainInferShare_／IF_GMDefault_ 三層級、IF_AmortRevShare；Cap_In 序列 L1_*_Ser 與 L1_MFleet_P25Lo／Hi）；Checks 新增 V23–V26 並計入驗證項目數、D104／D140 改讀 Alloc_In；保留的顯示用 155 列與新增死格補用途標記；既有 IF_／IFW_／L1_／RNG_ 數值不變）。以下為 v13.1（次版：工作單 docs/workorders/20261017_D15_B段.md——P1 D15 來源補齊（Gov_Map 312 列補 J／H 欄、Decisions D15-01…12、新 SRC：SRC_DC_018／019、SRC_PRC_045／046、SRC_HW_069／070，DB_Evidence R 欄與 E381–E386，Arch E6–E8 標記更正，SRC_PERF_060 待回查）；P2 查核 #96 小項（VR200 欄為點值的說明、區間時效指紋 Alloc P 節與 Checks RG3、C68 O 欄文字）；數值全部不變）。以下為 v13.0（主版：工作單 docs/workorders/20261017_4-2b.md 第 1 節（4-2b-1）——K1 批次口徑倍數區間（RNG_<名稱>_Lo／_Hi，Alloc O 節）；K2 區間時效（RNG_Version、RNG_StaleFlag、Checks RG1／RG2、parity 逐格重算）；K3 C68 類別更正為 Assumed 並進入 Load_Bearing；K4 『Pass＋Fail＋Warn＝Total』標恆等式；K5 名稱數更正；Decisions BB3-*）。以下為 v12.0（主版：v11.1 修補，工作單 docs/workorders/20261016_v11.1修補.md——H1 Checks V1–V3 軟上限加失敗門檻 CHK_SoftCapFail（新契約名稱）；H2 CAL_BatchEtaD GB200 2.36（兩點幾何平均，區間 1.83–3.04），V20 改校準相關；H3 Hopper 維持 1（已知低估、無解，區間 1–3.74）；H4 C68 更正註記（Assumed，無來源，區間 1.0–1.5）；H5 研發 GW 與 Q1 區間（Alloc N 節）；H6 文字；H7 V19 重算比對、V18 標恆等式；Decisions BB2-*）。以下為 v11.0（主版：大批次修正，工作單 docs/workorders/20261016_大批次修正.md——G1 C68 追查（無法確認重複計算，不改）；G2 CAL_BatchEtaD GB200＝3.04（Hopper 無解不寫入）、Calib J 節 C／D 欄改批次口徑；G3 新增 V20–V22（MLPerf offline、TensorRT-LLM H200；Calib L 節）；G4 V1–V3 改軟上限、新增 CHK_VerifyWarn；Decisions BB-*）。以下為 v10.3（次版：瘦身 4-2a，工作單 docs/workorders/20261016_瘦身4-2.md（4-2a 段）——F1 寫死參數外露（L1_JudgeTol、SR_RU_PxMultLo／Hi；物理慣例加註）；F2 重複定義（Sens_Rev 商業壽命、Cap_In H10 2025 欄改引用）；F3 Tech_Registry K／T 進 Checks V（V18／V19）；F4 用途標記；Decisions SL42-*。既有 IF_／IFW_／L1_ 名稱數值不變，只有 CHK_Verify* 變動）。以下為 v10.2（次版：η 校準與驗證判準，工作單 docs/workorders/20261016_η校準.md（分支 claude/batch4-wo，PR #78）——E1 Calib J 節複本列（Hopper 校準點 DeepSeek profile、GB200 校準點 vLLM WideEP；停損：C67／D67 不寫入）；E2 Serving SLO 改兩家量測商中位數的幾何平均（84.3／43.3／40.8），舊值留作情境 slo_v10；E3 Checks V2／V3 對照更新、V7／V8 條件對齊、V13／V14 上限、新增 V15、B26／B36 改回 V16／V17；E4 Perf_Batch R–S 標註；Decisions ETA-*）。以下為 v10.1（次版，工程類：瘦身 4-1，工作單 docs/workorders/20261016_瘦身4.md 第 1 節（4-1 段）——1-a 刪除無人讀取的格（Capability 頁、L1 O 欄、Alloc 診斷格、Perf 速覽列）；1-b 標記顯示用／未接線／複本讀取、補黃底；1-c 過時說明文字改引用現值；1-d Gov_Map 登錄整理；1-e 新增永久測試。所有既有具名範圍與契約名稱的值不變）。以下為 v10.0（主版：稽核修正第 2 批 2-5 段，工作單 docs/workorders/20261016_稽核修正2.md r1 第 6r1 節——D12：Interface L 節 IFW_*_LifeSelf（自算 L、m 情境，不回流）；D4：L1 性質欄與未解釋列；D5：Checks 性質欄、V 節驗證計數 CHK_Verify*、MLPerf 上限檢查（Calib H 節新增 Hopper／GB200 v5.1 server）、LMSYS 獨立驗證點、RL 與 harness 對照；2-4 後續標籤；Decisions AF2f-*）。以下為 v9.0（主版：稽核修正第 2 批 2-4 段，工作單 docs/workorders/20261016_稽核修正2.md r1 第 5r1 節——D9：快取命中進產能（Perf／Sens_Perf／_Prod 的 prefill 只計新鮮輸入；Perf_Batch 不變）、免費占比 token 口徑（Cap_In 第 87 列）、κ 套到價格端（Cap_In 第 90 列、CAP_Price25Mix）、IF_AmortRev_* 分母改付費 token；2-3 後續：需求路線 m 與 Cap_In 第 241 列改 2025 口徑、IF_AllocQ1_R2 改支出路線、L1_ExtServeGW 改回主口徑、L1_LReqFleet 判讀以恆等式讀法為主；Decisions AF2e-*）。以下為 v8.0（主版：稽核修正第 2 批 2-3 段，工作單 docs/workorders/20261016_稽核修正2.md r1 第 4r1 節——D2 年度口徑與 D14 服務 GW 主口徑：Cap_In M 節 2025 年度層級單價、Alloc K 節 AL_PriceFleet25 與 2025 機隊損益兩平、L1_MFleet／L1_LReqFleet／L1_PriceReqBE 改 2025 口徑；Alloc_In 研發世代組合與 Alloc J 節（AL_FamGWyr／AL_RefGWyr／AL_HoldTrain 依研發組合加權）；IF_AllocQ1／Q2／ServeGW 改支出路線（token 路線保留為 AL_Q1_Tok／AL_Q2_Tok／IF_AllocServeGW_Tok）；Checks B43 讀 AL_MixHopper、Z2；Astra Epoch 上限標示與隱含 token；Decisions AF2d-*）。以下為 v7.0（主版：稽核修正第 2 批 2-2 段，工作單 docs/workorders/20261016_稽核修正2.md r0 第 3 節——世代價格 B 段：Cap_In L 節世代上市間隔 CAP_GenGap_*、L1_GenPxThr_Rev_*／_Pay_* 門檻列（不含價格；契約第 4 節改寫）、DB_Evidence E366–E373；遺留：L1_FleetMargin／Checks K4 讀重解值（新增 L1_FleetProdRatio）、L1_GapUtil 乘生產折減、Interface A231 標題、Serving C18 固定 1.0（b_prod_derate 改驅動 CTL_ProdDerate）、Alloc 全 GB200／全 VR200 改純世代、Calib C68 標記倒推；Decisions AF2c-*）。以下為 v6.3（次版：稽核修正第 2 批 2-1b 段，工作單 docs/workorders/20261016_稽核修正2.md r1 第 2b 節——K1 機隊口徑單價與可達層級同口徑（Alloc I 節 AL_PriceGen／AL_PriceFleet、Cap_In K 節 B4_PriceFleet）；K2 整代不可達時不轉移世代權重（文字旗標『整代不可達』）；K3 TTFT 不可達的 decode 成本列輸出文字；J1 r1 依 2Q 報告修訂 ARCH_ScaleGen_Lo／_Hi 與情境 d1_model_scale；Decisions AF2b-K1／K2／K3）。以下為 v6.2（次版：稽核修正第 2 批 2-1 段，工作單 docs/workorders/20261016_稽核修正2.md r0——D1(c) 模型規模倍數（Spec_Rack 三列＋ARCH_ScaleGen*，基準 1，乘入 Perf 系第 28、32、33 列與 Training 系第 22 列）；TTFT 接進可達判斷（文字旗標『TTFT 不可達』）；Alloc 排除不可達層級後重新正規化（新增『未服務需求占比』）；Decisions AF2-D1c／AF2-TTFT／AF2-ALLOC）。以下為 v6.1（次版：稽核修正第 3B 批輸入值，工作單 docs/workorders/20261015_稽核修正3B.md r0——D3 Alloc_In 世代組合低／高改 2025 全年平均區間；D6 Calib C67 1.5 → 1.2（0.8–1.6，Derived）；D10 計價倍數 0.85（0.73–1.17）；D13 純利用率 0.41（0.3–0.65）並於 Cap_In 第 114、218、255 列改乘 CTL_ProdDerate（唯一公式修改），Serving C17／C18／C28 區間登錄、標記 Assumed；Q3 RL／輪數倍數只登錄區間（輪數敏感度區間 0.7–1.7）；Q6 Spec_Rack C16 與 Inputs H9／H17／H19 說明；Decisions AF3B-D3／D6／D10／D13／Q3／Q6）。以下為 v6.0（主版：下游契約定義變更，工作單 docs/workorders/20261015_稽核修正1.md r0——D7 `_Prod` 為重解 SLO 後的產能（IFW_TokGW_*_Prod 讀 Theory_Rev_Prod；m 下限與前緣單價改用重解後的付費產能比 AL_ProdRatioPaid），`_Life` 唯一定義為 IFW_*_Life（IF_*_Life 為過渡別名，下一個主版刪除），Checks Z1 為 _Prod 恆等式；D8 SLO 不可達輸出文字、不輸出 0（Perf／Training 消費端），Fleet_1GW 排除不可達層級並重新正規化；D11 回本溢價分母改為付費 token（IF_AmortBU_*／IF_FullCost_*／IF_FullCostDefault_* 上升）；Decisions D7／D8／D11）。以下為 v5.36（判斷類，工作單 docs/workorders/20261015_v5.36.md r0：token 分母閉合——推論支出改 OpenAI 端 SRC_DEM_004 8.4（區間 7.5–8.8；SRC_DEM_073 查核財報營業成本 7.5），Microsoft 端 SRC_DEM_018 12.6 改為對照列；計價倍數 2.0 → 1.3（1.0–1.6）；新增請求形狀修正 κ（1.0；0.65–1.2）取代 GapISL；落差分解改正（GapPrompt 有效倍數 1.3013、GapUtil 1.7143）與缺口恆等式（Cap_In J 節、Checks M5）；L1 新增 L1_ScaleServe2000、L1_PriceRealFleet／PriceRealDemand／PriceReqBE／PriceRho；DB_Evidence E344–E365、Decisions X45–X47；AL_ServeGWSpend 1.3471 → 0.8981、L1_ScaleServe 7.378 → 4.919、L1_MFleet 0.8098 → 0.7896；全部 IF_ 不變）。以下為 v5.35（判斷類，工作單 docs/workorders/20261014_v5.35.md r0：m 序列三項修正＋L 拆分——Cap_In H10 三分營收改以 m 分子營收為基底、廣告每欄各自輸入（Q1 0／Q2 0.5／FY2026 1.0）、2026 消費訂閱占付費 token 份額 0.65（2026 Q2 m_API 0.340、m_消費訂閱 5.399、m_商用席次 4.557、m_整體 1.343）；新增 I 節「L 拆分」L_total＝L_price × L_demote（基準 0.7412 × 0.867＝0.6426；g −0.10、T1 4、ρ 0.5、T＝IF_DeprLifeIT 6）與回本所需 L（m＝L1_MFleet 0.3645）；L1 新增 L1_LPrice、L1_LDemote、L1_LTotal、L1_LReqFleet；SRC_DEM_072、DB_Evidence E338–E343、Decisions X42–X44；既有 IF_、L1_ 數值全部不變；CTL_PriceLife／CTL_Monetize 不改）。以下為 v5.34（判斷類，工作單 docs/workorders/20261014_v5.34.md r0.1：變現率 m 細化——Cap_In 新增 H8「m 分拆」（營收三分 消費訂閱／商用席次／API × token 三分 → m_API 0.56、m_消費訂閱 4.26、m_商用席次 1.83、m_整體 1.743＝L1_MImplied；m_API＝折讓因子 × 隱含組合因子；訂閱 m 下限（方案上限讀法）；「必須為真」；J21 Anthropic 對照）、H9「token 帳三路線」（需求／機隊／上限、殘差、閉合解 τ* ≈ 13,950）、H10「m 季度序列」（2025／2026 Q1／Q2／FY2026；份額每欄各自輸入）；L1 新增 L1_MAPI、L1_MSub、L1_MSeat、L1_MixFactorAPI、L1_TokPerPromptClose、L1_MAPI_Anthropic；Checks M4；B4_Disc 高端 0.3 → 0.4（Cap_In E12；IF_Price* 不變）；SRC_DEM_069–071、DB_Evidence E325–E337、Decisions X35–X41；既有 IF_、L1_ 數值全部不變；CTL_Monetize 不改）。以下為 v5.33（判斷類，工作單 docs/workorders/20261012_v5.33.md r1；A 段查證 PR #40：付費 token 數量校準——Alloc_In 2025 基準年世代組合改 Hopper 0.6／GB200 0.4／GB300 0／VR200 0（J8）、每則提示 token 數高端 6,400 → 11,000（J9）；Cap_In 新增 H7「機隊口徑」（支出路線服務 GW ÷ Azure 倍數 × 利用率修正 → 機隊付費 token 點估計與上限 → 機隊 m、m 下限、「必須為真」三列、非文字對照）；L1 新增 L1_MFleet、L1_TokCeiling，Checks M2、M3；SRC_DEM_049–068、DB_Evidence E302–E324、Decisions X27–X34；IF_AllocQ1／Q1_R2／Q2／ServeGW／ImpliedNk 與 Alloc 相關 L1 隨世代組合改變，其餘 IF_ 不變；CTL_Monetize 不改）。以下為 v5.32（判斷類，工作單 docs/workorders/20261011_v5.32.md r1；A 段查證 PR #38：變現率 m 追蹤——Cap_In 新增 H 節「m 追蹤」（隱含 m＝付費營收 ÷（付費 token × 混合有效單價），訂閱、API、合併 × 模型 token、外部 token 兩種分母；程式代理對照列），L1 新增 L1_MImplied、L1_MImplied_Ext（外部欄＝CTL_Monetize），Checks M1（區間外 WARN）；SRC_DEM_019–048、DB_Evidence E279–E301、Decisions X21–X26；CTL_Monetize 與既有 IF_／L1_ 數值不變）。以下為 v5.31（判斷類，工作單 docs/workorders/20261008_v5.31.md r1；A 段查證 PR #34：J1 GB300 機架價格 4.0／5.0／6.5 → 4.0／4.3／5.0 $M；J2／J3 IT 維護改為機齡兩段（保固 3 年，保固期內 0.25／0.5／1.0%、期滿後 2／3／5%），Inputs 第 30 列改為壽命期等值費率公式（WACC、IT 折舊年限年金加權），Interface I 節（續）新增 IF_MaintITWarr、IF_MaintITPost、IF_WarrantyYrs；J4／J5 註記；J6 SRC_DC_014（IREN 29.0 $M/IT MW）與 L1_CapexITMW_GB300_vsIREN；DB_Evidence E263–E278；Decisions X16–X20）。以下為 v5.30（X15 定義更正，不改任何輸入值：(a) Interface J 節四層瀑布改為逐層累乘、單調遞減——IFW_*_Prod＝_Util × CTL_ProdDerate（營收列維持讀 G 節重解值；token 產能列改線性乘法）、IFW_*_Life＝_Prod × CTL_PriceLife × CTL_Monetize（營收列）；Front 四列 _Prod／_Life 改公式；Checks K3 改為來源比對＋單調檢查；(b) L1_HoldEconMW_* 改為不除以 1000（1 $B/GW＝1 $M/MW；GB300 0.0127 → 12.72 $M/MW/年）；(c) IFW_RevGW*／IFW_RevGWFleet*／IFW_RevGWFront* 四層與 IFW_TokGW_*_100 的 Decision Use 附「上限，不得作預測」（Checks K2 擴充）；其餘 IF_、L1 與模型頁數值逐格不變；Decisions X15a–c；工作單 docs/workorders/20261008_v5.30.md）。以下為 v5.29（X14 (a)–(m)：Interface 新增 R–U 輸出契約欄 Confidence／Decision Use／口徑層／最弱輸入更新日（IFC_；由公式自 Gov_Map 徙出，依賴列由 builder 反查）與 J 節四層瀑布 IFW_<name>_100／_Util／_Prod／_Life（8 個營收列、3 個 IF_TokGW 列）；L1 新增 L1_FleetBreakeven、L1_FleetMargin、L1_HoldEconMW_*、L1_TokMW_Gen_ratio_*、L1_HarVsGen_*、L1_PretrainFLOP_Astra_Ext、L1_AstraScale、L1_ScaleRD、L1_ScaleServe 與 token 對帳落差分解 L1_Gap*；新頁 Load_Bearing（高段 Assumed／Analogy 格清單）；SRC_Price 新增 X–AB 分層欄；Checks K 節；判斷類：新增 SRC_DEM_018（推論支出 Azure 帳單 12.6 $B，只用於支出路線服務 GW；SRC_DEM_004 8.4 維持 Active，供比例類公式——r2）、Alloc_In 每則提示 token 數 2,000 → 4,000（2,000–6,400）——L1_Ans1–3、L1_ExtServeGW／ExtDaily／ExtFreeShare 與 IF_Alloc* 連動改變；其餘 IF_ 與模型頁數值不變；DB_Evidence E256–E262；Decisions X14a–m、G16；工作單 docs/workorders/20261008_v5.29.md r1＋r2）。r2（2026-10-08，chat 端審查 PR #31 第九節）：SRC_DEM_004 與 SRC_DEM_018 兩筆並列 Active、只有支出路線服務 GW 用 018；Checks K4 改為比對含 CTL_ProdDerate × L × m 的 Theory_Rev 比值（應為 0）；反轉門檻改為 Gov_Map AK 欄（Excel 擁有，Load_Bearing K 欄以公式讀取）；L1_HoldEconMW_GB300、L1_FleetMargin 外部欄改「—」（對照改寫入讀法文字）。以下為 v5.27（X13：J8 證據與 L1 外部對照——SRC_MOD_055 登錄 Epoch 區間低 5e26／高 2e27，L1 第 36 列外部欄改連 _Lo／_Hi；L1 第 39 列（L1_Ans3）外部對照連 SRC_DEM_006（OpenAI 2025 訓練支出）；Grok-3 查核：Epoch 1e25 頁仍為 4.6e26，SRC_MOD_033 不改（E252）；SRC_Model 新增 SRC_MOD_057–062（Kimi K3 架構，純證據）；DB_Evidence E251–E255；Gov_Map 理由欄附註；Decisions X13；模型輸入值與所有模型頁數值不變；工作單 docs/workorders/20261008_v5.27.md）。以下為 v5.26（Interface 新增 I 節「DC_Cost 構件」：IF_DeprLifeIT、IF_DeprIT、IF_DeprFac、IF_AvgDraw、IF_PowerPrice、IF_MaintIT、IF_MaintFac、IF_StaffSW、IF_TaxIns、IF_OpexGW（DC_Cost 第 38–42、44–48 列，下游公司模型用）與加總核對列；數值與既有公式不變；工作單 docs/workorders/20261007_v5.26.md）。以下為 v5.25（X12：證據登錄——SRC_Demand 新增 SRC_DEM_014–017（OpenRouter《State of AI》，arXiv 2601.10088v1；純證據）、SRC_Model 新增 SRC_MOD_055（Epoch GPT-6 Astra 訓練算力 1.0001e27）、DB_Evidence E247–E250；L1 第 36 列（L1_PretrainFLOP_Astra）外部對照由 SRC_MOD_033 改為 SRC_MOD_055；Gov_Map GM248 區間下限 512→400；Decisions X11、X12；模型輸入值與所有模型頁數值不變；工作單 docs/workorders/20261007_v5.25.md）。以下為 v5.24（SRC_Perf 第 60–63 列（SRC_PERF_056–059）W 欄刪除 v5.21 遺留句「（第二來源欄依 W1 規則不手動填）」；數值與公式不變；工作單 docs/workorders/20261007_v5.24.md）。以下為 v5.23（X10：Perf_Batch 側新增 VR200 批次口徑 η_d 倍數 CAL_BatchEtaD（Calib I 節，VR200 基準 0.75、區間 0.70–1.0，其餘世代 1），Perf_Batch 與 Perf_Batch_Prod 第 53 列 C:Q 乘以該倍數（訓練相關輸出數值改變，營收與服務側 Perf 不變）；Decisions X10；SRC_Perf 第 56–63 列備註文字修正；工作單 docs/workorders/20261007_v5.23.md）。以下為 v5.22（X7：新增壽命期價格係數 L（CTL_PriceLife）與變現率 m（CTL_Monetize）兩個控制參數（Cap_In G 節，基準 1、區間 0.3–1.0），Interface H 節並列輸出 IF_RevGW_Luna／Sol／Astra_Life 與 IF_RevGWFleet_Life（＝對應基準列 × L × m），Checks X7 自我檢查；X8 補充：DB_Evidence E246（產業租金指數，L 的類比證據，不建 SRC）；X9 Q2：SRC_PERF_052–059 互填第二來源（W1 −8）；Decisions X7／X8／X9；既有 IF_RevGW_*、IF_RevGWFleet、L1 與 _Prod 列數值逐格不變；工作單 docs/workorders/20261006_v5.22.md）。以下為 v5.21（X6：X4 結案——MLPerf Inference v6.1 一手結果（summary.csv，repo HEAD 4bb63cd）寫入：SRC_Perf 027／028 升為 1 級、新增 SRC_PERF_052–059，DB_Evidence E245 取代 E244，Gov_Map GM344、Decisions X4／X6；Calib F67 與所有數值不改；Alloc_In G7 備註補區間；工作單 docs/workorders/20261006_v5.21.md）。以下為 v5.20（X3：X2 新高段 8 列補齊——DB_Evidence E236–E243、Gov_Map GM205／203／459／270／290／578 判 6.2 齊備、GM275／354 併入 Decisions C2；Alloc_In E7（N_refresh 區間上限）4 → 6；X4：DB_Evidence E244 記錄 Calib F67 衝突證據（F67 不改）；X5：Interface A3 與 README 加註攤提耦合；工作單 docs/workorders/20261006_v5.20.md）。以下為 v5.19（X1：Interface G 節新增七列生產折減並列輸出 IF_FullCost_Luna／Sol／Astra_Prod、IF_RevGW_Luna／Sol／Astra_Prod、IF_RevGWFleet_Prod，由新輸入格 CTL_ProdDerate（Serving!C28，預設 0.85）驅動，推導鏈以 8 個 *_Prod 鏡像頁重算，Checks X1 自我檢查；Serving!C18 維持 1.0（G0-11）；X2：Gov_Map P 欄升段 11 格；Decisions 新增 X1、X2；既有模型頁、Interface 既有列、L1 數值逐格不變；工作單 docs/workorders/20261006_v5.19.md）。以下為 v5.18（Stage 2 第一批寫入，工作單 docs/workorders/20261005_v5.18.md r2：SRC 等級依 S1 (a)、G15、H1 規則升級並登錄 DB_Evidence；Train_In C44、Calib C69 改公式；SRC_PERF_009／010 改為內插值；Arch KV 區間、Hopper 占機隊 0.57、Train_In C21 Hopper 倍數 1.0、SRC_MOD_015 拆為 Flash／Pro 兩筆；VR200 機架功率與價格、GB200／GB300 機架功率更新；Rubin Ultra 欄改為單架 72 封裝並新增 SRC_HW_061–064、SRC_MOD_054；Workload／Serving 區間依 Copilot 追蹤擴大；Gov_Map P 欄改 B 法「O＋L1」分段；Checks 第 21 列改述為 InferenceX 內部常數）。以下為 v5.17（收尾小項：L1!I43 讀法文字改為「依定義 ≥ 1」；數值與公式不變）。以下為 v5.16（L1 Answers 修正：第 5 題新增理論毛利率兩列（L1_Ans5_GM 毛利口徑、L1_Ans5_FullMargin 全成本口徑；毛利口徑附 2025 推論毛利隱含值對照）；第 6 題拆為 FLOPs 口徑（L1_Ans6）與 GPU 小時口徑（L1_Ans6_GPUh）；第 7 題改為 OpenAI 單價 ÷ 前緣單價；第 8 題改連 IF_HarR_Sol（選定 ÷ 標準）；L1 欄位約定：D＝基準、E＝低、F＝高，無區間時 E＝F＝D；Checks 新增 H3（L1 的 E ≤ D ≤ F 檢查，WARN）。模型頁、Interface、SRC、Gov_Map 不動）。以下為 v5.15（Block 6 Alloc：研發與服務的算力配置。新增 Alloc_In（輸入：N_major、N_refresh、k、服務世代組合、g、API 全年平均比例、每則提示 token 數、免費占比；全部 Assumed 或 Decision，附區間，登錄 Gov_Map）與 Alloc（需求 D → 服務 GW → 研發 GW → Q1、Q2 → 校準反推 → 外部對照 → 敏感度表）；Interface F 節新增 IF_AllocQ1、IF_AllocQ1_R2、IF_AllocQ2、IF_AllocServeGW、IF_AllocRDGW、IF_AllocDemand、IF_AllocImpliedNk；L1 新增 Answers 9 題（L1_Ans1–9）與外部對照 3 列；SRC_Demand 新增 SRC_DEM_010–013，DB_Evidence 新增 E166–E169，Decisions 新增 A9、A10 並將 A1–A8 狀態改為「v5.15 已建」；Checks 新增 H 節（H1 世代組合合計、H2 敏感度自我檢查），計入 GOV_Errors；既有模型頁、Interface 既有列、既有 L1 列的數值逐格不變）。以下為 v5.14（L1 第 O、P 欄加檢查 D 欄是否為數字：v5.13 在 SLO 不可達情境（生產折減 0.7、Tech_Registry T07–T09 開啟）下 L1!O35、P35 出現錯誤值，CC 第 13 輪發現；SRC 各頁 X 欄的比對範圍改為與 SRC_Index 相同（最後一筆紀錄＋50 列），全簿重算約減三成；基準數值不變；Block 6 改為 v5.15）。以下為 v5.13（切片二 B–E 包：Source 遷入、Gov_Map 擴及切片二頁、模型邏輯、寫回 Andy 審閱；v5.13 E：v5.11、C 包、D 包審閱檔 Andy 2026-10-03 全部依建議，寫入 Gov_Map 與 Decisions（原話 83 項確認、CV1 維持 4×HGX、G0-9 文字修正、輪數下限與快取命中區間修正）；Block 6 於 v5.14。v5.13 D：Arch 第 21–23 列 KV bytes 改公式（新增「KV 推導輸入」5 列），Arch C9、C10 連結 V4-Flash 官方 config（SRC_MOD_052、053），Cap_In 中國廠商旗標改公式，Checks 的外部比對移入 L1（新增 7 列）、樣本外實測值連結 SRC_Perf；數值不變。v5.13 C：切片二頁 515 個數值藍字格登錄 Gov_Map 129 列（分類、可比 SRC、區間、理由；Andy 2026-10-03 審閱「all ok」），Checks E12 擴及全部範圍。v5.13 B：新增 SRC_Price 44、SRC_Cap 21、SRC_Harness 15、SRC_Demand 9 筆（Stage 0 審閱的等級與立場），S30 一手原文補登 SRC_Perf 11 筆；Cap_In、Har_In、Workload 第 40 列 75 格改連結 SRC（值相等者），Checks C9:C10、最終訓練占研發區間、OpenAI 2025 對帳常數改連結 SRC_Price／SRC_Demand；數值逐格不變。以下為 v5.12（工程基礎）：新增 SRC_Index（各 SRC 頁 ID 依序堆疊），Gov_Map 的 SRC 狀態與等級改為每列 1 次 MATCH；SRC 各頁 X 欄改以 AH 同指標鍵比對；Checks 加 E13；Sources 更名 Sources_Legacy；公式內常數移到具名輸入格（CST_CtxKV、CST_STMult、CST_Eps、CST_MainMin），Sens_Train 情境倍數統一放在第 8 列；數值逐格不變。以下為 v5.11：Block 1＋2＋3＋4＋5＋治理 Stage 1 切片一；v5.11 建第 0 層 Source：SRC_HW、SRC_DC、SRC_Model、SRC_Perf（164 筆），模型頁原始數據改以公式連結 SRC_ID（數值逐格不變），DB_Evidence 加狀態與 SRC_ID 欄並登錄遷移紀錄，新增 Decisions、Gov_Map、L1 與 Checks G 節治理檢查；F14：Interface 與模型頁的每 GW 值除以 Inputs!E5，DC_Cost 改標為設施合計；v5.10 加成功任務成本前緣的可靠度下限 p_min（M1 (b)），Interface E 節增列每次嘗試成本、有效時間範圍與前緣；v5.9 加 Block 5：Har_In、Harness、Sens_Har，Workload 改為 harness 參數組，Block 4 補 SLO 不可達保護、K6 預設 (c)、機隊層級貢獻列、中國廠商旗標；v5.8 加 Block 4：Cap_In、Capability、Price_Frontier、Cache_Store、Fleet_1GW、Amortize、Theory_Rev、Sens_Rev；v5.2 加第二來源驗證與生產折減；v5.3、v5.4 依 CC 回饋補具名範圍與驗證表；v5.5 加 Block 3：Tech_Registry、Train_In、Perf_Batch、Training、Sens_Train，並更正 Hopper FP8 峰值；v5.6 非同步 RL 併入基準、補 TR_ 與訓練世代具名範圍；v5.7 改為 Excel 優先：輸入值由 Excel 擁有，新增 DB_Evidence 證據登錄表）。v4 的 Config／TL_Param／WP_Param／Revenue_Model 由 Arch、Serving、Workload、Calib、Perf、Unit_Cost 取代。
A6: 電力口徑 | B6: GW＝IT 關鍵電力（Andy 2026-09-30 確認）。設施電力＝IT × PUE，於 DC_Cost 與 Interface 並列。v5.11 起 DC_Cost 為設施合計（Inputs!E5 GW）；Interface、L1 與模型頁的每 GW 值一律除以 E5（F14）。
A7: 資料架構（v5.11） | B7: DB_Evidence（所有新訊息入口）→ 擇優 → SRC_*（第 0 層：只存原始訊息；SRC_ID 具名範圍）→ 模型頁（原始數據以公式連結 SRC；Analogy、Assumed、Decision 留在模型頁並登錄於 Gov_Map）→ Checks G 節（治理檢查，ERROR 必須為 0）→ L1（常用推算值，即時公式，附外部對照）／Interface（推算構件）→ 下游。規劃書：repo docs/plan/Tokenomics_governance_plan.md。
A8: Excel 擁有的治理頁（v5.11） | B8: SRC_HW、SRC_DC、SRC_Model、SRC_Perf、SRC_Price、SRC_Cap、SRC_Harness、SRC_Demand（v5.13）、Decisions、DB_Evidence，以及 Gov_Map 的 A–P 欄：builder 只在不存在時建立，之後不覆寫（v5.13 起既有 SRC 頁的新紀錄只在 ID 不存在時附加；Gov_Map 判斷欄的更新只在該格仍為舊值時寫入）。builder 每次重建：模型頁的 SRC 連結（gov_seed.FORMULA_MAP、gov_seed2.FORMULA_MAP2）、SRC 的 X–Z 與 AH 檢查欄、Gov_Map 的 Q–AF 欄、SRC_Index（v5.12）、L1、Checks G 節，以及 SRC_／L1_／GOV_／IDX_ 具名範圍；v5.12 起新輸入格的 Gov_Map 列只在未登錄時附加。
A9: 工作表 | B9: Inputs → Spec_Rack → Arch → Serving → Workload → Calib → Tech_Registry → Perf → Sens_Perf → Unit_Cost → DC_Cost → Train_In → Perf_Batch → Training → Sens_Train → Cap_In → Price_Frontier → Cache_Store → Fleet_1GW → Amortize → Theory_Rev → Sens_Rev → Har_In → Harness → Sens_Har → Alloc_In → Alloc → Perf_Prod → Perf_Batch_Prod → Training_Prod → Unit_Cost_Prod → Interface_Prod → Fleet_1GW_Prod → Amortize_Prod → Theory_Rev_Prod（v5.19 X1 鏡像頁）→ Interface → L1；Energy、NonNV、Sensitivity、Checks、Gov_Map、Decisions、SRC_HW、SRC_DC、SRC_Model、SRC_Perf、SRC_Price、SRC_Cap、SRC_Harness、SRC_Demand、SRC_Index（builder 擁有的查找索引）、Sources_Legacy（v5.12 起凍結）、DB_Evidence。
A10: Block 6 推導（v5.15） | B10: 實驗室年度算力＝研發需求＋服務需求。需求 D（token 路線，A9）：API＝SRC_DEM_010 × 525,600 × 全年平均比例；ChatGPT＝SRC_DEM_012 × 每則提示 token 數 × 365。服務 GW＝D ÷ 世代組合後每 GW 年產能（依 Cap_In 層級組合與 IF_TokGW_*、IF_Util，寫法同 Fleet_1GW 第 19–29 列）。研發 GW 年＝k ×（N_major × 家族計畫＋N_refresh × 改版計畫），家族計畫＝IF_ProgGWyr 三層級合計，改版計畫＝後訓練 GPU 小時 × 研發倍數換算 GW 年（訓練世代＝IF_TrainGenDefault）。Q1＝研發 GW ÷（研發＋服務 GW）；Q2 以各世代 IF_HoldEcon 加權，利用率不進入。研發占比的物理部分只給下限，實際占比由策略變數決定。隱含 N × k 由 2025 支出比反推（A3）。SLO 不可達時回傳文字。決策 A1–A10 見 Decisions。
A11: Block 3 推導 | B11: 預訓練：FLOPs＝3 ×（2 × 啟用參數＋注意力 FLOPs × 被注意 token）× token；GPU 小時＝FLOPs ÷（FP8 訓練峰值 × MFU × goodput）。RL、蒸餾、合成資料、評測的推論型運算以 Perf_Batch（與 Perf 同公式，只換速度下限與參考任務）計價；RL 有效 MFU 為推導值。研發計畫＝最終訓練 GPU 小時 × 研發倍數。
A12: Block 3 決策 | B12: J7 訓練精度 FP8（NVFP4 預訓練在 Tech_Registry）；J8 Astra 預訓練與 Arch 一致，前沿錨點列 Checks；J9 RL 由下而上，基準校到 RL÷預訓練 GPU 小時 Luna／Sol 0.3、Astra 1.0；J10 研發倍數 8，家族合計、依最終訓練比例分攤；J11 用途 × 型態只列單一計畫；J12 rollout NVFP4（FP8 為情境）；J13 下游預設 VR200、GB300 並列；J14 主流＝至少兩家實驗室公開採用，可覆寫。
A13: Excel 優先（v5.7） | B13: 藍字＝輸入，由本活頁簿擁有：要改輸入，直接改 Excel。builder 重建 Block 2、3 時會先讀取所有藍字輸入，重建後依『工作表＋欄 A 標籤＋欄位』寫回，程式內的預設值只用於新增的輸入列。公式頁不要手改（重建時會被覆寫）。
A14: DB_Evidence（v5.7） | B14: 證據登錄表：所有比對過的新資訊（含不採納者），記錄主張、來源、標記、對應參數、當時值、新值、判定與處理版本。builder 只在本頁不存在時建立。
A15: Tech_Registry | B15: 每列＝技術 × 作用物理量；有效倍數＝1＋開關 × 採用比例 ×（倍數−1）；已在基準者不套倍數。掛鉤彙總表連到 Perf、Perf_Batch、Training。全部開關為 0 時 Block 2 數值與 v5.4 相同。
... A57: v15.0 稽核結案 | B57: O1–O22 依預設結案：推論支出區間 RNG_Dem004_*、VR200 批次倍數區間（12 個名稱）、L1 外部對照換算同一單位、IF_FrontSuccVRQual 守衛、V16 改標恆等式（驗證計數 21）、SRC_PERF_060 來源更正、κ 推導區塊。基準值不變。細節見 Decisions SL46-*。

Sheet Inputs
A1: Inputs — 全域輸入（藍字可改）
A2: 低成本／基準／高成本為角落情境；單值輸入只填基準欄
A3: 參數 | B3: 單位 | D3: 低成本 | E3: 基準 | F3: 高成本 | G3: 標記 | H3: 來源／說明 | I3: 用途
A4: 控制
A5: IT 電力規模 | B5: GW | D5: =E5 -> 1 | E5: 1 | F5: =E5 -> 1 | G5: Decision | H5: 口徑：IT 關鍵電力。v5.11 起 DC_Cost 為設施合計；Interface、L1 與模型頁的「每 GW」一律已除以本格（F14） | I5: 顯示用：D5:F5（同表其他世代／層級欄）
A6: 功率情境（1 低／2 基準／3 高） | B6: 選擇 | D6: =E6 -> 2 | E6: 2 | F6: =E6 -> 2 | G6: Decision | H6: 決定每架配電設計功率；見 Spec_Rack 第 9–11 列 | I6: 顯示用：D6:F6（同表其他世代／層級欄）
A7: 規模與電力
A8: 機架外 IT 電力占比 | B8: % | D8: =E8 -> 0.08 | E8: 0.08 | F8: =E8 -> 0.08 | G8: Assumed | H8: 管理、儲存、網路機櫃等；區間 5–12%（見 Sensitivity）。v4 未計 | I8: 顯示用：D8:F8（同表其他世代／層級欄）
A9: PUE | B9: x | D9: 1.1 | E9: 1.2 | F9: 1.3 | G9: Analogy | H9: 液冷 AI 設施；v4＝1.2。S14 ｜全機型共用；未分氣冷 Hopper。3A Q6a：超大規模業者 1.10–1.17、colo 1.4–1.6；影響 m_fleet ≤ ±1.3%（稽核 2，Y4）。
A10: 平均用電 ÷ 配電設計功率 | B10: % | D10: 0.7 | E10: 0.8 | F10: 0.9 | G10: Assumed | H10: Block 2 以逐步能量模型閉合檢查
A11: 電價 | B11: $/kWh | D11: 0.06 | E11: 0.08 | F11: 0.1 | G11: Verified/Analogy | H11: EIA 美國工業電價 2026 年約 8.6–8.7¢（S13）；低端為 PPA（v4＝0.06）
A12: IT 設備（機架以外）
A13: Scale-out 網路 ÷ 機架價格 | B13: % | D13: 0.05 | E13: 0.1 | F13: =SRC_DC_002 -> 0.15 | G13: Analogy | H13: 1,024 GPU 叢集網路約為 GPU BOM 4–8%（S10）；GW 級多一層以上交換，取 5–15%
A14: 儲存與管理設備 | B14: $/GPU | D14: 300 | E14: 500 | F14: 800 | G14: Assumed | H14: v4 約 $350/GPU（$25K/架）
A15: 廠房（每 MW IT，$M）
A16: 土地 | B16: $M/MW | D16: 0.02 | E16: 0.02 | F16: 0.02 | G16: Assumed | H16: v4：100 英畝 × $200K／GW
A17: 建物與基地工程 | B17: $M/MW | D17: 3 | E17: 3.6 | F17: 4.5 | G17: Assumed | H17: 分項為假設；總額以 JLL 校準（S12） ｜各世代同值；建物造價未分氣冷 Hopper。3A Q6a：超大規模業者 1.10–1.17、colo 1.4–1.6；影響 m_fleet ≤ ±1.3%（稽核 2，Y4）。
A18: 電力設施（變電、中壓、發電機、UPS） | B18: $M/MW | D18: 3.8 | E18: 4.5 | F18: 5.5 | G18: Assumed | H18: 同上
A19: 機械與散熱（液冷迴路、散熱設備） | B19: $M/MW | D19: 2 | E19: 2.5 | F19: 3.2 | G19: Assumed | H19: 機架內冷板與 manifold 含在機架價格 ｜各世代同值；機械與散熱未分氣冷 Hopper。3A Q6a：超大規模業者 1.10–1.17、colo 1.4–1.6；影響 m_fleet ≤ ±1.3%（稽核 2，Y4）。
A20: 光纖、佈線、保全、BMS | B20: $M/MW | D20: 0.3 | E20: 0.4 | F20: 0.5 | G20: Assumed | H20: 同上
A21: 設計、管理與預備費 | B21: % 廠房 | D21: 0.12 | E21: 0.15 | F21: 0.18 | G21: Assumed | H21: v4＝15%
A22: 年限與資金成本
A23: IT 設備折舊年限 | B23: 年 | D23: =SRC_DC_007 -> 6 | E23: =SRC_DC_007 -> 6 | F23: =SRC_DC_008 -> 4 | G23: Verified | H23: CoreWeave 與主要 hyperscaler 6 年；Nebius 4 年、Lambda 5 年（S15）。高成本情境取 4
A24: 建物年限 | B24: 年 | D24: =E24 -> 30 | E24: 30 | F24: =E24 -> 30 | G24: Analogy | H24: v4
A25: 電力設施年限 | B25: 年 | D25: =E25 -> 20 | E25: 20 | F25: =E25 -> 20 | G25: Analogy | H25: v4
A26: 機械與散熱年限 | B26: 年 | D26: =E26 -> 15 | E26: 15 | F26: =E26 -> 15 | G26: Analogy | H26: v4
A27: 光纖與保全年限 | B27: 年 | D27: =E27 -> 10 | E27: 10 | F27: =E27 -> 10 | G27: Analogy | H27: v4
A28: WACC（經濟口徑） | B28: % | D28: 0.08 | E28: 0.1 | F28: 0.13 | G28: Assumed | H28: 與擁有者無關的單一假設；下游公司模型以自身 WACC 覆寫（Andy 2026-09-30 決定）
A29: 營運費用
A30: IT 維護（壽命期等值；由兩段費率計算） | B30: % IT 資本/年 | D30: =IF(D28=0,(D37*MIN(D36,D23)+D38*(D23-MIN(D36,D23)))/D23,(D37*(1-(1+D28)^(-MIN(D36,D23)))+D38*((1+D28)^(-MIN(D36,D23))-(1+D28)^(-D23)))/(1-(1+D28)^(-D23))) -> 0.01024435 | E30: =IF(E28=0,(E37*MIN(E36,E23)+E38*(E23-MIN(E36,E23)))/E23,(E37*(1-(1+E28)^(-MIN(E36,E23)))+E38*((1+E28)^(-MIN(E36,E23))-(1+E28)^(-E23)))/(1-(1+E28)^(-E23))) -> 0.015725011 | F30: =IF(F28=0,(F37*MIN(F36,F23)+F38*(F23-MIN(F36,F23)))/F23,(F37*(1-(1+F28)^(-MIN(F36,F23)))+F38*((1+F28)^(-MIN(F36,F23))-(1+F28)^(-F23)))/(1-(1+F28)^(-F23))) -> 0.018247768 | G30: Derived | H30: v5.31 X17：壽命期等值單一費率＝Σ r_y ÷ (1＋WACC)^y ÷ Σ 1 ÷ (1＋WACC)^y（y＝1…IT 折舊年限；r_y＝保固期內費率（y ≤ 保固年限）或保固期滿後費率，第 36–38 列）；各欄用同欄 WACC（第 28 列）與 IT 折舊年限（第 23 列）。DC_Cost 第 44 列仍為 IT 資本 × 本列。v5.30 以前為 2%／3%／4%（v4 沿用，Analogy→Assumed）
A31: 廠房維護 | B31: % 廠房資本/年 | D31: 0.015 | E31: 0.02 | F31: 0.025 | G31: Analogy | H31: v4＝2%
A32: 人員 | B32: $M/GW/年 | D32: 50 | E32: 75 | F32: 100 | G32: Assumed | H32: v4：500 FTE × $150K
A33: 軟體授權與連線 | B33: $M/GW/年 | D33: 150 | E33: 200 | F33: 250 | G33: Assumed | H33: v4＝$200M
A34: 水與耗材 | B34: $M/MW/年 | D34: 0.04 | E34: 0.05 | F34: 0.06 | G34: Assumed | H34: v4＝$50K/MW
A35: 財產稅與保險 | B35: % 總資本/年 | D35: 0.003 | E35: 0.005 | F35: 0.008 | G35: Analogy | H35: v4＝0.5%
A36: IT 原廠保固年限 | B36: 年 | D36: =E36 -> 3 | E36: =SRC_DC_015 -> 3 | F36: =E36 -> 3 | G36: Verified | H36: v5.31 X18：HPE GB300 NVL72 QuickSpecs（2026-09-08）3 年零件、3 年人工、3 年到場（SRC_DC_015）；Supermicro GPU 系統人工 3 年、零件 1 年（SRC_DC_016；零件 1 年由保固期內高情境 1% 涵蓋）；Dell XE9680 經銷頁 3 年 ProSupport。單值（低、高＝基準）
A37: IT 維護（保固期內） | B37: % IT 資本/年 | D37: 0.0025 | E37: 0.005 | F37: 0.01 | G37: Analogy | H37: v5.31 X17：保固期內零件與人工由原廠負擔（保固費已含在機架售價），只剩備品、物流與保固外損壞；CoreWeave 2026 Q2 營運成本反推約 0–0.8%（E276，Derived）；區間 0.25–1%（高端涵蓋 Supermicro 零件 1 年）
A38: IT 維護（保固期滿後） | B38: % IT 資本/年 | D38: 0.02 | E38: 0.03 | F38: 0.05 | G38: Analogy | H38: v5.31 X17：NVIDIA DGX B200 原廠支援續約 1 年 ≈ 系統價 3.8%（SRC_DC_017，英國經銷牌價）；Introl 企業 TCO 5%（Interested-party，E275）作高端；大型買家應低於零售牌價 → 基準 3%

Sheet Spec_Rack
A1: Spec_Rack — 各世代機架規格（Block 1 只含功率與價格；效能規格於 Block 2 加入）
A2: 價格為買方取得價（CSP/hyperscaler 口徑）；Hopper 以 4 台 HGX 構成一架（32 GPU）以便比較
I3: 用途
A4: 世代 | C4: Hopper H100 | D4: GB200 NVL72 | E4: GB300 NVL72 | F4: VR200 NVL72 | G4: Rubin Ultra（MGX NVL 單架，72 GPU） | H4: 標記／來源
A5: 平台／出貨 | C5: HGX ×4（32 GPU） | D5: 2024–25 出貨 | E5: 2025–26 主力 | F5: 2026 下半年開始出貨 | G5: 2027 預估（NVL576＝8 個單架互連）
A6: GPU 封裝／架 | C6: 32 | D6: =SRC_HW_047 -> 72 | E6: =SRC_HW_047 -> 72 | F6: =SRC_HW_047 -> 72 | G6: =SRC_HW_061 -> 72
A7: 冷卻 | C7: 氣冷 | D7: 液冷 | E7: 液冷 | F7: 液冷（必須） | G7: 液冷
A8: 配電設計功率 低（kW） | C8: 38 | D8: =SRC_HW_004_Lo -> 120 | E8: =SRC_HW_005_Lo -> 132 | F8: =SRC_HW_011 -> 188 | G8: 300
A9: 配電設計功率 基準（kW） | C9: 41 | D9: =SRC_HW_004_Hi -> 132 | E9: 136 | F9: =SRC_HW_014 -> 227 | G9: 340
A10: 配電設計功率 高（kW） | C10: 44 | D10: 140 | E10: =SRC_HW_005_Hi -> 140 | F10: =SRC_HW_012 -> 230 | G10: 454
A11: 機架價格 低（$M） | C11: 0.9 | D11: =SRC_HW_006_Lo -> 2.8 | E11: =SRC_HW_052 -> 4 | F11: 7.8 | G11: =F12*SR_RU_PxMultLo -> 12.6
A12: 機架價格 基準（$M） | C12: 1.1 | D12: 3.1 | E12: 4.3 | F12: 8.4 | G12: =F12*2 -> 16.8
A13: 機架價格 高（$M） | C13: 1.3 | D13: =SRC_HW_006_Hi -> 3.4 | E13: =SRC_HW_010 -> 5 | F13: 9.1 | G13: =F12*SR_RU_PxMultHi -> 21
A14: 價格涵蓋範圍 | C14: 8 GPU 伺服器 + CPU、NIC、機內儲存；以部署當時取得價計 | D14: 運算匣＋NVLink 交換匣＋機架內冷卻 | E14: 同上 | F14: 運算匣＋交換匣＋冷卻＋約 $1M NAND；是否含部分網路待查（S11）；Bernstein 平均約 $9.1M 含網路約 $1.2M；本模型另計 Scale-out 網路，高情境約重複 2%（v5.31 J4） | G14: 72 封裝（單架）；價格＝VR200 機架價格（F12，售價口徑）× 低倍數 SR_RU_PxMultLo／2.0／高倍數 SR_RU_PxMultHi（公式；倍數 Assumed，無來源，待證據；J2；v10.3 F1 外露，倍數見本頁「Rubin Ultra 機架價格倍數（v10.3 F1；Assumed，無來源；待證據）」）
A15: 功率來源 | C15: DGX H100 最大 10.2 kW／8 GPU（S1） | D15: 約 120–132 kW（SemiAnalysis 約 120；HPE QuickSpecs TDP 132 nominal；S3）；基準 132；v4＝139 | E15: 132–140 kW（wing.vc；S3、S5）；基準 136（區間中點） | F15: Max-Q 188、Max-P 227 kW（Schneider Electric 的 NVIDIA VR NVL72 參考設計 MaxQ 188／MaxP 227，2026-05-08；S7）；Supermicro 產品頁 DLC-2 冷卻 sized for 227 kW per rack（SRC_HW_064，口徑不同） | G15: 單架 300／340／454 kW（Derived：低＝舊路線圖 600 kW 依封裝數等比；基準＝72×3.6 kW＋VR 機架非 GPU 功率 61–97 kW 取 340；高＝VR 整架／GPU 功率比值等比；NVIDIA 未公布單架 kW）
A16: 價格來源 | C16: 部署當時 8 GPU HGX 伺服器約 $250–320K（Raymond James 2023-08，每顆 H100 2.5–3 萬；SemiAnalysis 2023-05 DGX H100 約 27 萬，旁證；HPCwire 2024-09 約 2.5 萬／顆）；×4＝一架。原 S2（clusterbid 2026 報價）降為對照。超大規模業者實付價：已搜尋，未找到（3A Q6b）。 | D16: $2.8–3.4M（S4）；Barron's 約 $3M | E16: v5.31 J1：低 4.0＝Morgan Stanley BOM 推算（VR200 BOM 7.8 ÷ 1.95，SRC_HW_052）；基準 4.3＝BOM ×（1＋代工毛利 7.5%），與 VR200 F12 算法相同，與 Wolfe Research 4.3（SRC_HW_065，Alt）相符；高 5.0＝Data Gravity 2026-08 採購單（不含 CDU，SRC_HW_010）；媒體 $6–6.5M（SRC_HW_007）改列 Alt；公司揭露對照：IREN 每 IT MW 29.0（SRC_DC_014，L1_CapexITMW_GB300_vsIREN） | F16: MS 物料成本 BOM $7.8M（自購記憶體 $6.7M）；Bernstein $9.09M；報價 $5–7M（S9）；v5.18：基準 8.4＝MS BOM 7.8 ×（1＋代工毛利約 7.5%，區間 5–10%，Assumed）；低 7.8（零毛利 BOM 下限）、高 9.1（不變，Bernstein） | G16: 無公開報價；純推估，不進基準比較
A17: 標記 | C17: Analogy | D17: Interested-party | E17: Derived／Interested-party | F17: Interested-party | G17: Derived／Assumed
A19: 註：GPU 數為封裝數。Rubin Ultra 欄為 MGX NVL 單架 72 封裝（NVIDIA 2026-09 技術部落格：NVL576＝8 個單架互連為單一 576-GPU NVLink 域；『GPU』＝封裝為推斷 [Derived]，部落格未明載）；Kyber NVL144 屬 Feynman 世代，不納入。
A21: B2. 效能規格（Block 2；藍字＝輸入；每 GPU 封裝）
A22: 服務精度 | C22: FP8 | D22: NVFP4 | E22: NVFP4 | F22: NVFP4 | G22: NVFP4 | H22: Hopper 不支援 FP4，以 FP8 服務
A23: 峰值 dense（基準）PF/GPU | C23: =SRC_HW_040 -> 1.979 | D23: =SRC_HW_022 -> 10 | E23: =SRC_HW_025 -> 15 | F23: =SRC_HW_028 -> 35 | G23: 70 | H23: Interested-party（NVIDIA 規格）：H100 FP8 dense 1,979 TF（v5.5 更正；v5.4 誤填 BF16 的 989）；GB200 FP4 10 PF（HGX B200 為 9）；B300 15；Rubin NVFP4 訓練 35（DGX VR 頁 2,520 PF÷72，Dense）；RU 單架 72 封裝：2×35＝70 [Derived；v5.18]。S28
A24: 峰值（高情境：NVFP4 推論口徑）PF/GPU | C24: =C23 -> 1.979 | D24: =SRC_HW_022 -> 10 | E24: =SRC_HW_025 -> 15 | F24: =SRC_HW_027 -> 50 | G24: 100 | H24: Rubin 50 PF 含自適應壓縮（Sparse）；RU 每封裝 2×50＝100 [Derived；v5.18，舊 15 EF÷144＝104]。J2：只作高情境
A25: HBM 容量 GB/GPU | C25: =SRC_HW_020 -> 80 | D25: 186 | E25: =SRC_HW_026 -> 288 | F25: =SRC_HW_029 -> 288 | G25: 1024 | H25: GB200 NVL72 13.4 TB ÷ 72；InferenceX 以 192 計。RU HBM4e 約 1 TB/封裝。S28
A26: HBM 頻寬 TB/s/GPU | C26: =SRC_HW_021 -> 3.35 | D26: =SRC_HW_023 -> 8 | E26: =SRC_HW_059 -> 8 | F26: =SRC_HW_030 -> 22 | G26: 32 | H26: Rubin 22 TB/s（NVIDIA 2026 上修）；RU 4.6 PB/s ÷ 144。S28
A27: EP 通訊頻寬 TB/s/GPU（單向） | C27: =SRC_HW_060/8/1000 -> 0.05 | D27: =SRC_HW_048 -> 0.9 | E27: =SRC_HW_048 -> 0.9 | F27: =SRC_HW_049 -> 1.8 | G27: 1.8 | H27: Hopper EP 跨節點走 400G IB；NVLink 5＝900 GB/s；NVLink 6＝1.8 TB/s（InferenceX 規格表 S20）；RU 取同 VR [Assumed] ｜物理慣例：÷8＝Gb/s 換 GB/s（8 bit／byte），不外露
A28: Scale-up 域 GPU 數 | C28: =SRC_HW_053 -> 8 | D28: =SRC_HW_047 -> 72 | E28: =SRC_HW_047 -> 72 | F28: =SRC_HW_047 -> 72 | G28: =SRC_HW_062 -> 576 | I28: 顯示用：C28:G28（規格表列（Gov_Map 登錄 SRC_HW_053）；不進任何輸出）
A29: decode EP 基準寬度 | C29: 64 | D29: 32 | E29: =SRC_PERF_008 -> 32 | F29: 32 | G29: 64 | H29: GB300 公開配方 dep32（S21）；Hopper 跨節點 [Analogy DeepSeek]；RU [Assumed]。權重放不下時自動加寬
A30: 專家權重 bytes/param | C30: =SRC_HW_055 -> 1 | D30: =SRC_HW_050 -> 0.5625 | E30: =SRC_HW_050 -> 0.5625 | F30: =SRC_HW_050 -> 0.5625 | G30: =SRC_HW_050 -> 0.5625 | H30: NVFP4＝4 bit＋每 16 值 8 bit scale＝0.5625 B；Hopper FP8
A31: 非專家權重 bytes/param | C31: 1 | D31: 1 | E31: 1 | F31: 1 | G31: 1 | H31: 注意力、路由、embedding 以 FP8 存放 [Analogy V4]
A32: 每 prefill 實例 GPU 數（算 TTFT） | C32: 8 | D32: 4 | E32: =SRC_PERF_007 -> 4 | F32: 4 | G32: 8 | H32: GB300 配方 dep4 prefill（S21）
A33: GPU 功率 W/封裝（能量用） | C33: =SRC_HW_056 -> 700 | D33: =SRC_HW_057 -> 1200 | E33: =SRC_HW_058 -> 1400 | F33: =SRC_HW_046*1000 -> 1800 | G33: 3600 | H33: Interested-party；Rubin 約 1.8 kW、RU 推估。僅用於能量下限估算
A34: HBM 存取能量 pJ/byte | C34: 31 | D34: 25 | E34: 25 | F34: =SRC_HW_034*8 -> 20 | G34: 18 | H34: Analogy：HBM3 約 3.9 pJ/bit、HBM3e 約 3、HBM4 約 2.5；區間 ±30%（S29） ｜物理慣例：×8＝pJ/bit 換 pJ/byte（8 bit／byte），不外露
A35: 計算用峰值 PF/GPU（依 Serving 峰值情境） | C35: =IF(Serving!$C$16=2,C24,C23) -> 1.979 | D35: =IF(Serving!$C$16=2,D24,D23) -> 10 | E35: =IF(Serving!$C$16=2,E24,E23) -> 15 | F35: =IF(Serving!$C$16=2,F24,F23) -> 35 | G35: =IF(Serving!$C$16=2,G24,G23) -> 70
A36: Ridge point（FLOP/byte） | C36: =C35*1000/C26 -> 590.74627 | D36: =D35*1000/D26 -> 1250 | E36: =E35*1000/E26 -> 1875 | F36: =F35*1000/F26 -> 1590.9091 | G36: =G35*1000/G26 -> 2187.5 | I36: 顯示用：C36:G36（roofline 推導鏈讀數（ridge point＝峰值÷頻寬）；建模精神 1a 要求露出推導鏈）
A38: B3. 訓練峰值（Block 3；dense；每 GPU 封裝；MFU 以 FP8 列為分母，J7）
A39: BF16 dense PF/GPU | C39: =SRC_HW_019 -> 0.989 | D39: =SRC_HW_042 -> 2.5 | E39: =SRC_HW_042 -> 2.5 | F39: =SRC_HW_039/SRC_HW_047 -> 4 | G39: 8 | H39: Interested-party（NVIDIA）：H100 989 TF；GB200／GB300 2.5；VR NVL72 288 PF ÷ 72＝4.0（S36）；RU 取 VR×2 [Assumed] | I39: 備用（無公式讀取）：G 欄 BF16 dense（Rubin Ultra）
A40: FP8 dense PF/GPU（訓練基準，J7） | C40: =SRC_HW_040 -> 1.979 | D40: =SRC_HW_043 -> 5 | E40: =SRC_HW_043 -> 5 | F40: =SRC_HW_038/SRC_HW_047 -> 17.5 | G40: 35 | H40: Interested-party（NVIDIA）：H100 1,979 TF；GB200／GB300 FP8 5 PF（B300 未提升 FP8）；VR NVL72 1,260 PF ÷ 72＝17.5（S36）；RU＝2×VR 17.5（1,260 PF÷72，Dense）＝35.0 [Derived；v5.18，舊 5 EF÷144＝34.7]
A41: NVFP4 訓練 dense PF/GPU（Tech_Registry 情境） | C41: =C40 -> 1.979 | D41: 10 | E41: 15 | F41: =SRC_HW_037/SRC_HW_047 -> 35 | G41: 70 | H41: Hopper 無 FP4，取 FP8；GB200 10（NVIDIA：Rubin 為 Blackwell 3.5 倍）；GB300 15 [Assumed，區間 10–15]；VR 2,520 PF ÷ 72＝35（S36）；RU＝2×VR 35＝70 [Derived；v5.18，舊 VR×104/50＝73] | I41: 複本讀取：C41:G41（被 Sens_／_Prod 複本頁讀取，不是死格）
A43: 模型規模倍數（D1(c)，啟用參數倍數，相對 2026 Arch 快照）
A44: 模型規模倍數：基準（ARCH_ScaleGen） | C44: 1 | D44: 1 | E44: 1 | F44: 1 | G44: 1 | H44: Assumed｜D1(c)：基準 1＝固定模型口徑（截面比較）；情境 d1_model_scale 為 J1 預設（R-a：GB300＝2026 快照）。只放大參數（每 token FLOPs、權重 bytes），KV 與層數不變，所以是模型變大效果的下限。第 5 欄（Rubin Ultra）固定 1，只為讓具名範圍與 Perf 的世代索引（1–5）一致；J1 只定義前四代
A45: 模型規模倍數：低（ARCH_ScaleGen_Lo） | C45: 0.5 | D45: 0.3 | E45: 1 | F45: 1 | G45: 1 | H45: Assumed（Hopper、GB200 為 Analogy）｜區間低端（相對 2026 Arch 快照的啟用參數倍數）：Hopper 0.5、GB200 0.3、GB300 1、VR200 1、Rubin Ultra 固定 1。r1（2Q 報告 Q2）：Hopper 代表模型 GPT-4 級啟用參數約 220–280B，大於快照 Astra 的 180B，r0 的 0.1 方向錯誤，改 0.5 | I45: 區間端點（供 Gov_Map 與情境）：ARCH_ScaleGen_Lo（C:G）
A46: 模型規模倍數：高（ARCH_ScaleGen_Hi） | C46: 1.3 | D46: 1 | E46: 1 | F46: 2.5 | G46: 1 | H46: Assumed（Hopper、GB200 為 Analogy）｜區間高端：Hopper 1.3、GB200 1.0、GB300 1、VR200 2.5、Rubin Ultra 固定 1。r1（2Q 報告 Q2）：Hopper 1.3、VR200 2.5（r0 的 4.4 無證據）；情境 d1_model_scale 取 Hopper 0.8／GB200 0.55／GB300 1／VR200 1.4。暫不分層級（留待 Andy 決定） | I46: 區間端點（供 Gov_Map 與情境）：ARCH_ScaleGen_Hi（C:G）
A48: Rubin Ultra 機架價格倍數（v10.3 F1；Assumed，無來源；待證據）
A49: Rubin Ultra 機架價格倍數：低（SR_RU_PxMultLo） | B49: x | C49: 1.5 | H49: Assumed（無來源；待證據）｜Rubin Ultra 單架機架價格低端＝VR200 機架價格（F12，售價口徑）× 本值；v10.3 前寫死在 G11 公式（×1.5）。Gov_Map 區間 1.2–2.0
A50: Rubin Ultra 機架價格倍數：高（SR_RU_PxMultHi） | B50: x | C50: 2.5 | H50: Assumed（無來源；待證據）｜Rubin Ultra 單架機架價格高端＝F12 × 本值；v10.3 前寫死在 G13 公式（×2.5）。Gov_Map 區間 2.0–3.0

Sheet Arch
A1: Arch — 三層級代表架構（D5：每層級一個代表；參數為公開模型卡或推估）
A2: Luna／Sol 以公開權重模型為物理代表 [Analogy：對應封閉層級]；Astra 為封閉前沿代理，KV 以情境處理（J1）
H3: 用途
A4: 參數 | B4: 單位 | C4: Luna（低層） | D4: Sol（中層） | E4: Astra（頂層） | F4: 標記 | G4: 來源／說明
A5: 代表架構 | C5: DeepSeek V4-Flash 類 | D5: DeepSeek V4-Pro 類 | E5: 封閉前沿代理 | F5: Decision | G5: D5；Andy 2026-09-30 確認
A6: 總參數 | B6: B | C6: =SRC_MOD_005 -> 284 | D6: =SRC_MOD_001 -> 1600 | E6: 4000 | F6: Assumed | G6: V4-Flash 284B、V4-Pro 1.6T（模型卡，S27）；Astra 4T [Assumed，區間 2–10T] ｜v13.1 更正（修訂九，Decisions D15-10）：標記欄原字樣『Verified／Assumed』更正為『Assumed』（以 Gov_Map 為準；Luna／Sol 欄數值連結 SRC_MOD，Astra 欄無公開來源）
A7: 啟用參數 | B7: B | C7: =SRC_MOD_006 -> 13 | D7: =SRC_MOD_002 -> 49 | E7: 180 | F7: Assumed | G7: V4-Flash 13B、V4-Pro 49B；Astra 180B [Assumed，區間 60–250B] ｜v13.1 更正（修訂九，Decisions D15-10）：標記欄原字樣『Verified／Assumed』更正為『Assumed』（以 Gov_Map 為準；Luna／Sol 欄數值連結 SRC_MOD，Astra 欄無公開來源）
A8: 層數 | B8: 層 | C8: =SRC_MOD_007 -> 43 | D8: =SRC_MOD_003 -> 61 | E8: 100 | F8: Assumed | G8: V4-Pro 61（config.json）；V4-Flash 43（二手）；Astra [Assumed] ｜v13.1 更正（修訂九，Decisions D15-10）：標記欄原字樣『Verified／Assumed』更正為『Assumed』（以 Gov_Map 為準；Luna／Sol 欄數值連結 SRC_MOD，Astra 欄無公開來源）
A9: d_model | C9: =SRC_MOD_052 -> 4096 | D9: =SRC_MOD_004 -> 7168 | E9: 12288 | F9: Verified／Assumed | G9: V4-Pro 7168；V4-Flash 4096（官方 config.json hidden_size，v5.13 讀原文）；Astra [Assumed]
A10: query heads | C10: =SRC_MOD_053 -> 64 | D10: =SRC_MOD_008 -> 128 | E10: 96 | F10: Verified／Assumed | G10: V4-Pro 128；V4-Flash 64（官方 config.json num_attention_heads，v5.13 讀原文）；Astra [Assumed]
A11: head_dim | C11: =SRC_MOD_009 -> 512 | D11: =SRC_MOD_009 -> 512 | E11: 128 | F11: Verified／Assumed | G11: V4 單一 512 維 KV head；Astra 128
A12: routed experts | C12: =SRC_MOD_010 -> 256 | D12: =SRC_MOD_011 -> 384 | E12: 512 | F12: Verified／Assumed
A13: 每 token 啟用 routed experts | C13: =SRC_MOD_012 -> 6 | D13: =SRC_MOD_012 -> 6 | E13: 16 | F13: Verified／Assumed
A14: shared experts | C14: =SRC_MOD_013 -> 1 | D14: =SRC_MOD_013 -> 1 | E14: 1 | F14: Verified
A15: vocab | C15: =SRC_MOD_014 -> 129280 | D15: =SRC_MOD_014 -> 129280 | E15: 200000 | F15: Verified／Assumed | H15: 顯示用：C15:D15（架構規格列（Gov_Map 登錄 SRC_MOD_014）；不進任何輸出）
A16: 全注意力層比例 | B16: % | C16: =SRC_MOD_015 -> 0.512 | D16: =SRC_MOD_054 -> 0.492 | E16: 1 | F16: Verified／Assumed | G16: V4：CSA 與 HCA 約各半；Astra 全層注意力
A17: 全注意力層跨度上限（0＝全上下文） | B17: tok | C17: =SRC_MOD_018*SRC_MOD_019+SRC_MOD_017 -> 4224 | D17: =SRC_MOD_018*SRC_MOD_019+SRC_MOD_017 -> 4224 | E17: 0 | F17: Derived | G17: V4 CSA：top-k 1,024 壓縮塊 × 4 ＋ 128 窗口
A18: 其他層壓縮比 | B18: x | C18: =SRC_MOD_016 -> 128 | D18: =SRC_MOD_016 -> 128 | E18: 1 | F18: Verified | G18: V4 HCA 128× 壓縮
A19: 其他層滑動窗 | B19: tok | C19: =SRC_MOD_017 -> 128 | D19: =SRC_MOD_017 -> 128 | E19: 0 | F19: Verified
A20: Astra KV 情境（1 混合／2 全層 MLA／3 GQA-8） | B20: 選擇 | E20: 2 | F20: Decision | G20: J1：基準 2（Andy 2026-09-30 確認）
A21: KV bytes/token — 情境 1 | B21: B | C21: =C34*C8 -> 2795 | D21: =D34*D8 -> 3965 | E21: =E36*E35*E8*$C$38 -> 14976 | F21: Derived（公式） | G21: Luna／Sol＝每層 KV bytes × 層數；Astra 混合＝MLA 層比例 × MLA 每層 KV 元素 × 層數 × 每元素 bytes（v5.13 改公式，值不變）
A22: KV bytes/token — 情境 2 | B22: B | C22: =C34*C8 -> 2795 | D22: =D34*D8 -> 3965 | E22: =E35*E8*$C$38 -> 57600 | F22: Derived（公式） | G22: Astra 全層 MLA＝MLA 每層 KV 元素 × 層數 × 每元素 bytes
A23: KV bytes/token — 情境 3 | B23: B | C23: =C34*C8 -> 2795 | D23: =D34*D8 -> 3965 | E23: =E37*E11*2*E8*$C$38 -> 204800 | F23: Derived（公式） | G23: Astra GQA＝KV heads × head_dim × 2（K、V）× 層數 × 每元素 bytes
A24: 導出
A25: KV bytes/token（採用） | B25: B | C25: =CHOOSE(IF(C20="",1,C20),C21,C22,C23) -> 2795 | D25: =CHOOSE(IF(D20="",1,D20),D21,D22,D23) -> 3965 | E25: =CHOOSE(IF(E20="",1,E20),E21,E22,E23) -> 57600
H26: 已刪除（v14.0，4-3B Q1）：功能未接線，已移除，需要時再接線；原範圍 C26:E26；見 Decisions SL43-1
A27: 每 routed expert 參數 | B27: B | C27: =(C6-C7)/(C8*(C12-C13)) -> 0.025209302 | D27: =(D6-D7)/(D8*(D12-D13)) -> 0.067265157 | E27: =(E6-E7)/(E8*(E12-E13)) -> 0.077016129 | G27: 由公開總參數與啟用參數反推，確保總數吻合（v4 方法）
A28: 非專家參數（注意力、路由、embedding） | B28: B | C28: =C7-C8*(C13+C14)*C27 -> 5.412 | D28: =D7-D8*(D13+D14)*D27 -> 20.277778 | E28: =E7-E8*(E13+E14)*E27 -> 49.072581
A29: 專家參數 | B29: B | C29: =C6-C28 -> 278.588 | D29: =D6-D28 -> 1579.7222 | E29: =E6-E28 -> 3950.9274
A30: 注意力 FLOPs／每個被注意的 token | B30: FLOP | C30: =4*C10*C11*C8 -> 5636096 | D30: =4*D10*D11*D8 -> 15990784 | E30: =4*E10*E11*E8 -> 4915200 | G30: 物理慣例：係數 4＝注意力 QKᵀ 與 AV 各 2 FLOPs／MAC，共 4，不外露
H31: 已刪除（v14.0，4-3B Q1）：功能未接線，已移除，需要時再接線；原範圍 C31:E31；見 Decisions SL43-1
A32: 上下文長度（上一列顯示用） | B32: tok | C32: 128000 | F32: 結構選擇 | G32: 顯示列的口徑：128,000（非 131,072）；三層級共用本格（CST_CtxKV）。不影響任何產出
A33: KV 推導輸入（v5.13 D：第 21–23 列由此計算）
A34: 每層 KV bytes/token（壓縮後平均，FP8） | B34: B | C34: 65 | D34: 65 | F34: Assumed | G34: v4 推導值；V4 官方 config：KV head 512（SRC_MOD_009）、CSA 壓縮 4×、HCA 128×、滑動窗 128，以結構重算會改值，Stage 2 處理
A35: MLA 每層 KV 元素數（Astra 情境 1、2） | B35: 元素 | E35: 576 | F35: Analogy | G35: 比照 DeepSeek-V3 MLA：512 latent＋64 RoPE（SRC_MOD_028）
A36: MLA 層比例（Astra 情境 1 混合） | B36: % | E36: 0.26 | F36: Assumed | G36: 混合注意力：其餘層為線性注意力（KV 不隨上下文成長，本列不計）
A37: GQA KV heads（Astra 情境 3） | B37: 個 | E37: 8 | F37: Assumed | G37: GQA-8（結構選擇）
A38: KV 每元素 bytes（FP8；三層級共用） | B38: B | C38: =SRC_HW_055 -> 1 | F38: 原始數據 | G38: FP8 每元素 1 byte（SRC_HW_055）

Sheet Serving
A1: Serving — 服務設定與各層級 SLO（主流：分離式 P/D、wide EP、attention DP、NVFP4、MTP、前綴快取）
A2: 藍字＝輸入。SLO 依 J3 採市場觀測輸出速度（Artificial Analysis 2026-09，S26）
G3: 用途
A4: 全域設定 | B4: 單位 | C4: 值 | D4: 標記 | F4: 說明
A5: 服務架構 | C5: 分離式 P/D＋wide EP＋attention DP | D5: Decision | F5: D6 與 Block 2 命題
A6: MTP 草稿數 N | B6: tok | C6: 3 | D6: Analogy | F6: DeepSeek MTP；區間 1–5
A7: 每個草稿 token 接受率 α | B7: % | C7: =SRC_PERF_005 -> 0.7 | D7: Verified-measured | F7: SGLang 修正後 0.57→0.70（S21）；區間 0.6–0.8
A8: 每步期望接受 token a | B8: tok | C8: =(1-C7^(C6+1))/(1-C7) -> 2.533 | D8: Derived | F8: (1−α^(N+1))/(1−α)
A9: HBM 保留比例（啟用值、工作區） | B9: % | C9: 0.1 | D9: Assumed | F9: 區間 5–20%
A10: 非專家權重占可用 HBM 上限 | B10: % | C10: 0.2 | D10: Assumed | F10: 超過時自動以注意力 TP 切分
A11: 專家權重占可用 HBM 上限 | B11: % | C11: 0.4 | D11: Assumed | F11: 超過時自動加寬 EP
A12: EP 啟用值 bytes/元素（dispatch＋combine） | B12: B | C12: 3 | D12: Analogy | F12: FP8 dispatch 1 B＋BF16 combine 2 B
A13: KV 讀取頻寬效率 η_mem | B13: % | C13: 0.7 | D13: Analogy | F13: 區間 0.5–0.85
A14: EP 通訊效率 η_link | B14: % | C14: 0.7 | D14: Analogy | F14: 區間 0.5–0.85
A15: 快取命中 KV 載入頻寬 | B15: TB/s/GPU | C15: 0.1 | D15: Assumed | F15: 主機記憶體／SSD 經 NIC 載入；區間 0.05–0.4。未計快取儲存成本
A16: 峰值情境（1＝dense 基準／2＝NVFP4 推論高） | B16: 選擇 | C16: 1 | D16: Decision | F16: J2：基準 1
A17: 基準利用率（第 0 層） | B17: % | C17: 0.6 | D17: Assumed | F17: J6：Andy 尚未給值，暫沿用 OpenAI v0.5 的 60%（區間 40–80%）。Unit_Cost 同時輸出 100% 版 ｜暫定、待證據（D13）；區間 0.4–0.8
A18: 實測→生產效率折減 | B18: x | C18: 1 | D18: Assumed | F18: 待 Andy 決定。基準測試為固定長度、穩態負載；生產環境另有長度變異、路由不均、故障。1.0＝不折減。作用：η_p、η_d 乘此值，每層延遲除以此值。第二來源（MLPerf、DeepSeek 自揭）目前均高於本模型，見 Calib H 節 ｜暫定、待證據（D13）；區間 0.7–1.0；基準 1.0 在區間端點（1.0＝主路徑不折減，折減改由 C28 表達；J3（第 2 批 2-2 段，v7.0；chat 端預設，可撤回）：C18 固定 1.0，不再作為折減入口；生產折減一律由 C28 `CTL_ProdDerate` 表達，情境 b_prod_derate 的輸入改為 CTL_ProdDerate）
A19: 各層級 SLO 與參考任務
A20: 項目 | B20: 單位 | C20: =Arch!C4 -> Luna（低層） | D20: =Arch!D4 -> Sol（中層） | E20: =Arch!E4 -> Astra（頂層） | F20: 說明 | G20: 顯示用：C20:E20（欄頭／表頭標籤）
A21: SLO：每用戶 decode 速度下限 | B21: tok/s | C21: =SQRT(SRC_PERF_066*SRC_PERF_067) -> 84.300059 | D21: =SQRT(SRC_PERF_068*SRC_PERF_069) -> 43.311661 | E21: =SQRT(SRC_PERF_070*SRC_PERF_071) -> 40.83136 | F21: SLO 為兩個第三方量測商中位數的幾何平均（v10.2 E2）：Luna＝GPT-6 Luna √(116.5×61)＝84.3；Sol＝GPT-6.1 Sol √(50.7×37)＝43.3；Astra＝GPT-6 Astra √(52.1×32)＝40.8 tok/s。區間取兩家之中較低者到較高者（Luna 61–116.5、Sol 37–50.7、Astra 32–52.1）。Derived（第三方量測 Verified → 幾何平均）。兩家系統性相差 1.5–2 倍（AA 探測請求、OpenRouter 實際流量）。舊口徑 120／65／55（GPT-5.6 時代，S26）留作情境 slo_v10。首 token 時間 SLO（第 22 列）不改
A22: TTFT 上限（只作檢查） | B22: s | C22: 2 | D22: 3 | E22: 5 | F22: Assumed
A23: 參考 ISL（每次請求輸入） | B23: tok | C23: 8192 | D23: 16384 | E23: 32768 | F23: Assumed：Astra 用於長任務；上下文敏感度見 Sens_Perf
A24: 參考 OSL（含思考） | B24: tok | C24: 1024 | D24: 2048 | E24: 4096 | F24: Assumed
F25: Derived | G25: 已刪除（v14.0，4-3B Q1）：功能未接線，已移除，需要時再接線；原範圍 C25:E25；見 Decisions SL43-1
F26: Derived | G26: 已刪除（v14.0，4-3B Q1）：功能未接線，已移除，需要時再接線；原範圍 C26:E26；見 Decisions SL43-1
A28: 並列輸出用生產折減（情境值，X1；非估計值） | B28: x | C28: 0.85 | D28: Assumed | F28: v5.19 X1：只驅動 Interface G 節的 _Prod 並列輸出（Perf_Prod 第 50 列）；Serving!C18 維持 1.0（G0-11），不受影響。0.85＝C18 區間 0.7–1.0 的中點，不是估計值；Andy 日後給 C18 值時，本格可保留作並列情境 ｜暫定、待證據（D13）；區間 0.7–1.0（C18 區間的中點）；v6.1 起同時作為 Alloc_In C24 純利用率的生產折減（D13）

Sheet Workload
A1: Workload — 任務制工作負載（每任務的 token 結構；思考 token 在物理上屬 decode）
A2: 任務組合權重不在第 0 層（J5）；本頁只定義標準任務。列 5–14＝標準 harness；harness 檔案在 Har_In，依 Tech_Registry T12 混合（Block 5，L1）
I3: 用途
A4: 參數 | B4: 單位 | C4: 一般聊天 | D4: 推理聊天 | E4: 單代理（工具迴圈） | F4: 多代理研究 | G4: Coding agent（長程） | H4: 說明
A5: 輪數 T | B5: 輪 | C5: 1 | D5: 1 | E5: 4 | F5: 4 | G5: 30 | H5: Assumed；整段對話的每任務指標約 ×2–2.5（LMSYS 2.0、WildChat 2.52；E235）
A6: 初始上下文 S（系統提示、歷史、工具定義） | B6: tok | C6: 2000 | D6: 2000 | E6: 3000 | F6: 3000 | G6: 12000 | H6: Assumed
A7: 每輪新輸入 u（使用者或工具結果） | B7: tok | C7: 500 | D7: 500 | E7: 1200 | F7: 1200 | G7: 2000 | H7: Assumed
A8: 每輪思考 token h | B8: tok | C8: 0 | D8: 3000 | E8: 400 | F8: 400 | G8: 600 | H8: Assumed；服務端思考占比待查
A9: 每輪可見輸出 o | B9: tok | C9: 500 | D9: 700 | E9: 200 | F9: 200 | G9: 400 | H9: Assumed
A10: 思考保留於上下文比例 ρ | B10: % | C10: 0 | D10: 0 | E10: 0 | F10: 0 | G10: 0 | H10: Assumed：多數 API 不保留前輪思考（標準 harness）
A11: 歷史快取命中率 χ | B11: % | C11: 0.5 | D11: 0.5 | E11: 0.9 | F11: 0.9 | G11: 0.9 | H11: Assumed；代理迴圈前綴重用高
A12: 並行子代理數 m | B12: 個 | C12: 0 | D12: 0 | E12: 0 | F12: 3 | G12: 0 | H12: Assumed：子代理沿用單代理參數
A13: harness token 倍數 | B13: x | C13: 1 | D13: 1 | E13: 1 | F13: 1 | G13: 1 | H13: v5.9 起為殘差倍數（預設 1.0）；harness 效果改由 Har_In 參數組表達（L1）
A14: 歷史保留比 c（壓縮後保留的歷史比例；1＝不壓縮） | B14: x | C14: 1 | D14: 1 | E14: 1 | F14: 1 | G14: 1 | H14: 標準 harness 不壓縮；v5.9 新增（L1）
A16: 有效參數（標準＋w ×（Har_In 選定檔案−標準）；w＝B5_W）
I17: 已刪除（v14.0，4-3B Q1）：功能未接線，已移除，需要時再接線；原範圍 C17:G17；見 Decisions SL43-1
A18: 有效輪數 T | B18: 輪 | C18: =C5*(1+B5_W*(INDEX(B5_SelT,1,1)-1)) -> 1 | D18: =D5*(1+B5_W*(INDEX(B5_SelT,1,2)-1)) -> 1 | E18: =E5*(1+B5_W*(INDEX(B5_SelT,1,3)-1)) -> 4 | F18: =F5*(1+B5_W*(INDEX(B5_SelT,1,4)-1)) -> 4 | G18: =G5*(1+B5_W*(INDEX(B5_SelT,1,5)-1)) -> 30
A19: 有效每輪思考 h | B19: tok | C19: =C8*(1+B5_W*(INDEX(B5_SelH,1,1)-1)) -> 0 | D19: =D8*(1+B5_W*(INDEX(B5_SelH,1,2)-1)) -> 3000 | E19: =E8*(1+B5_W*(INDEX(B5_SelH,1,3)-1)) -> 400 | F19: =F8*(1+B5_W*(INDEX(B5_SelH,1,4)-1)) -> 400 | G19: =G8*(1+B5_W*(INDEX(B5_SelH,1,5)-1)) -> 600
A20: 有效思考保留 ρ | B20: % | C20: =C10+B5_W*(INDEX(B5_Selrho,1,1)-C10) -> 0 | D20: =D10+B5_W*(INDEX(B5_Selrho,1,2)-D10) -> 0 | E20: =E10+B5_W*(INDEX(B5_Selrho,1,3)-E10) -> 0 | F20: =F10+B5_W*(INDEX(B5_Selrho,1,4)-F10) -> 0 | G20: =G10+B5_W*(INDEX(B5_Selrho,1,5)-G10) -> 0
A21: 有效快取命中 χ | B21: % | C21: =MIN(1,MAX(0,C11+B5_W*INDEX(B5_SelDChi,1,1))) -> 0.5 | D21: =MIN(1,MAX(0,D11+B5_W*INDEX(B5_SelDChi,1,2))) -> 0.5 | E21: =MIN(1,MAX(0,E11+B5_W*INDEX(B5_SelDChi,1,3))) -> 0.9 | F21: =MIN(1,MAX(0,F11+B5_W*INDEX(B5_SelDChi,1,4))) -> 0.9 | G21: =MIN(1,MAX(0,G11+B5_W*INDEX(B5_SelDChi,1,5))) -> 0.9
A22: 有效子代理數 m | B22: 個 | C22: =C12+B5_W*INDEX(B5_SelDM,1,1) -> 0 | D22: =D12+B5_W*INDEX(B5_SelDM,1,2) -> 0 | E22: =E12+B5_W*INDEX(B5_SelDM,1,3) -> 0 | F22: =F12+B5_W*INDEX(B5_SelDM,1,4) -> 3 | G22: =G12+B5_W*INDEX(B5_SelDM,1,5) -> 0
A23: 有效歷史保留比 c | B23: x | C23: =C14+B5_W*(INDEX(B5_SelC,1,1)-C14) -> 1 | D23: =D14+B5_W*(INDEX(B5_SelC,1,2)-D14) -> 1 | E23: =E14+B5_W*(INDEX(B5_SelC,1,3)-E14) -> 1 | F23: =F14+B5_W*(INDEX(B5_SelC,1,4)-F14) -> 1 | G23: =G14+B5_W*(INDEX(B5_SelC,1,5)-G14) -> 1
A25: 導出（每任務；用有效參數）
A26: 每輪上下文增量 u＋o＋ρh | B26: tok | C26: =C7+C9+C20*C19 -> 1000 | D26: =D7+D9+D20*D19 -> 1200 | E26: =E7+E9+E20*E19 -> 1400 | F26: =F7+F9+F20*F19 -> 1400 | G26: =G7+G9+G20*G19 -> 2400
A27: 單代理輸入總量 | B27: tok | C27: =C18*(C6+C7)+C23*C26*C18*(C18-1)/2 -> 2500 | D27: =D18*(D6+D7)+D23*D26*D18*(D18-1)/2 -> 2500 | E27: =E18*(E6+E7)+E23*E26*E18*(E18-1)/2 -> 25200 | F27: =F18*(F6+F7)+F23*F26*F18*(F18-1)/2 -> 25200 | G27: =G18*(G6+G7)+G23*G26*G18*(G18-1)/2 -> 1464000
A28: 其中可快取（前綴） | B28: tok | C28: =C21*(C18*C6+C23*C26*C18*(C18-1)/2) -> 1000 | D28: =D21*(D18*D6+D23*D26*D18*(D18-1)/2) -> 1000 | E28: =E21*(E18*E6+E23*E26*E18*(E18-1)/2) -> 18360 | F28: =F21*(F18*F6+F23*F26*F18*(F18-1)/2) -> 18360 | G28: =G21*(G18*G6+G23*G26*G18*(G18-1)/2) -> 1263600
A29: 其中新鮮 | B29: tok | C29: =C27-C28 -> 1500 | D29: =D27-D28 -> 1500 | E29: =E27-E28 -> 6840 | F29: =F27-F28 -> 6840 | G29: =G27-G28 -> 200400
A30: 單代理 decode（思考＋可見） | B30: tok | C30: =C18*(C19+C9) -> 500 | D30: =D18*(D19+D9) -> 3700 | E30: =E18*(E19+E9) -> 2400 | F30: =F18*(F19+F9) -> 2400 | G30: =G18*(G19+G9) -> 30000
A31: 系統倍數（1＋m）× harness 殘差倍數 | B31: x | C31: =(1+C22)*C13 -> 1 | D31: =(1+D22)*D13 -> 1 | E31: =(1+E22)*E13 -> 1 | F31: =(1+F22)*F13 -> 4 | G31: =(1+G22)*G13 -> 1
A32: 任務新鮮 prefill | B32: tok | C32: =C29*C31 -> 1500 | D32: =D29*D31 -> 1500 | E32: =E29*E31 -> 6840 | F32: =F29*F31 -> 27360 | G32: =G29*G31 -> 200400
A33: 任務快取 prefill | B33: tok | C33: =C28*C31 -> 1000 | D33: =D28*D31 -> 1000 | E33: =E28*E31 -> 18360 | F33: =F28*F31 -> 73440 | G33: =G28*G31 -> 1263600
A34: 任務 decode | B34: tok | C34: =C30*C31 -> 500 | D34: =D30*D31 -> 3700 | E34: =E30*E31 -> 2400 | F34: =F30*F31 -> 9600 | G34: =G30*G31 -> 30000
A35: 任務總 token | B35: tok | C35: =C32+C33+C34 -> 3000 | D35: =D32+D33+D34 -> 6200 | E35: =E32+E33+E34 -> 27600 | F35: =F32+F33+F34 -> 110400 | G35: =G32+G33+G34 -> 1494000
H36: Unit_Cost 的 decode 成本取各層級參考上下文；本列顯示任務實際上下文，差距大時看 Sens_Perf 的 ISL 情境 | I36: 已刪除（v14.0，4-3B Q1）：功能未接線，已移除，需要時再接線；原範圍 C36:G36；見 Decisions SL43-1
I37: 已刪除（v14.0，4-3B Q1）：功能未接線，已移除，需要時再接線；原範圍 C37:G37；見 Decisions SL43-1
A38: 總 token ÷ 一般聊天 | B38: x | C38: =C35/$C$35 -> 1 | D38: =D35/$C$35 -> 2.0666667 | E38: =E35/$C$35 -> 9.2 | F38: =F35/$C$35 -> 36.8 | G38: =G35/$C$35 -> 498
I39: 已刪除（v14.0，4-3B Q1）：功能未接線，已移除，需要時再接線；原範圍 C39:G39；見 Decisions SL43-1
A40: 參照：Anthropic 揭露倍數（相對聊天） | B40: x | C40: 1 | E40: =SRC_HAR_001 -> 4 | F40: =SRC_HAR_002 -> 15 | H40: Interested-party：Anthropic 2025-06 多代理研究系統文章，agent 約 4 倍、多代理約 15 倍聊天 token（S25）。其『聊天』口徑未說明是否含思考，故兩個倍數並列。本頁列 38 的單代理、多代理倍數高於此參照約 2.3–2.5 倍（Block 2 既有假設，未調整） | I40: 備用（無公式讀取）：C 欄（參照基準 1；E、F 欄連結 SRC）
A42: 每任務成本（$／任務；經濟口徑、基準成本情境、基準利用率；不含快取儲存，含儲存者見 Harness 頁）
I43: 已刪除（v14.0，4-3B Q1）：功能未接線，已移除，需要時再接線；原範圍 C43:G43；見 Decisions SL43-1
I44: 已刪除（v14.0，4-3B Q1）：功能未接線，已移除，需要時再接線；原範圍 C44:G44；見 Decisions SL43-1
I45: 已刪除（v14.0，4-3B Q1）：功能未接線，已移除，需要時再接線；原範圍 C45:G45；見 Decisions SL43-1
I46: 已刪除（v14.0，4-3B Q1）：功能未接線，已移除，需要時再接線；原範圍 C46:G46；見 Decisions SL43-1
I47: 已刪除（v14.0，4-3B Q1）：功能未接線，已移除，需要時再接線；原範圍 C47:G47；見 Decisions SL43-1
I48: 已刪除（v14.0，4-3B Q1）：功能未接線，已移除，需要時再接線；原範圍 C48:G48；見 Decisions SL43-1

Sheet Calib
A1: Calib — 以實測錨點校準效率係數（實測只校準係數，不取代推導）
A2: 錨點：DeepSeek V4-Pro（＝Sol 代表架構）、FP4、8K/1K、分離式 P/D，tok/s/GPU 為總 token 口徑。GB300 同一前緣上兩點聯立解出 η_d 與每層延遲；其餘各點為樣本外驗證
K3: 用途
A4: A. 輸入
A5: η_p：prefill 達成峰值比例 | B5: % | C5: 0.3 | J5: Analogy：DeepSeek H800 線上 prefill 約 0.37（S30，待查）；區間 0.15–0.45。擬合結果對此不敏感（見 G 節）；v15.0 O8：Hopper 吞吐為保守下界（獨立對照 V7、V8、V15 顯示模型約為實測 0.26–0.27 倍；Hopper η 倍數無獨立依據，Decisions SL46-13）；對外引用 Hopper 欄請標『保守下界』
A7: B. 錨點（每欄一個實測點）
A8: 項目 | B8: 單位
A9: 用途 | C9: 擬合點 1 | D9: 擬合點 2 | E9: 驗證 | F9: 驗證（舊軟體） | G9: 驗證（舊軟體） | H9: 驗證（口徑待查） | I9: 驗證（口徑待查）
A10: 世代索引 | C10: 3 | D10: 3 | E10: 3 | F10: 3 | G10: 2 | H10: 2 | I10: 3 | K10: 顯示用：I10（校準點逐步重現）
A11: 世代 | C11: =INDEX(Spec_Rack!$C$4:$G$4,C10) -> GB300 NVL72 | D11: =INDEX(Spec_Rack!$C$4:$G$4,D10) -> GB300 NVL72 | E11: =INDEX(Spec_Rack!$C$4:$G$4,E10) -> GB300 NVL72 | F11: =INDEX(Spec_Rack!$C$4:$G$4,F10) -> GB300 NVL72 | G11: =INDEX(Spec_Rack!$C$4:$G$4,G10) -> GB200 NVL72 | H11: =INDEX(Spec_Rack!$C$4:$G$4,H10) -> GB200 NVL72 | I11: =INDEX(Spec_Rack!$C$4:$G$4,I10) -> GB300 NVL72 | K11: 顯示用：C11:I11（欄頭／表頭標籤）
A12: 軟體／日期 | C12: InferenceX 最佳前緣（約 2026-07） | D12: InferenceX 最佳前緣（約 2026-07） | E12: SGLang＋MTP，2026-06 | F12: vLLM 無 MTP，2026-05-22 | G12: vLLM 無 MTP，2026-05-22 | H12: InferenceX 比較頁（0813） | I12: InferenceX 比較頁（0813）
A13: MTP（1＝有） | C13: =SRC_PERF_009_MTP -> 1 | D13: =SRC_PERF_010_MTP -> 1 | E13: =SRC_PERF_004_MTP -> 1 | F13: =SRC_PERF_001_MTP -> 0 | G13: =SRC_PERF_002_MTP -> 0 | H13: =SRC_PERF_014_MTP -> 1 | I13: =SRC_PERF_015_MTP -> 1 | K13: 顯示用：I13（校準點逐步重現）
A14: 每用戶速度 | B14: tok/s | C14: =SRC_PERF_009_Spd -> 72 | D14: =SRC_PERF_010_Spd -> 130 | E14: =SRC_PERF_004_Spd -> 50 | F14: =SRC_PERF_001_Spd -> 27 | G14: =SRC_PERF_002_Spd -> 27 | H14: =SRC_PERF_014_Spd -> 110 | I14: =SRC_PERF_015_Spd -> 110 | K14: 顯示用：I14（校準點逐步重現）
A15: ISL | B15: tok | C15: =SRC_PERF_009_ISL -> 8192 | D15: =SRC_PERF_010_ISL -> 8192 | E15: =SRC_PERF_004_ISL -> 8192 | F15: =SRC_PERF_001_ISL -> 8192 | G15: =SRC_PERF_002_ISL -> 8192 | H15: =SRC_PERF_014_ISL -> 8192 | I15: =SRC_PERF_015_ISL -> 8192 | K15: 顯示用：I15（校準點逐步重現）
A16: OSL | B16: tok | C16: =SRC_PERF_009_OSL -> 1024 | D16: =SRC_PERF_010_OSL -> 1024 | E16: =SRC_PERF_004_OSL -> 1024 | F16: =SRC_PERF_001_OSL -> 1024 | G16: =SRC_PERF_002_OSL -> 1024 | H16: =SRC_PERF_014_OSL -> 1024 | I16: =SRC_PERF_015_OSL -> 1024 | K16: 顯示用：I16（校準點逐步重現）
A17: 實測 tok/s/GPU（總 token） | B17: tok/s | C17: =SRC_PERF_009 -> 9342.1 | D17: =SRC_PERF_010 -> 3405.2 | E17: =SRC_PERF_004 -> 11200 | F17: =SRC_PERF_001 -> 6182 | G17: =SRC_PERF_002 -> 2189 | H17: =SRC_PERF_014 -> 3795.5 | I17: =SRC_PERF_015 -> 6522.4 | K17: 顯示用：I17（校準點逐步重現）
A18: 來源 | C18: S22 | D18: S22 | E18: S21 | F18: S20 | G18: S20 | H18: S23 | I18: S23
A19: 量測平台（獨立性） | C19: InferenceX（SemiAnalysis） | D19: InferenceX（SemiAnalysis） | E19: InferenceX（SemiAnalysis） | F19: InferenceX（SemiAnalysis） | G19: InferenceX（SemiAnalysis） | H19: InferenceX（SemiAnalysis） | I19: InferenceX（SemiAnalysis） | J19: 七個點全部來自同一平台（S21 為 SGLang 作者轉述 InferenceX 資料，不構成獨立來源）。第二來源見 H 節
A20: 點位標籤（世代｜用途｜速度） | C20: =C11&"｜"&C9&"｜"&TEXT(C14,"0")&" tok/s" -> GB300 NVL72｜擬合點 1｜72 tok/s | D20: =D11&"｜"&D9&"｜"&TEXT(D14,"0")&" tok/s" -> GB300 NVL72｜擬合點 2｜130 tok/s | E20: =E11&"｜"&E9&"｜"&TEXT(E14,"0")&" tok/s" -> GB300 NVL72｜驗證｜50 tok/s | F20: =F11&"｜"&F9&"｜"&TEXT(F14,"0")&" tok/s" -> GB300 NVL72｜驗證（舊軟體）｜27 tok/s | G20: =G11&"｜"&G9&"｜"&TEXT(G14,"0")&" tok/s" -> GB200 NVL72｜驗證（舊軟體）｜27 tok/s | H20: =H11&"｜"&H9&"｜"&TEXT(H14,"0")&" tok/s" -> GB200 NVL72｜驗證（口徑待查）｜110 tok/s | I20: =I11&"｜"&I9&"｜"&TEXT(I14,"0")&" tok/s" -> GB300 NVL72｜驗證（口徑待查）｜110 tok/s | K20: 顯示用：C20:I20（欄頭／表頭標籤）
A21: 口徑 | C21: 總 token（輸入＋輸出） | D21: 總 token（輸入＋輸出） | E21: 總 token（輸入＋輸出） | F21: 總 token（輸入＋輸出） | G21: 總 token（輸入＋輸出） | H21: 總 token（輸入＋輸出） | I21: 總 token（輸入＋輸出）
A22: C. 各點的模型量（Sol 架構；與 Perf 同一套公式）
A23: 計算用峰值 | B23: PF/GPU | C23: =INDEX(Spec_Rack!$C$35:$G$35,C10) -> 15 | D23: =INDEX(Spec_Rack!$C$35:$G$35,D10) -> 15 | E23: =INDEX(Spec_Rack!$C$35:$G$35,E10) -> 15 | F23: =INDEX(Spec_Rack!$C$35:$G$35,F10) -> 15 | G23: =INDEX(Spec_Rack!$C$35:$G$35,G10) -> 10 | H23: =INDEX(Spec_Rack!$C$35:$G$35,H10) -> 10 | I23: =INDEX(Spec_Rack!$C$35:$G$35,I10) -> 15 | K23: 顯示用：I23（校準點逐步重現）
A24: HBM 容量 | B24: GB | C24: =INDEX(Spec_Rack!$C$25:$G$25,C10) -> 288 | D24: =INDEX(Spec_Rack!$C$25:$G$25,D10) -> 288 | E24: =INDEX(Spec_Rack!$C$25:$G$25,E10) -> 288 | F24: =INDEX(Spec_Rack!$C$25:$G$25,F10) -> 288 | G24: =INDEX(Spec_Rack!$C$25:$G$25,G10) -> 186 | H24: =INDEX(Spec_Rack!$C$25:$G$25,H10) -> 186 | I24: =INDEX(Spec_Rack!$C$25:$G$25,I10) -> 288 | K24: 顯示用：D24:I24（校準點逐步重現）
A25: HBM 頻寬 | B25: TB/s | C25: =INDEX(Spec_Rack!$C$26:$G$26,C10) -> 8 | D25: =INDEX(Spec_Rack!$C$26:$G$26,D10) -> 8 | E25: =INDEX(Spec_Rack!$C$26:$G$26,E10) -> 8 | F25: =INDEX(Spec_Rack!$C$26:$G$26,F10) -> 8 | G25: =INDEX(Spec_Rack!$C$26:$G$26,G10) -> 8 | H25: =INDEX(Spec_Rack!$C$26:$G$26,H10) -> 8 | I25: =INDEX(Spec_Rack!$C$26:$G$26,I10) -> 8 | K25: 顯示用：D25:I25（校準點逐步重現）
A26: EP 通訊頻寬 | B26: TB/s | C26: =INDEX(Spec_Rack!$C$27:$G$27,C10) -> 0.9 | D26: =INDEX(Spec_Rack!$C$27:$G$27,D10) -> 0.9 | E26: =INDEX(Spec_Rack!$C$27:$G$27,E10) -> 0.9 | F26: =INDEX(Spec_Rack!$C$27:$G$27,F10) -> 0.9 | G26: =INDEX(Spec_Rack!$C$27:$G$27,G10) -> 0.9 | H26: =INDEX(Spec_Rack!$C$27:$G$27,H10) -> 0.9 | I26: =INDEX(Spec_Rack!$C$27:$G$27,I10) -> 0.9 | K26: 顯示用：D26:I26（校準點逐步重現）
A27: EP 基準寬度 | C27: =INDEX(Spec_Rack!$C$29:$G$29,C10) -> 32 | D27: =INDEX(Spec_Rack!$C$29:$G$29,D10) -> 32 | E27: =INDEX(Spec_Rack!$C$29:$G$29,E10) -> 32 | F27: =INDEX(Spec_Rack!$C$29:$G$29,F10) -> 32 | G27: =INDEX(Spec_Rack!$C$29:$G$29,G10) -> 32 | H27: =INDEX(Spec_Rack!$C$29:$G$29,H10) -> 32 | I27: =INDEX(Spec_Rack!$C$29:$G$29,I10) -> 32 | K27: 顯示用：D27:I27（校準點逐步重現）
A28: 專家 bytes/param | B28: B | C28: =INDEX(Spec_Rack!$C$30:$G$30,C10) -> 0.5625 | D28: =INDEX(Spec_Rack!$C$30:$G$30,D10) -> 0.5625 | E28: =INDEX(Spec_Rack!$C$30:$G$30,E10) -> 0.5625 | F28: =INDEX(Spec_Rack!$C$30:$G$30,F10) -> 0.5625 | G28: =INDEX(Spec_Rack!$C$30:$G$30,G10) -> 0.5625 | H28: =INDEX(Spec_Rack!$C$30:$G$30,H10) -> 0.5625 | I28: =INDEX(Spec_Rack!$C$30:$G$30,I10) -> 0.5625 | K28: 顯示用：D28:I28（校準點逐步重現）
A29: 非專家 bytes/param | B29: B | C29: =INDEX(Spec_Rack!$C$31:$G$31,C10) -> 1 | D29: =INDEX(Spec_Rack!$C$31:$G$31,D10) -> 1 | E29: =INDEX(Spec_Rack!$C$31:$G$31,E10) -> 1 | F29: =INDEX(Spec_Rack!$C$31:$G$31,F10) -> 1 | G29: =INDEX(Spec_Rack!$C$31:$G$31,G10) -> 1 | H29: =INDEX(Spec_Rack!$C$31:$G$31,H10) -> 1 | I29: =INDEX(Spec_Rack!$C$31:$G$31,I10) -> 1 | K29: 顯示用：D29:I29（校準點逐步重現）
A30: 啟用參數 | B30: B | C30: =Arch!$D$7 -> 49 | D30: =Arch!$D$7 -> 49 | E30: =Arch!$D$7 -> 49 | F30: =Arch!$D$7 -> 49 | G30: =Arch!$D$7 -> 49 | H30: =Arch!$D$7 -> 49 | I30: =Arch!$D$7 -> 49 | K30: 顯示用：I30（校準點逐步重現）
A31: 層數 | C31: =Arch!$D$8 -> 61 | D31: =Arch!$D$8 -> 61 | E31: =Arch!$D$8 -> 61 | F31: =Arch!$D$8 -> 61 | G31: =Arch!$D$8 -> 61 | H31: =Arch!$D$8 -> 61 | I31: =Arch!$D$8 -> 61 | K31: 顯示用：D31:I31（校準點逐步重現）
A32: d_model | C32: =Arch!$D$9 -> 7168 | D32: =Arch!$D$9 -> 7168 | E32: =Arch!$D$9 -> 7168 | F32: =Arch!$D$9 -> 7168 | G32: =Arch!$D$9 -> 7168 | H32: =Arch!$D$9 -> 7168 | I32: =Arch!$D$9 -> 7168 | K32: 顯示用：D32:I32（校準點逐步重現）
A33: 啟用專家 | C33: =Arch!$D$13 -> 6 | D33: =Arch!$D$13 -> 6 | E33: =Arch!$D$13 -> 6 | F33: =Arch!$D$13 -> 6 | G33: =Arch!$D$13 -> 6 | H33: =Arch!$D$13 -> 6 | I33: =Arch!$D$13 -> 6 | K33: 顯示用：D33:I33（校準點逐步重現）
A34: 非專家參數 | B34: B | C34: =Arch!$D$28 -> 20.277778 | D34: =Arch!$D$28 -> 20.277778 | E34: =Arch!$D$28 -> 20.277778 | F34: =Arch!$D$28 -> 20.277778 | G34: =Arch!$D$28 -> 20.277778 | H34: =Arch!$D$28 -> 20.277778 | I34: =Arch!$D$28 -> 20.277778 | K34: 顯示用：D34:I34（校準點逐步重現）
A35: 專家參數 | B35: B | C35: =Arch!$D$29 -> 1579.7222 | D35: =Arch!$D$29 -> 1579.7222 | E35: =Arch!$D$29 -> 1579.7222 | F35: =Arch!$D$29 -> 1579.7222 | G35: =Arch!$D$29 -> 1579.7222 | H35: =Arch!$D$29 -> 1579.7222 | I35: =Arch!$D$29 -> 1579.7222 | K35: 顯示用：D35:I35（校準點逐步重現）
A36: KV bytes/token | B36: B | C36: =Arch!$D$25 -> 3965 | D36: =Arch!$D$25 -> 3965 | E36: =Arch!$D$25 -> 3965 | F36: =Arch!$D$25 -> 3965 | G36: =Arch!$D$25 -> 3965 | H36: =Arch!$D$25 -> 3965 | I36: =Arch!$D$25 -> 3965 | K36: 顯示用：D36:I36（校準點逐步重現）
A37: 注意力 FLOPs／被注意 token | C37: =Arch!$D$30 -> 15990784 | D37: =Arch!$D$30 -> 15990784 | E37: =Arch!$D$30 -> 15990784 | F37: =Arch!$D$30 -> 15990784 | G37: =Arch!$D$30 -> 15990784 | H37: =Arch!$D$30 -> 15990784 | I37: =Arch!$D$30 -> 15990784 | K37: 顯示用：I37（校準點逐步重現）
A38: 全注意力層比例 | B38: % | C38: =Arch!$D$16 -> 0.492 | D38: =Arch!$D$16 -> 0.492 | E38: =Arch!$D$16 -> 0.492 | F38: =Arch!$D$16 -> 0.492 | G38: =Arch!$D$16 -> 0.492 | H38: =Arch!$D$16 -> 0.492 | I38: =Arch!$D$16 -> 0.492 | K38: 顯示用：I38（校準點逐步重現）
A39: 跨度上限 | C39: =Arch!$D$17 -> 4224 | D39: =Arch!$D$17 -> 4224 | E39: =Arch!$D$17 -> 4224 | F39: =Arch!$D$17 -> 4224 | G39: =Arch!$D$17 -> 4224 | H39: =Arch!$D$17 -> 4224 | I39: =Arch!$D$17 -> 4224 | K39: 顯示用：I39（校準點逐步重現）
A40: 壓縮比 | C40: =Arch!$D$18 -> 128 | D40: =Arch!$D$18 -> 128 | E40: =Arch!$D$18 -> 128 | F40: =Arch!$D$18 -> 128 | G40: =Arch!$D$18 -> 128 | H40: =Arch!$D$18 -> 128 | I40: =Arch!$D$18 -> 128 | K40: 顯示用：I40（校準點逐步重現）
A41: 滑動窗 | C41: =Arch!$D$19 -> 128 | D41: =Arch!$D$19 -> 128 | E41: =Arch!$D$19 -> 128 | F41: =Arch!$D$19 -> 128 | G41: =Arch!$D$19 -> 128 | H41: =Arch!$D$19 -> 128 | I41: =Arch!$D$19 -> 128 | K41: 顯示用：I41（校準點逐步重現）
A42: decode 平均上下文 | B42: tok | C42: =C15+C16/2 -> 8704 | D42: =D15+D16/2 -> 8704 | E42: =E15+E16/2 -> 8704 | F42: =F15+F16/2 -> 8704 | G42: =G15+G16/2 -> 8704 | H42: =H15+H16/2 -> 8704 | I42: =I15+I16/2 -> 8704 | K42: 顯示用：D42:I42（校準點逐步重現）
A43: decode 被注意 token | B43: tok | C43: =C38*IF(C39=0,C42,MIN(C42,C39))+(1-C38)*(C42/C40+C41) -> 2177.776 | D43: =D38*IF(D39=0,D42,MIN(D42,D39))+(1-D38)*(D42/D40+D41) -> 2177.776 | E43: =E38*IF(E39=0,E42,MIN(E42,E39))+(1-E38)*(E42/E40+E41) -> 2177.776 | F43: =F38*IF(F39=0,F42,MIN(F42,F39))+(1-F38)*(F42/F40+F41) -> 2177.776 | G43: =G38*IF(G39=0,G42,MIN(G42,G39))+(1-G38)*(G42/G40+G41) -> 2177.776 | H43: =H38*IF(H39=0,H42,MIN(H42,H39))+(1-H38)*(H42/H40+H41) -> 2177.776 | I43: =I38*IF(I39=0,I42,MIN(I42,I39))+(1-I38)*(I42/I40+I41) -> 2177.776 | K43: 顯示用：D43:I43（校準點逐步重現）
A44: decode FLOPs/token | B44: GFLOP | C44: =(2*C30*1000000000+C37*C43)/1000000000 -> 132.82435 | D44: =(2*D30*1000000000+D37*D43)/1000000000 -> 132.82435 | E44: =(2*E30*1000000000+E37*E43)/1000000000 -> 132.82435 | F44: =(2*F30*1000000000+F37*F43)/1000000000 -> 132.82435 | G44: =(2*G30*1000000000+G37*G43)/1000000000 -> 132.82435 | H44: =(2*H30*1000000000+H37*H43)/1000000000 -> 132.82435 | I44: =(2*I30*1000000000+I37*I43)/1000000000 -> 132.82435 | K44: 顯示用：D44:I44（校準點逐步重現）
A45: prefill 平均位置 | B45: tok | C45: =C15/2 -> 4096 | D45: =D15/2 -> 4096 | E45: =E15/2 -> 4096 | F45: =F15/2 -> 4096 | G45: =G15/2 -> 4096 | H45: =H15/2 -> 4096 | I45: =I15/2 -> 4096 | K45: 顯示用：I45（校準點逐步重現）
A46: prefill 被注意 token | B46: tok | C46: =C38*IF(C39=0,C45,MIN(C45,C39))+(1-C38)*(C45/C40+C41) -> 2096.512 | D46: =D38*IF(D39=0,D45,MIN(D45,D39))+(1-D38)*(D45/D40+D41) -> 2096.512 | E46: =E38*IF(E39=0,E45,MIN(E45,E39))+(1-E38)*(E45/E40+E41) -> 2096.512 | F46: =F38*IF(F39=0,F45,MIN(F45,F39))+(1-F38)*(F45/F40+F41) -> 2096.512 | G46: =G38*IF(G39=0,G45,MIN(G45,G39))+(1-G38)*(G45/G40+G41) -> 2096.512 | H46: =H38*IF(H39=0,H45,MIN(H45,H39))+(1-H38)*(H45/H40+H41) -> 2096.512 | I46: =I38*IF(I39=0,I45,MIN(I45,I39))+(1-I38)*(I45/I40+I41) -> 2096.512 | K46: 顯示用：I46（校準點逐步重現）
A47: prefill FLOPs/token | B47: GFLOP | C47: =(2*C30*1000000000+C37*C46)/1000000000 -> 131.52487 | D47: =(2*D30*1000000000+D37*D46)/1000000000 -> 131.52487 | E47: =(2*E30*1000000000+E37*E46)/1000000000 -> 131.52487 | F47: =(2*F30*1000000000+F37*F46)/1000000000 -> 131.52487 | G47: =(2*G30*1000000000+G37*G46)/1000000000 -> 131.52487 | H47: =(2*H30*1000000000+H37*H46)/1000000000 -> 131.52487 | I47: =(2*I30*1000000000+I37*I46)/1000000000 -> 131.52487 | K47: 顯示用：I47（校準點逐步重現）
A48: 可用 HBM | B48: GB | C48: =C24*(1-Serving!$C$9) -> 259.2 | D48: =D24*(1-Serving!$C$9) -> 259.2 | E48: =E24*(1-Serving!$C$9) -> 259.2 | F48: =F24*(1-Serving!$C$9) -> 259.2 | G48: =G24*(1-Serving!$C$9) -> 167.4 | H48: =H24*(1-Serving!$C$9) -> 167.4 | I48: =I24*(1-Serving!$C$9) -> 259.2 | K48: 顯示用：D48:I48（校準點逐步重現）
A49: 注意力 TP 度 | C49: =MAX(1,CEILING(C34*C29/(Serving!$C$10*C48),1)) -> 1 | D49: =MAX(1,CEILING(D34*D29/(Serving!$C$10*D48),1)) -> 1 | E49: =MAX(1,CEILING(E34*E29/(Serving!$C$10*E48),1)) -> 1 | F49: =MAX(1,CEILING(F34*F29/(Serving!$C$10*F48),1)) -> 1 | G49: =MAX(1,CEILING(G34*G29/(Serving!$C$10*G48),1)) -> 1 | H49: =MAX(1,CEILING(H34*H29/(Serving!$C$10*H48),1)) -> 1 | I49: =MAX(1,CEILING(I34*I29/(Serving!$C$10*I48),1)) -> 1 | K49: 顯示用：D49:I49（校準點逐步重現）
A50: EP 寬度 | C50: =MAX(C27,CEILING(C35*C28/(Serving!$C$11*C48),1)) -> 32 | D50: =MAX(D27,CEILING(D35*D28/(Serving!$C$11*D48),1)) -> 32 | E50: =MAX(E27,CEILING(E35*E28/(Serving!$C$11*E48),1)) -> 32 | F50: =MAX(F27,CEILING(F35*F28/(Serving!$C$11*F48),1)) -> 32 | G50: =MAX(G27,CEILING(G35*G28/(Serving!$C$11*G48),1)) -> 32 | H50: =MAX(H27,CEILING(H35*H28/(Serving!$C$11*H48),1)) -> 32 | I50: =MAX(I27,CEILING(I35*I28/(Serving!$C$11*I48),1)) -> 32 | K50: 顯示用：D50:I50（校準點逐步重現）
A51: 每 GPU 權重 | B51: GB | C51: =C34*C29/C49+C35*C28/C50 -> 48.046332 | D51: =D34*D29/D49+D35*D28/D50 -> 48.046332 | E51: =E34*E29/E49+E35*E28/E50 -> 48.046332 | F51: =F34*F29/F49+F35*F28/F50 -> 48.046332 | G51: =G34*G29/G49+G35*G28/G50 -> 48.046332 | H51: =H34*H29/H49+H35*H28/H50 -> 48.046332 | I51: =I34*I29/I49+I35*I28/I50 -> 48.046332 | K51: 顯示用：D51:I51（校準點逐步重現）
A52: 草稿數（無 MTP＝0） | C52: =Serving!$C$6*C13 -> 3 | D52: =Serving!$C$6*D13 -> 3 | E52: =Serving!$C$6*E13 -> 3 | F52: =Serving!$C$6*F13 -> 0 | G52: =Serving!$C$6*G13 -> 0 | H52: =Serving!$C$6*H13 -> 3 | I52: =Serving!$C$6*I13 -> 3 | K52: 顯示用：D52:I52（校準點逐步重現）
A53: 每步接受 token | C53: =IF(C13=1,Serving!$C$8,1) -> 2.533 | D53: =IF(D13=1,Serving!$C$8,1) -> 2.533 | E53: =IF(E13=1,Serving!$C$8,1) -> 2.533 | F53: =IF(F13=1,Serving!$C$8,1) -> 1 | G53: =IF(G13=1,Serving!$C$8,1) -> 1 | H53: =IF(H13=1,Serving!$C$8,1) -> 2.533 | I53: =IF(I13=1,Serving!$C$8,1) -> 2.533 | K53: 顯示用：I53（校準點逐步重現）
A54: prefill tok/s/GPU（η_p 基準） | B54: tok/s | C54: =$C$5*C23*1000000000000000/(C47*1000000000) -> 34214.061 | D54: =$C$5*D23*1000000000000000/(D47*1000000000) -> 34214.061 | E54: =$C$5*E23*1000000000000000/(E47*1000000000) -> 34214.061 | F54: =$C$5*F23*1000000000000000/(F47*1000000000) -> 34214.061 | G54: =$C$5*G23*1000000000000000/(G47*1000000000) -> 22809.374 | H54: =$C$5*H23*1000000000000000/(H47*1000000000) -> 22809.374 | I54: =$C$5*I23*1000000000000000/(I47*1000000000) -> 34214.061 | K54: 顯示用：E54:I54（校準點逐步重現）
A55: 每序列算力時間（η＝1） | B55: ms | C55: =(C52+1)*C44/C23/1000 -> 0.035419825 | D55: =(D52+1)*D44/D23/1000 -> 0.035419825 | E55: =(E52+1)*E44/E23/1000 -> 0.035419825 | F55: =(F52+1)*F44/F23/1000 -> 0.0088549564 | G55: =(G52+1)*G44/G23/1000 -> 0.013282435 | H55: =(H52+1)*H44/H23/1000 -> 0.053129738 | I55: =(I52+1)*I44/I23/1000 -> 0.035419825 | K55: 顯示用：D55:I55（校準點逐步重現）
A56: 實測反推 decode tok/s（每 decode GPU） | B56: tok/s | C56: =C16/((C15+C16)/C17-C15/C54) -> 1370.6914 | D56: =D16/((D15+D16)/D17-D15/D54) -> 415.07648 | E56: =E16/((E15+E16)/E17-E15/E54) -> 1755.1575 | F56: =F16/((F15+F16)/F17-F15/F54) -> 818.31886 | G56: =G16/((G15+G16)/G17-G15/G54) -> 265.90558 | H56: =H16/((H15+H16)/H17-H15/H54) -> 494.92795 | I56: =I16/((I15+I16)/I17-I15/I54) -> 872.57128 | J56: 只對擬合點有意義；假設 P:D GPU 依工作量配比 | K56: 顯示用：E56:I56（校準點逐步重現）
A57: 實測反推批次 | B57: 序列/GPU | C57: =C56/C14 -> 19.03738 | D57: =D56/D14 -> 3.192896 | E57: =E56/E14 -> 35.10315 | F57: =F56/F14 -> 30.308106 | G57: =G56/G14 -> 9.8483548 | H57: =H56/H14 -> 4.499345 | I57: =I56/I14 -> 7.9324662 | K57: 顯示用：E57:I57（校準點逐步重現）
A59: D. 擬合（擬合點 1、2 聯立；假設兩點皆為算力項綁定，見下列檢查）
A60: η_d：decode 每序列算力效率 | B60: % | C60: =(C57-D57)*C55/(1000*(C53/C14-D53/D14)) -> 0.035755033 | J60: B×c/η＝1000×a/s − 固定延遲；兩點相減消去固定延遲
A61: 每步固定延遲（GB300、Sol、含 MTP） | B61: ms | C61: =1000*C53/C14-C57*C55/C60 -> 16.321653
A62: 每層每次前向固定延遲 | B62: µs | C62: =(C61-C51/C25)*1000/(C31+C52) -> 161.18534 | J62: （固定延遲 − 權重讀取時間）÷（層數＋草稿數）：涵蓋 all-to-all 延遲、kernel 啟動、同步
A63: 檢查：擬合點 1 算力項為綁定 | C63: =IF(C55/C60>=MAX(C36*C42/(C25*Serving!$C$13)/1000000000,(C52+1)*C31*C33*C32*Serving!$C$12/(C26*Serving!$C$14)/1000000000),"成立","不成立") -> 成立 | K63: 顯示用：C63（驗證列）
A65: E. 各世代採用參數（GB300＝擬合值；其他世代＝擬合值 × 倍數）
A66: 世代 | C66: =Spec_Rack!C4 -> Hopper H100 | D66: =Spec_Rack!D4 -> GB200 NVL72 | E66: =Spec_Rack!E4 -> GB300 NVL72 | F66: =Spec_Rack!F4 -> VR200 NVL72 | G66: =Spec_Rack!G4 -> Rubin Ultra（MGX NVL 單架，72 GPU） | K66: 顯示用：C66:G66（欄頭／表頭標籤）
A67: η_d 倍數 | B67: x | C67: 1.2 | D67: 1 | E67: 1 | F67: 1 | G67: 1 | J67: Derived（粗略）：k ≈ 峰值比 7.58 ÷ 實測比；MLPerf v5.1 推得 1.45–1.63，LMSYS／NVIDIA 推得約 1.1–1.3，InferenceX 約 0.8–1.0；區間 0.8–1.6（3A 查證 Q4）。原 1.5 為 v5.5 為使 Hopper 產出不變而倒推。GB200、VR200 沿用 GB300 [Analogy]；RU [Assumed]；v15.0 O8：Hopper 吞吐為保守下界（獨立對照 V7、V8、V15 顯示模型約為實測 0.26–0.27 倍；Hopper η 倍數無獨立依據，Decisions SL46-13）；對外引用 Hopper 欄請標『保守下界』
A68: 每層延遲倍數 | B68: x | C68: 1.5 | D68: 1 | E68: 1 | F68: 1 | G68: 1 | J68: Hopper EP 跨節點走 IB [倒推（v5.5 建檔時與 C67 手算配對；Excel 內無公式關聯）1.5，區間 1–3]；J4（第 2 批 2-2 段，chat 端預設，可撤回）：不重新反解——反解需要一個實測目標，用 MLPerf 或 LMSYS 反解會把 D5 的驗證點變成校準點；等第 2-5 段有獨立驗證點後，若模型 ÷ 實測偏離過大再提出 ｜v11.0 G1 追查（Decisions BB-G1）：1.5 自 v5.2（2026-09-30）建檔即存在，標記 Assumed（Hopper EP 跨節點走 IB，區間 1–3），v5.2–v5.12 每層延遲＝240.4 µs（擬合 160.28 × 1.5），不是 DeepSeek 論文的 241.92 µs；該數字於 2026-10-16 才進 repo。v10.2 擬合更新為 161.19 µs 後乘積變 241.78 µs，與 241.92 µs 相差 0.06%＝巧合。物理上固定延遲（每層 all-to-all 延遲、同步）與 EP 通訊項（頻寬×資料量）也不是同一量。判定：無法確認重複計算，C68 不改。假設 C68＝1.0 的試算見 Decisions BB-G1 ｜v12.0 H4 更正（Decisions BB2-H4）：上文『倒推（v5.5 建檔時與 C67 手算配對；Excel 內無公式關聯）』一語是稽核第 2 批工作單 J4（2026-10-16，d25bb75）誤寫，無證據：v5.2–v5.12 各版工作簿的標記皆為 Assumed。正確標記：Assumed，無來源（v5.2 建檔以來的整數假設，非反推）；數值維持 1.5，區間 1.0–1.5（Gov_Map）；情境 c68_1 試算 C68＝1.0。原字樣保留，不刪改
A69: η_p 倍數 | B69: x | C69: =SRC_HW_019/SRC_HW_040 -> 0.49974735 | D69: 1 | E69: 1 | F69: 1 | G69: 1 | J69: Hopper 0.5：v5.5 峰值更正（989→1,979 TF）後維持 prefill 產出不變（誤差 0.05%）；S30 口徑查核後重推
A70: η_d（採用） | B70: % | C70: =$C$60*C67 -> 0.04290604 | D70: =$C$60*D67 -> 0.035755033 | E70: =$C$60*E67 -> 0.035755033 | F70: =$C$60*F67 -> 0.035755033 | G70: =$C$60*G67 -> 0.035755033
A71: 每層延遲（採用） | B71: µs | C71: =$C$62*C68 -> 241.77801 | D71: =$C$62*D68 -> 161.18534 | E71: =$C$62*E68 -> 161.18534 | F71: =$C$62*F68 -> 161.18534 | G71: =$C$62*G68 -> 161.18534
A72: η_p（採用） | B72: % | C72: =$C$5*C69 -> 0.1499242 | D72: =$C$5*D69 -> 0.3 | E72: =$C$5*E69 -> 0.3 | F72: =$C$5*F69 -> 0.3 | G72: =$C$5*G69 -> 0.3
A74: F. 樣本外驗證（以採用參數重算各點）
A75: η_d（該世代） | B75: % | C75: =INDEX($C$70:$G$70,C10) -> 0.035755033 | D75: =INDEX($C$70:$G$70,D10) -> 0.035755033 | E75: =INDEX($C$70:$G$70,E10) -> 0.035755033 | F75: =INDEX($C$70:$G$70,F10) -> 0.035755033 | G75: =INDEX($C$70:$G$70,G10) -> 0.035755033 | H75: =INDEX($C$70:$G$70,H10) -> 0.035755033 | I75: =INDEX($C$70:$G$70,I10) -> 0.035755033 | K75: 顯示用：D75:I75（校準點逐步重現）
A76: 每層延遲（該世代） | B76: µs | C76: =INDEX($C$71:$G$71,C10) -> 161.18534 | D76: =INDEX($C$71:$G$71,D10) -> 161.18534 | E76: =INDEX($C$71:$G$71,E10) -> 161.18534 | F76: =INDEX($C$71:$G$71,F10) -> 161.18534 | G76: =INDEX($C$71:$G$71,G10) -> 161.18534 | H76: =INDEX($C$71:$G$71,H10) -> 161.18534 | I76: =INDEX($C$71:$G$71,I10) -> 161.18534 | K76: 顯示用：D76:I76（校準點逐步重現）
A77: η_p（該世代） | B77: % | C77: =INDEX($C$72:$G$72,C10) -> 0.3 | D77: =INDEX($C$72:$G$72,D10) -> 0.3 | E77: =INDEX($C$72:$G$72,E10) -> 0.3 | F77: =INDEX($C$72:$G$72,F10) -> 0.3 | G77: =INDEX($C$72:$G$72,G10) -> 0.3 | H77: =INDEX($C$72:$G$72,H10) -> 0.3 | I77: =INDEX($C$72:$G$72,I10) -> 0.3 | K77: 顯示用：D77:I77（校準點逐步重現）
A78: prefill tok/s/GPU | B78: tok/s | C78: =C77*C23*1000000000000000/(C47*1000000000) -> 34214.061 | D78: =D77*D23*1000000000000000/(D47*1000000000) -> 34214.061 | E78: =E77*E23*1000000000000000/(E47*1000000000) -> 34214.061 | F78: =F77*F23*1000000000000000/(F47*1000000000) -> 34214.061 | G78: =G77*G23*1000000000000000/(G47*1000000000) -> 22809.374 | H78: =H77*H23*1000000000000000/(H47*1000000000) -> 22809.374 | I78: =I77*I23*1000000000000000/(I47*1000000000) -> 34214.061 | K78: 顯示用：D78:I78（校準點逐步重現）
A79: 每步固定延遲 | B79: ms | C79: =C51/C25+(C31+C52)*C76/1000 -> 16.321653 | D79: =D51/D25+(D31+D52)*D76/1000 -> 16.321653 | E79: =E51/E25+(E31+E52)*E76/1000 -> 16.321653 | F79: =F51/F25+(F31+F52)*F76/1000 -> 15.838097 | G79: =G51/G25+(G31+G52)*G76/1000 -> 15.838097 | H79: =H51/H25+(H31+H52)*H76/1000 -> 16.321653 | I79: =I51/I25+(I31+I52)*I76/1000 -> 16.321653 | K79: 顯示用：D79:I79（校準點逐步重現）
A80: 每序列每步時間 | B80: ms | C80: =MAX(C55/C75,C36*C42/(C25*Serving!$C$13)/1000000000,(C52+1)*C31*C33*C32*Serving!$C$12*(C50-1)/C50/(C26*Serving!$C$14)/1000000000) -> 0.99062487 | D80: =MAX(D55/D75,D36*D42/(D25*Serving!$C$13)/1000000000,(D52+1)*D31*D33*D32*Serving!$C$12*(D50-1)/D50/(D26*Serving!$C$14)/1000000000) -> 0.99062487 | E80: =MAX(E55/E75,E36*E42/(E25*Serving!$C$13)/1000000000,(E52+1)*E31*E33*E32*Serving!$C$12*(E50-1)/E50/(E26*Serving!$C$14)/1000000000) -> 0.99062487 | F80: =MAX(F55/F75,F36*F42/(F25*Serving!$C$13)/1000000000,(F52+1)*F31*F33*F32*Serving!$C$12*(F50-1)/F50/(F26*Serving!$C$14)/1000000000) -> 0.24765622 | G80: =MAX(G55/G75,G36*G42/(G25*Serving!$C$13)/1000000000,(G52+1)*G31*G33*G32*Serving!$C$12*(G50-1)/G50/(G26*Serving!$C$14)/1000000000) -> 0.37148433 | H80: =MAX(H55/H75,H36*H42/(H25*Serving!$C$13)/1000000000,(H52+1)*H31*H33*H32*Serving!$C$12*(H50-1)/H50/(H26*Serving!$C$14)/1000000000) -> 1.4859373 | I80: =MAX(I55/I75,I36*I42/(I25*Serving!$C$13)/1000000000,(I52+1)*I31*I33*I32*Serving!$C$12*(I50-1)/I50/(I26*Serving!$C$14)/1000000000) -> 0.99062487 | K80: 顯示用：D80:I80（校準點逐步重現）
A81: SLO 批次上限 | B81: 序列 | C81: =(1000*C53/C14-C79)/C80 -> 19.03738 | D81: =(1000*D53/D14-D79)/D80 -> 3.192896 | E81: =(1000*E53/E14-E79)/E80 -> 34.66332 | F81: =(1000*F53/F14-F79)/F80 -> 85.598254 | G81: =(1000*G53/G14-G79)/G80 -> 57.065503 | H81: =(1000*H53/H14-H79)/H80 -> 4.5127203 | I81: =(1000*I53/I14-I79)/I80 -> 6.7690805 | K81: 顯示用：D81:I81（校準點逐步重現）
A82: 容量批次上限 | B82: 序列 | C82: =(C48-C51)*1000000000/(C36*C42) -> 6118.3815 | D82: =(D48-D51)*1000000000/(D36*D42) -> 6118.3815 | E82: =(E48-E51)*1000000000/(E36*E42) -> 6118.3815 | F82: =(F48-F51)*1000000000/(F36*F42) -> 6118.3815 | G82: =(G48-G51)*1000000000/(G36*G42) -> 3458.3878 | H82: =(H48-H51)*1000000000/(H36*H42) -> 3458.3878 | I82: =(I48-I51)*1000000000/(I36*I42) -> 6118.3815 | K82: 顯示用：D82:I82（校準點逐步重現）
A83: B* | B83: 序列 | C83: =MAX(0,MIN(C81,C82)) -> 19.03738 | D83: =MAX(0,MIN(D81,D82)) -> 3.192896 | E83: =MAX(0,MIN(E81,E82)) -> 34.66332 | F83: =MAX(0,MIN(F81,F82)) -> 85.598254 | G83: =MAX(0,MIN(G81,G82)) -> 57.065503 | H83: =MAX(0,MIN(H81,H82)) -> 4.5127203 | I83: =MAX(0,MIN(I81,I82)) -> 6.7690805 | K83: 顯示用：D83:I83（校準點逐步重現）
A84: decode tok/s/GPU | B84: tok/s | C84: =IF(C83>0,C83*C53/((C79+C83*C80)/1000),0) -> 1370.6914 | D84: =IF(D83>0,D83*D53/((D79+D83*D80)/1000),0) -> 415.07648 | E84: =IF(E83>0,E83*E53/((E79+E83*E80)/1000),0) -> 1733.166 | F84: =IF(F83>0,F83*F53/((F79+F83*F80)/1000),0) -> 2311.1529 | G84: =IF(G83>0,G83*G53/((G79+G83*G80)/1000),0) -> 1540.7686 | H84: =IF(H83>0,H83*H53/((H79+H83*H80)/1000),0) -> 496.39924 | I84: =IF(I83>0,I83*I53/((I79+I83*I80)/1000),0) -> 744.59886 | K84: 顯示用：D84:I84（校準點逐步重現）
A85: 模型 tok/s/GPU（總 token） | B85: tok/s | C85: =IF(C84>0,(C15+C16)/(C15/C78+C16/C84),0) -> 9342.1 | D85: =IF(D84>0,(D15+D16)/(D15/D78+D16/D84),0) -> 3405.2 | E85: =IF(E84>0,(E15+E16)/(E15/E78+E16/E84),0) -> 11100.137 | F85: =IF(F84>0,(F15+F16)/(F15/F78+F16/F84),0) -> 13503.244 | G85: =IF(G84>0,(G15+G16)/(G15/G78+G16/G84),0) -> 9002.163 | H85: =IF(H84>0,(H15+H16)/(H15/H78+H16/H84),0) -> 3805.1099 | I85: =IF(I84>0,(I15+I16)/(I15/I78+I16/I84),0) -> 5707.6648 | K85: 顯示用：D85:I85（校準點逐步重現）
A86: 模型 ÷ 實測 | B86: x | C86: =C85/C17 -> 1 | D86: =D85/D17 -> 1 | E86: =E85/E17 -> 0.9910837 | F86: =F85/F17 -> 2.1842841 | G86: =G85/G17 -> 4.1124545 | H86: =H85/H17 -> 1.0025319 | I86: =I85/I17 -> 0.87508659 | K86: 顯示用：D86:I86（校準點逐步重現）
A87: 判讀 | C87: 擬合點：應為 1.00 | D87: 擬合點：應為 1.00 | E87: 同世代、不同日期與引擎：檢驗前緣形狀 | F87: 舊軟體：模型應高於實測（軟體差距） | G87: 舊軟體＋GB200 記憶體限制配方（S20 說明） | H87: 工作負載標示不明（頁面預設為 agentic） | I87: 同上
A89: G. η_p 敏感度：擬合結果隨 η_p 的變化（η_p 僅影響 prefill／decode GPU 分攤）
A90: η_p | C90: 0.15 | D90: 0.3 | E90: 0.45
A91: 擬合點 1 prefill tok/s | C91: =C90*$C$23*1000000000000000/($C$47*1000000000) -> 17107.031 | D91: =D90*$C$23*1000000000000000/($C$47*1000000000) -> 34214.061 | E91: =E90*$C$23*1000000000000000/($C$47*1000000000) -> 51321.092 | K91: 顯示用：C91:E91（校準擬合步驟）
A92: 擬合點 2 prefill tok/s | C92: =C90*$D$23*1000000000000000/($D$47*1000000000) -> 17107.031 | D92: =D90*$D$23*1000000000000000/($D$47*1000000000) -> 34214.061 | E92: =E90*$D$23*1000000000000000/($D$47*1000000000) -> 51321.092 | K92: 顯示用：C92:E92（校準擬合步驟）
A93: 擬合點 1 反推批次 | C93: =$C$16/(($C$15+$C$16)/$C$17-$C$15/C91)/$C$14 -> 28.016657 | D93: =$C$16/(($C$15+$C$16)/$C$17-$C$15/D91)/$C$14 -> 19.03738 | E93: =$C$16/(($C$15+$C$16)/$C$17-$C$15/E91)/$C$14 -> 17.199873 | K93: 顯示用：C93:E93（校準擬合步驟）
A94: 擬合點 2 反推批次 | C94: =$D$16/(($D$15+$D$16)/$D$17-$D$15/C92)/$D$14 -> 3.5360875 | D94: =$D$16/(($D$15+$D$16)/$D$17-$D$15/D92)/$D$14 -> 3.192896 | E94: =$D$16/(($D$15+$D$16)/$D$17-$D$15/E92)/$D$14 -> 3.0928385 | K94: 顯示用：C94:E94（校準擬合步驟）
A95: η_d | C95: =(C93-C94)*$C$55/(1000*($C$53/$C$14-$D$53/$D$14)) -> 0.055243425 | D95: =(D93-D94)*$C$55/(1000*($C$53/$C$14-$D$53/$D$14)) -> 0.035755033 | E95: =(E93-E94)*$C$55/(1000*($C$53/$C$14-$D$53/$D$14)) -> 0.031834264 | K95: 顯示用：C95:E95（校準擬合步驟）
A96: 每層延遲 µs | C96: =((1000*$C$53/$C$14-C93*$C$55/C95)-$C$51/$C$25)*1000/($C$31+$C$52) -> 175.1817 | D96: =((1000*$C$53/$C$14-D93*$C$55/D95)-$C$51/$C$25)*1000/($C$31+$C$52) -> 161.18534 | E96: =((1000*$C$53/$C$14-E93*$C$55/E95)-$C$51/$C$25)*1000/($C$31+$C$52) -> 156.838 | K96: 顯示用：C96:E96（校準擬合步驟）
A98: H. 第二來源驗證：MLPerf Inference DeepSeek-R1（MLCommons 稽核；提交者 NVIDIA 為利害關係方）
A99: R1 架構與工作負載（驗證專用輸入）
A100: 總參數 | B100: B | C100: =SRC_MOD_020 -> 671 | J100: Verified：DeepSeek-V3/R1 模型卡；ISL／OSL 800／3,880（MLCommons 2025-09，S33）
A101: 啟用參數 | B101: B | C101: =SRC_MOD_021 -> 37
A102: 層數 | C102: =SRC_MOD_022 -> 61
A103: d_model | C103: =SRC_MOD_023 -> 7168
A104: routed experts | C104: =SRC_MOD_024 -> 256
A105: 啟用 experts | C105: =SRC_MOD_025 -> 8
A106: shared experts | C106: =SRC_MOD_026 -> 1
...

Sheet Tech_Registry
A1: Tech_Registry — 新技術登錄與掛鉤（每列＝技術 × 作用物理量；基準值只在『已在基準＝否』且開關＝1 時套用）
A2: 有效倍數＝1＋開關 × 採用比例 ×（所選倍數−1）；已在基準者恆為 1，避免重複計算。主流判定（J14）：至少兩家實驗室公開採用；L 欄可由 Andy 覆寫
U3: 用途
A4: ID | B4: 技術 | C4: 掛鉤代碼 | D4: 作用物理量 | E4: 倍數 低 | F4: 倍數 基準 | G4: 倍數 高 | H4: 情境（1／2／3） | I4: 狀態 | J4: 公開採用實驗室數 | K4: 主流判定（J14） | L4: Andy 覆寫 | M4: 已在基準 | N4: 採用比例 | O4: 開關（0／1） | P4: 有效倍數 | Q4: 證據標記 | R4: 來源／說明 | S4: 下次檢查觸發 | T4: 一致性檢查
A5: T01 | B5: MTP 推測解碼 | C5: — | D5: Serving!C6:C8（N、α） | E5: 1 | F5: 1 | G5: 1 | H5: 2 | I5: 主流 | J5: 3 | K5: =IF(J5>=CST_MainMin,"主流","非主流") -> 主流 | M5: 是 | N5: 1 | O5: 1 | P5: =IF(M5="是",1,1+O5*N5*(CHOOSE(H5,E5,F5,G5)-1)) -> 1 | Q5: Verified | R5: DeepSeek V3／V4、GLM-4.5、MiMo 公開採用；已在 Serving 基準 | S5: — | T5: =IF(AND(IF(L5="",K5,L5)="主流",M5="否"),"主流但未入基準：須 Andy 判定",IF(AND(IF(L5="",K5,L5)="非主流",M5="是",I5<>"早期採用"),"非主流卻在基準","一致")) -> 一致
A6: T02 | B6: 壓縮／稀疏注意力（CSA/HCA 類） | C6: — | D6: Arch 列 16–19 | E6: 1 | F6: 1 | G6: 1 | H6: 2 | I6: 主流 | J6: 3 | K6: =IF(J6>=CST_MainMin,"主流","非主流") -> 主流 | M6: 是 | N6: 1 | O6: 1 | P6: =IF(M6="是",1,1+O6*N6*(CHOOSE(H6,E6,F6,G6)-1)) -> 1 | Q6: Verified | R6: DeepSeek V4 CSA/HCA、DeepSeek／GLM 稀疏注意力、Qwen3-Next 混合注意力；Luna／Sol 基準已含（S27、S35） | S6: — | T6: =IF(AND(IF(L6="",K6,L6)="主流",M6="否"),"主流但未入基準：須 Andy 判定",IF(AND(IF(L6="",K6,L6)="非主流",M6="是",I6<>"早期採用"),"非主流卻在基準","一致")) -> 一致
A7: T03 | B7: FP4 權重推論（NVFP4／MXFP4） | C7: — | D7: Spec_Rack 專家 bytes/param | E7: 1 | F7: 1 | G7: 1 | H7: 2 | I7: 主流 | J7: 2 | K7: =IF(J7>=CST_MainMin,"主流","非主流") -> 主流 | M7: 是 | N7: 1 | O7: 1 | P7: =IF(M7="是",1,1+O7*N7*(CHOOSE(H7,E7,F7,G7)-1)) -> 1 | Q7: Verified | R7: DeepSeek V4 原生 FP4 專家權重、OpenAI gpt-oss MXFP4；已在基準 | S7: — | T7: =IF(AND(IF(L7="",K7,L7)="主流",M7="否"),"主流但未入基準：須 Andy 判定",IF(AND(IF(L7="",K7,L7)="非主流",M7="是",I7<>"早期採用"),"非主流卻在基準","一致")) -> 一致
A8: T04 | B8: FP4 量化感知訓練（後訓練） | C8: — | D8: Spec_Rack 專家 bytes/param | E8: 1 | F8: 1 | G8: 1 | H8: 2 | I8: 主流 | J8: 2 | K8: =IF(J8>=CST_MainMin,"主流","非主流") -> 主流 | M8: 是 | N8: 1 | O8: 1 | P8: =IF(M8="是",1,1+O8*N8*(CHOOSE(H8,E8,F8,G8)-1)) -> 1 | Q8: Interested-party | R8: DeepSeek V4：主權重量化到 FP4 再反量化到 FP8 計算，沿用 FP8 訓練框架（S35） | S8: — | T8: =IF(AND(IF(L8="",K8,L8)="主流",M8="否"),"主流但未入基準：須 Andy 判定",IF(AND(IF(L8="",K8,L8)="非主流",M8="是",I8<>"早期採用"),"非主流卻在基準","一致")) -> 一致
A9: T05 | B9: On-policy 蒸餾（多專家整合） | C9: — | D9: Training G 節 | E9: 1 | F9: 1 | G9: 1 | H9: 2 | I9: 主流 | J9: 2 | K9: =IF(J9>=CST_MainMin,"主流","非主流") -> 主流 | M9: 是 | N9: 1 | O9: 1 | P9: =IF(M9="是",1,1+O9*N9*(CHOOSE(H9,E9,F9,G9)-1)) -> 1 | Q9: Interested-party | R9: DeepSeek V4（專家 SFT＋GRPO 後以 on-policy 蒸餾整合，S35）、Qwen3；已在 Training 基準 | S9: — | T9: =IF(AND(IF(L9="",K9,L9)="主流",M9="否"),"主流但未入基準：須 Andy 判定",IF(AND(IF(L9="",K9,L9)="非主流",M9="是",I9<>"早期採用"),"非主流卻在基準","一致")) -> 一致
A10: T06 | B10: Muon 優化器 | C10: H_TOK | D10: 預訓練所需 token | E10: 0.7 | F10: 0.85 | G10: 1 | H10: 2 | I10: 早期採用 | J10: 2 | K10: =IF(J10>=CST_MainMin,"主流","非主流") -> 主流 | M10: 是 | N10: 1 | O10: 0 | P10: =IF(M10="是",1,1+O10*N10*(CHOOSE(H10,E10,F10,G10)-1)) -> 1 | Q10: Interested-party | R10: Moonshot Kimi K2、DeepSeek V4 採用；Luna／Sol 的 token 數為實際值，已隱含其效果，故不套倍數 | S10: 第三家前沿實驗室採用，或公開同品質 token 節省的對照實驗 | T10: =IF(AND(IF(L10="",K10,L10)="主流",M10="否"),"主流但未入基準：須 Andy 判定",IF(AND(IF(L10="",K10,L10)="非主流",M10="是",I10<>"早期採用"),"非主流卻在基準","一致")) -> 一致
A11: T07 | B11: NVFP4 預訓練 | C11: H_TPK | D11: 訓練峰值 | E11: 1.5 | F11: 2 | G11: 3 | H11: 2 | I11: 早期採用 | J11: 1 | K11: =IF(J11>=CST_MainMin,"主流","非主流") -> 非主流 | M11: 否 | N11: 1 | O11: 0 | P11: =IF(M11="是",1,1+O11*N11*(CHOOSE(H11,E11,F11,G11)-1)) -> 1 | Q11: Interested-party | R11: 倍數＝NVFP4 訓練峰值 ÷ FP8（VR 35/17.5＝2；GB300 15/5＝3 [Assumed]）。NVIDIA 公開 12B 模型 10T token NVFP4 預訓練；前沿實驗室未見公開採用。MFU 可能同步下降，未計 | S11: 任一前沿實驗室公開以 FP4 完成主預訓練 | T11: =IF(AND(IF(L11="",K11,L11)="主流",M11="否"),"主流但未入基準：須 Andy 判定",IF(AND(IF(L11="",K11,L11)="非主流",M11="是",I11<>"早期採用"),"非主流卻在基準","一致")) -> 一致
A12: T08 | B12: Looped transformer（權重共享迴圈）— 計算量 | C12: H_FLOP | D12: 每 token FLOPs | E12: 1.5 | F12: 2 | G12: 4 | H12: 2 | I12: 研究 | J12: 0 | K12: =IF(J12>=CST_MainMin,"主流","非主流") -> 非主流 | M12: 否 | N12: 1 | O12: 0 | P12: =IF(M12="是",1,1+O12*N12*(CHOOSE(H12,E12,F12,G12)-1)) -> 1 | Q12: Assumed | R12: 同一組權重迴圈 k 次：FLOPs × k、權重 bytes × 1；能力增量於 Block 4（H_CAP）處理 | S12: 前沿模型卡或技術報告揭露迴圈深度 | T12: =IF(AND(IF(L12="",K12,L12)="主流",M12="否"),"主流但未入基準：須 Andy 判定",IF(AND(IF(L12="",K12,L12)="非主流",M12="是",I12<>"早期採用"),"非主流卻在基準","一致")) -> 一致
A13: T09 | B13: Looped transformer — 每層延遲 | C13: H_TL | D13: 每步逐層延遲 | E13: 1.5 | F13: 2 | G13: 4 | H13: 2 | I13: 研究 | J13: 0 | K13: =IF(J13>=CST_MainMin,"主流","非主流") -> 非主流 | M13: 否 | N13: 1 | O13: 0 | P13: =IF(M13="是",1,1+O13*N13*(CHOOSE(H13,E13,F13,G13)-1)) -> 1 | Q13: Assumed | R13: 迴圈使有效層數 × k，逐層延遲同比增加；與 T08 同時開關 | S13: 同 T08 | T13: =IF(AND(IF(L13="",K13,L13)="主流",M13="否"),"主流但未入基準：須 Andy 判定",IF(AND(IF(L13="",K13,L13)="非主流",M13="是",I13<>"早期採用"),"非主流卻在基準","一致")) -> 一致
A14: T10 | B14: 非同步 RL（rollout 與訓練解耦、部分 rollout） | C14: H_ROLL | D14: rollout 效率 | E14: 1.2 | F14: 1.4 | G14: 1.6 | H14: 2 | I14: 主流 | J14: =SRC_MOD_043+SRC_MOD_044+SRC_MOD_045+SRC_MOD_047 -> 4 | K14: =IF(J14>=CST_MainMin,"主流","非主流") -> 主流 | M14: 是 | N14: 1 | O14: 0 | P14: =IF(M14="是",1,1+O14*N14*(CHOOSE(H14,E14,F14,G14)-1)) -> 1 | Q14: Interested-party | R14: 旗艦模型公開採用：DeepSeek V4.1（幾乎全部 RL 與 OPD，S45）、Zhipu GLM-5（slime，S46）、Moonshot Kimi-Researcher（完全非同步 rollout，S47）、Meta Llama 3（LlamaRL，S48）。閉源四家未找到披露。v5.6 起併入基準：Train_In rollout 效率 0.85（Andy 2026-10-01 決定 (a)） | S14: 閉源實驗室披露同步做法，或前沿規模對照實驗顯示 off-policy 偏差抵銷吞吐增益 | T14: =IF(AND(IF(L14="",K14,L14)="主流",M14="否"),"主流但未入基準：須 Andy 判定",IF(AND(IF(L14="",K14,L14)="非主流",M14="是",I14<>"早期採用"),"非主流卻在基準","一致")) -> 一致
A15: T11 | B15: KV 快取壓縮（FP4 KV 等） | C15: H_KV | D15: KV bytes/token | E15: 0.5 | F15: 0.5 | G15: 0.75 | H15: 2 | I15: 早期採用 | J15: 1 | K15: =IF(J15>=CST_MainMin,"主流","非主流") -> 非主流 | M15: 否 | N15: 1 | O15: 0 | P15: =IF(M15="是",1,1+O15*N15*(CHOOSE(H15,E15,F15,G15)-1)) -> 1 | Q15: Assumed | R15: FP8 → FP4 KV：bytes × 0.5；準確率損失待查 | S15: 第二家實驗室在生產服務公開採用 | T15: =IF(AND(IF(L15="",K15,L15)="主流",M15="否"),"主流但未入基準：須 Andy 判定",IF(AND(IF(L15="",K15,L15)="非主流",M15="是",I15<>"早期採用"),"非主流卻在基準","一致")) -> 一致
A16: T12 | B16: Harness（代理框架） | C16: H_HAR | D16: Har_In 選定檔案（混合權重 w＝開關 × 採用比例） | E16: 1 | F16: 1 | G16: 1 | H16: 2 | I16: 追蹤中 | J16: 0 | K16: =IF(J16>=CST_MainMin,"主流","非主流") -> 非主流 | M16: 否 | N16: 1 | O16: 0 | P16: =IF(M16="是",1,1+O16*N16*(CHOOSE(H16,E16,F16,G16)-1)) -> 1 | Q16: Assumed | R16: v5.9：harness 以參數組表達（輪數、思考保留、思考量、歷史壓縮、快取命中、子代理、狀態保留）加成功率（L1、L2）；倍數欄不使用。基準不開（L3）。ARC-AGI-3（ARC Prize 自測）：GPT-6 Astra 標準 harness 最高推理 62.7%、$26,098 → OpenAI Provider Adapter 同檔 98.6%、$17,332（S58）。主流判定（J14）尚未評估 | S16: 中立方（ARC Prize、METR、Artificial Analysis）在同條件下測得第二個 harness 對照 | T16: =IF(AND(IF(L16="",K16,L16)="主流",M16="否"),"主流但未入基準：須 Andy 判定",IF(AND(IF(L16="",K16,L16)="非主流",M16="是",I16<>"早期採用"),"非主流卻在基準","一致")) -> 一致
A17: 門檻 | B17: 主流判定門檻：公開採用實驗室數 ≥ 本格（J14；K 欄共用） | J17: 2 | Q17: Decision | R17: J14：至少兩家實驗室公開採用即為主流（CST_MainMin）
A18: 掛鉤彙總（同一掛鉤多條目時取乘積；Perf、Perf_Batch、Training 連結本表 E 欄）
A19: 代碼 | B19: 意義 | D19: 作用位置 | E19: 倍數
A20: H_ETAD | B20: decode η_d 倍數 | D20: Perf／Perf_Batch：etadm 列 | E20: =EXP(SUMPRODUCT(($C$5:$C$16="H_ETAD")*LN($P$5:$P$16))) -> 1
A21: H_TL | B21: 每層延遲倍數 | D21: Perf／Perf_Batch：tlm 列 | E21: =EXP(SUMPRODUCT(($C$5:$C$16="H_TL")*LN($P$5:$P$16))) -> 1
A22: H_FLOP | B22: 每 token FLOPs 倍數（推論與訓練） | D22: Perf／Perf_Batch：hflop 列；Training：hflop 列 | E22: =EXP(SUMPRODUCT(($C$5:$C$16="H_FLOP")*LN($P$5:$P$16))) -> 1
A23: H_KV | B23: KV bytes/token 倍數 | D23: Perf／Perf_Batch：hkv 列 | E23: =EXP(SUMPRODUCT(($C$5:$C$16="H_KV")*LN($P$5:$P$16))) -> 1
A24: H_WB | B24: 權重 bytes/param 倍數 | D24: Perf／Perf_Batch：hwb 列 | E24: =EXP(SUMPRODUCT(($C$5:$C$16="H_WB")*LN($P$5:$P$16))) -> 1
A25: H_TPK | B25: 訓練峰值倍數 | D25: Training：htpk 列 | E25: =EXP(SUMPRODUCT(($C$5:$C$16="H_TPK")*LN($P$5:$P$16))) -> 1
A26: H_MFU | B26: 訓練 MFU 倍數 | D26: Training：hmfu 列 | E26: =EXP(SUMPRODUCT(($C$5:$C$16="H_MFU")*LN($P$5:$P$16))) -> 1
A27: H_TOK | B27: 達同等預訓練品質所需 token 倍數 | D27: Training：htok 列 | E27: =EXP(SUMPRODUCT(($C$5:$C$16="H_TOK")*LN($P$5:$P$16))) -> 1
A28: H_ROLL | B28: rollout 效率倍數 | D28: Training：hroll 列 | E28: =EXP(SUMPRODUCT(($C$5:$C$16="H_ROLL")*LN($P$5:$P$16))) -> 1
A29: H_CAP | B29: 能力增量（Block 4 占位，尚無作用） | D29: Block 4 | E29: =EXP(SUMPRODUCT(($C$5:$C$16="H_CAP")*LN($P$5:$P$16))) -> 1
A30: H_HAR | B30: harness（v5.9 起不作倍數；T12 的開關 × 採用比例＝Har_In 混合權重 w） | D30: Har_In → Workload B 節、Harness | E30: =EXP(SUMPRODUCT(($C$5:$C$16="H_HAR")*LN($P$5:$P$16))) -> 1 | U30: 顯示用：E30（掛鉤彙總表的一致讀數（H_HAR 的實際作用在 Workload 的 B5_W））
A32: 注意 | B32: 掛鉤作用於全部世代與層級。新條目：在表中插入一列（範圍內），填倍數、狀態與證據；開關預設 0。Sens_Perf 的 η_d 與每層延遲情境為覆寫值，不受 Registry 影響。

Sheet Perf
A1: Perf — 每架產出引擎（世代 × 層級；各層級 SLO 與參考任務；100% 利用率）
A2: decode：每步時間＝固定延遲＋B × 每序列時間；在 SLO 下解出批次 B*，再受 HBM 容量限制。prefill 為算力受限。黃底為關鍵輸出
R3: 用途
A4: 世代 | C4: =INDEX(Spec_Rack!$C$4:$G$4,C6) -> Hopper H100 | D4: =INDEX(Spec_Rack!$C$4:$G$4,D6) -> Hopper H100 | E4: =INDEX(Spec_Rack!$C$4:$G$4,E6) -> Hopper H100 | F4: =INDEX(Spec_Rack!$C$4:$G$4,F6) -> GB200 NVL72 | G4: =INDEX(Spec_Rack!$C$4:$G$4,G6) -> GB200 NVL72 | H4: =INDEX(Spec_Rack!$C$4:$G$4,H6) -> GB200 NVL72 | I4: =INDEX(Spec_Rack!$C$4:$G$4,I6) -> GB300 NVL72 | J4: =INDEX(Spec_Rack!$C$4:$G$4,J6) -> GB300 NVL72 | ... Q4: =INDEX(Spec_Rack!$C$4:$G$4,Q6) -> Rubin Ultra（MGX NVL 單架，72 GPU） | R4: 複本讀取：C4:Q4（被 Sens_／_Prod 複本頁讀取，不是死格）
A5: 層級 | C5: =INDEX(Arch!$C$4:$E$4,C7) -> Luna（低層） | D5: =INDEX(Arch!$C$4:$E$4,D7) -> Sol（中層） | E5: =INDEX(Arch!$C$4:$E$4,E7) -> Astra（頂層） | F5: =INDEX(Arch!$C$4:$E$4,F7) -> Luna（低層） | G5: =INDEX(Arch!$C$4:$E$4,G7) -> Sol（中層） | H5: =INDEX(Arch!$C$4:$E$4,H7) -> Astra（頂層） | I5: =INDEX(Arch!$C$4:$E$4,I7) -> Luna（低層） | J5: =INDEX(Arch!$C$4:$E$4,J7) -> Sol（中層） | ... Q5: =INDEX(Arch!$C$4:$E$4,Q7) -> Astra（頂層） | R5: 複本讀取：C5:Q5（被 Sens_／_Prod 複本頁讀取，不是死格）
A6: 世代索引 | C6: 1 | D6: 1 | E6: 1 | F6: 2 | G6: 2 | H6: 2 | I6: 3 | J6: 3 | K6: 3 | L6: 4 | M6: 4 | N6: 4 | O6: 5 | P6: 5 | Q6: 5
A7: 層級索引 | C7: 1 | D7: 2 | E7: 3 | F7: 1 | G7: 2 | H7: 3 | I7: 1 | J7: 2 | K7: 3 | L7: 1 | M7: 2 | N7: 3 | O7: 1 | P7: 2 | Q7: 3
A9: 0. Tech_Registry 掛鉤（基準＝1；Registry 未啟用任何條目時與 v5.4 相同）
A10: FLOPs/token 倍數（H_FLOP） | B10: x | C10: =Tech_Registry!$E$22 -> 1 | D10: =Tech_Registry!$E$22 -> 1 | E10: =Tech_Registry!$E$22 -> 1 | F10: =Tech_Registry!$E$22 -> 1 | G10: =Tech_Registry!$E$22 -> 1 | H10: =Tech_Registry!$E$22 -> 1 | I10: =Tech_Registry!$E$22 -> 1 | J10: =Tech_Registry!$E$22 -> 1 | ... Q10: =Tech_Registry!$E$22 -> 1
A11: KV bytes/token 倍數（H_KV） | B11: x | C11: =Tech_Registry!$E$23 -> 1 | D11: =Tech_Registry!$E$23 -> 1 | E11: =Tech_Registry!$E$23 -> 1 | F11: =Tech_Registry!$E$23 -> 1 | G11: =Tech_Registry!$E$23 -> 1 | H11: =Tech_Registry!$E$23 -> 1 | I11: =Tech_Registry!$E$23 -> 1 | J11: =Tech_Registry!$E$23 -> 1 | ... Q11: =Tech_Registry!$E$23 -> 1
A12: 權重 bytes/param 倍數（H_WB） | B12: x | C12: =Tech_Registry!$E$24 -> 1 | D12: =Tech_Registry!$E$24 -> 1 | E12: =Tech_Registry!$E$24 -> 1 | F12: =Tech_Registry!$E$24 -> 1 | G12: =Tech_Registry!$E$24 -> 1 | H12: =Tech_Registry!$E$24 -> 1 | I12: =Tech_Registry!$E$24 -> 1 | J12: =Tech_Registry!$E$24 -> 1 | ... Q12: =Tech_Registry!$E$24 -> 1
A13: A. 規格（連結 Spec_Rack、DC_Cost）
A14: 計算用峰值 | B14: PF/GPU | C14: =INDEX(Spec_Rack!$C$35:$G$35,C$6) -> 1.979 | D14: =INDEX(Spec_Rack!$C$35:$G$35,D$6) -> 1.979 | E14: =INDEX(Spec_Rack!$C$35:$G$35,E$6) -> 1.979 | F14: =INDEX(Spec_Rack!$C$35:$G$35,F$6) -> 10 | G14: =INDEX(Spec_Rack!$C$35:$G$35,G$6) -> 10 | H14: =INDEX(Spec_Rack!$C$35:$G$35,H$6) -> 10 | I14: =INDEX(Spec_Rack!$C$35:$G$35,I$6) -> 15 | J14: =INDEX(Spec_Rack!$C$35:$G$35,J$6) -> 15 | ... Q14: =INDEX(Spec_Rack!$C$35:$G$35,Q$6) -> 70
A15: HBM 容量 | B15: GB/GPU | C15: =INDEX(Spec_Rack!$C$25:$G$25,C$6) -> 80 | D15: =INDEX(Spec_Rack!$C$25:$G$25,D$6) -> 80 | E15: =INDEX(Spec_Rack!$C$25:$G$25,E$6) -> 80 | F15: =INDEX(Spec_Rack!$C$25:$G$25,F$6) -> 186 | G15: =INDEX(Spec_Rack!$C$25:$G$25,G$6) -> 186 | H15: =INDEX(Spec_Rack!$C$25:$G$25,H$6) -> 186 | I15: =INDEX(Spec_Rack!$C$25:$G$25,I$6) -> 288 | J15: =INDEX(Spec_Rack!$C$25:$G$25,J$6) -> 288 | ... Q15: =INDEX(Spec_Rack!$C$25:$G$25,Q$6) -> 1024
A16: HBM 頻寬 | B16: TB/s/GPU | C16: =INDEX(Spec_Rack!$C$26:$G$26,C$6) -> 3.35 | D16: =INDEX(Spec_Rack!$C$26:$G$26,D$6) -> 3.35 | E16: =INDEX(Spec_Rack!$C$26:$G$26,E$6) -> 3.35 | F16: =INDEX(Spec_Rack!$C$26:$G$26,F$6) -> 8 | G16: =INDEX(Spec_Rack!$C$26:$G$26,G$6) -> 8 | H16: =INDEX(Spec_Rack!$C$26:$G$26,H$6) -> 8 | I16: =INDEX(Spec_Rack!$C$26:$G$26,I$6) -> 8 | J16: =INDEX(Spec_Rack!$C$26:$G$26,J$6) -> 8 | ... Q16: =INDEX(Spec_Rack!$C$26:$G$26,Q$6) -> 32
A17: EP 通訊頻寬（單向） | B17: TB/s/GPU | C17: =INDEX(Spec_Rack!$C$27:$G$27,C$6) -> 0.05 | D17: =INDEX(Spec_Rack!$C$27:$G$27,D$6) -> 0.05 | E17: =INDEX(Spec_Rack!$C$27:$G$27,E$6) -> 0.05 | F17: =INDEX(Spec_Rack!$C$27:$G$27,F$6) -> 0.9 | G17: =INDEX(Spec_Rack!$C$27:$G$27,G$6) -> 0.9 | H17: =INDEX(Spec_Rack!$C$27:$G$27,H$6) -> 0.9 | I17: =INDEX(Spec_Rack!$C$27:$G$27,I$6) -> 0.9 | J17: =INDEX(Spec_Rack!$C$27:$G$27,J$6) -> 0.9 | ... Q17: =INDEX(Spec_Rack!$C$27:$G$27,Q$6) -> 1.8
A18: decode EP 基準寬度 | B18: GPU | C18: =INDEX(Spec_Rack!$C$29:$G$29,C$6) -> 64 | D18: =INDEX(Spec_Rack!$C$29:$G$29,D$6) -> 64 | E18: =INDEX(Spec_Rack!$C$29:$G$29,E$6) -> 64 | F18: =INDEX(Spec_Rack!$C$29:$G$29,F$6) -> 32 | G18: =INDEX(Spec_Rack!$C$29:$G$29,G$6) -> 32 | H18: =INDEX(Spec_Rack!$C$29:$G$29,H$6) -> 32 | I18: =INDEX(Spec_Rack!$C$29:$G$29,I$6) -> 32 | J18: =INDEX(Spec_Rack!$C$29:$G$29,J$6) -> 32 | ... Q18: =INDEX(Spec_Rack!$C$29:$G$29,Q$6) -> 64
A19: 專家權重 bytes/param（含 H_WB） | B19: B | C19: =INDEX(Spec_Rack!$C$30:$G$30,C$6)*C12 -> 1 | D19: =INDEX(Spec_Rack!$C$30:$G$30,D$6)*D12 -> 1 | E19: =INDEX(Spec_Rack!$C$30:$G$30,E$6)*E12 -> 1 | F19: =INDEX(Spec_Rack!$C$30:$G$30,F$6)*F12 -> 0.5625 | G19: =INDEX(Spec_Rack!$C$30:$G$30,G$6)*G12 -> 0.5625 | H19: =INDEX(Spec_Rack!$C$30:$G$30,H$6)*H12 -> 0.5625 | I19: =INDEX(Spec_Rack!$C$30:$G$30,I$6)*I12 -> 0.5625 | J19: =INDEX(Spec_Rack!$C$30:$G$30,J$6)*J12 -> 0.5625 | ... Q19: =INDEX(Spec_Rack!$C$30:$G$30,Q$6)*Q12 -> 0.5625
A20: 非專家權重 bytes/param（含 H_WB） | B20: B | C20: =INDEX(Spec_Rack!$C$31:$G$31,C$6)*C12 -> 1 | D20: =INDEX(Spec_Rack!$C$31:$G$31,D$6)*D12 -> 1 | E20: =INDEX(Spec_Rack!$C$31:$G$31,E$6)*E12 -> 1 | F20: =INDEX(Spec_Rack!$C$31:$G$31,F$6)*F12 -> 1 | G20: =INDEX(Spec_Rack!$C$31:$G$31,G$6)*G12 -> 1 | H20: =INDEX(Spec_Rack!$C$31:$G$31,H$6)*H12 -> 1 | I20: =INDEX(Spec_Rack!$C$31:$G$31,I$6)*I12 -> 1 | J20: =INDEX(Spec_Rack!$C$31:$G$31,J$6)*J12 -> 1 | ... Q20: =INDEX(Spec_Rack!$C$31:$G$31,Q$6)*Q12 -> 1
A21: 每 prefill 實例 GPU 數 | B21: GPU | C21: =INDEX(Spec_Rack!$C$32:$G$32,C$6) -> 8 | D21: =INDEX(Spec_Rack!$C$32:$G$32,D$6) -> 8 | E21: =INDEX(Spec_Rack!$C$32:$G$32,E$6) -> 8 | F21: =INDEX(Spec_Rack!$C$32:$G$32,F$6) -> 4 | G21: =INDEX(Spec_Rack!$C$32:$G$32,G$6) -> 4 | H21: =INDEX(Spec_Rack!$C$32:$G$32,H$6) -> 4 | I21: =INDEX(Spec_Rack!$C$32:$G$32,I$6) -> 4 | J21: =INDEX(Spec_Rack!$C$32:$G$32,J$6) -> 4 | ... Q21: =INDEX(Spec_Rack!$C$32:$G$32,Q$6) -> 8
A22: GPU 封裝／架 | B22: 顆 | C22: =INDEX(Spec_Rack!$C$6:$G$6,C$6) -> 32 | D22: =INDEX(Spec_Rack!$C$6:$G$6,D$6) -> 32 | E22: =INDEX(Spec_Rack!$C$6:$G$6,E$6) -> 32 | F22: =INDEX(Spec_Rack!$C$6:$G$6,F$6) -> 72 | G22: =INDEX(Spec_Rack!$C$6:$G$6,G$6) -> 72 | H22: =INDEX(Spec_Rack!$C$6:$G$6,H$6) -> 72 | I22: =INDEX(Spec_Rack!$C$6:$G$6,I$6) -> 72 | J22: =INDEX(Spec_Rack!$C$6:$G$6,J$6) -> 72 | ... Q22: =INDEX(Spec_Rack!$C$6:$G$6,Q$6) -> 72
A23: GPU 功率 | B23: W | C23: =INDEX(Spec_Rack!$C$33:$G$33,C$6) -> 700 | D23: =INDEX(Spec_Rack!$C$33:$G$33,D$6) -> 700 | E23: =INDEX(Spec_Rack!$C$33:$G$33,E$6) -> 700 | F23: =INDEX(Spec_Rack!$C$33:$G$33,F$6) -> 1200 | G23: =INDEX(Spec_Rack!$C$33:$G$33,G$6) -> 1200 | H23: =INDEX(Spec_Rack!$C$33:$G$33,H$6) -> 1200 | I23: =INDEX(Spec_Rack!$C$33:$G$33,I$6) -> 1400 | J23: =INDEX(Spec_Rack!$C$33:$G$33,J$6) -> 1400 | ... Q23: =INDEX(Spec_Rack!$C$33:$G$33,Q$6) -> 3600
A24: HBM 存取能量 | B24: pJ/B | C24: =INDEX(Spec_Rack!$C$34:$G$34,C$6) -> 31 | D24: =INDEX(Spec_Rack!$C$34:$G$34,D$6) -> 31 | E24: =INDEX(Spec_Rack!$C$34:$G$34,E$6) -> 31 | F24: =INDEX(Spec_Rack!$C$34:$G$34,F$6) -> 25 | G24: =INDEX(Spec_Rack!$C$34:$G$34,G$6) -> 25 | H24: =INDEX(Spec_Rack!$C$34:$G$34,H$6) -> 25 | I24: =INDEX(Spec_Rack!$C$34:$G$34,I$6) -> 25 | J24: =INDEX(Spec_Rack!$C$34:$G$34,J$6) -> 25 | ... Q24: =INDEX(Spec_Rack!$C$34:$G$34,Q$6) -> 18
A25: 每 GW 機架數（功率情境） | B25: 架 | C25: =INDEX(DC_Cost!$C$12:$Q$12,3*(C$6-1)+2)/CTL_GW -> 22439 | D25: =INDEX(DC_Cost!$C$12:$Q$12,3*(D$6-1)+2)/CTL_GW -> 22439 | E25: =INDEX(DC_Cost!$C$12:$Q$12,3*(E$6-1)+2)/CTL_GW -> 22439 | F25: =INDEX(DC_Cost!$C$12:$Q$12,3*(F$6-1)+2)/CTL_GW -> 6969 | G25: =INDEX(DC_Cost!$C$12:$Q$12,3*(G$6-1)+2)/CTL_GW -> 6969 | H25: =INDEX(DC_Cost!$C$12:$Q$12,3*(H$6-1)+2)/CTL_GW -> 6969 | I25: =INDEX(DC_Cost!$C$12:$Q$12,3*(I$6-1)+2)/CTL_GW -> 6764 | J25: =INDEX(DC_Cost!$C$12:$Q$12,3*(J$6-1)+2)/CTL_GW -> 6764 | ... Q25: =INDEX(DC_Cost!$C$12:$Q$12,3*(Q$6-1)+2)/CTL_GW -> 2705
A26: 每架配電設計功率 | B26: kW | C26: =INDEX(DC_Cost!$C$11:$Q$11,3*(C$6-1)+2) -> 41 | D26: =INDEX(DC_Cost!$C$11:$Q$11,3*(D$6-1)+2) -> 41 | E26: =INDEX(DC_Cost!$C$11:$Q$11,3*(E$6-1)+2) -> 41 | F26: =INDEX(DC_Cost!$C$11:$Q$11,3*(F$6-1)+2) -> 132 | G26: =INDEX(DC_Cost!$C$11:$Q$11,3*(G$6-1)+2) -> 132 | H26: =INDEX(DC_Cost!$C$11:$Q$11,3*(H$6-1)+2) -> 132 | I26: =INDEX(DC_Cost!$C$11:$Q$11,3*(I$6-1)+2) -> 136 | J26: =INDEX(DC_Cost!$C$11:$Q$11,3*(J$6-1)+2) -> 136 | ... Q26: =INDEX(DC_Cost!$C$11:$Q$11,3*(Q$6-1)+2) -> 340
A27: B. 架構（連結 Arch；啟用參數與非專家／專家參數已乘模型規模倍數 ARCH_ScaleGen，基準＝1；D1(c)，v6.2）
A28: 啟用參數 | B28: B | C28: =INDEX(Arch!$C$7:$E$7,C$7)*INDEX(ARCH_ScaleGen,1,C$6) -> 13 | D28: =INDEX(Arch!$C$7:$E$7,D$7)*INDEX(ARCH_ScaleGen,1,D$6) -> 49 | E28: =INDEX(Arch!$C$7:$E$7,E$7)*INDEX(ARCH_ScaleGen,1,E$6) -> 180 | F28: =INDEX(Arch!$C$7:$E$7,F$7)*INDEX(ARCH_ScaleGen,1,F$6) -> 13 | G28: =INDEX(Arch!$C$7:$E$7,G$7)*INDEX(ARCH_ScaleGen,1,G$6) -> 49 | H28: =INDEX(Arch!$C$7:$E$7,H$7)*INDEX(ARCH_ScaleGen,1,H$6) -> 180 | I28: =INDEX(Arch!$C$7:$E$7,I$7)*INDEX(ARCH_ScaleGen,1,I$6) -> 13 | J28: =INDEX(Arch!$C$7:$E$7,J$7)*INDEX(ARCH_ScaleGen,1,J$6) -> 49 | ... Q28: =INDEX(Arch!$C$7:$E$7,Q$7)*INDEX(ARCH_ScaleGen,1,Q$6) -> 180
A29: 層數 | B29: 層 | C29: =INDEX(Arch!$C$8:$E$8,C$7) -> 43 | D29: =INDEX(Arch!$C$8:$E$8,D$7) -> 61 | E29: =INDEX(Arch!$C$8:$E$8,E$7) -> 100 | F29: =INDEX(Arch!$C$8:$E$8,F$7) -> 43 | G29: =INDEX(Arch!$C$8:$E$8,G$7) -> 61 | H29: =INDEX(Arch!$C$8:$E$8,H$7) -> 100 | I29: =INDEX(Arch!$C$8:$E$8,I$7) -> 43 | J29: =INDEX(Arch!$C$8:$E$8,J$7) -> 61 | ... Q29: =INDEX(Arch!$C$8:$E$8,Q$7) -> 100
A30: d_model | C30: =INDEX(Arch!$C$9:$E$9,C$7) -> 4096 | D30: =INDEX(Arch!$C$9:$E$9,D$7) -> 7168 | E30: =INDEX(Arch!$C$9:$E$9,E$7) -> 12288 | F30: =INDEX(Arch!$C$9:$E$9,F$7) -> 4096 | G30: =INDEX(Arch!$C$9:$E$9,G$7) -> 7168 | H30: =INDEX(Arch!$C$9:$E$9,H$7) -> 12288 | I30: =INDEX(Arch!$C$9:$E$9,I$7) -> 4096 | J30: =INDEX(Arch!$C$9:$E$9,J$7) -> 7168 | ... Q30: =INDEX(Arch!$C$9:$E$9,Q$7) -> 12288
A31: 啟用 routed experts | C31: =INDEX(Arch!$C$13:$E$13,C$7) -> 6 | D31: =INDEX(Arch!$C$13:$E$13,D$7) -> 6 | E31: =INDEX(Arch!$C$13:$E$13,E$7) -> 16 | F31: =INDEX(Arch!$C$13:$E$13,F$7) -> 6 | G31: =INDEX(Arch!$C$13:$E$13,G$7) -> 6 | H31: =INDEX(Arch!$C$13:$E$13,H$7) -> 16 | I31: =INDEX(Arch!$C$13:$E$13,I$7) -> 6 | J31: =INDEX(Arch!$C$13:$E$13,J$7) -> 6 | ... Q31: =INDEX(Arch!$C$13:$E$13,Q$7) -> 16
A32: 非專家參數 | B32: B | C32: =INDEX(Arch!$C$28:$E$28,C$7)*INDEX(ARCH_ScaleGen,1,C$6) -> 5.412 | D32: =INDEX(Arch!$C$28:$E$28,D$7)*INDEX(ARCH_ScaleGen,1,D$6) -> 20.277778 | E32: =INDEX(Arch!$C$28:$E$28,E$7)*INDEX(ARCH_ScaleGen,1,E$6) -> 49.072581 | F32: =INDEX(Arch!$C$28:$E$28,F$7)*INDEX(ARCH_ScaleGen,1,F$6) -> 5.412 | G32: =INDEX(Arch!$C$28:$E$28,G$7)*INDEX(ARCH_ScaleGen,1,G$6) -> 20.277778 | H32: =INDEX(Arch!$C$28:$E$28,H$7)*INDEX(ARCH_ScaleGen,1,H$6) -> 49.072581 | I32: =INDEX(Arch!$C$28:$E$28,I$7)*INDEX(ARCH_ScaleGen,1,I$6) -> 5.412 | J32: =INDEX(Arch!$C$28:$E$28,J$7)*INDEX(ARCH_ScaleGen,1,J$6) -> 20.277778 | ... Q32: =INDEX(Arch!$C$28:$E$28,Q$7)*INDEX(ARCH_ScaleGen,1,Q$6) -> 49.072581
A33: 專家參數 | B33: B | C33: =INDEX(Arch!$C$29:$E$29,C$7)*INDEX(ARCH_ScaleGen,1,C$6) -> 278.588 | D33: =INDEX(Arch!$C$29:$E$29,D$7)*INDEX(ARCH_ScaleGen,1,D$6) -> 1579.7222 | E33: =INDEX(Arch!$C$29:$E$29,E$7)*INDEX(ARCH_ScaleGen,1,E$6) -> 3950.9274 | F33: =INDEX(Arch!$C$29:$E$29,F$7)*INDEX(ARCH_ScaleGen,1,F$6) -> 278.588 | G33: =INDEX(Arch!$C$29:$E$29,G$7)*INDEX(ARCH_ScaleGen,1,G$6) -> 1579.7222 | H33: =INDEX(Arch!$C$29:$E$29,H$7)*INDEX(ARCH_ScaleGen,1,H$6) -> 3950.9274 | I33: =INDEX(Arch!$C$29:$E$29,I$7)*INDEX(ARCH_ScaleGen,1,I$6) -> 278.588 | J33: =INDEX(Arch!$C$29:$E$29,J$7)*INDEX(ARCH_ScaleGen,1,J$6) -> 1579.7222 | ... Q33: =INDEX(Arch!$C$29:$E$29,Q$7)*INDEX(ARCH_ScaleGen,1,Q$6) -> 3950.9274
A34: KV bytes/token（含 H_KV） | B34: B | C34: =INDEX(Arch!$C$25:$E$25,C$7)*C11 -> 2795 | D34: =INDEX(Arch!$C$25:$E$25,D$7)*D11 -> 3965 | E34: =INDEX(Arch!$C$25:$E$25,E$7)*E11 -> 57600 | F34: =INDEX(Arch!$C$25:$E$25,F$7)*F11 -> 2795 | G34: =INDEX(Arch!$C$25:$E$25,G$7)*G11 -> 3965 | H34: =INDEX(Arch!$C$25:$E$25,H$7)*H11 -> 57600 | I34: =INDEX(Arch!$C$25:$E$25,I$7)*I11 -> 2795 | J34: =INDEX(Arch!$C$25:$E$25,J$7)*J11 -> 3965 | ... Q34: =INDEX(Arch!$C$25:$E$25,Q$7)*Q11 -> 57600
A35: 注意力 FLOPs／被注意 token | B35: FLOP | C35: =INDEX(Arch!$C$30:$E$30,C$7) -> 5636096 | D35: =INDEX(Arch!$C$30:$E$30,D$7) -> 15990784 | E35: =INDEX(Arch!$C$30:$E$30,E$7) -> 4915200 | F35: =INDEX(Arch!$C$30:$E$30,F$7) -> 5636096 | G35: =INDEX(Arch!$C$30:$E$30,G$7) -> 15990784 | H35: =INDEX(Arch!$C$30:$E$30,H$7) -> 4915200 | I35: =INDEX(Arch!$C$30:$E$30,I$7) -> 5636096 | J35: =INDEX(Arch!$C$30:$E$30,J$7) -> 15990784 | ... Q35: =INDEX(Arch!$C$30:$E$30,Q$7) -> 4915200
A36: 全注意力層比例 | B36: % | C36: =INDEX(Arch!$C$16:$E$16,C$7) -> 0.512 | D36: =INDEX(Arch!$C$16:$E$16,D$7) -> 0.492 | E36: =INDEX(Arch!$C$16:$E$16,E$7) -> 1 | F36: =INDEX(Arch!$C$16:$E$16,F$7) -> 0.512 | G36: =INDEX(Arch!$C$16:$E$16,G$7) -> 0.492 | H36: =INDEX(Arch!$C$16:$E$16,H$7) -> 1 | I36: =INDEX(Arch!$C$16:$E$16,I$7) -> 0.512 | J36: =INDEX(Arch!$C$16:$E$16,J$7) -> 0.492 | ... Q36: =INDEX(Arch!$C$16:$E$16,Q$7) -> 1
A37: 全注意力跨度上限 | B37: tok | C37: =INDEX(Arch!$C$17:$E$17,C$7) -> 4224 | D37: =INDEX(Arch!$C$17:$E$17,D$7) -> 4224 | E37: =INDEX(Arch!$C$17:$E$17,E$7) -> 0 | F37: =INDEX(Arch!$C$17:$E$17,F$7) -> 4224 | G37: =INDEX(Arch!$C$17:$E$17,G$7) -> 4224 | H37: =INDEX(Arch!$C$17:$E$17,H$7) -> 0 | I37: =INDEX(Arch!$C$17:$E$17,I$7) -> 4224 | J37: =INDEX(Arch!$C$17:$E$17,J$7) -> 4224 | ... Q37: =INDEX(Arch!$C$17:$E$17,Q$7) -> 0
A38: 其他層壓縮比 | B38: x | C38: =INDEX(Arch!$C$18:$E$18,C$7) -> 128 | D38: =INDEX(Arch!$C$18:$E$18,D$7) -> 128 | E38: =INDEX(Arch!$C$18:$E$18,E$7) -> 1 | F38: =INDEX(Arch!$C$18:$E$18,F$7) -> 128 | G38: =INDEX(Arch!$C$18:$E$18,G$7) -> 128 | H38: =INDEX(Arch!$C$18:$E$18,H$7) -> 1 | I38: =INDEX(Arch!$C$18:$E$18,I$7) -> 128 | J38: =INDEX(Arch!$C$18:$E$18,J$7) -> 128 | ... Q38: =INDEX(Arch!$C$18:$E$18,Q$7) -> 1
A39: 其他層滑動窗 | B39: tok | C39: =INDEX(Arch!$C$19:$E$19,C$7) -> 128 | D39: =INDEX(Arch!$C$19:$E$19,D$7) -> 128 | E39: =INDEX(Arch!$C$19:$E$19,E$7) -> 0 | F39: =INDEX(Arch!$C$19:$E$19,F$7) -> 128 | G39: =INDEX(Arch!$C$19:$E$19,G$7) -> 128 | H39: =INDEX(Arch!$C$19:$E$19,H$7) -> 0 | I39: =INDEX(Arch!$C$19:$E$19,I$7) -> 128 | J39: =INDEX(Arch!$C$19:$E$19,J$7) -> 128 | ... Q39: =INDEX(Arch!$C$19:$E$19,Q$7) -> 0
A40: C. 服務、SLO 與校準參數
A41: SLO：每用戶 decode 速度下限 | B41: tok/s | C41: =INDEX(Serving!$C$21:$E$21,C$7) -> 84.300059 | D41: =INDEX(Serving!$C$21:$E$21,D$7) -> 43.311661 | E41: =INDEX(Serving!$C$21:$E$21,E$7) -> 40.83136 | F41: =INDEX(Serving!$C$21:$E$21,F$7) -> 84.300059 | G41: =INDEX(Serving!$C$21:$E$21,G$7) -> 43.311661 | H41: =INDEX(Serving!$C$21:$E$21,H$7) -> 40.83136 | I41: =INDEX(Serving!$C$21:$E$21,I$7) -> 84.300059 | J41: =INDEX(Serving!$C$21:$E$21,J$7) -> 43.311661 | ... Q41: =INDEX(Serving!$C$21:$E$21,Q$7) -> 40.83136
A42: TTFT 上限 | B42: s | C42: =INDEX(Serving!$C$22:$E$22,C$7) -> 2 | D42: =INDEX(Serving!$C$22:$E$22,D$7) -> 3 | E42: =INDEX(Serving!$C$22:$E$22,E$7) -> 5 | F42: =INDEX(Serving!$C$22:$E$22,F$7) -> 2 | G42: =INDEX(Serving!$C$22:$E$22,G$7) -> 3 | H42: =INDEX(Serving!$C$22:$E$22,H$7) -> 5 | I42: =INDEX(Serving!$C$22:$E$22,I$7) -> 2 | J42: =INDEX(Serving!$C$22:$E$22,J$7) -> 3 | ... Q42: =INDEX(Serving!$C$22:$E$22,Q$7) -> 5
A43: 參考 ISL | B43: tok | C43: =INDEX(Serving!$C$23:$E$23,C$7) -> 8192 | D43: =INDEX(Serving!$C$23:$E$23,D$7) -> 16384 | E43: =INDEX(Serving!$C$23:$E$23,E$7) -> 32768 | F43: =INDEX(Serving!$C$23:$E$23,F$7) -> 8192 | G43: =INDEX(Serving!$C$23:$E$23,G$7) -> 16384 | H43: =INDEX(Serving!$C$23:$E$23,H$7) -> 32768 | I43: =INDEX(Serving!$C$23:$E$23,I$7) -> 8192 | J43: =INDEX(Serving!$C$23:$E$23,J$7) -> 16384 | ... Q43: =INDEX(Serving!$C$23:$E$23,Q$7) -> 32768
A44: 參考 OSL（含思考） | B44: tok | C44: =INDEX(Serving!$C$24:$E$24,C$7) -> 1024 | D44: =INDEX(Serving!$C$24:$E$24,D$7) -> 2048 | E44: =INDEX(Serving!$C$24:$E$24,E$7) -> 4096 | F44: =INDEX(Serving!$C$24:$E$24,F$7) -> 1024 | G44: =INDEX(Serving!$C$24:$E$24,G$7) -> 2048 | H44: =INDEX(Serving!$C$24:$E$24,H$7) -> 4096 | I44: =INDEX(Serving!$C$24:$E$24,I$7) -> 1024 | J44: =INDEX(Serving!$C$24:$E$24,J$7) -> 2048 | ... Q44: =INDEX(Serving!$C$24:$E$24,Q$7) -> 4096
A45: decode 平均上下文 | B45: tok | C45: =C43+C44/2 -> 8704 | D45: =D43+D44/2 -> 17408 | E45: =E43+E44/2 -> 34816 | F45: =F43+F44/2 -> 8704 | G45: =G43+G44/2 -> 17408 | H45: =H43+H44/2 -> 34816 | I45: =I43+I44/2 -> 8704 | J45: =J43+J44/2 -> 17408 | ... Q45: =Q43+Q44/2 -> 34816
A46: prefill 平均位置 | B46: tok | C46: =C43/2 -> 4096 | D46: =D43/2 -> 8192 | E46: =E43/2 -> 16384 | F46: =F43/2 -> 4096 | G46: =G43/2 -> 8192 | H46: =H43/2 -> 16384 | I46: =I43/2 -> 4096 | J46: =J43/2 -> 8192 | ... Q46: =Q43/2 -> 16384
A47: MTP 草稿數 | B47: tok | C47: =Serving!$C$6 -> 3 | D47: =Serving!$C$6 -> 3 | E47: =Serving!$C$6 -> 3 | F47: =Serving!$C$6 -> 3 | G47: =Serving!$C$6 -> 3 | H47: =Serving!$C$6 -> 3 | I47: =Serving!$C$6 -> 3 | J47: =Serving!$C$6 -> 3 | ... Q47: =Serving!$C$6 -> 3
A48: 草稿接受率 | B48: % | C48: =Serving!$C$7 -> 0.7 | D48: =Serving!$C$7 -> 0.7 | E48: =Serving!$C$7 -> 0.7 | F48: =Serving!$C$7 -> 0.7 | G48: =Serving!$C$7 -> 0.7 | H48: =Serving!$C$7 -> 0.7 | I48: =Serving!$C$7 -> 0.7 | J48: =Serving!$C$7 -> 0.7 | ... Q48: =Serving!$C$7 -> 0.7
A49: 每步期望接受 token | B49: tok | C49: =(1-C48^(C47+1))/(1-C48) -> 2.533 | D49: =(1-D48^(D47+1))/(1-D48) -> 2.533 | E49: =(1-E48^(E47+1))/(1-E48) -> 2.533 | F49: =(1-F48^(F47+1))/(1-F48) -> 2.533 | G49: =(1-G48^(G47+1))/(1-G48) -> 2.533 | H49: =(1-H48^(H47+1))/(1-H48) -> 2.533 | I49: =(1-I48^(I47+1))/(1-I48) -> 2.533 | J49: =(1-J48^(J47+1))/(1-J48) -> 2.533 | ... Q49: =(1-Q48^(Q47+1))/(1-Q48) -> 2.533
A50: 實測→生產效率折減 | B50: x | C50: =Serving!$C$18 -> 1 | D50: =Serving!$C$18 -> 1 | E50: =Serving!$C$18 -> 1 | F50: =Serving!$C$18 -> 1 | G50: =Serving!$C$18 -> 1 | H50: =Serving!$C$18 -> 1 | I50: =Serving!$C$18 -> 1 | J50: =Serving!$C$18 -> 1 | ... Q50: =Serving!$C$18 -> 1
A51: η_p（prefill 占峰值；含折減） | B51: % | C51: =INDEX(Calib!$C$72:$G$72,C$6)*C50 -> 0.1499242 | D51: =INDEX(Calib!$C$72:$G$72,D$6)*D50 -> 0.1499242 | E51: =INDEX(Calib!$C$72:$G$72,E$6)*E50 -> 0.1499242 | F51: =INDEX(Calib!$C$72:$G$72,F$6)*F50 -> 0.3 | G51: =INDEX(Calib!$C$72:$G$72,G$6)*G50 -> 0.3 | H51: =INDEX(Calib!$C$72:$G$72,H$6)*H50 -> 0.3 | I51: =INDEX(Calib!$C$72:$G$72,I$6)*I50 -> 0.3 | J51: =INDEX(Calib!$C$72:$G$72,J$6)*J50 -> 0.3 | ... Q51: =INDEX(Calib!$C$72:$G$72,Q$6)*Q50 -> 0.3
A52: η_d 倍數（Tech_Registry H_ETAD；Sens_Perf 情境覆寫） | B52: x | C52: =Tech_Registry!$E$20 -> 1 | D52: =Tech_Registry!$E$20 -> 1 | E52: =Tech_Registry!$E$20 -> 1 | F52: =Tech_Registry!$E$20 -> 1 | G52: =Tech_Registry!$E$20 -> 1 | H52: =Tech_Registry!$E$20 -> 1 | I52: =Tech_Registry!$E$20 -> 1 | J52: =Tech_Registry!$E$20 -> 1 | ... Q52: =Tech_Registry!$E$20 -> 1
A53: η_d（decode 每序列算力效率；含折減） | B53: % | C53: =INDEX(Calib!$C$70:$G$70,C$6)*C52*C50 -> 0.04290604 | D53: =INDEX(Calib!$C$70:$G$70,D$6)*D52*D50 -> 0.04290604 | E53: =INDEX(Calib!$C$70:$G$70,E$6)*E52*E50 -> 0.04290604 | F53: =INDEX(Calib!$C$70:$G$70,F$6)*F52*F50 -> 0.035755033 | G53: =INDEX(Calib!$C$70:$G$70,G$6)*G52*G50 -> 0.035755033 | H53: =INDEX(Calib!$C$70:$G$70,H$6)*H52*H50 -> 0.035755033 | I53: =INDEX(Calib!$C$70:$G$70,I$6)*I52*I50 -> 0.035755033 | J53: =INDEX(Calib!$C$70:$G$70,J$6)*J52*J50 -> 0.035755033 | ... Q53: =INDEX(Calib!$C$70:$G$70,Q$6)*Q52*Q50 -> 0.035755033
A54: 每層延遲倍數（Tech_Registry H_TL；Sens_Perf 情境覆寫） | B54: x | C54: =Tech_Registry!$E$21 -> 1 | D54: =Tech_Registry!$E$21 -> 1 | E54: =Tech_Registry!$E$21 -> 1 | F54: =Tech_Registry!$E$21 -> 1 | G54: =Tech_Registry!$E$21 -> 1 | H54: =Tech_Registry!$E$21 -> 1 | I54: =Tech_Registry!$E$21 -> 1 | J54: =Tech_Registry!$E$21 -> 1 | ... Q54: =Tech_Registry!$E$21 -> 1
A55: 每層每次前向固定延遲（含折減） | B55: µs | C55: =INDEX(Calib!$C$71:$G$71,C$6)*C54/C50 -> 241.77801 | D55: =INDEX(Calib!$C$71:$G$71,D$6)*D54/D50 -> 241.77801 | E55: =INDEX(Calib!$C$71:$G$71,E$6)*E54/E50 -> 241.77801 | F55: =INDEX(Calib!$C$71:$G$71,F$6)*F54/F50 -> 161.18534 | G55: =INDEX(Calib!$C$71:$G$71,G$6)*G54/G50 -> 161.18534 | H55: =INDEX(Calib!$C$71:$G$71,H$6)*H54/H50 -> 161.18534 | I55: =INDEX(Calib!$C$71:$G$71,I$6)*I54/I50 -> 161.18534 | J55: =INDEX(Calib!$C$71:$G$71,J$6)*J54/J50 -> 161.18534 | ... Q55: =INDEX(Calib!$C$71:$G$71,Q$6)*Q54/Q50 -> 161.18534
A56: HBM 保留比例 | B56: % | C56: =Serving!$C$9 -> 0.1 | D56: =Serving!$C$9 -> 0.1 | E56: =Serving!$C$9 -> 0.1 | F56: =Serving!$C$9 -> 0.1 | G56: =Serving!$C$9 -> 0.1 | H56: =Serving!$C$9 -> 0.1 | I56: =Serving!$C$9 -> 0.1 | J56: =Serving!$C$9 -> 0.1 | ... Q56: =Serving!$C$9 -> 0.1
A57: 非專家權重占 HBM 上限 | B57: % | C57: =Serving!$C$10 -> 0.2 | D57: =Serving!$C$10 -> 0.2 | E57: =Serving!$C$10 -> 0.2 | F57: =Serving!$C$10 -> 0.2 | G57: =Serving!$C$10 -> 0.2 | H57: =Serving!$C$10 -> 0.2 | I57: =Serving!$C$10 -> 0.2 | J57: =Serving!$C$10 -> 0.2 | ... Q57: =Serving!$C$10 -> 0.2
A58: 專家權重占 HBM 上限 | B58: % | C58: =Serving!$C$11 -> 0.4 | D58: =Serving!$C$11 -> 0.4 | E58: =Serving!$C$11 -> 0.4 | F58: =Serving!$C$11 -> 0.4 | G58: =Serving!$C$11 -> 0.4 | H58: =Serving!$C$11 -> 0.4 | I58: =Serving!$C$11 -> 0.4 | J58: =Serving!$C$11 -> 0.4 | ... Q58: =Serving!$C$11 -> 0.4
A59: EP 啟用值 bytes/元素 | B59: B | C59: =Serving!$C$12 -> 3 | D59: =Serving!$C$12 -> 3 | E59: =Serving!$C$12 -> 3 | F59: =Serving!$C$12 -> 3 | G59: =Serving!$C$12 -> 3 | H59: =Serving!$C$12 -> 3 | I59: =Serving!$C$12 -> 3 | J59: =Serving!$C$12 -> 3 | ... Q59: =Serving!$C$12 -> 3
A60: KV 讀取效率 | B60: % | C60: =Serving!$C$13 -> 0.7 | D60: =Serving!$C$13 -> 0.7 | E60: =Serving!$C$13 -> 0.7 | F60: =Serving!$C$13 -> 0.7 | G60: =Serving!$C$13 -> 0.7 | H60: =Serving!$C$13 -> 0.7 | I60: =Serving!$C$13 -> 0.7 | J60: =Serving!$C$13 -> 0.7 | ... Q60: =Serving!$C$13 -> 0.7
A61: EP 通訊效率 | B61: % | C61: =Serving!$C$14 -> 0.7 | D61: =Serving!$C$14 -> 0.7 | E61: =Serving!$C$14 -> 0.7 | F61: =Serving!$C$14 -> 0.7 | G61: =Serving!$C$14 -> 0.7 | H61: =Serving!$C$14 -> 0.7 | I61: =Serving!$C$14 -> 0.7 | J61: =Serving!$C$14 -> 0.7 | ... Q61: =Serving!$C$14 -> 0.7
A62: 快取載入頻寬 | B62: TB/s | C62: =Serving!$C$15 -> 0.1 | D62: =Serving!$C$15 -> 0.1 | E62: =Serving!$C$15 -> 0.1 | F62: =Serving!$C$15 -> 0.1 | G62: =Serving!$C$15 -> 0.1 | H62: =Serving!$C$15 -> 0.1 | I62: =Serving!$C$15 -> 0.1 | J62: =Serving!$C$15 -> 0.1 | ... Q62: =Serving!$C$15 -> 0.1
A63: D. 每 token 計算量
A64: decode 被注意 token 數 | B64: tok | C64: =C36*IF(C37=0,C45,MIN(C45,C37))+(1-C36)*(C45/C38+C39) -> 2258.336 | D64: =D36*IF(D37=0,D45,MIN(D45,D37))+(1-D36)*(D45/D38+D39) -> 2212.32 | E64: =E36*IF(E37=0,E45,MIN(E45,E37))+(1-E36)*(E45/E38+E39) -> 34816 | F64: =F36*IF(F37=0,F45,MIN(F45,F37))+(1-F36)*(F45/F38+F39) -> 2258.336 | G64: =G36*IF(G37=0,G45,MIN(G45,G37))+(1-G36)*(G45/G38+G39) -> 2212.32 | H64: =H36*IF(H37=0,H45,MIN(H45,H37))+(1-H36)*(H45/H38+H39) -> 34816 | I64: =I36*IF(I37=0,I45,MIN(I45,I37))+(1-I36)*(I45/I38+I39) -> 2258.336 | J64: =J36*IF(J37=0,J45,MIN(J45,J37))+(1-J36)*(J45/J38+J39) -> 2212.32 | ... Q64: =Q36*IF(Q37=0,Q45,MIN(Q45,Q37))+(1-Q36)*(Q45/Q38+Q39) -> 34816
A65: decode FLOPs/token | B65: GFLOP | C65: =(2*C28*1000000000+C35*C64)*C10/1000000000 -> 38.728198 | D65: =(2*D28*1000000000+D35*D64)*D10/1000000000 -> 133.37673 | E65: =(2*E28*1000000000+E35*E64)*E10/1000000000 -> 531.1276 | F65: =(2*F28*1000000000+F35*F64)*F10/1000000000 -> 38.728198 | G65: =(2*G28*1000000000+G35*G64)*G10/1000000000 -> 133.37673 | H65: =(2*H28*1000000000+H35*H64)*H10/1000000000 -> 531.1276 | I65: =(2*I28*1000000000+I35*I64)*I10/1000000000 -> 38.728198 | J65: =(2*J28*1000000000+J35*J64)*J10/1000000000 -> 133.37673 | ... Q65: =(2*Q28*1000000000+Q35*Q64)*Q10/1000000000 -> 531.1276
A66: prefill 被注意 token 數 | B66: tok | C66: =C36*IF(C37=0,C46,MIN(C46,C37))+(1-C36)*(C46/C38+C39) -> 2175.232 | D66: =D36*IF(D37=0,D46,MIN(D46,D37))+(1-D36)*(D46/D38+D39) -> 2175.744 | E66: =E36*IF(E37=0,E46,MIN(E46,E37))+(1-E36)*(E46/E38+E39) -> 16384 | F66: =F36*IF(F37=0,F46,MIN(F46,F37))+(1-F36)*(F46/F38+F39) -> 2175.232 | G66: =G36*IF(G37=0,G46,MIN(G46,G37))+(1-G36)*(G46/G38+G39) -> 2175.744 | H66: =H36*IF(H37=0,H46,MIN(H46,H37))+(1-H36)*(H46/H38+H39) -> 16384 | I66: =I36*IF(I37=0,I46,MIN(I46,I37))+(1-I36)*(I46/I38+I39) -> 2175.232 | J66: =J36*IF(J37=0,J46,MIN(J46,J37))+(1-J36)*(J46/J38+J39) -> 2175.744 | ... Q66: =Q36*IF(Q37=0,Q46,MIN(Q46,Q37))+(1-Q36)*(Q46/Q38+Q39) -> 16384
A67: prefill FLOPs/token | B67: GFLOP | C67: =(2*C28*1000000000+C35*C66)*C10/1000000000 -> 38.259816 | D67: =(2*D28*1000000000+D35*D66)*D10/1000000000 -> 132.79185 | E67: =(2*E28*1000000000+E35*E66)*E10/1000000000 -> 440.53064 | F67: =(2*F28*1000000000+F35*F66)*F10/1000000000 -> 38.259816 | G67: =(2*G28*1000000000+G35*G66)*G10/1000000000 -> 132.79185 | H67: =(2*H28*1000000000+H35*H66)*H10/1000000000 -> 440.53064 | I67: =(2*I28*1000000000+I35*I66)*I10/1000000000 -> 38.259816 | J67: =(2*J28*1000000000+J35*J66)*J10/1000000000 -> 132.79185 | ... Q67: =(2*Q28*1000000000+Q35*Q66)*Q10/1000000000 -> 440.53064
A68: E. 記憶體配置（attention DP＋wide EP；每 GPU）
A69: 可用 HBM | B69: GB | C69: =C15*(1-C56) -> 72 | D69: =D15*(1-D56) -> 72 | E69: =E15*(1-E56) -> 72 | F69: =F15*(1-F56) -> 167.4 | G69: =G15*(1-G56) -> 167.4 | H69: =H15*(1-H56) -> 167.4 | I69: =I15*(1-I56) -> 259.2 | J69: =J15*(1-J56) -> 259.2 | ... Q69: =Q15*(1-Q56) -> 921.6
A70: 注意力 TP 度（自動） | C70: =MAX(1,CEILING(C32*C20/(C57*C69),1)) -> 1 | D70: =MAX(1,CEILING(D32*D20/(D57*D69),1)) -> 2 | E70: =MAX(1,CEILING(E32*E20/(E57*E69),1)) -> 4 | F70: =MAX(1,CEILING(F32*F20/(F57*F69),1)) -> 1 | G70: =MAX(1,CEILING(G32*G20/(G57*G69),1)) -> 1 | H70: =MAX(1,CEILING(H32*H20/(H57*H69),1)) -> 2 | I70: =MAX(1,CEILING(I32*I20/(I57*I69),1)) -> 1 | J70: =MAX(1,CEILING(J32*J20/(J57*J69),1)) -> 1 | ... Q70: =MAX(1,CEILING(Q32*Q20/(Q57*Q69),1)) -> 1
A71: decode EP 寬度（自動） | B71: GPU | C71: =MAX(C18,CEILING(C33*C19/(C58*C69),1)) -> 64 | D71: =MAX(D18,CEILING(D33*D19/(D58*D69),1)) -> 64 | E71: =MAX(E18,CEILING(E33*E19/(E58*E69),1)) -> 138 | F71: =MAX(F18,CEILING(F33*F19/(F58*F69),1)) -> 32 | G71: =MAX(G18,CEILING(G33*G19/(G58*G69),1)) -> 32 | H71: =MAX(H18,CEILING(H33*H19/(H58*H69),1)) -> 34 | I71: =MAX(I18,CEILING(I33*I19/(I58*I69),1)) -> 32 | J71: =MAX(J18,CEILING(J33*J19/(J58*J69),1)) -> 32 | ... Q71: =MAX(Q18,CEILING(Q33*Q19/(Q58*Q69),1)) -> 64
A72: 每 GPU 權重 | B72: GB | C72: =C32*C20/C70+C33*C19/C71 -> 9.7649375 | D72: =D32*D20/D70+D33*D19/D71 -> 34.822049 | E72: =E32*E20/E70+E33*E19/E71 -> 40.898054 | F72: =F32*F20/F70+F33*F19/F71 -> 10.309055 | G72: =G32*G20/G70+G33*G19/G71 -> 48.046332 | H72: =H32*H20/H70+H33*H19/H71 -> 89.900898 | I72: =I32*I20/I70+I33*I19/I71 -> 10.309055 | J72: =J32*J20/J70+J33*J19/J71 -> 48.046332 | ... Q72: =Q32*Q20/Q70+Q33*Q19/Q71 -> 83.797529
A73: 權重占可用 HBM | B73: % | C73: =C72/C69 -> 0.13562413 | D73: =D72/D69 -> 0.48363956 | E73: =E72/E69 -> 0.56802853 | F73: =F72/F69 -> 0.061583361 | G73: =G72/G69 -> 0.28701513 | H73: =H72/H69 -> 0.5370424 | I73: =I72/I69 -> 0.039772588 | J73: =J72/J69 -> 0.18536394 | ... Q73: =Q72/Q69 -> 0.090926138 | R73: 顯示用：C73:Q73（記憶體配置讀數（權重／KV 占可用 HBM）；與 Perf_Batch 同列鏡像（D13 常設測試的比對對象））
A74: F. Prefill（算力受限）
A75: prefill tok/s（每 prefill GPU） | B75: tok/s | C75: =C51*C14*1000000000000000/(C67*1000000000) -> 7754.8726 | D75: =D51*D14*1000000000000000/(D67*1000000000) -> 2234.3238 | E75: =E51*E14*1000000000000000/(E67*1000000000) -> 673.50594 | F75: =F51*F14*1000000000000000/(F67*1000000000) -> 78411.249 | G75: =G51*G14*1000000000000000/(G67*1000000000) -> 22591.748 | H75: =H51*H14*1000000000000000/(H67*1000000000) -> 6809.969 | I75: =I51*I14*1000000000000000/(I67*1000000000) -> 117616.87 | J75: =J51*J14*1000000000000000/(J67*1000000000) -> 33887.621 | ... Q75: =Q51*Q14*1000000000000000/(Q67*1000000000) -> 47669.783
A76: TTFT（計算部分；v9.0 D9：prefill 只計新鮮輸入 ISL × (1 − B4_CacheHit)；快取命中後新鮮 token 位於序列後段，本式（prefill 平均位置取整段 ISL 的一半）略低估 prefill 時間；v10.0 N4） | B76: s | C76: =(C43*(1-B4_CacheHit))*C67*1000000000/(C51*C14*1000000000000000*C21) -> 0.059420706 | D76: =(D43*(1-B4_CacheHit))*D67*1000000000/(D51*D14*1000000000000000*D21) -> 0.41247378 | E76: =(E43*(1-B4_CacheHit))*E67*1000000000/(E51*E14*1000000000000000*E21) -> 2.7367242 | F76: =(F43*(1-B4_CacheHit))*F67*1000000000/(F51*F14*1000000000000000*F21) -> 0.011753416 | G76: =(G43*(1-B4_CacheHit))*G67*1000000000/(G51*G14*1000000000000000*G21) -> 0.081587314 | H76: =(H43*(1-B4_CacheHit))*H67*1000000000/(H51*H14*1000000000000000*H21) -> 0.54132405 | I76: =(I43*(1-B4_CacheHit))*I67*1000000000/(I51*I14*1000000000000000*I21) -> 0.0078356104 | J76: =(J43*(1-B4_CacheHit))*J67*1000000000/(J51*J14*1000000000000000*J21) -> 0.054391543 | ... Q76: =(Q43*(1-B4_CacheHit))*Q67*1000000000/(Q51*Q14*1000000000000000*Q21) -> 0.038666003
A77: TTFT 符合上限 | C77: =IF(C76<=C42,"是","否") -> 是 | D77: =IF(D76<=D42,"是","否") -> 是 | E77: =IF(E76<=E42,"是","否") -> 是 | F77: =IF(F76<=F42,"是","否") -> 是 | G77: =IF(G76<=G42,"是","否") -> 是 | H77: =IF(H76<=H42,"是","否") -> 是 | I77: =IF(I76<=I42,"是","否") -> 是 | J77: =IF(J76<=J42,"是","否") -> 是 | ... Q77: =IF(Q76<=Q42,"是","否") -> 是
A78: G. Decode：每步時間＝固定延遲＋B × 每序列時間；B* ＝ min(SLO 上限, HBM 容量上限)
A79: 每步固定延遲（權重讀取＋逐層延遲） | B79: ms | C79: =C72/C16+(C29+C47)*C55/1000 -> 14.036695 | D79: =D72/D16+(D29+D47)*D55/1000 -> 25.868434 | E79: =E72/E16+(E29+E47)*E55/1000 -> 37.111509 | F79: =F72/F16+(F29+F47)*F55/1000 -> 8.7031574 | G79: =G72/G16+(G29+G47)*G55/1000 -> 16.321653 | H79: =H72/H16+(H29+H47)*H55/1000 -> 27.839702 | I79: =I72/I16+(I29+I47)*I55/1000 -> 8.7031574 | J79: =J72/J16+(J29+J47)*J55/1000 -> 16.321653 | ... Q79: =Q72/Q16+(Q29+Q47)*Q55/1000 -> 19.220763
A80: 每序列每步 — 算力項 | B80: ms | C80: =(C47+1)*C65/(C14*C53)/1000 -> 1.8244126 | D80: =(D47+1)*D65/(D14*D53)/1000 -> 6.2831269 | E80: =(E47+1)*E65/(E14*E53)/1000 -> 25.020422 | F80: =(F47+1)*F65/(F14*F53)/1000 -> 0.4332615 | G80: =(G47+1)*G65/(G14*G53)/1000 -> 1.492117 | H80: =(H47+1)*H65/(H14*H53)/1000 -> 5.9418499 | I80: =(I47+1)*I65/(I14*I53)/1000 -> 0.288841 | J80: =(J47+1)*J65/(J14*J53)/1000 -> 0.99474465 | ... Q80: =(Q47+1)*Q65/(Q14*Q53)/1000 -> 0.8488357
A81: 每序列每步 — KV 讀取項 | B81: ms | C81: =C34*C45/(C16*C60)/1000000000 -> 0.010374277 | D81: =D34*D45/(D16*D60)/1000000000 -> 0.029433996 | E81: =E34*E45/(E16*E60)/1000000000 -> 0.85518192 | F81: =F34*F45/(F16*F60)/1000000000 -> 0.0043442286 | G81: =G34*G45/(G16*G60)/1000000000 -> 0.012325486 | H81: =H34*H45/(H16*H60)/1000000000 -> 0.35810743 | I81: =I34*I45/(I16*I60)/1000000000 -> 0.0043442286 | J81: =J34*J45/(J16*J60)/1000000000 -> 0.012325486 | ... Q81: =Q34*Q45/(Q16*Q60)/1000000000 -> 0.089526857
A82: 每序列每步 — EP 通訊項 | B82: ms | C82: =(C47+1)*C29*C31*C30*C59*(C71-1)/C71/(C17*C61)/1000000000 -> 0.3566592 | D82: =(D47+1)*D29*D31*D30*D59*(D71-1)/D71/(D17*D61)/1000000000 -> 0.8854272 | E82: =(E47+1)*E29*E31*E30*E59*(E71-1)/E71/(E17*E61)/1000000000 -> 6.691999 | F82: =(F47+1)*F29*F31*F30*F59*(F71-1)/F71/(F17*F61)/1000000000 -> 0.019499886 | G82: =(G47+1)*G29*G31*G30*G59*(G71-1)/G71/(G17*G61)/1000000000 -> 0.0484096 | H82: =(H47+1)*H29*H31*H30*H59*(H71-1)/H71/(H17*H61)/1000000000 -> 0.36347697 | I82: =(I47+1)*I29*I31*I30*I59*(I71-1)/I71/(I17*I61)/1000000000 -> 0.019499886 | J82: =(J47+1)*J29*J31*J30*J59*(J71-1)/J71/(J17*J61)/1000000000 -> 0.0484096 | ... Q82: =(Q47+1)*Q29*Q31*Q30*Q59*(Q71-1)/Q71/(Q17*Q61)/1000000000 -> 0.18432
A83: 每序列每步（取最大，假設三者可重疊） | B83: ms | C83: =MAX(C80,C81,C82) -> 1.8244126 | D83: =MAX(D80,D81,D82) -> 6.2831269 | E83: =MAX(E80,E81,E82) -> 25.020422 | F83: =MAX(F80,F81,F82) -> 0.4332615 | G83: =MAX(G80,G81,G82) -> 1.492117 | H83: =MAX(H80,H81,H82) -> 5.9418499 | I83: =MAX(I80,I81,I82) -> 0.288841 | J83: =MAX(J80,J81,J82) -> 0.99474465 | ... Q83: =MAX(Q80,Q81,Q82) -> 0.8488357
A84: 每序列綁定項 | C84: =IF(C83=C80,"算力",IF(C83=C81,"KV 頻寬","EP 通訊")) -> 算力 | D84: =IF(D83=D80,"算力",IF(D83=D81,"KV 頻寬","EP 通訊")) -> 算力 | E84: =IF(E83=E80,"算力",IF(E83=E81,"KV 頻寬","EP 通訊")) -> 算力 | F84: =IF(F83=F80,"算力",IF(F83=F81,"KV 頻寬","EP 通訊")) -> 算力 | G84: =IF(G83=G80,"算力",IF(G83=G81,"KV 頻寬","EP 通訊")) -> 算力 | H84: =IF(H83=H80,"算力",IF(H83=H81,"KV 頻寬","EP 通訊")) -> 算力 | I84: =IF(I83=I80,"算力",IF(I83=I81,"KV 頻寬","EP 通訊")) -> 算力 | J84: =IF(J83=J80,"算力",IF(J83=J81,"KV 頻寬","EP 通訊")) -> 算力 | ... Q84: =IF(Q83=Q80,"算力",IF(Q83=Q81,"KV 頻寬","EP 通訊")) -> 算力
A85: SLO 允許的批次上限 | B85: 序列/GPU | C85: =(1000*C49/C41-C79)/C83 -> 8.7758293 | D85: =(1000*D49/D41-D79)/D83 -> 5.1908328 | E85: =(1000*E49/E41-E79)/E83 -> 0.9961519 | F85: =(1000*F49/F41-F79)/F83 -> 49.264177 | G85: =(1000*G49/G41-G79)/G83 -> 28.256124 | H85: =(1000*H49/H41-H79)/H83 -> 5.7551013 | I85: =(1000*I49/I41-I79)/I83 -> 73.896265 | J85: =(1000*J49/J41-J79)/J83 -> 42.384185 | ... Q85: =(1000*Q49/Q41-Q79)/Q83 -> 50.439547
A86: HBM 容量允許的批次上限 | B86: 序列/GPU | C86: =(C69-C72)*1000000000/(C34*C45) -> 2558.1997 | D86: =(D69-D72)*1000000000/(D34*D45) -> 538.63353 | E86: =(E69-E72)*1000000000/(E34*E45) -> 15.509086 | F86: =(F69-F72)*1000000000/(F34*F45) -> 6457.2925 | G86: =(G69-G72)*1000000000/(G34*G45) -> 1729.1939 | H86: =(H69-H72)*1000000000/(H34*H45) -> 38.645178 | I86: =(I69-I72)*1000000000/(I34*I45) -> 10230.772 | J86: =(J69-J72)*1000000000/(J34*J45) -> 3059.1908 | ... Q86: =(Q69-Q72)*1000000000/(Q34*Q45) -> 417.77291
A87: 採用批次 B* | B87: 序列/GPU | C87: =MAX(0,MIN(C85,C86)) -> 8.7758293 | D87: =MAX(0,MIN(D85,D86)) -> 5.1908328 | E87: =MAX(0,MIN(E85,E86)) -> 0.9961519 | F87: =MAX(0,MIN(F85,F86)) -> 49.264177 | G87: =MAX(0,MIN(G85,G86)) -> 28.256124 | H87: =MAX(0,MIN(H85,H86)) -> 5.7551013 | I87: =MAX(0,MIN(I85,I86)) -> 73.896265 | J87: =MAX(0,MIN(J85,J86)) -> 42.384185 | ... Q87: =MAX(0,MIN(Q85,Q86)) -> 50.439547
A88: decode tok/s（每 decode GPU） | B88: tok/s | C88: =IF(C87>0,C87*C49/((C79+C87*C83)/1000),0) -> 739.80293 | D88: =IF(D87>0,D87*D49/((D79+D87*D83)/1000),0) -> 224.82359 | E88: =IF(E87>0,E87*E49/((E79+E87*E83)/1000),0) -> 40.674237 | F88: =IF(F87>0,F87*F49/((F79+F87*F83)/1000),0) -> 4152.973 | G88: =IF(G87>0,G87*G49/((G79+G87*G83)/1000),0) -> 1223.8197 | H88: =IF(H87>0,H87*H49/((H79+H87*H83)/1000),0) -> 234.98862 | I88: =IF(I87>0,I87*I49/((I79+I87*I83)/1000),0) -> 6229.4595 | J88: =IF(J87>0,J87*J49/((J79+J87*J83)/1000),0) -> 1835.7295 | ... Q88: =IF(Q87>0,Q87*Q49/((Q79+Q87*Q83)/1000),0) -> 2059.5153
A89: 實際每用戶速度 | B89: tok/s | C89: =IF(C87>0,C49/((C79+C87*C83)/1000),0) -> 84.300059 | D89: =IF(D87>0,D49/((D79+D87*D83)/1000),0) -> 43.311661 | E89: =IF(E87>0,E49/((E79+E87*E83)/1000),0) -> 40.83136 | F89: =IF(F87>0,F49/((F79+F87*F83)/1000),0) -> 84.300059 | G89: =IF(G87>0,G49/((G79+G87*G83)/1000),0) -> 43.311661 | H89: =IF(H87>0,H49/((H79+H87*H83)/1000),0) -> 40.83136 | I89: =IF(I87>0,I49/((I79+I87*I83)/1000),0) -> 84.300059 | J89: =IF(J87>0,J49/((J79+J87*J83)/1000),0) -> 43.311661 | ... Q89: =IF(Q87>0,Q49/((Q79+Q87*Q83)/1000),0) -> 40.83136
A90: 綁定約束（文字「SLO 不可達」＝decode 不可達；「TTFT 不可達」＝首 token 時間超過上限；兩者皆不符時顯示 SLO；v6.2） | C90: =IF(C87<=0,"SLO 不可達",IF(C77<>"是","TTFT 不可達",IF(C85<=C86,"SLO（"&C84&"）","HBM 容量"))) -> SLO（算力） | D90: =IF(D87<=0,"SLO 不可達",IF(D77<>"是","TTFT 不可達",IF(D85<=D86,"SLO（"&D84&"）","HBM 容量"))) -> SLO（算力） | E90: =IF(E87<=0,"SLO 不可達",IF(E77<>"是","TTFT 不可達",IF(E85<=E86,"SLO（"&E84&"）","HBM 容量"))) -> SLO（算力） | F90: =IF(F87<=0,"SLO 不可達",IF(F77<>"是","TTFT 不可達",IF(F85<=F86,"SLO（"&F84&"）","HBM 容量"))) -> SLO（算力） | G90: =IF(G87<=0,"SLO 不可達",IF(G77<>"是","TTFT 不可達",IF(G85<=G86,"SLO（"&G84&"）","HBM 容量"))) -> SLO（算力） | H90: =IF(H87<=0,"SLO 不可達",IF(H77<>"是","TTFT 不可達",IF(H85<=H86,"SLO（"&H84&"）","HBM 容量"))) -> SLO（算力） | I90: =IF(I87<=0,"SLO 不可達",IF(I77<>"是","TTFT 不可達",IF(I85<=I86,"SLO（"&I84&"）","HBM 容量"))) -> SLO（算力） | J90: =IF(J87<=0,"SLO 不可達",IF(J77<>"是","TTFT 不可達",IF(J85<=J86,"SLO（"&J84&"）","HBM 容量"))) -> SLO（算力） | ... Q90: =IF(Q87<=0,"SLO 不可達",IF(Q77<>"是","TTFT 不可達",IF(Q85<=Q86,"SLO（"&Q84&"）","HBM 容量"))) -> SLO（算力）
A91: KV 占可用 HBM | B91: % | C91: =C87*C34*C45/1000000000/C69 -> 0.0029652162 | D91: =D87*D34*D45/1000000000/D69 -> 0.0049761861 | E91: =E87*E34*E45/1000000000/E69 -> 0.02774562 | F91: =F87*F34*F45/1000000000/F69 -> 0.0071593974 | G91: =G87*G34*G45/1000000000/G69 -> 0.011650624 | H91: =H87*H34*H45/1000000000/H69 -> 0.068944381 | I91: =I87*I34*I45/1000000000/I69 -> 0.0069356662 | J91: =J87*J34*J45/1000000000/J69 -> 0.011286542 | ... Q91: =Q87*Q34*Q45/1000000000/Q69 -> 0.10975645 | R91: 顯示用：C91:Q91（記憶體配置讀數（權重／KV 占可用 HBM）；與 Perf_Batch 同列鏡像（D13 常設測試的比對對象））
A92: H. 每架與每 GW（參考任務；P:D 依工作量配比；100% 利用率）
A93: 每請求 GPU 秒（文字「SLO 不可達」＝decode 不可達；「TTFT 不可達」＝首 token 時間超過上限；兩者皆不符時顯示 SLO；v6.0 D8、v6.2；v9.0 D9：prefill 只計新鮮輸入 ISL × (1 − B4_CacheHit)） | B93: GPU-s | C93: =IF(ISNUMBER(C88),IF(C88>0,IF(C77="是",(C43*(1-B4_CacheHit))/C75+C44/C88,"TTFT 不可達"),"SLO 不可達"),"SLO 不可達") -> 1.859518 | D93: =IF(ISNUMBER(D88),IF(D88>0,IF(D77="是",(D43*(1-B4_CacheHit))/D75+D44/D88,"TTFT 不可達"),"SLO 不可達"),"SLO 不可達") -> 12.409155 | E93: =IF(ISNUMBER(E88),IF(E88>0,IF(E77="是",(E43*(1-B4_CacheHit))/E75+E44/E88,"TTFT 不可達"),"SLO 不可達"),"SLO 不可達") -> 122.59636 | F93: =IF(ISNUMBER(F88),IF(F88>0,IF(F77="是",(F43*(1-B4_CacheHit))/F75+F44/F88,"TTFT 不可達"),"SLO 不可達"),"SLO 不可達") -> 0.29358401 | G93: =IF(ISNUMBER(G88),IF(G88>0,IF(G77="是",(G43*(1-B4_CacheHit))/G75+G44/G88,"TTFT 不可達"),"SLO 不可達"),"SLO 不可達") -> 1.9997984 | H93: =IF(ISNUMBER(H88),IF(H88>0,IF(H77="是",(H43*(1-B4_CacheHit))/H75+H44/H88,"TTFT 不可達"),"SLO 不可達"),"SLO 不可達") -> 19.595928 | I93: =IF(ISNUMBER(I88),IF(I88>0,IF(I77="是",(I43*(1-B4_CacheHit))/I75+I44/I88,"TTFT 不可達"),"SLO 不可達"),"SLO 不可達") -> 0.19572267 | J93: =IF(ISNUMBER(J88),IF(J88>0,IF(J77="是",(J43*(1-B4_CacheHit))/J75+J44/J88,"TTFT 不可達"),"SLO 不可達"),"SLO 不可達") -> 1.333199 | ... Q93: =IF(ISNUMBER(Q88),IF(Q88>0,IF(Q77="是",(Q43*(1-B4_CacheHit))/Q75+Q44/Q88,"TTFT 不可達"),"SLO 不可達"),"SLO 不可達") -> 2.2981455
A94: prefill GPU 占比 | B94: % | C94: =IF(ISNUMBER(C93),IF(C93>0,((C43*(1-B4_CacheHit))/C75)/C93,0),C93) -> 0.25563917 | D94: =IF(ISNUMBER(D93),IF(D93>0,((D43*(1-B4_CacheHit))/D75)/D93,0),D93) -> 0.2659158 | E94: =IF(ISNUMBER(E93),IF(E93>0,((E43*(1-B4_CacheHit))/E75)/E93,0),E93) -> 0.17858437 | F94: =IF(ISNUMBER(F93),IF(F93>0,((F43*(1-B4_CacheHit))/F75)/F93,0),F93) -> 0.160137 | G94: =IF(ISNUMBER(G93),IF(G93>0,((G43*(1-B4_CacheHit))/G75)/G93,0),G93) -> 0.16319107 | H94: =IF(ISNUMBER(H93),IF(H93>0,((H43*(1-B4_CacheHit))/H75)/H93,0),H93) -> 0.11049725 | I94: =IF(ISNUMBER(I93),IF(I93>0,((I43*(1-B4_CacheHit))/I75)/I93,0),I93) -> 0.160137 | J94: =IF(ISNUMBER(J93),IF(J93>0,((J43*(1-B4_CacheHit))/J75)/J93,0),J93) -> 0.16319107 | ... Q94: =IF(ISNUMBER(Q93),IF(Q93>0,((Q43*(1-B4_CacheHit))/Q75)/Q93,0),Q93) -> 0.13459898 | R94: 顯示用：C94:Q94（P:D 配比讀數（DRV_PreShare）；Perf 第 118 列讀它；與 Perf_Batch 鏡像）
A95: 每架總 tok/s | B95: tok/s | C95: =IF(ISNUMBER(C93),IF(C93>0,C22*(C43+C44)/C93,0),C93) -> 158595.93 | D95: =IF(ISNUMBER(D93),IF(D93>0,D22*(D43+D44)/D93,0),D93) -> 47531.361 | E95: =IF(ISNUMBER(E93),IF(E93>0,E22*(E43+E44)/E93,0),E93) -> 9622.2108 | F95: =IF(ISNUMBER(F93),IF(F93>0,F22*(F43+F44)/F93,0),F93) -> 2260177.6 | G95: =IF(ISNUMBER(G93),IF(G93>0,G22*(G43+G44)/G93,0),G93) -> 663618.88 | H95: =IF(ISNUMBER(H93),IF(H93>0,H22*(H43+H44)/H93,0),H93) -> 135446.92 | I95: =IF(ISNUMBER(I93),IF(I93>0,I22*(I43+I44)/I93,0),I93) -> 3390266.4 | J95: =IF(ISNUMBER(J93),IF(J93>0,J22*(J43+J44)/J93,0),J93) -> 995428.32 | ... Q95: =IF(ISNUMBER(Q93),IF(Q93>0,Q22*(Q43+Q44)/Q93,0),Q93) -> 1154934.7
A96: 每架 decode tok/s | B96: tok/s | C96: =IF(ISNUMBER(C95),C95*C44/(C43+C44),C95) -> 17621.77 | D96: =IF(ISNUMBER(D95),D95*D44/(D43+D44),D95) -> 5281.2623 | E96: =IF(ISNUMBER(E95),E95*E44/(E43+E44),E95) -> 1069.1345 | F96: =IF(ISNUMBER(F95),F95*F44/(F43+F44),F95) -> 251130.84 | G96: =IF(ISNUMBER(G95),G95*G44/(G43+G44),G95) -> 73735.431 | H96: =IF(ISNUMBER(H95),H95*H44/(H43+H44),H95) -> 15049.657 | I96: =IF(ISNUMBER(I95),I95*I44/(I43+I44),I95) -> 376696.27 | J96: =IF(ISNUMBER(J95),J95*J44/(J43+J44),J95) -> 110603.15 | ... Q96: =IF(ISNUMBER(Q95),Q95*Q44/(Q43+Q44),Q95) -> 128326.08
A97: 每架 prefill tok/s | B97: tok/s | C97: =IF(ISNUMBER(C95),C95-C96,C95) -> 140974.16 | D97: =IF(ISNUMBER(D95),D95-D96,D95) -> 42250.098 | E97: =IF(ISNUMBER(E95),E95-E96,E95) -> 8553.0763 | F97: =IF(ISNUMBER(F95),F95-F96,F95) -> 2009046.7 | G97: =IF(ISNUMBER(G95),G95-G96,G95) -> 589883.45 | H97: =IF(ISNUMBER(H95),H95-H96,H95) -> 120397.26 | I97: =IF(ISNUMBER(I95),I95-I96,I95) -> 3013570.1 | J97: =IF(ISNUMBER(J95),J95-J96,J95) -> 884825.17 | ... Q97: =IF(ISNUMBER(Q95),Q95-Q96,Q95) -> 1026608.6
A98: 每 GW 總產出 | B98: M tok/年 | C98: =IF(ISNUMBER(C95),C95*C25*8760*3600/1000000,C95) -> 1.1222824e+11 | D98: =IF(ISNUMBER(D95),D95*D25*8760*3600/1000000,D95) -> 3.3634916e+10 | E98: =IF(ISNUMBER(E95),E95*E25*8760*3600/1000000,E95) -> 6.8090257e+09 | F98: =IF(ISNUMBER(F95),F95*F25*8760*3600/1000000,F95) -> 4.9672914e+11 | G98: =IF(ISNUMBER(G95),G95*G25*8760*3600/1000000,G95) -> 1.4584643e+11 | H98: =IF(ISNUMBER(H95),H95*H25*8760*3600/1000000,H95) -> 2.9767763e+10 | I98: =IF(ISNUMBER(I95),I95*I25*8760*3600/1000000,I95) -> 7.2317604e+11 | J98: =IF(ISNUMBER(J95),J95*J25*8760*3600/1000000,J95) -> 2.1233432e+11 | ... Q98: =IF(ISNUMBER(Q95),Q95*Q25*8760*3600/1000000,Q95) -> 9.8521567e+10
A99: 每 GW decode 產出 | B99: M tok/年 | C99: =IF(ISNUMBER(C96),C96*C25*8760*3600/1000000,C96) -> 1.2469805e+10 | D99: =IF(ISNUMBER(D96),D96*D25*8760*3600/1000000,D96) -> 3.7372129e+09 | E99: =IF(ISNUMBER(E96),E96*E25*8760*3600/1000000,E96) -> 7.5655841e+08 | F99: =IF(ISNUMBER(F96),F96*F25*8760*3600/1000000,F96) -> 5.5192126e+10 | G99: =IF(ISNUMBER(G96),G96*G25*8760*3600/1000000,G96) -> 1.6205159e+10 | H99: =IF(ISNUMBER(H96),H96*H25*8760*3600/1000000,H96) -> 3.3075292e+09 | I99: =IF(ISNUMBER(I96),I96*I25*8760*3600/1000000,I96) -> 8.0352894e+10 | J99: =IF(ISNUMBER(J96),J96*J25*8760*3600/1000000,J96) -> 2.3592702e+10 | ... Q99: =IF(ISNUMBER(Q96),Q96*Q25*8760*3600/1000000,Q96) -> 1.0946841e+10 | R99: 顯示用：C99:Q99（每 GW decode 產出讀數（下游用 IF_TokRackD_*）；與 Perf_Batch 鏡像（D13））
A100: I. 每 M token GPU 秒（供 Unit_Cost）與速覽成本
A101: 新鮮 prefill | B101: GPU-s/M | C101: =1000000/C75 -> 128.95118 | D101: =1000000/D75 -> 447.5627 | E101: =1000000/E75 -> 1484.7679 | F101: =1000000/F75 -> 12.753272 | G101: =1000000/G75 -> 44.263951 | H101: =1000000/H75 -> 146.84355 | I101: =1000000/I75 -> 8.5021814 | J101: =1000000/J75 -> 29.509301 | ... Q101: =1000000/Q75 -> 20.977649
...

Sheet Sens_Perf
A1: Sens_Perf — VR200 對 GB300 的單變數敏感度（先看敏感度，再看基準）
A2: 每組兩欄：左 VR200、右 GB300。黃底藍字＝該情境改動的輸入。GB300 為校準世代，VR200 的 η_d 與每層延遲為沿用值 [Analogy]，故 VR 專屬情境只動 VR 欄
A3: 情境 | C3: 基準 | E3: VR η_d × 0.5（新世代軟體未成熟） | G3: VR η_d × 1.5 | I3: VR 每層延遲 × 0.7 | K3: VR 每層延遲 × 1.5 | M3: VR 峰值 50 PF（J2 高情境） | O3: SLO 40 tok/s | Q3: SLO 100 tok/s | S3: MTP 接受率 0.60 | U3: MTP 接受率 0.80 | W3: ISL 4K | Y3: ISL 64K | AA3: 生產折減 0.7（兩世代） | AC3: Astra KV 情境 1（混合） | AE3: Astra KV 情境 2（全層 MLA，基準） | AG3: Astra KV 情境 3（GQA-8）
A4: 世代 | C4: =INDEX(Spec_Rack!$C$4:$G$4,C6) -> VR200 NVL72 | D4: =INDEX(Spec_Rack!$C$4:$G$4,D6) -> GB300 NVL72 | E4: =INDEX(Spec_Rack!$C$4:$G$4,E6) -> VR200 NVL72 | F4: =INDEX(Spec_Rack!$C$4:$G$4,F6) -> GB300 NVL72 | G4: =INDEX(Spec_Rack!$C$4:$G$4,G6) -> VR200 NVL72 | H4: =INDEX(Spec_Rack!$C$4:$G$4,H6) -> GB300 NVL72 | I4: =INDEX(Spec_Rack!$C$4:$G$4,I6) -> VR200 NVL72 | J4: =INDEX(Spec_Rack!$C$4:$G$4,J6) -> GB300 NVL72 | ... AH4: =INDEX(Spec_Rack!$C$4:$G$4,AH6) -> GB300 NVL72
A5: 層級 | C5: =INDEX(Arch!$C$4:$E$4,C7) -> Sol（中層） | D5: =INDEX(Arch!$C$4:$E$4,D7) -> Sol（中層） | E5: =INDEX(Arch!$C$4:$E$4,E7) -> Sol（中層） | F5: =INDEX(Arch!$C$4:$E$4,F7) -> Sol（中層） | G5: =INDEX(Arch!$C$4:$E$4,G7) -> Sol（中層） | H5: =INDEX(Arch!$C$4:$E$4,H7) -> Sol（中層） | I5: =INDEX(Arch!$C$4:$E$4,I7) -> Sol（中層） | J5: =INDEX(Arch!$C$4:$E$4,J7) -> Sol（中層） | ... AH5: =INDEX(Arch!$C$4:$E$4,AH7) -> Astra（頂層）
A6: 世代索引 | C6: 4 | D6: 3 | E6: 4 | F6: 3 | G6: 4 | H6: 3 | I6: 4 | J6: 3 | K6: 4 | L6: 3 | M6: 4 | N6: 3 | O6: 4 | P6: 3 | Q6: 4 | R6: 3 | S6: 4 | T6: 3 | U6: 4 | V6: 3 | W6: 4 | X6: 3 | Y6: 4 | Z6: 3 | AA6: 4 | AB6: 3 | AC6: 4 | AD6: 3 | AE6: 4 | AF6: 3 | AG6: 4 | AH6: 3
A7: 層級索引 | C7: 2 | D7: 2 | E7: 2 | F7: 2 | G7: 2 | H7: 2 | I7: 2 | J7: 2 | K7: 2 | L7: 2 | M7: 2 | N7: 2 | O7: 2 | P7: 2 | Q7: 2 | R7: 2 | S7: 2 | T7: 2 | U7: 2 | V7: 2 | W7: 2 | X7: 2 | Y7: 2 | Z7: 2 | AA7: 2 | AB7: 2 | AC7: 3 | AD7: 3 | AE7: 3 | AF7: 3 | AG7: 3 | AH7: 3
A9: 0. Tech_Registry 掛鉤（基準＝1；Registry 未啟用任何條目時與 v5.4 相同）
A10: FLOPs/token 倍數（H_FLOP） | B10: x | C10: =Tech_Registry!$E$22 -> 1 | D10: =Tech_Registry!$E$22 -> 1 | E10: =Tech_Registry!$E$22 -> 1 | F10: =Tech_Registry!$E$22 -> 1 | G10: =Tech_Registry!$E$22 -> 1 | H10: =Tech_Registry!$E$22 -> 1 | I10: =Tech_Registry!$E$22 -> 1 | J10: =Tech_Registry!$E$22 -> 1 | ... AH10: =Tech_Registry!$E$22 -> 1
A11: KV bytes/token 倍數（H_KV） | B11: x | C11: =Tech_Registry!$E$23 -> 1 | D11: =Tech_Registry!$E$23 -> 1 | E11: =Tech_Registry!$E$23 -> 1 | F11: =Tech_Registry!$E$23 -> 1 | G11: =Tech_Registry!$E$23 -> 1 | H11: =Tech_Registry!$E$23 -> 1 | I11: =Tech_Registry!$E$23 -> 1 | J11: =Tech_Registry!$E$23 -> 1 | ... AH11: =Tech_Registry!$E$23 -> 1
A12: 權重 bytes/param 倍數（H_WB） | B12: x | C12: =Tech_Registry!$E$24 -> 1 | D12: =Tech_Registry!$E$24 -> 1 | E12: =Tech_Registry!$E$24 -> 1 | F12: =Tech_Registry!$E$24 -> 1 | G12: =Tech_Registry!$E$24 -> 1 | H12: =Tech_Registry!$E$24 -> 1 | I12: =Tech_Registry!$E$24 -> 1 | J12: =Tech_Registry!$E$24 -> 1 | ... AH12: =Tech_Registry!$E$24 -> 1
A13: A. 規格（連結 Spec_Rack、DC_Cost）
A14: 計算用峰值 | B14: PF/GPU | C14: =INDEX(Spec_Rack!$C$35:$G$35,C$6) -> 35 | D14: =INDEX(Spec_Rack!$C$35:$G$35,D$6) -> 15 | E14: =INDEX(Spec_Rack!$C$35:$G$35,E$6) -> 35 | F14: =INDEX(Spec_Rack!$C$35:$G$35,F$6) -> 15 | G14: =INDEX(Spec_Rack!$C$35:$G$35,G$6) -> 35 | H14: =INDEX(Spec_Rack!$C$35:$G$35,H$6) -> 15 | I14: =INDEX(Spec_Rack!$C$35:$G$35,I$6) -> 35 | J14: =INDEX(Spec_Rack!$C$35:$G$35,J$6) -> 15 | ... L14: =INDEX(Spec_Rack!$C$35:$G$35,L$6) -> 15 | M14: 50 | N14: =INDEX(Spec_Rack!$C$35:$G$35,N$6) -> 15 | O14: =INDEX(Spec_Rack!$C$35:$G$35,O$6) -> 35 | P14: =INDEX(Spec_Rack!$C$35:$G$35,P$6) -> 15 | Q14: =INDEX(Spec_Rack!$C$35:$G$35,Q$6) -> 35 | R14: =INDEX(Spec_Rack!$C$35:$G$35,R$6) -> 15 | S14: =INDEX(Spec_Rack!$C$35:$G$35,S$6) -> 35 | T14: =INDEX(Spec_Rack!$C$35:$G$35,T$6) -> 15 | U14: =INDEX(Spec_Rack!$C$35:$G$35,U$6) -> 35 | ... AH14: =INDEX(Spec_Rack!$C$35:$G$35,AH$6) -> 15
A15: HBM 容量 | B15: GB/GPU | C15: =INDEX(Spec_Rack!$C$25:$G$25,C$6) -> 288 | D15: =INDEX(Spec_Rack!$C$25:$G$25,D$6) -> 288 | E15: =INDEX(Spec_Rack!$C$25:$G$25,E$6) -> 288 | F15: =INDEX(Spec_Rack!$C$25:$G$25,F$6) -> 288 | G15: =INDEX(Spec_Rack!$C$25:$G$25,G$6) -> 288 | H15: =INDEX(Spec_Rack!$C$25:$G$25,H$6) -> 288 | I15: =INDEX(Spec_Rack!$C$25:$G$25,I$6) -> 288 | J15: =INDEX(Spec_Rack!$C$25:$G$25,J$6) -> 288 | ... AH15: =INDEX(Spec_Rack!$C$25:$G$25,AH$6) -> 288
A16: HBM 頻寬 | B16: TB/s/GPU | C16: =INDEX(Spec_Rack!$C$26:$G$26,C$6) -> 22 | D16: =INDEX(Spec_Rack!$C$26:$G$26,D$6) -> 8 | E16: =INDEX(Spec_Rack!$C$26:$G$26,E$6) -> 22 | F16: =INDEX(Spec_Rack!$C$26:$G$26,F$6) -> 8 | G16: =INDEX(Spec_Rack!$C$26:$G$26,G$6) -> 22 | H16: =INDEX(Spec_Rack!$C$26:$G$26,H$6) -> 8 | I16: =INDEX(Spec_Rack!$C$26:$G$26,I$6) -> 22 | J16: =INDEX(Spec_Rack!$C$26:$G$26,J$6) -> 8 | ... AH16: =INDEX(Spec_Rack!$C$26:$G$26,AH$6) -> 8
A17: EP 通訊頻寬（單向） | B17: TB/s/GPU | C17: =INDEX(Spec_Rack!$C$27:$G$27,C$6) -> 1.8 | D17: =INDEX(Spec_Rack!$C$27:$G$27,D$6) -> 0.9 | E17: =INDEX(Spec_Rack!$C$27:$G$27,E$6) -> 1.8 | F17: =INDEX(Spec_Rack!$C$27:$G$27,F$6) -> 0.9 | G17: =INDEX(Spec_Rack!$C$27:$G$27,G$6) -> 1.8 | H17: =INDEX(Spec_Rack!$C$27:$G$27,H$6) -> 0.9 | I17: =INDEX(Spec_Rack!$C$27:$G$27,I$6) -> 1.8 | J17: =INDEX(Spec_Rack!$C$27:$G$27,J$6) -> 0.9 | ... AH17: =INDEX(Spec_Rack!$C$27:$G$27,AH$6) -> 0.9
A18: decode EP 基準寬度 | B18: GPU | C18: =INDEX(Spec_Rack!$C$29:$G$29,C$6) -> 32 | D18: =INDEX(Spec_Rack!$C$29:$G$29,D$6) -> 32 | E18: =INDEX(Spec_Rack!$C$29:$G$29,E$6) -> 32 | F18: =INDEX(Spec_Rack!$C$29:$G$29,F$6) -> 32 | G18: =INDEX(Spec_Rack!$C$29:$G$29,G$6) -> 32 | H18: =INDEX(Spec_Rack!$C$29:$G$29,H$6) -> 32 | I18: =INDEX(Spec_Rack!$C$29:$G$29,I$6) -> 32 | J18: =INDEX(Spec_Rack!$C$29:$G$29,J$6) -> 32 | ... AH18: =INDEX(Spec_Rack!$C$29:$G$29,AH$6) -> 32
A19: 專家權重 bytes/param（含 H_WB） | B19: B | C19: =INDEX(Spec_Rack!$C$30:$G$30,C$6)*C12 -> 0.5625 | D19: =INDEX(Spec_Rack!$C$30:$G$30,D$6)*D12 -> 0.5625 | E19: =INDEX(Spec_Rack!$C$30:$G$30,E$6)*E12 -> 0.5625 | F19: =INDEX(Spec_Rack!$C$30:$G$30,F$6)*F12 -> 0.5625 | G19: =INDEX(Spec_Rack!$C$30:$G$30,G$6)*G12 -> 0.5625 | H19: =INDEX(Spec_Rack!$C$30:$G$30,H$6)*H12 -> 0.5625 | I19: =INDEX(Spec_Rack!$C$30:$G$30,I$6)*I12 -> 0.5625 | J19: =INDEX(Spec_Rack!$C$30:$G$30,J$6)*J12 -> 0.5625 | ... AH19: =INDEX(Spec_Rack!$C$30:$G$30,AH$6)*AH12 -> 0.5625
A20: 非專家權重 bytes/param（含 H_WB） | B20: B | C20: =INDEX(Spec_Rack!$C$31:$G$31,C$6)*C12 -> 1 | D20: =INDEX(Spec_Rack!$C$31:$G$31,D$6)*D12 -> 1 | E20: =INDEX(Spec_Rack!$C$31:$G$31,E$6)*E12 -> 1 | F20: =INDEX(Spec_Rack!$C$31:$G$31,F$6)*F12 -> 1 | G20: =INDEX(Spec_Rack!$C$31:$G$31,G$6)*G12 -> 1 | H20: =INDEX(Spec_Rack!$C$31:$G$31,H$6)*H12 -> 1 | I20: =INDEX(Spec_Rack!$C$31:$G$31,I$6)*I12 -> 1 | J20: =INDEX(Spec_Rack!$C$31:$G$31,J$6)*J12 -> 1 | ... AH20: =INDEX(Spec_Rack!$C$31:$G$31,AH$6)*AH12 -> 1
A21: 每 prefill 實例 GPU 數 | B21: GPU | C21: =INDEX(Spec_Rack!$C$32:$G$32,C$6) -> 4 | D21: =INDEX(Spec_Rack!$C$32:$G$32,D$6) -> 4 | E21: =INDEX(Spec_Rack!$C$32:$G$32,E$6) -> 4 | F21: =INDEX(Spec_Rack!$C$32:$G$32,F$6) -> 4 | G21: =INDEX(Spec_Rack!$C$32:$G$32,G$6) -> 4 | H21: =INDEX(Spec_Rack!$C$32:$G$32,H$6) -> 4 | I21: =INDEX(Spec_Rack!$C$32:$G$32,I$6) -> 4 | J21: =INDEX(Spec_Rack!$C$32:$G$32,J$6) -> 4 | ... AH21: =INDEX(Spec_Rack!$C$32:$G$32,AH$6) -> 4
A22: GPU 封裝／架 | B22: 顆 | C22: =INDEX(Spec_Rack!$C$6:$G$6,C$6) -> 72 | D22: =INDEX(Spec_Rack!$C$6:$G$6,D$6) -> 72 | E22: =INDEX(Spec_Rack!$C$6:$G$6,E$6) -> 72 | F22: =INDEX(Spec_Rack!$C$6:$G$6,F$6) -> 72 | G22: =INDEX(Spec_Rack!$C$6:$G$6,G$6) -> 72 | H22: =INDEX(Spec_Rack!$C$6:$G$6,H$6) -> 72 | I22: =INDEX(Spec_Rack!$C$6:$G$6,I$6) -> 72 | J22: =INDEX(Spec_Rack!$C$6:$G$6,J$6) -> 72 | ... AH22: =INDEX(Spec_Rack!$C$6:$G$6,AH$6) -> 72
A23: GPU 功率 | B23: W | C23: =INDEX(Spec_Rack!$C$33:$G$33,C$6) -> 1800 | D23: =INDEX(Spec_Rack!$C$33:$G$33,D$6) -> 1400 | E23: =INDEX(Spec_Rack!$C$33:$G$33,E$6) -> 1800 | F23: =INDEX(Spec_Rack!$C$33:$G$33,F$6) -> 1400 | G23: =INDEX(Spec_Rack!$C$33:$G$33,G$6) -> 1800 | H23: =INDEX(Spec_Rack!$C$33:$G$33,H$6) -> 1400 | I23: =INDEX(Spec_Rack!$C$33:$G$33,I$6) -> 1800 | J23: =INDEX(Spec_Rack!$C$33:$G$33,J$6) -> 1400 | ... AH23: =INDEX(Spec_Rack!$C$33:$G$33,AH$6) -> 1400
A24: HBM 存取能量 | B24: pJ/B | C24: =INDEX(Spec_Rack!$C$34:$G$34,C$6) -> 20 | D24: =INDEX(Spec_Rack!$C$34:$G$34,D$6) -> 25 | E24: =INDEX(Spec_Rack!$C$34:$G$34,E$6) -> 20 | F24: =INDEX(Spec_Rack!$C$34:$G$34,F$6) -> 25 | G24: =INDEX(Spec_Rack!$C$34:$G$34,G$6) -> 20 | H24: =INDEX(Spec_Rack!$C$34:$G$34,H$6) -> 25 | I24: =INDEX(Spec_Rack!$C$34:$G$34,I$6) -> 20 | J24: =INDEX(Spec_Rack!$C$34:$G$34,J$6) -> 25 | ... AH24: =INDEX(Spec_Rack!$C$34:$G$34,AH$6) -> 25
A25: 每 GW 機架數（功率情境） | B25: 架 | C25: =INDEX(DC_Cost!$C$12:$Q$12,3*(C$6-1)+2)/CTL_GW -> 4052 | D25: =INDEX(DC_Cost!$C$12:$Q$12,3*(D$6-1)+2)/CTL_GW -> 6764 | E25: =INDEX(DC_Cost!$C$12:$Q$12,3*(E$6-1)+2)/CTL_GW -> 4052 | F25: =INDEX(DC_Cost!$C$12:$Q$12,3*(F$6-1)+2)/CTL_GW -> 6764 | G25: =INDEX(DC_Cost!$C$12:$Q$12,3*(G$6-1)+2)/CTL_GW -> 4052 | H25: =INDEX(DC_Cost!$C$12:$Q$12,3*(H$6-1)+2)/CTL_GW -> 6764 | I25: =INDEX(DC_Cost!$C$12:$Q$12,3*(I$6-1)+2)/CTL_GW -> 4052 | J25: =INDEX(DC_Cost!$C$12:$Q$12,3*(J$6-1)+2)/CTL_GW -> 6764 | ... AH25: =INDEX(DC_Cost!$C$12:$Q$12,3*(AH$6-1)+2)/CTL_GW -> 6764
A26: 每架配電設計功率 | B26: kW | C26: =INDEX(DC_Cost!$C$11:$Q$11,3*(C$6-1)+2) -> 227 | D26: =INDEX(DC_Cost!$C$11:$Q$11,3*(D$6-1)+2) -> 136 | E26: =INDEX(DC_Cost!$C$11:$Q$11,3*(E$6-1)+2) -> 227 | F26: =INDEX(DC_Cost!$C$11:$Q$11,3*(F$6-1)+2) -> 136 | G26: =INDEX(DC_Cost!$C$11:$Q$11,3*(G$6-1)+2) -> 227 | H26: =INDEX(DC_Cost!$C$11:$Q$11,3*(H$6-1)+2) -> 136 | I26: =INDEX(DC_Cost!$C$11:$Q$11,3*(I$6-1)+2) -> 227 | J26: =INDEX(DC_Cost!$C$11:$Q$11,3*(J$6-1)+2) -> 136 | ... AH26: =INDEX(DC_Cost!$C$11:$Q$11,3*(AH$6-1)+2) -> 136
A27: B. 架構（連結 Arch；啟用參數與非專家／專家參數已乘模型規模倍數 ARCH_ScaleGen，基準＝1；D1(c)，v6.2）
A28: 啟用參數 | B28: B | C28: =INDEX(Arch!$C$7:$E$7,C$7)*INDEX(ARCH_ScaleGen,1,C$6) -> 49 | D28: =INDEX(Arch!$C$7:$E$7,D$7)*INDEX(ARCH_ScaleGen,1,D$6) -> 49 | E28: =INDEX(Arch!$C$7:$E$7,E$7)*INDEX(ARCH_ScaleGen,1,E$6) -> 49 | F28: =INDEX(Arch!$C$7:$E$7,F$7)*INDEX(ARCH_ScaleGen,1,F$6) -> 49 | G28: =INDEX(Arch!$C$7:$E$7,G$7)*INDEX(ARCH_ScaleGen,1,G$6) -> 49 | H28: =INDEX(Arch!$C$7:$E$7,H$7)*INDEX(ARCH_ScaleGen,1,H$6) -> 49 | I28: =INDEX(Arch!$C$7:$E$7,I$7)*INDEX(ARCH_ScaleGen,1,I$6) -> 49 | J28: =INDEX(Arch!$C$7:$E$7,J$7)*INDEX(ARCH_ScaleGen,1,J$6) -> 49 | ... AH28: =INDEX(Arch!$C$7:$E$7,AH$7)*INDEX(ARCH_ScaleGen,1,AH$6) -> 180
A29: 層數 | B29: 層 | C29: =INDEX(Arch!$C$8:$E$8,C$7) -> 61 | D29: =INDEX(Arch!$C$8:$E$8,D$7) -> 61 | E29: =INDEX(Arch!$C$8:$E$8,E$7) -> 61 | F29: =INDEX(Arch!$C$8:$E$8,F$7) -> 61 | G29: =INDEX(Arch!$C$8:$E$8,G$7) -> 61 | H29: =INDEX(Arch!$C$8:$E$8,H$7) -> 61 | I29: =INDEX(Arch!$C$8:$E$8,I$7) -> 61 | J29: =INDEX(Arch!$C$8:$E$8,J$7) -> 61 | ... AH29: =INDEX(Arch!$C$8:$E$8,AH$7) -> 100
A30: d_model | C30: =INDEX(Arch!$C$9:$E$9,C$7) -> 7168 | D30: =INDEX(Arch!$C$9:$E$9,D$7) -> 7168 | E30: =INDEX(Arch!$C$9:$E$9,E$7) -> 7168 | F30: =INDEX(Arch!$C$9:$E$9,F$7) -> 7168 | G30: =INDEX(Arch!$C$9:$E$9,G$7) -> 7168 | H30: =INDEX(Arch!$C$9:$E$9,H$7) -> 7168 | I30: =INDEX(Arch!$C$9:$E$9,I$7) -> 7168 | J30: =INDEX(Arch!$C$9:$E$9,J$7) -> 7168 | ... AH30: =INDEX(Arch!$C$9:$E$9,AH$7) -> 12288
A31: 啟用 routed experts | C31: =INDEX(Arch!$C$13:$E$13,C$7) -> 6 | D31: =INDEX(Arch!$C$13:$E$13,D$7) -> 6 | E31: =INDEX(Arch!$C$13:$E$13,E$7) -> 6 | F31: =INDEX(Arch!$C$13:$E$13,F$7) -> 6 | G31: =INDEX(Arch!$C$13:$E$13,G$7) -> 6 | H31: =INDEX(Arch!$C$13:$E$13,H$7) -> 6 | I31: =INDEX(Arch!$C$13:$E$13,I$7) -> 6 | J31: =INDEX(Arch!$C$13:$E$13,J$7) -> 6 | ... AH31: =INDEX(Arch!$C$13:$E$13,AH$7) -> 16
A32: 非專家參數 | B32: B | C32: =INDEX(Arch!$C$28:$E$28,C$7)*INDEX(ARCH_ScaleGen,1,C$6) -> 20.277778 | D32: =INDEX(Arch!$C$28:$E$28,D$7)*INDEX(ARCH_ScaleGen,1,D$6) -> 20.277778 | E32: =INDEX(Arch!$C$28:$E$28,E$7)*INDEX(ARCH_ScaleGen,1,E$6) -> 20.277778 | F32: =INDEX(Arch!$C$28:$E$28,F$7)*INDEX(ARCH_ScaleGen,1,F$6) -> 20.277778 | G32: =INDEX(Arch!$C$28:$E$28,G$7)*INDEX(ARCH_ScaleGen,1,G$6) -> 20.277778 | H32: =INDEX(Arch!$C$28:$E$28,H$7)*INDEX(ARCH_ScaleGen,1,H$6) -> 20.277778 | I32: =INDEX(Arch!$C$28:$E$28,I$7)*INDEX(ARCH_ScaleGen,1,I$6) -> 20.277778 | J32: =INDEX(Arch!$C$28:$E$28,J$7)*INDEX(ARCH_ScaleGen,1,J$6) -> 20.277778 | ... AH32: =INDEX(Arch!$C$28:$E$28,AH$7)*INDEX(ARCH_ScaleGen,1,AH$6) -> 49.072581
A33: 專家參數 | B33: B | C33: =INDEX(Arch!$C$29:$E$29,C$7)*INDEX(ARCH_ScaleGen,1,C$6) -> 1579.7222 | D33: =INDEX(Arch!$C$29:$E$29,D$7)*INDEX(ARCH_ScaleGen,1,D$6) -> 1579.7222 | E33: =INDEX(Arch!$C$29:$E$29,E$7)*INDEX(ARCH_ScaleGen,1,E$6) -> 1579.7222 | F33: =INDEX(Arch!$C$29:$E$29,F$7)*INDEX(ARCH_ScaleGen,1,F$6) -> 1579.7222 | G33: =INDEX(Arch!$C$29:$E$29,G$7)*INDEX(ARCH_ScaleGen,1,G$6) -> 1579.7222 | H33: =INDEX(Arch!$C$29:$E$29,H$7)*INDEX(ARCH_ScaleGen,1,H$6) -> 1579.7222 | I33: =INDEX(Arch!$C$29:$E$29,I$7)*INDEX(ARCH_ScaleGen,1,I$6) -> 1579.7222 | J33: =INDEX(Arch!$C$29:$E$29,J$7)*INDEX(ARCH_ScaleGen,1,J$6) -> 1579.7222 | ... AH33: =INDEX(Arch!$C$29:$E$29,AH$7)*INDEX(ARCH_ScaleGen,1,AH$6) -> 3950.9274
A34: KV bytes/token（含 H_KV） | B34: B | C34: =INDEX(Arch!$C$25:$E$25,C$7)*C11 -> 3965 | D34: =INDEX(Arch!$C$25:$E$25,D$7)*D11 -> 3965 | E34: =INDEX(Arch!$C$25:$E$25,E$7)*E11 -> 3965 | F34: =INDEX(Arch!$C$25:$E$25,F$7)*F11 -> 3965 | G34: =INDEX(Arch!$C$25:$E$25,G$7)*G11 -> 3965 | H34: =INDEX(Arch!$C$25:$E$25,H$7)*H11 -> 3965 | I34: =INDEX(Arch!$C$25:$E$25,I$7)*I11 -> 3965 | J34: =INDEX(Arch!$C$25:$E$25,J$7)*J11 -> 3965 | ... AB34: =INDEX(Arch!$C$25:$E$25,AB$7)*AB11 -> 3965 | AC34: =Arch!$E$21 -> 14976 | AD34: =Arch!$E$21 -> 14976 | AE34: =Arch!$E$22 -> 57600 | AF34: =Arch!$E$22 -> 57600 | AG34: =Arch!$E$23 -> 204800 | AH34: =Arch!$E$23 -> 204800
A35: 注意力 FLOPs／被注意 token | B35: FLOP | C35: =INDEX(Arch!$C$30:$E$30,C$7) -> 15990784 | D35: =INDEX(Arch!$C$30:$E$30,D$7) -> 15990784 | E35: =INDEX(Arch!$C$30:$E$30,E$7) -> 15990784 | F35: =INDEX(Arch!$C$30:$E$30,F$7) -> 15990784 | G35: =INDEX(Arch!$C$30:$E$30,G$7) -> 15990784 | H35: =INDEX(Arch!$C$30:$E$30,H$7) -> 15990784 | I35: =INDEX(Arch!$C$30:$E$30,I$7) -> 15990784 | J35: =INDEX(Arch!$C$30:$E$30,J$7) -> 15990784 | ... AH35: =INDEX(Arch!$C$30:$E$30,AH$7) -> 4915200
A36: 全注意力層比例 | B36: % | C36: =INDEX(Arch!$C$16:$E$16,C$7) -> 0.492 | D36: =INDEX(Arch!$C$16:$E$16,D$7) -> 0.492 | E36: =INDEX(Arch!$C$16:$E$16,E$7) -> 0.492 | F36: =INDEX(Arch!$C$16:$E$16,F$7) -> 0.492 | G36: =INDEX(Arch!$C$16:$E$16,G$7) -> 0.492 | H36: =INDEX(Arch!$C$16:$E$16,H$7) -> 0.492 | I36: =INDEX(Arch!$C$16:$E$16,I$7) -> 0.492 | J36: =INDEX(Arch!$C$16:$E$16,J$7) -> 0.492 | ... AH36: =INDEX(Arch!$C$16:$E$16,AH$7) -> 1
A37: 全注意力跨度上限 | B37: tok | C37: =INDEX(Arch!$C$17:$E$17,C$7) -> 4224 | D37: =INDEX(Arch!$C$17:$E$17,D$7) -> 4224 | E37: =INDEX(Arch!$C$17:$E$17,E$7) -> 4224 | F37: =INDEX(Arch!$C$17:$E$17,F$7) -> 4224 | G37: =INDEX(Arch!$C$17:$E$17,G$7) -> 4224 | H37: =INDEX(Arch!$C$17:$E$17,H$7) -> 4224 | I37: =INDEX(Arch!$C$17:$E$17,I$7) -> 4224 | J37: =INDEX(Arch!$C$17:$E$17,J$7) -> 4224 | ... AH37: =INDEX(Arch!$C$17:$E$17,AH$7) -> 0
A38: 其他層壓縮比 | B38: x | C38: =INDEX(Arch!$C$18:$E$18,C$7) -> 128 | D38: =INDEX(Arch!$C$18:$E$18,D$7) -> 128 | E38: =INDEX(Arch!$C$18:$E$18,E$7) -> 128 | F38: =INDEX(Arch!$C$18:$E$18,F$7) -> 128 | G38: =INDEX(Arch!$C$18:$E$18,G$7) -> 128 | H38: =INDEX(Arch!$C$18:$E$18,H$7) -> 128 | I38: =INDEX(Arch!$C$18:$E$18,I$7) -> 128 | J38: =INDEX(Arch!$C$18:$E$18,J$7) -> 128 | ... AH38: =INDEX(Arch!$C$18:$E$18,AH$7) -> 1
A39: 其他層滑動窗 | B39: tok | C39: =INDEX(Arch!$C$19:$E$19,C$7) -> 128 | D39: =INDEX(Arch!$C$19:$E$19,D$7) -> 128 | E39: =INDEX(Arch!$C$19:$E$19,E$7) -> 128 | F39: =INDEX(Arch!$C$19:$E$19,F$7) -> 128 | G39: =INDEX(Arch!$C$19:$E$19,G$7) -> 128 | H39: =INDEX(Arch!$C$19:$E$19,H$7) -> 128 | I39: =INDEX(Arch!$C$19:$E$19,I$7) -> 128 | J39: =INDEX(Arch!$C$19:$E$19,J$7) -> 128 | ... AH39: =INDEX(Arch!$C$19:$E$19,AH$7) -> 0
A40: C. 服務、SLO 與校準參數
A41: SLO：每用戶 decode 速度下限 | B41: tok/s | C41: =INDEX(Serving!$C$21:$E$21,C$7) -> 43.311661 | D41: =INDEX(Serving!$C$21:$E$21,D$7) -> 43.311661 | E41: =INDEX(Serving!$C$21:$E$21,E$7) -> 43.311661 | F41: =INDEX(Serving!$C$21:$E$21,F$7) -> 43.311661 | G41: =INDEX(Serving!$C$21:$E$21,G$7) -> 43.311661 | H41: =INDEX(Serving!$C$21:$E$21,H$7) -> 43.311661 | I41: =INDEX(Serving!$C$21:$E$21,I$7) -> 43.311661 | J41: =INDEX(Serving!$C$21:$E$21,J$7) -> 43.311661 | ... N41: =INDEX(Serving!$C$21:$E$21,N$7) -> 43.311661 | O41: 40 | P41: 40 | Q41: 100 | R41: 100 | S41: =INDEX(Serving!$C$21:$E$21,S$7) -> 43.311661 | T41: =INDEX(Serving!$C$21:$E$21,T$7) -> 43.311661 | U41: =INDEX(Serving!$C$21:$E$21,U$7) -> 43.311661 | V41: =INDEX(Serving!$C$21:$E$21,V$7) -> 43.311661 | W41: =INDEX(Serving!$C$21:$E$21,W$7) -> 43.311661 | X41: =INDEX(Serving!$C$21:$E$21,X$7) -> 43.311661 | Y41: =INDEX(Serving!$C$21:$E$21,Y$7) -> 43.311661 | Z41: =INDEX(Serving!$C$21:$E$21,Z$7) -> 43.311661 | ... AH41: =INDEX(Serving!$C$21:$E$21,AH$7) -> 40.83136
A42: TTFT 上限 | B42: s | C42: =INDEX(Serving!$C$22:$E$22,C$7) -> 3 | D42: =INDEX(Serving!$C$22:$E$22,D$7) -> 3 | E42: =INDEX(Serving!$C$22:$E$22,E$7) -> 3 | F42: =INDEX(Serving!$C$22:$E$22,F$7) -> 3 | G42: =INDEX(Serving!$C$22:$E$22,G$7) -> 3 | H42: =INDEX(Serving!$C$22:$E$22,H$7) -> 3 | I42: =INDEX(Serving!$C$22:$E$22,I$7) -> 3 | J42: =INDEX(Serving!$C$22:$E$22,J$7) -> 3 | ... AH42: =INDEX(Serving!$C$22:$E$22,AH$7) -> 5
A43: 參考 ISL | B43: tok | C43: =INDEX(Serving!$C$23:$E$23,C$7) -> 16384 | D43: =INDEX(Serving!$C$23:$E$23,D$7) -> 16384 | E43: =INDEX(Serving!$C$23:$E$23,E$7) -> 16384 | F43: =INDEX(Serving!$C$23:$E$23,F$7) -> 16384 | G43: =INDEX(Serving!$C$23:$E$23,G$7) -> 16384 | H43: =INDEX(Serving!$C$23:$E$23,H$7) -> 16384 | I43: =INDEX(Serving!$C$23:$E$23,I$7) -> 16384 | J43: =INDEX(Serving!$C$23:$E$23,J$7) -> 16384 | ... V43: =INDEX(Serving!$C$23:$E$23,V$7) -> 16384 | W43: 4096 | X43: 4096 | Y43: 65536 | Z43: 65536 | AA43: =INDEX(Serving!$C$23:$E$23,AA$7) -> 16384 | AB43: =INDEX(Serving!$C$23:$E$23,AB$7) -> 16384 | AC43: =INDEX(Serving!$C$23:$E$23,AC$7) -> 32768 | AD43: =INDEX(Serving!$C$23:$E$23,AD$7) -> 32768 | AE43: =INDEX(Serving!$C$23:$E$23,AE$7) -> 32768 | AF43: =INDEX(Serving!$C$23:$E$23,AF$7) -> 32768 | AG43: =INDEX(Serving!$C$23:$E$23,AG$7) -> 32768 | AH43: =INDEX(Serving!$C$23:$E$23,AH$7) -> 32768
A44: 參考 OSL（含思考） | B44: tok | C44: =INDEX(Serving!$C$24:$E$24,C$7) -> 2048 | D44: =INDEX(Serving!$C$24:$E$24,D$7) -> 2048 | E44: =INDEX(Serving!$C$24:$E$24,E$7) -> 2048 | F44: =INDEX(Serving!$C$24:$E$24,F$7) -> 2048 | G44: =INDEX(Serving!$C$24:$E$24,G$7) -> 2048 | H44: =INDEX(Serving!$C$24:$E$24,H$7) -> 2048 | I44: =INDEX(Serving!$C$24:$E$24,I$7) -> 2048 | J44: =INDEX(Serving!$C$24:$E$24,J$7) -> 2048 | ... AH44: =INDEX(Serving!$C$24:$E$24,AH$7) -> 4096
A45: decode 平均上下文 | B45: tok | C45: =C43+C44/2 -> 17408 | D45: =D43+D44/2 -> 17408 | E45: =E43+E44/2 -> 17408 | F45: =F43+F44/2 -> 17408 | G45: =G43+G44/2 -> 17408 | H45: =H43+H44/2 -> 17408 | I45: =I43+I44/2 -> 17408 | J45: =J43+J44/2 -> 17408 | ... AH45: =AH43+AH44/2 -> 34816
A46: prefill 平均位置 | B46: tok | C46: =C43/2 -> 8192 | D46: =D43/2 -> 8192 | E46: =E43/2 -> 8192 | F46: =F43/2 -> 8192 | G46: =G43/2 -> 8192 | H46: =H43/2 -> 8192 | I46: =I43/2 -> 8192 | J46: =J43/2 -> 8192 | ... AH46: =AH43/2 -> 16384
A47: MTP 草稿數 | B47: tok | C47: =Serving!$C$6 -> 3 | D47: =Serving!$C$6 -> 3 | E47: =Serving!$C$6 -> 3 | F47: =Serving!$C$6 -> 3 | G47: =Serving!$C$6 -> 3 | H47: =Serving!$C$6 -> 3 | I47: =Serving!$C$6 -> 3 | J47: =Serving!$C$6 -> 3 | ... AH47: =Serving!$C$6 -> 3
A48: 草稿接受率 | B48: % | C48: =Serving!$C$7 -> 0.7 | D48: =Serving!$C$7 -> 0.7 | E48: =Serving!$C$7 -> 0.7 | F48: =Serving!$C$7 -> 0.7 | G48: =Serving!$C$7 -> 0.7 | H48: =Serving!$C$7 -> 0.7 | I48: =Serving!$C$7 -> 0.7 | J48: =Serving!$C$7 -> 0.7 | ... R48: =Serving!$C$7 -> 0.7 | S48: 0.6 | T48: 0.6 | U48: 0.8 | V48: 0.8 | W48: =Serving!$C$7 -> 0.7 | X48: =Serving!$C$7 -> 0.7 | Y48: =Serving!$C$7 -> 0.7 | Z48: =Serving!$C$7 -> 0.7 | AA48: =Serving!$C$7 -> 0.7 | AB48: =Serving!$C$7 -> 0.7 | AC48: =Serving!$C$7 -> 0.7 | AD48: =Serving!$C$7 -> 0.7 | ... AH48: =Serving!$C$7 -> 0.7
A49: 每步期望接受 token | B49: tok | C49: =(1-C48^(C47+1))/(1-C48) -> 2.533 | D49: =(1-D48^(D47+1))/(1-D48) -> 2.533 | E49: =(1-E48^(E47+1))/(1-E48) -> 2.533 | F49: =(1-F48^(F47+1))/(1-F48) -> 2.533 | G49: =(1-G48^(G47+1))/(1-G48) -> 2.533 | H49: =(1-H48^(H47+1))/(1-H48) -> 2.533 | I49: =(1-I48^(I47+1))/(1-I48) -> 2.533 | J49: =(1-J48^(J47+1))/(1-J48) -> 2.533 | ... AH49: =(1-AH48^(AH47+1))/(1-AH48) -> 2.533
A50: 實測→生產效率折減 | B50: x | C50: =Serving!$C$18 -> 1 | D50: =Serving!$C$18 -> 1 | E50: =Serving!$C$18 -> 1 | F50: =Serving!$C$18 -> 1 | G50: =Serving!$C$18 -> 1 | H50: =Serving!$C$18 -> 1 | I50: =Serving!$C$18 -> 1 | J50: =Serving!$C$18 -> 1 | ... Z50: =Serving!$C$18 -> 1 | AA50: 0.7 | AB50: 0.7 | AC50: =Serving!$C$18 -> 1 | AD50: =Serving!$C$18 -> 1 | AE50: =Serving!$C$18 -> 1 | AF50: =Serving!$C$18 -> 1 | AG50: =Serving!$C$18 -> 1 | AH50: =Serving!$C$18 -> 1
A51: η_p（prefill 占峰值；含折減） | B51: % | C51: =INDEX(Calib!$C$72:$G$72,C$6)*C50 -> 0.3 | D51: =INDEX(Calib!$C$72:$G$72,D$6)*D50 -> 0.3 | E51: =INDEX(Calib!$C$72:$G$72,E$6)*E50 -> 0.3 | F51: =INDEX(Calib!$C$72:$G$72,F$6)*F50 -> 0.3 | G51: =INDEX(Calib!$C$72:$G$72,G$6)*G50 -> 0.3 | H51: =INDEX(Calib!$C$72:$G$72,H$6)*H50 -> 0.3 | I51: =INDEX(Calib!$C$72:$G$72,I$6)*I50 -> 0.3 | J51: =INDEX(Calib!$C$72:$G$72,J$6)*J50 -> 0.3 | ... AH51: =INDEX(Calib!$C$72:$G$72,AH$6)*AH50 -> 0.3
A52: η_d 倍數（Tech_Registry H_ETAD；Sens_Perf 情境覆寫） | B52: x | C52: =Tech_Registry!$E$20 -> 1 | D52: =Tech_Registry!$E$20 -> 1 | E52: 0.5 | F52: =Tech_Registry!$E$20 -> 1 | G52: 1.5 | H52: =Tech_Registry!$E$20 -> 1 | I52: =Tech_Registry!$E$20 -> 1 | J52: =Tech_Registry!$E$20 -> 1 | K52: =Tech_Registry!$E$20 -> 1 | L52: =Tech_Registry!$E$20 -> 1 | M52: =Tech_Registry!$E$20 -> 1 | N52: =Tech_Registry!$E$20 -> 1 | O52: =Tech_Registry!$E$20 -> 1 | ... AH52: =Tech_Registry!$E$20 -> 1
A53: η_d（decode 每序列算力效率；含折減） | B53: % | C53: =INDEX(Calib!$C$70:$G$70,C$6)*C52*C50 -> 0.035755033 | D53: =INDEX(Calib!$C$70:$G$70,D$6)*D52*D50 -> 0.035755033 | E53: =INDEX(Calib!$C$70:$G$70,E$6)*E52*E50 -> 0.017877517 | F53: =INDEX(Calib!$C$70:$G$70,F$6)*F52*F50 -> 0.035755033 | G53: =INDEX(Calib!$C$70:$G$70,G$6)*G52*G50 -> 0.05363255 | H53: =INDEX(Calib!$C$70:$G$70,H$6)*H52*H50 -> 0.035755033 | I53: =INDEX(Calib!$C$70:$G$70,I$6)*I52*I50 -> 0.035755033 | J53: =INDEX(Calib!$C$70:$G$70,J$6)*J52*J50 -> 0.035755033 | ... AH53: =INDEX(Calib!$C$70:$G$70,AH$6)*AH52*AH50 -> 0.035755033
A54: 每層延遲倍數（Tech_Registry H_TL；Sens_Perf 情境覆寫） | B54: x | C54: =Tech_Registry!$E$21 -> 1 | D54: =Tech_Registry!$E$21 -> 1 | E54: =Tech_Registry!$E$21 -> 1 | F54: =Tech_Registry!$E$21 -> 1 | G54: =Tech_Registry!$E$21 -> 1 | H54: =Tech_Registry!$E$21 -> 1 | I54: 0.7 | J54: =Tech_Registry!$E$21 -> 1 | K54: 1.5 | L54: =Tech_Registry!$E$21 -> 1 | M54: =Tech_Registry!$E$21 -> 1 | N54: =Tech_Registry!$E$21 -> 1 | O54: =Tech_Registry!$E$21 -> 1 | P54: =Tech_Registry!$E$21 -> 1 | Q54: =Tech_Registry!$E$21 -> 1 | R54: =Tech_Registry!$E$21 -> 1 | S54: =Tech_Registry!$E$21 -> 1 | ... AH54: =Tech_Registry!$E$21 -> 1
A55: 每層每次前向固定延遲（含折減） | B55: µs | C55: =INDEX(Calib!$C$71:$G$71,C$6)*C54/C50 -> 161.18534 | D55: =INDEX(Calib!$C$71:$G$71,D$6)*D54/D50 -> 161.18534 | E55: =INDEX(Calib!$C$71:$G$71,E$6)*E54/E50 -> 161.18534 | F55: =INDEX(Calib!$C$71:$G$71,F$6)*F54/F50 -> 161.18534 | G55: =INDEX(Calib!$C$71:$G$71,G$6)*G54/G50 -> 161.18534 | H55: =INDEX(Calib!$C$71:$G$71,H$6)*H54/H50 -> 161.18534 | I55: =INDEX(Calib!$C$71:$G$71,I$6)*I54/I50 -> 112.82974 | J55: =INDEX(Calib!$C$71:$G$71,J$6)*J54/J50 -> 161.18534 | ... AH55: =INDEX(Calib!$C$71:$G$71,AH$6)*AH54/AH50 -> 161.18534
A56: HBM 保留比例 | B56: % | C56: =Serving!$C$9 -> 0.1 | D56: =Serving!$C$9 -> 0.1 | E56: =Serving!$C$9 -> 0.1 | F56: =Serving!$C$9 -> 0.1 | G56: =Serving!$C$9 -> 0.1 | H56: =Serving!$C$9 -> 0.1 | I56: =Serving!$C$9 -> 0.1 | J56: =Serving!$C$9 -> 0.1 | ... AH56: =Serving!$C$9 -> 0.1
A57: 非專家權重占 HBM 上限 | B57: % | C57: =Serving!$C$10 -> 0.2 | D57: =Serving!$C$10 -> 0.2 | E57: =Serving!$C$10 -> 0.2 | F57: =Serving!$C$10 -> 0.2 | G57: =Serving!$C$10 -> 0.2 | H57: =Serving!$C$10 -> 0.2 | I57: =Serving!$C$10 -> 0.2 | J57: =Serving!$C$10 -> 0.2 | ... AH57: =Serving!$C$10 -> 0.2
A58: 專家權重占 HBM 上限 | B58: % | C58: =Serving!$C$11 -> 0.4 | D58: =Serving!$C$11 -> 0.4 | E58: =Serving!$C$11 -> 0.4 | F58: =Serving!$C$11 -> 0.4 | G58: =Serving!$C$11 -> 0.4 | H58: =Serving!$C$11 -> 0.4 | I58: =Serving!$C$11 -> 0.4 | J58: =Serving!$C$11 -> 0.4 | ... AH58: =Serving!$C$11 -> 0.4
A59: EP 啟用值 bytes/元素 | B59: B | C59: =Serving!$C$12 -> 3 | D59: =Serving!$C$12 -> 3 | E59: =Serving!$C$12 -> 3 | F59: =Serving!$C$12 -> 3 | G59: =Serving!$C$12 -> 3 | H59: =Serving!$C$12 -> 3 | I59: =Serving!$C$12 -> 3 | J59: =Serving!$C$12 -> 3 | ... AH59: =Serving!$C$12 -> 3
A60: KV 讀取效率 | B60: % | C60: =Serving!$C$13 -> 0.7 | D60: =Serving!$C$13 -> 0.7 | E60: =Serving!$C$13 -> 0.7 | F60: =Serving!$C$13 -> 0.7 | G60: =Serving!$C$13 -> 0.7 | H60: =Serving!$C$13 -> 0.7 | I60: =Serving!$C$13 -> 0.7 | J60: =Serving!$C$13 -> 0.7 | ... AH60: =Serving!$C$13 -> 0.7
A61: EP 通訊效率 | B61: % | C61: =Serving!$C$14 -> 0.7 | D61: =Serving!$C$14 -> 0.7 | E61: =Serving!$C$14 -> 0.7 | F61: =Serving!$C$14 -> 0.7 | G61: =Serving!$C$14 -> 0.7 | H61: =Serving!$C$14 -> 0.7 | I61: =Serving!$C$14 -> 0.7 | J61: =Serving!$C$14 -> 0.7 | ... AH61: =Serving!$C$14 -> 0.7
A62: 快取載入頻寬 | B62: TB/s | C62: =Serving!$C$15 -> 0.1 | D62: =Serving!$C$15 -> 0.1 | E62: =Serving!$C$15 -> 0.1 | F62: =Serving!$C$15 -> 0.1 | G62: =Serving!$C$15 -> 0.1 | H62: =Serving!$C$15 -> 0.1 | I62: =Serving!$C$15 -> 0.1 | J62: =Serving!$C$15 -> 0.1 | ... AH62: =Serving!$C$15 -> 0.1
A63: D. 每 token 計算量
A64: decode 被注意 token 數 | B64: tok | C64: =C36*IF(C37=0,C45,MIN(C45,C37))+(1-C36)*(C45/C38+C39) -> 2212.32 | D64: =D36*IF(D37=0,D45,MIN(D45,D37))+(1-D36)*(D45/D38+D39) -> 2212.32 | E64: =E36*IF(E37=0,E45,MIN(E45,E37))+(1-E36)*(E45/E38+E39) -> 2212.32 | F64: =F36*IF(F37=0,F45,MIN(F45,F37))+(1-F36)*(F45/F38+F39) -> 2212.32 | G64: =G36*IF(G37=0,G45,MIN(G45,G37))+(1-G36)*(G45/G38+G39) -> 2212.32 | H64: =H36*IF(H37=0,H45,MIN(H45,H37))+(1-H36)*(H45/H38+H39) -> 2212.32 | I64: =I36*IF(I37=0,I45,MIN(I45,I37))+(1-I36)*(I45/I38+I39) -> 2212.32 | J64: =J36*IF(J37=0,J45,MIN(J45,J37))+(1-J36)*(J45/J38+J39) -> 2212.32 | ... AH64: =AH36*IF(AH37=0,AH45,MIN(AH45,AH37))+(1-AH36)*(AH45/AH38+AH39) -> 34816
A65: decode FLOPs/token | B65: GFLOP | C65: =(2*C28*1000000000+C35*C64)*C10/1000000000 -> 133.37673 | D65: =(2*D28*1000000000+D35*D64)*D10/1000000000 -> 133.37673 | E65: =(2*E28*1000000000+E35*E64)*E10/1000000000 -> 133.37673 | F65: =(2*F28*1000000000+F35*F64)*F10/1000000000 -> 133.37673 | G65: =(2*G28*1000000000+G35*G64)*G10/1000000000 -> 133.37673 | H65: =(2*H28*1000000000+H35*H64)*H10/1000000000 -> 133.37673 | I65: =(2*I28*1000000000+I35*I64)*I10/1000000000 -> 133.37673 | J65: =(2*J28*1000000000+J35*J64)*J10/1000000000 -> 133.37673 | ... AH65: =(2*AH28*1000000000+AH35*AH64)*AH10/1000000000 -> 531.1276
A66: prefill 被注意 token 數 | B66: tok | C66: =C36*IF(C37=0,C46,MIN(C46,C37))+(1-C36)*(C46/C38+C39) -> 2175.744 | D66: =D36*IF(D37=0,D46,MIN(D46,D37))+(1-D36)*(D46/D38+D39) -> 2175.744 | E66: =E36*IF(E37=0,E46,MIN(E46,E37))+(1-E36)*(E46/E38+E39) -> 2175.744 | F66: =F36*IF(F37=0,F46,MIN(F46,F37))+(1-F36)*(F46/F38+F39) -> 2175.744 | G66: =G36*IF(G37=0,G46,MIN(G46,G37))+(1-G36)*(G46/G38+G39) -> 2175.744 | H66: =H36*IF(H37=0,H46,MIN(H46,H37))+(1-H36)*(H46/H38+H39) -> 2175.744 | I66: =I36*IF(I37=0,I46,MIN(I46,I37))+(1-I36)*(I46/I38+I39) -> 2175.744 | J66: =J36*IF(J37=0,J46,MIN(J46,J37))+(1-J36)*(J46/J38+J39) -> 2175.744 | ... AH66: =AH36*IF(AH37=0,AH46,MIN(AH46,AH37))+(1-AH36)*(AH46/AH38+AH39) -> 16384
A67: prefill FLOPs/token | B67: GFLOP | C67: =(2*C28*1000000000+C35*C66)*C10/1000000000 -> 132.79185 | D67: =(2*D28*1000000000+D35*D66)*D10/1000000000 -> 132.79185 | E67: =(2*E28*1000000000+E35*E66)*E10/1000000000 -> 132.79185 | F67: =(2*F28*1000000000+F35*F66)*F10/1000000000 -> 132.79185 | G67: =(2*G28*1000000000+G35*G66)*G10/1000000000 -> 132.79185 | H67: =(2*H28*1000000000+H35*H66)*H10/1000000000 -> 132.79185 | I67: =(2*I28*1000000000+I35*I66)*I10/1000000000 -> 132.79185 | J67: =(2*J28*1000000000+J35*J66)*J10/1000000000 -> 132.79185 | ... AH67: =(2*AH28*1000000000+AH35*AH66)*AH10/1000000000 -> 440.53064
A68: E. 記憶體配置（attention DP＋wide EP；每 GPU）
A69: 可用 HBM | B69: GB | C69: =C15*(1-C56) -> 259.2 | D69: =D15*(1-D56) -> 259.2 | E69: =E15*(1-E56) -> 259.2 | F69: =F15*(1-F56) -> 259.2 | G69: =G15*(1-G56) -> 259.2 | H69: =H15*(1-H56) -> 259.2 | I69: =I15*(1-I56) -> 259.2 | J69: =J15*(1-J56) -> 259.2 | ... AH69: =AH15*(1-AH56) -> 259.2
A70: 注意力 TP 度（自動） | C70: =MAX(1,CEILING(C32*C20/(C57*C69),1)) -> 1 | D70: =MAX(1,CEILING(D32*D20/(D57*D69),1)) -> 1 | E70: =MAX(1,CEILING(E32*E20/(E57*E69),1)) -> 1 | F70: =MAX(1,CEILING(F32*F20/(F57*F69),1)) -> 1 | G70: =MAX(1,CEILING(G32*G20/(G57*G69),1)) -> 1 | H70: =MAX(1,CEILING(H32*H20/(H57*H69),1)) -> 1 | I70: =MAX(1,CEILING(I32*I20/(I57*I69),1)) -> 1 | J70: =MAX(1,CEILING(J32*J20/(J57*J69),1)) -> 1 | ... AH70: =MAX(1,CEILING(AH32*AH20/(AH57*AH69),1)) -> 1
A71: decode EP 寬度（自動） | B71: GPU | C71: =MAX(C18,CEILING(C33*C19/(C58*C69),1)) -> 32 | D71: =MAX(D18,CEILING(D33*D19/(D58*D69),1)) -> 32 | E71: =MAX(E18,CEILING(E33*E19/(E58*E69),1)) -> 32 | F71: =MAX(F18,CEILING(F33*F19/(F58*F69),1)) -> 32 | G71: =MAX(G18,CEILING(G33*G19/(G58*G69),1)) -> 32 | H71: =MAX(H18,CEILING(H33*H19/(H58*H69),1)) -> 32 | I71: =MAX(I18,CEILING(I33*I19/(I58*I69),1)) -> 32 | J71: =MAX(J18,CEILING(J33*J19/(J58*J69),1)) -> 32 | ... AH71: =MAX(AH18,CEILING(AH33*AH19/(AH58*AH69),1)) -> 32
A72: 每 GPU 權重 | B72: GB | C72: =C32*C20/C70+C33*C19/C71 -> 48.046332 | D72: =D32*D20/D70+D33*D19/D71 -> 48.046332 | E72: =E32*E20/E70+E33*E19/E71 -> 48.046332 | F72: =F32*F20/F70+F33*F19/F71 -> 48.046332 | G72: =G32*G20/G70+G33*G19/G71 -> 48.046332 | H72: =H32*H20/H70+H33*H19/H71 -> 48.046332 | I72: =I32*I20/I70+I33*I19/I71 -> 48.046332 | J72: =J32*J20/J70+J33*J19/J71 -> 48.046332 | ... AH72: =AH32*AH20/AH70+AH33*AH19/AH71 -> 118.52248
A73: 權重占可用 HBM | B73: % | C73: =C72/C69 -> 0.18536394 | D73: =D72/D69 -> 0.18536394 | E73: =E72/E69 -> 0.18536394 | F73: =F72/F69 -> 0.18536394 | G73: =G72/G69 -> 0.18536394 | H73: =H72/H69 -> 0.18536394 | I73: =I72/I69 -> 0.18536394 | J73: =J72/J69 -> 0.18536394 | ... AH73: =AH72/AH69 -> 0.45726264
A74: F. Prefill（算力受限）
A75: prefill tok/s（每 prefill GPU） | B75: tok/s | C75: =C51*C14*1000000000000000/(C67*1000000000) -> 79071.116 | D75: =D51*D14*1000000000000000/(D67*1000000000) -> 33887.621 | E75: =E51*E14*1000000000000000/(E67*1000000000) -> 79071.116 | F75: =F51*F14*1000000000000000/(F67*1000000000) -> 33887.621 | G75: =G51*G14*1000000000000000/(G67*1000000000) -> 79071.116 | H75: =H51*H14*1000000000000000/(H67*1000000000) -> 33887.621 | I75: =I51*I14*1000000000000000/(I67*1000000000) -> 79071.116 | J75: =J51*J14*1000000000000000/(J67*1000000000) -> 33887.621 | ... AH75: =AH51*AH14*1000000000000000/(AH67*1000000000) -> 10214.954
A76: TTFT（計算部分；v9.0 D9：prefill 只計新鮮輸入 ISL × (1 − B4_CacheHit)；快取命中後新鮮 token 位於序列後段，本式（prefill 平均位置取整段 ISL 的一半）略低估 prefill 時間；v10.0 N4） | B76: s | C76: =(C43*(1-B4_CacheHit))*C67*1000000000/(C51*C14*1000000000000000*C21) -> 0.023310661 | D76: =(D43*(1-B4_CacheHit))*D67*1000000000/(D51*D14*1000000000000000*D21) -> 0.054391543 | E76: =(E43*(1-B4_CacheHit))*E67*1000000000/(E51*E14*1000000000000000*E21) -> 0.023310661 | F76: =(F43*(1-B4_CacheHit))*F67*1000000000/(F51*F14*1000000000000000*F21) -> 0.054391543 | G76: =(G43*(1-B4_CacheHit))*G67*1000000000/(G51*G14*1000000000000000*G21) -> 0.023310661 | H76: =(H43*(1-B4_CacheHit))*H67*1000000000/(H51*H14*1000000000000000*H21) -> 0.054391543 | I76: =(I43*(1-B4_CacheHit))*I67*1000000000/(I51*I14*1000000000000000*I21) -> 0.023310661 | J76: =(J43*(1-B4_CacheHit))*J67*1000000000/(J51*J14*1000000000000000*J21) -> 0.054391543 | ... AH76: =(AH43*(1-B4_CacheHit))*AH67*1000000000/(AH51*AH14*1000000000000000*AH21) -> 0.3608827
A77: TTFT 符合上限 | C77: =IF(C76<=C42,"是","否") -> 是 | D77: =IF(D76<=D42,"是","否") -> 是 | E77: =IF(E76<=E42,"是","否") -> 是 | F77: =IF(F76<=F42,"是","否") -> 是 | G77: =IF(G76<=G42,"是","否") -> 是 | H77: =IF(H76<=H42,"是","否") -> 是 | I77: =IF(I76<=I42,"是","否") -> 是 | J77: =IF(J76<=J42,"是","否") -> 是 | ... AH77: =IF(AH76<=AH42,"是","否") -> 是
A78: G. Decode：每步時間＝固定延遲＋B × 每序列時間；B* ＝ min(SLO 上限, HBM 容量上限)
A79: 每步固定延遲（權重讀取＋逐層延遲） | B79: ms | C79: =C72/C16+(C29+C47)*C55/1000 -> 12.499786 | D79: =D72/D16+(D29+D47)*D55/1000 -> 16.321653 | E79: =E72/E16+(E29+E47)*E55/1000 -> 12.499786 | F79: =F72/F16+(F29+F47)*F55/1000 -> 16.321653 | G79: =G72/G16+(G29+G47)*G55/1000 -> 12.499786 | H79: =H72/H16+(H29+H47)*H55/1000 -> 16.321653 | I79: =I72/I16+(I29+I47)*I55/1000 -> 9.4050274 | J79: =J72/J16+(J29+J47)*J55/1000 -> 16.321653 | ... AH79: =AH72/AH16+(AH29+AH47)*AH55/1000 -> 31.417399
A80: 每序列每步 — 算力項 | B80: ms | C80: =(C47+1)*C65/(C14*C53)/1000 -> 0.42631914 | D80: =(D47+1)*D65/(D14*D53)/1000 -> 0.99474465 | E80: =(E47+1)*E65/(E14*E53)/1000 -> 0.85263827 | F80: =(F47+1)*F65/(F14*F53)/1000 -> 0.99474465 | G80: =(G47+1)*G65/(G14*G53)/1000 -> 0.28421276 | H80: =(H47+1)*H65/(H14*H53)/1000 -> 0.99474465 | I80: =(I47+1)*I65/(I14*I53)/1000 -> 0.42631914 | J80: =(J47+1)*J65/(J14*J53)/1000 -> 0.99474465 | ... AH80: =(AH47+1)*AH65/(AH14*AH53)/1000 -> 3.9612332
A81: 每序列每步 — KV 讀取項 | B81: ms | C81: =C34*C45/(C16*C60)/1000000000 -> 0.0044819948 | D81: =D34*D45/(D16*D60)/1000000000 -> 0.012325486 | E81: =E34*E45/(E16*E60)/1000000000 -> 0.0044819948 | F81: =F34*F45/(F16*F60)/1000000000 -> 0.012325486 | G81: =G34*G45/(G16*G60)/1000000000 -> 0.0044819948 | H81: =H34*H45/(H16*H60)/1000000000 -> 0.012325486 | I81: =I34*I45/(I16*I60)/1000000000 -> 0.0044819948 | J81: =J34*J45/(J16*J60)/1000000000 -> 0.012325486 | ... AH81: =AH34*AH45/(AH16*AH60)/1000000000 -> 1.2732709
A82: 每序列每步 — EP 通訊項 | B82: ms | C82: =(C47+1)*C29*C31*C30*C59*(C71-1)/C71/(C17*C61)/1000000000 -> 0.0242048 | D82: =(D47+1)*D29*D31*D30*D59*(D71-1)/D71/(D17*D61)/1000000000 -> 0.0484096 | E82: =(E47+1)*E29*E31*E30*E59*(E71-1)/E71/(E17*E61)/1000000000 -> 0.0242048 | F82: =(F47+1)*F29*F31*F30*F59*(F71-1)/F71/(F17*F61)/1000000000 -> 0.0484096 | G82: =(G47+1)*G29*G31*G30*G59*(G71-1)/G71/(G17*G61)/1000000000 -> 0.0242048 | H82: =(H47+1)*H29*H31*H30*H59*(H71-1)/H71/(H17*H61)/1000000000 -> 0.0484096 | I82: =(I47+1)*I29*I31*I30*I59*(I71-1)/I71/(I17*I61)/1000000000 -> 0.0242048 | J82: =(J47+1)*J29*J31*J30*J59*(J71-1)/J71/(J17*J61)/1000000000 -> 0.0484096 | ... AH82: =(AH47+1)*AH29*AH31*AH30*AH59*(AH71-1)/AH71/(AH17*AH61)/1000000000 -> 0.36278857
A83: 每序列每步（取最大，假設三者可重疊） | B83: ms | C83: =MAX(C80,C81,C82) -> 0.42631914 | D83: =MAX(D80,D81,D82) -> 0.99474465 | E83: =MAX(E80,E81,E82) -> 0.85263827 | F83: =MAX(F80,F81,F82) -> 0.99474465 | G83: =MAX(G80,G81,G82) -> 0.28421276 | H83: =MAX(H80,H81,H82) -> 0.99474465 | I83: =MAX(I80,I81,I82) -> 0.42631914 | J83: =MAX(J80,J81,J82) -> 0.99474465 | ... AH83: =MAX(AH80,AH81,AH82) -> 3.9612332
A84: 每序列綁定項 | C84: =IF(C83=C80,"算力",IF(C83=C81,"KV 頻寬","EP 通訊")) -> 算力 | D84: =IF(D83=D80,"算力",IF(D83=D81,"KV 頻寬","EP 通訊")) -> 算力 | E84: =IF(E83=E80,"算力",IF(E83=E81,"KV 頻寬","EP 通訊")) -> 算力 | F84: =IF(F83=F80,"算力",IF(F83=F81,"KV 頻寬","EP 通訊")) -> 算力 | G84: =IF(G83=G80,"算力",IF(G83=G81,"KV 頻寬","EP 通訊")) -> 算力 | H84: =IF(H83=H80,"算力",IF(H83=H81,"KV 頻寬","EP 通訊")) -> 算力 | I84: =IF(I83=I80,"算力",IF(I83=I81,"KV 頻寬","EP 通訊")) -> 算力 | J84: =IF(J83=J80,"算力",IF(J83=J81,"KV 頻寬","EP 通訊")) -> 算力 | ... AH84: =IF(AH83=AH80,"算力",IF(AH83=AH81,"KV 頻寬","EP 通訊")) -> 算力
A85: SLO 允許的批次上限 | B85: 序列/GPU | C85: =(1000*C49/C41-C79)/C83 -> 107.86124 | D85: =(1000*D49/D41-D79)/D83 -> 42.384185 | E85: =(1000*E49/E41-E79)/E83 -> 53.930618 | F85: =(1000*F49/F41-F79)/F83 -> 42.384185 | G85: =(1000*G49/G41-G79)/G83 -> 161.79185 | H85: =(1000*H49/H41-H79)/H83 -> 42.384185 | I85: =(1000*I49/I41-I79)/I83 -> 115.12049 | J85: =(1000*J49/J41-J79)/J83 -> 42.384185 | ... AH85: =(1000*AH49/AH41-AH79)/AH83 -> 7.7294744
A86: HBM 容量允許的批次上限 | B86: 序列/GPU | C86: =(C69-C72)*1000000000/(C34*C45) -> 3059.1908 | D86: =(D69-D72)*1000000000/(D34*D45) -> 3059.1908 | E86: =(E69-E72)*1000000000/(E34*E45) -> 3059.1908 | F86: =(F69-F72)*1000000000/(F34*F45) -> 3059.1908 | G86: =(G69-G72)*1000000000/(G34*G45) -> 3059.1908 | H86: =(H69-H72)*1000000000/(H34*H45) -> 3059.1908 | I86: =(I69-I72)*1000000000/(I34*I45) -> 3059.1908 | J86: =(J69-J72)*1000000000/(J34*J45) -> 3059.1908 | ... AH86: =(AH69-AH72)*1000000000/(AH34*AH45) -> 19.729491
A87: 採用批次 B* | B87: 序列/GPU | C87: =MAX(0,MIN(C85,C86)) -> 107.86124 | D87: =MAX(0,MIN(D85,D86)) -> 42.384185 | E87: =MAX(0,MIN(E85,E86)) -> 53.930618 | F87: =MAX(0,MIN(F85,F86)) -> 42.384185 | G87: =MAX(0,MIN(G85,G86)) -> 161.79185 | H87: =MAX(0,MIN(H85,H86)) -> 42.384185 | I87: =MAX(0,MIN(I85,I86)) -> 115.12049 | J87: =MAX(0,MIN(J85,J86)) -> 42.384185 | ... AH87: =MAX(0,MIN(AH85,AH86)) -> 7.7294744
A88: decode tok/s（每 decode GPU） | B88: tok/s | C88: =IF(C87>0,C87*C49/((C79+C87*C83)/1000),0) -> 4671.6493 | D88: =IF(D87>0,D87*D49/((D79+D87*D83)/1000),0) -> 1835.7295 | E88: =IF(E87>0,E87*E49/((E79+E87*E83)/1000),0) -> 2335.8247 | F88: =IF(F87>0,F87*F49/((F79+F87*F83)/1000),0) -> 1835.7295 | G88: =IF(G87>0,G87*G49/((G79+G87*G83)/1000),0) -> 7007.474 | H88: =IF(H87>0,H87*H49/((H79+H87*H83)/1000),0) -> 1835.7295 | I88: =IF(I87>0,I87*I49/((I79+I87*I83)/1000),0) -> 4986.0596 | J88: =IF(J87>0,J87*J49/((J79+J87*J83)/1000),0) -> 1835.7295 | ... AH88: =IF(AH87>0,AH87*AH49/((AH79+AH87*AH83)/1000),0) -> 315.60495
A89: 實際每用戶速度 | B89: tok/s | C89: =IF(C87>0,C49/((C79+C87*C83)/1000),0) -> 43.311661 | D89: =IF(D87>0,D49/((D79+D87*D83)/1000),0) -> 43.311661 | E89: =IF(E87>0,E49/((E79+E87*E83)/1000),0) -> 43.311661 | F89: =IF(F87>0,F49/((F79+F87*F83)/1000),0) -> 43.311661 | G89: =IF(G87>0,G49/((G79+G87*G83)/1000),0) -> 43.311661 | H89: =IF(H87>0,H49/((H79+H87*H83)/1000),0) -> 43.311661 | I89: =IF(I87>0,I49/((I79+I87*I83)/1000),0) -> 43.311661 | J89: =IF(J87>0,J49/((J79+J87*J83)/1000),0) -> 43.311661 | ... AH89: =IF(AH87>0,AH49/((AH79+AH87*AH83)/1000),0) -> 40.83136
A90: 綁定約束（文字「SLO 不可達」＝decode 不可達；「TTFT 不可達」＝首 token 時間超過上限；兩者皆不符時顯示 SLO；v6.2） | C90: =IF(C87<=0,"SLO 不可達",IF(C77<>"是","TTFT 不可達",IF(C85<=C86,"SLO（"&C84&"）","HBM 容量"))) -> SLO（算力） | D90: =IF(D87<=0,"SLO 不可達",IF(D77<>"是","TTFT 不可達",IF(D85<=D86,"SLO（"&D84&"）","HBM 容量"))) -> SLO（算力） | E90: =IF(E87<=0,"SLO 不可達",IF(E77<>"是","TTFT 不可達",IF(E85<=E86,"SLO（"&E84&"）","HBM 容量"))) -> SLO（算力） | F90: =IF(F87<=0,"SLO 不可達",IF(F77<>"是","TTFT 不可達",IF(F85<=F86,"SLO（"&F84&"）","HBM 容量"))) -> SLO（算力） | G90: =IF(G87<=0,"SLO 不可達",IF(G77<>"是","TTFT 不可達",IF(G85<=G86,"SLO（"&G84&"）","HBM 容量"))) -> SLO（算力） | H90: =IF(H87<=0,"SLO 不可達",IF(H77<>"是","TTFT 不可達",IF(H85<=H86,"SLO（"&H84&"）","HBM 容量"))) -> SLO（算力） | I90: =IF(I87<=0,"SLO 不可達",IF(I77<>"是","TTFT 不可達",IF(I85<=I86,"SLO（"&I84&"）","HBM 容量"))) -> SLO（算力） | J90: =IF(J87<=0,"SLO 不可達",IF(J77<>"是","TTFT 不可達",IF(J85<=J86,"SLO（"&J84&"）","HBM 容量"))) -> SLO（算力） | ... AH90: =IF(AH87<=0,"SLO 不可達",IF(AH77<>"是","TTFT 不可達",IF(AH85<=AH86,"SLO（"&AH84&"）","HBM 容量"))) -> SLO（算力）
A91: KV 占可用 HBM | B91: % | C91: =C87*C34*C45/1000000000/C69 -> 0.028722515 | D91: =D87*D34*D45/1000000000/D69 -> 0.011286542 | E91: =E87*E34*E45/1000000000/E69 -> 0.014361258 | F91: =F87*F34*F45/1000000000/F69 -> 0.011286542 | G91: =G87*G34*G45/1000000000/G69 -> 0.043083773 | H91: =H87*H34*H45/1000000000/H69 -> 0.011286542 | I91: =I87*I34*I45/1000000000/I69 -> 0.030655591 | J91: =J87*J34*J45/1000000000/J69 -> 0.011286542 | ... AH91: =AH87*AH34*AH45/1000000000/AH69 -> 0.21262963
A92: H. 每架與每 GW（參考任務；P:D 依工作量配比；100% 利用率）
A93: 每請求 GPU 秒（文字「SLO 不可達」＝decode 不可達；「TTFT 不可達」＝首 token 時間超過上限；兩者皆不符時顯示 SLO；v6.0 D8、v6.2；v9.0 D9：prefill 只計新鮮輸入 ISL × (1 − B4_CacheHit)） | B93: GPU-s | C93: =IF(ISNUMBER(C88),IF(C88>0,IF(C77="是",(C43*(1-B4_CacheHit))/C75+C44/C88,"TTFT 不可達"),"SLO 不可達"),"SLO 不可達") -> 0.53163171 | D93: =IF(ISNUMBER(D88),IF(D88>0,IF(D77="是",(D43*(1-B4_CacheHit))/D75+D44/D88,"TTFT 不可達"),"SLO 不可達"),"SLO 不可達") -> 1.333199 | E93: =IF(ISNUMBER(E88),IF(E88>0,IF(E77="是",(E43*(1-B4_CacheHit))/E75+E44/E88,"TTFT 不可達"),"SLO 不可達"),"SLO 不可達") -> 0.97002078 | F93: =IF(ISNUMBER(F88),IF(F88>0,IF(F77="是",(F43*(1-B4_CacheHit))/F75+F44/F88,"TTFT 不可達"),"SLO 不可達"),"SLO 不可達") -> 1.333199 | G93: =IF(ISNUMBER(G88),IF(G88>0,IF(G77="是",(G43*(1-B4_CacheHit))/G75+G44/G88,"TTFT 不可達"),"SLO 不可達"),"SLO 不可達") -> 0.38550202 | H93: =IF(ISNUMBER(H88),IF(H88>0,IF(H77="是",(H43*(1-B4_CacheHit))/H75+H44/H88,"TTFT 不可達"),"SLO 不可達"),"SLO 不可達") -> 1.333199 | I93: =IF(ISNUMBER(I88),IF(I88>0,IF(I77="是",(I43*(1-B4_CacheHit))/I75+I44/I88,"TTFT 不可達"),"SLO 不可達"),"SLO 不可達") -> 0.50398783 | J93: =IF(ISNUMBER(J88),IF(J88>0,IF(J77="是",(J43*(1-B4_CacheHit))/J75+J44/J88,"TTFT 不可達"),"SLO 不可達"),"SLO 不可達") -> 1.333199 | ... AH93: =IF(ISNUMBER(AH88),IF(AH88>0,IF(AH77="是",(AH43*(1-B4_CacheHit))/AH75+AH44/AH88,"TTFT 不可達"),"SLO 不可達"),"SLO 不可達") -> 14.421781
A94: prefill GPU 占比 | B94: % | C94: =IF(ISNUMBER(C93),IF(C93>0,((C43*(1-B4_CacheHit))/C75)/C93,0),C93) -> 0.17538955 | D94: =IF(ISNUMBER(D93),IF(D93>0,((D43*(1-B4_CacheHit))/D75)/D93,0),D93) -> 0.16319107 | E94: =IF(ISNUMBER(E93),IF(E93>0,((E43*(1-B4_CacheHit))/E75)/E93,0),E93) -> 0.096124378 | F94: =IF(ISNUMBER(F93),IF(F93>0,((F43*(1-B4_CacheHit))/F75)/F93,0),F93) -> 0.16319107 | G94: =IF(ISNUMBER(G93),IF(G93>0,((G43*(1-B4_CacheHit))/G75)/G93,0),G93) -> 0.24187329 | H94: =IF(ISNUMBER(H93),IF(H93>0,((H43*(1-B4_CacheHit))/H75)/H93,0),H93) -> 0.16319107 | I94: =IF(ISNUMBER(I93),IF(I93>0,((I43*(1-B4_CacheHit))/I75)/I93,0),I93) -> 0.18500971 | J94: =IF(ISNUMBER(J93),IF(J93>0,((J43*(1-B4_CacheHit))/J75)/J93,0),J93) -> 0.16319107 | ... AH94: =IF(ISNUMBER(AH93),IF(AH93>0,((AH43*(1-B4_CacheHit))/AH75)/AH93,0),AH93) -> 0.1000938
A95: 每架總 tok/s | B95: tok/s | C95: =IF(ISNUMBER(C93),IF(C93>0,C22*(C43+C44)/C93,0),C93) -> 2496284.5 | D95: =IF(ISNUMBER(D93),IF(D93>0,D22*(D43+D44)/D93,0),D93) -> 995428.32 | E95: =IF(ISNUMBER(E93),IF(E93>0,E22*(E43+E44)/E93,0),E93) -> 1368119.1 | F95: =IF(ISNUMBER(F93),IF(F93>0,F22*(F43+F44)/F93,0),F93) -> 995428.32 | G95: =IF(ISNUMBER(G93),IF(G93>0,G22*(G43+G44)/G93,0),G93) -> 3442534.5 | H95: =IF(ISNUMBER(H93),IF(H93>0,H22*(H43+H44)/H93,0),H93) -> 995428.32 | I95: =IF(ISNUMBER(I93),IF(I93>0,I22*(I43+I44)/I93,0),I93) -> 2633206.4 | J95: =IF(ISNUMBER(J93),IF(J93>0,J22*(J43+J44)/J93,0),J93) -> 995428.32 | ... AH95: =IF(ISNUMBER(AH93),IF(AH93>0,AH22*(AH43+AH44)/AH93,0),AH93) -> 184041.63
A96: 每架 decode tok/s | B96: tok/s | C96: =IF(ISNUMBER(C95),C95*C44/(C43+C44),C95) -> 277364.94 | D96: =IF(ISNUMBER(D95),D95*D44/(D43+D44),D95) -> 110603.15 | E96: =IF(ISNUMBER(E95),E95*E44/(E43+E44),E95) -> 152013.24 | F96: =IF(ISNUMBER(F95),F95*F44/(F43+F44),F95) -> 110603.15 | G96: =IF(ISNUMBER(G95),G95*G44/(G43+G44),G95) -> 382503.83 | H96: =IF(ISNUMBER(H95),H95*H44/(H43+H44),H95) -> 110603.15 | I96: =IF(ISNUMBER(I95),I95*I44/(I43+I44),I95) -> 292578.49 | J96: =IF(ISNUMBER(J95),J95*J44/(J43+J44),J95) -> 110603.15 | ... AH96: =IF(ISNUMBER(AH95),AH95*AH44/(AH43+AH44),AH95) -> 20449.07
A97: 每架 prefill tok/s | B97: tok/s | C97: =IF(ISNUMBER(C95),C95-C96,C95) -> 2218919.5 | D97: =IF(ISNUMBER(D95),D95-D96,D95) -> 884825.17 | E97: =IF(ISNUMBER(E95),E95-E96,E95) -> 1216105.9 | F97: =IF(ISNUMBER(F95),F95-F96,F95) -> 884825.17 | G97: =IF(ISNUMBER(G95),G95-G96,G95) -> 3060030.6 | H97: =IF(ISNUMBER(H95),H95-H96,H95) -> 884825.17 | I97: =IF(ISNUMBER(I95),I95-I96,I95) -> 2340627.9 | J97: =IF(ISNUMBER(J95),J95-J96,J95) -> 884825.17 | ... AH97: =IF(ISNUMBER(AH95),AH95-AH96,AH95) -> 163592.56
A98: 每 GW 總產出 | B98: M tok/年 | C98: =IF(ISNUMBER(C95),C95*C25*8760*3600/1000000,C95) -> 3.189849e+11 | D98: =IF(ISNUMBER(D95),D95*D25*8760*3600/1000000,D95) -> 2.1233432e+11 | E98: =IF(ISNUMBER(E95),E95*E25*8760*3600/1000000,E95) -> 1.7482356e+11 | F98: =IF(ISNUMBER(F95),F95*F25*8760*3600/1000000,F95) -> 2.1233432e+11 | G98: =IF(ISNUMBER(G95),G95*G25*8760*3600/1000000,G95) -> 4.3990038e+11 | H98: =IF(ISNUMBER(H95),H95*H25*8760*3600/1000000,H95) -> 2.1233432e+11 | I98: =IF(ISNUMBER(I95),I95*I25*8760*3600/1000000,I95) -> 3.3648131e+11 | J98: =IF(ISNUMBER(J95),J95*J25*8760*3600/1000000,J95) -> 2.1233432e+11 | ... AH98: =IF(ISNUMBER(AH95),AH95*AH25*8760*3600/1000000,AH95) -> 3.9257828e+10
A99: 每 GW decode 產出 | B99: M tok/年 | C99: =IF(ISNUMBER(C96),C96*C25*8760*3600/1000000,C96) -> 3.5442766e+10 | D99: =IF(ISNUMBER(D96),D96*D25*8760*3600/1000000,D96) -> 2.3592702e+10 | E99: =IF(ISNUMBER(E96),E96*E25*8760*3600/1000000,E96) -> 1.942484e+10 | F99: =IF(ISNUMBER(F96),F96*F25*8760*3600/1000000,F96) -> 2.3592702e+10 | G99: =IF(ISNUMBER(G96),G96*G25*8760*3600/1000000,G96) -> 4.887782e+10 | H99: =IF(ISNUMBER(H96),H96*H25*8760*3600/1000000,H96) -> 2.3592702e+10 | I99: =IF(ISNUMBER(I96),I96*I25*8760*3600/1000000,I96) -> 3.7386813e+10 | J99: =IF(ISNUMBER(J96),J96*J25*8760*3600/1000000,J96) -> 2.3592702e+10 | ... AH99: =IF(ISNUMBER(AH96),AH96*AH25*8760*3600/1000000,AH96) -> 4.3619809e+09
A100: I. 每 M token GPU 秒（供 Unit_Cost）與速覽成本
A101: 新鮮 prefill | B101: GPU-s/M | C101: =1000000/C75 -> 12.646843 | D101: =1000000/D75 -> 29.509301 | E101: =1000000/E75 -> 12.646843 | F101: =1000000/F75 -> 29.509301 | G101: =1000000/G75 -> 12.646843 | H101: =1000000/H75 -> 29.509301 | I101: =1000000/I75 -> 12.646843 | J101: =1000000/J75 -> 29.509301 | ... AH101: =1000000/AH75 -> 97.895697
...

Sheet Unit_Cost
A1: Unit_Cost — 每 M token 成本（世代 × 成本情境；依層級分區；新鮮 prefill／快取 prefill／decode）
A2: 成本＝每 GPU 小時持有成本（DC_Cost）× 每 M token GPU 秒（Perf）。思考 token 在物理上與可見輸出同為 decode，成本相同，差異只在計費（Block 4）。100% 為理想上限；基準利用率版＝100% 版 ÷ 利用率。快取命中只計 KV 載入 GPU 時間，未計儲存成本
R3: 用途
A4: 世代 | C4: =DC_Cost!C4 -> Hopper H100 | D4: =DC_Cost!D4 -> Hopper H100 | E4: =DC_Cost!E4 -> Hopper H100 | F4: =DC_Cost!F4 -> GB200 NVL72 | G4: =DC_Cost!G4 -> GB200 NVL72 | H4: =DC_Cost!H4 -> GB200 NVL72 | I4: =DC_Cost!I4 -> GB300 NVL72 | J4: =DC_Cost!J4 -> GB300 NVL72 | ... Q4: =DC_Cost!Q4 -> Rubin Ultra（MGX NVL 單架，72 GPU） | R4: 複本讀取：C4:Q4（被 Sens_／_Prod 複本頁讀取，不是死格）
A5: 成本情境 | C5: =DC_Cost!C5 -> 低成本 | D5: =DC_Cost!D5 -> 基準 | E5: =DC_Cost!E5 -> 高成本 | F5: =DC_Cost!F5 -> 低成本 | G5: =DC_Cost!G5 -> 基準 | H5: =DC_Cost!H5 -> 高成本 | I5: =DC_Cost!I5 -> 低成本 | J5: =DC_Cost!J5 -> 基準 | ... Q5: =DC_Cost!Q5 -> 高成本 | R5: 複本讀取：C5:Q5（被 Sens_／_Prod 複本頁讀取，不是死格）
A6: 世代索引 | C6: 1 | D6: 1 | E6: 1 | F6: 2 | G6: 2 | H6: 2 | I6: 3 | J6: 3 | K6: 3 | L6: 4 | M6: 4 | N6: 4 | O6: 5 | P6: 5 | Q6: 5
A7: 共用
A8: 每 GPU 小時持有成本 — 經濟 | B8: $/GPU-hr | C8: =DC_Cost!C58 -> 1.0796449 | D8: =DC_Cost!D58 -> 1.5425965 | E8: =DC_Cost!E58 -> 2.6492057 | F8: =DC_Cost!F58 -> 1.5042281 | G8: =DC_Cost!G58 -> 2.008461 | H8: =DC_Cost!H58 -> 3.2575623 | I8: =DC_Cost!I58 -> 1.9757439 | J8: =DC_Cost!J58 -> 2.5517876 | ... Q8: =DC_Cost!Q58 -> 16.42945
A9: 每 GPU 小時持有成本 — 會計 | B9: $/GPU-hr | C9: =DC_Cost!C57 -> 0.82510666 | D9: =DC_Cost!D57 -> 1.1294128 | E9: =DC_Cost!E57 -> 1.9406797 | F9: =DC_Cost!F57 -> 1.1487952 | G9: =DC_Cost!G57 -> 1.467227 | H9: =DC_Cost!H57 -> 2.3705216 | I9: =DC_Cost!I57 -> 1.5174202 | J9: =DC_Cost!J57 -> 1.8728472 | ... Q9: =DC_Cost!Q57 -> 12.232844
A10: 基準利用率 | B10: % | C10: =Serving!$C$17 -> 0.6 | D10: =Serving!$C$17 -> 0.6 | E10: =Serving!$C$17 -> 0.6 | F10: =Serving!$C$17 -> 0.6 | G10: =Serving!$C$17 -> 0.6 | H10: =Serving!$C$17 -> 0.6 | I10: =Serving!$C$17 -> 0.6 | J10: =Serving!$C$17 -> 0.6 | ... Q10: =Serving!$C$17 -> 0.6 | R10: 顯示用：C10:Q10（同表其他世代／層級欄）
A12: Luna（低層）
A13: GPU 秒／M 新鮮 prefill | B13: GPU-s | C13: =INDEX(Perf!$C$101:$Q$101,3*(C$6-1)+1) -> 128.95118 | D13: =INDEX(Perf!$C$101:$Q$101,3*(D$6-1)+1) -> 128.95118 | E13: =INDEX(Perf!$C$101:$Q$101,3*(E$6-1)+1) -> 128.95118 | F13: =INDEX(Perf!$C$101:$Q$101,3*(F$6-1)+1) -> 12.753272 | G13: =INDEX(Perf!$C$101:$Q$101,3*(G$6-1)+1) -> 12.753272 | H13: =INDEX(Perf!$C$101:$Q$101,3*(H$6-1)+1) -> 12.753272 | I13: =INDEX(Perf!$C$101:$Q$101,3*(I$6-1)+1) -> 8.5021814 | J13: =INDEX(Perf!$C$101:$Q$101,3*(J$6-1)+1) -> 8.5021814 | ... Q13: =INDEX(Perf!$C$101:$Q$101,3*(Q$6-1)+1) -> 1.821896
A14: GPU 秒／M 快取命中 prefill | B14: GPU-s | C14: =INDEX(Perf!$C$102:$Q$102,3*(C$6-1)+1) -> 0.02795 | D14: =INDEX(Perf!$C$102:$Q$102,3*(D$6-1)+1) -> 0.02795 | E14: =INDEX(Perf!$C$102:$Q$102,3*(E$6-1)+1) -> 0.02795 | F14: =INDEX(Perf!$C$102:$Q$102,3*(F$6-1)+1) -> 0.02795 | G14: =INDEX(Perf!$C$102:$Q$102,3*(G$6-1)+1) -> 0.02795 | H14: =INDEX(Perf!$C$102:$Q$102,3*(H$6-1)+1) -> 0.02795 | I14: =INDEX(Perf!$C$102:$Q$102,3*(I$6-1)+1) -> 0.02795 | J14: =INDEX(Perf!$C$102:$Q$102,3*(J$6-1)+1) -> 0.02795 | ... Q14: =INDEX(Perf!$C$102:$Q$102,3*(Q$6-1)+1) -> 0.02795
A15: GPU 秒／M decode（含思考 token；文字「SLO 不可達」＝不可達） | B15: GPU-s | C15: =INDEX(Perf!$C$103:$Q$103,3*(C$6-1)+1) -> 1351.7113 | D15: =INDEX(Perf!$C$103:$Q$103,3*(D$6-1)+1) -> 1351.7113 | E15: =INDEX(Perf!$C$103:$Q$103,3*(E$6-1)+1) -> 1351.7113 | F15: =INDEX(Perf!$C$103:$Q$103,3*(F$6-1)+1) -> 240.79135 | G15: =INDEX(Perf!$C$103:$Q$103,3*(G$6-1)+1) -> 240.79135 | H15: =INDEX(Perf!$C$103:$Q$103,3*(H$6-1)+1) -> 240.79135 | I15: =INDEX(Perf!$C$103:$Q$103,3*(I$6-1)+1) -> 160.52757 | J15: =INDEX(Perf!$C$103:$Q$103,3*(J$6-1)+1) -> 160.52757 | ... Q15: =INDEX(Perf!$C$103:$Q$103,3*(Q$6-1)+1) -> 32.796176
A16: 新鮮 prefill $/M — 經濟、100% | B16: $/M | C16: =C$8/3600*C13 -> 0.038672634 | D16: =D$8/3600*D13 -> 0.055255459 | E16: =E$8/3600*E13 -> 0.094893946 | F16: =F$8/3600*F13 -> 0.0053288419 | G16: =G$8/3600*G13 -> 0.0071151249 | H16: =H$8/3600*H13 -> 0.011540161 | I16: =I$8/3600*I13 -> 0.0046661481 | J16: =J$8/3600*J13 -> 0.0060266003 | ... Q16: =Q$8/3600*Q13 -> 0.0083146526
A17: 快取命中 prefill $/M — 經濟、100% | B17: $/M | C17: =C$8/3600*C14 -> 8.3822427e-06 | D17: =D$8/3600*D14 -> 1.1976548e-05 | E17: =E$8/3600*E14 -> 2.0568138e-05 | F17: =F$8/3600*F14 -> 1.167866e-05 | G17: =G$8/3600*G14 -> 1.5593468e-05 | H17: =H$8/3600*H14 -> 2.5291352e-05 | I17: =I$8/3600*I14 -> 1.5339456e-05 | J17: =J$8/3600*J14 -> 1.9811795e-05 | ... Q17: =Q$8/3600*Q14 -> 0.00012755642
A18: decode（含思考 token）$/M — 經濟、100% | B18: $/M | C18: =IF(ISNUMBER(C15),C$8/3600*C15,"SLO 不可達") -> 0.40538005 | D18: =IF(ISNUMBER(D15),D$8/3600*D15,"SLO 不可達") -> 0.579207 | E18: =IF(ISNUMBER(E15),E$8/3600*E15,"SLO 不可達") -> 0.99471146 | F18: =IF(ISNUMBER(F15),F$8/3600*F15,"SLO 不可達") -> 0.10061254 | G18: =IF(ISNUMBER(G15),G$8/3600*G15,"SLO 不可達") -> 0.1343389 | H18: =IF(ISNUMBER(H15),H$8/3600*H15,"SLO 不可達") -> 0.2178869 | I18: =IF(ISNUMBER(I15),I$8/3600*I15,"SLO 不可達") -> 0.088100381 | J18: =IF(ISNUMBER(J15),J$8/3600*J15,"SLO 不可達") -> 0.11378674 | ... Q18: =IF(ISNUMBER(Q15),Q$8/3600*Q15,"SLO 不可達") -> 0.14967309
A19: 新鮮 prefill $/M — 經濟、基準利用率 | B19: $/M | C19: =C16/C$10 -> 0.06445439 | D19: =D16/D$10 -> 0.092092431 | E19: =E16/E$10 -> 0.15815658 | F19: =F16/F$10 -> 0.0088814032 | G19: =G16/G$10 -> 0.011858542 | H19: =H16/H$10 -> 0.019233601 | I19: =I16/I$10 -> 0.0077769135 | J19: =J16/J$10 -> 0.010044334 | ... Q19: =Q16/Q$10 -> 0.013857754 | R19: 顯示用：C19:Q19（同表其他世代／層級欄）
A20: 快取命中 prefill $/M — 經濟、基準利用率 | B20: $/M | C20: =C17/C$10 -> 1.3970405e-05 | D20: =D17/D$10 -> 1.9960914e-05 | E20: =E17/E$10 -> 3.4280231e-05 | F20: =F17/F$10 -> 1.9464434e-05 | G20: =G17/G$10 -> 2.5989113e-05 | H20: =H17/H$10 -> 4.2152253e-05 | I20: =I17/I$10 -> 2.556576e-05 | J20: =J17/J$10 -> 3.3019659e-05 | ... Q20: =Q17/Q$10 -> 0.00021259404 | R20: 顯示用：C20:Q20（同表其他世代／層級欄）
A21: decode（含思考 token）$/M — 經濟、基準利用率 | B21: $/M | C21: =IF(ISNUMBER(C18),C18/C$10,C18) -> 0.67563342 | D21: =IF(ISNUMBER(D18),D18/D$10,D18) -> 0.96534501 | E21: =IF(ISNUMBER(E18),E18/E$10,E18) -> 1.6578524 | F21: =IF(ISNUMBER(F18),F18/F$10,F18) -> 0.16768756 | G21: =IF(ISNUMBER(G18),G18/G$10,G18) -> 0.22389817 | H21: =IF(ISNUMBER(H18),H18/H$10,H18) -> 0.36314483 | I21: =IF(ISNUMBER(I18),I18/I$10,I18) -> 0.14683397 | J21: =IF(ISNUMBER(J18),J18/J$10,J18) -> 0.18964457 | ... Q21: =IF(ISNUMBER(Q18),Q18/Q$10,Q18) -> 0.24945515 | R21: 顯示用：C21:Q21（同表其他世代／層級欄）
A22: decode（含思考 token）$/M — 會計、100% | B22: $/M | C22: =IF(ISNUMBER(C15),C$9/3600*C15,"SLO 不可達") -> 0.30980722 | D22: =IF(ISNUMBER(D15),D$9/3600*D15,"SLO 不可達") -> 0.42406667 | E22: =IF(ISNUMBER(E15),E$9/3600*E15,"SLO 不可達") -> 0.72867744 | F22: =IF(ISNUMBER(F15),F$9/3600*F15,"SLO 不可達") -> 0.076838874 | G22: =IF(ISNUMBER(G15),G$9/3600*G15,"SLO 不可達") -> 0.098137663 | H22: =IF(ISNUMBER(H15),H$9/3600*H15,"SLO 不可達") -> 0.15855586 | I22: =IF(ISNUMBER(I15),I$9/3600*I15,"SLO 不可達") -> 0.06766327 | J22: =IF(ISNUMBER(J15),J$9/3600*J15,"SLO 不可達") -> 0.083512114 | ... Q22: =IF(ISNUMBER(Q15),Q$9/3600*Q15,"SLO 不可達") -> 0.11144181
R23: 已刪除（v14.0，4-3B Q1）：功能未接線，已移除，需要時再接線；原範圍 C23:Q23；見 Decisions SL43-1
A25: Sol（中層）
A26: GPU 秒／M 新鮮 prefill | B26: GPU-s | C26: =INDEX(Perf!$C$101:$Q$101,3*(C$6-1)+2) -> 447.5627 | D26: =INDEX(Perf!$C$101:$Q$101,3*(D$6-1)+2) -> 447.5627 | E26: =INDEX(Perf!$C$101:$Q$101,3*(E$6-1)+2) -> 447.5627 | F26: =INDEX(Perf!$C$101:$Q$101,3*(F$6-1)+2) -> 44.263951 | G26: =INDEX(Perf!$C$101:$Q$101,3*(G$6-1)+2) -> 44.263951 | H26: =INDEX(Perf!$C$101:$Q$101,3*(H$6-1)+2) -> 44.263951 | I26: =INDEX(Perf!$C$101:$Q$101,3*(I$6-1)+2) -> 29.509301 | J26: =INDEX(Perf!$C$101:$Q$101,3*(J$6-1)+2) -> 29.509301 | ... Q26: =INDEX(Perf!$C$101:$Q$101,3*(Q$6-1)+2) -> 6.3234215
A27: GPU 秒／M 快取命中 prefill | B27: GPU-s | C27: =INDEX(Perf!$C$102:$Q$102,3*(C$6-1)+2) -> 0.03965 | D27: =INDEX(Perf!$C$102:$Q$102,3*(D$6-1)+2) -> 0.03965 | E27: =INDEX(Perf!$C$102:$Q$102,3*(E$6-1)+2) -> 0.03965 | F27: =INDEX(Perf!$C$102:$Q$102,3*(F$6-1)+2) -> 0.03965 | G27: =INDEX(Perf!$C$102:$Q$102,3*(G$6-1)+2) -> 0.03965 | H27: =INDEX(Perf!$C$102:$Q$102,3*(H$6-1)+2) -> 0.03965 | I27: =INDEX(Perf!$C$102:$Q$102,3*(I$6-1)+2) -> 0.03965 | J27: =INDEX(Perf!$C$102:$Q$102,3*(J$6-1)+2) -> 0.03965 | ... Q27: =INDEX(Perf!$C$102:$Q$102,3*(Q$6-1)+2) -> 0.03965
A28: GPU 秒／M decode（含思考 token；文字「SLO 不可達」＝不可達） | B28: GPU-s | C28: =INDEX(Perf!$C$103:$Q$103,3*(C$6-1)+2) -> 4447.9318 | D28: =INDEX(Perf!$C$103:$Q$103,3*(D$6-1)+2) -> 4447.9318 | E28: =INDEX(Perf!$C$103:$Q$103,3*(E$6-1)+2) -> 4447.9318 | F28: =INDEX(Perf!$C$103:$Q$103,3*(F$6-1)+2) -> 817.11386 | G28: =INDEX(Perf!$C$103:$Q$103,3*(G$6-1)+2) -> 817.11386 | H28: =INDEX(Perf!$C$103:$Q$103,3*(H$6-1)+2) -> 817.11386 | I28: =INDEX(Perf!$C$103:$Q$103,3*(I$6-1)+2) -> 544.74257 | J28: =INDEX(Perf!$C$103:$Q$103,3*(J$6-1)+2) -> 544.74257 | ... Q28: =INDEX(Perf!$C$103:$Q$103,3*(Q$6-1)+2) -> 104.49178
A29: 新鮮 prefill $/M — 經濟、100% | B29: $/M | C29: =C$8/3600*C26 -> 0.13422466 | D29: =D$8/3600*D26 -> 0.19178019 | E29: =E$8/3600*E26 -> 0.32935712 | F29: =F$8/3600*F26 -> 0.0184953 | G29: =G$8/3600*G26 -> 0.024695116 | H29: =H$8/3600*H26 -> 0.040053493 | I29: =I$8/3600*I26 -> 0.016195228 | J29: =J$8/3600*J26 -> 0.020917074 | ... Q29: =Q$8/3600*Q26 -> 0.028858427
A30: 快取命中 prefill $/M — 經濟、100% | B30: $/M | C30: =C$8/3600*C27 -> 1.1891089e-05 | D30: =D$8/3600*D27 -> 1.6989987e-05 | E30: =E$8/3600*E27 -> 2.9178057e-05 | F30: =F$8/3600*F27 -> 1.6567402e-05 | G30: =G$8/3600*G27 -> 2.2120966e-05 | H30: =H$8/3600*H27 -> 3.5878429e-05 | I30: =I$8/3600*I27 -> 2.1760624e-05 | J30: =J$8/3600*J27 -> 2.8105105e-05 | ... Q30: =Q$8/3600*Q27 -> 0.00018095214
A31: decode（含思考 token）$/M — 經濟、100% | B31: $/M | C31: =IF(ISNUMBER(C28),C$8/3600*C28,"SLO 不可達") -> 1.3339407 | D31: =IF(ISNUMBER(D28),D$8/3600*D28,"SLO 不可達") -> 1.9059345 | E31: =IF(ISNUMBER(E28),E$8/3600*E28,"SLO 不可達") -> 3.2731906 | F31: =IF(ISNUMBER(F28),F$8/3600*F28,"SLO 不可達") -> 0.34142379 | G31: =IF(ISNUMBER(G28),G$8/3600*G28,"SLO 不可達") -> 0.45587259 | H31: =IF(ISNUMBER(H28),H$8/3600*H28,"SLO 不可達") -> 0.73938869 | I31: =IF(ISNUMBER(I28),I$8/3600*I28,"SLO 不可達") -> 0.2989644 | J31: =IF(ISNUMBER(J28),J$8/3600*J28,"SLO 不可達") -> 0.38612982 | ... Q31: =IF(ISNUMBER(Q28),Q$8/3600*Q28,"SLO 不可達") -> 0.47687291
A32: 新鮮 prefill $/M — 經濟、基準利用率 | B32: $/M | C32: =C29/C$10 -> 0.22370776 | D32: =D29/D$10 -> 0.31963364 | E32: =E29/E$10 -> 0.54892853 | F32: =F29/F$10 -> 0.0308255 | G32: =G29/G$10 -> 0.041158527 | H32: =H29/H$10 -> 0.066755822 | I32: =I29/I$10 -> 0.026992047 | J32: =J29/J$10 -> 0.034861791 | ... Q32: =Q29/Q$10 -> 0.048097378 | R32: 顯示用：C32:Q32（同表其他世代／層級欄）
A33: 快取命中 prefill $/M — 經濟、基準利用率 | B33: $/M | C33: =C30/C$10 -> 1.9818481e-05 | D33: =D30/D$10 -> 2.8316645e-05 | E33: =E30/E$10 -> 4.8630094e-05 | F33: =F30/F$10 -> 2.7612336e-05 | G33: =G30/G$10 -> 3.6868277e-05 | H33: =H30/H$10 -> 5.9797382e-05 | I33: =I30/I$10 -> 3.6267707e-05 | J33: =J30/J$10 -> 4.6841842e-05 | ... Q33: =Q30/Q$10 -> 0.00030158689 | R33: 顯示用：C33:Q33（同表其他世代／層級欄）
A34: decode（含思考 token）$/M — 經濟、基準利用率 | B34: $/M | C34: =IF(ISNUMBER(C31),C31/C$10,C31) -> 2.2232346 | D34: =IF(ISNUMBER(D31),D31/D$10,D31) -> 3.1765575 | E34: =IF(ISNUMBER(E31),E31/E$10,E31) -> 5.4553176 | F34: =IF(ISNUMBER(F31),F31/F$10,F31) -> 0.56903966 | G34: =IF(ISNUMBER(G31),G31/G$10,G31) -> 0.75978764 | H34: =IF(ISNUMBER(H31),H31/H$10,H31) -> 1.2323145 | I34: =IF(ISNUMBER(I31),I31/I$10,I31) -> 0.49827399 | J34: =IF(ISNUMBER(J31),J31/J$10,J31) -> 0.6435497 | ... Q34: =IF(ISNUMBER(Q31),Q31/Q$10,Q31) -> 0.79478819 | R34: 顯示用：C34:Q34（同表其他世代／層級欄）
A35: decode（含思考 token）$/M — 會計、100% | B35: $/M | C35: =IF(ISNUMBER(C28),C$9/3600*C28,"SLO 不可達") -> 1.0194495 | D35: =IF(ISNUMBER(D28),D$9/3600*D28,"SLO 不可達") -> 1.3954308 | E35: =IF(ISNUMBER(E28),E$9/3600*E28,"SLO 不可達") -> 2.3977809 | F35: =IF(ISNUMBER(F28),F$9/3600*F28,"SLO 不可達") -> 0.26074902 | G35: =IF(ISNUMBER(G28),G$9/3600*G28,"SLO 不可達") -> 0.33302543 | H35: =IF(ISNUMBER(H28),H$9/3600*H28,"SLO 不可達") -> 0.53805169 | I35: =IF(ISNUMBER(I28),I$9/3600*I28,"SLO 不可達") -> 0.22961204 | J35: =IF(ISNUMBER(J28),J$9/3600*J28,"SLO 不可達") -> 0.28339433 | ... Q35: =IF(ISNUMBER(Q28),Q$9/3600*Q28,"SLO 不可達") -> 0.35506435
R36: 已刪除（v14.0，4-3B Q1）：功能未接線，已移除，需要時再接線；原範圍 C36:Q36；見 Decisions SL43-1
A38: Astra（頂層）
A39: GPU 秒／M 新鮮 prefill | B39: GPU-s | C39: =INDEX(Perf!$C$101:$Q$101,3*(C$6-1)+3) -> 1484.7679 | D39: =INDEX(Perf!$C$101:$Q$101,3*(D$6-1)+3) -> 1484.7679 | E39: =INDEX(Perf!$C$101:$Q$101,3*(E$6-1)+3) -> 1484.7679 | F39: =INDEX(Perf!$C$101:$Q$101,3*(F$6-1)+3) -> 146.84355 | G39: =INDEX(Perf!$C$101:$Q$101,3*(G$6-1)+3) -> 146.84355 | H39: =INDEX(Perf!$C$101:$Q$101,3*(H$6-1)+3) -> 146.84355 | I39: =INDEX(Perf!$C$101:$Q$101,3*(I$6-1)+3) -> 97.895697 | J39: =INDEX(Perf!$C$101:$Q$101,3*(J$6-1)+3) -> 97.895697 | ... Q39: =INDEX(Perf!$C$101:$Q$101,3*(Q$6-1)+3) -> 20.977649
A40: GPU 秒／M 快取命中 prefill | B40: GPU-s | C40: =INDEX(Perf!$C$102:$Q$102,3*(C$6-1)+3) -> 0.576 | D40: =INDEX(Perf!$C$102:$Q$102,3*(D$6-1)+3) -> 0.576 | E40: =INDEX(Perf!$C$102:$Q$102,3*(E$6-1)+3) -> 0.576 | F40: =INDEX(Perf!$C$102:$Q$102,3*(F$6-1)+3) -> 0.576 | G40: =INDEX(Perf!$C$102:$Q$102,3*(G$6-1)+3) -> 0.576 | H40: =INDEX(Perf!$C$102:$Q$102,3*(H$6-1)+3) -> 0.576 | I40: =INDEX(Perf!$C$102:$Q$102,3*(I$6-1)+3) -> 0.576 | J40: =INDEX(Perf!$C$102:$Q$102,3*(J$6-1)+3) -> 0.576 | ... Q40: =INDEX(Perf!$C$102:$Q$102,3*(Q$6-1)+3) -> 0.576
A41: GPU 秒／M decode（含思考 token；文字「SLO 不可達」＝不可達） | B41: GPU-s | C41: =INDEX(Perf!$C$103:$Q$103,3*(C$6-1)+3) -> 24585.587 | D41: =INDEX(Perf!$C$103:$Q$103,3*(D$6-1)+3) -> 24585.587 | E41: =INDEX(Perf!$C$103:$Q$103,3*(E$6-1)+3) -> 24585.587 | F41: =INDEX(Perf!$C$103:$Q$103,3*(F$6-1)+3) -> 4255.5253 | G41: =INDEX(Perf!$C$103:$Q$103,3*(G$6-1)+3) -> 4255.5253 | H41: =INDEX(Perf!$C$103:$Q$103,3*(H$6-1)+3) -> 4255.5253 | I41: =INDEX(Perf!$C$103:$Q$103,3*(I$6-1)+3) -> 3168.5181 | J41: =INDEX(Perf!$C$103:$Q$103,3*(J$6-1)+3) -> 3168.5181 | ... Q41: =INDEX(Perf!$C$103:$Q$103,3*(Q$6-1)+3) -> 485.55114
A42: 新鮮 prefill $/M — 經濟、100% | B42: $/M | C42: =C$8/3600*C39 -> 0.4452839 | D42: =D$8/3600*D39 -> 0.63622162 | E42: =E$8/3600*E39 -> 1.0926265 | F42: =F$8/3600*F39 -> 0.061357276 | G42: =G$8/3600*G39 -> 0.081924871 | H42: =H$8/3600*H39 -> 0.13287555 | I42: =I$8/3600*I39 -> 0.053726897 | J42: =J$8/3600*J39 -> 0.069391396 | ... Q42: =Q$8/3600*Q39 -> 0.095736455
A43: 快取命中 prefill $/M — 經濟、100% | B43: $/M | C43: =C$8/3600*C40 -> 0.00017274318 | D43: =D$8/3600*D40 -> 0.00024681545 | E43: =E$8/3600*E40 -> 0.0004238729 | F43: =F$8/3600*F40 -> 0.0002406765 | G43: =G$8/3600*G40 -> 0.00032135376 | H43: =H$8/3600*H40 -> 0.00052120996 | I43: =I$8/3600*I40 -> 0.00031611903 | J43: =J$8/3600*J40 -> 0.00040828602 | ... Q43: =Q$8/3600*Q40 -> 0.002628712
A44: decode（含思考 token）$/M — 經濟、100% | B44: $/M | C44: =IF(ISNUMBER(C41),C$8/3600*C41,"SLO 不可達") -> 7.3732507 | D44: =IF(ISNUMBER(D41),D$8/3600*D41,"SLO 不可達") -> 10.5349 | E44: =IF(ISNUMBER(E41),E$8/3600*E41,"SLO 不可達") -> 18.092299 | F44: =IF(ISNUMBER(F41),F$8/3600*F41,"SLO 不可達") -> 1.7781336 | G44: =IF(ISNUMBER(G41),G$8/3600*G41,"SLO 不可達") -> 2.3741824 | H44: =IF(ISNUMBER(H41),H$8/3600*H41,"SLO 不可達") -> 3.8507329 | I44: =IF(ISNUMBER(I41),I$8/3600*I41,"SLO 不可達") -> 1.738939 | J44: =IF(ISNUMBER(J41),J$8/3600*J41,"SLO 不可達") -> 2.2459403 | ... Q44: =IF(ISNUMBER(Q41),Q$8/3600*Q41,"SLO 不可達") -> 2.2159272
A45: 新鮮 prefill $/M — 經濟、基準利用率 | B45: $/M | C45: =C42/C$10 -> 0.74213983 | D45: =D42/D$10 -> 1.0603694 | E45: =E42/E$10 -> 1.8210442 | F45: =F42/F$10 -> 0.10226213 | G45: =G42/G$10 -> 0.13654145 | H45: =H42/H$10 -> 0.22145926 | I45: =I42/I$10 -> 0.089544828 | J45: =J42/J$10 -> 0.11565233 | ... Q45: =Q42/Q$10 -> 0.15956076 | R45: 顯示用：C45:Q45（同表其他世代／層級欄）
A46: 快取命中 prefill $/M — 經濟、基準利用率 | B46: $/M | C46: =C43/C$10 -> 0.0002879053 | D46: =D43/D$10 -> 0.00041135908 | E46: =E43/E$10 -> 0.00070645484 | F46: =F43/F$10 -> 0.00040112751 | G46: =G43/G$10 -> 0.0005355896 | H46: =H43/H$10 -> 0.00086868327 | I46: =I43/I$10 -> 0.00052686505 | J46: =J43/J$10 -> 0.0006804767 | ... Q46: =Q43/Q$10 -> 0.0043811866 | R46: 顯示用：C46:Q46（同表其他世代／層級欄）
A47: decode（含思考 token）$/M — 經濟、基準利用率 | B47: $/M | C47: =IF(ISNUMBER(C44),C44/C$10,C44) -> 12.288751 | D47: =IF(ISNUMBER(D44),D44/D$10,D44) -> 17.558167 | E47: =IF(ISNUMBER(E44),E44/E$10,E44) -> 30.153831 | F47: =IF(ISNUMBER(F44),F44/F$10,F44) -> 2.963556 | G47: =IF(ISNUMBER(G44),G44/G$10,G44) -> 3.9569706 | H47: =IF(ISNUMBER(H44),H44/H$10,H44) -> 6.4178882 | I47: =IF(ISNUMBER(I44),I44/I$10,I44) -> 2.8982316 | J47: =IF(ISNUMBER(J44),J44/J$10,J44) -> 3.7432339 | ... Q47: =IF(ISNUMBER(Q44),Q44/Q$10,Q44) -> 3.6932121 | R47: 顯示用：C47:Q47（同表其他世代／層級欄）
A48: decode（含思考 token）$/M — 會計、100% | B48: $/M | C48: =IF(ISNUMBER(C41),C$9/3600*C41,"SLO 不可達") -> 5.6349254 | D48: =IF(ISNUMBER(D41),D$9/3600*D41,"SLO 不可達") -> 7.7131322 | E48: =IF(ISNUMBER(E41),E$9/3600*E41,"SLO 不可達") -> 13.253542 | F48: =IF(ISNUMBER(F41),F$9/3600*F41,"SLO 不可達") -> 1.3579797 | G48: =IF(ISNUMBER(G41),G$9/3600*G41,"SLO 不可達") -> 1.7343949 | H48: =IF(ISNUMBER(H41),H$9/3600*H41,"SLO 不可達") -> 2.8021707 | I48: =IF(ISNUMBER(I41),I$9/3600*I41,"SLO 不可達") -> 1.3355481 | J48: =IF(ISNUMBER(J41),J$9/3600*J41,"SLO 不可達") -> 1.6483751 | ... Q48: =IF(ISNUMBER(Q41),Q$9/3600*Q41,"SLO 不可達") -> 1.6499087
R49: 已刪除（v14.0，4-3B Q1）：功能未接線，已移除，需要時再接線；原範圍 C49:Q49；見 Decisions SL43-1

Sheet DC_Cost
A1: DC_Cost — 設施合計（IT 規模＝Inputs!E5 GW，基準 1）：資本支出與年持有成本；5 世代 × 3 成本情境。每 GW 值見 Interface（F14）
A2: 功率情境由 Inputs!E6 控制；成本情境為角落情境（所有金額輸入同時取低或高）
R3: 用途
A4: 世代 | C4: =Spec_Rack!C4 -> Hopper H100 | D4: =Spec_Rack!C4 -> Hopper H100 | E4: =Spec_Rack!C4 -> Hopper H100 | F4: =Spec_Rack!D4 -> GB200 NVL72 | G4: =Spec_Rack!D4 -> GB200 NVL72 | H4: =Spec_Rack!D4 -> GB200 NVL72 | I4: =Spec_Rack!E4 -> GB300 NVL72 | J4: =Spec_Rack!E4 -> GB300 NVL72 | K4: =Spec_Rack!E4 -> GB300 NVL72 | L4: =Spec_Rack!F4 -> VR200 NVL72 | M4: =Spec_Rack!F4 -> VR200 NVL72 | N4: =Spec_Rack!F4 -> VR200 NVL72 | O4: =Spec_Rack!G4 -> Rubin Ultra（MGX NVL 單架，72 GPU） | P4: =Spec_Rack!G4 -> Rubin Ultra（MGX NVL 單架，72 GPU） | Q4: =Spec_Rack!G4 -> Rubin Ultra（MGX NVL 單架，72 GPU） | R4: 顯示用：C4:Q4（欄頭／表頭標籤）
A5: 成本情境 | C5: 低成本 | D5: 基準 | E5: 高成本 | F5: 低成本 | G5: 基準 | H5: 高成本 | I5: 低成本 | J5: 基準 | K5: 高成本 | L5: 低成本 | M5: 基準 | N5: 高成本 | O5: 低成本 | P5: 基準 | Q5: 高成本
A7: A. 規模與電力
A8: IT 電力 | B8: MW | C8: =Inputs!$E$5*1000 -> 1000 | D8: =Inputs!$E$5*1000 -> 1000 | E8: =Inputs!$E$5*1000 -> 1000 | F8: =Inputs!$E$5*1000 -> 1000 | G8: =Inputs!$E$5*1000 -> 1000 | H8: =Inputs!$E$5*1000 -> 1000 | I8: =Inputs!$E$5*1000 -> 1000 | J8: =Inputs!$E$5*1000 -> 1000 | ... Q8: =Inputs!$E$5*1000 -> 1000
A9: 機架外 IT 電力占比 | B9: % | C9: =Inputs!$E$8 -> 0.08 | D9: =Inputs!$E$8 -> 0.08 | E9: =Inputs!$E$8 -> 0.08 | F9: =Inputs!$E$8 -> 0.08 | G9: =Inputs!$E$8 -> 0.08 | H9: =Inputs!$E$8 -> 0.08 | I9: =Inputs!$E$8 -> 0.08 | J9: =Inputs!$E$8 -> 0.08 | ... Q9: =Inputs!$E$8 -> 0.08
A10: 機架可用 IT 電力 | B10: MW | C10: =C8*(1-C9) -> 920 | D10: =D8*(1-D9) -> 920 | E10: =E8*(1-E9) -> 920 | F10: =F8*(1-F9) -> 920 | G10: =G8*(1-G9) -> 920 | H10: =H8*(1-H9) -> 920 | I10: =I8*(1-I9) -> 920 | J10: =J8*(1-J9) -> 920 | ... Q10: =Q8*(1-Q9) -> 920
A11: 每架配電設計功率 | B11: kW | C11: =CHOOSE(Inputs!$E$6,Spec_Rack!C8,Spec_Rack!C9,Spec_Rack!C10) -> 41 | D11: =CHOOSE(Inputs!$E$6,Spec_Rack!C8,Spec_Rack!C9,Spec_Rack!C10) -> 41 | E11: =CHOOSE(Inputs!$E$6,Spec_Rack!C8,Spec_Rack!C9,Spec_Rack!C10) -> 41 | F11: =CHOOSE(Inputs!$E$6,Spec_Rack!D8,Spec_Rack!D9,Spec_Rack!D10) -> 132 | G11: =CHOOSE(Inputs!$E$6,Spec_Rack!D8,Spec_Rack!D9,Spec_Rack!D10) -> 132 | H11: =CHOOSE(Inputs!$E$6,Spec_Rack!D8,Spec_Rack!D9,Spec_Rack!D10) -> 132 | I11: =CHOOSE(Inputs!$E$6,Spec_Rack!E8,Spec_Rack!E9,Spec_Rack!E10) -> 136 | J11: =CHOOSE(Inputs!$E$6,Spec_Rack!E8,Spec_Rack!E9,Spec_Rack!E10) -> 136 | K11: =CHOOSE(Inputs!$E$6,Spec_Rack!E8,Spec_Rack!E9,Spec_Rack!E10) -> 136 | L11: =CHOOSE(Inputs!$E$6,Spec_Rack!F8,Spec_Rack!F9,Spec_Rack!F10) -> 227 | M11: =CHOOSE(Inputs!$E$6,Spec_Rack!F8,Spec_Rack!F9,Spec_Rack!F10) -> 227 | N11: =CHOOSE(Inputs!$E$6,Spec_Rack!F8,Spec_Rack!F9,Spec_Rack!F10) -> 227 | O11: =CHOOSE(Inputs!$E$6,Spec_Rack!G8,Spec_Rack!G9,Spec_Rack!G10) -> 340 | P11: =CHOOSE(Inputs!$E$6,Spec_Rack!G8,Spec_Rack!G9,Spec_Rack!G10) -> 340 | Q11: =CHOOSE(Inputs!$E$6,Spec_Rack!G8,Spec_Rack!G9,Spec_Rack!G10) -> 340
A12: 機架數（設施） | B12: 架 | C12: =FLOOR(C10*1000/C11,1) -> 22439 | D12: =FLOOR(D10*1000/D11,1) -> 22439 | E12: =FLOOR(E10*1000/E11,1) -> 22439 | F12: =FLOOR(F10*1000/F11,1) -> 6969 | G12: =FLOOR(G10*1000/G11,1) -> 6969 | H12: =FLOOR(H10*1000/H11,1) -> 6969 | I12: =FLOOR(I10*1000/I11,1) -> 6764 | J12: =FLOOR(J10*1000/J11,1) -> 6764 | ... Q12: =FLOOR(Q10*1000/Q11,1) -> 2705
A13: GPU 封裝／架 | B13: 顆 | C13: =Spec_Rack!C6 -> 32 | D13: =Spec_Rack!C6 -> 32 | E13: =Spec_Rack!C6 -> 32 | F13: =Spec_Rack!D6 -> 72 | G13: =Spec_Rack!D6 -> 72 | H13: =Spec_Rack!D6 -> 72 | I13: =Spec_Rack!E6 -> 72 | J13: =Spec_Rack!E6 -> 72 | K13: =Spec_Rack!E6 -> 72 | L13: =Spec_Rack!F6 -> 72 | M13: =Spec_Rack!F6 -> 72 | N13: =Spec_Rack!F6 -> 72 | O13: =Spec_Rack!G6 -> 72 | P13: =Spec_Rack!G6 -> 72 | Q13: =Spec_Rack!G6 -> 72
A14: GPU 數（設施） | B14: 顆 | C14: =C12*C13 -> 718048 | D14: =D12*D13 -> 718048 | E14: =E12*E13 -> 718048 | F14: =F12*F13 -> 501768 | G14: =G12*G13 -> 501768 | H14: =H12*H13 -> 501768 | I14: =I12*I13 -> 487008 | J14: =J12*J13 -> 487008 | ... Q14: =Q12*Q13 -> 194760
A15: PUE | B15: x | C15: =Inputs!D9 -> 1.1 | D15: =Inputs!E9 -> 1.2 | E15: =Inputs!F9 -> 1.3 | F15: =Inputs!D9 -> 1.1 | G15: =Inputs!E9 -> 1.2 | H15: =Inputs!F9 -> 1.3 | I15: =Inputs!D9 -> 1.1 | J15: =Inputs!E9 -> 1.2 | K15: =Inputs!F9 -> 1.3 | L15: =Inputs!D9 -> 1.1 | M15: =Inputs!E9 -> 1.2 | N15: =Inputs!F9 -> 1.3 | O15: =Inputs!D9 -> 1.1 | P15: =Inputs!E9 -> 1.2 | Q15: =Inputs!F9 -> 1.3
A16: 設施電力（IT × PUE） | B16: MW | C16: =C8*C15 -> 1100 | D16: =D8*D15 -> 1200 | E16: =E8*E15 -> 1300 | F16: =F8*F15 -> 1100 | G16: =G8*G15 -> 1200 | H16: =H8*H15 -> 1300 | I16: =I8*I15 -> 1100 | J16: =J8*J15 -> 1200 | ... Q16: =Q8*Q15 -> 1300
A17: B. 資本支出（$B；設施）
A18: 機架單價 | B18: $M | C18: =Spec_Rack!C11 -> 0.9 | D18: =Spec_Rack!C12 -> 1.1 | E18: =Spec_Rack!C13 -> 1.3 | F18: =Spec_Rack!D11 -> 2.8 | G18: =Spec_Rack!D12 -> 3.1 | H18: =Spec_Rack!D13 -> 3.4 | I18: =Spec_Rack!E11 -> 4 | J18: =Spec_Rack!E12 -> 4.3 | K18: =Spec_Rack!E13 -> 5 | L18: =Spec_Rack!F11 -> 7.8 | M18: =Spec_Rack!F12 -> 8.4 | N18: =Spec_Rack!F13 -> 9.1 | O18: =Spec_Rack!G11 -> 12.6 | P18: =Spec_Rack!G12 -> 16.8 | Q18: =Spec_Rack!G13 -> 21
A19: 機架 | B19: $B | C19: =C12*C18/1000 -> 20.1951 | D19: =D12*D18/1000 -> 24.6829 | E19: =E12*E18/1000 -> 29.1707 | F19: =F12*F18/1000 -> 19.5132 | G19: =G12*G18/1000 -> 21.6039 | H19: =H12*H18/1000 -> 23.6946 | I19: =I12*I18/1000 -> 27.056 | J19: =J12*J18/1000 -> 29.0852 | ... Q19: =Q12*Q18/1000 -> 56.805
A20: Scale-out 網路 ÷ 機架價格 | B20: % | C20: =Inputs!D13 -> 0.05 | D20: =Inputs!E13 -> 0.1 | E20: =Inputs!F13 -> 0.15 | F20: =Inputs!D13 -> 0.05 | G20: =Inputs!E13 -> 0.1 | H20: =Inputs!F13 -> 0.15 | I20: =Inputs!D13 -> 0.05 | J20: =Inputs!E13 -> 0.1 | K20: =Inputs!F13 -> 0.15 | L20: =Inputs!D13 -> 0.05 | M20: =Inputs!E13 -> 0.1 | N20: =Inputs!F13 -> 0.15 | O20: =Inputs!D13 -> 0.05 | P20: =Inputs!E13 -> 0.1 | Q20: =Inputs!F13 -> 0.15
A21: Scale-out 網路 | B21: $B | C21: =C19*C20 -> 1.009755 | D21: =D19*D20 -> 2.46829 | E21: =E19*E20 -> 4.375605 | F21: =F19*F20 -> 0.97566 | G21: =G19*G20 -> 2.16039 | H21: =H19*H20 -> 3.55419 | I21: =I19*I20 -> 1.3528 | J21: =J19*J20 -> 2.90852 | ... Q21: =Q19*Q20 -> 8.52075
A22: 儲存與管理 | B22: $/GPU | C22: =Inputs!D14 -> 300 | D22: =Inputs!E14 -> 500 | E22: =Inputs!F14 -> 800 | F22: =Inputs!D14 -> 300 | G22: =Inputs!E14 -> 500 | H22: =Inputs!F14 -> 800 | I22: =Inputs!D14 -> 300 | J22: =Inputs!E14 -> 500 | K22: =Inputs!F14 -> 800 | L22: =Inputs!D14 -> 300 | M22: =Inputs!E14 -> 500 | N22: =Inputs!F14 -> 800 | O22: =Inputs!D14 -> 300 | P22: =Inputs!E14 -> 500 | Q22: =Inputs!F14 -> 800
A23: 儲存與管理 | B23: $B | C23: =C14*C22/1000000000 -> 0.2154144 | D23: =D14*D22/1000000000 -> 0.359024 | E23: =E14*E22/1000000000 -> 0.5744384 | F23: =F14*F22/1000000000 -> 0.1505304 | G23: =G14*G22/1000000000 -> 0.250884 | H23: =H14*H22/1000000000 -> 0.4014144 | I23: =I14*I22/1000000000 -> 0.1461024 | J23: =J14*J22/1000000000 -> 0.243504 | ... Q23: =Q14*Q22/1000000000 -> 0.155808
A24: IT 設備小計 | B24: $B | C24: =C19+C21+C23 -> 21.420269 | D24: =D19+D21+D23 -> 27.510214 | E24: =E19+E21+E23 -> 34.120743 | F24: =F19+F21+F23 -> 20.63939 | G24: =G19+G21+G23 -> 24.015174 | H24: =H19+H21+H23 -> 27.650204 | I24: =I19+I21+I23 -> 28.554902 | J24: =J19+J21+J23 -> 32.237224 | ... Q24: =Q19+Q21+Q23 -> 65.481558
A25: 土地 | B25: $B | C25: =C8*Inputs!D16/1000 -> 0.02 | D25: =D8*Inputs!E16/1000 -> 0.02 | E25: =E8*Inputs!F16/1000 -> 0.02 | F25: =F8*Inputs!D16/1000 -> 0.02 | G25: =G8*Inputs!E16/1000 -> 0.02 | H25: =H8*Inputs!F16/1000 -> 0.02 | I25: =I8*Inputs!D16/1000 -> 0.02 | J25: =J8*Inputs!E16/1000 -> 0.02 | K25: =K8*Inputs!F16/1000 -> 0.02 | L25: =L8*Inputs!D16/1000 -> 0.02 | M25: =M8*Inputs!E16/1000 -> 0.02 | N25: =N8*Inputs!F16/1000 -> 0.02 | O25: =O8*Inputs!D16/1000 -> 0.02 | P25: =P8*Inputs!E16/1000 -> 0.02 | Q25: =Q8*Inputs!F16/1000 -> 0.02
A26: 建物與基地 | B26: $B | C26: =C8*Inputs!D17/1000 -> 3 | D26: =D8*Inputs!E17/1000 -> 3.6 | E26: =E8*Inputs!F17/1000 -> 4.5 | F26: =F8*Inputs!D17/1000 -> 3 | G26: =G8*Inputs!E17/1000 -> 3.6 | H26: =H8*Inputs!F17/1000 -> 4.5 | I26: =I8*Inputs!D17/1000 -> 3 | J26: =J8*Inputs!E17/1000 -> 3.6 | K26: =K8*Inputs!F17/1000 -> 4.5 | L26: =L8*Inputs!D17/1000 -> 3 | M26: =M8*Inputs!E17/1000 -> 3.6 | N26: =N8*Inputs!F17/1000 -> 4.5 | O26: =O8*Inputs!D17/1000 -> 3 | P26: =P8*Inputs!E17/1000 -> 3.6 | Q26: =Q8*Inputs!F17/1000 -> 4.5
A27: 電力設施 | B27: $B | C27: =C8*Inputs!D18/1000 -> 3.8 | D27: =D8*Inputs!E18/1000 -> 4.5 | E27: =E8*Inputs!F18/1000 -> 5.5 | F27: =F8*Inputs!D18/1000 -> 3.8 | G27: =G8*Inputs!E18/1000 -> 4.5 | H27: =H8*Inputs!F18/1000 -> 5.5 | I27: =I8*Inputs!D18/1000 -> 3.8 | J27: =J8*Inputs!E18/1000 -> 4.5 | K27: =K8*Inputs!F18/1000 -> 5.5 | L27: =L8*Inputs!D18/1000 -> 3.8 | M27: =M8*Inputs!E18/1000 -> 4.5 | N27: =N8*Inputs!F18/1000 -> 5.5 | O27: =O8*Inputs!D18/1000 -> 3.8 | P27: =P8*Inputs!E18/1000 -> 4.5 | Q27: =Q8*Inputs!F18/1000 -> 5.5
A28: 機械與散熱 | B28: $B | C28: =C8*Inputs!D19/1000 -> 2 | D28: =D8*Inputs!E19/1000 -> 2.5 | E28: =E8*Inputs!F19/1000 -> 3.2 | F28: =F8*Inputs!D19/1000 -> 2 | G28: =G8*Inputs!E19/1000 -> 2.5 | H28: =H8*Inputs!F19/1000 -> 3.2 | I28: =I8*Inputs!D19/1000 -> 2 | J28: =J8*Inputs!E19/1000 -> 2.5 | K28: =K8*Inputs!F19/1000 -> 3.2 | L28: =L8*Inputs!D19/1000 -> 2 | M28: =M8*Inputs!E19/1000 -> 2.5 | N28: =N8*Inputs!F19/1000 -> 3.2 | O28: =O8*Inputs!D19/1000 -> 2 | P28: =P8*Inputs!E19/1000 -> 2.5 | Q28: =Q8*Inputs!F19/1000 -> 3.2
A29: 光纖與保全 | B29: $B | C29: =C8*Inputs!D20/1000 -> 0.3 | D29: =D8*Inputs!E20/1000 -> 0.4 | E29: =E8*Inputs!F20/1000 -> 0.5 | F29: =F8*Inputs!D20/1000 -> 0.3 | G29: =G8*Inputs!E20/1000 -> 0.4 | H29: =H8*Inputs!F20/1000 -> 0.5 | I29: =I8*Inputs!D20/1000 -> 0.3 | J29: =J8*Inputs!E20/1000 -> 0.4 | K29: =K8*Inputs!F20/1000 -> 0.5 | L29: =L8*Inputs!D20/1000 -> 0.3 | M29: =M8*Inputs!E20/1000 -> 0.4 | N29: =N8*Inputs!F20/1000 -> 0.5 | O29: =O8*Inputs!D20/1000 -> 0.3 | P29: =P8*Inputs!E20/1000 -> 0.4 | Q29: =Q8*Inputs!F20/1000 -> 0.5
A30: 設計、管理與預備費率 | B30: % | C30: =Inputs!D21 -> 0.12 | D30: =Inputs!E21 -> 0.15 | E30: =Inputs!F21 -> 0.18 | F30: =Inputs!D21 -> 0.12 | G30: =Inputs!E21 -> 0.15 | H30: =Inputs!F21 -> 0.18 | I30: =Inputs!D21 -> 0.12 | J30: =Inputs!E21 -> 0.15 | K30: =Inputs!F21 -> 0.18 | L30: =Inputs!D21 -> 0.12 | M30: =Inputs!E21 -> 0.15 | N30: =Inputs!F21 -> 0.18 | O30: =Inputs!D21 -> 0.12 | P30: =Inputs!E21 -> 0.15 | Q30: =Inputs!F21 -> 0.18
A31: 設計、管理與預備費 | B31: $B | C31: =(C26+C27+C28+C29)*C30 -> 1.092 | D31: =(D26+D27+D28+D29)*D30 -> 1.65 | E31: =(E26+E27+E28+E29)*E30 -> 2.466 | F31: =(F26+F27+F28+F29)*F30 -> 1.092 | G31: =(G26+G27+G28+G29)*G30 -> 1.65 | H31: =(H26+H27+H28+H29)*H30 -> 2.466 | I31: =(I26+I27+I28+I29)*I30 -> 1.092 | J31: =(J26+J27+J28+J29)*J30 -> 1.65 | ... Q31: =(Q26+Q27+Q28+Q29)*Q30 -> 2.466
A32: 廠房小計 | B32: $B | C32: =C25+C26+C27+C28+C29+C31 -> 10.212 | D32: =D25+D26+D27+D28+D29+D31 -> 12.67 | E32: =E25+E26+E27+E28+E29+E31 -> 16.186 | F32: =F25+F26+F27+F28+F29+F31 -> 10.212 | G32: =G25+G26+G27+G28+G29+G31 -> 12.67 | H32: =H25+H26+H27+H28+H29+H31 -> 16.186 | I32: =I25+I26+I27+I28+I29+I31 -> 10.212 | J32: =J25+J26+J27+J28+J29+J31 -> 12.67 | ... Q32: =Q25+Q26+Q27+Q28+Q29+Q31 -> 16.186
A33: 總資本支出（設施） | B33: $B | C33: =C24+C32 -> 31.632269 | D33: =D24+D32 -> 40.180214 | E33: =E24+E32 -> 50.306743 | F33: =F24+F32 -> 30.85139 | G33: =G24+G32 -> 36.685174 | H33: =H24+H32 -> 43.836204 | I33: =I24+I32 -> 38.766902 | J33: =J24+J32 -> 44.907224 | ... Q33: =Q24+Q32 -> 81.667558
A34: 每 GPU 資本支出（含廠房） | B34: $K | C34: =C33*1000000/C14 -> 44.05314 | D34: =D33*1000000/D14 -> 55.95756 | E34: =E33*1000000/E14 -> 70.060419 | F34: =F33*1000000/F14 -> 61.485369 | G34: =G33*1000000/G14 -> 73.111825 | H34: =H33*1000000/H14 -> 87.363491 | I34: =I33*1000000/I14 -> 79.602188 | J34: =J33*1000000/J14 -> 92.210444 | ... Q34: =Q33*1000000/Q14 -> 419.32408 | R34: 顯示用：C34:Q34（核心列：Sensitivity 有同列同標籤的列，常設測試以此為逐格比對基準；下游用 IF_Capex*／IF_HoldEcon／IF_AvgDraw）
A35: 每 MW IT 資本支出 | B35: $M | C35: =C33*1000/C8 -> 31.632269 | D35: =D33*1000/D8 -> 40.180214 | E35: =E33*1000/E8 -> 50.306743 | F35: =F33*1000/F8 -> 30.85139 | G35: =G33*1000/G8 -> 36.685174 | H35: =H33*1000/H8 -> 43.836204 | I35: =I33*1000/I8 -> 38.766902 | J35: =J33*1000/J8 -> 44.907224 | ... Q35: =Q33*1000/Q8 -> 81.667558 | R35: 顯示用：C35:Q35（核心列：Sensitivity 有同列同標籤的列，常設測試以此為逐格比對基準；下游用 IF_Capex*／IF_HoldEcon／IF_AvgDraw）
A36: 每 MW IT 廠房資本支出 | B36: $M | C36: =C32*1000/C8 -> 10.212 | D36: =D32*1000/D8 -> 12.67 | E36: =E32*1000/E8 -> 16.186 | F36: =F32*1000/F8 -> 10.212 | G36: =G32*1000/G8 -> 12.67 | H36: =H32*1000/H8 -> 16.186 | I36: =I32*1000/I8 -> 10.212 | J36: =J32*1000/J8 -> 12.67 | ... Q36: =Q32*1000/Q8 -> 16.186 | R36: 顯示用：C36:Q36（同表其他世代／層級欄）
A37: C. 年持有成本 — 會計口徑（$B／年；設施）
