Workbook

Sheet README
A1: Stage 0 盤點（唯讀）— 20261002_Tokenomics_v5.10.xlsx
A2: 產生程式 | B2: tools/stage0_inventory.py（輸入 xlsx 路徑，輸出本檔；可重跑，不在 CI）
A3: 活頁簿 SHA-256 | B3: d7d59ab8a9c965e9c9a0ed96d7e5a6ba820fbb90adedd146a3542b0ba979497f | F3: 前後一致：是
A5: 目的 | B5: 盤點藍字輸入：依既有標記機械分類、建立靜態依賴圖、以擾動求 load-bearing 排序。分類只是『初步』；待分類與爭議列由 chat 端複核，Andy 核准遷移範圍（Gate 0）。
A6: 母體 | B6: 藍字格＝字型色 RGB 結尾 0000FF、值非空、非公式；盤點單位＝工作表 × 列。藍字但為公式者另列（藍字公式格）。
A8: 初步分類規則（依序，先符合者為準）
A9: R1 | B9: 工作表＝DB_Evidence | C9: Evidence 登錄（非輸入）
A10: R2 | B10: 工作表＝Checks | C10: Checks 外部參照
A11: R3 | B11: 主標記＝Verified 或 Interested-party | C11: 原始數據（候選）
A12: R4 | B12: 主標記＝Analogy／Assumed／Decision | C12: 同主標記
A13: R5 | B13: 主標記＝Derived | C13: Derived 藍字（異常）
A14: R6 | B14: 無標記，且工作表以 Sens_ 開頭、或單位＝「選擇」、或標籤含「索引」 | C14: 情境選擇
A15: R7 | B15: 其餘 | C15: 待分類
A16: 標記擷取 | B16: 標記＝該列所有非公式文字格（含 A、B 欄與藍字文字格）的子字串比對（區分大小寫）：Verified、Interested-party、Analogy、Assumed、Decision、Derived；主標記依序取第一個；兩個以上者標『多標記』。
A17: 擾動方法 | B17: engine（pycel）重算；每列所有數值藍字格同時 ×1.1 與 ×0.9，之後還原；ε₊＝(y₊/y₀−1)/0.1、ε₋＝(1−y₋/y₀)/0.1、ε＝(y₊−y₋)/(y₀×0.2)；單位 % 且 ×1.1>1 者只做 −10%（單邊）。
A18: 整數選擇格（本工具的解讀） | B18: 列屬『情境選擇』、或單位＝選擇、或標籤含『索引』、或標籤含『（1／2／3）』類選項說明，或標籤含『（1＝有）』『（1＝是）』類 0／1 旗標說明時，其中值為整數的藍字格不擾動；同列非整數數值格仍擾動。X2＝該列沒有任何可擾動格。
A19: 不擾動原因代碼 | B19: X1 文字值（列內無數值格）；X2 整數選擇格；X3 基準值為 0；X4 Evidence／Checks 列；X5a 靜態不可達任何 IF_；X5b 可達 IF_ 但未達 O01–O14（彈性記 0）。
A20: 分段（僅供排序閱讀） | B20: 高 ≥ 0.5；中 0.1–0.5；低 < 0.1；無＝0（含未擾動）。分數＝O01–O13 的 |ε| 最大值。門檻由 chat 端日後判斷是否調整。
A22: 期望值核對表（第 2、3.3 節）
A23: 類別 | B23: 項目 | C23: 期望 | D23: 實得 | E23: 差異
A24: 總計 | B24: 藍字列 | C24: 324 | D24: 324 | E24: 0
A25: 總計 | B25: 藍字格 | C25: 1491 | D25: 1491 | E25: 0
A26: 總計 | B26: 藍字公式格 | C26: 31 | D26: 31 | E26: 0
A27: 工作表列數 | B27: Inputs | C27: 26 | D27: 26 | E27: 0
A28: 工作表列數 | B28: Spec_Rack | C28: 22 | D28: 22 | E28: 0
A29: 工作表列數 | B29: Arch | C29: 18 | D29: 18 | E29: 0
A30: 工作表列數 | B30: Serving | C30: 16 | D30: 16 | E30: 0
A31: 工作表列數 | B31: Workload | C31: 11 | D31: 11 | E31: 0
A32: 工作表列數 | B32: Calib | C32: 26 | D32: 26 | E32: 0
A33: 工作表列數 | B33: Tech_Registry | C33: 12 | D33: 12 | E33: 0
A34: 工作表列數 | B34: Perf | C34: 2 | D34: 2 | E34: 0
A35: 工作表列數 | B35: Sens_Perf | C35: 9 | D35: 9 | E35: 0
... A68: 動態引用 | B68: OFFSET／INDIRECT 公式數 | C68: 0 | D68: 0 | E68: 0
A70: 與 builder restore_log 口徑的差異（依工作表）
A71: 工作表 | B71: builder 是否重建 | C71: 本母體藍字格 | D71: restore 快照格 | E71: 差異 | F71: 差異來源
A72: Inputs | B72: 否 | C72: 64 | D72: 0 | E72: 64 | F72: builder 不重建此頁（輸入頁或登錄頁）
A73: Spec_Rack | B73: 是 | C73: 110 | D73: 75 | E73: 35 | F73: 重建頁內不在快照：A 欄藍字（如 Cap_In 模型名稱列）或 Spec_Rack 第 20 列以前（Block 1 區，由 Excel 擁有）
A74: Arch | B74: 是 | C74: 52 | D74: 52 | E74: 0
A75: Serving | B75: 是 | C75: 24 | D75: 24 | E75: 0
A76: Workload | B76: 是 | C76: 53 | D76: 53 | E76: 0
A77: Calib | B77: 是 | C77: 82 | D77: 82 | E77: 0
A78: Tech_Registry | B78: 是 | C78: 108 | D78: 108 | E78: 0
A79: Perf | B79: 是 | C79: 30 | D79: 30 | E79: 0
A80: Sens_Perf | B80: 是 | C80: 83 | D80: 83 | E80: 0
A81: Unit_Cost | B81: 是 | C81: 15 | D81: 15 | E81: 0
A82: Train_In | B82: 是 | C82: 68 | D82: 68 | E82: 0
A83: Perf_Batch | B83: 是 | C83: 38 | D83: 38 | E83: 0
A84: Training | B84: 是 | C84: 30 | D84: 30 | E84: 0
A85: Sens_Train | B85: 是 | C85: 84 | D85: 84 | E85: 0
A86: Cap_In | B86: 是 | C86: 233 | D86: 220 | E86: 13 | F86: 重建頁內不在快照：A 欄藍字（如 Cap_In 模型名稱列）或 Spec_Rack 第 20 列以前（Block 1 區，由 Excel 擁有）
A87: Sens_Rev | B87: 是 | C87: 13 | D87: 13 | E87: 0
A88: Har_In | B88: 是 | C88: 144 | D88: 144 | E88: 0
A89: Energy | B89: 是 | C89: 3 | D89: 3 | E89: 0
A90: NonNV | B90: 是 | C90: 30 | D90: 30 | E90: 0
A91: Checks | B91: 否 | C91: 11 | D91: 0 | E91: 11 | F91: builder 不重建此頁（輸入頁或登錄頁）
A92: DB_Evidence | B92: 否 | C92: 216 | D92: 0 | E92: 216 | F92: builder 不重建此頁（輸入頁或登錄頁）
A93: 合計 | C93: 1491 | D93: 1152 | E93: 339 | F93: restore_log 口徑：builder 重建頁、欄 ≥ B、字型色 FF0000FF、列標籤（A 欄）非公式；本母體另含不重建的頁、A 欄藍字與 0000FF 尾碼的其他色
A95: 依賴圖
A96: 公式格數 | B96: 20780
A97: 使用函數 | B97: ABS×28、AND×1048、AVERAGE×1、CEILING×150、CHOOSE×91、COUNTIF×5、EXP×16、FLOOR×38、IF×4194、INDEX×8095、ISNUMBER×2385、LN×30、MATCH×15、MAX×330、MIN×415、OR×100、SUMPRODUCT×71、TEXT×9
A98: 動態引用（OFFSET／INDIRECT） | B98: 0
A99: 無法解析的參照 | B99: 0
A100: 區域引用 | B100: 一律展開為每一格；INDEX、CHOOSE 因此為保守上界。
A102: 驗證（第 5.4 節）
A103: 1. 觀測 ⊆ 靜態：違反數 | B103: 0
A104: 靜態可達但未觀測到改變（名稱 × 列，僅計數） | B104: 3206
A105: 2. LibreOffice 抽驗（分數最高 10 列）最大相對誤差 | B105: 3.9596435e-15 | C105: 通過
A106: 3. 還原：每次擾動後全簿公式格重算（20780 格） | B106: 308 次中不一致 0 次
A107: 全部完成後新引擎基準 vs 起點 | B107: 20780 | C107: 不一致 0 格
A108: 4. 擾動執行時間（秒） | B108: 67 | C108: 總執行 193 秒
A109: 基準 engine vs 活頁簿快取值（O01–O14）最大相對誤差 | B109: 1.8719186e-15 | C109: 通過

Sheet 盤點
A1: INV_ID | B1: 工作表 | C1: 列 | D1: 標籤 | E1: 單位 | F1: 藍字格位址 | G1: 藍字格數 | H1: 基準值 | I1: 全部標記 | J1: 主標記 | K1: 多標記 | L1: 來源編號（S） | M1: 證據編號（E） | N1: 說明原文 | O1: 初步分類 | P1: 分類依據 | Q1: 可達 IF_ 數 | R1: 可達主要輸出 | S1: 最大 |ε| | T1: 分段 | U1: 排名 | V1: 可達公式格數 | W1: 可達工作表 | X1: 不擾動原因 | Y1: chat 複核分類 | Z1: SRC 分頁候選 | AA1: 理由 | AB1: Gate 0 爭議
A2: INV-001 | B2: Inputs | C2: 5 | D2: IT 電力規模 | E2: GW | F2: E5 | G2: 1 | H2: 1 | I2: Decision | J2: Decision | N2: G5: Decision ｜ H5: 口徑：IT 關鍵電力 | O2: Decision | P2: R4 | Q2: 87 | R2: O01、O02、O03、O04、O05、O06、O08、O10、O11、O12、O13、O14 | S2: 1.0007404 | T2: 高 | U2: 10 | V2: 6128 | W2: Amortize、Cache_Store、Capability、Checks、DC_Cost、Fleet_1GW、Harness、Inputs、Interface、Perf、Perf_Batch、Sens_Har、Sens_Perf、Sens_Rev、Sens_Train、Sensitivity、Theory_Rev、Training、Unit_Cost、Workload
A3: INV-002 | B3: Inputs | C3: 6 | D3: 功率情境（1 低／2 基準／3 高） | E3: 選擇 | F3: E6 | G3: 1 | H3: 2 | I3: Decision | J3: Decision | N3: G6: Decision ｜ H6: 決定每架配電設計功率；見 Spec_Rack 第 9–11 列 | O3: Decision | P3: R4 | Q3: 87 | R3: O01、O02、O03、O04、O05、O06、O08、O10、O11、O12、O13、O14 | T3: 無 | V3: 5243 | W3: Amortize、Cache_Store、Capability、Checks、DC_Cost、Fleet_1GW、Harness、Inputs、Interface、Perf、Perf_Batch、Sens_Har、Sens_Perf、Sens_Rev、Sens_Train、Theory_Rev、Training、Unit_Cost、Workload | X3: X2
A4: INV-003 | B4: Inputs | C4: 8 | D4: 機架外 IT 電力占比 | E4: % | F4: E8 | G4: 1 | H4: 0.08 | I4: Assumed | J4: Assumed | N4: G8: Assumed ｜ H8: 管理、儲存、網路機櫃等；區間 5–12%（見 Sensitivity）。v4 未計 | O4: Assumed | P4: R4 | Q4: 84 | R4: O01、O02、O03、O04、O05、O06、O08、O10、O11、O12、O13、O14 | S4: 0.087611056 | T4: 低 | U4: 66 | V4: 5457 | W4: Amortize、Cache_Store、Capability、Checks、DC_Cost、Fleet_1GW、Harness、Inputs、Interface、Perf、Perf_Batch、Sens_Har、Sens_Perf、Sens_Rev、Sens_Train、Sensitivity、Theory_Rev、Training、Unit_Cost、Workload
A5: INV-004 | B5: Inputs | C5: 9 | D5: PUE | E5: x | F5: D9、E9、F9 | G5: 3 | H5: 1.1；1.2；1.3 | I5: Analogy | J5: Analogy | L5: S14 | N5: G9: Analogy ｜ H9: 液冷 AI 設施；v4＝1.2。S14 | O5: Analogy | P5: R4 | Q5: 59 | R5: O02、O04、O05、O06、O08、O10、O13、O14 | S5: 0.055811125 | T5: 低 | U5: 74 | V5: 3647 | W5: Amortize、Cache_Store、Capability、Checks、DC_Cost、Harness、Interface、Perf、Perf_Batch、Sens_Har、Sens_Perf、Sens_Rev、Sens_Train、Sensitivity、Theory_Rev、Training、Unit_Cost、Workload
A6: INV-005 | B6: Inputs | C6: 10 | D6: 平均用電 ÷ 配電設計功率 | E6: % | F6: D10、E10、F10 | G6: 3 | H6: 0.7；0.8；0.9 | I6: Assumed | J6: Assumed | N6: G10: Assumed ｜ H10: Block 2 以逐步能量模型閉合檢查 | O6: Assumed | P6: R4 | Q6: 61 | R6: O02、O04、O05、O06、O08、O10、O13、O14 | S6: 0.055811125 | T6: 低 | U6: 73 | V6: 3897 | W6: Amortize、Cache_Store、Capability、Checks、DC_Cost、Harness、Interface、Perf、Perf_Batch、Sens_Har、Sens_Perf、Sens_Rev、Sens_Train、Sensitivity、Theory_Rev、Training、Unit_Cost、Workload
A7: INV-006 | B7: Inputs | C7: 11 | D7: 電價 | E7: $/kWh | F7: D11、E11、F11 | G7: 3 | H7: 0.06；0.08；0.1 | I7: Verified、Analogy | J7: Verified | K7: 多標記 | L7: S13 | N7: G11: Verified/Analogy ｜ H11: EIA 美國工業電價 2026 年約 8.6–8.7¢（S13）；低端為 PPA（v4＝0.06） | O7: 原始數據（候選） | P7: R3 | Q7: 58 | R7: O02、O04、O05、O06、O08、O10、O13、O14 | S7: 0.055811125 | T7: 低 | U7: 75 | V7: 3556 | W7: Amortize、Cache_Store、Capability、Checks、DC_Cost、Harness、Interface、Perf、Perf_Batch、Sens_Har、Sens_Perf、Sens_Rev、Sens_Train、Sensitivity、Theory_Rev、Training、Unit_Cost、Workload
A8: INV-007 | B8: Inputs | C8: 13 | D8: Scale-out 網路 ÷ 機架價格 | E8: % | F8: D13、E13、F13 | G8: 3 | H8: 0.05；0.1；0.15 | I8: Analogy | J8: Analogy | L8: S10 | N8: G13: Analogy ｜ H13: 1,024 GPU 叢集網路約為 GPU BOM 4–8%（S10）；GW 級多一層以上交換，取 5–15% | O8: Analogy | P8: R4 | Q8: 59 | R8: O01、O02、O04、O05、O06、O08、O10、O13、O14 | S8: 0.0702143 | T8: 低 | U8: 68 | V8: 3911 | W8: Amortize、Cache_Store、Capability、Checks、DC_Cost、Harness、Interface、Perf、Perf_Batch、Sens_Har、Sens_Perf、Sens_Rev、Sens_Train、Sensitivity、Theory_Rev、Training、Unit_Cost、Workload
A9: INV-008 | B9: Inputs | C9: 14 | D9: 儲存與管理設備 | E9: $/GPU | F9: D14、E14、F14 | G9: 3 | H9: 300；500；800 | I9: Assumed | J9: Assumed | N9: G14: Assumed ｜ H14: v4 約 $350/GPU（$25K/架） | O9: Assumed | P9: R4 | Q9: 59 | R9: O01、O02、O04、O05、O06、O08、O10、O13、O14 | S9: 0.0050554296 | T9: 低 | U9: 94 | V9: 3911 | W9: Amortize、Cache_Store、Capability、Checks、DC_Cost、Harness、Interface、Perf、Perf_Batch、Sens_Har、Sens_Perf、Sens_Rev、Sens_Train、Sensitivity、Theory_Rev、Training、Unit_Cost、Workload
A10: INV-009 | B10: Inputs | C10: 16 | D10: 土地 | E10: $M/MW | F10: D16、E16、F16 | G10: 3 | H10: 0.02；0.02；0.02 | I10: Assumed | J10: Assumed | N10: G16: Assumed ｜ H16: v4：100 英畝 × $200K／GW | O10: Assumed | P10: R4 | Q10: 59 | R10: O01、O02、O04、O05、O06、O08、O10、O13、O14 | S10: 0.00042032673 | T10: 低 | U10: 106 | V10: 3875 | W10: Amortize、Cache_Store、Capability、Checks、DC_Cost、Harness、Interface、Perf、Perf_Batch、Sens_Har、Sens_Perf、Sens_Rev、Sens_Train、Sensitivity、Theory_Rev、Training、Unit_Cost、Workload
A11: INV-010 | B11: Inputs | C11: 17 | D11: 建物與基地工程 | E11: $M/MW | F11: D17、E17、F17 | G11: 3 | H11: 3；3.6；4.5 | I11: Assumed | J11: Assumed | L11: S12 | N11: G17: Assumed ｜ H17: 分項為假設；總額以 JLL 校準（S12） | O11: Assumed | P11: R4 | Q11: 59 | R11: O01、O02、O04、O05、O06、O08、O10、O13、O14 | S11: 0.087007633 | T11: 低 | U11: 67 | V11: 3951 | W11: Amortize、Cache_Store、Capability、Checks、DC_Cost、Harness、Interface、Perf、Perf_Batch、Sens_Har、Sens_Perf、Sens_Rev、Sens_Train、Sensitivity、Theory_Rev、Training、Unit_Cost、Workload
A12: INV-011 | B12: Inputs | C12: 18 | D12: 電力設施（變電、中壓、發電機、UPS） | E12: $M/MW | F12: D18、E18、F18 | G12: 3 | H12: 3.8；4.5；5.5 | I12: Assumed | J12: Assumed | N12: G18: Assumed ｜ H18: 同上 | O12: Assumed | P12: R4 | Q12: 59 | R12: O01、O02、O04、O05、O06、O08、O10、O13、O14 | S12: 0.10875954 | T12: 中 | U12: 59 | V12: 3951 | W12: Amortize、Cache_Store、Capability、Checks、DC_Cost、Harness、Interface、Perf、Perf_Batch、Sens_Har、Sens_Perf、Sens_Rev、Sens_Train、Sensitivity、Theory_Rev、Training、Unit_Cost、Workload
A13: INV-012 | B13: Inputs | C13: 19 | D13: 機械與散熱（液冷迴路、散熱設備） | E13: $M/MW | F13: D19、E19、F19 | G13: 3 | H13: 2；2.5；3.2 | I13: Assumed | J13: Assumed | N13: G19: Assumed ｜ H19: 機架內冷板與 manifold 含在機架價格 | O13: Assumed | P13: R4 | Q13: 59 | R13: O01、O02、O04、O05、O06、O08、O10、O13、O14 | S13: 0.060421968 | T13: 低 | U13: 69 | V13: 3951 | W13: Amortize、Cache_Store、Capability、Checks、DC_Cost、Harness、Interface、Perf、Perf_Batch、Sens_Har、Sens_Perf、Sens_Rev、Sens_Train、Sensitivity、Theory_Rev、Training、Unit_Cost、Workload
A14: INV-013 | B14: Inputs | C14: 20 | D14: 光纖、佈線、保全、BMS | E14: $M/MW | F14: D20、E20、F20 | G14: 3 | H14: 0.3；0.4；0.5 | I14: Assumed | J14: Assumed | N14: G20: Assumed ｜ H20: 同上 | O14: Assumed | P14: R4 | Q14: 59 | R14: O01、O02、O04、O05、O06、O08、O10、O13、O14 | S14: 0.0096675148 | T14: 低 | U14: 89 | V14: 3951 | W14: Amortize、Cache_Store、Capability、Checks、DC_Cost、Harness、Interface、Perf、Perf_Batch、Sens_Har、Sens_Perf、Sens_Rev、Sens_Train、Sensitivity、Theory_Rev、Training、Unit_Cost、Workload
A15: INV-014 | B15: Inputs | C15: 21 | D15: 設計、管理與預備費 | E15: % 廠房 | F15: D21、E21、F21 | G15: 3 | H15: 0.12；0.15；0.18 | I15: Assumed | J15: Assumed | N15: G21: Assumed ｜ H21: v4＝15% | O15: Assumed | P15: R4 | Q15: 59 | R15: O01、O02、O04、O05、O06、O08、O10、O13、O14 | S15: 0.034676955 | T15: 低 | U15: 79 | V15: 3951 | W15: Amortize、Cache_Store、Capability、Checks、DC_Cost、Harness、Interface、Perf、Perf_Batch、Sens_Har、Sens_Perf、Sens_Rev、Sens_Train、Sensitivity、Theory_Rev、Training、Unit_Cost、Workload
A16: INV-015 | B16: Inputs | C16: 23 | D16: IT 設備折舊年限 | E16: 年 | F16: D23、E23、F23 | G16: 3 | H16: 6；6；4 | I16: Verified | J16: Verified | L16: S15 | N16: G23: Verified ｜ H23: CoreWeave 與主要 hyperscaler 6 年；Nebius 4 年、Lambda 5 年（S15）。高成本情境取 4 | O16: 原始數據（候選） | P16: R3 | Q16: 57 | R16: O02、O04、O05、O06、O08、O10、O13、O14 | S16: 0.50517384 | T16: 高 | U16: 30 | V16: 3566 | W16: Amortize、Cache_Store、Capability、Checks、DC_Cost、Harness、Interface、Perf、Perf_Batch、Sens_Har、Sens_Perf、Sens_Rev、Sens_Train、Sensitivity、Theory_Rev、Training、Unit_Cost、Workload
A17: INV-016 | B17: Inputs | C17: 24 | D17: 建物年限 | E17: 年 | F17: E24 | G17: 1 | H17: 30 | I17: Analogy | J17: Analogy | N17: G24: Analogy ｜ H24: v4 | O17: Analogy | P17: R4 | Q17: 57 | R17: O02、O04、O05、O06、O08、O10、O13、O14 | S17: 0.0064537158 | T17: 低 | U17: 90 | V17: 3505 | W17: Amortize、Cache_Store、Capability、Checks、DC_Cost、Harness、Inputs、Interface、Perf、Perf_Batch、Sens_Har、Sens_Perf、Sens_Rev、Sens_Train、Sensitivity、Theory_Rev、Training、Unit_Cost、Workload
A18: INV-017 | B18: Inputs | C18: 25 | D18: 電力設施年限 | E18: 年 | F18: E25 | G18: 1 | H18: 20 | I18: Analogy | J18: Analogy | N18: G25: Analogy ｜ H25: v4 | O18: Analogy | P18: R4 | Q18: 57 | R18: O02、O04、O05、O06、O08、O10、O13、O14 | S18: 0.017011547 | T18: 低 | U18: 84 | V18: 3505 | W18: Amortize、Cache_Store、Capability、Checks、DC_Cost、Harness、Inputs、Interface、Perf、Perf_Batch、Sens_Har、Sens_Perf、Sens_Rev、Sens_Train、Sensitivity、Theory_Rev、Training、Unit_Cost、Workload
A19: INV-018 | B19: Inputs | C19: 26 | D19: 機械與散熱年限 | E19: 年 | F19: E26 | G19: 1 | H19: 15 | I19: Analogy | J19: Analogy | N19: G26: Analogy ｜ H26: v4 | O19: Analogy | P19: R4 | Q19: 57 | R19: O02、O04、O05、O06、O08、O10、O13、O14 | S19: 0.01427859 | T19: 低 | U19: 86 | V19: 3505 | W19: Amortize、Cache_Store、Capability、Checks、DC_Cost、Harness、Inputs、Interface、Perf、Perf_Batch、Sens_Har、Sens_Perf、Sens_Rev、Sens_Train、Sensitivity、Theory_Rev、Training、Unit_Cost、Workload
A20: INV-019 | B20: Inputs | C20: 27 | D20: 光纖與保全年限 | E20: 年 | F20: E27 | G20: 1 | H20: 10 | I20: Analogy | J20: Analogy | N20: G27: Analogy ｜ H27: v4 | O20: Analogy | P20: R4 | Q20: 57 | R20: O02、O04、O05、O06、O08、O10、O13、O14 | S20: 0.0037544898 | T20: 低 | U20: 99 | V20: 3505 | W20: Amortize、Cache_Store、Capability、Checks、DC_Cost、Harness、Inputs、Interface、Perf、Perf_Batch、Sens_Har、Sens_Perf、Sens_Rev、Sens_Train、Sensitivity、Theory_Rev、Training、Unit_Cost、Workload
A21: INV-020 | B21: Inputs | C21: 28 | D21: WACC（經濟口徑） | E21: % | F21: D28、E28、F28 | G21: 3 | H21: 0.08；0.1；0.13 | I21: Assumed | J21: Assumed | N21: G28: Assumed ｜ H28: 與擁有者無關的單一假設；下游公司模型以自身 WACC 覆寫（Andy 2026-09-30 決定） | O21: Assumed | P21: R4 | Q21: 53 | R21: O02、O04、O05、O06、O08、O10、O13、O14 | S21: 0.280379 | T21: 中 | U21: 45 | V21: 3289 | W21: Amortize、Cache_Store、Capability、Checks、DC_Cost、Harness、Interface、Perf、Perf_Batch、Sens_Har、Sens_Perf、Sens_Rev、Sens_Train、Sensitivity、Theory_Rev、Training、Unit_Cost、Workload
A22: INV-021 | B22: Inputs | C22: 30 | D22: IT 維護 | E22: % IT 資本/年 | F22: D30、E30、F30 | G22: 3 | H22: 0.02；0.03；0.04 | I22: Analogy | J22: Analogy | N22: G30: Analogy ｜ H30: v4＝3% | O22: Analogy | P22: R4 | Q22: 57 | R22: O02、O04、O05、O06、O08、O10、O13、O14 | S22: 0.088139574 | T22: 低 | U22: 65 | V22: 3503 | W22: Amortize、Cache_Store、Capability、Checks、DC_Cost、Harness、Interface、Perf、Perf_Batch、Sens_Har、Sens_Perf、Sens_Rev、Sens_Train、Sensitivity、Theory_Rev、Training、Unit_Cost、Workload
A23: INV-022 | B23: Inputs | C23: 31 | D23: 廠房維護 | E23: % 廠房資本/年 | F23: D31、E31、F31 | G23: 3 | H23: 0.015；0.02；0.025 | I23: Analogy | J23: Analogy | N23: G31: Analogy ｜ H31: v4＝2% | O23: Analogy | P23: R4 | Q23: 57 | R23: O02、O04、O05、O06、O08、O10、O13、O14 | S23: 0.02102142 | T23: 低 | U23: 81 | V23: 3503 | W23: Amortize、Cache_Store、Capability、Checks、DC_Cost、Harness、Interface、Perf、Perf_Batch、Sens_Har、Sens_Perf、Sens_Rev、Sens_Train、Sensitivity、Theory_Rev、Training、Unit_Cost、Workload
A24: INV-023 | B24: Inputs | C24: 32 | D24: 人員 | E24: $M/GW/年 | F24: D32、E32、F32 | G24: 3 | H24: 50；75；100 | I24: Assumed | J24: Assumed | N24: G32: Assumed ｜ H32: v4：500 FTE × $150K | O24: Assumed | P24: R4 | Q24: 57 | R24: O02、O04、O05、O06、O08、O10、O13、O14 | S24: 0.0062218095 | T24: 低 | U24: 91 | V24: 3503 | W24: Amortize、Cache_Store、Capability、Checks、DC_Cost、Harness、Interface、Perf、Perf_Batch、Sens_Har、Sens_Perf、Sens_Rev、Sens_Train、Sensitivity、Theory_Rev、Training、Unit_Cost、Workload
A25: INV-024 | B25: Inputs | C25: 33 | D25: 軟體授權與連線 | E25: $M/GW/年 | F25: D33、E33、F33 | G25: 3 | H25: 150；200；250 | I25: Assumed | J25: Assumed | N25: G33: Assumed ｜ H33: v4＝$200M | O25: Assumed | P25: R4 | Q25: 57 | R25: O02、O04、O05、O06、O08、O10、O13、O14 | S25: 0.016591492 | T25: 低 | U25: 85 | V25: 3503 | W25: Amortize、Cache_Store、Capability、Checks、DC_Cost、Harness、Interface、Perf、Perf_Batch、Sens_Har、Sens_Perf、Sens_Rev、Sens_Train、Sensitivity、Theory_Rev、Training、Unit_Cost、Workload
A26: INV-025 | B26: Inputs | C26: 34 | D26: 水與耗材 | E26: $M/MW/年 | F26: D34、E34、F34 | G26: 3 | H26: 0.04；0.05；0.06 | I26: Assumed | J26: Assumed | N26: G34: Assumed ｜ H34: v4＝$50K/MW | O26: Assumed | P26: R4 | Q26: 57 | R26: O02、O04、O05、O06、O08、O10、O13、O14 | S26: 0.004147873 | T26: 低 | U26: 96 | V26: 3503 | W26: Amortize、Cache_Store、Capability、Checks、DC_Cost、Harness、Interface、Perf、Perf_Batch、Sens_Har、Sens_Perf、Sens_Rev、Sens_Train、Sensitivity、Theory_Rev、Training、Unit_Cost、Workload
A27: INV-026 | B27: Inputs | C27: 35 | D27: 財產稅與保險 | E27: % 總資本/年 | F27: D35、E35、F35 | G27: 3 | H27: 0.003；0.005；0.008 | I27: Analogy | J27: Analogy | N27: G35: Analogy ｜ H35: v4＝0.5% | O27: Analogy | P27: R4 | Q27: 57 | R27: O02、O04、O05、O06、O08、O10、O13、O14 | S27: 0.019736423 | T27: 低 | U27: 82 | V27: 3503 | W27: Amortize、Cache_Store、Capability、Checks、DC_Cost、Harness、Interface、Perf、Perf_Batch、Sens_Har、Sens_Perf、Sens_Rev、Sens_Train、Sensitivity、Theory_Rev、Training、Unit_Cost、Workload
A28: INV-027 | B28: Spec_Rack | C28: 6 | D28: GPU 封裝／架 | F28: C6、D6、E6、F6、G6 | G28: 5 | H28: 32；72；72；72；144 | O28: 待分類 | P28: R7 | Q28: 92 | R28: O01、O02、O03、O04、O05、O06、O08、O10、O11、O12、O13、O14 | S28: 1.0068666 | T28: 高 | U28: 9 | V28: 5924 | W28: Amortize、Cache_Store、Capability、Checks、DC_Cost、Fleet_1GW、Harness、Interface、Perf、Perf_Batch、Sens_Har、Sens_Perf、Sens_Rev、Sens_Train、Sensitivity、Theory_Rev、Training、Unit_Cost、Workload
A29: INV-028 | B29: Spec_Rack | C29: 8 | D29: 配電設計功率 低（kW） | F29: C8、D8、E8、F8、G8 | G29: 5 | H29: 38；120；132；190；550 | O29: 待分類 | P29: R7 | Q29: 87 | R29: O01、O02、O03、O04、O05、O06、O08、O10、O11、O12、O13、O14 | S29: 0 | T29: 無 | U29: 123 | V29: 5268 | W29: Amortize、Cache_Store、Capability、Checks、DC_Cost、Fleet_1GW、Harness、Interface、Perf、Perf_Batch、Sens_Har、Sens_Perf、Sens_Rev、Sens_Train、Sensitivity、Theory_Rev、Training、Unit_Cost、Workload
A30: INV-029 | B30: Spec_Rack | C30: 9 | D30: 配電設計功率 基準（kW） | F30: C9、D9、E9、F9、G9 | G30: 5 | H30: 41；130；137；227；600 | O30: 待分類 | P30: R7 | Q30: 87 | R30: O01、O02、O03、O04、O05、O06、O08、O10、O11、O12、O13、O14 | S30: 1.010612 | T30: 高 | U30: 6 | V30: 5786 | W30: Amortize、Cache_Store、Capability、Checks、DC_Cost、Fleet_1GW、Harness、Interface、Perf、Perf_Batch、Sens_Har、Sens_Perf、Sens_Rev、Sens_Train、Sensitivity、Theory_Rev、Training、Unit_Cost、Workload
A31: INV-030 | B31: Spec_Rack | C31: 10 | D31: 配電設計功率 高（kW） | F31: C10、D10、E10、F10、G10 | G31: 5 | H31: 44；140；142；230；650 | O31: 待分類 | P31: R7 | Q31: 87 | R31: O01、O02、O03、O04、O05、O06、O08、O10、O11、O12、O13、O14 | S31: 0 | T31: 無 | U31: 124 | V31: 5268 | W31: Amortize、Cache_Store、Capability、Checks、DC_Cost、Fleet_1GW、Harness、Interface、Perf、Perf_Batch、Sens_Har、Sens_Perf、Sens_Rev、Sens_Train、Sensitivity、Theory_Rev、Training、Unit_Cost、Workload
A32: INV-031 | B32: Spec_Rack | C32: 11 | D32: 機架價格 低（$M） | F32: C11、D11、E11、F11、G11 | G32: 5 | H32: 0.9；2.8；4；6.7；23.4 | O32: 待分類 | P32: R7 | Q32: 44 | R32: O10 | S32: 0 | T32: 無 | U32: 111 | V32: 2136 | W32: Amortize、Cache_Store、Capability、Checks、DC_Cost、Interface、Perf、Perf_Batch、Sens_Perf、Sens_Rev、Sens_Train、Sensitivity、Theory_Rev、Training、Unit_Cost
A33: INV-032 | B33: Spec_Rack | C33: 12 | D33: 機架價格 基準（$M） | F33: C12、D12、E12、F12、G12 | G33: 5 | H33: 1.1；3.1；5；7.8；31.2 | O33: 待分類 | P33: R7 | Q33: 59 | R33: O01、O02、O04、O05、O06、O08、O10、O13、O14 | S33: 0.7723573 | T33: 高 | U33: 18 | V33: 3115 | W33: Amortize、Cache_Store、Capability、Checks、DC_Cost、Harness、Interface、Perf、Perf_Batch、Sens_Har、Sens_Perf、Sens_Rev、Sens_Train、Sensitivity、Theory_Rev、Training、Unit_Cost、Workload
A34: INV-033 | B34: Spec_Rack | C34: 13 | D34: 機架價格 高（$M） | F34: C13、D13、E13、F13、G13 | G34: 5 | H34: 1.3；3.4；6.5；9.1；39 | O34: 待分類 | P34: R7 | Q34: 44 | R34: O10 | S34: 0 | T34: 無 | U34: 112 | V34: 2136 | W34: Amortize、Cache_Store、Capability、Checks、DC_Cost、Interface、Perf、Perf_Batch、Sens_Perf、Sens_Rev、Sens_Train、Sensitivity、Theory_Rev、Training、Unit_Cost
A35: INV-034 | B35: Spec_Rack | C35: 23 | D35: 峰值 dense（基準）PF/GPU | F35: C23、D23、E23、F23、G23 | G35: 5 | H35: 1.979；10；15；35；73 | I35: Interested-party、Derived | J35: Interested-party | K35: 多標記 | L35: S28 | N35: H23: Interested-party（NVIDIA 規格）：H100 FP8 dense 1,979 TF（v5.5 更正；v5.4 誤填 BF16 的 989）；GB200 FP4 10 PF（HGX B200 為 9）；B300 15；Rubin NVFP4 訓練 35；RU＝104×35/50 推估 [Derived]。S28 | O35: 原始數據（候選） | P35: R3 | Q35: 92 | R35: O03、O04、O05、O06、O07、O08、O09、O10、O11、O12、O13、O14 | S35: 0.34060378 | T35: 中 | U35: 37 | V35: 7639 | W35: Amortize、Calib、Capability、Checks、Fleet_1GW、Harness、Interface、Perf、Perf_Batch、Sens_Har、Sens_Perf、Sens_Rev、Sens_Train、Spec_Rack、Theory_Rev、Training、Unit_Cost、Workload
A36: INV-035 | B36: Spec_Rack | C36: 24 | D36: 峰值（高情境：NVFP4 推論口徑）PF/GPU | F36: C24、D24、E24、F24、G24 | G36: 5 | H36: 1.979；10；15；50；104 | N36: H24: Rubin 50 PF 含自適應壓縮；RU NVL576 15 EF ÷ 144。J2：只作高情境 | O36: 待分類 | P36: R7 | Q36: 92 | R36: O03、O04、O05、O06、O07、O08、O09、O10、O11、O12、O13、O14 | S36: 0 | T36: 無 | U36: 125 | V36: 7639 | W36: Amortize、Calib、Capability、Checks、Fleet_1GW、Harness、Interface、Perf、Perf_Batch、Sens_Har、Sens_Perf、Sens_Rev、Sens_Train、Spec_Rack、Theory_Rev、Training、Unit_Cost、Workload
A37: INV-036 | B37: Spec_Rack | C37: 25 | D37: HBM 容量 GB/GPU | F37: C25、D25、E25、F25、G25 | G37: 5 | H37: 80；186；288；288；1024 | L37: S28 | N37: H25: GB200 NVL72 13.4 TB ÷ 72；InferenceX 以 192 計。RU HBM4e 約 1 TB/封裝。S28 | O37: 待分類 | P37: R7 | Q37: 92 | R37: O03、O04、O05、O06、O07、O08、O09、O10、O11、O12、O13、O14 | S37: 0.22064113 | T37: 中 | U37: 49 | V37: 7394 | W37: Amortize、Cache_Store、Calib、Capability、Checks、Fleet_1GW、Harness、Interface、Perf、Perf_Batch、Sens_Har、Sens_Perf、Sens_Rev、Sens_Train、Theory_Rev、Training、Unit_Cost、Workload
A38: INV-037 | B38: Spec_Rack | C38: 26 | D38: HBM 頻寬 TB/s/GPU | F38: C26、D26、E26、F26、G26 | G38: 5 | H38: 3.35；8；8；22；32 | L38: S28 | N38: H26: Rubin 22 TB/s（NVIDIA 2026 上修）；RU 4.6 PB/s ÷ 144。S28 | O38: 待分類 | P38: R7 | Q38: 89 | R38: O03、O04、O05、O06、O07、O08、O09、O10、O11、O12、O13、O14 | S38: 0.17829583 | T38: 中 | U38: 54 | V38: 6755 | W38: Amortize、Calib、Capability、Checks、Fleet_1GW、Harness、Interface、Perf、Perf_Batch、Sens_Har、Sens_Perf、Sens_Rev、Sens_Train、Spec_Rack、Theory_Rev、Training、Unit_Cost、Workload
A39: INV-038 | B39: Spec_Rack | C39: 27 | D39: EP 通訊頻寬 TB/s/GPU（單向） | F39: C27、D27、E27、F27、G27 | G39: 5 | H39: 0.05；0.9；0.9；1.8；1.8 | I39: Assumed | J39: Assumed | L39: S20 | N39: H27: Hopper EP 跨節點走 400G IB；NVLink 5＝900 GB/s；NVLink 6＝1.8 TB/s（InferenceX 規格表 S20）；RU 取同 VR [Assumed] | O39: Assumed | P39: R4 | Q39: 89 | R39: O03、O04、O05、O06、O07、O08、O09、O10、O11、O12、O13、O14 | S39: 0 | T39: 無 | U39: 126 | V39: 6591 | W39: Amortize、Calib、Capability、Checks、Fleet_1GW、Harness、Interface、Perf、Perf_Batch、Sens_Har、Sens_Perf、Sens_Rev、Sens_Train、Theory_Rev、Training、Unit_Cost、Workload
A40: INV-039 | B40: Spec_Rack | C40: 28 | D40: Scale-up 域 GPU 數 | F40: C28、D28、E28、F28、G28 | G40: 5 | H40: 8；72；72；72；144 | O40: 待分類 | P40: R7 | Q40: 0 | T40: 無 | V40: 0 | X40: X5a
A41: INV-040 | B41: Spec_Rack | C41: 29 | D41: decode EP 基準寬度 | F41: C29、D29、E29、F29、G29 | G41: 5 | H41: 64；32；32；32；64 | I41: Analogy、Assumed | J41: Analogy | K41: 多標記 | L41: S21 | N41: H29: GB300 公開配方 dep32（S21）；Hopper 跨節點 [Analogy DeepSeek]；RU [Assumed]。權重放不下時自動加寬 | O41: Analogy | P41: R4 | Q41: 89 | R41: O03、O04、O05、O06、O07、O08、O09、O10、O11、O12、O13、O14 | S41: 0.10138279 | T41: 中 | U41: 63 | V41: 7034 | W41: Amortize、Calib、Capability、Checks、Fleet_1GW、Harness、Interface、Perf、Perf_Batch、Sens_Har、Sens_Perf、Sens_Rev、Sens_Train、Theory_Rev、Training、Unit_Cost、Workload
A42: INV-041 | B42: Spec_Rack | C42: 30 | D42: 專家權重 bytes/param | F42: C30、D30、E30、F30、G30 | G42: 5 | H42: 1；0.5625；0.5625；0.5625；0.5625 | N42: H30: NVFP4＝4 bit＋每 16 值 8 bit scale＝0.5625 B；Hopper FP8 | O42: 待分類 | P42: R7 | Q42: 89 | R42: O03、O04、O05、O06、O07、O08、O09、O10、O11、O12、O13、O14 | S42: 0.10057279 | T42: 中 | U42: 64 | V42: 7018 | W42: Amortize、Calib、Capability、Checks、Fleet_1GW、Harness、Interface、Perf、Perf_Batch、Sens_Har、Sens_Perf、Sens_Rev、Sens_Train、Theory_Rev、Training、Unit_Cost、Workload
A43: INV-042 | B43: Spec_Rack | C43: 31 | D43: 非專家權重 bytes/param | F43: C31、D31、E31、F31、G31 | G43: 5 | H43: 1；1；1；1；1 | I43: Analogy | J43: Analogy | N43: H31: 注意力、路由、embedding 以 FP8 存放 [Analogy V4] | O43: Analogy | P43: R4 | Q43: 89 | R43: O03、O04、O05、O06、O07、O08、O09、O10、O11、O12、O13、O14 | S43: 0.31460031 | T43: 中 | U43: 42 | V43: 6821 | W43: Amortize、Calib、Capability、Checks、Fleet_1GW、Harness、Interface、Perf、Perf_Batch、Sens_Har、Sens_Perf、Sens_Rev、Sens_Train、Theory_Rev、Training、Unit_Cost、Workload
A44: INV-043 | B44: Spec_Rack | C44: 32 | D44: 每 prefill 實例 GPU 數（算 TTFT） | F44: C32、D32、E32、F32、G32 | G44: 5 | H44: 8；4；4；4；8 | L44: S21 | N44: H32: GB300 配方 dep4 prefill（S21） | O44: 待分類 | P44: R7 | Q44: 0 | T44: 無 | V44: 192 | W44: Perf、Perf_Batch、Sens_Perf | X44: X5a
A45: INV-044 | B45: Spec_Rack | C45: 33 | D45: GPU 功率 W/封裝（能量用） | F45: C33、D33、E33、F33、G33 | G45: 5 | H45: 700；1200；1400；1800；3600 | I45: Interested-party | J45: Interested-party | N45: H33: Interested-party；Rubin 約 1.8 kW、RU 推估。僅用於能量下限估算 | O45: 原始數據（候選） | P45: R3 | Q45: 0 | T45: 無 | V45: 385 | W45: Checks、Perf、Perf_Batch、Sens_Perf | X45: X5a
A46: INV-045 | B46: Spec_Rack | C46: 34 | D46: HBM 存取能量 pJ/byte | F46: C34、D34、E34、F34、G34 | G46: 5 | H46: 31；25；25；20；18 | I46: Analogy | J46: Analogy | L46: S29 | N46: H34: Analogy：HBM3 約 3.9 pJ/bit、HBM3e 約 3、HBM4 約 2.5；區間 ±30%（S29） | O46: Analogy | P46: R4 | Q46: 0 | T46: 無 | V46: 257 | W46: Checks、Perf、Perf_Batch、Sens_Perf | X46: X5a
A47: INV-046 | B47: Spec_Rack | C47: 39 | D47: BF16 dense PF/GPU | F47: C39、D39、E39、F39、G39 | G47: 5 | H47: 0.989；2.5；2.5；4；8 | I47: Interested-party、Assumed | J47: Interested-party | K47: 多標記 | L47: S36 | N47: H39: Interested-party（NVIDIA）：H100 989 TF；GB200／GB300 2.5；VR NVL72 288 PF ÷ 72＝4.0（S36）；RU 取 VR×2 [Assumed] | O47: 原始數據（候選） | P47: R3 | Q47: 0 | T47: 無 | V47: 0 | X47: X5a
A48: INV-047 | B48: Spec_Rack | C48: 40 | D48: FP8 dense PF/GPU（訓練基準，J7） | F48: C40、D40、E40、F40、G40 | G48: 5 | H48: 1.979；5；5；17.5；34.7 | I48: Interested-party | J48: Interested-party | L48: S36 | N48: H40: Interested-party（NVIDIA）：H100 1,979 TF；GB200／GB300 FP8 5 PF（B300 未提升 FP8）；VR NVL72 1,260 PF ÷ 72＝17.5（S36）；RU NVL576 5 EF ÷ 144 [模型內建知識，待查] | O48: 原始數據（候選） | P48: R3 | Q48: 33 | R48: O07、O08、O09、O10 | S48: 0.73229843 | T48: 高 | U48: 20 | V48: 2563 | W48: Amortize、Checks、Fleet_1GW、Interface、Perf_Batch、Sens_Rev、Sens_Train、Theory_Rev、Training
A49: INV-048 | B49: Spec_Rack | C49: 41 | D49: NVFP4 訓練 dense PF/GPU（Tech_Registry 情境） | F49: C41、D41、E41、F41、G41 | G49: 5 | H49: 1.979；10；15；35；73 | I49: Assumed、Derived | J49: Assumed | K49: 多標記 | L49: S36 | N49: H41: Hopper 無 FP4，取 FP8；GB200 10（NVIDIA：Rubin 為 Blackwell 3.5 倍）；GB300 15 [Assumed，區間 10–15]；VR 2,520 PF ÷ 72＝35（S36）；RU＝VR × 104/50 [Derived] | O49: Assumed | P49: R4 | Q49: 0 | T49: 無 | V49: 66 | W49: Sens_Train | X49: X5a
A50: INV-049 | B50: Arch | C50: 6 | D50: 總參數 | E50: B | F50: C6、D6、E6 | G50: 3 | H50: 284；1600；4000 | I50: Verified、Assumed | J50: Verified | K50: 多標記 | L50: S27 | N50: F6: Verified／Assumed ｜ G6: V4-Flash 284B、V4-Pro 1.6T（模型卡，S27）；Astra 4T [Assumed，區間 2–10T] | O50: 原始數據（候選） | P50: R3 | Q50: 89 | R50: O03、O04、O05、O06、O07、O08、O09、O10、O11、O12、O13、O14 | S50: 0.17212627 | T50: 中 | U50: 55 | V50: 7169 | W50: Amortize、Arch、Calib、Capability、Checks、Fleet_1GW、Harness、Interface、Perf、Perf_Batch、Sens_Har、Sens_Perf、Sens_Rev、Sens_Train、Theory_Rev、Training、Unit_Cost、Workload
A51: INV-050 | B51: Arch | C51: 7 | D51: 啟用參數 | E51: B | F51: C7、D7、E7 | G51: 3 | H51: 13；49；180 | I51: Verified、Assumed | J51: Verified | K51: 多標記 | N51: F7: Verified／Assumed ｜ G7: V4-Flash 13B、V4-Pro 49B；Astra 180B [Assumed，區間 60–250B] | O51: 原始數據（候選） | P51: R3 | Q51: 95 | R51: O03、O04、O05、O06、O07、O08、O09、O10、O11、O12、O13、O14 | S51: 0.64181863 | T51: 高 | U51: 28 | V51: 10005 | W51: Amortize、Arch、Calib、Capability、Checks、Fleet_1GW、Harness、Interface、Perf、Perf_Batch、Sens_Har、Sens_Perf、Sens_Rev、Sens_Train、Theory_Rev、Training、Unit_Cost、Workload
A52: INV-051 | B52: Arch | C52: 8 | D52: 層數 | E52: 層 | F52: C8、D8、E8 | G52: 3 | H52: 43；61；100 | I52: Verified、Assumed | J52: Verified | K52: 多標記 | N52: F8: Verified／Assumed ｜ G8: V4-Pro 61（config.json）；V4-Flash 43（二手）；Astra [Assumed] | O52: 原始數據（候選） | P52: R3 | Q52: 95 | R52: O03、O04、O05、O06、O07、O08、O09、O10、O11、O12、O13、O14 | S52: 0.10389553 | T52: 中 | U52: 60 | V52: 10143 | W52: Amortize、Arch、Calib、Capability、Checks、Fleet_1GW、Harness、Interface、Perf、Perf_Batch、Sens_Har、Sens_Perf、Sens_Rev、Sens_Train、Theory_Rev、Training、Unit_Cost、Workload
A53: INV-052 | B53: Arch | C53: 9 | D53: d_model | F53: C9、D9、E9 | G53: 3 | H53: 4096；7168；12288 | I53: Verified、Assumed、Derived | J53: Verified | K53: 多標記 | N53: F9: Verified／Derived ｜ G9: V4-Pro 7168；V4-Flash 由專家維度反推；Astra [Assumed] | O53: 原始數據（候選） | P53: R3 | Q53: 89 | R53: O03、O04、O05、O06、O07、O08、O09、O10、O11、O12、O13、O14 | S53: 0 | T53: 無 | U53: 127 | V53: 6629 | W53: Amortize、Arch、Calib、Capability、Checks、Fleet_1GW、Harness、Interface、Perf、Perf_Batch、Sens_Har、Sens_Perf、Sens_Rev、Sens_Train、Theory_Rev、Training、Unit_Cost、Workload
A54: INV-053 | B54: Arch | C54: 10 | D54: query heads | F54: C10、D10、E10 | G54: 3 | H54: 64；128；96 | I54: Verified、Analogy | J54: Verified | K54: 多標記 | N54: F10: Verified／Analogy ｜ G10: V4-Pro 128；V4-Flash 取 Pro 一半 [Analogy] | O54: 原始數據（候選） | P54: R3 | Q54: 95 | R54: O03、O04、O05、O06、O07、O08、O09、O10、O11、O12、O13、O14 | S54: 0.10389553 | T54: 中 | U54: 61 | V54: 9445 | W54: Amortize、Arch、Calib、Capability、Checks、Fleet_1GW、Harness、Interface、Perf、Perf_Batch、Sens_Har、Sens_Perf、Sens_Rev、Sens_Train、Theory_Rev、Training、Unit_Cost、Workload
A55: INV-054 | B55: Arch | C55: 11 | D55: head_dim | F55: C11、D11、E11 | G55: 3 | H55: 512；512；128 | I55: Verified、Assumed | J55: Verified | K55: 多標記 | N55: F11: Verified／Assumed ｜ G11: V4 單一 512 維 KV head；Astra 128 | O55: 原始數據（候選） | P55: R3 | Q55: 95 | R55: O03、O04、O05、O06、O07、O08、O09、O10、O11、O12、O13、O14 | S55: 0.10389553 | T55: 中 | U55: 62 | V55: 9445 | W55: Amortize、Arch、Calib、Capability、Checks、Fleet_1GW、Harness、Interface、Perf、Perf_Batch、Sens_Har、Sens_Perf、Sens_Rev、Sens_Train、Theory_Rev、Training、Unit_Cost、Workload
A56: INV-055 | B56: Arch | C56: 12 | D56: routed experts | F56: C12、D12、E12 | G56: 3 | H56: 256；384；512 | I56: Verified、Assumed | J56: Verified | K56: 多標記 | N56: F12: Verified／Assumed | O56: 原始數據（候選） | P56: R3 | Q56: 89 | R56: O03、O04、O05、O06、O07、O08、O09、O10、O11、O12、O13、O14 | S56: 0.26192003 | T56: 中 | U56: 46 | V56: 7169 | W56: Amortize、Arch、Calib、Capability、Checks、Fleet_1GW、Harness、Interface、Perf、Perf_Batch、Sens_Har、Sens_Perf、Sens_Rev、Sens_Train、Theory_Rev、Training、Unit_Cost、Workload
A57: INV-056 | B57: Arch | C57: 13 | D57: 每 token 啟用 routed experts | F57: C13、D13、E13 | G57: 3 | H57: 6；6；16 | I57: Verified、Assumed | J57: Verified | K57: 多標記 | N57: F13: Verified／Assumed | O57: 原始數據（候選） | P57: R3 | Q57: 89 | R57: O03、O04、O05、O06、O07、O08、O09、O10、O11、O12、O13、O14 | S57: 0.24578506 | T57: 中 | U57: 48 | V57: 7305 | W57: Amortize、Arch、Calib、Capability、Checks、Fleet_1GW、Harness、Interface、Perf、Perf_Batch、Sens_Har、Sens_Perf、Sens_Rev、Sens_Train、Theory_Rev、Training、Unit_Cost、Workload
A58: INV-057 | B58: Arch | C58: 14 | D58: shared experts | F58: C14、D14、E14 | G58: 3 | H58: 1；1；1 | I58: Verified | J58: Verified | N58: F14: Verified | O58: 原始數據（候選） | P58: R3 | Q58: 89 | R58: O03、O04、O05、O06、O07、O08、O09、O10、O11、O12、O13、O14 | S58: 0.019331343 | T58: 低 | U58: 83 | V58: 7166 | W58: Amortize、Arch、Calib、Capability、Checks、Fleet_1GW、Harness、Interface、Perf、Perf_Batch、Sens_Har、Sens_Perf、Sens_Rev、Sens_Train、Theory_Rev、Training、Unit_Cost、Workload
A59: INV-058 | B59: Arch | C59: 15 | D59: vocab | F59: C15、D15、E15 | G59: 3 | H59: 129280；129280；200000 | I59: Verified、Assumed | J59: Verified | K59: 多標記 | N59: F15: Verified／Assumed | O59: 原始數據（候選） | P59: R3 | Q59: 0 | T59: 無 | V59: 3 | W59: Arch | X59: X5a
A60: INV-059 | B60: Arch | C60: 16 | D60: 全注意力層比例 | E60: % | F60: C16、D16、E16 | G60: 3 | H60: 0.5；0.5；1 | I60: Verified、Assumed | J60: Verified | K60: 多標記 | N60: F16: Verified／Assumed ｜ G16: V4：CSA 與 HCA 約各半；Astra 全層注意力 | O60: 原始數據（候選） | P60: R3 | Q60: 95 | R60: O03、O04、O05、O06、O07、O08、O09、O10、O11、O12、O13、O14 | S60: 0.32371713 | T60: 中 | U60: 40 | V60: 9583 | W60: Amortize、Calib、Capability、Checks、Fleet_1GW、Harness、Interface、Perf、Perf_Batch、Sens_Har、Sens_Perf、Sens_Rev、Sens_Train、Theory_Rev、Training、Unit_Cost、Workload
A61: INV-060 | B61: Arch | C61: 17 | D61: 全注意力層跨度上限（0＝全上下文） | E61: tok | F61: C17、D17、E17 | G61: 3 | H61: 4224；4224；0 | I61: Derived | J61: Derived | N61: F17: Derived ｜ G17: V4 CSA：top-k 1,024 壓縮塊 × 4 ＋ 128 窗口 | O61: Derived 藍字（異常） | P61: R5 | Q61: 95 | R61: O03、O04、O05、O06、O07、O08、O09、O10、O11、O12、O13、O14 | S61: 0.2819816 | T61: 中 | U61: 44 | V61: 9583 | W61: Amortize、Calib、Capability、Checks、Fleet_1GW、Harness、Interface、Perf、Perf_Batch、Sens_Har、Sens_Perf、Sens_Rev、Sens_Train、Theory_Rev、Training、Unit_Cost、Workload
A62: INV-061 | B62: Arch | C62: 18 | D62: 其他層壓縮比 | E62: x | F62: C18、D18、E18 | G62: 3 | H62: 128；128；1 | I62: Verified | J62: Verified | N62: F18: Verified ｜ G18: V4 HCA 128× 壓縮 | O62: 原始數據（候選） | P62: R3 | Q62: 95 | R62: O03、O04、O05、O06、O07、O08、O09、O10、O11、O12、O13、O14 | S62: 0.0047291072 | T62: 低 | U62: 95 | V62: 9583 | W62: Amortize、Calib、Capability、Checks、Fleet_1GW、Harness、Interface、Perf、Perf_Batch、Sens_Har、Sens_Perf、Sens_Rev、Sens_Train、Theory_Rev、Training、Unit_Cost、Workload
A63: INV-062 | B63: Arch | C63: 19 | D63: 其他層滑動窗 | E63: tok | F63: C19、D19、E19 | G63: 3 | H63: 128；128；0 | I63: Verified | J63: Verified | N63: F19: Verified | O63: 原始數據（候選） | P63: R3 | Q63: 95 | R63: O03、O04、O05、O06、O07、O08、O09、O10、O11、O12、O13、O14 | S63: 0.010094194 | T63: 低 | U63: 88 | V63: 9583 | W63: Amortize、Calib、Capability、Checks、Fleet_1GW、Harness、Interface、Perf、Perf_Batch、Sens_Har、Sens_Perf、Sens_Rev、Sens_Train、Theory_Rev、Training、Unit_Cost、Workload
A64: INV-063 | B64: Arch | C64: 20 | D64: Astra KV 情境（1 混合／2 全層 MLA／3 GQA-8） | E64: 選擇 | F64: E20 | G64: 1 | H64: 2 | I64: Decision | J64: Decision | N64: F20: Decision ｜ G20: J1：基準 2（Andy 2026-09-30 確認） | O64: Decision | P64: R4 | Q64: 93 | R64: O03、O04、O05、O06、O07、O08、O09、O10、O11、O12、O13、O14 | T64: 無 | V64: 6754 | W64: Amortize、Arch、Cache_Store、Capability、Checks、Fleet_1GW、Harness、Interface、Perf、Perf_Batch、Sens_Har、Sens_Perf、Sens_Rev、Sens_Train、Theory_Rev、Training、Unit_Cost、Workload | X64: X2
A65: INV-064 | B65: Arch | C65: 21 | D65: KV bytes/token — 情境 1 | E65: B | F65: C21、D21、E21 | G65: 3 | H65: 2795；3965；14976 | I65: Assumed、Derived | J65: Assumed | K65: 多標記 | N65: F21: Derived／Assumed ｜ G21: Luna 65×43、Sol 65×61（v4 推導，FP8 KV）；Astra 混合：26% 層 × 576 × 100 層（類 K3） | O65: Assumed | P65: R4 | Q65: 95 | R65: O03、O04、O05、O06、O07、O08、O09、O10、O11、O12、O13、O14 | S65: 0.0061067377 | T65: 低 | U65: 92 | V65: 6996 | W65: Amortize、Arch、Cache_Store、Calib、Capability、Checks、Fleet_1GW、Harness、Interface、Perf、Perf_Batch、Sens_Har、Sens_Perf、Sens_Rev、Sens_Train、Theory_Rev、Training、Unit_Cost、Workload
A66: INV-065 | B66: Arch | C66: 22 | D66: KV bytes/token — 情境 2 | E66: B | F66: C22、D22、E22 | G66: 3 | H66: 2795；3965；57600 | I66: Assumed、Derived | J66: Assumed | K66: 多標記 | N66: F22: Derived／Assumed ｜ G22: Astra 全層 MLA：576 × 100 | O66: Assumed | P66: R4 | Q66: 95 | R66: O03、O04、O05、O06、O07、O08、O09、O10、O11、O12、O13、O14 | S66: 0.00023979523 | T66: 低 | U66: 107 | V66: 6996 | W66: Amortize、Arch、Cache_Store、Calib、Capability、Checks、Fleet_1GW、Harness、Interface、Perf、Perf_Batch、Sens_Har、Sens_Perf、Sens_Rev、Sens_Train、Theory_Rev、Training、Unit_Cost、Workload
A67: INV-066 | B67: Arch | C67: 23 | D67: KV bytes/token — 情境 3 | E67: B | F67: C23、D23、E23 | G67: 3 | H67: 2795；3965；204800 | I67: Assumed、Derived | J67: Assumed | K67: 多標記 | N67: F23: Derived／Assumed ｜ G23: Astra GQA-8：8 × 128 × 2 × 100 | O67: Assumed | P67: R4 | Q67: 95 | R67: O03、O04、O05、O06、O07、O08、O09、O10、O11、O12、O13、O14 | S67: 0 | T67: 無 | U67: 128 | V67: 6996 | W67: Amortize、Arch、Cache_Store、Calib、Capability、Checks、Fleet_1GW、Harness、Interface、Perf、Perf_Batch、Sens_Har、Sens_Perf、Sens_Rev、Sens_Train、Theory_Rev、Training、Unit_Cost、Workload
A68: INV-067 | B68: Serving | C68: 6 | D68: MTP 草稿數 N | E68: tok | F68: C6 | G68: 1 | H68: 3 | I68: Analogy | J68: Analogy | N68: D6: Analogy ｜ F6: DeepSeek MTP；區間 1–5 | O68: Analogy | P68: R4 | Q68: 89 | R68: O03、O04、O05、O06、O07、O08、O09、O10、O11、O12、O13、O14 | S68: 0.048994923 | T68: 低 | U68: 76 | V68: 7110 | W68: Amortize、Calib、Capability、Checks、Fleet_1GW、Harness、Interface、Perf、Perf_Batch、Sens_Har、Sens_Perf、Sens_Rev、Sens_Train、Serving、Theory_Rev、Training、Unit_Cost、Workload
A69: INV-068 | B69: Serving | C69: 7 | D69: 每個草稿 token 接受率 α | E69: % | F69: C7 | G69: 1 | H69: 0.7 | I69: Verified | J69: Verified | L69: S21 | N69: D7: Verified-measured ｜ F7: SGLang 修正後 0.57→0.70（S21）；區間 0.6–0.8 | O69: 原始數據（候選） | P69: R3 | Q69: 89 | R69: O03、O04、O05、O06、O07、O08、O09、O10、O11、O12、O13、O14 | S69: 0.18923 | T69: 中 | U69: 52 | V69: 7012 | W69: Amortize、Calib、Capability、Checks、Fleet_1GW、Harness、Interface、Perf、Perf_Batch、Sens_Har、Sens_Perf、Sens_Rev、Sens_Train、Serving、Theory_Rev、Training、Unit_Cost、Workload
A70: INV-069 | B70: Serving | C70: 9 | D70: HBM 保留比例（啟用值、工作區） | E70: % | F70: C9 | G70: 1 | H70: 0.1 | I70: Assumed | J70: Assumed | N70: D9: Assumed ｜ F9: 區間 5–20% | O70: Assumed | P70: R4 | Q70: 89 | R70: O03、O04、O05、O06、O07、O08、O09、O10、O11、O12、O13、O14 | S70: 0 | T70: 無 | U70: 109 | V70: 7173 | W70: Amortize、Calib、Capability、Checks、Fleet_1GW、Harness、Interface、Perf、Perf_Batch、Sens_Har、Sens_Perf、Sens_Rev、Sens_Train、Theory_Rev、Training、Unit_Cost、Workload
A71: INV-070 | B71: Serving | C71: 10 | D71: 非專家權重占可用 HBM 上限 | E71: % | F71: C10 | G71: 1 | H71: 0.2 | I71: Assumed | J71: Assumed | N71: D10: Assumed ｜ F10: 超過時自動以注意力 TP 切分 | O71: Assumed | P71: R4 | Q71: 89 | R71: O03、O04、O05、O06、O07、O08、O09、O10、O11、O12、O13、O14 | S71: 0.22064113 | T71: 中 | U71: 50 | V71: 6820 | W71: Amortize、Calib、Capability、Checks、Fleet_1GW、Harness、Interface、Perf、Perf_Batch、Sens_Har、Sens_Perf、Sens_Rev、Sens_Train、Theory_Rev、Training、Unit_Cost、Workload
A72: INV-071 | B72: Serving | C72: 11 | D72: 專家權重占可用 HBM 上限 | E72: % | F72: C11 | G72: 1 | H72: 0.4 | I72: Assumed | J72: Assumed | N72: D11: Assumed ｜ F11: 超過時自動加寬 EP | O72: Assumed | P72: R4 | Q72: 89 | R72: O03、O04、O05、O06、O07、O08、O09、O10、O11、O12、O13、O14 | S72: 0 | T72: 無 | U72: 110 | V72: 7023 | W72: Amortize、Calib、Capability、Checks、Fleet_1GW、Harness、Interface、Perf、Perf_Batch、Sens_Har、Sens_Perf、Sens_Rev、Sens_Train、Theory_Rev、Training、Unit_Cost、Workload
A73: INV-072 | B73: Serving | C73: 12 | D73: EP 啟用值 bytes/元素（dispatch＋combine） | E73: B | F73: C12 | G73: 1 | H73: 3 | I73: Analogy | J73: Analogy | N73: D12: Analogy ｜ F12: FP8 dispatch 1 B＋BF16 combine 2 B | O73: Analogy | P73: R4 | Q73: 89 | R73: O03、O04、O05、O06、O07、O08、O09、O10、O11、O12、O13、O14 | S73: 0 | T73: 無 | U73: 129 | V73: 6644 | W73: Amortize、Calib、Capability、Checks、Fleet_1GW、Harness、Interface、Perf、Perf_Batch、Sens_Har、Sens_Perf、Sens_Rev、Sens_Train、Theory_Rev、Training、Unit_Cost、Workload
A74: INV-073 | B74: Serving | C74: 13 | D74: KV 讀取頻寬效率 η_mem | E74: % | F74: C13 | G74: 1 | H74: 0.7 | I74: Analogy | J74: Analogy | N74: D13: Analogy ｜ F13: 區間 0.5–0.85 | O74: Analogy | P74: R4 | Q74: 89 | R74: O03、O04、O05、O06、O07、O08、O09、O10、O11、O12、O13、O14 | S74: 0 | T74: 無 | U74: 130 | V74: 6580 | W74: Amortize、Calib、Capability、Checks、Fleet_1GW、Harness、Interface、Perf、Perf_Batch、Sens_Har、Sens_Perf、Sens_Rev、Sens_Train、Theory_Rev、Training、Unit_Cost、Workload
A75: INV-074 | B75: Serving | C75: 14 | D75: EP 通訊效率 η_link | E75: % | F75: C14 | G75: 1 | H75: 0.7 | I75: Analogy | J75: Analogy | N75: D14: Analogy ｜ F14: 區間 0.5–0.85 | O75: Analogy | P75: R4 | Q75: 89 | R75: O03、O04、O05、O06、O07、O08、O09、O10、O11、O12、O13、O14 | S75: 0 | T75: 無 | U75: 131 | V75: 6580 | W75: Amortize、Calib、Capability、Checks、Fleet_1GW、Harness、Interface、Perf、Perf_Batch、Sens_Har、Sens_Perf、Sens_Rev、Sens_Train、Theory_Rev、Training、Unit_Cost、Workload
A76: INV-075 | B76: Serving | C76: 15 | D76: 快取命中 KV 載入頻寬 | E76: TB/s/GPU | F76: C15 | G76: 1 | H76: 0.1 | I76: Assumed | J76: Assumed | N76: D15: Assumed ｜ F15: 主機記憶體／SSD 經 NIC 載入；區間 0.05–0.4。未計快取儲存成本 | O76: Assumed | P76: R4 | Q76: 33 | R76: O10、O13、O14 | S76: 0.0050651299 | T76: 低 | U76: 93 | V76: 1758 | W76: Amortize、Cache_Store、Checks、Harness、Interface、Perf、Perf_Batch、Sens_Har、Sens_Perf、Theory_Rev、Unit_Cost、Workload
A77: INV-076 | B77: Serving | C77: 16 | D77: 峰值情境（1＝dense 基準／2＝NVFP4 推論高） | E77: 選擇 | F77: C16 | G77: 1 | H77: 1 | I77: Decision | J77: Decision | N77: D16: Decision ｜ F16: J2：基準 1 | O77: Decision | P77: R4 | Q77: 92 | R77: O03、O04、O05、O06、O07、O08、O09、O10、O11、O12、O13、O14 | T77: 無 | V77: 7639 | W77: Amortize、Calib、Capability、Checks、Fleet_1GW、Harness、Interface、Perf、Perf_Batch、Sens_Har、Sens_Perf、Sens_Rev、Sens_Train、Spec_Rack、Theory_Rev、Training、Unit_Cost、Workload | X77: X2
A78: INV-077 | B78: Serving | C78: 17 | D78: 基準利用率（第 0 層） | E78: % | F78: C17 | G78: 1 | H78: 0.6 | I78: Assumed | J78: Assumed | N78: D17: Assumed ｜ F17: J6：Andy 尚未給值，暫沿用 OpenAI v0.5 的 60%（區間 40–80%）。Unit_Cost 同時輸出 100% 版 | O78: Assumed | P78: R4 | Q78: 48 | R78: O10、O11、O12、O13、O14 | S78: 1.010101 | T78: 高 | U78: 8 | V78: 2584 | W78: Amortize、Checks、Fleet_1GW、Harness、Interface、Sens_Har、Sens_Rev、Theory_Rev、Unit_Cost、Workload
A79: INV-078 | B79: Serving | C79: 18 | D79: 實測→生產效率折減 | E79: x | F79: C18 | G79: 1 | H79: 1 | I79: Assumed | J79: Assumed | N79: D18: Assumed ｜ F18: 待 Andy 決定。基準測試為固定長度、穩態負載；生產環境另有長度變異、路由不均、故障。1.0＝不折減。作用：η_p、η_d 乘此值，每層延遲除以此值。第二來源（MLPerf、DeepSeek 自揭）目前均高於本模型，見 Calib H 節 | O79: Assumed | P79: R4 | Q79: 92 | R79: O03、O04、O05、O06、O07、O08、O09、O10、O11、O12、O13、O14 | S79: 1.7324417 | T79: 高 | U79: 1 | V79: 7334 | W79: Amortize、Capability、Checks、Fleet_1GW、Harness、Interface、Perf、Perf_Batch、Sens_Har、Sens_Perf、Sens_Rev、Sens_Train、Theory_Rev、Training、Unit_Cost、Workload
A80: INV-079 | B80: Serving | C80: 21 | D80: SLO：每用戶 decode 速度下限 | E80: tok/s | F80: C21、D21、E21 | G80: 3 | H80: 120；65；55 | I80: Verified | J80: Verified | L80: S26 | N80: F21: Verified-measured（市場觀測）：GPT-5.6 Luna 約 120、GPT-5.6 Sol 約 68、GPT-6 Astra 約 52–56、Opus 5 約 54 tok/s（S26）。區間 Luna 100–300、Sol 50–100、Astra 30–75 | O80: 原始數據（候選） | P80: R3 | Q80: 68 | R80: O03、O04、O05、O06、O10、O11、O12、O13、O14 | S80: 0.91385915 | T80: 高 | U80: 14 | V80: 4025 | W80: Amortize、Capability、Checks、Fleet_1GW、Harness、Interface、Perf、Sens_Har、Sens_Perf、Sens_Rev、Theory_Rev、Unit_Cost、Workload
A81: INV-080 | B81: Serving | C81: 22 | D81: TTFT 上限（只作檢查） | E81: s | F81: C22、D22、E22 | G81: 3 | H81: 2；3；5 | I81: Assumed | J81: Assumed | N81: F22: Assumed | O81: Assumed | P81: R4 | Q81: 0 | T81: 無 | V81: 128 | W81: Perf、Perf_Batch、Sens_Perf | X81: X5a
A82: INV-081 | B82: Serving | C82: 23 | D82: 參考 ISL（每次請求輸入） | E82: tok | F82: C23、D23、E23 | G82: 3 | H82: 8192；16384；32768 | I82: Assumed | J82: Assumed | N82: F23: Assumed：Astra 用於長任務；上下文敏感度見 Sens_Perf | O82: Assumed | P82: R4 | Q82: 80 | R82: O03、O04、O05、O06、O10、O11、O12、O13、O14 | S82: 0.70345561 | T82: 高 | U82: 25 | V82: 5159 | W82: Amortize、Capability、Checks、Fleet_1GW、Harness、Interface、Perf、Price_Frontier、Sens_Har、Sens_Perf、Sens_Rev、Serving、Theory_Rev、Unit_Cost、Workload
A83: INV-082 | B83: Serving | C83: 24 | D83: 參考 OSL（含思考） | E83: tok | F83: C24、D24、E24 | G83: 3 | H83: 1024；2048；4096 | I83: Assumed | J83: Assumed | N83: F24: Assumed | O83: Assumed | P83: R4 | Q83: 77 | R83: O03、O04、O05、O06、O10、O11、O12、O13、O14 | S83: 0.74068027 | T83: 高 | U83: 19 | V83: 4717 | W83: Amortize、Capability、Checks、Fleet_1GW、Harness、Interface、Perf、Price_Frontier、Sens_Har、Sens_Perf、Sens_Rev、Serving、Theory_Rev、Unit_Cost、Workload
A84: INV-083 | B84: Workload | C84: 5 | D84: 輪數 T | E84: 輪 | F84: C5、D5、E5、F5、G5 | G84: 5 | H84: 1；1；4；4；30 | I84: Assumed | J84: Assumed | N84: H5: Assumed | O84: Assumed | P84: R4 | Q84: 23 | R84: O13、O14 | S84: 1.1419317 | T84: 高 | U84: 4 | V84: 979 | W84: Checks、Harness、Interface、Sens_Har、Theory_Rev、Workload
A85: INV-084 | B85: Workload | C85: 6 | D85: 初始上下文 S（系統提示、歷史、工具定義） | E85: tok | F85: C6、D6、E6、F6、G6 | G85: 5 | H85: 2000；2000；3000；3000；12000 | I85: Assumed | J85: Assumed | N85: H6: Assumed | O85: Assumed | P85: R4 | Q85: 22 | R85: O13、O14 | S85: 0.047310579 | T85: 低 | U85: 78 | V85: 890 | W85: Checks、Harness、Interface、Sens_Har、Theory_Rev、Workload
A86: INV-085 | B86: Workload | C86: 7 | D86: 每輪新輸入 u（使用者或工具結果） | E86: tok | F86: C7、D7、E7、F7、G7 | G86: 5 | H86: 500；500；1200；1200；2000 | I86: Assumed | J86: Assumed | N86: H7: Assumed | O86: Assumed | P86: R4 | Q86: 22 | R86: O13、O14 | S86: 0.19057515 | T86: 中 | U86: 51 | V86: 922 | W86: Checks、Harness、Interface、Sens_Har、Theory_Rev、Workload
A87: INV-086 | B87: Workload | C87: 8 | D87: 每輪思考 token h | E87: tok | F87: C8、D8、E8、F8、G8 | G87: 5 | H87: 0；3000；400；400；600 | I87: Assumed | J87: Assumed | N87: H8: Assumed；服務端思考占比待查 | O87: Assumed | P87: R4 | Q87: 23 | R87: O13、O14 | S87: 0.4435485 | T87: 中 | U87: 31 | V87: 1016 | W87: Checks、Harness、Interface、Sens_Har、Theory_Rev、Workload
A88: INV-087 | B88: Workload | C88: 9 | D88: 每輪可見輸出 o | E88: tok | F88: C9、D9、E9、F9、G9 | G88: 5 | H88: 500；700；200；200；400 | I88: Assumed | J88: Assumed | N88: H9: Assumed | O88: Assumed | P88: R4 | Q88: 23 | R88: O13、O14 | S88: 0.31856578 | T88: 中 | U88: 41 | V88: 984 | W88: Checks、Harness、Interface、Sens_Har、Theory_Rev、Workload
A89: INV-088 | B89: Workload | C89: 10 | D89: 思考保留於上下文比例 ρ | E89: % | F89: C10、D10、E10、F10、G10 | G89: 5 | H89: 0；0；0；0；0 | I89: Assumed | J89: Assumed | N89: H10: Assumed：多數 API 不保留前輪思考（標準 harness） | O89: Assumed | P89: R4 | Q89: 21 | R89: O13、O14 | T89: 無 | V89: 656 | W89: Checks、Harness、Interface、Sens_Har、Theory_Rev、Workload | X89: X3
A90: INV-089 | B90: Workload | C90: 11 | D90: 歷史快取命中率 χ | E90: % | F90: C11、D11、E11、F11、G11 | G90: 5 | H90: 0.5；0.5；0.9；0.9；0.9 | I90: Assumed | J90: Assumed | N90: H11: Assumed；代理迴圈前綴重用高 | O90: Assumed | P90: R4 | Q90: 22 | R90: O13、O14 | S90: 1.599534 | T90: 高 | U90: 2 | V90: 868 | W90: Checks、Harness、Interface、Sens_Har、Theory_Rev、Workload
A91: INV-090 | B91: Workload | C91: 12 | D91: 並行子代理數 m | E91: 個 | F91: C12、D12、E12、F12、G12 | G91: 5 | H91: 0；0；0；3；0 | I91: Assumed | J91: Assumed | N91: H12: Assumed：子代理沿用單代理參數 | O91: Assumed | P91: R4 | Q91: 23 | R91: O13、O14 | S91: 0 | T91: 無 | U91: 121 | V91: 888 | W91: Checks、Harness、Interface、Sens_Har、Theory_Rev、Workload
A92: INV-091 | B92: Workload | C92: 13 | D92: harness token 倍數 | E92: x | F92: C13、D13、E13、F13、G13 | G92: 5 | H92: 1；1；1；1；1 | N92: H13: v5.9 起為殘差倍數（預設 1.0）；harness 效果改由 Har_In 參數組表達（L1） | O92: 待分類 | P92: R7 | Q92: 23 | R92: O13、O14 | S92: 1 | T92: 高 | U92: 13 | V92: 873 | W92: Checks、Harness、Interface、Sens_Har、Theory_Rev、Workload
A93: INV-092 | B93: Workload | C93: 14 | D93: 歷史保留比 c（壓縮後保留的歷史比例；1＝不壓縮） | E93: x | F93: C14、D14、E14、F14、G14 | G93: 5 | H93: 1；1；1；1；1 | N93: H14: 標準 harness 不壓縮；v5.9 新增（L1） | O93: 待分類 | P93: R7 | Q93: 21 | R93: O13、O14 | S93: 0.13720068 | T93: 中 | U93: 58 | V93: 646 | W93: Checks、Harness、Interface、Sens_Har、Theory_Rev、Workload
A94: INV-093 | B94: Workload | C94: 40 | D94: 參照：Anthropic 揭露倍數（相對聊天） | E94: x | F94: C40、E40、F40 | G94: 3 | H94: 1；4；15 | I94: Interested-party | J94: Interested-party | L94: S25 | N94: H40: Interested-party：Anthropic 2025-06 多代理研究系統文章，agent 約 4 倍、多代理約 15 倍聊天 token（S25）。其『聊天』口徑未說明是否含思考，故兩個倍數並列。本頁列 38 的單代理、多代理倍數高於此參照約 2.3–2.5 倍（Block 2 既有假設，未調整） | O94: 原始數據（候選） | P94: R3 | Q94: 0 | T94: 無 | V94: 0 | X94: X5a
A95: INV-094 | B95: Calib | C95: 5 | D95: η_p：prefill 達成峰值比例 | E95: % | F95: C5 | G95: 1 | H95: 0.3 | I95: Analogy | J95: Analogy | L95: S30 | N95: J5: Analogy：DeepSeek H800 線上 prefill 約 0.37（S30，待查）；區間 0.15–0.45。擬合結果對此不敏感（見 G 節） | O95: Analogy | P95: R4 | Q95: 92 | R95: O03、O04、O05、O06、O07、O08、O09、O10、O11、O12、O13、O14 | S95: 0.34060378 | T95: 中 | U95: 38 | V95: 7507 | W95: Amortize、Calib、Capability、Checks、Fleet_1GW、Harness、Interface、Perf、Perf_Batch、Sens_Har、Sens_Perf、Sens_Rev、Sens_Train、Theory_Rev、Training、Unit_Cost、Workload
A96: INV-095 | B96: Calib | C96: 10 | D96: 世代索引 | F96: C10、D10、E10、F10、G10、H10、I10 | G96: 7 | H96: 3；3；3；3；2；2；3 | O96: 情境選擇 | P96: R6 | Q96: 89 | R96: O03、O04、O05、O06、O07、O08、O09、O10、O11、O12、O13、O14 | T96: 無 | V96: 6912 | W96: Amortize、Calib、Capability、Checks、Fleet_1GW、Harness、Interface、Perf、Perf_Batch、Sens_Har、Sens_Perf、Sens_Rev、Sens_Train、Theory_Rev、Training、Unit_Cost、Workload | X96: X2
A97: INV-096 | B97: Calib | C97: 13 | D97: MTP（1＝有） | F97: C13、D13、E13、F13、G13、H13、I13 | G97: 7 | H97: 1；1；1；0；0；1；1 | O97: 待分類 | P97: R7 | Q97: 89 | R97: O03、O04、O05、O06、O07、O08、O09、O10、O11、O12、O13、O14 | T97: 無 | V97: 6781 | W97: Amortize、Calib、Capability、Checks、Fleet_1GW、Harness、Interface、Perf、Perf_Batch、Sens_Har、Sens_Perf、Sens_Rev、Sens_Train、Theory_Rev、Training、Unit_Cost、Workload | X97: X2
A98: INV-097 | B98: Calib | C98: 14 | D98: 每用戶速度 | E98: tok/s | F98: C14、D14、E14、F14、G14、H14、I14 | G98: 7 | H98: 72；130；50；27；27；110；110 | O98: 待分類 | P98: R7 | Q98: 89 | R98: O03、O04、O05、O06、O07、O08、O09、O10、O11、O12、O13、O14 | S98: 1.1326037 | T98: 高 | U98: 5 | V98: 6780 | W98: Amortize、Calib、Capability、Checks、Fleet_1GW、Harness、Interface、Perf、Perf_Batch、Sens_Har、Sens_Perf、Sens_Rev、Sens_Train、Theory_Rev、Training、Unit_Cost、Workload
A99: INV-098 | B99: Calib | C99: 15 | D99: ISL | E99: tok | F99: C15、D15、E15、F15、G15、H15、I15 | G99: 7 | H99: 8192；8192；8192；8192；8192；8192；8192 | O99: 待分類 | P99: R7 | Q99: 89 | R99: O03、O04、O05、O06、O07、O08、O09、O10、O11、O12、O13、O14 | S99: 0.80163775 | T99: 高 | U99: 17 | V99: 6856 | W99: Amortize、Calib、Capability、Checks、Fleet_1GW、Harness、Interface、Perf、Perf_Batch、Sens_Har、Sens_Perf、Sens_Rev、Sens_Train、Theory_Rev、Training、Unit_Cost、Workload
A100: INV-099 | B100: Calib | C100: 16 | D100: OSL | E100: tok | F100: C16、D16、E16、F16、G16、H16、I16 | G100: 7 | H100: 1024；1024；1024；1024；1024；1024；1024 | O100: 待分類 | P100: R7 | Q100: 89 | R100: O03、O04、O05、O06、O07、O08、O09、O10、O11、O12、O13、O14 | S100: 0.86308469 | T100: 高 | U100: 15 | V100: 6815 | W100: Amortize、Calib、Capability、Checks、Fleet_1GW、Harness、Interface、Perf、Perf_Batch、Sens_Har、Sens_Perf、Sens_Rev、Sens_Train、Theory_Rev、Training、Unit_Cost、Workload
...

Sheet 藍字格
A1: INV_ID | B1: 工作表 | C1: 格位址 | D1: 值 | E1: 型別 | F1: 欄表頭
A2: INV-001 | B2: Inputs | C2: E5 | D2: 1 | E2: 數值 | F2: 基準
A3: INV-002 | B3: Inputs | C3: E6 | D3: 2 | E3: 數值 | F3: 基準
A4: INV-003 | B4: Inputs | C4: E8 | D4: 0.08 | E4: 數值 | F4: 基準
A5: INV-004 | B5: Inputs | C5: D9 | D5: 1.1 | E5: 數值 | F5: 低成本
A6: INV-004 | B6: Inputs | C6: E9 | D6: 1.2 | E6: 數值 | F6: 基準
A7: INV-004 | B7: Inputs | C7: F9 | D7: 1.3 | E7: 數值 | F7: 高成本
A8: INV-005 | B8: Inputs | C8: D10 | D8: 0.7 | E8: 數值 | F8: 低成本
A9: INV-005 | B9: Inputs | C9: E10 | D9: 0.8 | E9: 數值 | F9: 基準
A10: INV-005 | B10: Inputs | C10: F10 | D10: 0.9 | E10: 數值 | F10: 高成本
A11: INV-006 | B11: Inputs | C11: D11 | D11: 0.06 | E11: 數值 | F11: 低成本
A12: INV-006 | B12: Inputs | C12: E11 | D12: 0.08 | E12: 數值 | F12: 基準
A13: INV-006 | B13: Inputs | C13: F11 | D13: 0.1 | E13: 數值 | F13: 高成本
... A241: INV-079 | B241: Serving | C241: D21 | D241: 65 | E241: 數值 | F241: 標記
A242: INV-079 | B242: Serving | C242: E21 | D242: 55 | E242: 數值
A243: INV-080 | B243: Serving | C243: C22 | D243: 2 | E243: 數值 | F243: 值
A244: INV-080 | B244: Serving | C244: D22 | D244: 3 | E244: 數值 | F244: 標記
A245: INV-080 | B245: Serving | C245: E22 | D245: 5 | E245: 數值
A246: INV-081 | B246: Serving | C246: C23 | D246: 8192 | E246: 數值 | F246: 值
A247: INV-081 | B247: Serving | C247: D23 | D247: 16384 | E247: 數值 | F247: 標記
A248: INV-081 | B248: Serving | C248: E23 | D248: 32768 | E248: 數值
A249: INV-082 | B249: Serving | C249: C24 | D249: 1024 | E249: 數值 | F249: 值
A250: INV-082 | B250: Serving | C250: D24 | D250: 2048 | E250: 數值 | F250: 標記
A251: INV-082 | B251: Serving | C251: E24 | D251: 4096 | E251: 數值
A252: INV-083 | B252: Workload | C252: C5 | D252: 1 | E252: 數值 | F252: 一般聊天
A253: INV-083 | B253: Workload | C253: D5 | D253: 1 | E253: 數值 | F253: 推理聊天
A254: INV-083 | B254: Workload | C254: E5 | D254: 4 | E254: 數值 | F254: 單代理（工具迴圈）
A255: INV-083 | B255: Workload | C255: F5 | D255: 4 | E255: 數值 | F255: 多代理研究
A256: INV-083 | B256: Workload | C256: G5 | D256: 30 | E256: 數值 | F256: Coding agent（長程）
A257: INV-084 | B257: Workload | C257: C6 | D257: 2000 | E257: 數值 | F257: 一般聊天
A258: INV-084 | B258: Workload | C258: D6 | D258: 2000 | E258: 數值 | F258: 推理聊天
A259: INV-084 | B259: Workload | C259: E6 | D259: 3000 | E259: 數值 | F259: 單代理（工具迴圈）
A260: INV-084 | B260: Workload | C260: F6 | D260: 3000 | E260: 數值 | F260: 多代理研究
A261: INV-084 | B261: Workload | C261: G6 | D261: 12000 | E261: 數值 | F261: Coding agent（長程）
A262: INV-085 | B262: Workload | C262: C7 | D262: 500 | E262: 數值 | F262: 一般聊天
A263: INV-085 | B263: Workload | C263: D7 | D263: 500 | E263: 數值 | F263: 推理聊天
... A304: INV-093 | B304: Workload | C304: F40 | D304: 15 | E304: 數值 | F304: 多代理研究
A305: INV-094 | B305: Calib | C305: C5 | D305: 0.3 | E305: 數值
A306: INV-095 | B306: Calib | C306: C10 | D306: 3 | E306: 數值 | F306: 擬合點 1
A307: INV-095 | B307: Calib | C307: D10 | D307: 3 | E307: 數值 | F307: 擬合點 2
A308: INV-095 | B308: Calib | C308: E10 | D308: 3 | E308: 數值 | F308: 驗證
A309: INV-095 | B309: Calib | C309: F10 | D309: 3 | E309: 數值 | F309: 驗證（舊軟體）
A310: INV-095 | B310: Calib | C310: G10 | D310: 2 | E310: 數值 | F310: 驗證（舊軟體）
A311: INV-095 | B311: Calib | C311: H10 | D311: 2 | E311: 數值 | F311: 驗證（口徑待查）
A312: INV-095 | B312: Calib | C312: I10 | D312: 3 | E312: 數值 | F312: 驗證（口徑待查）
A313: INV-096 | B313: Calib | C313: C13 | D313: 1 | E313: 數值 | F313: 擬合點 1
A314: INV-096 | B314: Calib | C314: D13 | D314: 1 | E314: 數值 | F314: 擬合點 2
A315: INV-096 | B315: Calib | C315: E13 | D315: 1 | E315: 數值 | F315: 驗證
A316: INV-096 | B316: Calib | C316: F13 | D316: 0 | E316: 數值 | F316: 驗證（舊軟體）
A317: INV-096 | B317: Calib | C317: G13 | D317: 0 | E317: 數值 | F317: 驗證（舊軟體）
... A390: INV-120 | B390: Tech_Registry | C390: H5 | D390: 2 | E390: 數值 | F390: 情境（1／2／3）
A391: INV-120 | B391: Tech_Registry | C391: I5 | D391: 主流 | E391: 文字 | F391: 狀態
A392: INV-120 | B392: Tech_Registry | C392: J5 | D392: 3 | E392: 數值 | F392: 公開採用實驗室數
A393: INV-120 | B393: Tech_Registry | C393: M5 | D393: 是 | E393: 文字 | F393: 已在基準
A394: INV-120 | B394: Tech_Registry | C394: N5 | D394: 1 | E394: 數值 | F394: 採用比例
A395: INV-120 | B395: Tech_Registry | C395: O5 | D395: 1 | E395: 數值 | F395: 開關（0／1）
A396: INV-121 | B396: Tech_Registry | C396: E6 | D396: 1 | E396: 數值 | F396: 倍數 低
A397: INV-121 | B397: Tech_Registry | C397: F6 | D397: 1 | E397: 數值 | F397: 倍數 基準
A398: INV-121 | B398: Tech_Registry | C398: G6 | D398: 1 | E398: 數值 | F398: 倍數 高
A399: INV-121 | B399: Tech_Registry | C399: H6 | D399: 2 | E399: 數值 | F399: 情境（1／2／3）
A400: INV-121 | B400: Tech_Registry | C400: I6 | D400: 主流 | E400: 文字 | F400: 狀態
A401: INV-121 | B401: Tech_Registry | C401: J6 | D401: 3 | E401: 數值 | F401: 公開採用實驗室數
A402: INV-121 | B402: Tech_Registry | C402: M6 | D402: 是 | E402: 文字 | F402: 已在基準
A403: INV-121 | B403: Tech_Registry | C403: N6 | D403: 1 | E403: 數值 | F403: 採用比例
A404: INV-121 | B404: Tech_Registry | C404: O6 | D404: 1 | E404: 數值 | F404: 開關（0／1）
A405: INV-122 | B405: Tech_Registry | C405: E7 | D405: 1 | E405: 數值 | F405: 倍數 低
A406: INV-122 | B406: Tech_Registry | C406: F7 | D406: 1 | E406: 數值 | F406: 倍數 基準
A407: INV-122 | B407: Tech_Registry | C407: G7 | D407: 1 | E407: 數值 | F407: 倍數 高
A408: INV-122 | B408: Tech_Registry | C408: H7 | D408: 2 | E408: 數值 | F408: 情境（1／2／3）
A409: INV-122 | B409: Tech_Registry | C409: I7 | D409: 主流 | E409: 文字 | F409: 狀態
A410: INV-122 | B410: Tech_Registry | C410: J7 | D410: 2 | E410: 數值 | F410: 公開採用實驗室數
A411: INV-122 | B411: Tech_Registry | C411: M7 | D411: 是 | E411: 文字 | F411: 已在基準
A412: INV-122 | B412: Tech_Registry | C412: N7 | D412: 1 | E412: 數值 | F412: 採用比例
A413: INV-122 | B413: Tech_Registry | C413: O7 | D413: 1 | E413: 數值 | F413: 開關（0／1）
A414: INV-123 | B414: Tech_Registry | C414: E8 | D414: 1 | E414: 數值 | F414: 倍數 低
A415: INV-123 | B415: Tech_Registry | C415: F8 | D415: 1 | E415: 數值 | F415: 倍數 基準
A416: INV-123 | B416: Tech_Registry | C416: G8 | D416: 1 | E416: 數值 | F416: 倍數 高
A417: INV-123 | B417: Tech_Registry | C417: H8 | D417: 2 | E417: 數值 | F417: 情境（1／2／3）
A418: INV-123 | B418: Tech_Registry | C418: I8 | D418: 主流 | E418: 文字 | F418: 狀態
A419: INV-123 | B419: Tech_Registry | C419: J8 | D419: 2 | E419: 數值 | F419: 公開採用實驗室數
A420: INV-123 | B420: Tech_Registry | C420: M8 | D420: 是 | E420: 文字 | F420: 已在基準
A421: INV-123 | B421: Tech_Registry | C421: N8 | D421: 1 | E421: 數值 | F421: 採用比例
A422: INV-123 | B422: Tech_Registry | C422: O8 | D422: 1 | E422: 數值 | F422: 開關（0／1）
A423: INV-124 | B423: Tech_Registry | C423: E9 | D423: 1 | E423: 數值 | F423: 倍數 低
A424: INV-124 | B424: Tech_Registry | C424: F9 | D424: 1 | E424: 數值 | F424: 倍數 基準
A425: INV-124 | B425: Tech_Registry | C425: G9 | D425: 1 | E425: 數值 | F425: 倍數 高
A426: INV-124 | B426: Tech_Registry | C426: H9 | D426: 2 | E426: 數值 | F426: 情境（1／2／3）
A427: INV-124 | B427: Tech_Registry | C427: I9 | D427: 主流 | E427: 文字 | F427: 狀態
A428: INV-124 | B428: Tech_Registry | C428: J9 | D428: 2 | E428: 數值 | F428: 公開採用實驗室數
A429: INV-124 | B429: Tech_Registry | C429: M9 | D429: 是 | E429: 文字 | F429: 已在基準
A430: INV-124 | B430: Tech_Registry | C430: N9 | D430: 1 | E430: 數值 | F430: 採用比例
A431: INV-124 | B431: Tech_Registry | C431: O9 | D431: 1 | E431: 數值 | F431: 開關（0／1）
A432: INV-125 | B432: Tech_Registry | C432: E10 | D432: 0.7 | E432: 數值 | F432: 倍數 低
A433: INV-125 | B433: Tech_Registry | C433: F10 | D433: 0.85 | E433: 數值 | F433: 倍數 基準
A434: INV-125 | B434: Tech_Registry | C434: G10 | D434: 1 | E434: 數值 | F434: 倍數 高
A435: INV-125 | B435: Tech_Registry | C435: H10 | D435: 2 | E435: 數值 | F435: 情境（1／2／3）
A436: INV-125 | B436: Tech_Registry | C436: I10 | D436: 早期採用 | E436: 文字 | F436: 狀態
A437: INV-125 | B437: Tech_Registry | C437: J10 | D437: 2 | E437: 數值 | F437: 公開採用實驗室數
A438: INV-125 | B438: Tech_Registry | C438: M10 | D438: 是 | E438: 文字 | F438: 已在基準
A439: INV-125 | B439: Tech_Registry | C439: N10 | D439: 1 | E439: 數值 | F439: 採用比例
...

Sheet 藍字公式格
A1: 工作表 | B1: 格位址 | C1: 公式 | D1: 該列標籤
A2: Calib | B2: C118 | C2: =1000/15 | D2: 每用戶速度下限（1000 ÷ TPOT）
A3: Calib | B3: D118 | C3: =1000/15 | D3: 每用戶速度下限（1000 ÷ TPOT）
A4: Calib | B4: E118 | C4: =1000/15 | D4: 每用戶速度下限（1000 ÷ TPOT）
A5: Calib | B5: F118 | C5: =1000/80 | D5: 每用戶速度下限（1000 ÷ TPOT）
A6: Calib | B6: C120 | C6: =253506/72 | D6: MLPerf 實測輸出 tok/s/GPU（總量 ÷ 72）
A7: Calib | B7: D120 | C7: =240318/72 | D7: MLPerf 實測輸出 tok/s/GPU（總量 ÷ 72）
A8: Calib | B8: E120 | C8: =652750/72 | D8: MLPerf 實測輸出 tok/s/GPU（總量 ÷ 72）
A9: Sens_Perf | B9: AC34 | C9: =Arch!$E$21 | D9: KV bytes/token（含 H_KV）
A10: Sens_Perf | B10: AD34 | C10: =Arch!$E$21 | D10: KV bytes/token（含 H_KV）
A11: Sens_Perf | B11: AE34 | C11: =Arch!$E$22 | D11: KV bytes/token（含 H_KV）
A12: Sens_Perf | B12: AF34 | C12: =Arch!$E$22 | D12: KV bytes/token（含 H_KV）
A13: Sens_Perf | B13: AG34 | C13: =Arch!$E$23 | D13: KV bytes/token（含 H_KV）
A14: Sens_Perf | B14: AH34 | C14: =Arch!$E$23 | D14: KV bytes/token（含 H_KV）
A15: Perf_Batch | B15: R14 | C15: =Spec_Rack!$F$40 | D15: 計算用峰值
A16: Perf_Batch | B16: S14 | C16: =Spec_Rack!$F$40 | D16: 計算用峰值
A17: Sens_Train | B17: I10 | C17: =INDEX(Spec_Rack!$C$41:$G$41,I$6) | D17: FP8 dense 峰值
A18: Sens_Train | B18: J10 | C18: =INDEX(Spec_Rack!$C$41:$G$41,J$6) | D18: FP8 dense 峰值
A19: Sens_Train | B19: O53 | C19: =INDEX(Train_In!$C$34:$E$34,O$7)*0.3 | D19: rollout 輸出 token
A20: Sens_Train | B20: P53 | C20: =INDEX(Train_In!$C$34:$E$34,P$7)*0.3 | D20: rollout 輸出 token
A21: Sens_Train | B21: Q53 | C21: =INDEX(Train_In!$C$34:$E$34,Q$7)*3 | D21: rollout 輸出 token
A22: Sens_Train | B22: R53 | C22: =INDEX(Train_In!$C$34:$E$34,R$7)*3 | D22: rollout 輸出 token
A23: Sens_Train | B23: W59 | C23: =Perf_Batch!R103 | D23: rollout decode GPU 秒／M（Perf_Batch 本層級）
A24: Sens_Train | B24: X59 | C24: =Perf_Batch!S103 | D24: rollout decode GPU 秒／M（Perf_Batch 本層級）
A25: Sens_Train | B25: W60 | C25: =Perf_Batch!R101 | D25: rollout prefill GPU 秒／M
A26: Sens_Train | B26: X60 | C26: =Perf_Batch!S101 | D26: rollout prefill GPU 秒／M
A27: Sens_Train | B27: W61 | C27: =Perf_Batch!R65 | D27: rollout decode FLOPs/token
A28: Sens_Train | B28: X61 | C28: =Perf_Batch!S65 | D28: rollout decode FLOPs/token
A29: Sens_Train | B29: W62 | C29: =Perf_Batch!R67 | D29: rollout prefill FLOPs/token
A30: Sens_Train | B30: X62 | C30: =Perf_Batch!S67 | D30: rollout prefill FLOPs/token
A31: Sens_Train | B31: AA93 | C31: =INDEX(Train_In!$C$37:$E$37,AA$7)*3 | D31: 合成資料 token
A32: Sens_Train | B32: AB93 | C32: =INDEX(Train_In!$C$37:$E$37,AB$7)*3 | D32: 合成資料 token

Sheet 依賴
A1: INV_ID | B1: IF_ 名稱 | C1: 名稱內可達格數 | D1: 擾動是否觀測到改變（空白＝未擾動）
A2: INV-001 | B2: IF_AmortBU_Astra | C2: 15 | D2: 是
A3: INV-001 | B3: IF_AmortBU_Luna | C3: 15 | D3: 是
A4: INV-001 | B4: IF_AmortBU_Sol | C4: 15 | D4: 是
A5: INV-001 | B5: IF_AmortDefault_Astra | C5: 15 | D5: 是
A6: INV-001 | B6: IF_AmortDefault_Luna | C6: 15 | D6: 是
A7: INV-001 | B7: IF_AmortDefault_Sol | C7: 15 | D7: 是
A8: INV-001 | B8: IF_AmortRev_Astra | C8: 15 | D8: 是
A9: INV-001 | B9: IF_AmortRev_Luna | C9: 15 | D9: 是
A10: INV-001 | B10: IF_AmortRev_Sol | C10: 15 | D10: 是
A11: INV-001 | B11: IF_AmortTD_Astra | C11: 15 | D11: 是
A12: INV-001 | B12: IF_AmortTD_Luna | C12: 15 | D12: 是
A13: INV-001 | B13: IF_AmortTD_Sol | C13: 15 | D13: 是
... A88: INV-001 | B88: IF_VReq_Sol | C88: 15 | D88: 是
A89: INV-002 | B89: IF_AmortBU_Astra | C89: 15
A90: INV-002 | B90: IF_AmortBU_Luna | C90: 15
A91: INV-002 | B91: IF_AmortBU_Sol | C91: 15
A92: INV-002 | B92: IF_AmortDefault_Astra | C92: 15
A93: INV-002 | B93: IF_AmortDefault_Luna | C93: 15
A94: INV-002 | B94: IF_AmortDefault_Sol | C94: 15
A95: INV-002 | B95: IF_AmortRev_Astra | C95: 15
A96: INV-002 | B96: IF_AmortRev_Luna | C96: 15
A97: INV-002 | B97: IF_AmortRev_Sol | C97: 15
A98: INV-002 | B98: IF_AmortTD_Astra | C98: 15
A99: INV-002 | B99: IF_AmortTD_Luna | C99: 15
A100: INV-002 | B100: IF_AmortTD_Sol | C100: 15
... A175: INV-002 | B175: IF_VReq_Sol | C175: 15
A176: INV-003 | B176: IF_AmortBU_Astra | C176: 15 | D176: 是
A177: INV-003 | B177: IF_AmortBU_Luna | C177: 15 | D177: 是
A178: INV-003 | B178: IF_AmortBU_Sol | C178: 15 | D178: 是
A179: INV-003 | B179: IF_AmortDefault_Astra | C179: 15 | D179: 是
A180: INV-003 | B180: IF_AmortDefault_Luna | C180: 15 | D180: 是
A181: INV-003 | B181: IF_AmortDefault_Sol | C181: 15 | D181: 是
A182: INV-003 | B182: IF_AmortRev_Astra | C182: 15 | D182: 是
A183: INV-003 | B183: IF_AmortRev_Luna | C183: 15 | D183: 是
A184: INV-003 | B184: IF_AmortRev_Sol | C184: 15 | D184: 是
A185: INV-003 | B185: IF_AmortTD_Astra | C185: 15 | D185: 是
A186: INV-003 | B186: IF_AmortTD_Luna | C186: 15 | D186: 是
A187: INV-003 | B187: IF_AmortTD_Sol | C187: 15 | D187: 是
... A4048: INV-062 | B4048: IF_VReq_Sol | C4048: 15 | D4048: 是
A4049: INV-063 | B4049: IF_AmortBU_Astra | C4049: 15
A4050: INV-063 | B4050: IF_AmortBU_Luna | C4050: 15
A4051: INV-063 | B4051: IF_AmortBU_Sol | C4051: 15
A4052: INV-063 | B4052: IF_AmortDefault_Astra | C4052: 15
A4053: INV-063 | B4053: IF_AmortDefault_Luna | C4053: 15
A4054: INV-063 | B4054: IF_AmortDefault_Sol | C4054: 15
A4055: INV-063 | B4055: IF_AmortRev_Astra | C4055: 15
A4056: INV-063 | B4056: IF_AmortRev_Luna | C4056: 15
A4057: INV-063 | B4057: IF_AmortRev_Sol | C4057: 15
A4058: INV-063 | B4058: IF_AmortTD_Astra | C4058: 15
A4059: INV-063 | B4059: IF_AmortTD_Luna | C4059: 15
A4060: INV-063 | B4060: IF_AmortTD_Sol | C4060: 15
... A4141: INV-063 | B4141: IF_VReq_Sol | C4141: 15
A4142: INV-064 | B4142: IF_AmortBU_Astra | C4142: 15 | D4142: 否
A4143: INV-064 | B4143: IF_AmortBU_Luna | C4143: 15 | D4143: 否
A4144: INV-064 | B4144: IF_AmortBU_Sol | C4144: 15 | D4144: 否
A4145: INV-064 | B4145: IF_AmortDefault_Astra | C4145: 15 | D4145: 是
A4146: INV-064 | B4146: IF_AmortDefault_Luna | C4146: 15 | D4146: 是
A4147: INV-064 | B4147: IF_AmortDefault_Sol | C4147: 15 | D4147: 是
A4148: INV-064 | B4148: IF_AmortRev_Astra | C4148: 15 | D4148: 是
A4149: INV-064 | B4149: IF_AmortRev_Luna | C4149: 15 | D4149: 是
A4150: INV-064 | B4150: IF_AmortRev_Sol | C4150: 15 | D4150: 是
A4151: INV-064 | B4151: IF_AmortTD_Astra | C4151: 15 | D4151: 否
A4152: INV-064 | B4152: IF_AmortTD_Luna | C4152: 15 | D4152: 是
A4153: INV-064 | B4153: IF_AmortTD_Sol | C4153: 15 | D4153: 是
... A5171: INV-075 | B5171: IF_HarR_Sol | C5171: 5 | D5171: 是
A5172: INV-076 | B5172: IF_AmortBU_Astra | C5172: 15
A5173: INV-076 | B5173: IF_AmortBU_Luna | C5173: 15
A5174: INV-076 | B5174: IF_AmortBU_Sol | C5174: 15
A5175: INV-076 | B5175: IF_AmortDefault_Astra | C5175: 15
A5176: INV-076 | B5176: IF_AmortDefault_Luna | C5176: 15
A5177: INV-076 | B5177: IF_AmortDefault_Sol | C5177: 15
A5178: INV-076 | B5178: IF_AmortRev_Astra | C5178: 15
A5179: INV-076 | B5179: IF_AmortRev_Luna | C5179: 15
A5180: INV-076 | B5180: IF_AmortRev_Sol | C5180: 15
A5181: INV-076 | B5181: IF_AmortTD_Astra | C5181: 15
A5182: INV-076 | B5182: IF_AmortTD_Luna | C5182: 15
A5183: INV-076 | B5183: IF_AmortTD_Sol | C5183: 15
... A5263: INV-076 | B5263: IF_VReq_Sol | C5263: 15
A5264: INV-077 | B5264: IF_AmortBU_Astra | C5264: 15 | D5264: 是
A5265: INV-077 | B5265: IF_AmortBU_Luna | C5265: 15 | D5265: 是
A5266: INV-077 | B5266: IF_AmortBU_Sol | C5266: 15 | D5266: 是
A5267: INV-077 | B5267: IF_AmortDefault_Astra | C5267: 15 | D5267: 是
A5268: INV-077 | B5268: IF_AmortDefault_Luna | C5268: 15 | D5268: 是
A5269: INV-077 | B5269: IF_AmortDefault_Sol | C5269: 15 | D5269: 是
A5270: INV-077 | B5270: IF_AmortRev_Astra | C5270: 15 | D5270: 是
A5271: INV-077 | B5271: IF_AmortRev_Luna | C5271: 15 | D5271: 是
A5272: INV-077 | B5272: IF_AmortRev_Sol | C5272: 15 | D5272: 是
A5273: INV-077 | B5273: IF_AmortTD_Astra | C5273: 15 | D5273: 是
A5274: INV-077 | B5274: IF_AmortTD_Luna | C5274: 15 | D5274: 是
A5275: INV-077 | B5275: IF_AmortTD_Sol | C5275: 15 | D5275: 是
... A5741: INV-087 | B5741: IF_TaskTokSel | C5741: 5 | D5741: 是
A5742: INV-088 | B5742: IF_CostAttVR_Astra | C5742: 5
A5743: INV-088 | B5743: IF_CostAttVR_Luna | C5743: 5
A5744: INV-088 | B5744: IF_CostAttVR_Sol | C5744: 5
A5745: INV-088 | B5745: IF_CostSuccGB_Astra | C5745: 5
A5746: INV-088 | B5746: IF_CostSuccGB_Luna | C5746: 5
A5747: INV-088 | B5747: IF_CostSuccGB_Sol | C5747: 5
A5748: INV-088 | B5748: IF_CostSuccVR_Astra | C5748: 5
A5749: INV-088 | B5749: IF_CostSuccVR_Luna | C5749: 5
...

Sheet 敏感度
A1: INV_ID | B1: 輸出 ID | C1: y₀ | D1: y₊ | E1: y₋ | F1: ε₊ | G1: ε₋ | H1: ε | I1: 單邊 | J1: 錯誤／文字結果
A2: INV-001 | B2: O01 | C2: 47.582032 | D2: 52.347128 | E2: 42.825552 | F2: 1.0014486 | G2: 0.99963785 | H2: 1.0005432
A3: INV-001 | B3: O02 | C3: 12.054371 | D3: 13.261632 | E3: 10.84939 | F3: 1.001513 | G3: 0.99962174 | H3: 1.0005674
A4: INV-001 | B4: O03 | C4: 2.3809835e+11 | D4: 2.619552e+11 | E4: 2.1430027e+11 | F4: 1.0019743 | G4: 0.99950642 | H4: 1.0007404
A5: INV-001 | B5: O04 | C5: 0.3225757 | D5: 0.32256217 | E5: 0.32257156 | F5: -0.00041927417 | G5: 0.00012812752 | H5: -0.00014557333
A6: INV-001 | B6: O05 | C6: 1.6606622 | D6: 1.6605925 | E6: 1.6606409 | F6: -0.00041927417 | G6: 0.00012812752 | H6: -0.00014557333
A7: INV-001 | B7: O06 | C7: 0.55698369 | D7: 0.55699208 | E7: 0.55699395 | F7: 0.00015068188 | G7: -0.00018416951 | H7: -1.6743816e-05
A8: INV-001 | B8: O07 | C8: 11677661 | D8: 11677661 | E8: 11677661 | F8: 0 | G8: 0 | H8: 0
A9: INV-001 | B9: O08 | C9: 440.64044 | D9: 440.62197 | E9: 440.6348 | F9: -0.00041927417 | G9: 0.00012812752 | H9: -0.00014557333
A10: INV-001 | B10: O09 | C10: 0.25575637 | D10: 0.25575637 | E10: 0.25575637 | F10: 0 | G10: 0 | H10: 0
A11: INV-001 | B11: O10 | C11: 0.10469626 | D11: 0.10469187 | E11: 0.10469492 | F11: -0.00041915084 | G11: 0.00012808983 | H11: -0.0001455305
A12: INV-001 | B12: O11 | C12: 229.59031 | D12: 252.59467 | E12: 206.64261 | F12: 1.0019743 | G12: 0.99950642 | H12: 1.0007404
A13: INV-001 | B13: O12 | C13: 49.106545 | D13: 54.026895 | E13: 44.198314 | F13: 1.0019743 | G13: 0.99950642 | H13: 1.0007404
... A701: INV-057 | B701: O14 | C701: 0.020916193 | D701: 0.020935366 | E701: 0.020897066 | F701: 0.0091667447 | G701: 0.0091446108 | H701: 0.0091556778
A702: INV-059 | B702: O01 | C702: 47.582032 | E702: 47.582032 | G702: 0 | H702: 0 | I702: 單邊
A703: INV-059 | B703: O02 | C703: 12.054371 | E703: 12.054371 | G703: 0 | H703: 0 | I703: 單邊
A704: INV-059 | B704: O03 | C704: 2.3809835e+11 | E704: 2.3833706e+11 | G704: -0.010025382 | H704: -0.010025382 | I704: 單邊
A705: INV-059 | B705: O04 | C705: 0.3225757 | E705: 0.32533743 | G705: -0.08561503 | H705: -0.08561503 | I705: 單邊
A706: INV-059 | B706: O05 | C706: 1.6606622 | E706: 1.7144206 | G706: -0.32371713 | H706: -0.32371713 | I706: 單邊
A707: INV-059 | B707: O06 | C707: 0.55698369 | E707: 0.56167845 | G707: -0.084288996 | H707: -0.084288996 | I707: 單邊
A708: INV-059 | B708: O07 | C708: 11677661 | E708: 11784919 | G708: -0.091849169 | H708: -0.091849169 | I708: 單邊
A709: INV-059 | B709: O08 | C709: 440.64044 | E709: 444.68769 | G709: -0.091849169 | H709: -0.091849169 | I709: 單邊
A710: INV-059 | B710: O09 | C710: 0.25575637 | E710: 0.25403371 | G710: 0.067355778 | H710: 0.067355778 | I710: 單邊
A711: INV-059 | B711: O10 | C711: 0.10469626 | E711: 0.10517341 | G711: -0.045575039 | H711: -0.045575039 | I711: 單邊
A712: INV-059 | B712: O11 | C712: 229.59031 | E712: 229.82048 | G712: -0.010025382 | H712: -0.010025382 | I712: 單邊
A713: INV-059 | B713: O12 | C713: 49.106545 | E713: 48.474548 | G713: 0.1286991 | H713: 0.1286991 | I713: 單邊
... A715: INV-059 | B715: O14 | C715: 0.020916193 | E715: 0.02093473 | G715: -0.0088624555 | H715: -0.0088624555 | I715: 單邊
A716: INV-060 | B716: O01 | C716: 47.582032 | D716: 47.582032 | E716: 47.582032 | F716: 0 | G716: 0 | H716: 0
A717: INV-060 | B717: O02 | C717: 12.054371 | D717: 12.054371 | E717: 12.054371 | F717: 0 | G717: 0 | H717: 0
A718: INV-060 | B718: O03 | C718: 2.3809835e+11 | D718: 2.3636628e+11 | E718: 2.3883068e+11 | F718: -0.072746181 | G718: -0.030757309 | H718: -0.051751745
A719: INV-060 | B719: O04 | C719: 0.3225757 | D719: 0.32254334 | E719: 0.32454986 | F719: -0.001003145 | G719: -0.06120008 | H719: -0.031101612
A720: INV-060 | B720: O05 | C720: 1.6606622 | D720: 1.6196396 | E720: 1.7132948 | F720: -0.24702534 | G720: -0.31693785 | H720: -0.2819816
A721: INV-060 | B721: O06 | C721: 0.55698369 | D721: 0.55692782 | E721: 0.5603373 | F721: -0.001003145 | G721: -0.060210105 | H721: -0.030606625
A722: INV-060 | B722: O07 | C722: 11677661 | D722: 11598496 | E722: 11781860 | F722: -0.067791777 | G722: -0.089229351 | H722: -0.078510564
A723: INV-060 | B723: O08 | C723: 440.64044 | D723: 437.65326 | E723: 444.57225 | F723: -0.067791777 | G723: -0.089229351 | H723: -0.078510564
A724: INV-060 | B724: O09 | C724: 0.25575637 | D724: 0.25830962 | E724: 0.25370456 | F724: 0.099831318 | G724: 0.080225107 | H724: 0.090028213
A725: INV-060 | B725: O10 | C725: 0.10469626 | D725: 0.10493973 | E725: 0.10496179 | F725: 0.023255413 | G725: -0.025361892 | H725: -0.0010532394
A726: INV-060 | B726: O11 | C726: 229.59031 | D726: 227.92013 | E726: 230.29647 | F726: -0.072746181 | G726: -0.030757309 | H726: -0.051751745
A727: INV-060 | B727: O12 | C727: 49.106545 | D727: 49.487592 | E727: 48.521922 | F727: 0.077596021 | G727: 0.11905195 | H727: 0.098323983
... A1975: INV-246 | B1975: O14 | C1975: 0.020916193 | D1975: 0.023240699 | E1975: 0.01863403 | F1975: 1.1113427 | G1975: 1.0910986 | H1975: 1.1012206
A1976: INV-247 | B1976: O01 | C1976: 47.582032 | E1976: 47.582032 | G1976: 0 | H1976: 0 | I1976: 單邊
A1977: INV-247 | B1977: O02 | C1977: 12.054371 | E1977: 12.054371 | G1977: 0 | H1977: 0 | I1977: 單邊
A1978: INV-247 | B1978: O03 | C1978: 2.3809835e+11 | E1978: 2.3809835e+11 | G1978: 0 | H1978: 0 | I1978: 單邊
A1979: INV-247 | B1979: O04 | C1979: 0.3225757 | E1979: 0.3225757 | G1979: 0 | H1979: 0 | I1979: 單邊
A1980: INV-247 | B1980: O05 | C1980: 1.6606622 | E1980: 1.6606622 | G1980: 0 | H1980: 0 | I1980: 單邊
A1981: INV-247 | B1981: O06 | C1981: 0.55698369 | E1981: 0.55698369 | G1981: 0 | H1981: 0 | I1981: 單邊
A1982: INV-247 | B1982: O07 | C1982: 11677661 | E1982: 11677661 | G1982: 0 | H1982: 0 | I1982: 單邊
A1983: INV-247 | B1983: O08 | C1983: 440.64044 | E1983: 440.64044 | G1983: 0 | H1983: 0 | I1983: 單邊
A1984: INV-247 | B1984: O09 | C1984: 0.25575637 | E1984: 0.25575637 | G1984: 0 | H1984: 0 | I1984: 單邊
A1985: INV-247 | B1985: O10 | C1985: 0.10469626 | E1985: 0.10469626 | G1985: 0 | H1985: 0 | I1985: 單邊
A1986: INV-247 | B1986: O11 | C1986: 229.59031 | E1986: 229.59031 | G1986: 0 | H1986: 0 | I1986: 單邊
A1987: INV-247 | B1987: O12 | C1987: 49.106545 | E1987: 49.106545 | G1987: 0 | H1987: 0 | I1987: 單邊
... A1989: INV-247 | B1989: O14 | C1989: 0.020916193 | E1989: 0.020882587 | G1989: 0.016066765 | H1989: 0.016066765 | I1989: 單邊
A1990: INV-248 | B1990: O01 | C1990: 47.582032 | D1990: 47.582032 | E1990: 47.582032 | F1990: 0 | G1990: 0 | H1990: 0
A1991: INV-248 | B1991: O02 | C1991: 12.054371 | D1991: 12.054371 | E1991: 12.054371 | F1991: 0 | G1991: 0 | H1991: 0
A1992: INV-248 | B1992: O03 | C1992: 2.3809835e+11 | D1992: 2.3809835e+11 | E1992: 2.3809835e+11 | F1992: 0 | G1992: 0 | H1992: 0
A1993: INV-248 | B1993: O04 | C1993: 0.3225757 | D1993: 0.3225757 | E1993: 0.3225757 | F1993: 0 | G1993: 0 | H1993: 0
A1994: INV-248 | B1994: O05 | C1994: 1.6606622 | D1994: 1.6606622 | E1994: 1.6606622 | F1994: 0 | G1994: 0 | H1994: 0
A1995: INV-248 | B1995: O06 | C1995: 0.55698369 | D1995: 0.55698369 | E1995: 0.55698369 | F1995: 0 | G1995: 0 | H1995: 0
A1996: INV-248 | B1996: O07 | C1996: 11677661 | D1996: 11677661 | E1996: 11677661 | F1996: 0 | G1996: 0 | H1996: 0
A1997: INV-248 | B1997: O08 | C1997: 440.64044 | D1997: 440.64044 | E1997: 440.64044 | F1997: 0 | G1997: 0 | H1997: 0
A1998: INV-248 | B1998: O09 | C1998: 0.25575637 | D1998: 0.25575637 | E1998: 0.25575637 | F1998: 0 | G1998: 0 | H1998: 0
A1999: INV-248 | B1999: O10 | C1999: 0.10469626 | D1999: 0.10469626 | E1999: 0.10469626 | F1999: 0 | G1999: 0 | H1999: 0
A2000: INV-248 | B2000: O11 | C2000: 229.59031 | D2000: 229.59031 | E2000: 229.59031 | F2000: 0 | G2000: 0 | H2000: 0
A2001: INV-248 | B2001: O12 | C2001: 49.106545 | D2001: 49.106545 | E2001: 49.106545 | F2001: 0 | G2001: 0 | H2001: 0
... A2171: INV-268 | B2171: O14 | C2171: 0.020916193 | D2171: 0.02149412 | E2171: 0.020323608 | F2171: 0.27630583 | G2171: 0.28331388 | H2171: 0.27980985

Sheet 排序
A1: 排名 | B1: INV_ID | C1: 工作表 | D1: 列 | E1: 標籤 | F1: 初步分類 | G1: 主標記 | H1: 最大 |ε|（O01–O13） | I1: 所屬輸出 | J1: 分段 | K1: Interface 改變格數 | L1: 離散事件（前緣翻轉） | M1: 擾動格數 | N1: 單邊 | O1: O14 |ε|（另列）
A2: 1 | B2: INV-078 | C2: Serving | D2: 18 | E2: 實測→生產效率折減 | F2: Assumed | G2: Assumed | H2: 1.7324417 | I2: O05 | J2: 高 | K2: 1205 | M2: 1 | O2: 1.304788
A3: 2 | B3: INV-089 | C3: Workload | D3: 11 | E3: 歷史快取命中率 χ | F3: Assumed | G3: Assumed | H3: 1.599534 | I3: O13 | J3: 高 | K3: 84 | M3: 5 | O3: 1.2736519
A4: 3 | B4: INV-100 | C4: Calib | D4: 17 | E4: 實測 tok/s/GPU（總 token） | F4: 待分類 | H4: 1.3508007 | I4: O04 | J4: 高 | K4: 1160 | M4: 7 | O4: 1.0231604
A5: 4 | B5: INV-083 | C5: Workload | D5: 5 | E5: 輪數 T | F5: Assumed | G5: Assumed | H5: 1.1419317 | I5: O13 | J5: 高 | K5: 97 | M5: 5 | O5: 1.1012206
A6: 5 | B6: INV-097 | C6: Calib | D6: 14 | E6: 每用戶速度 | F6: 待分類 | H6: 1.1326037 | I6: O05 | J6: 高 | K6: 1160 | M6: 7 | O6: 0.47678638
A7: 6 | B7: INV-029 | C7: Spec_Rack | D7: 9 | E7: 配電設計功率 基準（kW） | F7: 待分類 | H7: 1.010612 | I7: O11 | J7: 高 | K7: 1085 | M7: 5 | O7: 0.23205326
A8: 7 | B8: INV-101 | C8: Calib | D8: 67 | E8: η_d 倍數 | F8: Analogy | G8: Analogy | H8: 1.010101 | I8: O04 | J8: 高 | K8: 1160 | M8: 5 | O8: 0.76509833
A9: 8 | B9: INV-077 | C9: Serving | D9: 17 | E9: 基準利用率（第 0 層） | F9: Assumed | G9: Assumed | H9: 1.010101 | I9: O10 | J9: 高 | K9: 540 | M9: 1 | O9: 1.0030037
A10: 9 | B10: INV-027 | C10: Spec_Rack | D10: 6 | E10: GPU 封裝／架 | F10: 待分類 | H10: 1.0068666 | I10: O08 | J10: 高 | K10: 1124 | M10: 5 | O10: 0.99979198
A11: 10 | B11: INV-001 | C11: Inputs | D11: 5 | E11: IT 電力規模 | F11: Decision | G11: Decision | H11: 1.0007404 | I11: O11 | J11: 高 | K11: 1085 | M11: 1 | O11: 0.00014455047
A12: 11 | B12: INV-152 | C12: Train_In | D12: 13 | E12: 研發倍數（研發總 GPU 小時 ÷ 最終訓練） | F12: Analogy | G12: Analogy | H12: 1 | I12: O08 | J12: 高 | K12: 226 | M12: 1 | O12: 0
A13: 12 | B13: INV-207 | C13: Cap_In | D13: 28 | E13: 對外服務占機隊 | F13: 原始數據（候選） | G13: Interested-party | H13: 1 | I13: O12 | J13: 高 | K13: 391 | M13: 3 | O13: 0
A14: 13 | B14: INV-091 | C14: Workload | D14: 13 | E14: harness token 倍數 | F14: 待分類 | H14: 1 | I14: O13 | J14: 高 | K14: 85 | M14: 5 | O14: 1
A15: 14 | B15: INV-079 | C15: Serving | D15: 21 | E15: SLO：每用戶 decode 速度下限 | F15: 原始數據（候選） | G15: Verified | H15: 0.91385915 | I15: O05 | J15: 高 | K15: 845 | M15: 3 | O15: 0.3560364
A16: 15 | B16: INV-099 | C16: Calib | D16: 16 | E16: OSL | F16: 待分類 | H16: 0.86308469 | I16: O05 | J16: 高 | K16: 1160 | M16: 7 | O16: 0.65159985
A17: 16 | B17: INV-208 | C17: Cap_In | D17: 29 | E17: 其中免費服務占服務 | F17: 原始數據（候選） | G17: Interested-party | H17: 0.85185185 | I17: O12 | J17: 高 | K17: 346 | M17: 3 | O17: 0
A18: 17 | B18: INV-098 | C18: Calib | D18: 15 | E18: ISL | F18: 待分類 | H18: 0.80163775 | I18: O05 | J18: 高 | K18: 1160 | M18: 7 | O18: 0.60207763
A19: 18 | B19: INV-032 | C19: Spec_Rack | D19: 12 | E19: 機架價格 基準（$M） | F19: 待分類 | H19: 0.7723573 | I19: O06 | J19: 高 | K19: 264 | M19: 5 | O19: 0.75779517
A20: 19 | B20: INV-082 | C20: Serving | D20: 24 | E20: 參考 OSL（含思考） | F20: Assumed | G20: Assumed | H20: 0.74068027 | I20: O10 | J20: 高 | K20: 851 | M20: 3 | O20: 0.00036187262
A21: 20 | B21: INV-047 | C21: Spec_Rack | D21: 40 | E21: FP8 dense PF/GPU（訓練基準，J7） | F21: 原始數據（候選） | G21: Interested-party | H21: 0.73229843 | I21: O07 | J21: 高 | K21: 495 | M21: 5 | O21: 0
A22: 21 | B22: INV-145 | C22: Train_In | D22: 6 | E22: 預訓練 MFU 基準（FP8 分母；GB200／GB300） | F22: Analogy | G22: Analogy | H22: 0.73229843 | I22: O07 | J22: 高 | K22: 495 | M22: 1 | O22: 0
A23: 22 | B23: INV-157 | C23: Train_In | D23: 21 | E23: 預訓練 MFU 世代倍數 | F23: Assumed | G23: Assumed | H23: 0.73229843 | I23: O07 | J23: 高 | K23: 495 | M23: 5 | O23: 0
A24: 23 | B24: INV-146 | C24: Train_In | D24: 7 | E24: goodput（扣除故障、重啟、checkpoint 的有效時間比） | F24: Analogy | G24: Analogy | H24: 0.73229843 | I24: O07 | J24: 高 | K24: 495 | M24: 1 | O24: 0
A25: 24 | B25: INV-158 | C25: Train_In | D25: 25 | E25: 預訓練 token | F25: 原始數據（候選） | G25: Verified | H25: 0.72513098 | I25: O09 | J25: 高 | K25: 495 | M25: 3 | O25: 0
A26: 25 | B26: INV-081 | C26: Serving | D26: 23 | E26: 參考 ISL（每次請求輸入） | F26: Assumed | G26: Assumed | H26: 0.70345561 | I26: O10 | J26: 高 | K26: 896 | M26: 3 | O26: 0.0066786353
A27: 26 | B27: INV-102 | C27: Calib | D27: 68 | E27: 每層延遲倍數 | F27: Assumed | G27: Assumed | H27: 0.68655609 | I27: O05 | J27: 高 | K27: 1160 | M27: 5 | O27: 0.29333356
A28: 27 | B28: INV-167 | C28: Train_In | D28: 34 | E28: RL rollout 輸出 token（含各領域專家） | F28: 待分類 | H28: 0.68078555 | I28: O09 | J28: 高 | K28: 495 | M28: 3 | O28: 0
A29: 28 | B29: INV-050 | C29: Arch | D29: 7 | E29: 啟用參數 | F29: 原始數據（候選） | G29: Verified | H29: 0.64181863 | I29: O05 | J29: 高 | K29: 1250 | M29: 3 | O29: 0.13311852
A30: 29 | B30: INV-196 | C30: Cap_In | D30: 8 | E30: 輸出（含思考 token） | F30: 原始數據（候選） | G30: Verified | H30: 0.55309735 | I30: O12 | J30: 高 | K30: 129 | M30: 3 | O30: 0
A31: 30 | B31: INV-015 | C31: Inputs | D31: 23 | E31: IT 設備折舊年限 | F31: 原始數據（候選） | G31: Verified | H31: 0.50517384 | I31: O06 | J31: 高 | K31: 644 | M31: 3 | O31: 0.4944922
A32: 31 | B32: INV-086 | C32: Workload | D32: 8 | E32: 每輪思考 token h | F32: Assumed | G32: Assumed | H32: 0.4435485 | I32: O13 | J32: 中 | K32: 72 | M32: 4 | O32: 0.42921986
A33: 32 | B33: INV-198 | C33: Cap_In | D33: 13 | E33: 參考請求快取命中率 χ（輸入中屬快取命中的比例） | F33: Assumed | G33: Assumed | H33: 0.4380531 | I33: O12 | J33: 中 | K33: 441 | M33: 3 | O33: 0
A34: 33 | B34: INV-148 | C34: Train_In | D34: 9 | E34: RL trainer MFU 係數（× 預訓練 MFU） | F34: Assumed | G34: Assumed | H34: 0.4189445 | I34: O09 | J34: 中 | K34: 495 | M34: 1 | O34: 0
A35: 34 | B35: INV-194 | C35: Cap_In | D35: 6 | E35: 新鮮輸入 | F35: 原始數據（候選） | G35: Verified | H35: 0.39823009 | I35: O12 | J35: 中 | K35: 126 | M35: 3 | O35: 0
A36: 35 | B36: INV-264 | C36: Har_In | D36: 48 | E36: 50% 時間範圍 基準 | F36: Analogy | G36: Analogy | H36: 0.37803485 | I36: O13 | J36: 中 | K36: 109 | M36: 3 | O36: 0.28192696
A37: 36 | B37: INV-268 | C37: Har_In | D37: 53 | E37: 任務長度（人類完成時間） | F37: Assumed | G37: Assumed | H37: 0.37519603 | I37: O13 | J37: 中 | K37: 99 | M37: 5 | O37: 0.27980985
A38: 37 | B38: INV-034 | C38: Spec_Rack | D38: 23 | E38: 峰值 dense（基準）PF/GPU | F38: 原始數據（候選） | G38: Interested-party | H38: 0.34060378 | I38: O04 | J38: 中 | K38: 1205 | M38: 5 | O38: 0.024136772
A39: 38 | B39: INV-094 | C39: Calib | D39: 5 | E39: η_p：prefill 達成峰值比例 | F39: Analogy | G39: Analogy | H39: 0.34060378 | I39: O04 | J39: 中 | K39: 1205 | M39: 1 | O39: 0.024136772
A40: 39 | B40: INV-150 | C40: Train_In | D40: 11 | E40: rollout 效率（長尾等待、權重同步、閒置） | F40: Analogy | G40: Analogy | H40: 0.32472349 | I40: O09 | J40: 中 | K40: 495 | M40: 1 | O40: 0
A41: 40 | B41: INV-059 | C41: Arch | D41: 16 | E41: 全注意力層比例 | F41: 原始數據（候選） | G41: Verified | H41: 0.32371713 | I41: O05 | J41: 中 | K41: 1220 | M41: 3 | N41: 單邊 | O41: 0.0088624555
A42: 41 | B42: INV-087 | C42: Workload | D42: 9 | E42: 每輪可見輸出 o | F42: Assumed | G42: Assumed | H42: 0.31856578 | I42: O13 | J42: 中 | K42: 93 | M42: 5 | O42: 0.35768322
A43: 42 | B43: INV-042 | C43: Spec_Rack | D43: 31 | E43: 非專家權重 bytes/param | F43: Analogy | G43: Analogy | H43: 0.31460031 | I43: O05 | J43: 中 | K43: 1089 | M43: 5 | O43: 0.046058338
A44: 43 | B44: INV-103 | C44: Calib | D44: 69 | E44: η_p 倍數 | F44: 待分類 | H44: 0.29352373 | I44: O11 | J44: 中 | K44: 1115 | M44: 5 | O44: 0.23385266
A45: 44 | B45: INV-060 | C45: Arch | D45: 17 | E45: 全注意力層跨度上限（0＝全上下文） | F45: Derived 藍字（異常） | G45: Derived | H45: 0.2819816 | I45: O05 | J45: 中 | K45: 1220 | M45: 2 | O45: 0.035094608
A46: 45 | B46: INV-020 | C46: Inputs | D46: 28 | E46: WACC（經濟口徑） | F46: Assumed | G46: Assumed | H46: 0.280379 | I46: O05 | J46: 中 | K46: 584 | M46: 3 | O46: 0.27840895
A47: 46 | B47: INV-055 | C47: Arch | D47: 12 | E47: routed experts | F47: 原始數據（候選） | G47: Verified | H47: 0.26192003 | I47: O05 | J47: 中 | K47: 1089 | M47: 3 | O47: 0.065907076
A48: 47 | B48: INV-197 | C48: Cap_In | D48: 12 | E48: 有效折扣（Batch／Flex 半價＋企業議價，加權） | F48: 原始數據（候選） | G48: Verified | H48: 0.25 | I48: O11 | J48: 中 | K48: 243 | M48: 3 | O48: 0
A49: 48 | B49: INV-056 | C49: Arch | D49: 13 | E49: 每 token 啟用 routed experts | F49: 原始數據（候選） | G49: Verified | H49: 0.24578506 | I49: O05 | J49: 中 | K49: 1089 | M49: 3 | O49: 0.055955789
A50: 49 | B50: INV-036 | C50: Spec_Rack | D50: 25 | E50: HBM 容量 GB/GPU | F50: 待分類 | H50: 0.22064113 | I50: O05 | J50: 中 | K50: 618 | M50: 5 | O50: 0
A51: 50 | B51: INV-070 | C51: Serving | D51: 10 | E51: 非專家權重占可用 HBM 上限 | F51: Assumed | G51: Assumed | H51: 0.22064113 | I51: O05 | J51: 中 | K51: 324 | M51: 1 | O51: 0
A52: 51 | B52: INV-085 | C52: Workload | D52: 7 | E52: 每輪新輸入 u（使用者或工具結果） | F52: Assumed | G52: Assumed | H52: 0.19057515 | I52: O13 | J52: 中 | K52: 90 | M52: 5 | O52: 0.15571561
A53: 52 | B53: INV-068 | C53: Serving | D53: 7 | E53: 每個草稿 token 接受率 α | F53: 原始數據（候選） | G53: Verified | H53: 0.18923 | I53: O05 | J53: 中 | K53: 1089 | M53: 1 | O53: 0.1166366
A54: 53 | B54: INV-159 | C54: Train_In | D54: 26 | E54: 預訓練序列長（dense 注意力） | F54: Assumed | G54: Assumed | H54: 0.18073963 | I54: O09 | J54: 中 | K54: 495 | M54: 3 | O54: 0
A55: 54 | B55: INV-037 | C55: Spec_Rack | D55: 26 | E55: HBM 頻寬 TB/s/GPU | F55: 待分類 | H55: 0.17829583 | I55: O05 | J55: 中 | K55: 1089 | M55: 5 | O55: 0.10993235
A56: 55 | B56: INV-049 | C56: Arch | D56: 6 | E56: 總參數 | F56: 原始數據（候選） | G56: Verified | H56: 0.17212627 | I56: O05 | J56: 中 | K56: 1089 | M56: 3 | O56: 0.002234483
A57: 56 | B57: INV-165 | C57: Train_In | D57: 32 | E57: rollout 參考輸入（prompt＋工具結果） | F57: Assumed | G57: Assumed | H57: 0.14245212 | I57: O09 | J57: 中 | K57: 540 | M57: 3 | O57: 0
A58: 57 | B58: INV-166 | C58: Train_In | D58: 33 | E58: rollout 參考輸出（含思考） | F58: Assumed | G58: Assumed | H58: 0.13842676 | I58: O09 | J58: 中 | K58: 540 | M58: 3 | O58: 0
A59: 58 | B59: INV-092 | C59: Workload | D59: 14 | E59: 歷史保留比 c（壓縮後保留的歷史比例；1＝不壓縮） | F59: 待分類 | H59: 0.13720068 | I59: O13 | J59: 中 | K59: 54 | M59: 5 | O59: 0
A60: 59 | B60: INV-011 | C60: Inputs | D60: 18 | E60: 電力設施（變電、中壓、發電機、UPS） | F60: Assumed | G60: Assumed | H60: 0.10875954 | I60: O01 | J60: 中 | K60: 674 | M60: 3 | O60: 0.060728885
A61: 60 | B61: INV-051 | C61: Arch | D61: 8 | E61: 層數 | F61: 原始數據（候選） | G61: Verified | H61: 0.10389553 | I61: O09 | J61: 中 | K61: 1250 | M61: 3 | O61: 0.0022597139
A62: 61 | B62: INV-053 | C62: Arch | D62: 10 | E62: query heads | F62: 原始數據（候選） | G62: Verified | H62: 0.10389553 | I62: O09 | J62: 中 | K62: 1250 | M62: 3 | O62: 0.0022597139
A63: 62 | B63: INV-054 | C63: Arch | D63: 11 | E63: head_dim | F63: 原始數據（候選） | G63: Verified | H63: 0.10389553 | I63: O09 | J63: 中 | K63: 1250 | M63: 3 | O63: 0.0022597139
A64: 63 | B64: INV-040 | C64: Spec_Rack | D64: 29 | E64: decode EP 基準寬度 | F64: Analogy | G64: Analogy | H64: 0.10138279 | I64: O05 | J64: 中 | K64: 1089 | M64: 5 | O64: 0.063604867
A65: 64 | B65: INV-041 | C65: Spec_Rack | D65: 30 | E65: 專家權重 bytes/param | F65: 待分類 | H65: 0.10057279 | I65: O05 | J65: 中 | K65: 1089 | M65: 5 | O65: 0.063074705
A66: 65 | B66: INV-021 | C66: Inputs | D66: 30 | E66: IT 維護 | F66: Analogy | G66: Analogy | H66: 0.088139574 | I66: O06 | J66: 低 | K66: 644 | M66: 3 | O66: 0.086275908
A67: 66 | B67: INV-003 | C67: Inputs | D67: 8 | E67: 機架外 IT 電力占比 | F67: Assumed | G67: Assumed | H67: 0.087611056 | I67: O11 | J67: 低 | K67: 1040 | M67: 1 | O67: 0.020322211
A68: 67 | B68: INV-010 | C68: Inputs | D68: 17 | E68: 建物與基地工程 | F68: Assumed | G68: Assumed | H68: 0.087007633 | I68: O01 | J68: 低 | K68: 674 | M68: 3 | O68: 0.04470205
A69: 68 | B69: INV-007 | C69: Inputs | D69: 13 | E69: Scale-out 網路 ÷ 機架價格 | F69: Analogy | G69: Analogy | H69: 0.0702143 | I69: O06 | J69: 低 | K69: 674 | M69: 3 | O69: 0.06889047
A70: 69 | B70: INV-012 | C70: Inputs | D70: 19 | E70: 機械與散熱（液冷迴路、散熱設備） | F70: Assumed | G70: Assumed | H70: 0.060421968 | I70: O01 | J70: 低 | K70: 674 | M70: 3 | O70: 0.037057197
A71: 70 | B71: INV-168 | C71: Train_In | D71: 35 | E71: On-policy 蒸餾：學生 rollout 輸出 token | F71: Assumed | G71: Assumed | H71: 0.059777109 | I71: O09 | J71: 低 | K71: 495 | M71: 3 | O71: 0
A72: 71 | B72: INV-164 | C72: Train_In | D72: 31 | E72: 批次推論速度下限（rollout、合成、評測） | F72: Assumed | G72: Assumed | H72: 0.05738803 | I72: O07 | J72: 低 | K72: 495 | M72: 3 | O72: 0
A73: 72 | B73: INV-170 | C73: Train_In | D73: 37 | E73: 合成資料生成 token | F73: Assumed | G73: Assumed | H73: 0.056276865 | I73: O07 | J73: 低 | K73: 405 | M73: 3 | O73: 0
A74: 73 | B74: INV-005 | C74: Inputs | D74: 10 | E74: 平均用電 ÷ 配電設計功率 | F74: Assumed | G74: Assumed | H74: 0.055811125 | I74: O04 | J74: 低 | K74: 704 | M74: 3 | O74: 0.055418974
A75: 74 | B75: INV-004 | C75: Inputs | D75: 9 | E75: PUE | F75: Analogy | G75: Analogy | H75: 0.055811125 | I75: O04 | J75: 低 | K75: 674 | M75: 3 | O75: 0.055418974
A76: 75 | B76: INV-006 | C76: Inputs | D76: 11 | E76: 電價 | F76: 原始數據（候選） | G76: Verified | H76: 0.055811125 | I76: O04 | J76: 低 | K76: 659 | M76: 3 | O76: 0.055418974
A77: 76 | B77: INV-067 | C77: Serving | D77: 6 | E77: MTP 草稿數 N | F77: Analogy | G77: Analogy | H77: 0.048994923 | I77: O04 | J77: 低 | K77: 1089 | M77: 1 | O77: 0.037111075
... A103: 102 | B103: INV-215 | C103: Cap_In | D103: 40 | E103: DRAM 折舊年限 | F103: Assumed | G103: Assumed | H103: 0.001103292 | I103: O13 | J103: 低 | K103: 329 | M103: 3 | O103: 0.0070973567
A104: 103 | B104: INV-212 | C104: Cap_In | D104: 37 | E104: 保留時間 | F104: Analogy | G104: Analogy | H104: 0.0010922591 | I104: O13 | J104: 低 | K104: 334 | L104: IF_FrontSuccVRName（+10%） | M104: 3 | O104: 0
A105: 104 | B105: INV-214 | C105: Cap_In | D105: 39 | E105: DRAM 取得成本 | F105: Assumed | G105: Assumed | H105: 0.0010922591 | I105: O13 | J105: 低 | K105: 329 | M105: 3 | O105: 0.0070263831
A106: 105 | B106: INV-151 | C106: Train_In | D106: 12 | E106: GRPO 每題取樣數（共用 prompt，prefill 只算一次） | F106: Analogy | G106: Analogy | H106: 0.00063330434 | I106: O09 | J106: 低 | K106: 540 | M106: 1 | O106: 0
A107: 106 | B107: INV-009 | C107: Inputs | D107: 16 | E107: 土地 | F107: Assumed | G107: Assumed | H107: 0.00042032673 | I107: O01 | J107: 低 | K107: 674 | M107: 3 | O107: 0.00020593642
A108: 107 | B108: INV-065 | C108: Arch | D108: 22 | E108: KV bytes/token — 情境 2 | F108: Assumed | G108: Assumed | H108: 0.00023979523 | I108: O10 | J108: 低 | K108: 213 | M108: 3 | O108: 0
A109: 108 | B109: INV-163 | C109: Train_In | D109: 30 | E109: SFT 序列長 | F109: Assumed | G109: Assumed | H109: 0.00010135402 | I109: O07 | J109: 低 | K109: 495 | M109: 3 | O109: 0
A110: 109 | B110: INV-069 | C110: Serving | D110: 9 | E110: HBM 保留比例（啟用值、工作區） | F110: Assumed | G110: Assumed | H110: 0 | I110: O13 | J110: 無 | K110: 300 | M110: 1 | O110: 0
A111: 110 | B111: INV-071 | C111: Serving | D111: 11 | E111: 專家權重占可用 HBM 上限 | F111: Assumed | G111: Assumed | H111: 0 | I111: O13 | J111: 無 | K111: 300 | M111: 1 | O111: 0
A112: 111 | B112: INV-031 | C112: Spec_Rack | D112: 11 | E112: 機架價格 低（$M） | F112: 待分類 | H112: 0 | I112: O13 | J112: 無 | K112: 205 | M112: 5 | O112: 0
A113: 112 | B113: INV-033 | C113: Spec_Rack | D113: 13 | E113: 機架價格 高（$M） | F113: 待分類 | H113: 0 | I113: O13 | J113: 無 | K113: 205 | M113: 5 | O113: 0
A114: 113 | B114: INV-204 | C114: Cap_In | D114: 22 | E114: 商業壽命 基準 | F114: Assumed | G114: Assumed | H114: 0 | I114: O13 | J114: 無 | K114: 93 | M114: 3 | O114: 0
A115: 114 | B115: INV-267 | C115: Har_In | D115: 51 | E115: 斜率 β（C＝基準、D＝低、E＝高） | F115: Derived 藍字（異常） | G115: Derived | H115: 0 | I115: O13 | J115: 無 | K115: 90 | M115: 3 | O115: 0.1939354
A116: 115 | B116: INV-253 | C116: Har_In | D116: 19 | E116: 時間範圍倍數（本任務） | F116: Assumed | G116: Assumed | H116: 0 | I116: O13 | J116: 無 | K116: 42 | L116: IF_FrontSuccVRName（+10%） | M116: 5 | O116: 0.28192696
A117: 116 | B117: INV-246 | C117: Har_In | D117: 12 | E117: 輪數倍數 | F117: Assumed | G117: Assumed | H117: 0 | I117: O13 | J117: 無 | K117: 32 | L117: IF_FrontSuccVRName（-10%） | M117: 5 | O117: 1.1012206
A118: 117 | B118: INV-248 | C118: Har_In | D118: 14 | E118: 每輪思考倍數 | F118: Assumed | G118: Assumed | H118: 0 | I118: O13 | J118: 無 | K118: 25 | L118: IF_FrontSuccVRName（-10%） | M118: 5 | O118: 0.42921986
A119: 118 | B119: INV-252 | C119: Har_In | D119: 18 | E119: 狀態保留時間 | F119: Analogy | G119: Analogy | H119: 0 | I119: O13 | J119: 無 | K119: 22 | L119: IF_FrontSuccVRName（-10%） | M119: 5 | O119: 0.0070263831
A120: 119 | B120: INV-247 | C120: Har_In | D120: 13 | E120: 思考保留 ρ | F120: 原始數據（候選） | G120: Verified | H120: 0 | I120: O13 | J120: 無 | K120: 18 | M120: 3 | N120: 單邊 | O120: 0.016066765
A121: 120 | B121: INV-249 | C121: Har_In | D121: 15 | E121: 歷史保留比 c（壓縮後） | F121: Assumed | G121: Assumed | H121: 0 | I121: O13 | J121: 無 | K121: 18 | M121: 5 | O121: 0.096400592
A122: 121 | B122: INV-090 | C122: Workload | D122: 12 | E122: 並行子代理數 m | F122: Assumed | G122: Assumed | H122: 0 | I122: O13 | J122: 無 | K122: 17 | M122: 1 | O122: 0
A123: 122 | B123: INV-245 | C123: Har_In | D123: 8 | E123: 可靠度下限 p_min（成功任務成本前緣只比較 p ≥ 此值者） | F123: Decision | G123: Decision | H123: 0 | I123: O13 | J123: 無 | K123: 1 | M123: 1 | O123: 0
A124: 123 | B124: INV-028 | C124: Spec_Rack | D124: 8 | E124: 配電設計功率 低（kW） | F124: 待分類 | H124: 0 | I124: O13 | J124: 無 | K124: 0 | M124: 5 | O124: 0
A125: 124 | B125: INV-030 | C125: Spec_Rack | D125: 10 | E125: 配電設計功率 高（kW） | F125: 待分類 | H125: 0 | I125: O13 | J125: 無 | K125: 0 | M125: 5 | O125: 0
...

Sheet 各輸出前5
A1: 輸出 ID | B1: 名次 | C1: INV_ID | D1: 工作表 | E1: 列 | F1: 標籤 | G1: 初步分類 | H1: 主標記 | I1: |ε|
A2: O01 | B2: 1 | C2: INV-001 | D2: Inputs | E2: 5 | F2: IT 電力規模 | G2: Decision | H2: Decision | I2: 1.0005432
A3: O01 | B3: 2 | C3: INV-029 | D3: Spec_Rack | E3: 9 | F3: 配電設計功率 基準（kW） | G3: 待分類 | I3: 0.74150932
A4: O01 | B4: 3 | C4: INV-032 | D4: Spec_Rack | E4: 12 | F4: 機架價格 基準（$M） | G4: 待分類 | I4: 0.73065732
A5: O01 | B5: 4 | C5: INV-011 | D5: Inputs | E5: 18 | F5: 電力設施（變電、中壓、發電機、UPS） | G5: Assumed | H5: Assumed | I5: 0.10875954
A6: O01 | B6: 5 | C6: INV-010 | D6: Inputs | E6: 17 | F6: 建物與基地工程 | G6: Assumed | H6: Assumed | I6: 0.087007633
A7: O02 | B7: 1 | C7: INV-001 | D7: Inputs | E7: 5 | F7: IT 電力規模 | G7: Decision | H7: Decision | I7: 1.0005674
A8: O02 | B8: 2 | C8: INV-029 | D8: Spec_Rack | E8: 9 | F8: 配電設計功率 基準（kW） | G8: 待分類 | I8: 0.77449211
A9: O02 | B9: 3 | C9: INV-032 | D9: Spec_Rack | E9: 12 | F9: 機架價格 基準（$M） | G9: 待分類 | I9: 0.76315741
A10: O02 | B10: 4 | C10: INV-015 | D10: Inputs | E10: 23 | F10: IT 設備折舊年限 | G10: 原始數據（候選） | H10: Verified | I10: 0.49799128
A11: O02 | B11: 5 | C11: INV-020 | D11: Inputs | E11: 28 | F11: WACC（經濟口徑） | G11: Assumed | H11: Assumed | I11: 0.280379
A12: O03 | B12: 1 | C12: INV-078 | D12: Serving | E12: 18 | F12: 實測→生產效率折減 | G12: Assumed | H12: Assumed | I12: 1.2741023
A13: O03 | B13: 2 | C13: INV-029 | D13: Spec_Rack | E13: 9 | F13: 配電設計功率 基準（kW） | G13: 待分類 | I13: 1.010612
A14: O03 | B14: 3 | C14: INV-001 | D14: Inputs | E14: 5 | F14: IT 電力規模 | G14: Decision | H14: Decision | I14: 1.0007404
A15: O03 | B15: 4 | C15: INV-027 | D15: Spec_Rack | E15: 6 | F15: GPU 封裝／架 | G15: 待分類 | I15: 1
A16: O03 | B16: 5 | C16: INV-100 | D16: Calib | E16: 17 | F16: 實測 tok/s/GPU（總 token） | G16: 待分類 | I16: 0.94671767
A17: O04 | B17: 1 | C17: INV-078 | D17: Serving | E17: 18 | F17: 實測→生產效率折減 | G17: Assumed | H17: Assumed | I17: 1.4138743
A18: O04 | B18: 2 | C18: INV-100 | D18: Calib | E18: 17 | F18: 實測 tok/s/GPU（總 token） | G18: 待分類 | I18: 1.3508007
A19: O04 | B19: 3 | C19: INV-101 | D19: Calib | E19: 67 | F19: η_d 倍數 | G19: Analogy | H19: Analogy | I19: 1.010101
A20: O04 | B20: 4 | C20: INV-027 | D20: Spec_Rack | E20: 6 | F20: GPU 封裝／架 | G20: 待分類 | I20: 1.0068666
A21: O04 | B21: 5 | C21: INV-099 | D21: Calib | E21: 16 | F21: OSL | G21: 待分類 | I21: 0.86025761
A22: O05 | B22: 1 | C22: INV-078 | D22: Serving | E22: 18 | F22: 實測→生產效率折減 | G22: Assumed | H22: Assumed | I22: 1.7324417
A23: O05 | B23: 2 | C23: INV-100 | D23: Calib | E23: 17 | F23: 實測 tok/s/GPU（總 token） | G23: 待分類 | I23: 1.3252981
A24: O05 | B24: 3 | C24: INV-097 | D24: Calib | E24: 14 | F24: 每用戶速度 | G24: 待分類 | I24: 1.1326037
A25: O05 | B25: 4 | C25: INV-101 | D25: Calib | E25: 67 | F25: η_d 倍數 | G25: Analogy | H25: Analogy | I25: 1.010101
A26: O05 | B26: 5 | C26: INV-027 | D26: Spec_Rack | E26: 6 | F26: GPU 封裝／架 | G26: 待分類 | I26: 1.0068666
A27: O06 | B27: 1 | C27: INV-078 | D27: Serving | E27: 18 | F27: 實測→生產效率折減 | G27: Assumed | H27: Assumed | I27: 1.4830322
A28: O06 | B28: 2 | C28: INV-100 | D28: Calib | E28: 17 | F28: 實測 tok/s/GPU（總 token） | G28: 待分類 | I28: 1.3452042
A29: O06 | B29: 3 | C29: INV-101 | D29: Calib | E29: 67 | F29: η_d 倍數 | G29: Analogy | H29: Analogy | I29: 1.010101
A30: O06 | B30: 4 | C30: INV-027 | D30: Spec_Rack | E30: 6 | F30: GPU 封裝／架 | G30: 待分類 | I30: 1.0049945
A31: O06 | B31: 5 | C31: INV-099 | D31: Calib | E31: 16 | F31: OSL | G31: 待分類 | I31: 0.86087786
A32: O07 | B32: 1 | C32: INV-047 | D32: Spec_Rack | E32: 40 | F32: FP8 dense PF/GPU（訓練基準，J7） | G32: 原始數據（候選） | H32: Interested-party | I32: 0.73229843
A33: O07 | B33: 2 | C33: INV-145 | D33: Train_In | E33: 6 | F33: 預訓練 MFU 基準（FP8 分母；GB200／GB300） | G33: Analogy | H33: Analogy | I33: 0.73229843
A34: O07 | B34: 3 | C34: INV-157 | D34: Train_In | E34: 21 | F34: 預訓練 MFU 世代倍數 | G34: Assumed | H34: Assumed | I34: 0.73229843
A35: O07 | B35: 4 | C35: INV-146 | D35: Train_In | E35: 7 | F35: goodput（扣除故障、重啟、checkpoint 的有效時間比） | G35: Analogy | H35: Analogy | I35: 0.73229843
A36: O07 | B36: 5 | C36: INV-050 | D36: Arch | E36: 7 | F36: 啟用參數 | G36: 原始數據（候選） | H36: Verified | I36: 0.52038413
A37: O08 | B37: 1 | C37: INV-027 | D37: Spec_Rack | E37: 6 | F37: GPU 封裝／架 | G37: 待分類 | I37: 1.0068666
A38: O08 | B38: 2 | C38: INV-152 | D38: Train_In | E38: 13 | F38: 研發倍數（研發總 GPU 小時 ÷ 最終訓練） | G38: Analogy | H38: Analogy | I38: 1
A39: O08 | B39: 3 | C39: INV-032 | D39: Spec_Rack | E39: 12 | F39: 機架價格 基準（$M） | G39: 待分類 | I39: 0.76315741
A40: O08 | B40: 4 | C40: INV-047 | D40: Spec_Rack | E40: 40 | F40: FP8 dense PF/GPU（訓練基準，J7） | G40: 原始數據（候選） | H40: Interested-party | I40: 0.73229843
A41: O08 | B41: 5 | C41: INV-145 | D41: Train_In | E41: 6 | F41: 預訓練 MFU 基準（FP8 分母；GB200／GB300） | G41: Analogy | H41: Analogy | I41: 0.73229843
A42: O09 | B42: 1 | C42: INV-158 | D42: Train_In | E42: 25 | F42: 預訓練 token | G42: 原始數據（候選） | H42: Verified | I42: 0.72513098
A43: O09 | B43: 2 | C43: INV-167 | D43: Train_In | E43: 34 | F43: RL rollout 輸出 token（含各領域專家） | G43: 待分類 | I43: 0.68078555
A44: O09 | B44: 3 | C44: INV-100 | D44: Calib | E44: 17 | F44: 實測 tok/s/GPU（總 token） | G44: 待分類 | I44: 0.44128026
A45: O09 | B45: 4 | C45: INV-148 | D45: Train_In | E45: 9 | F45: RL trainer MFU 係數（× 預訓練 MFU） | G45: Assumed | H45: Assumed | I45: 0.4189445
A46: O09 | B46: 5 | C46: INV-078 | D46: Serving | E46: 18 | F46: 實測→生產效率折減 | G46: Assumed | H46: Assumed | I46: 0.35654121
A47: O10 | B47: 1 | C47: INV-078 | D47: Serving | E47: 18 | F47: 實測→生產效率折減 | G47: Assumed | H47: Assumed | I47: 1.4134556
A48: O10 | B48: 2 | C48: INV-100 | D48: Calib | E48: 17 | F48: 實測 tok/s/GPU（總 token） | G48: 待分類 | I48: 1.1608758
A49: O10 | B49: 3 | C49: INV-077 | D49: Serving | E49: 17 | F49: 基準利用率（第 0 層） | G49: Assumed | H49: Assumed | I49: 1.010101
A50: O10 | B50: 4 | C50: INV-027 | D50: Spec_Rack | E50: 6 | F50: GPU 封裝／架 | G50: 待分類 | I50: 1.0065704
A51: O10 | B51: 5 | C51: INV-101 | D51: Calib | E51: 67 | F51: η_d 倍數 | G51: Analogy | H51: Analogy | I51: 0.87066044
A52: O11 | B52: 1 | C52: INV-078 | D52: Serving | E52: 18 | F52: 實測→生產效率折減 | G52: Assumed | H52: Assumed | I52: 1.2741023
A53: O11 | B53: 2 | C53: INV-029 | D53: Spec_Rack | E53: 9 | F53: 配電設計功率 基準（kW） | G53: 待分類 | I53: 1.010612
A54: O11 | B54: 3 | C54: INV-001 | D54: Inputs | E54: 5 | F54: IT 電力規模 | G54: Decision | H54: Decision | I54: 1.0007404
A55: O11 | B55: 4 | C55: INV-027 | D55: Spec_Rack | E55: 6 | F55: GPU 封裝／架 | G55: 待分類 | I55: 1
A56: O11 | B56: 5 | C56: INV-077 | D56: Serving | E56: 17 | F56: 基準利用率（第 0 層） | G56: Assumed | H56: Assumed | I56: 1
A57: O12 | B57: 1 | C57: INV-078 | D57: Serving | E57: 18 | F57: 實測→生產效率折減 | G57: Assumed | H57: Assumed | I57: 1.4330976
A58: O12 | B58: 2 | C58: INV-029 | D58: Spec_Rack | E58: 9 | F58: 配電設計功率 基準（kW） | G58: 待分類 | I58: 1.010612
A59: O12 | B59: 3 | C59: INV-001 | D59: Inputs | E59: 5 | F59: IT 電力規模 | G59: Decision | H59: Decision | I59: 1.0007404
A60: O12 | B60: 4 | C60: INV-027 | D60: Spec_Rack | E60: 6 | F60: GPU 封裝／架 | G60: 待分類 | I60: 1
A61: O12 | B61: 5 | C61: INV-077 | D61: Serving | E61: 17 | F61: 基準利用率（第 0 層） | G61: Assumed | H61: Assumed | I61: 1
A62: O13 | B62: 1 | C62: INV-089 | D62: Workload | E62: 11 | F62: 歷史快取命中率 χ | G62: Assumed | H62: Assumed | I62: 1.599534
A63: O13 | B63: 2 | C63: INV-078 | D63: Serving | E63: 18 | F63: 實測→生產效率折減 | G63: Assumed | H63: Assumed | I63: 1.302421
A64: O13 | B64: 3 | C64: INV-083 | D64: Workload | E64: 5 | F64: 輪數 T | G64: Assumed | H64: Assumed | I64: 1.1419317
A65: O13 | B65: 4 | C65: INV-077 | D65: Serving | E65: 17 | F65: 基準利用率（第 0 層） | G65: Assumed | H65: Assumed | I65: 1.0089977
A66: O13 | B66: 5 | C66: INV-027 | D66: Spec_Rack | E66: 6 | F66: GPU 封裝／架 | G66: 待分類 | I66: 1.0057668
A67: O14 | B67: 1 | C67: INV-078 | D67: Serving | E67: 18 | F67: 實測→生產效率折減 | G67: Assumed | H67: Assumed | I67: 1.304788
A68: O14 | B68: 2 | C68: INV-089 | D68: Workload | E68: 11 | F68: 歷史快取命中率 χ | G68: Assumed | H68: Assumed | I68: 1.2736519
A69: O14 | B69: 3 | C69: INV-083 | D69: Workload | E69: 5 | F69: 輪數 T | G69: Assumed | H69: Assumed | I69: 1.1012206
A70: O14 | B70: 4 | C70: INV-246 | D70: Har_In | E70: 12 | F70: 輪數倍數 | G70: Assumed | H70: Assumed | I70: 1.1012206
A71: O14 | B71: 5 | C71: INV-100 | D71: Calib | E71: 17 | F71: 實測 tok/s/GPU（總 token） | G71: 待分類 | I71: 1.0231604

Sheet 不擾動
A1: INV_ID | B1: 工作表 | C1: 列 | D1: 標籤 | E1: 初步分類 | F1: 原因代碼 | G1: 靜態可達主要輸出 | H1: 可達 IF_ 數
A2: INV-002 | B2: Inputs | C2: 6 | D2: 功率情境（1 低／2 基準／3 高） | E2: Decision | F2: X2 | G2: O01、O02、O03、O04、O05、O06、O08、O10、O11、O12、O13、O14 | H2: 87
A3: INV-039 | B3: Spec_Rack | C3: 28 | D3: Scale-up 域 GPU 數 | E3: 待分類 | F3: X5a | H3: 0
A4: INV-043 | B4: Spec_Rack | C4: 32 | D4: 每 prefill 實例 GPU 數（算 TTFT） | E4: 待分類 | F4: X5a | H4: 0
A5: INV-044 | B5: Spec_Rack | C5: 33 | D5: GPU 功率 W/封裝（能量用） | E5: 原始數據（候選） | F5: X5a | H5: 0
A6: INV-045 | B6: Spec_Rack | C6: 34 | D6: HBM 存取能量 pJ/byte | E6: Analogy | F6: X5a | H6: 0
A7: INV-046 | B7: Spec_Rack | C7: 39 | D7: BF16 dense PF/GPU | E7: 原始數據（候選） | F7: X5a | H7: 0
A8: INV-048 | B8: Spec_Rack | C8: 41 | D8: NVFP4 訓練 dense PF/GPU（Tech_Registry 情境） | E8: Assumed | F8: X5a | H8: 0
A9: INV-058 | B9: Arch | C9: 15 | D9: vocab | E9: 原始數據（候選） | F9: X5a | H9: 0
A10: INV-063 | B10: Arch | C10: 20 | D10: Astra KV 情境（1 混合／2 全層 MLA／3 GQA-8） | E10: Decision | F10: X2 | G10: O03、O04、O05、O06、O07、O08、O09、O10、O11、O12、O13、O14 | H10: 93
A11: INV-076 | B11: Serving | C11: 16 | D11: 峰值情境（1＝dense 基準／2＝NVFP4 推論高） | E11: Decision | F11: X2 | G11: O03、O04、O05、O06、O07、O08、O09、O10、O11、O12、O13、O14 | H11: 92
A12: INV-080 | B12: Serving | C12: 22 | D12: TTFT 上限（只作檢查） | E12: Assumed | F12: X5a | H12: 0
A13: INV-088 | B13: Workload | C13: 10 | D13: 思考保留於上下文比例 ρ | E13: Assumed | F13: X3 | G13: O13、O14 | H13: 21
A14: INV-093 | B14: Workload | C14: 40 | D14: 參照：Anthropic 揭露倍數（相對聊天） | E14: 原始數據（候選） | F14: X5a | H14: 0
A15: INV-095 | B15: Calib | C15: 10 | D15: 世代索引 | E15: 情境選擇 | F15: X2 | G15: O03、O04、O05、O06、O07、O08、O09、O10、O11、O12、O13、O14 | H15: 89
A16: INV-096 | B16: Calib | C16: 13 | D16: MTP（1＝有） | E16: 待分類 | F16: X2 | G16: O03、O04、O05、O06、O07、O08、O09、O10、O11、O12、O13、O14 | H16: 89
A17: INV-104 | B17: Calib | C17: 90 | D17: η_p | E17: 待分類 | F17: X5a | H17: 0
A18: INV-105 | B18: Calib | C18: 100 | D18: 總參數 | E18: 原始數據（候選） | F18: X5a | H18: 0
A19: INV-106 | B19: Calib | C19: 101 | D19: 啟用參數 | E19: 待分類 | F19: X5a | H19: 0
A20: INV-107 | B20: Calib | C20: 102 | D20: 層數 | E20: 待分類 | F20: X5a | H20: 0
A21: INV-108 | B21: Calib | C21: 103 | D21: d_model | E21: 待分類 | F21: X5a | H21: 0
A22: INV-109 | B22: Calib | C22: 104 | D22: routed experts | E22: 待分類 | F22: X5a | H22: 0
A23: INV-110 | B23: Calib | C23: 105 | D23: 啟用 experts | E23: 待分類 | F23: X5a | H23: 0
A24: INV-111 | B24: Calib | C24: 106 | D24: shared experts | E24: 待分類 | F24: X5a | H24: 0
A25: INV-112 | B25: Calib | C25: 107 | D25: vocab | E25: 待分類 | F25: X5a | H25: 0
A26: INV-113 | B26: Calib | C26: 108 | D26: KV bytes/token（MLA 576 × 61 層，FP8） | E26: 待分類 | F26: X5a | H26: 0
A27: INV-114 | B27: Calib | C27: 109 | D27: 注意力 FLOPs／被注意 token（MLA：2×128×192＋2×128×128，× 61） | E27: 待分類 | F27: X5a | H27: 0
A28: INV-115 | B28: Calib | C28: 110 | D28: 平均 ISL（MLCommons 資料集） | E28: 待分類 | F28: X5a | H28: 0
... A32: INV-119 | B32: Calib | C32: 120 | D32: MLPerf 實測輸出 tok/s/GPU（總量 ÷ 72） | E32: 待分類 | F32: X5a | H32: 0
A33: INV-132 | B33: Perf | C33: 6 | D33: 世代索引 | E33: 情境選擇 | F33: X2 | G33: O03、O04、O05、O06、O10、O11、O12、O13、O14 | H33: 71
A34: INV-133 | B34: Perf | C34: 7 | D34: 層級索引 | E34: 情境選擇 | F34: X2 | G34: O03、O04、O05、O06、O10、O11、O12、O13、O14 | H34: 74
A35: INV-134 | B35: Sens_Perf | C35: 6 | D35: 世代索引 | E35: 情境選擇 | F35: X2 | H35: 0
A36: INV-135 | B36: Sens_Perf | C36: 7 | D36: 層級索引 | E36: 情境選擇 | F36: X2 | H36: 0
A37: INV-136 | B37: Sens_Perf | C37: 14 | D37: 計算用峰值 | E37: 情境選擇 | F37: X2 | H37: 0
A38: INV-137 | B38: Sens_Perf | C38: 41 | D38: SLO：每用戶 decode 速度下限 | E38: 情境選擇 | F38: X2 | H38: 0
A39: INV-138 | B39: Sens_Perf | C39: 43 | D39: 參考 ISL | E39: 情境選擇 | F39: X2 | H39: 0
A40: INV-139 | B40: Sens_Perf | C40: 48 | D40: 草稿接受率 | E40: 情境選擇 | F40: X5a | H40: 0
A41: INV-140 | B41: Sens_Perf | C41: 50 | D41: 實測→生產效率折減 | E41: 情境選擇 | F41: X5a | H41: 0
A42: INV-141 | B42: Sens_Perf | C42: 52 | D42: η_d 倍數（Tech_Registry H_ETAD；Sens_Perf 情境覆寫） | E42: 情境選擇 | F42: X5a | H42: 0
A43: INV-142 | B43: Sens_Perf | C43: 54 | D43: 每層延遲倍數（Tech_Registry H_TL；Sens_Perf 情境覆寫） | E43: 情境選擇 | F43: X5a | H43: 0
A44: INV-143 | B44: Unit_Cost | C44: 6 | D44: 世代索引 | E44: 情境選擇 | F44: X2 | G44: O03、O04、O05、O06、O07、O08、O09、O10、O11、O12、O13、O14 | H44: 98
A45: INV-144 | B45: Train_In | C45: 5 | D45: 訓練精度（MFU 分母） | E45: Decision | F45: X1 | H45: 0
A46: INV-149 | B46: Train_In | C46: 10 | D46: 參考模型前向（KL 懲罰；0＝無、1＝有） | E46: Assumed | F46: X2 | G46: O07、O08、O09、O10 | H46: 36
A47: INV-153 | B47: Train_In | C47: 14 | D47: 研發歸屬 | E47: Decision | F47: X1 | H47: 0
A48: INV-154 | B48: Train_In | C48: 15 | D48: 合成資料生成層級（1 Luna／2 Sol／3 Astra） | E48: Assumed | F48: X2 | G48: O07、O08、O10 | H48: 27
A49: INV-155 | B49: Train_In | C49: 16 | D49: 下游預設訓練世代（世代索引） | E49: Decision | F49: X2 | H49: 2
A50: INV-156 | B50: Train_In | C50: 17 | D50: 並列訓練世代（世代索引） | E50: Decision | F50: X2 | H50: 2
A51: INV-169 | B51: Train_In | C51: 36 | D51: 蒸餾教師層級（1／2／3） | E51: 原始數據（候選） | F51: X2 | G51: O07、O08、O09、O10 | H51: 33
A52: INV-172 | B52: Train_In | C52: 41 | D52: DeepSeek V3 預訓練 token | E52: 原始數據（候選） | F52: X5a | H52: 0
A53: INV-173 | B53: Train_In | C53: 42 | D53: DeepSeek V3 預訓練 H800 GPU 小時 | E53: 待分類 | F53: X5a | H53: 0
A54: INV-174 | B54: Train_In | C54: 43 | D54: DeepSeek V3 預訓練序列長 | E54: 待分類 | F54: X5a | H54: 0
A55: INV-175 | B55: Train_In | C55: 44 | D55: DeepSeek R1 RL GPU 小時 ÷ V3 預訓練 | E55: 待分類 | F55: X5a | H55: 0
A56: INV-176 | B56: Train_In | C56: 45 | D56: Grok 4 RL ÷ 預訓練（宣稱） | E56: 原始數據（候選） | F56: X5a | H56: 0
A57: INV-177 | B57: Train_In | C57: 46 | D57: 前沿預訓練錨點 低 | E57: Analogy | F57: X5a | H57: 0
A58: INV-178 | B58: Train_In | C58: 47 | D58: 前沿預訓練錨點 中 | E58: 待分類 | F58: X5a | H58: 0
A59: INV-179 | B59: Train_In | C59: 48 | D59: 前沿預訓練錨點 高 | E59: 待分類 | F59: X5a | H59: 0
A60: INV-180 | B60: Perf_Batch | C60: 6 | D60: 世代索引 | E60: 情境選擇 | F60: X2 | G60: O07、O08、O09、O10 | H60: 33
A61: INV-181 | B61: Perf_Batch | C61: 7 | D61: 層級索引 | E61: 情境選擇 | F61: X2 | G61: O07、O08、O09、O10 | H61: 36
A62: INV-182 | B62: Perf_Batch | C62: 19 | D62: 專家權重 bytes/param（含 H_WB） | E62: 待分類 | F62: X5a | H62: 0
A63: INV-183 | B63: Perf_Batch | C63: 20 | D63: 非專家權重 bytes/param（含 H_WB） | E63: 待分類 | F63: X5a | H63: 0
A64: INV-184 | B64: Training | C64: 6 | D64: 世代索引 | E64: 情境選擇 | F64: X2 | G64: O07、O08、O09、O10 | H64: 36
A65: INV-185 | B65: Training | C65: 7 | D65: 層級索引 | E65: 情境選擇 | F65: X2 | G65: O07、O08、O09、O10 | H65: 36
A66: INV-186 | B66: Sens_Train | C66: 6 | D66: 世代索引 | E66: 情境選擇 | F66: X2 | H66: 0
A67: INV-187 | B67: Sens_Train | C67: 7 | D67: 層級索引 | E67: 情境選擇 | F67: X2 | H67: 0
A68: INV-188 | B68: Sens_Train | C68: 13 | D68: 預訓練 MFU 基準 | E68: 情境選擇 | F68: X5a | H68: 0
A69: INV-189 | B69: Sens_Train | C69: 17 | D69: goodput | E69: 情境選擇 | F69: X5a | H69: 0
A70: INV-190 | B70: Sens_Train | C70: 30 | D70: 所需 token 倍數（H_TOK） | E70: 情境選擇 | F70: X5a | H70: 0
A71: INV-191 | B71: Sens_Train | C71: 64 | D71: rollout 效率（採用） | E71: 情境選擇 | F71: X5a | H71: 0
A72: INV-192 | B72: Sens_Train | C72: 93 | D72: 合成資料 token | E72: 情境選擇 | F72: X2 | H72: 0
A73: INV-193 | B73: Sens_Train | C73: 119 | D73: 研發倍數 | E73: 情境選擇 | F73: X5a | H73: 0
A74: INV-201 | B74: Cap_In | C74: 16 | D74: 尖峰／離峰口徑（1＝尖峰價；2＝依時數加權） | E74: Decision | F74: X2 | H74: 13
A75: INV-202 | B75: Cap_In | C75: 17 | D75: 尖峰時數（每週） | E75: 原始數據（候選） | F75: X5b | H75: 13
A76: INV-203 | B76: Cap_In | C76: 18 | D76: 離峰價 ÷ 尖峰價 | E76: 原始數據（候選） | F76: X5b | H76: 13
A77: INV-205 | B77: Cap_In | C77: 23 | D77: 商業壽命 低 | E77: Assumed | F77: X5a | H77: 0
A78: INV-206 | B78: Cap_In | C78: 24 | D78: 商業壽命 高 | E78: Assumed | F78: X5a | H78: 0
A79: INV-211 | B79: Cap_In | C79: 36 | D79: 儲存層（1＝SSD；2＝DRAM；3＝HBM） | E79: Assumed | F79: X2 | G79: O10、O13、O14 | H79: 33
A80: INV-218 | B80: Cap_In | C80: 46 | D80: GPT-6 Luna | E80: 原始數據（候選） | F80: X5b | H80: 13
A81: INV-219 | B81: Cap_In | C81: 47 | D81: GPT-6 Sol | E81: 原始數據（候選） | F81: X5b | H81: 13
A82: INV-220 | B82: Cap_In | C82: 48 | D82: GPT-6 Astra | E82: 原始數據（候選） | F82: X5b | H82: 13
A83: INV-221 | B83: Cap_In | C83: 49 | D83: Claude Fable 5.1 | E83: 原始數據（候選） | F83: X5b | H83: 13
A84: INV-222 | B84: Cap_In | C84: 50 | D84: Claude Opus 5 | E84: 原始數據（候選） | F84: X5b | H84: 13
A85: INV-223 | B85: Cap_In | C85: 51 | D85: Claude Opus 5.5 | E85: 原始數據（候選） | F85: X5b | H85: 13
A86: INV-224 | B86: Cap_In | C86: 52 | D86: DeepSeek V4.1-Flash | E86: 原始數據（候選） | F86: X5b | H86: 13
A87: INV-225 | B87: Cap_In | C87: 53 | D87: DeepSeek V4-Pro-0813 | E87: 原始數據（候選） | F87: X5b | H87: 13
A88: INV-226 | B88: Cap_In | C88: 54 | D88: GLM-5.3 | E88: 原始數據（候選） | F88: X5b | H88: 13
A89: INV-227 | B89: Cap_In | C89: 55 | D89: GLM-5.3-Flash | E89: 原始數據（候選） | F89: X5b | H89: 13
A90: INV-228 | B90: Cap_In | C90: 56 | D90: Qwen3.8-Max | E90: 原始數據（候選） | F90: X5b | H90: 13
A91: INV-229 | B91: Cap_In | C91: 57 | D91: Kimi K3 | E91: 原始數據（候選） | F91: X5b | H91: 13
... A105: INV-243 | B105: Sens_Rev | C105: 21 | D105: 壽命 24 個月 | E105: 情境選擇 | F105: X2 | H105: 0
A106: INV-244 | B106: Har_In | C106: 5 | D106: 情境檔案（2＝供應商原生增強；3＝多代理編排） | E106: Decision | F106: X2 | G106: O13、O14 | H106: 33
A107: INV-250 | B107: Har_In | C107: 16 | D107: 快取命中變動 | E107: Assumed | F107: X3 | G107: O13、O14 | H107: 22
A108: INV-251 | B108: Har_In | C108: 17 | D108: 子代理數增量 | E108: Assumed | F108: X3 | G108: O13、O14 | H108: 23
A109: INV-254 | B109: Har_In | C109: 20 | D109: 供應商專屬（1＝是） | E109: 原始數據（候選） | F109: X2 | H109: 0
A110: INV-256 | B110: Har_In | C110: 25 | D110: 思考保留 ρ | E110: Assumed | F110: X3 | G110: O13、O14 | H110: 22
A111: INV-259 | B111: Har_In | C111: 28 | D111: 快取命中變動 | E111: Assumed | F111: X3 | G111: O13、O14 | H111: 22
A112: INV-263 | B112: Har_In | C112: 32 | D112: 供應商專屬（1＝是） | E112: Assumed | F112: X2 | H112: 0
A113: INV-265 | B113: Har_In | C113: 49 | D113: 50% 時間範圍 低 | E113: Analogy | F113: X5a | H113: 0
A114: INV-266 | B114: Har_In | C114: 50 | D114: 50% 時間範圍 高 | E114: Analogy | F114: X5a | H114: 0
A115: INV-269 | B115: Har_In | C115: 54 | D115: 任務期程類別 | E115: 待分類 | F115: X1 | H115: 0
A116: INV-270 | B116: Har_In | C116: 61 | D116: 輪數倍數 | E116: Assumed | F116: X5a | H116: 0
...

Sheet 主要輸出
A1: ID | B1: 具名範圍 | C1: 欄 | D1: 儲存格 | E1: 內容 | F1: 單位 | G1: 指令表基準值（6 位有效） | H1: 活頁簿快取值（LibreOffice） | I1: engine 基準值 | J1: engine vs 快取 相對誤差 | K1: engine vs 指令表 相對誤差
A2: O01 | B2: IF_CapexTotal | C2: 11 | D2: Interface!M11 | E2: VR200 每 GW 資本支出合計 | F2: $B | G2: 47.582 | H2: 47.582032 | I2: 47.582032 | J2: 0 | K2: 6.7252322e-07
A3: O02 | B3: IF_HoldEcon | C3: 11 | D3: Interface!M13 | E3: VR200 每 GW 年持有成本（經濟） | F3: $B/年 | G3: 12.0544 | H3: 12.054371 | I3: 12.054371 | J3: 1.0315344e-15 | K3: 2.4085132e-06
A4: O03 | B4: IF_TokGW_Sol | C4: 11 | D4: Interface!M31 | E4: VR200 Sol 每 GW 總產出（100%） | F4: M tok/年 | G4: 238098000000 | H4: 2.3809835e+11 | I4: 2.3809835e+11 | J4: 1.666238e-15 | K4: 1.4909218e-06
A5: O04 | B5: IF_CostDec_Sol | C5: 11 | D5: Interface!M35 | E5: VR200 Sol decode $/M（經濟、100%） | F5: $/M | G5: 0.322576 | H5: 0.3225757 | I5: 0.3225757 | J5: 1.7208721e-16 | K5: 9.3830269e-07
A6: O05 | B6: IF_CostDec_Astra | C6: 11 | D6: Interface!M45 | E6: VR200 Astra decode $/M | F6: $/M | G6: 1.66066 | H6: 1.6606622 | I6: 1.6606622 | J6: 1.8719186e-15 | K6: 1.3022356e-06
A7: O06 | B7: IF_CostDec_Sol | C7: 8 | D7: Interface!J35 | E7: GB300 Sol decode $/M | F7: $/M | G7: 0.556984 | H7: 0.55698369 | I7: 0.55698369 | J7: 7.9731098e-16 | K7: 5.5581488e-07
A8: O07 | B8: IF_TrainGPUh_Astra | C8: 11 | D8: Interface!M72 | E8: VR200 Astra 最終訓練 GPU 小時 | F8: GPU-hr | G8: 11677700 | H8: 11677661 | I8: 11677661 | J8: 1.5950499e-15 | K8: 3.3640749e-06
A9: O08 | B9: IF_ProgCost_Astra | C9: 11 | D9: Interface!M78 | E9: VR200 Astra 研發計畫成本（經濟） | F9: $M | G9: 440.64 | H9: 440.64044 | I9: 440.64044 | J9: 0 | K9: 1.0008913e-06
A10: O09 | B10: IF_PostShareGPUh_Sol | C10: 11 | D10: Interface!M66 | E10: VR200 Sol 後訓練占比（GPU 小時） | F10: % | G10: 0.255756 | H10: 0.25575637 | I10: 0.25575637 | J10: 1.085235e-15 | K10: 1.4588592e-06
A11: O10 | B11: IF_FullCostDefault_Sol | C11: 11 | D11: Interface!M118 | E11: VR200 Sol 全成本 $/M（下游預設） | F11: $/M | G11: 0.104696 | H11: 0.10469626 | I11: 0.10469626 | J11: 1.5906342e-15 | K11: 2.4765646e-06
A12: O11 | B12: IF_RevGW_Sol | C12: 11 | D12: Interface!M119 | E12: VR200 Sol 每 GW 理論營收 | F12: $B/年 | G12: 229.59 | H12: 229.59031 | I12: 229.59031 | J12: 4.9517264e-16 | K12: 1.3376048e-06
A13: O12 | B13: IF_RevGWFleet | C13: 11 | D13: Interface!M143 | E13: VR200 1 GW 參考機隊付費服務營收 | F13: $B/年 | G13: 49.1065 | H13: 49.106545 | I13: 49.106545 | J13: 8.681646e-16 | K13: 9.1685556e-07
... A15: O14 | B15: IF_FrontSuccVR | C15: 5 | D15: Interface!G190 | E15: Coding agent 成功任務成本前緣 | F15: $（或文字「無合格」） | G15: 0.0209162 | H15: 0.020916193 | I15: 0.020916193 | J15: 8.2936865e-16 | K15: 3.3413376e-07

Sheet 異常
A1: 類型 | B1: INV_ID | C1: 工作表 | D1: 列／格 | E1: 標籤／輸出 | F1: 內容 | G1: 初步分類
A2: 多標記 | B2: INV-006 | C2: Inputs | D2: 11 | E2: 電價 | F2: Verified、Analogy | G2: 原始數據（候選）
A3: 多標記 | B3: INV-034 | C3: Spec_Rack | D3: 23 | E3: 峰值 dense（基準）PF/GPU | F3: Interested-party、Derived | G3: 原始數據（候選）
A4: 多標記 | B4: INV-040 | C4: Spec_Rack | D4: 29 | E4: decode EP 基準寬度 | F4: Analogy、Assumed | G4: Analogy
A5: 多標記 | B5: INV-046 | C5: Spec_Rack | D5: 39 | E5: BF16 dense PF/GPU | F5: Interested-party、Assumed | G5: 原始數據（候選）
A6: 多標記 | B6: INV-048 | C6: Spec_Rack | D6: 41 | E6: NVFP4 訓練 dense PF/GPU（Tech_Registry 情境） | F6: Assumed、Derived | G6: Assumed
A7: 多標記 | B7: INV-049 | C7: Arch | D7: 6 | E7: 總參數 | F7: Verified、Assumed | G7: 原始數據（候選）
A8: 多標記 | B8: INV-050 | C8: Arch | D8: 7 | E8: 啟用參數 | F8: Verified、Assumed | G8: 原始數據（候選）
A9: 多標記 | B9: INV-051 | C9: Arch | D9: 8 | E9: 層數 | F9: Verified、Assumed | G9: 原始數據（候選）
A10: 多標記 | B10: INV-052 | C10: Arch | D10: 9 | E10: d_model | F10: Verified、Assumed、Derived | G10: 原始數據（候選）
A11: 多標記 | B11: INV-053 | C11: Arch | D11: 10 | E11: query heads | F11: Verified、Analogy | G11: 原始數據（候選）
A12: 多標記 | B12: INV-054 | C12: Arch | D12: 11 | E12: head_dim | F12: Verified、Assumed | G12: 原始數據（候選）
A13: 多標記 | B13: INV-055 | C13: Arch | D13: 12 | E13: routed experts | F13: Verified、Assumed | G13: 原始數據（候選）
... A30: Derived 藍字 | B30: INV-267 | C30: Har_In | D30: 51 | E30: 斜率 β（C＝基準、D＝低、E＝高） | F30: Derived | G30: Derived 藍字（異常）
A31: 藍字公式格 | C31: Calib | D31: C118 | E31: 每用戶速度下限（1000 ÷ TPOT） | F31: =1000/15
A32: 藍字公式格 | C32: Calib | D32: D118 | E32: 每用戶速度下限（1000 ÷ TPOT） | F32: =1000/15
A33: 藍字公式格 | C33: Calib | D33: E118 | E33: 每用戶速度下限（1000 ÷ TPOT） | F33: =1000/15
A34: 藍字公式格 | C34: Calib | D34: F118 | E34: 每用戶速度下限（1000 ÷ TPOT） | F34: =1000/80
A35: 藍字公式格 | C35: Calib | D35: C120 | E35: MLPerf 實測輸出 tok/s/GPU（總量 ÷ 72） | F35: =253506/72
A36: 藍字公式格 | C36: Calib | D36: D120 | E36: MLPerf 實測輸出 tok/s/GPU（總量 ÷ 72） | F36: =240318/72
A37: 藍字公式格 | C37: Calib | D37: E120 | E37: MLPerf 實測輸出 tok/s/GPU（總量 ÷ 72） | F37: =652750/72
A38: 藍字公式格 | C38: Sens_Perf | D38: AC34 | E38: KV bytes/token（含 H_KV） | F38: =Arch!$E$21
A39: 藍字公式格 | C39: Sens_Perf | D39: AD34 | E39: KV bytes/token（含 H_KV） | F39: =Arch!$E$21
A40: 藍字公式格 | C40: Sens_Perf | D40: AE34 | E40: KV bytes/token（含 H_KV） | F40: =Arch!$E$22
A41: 藍字公式格 | C41: Sens_Perf | D41: AF34 | E41: KV bytes/token（含 H_KV） | F41: =Arch!$E$22
A42: 藍字公式格 | C42: Sens_Perf | D42: AG34 | E42: KV bytes/token（含 H_KV） | F42: =Arch!$E$23
A43: 藍字公式格 | C43: Sens_Perf | D43: AH34 | E43: KV bytes/token（含 H_KV） | F43: =Arch!$E$23
A44: 藍字公式格 | C44: Perf_Batch | D44: R14 | E44: 計算用峰值 | F44: =Spec_Rack!$F$40
A45: 藍字公式格 | C45: Perf_Batch | D45: S14 | E45: 計算用峰值 | F45: =Spec_Rack!$F$40
A46: 藍字公式格 | C46: Sens_Train | D46: I10 | E46: FP8 dense 峰值 | F46: =INDEX(Spec_Rack!$C$41:$G$41,I$6)
A47: 藍字公式格 | C47: Sens_Train | D47: J10 | E47: FP8 dense 峰值 | F47: =INDEX(Spec_Rack!$C$41:$G$41,J$6)
A48: 藍字公式格 | C48: Sens_Train | D48: O53 | E48: rollout 輸出 token | F48: =INDEX(Train_In!$C$34:$E$34,O$7)*0.3
A49: 藍字公式格 | C49: Sens_Train | D49: P53 | E49: rollout 輸出 token | F49: =INDEX(Train_In!$C$34:$E$34,P$7)*0.3
A50: 藍字公式格 | C50: Sens_Train | D50: Q53 | E50: rollout 輸出 token | F50: =INDEX(Train_In!$C$34:$E$34,Q$7)*3
A51: 藍字公式格 | C51: Sens_Train | D51: R53 | E51: rollout 輸出 token | F51: =INDEX(Train_In!$C$34:$E$34,R$7)*3
A52: 藍字公式格 | C52: Sens_Train | D52: W59 | E52: rollout decode GPU 秒／M（Perf_Batch 本層級） | F52: =Perf_Batch!R103
A53: 藍字公式格 | C53: Sens_Train | D53: X59 | E53: rollout decode GPU 秒／M（Perf_Batch 本層級） | F53: =Perf_Batch!S103
A54: 藍字公式格 | C54: Sens_Train | D54: W60 | E54: rollout prefill GPU 秒／M | F54: =Perf_Batch!R101
A55: 藍字公式格 | C55: Sens_Train | D55: X60 | E55: rollout prefill GPU 秒／M | F55: =Perf_Batch!S101
A56: 藍字公式格 | C56: Sens_Train | D56: W61 | E56: rollout decode FLOPs/token | F56: =Perf_Batch!R65
A57: 藍字公式格 | C57: Sens_Train | D57: X61 | E57: rollout decode FLOPs/token | F57: =Perf_Batch!S65
A58: 藍字公式格 | C58: Sens_Train | D58: W62 | E58: rollout prefill FLOPs/token | F58: =Perf_Batch!R67
A59: 藍字公式格 | C59: Sens_Train | D59: X62 | E59: rollout prefill FLOPs/token | F59: =Perf_Batch!S67
A60: 藍字公式格 | C60: Sens_Train | D60: AA93 | E60: 合成資料 token | F60: =INDEX(Train_In!$C$37:$E$37,AA$7)*3
A61: 藍字公式格 | C61: Sens_Train | D61: AB93 | E61: 合成資料 token | F61: =INDEX(Train_In!$C$37:$E$37,AB$7)*3
A62: 靜態不可達（原始數據／Analogy／Assumed） | B62: INV-044 | C62: Spec_Rack | D62: 33 | E62: GPU 功率 W/封裝（能量用） | F62: X5a | G62: 原始數據（候選）
A63: 靜態不可達（原始數據／Analogy／Assumed） | B63: INV-045 | C63: Spec_Rack | D63: 34 | E63: HBM 存取能量 pJ/byte | F63: X5a | G63: Analogy
A64: 靜態不可達（原始數據／Analogy／Assumed） | B64: INV-046 | C64: Spec_Rack | D64: 39 | E64: BF16 dense PF/GPU | F64: X5a | G64: 原始數據（候選）
A65: 靜態不可達（原始數據／Analogy／Assumed） | B65: INV-048 | C65: Spec_Rack | D65: 41 | E65: NVFP4 訓練 dense PF/GPU（Tech_Registry 情境） | F65: X5a | G65: Assumed
A66: 靜態不可達（原始數據／Analogy／Assumed） | B66: INV-058 | C66: Arch | D66: 15 | E66: vocab | F66: X5a | G66: 原始數據（候選）
A67: 靜態不可達（原始數據／Analogy／Assumed） | B67: INV-080 | C67: Serving | D67: 22 | E67: TTFT 上限（只作檢查） | F67: X5a | G67: Assumed
A68: 靜態不可達（原始數據／Analogy／Assumed） | B68: INV-093 | C68: Workload | D68: 40 | E68: 參照：Anthropic 揭露倍數（相對聊天） | F68: X5a | G68: 原始數據（候選）
A69: 靜態不可達（原始數據／Analogy／Assumed） | B69: INV-105 | C69: Calib | D69: 100 | E69: 總參數 | F69: X5a | G69: 原始數據（候選）
A70: 靜態不可達（原始數據／Analogy／Assumed） | B70: INV-172 | C70: Train_In | D70: 41 | E70: DeepSeek V3 預訓練 token | F70: X5a | G70: 原始數據（候選）
A71: 靜態不可達（原始數據／Analogy／Assumed） | B71: INV-176 | C71: Train_In | D71: 45 | E71: Grok 4 RL ÷ 預訓練（宣稱） | F71: X5a | G71: 原始數據（候選）
A72: 靜態不可達（原始數據／Analogy／Assumed） | B72: INV-177 | C72: Train_In | D72: 46 | E72: 前沿預訓練錨點 低 | F72: X5a | G72: Analogy
A73: 靜態不可達（原始數據／Analogy／Assumed） | B73: INV-202 | C73: Cap_In | D73: 17 | E73: 尖峰時數（每週） | F73: X5b | G73: 原始數據（候選）
... A115: 靜態不可達（原始數據／Analogy／Assumed） | B115: INV-293 | C115: NonNV | D115: 9 | E115: OpenAI／Broadcom 客製 | F115: X5a | G115: Assumed
A116: 藍字格無任何公式引用 | B116: INV-039 | C116: Spec_Rack | D116: C28 | E116: Scale-up 域 GPU 數 | F116: 8 | G116: 待分類
A117: 藍字格無任何公式引用 | B117: INV-039 | C117: Spec_Rack | D117: D28 | E117: Scale-up 域 GPU 數 | F117: 72 | G117: 待分類
A118: 藍字格無任何公式引用 | B118: INV-039 | C118: Spec_Rack | D118: E28 | E118: Scale-up 域 GPU 數 | F118: 72 | G118: 待分類
A119: 藍字格無任何公式引用 | B119: INV-039 | C119: Spec_Rack | D119: F28 | E119: Scale-up 域 GPU 數 | F119: 72 | G119: 待分類
A120: 藍字格無任何公式引用 | B120: INV-039 | C120: Spec_Rack | D120: G28 | E120: Scale-up 域 GPU 數 | F120: 144 | G120: 待分類
A121: 藍字格無任何公式引用 | B121: INV-046 | C121: Spec_Rack | D121: C39 | E121: BF16 dense PF/GPU | F121: 0.989 | G121: 原始數據（候選）
A122: 藍字格無任何公式引用 | B122: INV-046 | C122: Spec_Rack | D122: D39 | E122: BF16 dense PF/GPU | F122: 2.5 | G122: 原始數據（候選）
A123: 藍字格無任何公式引用 | B123: INV-046 | C123: Spec_Rack | D123: E39 | E123: BF16 dense PF/GPU | F123: 2.5 | G123: 原始數據（候選）
A124: 藍字格無任何公式引用 | B124: INV-046 | C124: Spec_Rack | D124: F39 | E124: BF16 dense PF/GPU | F124: 4 | G124: 原始數據（候選）
A125: 藍字格無任何公式引用 | B125: INV-046 | C125: Spec_Rack | D125: G39 | E125: BF16 dense PF/GPU | F125: 8 | G125: 原始數據（候選）
A126: 藍字格無任何公式引用 | B126: INV-093 | C126: Workload | D126: C40 | E126: 參照：Anthropic 揭露倍數（相對聊天） | F126: 1 | G126: 原始數據（候選）
A127: 藍字格無任何公式引用 | B127: INV-093 | C127: Workload | D127: E40 | E127: 參照：Anthropic 揭露倍數（相對聊天） | F127: 4 | G127: 原始數據（候選）
... A242: 藍字格無任何公式引用 | B242: INV-281 | C242: Har_In | D242: E75 | E242: Anthropic 多代理研究系統（相對單代理） | F242: 3.75 | G242: 原始數據（候選）
