Workbook

Sheet 逐列檢查
A1: 規則：第 0 段「C3_核心推導列」扣除「C7_m路徑」後屬 3A 工作表的 510 個頁＋列，逐列檢查 L1–L9。「—」＝沒有發現問題（不等於已證明正確）。L3 以 10_mech.py 機械檢查（世代×層級／成本頁之間同欄對位 0 處不符；Interface 層級常數 3*(世代−1)+k 對列標籤 0 處不符）；L7 以 20_l7_closure.py 在 4 個端點情境重算（文字或 0）；L8「直接」＝本列公式直接引用第 1 段 Y1–Y9 輸入格，「上游」＝依賴圖上游任一處含 Y 類輸入。G 編號對應報告第 3 節。嚴重度：高＝直接作用在下游契約名稱的口徑或閉合問題；中＝其他 L1–L9；低＝結構或顯示；資訊＝只有 L8。只標問題，不判定對錯、不提修法。
A2: 頁 | B2: 列 | C2: 列標籤 | D2: 單位 | E2: 公式格數 | F2: 同列公式結構數（R1C1） | G2: 代表格 | H2: 代表公式 | I2: 代表值 | J2: L1 量綱 | K2: L2 口徑 | L2: L3 引用對位 | M2: L4 重複／漏算 | N2: L5 恆等式與閉合 | O2: L6 倒推 | P2: L7 條件分支 | Q2: L8 與 Y1–Y9 的連結 | R2: L9 物理合理性 | S2: 上游 Y 類 | T2: 直接 Y 類 | U2: 非治理頁下游格數 | V2: G 編號 | W2: 嚴重度
A3: Spec_Rack | B3: 33 | C3: GPU 功率 W/封裝（能量用） | E3: 4 | F3: 4 | G3: C33 | H3: =SRC_HW_056 | I3: 700 | J3: — | K3: — | L3: — | M3: — | N3: — | O3: — | P3: — | Q3: — | R3: [G23] RU 3,600 W／封裝為推估（Interested-party；只進能量下限）；F 欄以 SRC_HW_046×1000，其他欄為單一 SRC | U3: 64 | V3: G23 | W3: 低
A4: Spec_Rack | B4: 34 | C4: HBM 存取能量 pJ/byte | E4: 1 | F4: 1 | G4: F34 | H4: =SRC_HW_034*8 | I4: 20 | J4: — | K4: — | L4: — | M4: — | N4: — | O4: — | P4: — | Q4: — | R4: — | U4: 64 | W4: —
A5: Spec_Rack | B5: 40 | C5: FP8 dense PF/GPU（訓練基準，J7） | E5: 4 | F5: 3 | G5: C40 | H5: =SRC_HW_040 | I5: 1.979 | J5: — | K5: — | L5: — | M5: — | N5: — | O5: — | P5: — | Q5: — | R5: — | U5: 65 | W5: —
A6: Serving | B6: 15 | C6: 快取命中 KV 載入頻寬 | D6: TB/s/GPU | E6: 0 | F6: 0 | J6: — | K6: — | L6: — | M6: — | N6: — | O6: — | P6: — | Q6: — | R6: — | U6: 64 | W6: —
A7: Workload | B7: 5 | C7: 輪數 T | D7: 輪 | E7: 0 | F7: 0 | J7: — | K7: — | L7: — | M7: — | N7: — | O7: — | P7: — | Q7: — | R7: — | U7: 32 | W7: —
A8: Workload | B8: 6 | C8: 初始上下文 S（系統提示、歷史、工具定義） | D8: tok | E8: 0 | F8: 0 | J8: — | K8: — | L8: — | M8: — | N8: — | O8: — | P8: — | Q8: — | R8: — | U8: 69 | W8: —
A9: Workload | B9: 7 | C9: 每輪新輸入 u（使用者或工具結果） | D9: tok | E9: 0 | F9: 0 | J9: — | K9: — | L9: — | M9: — | N9: — | O9: — | P9: — | Q9: — | R9: — | U9: 69 | W9: —
A10: Workload | B10: 8 | C10: 每輪思考 token h | D10: tok | E10: 0 | F10: 0 | J10: — | K10: — | L10: — | M10: — | N10: — | O10: — | P10: — | Q10: 直接引用 Y5 類輸入 | R10: — | S10: Y5 | T10: Y5 | U10: 32 | W10: 資訊（只有 L8）
A11: Workload | B11: 9 | C11: 每輪可見輸出 o | D11: tok | E11: 0 | F11: 0 | J11: — | K11: — | L11: — | M11: — | N11: — | O11: — | P11: — | Q11: — | R11: — | U11: 74 | W11: —
A12: Workload | B12: 10 | C12: 思考保留於上下文比例 ρ | D12: % | E12: 0 | F12: 0 | J12: — | K12: — | L12: — | M12: — | N12: — | O12: — | P12: — | Q12: — | R12: — | U12: 10 | W12: —
A13: Workload | B13: 11 | C13: 歷史快取命中率 χ | D13: % | E13: 0 | F13: 0 | J13: — | K13: — | L13: — | M13: — | N13: — | O13: — | P13: — | Q13: — | R13: — | U13: 32 | W13: —
A14: Workload | B14: 12 | C14: 並行子代理數 m | D14: 個 | E14: 0 | F14: 0 | J14: — | K14: — | L14: — | M14: — | N14: — | O14: — | P14: — | Q14: — | R14: — | U14: 66 | W14: —
A15: Workload | B15: 13 | C15: harness token 倍數 | D15: x | E15: 0 | F15: 0 | J15: — | K15: — | L15: — | M15: — | N15: [G16] harness token 倍數標為「殘差倍數」（基準 1） | O15: — | P15: — | Q15: — | R15: — | U15: 66 | V15: G16 | W15: 低
A16: Workload | B16: 14 | C16: 歷史保留比 c（壓縮後保留的歷史比例；1＝不壓縮） | D16: x | E16: 0 | F16: 0 | J16: — | K16: — | L16: — | M16: — | N16: — | O16: — | P16: — | Q16: — | R16: — | U16: 10 | W16: —
A17: Workload | B17: 18 | C17: 有效輪數 T | D17: 輪 | E17: 5 | F17: 5 | G17: C18 | H17: =C5*(1+B5_W*(INDEX(B5_SelT,1,1)-1)) | I17: 1 | J17: — | K17: — | L17: — | M17: — | N17: — | O17: — | P17: — | Q17: — | R17: — | U17: 20 | W17: —
A18: Workload | B18: 19 | C18: 有效每輪思考 h | D18: tok | E18: 5 | F18: 5 | G18: C19 | H18: =C8*(1+B5_W*(INDEX(B5_SelH,1,1)-1)) | I18: 0 | J18: — | K18: — | L18: — | M18: — | N18: — | O18: — | P18: — | Q18: 直接引用 Y5 類輸入 | R18: — | S18: Y5 | T18: Y5 | U18: 20 | W18: 資訊（只有 L8）
A19: Workload | B19: 20 | C19: 有效思考保留 ρ | D19: % | E19: 5 | F19: 5 | G19: C20 | H19: =C10+B5_W*(INDEX(B5_Selrho,1,1)-C10) | I19: 0 | J19: — | K19: — | L19: — | M19: — | N19: — | O19: — | P19: — | Q19: — | R19: — | U19: 5 | W19: —
A20: Workload | B20: 21 | C20: 有效快取命中 χ | D20: % | E20: 5 | F20: 5 | G20: C21 | H20: =MIN(1,MAX(0,C11+B5_W*INDEX(B5_SelDChi,1,1))) | I20: 0.5 | J20: — | K20: — | L20: — | M20: — | N20: — | O20: — | P20: [G16] MIN(1,MAX(0,…)) 截斷：harness 檔案 Δχ 使 χ 超出 0–1 時無提示 | Q20: — | R20: — | U20: 5 | V20: G16 | W20: 低
A21: Workload | B21: 22 | C21: 有效子代理數 m | D21: 個 | E21: 5 | F21: 5 | G21: C22 | H21: =C12+B5_W*INDEX(B5_SelDM,1,1) | I21: 0 | J21: — | K21: — | L21: — | M21: — | N21: — | O21: — | P21: — | Q21: — | R21: — | U21: 5 | W21: —
A22: Workload | B22: 23 | C22: 有效歷史保留比 c | D22: x | E22: 5 | F22: 5 | G22: C23 | H22: =C14+B5_W*(INDEX(B5_SelC,1,1)-C14) | I22: 1 | J22: — | K22: — | L22: — | M22: — | N22: — | O22: — | P22: — | Q22: — | R22: — | U22: 15 | W22: —
A23: Workload | B23: 26 | C23: 每輪上下文增量 u＋o＋ρh | D23: tok | E23: 5 | F23: 1 | G23: C26 | H23: =C7+C9+C20*C19 | I23: 1000 | J23: — | K23: [G16] 任務 token 結構（例：一般聊天輸入 2,500、輸出 500、思考 0）與 Serving 參考請求（Luna ISL 8,192／OSL 1,024 含思考）是兩套獨立定義，分別進每成功任務成本與每 M token 單價（與 Y6 同類） | L23: — | M23: — | N23: — | O23: — | P23: — | Q23: 上游含 Y5 | R23: — | S23: Y5 | U23: 15 | V23: G16 | W23: 中
A24: Workload | B24: 27 | C24: 單代理輸入總量 | D24: tok | E24: 5 | F24: 1 | G24: C27 | H24: =C18*(C6+C7)+C23*C26*C18*(C18-1)/2 | I24: 2500 | J24: — | K24: [G16] 任務 token 結構（例：一般聊天輸入 2,500、輸出 500、思考 0）與 Serving 參考請求（Luna ISL 8,192／OSL 1,024 含思考）是兩套獨立定義，分別進每成功任務成本與每 M token 單價（與 Y6 同類） | L24: — | M24: — | N24: — | O24: — | P24: — | Q24: 上游含 Y5 | R24: — | S24: Y5 | U24: 5 | V24: G16 | W24: 中
A25: Workload | B25: 28 | C25: 其中可快取（前綴） | D25: tok | E25: 5 | F25: 1 | G25: C28 | H25: =C21*(C18*C6+C23*C26*C18*(C18-1)/2) | I25: 1000 | J25: — | K25: [G16] 任務 token 結構（例：一般聊天輸入 2,500、輸出 500、思考 0）與 Serving 參考請求（Luna ISL 8,192／OSL 1,024 含思考）是兩套獨立定義，分別進每成功任務成本與每 M token 單價（與 Y6 同類） | L25: — | M25: — | N25: — | O25: — | P25: — | Q25: 上游含 Y5 | R25: — | S25: Y5 | U25: 10 | V25: G16 | W25: 中
A26: Workload | B26: 29 | C26: 其中新鮮 | D26: tok | E26: 5 | F26: 1 | G26: C29 | H26: =C27-C28 | I26: 1500 | J26: — | K26: [G16] 任務 token 結構（例：一般聊天輸入 2,500、輸出 500、思考 0）與 Serving 參考請求（Luna ISL 8,192／OSL 1,024 含思考）是兩套獨立定義，分別進每成功任務成本與每 M token 單價（與 Y6 同類） | L26: — | M26: — | N26: — | O26: — | P26: — | Q26: 上游含 Y5 | R26: — | S26: Y5 | U26: 5 | V26: G16 | W26: 中
A27: Workload | B27: 30 | C27: 單代理 decode（思考＋可見） | D27: tok | E27: 5 | F27: 1 | G27: C30 | H27: =C18*(C19+C9) | I27: 500 | J27: — | K27: [G16] 任務 token 結構（例：一般聊天輸入 2,500、輸出 500、思考 0）與 Serving 參考請求（Luna ISL 8,192／OSL 1,024 含思考）是兩套獨立定義，分別進每成功任務成本與每 M token 單價（與 Y6 同類） | L27: — | M27: — | N27: — | O27: — | P27: — | Q27: 上游含 Y5 | R27: — | S27: Y5 | U27: 5 | V27: G16 | W27: 中
A28: Workload | B28: 31 | C28: 系統倍數（1＋m）× harness 殘差倍數 | D28: x | E28: 5 | F28: 1 | G28: C31 | H28: =(1+C22)*C13 | I28: 1 | J28: — | K28: — | L28: — | M28: — | N28: — | O28: — | P28: — | Q28: — | R28: — | U28: 15 | W28: —
A29: Workload | B29: 32 | C29: 任務新鮮 prefill | D29: tok | E29: 5 | F29: 1 | G29: C32 | H29: =C29*C31 | I29: 1500 | J29: — | K29: — | L29: — | M29: — | N29: — | O29: — | P29: — | Q29: 上游含 Y5 | R29: — | S29: Y5 | U29: 55 | W29: 資訊（只有 L8）
A30: Workload | B30: 33 | C30: 任務快取 prefill | D30: tok | E30: 5 | F30: 1 | G30: C33 | H30: =C28*C31 | I30: 1000 | J30: — | K30: — | L30: — | M30: — | N30: — | O30: — | P30: — | Q30: 上游含 Y5 | R30: — | S30: Y5 | U30: 55 | W30: 資訊（只有 L8）
A31: Workload | B31: 34 | C31: 任務 decode | D31: tok | E31: 5 | F31: 1 | G31: C34 | H31: =C30*C31 | I31: 500 | J31: — | K31: — | L31: — | M31: — | N31: — | O31: — | P31: — | Q31: 上游含 Y5 | R31: — | S31: Y5 | U31: 55 | W31: 資訊（只有 L8）
A32: Workload | B32: 35 | C32: 任務總 token | D32: tok | E32: 5 | F32: 1 | G32: C35 | H32: =C32+C33+C34 | I32: 3000 | J32: — | K32: [G16] 任務 token 結構（例：一般聊天輸入 2,500、輸出 500、思考 0）與 Serving 參考請求（Luna ISL 8,192／OSL 1,024 含思考）是兩套獨立定義，分別進每成功任務成本與每 M token 單價（與 Y6 同類） | L32: — | M32: — | N32: — | O32: — | P32: — | Q32: 上游含 Y5 | R32: — | S32: Y5 | U32: 15 | V32: G16 | W32: 中
A33: Calib | B33: 26 | C33: EP 通訊頻寬 | D33: TB/s | E33: 7 | F33: 1 | G33: C26 | H33: =INDEX(Spec_Rack!$C$27:$G$27,C10) | I33: 0.9 | J33: — | K33: — | L33: — | M33: — | N33: — | O33: — | P33: — | Q33: — | R33: — | U33: 8 | W33: —
A34: Calib | B34: 32 | C34: d_model | E34: 7 | F34: 1 | G34: C32 | H34: =Arch!$D$9 | I34: 7168 | J34: — | K34: — | L34: — | M34: — | N34: — | O34: — | P34: — | Q34: — | R34: — | U34: 8 | W34: —
A35: Calib | B35: 33 | C35: 啟用專家 | E35: 7 | F35: 1 | G35: C33 | H35: =Arch!$D$13 | I35: 6 | J35: — | K35: — | L35: — | M35: — | N35: — | O35: — | P35: — | Q35: — | R35: — | U35: 8 | W35: —
A36: Calib | B36: 36 | C36: KV bytes/token | D36: B | E36: 7 | F36: 1 | G36: C36 | H36: =Arch!$D$25 | I36: 3965 | J36: — | K36: — | L36: — | M36: — | N36: — | O36: — | P36: — | Q36: 上游含 Y1 | R36: — | S36: Y1 | U36: 15 | W36: 資訊（只有 L8）
A37: Calib | B37: 75 | C37: η_d（該世代） | D37: % | E37: 7 | F37: 1 | G37: C75 | H37: =INDEX($C$70:$G$70,C10) | I37: 0.035755 | J37: — | K37: — | L37: — | M37: — | N37: — | O37: [G05] 驗證點以擬合值重算；擬合點本身恆等，樣本外點 E／H／I 為 0.99／1.00／0.88，F／G（舊軟體）2.18／4.11；七點全部同一平台（J19） | P37: — | Q37: 上游含 Y5,Y8 | R37: — | S37: Y5,Y8 | U37: 7 | V37: G05 | W37: 中
A38: Calib | B38: 76 | C38: 每層延遲（該世代） | D38: µs | E38: 7 | F38: 1 | G38: C76 | H38: =INDEX($C$71:$G$71,C10) | I38: 161.18534 | J38: — | K38: — | L38: — | M38: — | N38: — | O38: [G05] 驗證點以擬合值重算；擬合點本身恆等，樣本外點 E／H／I 為 0.99／1.00／0.88，F／G（舊軟體）2.18／4.11；七點全部同一平台（J19） | P38: — | Q38: 上游含 Y5,Y8 | R38: — | S38: Y5,Y8 | U38: 7 | V38: G05 | W38: 中
A39: Calib | B39: 77 | C39: η_p（該世代） | D39: % | E39: 7 | F39: 1 | G39: C77 | H39: =INDEX($C$72:$G$72,C10) | I39: 0.3 | J39: — | K39: — | L39: — | M39: — | N39: — | O39: [G05] 驗證點以擬合值重算；擬合點本身恆等，樣本外點 E／H／I 為 0.99／1.00／0.88，F／G（舊軟體）2.18／4.11；七點全部同一平台（J19） | P39: — | Q39: 上游含 Y5,Y8 | R39: — | S39: Y5,Y8 | U39: 7 | V39: G05 | W39: 中
A40: Calib | B40: 78 | C40: prefill tok/s/GPU | D40: tok/s | E40: 7 | F40: 1 | G40: C78 | H40: =C77*C23*1000000000000000/(C47*1000000000) | I40: 34214.061 | J40: — | K40: — | L40: — | M40: — | N40: — | O40: [G05] 驗證點以擬合值重算；擬合點本身恆等，樣本外點 E／H／I 為 0.99／1.00／0.88，F／G（舊軟體）2.18／4.11；七點全部同一平台（J19） | P40: — | Q40: 上游含 Y5,Y8 | R40: — | S40: Y5,Y8 | U40: 7 | V40: G05 | W40: 中
A41: Calib | B41: 79 | C41: 每步固定延遲 | D41: ms | E41: 7 | F41: 1 | G41: C79 | H41: =C51/C25+(C31+C52)*C76/1000 | I41: 16.321653 | J41: — | K41: — | L41: — | M41: — | N41: — | O41: [G05] 驗證點以擬合值重算；擬合點本身恆等，樣本外點 E／H／I 為 0.99／1.00／0.88，F／G（舊軟體）2.18／4.11；七點全部同一平台（J19） | P41: — | Q41: 上游含 Y5,Y8 | R41: — | S41: Y5,Y8 | U41: 14 | V41: G05 | W41: 中
A42: Calib | B42: 80 | C42: 每序列每步時間 | D42: ms | E42: 7 | F42: 1 | G42: C80 | H42: =MAX(C55/C75,C36*C42/(C25*Serving!$C$13)/1000000000,(C52+1)*C31*C33*C32*Serving!$C$12*(C50-1)/C50/(C26*Serving!$C$14)/1000000000) | I42: 0.990625 | J42: — | K42: — | L42: — | M42: — | N42: — | O42: [G05] 驗證點以擬合值重算；擬合點本身恆等，樣本外點 E／H／I 為 0.99／1.00／0.88，F／G（舊軟體）2.18／4.11；七點全部同一平台（J19） | P42: — | Q42: 上游含 Y1,Y5,Y8 | R42: — | S42: Y1,Y5,Y8 | U42: 14 | V42: G05 | W42: 中
A43: Calib | B43: 81 | C43: SLO 批次上限 | D43: 序列 | E43: 7 | F43: 1 | G43: C81 | H43: =(1000*C53/C14-C79)/C80 | I43: 19.03738 | J43: — | K43: — | L43: — | M43: — | N43: — | O43: [G05] 驗證點以擬合值重算；擬合點本身恆等，樣本外點 E／H／I 為 0.99／1.00／0.88，F／G（舊軟體）2.18／4.11；七點全部同一平台（J19） | P43: — | Q43: 上游含 Y1,Y5,Y8 | R43: — | S43: Y1,Y5,Y8 | U43: 7 | V43: G05 | W43: 中
A44: Calib | B44: 82 | C44: 容量批次上限 | D44: 序列 | E44: 7 | F44: 1 | G44: C82 | H44: =(C48-C51)*1000000000/(C36*C42) | I44: 6118.3815 | J44: — | K44: — | L44: — | M44: — | N44: — | O44: [G05] 驗證點以擬合值重算；擬合點本身恆等，樣本外點 E／H／I 為 0.99／1.00／0.88，F／G（舊軟體）2.18／4.11；七點全部同一平台（J19） | P44: — | Q44: 上游含 Y1 | R44: — | S44: Y1 | U44: 7 | V44: G05 | W44: 中
A45: Calib | B45: 83 | C45: B* | D45: 序列 | E45: 7 | F45: 1 | G45: C83 | H45: =MAX(0,MIN(C81,C82)) | I45: 19.03738 | J45: — | K45: — | L45: — | M45: — | N45: — | O45: [G05] 驗證點以擬合值重算；擬合點本身恆等，樣本外點 E／H／I 為 0.99／1.00／0.88，F／G（舊軟體）2.18／4.11；七點全部同一平台（J19） | P45: — | Q45: 上游含 Y1,Y5,Y8 | R45: — | S45: Y1,Y5,Y8 | U45: 7 | V45: G05 | W45: 中
A46: Calib | B46: 84 | C46: decode tok/s/GPU | D46: tok/s | E46: 7 | F46: 1 | G46: C84 | H46: =IF(C83>0,C83*C53/((C79+C83*C80)/1000),0) | I46: 1370.6914 | J46: — | K46: — | L46: — | M46: — | N46: — | O46: [G05] 驗證點以擬合值重算；擬合點本身恆等，樣本外點 E／H／I 為 0.99／1.00／0.88，F／G（舊軟體）2.18／4.11；七點全部同一平台（J19） | P46: — | Q46: 上游含 Y1,Y5,Y8 | R46: — | S46: Y1,Y5,Y8 | U46: 7 | V46: G05 | W46: 中
A47: Calib | B47: 85 | C47: 模型 tok/s/GPU（總 token） | D47: tok/s | E47: 7 | F47: 1 | G47: C85 | H47: =IF(C84>0,(C15+C16)/(C15/C78+C16/C84),0) | I47: 9342.1 | J47: — | K47: — | L47: — | M47: — | N47: — | O47: [G05] 驗證點以擬合值重算；擬合點本身恆等，樣本外點 E／H／I 為 0.99／1.00／0.88，F／G（舊軟體）2.18／4.11；七點全部同一平台（J19） | P47: — | Q47: 上游含 Y1,Y5,Y8 | R47: — | S47: Y1,Y5,Y8 | U47: 7 | V47: G05 | W47: 中
A48: Calib | B48: 86 | C48: 模型 ÷ 實測 | D48: x | E48: 7 | F48: 1 | G48: C86 | H48: =C85/C17 | I48: 1 | J48: — | K48: — | L48: — | M48: — | N48: [G05] Calib D 節以兩個擬合點聯立解兩個未知數（η_d、每層延遲），F 節擬合點「模型 ÷ 實測」恆為 1.00（Checks B14），是代數恆等，不是驗證。η_d＝3.58% 是吸收未建模開銷的擬合係數，比一般 GEMM 達成率低一個數量級以上（L9）。J5 說明「擬合結果對 η_p 不敏感」，但 G 節顯示 η_p 0.15／0.3／0.45 → η_d 0.055／0.036／0.032、每層延遲 175／161／157 µs；S3：η_p 端點 → IF_CostPre_Sol（VR200）+100%／−33%、IF_CostDec_Sol −33%／+11%、IFW_RevGWFleet_Prod（Hopper）−30%／+8% | O48: — | P48: — | Q48: 上游含 Y1,Y5,Y8 | R48: [G05] 擬合 η_d 3.58%（GB300、Sol）；Perf 推出的 decode 有效 MFU（含草稿驗證）全部 15 欄 1.0–2.5% | S48: Y1,Y5,Y8 | U48: 0 | V48: G05 | W48: 高
A49: Calib | B49: 100 | C49: 總參數 | D49: B | E49: 1 | F49: 1 | G49: C100 | H49: =SRC_MOD_020 | I49: 671 | J49: — | K49: — | L49: — | M49: — | N49: — | O49: — | P49: — | Q49: — | R49: — | U49: 2 | W49: —
A50: Calib | B50: 101 | C50: 啟用參數 | D50: B | E50: 1 | F50: 1 | G50: C101 | H50: =SRC_MOD_021 | I50: 37 | J50: — | K50: — | L50: — | M50: — | N50: — | O50: — | P50: — | Q50: — | R50: — | U50: 10 | W50: —
A51: Calib | B51: 102 | C51: 層數 | E51: 1 | F51: 1 | G51: C102 | H51: =SRC_MOD_022 | I51: 61 | J51: — | K51: — | L51: — | M51: — | N51: — | O51: — | P51: — | Q51: — | R51: — | U51: 10 | W51: —
A52: Calib | B52: 103 | C52: d_model | E52: 1 | F52: 1 | G52: C103 | H52: =SRC_MOD_023 | I52: 7168 | J52: — | K52: — | L52: — | M52: — | N52: — | O52: — | P52: — | Q52: — | R52: — | U52: 4 | W52: —
A53: Calib | B53: 104 | C53: routed experts | E53: 1 | F53: 1 | G53: C104 | H53: =SRC_MOD_024 | I53: 256 | J53: — | K53: — | L53: — | M53: — | N53: — | O53: — | P53: — | Q53: — | R53: — | U53: 1 | W53: —
A54: Calib | B54: 105 | C54: 啟用 experts | E54: 1 | F54: 1 | G54: C105 | H54: =SRC_MOD_025 | I54: 8 | J54: — | K54: — | L54: — | M54: — | N54: — | O54: — | P54: — | Q54: — | R54: — | U54: 6 | W54: —
A55: Calib | B55: 106 | C55: shared experts | E55: 1 | F55: 1 | G55: C106 | H55: =SRC_MOD_026 | I55: 1 | J55: — | K55: — | L55: — | M55: — | N55: — | O55: — | P55: — | Q55: — | R55: — | U55: 1 | W55: —
A56: Calib | B56: 108 | C56: KV bytes/token（MLA 576 × 61 層，FP8） | D56: B | E56: 1 | F56: 1 | G56: C108 | H56: =SRC_MOD_028*SRC_MOD_022 | I56: 35136 | J56: — | K56: — | L56: — | M56: — | N56: — | O56: — | P56: — | Q56: — | R56: — | U56: 8 | W56: —
A57: Calib | B57: 109 | C57: 注意力 FLOPs／被注意 token（MLA：2×128×192＋2×128×128，× 61） | D57: FLOP | E57: 1 | F57: 1 | G57: C109 | H57: =(2*SRC_MOD_049*SRC_MOD_050+2*SRC_MOD_049*SRC_MOD_051)*SRC_MOD_022 | I57: 4997120 | J57: — | K57: — | L57: — | M57: — | N57: — | O57: — | P57: — | Q57: — | R57: — | U57: 8 | W57: —
A58: Calib | B58: 110 | C58: 平均 ISL（MLCommons 資料集） | D58: tok | E58: 1 | F58: 1 | G58: C110 | H58: =SRC_PERF_029 | I58: 800 | J58: — | K58: — | L58: — | M58: — | N58: — | O58: — | P58: — | Q58: — | R58: — | U58: 12 | W58: —
A59: Calib | B59: 111 | C59: 平均 OSL | D59: tok | E59: 1 | F59: 1 | G59: C111 | H59: =SRC_PERF_030 | I59: 3880 | J59: — | K59: — | L59: — | M59: — | N59: — | O59: — | P59: — | Q59: — | R59: — | U59: 8 | W59: —
A60: Calib | B60: 112 | C60: 每 routed expert 參數 | D60: B | E60: 1 | F60: 1 | G60: C112 | H60: =(C100-C101)/(C102*(C104-C105)) | I60: 0.041909 | J60: [G21] 每專家參數＝（總 − 啟用）÷（層數 ×（routed − 啟用））假設 61 層全為 MoE 層；DeepSeek-R1 前 3 層為 dense。只影響 H 節 MLPerf 對照 | K60: — | L60: — | M60: — | N60: — | O60: — | P60: — | Q60: — | R60: — | U60: 1 | V60: G21 | W60: 低
A61: Calib | B61: 113 | C61: 非專家參數 | D61: B | E61: 1 | F61: 1 | G61: C113 | H61: =C101-C102*(C105+C106)*C112 | I61: 13.991935 | J61: [G21] 每專家參數＝（總 − 啟用）÷（層數 ×（routed − 啟用））假設 61 層全為 MoE 層；DeepSeek-R1 前 3 層為 dense。只影響 H 節 MLPerf 對照 | K61: — | L61: — | M61: — | N61: — | O61: — | P61: — | Q61: — | R61: — | U61: 9 | V61: G21 | W61: 低
A62: Calib | B62: 114 | C62: 專家參數 | D62: B | E62: 1 | F62: 1 | G62: C114 | H62: =C100-C113 | I62: 657.00806 | J62: — | K62: — | L62: — | M62: — | N62: — | O62: — | P62: — | Q62: — | R62: — | U62: 8 | W62: —
A63: Calib | B63: 117 | C63: 世代索引 | E63: 0 | F63: 0 | J63: — | K63: — | L63: — | M63: — | N63: — | O63: — | P63: — | Q63: — | R63: — | U63: 44 | W63: —
A64: Calib | B64: 118 | C64: 每用戶速度下限（1000 ÷ TPOT） | D64: tok/s | E64: 4 | F64: 2 | G64: C118 | H64: =1000/SRC_PERF_031 | I64: 66.666667 | J64: — | K64: — | L64: — | M64: — | N64: — | O64: — | P64: — | Q64: — | R64: — | U64: 4 | W64: —
A65: Calib | B65: 119 | C65: 推測解碼（1＝有） | E65: 0 | F65: 0 | J65: — | K65: — | L65: — | M65: — | N65: — | O65: — | P65: — | Q65: — | R65: — | U65: 8 | W65: —
A66: Calib | B66: 120 | C66: MLPerf 實測輸出 tok/s/GPU（總量 ÷ 72） | D66: tok/s/GPU | E66: 4 | F66: 4 | G66: C120 | H66: =SRC_PERF_028/SRC_HW_047 | I66: 3520.9167 | J66: — | K66: [G07] MLPerf 對照混用不同輪次：GB300 interactive v6.1（2026-09）、GB200 interactive v6.0（2026-04）、VR200 v6.1 預覽類、GB300 server v6.0；Calib D152「GB300 ÷ GB200＝1.055」是 v6.1 對 v6.0 | L66: — | M66: — | N66: — | O66: — | P66: — | Q66: — | R66: — | U66: 6 | V66: G07 | W66: 中
A67: Calib | B67: 124 | C67: 計算用峰值 | D67: PF | E67: 4 | F67: 1 | G67: C124 | H67: =INDEX(Spec_Rack!$C$35:$G$35,C117) | I67: 15 | J67: — | K67: — | L67: — | M67: — | N67: — | O67: — | P67: — | Q67: — | R67: — | U67: 8 | W67: —
A68: Calib | B68: 125 | C68: HBM | D68: GB | E68: 4 | F68: 1 | G68: C125 | H68: =INDEX(Spec_Rack!$C$25:$G$25,C117) | I68: 288 | J68: — | K68: — | L68: — | M68: — | N68: — | O68: — | P68: — | Q68: — | R68: — | U68: 4 | W68: —
A69: Calib | B69: 126 | C69: HBM 頻寬 | D69: TB/s | E69: 4 | F69: 1 | G69: C126 | H69: =INDEX(Spec_Rack!$C$26:$G$26,C117) | I69: 8 | J69: — | K69: — | L69: — | M69: — | N69: — | O69: — | P69: — | Q69: — | R69: — | U69: 8 | W69: —
A70: Calib | B70: 127 | C70: EP 頻寬 | D70: TB/s | E70: 4 | F70: 1 | G70: C127 | H70: =INDEX(Spec_Rack!$C$27:$G$27,C117) | I70: 0.9 | J70: — | K70: — | L70: — | M70: — | N70: — | O70: — | P70: — | Q70: — | R70: — | U70: 4 | W70: —
A71: Calib | B71: 128 | C71: EP 基準 | E71: 4 | F71: 1 | G71: C128 | H71: =INDEX(Spec_Rack!$C$29:$G$29,C117) | I71: 32 | J71: — | K71: — | L71: — | M71: — | N71: — | O71: — | P71: — | Q71: — | R71: — | U71: 4 | W71: —
A72: Calib | B72: 129 | C72: 專家 B/param | E72: 4 | F72: 1 | G72: C129 | H72: =INDEX(Spec_Rack!$C$30:$G$30,C117) | I72: 0.5625 | J72: — | K72: — | L72: — | M72: — | N72: — | O72: — | P72: — | Q72: — | R72: — | U72: 8 | W72: —
A73: Calib | B73: 130 | C73: 非專家 B/param | E73: 4 | F73: 1 | G73: C130 | H73: =INDEX(Spec_Rack!$C$31:$G$31,C117) | I73: 1 | J73: — | K73: — | L73: — | M73: — | N73: — | O73: — | P73: — | Q73: — | R73: — | U73: 8 | W73: —
A74: Calib | B74: 131 | C74: 可用 HBM | D74: GB | E74: 4 | F74: 1 | G74: C131 | H74: =C125*(1-Serving!$C$9) | I74: 259.2 | J74: — | K74: — | L74: — | M74: — | N74: — | O74: — | P74: — | Q74: — | R74: — | U74: 12 | W74: —
A75: Calib | B75: 132 | C75: 注意力 TP | E75: 4 | F75: 1 | G75: C132 | H75: =MAX(1,CEILING($C$113*C130/(Serving!$C$10*C131),1)) | I75: 1 | J75: — | K75: — | L75: — | M75: — | N75: — | O75: — | P75: — | Q75: — | R75: — | U75: 4 | W75: —
A76: Calib | B76: 133 | C76: EP 寬度 | E76: 4 | F76: 1 | G76: C133 | H76: =MAX(C128,CEILING($C$114*C129/(Serving!$C$11*C131),1)) | I76: 32 | J76: — | K76: — | L76: — | M76: — | N76: — | O76: — | P76: — | Q76: — | R76: — | U76: 8 | W76: —
A77: Calib | B77: 134 | C77: 每 GPU 權重 | D77: GB | E77: 4 | F77: 1 | G77: C134 | H77: =$C$113*C130/C132+$C$114*C129/C133 | I77: 25.540905 | J77: — | K77: — | L77: — | M77: — | N77: — | O77: — | P77: — | Q77: — | R77: — | U77: 8 | W77: —
A78: Calib | B78: 135 | C78: decode 平均上下文 | D78: tok | E78: 4 | F78: 1 | G78: C135 | H78: =$C$110+$C$111/2 | I78: 2740 | J78: — | K78: — | L78: — | M78: — | N78: — | O78: — | P78: — | Q78: — | R78: — | U78: 12 | W78: —
A79: Calib | B79: 136 | C79: decode FLOPs/token | D79: GFLOP | E79: 4 | F79: 1 | G79: C136 | H79: =(2*$C$101*1000000000+$C$109*C135)/1000000000 | I79: 87.692109 | J79: — | K79: — | L79: — | M79: — | N79: — | O79: — | P79: — | Q79: — | R79: — | U79: 4 | W79: —
A80: Calib | B80: 137 | C80: prefill FLOPs/token | D80: GFLOP | E80: 4 | F80: 1 | G80: C137 | H80: =(2*$C$101*1000000000+$C$109*$C$110/2)/1000000000 | I80: 75.998848 | J80: — | K80: — | L80: — | M80: — | N80: — | O80: — | P80: — | Q80: — | R80: — | U80: 4 | W80: —
A81: Calib | B81: 138 | C81: 草稿數 | E81: 4 | F81: 1 | G81: C138 | H81: =Serving!$C$6*C119 | I81: 3 | J81: — | K81: — | L81: — | M81: — | N81: — | O81: — | P81: — | Q81: — | R81: — | U81: 8 | W81: —
A82: Calib | B82: 139 | C82: 每步接受 | E82: 4 | F82: 1 | G82: C139 | H82: =IF(C119=1,Serving!$C$8,1) | I82: 2.533 | J82: — | K82: — | L82: — | M82: — | N82: — | O82: — | P82: — | Q82: — | R82: — | U82: 8 | W82: —
A83: Calib | B83: 140 | C83: η_d（該世代） | D83: % | E83: 4 | F83: 1 | G83: C140 | H83: =INDEX($C$70:$G$70,C117) | I83: 0.035755 | J83: — | K83: — | L83: — | M83: — | N83: — | O83: — | P83: — | Q83: 上游含 Y5,Y8 | R83: — | S83: Y5,Y8 | U83: 4 | W83: 資訊（只有 L8）
A84: Calib | B84: 141 | C84: 每層延遲（該世代） | D84: µs | E84: 4 | F84: 1 | G84: C141 | H84: =INDEX($C$71:$G$71,C117) | I84: 161.18534 | J84: — | K84: — | L84: — | M84: — | N84: — | O84: — | P84: — | Q84: 上游含 Y5,Y8 | R84: — | S84: Y5,Y8 | U84: 4 | W84: 資訊（只有 L8）
A85: Calib | B85: 142 | C85: η_p（該世代） | D85: % | E85: 4 | F85: 1 | G85: C142 | H85: =INDEX($C$72:$G$72,C117) | I85: 0.3 | J85: — | K85: — | L85: — | M85: — | N85: — | O85: — | P85: — | Q85: 上游含 Y5,Y8 | R85: — | S85: Y5,Y8 | U85: 4 | W85: 資訊（只有 L8）
A86: Calib | B86: 143 | C86: prefill tok/s/GPU | D86: tok/s | E86: 4 | F86: 1 | G86: C143 | H86: =C142*C124*1000000000000000/(C137*1000000000) | I86: 59211.424 | J86: — | K86: — | L86: — | M86: — | N86: — | O86: — | P86: — | Q86: 上游含 Y5,Y8 | R86: — | S86: Y5,Y8 | U86: 4 | W86: 資訊（只有 L8）
A87: Calib | B87: 144 | C87: 每步固定延遲 | D87: ms | E87: 4 | F87: 1 | G87: C144 | H87: =C134/C126+($C$102+C138)*C141/1000 | I87: 13.508475 | J87: — | K87: — | L87: — | M87: — | N87: — | O87: — | P87: — | Q87: 上游含 Y5,Y8 | R87: — | S87: Y5,Y8 | U87: 8 | W87: 資訊（只有 L8）
A88: Calib | B88: 145 | C88: 每序列每步時間 | D88: ms | E88: 4 | F88: 1 | G88: C145 | H88: =MAX((C138+1)*C136/(C124*C140)/1000,$C$108*C135/(C126*Serving!$C$13)/1000000000,(C138+1)*$C$102*$C$105*$C$103*Serving!$C$12*(C133-1)/C133/(C127*Serving!$C$14)/1000000000) | I88: 0.654022 | J88: — | K88: — | L88: — | M88: — | N88: — | O88: — | P88: — | Q88: 上游含 Y5,Y8 | R88: — | S88: Y5,Y8 | U88: 8 | W88: 資訊（只有 L8）
A89: Calib | B89: 146 | C89: B* | D89: 序列 | E89: 4 | F89: 1 | G89: C146 | H89: =MAX(0,MIN((1000*C139/C118-C144)/C145,(C131-C134)*1000000000/($C$108*C135))) | I89: 37.439936 | J89: — | K89: — | L89: — | M89: — | N89: — | O89: — | P89: — | Q89: 上游含 Y5,Y8 | R89: — | S89: Y5,Y8 | U89: 4 | W89: 資訊（只有 L8）
A90: Calib | B90: 147 | C90: decode tok/s/GPU | D90: tok/s | E90: 4 | F90: 1 | G90: C147 | H90: =IF(C146>0,C146*C139/((C144+C146*C145)/1000),0) | I90: 2495.9958 | J90: — | K90: — | L90: — | M90: — | N90: — | O90: — | P90: — | Q90: 上游含 Y5,Y8 | R90: — | S90: Y5,Y8 | U90: 4 | W90: 資訊（只有 L8）
A91: Calib | B91: 148 | C91: 模型輸出 tok/s/GPU（含 prefill 分攤） | D91: tok/s | E91: 4 | F91: 1 | G91: C148 | H91: =IF(C147>0,$C$111/($C$110/C143+$C$111/C147),0) | I91: 2474.4887 | J91: — | K91: — | L91: — | M91: — | N91: — | O91: — | P91: — | Q91: 上游含 Y5,Y8 | R91: — | S91: Y5,Y8 | U91: 6 | W91: 資訊（只有 L8）
A92: Calib | B92: 149 | C92: 模型 ÷ MLPerf | D92: x | E92: 4 | F92: 1 | G92: C149 | H92: =C148/C120 | I92: 0.702797 | J92: — | K92: — | L92: — | M92: — | N92: — | O92: — | P92: — | Q92: 上游含 Y5,Y8 | R92: [G07] 模型 ÷ MLPerf＝0.70／0.49／0.69／0.62：服務產能用的同一套效率，比稽核過的基準低 30–51%；Checks B23 只顯示 | S92: Y5,Y8 | U92: 0 | V92: G07 | W92: 中
A93: Calib | B93: 150 | C93: VR200 ÷ GB300（interactive）：模型 | E93: 1 | F93: 1 | G93: C150 | H93: =E148/C148 | I93: 2.525126 | J93: — | K93: — | L93: — | M93: — | N93: [G07] VR200 ÷ GB300 模型 2.525 對 MLPerf 2.575：VR200 用預覽類提交（利害關係方） | O93: — | P93: — | Q93: 上游含 Y5,Y8 | R93: — | S93: Y5,Y8 | U93: 0 | V93: G07 | W93: 低
A94: Calib | B94: 151 | C94: VR200 ÷ GB300（interactive）：MLPerf v6.1 | E94: 1 | F94: 1 | G94: C151 | H94: =E120/C120 | I94: 2.57489 | J94: — | K94: [G07] MLPerf 對照混用不同輪次：GB300 interactive v6.1（2026-09）、GB200 interactive v6.0（2026-04）、VR200 v6.1 預覽類、GB300 server v6.0；Calib D152「GB300 ÷ GB200＝1.055」是 v6.1 對 v6.0 | L94: — | M94: — | N94: — | O94: — | P94: — | Q94: — | R94: — | U94: 0 | V94: G07 | W94: 中
A95: Calib | B95: 152 | C95: GB300 ÷ GB200（interactive）：模型 ／ MLPerf | E95: 2 | F95: 2 | G95: C152 | H95: =C148/D148 | I95: 1.5 | J95: — | K95: [G07] MLPerf 對照混用不同輪次：GB300 interactive v6.1（2026-09）、GB200 interactive v6.0（2026-04）、VR200 v6.1 預覽類、GB300 server v6.0；Calib D152「GB300 ÷ GB200＝1.055」是 v6.1 對 v6.0 | L95: — | M95: — | N95: — | O95: — | P95: — | Q95: 上游含 Y5,Y8 | R95: — | S95: Y5,Y8 | U95: 0 | V95: G07 | W95: 中
A96: Calib | B96: 156 | C96: 批次口徑 η_d 倍數（X10；CAL_BatchEtaD） | D96: x | E96: 0 | F96: 0 | J96: — | K96: — | L96: — | M96: — | N96: — | O96: [G08] VR200 0.75＝MLPerf v6.1 Offline 比值（1.62–1.74）÷ 模型高批次比值（2.33）：由目標比值反推的校準值；其餘世代為 1（說明自述「無批次口徑實測」）。S3：0.7／1.0 → IF_ProgCost_Sol（VR200）+2.8%／−9.8% | P96: — | Q96: — | R96: — | U96: 45 | V96: G08 | W96: 中
A97: Tech_Registry | B97: 25 | C97: H_TPK | D97: 訓練峰值倍數 | E97: 1 | F97: 1 | G97: E25 | H97: =EXP(SUMPRODUCT(($C$5:$C$16="H_TPK")*LN($P$5:$P$16))) | I97: 1 | J97: — | K97: — | L97: — | M97: — | N97: — | O97: — | P97: [G22] EXP(SUMPRODUCT(LN(P)))：任一 P ≤ 0 即 #NUM!；基準 P 全為 1 | Q97: — | R97: — | U97: 47 | V97: G22 | W97: 低
A98: Tech_Registry | B98: 26 | C98: H_MFU | D98: 訓練 MFU 倍數 | E98: 1 | F98: 1 | G98: E26 | H98: =EXP(SUMPRODUCT(($C$5:$C$16="H_MFU")*LN($P$5:$P$16))) | I98: 1 | J98: — | K98: — | L98: — | M98: — | N98: — | O98: — | P98: [G22] EXP(SUMPRODUCT(LN(P)))：任一 P ≤ 0 即 #NUM!；基準 P 全為 1 | Q98: — | R98: — | U98: 47 | V98: G22 | W98: 低
A99: Tech_Registry | B99: 27 | C99: H_TOK | D99: 達同等預訓練品質所需 token 倍數 | E99: 1 | F99: 1 | G99: E27 | H99: =EXP(SUMPRODUCT(($C$5:$C$16="H_TOK")*LN($P$5:$P$16))) | I99: 1 | J99: — | K99: — | L99: — | M99: — | N99: — | O99: — | P99: [G22] EXP(SUMPRODUCT(LN(P)))：任一 P ≤ 0 即 #NUM!；基準 P 全為 1 | Q99: — | R99: — | U99: 43 | V99: G22 | W99: 低
A100: Tech_Registry | B100: 28 | C100: H_ROLL | D100: rollout 效率倍數 | E100: 1 | F100: 1 | G100: E28 | H100: =EXP(SUMPRODUCT(($C$5:$C$16="H_ROLL")*LN($P$5:$P$16))) | I100: 1 | J100: — | K100: — | L100: — | M100: — | N100: — | O100: — | P100: [G22] EXP(SUMPRODUCT(LN(P)))：任一 P ≤ 0 即 #NUM!；基準 P 全為 1 | Q100: — | R100: — | U100: 47 | V100: G22 | W100: 低
...

Sheet 傳遞強度
A1: 規則：嚴重度「高」的問題（G01–G06、G14、G15），估計對下游契約名稱（docs/plan/Tokenomics_downstream_contract.md：IF_／IFW_／L1_）的影響方向與大小。結構量直接由工作簿數值計算；端點擾動以第 2 段 20_eval.py（工作簿公式原文求值；3A 5,628 格對快取值 0 不符；LibreOffice 1 次 27 格 0 不符）單一輸入取 Gov_Map 區間端點、其他不變重算。「替代讀法」只重組工作簿數值，不是活頁簿機制，只用來顯示大小。G05（η_p）、G15（B4_Serve、B4_Free）的大小見端點列。
A2: G 編號 | B2: 問題 | C2: 受影響的契約名稱 | D2: 方向 | E2: 大小 | F2: 方法
A3: G01 | B3: 由上而下攤提閉合 0.82–0.88（Amortize 39） | C3: IF_AmortTD_*、IF_AmortDefault_*、IF_AmortRev_*、IF_FullCostDefault_* | D3: 偏低 | E3: Hopper 閉合 0.820（閉合到訓練 GW × 持有成本時攤提 +22%）；GB200 閉合 0.874（閉合到訓練 GW × 持有成本時攤提 +14%）；GB300 閉合 0.881（閉合到訓練 GW × 持有成本時攤提 +14%）；VR200 閉合 0.859（閉合到訓練 GW × 持有成本時攤提 +16%）；Rubin 閉合 0.855（閉合到訓練 GW × 持有成本時攤提 +17%） | F3: 結構量（不擾動）；χ＝0 時閉合 1.00（Python 與 LibreOffice 各 1 次）
A4: G02 | B4: 自下而上攤提分母含免費 token（Amortize 13／22／32） | C4: IF_AmortBU_*、IF_FullCost_*、IF_AmortDefault_*、IF_FullCostDefault_* | D4: 偏低（以付費 token 為分母時） | E4: Hopper Luna：分母比 8.42，IF_FullCost +46%、IF_FullCostDefault +94%；Hopper Sol：分母比 1.73，IF_FullCost +14%、IF_FullCostDefault +25%；Hopper Astra：分母比 1.00，IF_FullCost +0%、IF_FullCostDefault +0%；VR200 Luna：分母比 7.46，IF_FullCost +10%、IF_FullCostDefault +75%；VR200 Sol：分母比 1.64，IF_FullCost +4%、IF_FullCostDefault +21%；VR200 Astra：分母比 1.00，IF_FullCost +0%、IF_FullCostDefault +0% | F4: 替代讀法（只重組工作簿數值；33_alt.py）
A5: G03 | B5: _Prod 層 token 線性 0.85、營收重解 SLO | C5: IFW_TokGW_*_Prod、IFW_RevGW*_Prod | D5: token 層偏高（相對營收層） | E5: IFW_RevGW_Sol：Hopper 0.730、GB200 0.798、GB300 0.798、VR200 0.808、Rubin 0.810；IFW_RevGW_Astra：Hopper 0.486、GB200 0.733、GB300 0.699、VR200 0.766、Rubin 0.776；IFW_RevGWFleet：Hopper 0.560、GB200 0.758、GB300 0.732、VR200 0.782、Rubin 0.789；IFW_TokGW_Sol：Hopper 0.850、GB200 0.850、GB300 0.850、VR200 0.850、Rubin 0.850 | F5: 結構量（_Prod ÷ _Util）
A6: G04 | B6: 兩組 _Life（IF_ 不含折減、IFW_ 含重解折減） | C6: IF_RevGW_*_Life、IF_RevGWFleet_Life 對 IFW_*_Life | D6: IF_ 組偏高 | E6: IFW_RevGW_Luna_Life：Hopper 0.685、GB200 0.782、GB300 0.782、VR200 0.787、Rubin 0.788；IFW_RevGW_Sol_Life：Hopper 0.730、GB200 0.798、GB300 0.798、VR200 0.808、Rubin 0.810；IFW_RevGW_Astra_Life：Hopper 0.486、GB200 0.733、GB300 0.699、VR200 0.766、Rubin 0.776；IFW_RevGWFleet_Life：Hopper 0.560、GB200 0.758、GB300 0.732、VR200 0.782、Rubin 0.789 | F6: 結構量（IFW ÷ IF）
A7: G06 | B7: 組合旗標使可達層級也變文字；單一層級列變 0 | C7: IF_AmortBU_*、IF_AmortDefault_*、IF_FullCost*、IFW_RevGWFleet*；IFW_TokGW_Astra_*、IFW_RevGW_Astra_* 等 | D7: 文字／0 | E7: Serving!C18=0.7：變文字 28 個名稱、變 0 13 個名稱；Arch!E8=160：變文字 31 個名稱、變 0 13 個名稱；Calib!C68=3：變文字 37 個名稱、變 0 39 個名稱；Serving!D21,E21=100：變文字 34 個名稱、變 0 26 個名稱 | F7: 4 個 L7 情境（20_l7_closure.py）
A8: G14 | B8: 縮放倍數 2.2–12.0；預設攤提總額由 B4_Serve 決定 | C8: IF_AmortDefault_*、IF_FullCostDefault_* | D8: 視 B4_Serve | E8: 見下方 A02 列（B4_Serve 0.3／0.6） | F8: 端點擾動
A9: 端點 | B9: A01／Y11 快取命中 χ（Cap_In C13） | C9: IF_AmortTD_Sol（VR200 基準）、IF_FullCost_Sol（VR200 基準）、IF_AmortDefault_Sol（VR200 基準）、IF_FullCostDefault_Sol（VR200 基準）、IF_FullCostDefault_Luna（Hopper 基準）、IFW_RevGW_Sol_Prod（VR200）、IFW_RevGWFleet_Prod（Hopper 基準）、IFW_RevGWFleet_Prod（VR200 基準）、縮放倍數 Amortize!M41 | D9: 低端／高端 | E9: IF_AmortTD_Sol（VR200 基準） +8.6%／-6.9%；IF_FullCost_Sol（VR200 基準） +8.1%／-6.5%；IF_AmortDefault_Sol（VR200 基準） +7.4%／-6.0%；IF_FullCostDefault_Sol（VR200 基準） +8.2%／-6.6%；IF_FullCostDefault_Luna（Hopper 基準） +11.6%／-9.3%；IFW_RevGW_Sol_Prod（VR200） +19.9%／-15.9%；IFW_RevGWFleet_Prod（Hopper 基準） +19.9%／-15.9%；IFW_RevGWFleet_Prod（VR200 基準） +19.9%／-15.9%；縮放倍數 Amortize!M41 +7.4%／-6.0% | F9: 單一輸入端點 0.3／0.75；20_eval.py
A10: 端點 | B10: A02／Y11 對外服務占機隊（Cap_In C28） | C10: IF_AmortBU_Sol（VR200 基準）、IF_AmortTD_Sol（VR200 基準）、IF_FullCost_Sol（VR200 基準）、IF_AmortDefault_Sol（VR200 基準）、IF_FullCostDefault_Sol（VR200 基準）、IF_AmortBU_Luna（Hopper 基準）、IF_FullCostDefault_Luna（Hopper 基準）、IFW_RevGWFleet_Prod（Hopper 基準）、IFW_RevGWFleet_Prod（VR200 基準）、縮放倍數 Amortize!M41 | D10: 低端／高端 | E10: IF_AmortBU_Sol（VR200 基準） +36.7%／-31.7%；IF_AmortTD_Sol（VR200 基準） +62.1%／-53.7%；IF_FullCost_Sol（VR200 基準） +2.1%／-1.8%；IF_AmortDefault_Sol（VR200 基準） +62.1%／-53.7%；IF_FullCostDefault_Sol（VR200 基準） +20.3%／-17.5%；IF_AmortBU_Luna（Hopper 基準） +36.7%／-31.7%；IF_FullCostDefault_Luna（Hopper 基準） +7.8%／-6.8%；IFW_RevGWFleet_Prod（Hopper 基準） -26.8%／+46.3%；IFW_RevGWFleet_Prod（VR200 基準） -26.8%／+46.3%；縮放倍數 Amortize!M41 +18.6%／-32.2% | F10: 單一輸入端點 0.3／0.6；20_eval.py
A11: 端點 | B11: A03／Y11 免費占服務（Cap_In C29） | C11: IF_AmortBU_Sol（VR200 基準）、IF_FullCost_Sol（VR200 基準）、IF_AmortDefault_Sol（VR200 基準）、IF_FullCostDefault_Sol（VR200 基準）、IF_AmortBU_Luna（Hopper 基準）、IF_FullCostDefault_Luna（Hopper 基準）、IFW_RevGWFleet_Prod（Hopper 基準）、IFW_RevGWFleet_Prod（VR200 基準）、縮放倍數 Amortize!M41 | D11: 低端／高端 | E11: IF_AmortBU_Sol（VR200 基準） -3.0%／+4.1%；IF_FullCost_Sol（VR200 基準） -0.2%／+0.2%；IF_AmortDefault_Sol（VR200 基準） -2.8%／+3.8%；IF_FullCostDefault_Sol（VR200 基準） -0.9%／+1.2%；IF_AmortBU_Luna（Hopper 基準） +22.9%／-19.2%；IF_FullCostDefault_Luna（Hopper 基準） +3.0%／-2.5%；IFW_RevGWFleet_Prod（Hopper 基準） +20.4%／-25.9%；IFW_RevGWFleet_Prod（VR200 基準） +20.4%／-25.9%；縮放倍數 Amortize!M41 +0.2%／-0.3% | F11: 單一輸入端點 0.35／0.6；20_eval.py
A12: 端點 | B12: A02 研發倍數（Train_In C13） | C12: IF_AmortBU_Sol（VR200 基準）、IF_FullCost_Sol（VR200 基準）、IF_AmortBU_Luna（Hopper 基準）、IF_ProgCost_Sol（VR200 基準）、縮放倍數 Amortize!M41 | D12: 低端／高端 | E12: IF_AmortBU_Sol（VR200 基準） -45.0%／+30.0%；IF_FullCost_Sol（VR200 基準） -2.5%／+1.7%；IF_AmortBU_Luna（Hopper 基準） -45.0%／+30.0%；IF_ProgCost_Sol（VR200 基準） -45.0%／+30.0%；縮放倍數 Amortize!M41 +81.8%／-23.1% | F12: 單一輸入端點 4.4／10.4；20_eval.py
A13: 端點 | B13: A04／Y10 生產折減（Serving C28） | C13: IFW_TokGW_Sol_Prod（VR200）、IFW_RevGW_Sol_Prod（VR200）、IFW_RevGWFleet_Prod（Hopper 基準）、IFW_RevGWFleet_Prod（VR200 基準） | D13: 低端／高端 | E13: IFW_TokGW_Sol_Prod（VR200） -17.6%／+17.6%；IFW_RevGW_Sol_Prod（VR200） -24.1%／+23.8%；IFW_RevGWFleet_Prod（Hopper 基準） —／+78.6%；IFW_RevGWFleet_Prod（VR200 基準） -28.7%／+27.8% | F13: 單一輸入端點 0.7／1.0；20_eval.py
... A18: 端點 | B18: A07 平均用電 ÷ 設計功率（Inputs E10） | C18: IF_CostDec_Sol（VR200 基準）、IF_CostPre_Sol（VR200 基準）、IF_AmortBU_Sol（VR200 基準）、IF_AmortTD_Sol（VR200 基準）、IF_FullCost_Sol（VR200 基準）、IF_AmortDefault_Sol（VR200 基準）、IF_FullCostDefault_Sol（VR200 基準）、IF_AmortBU_Luna（Hopper 基準）、IF_FullCostDefault_Luna（Hopper 基準）、IF_ProgCost_Sol（VR200 基準）、IF_TokPerJ_Sol（VR200） | D18: 低端／高端 | E18: IF_CostDec_Sol（VR200 基準） -0.7%／+0.7%；IF_CostPre_Sol（VR200 基準） -0.7%／+0.7%；IF_AmortBU_Sol（VR200 基準） -0.7%／+0.7%；IF_AmortTD_Sol（VR200 基準） -0.7%／+0.7%；IF_FullCost_Sol（VR200 基準） -0.7%／+0.7%；IF_AmortDefault_Sol（VR200 基準） -0.7%／+0.7%；IF_FullCostDefault_Sol（VR200 基準） -0.7%／+0.7%；IF_AmortBU_Luna（Hopper 基準） -0.9%／+0.9%；IF_FullCostDefault_Luna（Hopper 基準） -0.9%／+0.9%；IF_ProgCost_Sol（VR200 基準） -0.7%／+0.7%；IF_TokPerJ_Sol（VR200） +14.3%／-11.1% | F18: 單一輸入端點 0.7／0.9；20_eval.py

Sheet 高嚴重度
A1: 規則：「逐列檢查」頁嚴重度＝高的列（直接作用在下游契約名稱的口徑或閉合問題）。只標問題，不判定對錯、不提修法。
A2: 頁 | B2: 列 | C2: 列標籤 | D2: G 編號 | E2: L2 | F2: L4 | G2: L5 | H2: L6 | I2: L7 | J2: L9 | K2: L8
A3: Calib | B3: 86 | C3: 模型 ÷ 實測 | D3: G05 | E3: — | F3: — | G3: [G05] Calib D 節以兩個擬合點聯立解兩個未知數（η_d、每層延遲），F 節擬合點「模型 ÷ 實測」恆為 1.00（Checks B14），是代數恆等，不是驗證。η_d＝3.58% 是吸收未建模開銷的擬合係數，比一般 GEMM 達成率低一個數量級以上（L9）。J5 說明「擬合結果對 η_p 不敏感」，但 G 節顯示 η_p 0.15／0.3／0.45 → η_d 0.055／0.036／0.032、每層延遲 175／161／157 µs；S3：η_p 端點 → IF_CostPre_Sol（VR200）+100%／−33%、IF_CostDec_Sol −33%／+11%、IFW_RevGWFleet_Prod（Hopper）−30%／+8% | H3: — | I3: — | J3: [G05] 擬合 η_d 3.58%（GB300、Sol）；Perf 推出的 decode 有效 MFU（含草稿驗證）全部 15 欄 1.0–2.5% | K3: 上游含 Y1,Y5,Y8
A4: Fleet_1GW | B4: 10 | C4: 對外服務 | D4: G15 | E4: [G15] 1 GW 參考機隊的服務／免費／訓練占比＝2025 OpenAI 支出比（B4_Serve 0.41、B4_Free 0.46），全部世代同值（Y11；與第 1 段 Y3 同源） | F4: — | G4: — | H4: — | I4: — | J4: — | K4: 直接引用 Y3 類輸入
A5: Fleet_1GW | B5: 12 | C5: 免費服務 | D5: G15 | E5: [G15] 1 GW 參考機隊的服務／免費／訓練占比＝2025 OpenAI 支出比（B4_Serve 0.41、B4_Free 0.46），全部世代同值（Y11；與第 1 段 Y3 同源） | F5: — | G5: — | H5: — | I5: — | J5: — | K5: 直接引用 Y3 類輸入
A6: Fleet_1GW | B6: 13 | C6: 訓練＋研發 | D6: G15 | E6: [G15] 1 GW 參考機隊的服務／免費／訓練占比＝2025 OpenAI 支出比（B4_Serve 0.41、B4_Free 0.46），全部世代同值（Y11；與第 1 段 Y3 同源） | F6: — | G6: — | H6: — | I6: — | J6: — | K6: 直接引用 Y3 類輸入
A7: Fleet_1GW | B7: 33 | C7: 家族研發計畫占 1 GW 年（三層級合計） | D7: G14 | E7: — | F7: — | G7: — | H7: — | I7: — | J7: [G14] 隱含每 GW 年家族研發計畫 3.4（Hopper）–12.1（VR200），活頁簿自己的參考範圍 1–3（Checks B51，只顯示） | K7: 上游含 Y1,Y5,Y8
A8: Fleet_1GW | B8: 34 | C8: 隱含每 GW 年可容納的家族研發計畫數（訓練＋研發 ÷ 家族計畫） | D8: G14 | E8: — | F8: — | G8: — | H8: — | I8: — | J8: [G14] 隱含每 GW 年家族研發計畫 3.4（Hopper）–12.1（VR200），活頁簿自己的參考範圍 1–3（Checks B51，只顯示） | K8: 上游含 Y1,Y3,Y5,Y8
A9: Amortize | B9: 13 | C9: 自下而上攤提＝回本所需單價溢價 [IF_AmortBU_Luna] | D9: G02,G06 | E9: [G02] 自下而上攤提＝研發計畫成本 ÷ 壽命內「付費＋免費」token，列標籤卻是「回本所需單價溢價」：免費 token 不付費，以付費 token 為分母時 Luna 溢價為 8.4 倍（Hopper）／7.5 倍（VR200）、Sol 1.6–1.8 倍、Astra 1.0 倍（免費組合 Astra 0%）（30_s3.json BU_denominator_ratio） | F9: — | G9: — | H9: — | I9: [G06] 組合旗標使本列在任一層級不可達時變文字，包括可達層級（20_l7_closure.json） | J9: — | K9: 上游含 Y1,Y2,Y3,Y4,Y5,Y6,Y7,Y8
A10: Amortize | B10: 15 | C10: 由上而下攤提 [IF_AmortTD_Luna] | D10: G01,G06 | E10: — | F10: [G01] 由上而下溢價＝訓練占比 ÷（1 − 訓練占比）× 服務成本（快取混合）；因服務成本 × 服務 token ≠ 服務 GW × 持有成本，攤提總額少計 12–18%（見 Amortize 第 39 列） | G10: — | H10: — | I10: [G06] 組合旗標使本列在任一層級不可達時變文字，包括可達層級（20_l7_closure.json） | J10: — | K10: 上游含 Y1,Y2,Y3,Y4,Y5,Y6,Y7,Y8
A11: Amortize | B11: 22 | C11: 自下而上攤提＝回本所需單價溢價 [IF_AmortBU_Sol] | D11: G02,G06 | E11: [G02] 自下而上攤提＝研發計畫成本 ÷ 壽命內「付費＋免費」token，列標籤卻是「回本所需單價溢價」：免費 token 不付費，以付費 token 為分母時 Luna 溢價為 8.4 倍（Hopper）／7.5 倍（VR200）、Sol 1.6–1.8 倍、Astra 1.0 倍（免費組合 Astra 0%）（30_s3.json BU_denominator_ratio） | F11: — | G11: — | H11: — | I11: [G06] 組合旗標使本列在任一層級不可達時變文字，包括可達層級（20_l7_closure.json） | J11: — | K11: 上游含 Y1,Y2,Y3,Y4,Y5,Y6,Y7,Y8
A12: Amortize | B12: 24 | C12: 由上而下攤提 [IF_AmortTD_Sol] | D12: G01,G06 | E12: — | F12: [G01] 由上而下溢價＝訓練占比 ÷（1 − 訓練占比）× 服務成本（快取混合）；因服務成本 × 服務 token ≠ 服務 GW × 持有成本，攤提總額少計 12–18%（見 Amortize 第 39 列） | G12: — | H12: — | I12: [G06] 組合旗標使本列在任一層級不可達時變文字，包括可達層級（20_l7_closure.json） | J12: — | K12: 上游含 Y1,Y2,Y3,Y4,Y5,Y6,Y7,Y8
A13: Amortize | B13: 32 | C13: 自下而上攤提＝回本所需單價溢價 [IF_AmortBU_Astra] | D13: G02,G06 | E13: [G02] 自下而上攤提＝研發計畫成本 ÷ 壽命內「付費＋免費」token，列標籤卻是「回本所需單價溢價」：免費 token 不付費，以付費 token 為分母時 Luna 溢價為 8.4 倍（Hopper）／7.5 倍（VR200）、Sol 1.6–1.8 倍、Astra 1.0 倍（免費組合 Astra 0%）（30_s3.json BU_denominator_ratio） | F13: — | G13: — | H13: — | I13: [G06] 組合旗標使本列在任一層級不可達時變文字，包括可達層級（20_l7_closure.json） | J13: — | K13: 上游含 Y1,Y2,Y3,Y4,Y5,Y6,Y7,Y8
A14: Amortize | B14: 34 | C14: 由上而下攤提 [IF_AmortTD_Astra] | D14: G01,G06 | E14: — | F14: [G01] 由上而下溢價＝訓練占比 ÷（1 − 訓練占比）× 服務成本（快取混合）；因服務成本 × 服務 token ≠ 服務 GW × 持有成本，攤提總額少計 12–18%（見 Amortize 第 39 列） | G14: — | H14: — | I14: [G06] 組合旗標使本列在任一層級不可達時變文字，包括可達層級（20_l7_closure.json） | J14: — | K14: 上游含 Y1,Y2,Y3,Y4,Y5,Y6,Y7,Y8
... A53: Interface | B53: 285 | C53: 每 GW 總產出（100%）｜× CTL_ProdDerate（＝Util 列 × CTL_ProdDerate，線性；Interface_Prod 同列為 100% 口徑重解值，保留原處作對照） [IFW_TokGW_Astra_Prod] | D53: G03,G06 | E53: [G03] 每 GW 產出的 _Prod 層＝Util 列 × CTL_ProdDerate（線性 0.85），同一瀑布的營收 _Prod 層（第 235／240／245／250 列）＝重解 SLO 後的值，比 Util 低 0.49–0.81 倍（Hopper Astra 0.486、VR200 Sol 0.808）。同一層名稱，token 與營收的折減方式不同，_Prod 層的營收 ÷ token 不再等於單價。契約第 2 條寫「_Prod＝_Util × CTL_ProdDerate」（線性） | F53: — | G53: — | H53: — | I53: [G06] 單一層級列不可達時輸出 0（數值）而非文字；與組合列的文字處理方式相反（第 2 段 F09） | J53: — | K53: 直接引用 Y5 類輸入

Sheet L9 物理量
A1: 規則：Perf 15 欄（世代 × 成本情境欄依層級）在基準下的中間物理量。decode 有效 MFU＝每 GPU decode tok/s × decode FLOPs/token ×（草稿數＋1）÷ 每步接受 token ÷ 計算用峰值（含草稿驗證）；prefill MFU＝prefill tok/s × prefill FLOPs/token ÷ 峰值；decode HBM 頻寬利用率＝每 GPU decode tok/s × 每接受 token HBM 讀取 ÷ HBM 頻寬。全部由工作簿數值計算（31_l9_closure_cause.py），不新增機制。只顯示，不判定。
A2: 世代 | B2: 層級 | C2: B*（序列/GPU） | D2: decode tok/s/GPU | E2: 每用戶速度 | F2: decode 有效 MFU | G2: prefill MFU | H2: decode HBM 頻寬利用率 | I2: TTFT 計算（s） | J2: TTFT 符合 | K2: tok/J | L2: J/decode token | M2: 能量閉合比 | N2: 權重占可用 HBM
A3: Hopper H100 | B3: Luna | C3: 4.85 | D3: 581.4 | E3: 120 | F3: 0.018 | G3: 0.15 | H3: 0.14 | I3: 0.132 | J3: 是 | K3: 3.19 | L3: 1.763 | M3: 0.037 | N3: 0.136
A4: Hopper H100 | B4: Sol | C4: 2.61 | D4: 169.4 | E4: 65 | F4: 0.018 | G4: 0.15 | H4: 0.268 | I4: 0.917 | J4: 是 | K4: 0.93 | L4: 6.05 | M4: 0.045 | N4: 0.484
A5: Hopper H100 | B5: Astra | C5: 0.45 | D5: 24.6 | E5: 55 | F5: 0.0104 | G5: 0.15 | H5: 0.271 | I5: 6.082 | J5: 否 | K5: 0.17 | L5: 41.712 | M5: 0.038 | N5: 0.568
A6: GB200 NVL72 | B6: Luna | C6: 28.63 | D6: 3435.8 | E6: 120 | F6: 0.021 | G6: 0.3 | H6: 0.065 | I6: 0.026 | J6: 是 | K6: 15.61 | L6: 0.427 | M6: 0.053 | N6: 0.062
A7: GB200 NVL72 | B7: Sol | C7: 15.18 | D7: 986.6 | E7: 65 | F7: 0.0208 | G7: 0.3 | H7: 0.157 | I7: 0.181 | J7: 是 | K7: 4.49 | L7: 1.487 | M7: 0.062 | N7: 0.287
A8: GB200 NVL72 | B8: Astra | C8: 3.07 | D8: 168.6 | E8: 55 | F8: 0.0141 | G8: 0.3 | H8: 0.261 | I8: 1.203 | J8: 是 | K8: 0.86 | L8: 8.699 | M8: 0.06 | N8: 0.537
A9: GB300 NVL72 | B9: Luna | C9: 42.95 | D9: 5153.8 | E9: 120 | F9: 0.021 | G9: 0.3 | H9: 0.067 | I9: 0.017 | J9: 是 | K9: 22.73 | L9: 0.293 | M9: 0.059 | N9: 0.04
A10: GB300 NVL72 | B10: Sol | C10: 22.77 | D10: 1479.9 | E10: 65 | F10: 0.0208 | G10: 0.3 | H10: 0.159 | I10: 0.121 | J10: 是 | K10: 6.53 | L10: 1.021 | M10: 0.067 | N10: 0.185
A11: GB300 NVL72 | B11: Astra | C11: 3.7 | D11: 203.2 | E11: 55 | F11: 0.0114 | G11: 0.3 | H11: 0.342 | I11: 0.802 | J11: 是 | K11: 1.04 | L11: 7.435 | M11: 0.067 | N11: 0.457
A12: VR200 NVL72 | B12: Luna | C12: 106.84 | D12: 12820.4 | E12: 120 | F12: 0.0224 | G12: 0.3 | H12: 0.028 | I12: 0.007 | J12: 是 | K12: 33.3 | L12: 0.197 | M12: 0.046 | N12: 0.04
A13: VR200 NVL72 | B13: Sol | C13: 62.09 | D13: 4035.7 | E13: 65 | F13: 0.0243 | G13: 0.3 | H13: 0.061 | I13: 0.052 | J13: 是 | K13: 10.23 | L13: 0.625 | M13: 0.052 | N13: 0.185
A14: VR200 NVL72 | B14: Astra | C14: 14.18 | D14: 779.6 | E14: 55 | F14: 0.0187 | G14: 0.3 | H14: 0.145 | I14: 0.344 | J14: 是 | K14: 2.2 | L14: 3.235 | M14: 0.053 | N14: 0.457
... A17: Rubin Ultra | B17: Astra | C17: 31.61 | D17: 1738.7 | E17: 55 | F17: 0.0208 | G17: 0.3 | H17: 0.1 | I17: 0.086 | J17: 是 | K17: 3.21 | L17: 2.173 | M17: 0.06 | N17: 0.091
