Workbook

Sheet TK 拆解
A1: Tokenomics 每 IT-GW·年 經濟口徑持有成本拆解（$B/GW·年）
A2: 來源活頁簿：model/20261023_Tokenomics_v20.1.xlsx（model/CURRENT）。藍字＝自模型讀入的輸入（附儲存格位置）；黑字＝本頁公式重算；「模型值」列為 DC_Cost!第55列，差列應為 0。GW 口徑＝IT 關鍵電力（CLAUDE.md 第 7 節）。
A4: 項目 | B4: 單位 | C4: Hopper H100 | D4: GB200 NVL72 | E4: GB300 NVL72 | F4: VR200 NVL72 | G4: 2025 機隊組合（0.6/0.4） | H4: 模型儲存格位置 | I4: 標記 | J4: 說明
A5: A. 輸入（自模型讀入）
A6: 服務世代組合（2025 全年平均） | B6: % | C6: 0.6 | D6: 0.4 | E6: 0 | F6: 0 | G6: =SUM(C6:F6) -> 1 | H6: Alloc_In!C9:C12 | I6: Derived | J6: 3A 查證 Q1；Blackwell 自 Q2 線性爬升
A7: IT 電力 | B7: MW | C7: 1000 | D7: =$C7 -> 1000 | E7: =$C7 -> 1000 | F7: =$C7 -> 1000 | H7: Inputs!E5×1000 | I7: Decision
A8: 機架外 IT 電力占比 | B8: % | C8: 0.08 | D8: =$C8 -> 0.08 | E8: =$C8 -> 0.08 | F8: =$C8 -> 0.08 | H8: Inputs!E8 | I8: Assumed
A9: PUE | B9: x | C9: 1.2 | D9: =$C9 -> 1.2 | E9: =$C9 -> 1.2 | F9: =$C9 -> 1.2 | H9: Inputs!E9 | I9: Analogy（區間 1.1–1.3）
A10: WACC | B10: % | C10: 0.1 | D10: =$C10 -> 0.1 | E10: =$C10 -> 0.1 | F10: =$C10 -> 0.1 | H10: Inputs!E28 | I10: Assumed（區間 8–13%）
A11: IT 折舊年限 | B11: 年 | C11: 6 | D11: =$C11 -> 6 | E11: =$C11 -> 6 | F11: =$C11 -> 6 | H11: Inputs!E23 | I11: Verified（區間 4–6）
A12: 每架配電設計功率（基準） | B12: kW | C12: 41 | D12: 132 | E12: 136 | F12: 227 | H12: Spec_Rack!C9:F9 | I12: Verified/Analogy
A13: GPU 封裝／架 | B13: 顆 | C13: 32 | D13: 72 | E13: 72 | F13: 72 | H13: Spec_Rack!C6:F6 | I13: Verified
A14: 機架單價（基準） | B14: $M | C14: 1.1 | D14: 3.1 | E14: 4.3 | F14: 8.4 | H14: Spec_Rack!C12:F12 | I14: Analogy
A15: Scale-out 網路 ÷ 機架價格 | B15: % | C15: 0.1 | D15: =$C15 -> 0.1 | E15: =$C15 -> 0.1 | F15: =$C15 -> 0.1 | H15: Inputs!E13 | I15: Analogy（5–15%）
A16: 儲存與管理 | B16: $/GPU | C16: 500 | D16: =$C16 -> 500 | E16: =$C16 -> 500 | F16: =$C16 -> 500 | H16: Inputs!E14 | I16: Assumed（300–800）
A17: 平均用電 ÷ 配電設計功率 | B17: % | C17: 0.8 | D17: =$C17 -> 0.8 | E17: =$C17 -> 0.8 | F17: =$C17 -> 0.8 | H17: Inputs!E10 | I17: Assumed（0.7–0.9）
A18: 電價 | B18: $/kWh | C18: 0.08 | D18: =$C18 -> 0.08 | E18: =$C18 -> 0.08 | F18: =$C18 -> 0.08 | H18: Inputs!E11 | I18: Verified/Analogy
A19: IT 維護費率（壽命期等值） | B19: %/年 | C19: 0.015725011 | D19: =$C19 -> 0.015725011 | E19: =$C19 -> 0.015725011 | F19: =$C19 -> 0.015725011 | H19: Inputs!E30 | I19: Derived | J19: 0.5% 保固期內 3 年、3% 保固後；以 WACC 折現成單一費率
A20: 廠房維護率 | B20: %/年 | C20: 0.02 | D20: =$C20 -> 0.02 | E20: =$C20 -> 0.02 | F20: =$C20 -> 0.02 | H20: Inputs!E31 | I20: Analogy
A21: 站點營運（人員＋軟體＋水耗材） | B21: $B/GW·年 | C21: 0.325 | D21: =$C21 -> 0.325 | E21: =$C21 -> 0.325 | F21: =$C21 -> 0.325 | H21: Inputs!E32:E34 | I21: Assumed | J21: 人員 75＋軟體 200＋水耗材 50 $M/GW·年
A22: 財產稅與保險率 | B22: %/年（總資本） | C22: 0.005 | D22: =$C22 -> 0.005 | E22: =$C22 -> 0.005 | F22: =$C22 -> 0.005 | H22: Inputs!E35 | I22: Analogy
A23: 土地 | B23: $M/MW | C23: 0.02 | D23: =$C23 -> 0.02 | E23: =$C23 -> 0.02 | F23: =$C23 -> 0.02 | H23: Inputs!E16 | I23: Assumed
A24: 建物與基地 | B24: $M/MW | C24: 3.6 | D24: =$C24 -> 3.6 | E24: =$C24 -> 3.6 | F24: =$C24 -> 3.6 | H24: Inputs!E17 | I24: Assumed（JLL 校準）
A25: 電力設施 | B25: $M/MW | C25: 4.5 | D25: =$C25 -> 4.5 | E25: =$C25 -> 4.5 | F25: =$C25 -> 4.5 | H25: Inputs!E18 | I25: Assumed
A26: 機械與散熱 | B26: $M/MW | C26: 2.5 | D26: =$C26 -> 2.5 | E26: =$C26 -> 2.5 | F26: =$C26 -> 2.5 | H26: Inputs!E19 | I26: Assumed
A27: 光纖、佈線、保全 | B27: $M/MW | C27: 0.4 | D27: =$C27 -> 0.4 | E27: =$C27 -> 0.4 | F27: =$C27 -> 0.4 | H27: Inputs!E20 | I27: Assumed
A28: 設計、管理與預備費率 | B28: % | C28: 0.15 | D28: =$C28 -> 0.15 | E28: =$C28 -> 0.15 | F28: =$C28 -> 0.15 | H28: Inputs!E21 | I28: Assumed
A29: 建物年限 | B29: 年 | C29: 30 | D29: =$C29 -> 30 | E29: =$C29 -> 30 | F29: =$C29 -> 30 | H29: Inputs!E24 | I29: Analogy
A30: 電力設施年限 | B30: 年 | C30: 20 | D30: =$C30 -> 20 | E30: =$C30 -> 20 | F30: =$C30 -> 20 | H30: Inputs!E25 | I30: Analogy
A31: 機械與散熱年限 | B31: 年 | C31: 15 | D31: =$C31 -> 15 | E31: =$C31 -> 15 | F31: =$C31 -> 15 | H31: Inputs!E26 | I31: Analogy
A32: 光纖與保全年限 | B32: 年 | C32: 10 | D32: =$C32 -> 10 | E32: =$C32 -> 10 | F32: =$C32 -> 10 | H32: Inputs!E27 | I32: Analogy
A33: B. 規模與資本支出（$B／GW IT）
A34: 機架數 | B34: 架 | C34: =FLOOR(C7*(1-C8)*1000/C12,1) -> 22439 | D34: =FLOOR(D7*(1-D8)*1000/D12,1) -> 6969 | E34: =FLOOR(E7*(1-E8)*1000/E12,1) -> 6764 | F34: =FLOOR(F7*(1-F8)*1000/F12,1) -> 4052 | G34: =SUMPRODUCT($C$6:$F$6,C34:F34) -> 16251 | H34: DC_Cost!第12列
A35: GPU 數 | B35: 顆 | C35: =C34*C13 -> 718048 | D35: =D34*D13 -> 501768 | E35: =E34*E13 -> 487008 | F35: =F34*F13 -> 291744 | G35: =SUMPRODUCT($C$6:$F$6,C35:F35) -> 631536 | H35: DC_Cost!第14列 | J35: 外部價格換算頁用此數把「每 GPU 小時」轉成「每 GW」
A36: 機架 capex | B36: $B | C36: =C34*C14/1000 -> 24.6829 | D36: =D34*D14/1000 -> 21.6039 | E36: =E34*E14/1000 -> 29.0852 | F36: =F34*F14/1000 -> 34.0368 | G36: =SUMPRODUCT($C$6:$F$6,C36:F36) -> 23.4513 | H36: DC_Cost!第19列
A37: Scale-out 網路 capex | B37: $B | C37: =C36*C15 -> 2.46829 | D37: =D36*D15 -> 2.16039 | E37: =E36*E15 -> 2.90852 | F37: =F36*F15 -> 3.40368 | G37: =SUMPRODUCT($C$6:$F$6,C37:F37) -> 2.34513 | H37: DC_Cost!第21列
A38: 儲存與管理 capex | B38: $B | C38: =C35*C16/1000000000 -> 0.359024 | D38: =D35*D16/1000000000 -> 0.250884 | E38: =E35*E16/1000000000 -> 0.243504 | F38: =F35*F16/1000000000 -> 0.145872 | G38: =SUMPRODUCT($C$6:$F$6,C38:F38) -> 0.315768 | H38: DC_Cost!第23列
A39: IT 設備 capex 小計 | B39: $B | C39: =C36+C37+C38 -> 27.510214 | D39: =D36+D37+D38 -> 24.015174 | E39: =E36+E37+E38 -> 32.237224 | F39: =F36+F37+F38 -> 37.586352 | G39: =SUMPRODUCT($C$6:$F$6,C39:F39) -> 26.112198 | H39: DC_Cost!第24列
A40: 土地 | B40: $B | C40: =C7*C23/1000 -> 0.02 | D40: =D7*D23/1000 -> 0.02 | E40: =E7*E23/1000 -> 0.02 | F40: =F7*F23/1000 -> 0.02 | G40: =SUMPRODUCT($C$6:$F$6,C40:F40) -> 0.02 | H40: DC_Cost!第25列
A41: 建物與基地 | B41: $B | C41: =C7*C24/1000 -> 3.6 | D41: =D7*D24/1000 -> 3.6 | E41: =E7*E24/1000 -> 3.6 | F41: =F7*F24/1000 -> 3.6 | G41: =SUMPRODUCT($C$6:$F$6,C41:F41) -> 3.6 | H41: DC_Cost!第26列
A42: 電力設施 | B42: $B | C42: =C7*C25/1000 -> 4.5 | D42: =D7*D25/1000 -> 4.5 | E42: =E7*E25/1000 -> 4.5 | F42: =F7*F25/1000 -> 4.5 | G42: =SUMPRODUCT($C$6:$F$6,C42:F42) -> 4.5 | H42: DC_Cost!第27列
A43: 機械與散熱 | B43: $B | C43: =C7*C26/1000 -> 2.5 | D43: =D7*D26/1000 -> 2.5 | E43: =E7*E26/1000 -> 2.5 | F43: =F7*F26/1000 -> 2.5 | G43: =SUMPRODUCT($C$6:$F$6,C43:F43) -> 2.5 | H43: DC_Cost!第28列
A44: 光纖與保全 | B44: $B | C44: =C7*C27/1000 -> 0.4 | D44: =D7*D27/1000 -> 0.4 | E44: =E7*E27/1000 -> 0.4 | F44: =F7*F27/1000 -> 0.4 | G44: =SUMPRODUCT($C$6:$F$6,C44:F44) -> 0.4 | H44: DC_Cost!第29列
A45: 設計、管理與預備費 | B45: $B | C45: =(C41+C42+C43+C44)*C28 -> 1.65 | D45: =(D41+D42+D43+D44)*D28 -> 1.65 | E45: =(E41+E42+E43+E44)*E28 -> 1.65 | F45: =(F41+F42+F43+F44)*F28 -> 1.65 | G45: =SUMPRODUCT($C$6:$F$6,C45:F45) -> 1.65 | H45: DC_Cost!第31列
A46: 廠房 capex 小計 | B46: $B | C46: =SUM(C40:C45) -> 12.67 | D46: =SUM(D40:D45) -> 12.67 | E46: =SUM(E40:E45) -> 12.67 | F46: =SUM(F40:F45) -> 12.67 | G46: =SUMPRODUCT($C$6:$F$6,C46:F46) -> 12.67 | H46: DC_Cost!第32列
A47: 總 capex（IT＋廠房） | B47: $B | C47: =C39+C46 -> 40.180214 | D47: =D39+D46 -> 36.685174 | E47: =E39+E46 -> 44.907224 | F47: =F39+F46 -> 50.256352 | G47: =SUMPRODUCT($C$6:$F$6,C47:F47) -> 38.782198 | H47: DC_Cost!第33列
A48: 每 MW IT 總 capex | B48: $M/MW | C48: =C47*1000/C7 -> 40.180214 | D48: =D47*1000/D7 -> 36.685174 | E48: =E47*1000/E7 -> 44.907224 | F48: =F47*1000/F7 -> 50.256352 | G48: =SUMPRODUCT($C$6:$F$6,C48:F48) -> 38.782198 | H48: DC_Cost!第35列 | J48: 對照 Epoch Abilene 資本成本 15.9B／421 MW IT ＝ 37.8 $M/MW
A49: C. 年持有成本（經濟口徑；$B／GW IT·年）
A50: IT 資本回收（年金） | B50: $B | C50: =C39*C10/(1-(1+C10)^(-C11)) -> 6.3165482 | D50: =D39*D10/(1-(1+D10)^(-D11)) -> 5.5140612 | E50: =E39*E10/(1-(1+E10)^(-E11)) -> 7.4019046 | F50: =F39*F10/(1-(1+F10)^(-F11)) -> 8.6301038 | G50: =SUMPRODUCT($C$6:$F$6,C50:F50) -> 5.9955534 | H50: DC_Cost!第53列
A51: 其中機架 | B51: $B | C51: =C36*C10/(1-(1+C10)^(-C11)) -> 5.667376 | D51: =D36*D10/(1-(1+D10)^(-D11)) -> 4.9604149 | E51: =E36*E10/(1-(1+E10)^(-E11)) -> 6.6781766 | F51: =F36*F10/(1-(1+F10)^(-F11)) -> 7.8151005 | G51: =SUMPRODUCT($C$6:$F$6,C51:F51) -> 5.3845916
A52: 其中網路 | B52: $B | C52: =C37*C10/(1-(1+C10)^(-C11)) -> 0.5667376 | D52: =D37*D10/(1-(1+D10)^(-D11)) -> 0.49604149 | E52: =E37*E10/(1-(1+E10)^(-E11)) -> 0.66781766 | F52: =F37*F10/(1-(1+F10)^(-F11)) -> 0.78151005 | G52: =SUMPRODUCT($C$6:$F$6,C52:F52) -> 0.53845916
A53: 其中儲存 | B53: $B | C53: =C38*C10/(1-(1+C10)^(-C11)) -> 0.08243456 | D53: =D38*D10/(1-(1+D10)^(-D11)) -> 0.057604818 | E53: =E38*E10/(1-(1+E10)^(-E11)) -> 0.055910316 | F53: =F38*F10/(1-(1+F10)^(-F11)) -> 0.033493288 | G53: =SUMPRODUCT($C$6:$F$6,C53:F53) -> 0.072502663
A54: 廠房資本回收（年金；土地按 WACC） | B54: $B | C54: =C41*C10/(1-(1+C10)^(-C29))*(1+C28)+C42*C10/(1-(1+C10)^(-C30))*(1+C28)+C43*C10/(1-(1+C10)^(-C31))*(1+C28)+C44*C10/(1-(1+C10)^(-C32))*(1+C28)+C40*C10 -> 1.5018716 | D54: =D41*D10/(1-(1+D10)^(-D29))*(1+D28)+D42*D10/(1-(1+D10)^(-D30))*(1+D28)+D43*D10/(1-(1+D10)^(-D31))*(1+D28)+D44*D10/(1-(1+D10)^(-D32))*(1+D28)+D40*D10 -> 1.5018716 | E54: =E41*E10/(1-(1+E10)^(-E29))*(1+E28)+E42*E10/(1-(1+E10)^(-E30))*(1+E28)+E43*E10/(1-(1+E10)^(-E31))*(1+E28)+E44*E10/(1-(1+E10)^(-E32))*(1+E28)+E40*E10 -> 1.5018716 | F54: =F41*F10/(1-(1+F10)^(-F29))*(1+F28)+F42*F10/(1-(1+F10)^(-F30))*(1+F28)+F43*F10/(1-(1+F10)^(-F31))*(1+F28)+F44*F10/(1-(1+F10)^(-F32))*(1+F28)+F40*F10 -> 1.5018716 | G54: =SUMPRODUCT($C$6:$F$6,C54:F54) -> 1.5018716 | H54: DC_Cost!第54列
A55: 其中建物（含預備費） | B55: $B | C55: =C41*C10/(1-(1+C10)^(-C29))*(1+C28) -> 0.43916809 | D55: =D41*D10/(1-(1+D10)^(-D29))*(1+D28) -> 0.43916809 | E55: =E41*E10/(1-(1+E10)^(-E29))*(1+E28) -> 0.43916809 | F55: =F41*F10/(1-(1+F10)^(-F29))*(1+F28) -> 0.43916809 | G55: =SUMPRODUCT($C$6:$F$6,C55:F55) -> 0.43916809
A56: 其中電力設施（含預備費） | B56: $B | C56: =C42*C10/(1-(1+C10)^(-C30))*(1+C28) -> 0.60785356 | D56: =D42*D10/(1-(1+D10)^(-D30))*(1+D28) -> 0.60785356 | E56: =E42*E10/(1-(1+E10)^(-E30))*(1+E28) -> 0.60785356 | F56: =F42*F10/(1-(1+F10)^(-F30))*(1+F28) -> 0.60785356 | G56: =SUMPRODUCT($C$6:$F$6,C56:F56) -> 0.60785356
A57: 其中機械散熱（含預備費） | B57: $B | C57: =C43*C10/(1-(1+C10)^(-C31))*(1+C28) -> 0.37798711 | D57: =D43*D10/(1-(1+D10)^(-D31))*(1+D28) -> 0.37798711 | E57: =E43*E10/(1-(1+E10)^(-E31))*(1+E28) -> 0.37798711 | F57: =F43*F10/(1-(1+F10)^(-F31))*(1+F28) -> 0.37798711 | G57: =SUMPRODUCT($C$6:$F$6,C57:F57) -> 0.37798711
A58: 其中光纖保全（含預備費） | B58: $B | C58: =C44*C10/(1-(1+C10)^(-C32))*(1+C28) -> 0.074862882 | D58: =D44*D10/(1-(1+D10)^(-D32))*(1+D28) -> 0.074862882 | E58: =E44*E10/(1-(1+E10)^(-E32))*(1+E28) -> 0.074862882 | F58: =F44*F10/(1-(1+F10)^(-F32))*(1+F28) -> 0.074862882 | G58: =SUMPRODUCT($C$6:$F$6,C58:F58) -> 0.074862882
A59: 其中土地（機會成本） | B59: $B | C59: =C40*C10 -> 0.002 | D59: =D40*D10 -> 0.002 | E59: =E40*E10 -> 0.002 | F59: =F40*F10 -> 0.002 | G59: =SUMPRODUCT($C$6:$F$6,C59:F59) -> 0.002
A60: 電費 | B60: $B | C60: =C7*1000*C17*C9*8760*C18/1000000000 -> 0.672768 | D60: =D7*1000*D17*D9*8760*D18/1000000000 -> 0.672768 | E60: =E7*1000*E17*E9*8760*E18/1000000000 -> 0.672768 | F60: =F7*1000*F17*F9*8760*F18/1000000000 -> 0.672768 | G60: =SUMPRODUCT($C$6:$F$6,C60:F60) -> 0.672768 | H60: DC_Cost!第43列 | J60: 設施電力＝IT×PUE；平均負載 80%
A61: IT 維護 | B61: $B | C61: =C39*C19 -> 0.43259841 | D61: =D39*D19 -> 0.37763887 | E61: =E39*E19 -> 0.50693069 | F61: =F39*F19 -> 0.59104579 | G61: =SUMPRODUCT($C$6:$F$6,C61:F61) -> 0.41061459 | H61: DC_Cost!第44列
A62: 廠房維護 | B62: $B | C62: =C46*C20 -> 0.2534 | D62: =D46*D20 -> 0.2534 | E62: =E46*E20 -> 0.2534 | F62: =F46*F20 -> 0.2534 | G62: =SUMPRODUCT($C$6:$F$6,C62:F62) -> 0.2534 | H62: DC_Cost!第45列
A63: 站點營運（人員、軟體、水、耗材） | B63: $B | C63: =C21 -> 0.325 | D63: =D21 -> 0.325 | E63: =E21 -> 0.325 | F63: =F21 -> 0.325 | G63: =SUMPRODUCT($C$6:$F$6,C63:F63) -> 0.325 | H63: DC_Cost!第46列
A64: 財產稅與保險 | B64: $B | C64: =C47*C22 -> 0.20090107 | D64: =D47*D22 -> 0.18342587 | E64: =E47*E22 -> 0.22453612 | F64: =F47*F22 -> 0.25128176 | G64: =SUMPRODUCT($C$6:$F$6,C64:F64) -> 0.19391099 | H64: DC_Cost!第47列
A65: 營運費用小計（不含折舊） | B65: $B | C65: =SUM(C60:C64) -> 1.8846675 | D65: =SUM(D60:D64) -> 1.8122327 | E65: =SUM(E60:E64) -> 1.9826348 | F65: =SUM(F60:F64) -> 2.0934955 | G65: =SUMPRODUCT($C$6:$F$6,C65:F65) -> 1.8556936 | H65: DC_Cost!第48列
A66: 年持有成本（經濟口徑）＝IT 年金＋廠房年金＋營運 | B66: $B/GW·年 | C66: =C50+C54+C65 -> 9.7030873 | D66: =D50+D54+D65 -> 8.8281656 | E66: =E50+E54+E65 -> 10.886411 | F66: =F50+F54+F65 -> 12.225471 | G66: =SUMPRODUCT($C$6:$F$6,C66:F66) -> 9.3531186 | H66: DC_Cost!第55列；組合＝Alloc!C157（AL_FleetHold）
A67: 模型值（DC_Cost 第55列；G 欄＝Alloc!C157） | B67: $B/GW·年 | C67: 9.7030873 | D67: 8.8281656 | E67: 10.886411 | F67: 12.225471 | G67: 9.3531186 | H67: DC_Cost!D55,G55,J55,M55；Alloc!C157 | I67: Verified（模型快取值）
A68: 差（本頁公式 − 模型值） | B68: $B | C68: =C66-C67 -> 0 | D68: =D66-D67 -> 0 | E68: =E66-E67 -> -4.4408921e-14 | F68: =F66-F67 -> 0 | G68: =G66-G67 -> 0 | J68: 應為 0（浮點誤差內）
A69: D. 結構占比
A70: IT 資本回收占比 | B70: % | C70: =C50/C66 -> 0.65098334 | D70: =D50/D66 -> 0.62459875 | E70: =E50/E66 -> 0.67992147 | F70: =F50/F66 -> 0.70591177 | G70: =G50/G66 -> 0.64102185
A71: 廠房資本回收占比 | B71: % | C71: =C54/C66 -> 0.15478286 | D71: =D54/D66 -> 0.17012273 | E71: =E54/E66 -> 0.13795838 | F71: =F54/F66 -> 0.12284775 | G71: =G54/G66 -> 0.16057442
A72: 電費占比 | B72: % | C72: =C60/C66 -> 0.069335458 | D72: =D60/D66 -> 0.076206998 | E72: =E60/E66 -> 0.061798879 | F72: =F60/F66 -> 0.055030027 | G72: =G60/G66 -> 0.071929805
A73: 維護（IT＋廠房）占比 | B73: % | C73: =(C61+C62)/C66 -> 0.070698984 | D73: =(D61+D62)/D66 -> 0.071480181 | E73: =(E61+E62)/E66 -> 0.069842182 | F73: =(F61+F62)/F66 -> 0.069072659 | G73: =(G61+G62)/G66 -> 0.070993924
A74: 其他營運（站點＋稅保）占比 | B74: % | C74: =(C63+C64)/C66 -> 0.054199355 | D74: =(D63+D64)/D66 -> 0.057591338 | E74: =(E63+E64)/E66 -> 0.05047909 | F74: =(F63+F64)/F66 -> 0.047137796 | G74: =(G63+G64)/G66 -> 0.055479997
A75: 資本回收合計占比 | B75: % | C75: =(C50+C54)/C66 -> 0.8057662 | D75: =(D50+D54)/D66 -> 0.79472148 | E75: =(E50+E54)/E66 -> 0.81787985 | F75: =(F50+F54)/F66 -> 0.82875952 | G75: =(G50+G54)/G66 -> 0.80159627
A76: 每 GPU 小時持有成本（經濟） | B76: $/GPU-hr | C76: =C66*1000000000/(C35*8760) -> 1.5425965 | D76: =D66*1000000000/(D35*8760) -> 2.008461 | E76: =E66*1000000000/(E35*8760) -> 2.5517876 | F76: =F66*1000000000/(F35*8760) -> 4.7836518 | G76: =G66*1000000000/(G35*8760) -> 1.690652 | J76: 組合欄＝加權成本 ÷ 加權 GPU 數（總成本 ÷ 總 GPU 小時；非 $/hr 直接加權 1.729）
A77: E. 敏感度：同一資本結構下，持有成本隨 WACC 與 IT 年限的變化（營運費用固定；IT 維護率不隨 WACC 重算）
A78: 情境 | C78: Hopper | D78: GB200 | E78: GB300 | F78: VR200 | G78: 組合 0.6/0.4 | I78: WACC | J78: IT 年限
A79: WACC 3.31%（IREN GPU 融資平均成本） | B79: $B/GW·年 | C79: =C39*$I79/(1-(1+$I79)^(-$J79))+C41*$I79/(1-(1+$I79)^(-C29))*(1+C28)+C42*$I79/(1-(1+$I79)^(-C30))*(1+C28)+C43*$I79/(1-(1+$I79)^(-C31))*(1+C28)+C44*$I79/(1-(1+$I79)^(-C32))*(1+C28)+C40*$I79+C65 -> 7.8946479 | D79: =D39*$I79/(1-(1+$I79)^(-$J79))+D41*$I79/(1-(1+$I79)^(-D29))*(1+D28)+D42*$I79/(1-(1+$I79)^(-D30))*(1+D28)+D43*$I79/(1-(1+$I79)^(-D31))*(1+D28)+D44*$I79/(1-(1+$I79)^(-D32))*(1+D28)+D40*$I79+D65 -> 7.1703931 | E79: =E39*$I79/(1-(1+$I79)^(-$J79))+E41*$I79/(1-(1+$I79)^(-E29))*(1+E28)+E42*$I79/(1-(1+$I79)^(-E30))*(1+E28)+E43*$I79/(1-(1+$I79)^(-E31))*(1+E28)+E44*$I79/(1-(1+$I79)^(-E32))*(1+E28)+E40*$I79+E65 -> 8.8741961 | F79: =F39*$I79/(1-(1+$I79)^(-$J79))+F41*$I79/(1-(1+$I79)^(-F29))*(1+F28)+F42*$I79/(1-(1+$I79)^(-F30))*(1+F28)+F43*$I79/(1-(1+$I79)^(-F31))*(1+F28)+F44*$I79/(1-(1+$I79)^(-F32))*(1+F28)+F40*$I79+F65 -> 9.9826619 | G79: =SUMPRODUCT($C$6:$F$6,C79:F79) -> 7.604946 | I79: 0.0331 | J79: 6
A80: WACC 5% | B80: $B/GW·年 | C80: =C39*$I80/(1-(1+$I80)^(-$J80))+C41*$I80/(1-(1+$I80)^(-C29))*(1+C28)+C42*$I80/(1-(1+$I80)^(-C30))*(1+C28)+C43*$I80/(1-(1+$I80)^(-C31))*(1+C28)+C44*$I80/(1-(1+$I80)^(-C32))*(1+C28)+C40*$I80+C65 -> 8.3267847 | D80: =D39*$I80/(1-(1+$I80)^(-$J80))+D41*$I80/(1-(1+$I80)^(-D29))*(1+D28)+D42*$I80/(1-(1+$I80)^(-D30))*(1+D28)+D43*$I80/(1-(1+$I80)^(-D31))*(1+D28)+D44*$I80/(1-(1+$I80)^(-D32))*(1+D28)+D40*$I80+D65 -> 7.565766 | E80: =E39*$I80/(1-(1+$I80)^(-$J80))+E41*$I80/(1-(1+$I80)^(-E29))*(1+E28)+E42*$I80/(1-(1+$I80)^(-E30))*(1+E28)+E43*$I80/(1-(1+$I80)^(-E31))*(1+E28)+E44*$I80/(1-(1+$I80)^(-E32))*(1+E28)+E40*$I80+E65 -> 9.3560556 | F80: =F39*$I80/(1-(1+$I80)^(-$J80))+F41*$I80/(1-(1+$I80)^(-F29))*(1+F28)+F42*$I80/(1-(1+$I80)^(-F30))*(1+F28)+F43*$I80/(1-(1+$I80)^(-F31))*(1+F28)+F44*$I80/(1-(1+$I80)^(-F32))*(1+F28)+F40*$I80+F65 -> 10.520788 | G80: =SUMPRODUCT($C$6:$F$6,C80:F80) -> 8.0223772 | I80: 0.05 | J80: 6
A81: WACC 8%（模型低端） | B81: $B/GW·年 | C81: =C39*$I81/(1-(1+$I81)^(-$J81))+C41*$I81/(1-(1+$I81)^(-C29))*(1+C28)+C42*$I81/(1-(1+$I81)^(-C30))*(1+C28)+C43*$I81/(1-(1+$I81)^(-C31))*(1+C28)+C44*$I81/(1-(1+$I81)^(-C32))*(1+C28)+C40*$I81+C65 -> 9.1364193 | D81: =D39*$I81/(1-(1+$I81)^(-$J81))+D41*$I81/(1-(1+$I81)^(-D29))*(1+D28)+D42*$I81/(1-(1+$I81)^(-D30))*(1+D28)+D43*$I81/(1-(1+$I81)^(-D31))*(1+D28)+D44*$I81/(1-(1+$I81)^(-D32))*(1+D28)+D40*$I81+D65 -> 8.3079536 | E81: =E39*$I81/(1-(1+$I81)^(-$J81))+E41*$I81/(1-(1+$I81)^(-E29))*(1+E28)+E42*$I81/(1-(1+$I81)^(-E30))*(1+E28)+E43*$I81/(1-(1+$I81)^(-E31))*(1+E28)+E44*$I81/(1-(1+$I81)^(-E32))*(1+E28)+E40*$I81+E65 -> 10.256912 | F81: =F39*$I81/(1-(1+$I81)^(-$J81))+F41*$I81/(1-(1+$I81)^(-F29))*(1+F28)+F42*$I81/(1-(1+$I81)^(-F30))*(1+F28)+F43*$I81/(1-(1+$I81)^(-F31))*(1+F28)+F44*$I81/(1-(1+$I81)^(-F32))*(1+F28)+F40*$I81+F65 -> 11.524871 | G81: =SUMPRODUCT($C$6:$F$6,C81:F81) -> 8.805033 | I81: 0.08 | J81: 6
A82: WACC 10%（基準） | B82: $B/GW·年 | C82: =C39*$I82/(1-(1+$I82)^(-$J82))+C41*$I82/(1-(1+$I82)^(-C29))*(1+C28)+C42*$I82/(1-(1+$I82)^(-C30))*(1+C28)+C43*$I82/(1-(1+$I82)^(-C31))*(1+C28)+C44*$I82/(1-(1+$I82)^(-C32))*(1+C28)+C40*$I82+C65 -> 9.7030873 | D82: =D39*$I82/(1-(1+$I82)^(-$J82))+D41*$I82/(1-(1+$I82)^(-D29))*(1+D28)+D42*$I82/(1-(1+$I82)^(-D30))*(1+D28)+D43*$I82/(1-(1+$I82)^(-D31))*(1+D28)+D44*$I82/(1-(1+$I82)^(-D32))*(1+D28)+D40*$I82+D65 -> 8.8281656 | E82: =E39*$I82/(1-(1+$I82)^(-$J82))+E41*$I82/(1-(1+$I82)^(-E29))*(1+E28)+E42*$I82/(1-(1+$I82)^(-E30))*(1+E28)+E43*$I82/(1-(1+$I82)^(-E31))*(1+E28)+E44*$I82/(1-(1+$I82)^(-E32))*(1+E28)+E40*$I82+E65 -> 10.886411 | F82: =F39*$I82/(1-(1+$I82)^(-$J82))+F41*$I82/(1-(1+$I82)^(-F29))*(1+F28)+F42*$I82/(1-(1+$I82)^(-F30))*(1+F28)+F43*$I82/(1-(1+$I82)^(-F31))*(1+F28)+F44*$I82/(1-(1+$I82)^(-F32))*(1+F28)+F40*$I82+F65 -> 12.225471 | G82: =SUMPRODUCT($C$6:$F$6,C82:F82) -> 9.3531186 | I82: 0.1 | J82: 6
A83: WACC 13%（模型高端） | B83: $B/GW·年 | C83: =C39*$I83/(1-(1+$I83)^(-$J83))+C41*$I83/(1-(1+$I83)^(-C29))*(1+C28)+C42*$I83/(1-(1+$I83)^(-C30))*(1+C28)+C43*$I83/(1-(1+$I83)^(-C31))*(1+C28)+C44*$I83/(1-(1+$I83)^(-C32))*(1+C28)+C40*$I83+C65 -> 10.587693 | D83: =D39*$I83/(1-(1+$I83)^(-$J83))+D41*$I83/(1-(1+$I83)^(-D29))*(1+D28)+D42*$I83/(1-(1+$I83)^(-D30))*(1+D28)+D43*$I83/(1-(1+$I83)^(-D31))*(1+D28)+D44*$I83/(1-(1+$I83)^(-D32))*(1+D28)+D40*$I83+D65 -> 9.6409629 | E83: =E39*$I83/(1-(1+$I83)^(-$J83))+E41*$I83/(1-(1+$I83)^(-E29))*(1+E28)+E42*$I83/(1-(1+$I83)^(-E30))*(1+E28)+E43*$I83/(1-(1+$I83)^(-E31))*(1+E28)+E44*$I83/(1-(1+$I83)^(-E32))*(1+E28)+E40*$I83+E65 -> 11.868137 | F83: =F39*$I83/(1-(1+$I83)^(-$J83))+F41*$I83/(1-(1+$I83)^(-F29))*(1+F28)+F42*$I83/(1-(1+$I83)^(-F30))*(1+F28)+F43*$I83/(1-(1+$I83)^(-F31))*(1+F28)+F44*$I83/(1-(1+$I83)^(-F32))*(1+F28)+F40*$I83+F65 -> 13.3171 | G83: =SUMPRODUCT($C$6:$F$6,C83:F83) -> 10.209001 | I83: 0.13 | J83: 6
A84: WACC 10%、IT 年限 5 年（對齊 5 年合約） | B84: $B/GW·年 | C84: =C39*$I84/(1-(1+$I84)^(-$J84))+C41*$I84/(1-(1+$I84)^(-C29))*(1+C28)+C42*$I84/(1-(1+$I84)^(-C30))*(1+C28)+C43*$I84/(1-(1+$I84)^(-C31))*(1+C28)+C44*$I84/(1-(1+$I84)^(-C32))*(1+C28)+C40*$I84+C65 -> 10.643664 | D84: =D39*$I84/(1-(1+$I84)^(-$J84))+D41*$I84/(1-(1+$I84)^(-D29))*(1+D28)+D42*$I84/(1-(1+$I84)^(-D30))*(1+D28)+D43*$I84/(1-(1+$I84)^(-D31))*(1+D28)+D44*$I84/(1-(1+$I84)^(-D32))*(1+D28)+D40*$I84+D65 -> 9.6492468 | E84: =E39*$I84/(1-(1+$I84)^(-$J84))+E41*$I84/(1-(1+$I84)^(-E29))*(1+E28)+E42*$I84/(1-(1+$I84)^(-E30))*(1+E28)+E43*$I84/(1-(1+$I84)^(-E31))*(1+E28)+E44*$I84/(1-(1+$I84)^(-E32))*(1+E28)+E40*$I84+E65 -> 11.988605 | F84: =F39*$I84/(1-(1+$I84)^(-$J84))+F41*$I84/(1-(1+$I84)^(-F29))*(1+F28)+F42*$I84/(1-(1+$I84)^(-F30))*(1+F28)+F43*$I84/(1-(1+$I84)^(-F31))*(1+F28)+F44*$I84/(1-(1+$I84)^(-F32))*(1+F28)+F40*$I84+F65 -> 13.510552 | G84: =SUMPRODUCT($C$6:$F$6,C84:F84) -> 10.245897 | I84: 0.1 | J84: 5
A85: WACC 8%、IT 年限 5 年 | B85: $B/GW·年 | C85: =C39*$I85/(1-(1+$I85)^(-$J85))+C41*$I85/(1-(1+$I85)^(-C29))*(1+C28)+C42*$I85/(1-(1+$I85)^(-C30))*(1+C28)+C43*$I85/(1-(1+$I85)^(-C31))*(1+C28)+C44*$I85/(1-(1+$I85)^(-C32))*(1+C28)+C40*$I85+C65 -> 10.075647 | D85: =D39*$I85/(1-(1+$I85)^(-$J85))+D41*$I85/(1-(1+$I85)^(-D29))*(1+D28)+D42*$I85/(1-(1+$I85)^(-D30))*(1+D28)+D43*$I85/(1-(1+$I85)^(-D31))*(1+D28)+D44*$I85/(1-(1+$I85)^(-D32))*(1+D28)+D40*$I85+D65 -> 9.1278573 | E85: =E39*$I85/(1-(1+$I85)^(-$J85))+E41*$I85/(1-(1+$I85)^(-E29))*(1+E28)+E42*$I85/(1-(1+$I85)^(-E30))*(1+E28)+E43*$I85/(1-(1+$I85)^(-E31))*(1+E28)+E44*$I85/(1-(1+$I85)^(-E32))*(1+E28)+E40*$I85+E65 -> 11.357525 | F85: =F39*$I85/(1-(1+$I85)^(-$J85))+F41*$I85/(1-(1+$I85)^(-F29))*(1+F28)+F42*$I85/(1-(1+$I85)^(-F30))*(1+F28)+F43*$I85/(1-(1+$I85)^(-F31))*(1+F28)+F44*$I85/(1-(1+$I85)^(-F32))*(1+F28)+F40*$I85+F65 -> 12.808109 | G85: =SUMPRODUCT($C$6:$F$6,C85:F85) -> 9.6965314 | I85: 0.08 | J85: 5
A86: WACC 3.31%、IT 年限 5 年 | B86: $B/GW·年 | C86: =C39*$I86/(1-(1+$I86)^(-$J86))+C41*$I86/(1-(1+$I86)^(-C29))*(1+C28)+C42*$I86/(1-(1+$I86)^(-C30))*(1+C28)+C43*$I86/(1-(1+$I86)^(-C31))*(1+C28)+C44*$I86/(1-(1+$I86)^(-C32))*(1+C28)+C40*$I86+C65 -> 8.8242821 | D86: =D39*$I86/(1-(1+$I86)^(-$J86))+D41*$I86/(1-(1+$I86)^(-D29))*(1+D28)+D42*$I86/(1-(1+$I86)^(-D30))*(1+D28)+D43*$I86/(1-(1+$I86)^(-D31))*(1+D28)+D44*$I86/(1-(1+$I86)^(-D32))*(1+D28)+D40*$I86+D65 -> 7.9819217 | E86: =E39*$I86/(1-(1+$I86)^(-$J86))+E41*$I86/(1-(1+$I86)^(-E29))*(1+E28)+E42*$I86/(1-(1+$I86)^(-E30))*(1+E28)+E43*$I86/(1-(1+$I86)^(-E31))*(1+E28)+E44*$I86/(1-(1+$I86)^(-E32))*(1+E28)+E40*$I86+E65 -> 9.963567 | F86: =F39*$I86/(1-(1+$I86)^(-$J86))+F41*$I86/(1-(1+$I86)^(-F29))*(1+F28)+F42*$I86/(1-(1+$I86)^(-F30))*(1+F28)+F43*$I86/(1-(1+$I86)^(-F31))*(1+F28)+F44*$I86/(1-(1+$I86)^(-F32))*(1+F28)+F40*$I86+F65 -> 11.252792 | G86: =SUMPRODUCT($C$6:$F$6,C86:F86) -> 8.4873379 | I86: 0.0331 | J86: 5

Sheet 外部價格換算
A1: 外部價格 → 每 IT-GW·年（$B）換算，及其包含／不包含的項目
A2: 藍字＝外部證據輸入（出處見「證據」頁 ID）；黑字＝公式。倍數＝外部價 ÷ TK 同口徑持有成本（分母指定於「對照 TK」欄）。
A4: ID | B4: 項目 | C4: 總額／數值 | D4: 單位 | E4: 年數／係數 | F4: 容量（GW） | G4: 容量口徑 | H4: → 每年 $B | I4: → 每 IT-GW·年 $B（點估） | J4: 低 | K4: 高 | L4: 對照 TK 項 | M4: TK 值 | N4: 倍數（點估） | O4: 倍數 低 | P4: 倍數 高 | Q4: 電費 | R4: 廠房 | S4: 網路／儲存 | T4: 維運 | U4: 出租方利潤／毛利 | V4: 利用率／付款假設 | W4: GPU 世代 | X4: 標記 | Y4: 品質與限制 | Z4: 證據 ID
A5: A. 合約／財報營收型（已是每年金額，除以容量）
A6: X1 | B6: IREN–Microsoft（2025-11-03；GB300；5 年） | C6: 9.7 | D6: $B 合約總額 | E6: 5 | F6: 0.2 | G6: IT（約 200MW critical IT load） | H6: =C6/E6 -> 1.94 | I6: =H6/F6 -> 9.7 | J6: =I6 -> 9.7 | K6: =I6 -> 9.7 | L6: GB300（E 欄） | M6: ='TK 拆解'!E66 -> 10.886411 | N6: =I6/M6 -> 0.89101909 | O6: =J6/M6 -> 0.89101909 | P6: =K6/M6 -> 0.89101909 | Q6: 含：EBITDA 85% 定義為扣除電力、維修與直接營運成本，故電費由 IREN 負擔（公司估計） | R6: 含：IREN 自建 Childress Horizon 1–4（含電力、冷卻） | S6: 含：GPU 與輔助設備（Dell 約 $5.8B） | T6: 含 | U6: 含；公司估計專案 EBITDA 85%（資本前）；20% 預付款於第 3–5 年抵扣（現金時點，非降價） | V6: 5 年固定期限；Microsoft 可因延遲交付終止；未披露保證利用率 | W6: GB300 | X6: Verified（公司 8-K／新聞稿）；利害關係：賣方 | Y6: 高：IT 口徑明確、單一原始來源（各媒體轉述同一份公告）。5 年合約短於 GPU 經濟壽命，殘值歸出租方。 | Z6: E1–E3
A7: X2a | B7: CoreWeave 2025Q4 營收年化 ÷ 平均 active power（照字面當 IT） | C7: 1.572 | D7: $B 季營收 | E7: 4 | F7: =(590+850)/2/1000 -> 0.72 | G7: 不明（active power 定義未找到）；590 為由「+260 → >850」反推 | H7: =C7*E7 -> 6.288 | I7: =H7/F7 -> 8.7333333 | J7: =I7 -> 8.7333333 | K7: =I7 -> 8.7333333 | L7: 2025 組合 0.6/0.4（G 欄） | M7: ='TK 拆解'!G66 -> 9.3531186 | N7: =I7/M7 -> 0.93373491 | O7: =J7/M7 -> 0.93373491 | P7: =K7/M7 -> 0.93373491 | Q7: 含 | R7: 含（CoreWeave 自租／自建混合，租賃費用在其成本內） | S7: 含 | T7: 含 | U7: 含；Q4 調整後營業利益率 6%、GAAP 營業虧損 $89M | V7: 包含新容量爬坡期（電已通但尚未計費）→ 營收偏低；承諾使用量不明 | W7: Hopper 為主＋GB200 爬坡（推測，未揭露） | X7: Verified（營收、MW 為公司揭露）；平均 MW 為 Derived | Y7: 中低：全公司彙總、混合世代、MW 為期初期末平均 | Z7: E4–E5
A8: X2b | B8: 同上，若 active power 為設施口徑，換成 IT（÷PUE 1.2） | C8: 1.572 | D8: $B 季營收 | E8: 4 | F8: =(590+850)/2/1000/'TK 拆解'!C9 -> 0.6 | G8: IT（由設施換算；假設） | H8: =C8*E8 -> 6.288 | I8: =H8/F8 -> 10.48 | J8: =I8 -> 10.48 | K8: =I8 -> 10.48 | L8: 2025 組合 0.6/0.4（G 欄） | M8: ='TK 拆解'!G66 -> 9.3531186 | N8: =I8/M8 -> 1.1204819 | O8: =J8/M8 -> 1.1204819 | P8: =K8/M8 -> 1.1204819 | Q8: 同 X2a | R8: 同 X2a | S8: 同 X2a | T8: 同 X2a | U8: 同 X2a | V8: 同 X2a | W8: 同 X2a | X8: Derived（口徑假設 Assumed） | Y8: 中低：僅用於區間上端 | Z8: E4–E5
A9: X3 | B9: Nebius–Microsoft（2025-09；5 年；基本 $17.4B，含選擇權 $19.4B）— 下界 | C9: 17.4 | D9: $B 合約總額 | E9: 5 | F9: 0.3 | G9: 未明（Vineland 目標 300MW，單一來源 GCN） | H9: =C9/E9 -> 3.48 | I9: =H9/F9 -> 11.6 | J9: =I9 -> 11.6 | K9: =I9*19.4/17.4 -> 12.933333 | L9: GB300（E 欄；世代未揭露） | M9: ='TK 拆解'!E66 -> 10.886411 | N9: =I9/M9 -> 1.0655486 | O9: =J9/M9 -> 1.0655486 | P9: =K9/M9 -> 1.1880255 | Q9: 不明 | R9: 不明 | S9: 不明（專屬 GPU 容量） | T9: 不明 | U9: 不明 | V9: 分階段 2025–2026 上線，分子含未上線期間 | W9: 未揭露 | X9: Interested-party（Nebius 公告／媒體） | Y9: 只是下界：合約容量 ≤ 300MW 且未計爬坡；300MW 只見單一來源。不進分布。 | Z9: E6
A10: X4a | B10: Nebius 2026Q2 新簽四筆合約收益率（營收認列基礎） | C10: 20 | D10: $M／MW·年 | E10: 1 | F10: 0.001 | G10: 未明（每 MW 未說 IT 或設施） | H10: =C10*E10/1000 -> 0.02 | I10: =H10/F10 -> 20 | J10: =C10 -> 20 | K10: =25 -> 25 | L10: GB300（E 欄） | M10: ='TK 拆解'!E66 -> 10.886411 | N10: =I10/M10 -> 1.8371528 | O10: =J10/M10 -> 1.8371528 | P10: =K10/M10 -> 2.2964409 | Q10: 不明 | R10: 不明 | S10: 不明（全含雲服務） | T10: 不明 | U10: 不明；客戶為 Reflection、Cohere 等非 hyperscaler，信用風險溢價 | V10: 預付款涵蓋 capex 50–60%（不計入營收認列） | W10: 未揭露（2026 簽） | X10: Interested-party（管理層電話會議；二手轉述） | Y10: 不可直接比：2026 年定價、非投資級客戶、含預付款融資。顯示 2026 年定價已高於 2025 年合約。 | Z10: E7
A11: X4b | B11: Nebius 短期（≤6 個月）議價中的收益率 | C11: 40 | D11: $M／MW·年 | E11: 1 | F11: 0.001 | G11: 未明 | H11: =C11*E11/1000 -> 0.04 | I11: =H11/F11 -> 40 | J11: =C11 -> 40 | K11: =50 -> 50 | L11: GB300（E 欄） | M11: ='TK 拆解'!E66 -> 10.886411 | N11: =I11/M11 -> 3.6743055 | O11: =J11/M11 -> 3.6743055 | P11: =K11/M11 -> 4.5928819 | Q11: 不明 | R11: 不明 | S11: 不明 | T11: 不明 | U11: 不明 | V11: 短約，非 take-or-pay 長約 | W11: 未揭露 | X11: Interested-party（管理層；「議價中」非已簽） | Y11: 僅作現貨端參考；非合約價。 | Z11: E7
A12: X5a | B12: Oracle–OpenAI（WSJ 轉述：約 $300B／5 年，4.5GW，2027 起）— 4.5GW 當設施口徑，換 IT | C12: 300 | D12: $B 合約總額 | E12: 5 | F12: =4.5/'TK 拆解'!C9 -> 3.75 | G12: 設施 4.5GW ÷ PUE 1.2 ＝ IT | H12: =C12/E12 -> 60 | I12: =H12/F12 -> 16 | J12: =C12/E12/4.5 -> 13.333333 | K12: =I12 -> 16 | L12: VR200（F 欄；2027 起交付世代，Assumed） | M12: ='TK 拆解'!F66 -> 12.225471 | N12: =I12/M12 -> 1.308743 | O12: =J12/M12 -> 1.0906192 | P12: =K12/M12 -> 1.308743 | Q12: 含（Oracle 轉租整套設施） | R12: 含 | S12: 含 | T12: 含 | U12: 含；Oracle AI 雲毛利「極薄」（2020 年代報導 ≈ 16%，單一轉述，見 20261020 筆記） | V12: 合約總額含爬坡與選擇權不明；非 SEC 具約束揭露 | W12: 2027 起；世代未揭露 | X12: Interested-party（匿名消息；Oracle 未逐項確認） | Y12: 低：口徑（IT／設施）與爬坡未明；$60B／年是除法，非揭露數字。 | Z12: E8
A13: X5b | B13: 同上，4.5GW 當 IT 口徑 | C13: 300 | D13: $B 合約總額 | E13: 5 | F13: 4.5 | G13: IT | H13: =C13/E13 -> 60 | I13: =H13/F13 -> 13.333333 | J13: =I13 -> 13.333333 | K13: =I13 -> 13.333333 | L13: VR200（F 欄） | M13: ='TK 拆解'!F66 -> 12.225471 | N13: =I13/M13 -> 1.0906192 | O13: =J13/M13 -> 1.0906192 | P13: =K13/M13 -> 1.0906192 | Q13: 同 X5a | R13: 同 X5a | S13: 同 X5a | T13: 同 X5a | U13: 同 X5a | V13: 同 X5a | W13: 同 X5a | X13: Interested-party | Y13: 低 | Z13: E8
A14: X5c | B14: Oracle–OpenAI 早期報導：年約 $30B／4.5GW（與 X5a 的 $60B／年互相矛盾，未解） | C14: 30 | D14: $B／年 | E14: 1 | F14: =4.5/'TK 拆解'!C9 -> 3.75 | G14: 設施 ÷ PUE ＝ IT | H14: =C14/E14 -> 30 | I14: =H14/F14 -> 8 | J14: =C14/4.5 -> 6.6666667 | K14: =H14/F14 -> 8 | L14: VR200（F 欄；與規格一致，世代實際未揭露） | M14: ='TK 拆解'!F66 -> 12.225471 | N14: =I14/M14 -> 0.65437152 | O14: =J14/M14 -> 0.5453096 | P14: =K14/M14 -> 0.65437152 | Q14: 含 | R14: 含 | S14: 含 | T14: 含 | U14: 含 | V14: 同 X5a | W14: GB200 為主（推測） | X14: Interested-party（匿名消息） | Y14: 低：與 X5a 差一倍，哪個為真未知；列出僅為完整。 | Z14: E8
A15: B. 支出 ÷ 機隊 GW 型（不是價格）
A16: X6a | B16: OpenAI 2025 雲端算力支出 $16.3B ÷ 1.25GW（分子取 Epoch 方法頁 16.3（Andy 記錄的約值 16.0 為 12.8／1.37，見 B 段頁第2節）；1.25GW＝(0.6+1.9)/2 線性內插，見證據 E20） | C16: 16.3 | D16: $B／年（研究＋訓練＋推論） | E16: 1 | F16: 1.25 | G16: 未明（Epoch 資料集口徑未確認） | H16: =C16/E16 -> 16.3 | I16: =H16/F16 -> 13.04 | J16: =H16/1.5 -> 10.866667 | K16: =H16/1 -> 16.3 | L16: 2025 組合 0.6/0.4（G 欄） | M16: ='TK 拆解'!G66 -> 9.3531186 | N16: =I16/M16 -> 1.3941874 | O16: =J16/M16 -> 1.1618228 | P16: =K16/M16 -> 1.7427342 | Q16: 視供應商 | R16: 視供應商 | S16: 視供應商 | T16: 視供應商 | U16: 視供應商；含 Microsoft 授予的非現金 Azure 額度（The Register 提醒） | V16: 支出不等於已用容量；含預留與預付 | W16: Hopper＋GB200 | X16: Interested-party（二手；OpenAI 內部文件轉述） | Y16: 低：這是「花多少」÷「平均多少 GW」，不是單價；分母與分子時間窗不一定一致。低／高欄為分母 1.5／1.0GW 的敏感度（Assumed）。 | Z16: E9
A17: X6b | B17: 同上，分母改用模型 AL_FleetGW25（2025 平均上線 GW，指數內插 0.6→1.9） | C17: 16.3 | D17: $B／年 | E17: 1 | F17: 1.127807 | G17: 模型 Cap_In!C331（Derived） | H17: =C17/E17 -> 16.3 | I17: =H17/F17 -> 14.452828 | J17: =I17 -> 14.452828 | K17: =I17 -> 14.452828 | L17: 2025 組合 0.6/0.4（G 欄） | M17: ='TK 拆解'!G66 -> 9.3531186 | N17: =I17/M17 -> 1.5452416 | O17: =J17/M17 -> 1.5452416 | P17: =K17/M17 -> 1.5452416 | Q17: 同 X6a | R17: 同 X6a | S17: 同 X6a | T17: 同 X6a | U17: 同 X6a | V17: 同 X6a | W17: 同 X6a | X17: Derived | Y17: 低：與 X6a 同。 | Z17: E9
A18: X6c | B18: （對照，不是價格）Epoch Abilene 資本成本 $15.9B ÷ 421MW IT → $M／MW IT | C18: 15.9 | D18: $B 資本成本（Epoch 估計） | E18: 1 | F18: 0.421 | G18: IT（Epoch 頁面未精確定義 IT power） | H18: =C18/E18 -> 15.9 | I18: =H18/F18 -> 37.767221 | J18: =I18 -> 37.767221 | K18: =I18 -> 37.767221 | L18: TK GB200 每 MW IT 總 capex（D 欄，$M） | M18: ='TK 拆解'!D48 -> 36.685174 | N18: =I18/M18 -> 1.0294955 | O18: =J18/M18 -> 1.0294955 | P18: =K18/M18 -> 1.0294955 | Q18: — | R18: 含（Epoch 資本成本口徑未詳） | S18: 含 | T18: — | U18: — | V18: — | W18: B200／GB200（Epoch 估計） | X18: Derived／Analogy（衛星影像＋冷卻模型的估計） | Y18: 此列單位是 $M／MW 的 capex，不是年價；用來檢查 TK 資本支出，不進價格倍數。⚠ 與 X6a 的 $16B 是兩個不同的量。 | Z18: E10
A19: C. GPU 小時價 → 每 IT-GW·年（價格 × TK 每 GW GPU 數 × 8760 ×利用率）
A20: X7a | B20: H100：Silicon Data 新雲指數 2026-10-22 | C20: 2.53 | D20: $/GPU-hr | E20: 8760 | F20: ='TK 拆解'!C35/1000000000 -> 0.000718048 | G20: TK 每 IT-GW GPU 數（見 TK 拆解第35列） | H20: =C20*E20*F20 -> 15.913954 | I20: =H20*1 -> 15.913954 | J20: =H20*0.7 -> 11.139768 | K20: =H20*1 -> 15.913954 | L20: Hopper（C 欄） | M20: ='TK 拆解'!C66 -> 9.7030873 | N20: =I20/M20 -> 1.6400918 | O20: =J20/M20 -> 1.1480643 | P20: =K20/M20 -> 1.6400918 | Q20: 不明（零售／指數價） | R20: 不明（零售／指數價） | S20: 不明（零售／指數價） | T20: 不明（零售／指數價） | U20: 含出租方利潤 | V20: 低／高＝利用率 0.7／1.0（Assumed） | X20: Interested-party（指數商） | Y20: 中：跨供應商標準化現貨型指數，2026 年 10 月；2025 年同期較低（報導 2025-10→2026-03 漲約 40%） | Z20: E11
A21: X7b | B21: H100：Ornn OCPI 成交結算價 2026-10-22 | C21: 3.15 | D21: $/GPU-hr | E21: 8760 | F21: ='TK 拆解'!C35/1000000000 -> 0.000718048 | G21: TK 每 IT-GW GPU 數（見 TK 拆解第35列） | H21: =C21*E21*F21 -> 19.813817 | I21: =H21*1 -> 19.813817 | J21: =H21*0.7 -> 13.869672 | K21: =H21*1 -> 19.813817 | L21: Hopper（C 欄） | M21: ='TK 拆解'!C66 -> 9.7030873 | N21: =I21/M21 -> 2.0420116 | O21: =J21/M21 -> 1.4294081 | P21: =K21/M21 -> 2.0420116 | Q21: 不明（零售／指數價） | R21: 不明（零售／指數價） | S21: 不明（零售／指數價） | T21: 不明（零售／指數價） | U21: 含出租方利潤 | V21: 低／高＝利用率 0.7／1.0（Assumed） | X21: Interested-party（指數商） | Y21: 中：成交價，但單日、短約 | Z21: E11
A22: X7c | B22: H100：CoreWeave 公開牌價 HGX H100 | C22: 6.16 | D22: $/GPU-hr | E22: 8760 | F22: ='TK 拆解'!C35/1000000000 -> 0.000718048 | G22: TK 每 IT-GW GPU 數（見 TK 拆解第35列） | H22: =C22*E22*F22 -> 38.747019 | I22: =H22*1 -> 38.747019 | J22: =H22*0.7 -> 27.122913 | K22: =H22*1 -> 38.747019 | L22: Hopper（C 欄） | M22: ='TK 拆解'!C66 -> 9.7030873 | N22: =I22/M22 -> 3.9932671 | O22: =J22/M22 -> 2.795287 | P22: =K22/M22 -> 3.9932671 | Q22: 不明（零售／指數價） | R22: 不明（零售／指數價） | S22: 不明（零售／指數價） | T22: 不明（零售／指數價） | U22: 含出租方利潤 | V22: 低／高＝利用率 0.7／1.0（Assumed） | X22: Interested-party（賣方牌價） | Y22: 低：牌價；大客戶多簽多年約，不付牌價 | Z22: E12
A23: X7d | B23: H100：Lambda 隨選 | C23: 3.29 | D23: $/GPU-hr | E23: 8760 | F23: ='TK 拆解'!C35/1000000000 -> 0.000718048 | G23: TK 每 IT-GW GPU 數（見 TK 拆解第35列） | H23: =C23*E23*F23 -> 20.694431 | I23: =H23*1 -> 20.694431 | J23: =H23*0.7 -> 14.486101 | K23: =H23*1 -> 20.694431 | L23: Hopper（C 欄） | M23: ='TK 拆解'!C66 -> 9.7030873 | N23: =I23/M23 -> 2.1327676 | O23: =J23/M23 -> 1.4929373 | P23: =K23/M23 -> 2.1327676 | Q23: 不明（零售／指數價） | R23: 不明（零售／指數價） | S23: 不明（零售／指數價） | T23: 不明（零售／指數價） | U23: 含出租方利潤 | V23: 低／高＝利用率 0.7／1.0（Assumed） | X23: Interested-party（賣方牌價） | Y23: 低：牌價（另一來源 $3.99） | Z23: E12
A24: X7e | B24: GB200 NVL72：CoreWeave 牌價 $42/4 GPU | C24: 10.5 | D24: $/GPU-hr | E24: 8760 | F24: ='TK 拆解'!D35/1000000000 -> 0.000501768 | G24: TK 每 IT-GW GPU 數（見 TK 拆解第35列） | H24: =C24*E24*F24 -> 46.152621 | I24: =H24*1 -> 46.152621 | J24: =H24*0.7 -> 32.306834 | K24: =H24*1 -> 46.152621 | L24: GB200（D 欄） | M24: ='TK 拆解'!D66 -> 8.8281656 | N24: =I24/M24 -> 5.2278834 | O24: =J24/M24 -> 3.6595184 | P24: =K24/M24 -> 5.2278834 | Q24: 不明（零售／指數價） | R24: 不明（零售／指數價） | S24: 不明（零售／指數價） | T24: 不明（零售／指數價） | U24: 含出租方利潤 | V24: 低／高＝利用率 0.7／1.0（Assumed） | X24: Interested-party（賣方牌價） | Y24: 低：牌價 | Z24: E12
A25: X7f | B25: GB200：Bitdeer 3 年預留（彙整站列價） | C25: 5 | D25: $/GPU-hr | E25: 8760 | F25: ='TK 拆解'!D35/1000000000 -> 0.000501768 | G25: TK 每 IT-GW GPU 數（見 TK 拆解第35列） | H25: =C25*E25*F25 -> 21.977438 | I25: =H25*1 -> 21.977438 | J25: =H25*0.7 -> 15.384207 | K25: =H25*1 -> 21.977438 | L25: GB200（D 欄） | M25: ='TK 拆解'!D66 -> 8.8281656 | N25: =I25/M25 -> 2.4894683 | O25: =J25/M25 -> 1.7426278 | P25: =K25/M25 -> 2.4894683 | Q25: 不明（零售／指數價） | R25: 不明（零售／指數價） | S25: 不明（零售／指數價） | T25: 不明（零售／指數價） | U25: 含出租方利潤 | V25: 低／高＝利用率 0.7／1.0（Assumed） | X25: Interested-party（彙整站，未對照原頁） | Y25: 低：單一彙整站列價 | Z25: E13
A26: X7g | B26: GB300：Nscale–Microsoft Narvik 隱含 $6.2B／5 年／52,000 GPU（第三方推算） | C26: =6200000000/5/52000/8760 -> 2.7221637 | D26: $/GPU-hr | E26: 8760 | F26: ='TK 拆解'!E35/1000000000 -> 0.000487008 | G26: TK 每 IT-GW GPU 數（見 TK 拆解第35列） | H26: =C26*E26*F26 -> 11.613268 | I26: =H26*1 -> 11.613268 | J26: =H26*0.7 -> 8.1292874 | K26: =H26*1 -> 11.613268 | L26: GB300（E 欄） | M26: ='TK 拆解'!E66 -> 10.886411 | N26: =I26/M26 -> 1.0667673 | O26: =J26/M26 -> 0.74673714 | P26: =K26/M26 -> 1.0667673 | Q26: 不明；含 Microsoft 長約 | R26: 不明；含 Microsoft 長約 | S26: 不明；含 Microsoft 長約 | T26: 不明；含 Microsoft 長約 | U26: 含出租方利潤 | V26: 低／高＝利用率 0.7／1.0（Assumed） | X26: Derived（CV Research Substack 推算；合約價非原文） | Y26: 低中：單一第二手；用 TK 每 GW GPU 數換算，若 Nscale 實際 kW／GPU 不同則偏 | Z26: E14
A27: X7h | B27: GB300：STN 3 年預留（彙整站列價） | C27: 7.15 | D27: $/GPU-hr | E27: 8760 | F27: ='TK 拆解'!E35/1000000000 -> 0.000487008 | G27: TK 每 IT-GW GPU 數（見 TK 拆解第35列） | H27: =C27*E27*F27 -> 30.503259 | I27: =H27*1 -> 30.503259 | J27: =H27*0.7 -> 21.352281 | K27: =H27*1 -> 30.503259 | L27: GB300（E 欄） | M27: ='TK 拆解'!E66 -> 10.886411 | N27: =I27/M27 -> 2.8019573 | O27: =J27/M27 -> 1.9613701 | P27: =K27/M27 -> 2.8019573 | Q27: 不明（零售／指數價） | R27: 不明（零售／指數價） | S27: 不明（零售／指數價） | T27: 不明（零售／指數價） | U27: 含出租方利潤 | V27: 低／高＝利用率 0.7／1.0（Assumed） | X27: Interested-party（彙整站） | Y27: 低 | Z27: E13
A29: 註：B200／B300 單卡價（Silicon Data 5.93／6.71、Ornn 9.32）未換算，因 TK 世代欄位為 NVL72 機架且 B200 HGX 的每 GW GPU 數不同（缺 B200 HGX 的 kW／機架輸入）。
A30: 註：X7 列的「低／高」＝利用率 0.7／1.0。長約 take-or-pay 以 1.0 為宜；隨選／現貨應打折。
A31: X5d | B31: Oracle–OpenAI（The Register 轉述 WSJ：$300B／5 年／5GW）— 5GW 當 IT 口徑（=Andy 的 12.0） | C31: 300 | D31: $B 合約總額 | E31: 5 | F31: 5 | G31: IT | H31: =C31/E31 -> 60 | I31: =H31/F31 -> 12 | J31: =I31 -> 12 | K31: =I31 -> 12 | L31: VR200（F 欄） | M31: ='TK 拆解'!F66 -> 12.225471 | N31: =I31/M31 -> 0.98155727 | O31: =J31/M31 -> 0.98155727 | P31: =K31/M31 -> 0.98155727 | Q31: 同 X5a | R31: 同 X5a | S31: 同 X5a | T31: 同 X5a | U31: 同 X5a | V31: 同 X5a | W31: 同 X5a | X31: Interested-party | Y31: 低：5GW 版本（The Register 轉述 WSJ，供給側查證.md 第59列）；口徑未明 | Z31: E19
A32: X5e | B32: 同上，5GW 當設施口徑，換 IT（÷PUE） | C32: 300 | D32: $B 合約總額 | E32: 5 | F32: =5/'TK 拆解'!C9 -> 4.1666667 | G32: 設施 5GW ÷ PUE 1.2 ＝ IT | H32: =C32/E32 -> 60 | I32: =H32/F32 -> 14.4 | J32: =C32/E32/5 -> 12 | K32: =I32 -> 14.4 | L32: VR200（F 欄；2027 起交付世代，Assumed） | M32: ='TK 拆解'!F66 -> 12.225471 | N32: =I32/M32 -> 1.1778687 | O32: =J32/M32 -> 0.98155727 | P32: =K32/M32 -> 1.1778687 | Q32: 含（Oracle 轉租整套設施） | R32: 含 | S32: 含 | T32: 含 | U32: 含；Oracle AI 雲毛利「極薄」（2020 年代報導 ≈ 16%，單一轉述，見 20261020 筆記） | V32: 合約總額含爬坡與選擇權不明；非 SEC 具約束揭露 | W32: 2027 起；世代未揭露 | X32: Interested-party（匿名消息；Oracle 未逐項確認） | Y32: 低：5GW 版本（The Register 轉述 WSJ，供給側查證.md 第59列）；口徑未明 | Z32: E19

Sheet 對帳
A1: 對帳：TK 拆解項 × 外部價格
A3: A. 唯一可逐項拆開的外部價格：IREN–Microsoft（GB300）對 TK GB300（$B/GW IT·年）
A4: 項目 | B4: TK GB300 | C4: IREN 隱含 | D4: 差（IREN − TK） | E4: 比（IREN ÷ TK） | F4: IREN 輸入／推導 | G4: 標記 | H4: 說明
A5: IREN 年租金（每 IT-GW） | B5: ='TK 拆解'!E66 -> 10.886411 | C5: =外部價格換算!I6 -> 9.7 | D5: =C5-B5 -> -1.186411 | E5: =C5/B5 -> 0.89101909
A6: IT 設備 capex（$B/GW） | B6: ='TK 拆解'!E39 -> 32.237224 | C6: =5.8/0.2 -> 29 | D6: =C6-B6 -> -3.237224 | E6: =C6/B6 -> 0.89958118 | F6: Dell 約 $5.8B（GPU＋輔助設備）÷ 0.2 GW | G6: Verified（公司公告）
A7: IREN 不含 GPU 的全部 capex（$B/GW；本體 9–11＋叢集部署 3＋加速 2）對 TK 廠房 capex | B7: ='TK 拆解'!E46 -> 12.67 | C7: 15 | D7: =C7-B7 -> 2.33 | E7: =C7/B7 -> 1.183899 | F7: 原文：每 MW 14–16 百萬美元（取 15）＝資料中心本體 9–11＋叢集部署 3＋加速 2；TK 廠房不含叢集部署與網路。like-for-like（對本體 9–11 或 12–14）見「B 段」頁第3節 | G7: Verified（8-K 原文）；Interested-party | H7: B 段更正：此列比值 1.18 是「全包 vs TK 廠房」，不是 like-for-like。對本體 9–11，TK 廠房偏高 15–41%；本體加叢集部署（12–14）則持平。「TK 廠房可能偏低」撤回。
A8: 總 capex（$B/GW） | B8: ='TK 拆解'!E47 -> 44.907224 | C8: =C6+C7 -> 44 | D8: =C8-B8 -> -0.907224 | E8: =C8/B8 -> 0.97979782
A9: 營運費用（不含資本） | B9: ='TK 拆解'!E65 -> 1.9826348 | C9: =(1-0.85)*C5 -> 1.455 | D9: =C9-B9 -> -0.52763481 | E9: =C9/B9 -> 0.73387191 | F9: 營收 ×(1−85%)；85%＝公司估計專案 EBITDA 率（扣電力、維修、直接營運成本，未扣公司管理費與融資） | G9: Interested-party | H9: 是下界：15%×9.70；原文確認扣電費、維修、其他直接營運費，不含企業管理費、財務費用、非現金項目。
A10: 資本回收（租金 − 營運） | B10: ='TK 拆解'!E50+'TK 拆解'!E54 -> 8.9037762 | C10: =C5-C9 -> 8.245 | D10: =C10-B10 -> -0.65877619 | E10: =C10/B10 -> 0.9260116 | F10: IREN 隱含＝租金 − 營運費用 | G10: Derived
A11: 租金差額拆解：營運費用貢獻 | D11: =C9-B9 -> -0.52763481 | E11: =D11/D5 -> 0.44473189 | H11: 負值＝IREN 隱含營運費用低於 TK；占總差額比例見右欄
A12: 租金差額拆解：資本回收貢獻 | D12: =C10-B10 -> -0.65877619 | E12: =D12/D5 -> 0.55526811
A13: 檢查：兩項貢獻合計 − 總差額（應為 0） | D13: =D11+D12-D5 -> 0
A15: B. 資本回收口徑：IREN 的 5 年租金是否足以回收其 capex？（以 IREN 隱含資本回收與總 capex 估算）
A16: 折現率 | B16: 5 年淨租金現值 ($B/GW) | C16: 總 capex ($B/GW) | D16: 5 年末所需殘值／重新出租價值現值之外 ($B，年末價值) | E16: 殘值占總 capex | F16: 說明 | G16: 折現率
A17: 3.31%（IREN GPU 融資平均成本） | B17: =$C$10*(1-(1+G17)^(-5))/G17 -> 37.427775 | C17: =$C$8 -> 44 | D17: =(C17-B17)*(1+G17)^5 -> 7.7343577 | E17: =D17/C17 -> 0.17578086 | F17: 殘值＝第 5 年末資產仍須有的價值（含續約租金或轉售），才能在該折現率下回本。 | G17: 0.0331 | H17: 廠房取 14／16 時（10%）所需殘值 18.9／22.1；（3.31%）6.6／8.9 $B/GW。
A18: 6% | B18: =$C$10*(1-(1+G18)^(-5))/G18 -> 34.730939 | C18: =$C$8 -> 44 | D18: =(C18-B18)*(1+G18)^5 -> 12.404094 | E18: =D18/C18 -> 0.28191123 | G18: 0.06
A19: 8% | B19: =$C$10*(1-(1+G19)^(-5))/G19 -> 32.919894 | C19: =$C$8 -> 44 | D19: =(C19-B19)*(1+G19)^5 -> 16.28031 | E19: =D19/C19 -> 0.37000706 | G19: 0.08
A20: 10%（TK WACC） | B20: =$C$10*(1-(1+G20)^(-5))/G20 -> 31.255037 | C20: =$C$8 -> 44 | D20: =(C20-B20)*(1+G20)^5 -> 20.52589 | E20: =D20/C20 -> 0.46649751 | F20: 修正（B 段第二輪）：先前稱「租金低於 TK 主要是出租方折現率較低」不成立。以 IREN 自己的 capex 與營運下界反推，隱含 WACC 約 9–10%；差額主要來自 IT 設備單價與營運費用（見 B 段頁第6節）。IREN 3.31% 融資只是個案，CoreWeave 債務 9.6–9.9%。 | G20: 0.1
A21: 13% | B21: =$C$10*(1-(1+G21)^(-5))/G21 -> 28.999572 | C21: =$C$8 -> 44 | D21: =(C21-B21)*(1+G21)^5 -> 27.637317 | E21: =D21/C21 -> 0.62812083 | G21: 0.13
A22: 隱含 WACC（使 TK GB300 持有成本＝IREN 租金 9.70；Derived）： | B22: 0.061674015 | C22: 0.023678147 | D22: 0.079052532 | E22: 0.042338 | F22: 依序：IT 6 年＋TK 營運費；IT 5 年＋TK 營運費；IT 6 年＋IREN 隱含營運費；IT 5 年＋IREN 隱含營運費
A23: C. 其他外部價格：能對到哪一項、差額多少、不可分離之處
A24: 外部價格 | B24: 每 IT-GW·年（點估） | C24: TK 對照（同世代） | D24: 差額 $B（外部−TK） | E24: 倍數 | F24: 可歸因到的 TK 拆解項 | G24: 不可分離的部分 | H24: 缺哪個輸入
A25: X2a CoreWeave 2025Q4 彙總 | B25: =外部價格換算!I7 -> 8.7333333 | C25: ='TK 拆解'!G66 -> 9.3531186 | D25: =B25-C25 -> -0.61978526 | E25: =B25/C25 -> 0.93373491 | F25: 無法歸因到單項。可知：CoreWeave 調整後營業利益率 6%（Q4），表示營收約等於含折舊與利息前的成本；但折舊、利息、租賃費沒有在搜尋摘要中。 | G25: 世代組合、active power 是 IT 或設施、爬坡中容量 | H25: CoreWeave 季報 10-Q 的 cost of revenue／折舊／租賃費；active power 定義；分世代營收
A26: X3 Nebius–Microsoft（下界） | B26: =外部價格換算!I9 -> 11.6 | C26: ='TK 拆解'!E66 -> 10.886411 | D26: =B26-C26 -> 0.713589 | E26: =B26/C26 -> 1.0655486 | F26: 只能說 ≥ 此值；若容量全用上，倍數 ≥ 1.07（對 GB300）。 | G26: 容量實際分配、爬坡、世代、MW 口徑 | H26: 合約 MW、各階段上線日、GPU 世代
A27: X4a Nebius 2026Q2 新約（低） | B27: =外部價格換算!I10 -> 20 | C27: ='TK 拆解'!E66 -> 10.886411 | D27: =B27-C27 -> 9.113589 | E27: =B27/C27 -> 1.8371528 | F27: 不可分離：2026 定價、信用溢價、預付融資三者疊加。 | G27: 定價趨勢 vs 客戶信用 vs 預付款 | H27: 每筆合約的 MW 口徑、世代、年期、預付金額
A28: X5a Oracle（設施→IT） | B28: =外部價格換算!I12 -> 16 | C28: ='TK 拆解'!F66 -> 12.225471 | D28: =B28-C28 -> 3.774529 | E28: =B28/C28 -> 1.308743 | F28: 與 VR200 持有成本相比差距小（見倍數）；差額可能來自爬坡平均、選擇權與 Oracle 毛利。 | G28: 爬坡與選擇權、毛利、世代 | H28: 合約逐年 GW 與金額、Oracle 該合約毛利
A29: X5b Oracle（IT 口徑） | B29: =外部價格換算!I13 -> 13.333333 | C29: ='TK 拆解'!F66 -> 12.225471 | D29: =B29-C29 -> 1.1078623 | E29: =B29/C29 -> 1.0906192 | F29: 同上 | G29: 同上 | H29: 同上
A30: X6b 支出 ÷ 平均上線 GW | B30: =外部價格換算!I17 -> 14.452828 | C30: ='TK 拆解'!G66 -> 9.3531186 | D30: =B30-C30 -> 5.0997091 | E30: =B30/C30 -> 1.5452416 | F30: 不可分離：分子為 OpenAI 全部雲端支出（含研究、訓練、預留與非現金額度），分母為模型內插值。 | G30: 訓練／研究／推論用量、額度、預付、機隊 GW 時間序 | H30: OpenAI 付費 GPU-hour 或各供應商實際上線 MW 的月度序列
A31: X7a H100 Silicon Data 現貨型（u=1） | B31: =外部價格換算!I20 -> 15.913954 | C31: ='TK 拆解'!C66 -> 9.7030873 | D31: =B31-C31 -> 6.2108669 | E31: =B31/C31 -> 1.6400918 | F31: 現貨價高於 2025 長約價；TK Hopper 持有成本代表「持有」，不含出租方利潤與稀缺租金。 | G31: 出租方利潤、稀缺租金、2026 與 2025 差 | H31: 2025 年同口徑現貨序列、利用率
A32: X7g Nscale GB300（u=1） | B32: =外部價格換算!I26 -> 11.613268 | C32: ='TK 拆解'!E66 -> 10.886411 | D32: =B32-C32 -> 0.72685669 | E32: =B32/C32 -> 1.0667673 | F32: 隱含 $2.7／GPU-hr，與 IREN 隱含值同量級。 | G32: kW／GPU 與 GPU 數 | H32: Nscale Narvik 實際 MW 與 GPU 數
A34: D. 世代對齊：同一個外部價，分別除以不同 TK 世代（說明「12–12.8 對 9.35」與「0.9 對 10.89」為何方向相反）
A35: 外部價格 | B35: 每 IT-GW·年 | C35: ÷ Hopper | D35: ÷ GB200 | E35: ÷ GB300 | F35: ÷ VR200 | G35: ÷ 2025 組合 0.6/0.4 | H35: 說明
A36: X1 IREN（GB300 實簽） | B36: =外部價格換算!I6 -> 9.7 | C36: =$B36/'TK 拆解'!C66 -> 0.99968182 | D36: =$B36/'TK 拆解'!D66 -> 1.098756 | E36: =$B36/'TK 拆解'!E66 -> 0.89101909 | F36: =$B36/'TK 拆解'!F66 -> 0.79342546 | G36: =$B36/'TK 拆解'!G66 -> 1.0370872 | H36: 對 GB300 0.89；對 2025 組合 1.04（因組合偏 Hopper／GB200，持有成本較低）。
A37: X5a Oracle 設施→IT（2027 起） | B37: =外部價格換算!I12 -> 16 | C37: =$B37/'TK 拆解'!C66 -> 1.6489597 | D37: =$B37/'TK 拆解'!D66 -> 1.8123811 | E37: =$B37/'TK 拆解'!E66 -> 1.4697222 | F37: =$B37/'TK 拆解'!F66 -> 1.308743 | G37: =$B37/'TK 拆解'!G66 -> 1.7106594 | H37: Oracle 2027 起的合約若交付 GB300／VR200 世代，倍數 1.1–1.5；拿 2025 組合 9.35 當分母會被放大到 1.4–1.7。
A38: X5b Oracle IT 口徑 | B38: =外部價格換算!I13 -> 13.333333 | C38: =$B38/'TK 拆解'!C66 -> 1.3741331 | D38: =$B38/'TK 拆解'!D66 -> 1.5103175 | E38: =$B38/'TK 拆解'!E66 -> 1.2247685 | F38: =$B38/'TK 拆解'!F66 -> 1.0906192 | G38: =$B38/'TK 拆解'!G66 -> 1.4255495
A39: X6a 支出 16.3÷1.25GW（16.0 版＝12.8） | B39: =外部價格換算!I16 -> 13.04 | C39: =$B39/'TK 拆解'!C66 -> 1.3439022 | D39: =$B39/'TK 拆解'!D66 -> 1.4770906 | E39: =$B39/'TK 拆解'!E66 -> 1.1978236 | F39: =$B39/'TK 拆解'!F66 -> 1.0666256 | G39: =$B39/'TK 拆解'!G66 -> 1.3941874 | H39: 分母 9.35 是 2025 年舊世代組合；若同一支出對應的是更新世代，倍數降低。
A40: X6b 支出÷模型 GW | B40: =外部價格換算!I17 -> 14.452828 | C40: =$B40/'TK 拆解'!C66 -> 1.4895082 | D40: =$B40/'TK 拆解'!D66 -> 1.6371269 | E40: =$B40/'TK 拆解'!E66 -> 1.3276026 | F40: =$B40/'TK 拆解'!F66 -> 1.1821898 | G40: =$B40/'TK 拆解'!G66 -> 1.5452416
A41: X2a CoreWeave 2025Q4 | B41: =外部價格換算!I7 -> 8.7333333 | C41: =$B41/'TK 拆解'!C66 -> 0.90005718 | D41: =$B41/'TK 拆解'!D66 -> 0.98925799 | E41: =$B41/'TK 拆解'!E66 -> 0.80222337 | F41: =$B41/'TK 拆解'!F66 -> 0.71435557 | G41: =$B41/'TK 拆解'!G66 -> 0.93373491
A43: E. 結論用區間（同口徑＝外部價 ÷ 同世代 TK 持有成本；公式引用上方各列）
A44: 類別 | B44: 低 | C44: 高 | D44: 納入項目 | E44: 是否同口徑 | F44: 說明
A45: 1 已簽長約、已上線資產（2025 年份） | B45: =MIN(外部價格換算!N6,外部價格換算!N7) -> 0.89101909 | C45: =MAX(外部價格換算!N6,外部價格換算!N8,外部價格換算!N26*1) -> 1.1204819 | D45: X1 IREN、X2a／b CoreWeave、X7g Nscale（u=1） | E45: 是（IT GW；世代對齊） | F45: 同口徑長約倍數集中在 0.9–1.1，與 TK 10% WACC 的持有成本大致相符，不支持「市場價 ≈ 1.3 倍 TK」。
A46: 2 遠期大合約（2027 起，世代未揭露）對 VR200 | B46: =MIN(外部價格換算!N12,外部價格換算!N13,外部價格換算!N31,外部價格換算!N32) -> 0.98155727 | C46: =MAX(外部價格換算!N12,外部價格換算!N13,外部價格換算!N31,外部價格換算!N32) -> 1.308743 | D46: X5a／b（4.5GW）、X5d／e（5GW）Oracle | E46: 部分（口徑與世代均為假設）
A47: 3 現貨／短約（2026-10）對 Hopper | B47: =外部價格換算!O20 -> 1.1480643 | C47: =外部價格換算!P21 -> 2.0420116 | D47: X7a、X7b（u 0.7–1.0） | E47: 否（時點、期限不同） | F47: 現貨與 2026 年新約高於長約是時點與稀缺性，不等於 2025 年持有成本偏低。
A48: 4 2026 年新簽（Nebius）對 GB300 | B48: =外部價格換算!N10 -> 1.8371528 | C48: =外部價格換算!P11 -> 4.5928819 | D48: X4a／b | E48: 否（MW 口徑未明）
A49: 5 支出÷GW（非價格） | B49: =MIN(外部價格換算!N17,外部價格換算!N16) -> 1.3941874 | C49: =MAX(外部價格換算!N17,外部價格換算!N16) -> 1.5452416 | D49: X6a／b | E49: 否 | F49: 「12–13」型數字（16.0 版 12.8，倍數 1.37／1.52；16.3 版 13.04，倍數 1.39／1.55）屬第 5 類或第 2 類；它們用 2025 組合 9.35 當分母才顯得高。

Sheet 證據
A1: ID | B1: 項目 | C1: 事實（含原文／數字） | D1: 來源 URL | E1: 日期／存取 | F1: 標記 | G1: 搜尋狀態 | H1: 限制
A2: E1 | B2: IREN–Microsoft 條款 | C2: 總額約 $9.7B、5 年（至 2031）、20% 預付款於各批交付前支付並於第 3–5 年抵扣；GB300 裝於 Childress Horizon 1–4，合計約 200MW IT load，2026 年交付；IREN 向 Dell 購買 GPU 與輔助設備約 $5.8B。 | D2: https://www.sec.gov/Archives/edgar/data/1878848/000114036125040072/ef20058139_8k.htm | E2: 2025-11-03；搜尋摘要（本環境直接抓取被擋） | F2: Verified（公司 8-K／新聞稿）；賣方＝利害關係人 | G2: 已找到（摘要）；原文未直接讀 | H2: sec.gov 與 IR 網站在本環境 ENOTFOUND，只能引用搜尋摘要。GPU 顆數搜尋未找到（「76,000」查無來源）。
A3: E2 | B3: IREN 專案經濟 | C3: 預期年化營收 $1.94B；公司估計專案 EBITDA 率 85%（扣電力、維修、直接營運成本；未扣公司管理費與融資）；資料中心基礎設施約 $14–16M/MW IT（簡報，二手轉述）；GPU 融資：$3.65B 投資級設施（約占 $5.81B GPU capex 的 62.8%）加客戶預付款，合計融資 $5.59B（約 96%），平均成本 3.31%。 | D3: https://iren.gcs-web.com/static-files/a421bb34-0156-4687-be7d-19f53a5236e5 | E3: 2025-11；2026-06 融資新聞 | F3: Interested-party | G3: 已找到（搜尋摘要） | H3: $14–16M 與 $9–11M 兩個數字在摘要中口徑混在一起；以 $14–16M×200MW＝$2.8–3.2B 與第三方估計吻合而採用。｜B 段更正：原文顯示 $14–16M/MW 為「全部 capex（IT 口徑）」＝本體 9–11＋叢集部署 3＋加速 2，不是資料中心本體。
A4: E3 | B4: IREN 交付進度 | C4: Horizon 1（50MW critical IT）已交付 Microsoft，共四個 50MW 於 2026 年交付。 | D4: https://finance.yahoo.com/technology/ai/articles/iren-delivers-first-50mw-microsoft-133130586.html | E4: 2026 | F4: Verified（二手轉述公司公告） | G4: 已找到 | H4: —
A5: E4 | B5: CoreWeave 2025Q4 營收與 active power | C5: Q4 營收 $1,572M（年增 110%）；調整後營業利益 $88M（6%）、GAAP 營業虧損 $89M；Q4 新增約 260MW active power，期末 >850MW；contracted power 約 3.1GW；backlog $66.8B。 | D5: https://www.businesswire.com/news/home/20260226281661/en/CoreWeave-Reports-Strong-Fourth-Quarter-and-Fiscal-Year-2025-Results | E5: 2026-02-26；搜尋摘要 | F5: Verified（公司揭露） | G5: 已找到（摘要） | H5: 期初 590MW 由 850−260 反推（Derived）。cost of revenue、折舊、租賃費未找到。
A6: E5 | B6: CoreWeave active power 定義 | C6: 公司正式定義未找到；第三方描述為「已通電、可跑營收工作負載的資料中心電力容量」，是 IT 或設施未明。State of AI 報告指出 active 與 contracted 重疊、非 GPU 數。 | D6: https://www.stateof.ai/2026-explore/data/compute | E6: 2026 | F6: Analogy／二手 | G6: 已搜尋，未找到（一手定義） | H6: 這決定 X2a／X2b 差 20%。
A7: E6 | B7: Nebius–Microsoft | C7: 基本 $17.4B、5 年（至 2031），選擇權可至約 $19.4B；Vineland NJ，分階段 2025–2026；300MW 僅 GCN 一處提及（引 6-K 為 Nebius 目標）。 | D7: https://www.verdict.co.uk/nebius-agreement-microsoft-gpu-services/ | E7: 2025-09 | F7: Interested-party | G7: 已找到；容量單一來源 | H7: 容量實際分配未揭露，只用於下界。
A8: E7 | B8: Nebius 2026Q2 電話會議 | C8: 四筆新 AI 雲合約平均 >$1B，收益率 $20–25M/MW（營收認列基礎，不含預付款），預付款涵蓋 capex 50–60%；短約（≤6 個月）議價 $40–50M/MW；Q2 營收約 $582M，ARR $3B（6 月底）；2026 capex $20–25B；contracted power 目標 5GW；connected 800MW–1GW。 | D8: https://www.marketbeat.com/instant-alerts/nebius-group-q2-earnings-call-highlights-2026-08-12/ | E8: 2026-08-12 | F8: Interested-party（管理層） | G8: 已找到（二手摘要） | H8: MW 是 IT 還是設施、世代皆未說明。
A9: E8 | B9: Oracle–OpenAI | C9: WSJ（2025-09）：約 $300B／約 5 年、需約 4.5GW、2027 起；$60B／年是除法。較早（2025-07）報導「年約 $30B」。均為匿名消息，Oracle 未逐項確認；Gartner 稱「非鐵板釘釘的第一天數字」。Oracle RPO $664B（2026-08 底）。 | D9: https://www.techmeme.com/250910/p43 | E9: 2025-09；2026 | F9: Interested-party（匿名消息） | G9: 已找到；口徑（IT／設施）未找到 | H9: A 段僅用 4.5GW 版本（13.3；設施換 IT 為 16.0）。B 段補：5GW 版本（E19）12.0＝300÷5÷5（5GW 當設施換 IT 為 14.4）；四種讀法並列於外部價格換算 X5a–X5e 與 B 段頁。
A10: E9 | B10: OpenAI 2025 雲端算力支出 | C10: Epoch 方法頁引用 OpenAI 雲端算力支出 2024 年 $6.8B、2025 年 $16.3B（亦有「>$15B」「$16B」不同說法）；The Information 轉述 2025 推論 $8.4B。 | D10: https://epoch.ai/data/ai-chip-users-documentation/methodology | E10: 2025-10 起 | F10: Interested-party／二手 | G10: 已找到 | H10: 這是「全部雲端支出」，不是 GW 單價；「1.25GW」＝(0.6+1.9)/2 線性內插（見 E20，供給側查證.md 第27–31列）。分子 16.3（方法頁）與約值 16.0 並存，見 B 段頁。
A11: E10 | B11: Epoch Abilene 資本成本 | C11: 現況（2026-07）：IT power 421MW、H100e 509k、資本成本 $15.9B；預計 2026Q4：843MW、$31.9B。估計值，IT power 未精確定義；晶片估為 B200／B300，Oracle 自 2025-06 交付 GB200。 | D11: https://epoch.ai/data/data-centers/satellite-explorer/OpenAIStargateAbilene | E11: 2026-07 | F11: Derived／Analogy（Epoch 估計） | G11: 已找到（原頁讀到） | H11: $15.9B 是資本成本，不是年租；與 X6a 的 $16.3B 是不同的量，兩者數字相近，需防混淆。
A12: E11 | B12: H100 租價指數 | C12: Silicon Data 新雲指數 $2.53／GPU-hr（2026-10-22；另報 2026-10-07 為 $2.81）；Ornn OCPI 成交結算 H100 SXM $3.15、B200 $9.32（2026-10-22）。報導稱 2025-10→2026-03 租價漲約 40%（$1.70→$2.35）。 | D12: https://www.silicondata.com/products/silicon-index/h100 | E12: 2026-10-22 | F12: Interested-party（指數商） | G12: 已找到（搜尋摘要） | H12: SemiAnalysis 價格儀表板未採用（付費牆、且不得為單一來源）。
... A27: E26 | B27: CoreWeave 2026Q2 10-Q 續（chat 端由 Drive PDF 讀取；僅讀前約 80/181 頁） | C27: (1) active power／contracted power 在已讀範圍內未找到定義與數值；租約附註只有站點電力：393MW、355MW（2026–2028 交付）、DCSP 最多 78MW，只寫 electrical power，未標 IT 或 gross。(2) GPU 耐用年限未找到（附註1空白）。PP&E（$M，6/30/26 對 12/31/25）：Technology equipment 33,823／20,903；Data center equipment & leasehold 5,997／2,842；CIP 11,918／9,376；淨額 46,736／30,557；Q2 折舊 $1.4B。(3) 債務 Note 10 有效利率與餘額：見 B 段頁第6節 16 列；原文唯一加權平均：OEM 短期工具 9%。DDTL 4.0 為 SOFR+2.25% 或 Treasury+2.00%，DDTL 5.0 為 SOFR+4.50%。(4) 損益：營收 2,575；營業成本 879（含資料中心租金、電力、電力系統折舊；增加額中租金約 +335、電力約 +87、電力系統折舊約 +79）；技術與基礎設施 1,507（折舊約 1,300）；營業損失 (49)；利息費用淨額 (640)；淨損 (626)。(5) 客戶 A 36%、B 26%、C 10%；98% 營收來自承諾合約；RPO $103.7B（41% 在 24 個月內、39% 在 25–48 個月）；加權平均合約期間未找到；資料中心租約期 5–15 年。 | D27: Drive 02-算力收支/Tokenomics/inbox/（10-Q PDF） | E27: 2026-10-23 | F27: Verified（公司申報）；加權平均為 Derived | G27: 部分（後半未讀到） | H27: 加權平均利率為 chat 端按餘額加權：全部 8.4%、不含可轉債 9.9%、DDTL 9.6%；本檔重算一致

Sheet 待判斷
A1: # | B1: 問題 | C1: 預設（建議） | D1: 替代 | E1: 影響 | F1: 依據 | G1: 決定／B 段狀態
A2: 1 | B2: 「計價倍數」的基準：以 IT 口徑、同世代對比，還是用 2025 機隊組合 9.35 當通用分母？ | C2: 同世代對比（IREN→GB300、Oracle→VR200）；機隊層級才用 9.35 | D2: 一律用 9.35 | E2: 使用 9.35 時，Oracle／支出÷GW 的倍數相對同世代分母虛高約 1.16–1.31 倍（÷GB300 對 ÷組合 1.16；÷VR200 對 ÷組合 1.31；見對帳 D 節） | F2: 對帳 D 節 | G2: 決定（Andy，2026-10-23）：同世代對比；9.35 只用於機隊層級
A3: 2 | B3: TK 的 WACC 10% 是否應下調或分「持有者」？ | C3: 不改模型。TK 以 10% 為基準；出租方資金成本依公司分列：IREN 3.31%（Microsoft 擔保＋預付款，個案）、CoreWeave 債務 9.6–9.9%。先前「出租方 3–8%」只適用 IREN 個案 | D3: WACC 改 8% | E3: TK 拆解敏感度：GB300 在 WACC 8% 約 −0.63；在 3.31% 約 −2.01（見 TK 拆解第79列起，營運費用固定） | F3: TK 拆解 E 節；IREN 融資成本 3.31% | G3: 決定：不改模型；同列 10% 與出租方 3–8%
A4: 3 | B4: IREN 隱含營運費用（≥1.46，下界）低於 TK（1.98）：以誰為準？ | C4: TK 不動；列入待查，要求取得 IREN 或 CoreWeave 的分項營運費 | D4: TK 營運費下調 0.3–0.5 | E4: 影響約 −0.5 $B/GW（約 5%） | F4: 對帳 A 節 | G4: 決定：先不改；B 段原文已取得：IREN 營運下界 1.455 有依據
A5: 4 | B5: 廠房 capex：TK 12.67 $M/MW 相對 IREN 原文如何？（原問題誤以 14–16 為資料中心本體） | C5: 不改。B 段撤回「偏低」：對 IREN 本體 9–11，TK 偏高；加叢集部署 12–14 則持平 | D5: 廠房改為 IREN 值 | E5: 每 +1 $M/MW（＝+1 $B/GW）約 +0.1436 $B/GW·年＝廠房資本回收 1.5019＋廠房維護 0.2534＋財產稅 0.0634（0.5% 總資本）÷ 廠房 capex 12.67（GB300；含土地年金與預備費攤銷）。廠房取 10／13／15 $M/MW（本體中點／含叢集中點／全包）→ −0.38／+0.05／+0.33 | F5: 對帳 A 節 | G5: 決定：先不改；B 段原文：IREN 本體 9–11、含叢集 12–14；TK 12.67 不含叢集部署，結論見 B 段頁第3節（廠房偏低的說法撤回）
A6: 5 | B6: Epoch「160 億 ÷ 1.25GW」是否採用為市場價？ | C6: 保留作機隊層級對照，不當價格；1.25GW 已確認為 (0.6+1.9)/2 線性內插 | D6: 採用並與 IREN 並列 | E6: 若採用，倍數 1.37–1.55（分子 16.0／16.3 × 線性／指數 GW），與同口徑長約相反 | F6: 證據 E9、E10、E17 | G6: 決定：保留作機隊層級對照；算式 160÷1.25，1.25 為內插（E20）
A7: 6 | B7: Oracle 算式：300÷5 年÷5GW＝12.0（Andy）；4.5GW 版本 13.3 | C7: 並列 5GW（IT 12.0／設施 14.4）與 4.5GW（IT 13.3／設施 16.0），標明各自出處；不影響結論：對 VR200 為 0.98–1.31 倍 | D7: 只用單一 GW 版本 | E7: 對 VR200 倍數 0.98–1.31 | F7: 對帳 D 節 | G7: 決定：已有算式 300÷5÷5＝12.0（5GW）；B 段並列 5GW 與 4.5GW
A8: 7 | B8: 2026-10 現貨與 Nebius 新約高於 2025 長約：是否視為「2025 年持有成本偏低」的證據？ | C8: 否：屬 2026 年稀缺租金與期限差異；另取 2025 年同口徑現貨序列再議 | D8: 是 | E8: 若是，TK 持有成本應上調約 1.3–2 倍，與 IREN／CoreWeave 長約矛盾 | F8: 對帳 E 節 | G8: 決定：不作為 2025 年持有成本偏低的證據
A9: 8 | B9: 下一步（B 段）是否取得原始文件（IREN 簡報、CoreWeave 10-Q、Nebius 6-K）？ | C9: 是：以可連線環境取原文，補 cost of revenue／折舊／租賃費、active power 定義 | D9: 維持二手摘要 | E9: 可把「不可分離」項減少至少 3 項 | F9: 證據 E18 | G9: 決定：讀原文；已取得 IREN、CoreWeave 部分、Nebius；CoreWeave 10-Q 全文待 Drive inbox
A10: 9 | B10: Epoch 機隊對照的矛盾（1.37 對 0.89–0.93）要不要進一步拆？ | C10: 維持「不可分離」，並以「每 GPU 小時租金不隨世代變」作為最可能的解釋方向，列 B 段頁第4節 | D10: 要求 OpenAI 雲端帳單分項 | E10: 影響機隊層級 9.35 的使用方式 | F10: B 段頁第2、4節 | G10: 決定（Andy）：維持「不可分離」。補記：OpenAI 揭露支出分項，或揭露對 Azure 的實付價，才能分開。
A11: 10 | B11: CoreWeave 取得 10-Q 全文後，是否用其債務利率與折舊年限回填「出租方折現率」？ | C11: 是（待 inbox） | D11: 維持 3–8% 區間 | E11: 把 WACC 差異從假設變成實值 | F11: B 段頁第5節 | G11: 決定（Andy）：要；只寫進查證檔，不改模型（Tokenomics 維持 10%）。
A12: 11 | B12: IREN 叢集部署 3 $M/MW 是否已在 5.8B 內？ | C12: 原文未明，A/B 兩配置並列 | D12: 向 IREN 簡報原頁確認 | E12: 不影響總 capex；影響 IT／廠房側拆分 | F12: B 段頁第3節 | G12: 決定（Andy）：A／B 兩種配置並列即可，不再追；影響 GB300 持有成本 −0.38 至 +0.33（約 ±3%），不改結論。
A13: 12 | B13: 是否把 Project 決定第 2 題的「出租方折現率 3–8%」改為依公司分列？ | C13: 是：IREN 3.31%（個案）、CoreWeave 債務 9.6–9.9%；README 已據此撤回「WACC 是主因」 | D13: 維持 3–8% 區間 | E13: 「WACC 主因」結論被推翻：以 IREN 自己的 capex 與營運反推，隱含 WACC 約 9–10%；差額主因為 IT 設備單價與營運費用 | F13: B 段頁第6節；證據 E26
A14: 13 | B14: TK GB300 的 IT 設備（32.2 $B/GW）比 IREN（29.0）高 11%，且營運費用高 36%：要查嗎？ | C14: 先不改模型；列為待查（機架單價 $4.3M、GPU 密度 kW／GPU、Dell 大單折扣、營運範圍定義） | D14: TK 下調 | E14: 兩項合計約 1.27 $B/GW（約 12%） | F14: B 段頁第6節

Sheet B 段
A1: B 段補充：Oracle 並列、Epoch 12.8 矛盾評估、IREN 原文對帳、每 GPU 小時視角、CoreWeave／Nebius 財報結構
A2: 藍字＝外部輸入（出處見「證據」頁 E19 以後）；黑字＝公式。TK 值一律引用「TK 拆解」頁。
A5: 1. Oracle–OpenAI：5 GW 與 4.5 GW 並列（$300B／5 年；匿名消息，Interested-party）
A6: 版本 | B6: 總額 $B | C6: 年數 | D6: GW | E6: GW 口徑假設 | F6: 每年 $B | G6: 每 IT-GW·年 $B | H6: 倍數 ÷VR200 | I6: 倍數 ÷GB300 | J6: 倍數 ÷組合 9.35 | K6: 出處
A7: 5GW 當 IT（Andy 的 12.0） | B7: 300 | C7: 5 | D7: 5 | E7: IT | F7: =B7/C7 -> 60 | G7: =F7/D7 -> 12 | H7: =G7/'TK 拆解'!F66 -> 0.98155727 | I7: =G7/'TK 拆解'!E66 -> 1.1022917 | J7: =G7/'TK 拆解'!G66 -> 1.2829945 | K7: The Register 2025-09-11 轉述 WSJ："$300 billion ... five gigawatts ... over the course of five years ... begin in 2027"；repo docs/evidence/20261021_token帳閉合A段/供給側查證.md 第59列
A8: 5GW 當設施，換 IT | B8: 300 | C8: 5 | D8: 5 | E8: 設施 | F8: =B8/C8 -> 60 | G8: =F8/(D8/'TK 拆解'!C9) -> 14.4 | H8: =G8/'TK 拆解'!F66 -> 1.1778687 | I8: =G8/'TK 拆解'!E66 -> 1.32275 | J8: =G8/'TK 拆解'!G66 -> 1.5395934 | K8: 同上
A9: 4.5GW 當 IT | B9: 300 | C9: 5 | D9: 4.5 | E9: IT | F9: =B9/C9 -> 60 | G9: =F9/D9 -> 13.333333 | H9: =G9/'TK 拆解'!F66 -> 1.0906192 | I9: =G9/'TK 拆解'!E66 -> 1.2247685 | J9: =G9/'TK 拆解'!G66 -> 1.4255495 | K9: A 段所用報導（WSJ 經 Techmeme 2025-09-10 摘要："requiring 4.5 gigawatts"）；https://www.techmeme.com/250910/p43
A10: 4.5GW 當設施，換 IT | B10: 300 | C10: 5 | D10: 4.5 | E10: 設施 | F10: =B10/C10 -> 60 | G10: =F10/(D10/'TK 拆解'!C9) -> 16 | H10: =G10/'TK 拆解'!F66 -> 1.308743 | I10: =G10/'TK 拆解'!E66 -> 1.4697222 | J10: =G10/'TK 拆解'!G66 -> 1.7106594 | K10: 同上
A11: 兩份報導的 GW 數不同（5 對 4.5）且 IT／設施口徑均未明：每 IT-GW·年介於 12.0–16.0，對 VR200 倍數 0.98–1.31。A 段「複算不出 12.0」是因我只用了 4.5GW 的報導；Andy 的 12.0＝5GW 當 IT。
A13: 2. Epoch／OpenAI 2025 雲端支出 ÷ GW（機隊層級對照；保留，不當單價）
A14: 項目 | B14: 16.3（Epoch 方法頁，原文值） | C14: 16.0（10-21 筆記約值；Andy 記錄 12.8／1.37／1.52） | D14: 單位 | E14: 標記／來源
A15: 雲端算力支出 2025 | B15: 16.3 | C15: 16 | D15: $B | E15: Interested-party；二手。兩個分子並列，全檔以 16.3 為主、16.0 對照 Andy 的記錄
A16: 上線 GW 2024 年底 | B16: 0.6 | D16: GW | E16: 官方（OpenAI 財務長揭露，供給側查證.md 第27–31列）
A17: 上線 GW 2025 年底 | B17: 1.9 | D17: GW | E17: 同上
A18: 全年平均 GW：線性內插 | B18: =(B16+B17)/2 -> 1.25 | D18: GW | E18: Derived（=1.25＝(0.6+1.9)/2）
A19: 全年平均 GW：指數內插 | B19: =(B17-B16)/LN(B17/B16) -> 1.127807 | D19: GW | E19: Derived（=1.13）
A20: 每 GW·年：線性（$B） | B20: =B15/B18 -> 13.04 | C20: =C15/B18 -> 12.8 | D20: $B/GW·年 | E20: Derived（16.0 版＝12.8）
A21: 每 GW·年：指數（$B） | B21: =B15/B19 -> 14.452828 | C21: =C15/B19 -> 14.186825 | D21: $B/GW·年 | E21: Derived（16.0 版＝14.19）
A22: 倍數 ÷ 2025 組合 9.35：線性 | B22: =B20/'TK 拆解'!G66 -> 1.3941874 | C22: =C20/'TK 拆解'!G66 -> 1.3685275 | D22: x | E22: 16.3：1.39；16.0：1.37
A23: 倍數 ÷ 2025 組合 9.35：指數 | B23: =B21/'TK 拆解'!G66 -> 1.5452416 | C23: =C21/'TK 拆解'!G66 -> 1.5168015 | D23: x | E23: 16.3：1.55；16.0：1.52
A24: 若要把倍數拉回 0.93，分子須為多少（「必須為真」是反推，不是證據）
A25: 反推項目 | B25: 16.3 版 | C25: 16.0 版 | D25: 單位 | E25: 說明
A26: 分子須為（線性 GW） | B26: =0.93*'TK 拆解'!G66*B18 -> 10.873 | C26: =0.93*'TK 拆解'!G66*B18 -> 10.873 | D26: $B | E26: 同一個數，與分子版本無關
A27: 須排除的支出（線性 GW） | B27: =B15-B26 -> 5.4269996 | C27: =C15-C26 -> 5.1269996 | D27: $B | E27: 不是 GPU 容量租金的部分
A28: 占全年支出 | B28: =B27/B15 -> 0.33294476 | C28: =C27/C15 -> 0.32043748 | D28: %
A29: 分子須為（指數 GW 1.13） | B29: =0.93*'TK 拆解'!G66*B19 -> 9.8101166 | C29: =0.93*'TK 拆解'!G66*B19 -> 9.8101166 | D29: $B
A30: 須排除的支出（指數 GW） | B30: =B15-B29 -> 6.4898834 | C30: =C15-C29 -> 6.1898834 | D30: $B | E30: 16.0 版＝6.19
A31: 占全年支出 | B31: =B30/B15 -> 0.39815236 | C31: =C30/C15 -> 0.38686771 | D31: %
A32: 與長約 0.89–0.93 矛盾的可能原因逐項評估
A33: 可能原因 | B33: 方向 | C33: 量級 | D33: 評估 | E33: 證據狀態 | F33: 能解決它的輸入
A34: (a) 非 GPU 雲端服務與研究實驗（儲存、CPU、網路出口、推論以外的雲端帳單） | B34: 降低倍數 | C34: 須排除約 $5.1–6.5B（占 32–40%，見上表） | D34: 合理但無數字：OpenAI 營業成本 75 億 vs 推論 84 億已顯示口徑不整齊（出處見證據 E25）；若這類占 30–40% 即可解釋 | E34: 搜尋未找到分項 | F34: OpenAI 雲端帳單分項（GPU 時數 vs 其他服務）
A35: (b) 2025 年初 Hopper 舊約 | B35: 提高（Hopper 租金 > TK Hopper 持有成本） | C35: =B20*1000000000/('TK 拆解'!G35*8760) -> 2.3570857 | D35: 隱含每 GPU 小時 ($，16.3 版)；若 2025 Hopper 約定價 $2.0–2.5 即與 13.0 一致；GB300 長約隱含 $2.27，兩者同量級→租金不隨世代上升，TK 持有成本隨世代上升 | E35: Derived | F35: OpenAI 各供應商實付 $/GPU-hr（已搜尋，未找到）
A36: (c) 雲端商加價（Azure 轉售） | B36: 提高 | C36: 倍數 ×(1+加價)：1.0–1.3（Assumed） | D36: IREN 賣給 Microsoft 是批發價；Microsoft 轉給 OpenAI 若加價 20% → 0.89×1.2＝1.07；與 Microsoft–OpenAI 關係（持股、額度）交織 | E36: Assumed | F36: OpenAI 向 Microsoft 的實付價（找不到）
A37: (d) GW 口徑 | B37: 若 1.25 為設施口徑 → IT GW 較小（÷PUE）→ 每 IT-GW 支出較高 → 倍數更高；若為 IT 口徑則維持 | C37: =B15/(B18/'TK 拆解'!C9) -> 15.648 | D37: 設施口徑下每 IT-GW 支出（$B，16.3 版）；不能降低倍數，只會更高 | E37: Derived | F37: OpenAI 財務長 GW 的定義（IT 或設施）
A38: (e) 非現金額度 | B38: 降低現金口徑，但「支出」若含額度則提高 | C38: 無數字 | D38: The Register 提醒 Microsoft 端數字可能含額度 | E38: 二手 | F38: OpenAI 現金支付表
A39: (f) 時間窗與預付 | B39: 分子含預留未上線容量→提高 | C39: 無數字 | D39: 分母用年底上線 GW 內插，未含「已付費但未上線」容量 | E39: Assumed | F39: 各供應商合約生效與上線日
A40: 綜合 | D40: (a) 與 (b)(c)(d)(f) 方向相反且量級都能到 ±20–30%；現有資料無法分離 → 列為「不可分離」。補記：OpenAI 揭露支出分項，或揭露對 Azure 的實付價，才能分開。
A42: 3. IREN 原文對帳（sec.gov 8-K 附件 99-1、99-2；chat 端 WebFetch 取得，[Verified]；IREN＝Interested-party）
A43: 項目 | B43: IREN 值 | C43: 單位 | D43: TK 值 | E43: IREN ÷ TK | F43: 說明
A44: GPU 與周邊 capex（含部署服務、伺服器、InfiniBand、線材、軟體授權） | B44: 5.8 | C44: $B | F44: 原文
A45: 容量（critical IT load） | B45: 0.2 | C45: GW IT | F45: 原文
A46: GPU 與周邊 capex 每 IT-GW | B46: =B44/B45 -> 29 | C46: $B/GW | D46: ='TK 拆解'!E39 -> 32.237224 | E46: =B46/D46 -> 0.89958118 | F46: TK GB300 IT 設備（機架＋網路＋儲存）
A47: 資料中心本體 低 | B47: 9 | C47: $M/MW | D47: ='TK 拆解'!E46*1000/'TK 拆解'!E7 -> 12.67 | E47: =B47/D47 -> 0.71033938 | F47: Tier III 同級；TK 廠房 capex 每 MW＝12.67（土地、建物、電力、機械、光纖保全、預備費）
A48: 資料中心本體 高 | B48: 11 | C48: $M/MW | D48: ='TK 拆解'!E46*1000/'TK 拆解'!E7 -> 12.67 | E48: =B48/D48 -> 0.86819258
A49: 100MW 超級叢集架構部署 | B49: 3 | C49: $M/MW | F49: 是否已含在 5.8B 的 GPU 周邊內：原文未明（不可分離）
A50: 2026 年交付 200MW 的加速費用 | B50: 2 | C50: $M/MW | F50: 一次性，非穩態
A51: 每 MW 全部 capex（不含 GPU）：低／高 | B51: =B47+B49+B50 -> 14 | C51: $M/MW | D51: =B48+B49+B50 -> 16 | F51: 低 14、高 16，與原文一致
A52: TK 廠房 capex 是否含網路與叢集部署？—不含。DC_Cost 第25–31列只有土地、建物、電力設施、機械散熱、光纖保全、預備費；網路在第21列（機架價 ×10%）、儲存在第23列，都屬 IT 設備；機架價含機架內冷卻。
A53: 配置方式（資本支出配置有兩種讀法） | B53: IREN IT 側 $B/GW | C53: IREN 廠房側 $B/GW | D53: TK IT | E53: TK 廠房 | F53: IT 比 | G53: 廠房比 | H53: 廠房 capex 若改為 IREN 值，TK GB300 持有成本變化 $B/GW·年
A54: A. 叢集部署歸 IT 側（29.0＋3）；廠房＝本體 10（中點） | B54: =B46+B49 -> 32 | C54: 10 | D54: ='TK 拆解'!E39 -> 32.237224 | E54: ='TK 拆解'!E46 -> 12.67 | F54: =B54/D54 -> 0.9926413 | G54: =C54/E54 -> 0.78926598 | H54: =(C54-E54)*(('TK 拆解'!E54+'TK 拆解'!E62+0.005*'TK 拆解'!E46)/'TK 拆解'!E46) -> -0.38324544
A55: B. 叢集部署歸廠房側（29.0；10＋3） | B55: =B46 -> 29 | C55: 13 | D55: ='TK 拆解'!E39 -> 32.237224 | E55: ='TK 拆解'!E46 -> 12.67 | F55: =B55/D55 -> 0.89958118 | G55: =C55/E55 -> 1.0260458 | H55: =(C55-E55)*(('TK 拆解'!E54+'TK 拆解'!E62+0.005*'TK 拆解'!E46)/'TK 拆解'!E46) -> 0.047367414
A56: C. 全包（A 段用法）：29.0＋15 | B56: =B46 -> 29 | C56: 15 | D56: ='TK 拆解'!E39 -> 32.237224 | E56: ='TK 拆解'!E46 -> 12.67 | F56: =B56/D56 -> 0.89958118 | G56: =C56/E56 -> 1.183899 | H56: =(C56-E56)*(('TK 拆解'!E54+'TK 拆解'!E62+0.005*'TK 拆解'!E46)/'TK 拆解'!E46) -> 0.33444265
A57: 讀法：IT 設備與 IREN 一致（A 配置 0.99、B/C 配置 0.90）；廠房本體 TK 12.67 高於 IREN 9–11（高 15–41%），但加上叢集部署 3 後（12–14）TK 落在區間內。→ A 段「廠房可能偏低」應撤回：以原文的本體 9–11 比，TK 偏高；以含叢集部署比，TK 持平。總 capex：C 配置（29＋15）為 44.0、0.98 倍；A、B 配置（32＋10＝29＋13）為 42.0、0.935 倍（對 TK 44.9）。租金差額的分解方式不受影響。
A58: 營運費用下界 | B58: =0.15*9.7 -> 1.455 | C58: $B/GW·年 | D58: ='TK 拆解'!E65 -> 1.9826348 | E58: =B58/D58 -> 0.73387191 | F58: 15%×9.70＝1.455；扣電費、維修、其他直接營運費，不含企業管理費、財務費用、非現金項目 → 是下界（原文有依據）；TK 1.98 含站點營運與財產稅
A60: 4. 每 GPU 小時視角：長約租金是否不隨世代上升，而 TK 持有成本隨世代上升？（Derived）
A61: 世代 | B61: TK 每 GW GPU 數 | C61: TK 持有成本 $/GPU-hr | D61: 外部租金 $/GPU-hr（隱含） | E61: 外部 ÷ TK | F61: 外部來源
A62: Hopper：Silicon Data H100 指數（2026-10） | B62: ='TK 拆解'!C35 -> 718048 | C62: ='TK 拆解'!C76 -> 1.5425965 | D62: 2.53 | E62: =D62/C62 -> 1.6400918 | F62: Interested-party（指數商）
A63: Hopper：Ornn H100 成交價（2026-10） | B63: ='TK 拆解'!C35 -> 718048 | C63: ='TK 拆解'!C76 -> 1.5425965 | D63: 3.15 | E63: =D63/C63 -> 2.0420116 | F63: Interested-party
A64: 機隊層級（2025 組合，含 Hopper）：16.3÷1.25＝13.04 隱含（16.0 版 12.8 → $2.31） | B64: ='TK 拆解'!G35 -> 631536 | C64: ='TK 拆解'!G76 -> 1.690652 | D64: =B20*1000000000/(B64*8760) -> 2.3570857 | E64: =D64/C64 -> 1.3941874 | F64: Derived：機隊層級，非單一世代
A65: GB300：IREN 9.70 | B65: ='TK 拆解'!E35 -> 487008 | C65: ='TK 拆解'!E76 -> 2.5517876 | D65: =9.7*1000000000/(B65*8760) -> 2.2736915 | E65: =D65/C65 -> 0.89101909 | F65: Interested-party（8-K）
A66: GB300：Nscale Narvik（第三方推算） | B66: ='TK 拆解'!E35 -> 487008 | C66: ='TK 拆解'!E76 -> 2.5517876 | D66: =6200000000/5/52000/8760 -> 2.7221637 | E66: =D66/C66 -> 1.0667673 | F66: Derived（單一第二手）
A67: VR200：Oracle 12.0（5GW 當 IT） | B67: ='TK 拆解'!F35 -> 291744 | C67: ='TK 拆解'!F76 -> 4.7836518 | D67: =G7*1000000000/(B67*8760) -> 4.6954282 | E67: =D67/C67 -> 0.98155727 | F67: Interested-party（匿名消息）
A68: 觀察：外部隱含租金約 $2.3–2.7／GPU-hr，幾乎不隨世代變；TK 持有成本由 Hopper 1.54 升到 VR200 4.78。→ 倍數隨世代由 >1（Hopper、舊世代組合）降到 <1（GB300）。這同時解釋「機隊層級 1.37」與「GB300 長約 0.89」，但依賴「租金不隨世代變」，且資料點少。反例：Oracle→VR200 隱含 $4.7（匿名消息、且假設交付 VR200；若交付 GB300 則隱含約 $2.8，與「租金不隨世代變」一致）。CoreWeave 2026Q2 隱含 $1.5（見第5節）則低於此區間，與假設不合，原因不可分離。
A70: 5. CoreWeave 2026Q2（10-Q 部分）與 Nebius 2026Q2（6-K）財報結構（百萬美元）
A71: 項目 | B71: CoreWeave Q2 2026 | C71: Nebius Q2 2026 | D71: 說明
A72: 營收 | B72: 2575 | C72: 582.3 | D72: 10-Q／6-K
A73: 營業成本（cost of revenue） | B73: 879 | C73: 133.6
A74: 技術與基礎設施 | B74: 1507 | D74: CoreWeave 項目
A75: 折舊 | B75: 1400 | C75: 259.7 | D75: CoreWeave：是否含在技術與基礎設施內，部分 10-Q 未明（假設含）
A76: 營業成本 ÷ 營收 | B76: =B73/B72 -> 0.34135922 | C76: =C73/C72 -> 0.229435
A77: 折舊 ÷ 營收 | B77: =B75/B72 -> 0.54368932 | C77: =C75/C72 -> 0.44599004
A78: 營收 − 營業成本 − 技術與基礎設施（SG&A 前） | B78: =B72-B73-B74 -> 189 | D78: 若折舊含於技術與基礎設施：營業利益率
A79: ÷ 營收 | B79: =B78/B72 -> 0.073398058
A80: TK 對照：廠房側成本占持有成本（廠房年金＋電費＋廠房維護＋站點營運＋廠房財產稅） | B80: =('TK 拆解'!G54+'TK 拆解'!G60+'TK 拆解'!G62+'TK 拆解'!G63+0.005*'TK 拆解'!G46)/'TK 拆解'!G66 -> 0.30111771 | D80: CoreWeave 營業成本含租賃機房與電力 → 與此對照（34% vs 約 30%），量級吻合；營業成本內容未逐項揭露（Derived）；分母不同（營收 vs 持有成本）：34%×營收 8.24≈2.81，30%×持有成本 9.35≈2.82，絕對值吻合
A81: TK 對照：IT 帳面折舊 ÷ 持有成本（組合） | B81: ='TK 拆解'!G39/'TK 拆解'!E11/'TK 拆解'!G66 -> 0.46530288 | D81: CoreWeave 折舊占營收 54%；TK 組合 IT 折舊約 47%（以 9.35 為營收）；差距可由新世代較貴、含租賃改良折舊解釋（Derived）
A82: CoreWeave active power Q1 末（GW） | B82: 1 | D82: 由 Q2 末 1.5GW 與「Q2 淨增近 500MW」反推（與「Q1 突破 1GW」一致）；IT 或設施口徑未取得
A83: CoreWeave active power Q2 末（GW） | B83: 1.5 | D83: Q2 新聞稿（搜尋摘要，二手）
A84: 平均 active power Q2（GW） | B84: =(B82+B83)/2 -> 1.25
A85: 營收年化 ÷ 平均 active power（$B/GW·年） | B85: =B72*4/1000/B84 -> 8.24 | D85: Q4 2025 為 8.73（A 段）；新容量爬坡拉低比值
A86: ÷ TK 組合 9.35 | B86: =B85/'TK 拆解'!G66 -> 0.88098958
A87: 隱含 $/GPU-hr（用 TK 組合每 GW GPU 數） | B87: =B85*1000000000/('TK 拆解'!G35*8760) -> 1.4894468 | D87: 明顯低於 H100 指數 2.5–3.2：爬坡落差（電通但未計費）＋舊約低價＋口徑；不可分離
A88: Nebius 設備耐用年限 | B88: 4 → 5 年（2026Q1 起） | D88: 折舊率下降約 20%，抬高帳面利潤，不改現金成本；MW 定義未揭露
A89: 未取得（待 Drive inbox 的 10-Q 全文） | B89: active power 定義、GPU 耐用年限、債務利率 | D89: → 有了債務利率才能把「出租方折現率 3–8%」落到 CoreWeave 實值
A91: 6. 出租方資金成本依公司分列；IREN 租金差額重新拆解（CoreWeave 10-Q Note 10；IREN 8-K）
A92: 注意：10-Q 只讀到 181 頁中的前約 80 頁（財報本文、附註 1–15、MD&A 前半）；active power 與 contracted power 定義、GPU 耐用年限未找到。
A93: CoreWeave 債務（2026-06-30；$M） | B93: 有效利率 | C93: 餘額 $M | D93: 類別 | E93: 說明
A94: DDTL 1.0 | B94: 0.15 | C94: 1300 | D94: DDTL | E94: 10-Q Note 10「Effective Interest Rates」
A95: DDTL 2.0 | B95: 0.11 | C95: 3190 | D95: DDTL | E95: 10-Q Note 10「Effective Interest Rates」
A96: DDTL 2.1 | B96: 0.09 | C96: 3000 | D96: DDTL | E96: 10-Q Note 10「Effective Interest Rates」
A97: DDTL 3.0 | B97: 0.09 | C97: 2215 | D97: DDTL | E97: 10-Q Note 10「Effective Interest Rates」
A98: DDTL 5.0（SOFR+4.50%） | B98: 0.09 | C98: 1101 | D98: DDTL | E98: 10-Q Note 10「Effective Interest Rates」
A99: DDTL 4.0（non-recourse；SOFR+2.25% 或 Treasury+2.00%） | B99: 0.07 | C99: 2837 | D99: DDTL | E99: 10-Q Note 10「Effective Interest Rates」
A100: 2030 Senior Notes | B100: 0.1 | C100: 2000 | D100: 其他 | E100: 10-Q Note 10「Effective Interest Rates」
A101: 2031 9.00% Notes | B101: 0.1 | C101: 1750 | D101: 其他 | E101: 10-Q Note 10「Effective Interest Rates」
A102: 2031 9.75% Notes | B102: 0.1 | C102: 2750 | D102: 其他 | E102: 10-Q Note 10「Effective Interest Rates」
A103: 2032 9.625% Notes | B103: 0.1 | C103: 1250 | D103: 其他 | E103: 10-Q Note 10「Effective Interest Rates」
A104: 2032 EUR Notes | B104: 0.09 | C104: 2279 | D104: 其他 | E104: 10-Q Note 10「Effective Interest Rates」
A105: 2031 Convertible | B105: 0.02 | C105: 2588 | D105: 可轉債 | E105: 10-Q Note 10「Effective Interest Rates」
... A109: Magnetar Loan | B109: 0.12 | C109: 189 | D109: 其他 | E109: 10-Q Note 10「Effective Interest Rates」
A110: 加權平均（全部，按餘額） | B110: =SUMPRODUCT(B94:B109,C94:C109)/SUM(C94:C109) -> 0.084134342 | C110: =SUM(C94:C109) -> 35551 | E110: Derived（10-Q 無整體加權平均；原文只有 OEM 短期工具 9%）
...
