Workbook

Sheet 參數
A1: 名稱 | B1: 基準 | C1: 低 | D1: 高 | E1: 單位 | F1: 標記 | G1: 來源／說明
A2: AL_FleetHold（TK 機隊持有成本，每 IT-GW·年） | B2: 9.3531186 | C2: 6.7193713 | D2: 15.725692 | E2: $B/GW·年 | F2: Derived（TK v21.2 Alloc!C157/D157/E157） | G2: IT 關鍵電力口徑；Hopper 0.6／GB200 0.4
A3: AL_SpendBasis（計價倍數） | B3: 1.8 | C3: 0.85 | D3: 2.3 | E3: x | F3: Derived | G3: TK v21.2 Alloc_In!C23；本段檢驗對象
A4: IF_GPUsPerGW Hopper | B4: 718048 | E4: 顆/GW | F4: Derived（TK） | G4: 沿用 9a 筆記
A5: IF_GPUsPerGW GB200 | B5: 501768 | E5: 顆/GW | F5: Derived（TK） | G5: 沿用 9a 筆記
A6: 2025 機隊 Hopper 權重 | B6: 0.6 | F6: Derived（TK） | G6: GB200 權重＝1−此值
A7: 每年小時數 | B7: 8760 | E7: 小時 | F7: 常數
A8: AL_FleetGW25（OpenAI 2025 平均上線 GW） | B8: 1.127807 | C8: 1 | D8: 1.25 | E8: GW | F8: Derived（TK Cap_In!C331） | G8: 9a：0.6→1.9 GW 端點內插
A9: OpenAI 2025 全部算力支出（84＋120） | B9: 20.4 | C9: 16.1 | D9: 21.7 | E9: $B | F9: Interested-party（外流查核帳；chat 端 9a） | G9: 204 億；161–217 億為 chat 端查核帳框出區間
A10: s：204 億中屬當年上線算力費用的比例 | B10: 0.9 | C10: 0.79 | D10: 1 | F10: Derived（chat 端 9a） | G10: 基準取 0.9 為本段簡化，非 9a 數字
A11: 設施電力／IT 電力（PUE，設施口徑 GW 換 IT 用） | B11: 1.2 | C11: 1 | D11: 1.3 | E11: x | F11: Assumed | G11: TK 慣例 GW＝IT；外部 GW 口徑未明時才用；Epoch 對 PUE 區間 1.1–1.7
A13: 衍生（公式）
A14: 混合 GPU 數／GW＝Hopper 權重×顆數＋GB200 權重×顆數 | B14: =參數!$B$6*參數!$B$4+(1-參數!$B$6)*參數!$B$5 -> 631536 | E14: 顆/GW | F14: Derived | G14: 約 63.2 萬顆
A15: TK 持有成本每 GPU 小時 | B15: =參數!$B$2*1000000000/(參數!$B$14*參數!$B$7) -> 1.690652 | E15: $/GPU·小時 | F15: Derived | G15: 約 1.69
A16: 1.8 倍對應的實付價（每 GW·年） | B16: =參數!$B$3*參數!$B$2 -> 16.835613 | E16: $B/GW·年 | F16: Derived | G16: 約 16.8
A17: 1.8 倍對應的實付價（每 GPU 小時） | B17: =參數!$B$3*參數!$B$15 -> 3.0431736 | E17: $/GPU·小時 | F17: Derived | G17: 約 3.04

Sheet 換算
A1: 區塊／項目 | B1: 數值 | C1: 單位 | D1: 標記 | E1: 說明（藍字＝輸入；黑字＝公式）
A3: E01 The Information 2024（DCD 轉述）：A100 每小時 1.30 美元、等效 35 萬顆 A100
A4: Microsoft 向 OpenAI 收費（每 A100 小時） | B4: 1.3 | C4: $/A100·小時 | D4: Interested-party | E4: DCD：「about $1.30 per A100 server per hour」；以下用『每顆』讀法：The Information 原句寫 chips；若 35 萬是 8 顆伺服器，則 280 萬顆 A100 約 2.6 GW，遠超 OpenAI 2024 年底總量 0.6 GW。金額 35 萬×1.30×8760＝39.9 億兩種讀法都吻合
A5: 等效 A100 顆數 | B5: 350000 | C5: 顆 | D5: Interested-party | E5: The Information 2024-07：cluster 'has the equivalent of 350,000 Nvidia A100 chips'
A6: 隱含年支出 | B6: =換算!$B$4*換算!$B$5*參數!$B$7/1000000000 -> 3.9858 | C6: $B/年 | D6: Derived | E6: 應≈ 報導『約 40 億』
A7: 對照：Zitron 內部文件 2024 全年 Azure 推論（4 季加總） | B7: 3.767 | C7: $B | D7: Interested-party | E7: wheresyoured.at；與上行同量級（相差約 6%）
A8: 每顆 A100 的 IT 電力（含伺服器內網路等）基準 | B8: 0.93 | C8: kW/顆 | D8: Assumed | E8: DGX A100 約 6.5kW／8 顆＝0.81；×Epoch IT 開銷係數 1.14＝0.93；區間 0.8–1.1
A9: kW 低 | B9: 0.8 | C9: kW/顆 | D9: Assumed
A10: kW 高 | B10: 1.1 | C10: kW/顆 | D10: Assumed
A11: 隱含 IT-GW（基準） | B11: =換算!$B$5*換算!$B$8/1000000 -> 0.3255 | C11: GW | D11: Derived
A12: 隱含 IT-GW（kW 低） | B12: =換算!$B$5*換算!$B$9/1000000 -> 0.28 | C12: GW | D12: Derived
A13: 隱含 IT-GW（kW 高） | B13: =換算!$B$5*換算!$B$10/1000000 -> 0.385 | C13: GW | D13: Derived
A14: 每 GW·年 | B14: =換算!$B$6/換算!$B$11 -> 12.245161 | C14: $B/GW·年 | D14: Derived | E14: 2024 年、A100 世代；比較基準仍用 TK 2025 機隊持有成本（假設每 IT-kW 的持有成本跨世代近似不變：伺服器資本 /kW 約 25–31 千美元，Assumed）
A15: ÷ AL_FleetHold（倍數） | B15: =換算!$B$14/參數!$B$2 -> 1.3092062 | C15: x | D15: Derived
A16: 倍數低（kW 高） | B16: =換算!$B$6/換算!$B$13/參數!$B$2 -> 1.1068744 | C16: x | D16: Derived
A17: 倍數高（kW 低） | B17: =換算!$B$6/換算!$B$12/參數!$B$2 -> 1.5219523 | C17: x | D17: Derived
A18: 換成 2025 機隊口徑每 GPU 小時（倍數×TK 每 GPU 小時持有成本，基準） | B18: =換算!$B$15*參數!$B$15 -> 2.2134122 | C18: $/GPU·小時 | D18: Derived | E18: 對照證偽條件 (b) 的 2 美元門檻
A19: 同上（低） | B19: =換算!$B$16*參數!$B$15 -> 1.8713394 | C19: $/GPU·小時 | D19: Derived
A20: 同上（高） | B20: =換算!$B$17*參數!$B$15 -> 2.5730916 | C20: $/GPU·小時 | D20: Derived | E20: 橫跨 2 美元 → (b) 不能判為觸發，也不能判為排除
A22: E02 同一個 1.30：換成『占牌價比例』再套到 2025 機隊（與 E01 同源，算一筆）
A23: Azure ND96amsr A100 v4 隨需牌價（8 顆） | B23: 32.77 | C23: $/小時 | D23: Verified（牌價，三方追蹤站 sparecores）
A24: 每顆 A100 牌價 | B24: =換算!$B$23/8 -> 4.09625 | C24: $/A100·小時 | D24: Derived
A25: 1.30 占牌價比例 | B25: =換算!$B$4/換算!$B$24 -> 0.31736344 | D25: Derived | E25: 約 0.32（折扣約 68%）
A26: H100 v5 隨需牌價每顆（98.32÷8） | B26: =98.32/8 -> 12.29 | C26: $/H100·小時 | D26: Verified（牌價，azurespeed）
A27: GB200 v6 隨需牌價每顆（108.16÷4） | B27: =108.16/4 -> 27.04 | C27: $/GB200·小時 | D27: Verified（牌價，azurespeed；Microsoft Learn：每 VM 4 顆）
A28: 2025 機隊權重牌價（0.6／0.4） | B28: =參數!$B$6*換算!$B$26+(1-參數!$B$6)*換算!$B$27 -> 18.19 | C28: $/GPU·小時 | D28: Derived
A29: 套用 0.32 後的每 GPU 小時 | B29: =換算!$B$25*換算!$B$28 -> 5.772841 | C29: $/GPU·小時 | D29: Derived | E29: 把 2024 A100 的折扣比例硬套到 2025 世代，僅作上界示意
A30: ÷ TK 每 GPU 小時持有成本 | B30: =換算!$B$29/參數!$B$15 -> 3.4145649 | C30: x | D30: Derived | E30: 牌價每 kW 隨世代大漲（見 E10），折扣比例不可跨世代套用；本列為上界，不作支持證據
A32: E03 Microsoft FY26 10-K：來自 OpenAI 的營收 241 億（含營收分成）
A33: Microsoft 對 OpenAI 營收（FY26＝2025-07 至 2026-06，含營收分成） | B33: 24.1 | C33: $B | D33: Verified | E33: 10-K：'revenue from commercial arrangements with OpenAI, inclusive of revenue-sharing payments, of $24.1 billion'
A34: 扣除營收分成（OpenAI 付 Microsoft 的 20% 分成；金額未披露） | B34: 3 | C34: $B | D34: Assumed | E34: 20% 營收分成的粗估，區間 2.0–4.0；OpenAI FY26 營收未知，無來源
A35: 可歸屬算力使用費 | B35: =換算!$B$33-換算!$B$34 -> 21.1 | C35: $B | D35: Derived
A36: 假設 Azure 承載 OpenAI 的 FY26 平均 IT-GW（低） | B36: 1 | C36: GW | D36: Assumed | E36: 無來源；OpenAI 2025 年底總量 1.9 GW
A37: 同上（中） | B37: 1.75 | C37: GW | D37: Assumed
A38: 同上（高） | B38: 2.5 | C38: GW | D38: Assumed
A39: 倍數（GW 低） | B39: =換算!$B$35/換算!$B$36/參數!$B$2 -> 2.255932 | C39: x | D39: Derived
A40: 倍數（GW 中） | B40: =換算!$B$35/換算!$B$37/參數!$B$2 -> 1.289104 | C40: x | D40: Derived
A41: 倍數（GW 高） | B41: =換算!$B$35/換算!$B$38/參數!$B$2 -> 0.90237282 | C41: x | D41: Derived | E41: 分母 Azure 承載 GW 無來源 → 不可分離，僅作量級
A43: E04 2025-10 重組：OpenAI 向 Azure 增購 2,500 億美元（無單價、無期間）
A44: 增購承諾 | B44: 250 | C44: $B | D44: Verified（Microsoft 官方部落格） | E44: 'contracted to purchase an incremental $250B of Azure services'；未載單價與期間
A45: 若單價＝1.0×持有成本，可買 | B45: =換算!$B$44/參數!$B$2 -> 26.729053 | C45: GW·年 | D45: Derived
A46: 若單價＝1.8×持有成本，可買 | B46: =換算!$B$44/參數!$B$16 -> 14.849474 | C46: GW·年 | D46: Derived | E46: 期間未知 → 無法反推單價
A48: E05 Oracle–OpenAI：3,000 億美元、5 年、4.5 GW（Next Platform：'culminates with 4.5 GW'）
A49: 合約總額 | B49: 300 | C49: $B | D49: Interested-party（媒體；Oracle 申報未點名客戶）
A50: 年數 | B50: 5 | C50: 年 | D50: Interested-party
A51: 終局容量 | B51: 4.5 | C51: GW | D51: Interested-party | E51: 口徑（IT／設施）未明；起點 2027 年中，非 2025 價格
A52: 每 GW·年（假設 4.5 GW 全期都在、且為 IT 口徑） | B52: =換算!$B$49/換算!$B$50/換算!$B$51 -> 13.333333 | C52: $B/GW·年 | D52: Derived | E52: 下限情境
A53: 全期平均容量÷終局容量（爬坡）基準 | B53: 0.8 | D53: Assumed | E53: 區間 0.6–1.0；'culminates' 表示終局才達 4.5 GW
A54: 爬坡低（平均容量比例小） | B54: 0.6 | D54: Assumed
A55: 設施→IT 換算（PUE）基準 | B55: =參數!$B$11 -> 1.2 | C55: x | D55: Assumed | E55: 若 4.5 GW 為設施口徑
A56: PUE 高 | B56: =參數!$D$11 -> 1.3 | C56: x | D56: Assumed
A57: 倍數低（IT 口徑、無爬坡） | B57: =換算!$B$52/參數!$B$2 -> 1.4255495 | C57: x | D57: Derived
A58: 倍數基準（PUE 基準、爬坡 0.8） | B58: =換算!$B$52*換算!$B$55/換算!$B$53/參數!$B$2 -> 2.1383242 | C58: x | D58: Derived
A59: 倍數高（PUE 高、爬坡 0.6） | B59: =換算!$B$52*換算!$B$56/換算!$B$54/參數!$B$2 -> 3.0886905 | C59: x | D59: Derived
A61: E06 供應商毛利率錨點：價格÷供應商成本＝1÷(1−毛利率)
A62: Oracle AI 雲 2025-06～08 季平均毛利率（The Information 內部文件，DCD 轉述） | B62: 0.16 | D62: Interested-party | E62: 季間 10–20%；該季 AI 伺服器出租 9 億、毛利 1.25 億（約 14%）
A63: Oracle 預期 AI 基礎設施毛利率上限（itiger 轉述） | B63: 0.35 | D63: Interested-party | E63: 'gross margin of up to 35%'；是否全合約期未明
A64: Oracle 目標毛利率（Next Platform 引述） | B64: 0.4 | D64: Interested-party | E64: 'try to get 40 percent gross margins'
A65: 價格÷成本（16%） | B65: =1/(1-換算!$B$62) -> 1.1904762 | C65: x | D65: Derived
A66: 價格÷成本（35%） | B66: =1/(1-換算!$B$63) -> 1.5384615 | C66: x | D66: Derived
A67: 價格÷成本（40%） | B67: =1/(1-換算!$B$64) -> 1.6666667 | C67: x | D67: Derived | E67: 『成本』是供應商會計成本，與 TK 經濟持有成本是否同口徑未知
A69: E07 CoreWeave（公司申報）：營收÷活躍電力
A70: 2025Q3 營收 | B70: 1.365 | C70: $B | D70: Verified | E70: CoreWeave 2025Q3 新聞稿（9a W3-03）
A71: Q2 末活躍電力 | B71: 470 | C71: MW | D71: Verified（由 Q3 稿『+120 MW』推得）
A72: Q3 末活躍電力 | B72: 590 | C72: MW | D72: Verified
A73: 2025Q4 營收 | B73: 1.572 | C73: $B | D73: Verified | E73: CoreWeave 2025Q4 新聞稿（businesswire 2026-02-26）；全年 5.131
A74: Q4 末活躍電力 | B74: 850 | C74: MW | D74: Verified | E74: 'more than 850 MW'（取下限）
A75: Q3：年化營收÷平均活躍電力 | B75: =換算!$B$70*4/((換算!$B$71+換算!$B$72)/2/1000) -> 10.301887 | C75: $B/GW·年 | D75: Derived | E75: 全客戶混合；活躍電力口徑（IT／設施）公司未明
A76: Q4：年化營收÷平均活躍電力 | B76: =換算!$B$73*4/((換算!$B$72+換算!$B$74)/2/1000) -> 8.7333333 | C76: $B/GW·年 | D76: Derived | E76: Q4 大量新增電力尚在爬坡，分母偏大
A77: Q3 倍數 | B77: =換算!$B$75/參數!$B$2 -> 1.1014387 | C77: x | D77: Derived
A78: Q4 倍數 | B78: =換算!$B$76/參數!$B$2 -> 0.93373491 | C78: x | D78: Derived
A79: Q3＋Q4 合併倍數 | B79: =(換算!$B$70+換算!$B$73)*2/(((換算!$B$71+換算!$B$72)/2+(換算!$B$72+換算!$B$74)/2)/2/1000)/參數!$B$2 -> 1.0048413 | C79: x | D79: Derived
A81: E08 IREN–Microsoft（公司公告）：97 億美元、5 年、約 200 MW IT
A82: 合約總額 | B82: 9.7 | C82: $B | D82: Verified（公司公告；techinformed 轉述） | E82: 20% 預付款，第 24 個月後抵用；GPU 為 GB300；Microsoft 是買方
A83: 年數 | B83: 5 | C83: 年 | D83: Verified
A84: IT 負載 | B84: 0.2 | C84: GW | D84: Verified（公告用語 'about 200 MW of IT load'）
A85: 每 GW·年 | B85: =換算!$B$82/換算!$B$83/換算!$B$84 -> 9.7 | C85: $B/GW·年 | D85: Derived | E85: 分母是額定 IT 容量、分子含爬坡期 → 實際單價 ≥ 此值
A86: 倍數 | B86: =換算!$B$85/參數!$B$2 -> 1.0370872 | C86: x | D86: Derived
A88: E10 Azure 公開牌價（上界錨點）
A89: ND H100 v5 隨需（每 GPU 小時） | B89: =98.32/8 -> 12.29 | C89: $/小時 | D89: Verified（牌價，azurespeed／sparecores；東美） | E89: 8 顆
A90: ND H100 v5 一年預留（9a 沿用 Spheron） | B90: 7.93 | C90: $/小時 | D90: Analogy（二手）
A91: ND H100 v5 三年預留（9a 沿用 Spheron） | B91: 5.47 | C91: $/小時 | D91: Analogy（二手）
A92: ND H100 v5 Spot（azurespeed／sparecores 18.1695÷8） | B92: =18.1695/8 -> 2.2711875 | C92: $/小時 | D92: Verified（牌價，可被收回） | E92: 非生產用途；公開最低價
A93: ND GB200 v6 隨需（108.16÷4） | B93: =108.16/4 -> 27.04 | C93: $/小時 | D93: Verified（牌價） | E93: 每 VM 4 顆
A94: ND GB200 v6 一年預留（69.222÷4） | B94: =69.222/4 -> 17.3055 | C94: $/小時 | D94: Verified（牌價，devzero） | E94: 三年預留未找到
A95: H100 隨需：每 GW·年 | B95: =換算!$B$89*參數!$B$4*參數!$B$7/1000000000 -> 77.305335 | C95: $B/GW·年 | D95: Derived
A96: H100 隨需：÷ 持有成本 | B96: =換算!$B$95/參數!$B$2 -> 8.2651935 | C96: x | D96: Derived
A97: H100 隨需：1.8 倍相當於牌價折扣 | B97: =1-參數!$B$16/換算!$B$95 -> 0.78221925 | D97: Derived
A98: H100 三年預留：每 GW·年 | B98: =換算!$B$91*參數!$B$4*參數!$B$7/1000000000 -> 34.40685 | C98: $B/GW·年 | D98: Derived
A99: H100 三年預留：÷ 持有成本 | B99: =換算!$B$98/參數!$B$2 -> 3.67865 | C99: x | D99: Derived
A100: H100 三年預留：1.8 倍相當於牌價折扣 | B100: =1-參數!$B$16/換算!$B$98 -> 0.51069006 | D100: Derived
A101: H100 Spot：每 GW·年 | B101: =換算!$B$92*參數!$B$4*參數!$B$7/1000000000 -> 14.285998 | C101: $B/GW·年 | D101: Derived
A102: H100 Spot：÷ 持有成本 | B102: =換算!$B$101/參數!$B$2 -> 1.5274047 | C102: x | D102: Derived
A103: H100 Spot：1.8 倍相當於牌價折扣 | B103: =1-參數!$B$16/換算!$B$101 -> -0.17846957 | D103: Derived
A104: GB200 隨需：每 GW·年 | B104: =換算!$B$93*參數!$B$5*參數!$B$7/1000000000 -> 118.85399 | C104: $B/GW·年 | D104: Derived
A105: GB200 隨需：÷ 持有成本 | B105: =換算!$B$104/參數!$B$2 -> 12.707418 | C105: x | D105: Derived
A106: GB200 隨需：1.8 倍相當於牌價折扣 | B106: =1-參數!$B$16/換算!$B$104 -> 0.85835045 | D106: Derived
A107: GB200 一年預留：每 GW·年 | B107: =換算!$B$94*參數!$B$5*參數!$B$7/1000000000 -> 76.066112 | C107: $B/GW·年 | D107: Derived
A108: GB200 一年預留：÷ 持有成本 | B108: =換算!$B$107/參數!$B$2 -> 8.1327005 | C108: x | D108: Derived
A109: GB200 一年預留：1.8 倍相當於牌價折扣 | B109: =1-參數!$B$16/換算!$B$107 -> 0.7786713 | D109: Derived
...

Sheet 證據表
A1: 編號 | B1: 同源群組 | C1: 項目 | D1: 來源 | E1: 日期（出處／讀取） | F1: 原文摘錄（引號內逐字；其餘為摘述） | G1: 原始數值與單位 | H1: 口徑 | I1: 換算步驟（公式在『換算』頁） | J1: 每 GW·年（$B） | K1: ÷9.353 倍數 | L1: 倍數低 | M1: 倍數高 | N1: 標記 | O1: 對 1.8 的判斷
A2: E01 | B2: S1 The Information 2024 | C2: Microsoft 向 OpenAI 收的 A100 單價 | D2: DCD 轉述 The Information（2024-07）https://www.datacenterdynamics.com/en/news/openai-training-and-inference-costs-could-reach-7bn-for-2024-ai-startup-set-to-lose-5bn-report/ | E2: 2024-07／讀取 2026-10-24 | F2: 'Microsoft has charged OpenAI about $1.30 per A100 server per hour, way below normal rates.'；'350,000 Nvidia A100 chips' | G2: 1.30 美元／A100·小時；35 萬顆；約 40 億／年 | H2: 2024 年、A100、推論叢集；IT-GW 由 kW/顆 Assumed 換算 | I2: 35 萬×1.30×8760＝年支出；除以 35 萬×0.93kW＝GW | J2: =換算!$B$14 -> 12.245161 | K2: =換算!$B$15 -> 1.3092062 | L2: =換算!$B$16 -> 1.1068744 | M2: =換算!$B$17 -> 1.5219523 | N2: Interested-party（報導洩漏；Microsoft 稱數字不盡正確的是另案）；換算含 Assumed | O2: 弱反對：2024／A100 約 1.3 倍（1.1–1.5），低於 1.8 但在 0.85–2.3 內；世代與年度不同
A3: E02 | B3: S1 The Information 2024 | C3: 同一個 1.30 換成占牌價比例再套 2025 機隊 | D3: 同上＋Azure 牌價頁（sparecores、azurespeed） | E3: 2024／2026 | F3: 同 E01；牌價 A100 32.77／8 顆、H100 98.32／8 顆、GB200 108.16／4 顆 | G3: 1.30÷4.10＝0.32 → ×2025 權重牌價 | H3: 把折扣比例跨世代硬套 | I3: 見換算頁 E02（套用結果約 5.8 美元／GPU·小時） | K3: =換算!$B$30 -> 3.4145649 | N3: Analogy：2024 A100 折扣 → 2025 世代；差在牌價每 kW 隨世代暴漲 | O3: 無關（上界示意，不採用）：套用結果約 3.4 倍，高於 2.3 上限，顯示折扣不可跨世代套用
A4: E03 | B4: S2 Microsoft 申報 | C4: Microsoft FY26 來自 OpenAI 的營收 | D4: Microsoft 10-K FY2026 Note 1（sec.gov）https://www.sec.gov/Archives/edgar/data/789019/000119312526323660/msft-20260630.htm | E4: 2026-07／讀取 2026-10-24 | F4: 'For fiscal year 2026, we recorded revenue from commercial arrangements with OpenAI, inclusive of revenue-sharing payments, of $24.1 billion, and accounts receivable from OpenAI as of June 30, 2026 was $6.0 billion.' | G4: 241 億；應收 60 億 | H4: FY26＝2025-07～2026-06；含 20% 營收分成與其他安排；未分 Azure／分成 | I4: 需 Azure 承載 GW 才能換算（無來源）→ 以 1.0／1.75／2.5 GW 示範 | J4: =換算!$B$35/換算!$B$37 -> 12.057143 | K4: =換算!$B$40 -> 1.289104 | L4: =換算!$B$41 -> 0.90237282 | M4: =換算!$B$39 -> 2.255932 | N4: Verified（金額）；GW 為 Assumed | O4: 無關（不可分離）：只有金額，無同期 Azure 分配容量；示範倍數 0.9–2.3
A5: E04 | B5: S3 重組條款 | C5: 2025-10 重組：增購 Azure 2,500 億 | D5: Microsoft 官方部落格 https://blogs.microsoft.com/blog/2025/10/28/the-next-chapter-of-the-microsoft-openai-partnership/ | E5: 2025-10-28／讀取 2026-10-24 | F5: 'OpenAI has contracted to purchase an incremental $250B of Azure services'；Microsoft 不再有 compute 優先承購權 | G5: 2,500 億美元 | H5: 未載單價、期間、世代 | I5: 無法換算：僅示範可買幾個 GW·年 | N5: Verified（金額） | O5: 無關（不可分離）：單價與期間皆未揭露
A6: E05 | B6: S4 Oracle 合約 | C6: Oracle–OpenAI | D6: Next Platform 2026-02-02 https://www.nextplatform.com/2026/02/02/oracles-financing-primes-the-openai-pump/；金額原見 WSJ／9a W3-01 | E6: 2025-09 簽；2026-02／讀取 2026-10-24 | F6: 'a five year deal that culminates with 4.5 gigawatts of datacenter facilities' | G6: 3,000 億美元／5 年／4.5 GW | H6: 2027 起、新世代；GW 口徑未明（facility 字樣） | I6: 300÷5÷4.5＝13.3；再依 PUE、爬坡調整 | J6: =換算!$B$52 -> 13.333333 | K6: =換算!$B$58 -> 2.1383242 | L6: =換算!$B$57 -> 1.4255495 | M6: =換算!$B$59 -> 3.0886905 | N6: Interested-party（Oracle／OpenAI 轉述）+ Analogy（非 Azure、非 2025） | O6: 支持（偏高端）：最低 1.4，合理 2.1，facility＋爬坡可達 3.1；但屬未來價
A7: E06 | B7: S5 Oracle 毛利率 | C7: 供應商加價的上限錨點 | D7: DCD／The Information https://www.datacenterdynamics.com/en/news/internal-documents-show-oracles-average-profit-margin-for-ai-cloud-deals-was-16-report/；itiger；Next Platform | E7: 2025-10／讀取 2026-10-24 | F7: 'average gross profit margin of just 16 percent'（季間 10–20%）；'gross margin of up to 35%'；'try to get 40 percent gross margins' | G7: 16%／35%／40% | H7: 價格÷供應商會計成本 | I7: 1÷(1−毛利率) | K7: =換算!$B$65 -> 1.1904762 | L7: =換算!$B$65 -> 1.1904762 | M7: =換算!$B$67 -> 1.6666667 | N7: Interested-party：Oracle（內部文件外流／管理層目標） | O7: 弱反對：純供應商毛利只能解釋 1.19–1.67 倍；1.8 還需 TK 持有成本低估或隨需溢價（見 README）
A8: E07 | B8: S6 CoreWeave 申報 | C8: CoreWeave 營收÷活躍電力 | D8: CoreWeave 2025Q4 新聞稿 https://www.businesswire.com/news/home/20260226281661/en/CoreWeave-Reports-Strong-Fourth-Quarter-and-Fiscal-Year-2025-Results；Q3 稿（9a） | E8: 2026-02-26／讀取 2026-10-24 | F8: Q4 營收 1,572 百萬；'Added approximately 260 MW of active power capacity, bringing the total to more than 850 MW' | G8: Q3 1.365B／530MW；Q4 1.572B／720MW | H8: 全客戶、Hopper 為主、含網路儲存；活躍電力口徑未明 | I8: 年化營收÷平均活躍電力 | J8: =換算!$B$76 -> 8.7333333 | K8: =換算!$B$79 -> 1.0048413 | L8: =換算!$B$78 -> 0.93373491 | M8: =換算!$B$77 -> 1.1014387 | N8: Verified（原數）／Derived（比值）；Analogy（非 OpenAI、非 Azure） | O8: 反對：neocloud 已實現單價約 0.9–1.1 倍；Azure 對 OpenAI 若遠高於此需另有理由
A9: E08 | B9: S7 IREN 公告 | C9: Microsoft 向 IREN 租 GB300 | D9: techinformed 轉述 IREN 公告 https://techinformed.com/microsoft-signs-9-7-billion-iren-deal-for-nvidia-gb300-capacity/ | E9: 2025-11／讀取 2026-10-24 | F9: 'about $9.7 billion'；五年；'about 200 MW of IT load'；20% 預付 | G9: 97 億／5 年／200 MW IT | H9: IT 口徑、GB300、Microsoft 是買方 | I9: 9.7÷5÷0.2 | J9: =換算!$B$85 -> 9.7 | K9: =換算!$B$86 -> 1.0370872 | L9: =換算!$B$86 -> 1.0370872 | N9: Verified（公司公告）+ Analogy（買方價，非賣給 OpenAI） | O9: 反對（弱）：Microsoft 向 neocloud 租的成本約 1.0 倍；Azure 轉售給 OpenAI 要加到 1.8 倍需加價約 73%
A10: E10 | B10: S8 Azure 牌價 | C10: Azure ND H100 v5／ND GB200 v6 公開牌價 | D10: azurespeed https://www.azurespeed.com/AzureVmPricing/Standard_ND96isr_H100_v5 、…/Standard_ND128isr_NDR_GB200_v6；sparecores；devzero；Microsoft Learn（GB200 每 VM 4 顆） | E10: 2026／讀取 2026-10-24 | F10: H100 v5 隨需 98.32 美元／小時（8 顆）；GB200 v6 隨需 108.16（4 顆）、一年預留 69.222；H100 Spot 18.1695 | G10: H100 12.29／顆；GB200 27.04／顆 | H10: 公開牌價（非 OpenAI 實付）；東美最低區 | I10: 價×每 GW 顆數×8760（基準欄＝H100 三年預留；低＝H100 Spot；高＝GB200 隨需） | J10: =換算!$B$98 -> 34.40685 | K10: =換算!$B$99 -> 3.67865 | L10: =換算!$B$102 -> 1.5274047 | M10: =換算!$B$105 -> 12.707418 | N10: Verified（牌價）；非實付價 | O10: 支持（上界）：牌價約 3.7–12.7 倍（Spot 1.5 倍）；1.8 倍相當於牌價折扣 51–86%
A11: E13 | B11: S9 AWS 公告 | C11: OpenAI–AWS 380 億／7 年 | D11: DCD https://www.datacenterdynamics.com/en/news/openai-signs-38bn-multi-year-agreement-with-aws-for-access-to-nvidia-gb200s-and-gb300s/ | E11: 2025-11／讀取 2026-10-24 | F11: '$38 billion seven-year agreement'；'hundreds of thousands' of GB200／GB300 | G11: 380 億／7 年；數十萬顆 | H11: 無 MW；顆數 Assumed | I11: 38÷7÷(顆數÷501,768) | K11: =換算!$B$118 -> 0.72806824 | L11: =換算!$B$119 -> 0.48537882 | M11: =換算!$B$117 -> 1.4561365 | N11: Interested-party（公告）+ Assumed 顆數 | O11: 無關（顆數 Assumed，倍數 0.5–1.5 太寬）
A12: E15 | B12: S10 GW 與顆數 | C12: OpenAI 2025 平均上線 GW 的新佐證 | D12: Altman X 2025-07-20（Tom's Hardware）；Epoch AI 方法頁 https://epoch.ai/data/ai-chip-users-documentation/methodology | E12: 2025-07／2026 | F12: 'we will cross well over 1 million GPUs brought online by the end of this year!'；Epoch 年底 H100e 2024 38.4 萬、2025 174 萬 | G12: 見換算頁 | H12: 年底時點值；Epoch 認為 GW 為 IT 口徑（約 90% 機率） | I12: 前重情境上限＝0.6＋1.3×(1−0.35) | N12: Interested-party（OpenAI／Altman）+ Analogy（Epoch） | O12: 證偽條件 (a) 未觸發：平均 GW 上限約 1.45，遠低於 1.8

Sheet 未找到與不可分離
A1: 編號 | B1: 類別 | C1: 項目 | D1: 查詢／處理 | E1: 結果
A2: N1 | B2: 已搜尋，未找到 | C2: OpenAI 2025 在 Azure 的實付每 GPU 小時 | D2: OpenAI price per GPU hour Azure discount；OpenAI pays Microsoft hourly；Zitron 文件頁（wheresyoured.at）全文 | E2: 無任何 2025 世代單價；Zitron 文件只有季別金額，無容量
A3: N2 | B3: 已搜尋，未找到 | C3: Microsoft 對 OpenAI 的關聯方定價（成本加成／最惠條款） | D3: cost plus／at cost／most favored；Musk v. Altman 公開附件（courtlistener 433688 號 391.62，為 2016 年簡報） | E3: 附件為 2016 年 AWS 時期簡報，無 Azure 單價；重組條款頁只有金額
A4: N3 | B4: 已搜尋，未找到 | C4: OpenAI 2025 Azure 帳單金額＋同期分配容量的配對 | D4: Microsoft 10-K／10-Q；法說會逐字稿（FY26Q2：RPO 6,250 億，OpenAI 約 45%） | E4: 只有金額與 RPO 占比，無容量；10-K 只披露營收 241 億
A5: N4 | B5: 已搜尋，未找到 | C5: 2025 年 Azure 承載 OpenAI 的 GW | D5: Azure OpenAI GW；Fairwater OpenAI GW | E5: 無；Epoch 稱 Microsoft 自家託管推論最高約占 OpenAI 第一方機隊 25%（方向相反，非 Azure 出租量）
A6: N5 | B6: 已搜尋，未找到 | C6: OpenAI 2025 季度或月度上線 GW | D6: quarterly GW；mid-2025 GW | E6: 只有年底端點 0.2／0.6／1.9 GW
A7: N6 | B7: 已搜尋，未找到 | C7: OpenAI–Google Cloud 合約金額與容量 | D7: — | E7: 9a 亦無；本段無新增
A8: N7 | B8: 已搜尋，未找到 | C8: Nebius–Microsoft 的 MW／顆數 | D8: Nebius Microsoft Vineland capacity MW | E8: 金額 174 億（可到 194 億）／5 年，容量未揭露 → 無法換算
A9: N8 | B9: 已搜尋，未找到 | C9: GB200 v6 三年預留牌價；H100 v5 官方價格頁逐字 | D9: azure.microsoft.com 價格頁（JS 頁）；learn.microsoft.com 價格頁 | E9: 官方價格頁與 vantage.sh 被工作環境阻擋；改用三方追蹤站（azurespeed、sparecores、devzero）
A10: D1 | B10: 不存在／不可分離 | C10: 重組條款 2,500 億 | D10: Microsoft 官方部落格 | E10: 金額有，單價與期間無 → 不可換算
A11: D2 | B11: 不存在／不可分離 | C11: Microsoft FY26 對 OpenAI 營收 241 億 | D11: 10-K | E11: 含營收分成與非 Azure 安排；無同期容量 → 不可分離
A12: D3 | B12: 不存在／不可分離 | C12: Anthropic–Azure 300 億、up to 1 GW | D12: pureai 轉述公告 | E12: 期間未揭露（'up to one gigawatt'）→ 不可換算；且非 OpenAI
... A15: D6 | B15: 不存在／不可分離 | C15: SemiAnalysis／InferenceX | D15: — | E15: 依任務規定不可單獨作依據；本段未使用
