Workbook

Sheet 彙總
A1: 出租方計價倍數錨點彙總：每 GW 年營收 ÷ TK 世代持有成本（AL_SpendBasis 基準 1.8，區間 0.85–2.3）
A3: 出租方 | B3: 項目 | C3: 類型 | D3: 電力口徑 | E3: 比值 低 | F3: 比值 高 | G3: 標記 | H3: 說明
A4: CoreWeave | B4: Q2 2026 每 active GW（PR #163） | C4: 機隊平均 | D4: active power，口徑未定義（IT／設施兩算） | E4: =CoreWeave!B23 -> 0.75690694 | F4: =CoreWeave!B24 -> 1.2817491 | G4: 營收 Verified；MW Interested-party | H4: ÷GB200／GB300
A5: CoreWeave | B5: Q2 2026 × 7 月漲價 1.25 | C5: 機隊平均（漲價後） | D5: 同上 | E5: =CoreWeave!B25 -> 0.94613367 | F5: =CoreWeave!B26 -> 1.6021863 | G5: 漲價為法說
A6: CoreWeave | B6: Q1 2026 每 active GW | C6: 機隊平均 | D6: 同上 | E6: =CoreWeave!B27 -> 0.82542777 | F6: =CoreWeave!B28 -> 1.3232341 | G6: 營收 Verified（H1−Q2） | H6: ÷Hopper／GB200／GB300；IT 與 PUE 1.3
A7: Nebius | B7: Q4 2025 每 active GW | C7: 機隊平均 | D7: active＝IT 設備耗用容量（公司定義） | E7: =Nebius!B18 -> 0.65408735 | F7: =Nebius!B19 -> 0.8328957 | G7: Interested-party；9 月底 MW 為 Assumed | H7: ÷Hopper／GB200
A8: Nebius | B8: 「2026 base」ACV per MW | C8: 存量合約平均 | D8: MW 未定義（以 IT 計） | E8: =Nebius!D24 -> 1.1022917 | F8: =Nebius!C24 -> 1.3592858 | G8: Interested-party | H8: ÷GB300 至 ÷GB200
A9: Nebius | B9: Q2 2026 四筆大單 $20–25M/MW | C9: 新約邊際 | D9: 同上 | E9: =Nebius!D25 -> 1.8371528 | F9: =Nebius!D26 -> 2.2964409 | G9: Interested-party | H9: ÷GB300；÷VR200 為 1.64–2.04
A10: Nebius | B10: Q3 短期 $40–50M/MW | C10: 短約邊際 | D10: 同上 | E10: =Nebius!D27 -> 3.6743055 | F10: =Nebius!D28 -> 4.5928819 | G10: Interested-party | H10: ÷GB300；≤6 個月
A11: IREN | B11: Microsoft 合約（2025-11） | C11: 長約（簽約時） | D11: MW-IT（公司標明） | E11: =IREN!C5 -> 0.89101909 | F11: =IREN!C5 -> 0.89101909 | G11: Interested-party；MW 對應 Assumed | H11: ÷GB300
A12: IREN | B12: 近期 3 年約 >$20M／洽談 ~$25M per MW(IT) | C12: 新約邊際 | D12: MW-IT（公司標明） | E12: =IREN!C8 -> 1.8371528 | F12: =IREN!C9 -> 2.2964409 | G12: Interested-party | H12: ÷GB300；÷VR200 為 1.64–2.04
A13: WhiteFiber | B13: Q2 2026 經常性雲端 ÷ 冰島 5.5 MW-IT | C13: 機隊平均（偏上界） | D13: IT（公司揭露 IT 負載） | E13: =MIN(WhiteFiber!B6:B7) -> 0.86240593 | F13: =MAX(WhiteFiber!B6:B7) -> 0.94787529 | G13: 營收 Verified（10-Q）；MW Interested-party | H13: ÷GB200／Hopper
A14: WhiteFiber | B14: Blackwell 新約（B300／GB200） | C14: 新約邊際 | D14: GPU 數 × TK 密度（Analogy） | E14: =WhiteFiber!B18 -> 1.3591486 | F14: =WhiteFiber!B19 -> 1.8639752 | G14: 合約 Verified（10-Q）；換算 Analogy | H14: 同世代 TK 持有成本
A15: WhiteFiber | B15: 存量世代續約（B200、H100） | C15: 存量續約 | D15: 同上 | E15: =WhiteFiber!B20 -> 0.90695828 | F15: =WhiteFiber!B21 -> 1.339522 | G15: 同上
A16: WhiteFiber | B16: VR200 576 顆（2027 Q2 起） | C16: 新約邊際 | D16: 同上 | E16: =WhiteFiber!B22 -> 1.4942383 | F16: =WhiteFiber!B22 -> 1.4942383 | G16: 同上
A18: 組別 | E18: 低 | F18: 高
A19: 機隊平均（不含漲價列、不含 WhiteFiber 上界） | E19: =MIN(E4,E6,E7) -> 0.65408735 | F19: =MAX(F4,F6,F7) -> 1.3232341 | G19: Derived | H19: CoreWeave Q1／Q2、Nebius Q4
A20: 新約邊際（Nebius、IREN、WhiteFiber Blackwell；不含短約） | E20: =MIN(E9,E12,E14) -> 1.3591486 | F20: =MAX(F9,F12,F14) -> 2.2964409 | G20: Derived
A21: AL_SpendBasis 基準 | E21: =輸入!$C$25 -> 1.8 | F21: =輸入!$C$25 -> 1.8 | G21: Assumed | H21: 區間 0.85–2.3

Sheet 輸入
A1: 鍵 | B1: 項目 | C1: 值 | D1: 單位 | E1: 標記 | F1: 來源
A2: tk_hop | B2: TK 持有成本 Hopper（AL_HoldGen／L1_HoldEconGW_Hopper） | C2: 9.7030873 | D2: $B/GW·年 | E2: Derived | F2: TK v21.4（model/20261024_Tokenomics_v21.4.xlsx） Alloc!C39
A3: tk_gb200 | B3: TK 持有成本 GB200 | C3: 8.8281656 | D3: $B/GW·年 | E3: Derived | F3: TK v21.4（model/20261024_Tokenomics_v21.4.xlsx） Alloc!D39
A4: tk_gb300 | B4: TK 持有成本 GB300 | C4: 10.886411 | D4: $B/GW·年 | E4: Derived | F4: TK v21.4（model/20261024_Tokenomics_v21.4.xlsx） Alloc!E39
A5: tk_vr200 | B5: TK 持有成本 VR200 | C5: 12.225471 | D5: $B/GW·年 | E5: Derived | F5: TK v21.4（model/20261024_Tokenomics_v21.4.xlsx） Alloc!F39
A6: tk_gpu_hop | B6: TK 每 IT GW GPU 數 Hopper | C6: 718048 | D6: 顆/GW | E6: Derived | F6: TK v21.4（model/20261024_Tokenomics_v21.4.xlsx） Interface!D7
A7: tk_gpu_gb200 | B7: TK 每 IT GW GPU 數 GB200 | C7: 501768 | D7: 顆/GW | E7: Derived | F7: TK v21.4（model/20261024_Tokenomics_v21.4.xlsx） Interface!G7
A8: tk_gpu_gb300 | B8: TK 每 IT GW GPU 數 GB300 | C8: 487008 | D8: 顆/GW | E8: Derived | F8: TK v21.4（model/20261024_Tokenomics_v21.4.xlsx） Interface!J7
A9: tk_gpu_vr200 | B9: TK 每 IT GW GPU 數 VR200 | C9: 291744 | D9: 顆/GW | E9: Derived | F9: TK v21.4（model/20261024_Tokenomics_v21.4.xlsx） Interface!M7
A10: tk_capexit_lo | B10: TK IF_CapexIT GB300 低 | C10: 28.554902 | D10: $B/GW | E10: Derived | F10: TK v21.4（model/20261024_Tokenomics_v21.4.xlsx） Interface!I9
A11: tk_capexit | B11: TK IF_CapexIT GB300 基準 | C11: 32.237224 | D11: $B/GW | E11: Derived | F11: TK v21.4（model/20261024_Tokenomics_v21.4.xlsx） Interface!J9
A12: tk_capexit_hi | B12: TK IF_CapexIT GB300 高 | C12: 39.282606 | D12: $B/GW | E12: Derived | F12: TK v21.4（model/20261024_Tokenomics_v21.4.xlsx） Interface!K9
A13: tk_capexfac | B13: TK IF_CapexFacility 基準 | C13: 12.67 | D13: $B/GW | E13: Derived | F13: TK v21.4（model/20261024_Tokenomics_v21.4.xlsx） Interface!J10
... A84: dg_ophi | B84: Data Gravity：每架年營運成本 高 | C84: 0.41 | D84: $M/架·年 | E84: Analogy | F84: 同上

Sheet CoreWeave
A1: CoreWeave（承接 PR #163 錨點；同算法重算 Q2，並加 Q1 2026 點）
A3: A. 季平均 active GW | B3: 值 | E3: 說明
A4: 3/31 active GW（＝6/30 − Q2 新增） | B4: =輸入!$C$28-輸入!$C$29 -> 1 | E4: GW；與 8-K「surpassed 1 GW」一致
A5: Q2 平均（線性） | B5: =(B4+輸入!$C$28)/2 -> 1.25 | E5: GW
A6: Q2 平均（6 月集中） | B6: =B4+(輸入!$C$29-輸入!$C$30)*(2/3)+輸入!$C$30*(1/6) -> 1.1833333 | E6: GW；4–5 月新增計 2/3 季、6 月新增計 1/6 季
A7: Q1 營收（H1 − Q2） | B7: =輸入!$C$27-輸入!$C$26 -> 2.078 | E7: $B
A8: Q1 平均（線性；12/31 0.85 → 3/31 1.0） | B8: =(輸入!$C$31+輸入!$C$32)/2 -> 0.925 | E8: GW；兩端皆為「逾」，平均偏低 → 每 GW 營收偏高
A10: B. 每 active GW 年營收（$B/GW·年） | B10: Q2 線性 | C10: Q2 6 月集中 | D10: Q1 線性
A11: IT 口徑 | B11: =輸入!$C$26*4/B5 -> 8.24 | C11: =輸入!$C$26*4/B6 -> 8.7042254 | D11: =B7*4/B8 -> 8.9859459
A12: 設施口徑 PUE 1.2（IT＝設施 ÷ PUE） | B12: =B11*輸入!$C$23 -> 9.888 | C12: =C11*輸入!$C$23 -> 10.44507 | D12: =D11*輸入!$C$23 -> 10.783135
A13: 設施口徑 PUE 1.3 | B13: =B11*輸入!$C$24 -> 10.712 | C13: =C11*輸入!$C$24 -> 11.315493 | D13: =D11*輸入!$C$24 -> 11.68173
A15: C. ÷ TK 持有成本 | B15: Hopper | C15: GB200 | D15: GB300
A16: Q2 IT 線性 | B16: =B11/輸入!$C$2 -> 0.84921425 | C16: =B11/輸入!$C$3 -> 0.93337624 | D16: =B11/輸入!$C$4 -> 0.75690694
A17: Q2 IT 6 月集中 | B17: =C11/輸入!$C$2 -> 0.89705731 | C17: =C11/輸入!$C$3 -> 0.98596082 | D17: =C11/輸入!$C$4 -> 0.79954958
A18: Q2 設施 PUE 1.2 線性 | B18: =B12/輸入!$C$2 -> 1.0190571 | C18: =B12/輸入!$C$3 -> 1.1200515 | D18: =B12/輸入!$C$4 -> 0.90828832
A19: Q2 設施 PUE 1.3 6 月集中 | B19: =C13/輸入!$C$2 -> 1.1661745 | C19: =C13/輸入!$C$3 -> 1.2817491 | D19: =C13/輸入!$C$4 -> 1.0394145
A20: Q1 IT 線性 | B20: =D11/輸入!$C$2 -> 0.92609143 | C20: =D11/輸入!$C$3 -> 1.0178724 | D20: =D11/輸入!$C$4 -> 0.82542777
A21: Q1 設施 PUE 1.3 | B21: =D13/輸入!$C$2 -> 1.2039189 | C21: =D13/輸入!$C$3 -> 1.3232341 | D21: =D13/輸入!$C$4 -> 1.0730561
A23: Q2 區間（GB200／GB300 欄，同 PR #163）：最小 | B23: =MIN(C16:D19) -> 0.75690694 | E23: PR #163 為 0.76
A24: Q2 區間：最大 | B24: =MAX(C16:D19) -> 1.2817491 | E24: PR #163 為 1.28
A25: Q2 區間 × 7 月漲價：最小 | B25: =B23*輸入!$C$33 -> 0.94613367
A26: Q2 區間 × 7 月漲價：最大 | B26: =B24*輸入!$C$33 -> 1.6021863
A27: Q1 區間（Hopper／GB200／GB300，IT 與 PUE 1.3）：最小 | B27: =MIN(B20:D21) -> 0.82542777
A28: Q1 區間：最大 | B28: =MAX(B20:D21) -> 1.3232341

Sheet Nebius
A1: Nebius（NBIS）：active power＝「capacity being consumed by IT equipment and available for revenue generation」（20-F）→ IT 側
A3: A. 機隊平均：2025 Q4（唯一有 active MW 的時點） | B3: 值 | E3: 說明
A4: 9/30 active GW 估計（依 ARR 比例） | B4: =輸入!$C$37*輸入!$C$36/輸入!$C$35 -> 0.074936 | E4: Assumed：每 GW 營收 9 月與 12 月相同
A5: 9/30 active GW 上界 | B5: =輸入!$C$38 -> 0.1 | E5: Q3 信稱年底目標 100 MW → 9 月底應低於此
A6: Q4 平均（線性，ARR 比例起點） | B6: =(B4+輸入!$C$37)/2 -> 0.122468 | E6: GW
A7: Q4 平均（線性，上界起點） | B7: =(B5+輸入!$C$37)/2 -> 0.135 | E7: GW；平均偏大 → 每 GW 營收偏低（保守端）
A9: 每 active GW 年營收（$B/GW·年） | B9: 值
A10: (1) ARR ÷ 年底 active | B10: =輸入!$C$35/輸入!$C$37 -> 7.3529412 | E10: 12 月營收 × 12 ÷ 年底 MW；12 月平均 MW 低於年底 → 此值略偏低
A11: (2) Q4 營收 × 4 ÷ Q4 平均（ARR 比例起點） | B11: =輸入!$C$39*4/B6 -> 6.9961133 | E11: core AI cloud 營收
A12: (3) Q4 營收 × 4 ÷ Q4 平均（上界起點） | B12: =輸入!$C$39*4/B7 -> 6.3466667 | E12: 保守端
A14: ÷ TK 持有成本（機隊：Hopper 為主，B200／GB200 次之，B300／GB300 剛開始） | B14: Hopper | C14: GB200 | D14: GB300
A15: (1) | B15: =B10/輸入!$C$2 -> 0.75779398 | C15: =B10/輸入!$C$3 -> 0.8328957 | D15: =B10/輸入!$C$4 -> 0.67542381
A16: (2) | B16: =B11/輸入!$C$2 -> 0.72101931 | C16: =B11/輸入!$C$3 -> 0.79247645 | D16: =B11/輸入!$C$4 -> 0.64264644
A17: (3) | B17: =B12/輸入!$C$2 -> 0.65408735 | C17: =B12/輸入!$C$3 -> 0.71891115 | D17: =B12/輸入!$C$4 -> 0.58298981
A18: 機隊區間（Hopper／GB200 欄）：最小 | B18: =MIN(B15:C17) -> 0.65408735
A19: 機隊區間：最大 | B19: =MAX(B15:C17) -> 0.8328957
A20: 敏感度：若 active 為實際耗電（設計功率＝active ÷ 平均用電比 0.7–0.9）→ 最小 | B20: =B18*輸入!$C$21 -> 0.45786115 | E20: 本段判斷不採（「capacity … available for revenue generation」讀作可用容量）
A21: 同上 → 最大 | B21: =B19*輸入!$C$22 -> 0.74960613
A23: B. 新約與存量合約單價（ACV per MW；MW 口徑未定義，以 IT 計） | B23: 單價 | C23: ÷GB200 | D23: ÷GB300 | E23: ÷VR200
A24: 「2026 base」ACV per MW | B24: =輸入!$C$40 -> 12 | C24: =B24/輸入!$C$3 -> 1.3592858 | D24: =B24/輸入!$C$4 -> 1.1022917 | E24: =B24/輸入!$C$5 -> 0.98155727
A25: Q2 四筆大單 低 | B25: =輸入!$C$41 -> 20 | C25: =B25/輸入!$C$3 -> 2.2654763 | D25: =B25/輸入!$C$4 -> 1.8371528 | E25: =B25/輸入!$C$5 -> 1.6359288
A26: Q2 四筆大單 高 | B26: =輸入!$C$42 -> 25 | C26: =B26/輸入!$C$3 -> 2.8318454 | D26: =B26/輸入!$C$4 -> 2.2964409 | E26: =B26/輸入!$C$5 -> 2.044911
A27: Q3 短期（≤6 個月）低 | B27: =輸入!$C$43 -> 40 | C27: =B27/輸入!$C$3 -> 4.5309526 | D27: =B27/輸入!$C$4 -> 3.6743055 | E27: =B27/輸入!$C$5 -> 3.2718576
A28: Q3 短期 高 | B28: =輸入!$C$44 -> 50 | C28: =B28/輸入!$C$3 -> 5.6636908 | D28: =B28/輸入!$C$4 -> 4.5928819 | E28: =B28/輸入!$C$5 -> 4.089822
A29: 若 MW 為設施電力：Q2 大單 ÷GB300 × PUE 1.2（低） | D29: =D25*輸入!$C$23 -> 2.2045833
A30: 同上 × PUE 1.3（高） | D30: =D26*輸入!$C$24 -> 2.9853732
A32: C. 回本期檢查（年化讀法是否成立） | B32: 值 | E32: 說明
A33: 隱含資本支出（Q2 大單低，扣 TK opex 基準） | B33: =輸入!$C$45*(B25-輸入!$C$15) -> 33.031836 | E33: $B/GW；回本期 × (ACV − 營運費用)
A34: 隱含資本支出（Q2 大單高） | B34: =輸入!$C$45*(B26-輸入!$C$15) -> 42.198503
A35: 對照 TK GB300 IT＋廠房資本支出（基準） | B35: =輸入!$C$11+輸入!$C$13 -> 44.907224 | E35: 若 ACV 是總額而非年額，隱含資本支出只有約 1/3，與任何口徑都不符 → 年化讀法成立
A36: 隱含 ÷ TK（低／高） | B36: =B33/B35 -> 0.73555729 | C36: =B34/B35 -> 0.93968184

Sheet IREN
A1: IREN（AI cloud 部分）：MW 標明「(IT)」；機隊 MW 未揭露 → 只做合約層
A3: A. Microsoft 合約（2025-11，GB300，5 年） | B3: 值 | C3: ÷GB300 | E3: 說明
A4: 年營收 | B4: =輸入!$C$46/輸入!$C$47 -> 1.94 | E4: $B/年（含 20% 預付，按直線平均）
A5: 每 IT GW 年營收 | B5: =B4/(輸入!$C$48/1000) -> 9.7 | C5: =B5/輸入!$C$4 -> 0.89101909 | E5: $B/GW·年；TK DB_Evidence E297 已記 9.70
A7: B. 近期合約（2026，3–5 年） | B7: 單價 | C7: ÷GB300 | D7: ÷VR200
A8: 近期 3 年約（下限） | B8: =輸入!$C$49 -> 20 | C8: =B8/輸入!$C$4 -> 1.8371528 | D8: =B8/輸入!$C$5 -> 1.6359288 | E8: 「>$20m」；GPU 為「ordered quite some time ago」→ 以 GB300 為主
A9: 洽談中 | B9: =輸入!$C$50 -> 25 | C9: =B9/輸入!$C$4 -> 2.2964409 | D9: =B9/輸入!$C$5 -> 2.044911
A11: C. 直接成本率與營運費用 | B11: 值
A12: Q4 FY26 AI Cloud 直接成本 ÷ 營收 | B12: =輸入!$C$53/輸入!$C$52 -> 0.13049645 | E12: 不含折舊；IREN 自有機房，主要為電費與站點營運
A13: 隱含營運費用：單價 20 × 直接成本率 | B13: =B12*B8 -> 2.6099291 | E13: $B/GW·年；對照 TK IF_OpexGW GB300 1.98（1.21–3.00）
A14: 隱含營運費用：單價 25 × 直接成本率 | B14: =B12*B9 -> 3.2624113
A16: D. 回本期隱含 GPU 資本支出（註 3 定義） | B16: 值 | C16: ÷TK IT
A17: 回本 × (20 − 隱含營運費用) | B17: =輸入!$C$51*(B8-B13) -> 34.780142 | C17: =B17/輸入!$C$11 -> 1.0788814 | E17: $B/GW；GPU 與附屬設備
A18: 回本 × (25 − 隱含營運費用) | B18: =輸入!$C$51*(B9-B14) -> 43.475177 | C18: =B18/輸入!$C$11 -> 1.3486018
A19: 對照：Dell 採購 ÷ 200 MW-IT（2025-11） | B19: =輸入!$C$54/(輸入!$C$48/1000) -> 29 | C19: =B19/輸入!$C$11 -> 0.89958118 | E19: TK SRC_DC_014＝29.0

Sheet WhiteFiber
A1: WhiteFiber（WYFI）：雲端分部；MW 以 IT 負載揭露（冰島 5.5 MW-IT）
A3: A. 機隊平均：2026 Q2 | B3: 值 | E3: 說明
A4: 經常性雲端營收（扣終止費） | B4: =輸入!$C$55-輸入!$C$56 -> 11.506 | E4: $M/季
A5: 每 IT GW 年營收（÷ 冰島 5.5 MW） | B5: =B4*4/輸入!$C$57 -> 8.368 | E5: $M/MW·年＝$B/GW·年；亞特蘭大等未計入 MW → 偏上界
A6: ÷ TK 持有成本 Hopper | B6: =B5/輸入!$C$2 -> 0.86240593 | E6: 機隊 H100／H200／B200 為主
A7: ÷ TK 持有成本 GB200 | B7: =B5/輸入!$C$3 -> 0.94787529
A9: B. 合約層（GPU 數 ÷ TK 每 GW GPU 數換算 IT GW；Analogy） | B9: 年營收 $M | C9: IT MW | D9: $B/GW·年 | E9: TK 持有成本 | F9: 比值 | G9: 世代
A10: Baseten 1,392 B300（36 個月，2026-11 起） | B10: =輸入!$C$58/輸入!$C$59 -> 55.066667 | C10: =輸入!$C$60/輸入!$C$8*1000 -> 2.8582693 | D10: =B10/C10 -> 19.265738 | E10: =輸入!$C$4 -> 10.886411 | F10: =D10/E10 -> 1.7697052 | G10: GB300
A11: 冰島 576 B300（5 年，2026-12 起；另有營收分成） | B11: =輸入!$C$61/輸入!$C$62 -> 17.5 | C11: =輸入!$C$63/輸入!$C$8*1000 -> 1.1827321 | D11: =B11/C11 -> 14.79625 | E11: =輸入!$C$4 -> 10.886411 | F11: =D11/E11 -> 1.3591486 | G11: GB300
A12: 新客戶 128 B300（36 個月，2026-07 簽） | B12: =輸入!$C$64/輸入!$C$65 -> 5.3333333 | C12: =輸入!$C$66/輸入!$C$8*1000 -> 0.26282936 | D12: =B12/C12 -> 20.292 | E12: =輸入!$C$4 -> 10.886411 | F12: =D12/E12 -> 1.8639752 | G12: GB300
A13: Prime Intellect 576 VR200（36 個月，2027 Q2 起） | B13: =輸入!$C$67/輸入!$C$68 -> 36.066667 | C13: =輸入!$C$69/輸入!$C$9*1000 -> 1.9743337 | D13: =B13/C13 -> 18.267767 | E13: =輸入!$C$5 -> 12.225471 | F13: =D13/E13 -> 1.4942383 | G13: VR200
A14: Prime Intellect 216 GB200（12 個月，2026-07 起） | B14: =輸入!$C$70/輸入!$C$71 -> 6.8 | C14: =輸入!$C$72/輸入!$C$7*1000 -> 0.43047783 | D14: =B14/C14 -> 15.7964 | E14: =輸入!$C$3 -> 8.8281656 | F14: =D14/E14 -> 1.7893185 | G14: GB200
A15: 既有客戶 384 B200（24 個月，2026-01 起） | B15: =輸入!$C$73/輸入!$C$74 -> 9.05 | C15: =輸入!$C$75/輸入!$C$7*1000 -> 0.76529392 | D15: =B15/C15 -> 11.825522 | E15: =輸入!$C$3 -> 8.8281656 | F15: =D15/E15 -> 1.339522 | G15: GB200
A16: 既有客戶 256 台 H100 伺服器（24 個月，2026 Q2 起；以 8 顆／台計 2,048 顆） | B16: =輸入!$C$76/輸入!$C$77 -> 25.1 | C16: =輸入!$C$78/輸入!$C$6*1000 -> 2.852177 | D16: =B16/C16 -> 8.8002953 | E16: =輸入!$C$2 -> 9.7030873 | F16: =D16/E16 -> 0.90695828 | G16: Hopper
A18: Blackwell 新約（B300／GB300／GB200、2026 下半年起）比值：最小 | B18: =MIN(F10:F12,F14) -> 1.3591486
A19: 同上：最大 | B19: =MAX(F10:F12,F14) -> 1.8639752
A20: 存量世代續約（B200 2026-01、H100 2026 Q2）：最小 | B20: =MIN(F15:F16) -> 0.90695828
A21: 同上：最大 | B21: =MAX(F15:F16) -> 1.339522
A22: VR200（2027 Q2 起） | B22: =F13 -> 1.4942383

Sheet GB300單價與營運費用
A1: GB300 NVL72 IT 資本支出與營運費用：公開點對照 TK（只列，不改 TK）
A3: A. 每 IT GW 的 IT 資本支出（$B/GW） | B3: 值 | C3: ÷TK 基準 | E3: 口徑
A4: TK IF_CapexIT GB300 低／基準／高 | B4: =輸入!$C$11 -> 32.237224 | C4: =B4/輸入!$C$11 -> 1 | E4: =TEXT(輸入!$C$10,"0.0")&"／"&TEXT(輸入!$C$11,"0.0")&"／"&TEXT(輸入!$C$12,"0.0")&"；機架＋scale-out 網路＋儲存與管理" -> 28.6／32.2／39.3；機架＋scale-out 網路＋儲存與管理
A5: TK 機架價 4.3 × 6,764 架（只機架） | B5: =輸入!$C$19*輸入!$C$17/1000 -> 29.0852 | C5: =B5/輸入!$C$11 -> 0.90222409 | E5: IF_RackPrice 基準；低 4.0、高 5.0
A6: IREN Dell 採購 ÷ 200 MW-IT（2025-11） | B6: =IREN!B19 -> 29 | C6: =B6/輸入!$C$11 -> 0.89958118 | E6: 含伺服器、IB、線材、軟體、部署；TK 已有（SRC_DC_014）
A7: Data Gravity 採購單 5.0 × 6,764 架（只機架，2026-08） | B7: =輸入!$C$79*輸入!$C$17/1000 -> 33.82 | C7: =B7/輸入!$C$11 -> 1.0490978 | E7: 不含 CDU、網路、儲存；TK 高情境機架價即此值
A8: Data Gravity 部署後 5.68 × 6,764 架 | B8: =輸入!$C$80*輸入!$C$17/1000 -> 38.41952 | C8: =B8/輸入!$C$11 -> 1.1917751 | E8: 含部署項目；不含叢集核心交換與儲存
A9: 媒體 6.0 × 6,764 架 | B9: =輸入!$C$81*輸入!$C$17/1000 -> 40.584 | C9: =B9/輸入!$C$11 -> 1.2589173 | E9: TK 列 Alt
A10: 媒體 6.5 × 6,764 架 | B10: =輸入!$C$82*輸入!$C$17/1000 -> 43.966 | C10: =B10/輸入!$C$11 -> 1.3638271
A11: IREN 回本期隱含（單價 20） | B11: =IREN!B17 -> 34.780142 | C11: =B11/輸入!$C$11 -> 1.0788814 | E11: Derived；GPU 與附屬設備
A12: IREN 回本期隱含（單價 25） | B12: =IREN!B18 -> 43.475177 | C12: =B12/輸入!$C$11 -> 1.3486018
A13: Nebius 回本期隱含（單價 20／25）÷ TK IT＋廠房 | B13: =Nebius!B33 -> 33.031836 | C13: =Nebius!B36 -> 0.73555729 | D13: =Nebius!C36 -> 0.93968184 | E13: 「associated capex」範圍未定義；C、D 欄為 ÷ TK IT＋廠房 44.9
A15: B. 每 IT GW 年營運費用（不含折舊，$B/GW·年） | B15: 值 | C15: ÷TK 基準 | E15: 口徑
A16: TK IF_OpexGW GB300 基準（低 1.21／高 3.00） | B16: =輸入!$C$15 -> 1.9826348 | C16: =B16/輸入!$C$15 -> 1 | E16: 含電費、維護、人員、稅保；不含廠房資本成本
A17: IREN 直接成本率 × 單價 20 | B17: =IREN!B13 -> 2.6099291 | C17: =B17/輸入!$C$15 -> 1.3163943 | E17: Derived；直接成本率 13% 來自 Q4 FY26 混合機隊
A18: IREN 直接成本率 × 單價 25 | B18: =IREN!B14 -> 3.2624113 | C18: =B18/輸入!$C$15 -> 1.6454928
A19: CoreWeave Q2 cost of revenue × 4 ÷ Q2 平均 active GW（線性） | B19: =輸入!$C$34*4/CoreWeave!B5 -> 2.8128 | C19: =B19/輸入!$C$15 -> 1.4187182 | E19: 含機房租金（託管）→ 應對 TK opex＋廠房資本成本，不可直接比
A20: Data Gravity 每架年營運 0.24 × 6,764 架 | B20: =輸入!$C$83*輸入!$C$17/1000 -> 1.62336 | C20: =B20/輸入!$C$15 -> 0.81878921 | E20: 範圍口徑未明（文中託管租金約 0.318／架落在區間內）；只作量級
A21: Data Gravity 每架年營運 0.41 × 6,764 架 | B21: =輸入!$C$84*輸入!$C$17/1000 -> 2.77324 | C21: =B21/輸入!$C$15 -> 1.3987649
