Workbook

Sheet 結論
A1: 9a Q 側約 2 倍缺口：審閱檔（2026-10-23；唯讀查證，未改模型）
A2: Tokenomics 基準 v21.1（master 4ef0b0a）。來源：chat 端查證筆記（Drive Tokenomics/證據研究/20261023_9a_chat端查證筆記.md）＋ PR #155 雲端 CC A 段（docs/evidence/20261023_Q側缺口_A段/）。
A3: 一句話結論：約 2 倍缺口主要是「OpenAI 實付算力單價高於 Tokenomics 持有成本」（價格因子約 1.4–2.2 倍），不是 Q 側（GW）錯誤；9a 不構成 token 帳修正。
A4: 1. 恆等式：B4_Serve 0.41＝84 ÷（84＋120），所以 9a 比值 1.94 ≈ 2025 全部算力支出 204 億 ÷（平均上線 GW 1.128 × 每 GW 持有成本 9.353）。見「三因子」。
A5: 2. 口徑因子約 1.0–1.27：外流查核財報（FT 核實）付 Microsoft 172.1 億（若含約 26 億營收分成，則算力為 146 億），加非 Microsoft 算力 14.5–44.5 億，2025 全部算力約 161–217 億，與 204 相容；Epoch 引的 160 億落在下界，不能據以說 204 高估 27%（見「衝突裁定」）。
A6: 3. GW 因子 0.89–1.11：官方年底 0.6→1.9 GW 內插平均 1.0–1.25；1.9 GW 依 Epoch 讀法已含 Azure。要讓價格＝持有成本，平均 GW 須約 1.7–2.3（「三因子」B15／B16，以查核帳 161–217 億計），證據不支持。
A7: 4. 所以價格因子是殘差，必須約 1.4–2.2（必須為真，見「三因子」第 13–14 列與「敏感度」；s 上限截在 1，不截則上端 2.32）。以 Microsoft 帳換一種切法（Azure 占 70–100% 情境），隱含每 GW·年為持有成本 1.38–2.33 倍、約每 GPU 小時 2.3–3.9 美元——與上句共用付 Microsoft 172.1 億，不是獨立證據。OpenAI 實付價的直接證據：無。
A8: 5. 與缺口恆等式相容（循環，非獨立印證）：若把模型的計價倍數 AL_SpendBasis 由 0.85 改為約 1.8（1.4–2.2），支出路線服務 GW 由 1.06 降到約 0.50，接近 GW 優先口徑 0.46——在 1.94 倍缺口下這是代數上必然。它說明 10-21 起「支出路線 GW 高估約 2 倍」與 9a 是同一件事：同一個價格假設。見「支出路線對照」。
A9: 6. 對模型的含義：主判讀（v20.0 起 GW 優先、全部算力持有成本）不受影響；受影響的是 AL_SpendBasis 0.85 及其對照列（Cap_In 第 109、218、255、343 列）。是否改值見「待判斷」J5（判斷類，另開版本）。
A10: 最強反證：找不到 OpenAI 實付每 GPU 小時；訓練多以 Microsoft 抵用額度支付（TechCrunch），若抵用額度以牌價入帳，價格因子部分是會計計價而非經濟成本——不改變「Q 側不是主因」，但會改變「OpenAI 真實算力成本」的讀法。
A11: 證偽條件：(a) OpenAI 2025 平均或季度 GW ≥ 1.8；(b) OpenAI 在 Azure 實付價 ≤ 2 美元／GPU 小時；(c) 付 Microsoft 172 億中有大額非算力項。
A12: 標記：[Verified] SEC／公司申報；[Verified-ish] 外流查核財報經 FT 核實；[Interested-party] 投資人資料、Zitron；[Derived] 本檔推算；[Assumed] 無依據。藍字＝輸入，黑字＝公式。

Sheet 輸入
A1: 輸入 | B1: 值 | C1: 單位 | D1: 標記 | E1: 來源／說明
A2: 平均上線 GW 2025（AL_FleetGW25） | B2: 1.127807 | C2: GW | D2: Derived | E2: TK v21.1 Cap_In C331：0.6→1.9 GW 指數內插（SRC_DEM_008／009，OpenAI，Interested-party）
A3: 平均上線 GW 低端 | B3: 1 | C3: GW | D3: Derived | E3: TK Cap_In D331（後段集中）
A4: 平均上線 GW 高端 | B4: 1.25 | C4: GW | D4: Derived | E4: TK Cap_In E331（線性）
A5: 每 GW 年持有成本（AL_FleetHold） | B5: 9.3531186 | C5: $B/GW·年 | D5: Derived | E5: TK v21.1：2025 機隊 Hopper 0.6／GB200 0.4
A6: 2025 推論支出（SRC_DEM_004） | B6: 8.4 | C6: $B | D6: Interested-party | E6: The Information（付費牆）經二手轉述；含免費 3.9
A7: 2025 訓練支出（SRC_DEM_006） | B7: 12 | C7: $B | D7: Interested-party | E7: 出處待補；外部最近值為 2025-09 預測「逾 90 億」
A8: 對外服務占機隊（B4_Serve） | B8: 0.41 | C8: 比例 | D8: Interested-party／Derived | E8: ＝84÷(84＋120) 四捨五入
A9: 付 Microsoft 合計 2025 | B9: 17.206 | C9: $B | D9: Verified-ish | E9: 外流查核財報（FT 核實）：營業成本 6.047＋研發 10.59＋行銷 0.527＋管理 0.042
A10: 其中可能為營收分成（若在帳內） | B10: 2.6 | C10: $B | D10: Assumed | E10: 20%×營收 13.07（20% 出自 Microsoft–OpenAI 協議的公開報導，The Register／om.co）；記帳位置未找到（可能為營收減項）
A11: 營業成本中非 Microsoft 部分 | B11: 1.45 | C11: $B | D11: Derived | E11: 7.5−6.047
A12: 研發中非 Microsoft 算力 低 | B12: 0 | C12: $B | D12: Assumed | E12: 研發 19.18−10.59＝8.59 含人員與股份酬勞（H1 約 25 億）
A13: 研發中非 Microsoft 算力 高 | B13: 3 | C13: $B | D13: Assumed | E13: 同上
... A22: Azure 占 OpenAI 平均算力（情境）高 | B22: 1 | C22: 比例 | D22: Assumed | E22: 同上

Sheet 三因子
A1: 項目 | B1: 值 | C1: 公式說明
A2: 服務 GW（TK） | B2: =輸入!B2*輸入!B8 -> 0.46240086 | C2: 平均 GW × B4_Serve
A3: 服務算力成本 $B | B3: =B2*輸入!B5 -> 4.3248901 | C3: × 持有成本
A4: 9a 比值（推論 ÷ 服務成本） | B4: =輸入!B6/B3 -> 1.9422459 | C4: 現行 1.94
A5: 全部算力 204 ÷ 全機隊持有成本 | B5: =(輸入!B6+輸入!B7)/(輸入!B2*輸入!B5) -> 1.933922 | C5: 恆等式：與 9a 只差 B4_Serve 四捨五入
A6: 兩者比 | B6: =B4/B5 -> 1.0043042 | C6: ＝(84/204)/0.41
A7: 查核帳全部算力 低 $B | B7: =輸入!B9-輸入!B10+輸入!B11+輸入!B12 -> 16.056 | C7: 付 MS 扣營收分成＋營業成本非 MS＋研發非 MS 低
A8: 查核帳全部算力 高 $B | B8: =輸入!B9+輸入!B11+輸入!B13 -> 21.656 | C8: 付 MS 全額＋非 MS 高
A9: 口徑 s 低（查核低 ÷ 204） | B9: =B7/(輸入!B6+輸入!B7) -> 0.78705882 | C9: s＝204 中屬當年算力費用比例
A10: 口徑 s 高（上限 1） | B10: =MIN(1,B8/(輸入!B6+輸入!B7)) -> 1
A11: GW 因子 低 | B11: =輸入!B3/輸入!B2 -> 0.88667655
A12: GW 因子 高 | B12: =輸入!B4/輸入!B2 -> 1.1083457
A13: 所需價格因子 低端（GW 高、s 低） | B13: =B5*B9/B12 -> 1.3733173 | C13: 總缺口 × s ÷ GW 因子
A14: 所需價格因子 高端（GW 低、s 上限） | B14: =B5*B10/B11 -> 2.1810907
A15: 若價格＝持有成本，所需平均 GW（用查核低） | B15: =B7/輸入!B5 -> 1.7166467
A16: 若價格＝持有成本，所需平均 GW（用查核高） | B16: =B8/輸入!B5 -> 2.3153775 | C16: 註：所需價格因子上端以 s 截在 1 計；不截為 2.32

Sheet 敏感度
A1: 所需價格因子＝總缺口×s÷GW 因子 | B1: GW 1.0 | C1: GW 1.128 | D1: GW 1.25 | E1: 說明
A2: 0.78 | B2: =三因子!$B$5*$A2/(輸入!B3/輸入!$B$2) -> 1.7012507 | C2: =三因子!$B$5*$A2/(輸入!B2/輸入!$B$2) -> 1.5084591 | D2: =三因子!$B$5*$A2/(輸入!B4/輸入!$B$2) -> 1.3610006 | E2: s 0.78＝Epoch 160÷204（被查核帳取代，僅對照）
A3: 0.85 | B3: =三因子!$B$5*$A3/(輸入!B3/輸入!$B$2) -> 1.8539271 | C3: =三因子!$B$5*$A3/(輸入!B2/輸入!$B$2) -> 1.6438337 | D3: =三因子!$B$5*$A3/(輸入!B4/輸入!$B$2) -> 1.4831417
A4: 0.92 | B4: =三因子!$B$5*$A4/(輸入!B3/輸入!$B$2) -> 2.0066034 | C4: =三因子!$B$5*$A4/(輸入!B2/輸入!$B$2) -> 1.7792082 | D4: =三因子!$B$5*$A4/(輸入!B4/輸入!$B$2) -> 1.6052828
A5: 1 | B5: =三因子!$B$5*$A5/(輸入!B3/輸入!$B$2) -> 2.1810907 | C5: =三因子!$B$5*$A5/(輸入!B2/輸入!$B$2) -> 1.933922 | D5: =三因子!$B$5*$A5/(輸入!B4/輸入!$B$2) -> 1.7448726
A7: 訓練支出敏感度（B4_Serve 隨之重算） | B7: 訓練 $B | C7: B4_Serve | D7: 9a 比值（GW 1.128）
B8: 4 | C8: =輸入!$B$6/(輸入!$B$6+B8) -> 0.67741935 | D8: =(輸入!$B$6+B8)/(輸入!$B$2*輸入!$B$5) -> 1.1755212
B9: 6 | C9: =輸入!$B$6/(輸入!$B$6+B9) -> 0.58333333 | D9: =(輸入!$B$6+B9)/(輸入!$B$2*輸入!$B$5) -> 1.3651214
B10: 8 | C10: =輸入!$B$6/(輸入!$B$6+B10) -> 0.51219512 | D10: =(輸入!$B$6+B10)/(輸入!$B$2*輸入!$B$5) -> 1.5547216
B11: 10 | C11: =輸入!$B$6/(輸入!$B$6+B11) -> 0.45652174 | D11: =(輸入!$B$6+B11)/(輸入!$B$2*輸入!$B$5) -> 1.7443218
B12: 12 | C12: =輸入!$B$6/(輸入!$B$6+B12) -> 0.41176471 | D12: =(輸入!$B$6+B12)/(輸入!$B$2*輸入!$B$5) -> 1.933922
B13: 14 | C13: =輸入!$B$6/(輸入!$B$6+B13) -> 0.375 | D13: =(輸入!$B$6+B13)/(輸入!$B$2*輸入!$B$5) -> 2.1235222
A15: Microsoft 帳隱含價格（Azure 占比情境） | B15: 付 MS 扣營收分成 | C15: 付 MS 全額
A16: 每 GPU 小時持有成本（TK，美元） | B16: =輸入!B5*1000000000/((輸入!B18*輸入!B16+(1-輸入!B18)*輸入!B17)*8760) -> 1.690652 | E16: 2025 機隊 GPU 加權
A17: =" Azure 占 "&TEXT(輸入!B20,"0%")&"：價格因子" -> Azure 占 70%：價格因子 | B17: =(輸入!$B$9-輸入!$B$10)/(輸入!$B$2*輸入!B20)/輸入!$B$5 -> 1.9780717 | C17: =輸入!$B$9/(輸入!$B$2*輸入!B20)/輸入!$B$5 -> 2.3301864
A18: =" Azure 占 "&TEXT(輸入!B21,"0%")&"：價格因子" -> Azure 占 85%：價格因子 | B18: =(輸入!$B$9-輸入!$B$10)/(輸入!$B$2*輸入!B21)/輸入!$B$5 -> 1.6290002 | C18: =輸入!$B$9/(輸入!$B$2*輸入!B21)/輸入!$B$5 -> 1.918977
A19: =" Azure 占 "&TEXT(輸入!B22,"0%")&"：價格因子" -> Azure 占 100%：價格因子 | B19: =(輸入!$B$9-輸入!$B$10)/(輸入!$B$2*輸入!B22)/輸入!$B$5 -> 1.3846502 | C19: =輸入!$B$9/(輸入!$B$2*輸入!B22)/輸入!$B$5 -> 1.6311305
A20: =" Azure 占 "&TEXT(輸入!B20,"0%")&"：每 GPU 小時（美元）" -> Azure 占 70%：每 GPU 小時（美元） | B20: =B17*$B$16 -> 3.3442309 | C20: =C17*$B$16 -> 3.9395343
A21: =" Azure 占 "&TEXT(輸入!B21,"0%")&"：每 GPU 小時（美元）" -> Azure 占 85%：每 GPU 小時（美元） | B21: =B18*$B$16 -> 2.7540725 | C21: =C18*$B$16 -> 3.2443223
A22: =" Azure 占 "&TEXT(輸入!B22,"0%")&"：每 GPU 小時（美元）" -> Azure 占 100%：每 GPU 小時（美元） | B22: =B19*$B$16 -> 2.3409616 | C22: =C19*$B$16 -> 2.757674

Sheet 支出路線對照
A1: 計價倍數 AL_SpendBasis | B1: 值 | C1: 支出路線服務 GW | D1: 說明（推論支出 ÷ 持有成本 ÷ 倍數）
A2: 現值 | B2: =輸入!B19 -> 0.85 | C2: =輸入!$B$6/輸入!$B$5/B2 -> 1.0565837
A3: 證據低端 | B3: 1.4 | C3: =輸入!$B$6/輸入!$B$5/B3 -> 0.64149727
A4: 中點 | B4: 1.8 | C4: =輸入!$B$6/輸入!$B$5/B4 -> 0.49894232
A5: 證據高端 | B5: 2.2 | C5: =輸入!$B$6/輸入!$B$5/B5 -> 0.40822553
A6: GW 優先服務 GW（TK L1_ServeGW_GW25） | C6: =三因子!B2 -> 0.46240086 | D6: 對照
A7: 外部服務 GW（10-21 token 帳 A 段） | C7: 0.5–0.63 | D7: 官方年底值內插 × 研發推論各半（Epoch）
A8: 註：TK Cap_In C109 現值 1.0566＝本表 C2（κ＝1）；利用率修正在第 218 列。0.50 接近 0.46 是 1.94 倍缺口下的代數結果，非獨立印證。

Sheet 證據
A1: 編號 | B1: 主張 | C1: 數值 | D1: 標記 | E1: 來源 | F1: 對因子的含義
A2: C1 | B2: OpenAI 2025 營業成本 7.5、研發 19.18、行銷 5.73、營收 13.07 $B | C2: 見主張 | D2: Verified-ish | E2: 外流查核財報，FT 核實（techstrong.ai 等轉述） | F2: 口徑：全部算力的上下界
A3: C2 | B3: 付 Microsoft 17.206 $B（營業成本 6.047、研發 10.59、行銷 0.527、管理 0.042） | C3: 17.206 | D3: Verified-ish | E3: TechFlow；Drive 20261017_推論支出調和分析 F5 | F3: 口徑；Microsoft 帳價格
A4: C3 | B4: Azure 推論 2025 Q1 2.075、Q2 2.947、Q3 3.648 $B | C4: 8.67 | D4: Interested-party | E4: Zitron 洩漏文件；The Register | F4: 含研究推論（10-17 分析）
A5: C4 | B5: Microsoft 認列 OpenAI 投資淨損失 FY26Q1 4.1 $B（前年同期 0.688） | C5: 4.1 | D5: Verified | E5: Microsoft 10-Q 2025-09-30（sec.gov） | F5: 總量對照（含非現金）
A6: C5 | B6: 隱含 OpenAI 單季淨損約 11.5（稅後÷27%）–15 $B | C6: 11.5–15 | D6: Derived | E6: heise；本檔 | F6: 總量對照
A7: C6 | B7: 2024 OpenAI 雲端算力約 7（研發 5、推論 1.8）$B | C7: 7 | D7: Interested-party | E7: Epoch AI（投資人文件） | F7: 歷史對照
A8: W2 | B8: 1.9 GW 為 2025 年底值；Epoch 讀為 IT 電力、含租用雲端（Microsoft、Oracle、CoreWeave） | C8: 1.9 | D8: 官方＋第三方推定 | E8: PR #155 W2_優先查證 W2-01–03 | F8: GW 因子不調
A9: W2 | B9: Azure 占 OpenAI 算力比例：已搜尋，未找到 | C9: — | D9: — | E9: PR #155 N 清單 | F9: Azure 占比為情境
A10: W1 | B10: 訓練 120 億：外部原文未找到；最近為 2025-09 預測「逾 90 億」 | C10: ≥9 | D10: Interested-party | E10: PR #155 W1-05／06（抽查：無法核對 94 億） | F10: J1 標出處待補
A11: W1 | B11: 84 億＝2025 推論成本（含免費 3.9、付費 4.5），調整後毛利 33% | C11: 8.4 | D11: Interested-party | E11: PR #155 W1-01（39／45 拆分未核對） | F11: 口徑
A12: W1 | B12: 訓練多以 Microsoft 抵用額度支付 | C12: — | D12: 媒體 | E12: PR #155 抽查 W1-11（TechCrunch） | F12: 價格可能含會計計價
A13: W3 | B13: OpenAI 實付每 GPU 小時、Microsoft 關聯方折扣：已搜尋，未找到 | C13: — | D13: — | E13: PR #155 N05 | F13: 價格因子無直接證據
A14: W3 | B14: Azure ND H100 v5 牌價：隨需 12.29、1 年預留 7.93、3 年預留 5.47 美元／GPU 小時 | C14: 12.29／7.93／5.47 | D14: 二手（Spheron 2026-05） | E14: PR #155 W3-06（抽查更正出處） | F14: 隱含 2.3–3.9 約為 3 年預留牌價 4–7 折
A15: W3 | B15: 新雲長約 ÷ TK 0.89–0.93；Oracle 2027 起 0.71–1.43；CoreWeave 全客戶約 1.07 | C15: 見主張 | D15: Derived | E15: PR #155 W3-01–09 | F15: 新世代／未來價，不作 2025 Azure 反證
A16: W4 | B16: Brockman：2026 算力支出 500 億；Epoch：為 2025 三倍（同一證詞） | C16: 50 | D16: Interested-party | E16: PR #155 W4-01／02 | F16: 2026 GW 無來源，不構成獨立驗證

Sheet 衝突裁定
A1: 議題 | B1: 說法 A | C1: 說法 B | D1: 裁定
A2: 口徑因子 | B2: PR #155：204 比 Epoch 160 高 27% → 口徑因子 1.28 | C2: chat 端：查核帳框出全部算力 161–217（付 MS 172.1，扣可能的營收分成 26 後 146；加非 MS 14.5–44.5） | D2: 部分採 B：160 落在查核帳下界（營收分成在帳內、研發無非 MS 算力時），不構成「204 高估 27%」的證據；s 取 0.79–1.0。chat 端 21:25 曾寫「172–210、160 已被取代」，下界算錯，已更正。
A3: 價格因子 | B3: PR #155：間接 0.71–1.43（長約、Oracle、CoreWeave） | C3: chat 端：必須為真 1.37–2.18；Microsoft 帳另一切法 1.38–2.33（共用 172.1 億，非獨立） | D3: 採 B：A 的證據為新世代／未來價或全客戶平均；2025 OpenAI 在 Azure 以 Hopper 為主、可能含隨需與抵用額度計價。保留「無實付價直接證據」為最強反證。
A4: B4_Serve 分母 | B4: PR #155 J2：204 高於 160，是否調整 | C4: chat 端：與查核帳相容 | D4: 維持 0.41（J2 預設）。

Sheet 待判斷
A1: 編號 | B1: 事項 | C1: 建議預設（未回應即採用，可撤回） | D1: 替代
A2: J1 | B2: SRC_DEM_006 訓練 120 億 | C2: 只標「出處待補；外部最近為 2025-09 預測逾 90 億」，數值不改 | D2: 改 9–12 區間
A3: J2 | B3: B4_Serve 0.41 是否因 160 億調整 | C3: 維持；204 在查核帳區間內 | D3: 改用 Epoch 2024 比例 0.265
A4: J3 | B4: 9a 是否構成 Q 側修正 | C4: 不構成；交接檔 9a 結案為「價格因子」，Q 側證據優先序回到 m／利用率 | D4: 保留 9a 待 OpenAI 實付價出現
A5: J4 | B5: GW 因子 | C5: 維持 1.128（已定） | D5: —
A6: J5 | B6: 計價倍數 AL_SpendBasis 0.85 | C6: 下一版（另開，建置前再問）改基準 1.8、區間 0.85–2.3（證據 1.4–2.2），標 Derived（查核帳＋必須為真），只影響支出路線對照列與缺口恆等式 | D6: 維持 0.85、只加註；或等 OpenAI 實付價

Sheet 方向與涵蓋
A1: 方向檢核（第 10 條）：(1) 1.9 GW 含 Azure——採 Epoch 讀法，收窄（排除「漏算 Azure」）；(2) 160 vs 查核帳——保留（s 取 0.79–1.0，含 160 對應的下界）；(3) Microsoft 自家產品推論不在 84 億——收窄；(4) 抵用額度計價——保留兩種讀法；(5) Azure 占比——保留為 70–100% 情境。收窄 2、保留 3。
A2: 涵蓋檢核（第 11 條）：[A] 會計恆等式（B4_Serve 代入、查核帳上下界）已做；[P] GW 端點與每 GPU 小時換算已做；[I] 關聯方定價、抵用額度、投資人資料誘因已列，實付價未找到。未做：OpenAI 非 Microsoft 供應商 2025 實付（CoreWeave、Oracle 2025 交付量與收入）——SEC 申報未點名到可換算程度，列為下一步。
A3: 獨立核對：見 repo 同資料夾「獨立核對報告.md」（未參與代理；數值 0 不符，文字 5 項＋說明 1 項已依建議修正）。未核對：Epoch 16（頁面拒抓）、Azure 8.67 原頁（只核算術）。
