Workbook

Sheet README
A1: Tokenomics v5.2 — Block 1＋2：機架規格、每 GW 成本、各層級產出與每 token 成本
A2: 第 0 層規格來源。理論營收於 Block 4 加入。
A4: 用途 | B4: 回答：每 1 GW IT 電力，各世代可容納多少機架、資本支出與持有成本（Block 1），以及在各層級 SLO 下的產出、依『世代 × 層級 × token 類型』的每 M token 成本（Block 2）。不含營收（Block 4）。
A5: 版本 | B5: 20260930_Tokenomics_v5.2（Block 1＋Block 2；v5.2 加第二來源驗證與生產折減輸入）。v4 的 Config／TL_Param／WP_Param／Revenue_Model 由 Arch、Serving、Workload、Calib、Perf、Unit_Cost 取代。
A6: 電力口徑 | B6: GW＝IT 關鍵電力（Andy 2026-09-30 確認）。設施電力＝IT × PUE，於 DC_Cost 與 Interface 並列。
A7: 工作表 | B7: Inputs → Spec_Rack → Arch → Serving → Workload → Calib → Perf → Sens_Perf → Unit_Cost → DC_Cost → Interface；Energy、NonNV、Sensitivity、Checks、Sources。
A8: Block 2 推導 | B8: prefill：tok/s＝η_p × 峰值 ÷ FLOPs/token。decode：每步時間＝固定延遲（權重讀取＋每層延遲 ×（層數＋草稿數））＋B × 每序列時間；在 SLO 下解出批次 B*，再受 HBM 容量限制。η_d 與每層延遲由 GB300 同一前緣兩點聯立解出（Calib）。
A9: 成本情境 | B9: 低成本／基準／高成本為角落情境。單一變數影響看 Sensitivity（Block 1）與 Sens_Perf（Block 2）。
A10: 功率情境 | B10: Inputs!E6 選 1／2／3，決定每架配電設計功率與每 GW 機架數。
A11: 顏色 | B11: 藍字＝輸入；黑字＝公式；綠字＝跨頁連結；淡黃底＝關鍵輸出；亮黃底＝待 Andy 決定或情境改動。
A12: 來源標記 | B12: Verified／Interested-party／Analogy／Assumed／Derived。Analogy 與 Assumed 一律給區間。
A13: 網站同步 | B13: 本檔為事實來源；repo 以公式引擎直接計算本檔，parity 測試比對 Interface 全部格（新增 IF_ 具名範圍見 Interface B 節）。
A14: 來源原則 | B14: SemiAnalysis（含 InferenceX）資料一律須有第二來源佐證並標記 Interested-party；目前第二來源為 MLPerf（MLCommons 稽核，NVIDIA 提交）與 DeepSeek 自揭（待查）。
A15: 未結事項 | B15: (1) VR200 報價是否含網路（S11）。(2) 所有來源待 Andy 查核。(3) Rubin Ultra 為推估。(4) J6 基準利用率暫用 60%、生產折減暫用 1.0，皆待 Andy 給值。(5) VR200 無實測，η_d 與每層延遲沿用 GB300。(6) 交接錨點 6,182 屬舊軟體（vLLM 無 MTP），已改為 GB300 最新前緣兩點校準。(7) 快取命中只計載入時間，未計儲存成本。

Sheet Inputs
A1: Inputs — 全域輸入（藍字可改）
A2: 低成本／基準／高成本為角落情境；單值輸入只填基準欄
A3: 參數 | B3: 單位 | D3: 低成本 | E3: 基準 | F3: 高成本 | G3: 標記 | H3: 來源／說明
A4: 控制
A5: IT 電力規模 | B5: GW | D5: =E5 -> 1 | E5: 1 | F5: =E5 -> 1 | G5: Decision | H5: 口徑：IT 關鍵電力
A6: 功率情境（1 低／2 基準／3 高） | B6: 選擇 | D6: =E6 -> 2 | E6: 2 | F6: =E6 -> 2 | G6: Decision | H6: 決定每架配電設計功率；見 Spec_Rack 第 9–11 列
A7: 規模與電力
A8: 機架外 IT 電力占比 | B8: % | D8: =E8 -> 0.08 | E8: 0.08 | F8: =E8 -> 0.08 | G8: Assumed | H8: 管理、儲存、網路機櫃等；區間 5–12%（見 Sensitivity）。v4 未計
A9: PUE | B9: x | D9: 1.1 | E9: 1.2 | F9: 1.3 | G9: Analogy | H9: 液冷 AI 設施；v4＝1.2。S14
A10: 平均用電 ÷ 配電設計功率 | B10: % | D10: 0.7 | E10: 0.8 | F10: 0.9 | G10: Assumed | H10: Block 2 以逐步能量模型閉合檢查
A11: 電價 | B11: $/kWh | D11: 0.06 | E11: 0.08 | F11: 0.1 | G11: Verified/Analogy | H11: EIA 美國工業電價 2026 年約 8.6–8.7¢（S13）；低端為 PPA（v4＝0.06）
A12: IT 設備（機架以外）
A13: Scale-out 網路 ÷ 機架價格 | B13: % | D13: 0.05 | E13: 0.1 | F13: 0.15 | G13: Analogy | H13: 1,024 GPU 叢集網路約為 GPU BOM 4–8%（S10）；GW 級多一層以上交換，取 5–15%
A14: 儲存與管理設備 | B14: $/GPU | D14: 300 | E14: 500 | F14: 800 | G14: Assumed | H14: v4 約 $350/GPU（$25K/架）
A15: 廠房（每 MW IT，$M）
A16: 土地 | B16: $M/MW | D16: 0.02 | E16: 0.02 | F16: 0.02 | G16: Assumed | H16: v4：100 英畝 × $200K／GW
A17: 建物與基地工程 | B17: $M/MW | D17: 3 | E17: 3.6 | F17: 4.5 | G17: Assumed | H17: 分項為假設；總額以 JLL 校準（S12）
A18: 電力設施（變電、中壓、發電機、UPS） | B18: $M/MW | D18: 3.8 | E18: 4.5 | F18: 5.5 | G18: Assumed | H18: 同上
A19: 機械與散熱（液冷迴路、散熱設備） | B19: $M/MW | D19: 2 | E19: 2.5 | F19: 3.2 | G19: Assumed | H19: 機架內冷板與 manifold 含在機架價格
A20: 光纖、佈線、保全、BMS | B20: $M/MW | D20: 0.3 | E20: 0.4 | F20: 0.5 | G20: Assumed | H20: 同上
A21: 設計、管理與預備費 | B21: % 廠房 | D21: 0.12 | E21: 0.15 | F21: 0.18 | G21: Assumed | H21: v4＝15%
A22: 年限與資金成本
A23: IT 設備折舊年限 | B23: 年 | D23: 6 | E23: 6 | F23: 4 | G23: Verified | H23: CoreWeave 與主要 hyperscaler 6 年；Nebius 4 年、Lambda 5 年（S15）。高成本情境取 4
A24: 建物年限 | B24: 年 | D24: =E24 -> 30 | E24: 30 | F24: =E24 -> 30 | G24: Analogy | H24: v4
A25: 電力設施年限 | B25: 年 | D25: =E25 -> 20 | E25: 20 | F25: =E25 -> 20 | G25: Analogy | H25: v4
A26: 機械與散熱年限 | B26: 年 | D26: =E26 -> 15 | E26: 15 | F26: =E26 -> 15 | G26: Analogy | H26: v4
A27: 光纖與保全年限 | B27: 年 | D27: =E27 -> 10 | E27: 10 | F27: =E27 -> 10 | G27: Analogy | H27: v4
A28: WACC（經濟口徑） | B28: % | D28: 0.08 | E28: 0.1 | F28: 0.13 | G28: Assumed | H28: 與擁有者無關的單一假設；下游公司模型以自身 WACC 覆寫（Andy 2026-09-30 決定）
A29: 營運費用
A30: IT 維護 | B30: % IT 資本/年 | D30: 0.02 | E30: 0.03 | F30: 0.04 | G30: Analogy | H30: v4＝3%
A31: 廠房維護 | B31: % 廠房資本/年 | D31: 0.015 | E31: 0.02 | F31: 0.025 | G31: Analogy | H31: v4＝2%
A32: 人員 | B32: $M/GW/年 | D32: 50 | E32: 75 | F32: 100 | G32: Assumed | H32: v4：500 FTE × $150K
A33: 軟體授權與連線 | B33: $M/GW/年 | D33: 150 | E33: 200 | F33: 250 | G33: Assumed | H33: v4＝$200M
A34: 水與耗材 | B34: $M/MW/年 | D34: 0.04 | E34: 0.05 | F34: 0.06 | G34: Assumed | H34: v4＝$50K/MW
A35: 財產稅與保險 | B35: % 總資本/年 | D35: 0.003 | E35: 0.005 | F35: 0.008 | G35: Analogy | H35: v4＝0.5%

Sheet Spec_Rack
A1: Spec_Rack — 各世代機架規格（Block 1 只含功率與價格；效能規格於 Block 2 加入）
A2: 價格為買方取得價（CSP/hyperscaler 口徑）；Hopper 以 4 台 HGX 構成一架（32 GPU）以便比較
A4: 世代 | C4: Hopper H100 | D4: GB200 NVL72 | E4: GB300 NVL72 | F4: VR200 NVL72 | G4: Rubin Ultra NVL576 | H4: 標記／來源
A5: 平台／出貨 | C5: HGX ×4（32 GPU） | D5: 2024–25 出貨 | E5: 2025–26 主力 | F5: 2026 下半年開始出貨 | G5: 2027 預估（Kyber）
A6: GPU 封裝／架 | C6: 32 | D6: 72 | E6: 72 | F6: 72 | G6: 144
A7: 冷卻 | C7: 氣冷 | D7: 液冷 | E7: 液冷 | F7: 液冷（必須） | G7: 液冷
A8: 配電設計功率 低（kW） | C8: 38 | D8: 120 | E8: 132 | F8: 190 | G8: 550
A9: 配電設計功率 基準（kW） | C9: 41 | D9: 130 | E9: 137 | F9: 227 | G9: 600
A10: 配電設計功率 高（kW） | C10: 44 | D10: 140 | E10: 142 | F10: 230 | G10: 650
A11: 機架價格 低（$M） | C11: 0.9 | D11: 2.8 | E11: 4 | F11: 6.7 | G11: 23.4
A12: 機架價格 基準（$M） | C12: 1.1 | D12: 3.1 | E12: 5 | F12: 7.8 | G12: 31.2
A13: 機架價格 高（$M） | C13: 1.3 | D13: 3.4 | E13: 6.5 | F13: 9.1 | G13: 39
A14: 價格涵蓋範圍 | C14: 8 GPU 伺服器 + CPU、NIC、機內儲存；以部署當時取得價計 | D14: 運算匣＋NVLink 交換匣＋機架內冷卻 | E14: 同上 | F14: 運算匣＋交換匣＋冷卻＋約 $1M NAND；是否含部分網路待查（S11） | G14: 144 封裝；價格＝VR 每 GPU 價 × 1.5／2.0／2.5（推估）
A15: 功率來源 | C15: DGX H100 最大 10.2 kW／8 GPU（S1） | D15: 約 120–130 kW（S3）；v4＝139 | E15: 132–142 kW（S3、S5） | F15: Max-Q 約 190、Max-P 約 230 kW（S7）；Supermicro DLC-2 設計點 227 kW（S8） | G15: 約 600 kW（S7）
A16: 價格來源 | C16: HGX H100 8 GPU 伺服器約 $220–320K（S2，弱證據） | D16: $2.8–3.4M（S4）；Barron's 約 $3M | E16: MS 約 $4M；2026-08 採購單約 $5M；媒體 $6–6.5M（S4、S6） | F16: MS $7.8M（自購記憶體 $6.7M）；Bernstein $9.09M；報價 $5–7M（S9） | G16: 無公開報價；純推估，不進基準比較
A17: 標記 | C17: Analogy | D17: Interested-party | E17: Interested-party | F17: Interested-party | G17: Assumed
A19: 註：GPU 數為封裝數（Rubin Ultra 為 144 封裝，NVIDIA 以 576 die 命名為 NVL576）。
A21: B2. 效能規格（Block 2；藍字＝輸入；每 GPU 封裝）
A22: 服務精度 | C22: FP8 | D22: NVFP4 | E22: NVFP4 | F22: NVFP4 | G22: NVFP4 | H22: Hopper 不支援 FP4，以 FP8 服務
A23: 峰值 dense（基準）PF/GPU | C23: 0.989 | D23: 10 | E23: 15 | F23: 35 | G23: 73 | H23: Interested-party（NVIDIA 規格）：H100 FP8 989 TF；GB200 FP4 10 PF（HGX B200 為 9）；B300 15；Rubin NVFP4 訓練 35；RU＝104×35/50 推估 [Derived]。S28
A24: 峰值（高情境：NVFP4 推論口徑）PF/GPU | C24: 0.989 | D24: 10 | E24: 15 | F24: 50 | G24: 104 | H24: Rubin 50 PF 含自適應壓縮；RU NVL576 15 EF ÷ 144。J2：只作高情境
A25: HBM 容量 GB/GPU | C25: 80 | D25: 186 | E25: 288 | F25: 288 | G25: 1024 | H25: GB200 NVL72 13.4 TB ÷ 72；InferenceX 以 192 計。RU HBM4e 約 1 TB/封裝。S28
A26: HBM 頻寬 TB/s/GPU | C26: 3.35 | D26: 8 | E26: 8 | F26: 22 | G26: 32 | H26: Rubin 22 TB/s（NVIDIA 2026 上修）；RU 4.6 PB/s ÷ 144。S28
A27: EP 通訊頻寬 TB/s/GPU（單向） | C27: 0.05 | D27: 0.9 | E27: 0.9 | F27: 1.8 | G27: 1.8 | H27: Hopper EP 跨節點走 400G IB；NVLink 5＝900 GB/s；NVLink 6＝1.8 TB/s（InferenceX 規格表 S20）；RU 取同 VR [Assumed]
A28: Scale-up 域 GPU 數 | C28: 8 | D28: 72 | E28: 72 | F28: 72 | G28: 144
A29: decode EP 基準寬度 | C29: 64 | D29: 32 | E29: 32 | F29: 32 | G29: 64 | H29: GB300 公開配方 dep32（S21）；Hopper 跨節點 [Analogy DeepSeek]；RU [Assumed]。權重放不下時自動加寬
A30: 專家權重 bytes/param | C30: 1 | D30: 0.5625 | E30: 0.5625 | F30: 0.5625 | G30: 0.5625 | H30: NVFP4＝4 bit＋每 16 值 8 bit scale＝0.5625 B；Hopper FP8
A31: 非專家權重 bytes/param | C31: 1 | D31: 1 | E31: 1 | F31: 1 | G31: 1 | H31: 注意力、路由、embedding 以 FP8 存放 [Analogy V4]
A32: 每 prefill 實例 GPU 數（算 TTFT） | C32: 8 | D32: 4 | E32: 4 | F32: 4 | G32: 8 | H32: GB300 配方 dep4 prefill（S21）
A33: GPU 功率 W/封裝（能量用） | C33: 700 | D33: 1200 | E33: 1400 | F33: 1800 | G33: 3600 | H33: Interested-party；Rubin 約 1.8 kW、RU 推估。僅用於能量下限估算
A34: HBM 存取能量 pJ/byte | C34: 31 | D34: 25 | E34: 25 | F34: 20 | G34: 18 | H34: Analogy：HBM3 約 3.9 pJ/bit、HBM3e 約 3、HBM4 約 2.5；區間 ±30%（S29）
A35: 計算用峰值 PF/GPU（依 Serving 峰值情境） | C35: =IF(Serving!$C$16=2,C24,C23) -> 0.989 | D35: =IF(Serving!$C$16=2,D24,D23) -> 10 | E35: =IF(Serving!$C$16=2,E24,E23) -> 15 | F35: =IF(Serving!$C$16=2,F24,F23) -> 35 | G35: =IF(Serving!$C$16=2,G24,G23) -> 73
A36: Ridge point（FLOP/byte） | C36: =C35*1000/C26 -> 295.22388 | D36: =D35*1000/D26 -> 1250 | E36: =E35*1000/E26 -> 1875 | F36: =F35*1000/F26 -> 1590.9091 | G36: =G35*1000/G26 -> 2281.25

Sheet Arch
A1: Arch — 三層級代表架構（D5：每層級一個代表；參數為公開模型卡或推估）
A2: Luna／Sol 以公開權重模型為物理代表 [Analogy：對應封閉層級]；Astra 為封閉前沿代理，KV 以情境處理（J1）
A4: 參數 | B4: 單位 | C4: Luna（低層） | D4: Sol（中層） | E4: Astra（頂層） | F4: 標記 | G4: 來源／說明
A5: 代表架構 | C5: DeepSeek V4-Flash 類 | D5: DeepSeek V4-Pro 類 | E5: 封閉前沿代理 | F5: Decision | G5: D5；Andy 2026-09-30 確認
A6: 總參數 | B6: B | C6: 284 | D6: 1600 | E6: 4000 | F6: Verified／Assumed | G6: V4-Flash 284B、V4-Pro 1.6T（模型卡，S27）；Astra 4T [Assumed，區間 2–10T]
A7: 啟用參數 | B7: B | C7: 13 | D7: 49 | E7: 180 | F7: Verified／Assumed | G7: V4-Flash 13B、V4-Pro 49B；Astra 180B [Assumed，區間 60–250B]
A8: 層數 | B8: 層 | C8: 43 | D8: 61 | E8: 100 | F8: Verified／Assumed | G8: V4-Pro 61（config.json）；V4-Flash 43（二手）；Astra [Assumed]
A9: d_model | C9: 4096 | D9: 7168 | E9: 12288 | F9: Verified／Derived | G9: V4-Pro 7168；V4-Flash 由專家維度反推；Astra [Assumed]
A10: query heads | C10: 64 | D10: 128 | E10: 96 | F10: Verified／Analogy | G10: V4-Pro 128；V4-Flash 取 Pro 一半 [Analogy]
A11: head_dim | C11: 512 | D11: 512 | E11: 128 | F11: Verified／Assumed | G11: V4 單一 512 維 KV head；Astra 128
A12: routed experts | C12: 256 | D12: 384 | E12: 512 | F12: Verified／Assumed
A13: 每 token 啟用 routed experts | C13: 6 | D13: 6 | E13: 16 | F13: Verified／Assumed
A14: shared experts | C14: 1 | D14: 1 | E14: 1 | F14: Verified
A15: vocab | C15: 129280 | D15: 129280 | E15: 200000 | F15: Verified／Assumed
A16: 全注意力層比例 | B16: % | C16: 0.5 | D16: 0.5 | E16: 1 | F16: Verified／Assumed | G16: V4：CSA 與 HCA 約各半；Astra 全層注意力
A17: 全注意力層跨度上限（0＝全上下文） | B17: tok | C17: 4224 | D17: 4224 | E17: 0 | F17: Derived | G17: V4 CSA：top-k 1,024 壓縮塊 × 4 ＋ 128 窗口
A18: 其他層壓縮比 | B18: x | C18: 128 | D18: 128 | E18: 1 | F18: Verified | G18: V4 HCA 128× 壓縮
A19: 其他層滑動窗 | B19: tok | C19: 128 | D19: 128 | E19: 0 | F19: Verified
A20: Astra KV 情境（1 混合／2 全層 MLA／3 GQA-8） | B20: 選擇 | E20: 2 | F20: Decision | G20: J1：基準 2（Andy 2026-09-30 確認）
A21: KV bytes/token — 情境 1 | B21: B | C21: 2795 | D21: 3965 | E21: 14976 | F21: Derived／Assumed | G21: Luna 65×43、Sol 65×61（v4 推導，FP8 KV）；Astra 混合：26% 層 × 576 × 100 層（類 K3）
A22: KV bytes/token — 情境 2 | B22: B | C22: 2795 | D22: 3965 | E22: 57600 | F22: Derived／Assumed | G22: Astra 全層 MLA：576 × 100
A23: KV bytes/token — 情境 3 | B23: B | C23: 2795 | D23: 3965 | E23: 204800 | F23: Derived／Assumed | G23: Astra GQA-8：8 × 128 × 2 × 100
A24: 導出
A25: KV bytes/token（採用） | B25: B | C25: =CHOOSE(IF(C20="",1,C20),C21,C22,C23) -> 2795 | D25: =CHOOSE(IF(D20="",1,D20),D21,D22,D23) -> 3965 | E25: =CHOOSE(IF(E20="",1,E20),E21,E22,E23) -> 57600
A26: Embedding＋LM head 參數 | B26: B | C26: =C15*C9*2/1000000000 -> 1.0590618 | D26: =D15*D9*2/1000000000 -> 1.8533581 | E26: =E15*E9*2/1000000000 -> 4.9152
A27: 每 routed expert 參數 | B27: B | C27: =(C6-C7)/(C8*(C12-C13)) -> 0.025209302 | D27: =(D6-D7)/(D8*(D12-D13)) -> 0.067265157 | E27: =(E6-E7)/(E8*(E12-E13)) -> 0.077016129 | G27: 由公開總參數與啟用參數反推，確保總數吻合（v4 方法）
A28: 非專家參數（注意力、路由、embedding） | B28: B | C28: =C7-C8*(C13+C14)*C27 -> 5.412 | D28: =D7-D8*(D13+D14)*D27 -> 20.277778 | E28: =E7-E8*(E13+E14)*E27 -> 49.072581
A29: 專家參數 | B29: B | C29: =C6-C28 -> 278.588 | D29: =D6-D28 -> 1579.7222 | E29: =E6-E28 -> 3950.9274
A30: 注意力 FLOPs／每個被注意的 token | B30: FLOP | C30: =4*C10*C11*C8 -> 5636096 | D30: =4*D10*D11*D8 -> 15990784 | E30: =4*E10*E11*E8 -> 4915200
A31: 128K 上下文每序列 KV | B31: GB | C31: =C25*128000/1000000000 -> 0.35776 | D31: =D25*128000/1000000000 -> 0.50752 | E31: =E25*128000/1000000000 -> 7.3728

Sheet Serving
A1: Serving — 服務設定與各層級 SLO（主流：分離式 P/D、wide EP、attention DP、NVFP4、MTP、前綴快取）
A2: 藍字＝輸入。SLO 依 J3 採市場觀測輸出速度（Artificial Analysis 2026-09，S26）
A4: 全域設定 | B4: 單位 | C4: 值 | D4: 標記 | F4: 說明
A5: 服務架構 | C5: 分離式 P/D＋wide EP＋attention DP | D5: Decision | F5: D6 與 Block 2 命題
A6: MTP 草稿數 N | B6: tok | C6: 3 | D6: Analogy | F6: DeepSeek MTP；區間 1–5
A7: 每個草稿 token 接受率 α | B7: % | C7: 0.7 | D7: Verified-measured | F7: SGLang 修正後 0.57→0.70（S21）；區間 0.6–0.8
A8: 每步期望接受 token a | B8: tok | C8: =(1-C7^(C6+1))/(1-C7) -> 2.533 | D8: Derived | F8: (1−α^(N+1))/(1−α)
A9: HBM 保留比例（啟用值、工作區） | B9: % | C9: 0.1 | D9: Assumed | F9: 區間 5–20%
A10: 非專家權重占可用 HBM 上限 | B10: % | C10: 0.2 | D10: Assumed | F10: 超過時自動以注意力 TP 切分
A11: 專家權重占可用 HBM 上限 | B11: % | C11: 0.4 | D11: Assumed | F11: 超過時自動加寬 EP
A12: EP 啟用值 bytes/元素（dispatch＋combine） | B12: B | C12: 3 | D12: Analogy | F12: FP8 dispatch 1 B＋BF16 combine 2 B
A13: KV 讀取頻寬效率 η_mem | B13: % | C13: 0.7 | D13: Analogy | F13: 區間 0.5–0.85
A14: EP 通訊效率 η_link | B14: % | C14: 0.7 | D14: Analogy | F14: 區間 0.5–0.85
A15: 快取命中 KV 載入頻寬 | B15: TB/s/GPU | C15: 0.1 | D15: Assumed | F15: 主機記憶體／SSD 經 NIC 載入；區間 0.05–0.4。未計快取儲存成本
A16: 峰值情境（1＝dense 基準／2＝NVFP4 推論高） | B16: 選擇 | C16: 1 | D16: Decision | F16: J2：基準 1
A17: 基準利用率（第 0 層） | B17: % | C17: 0.6 | D17: Assumed | F17: J6：Andy 尚未給值，暫沿用 OpenAI v0.5 的 60%（區間 40–80%）。Unit_Cost 同時輸出 100% 版
A18: 實測→生產效率折減 | B18: x | C18: 1 | D18: Assumed | F18: 待 Andy 決定。基準測試為固定長度、穩態負載；生產環境另有長度變異、路由不均、故障。1.0＝不折減。作用：η_p、η_d 乘此值，每層延遲除以此值。第二來源（MLPerf、DeepSeek 自揭）目前均高於本模型，見 Calib H 節
A19: 各層級 SLO 與參考任務
A20: 項目 | B20: 單位 | C20: =Arch!C4 -> Luna（低層） | D20: =Arch!D4 -> Sol（中層） | E20: =Arch!E4 -> Astra（頂層） | F20: 說明
A21: SLO：每用戶 decode 速度下限 | B21: tok/s | C21: 120 | D21: 65 | E21: 55 | F21: Verified-measured（市場觀測）：GPT-5.6 Luna 約 120、GPT-5.6 Sol 約 68、GPT-6 Astra 約 52–56、Opus 5 約 54 tok/s（S26）。區間 Luna 100–300、Sol 50–100、Astra 30–75
A22: TTFT 上限（只作檢查） | B22: s | C22: 2 | D22: 3 | E22: 5 | F22: Assumed
A23: 參考 ISL（每次請求輸入） | B23: tok | C23: 8192 | D23: 16384 | E23: 32768 | F23: Assumed：Astra 用於長任務；上下文敏感度見 Sens_Perf
A24: 參考 OSL（含思考） | B24: tok | C24: 1024 | D24: 2048 | E24: 4096 | F24: Assumed
A25: decode 平均上下文 | B25: tok | C25: =C23+C24/2 -> 8704 | D25: =D23+D24/2 -> 17408 | E25: =E23+E24/2 -> 34816 | F25: Derived
A26: prefill 平均位置 | B26: tok | C26: =C23/2 -> 4096 | D26: =D23/2 -> 8192 | E26: =E23/2 -> 16384 | F26: Derived

Sheet Workload
A1: Workload — 任務制工作負載（每任務的 token 結構；思考 token 在物理上屬 decode）
A2: 任務組合權重不在第 0 層（J5）；本頁只定義標準任務。harness token 倍數預設 1.0，Block 5 接手
A4: 參數 | B4: 單位 | C4: 一般聊天 | D4: 推理聊天 | E4: 單代理（工具迴圈） | F4: 多代理研究 | G4: Coding agent（長程） | H4: 說明
A5: 輪數 T | B5: 輪 | C5: 1 | D5: 1 | E5: 4 | F5: 4 | G5: 30 | H5: Assumed
A6: 初始上下文 S（系統提示、歷史、工具定義） | B6: tok | C6: 2000 | D6: 2000 | E6: 3000 | F6: 3000 | G6: 12000 | H6: Assumed
A7: 每輪新輸入 u（使用者或工具結果） | B7: tok | C7: 500 | D7: 500 | E7: 1200 | F7: 1200 | G7: 2000 | H7: Assumed
A8: 每輪思考 token h | B8: tok | C8: 0 | D8: 3000 | E8: 400 | F8: 400 | G8: 600 | H8: Assumed；服務端思考占比待查
A9: 每輪可見輸出 o | B9: tok | C9: 500 | D9: 700 | E9: 200 | F9: 200 | G9: 400 | H9: Assumed
A10: 思考保留於上下文比例 ρ | B10: % | C10: 0 | D10: 0 | E10: 0 | F10: 0 | G10: 0 | H10: Assumed：多數 API 不保留前輪思考
A11: 歷史快取命中率 χ | B11: % | C11: 0.5 | D11: 0.5 | E11: 0.9 | F11: 0.9 | G11: 0.9 | H11: Assumed；代理迴圈前綴重用高
A12: 並行子代理數 m | B12: 個 | C12: 0 | D12: 0 | E12: 0 | F12: 3 | G12: 0 | H12: Assumed：子代理沿用單代理參數
A13: harness token 倍數 | B13: x | C13: 1 | D13: 1 | E13: 1 | F13: 1 | G13: 1 | H13: 預設 1.0（Block 5）
A15: 導出（每任務）
A16: 每輪上下文增量 u＋o＋ρh | B16: tok | C16: =C7+C9+C10*C8 -> 1000 | D16: =D7+D9+D10*D8 -> 1200 | E16: =E7+E9+E10*E8 -> 1400 | F16: =F7+F9+F10*F8 -> 1400 | G16: =G7+G9+G10*G8 -> 2400
A17: 單代理輸入總量 | B17: tok | C17: =C5*(C6+C7)+C16*C5*(C5-1)/2 -> 2500 | D17: =D5*(D6+D7)+D16*D5*(D5-1)/2 -> 2500 | E17: =E5*(E6+E7)+E16*E5*(E5-1)/2 -> 25200 | F17: =F5*(F6+F7)+F16*F5*(F5-1)/2 -> 25200 | G17: =G5*(G6+G7)+G16*G5*(G5-1)/2 -> 1464000
A18: 其中可快取（前綴） | B18: tok | C18: =C11*(C5*C6+C16*C5*(C5-1)/2) -> 1000 | D18: =D11*(D5*D6+D16*D5*(D5-1)/2) -> 1000 | E18: =E11*(E5*E6+E16*E5*(E5-1)/2) -> 18360 | F18: =F11*(F5*F6+F16*F5*(F5-1)/2) -> 18360 | G18: =G11*(G5*G6+G16*G5*(G5-1)/2) -> 1263600
A19: 其中新鮮 | B19: tok | C19: =C17-C18 -> 1500 | D19: =D17-D18 -> 1500 | E19: =E17-E18 -> 6840 | F19: =F17-F18 -> 6840 | G19: =G17-G18 -> 200400
A20: 單代理 decode（思考＋可見） | B20: tok | C20: =C5*(C8+C9) -> 500 | D20: =D5*(D8+D9) -> 3700 | E20: =E5*(E8+E9) -> 2400 | F20: =F5*(F8+F9) -> 2400 | G20: =G5*(G8+G9) -> 30000
A21: 系統倍數（1＋m）× harness | B21: x | C21: =(1+C12)*C13 -> 1 | D21: =(1+D12)*D13 -> 1 | E21: =(1+E12)*E13 -> 1 | F21: =(1+F12)*F13 -> 4 | G21: =(1+G12)*G13 -> 1
A22: 任務新鮮 prefill | B22: tok | C22: =C19*C21 -> 1500 | D22: =D19*D21 -> 1500 | E22: =E19*E21 -> 6840 | F22: =F19*F21 -> 27360 | G22: =G19*G21 -> 200400
A23: 任務快取 prefill | B23: tok | C23: =C18*C21 -> 1000 | D23: =D18*D21 -> 1000 | E23: =E18*E21 -> 18360 | F23: =F18*F21 -> 73440 | G23: =G18*G21 -> 1263600
A24: 任務 decode | B24: tok | C24: =C20*C21 -> 500 | D24: =D20*D21 -> 3700 | E24: =E20*E21 -> 2400 | F24: =F20*F21 -> 9600 | G24: =G20*G21 -> 30000
A25: 任務總 token | B25: tok | C25: =C22+C23+C24 -> 3000 | D25: =D22+D23+D24 -> 6200 | E25: =E22+E23+E24 -> 27600 | F25: =F22+F23+F24 -> 110400 | G25: =G22+G23+G24 -> 1494000
A26: decode 平均上下文 | B26: tok | C26: =C6+C7+(C5-1)/2*C16+(C8+C9)/2 -> 2750 | D26: =D6+D7+(D5-1)/2*D16+(D8+D9)/2 -> 4350 | E26: =E6+E7+(E5-1)/2*E16+(E8+E9)/2 -> 6600 | F26: =F6+F7+(F5-1)/2*F16+(F8+F9)/2 -> 6600 | G26: =G6+G7+(G5-1)/2*G16+(G8+G9)/2 -> 49300 | H26: Unit_Cost 的 decode 成本取各層級參考上下文；本列顯示任務實際上下文，差距大時看 Sens_Perf 的 ISL 情境
A27: 思考占 decode | B27: % | C27: =IF(C8+C9>0,C8/(C8+C9),0) -> 0 | D27: =IF(D8+D9>0,D8/(D8+D9),0) -> 0.81081081 | E27: =IF(E8+E9>0,E8/(E8+E9),0) -> 0.66666667 | F27: =IF(F8+F9>0,F8/(F8+F9),0) -> 0.66666667 | G27: =IF(G8+G9>0,G8/(G8+G9),0) -> 0.6
A28: 總 token ÷ 一般聊天 | B28: x | C28: =C25/$C$25 -> 1 | D28: =D25/$C$25 -> 2.0666667 | E28: =E25/$C$25 -> 9.2 | F28: =F25/$C$25 -> 36.8 | G28: =G25/$C$25 -> 498
A29: 總 token ÷ 推理聊天 | B29: x | C29: =C25/$D$25 -> 0.48387097 | D29: =D25/$D$25 -> 1 | E29: =E25/$D$25 -> 4.4516129 | F29: =F25/$D$25 -> 17.806452 | G29: =G25/$D$25 -> 240.96774
A30: 參照：Anthropic 揭露倍數（相對聊天） | B30: x | C30: 1 | E30: 4 | F30: 15 | H30: Interested-party：Anthropic 2025-06 多代理研究系統文章，agent 約 4 倍、多代理約 15 倍聊天 token（S25）。其『聊天』口徑未說明是否含思考，故兩個倍數並列
A32: 每任務成本（$／任務；經濟口徑、基準成本情境、基準利用率）
A33: VR200 × Luna | B33: $ | C33: =IF(ISNUMBER(Unit_Cost!M21),(C22*Unit_Cost!M19+C23*Unit_Cost!M20+C24*Unit_Cost!M21)/1000000,"SLO 不可達") -> 9.5539556e-05 | D33: =IF(ISNUMBER(Unit_Cost!M21),(D22*Unit_Cost!M19+D23*Unit_Cost!M20+D24*Unit_Cost!M21)/1000000,"SLO 不可達") -> 0.00063074831 | E33: =IF(ISNUMBER(Unit_Cost!M21),(E22*Unit_Cost!M19+E23*Unit_Cost!M20+E24*Unit_Cost!M21)/1000000,"SLO 不可達") -> 0.00045657296 | F33: =IF(ISNUMBER(Unit_Cost!M21),(F22*Unit_Cost!M19+F23*Unit_Cost!M20+F24*Unit_Cost!M21)/1000000,"SLO 不可達") -> 0.0018262919 | G33: =IF(ISNUMBER(Unit_Cost!M21),(G22*Unit_Cost!M19+G23*Unit_Cost!M20+G24*Unit_Cost!M21)/1000000,"SLO 不可達") -> 0.0066781516
A34: VR200 × Sol | B34: $ | C34: =IF(ISNUMBER(Unit_Cost!M34),(C22*Unit_Cost!M32+C23*Unit_Cost!M33+C24*Unit_Cost!M34)/1000000,"SLO 不可達") -> 0.00031048515 | D34: =IF(ISNUMBER(Unit_Cost!M34),(D22*Unit_Cost!M32+D23*Unit_Cost!M33+D24*Unit_Cost!M34)/1000000,"SLO 不可達") -> 0.0020308889 | E34: =IF(ISNUMBER(Unit_Cost!M34),(E22*Unit_Cost!M32+E23*Unit_Cost!M33+E24*Unit_Cost!M34)/1000000,"SLO 不可達") -> 0.0014815223 | F34: =IF(ISNUMBER(Unit_Cost!M34),(F22*Unit_Cost!M32+F23*Unit_Cost!M33+F24*Unit_Cost!M34)/1000000,"SLO 不可達") -> 0.005926089 | G34: =IF(ISNUMBER(Unit_Cost!M34),(G22*Unit_Cost!M32+G23*Unit_Cost!M33+G24*Unit_Cost!M34)/1000000,"SLO 不可達") -> 0.021794011
A35: VR200 × Astra | B35: $ | C35: =IF(ISNUMBER(Unit_Cost!M47),(C22*Unit_Cost!M45+C23*Unit_Cost!M46+C24*Unit_Cost!M47)/1000000,"SLO 不可達") -> 0.001522567 | D35: =IF(ISNUMBER(Unit_Cost!M47),(D22*Unit_Cost!M45+D23*Unit_Cost!M46+D24*Unit_Cost!M47)/1000000,"SLO 不可達") -> 0.010379432 | E35: =IF(ISNUMBER(Unit_Cost!M47),(E22*Unit_Cost!M45+E23*Unit_Cost!M46+E24*Unit_Cost!M47)/1000000,"SLO 不可達") -> 0.0072923954 | F35: =IF(ISNUMBER(Unit_Cost!M47),(F22*Unit_Cost!M45+F23*Unit_Cost!M46+F24*Unit_Cost!M47)/1000000,"SLO 不可達") -> 0.029169582 | G35: =IF(ISNUMBER(Unit_Cost!M47),(G22*Unit_Cost!M45+G23*Unit_Cost!M46+G24*Unit_Cost!M47)/1000000,"SLO 不可達") -> 0.10298231
A36: GB300 × Luna | B36: $ | C36: =IF(ISNUMBER(Unit_Cost!J21),(C22*Unit_Cost!J19+C23*Unit_Cost!J20+C24*Unit_Cost!J21)/1000000,"SLO 不可達") -> 0.00014928998 | D36: =IF(ISNUMBER(Unit_Cost!J21),(D22*Unit_Cost!J19+D23*Unit_Cost!J20+D24*Unit_Cost!J21)/1000000,"SLO 不可達") -> 0.00099239332 | E36: =IF(ISNUMBER(Unit_Cost!J21),(E22*Unit_Cost!J19+E23*Unit_Cost!J20+E24*Unit_Cost!J21)/1000000,"SLO 不可達") -> 0.00071291214 | F36: =IF(ISNUMBER(Unit_Cost!J21),(F22*Unit_Cost!J19+F23*Unit_Cost!J20+F24*Unit_Cost!J21)/1000000,"SLO 不可達") -> 0.0028516486 | G36: =IF(ISNUMBER(Unit_Cost!J21),(G22*Unit_Cost!J19+G23*Unit_Cost!J20+G24*Unit_Cost!J21)/1000000,"SLO 不可達") -> 0.010293136
A37: GB300 × Sol | B37: $ | C37: =IF(ISNUMBER(Unit_Cost!J34),(C22*Unit_Cost!J32+C23*Unit_Cost!J33+C24*Unit_Cost!J34)/1000000,"SLO 不可達") -> 0.00052566753 | D37: =IF(ISNUMBER(Unit_Cost!J34),(D22*Unit_Cost!J32+D23*Unit_Cost!J33+D24*Unit_Cost!J34)/1000000,"SLO 不可達") -> 0.0034962472 | E37: =IF(ISNUMBER(Unit_Cost!J34),(E22*Unit_Cost!J32+E23*Unit_Cost!J33+E24*Unit_Cost!J34)/1000000,"SLO 不可達") -> 0.0025091975 | F37: =IF(ISNUMBER(Unit_Cost!J34),(F22*Unit_Cost!J32+F23*Unit_Cost!J33+F24*Unit_Cost!J34)/1000000,"SLO 不可達") -> 0.01003679 | G37: =IF(ISNUMBER(Unit_Cost!J34),(G22*Unit_Cost!J32+G23*Unit_Cost!J33+G24*Unit_Cost!J34)/1000000,"SLO 不可達") -> 0.036129486
A38: GB300 × Astra | B38: $ | C38: =IF(ISNUMBER(Unit_Cost!J47),(C22*Unit_Cost!J45+C23*Unit_Cost!J46+C24*Unit_Cost!J47)/1000000,"SLO 不可達") -> 0.0035581725 | D38: =IF(ISNUMBER(Unit_Cost!J47),(D22*Unit_Cost!J45+D23*Unit_Cost!J46+D24*Unit_Cost!J47)/1000000,"SLO 不可達") -> 0.025025535 | E38: =IF(ISNUMBER(Unit_Cost!J47),(E22*Unit_Cost!J45+E23*Unit_Cost!J46+E24*Unit_Cost!J47)/1000000,"SLO 不可達") -> 0.017041287 | F38: =IF(ISNUMBER(Unit_Cost!J47),(F22*Unit_Cost!J45+F23*Unit_Cost!J46+F24*Unit_Cost!J47)/1000000,"SLO 不可達") -> 0.068165147 | G38: =IF(ISNUMBER(Unit_Cost!J47),(G22*Unit_Cost!J45+G23*Unit_Cost!J46+G24*Unit_Cost!J47)/1000000,"SLO 不可達") -> 0.22939741

Sheet Calib
A1: Calib — 以實測錨點校準效率係數（實測只校準係數，不取代推導）
A2: 錨點：DeepSeek V4-Pro（＝Sol 代表架構）、FP4、8K/1K、分離式 P/D，tok/s/GPU 為總 token 口徑。GB300 同一前緣上兩點聯立解出 η_d 與每層延遲；其餘各點為樣本外驗證
A4: A. 輸入
A5: η_p：prefill 達成峰值比例 | B5: % | C5: 0.3 | J5: Analogy：DeepSeek H800 線上 prefill 約 0.37（S30，待查）；區間 0.15–0.45。擬合結果對此不敏感（見 G 節）
A7: B. 錨點（每欄一個實測點）
A8: 項目 | B8: 單位
A9: 用途 | C9: 擬合點 1 | D9: 擬合點 2 | E9: 驗證 | F9: 驗證（舊軟體） | G9: 驗證（舊軟體） | H9: 驗證（口徑待查） | I9: 驗證（口徑待查）
A10: 世代索引 | C10: 3 | D10: 3 | E10: 3 | F10: 3 | G10: 2 | H10: 2 | I10: 3
A11: 世代 | C11: =INDEX(Spec_Rack!$C$4:$G$4,C10) -> GB300 NVL72 | D11: =INDEX(Spec_Rack!$C$4:$G$4,D10) -> GB300 NVL72 | E11: =INDEX(Spec_Rack!$C$4:$G$4,E10) -> GB300 NVL72 | F11: =INDEX(Spec_Rack!$C$4:$G$4,F10) -> GB300 NVL72 | G11: =INDEX(Spec_Rack!$C$4:$G$4,G10) -> GB200 NVL72 | H11: =INDEX(Spec_Rack!$C$4:$G$4,H10) -> GB200 NVL72 | I11: =INDEX(Spec_Rack!$C$4:$G$4,I10) -> GB300 NVL72
A12: 軟體／日期 | C12: InferenceX 最佳前緣（約 2026-07） | D12: InferenceX 最佳前緣（約 2026-07） | E12: SGLang＋MTP，2026-06 | F12: vLLM 無 MTP，2026-05-22 | G12: vLLM 無 MTP，2026-05-22 | H12: InferenceX 比較頁（0813） | I12: InferenceX 比較頁（0813）
A13: MTP（1＝有） | C13: 1 | D13: 1 | E13: 1 | F13: 0 | G13: 0 | H13: 1 | I13: 1
A14: 每用戶速度 | B14: tok/s | C14: 72 | D14: 130 | E14: 50 | F14: 27 | G14: 27 | H14: 110 | I14: 110
A15: ISL | B15: tok | C15: 8192 | D15: 8192 | E15: 8192 | F15: 8192 | G15: 8192 | H15: 8192 | I15: 8192
A16: OSL | B16: tok | C16: 1024 | D16: 1024 | E16: 1024 | F16: 1024 | G16: 1024 | H16: 1024 | I16: 1024
A17: 實測 tok/s/GPU（總 token） | B17: tok/s | C17: 9384.4 | D17: 3473.9 | E17: 11200 | F17: 6182 | G17: 2189 | H17: 3795.5 | I17: 6522.4
A18: 來源 | C18: S22 | D18: S22 | E18: S21 | F18: S20 | G18: S20 | H18: S23 | I18: S23
A19: 量測平台（獨立性） | C19: InferenceX（SemiAnalysis） | D19: InferenceX（SemiAnalysis） | E19: InferenceX（SemiAnalysis） | F19: InferenceX（SemiAnalysis） | G19: InferenceX（SemiAnalysis） | H19: InferenceX（SemiAnalysis） | I19: InferenceX（SemiAnalysis） | J19: 七個點全部來自同一平台（S21 為 SGLang 作者轉述 InferenceX 資料，不構成獨立來源）。第二來源見 H 節
A20: C. 各點的模型量（Sol 架構；與 Perf 同一套公式）
A21: 計算用峰值 | B21: PF/GPU | C21: =INDEX(Spec_Rack!$C$35:$G$35,C10) -> 15 | D21: =INDEX(Spec_Rack!$C$35:$G$35,D10) -> 15 | E21: =INDEX(Spec_Rack!$C$35:$G$35,E10) -> 15 | F21: =INDEX(Spec_Rack!$C$35:$G$35,F10) -> 15 | G21: =INDEX(Spec_Rack!$C$35:$G$35,G10) -> 10 | H21: =INDEX(Spec_Rack!$C$35:$G$35,H10) -> 10 | I21: =INDEX(Spec_Rack!$C$35:$G$35,I10) -> 15
A22: HBM 容量 | B22: GB | C22: =INDEX(Spec_Rack!$C$25:$G$25,C10) -> 288 | D22: =INDEX(Spec_Rack!$C$25:$G$25,D10) -> 288 | E22: =INDEX(Spec_Rack!$C$25:$G$25,E10) -> 288 | F22: =INDEX(Spec_Rack!$C$25:$G$25,F10) -> 288 | G22: =INDEX(Spec_Rack!$C$25:$G$25,G10) -> 186 | H22: =INDEX(Spec_Rack!$C$25:$G$25,H10) -> 186 | I22: =INDEX(Spec_Rack!$C$25:$G$25,I10) -> 288
A23: HBM 頻寬 | B23: TB/s | C23: =INDEX(Spec_Rack!$C$26:$G$26,C10) -> 8 | D23: =INDEX(Spec_Rack!$C$26:$G$26,D10) -> 8 | E23: =INDEX(Spec_Rack!$C$26:$G$26,E10) -> 8 | F23: =INDEX(Spec_Rack!$C$26:$G$26,F10) -> 8 | G23: =INDEX(Spec_Rack!$C$26:$G$26,G10) -> 8 | H23: =INDEX(Spec_Rack!$C$26:$G$26,H10) -> 8 | I23: =INDEX(Spec_Rack!$C$26:$G$26,I10) -> 8
A24: EP 通訊頻寬 | B24: TB/s | C24: =INDEX(Spec_Rack!$C$27:$G$27,C10) -> 0.9 | D24: =INDEX(Spec_Rack!$C$27:$G$27,D10) -> 0.9 | E24: =INDEX(Spec_Rack!$C$27:$G$27,E10) -> 0.9 | F24: =INDEX(Spec_Rack!$C$27:$G$27,F10) -> 0.9 | G24: =INDEX(Spec_Rack!$C$27:$G$27,G10) -> 0.9 | H24: =INDEX(Spec_Rack!$C$27:$G$27,H10) -> 0.9 | I24: =INDEX(Spec_Rack!$C$27:$G$27,I10) -> 0.9
A25: EP 基準寬度 | C25: =INDEX(Spec_Rack!$C$29:$G$29,C10) -> 32 | D25: =INDEX(Spec_Rack!$C$29:$G$29,D10) -> 32 | E25: =INDEX(Spec_Rack!$C$29:$G$29,E10) -> 32 | F25: =INDEX(Spec_Rack!$C$29:$G$29,F10) -> 32 | G25: =INDEX(Spec_Rack!$C$29:$G$29,G10) -> 32 | H25: =INDEX(Spec_Rack!$C$29:$G$29,H10) -> 32 | I25: =INDEX(Spec_Rack!$C$29:$G$29,I10) -> 32
A26: 專家 bytes/param | B26: B | C26: =INDEX(Spec_Rack!$C$30:$G$30,C10) -> 0.5625 | D26: =INDEX(Spec_Rack!$C$30:$G$30,D10) -> 0.5625 | E26: =INDEX(Spec_Rack!$C$30:$G$30,E10) -> 0.5625 | F26: =INDEX(Spec_Rack!$C$30:$G$30,F10) -> 0.5625 | G26: =INDEX(Spec_Rack!$C$30:$G$30,G10) -> 0.5625 | H26: =INDEX(Spec_Rack!$C$30:$G$30,H10) -> 0.5625 | I26: =INDEX(Spec_Rack!$C$30:$G$30,I10) -> 0.5625
A27: 非專家 bytes/param | B27: B | C27: =INDEX(Spec_Rack!$C$31:$G$31,C10) -> 1 | D27: =INDEX(Spec_Rack!$C$31:$G$31,D10) -> 1 | E27: =INDEX(Spec_Rack!$C$31:$G$31,E10) -> 1 | F27: =INDEX(Spec_Rack!$C$31:$G$31,F10) -> 1 | G27: =INDEX(Spec_Rack!$C$31:$G$31,G10) -> 1 | H27: =INDEX(Spec_Rack!$C$31:$G$31,H10) -> 1 | I27: =INDEX(Spec_Rack!$C$31:$G$31,I10) -> 1
A28: 啟用參數 | B28: B | C28: =Arch!$D$7 -> 49 | D28: =Arch!$D$7 -> 49 | E28: =Arch!$D$7 -> 49 | F28: =Arch!$D$7 -> 49 | G28: =Arch!$D$7 -> 49 | H28: =Arch!$D$7 -> 49 | I28: =Arch!$D$7 -> 49
A29: 層數 | C29: =Arch!$D$8 -> 61 | D29: =Arch!$D$8 -> 61 | E29: =Arch!$D$8 -> 61 | F29: =Arch!$D$8 -> 61 | G29: =Arch!$D$8 -> 61 | H29: =Arch!$D$8 -> 61 | I29: =Arch!$D$8 -> 61
A30: d_model | C30: =Arch!$D$9 -> 7168 | D30: =Arch!$D$9 -> 7168 | E30: =Arch!$D$9 -> 7168 | F30: =Arch!$D$9 -> 7168 | G30: =Arch!$D$9 -> 7168 | H30: =Arch!$D$9 -> 7168 | I30: =Arch!$D$9 -> 7168
A31: 啟用專家 | C31: =Arch!$D$13 -> 6 | D31: =Arch!$D$13 -> 6 | E31: =Arch!$D$13 -> 6 | F31: =Arch!$D$13 -> 6 | G31: =Arch!$D$13 -> 6 | H31: =Arch!$D$13 -> 6 | I31: =Arch!$D$13 -> 6
A32: 非專家參數 | B32: B | C32: =Arch!$D$28 -> 20.277778 | D32: =Arch!$D$28 -> 20.277778 | E32: =Arch!$D$28 -> 20.277778 | F32: =Arch!$D$28 -> 20.277778 | G32: =Arch!$D$28 -> 20.277778 | H32: =Arch!$D$28 -> 20.277778 | I32: =Arch!$D$28 -> 20.277778
A33: 專家參數 | B33: B | C33: =Arch!$D$29 -> 1579.7222 | D33: =Arch!$D$29 -> 1579.7222 | E33: =Arch!$D$29 -> 1579.7222 | F33: =Arch!$D$29 -> 1579.7222 | G33: =Arch!$D$29 -> 1579.7222 | H33: =Arch!$D$29 -> 1579.7222 | I33: =Arch!$D$29 -> 1579.7222
A34: KV bytes/token | B34: B | C34: =Arch!$D$25 -> 3965 | D34: =Arch!$D$25 -> 3965 | E34: =Arch!$D$25 -> 3965 | F34: =Arch!$D$25 -> 3965 | G34: =Arch!$D$25 -> 3965 | H34: =Arch!$D$25 -> 3965 | I34: =Arch!$D$25 -> 3965
A35: 注意力 FLOPs／被注意 token | C35: =Arch!$D$30 -> 15990784 | D35: =Arch!$D$30 -> 15990784 | E35: =Arch!$D$30 -> 15990784 | F35: =Arch!$D$30 -> 15990784 | G35: =Arch!$D$30 -> 15990784 | H35: =Arch!$D$30 -> 15990784 | I35: =Arch!$D$30 -> 15990784
A36: 全注意力層比例 | B36: % | C36: =Arch!$D$16 -> 0.5 | D36: =Arch!$D$16 -> 0.5 | E36: =Arch!$D$16 -> 0.5 | F36: =Arch!$D$16 -> 0.5 | G36: =Arch!$D$16 -> 0.5 | H36: =Arch!$D$16 -> 0.5 | I36: =Arch!$D$16 -> 0.5
A37: 跨度上限 | C37: =Arch!$D$17 -> 4224 | D37: =Arch!$D$17 -> 4224 | E37: =Arch!$D$17 -> 4224 | F37: =Arch!$D$17 -> 4224 | G37: =Arch!$D$17 -> 4224 | H37: =Arch!$D$17 -> 4224 | I37: =Arch!$D$17 -> 4224
A38: 壓縮比 | C38: =Arch!$D$18 -> 128 | D38: =Arch!$D$18 -> 128 | E38: =Arch!$D$18 -> 128 | F38: =Arch!$D$18 -> 128 | G38: =Arch!$D$18 -> 128 | H38: =Arch!$D$18 -> 128 | I38: =Arch!$D$18 -> 128
A39: 滑動窗 | C39: =Arch!$D$19 -> 128 | D39: =Arch!$D$19 -> 128 | E39: =Arch!$D$19 -> 128 | F39: =Arch!$D$19 -> 128 | G39: =Arch!$D$19 -> 128 | H39: =Arch!$D$19 -> 128 | I39: =Arch!$D$19 -> 128
A40: decode 平均上下文 | B40: tok | C40: =C15+C16/2 -> 8704 | D40: =D15+D16/2 -> 8704 | E40: =E15+E16/2 -> 8704 | F40: =F15+F16/2 -> 8704 | G40: =G15+G16/2 -> 8704 | H40: =H15+H16/2 -> 8704 | I40: =I15+I16/2 -> 8704
A41: decode 被注意 token | B41: tok | C41: =C36*IF(C37=0,C40,MIN(C40,C37))+(1-C36)*(C40/C38+C39) -> 2210 | D41: =D36*IF(D37=0,D40,MIN(D40,D37))+(1-D36)*(D40/D38+D39) -> 2210 | E41: =E36*IF(E37=0,E40,MIN(E40,E37))+(1-E36)*(E40/E38+E39) -> 2210 | F41: =F36*IF(F37=0,F40,MIN(F40,F37))+(1-F36)*(F40/F38+F39) -> 2210 | G41: =G36*IF(G37=0,G40,MIN(G40,G37))+(1-G36)*(G40/G38+G39) -> 2210 | H41: =H36*IF(H37=0,H40,MIN(H40,H37))+(1-H36)*(H40/H38+H39) -> 2210 | I41: =I36*IF(I37=0,I40,MIN(I40,I37))+(1-I36)*(I40/I38+I39) -> 2210
A42: decode FLOPs/token | B42: GFLOP | C42: =(2*C28*1000000000+C35*C41)/1000000000 -> 133.33963 | D42: =(2*D28*1000000000+D35*D41)/1000000000 -> 133.33963 | E42: =(2*E28*1000000000+E35*E41)/1000000000 -> 133.33963 | F42: =(2*F28*1000000000+F35*F41)/1000000000 -> 133.33963 | G42: =(2*G28*1000000000+G35*G41)/1000000000 -> 133.33963 | H42: =(2*H28*1000000000+H35*H41)/1000000000 -> 133.33963 | I42: =(2*I28*1000000000+I35*I41)/1000000000 -> 133.33963
A43: prefill 平均位置 | B43: tok | C43: =C15/2 -> 4096 | D43: =D15/2 -> 4096 | E43: =E15/2 -> 4096 | F43: =F15/2 -> 4096 | G43: =G15/2 -> 4096 | H43: =H15/2 -> 4096 | I43: =I15/2 -> 4096
A44: prefill 被注意 token | B44: tok | C44: =C36*IF(C37=0,C43,MIN(C43,C37))+(1-C36)*(C43/C38+C39) -> 2128 | D44: =D36*IF(D37=0,D43,MIN(D43,D37))+(1-D36)*(D43/D38+D39) -> 2128 | E44: =E36*IF(E37=0,E43,MIN(E43,E37))+(1-E36)*(E43/E38+E39) -> 2128 | F44: =F36*IF(F37=0,F43,MIN(F43,F37))+(1-F36)*(F43/F38+F39) -> 2128 | G44: =G36*IF(G37=0,G43,MIN(G43,G37))+(1-G36)*(G43/G38+G39) -> 2128 | H44: =H36*IF(H37=0,H43,MIN(H43,H37))+(1-H36)*(H43/H38+H39) -> 2128 | I44: =I36*IF(I37=0,I43,MIN(I43,I37))+(1-I36)*(I43/I38+I39) -> 2128
A45: prefill FLOPs/token | B45: GFLOP | C45: =(2*C28*1000000000+C35*C44)/1000000000 -> 132.02839 | D45: =(2*D28*1000000000+D35*D44)/1000000000 -> 132.02839 | E45: =(2*E28*1000000000+E35*E44)/1000000000 -> 132.02839 | F45: =(2*F28*1000000000+F35*F44)/1000000000 -> 132.02839 | G45: =(2*G28*1000000000+G35*G44)/1000000000 -> 132.02839 | H45: =(2*H28*1000000000+H35*H44)/1000000000 -> 132.02839 | I45: =(2*I28*1000000000+I35*I44)/1000000000 -> 132.02839
A46: 可用 HBM | B46: GB | C46: =C22*(1-Serving!$C$9) -> 259.2 | D46: =D22*(1-Serving!$C$9) -> 259.2 | E46: =E22*(1-Serving!$C$9) -> 259.2 | F46: =F22*(1-Serving!$C$9) -> 259.2 | G46: =G22*(1-Serving!$C$9) -> 167.4 | H46: =H22*(1-Serving!$C$9) -> 167.4 | I46: =I22*(1-Serving!$C$9) -> 259.2
A47: 注意力 TP 度 | C47: =MAX(1,CEILING(C32*C27/(Serving!$C$10*C46),1)) -> 1 | D47: =MAX(1,CEILING(D32*D27/(Serving!$C$10*D46),1)) -> 1 | E47: =MAX(1,CEILING(E32*E27/(Serving!$C$10*E46),1)) -> 1 | F47: =MAX(1,CEILING(F32*F27/(Serving!$C$10*F46),1)) -> 1 | G47: =MAX(1,CEILING(G32*G27/(Serving!$C$10*G46),1)) -> 1 | H47: =MAX(1,CEILING(H32*H27/(Serving!$C$10*H46),1)) -> 1 | I47: =MAX(1,CEILING(I32*I27/(Serving!$C$10*I46),1)) -> 1
A48: EP 寬度 | C48: =MAX(C25,CEILING(C33*C26/(Serving!$C$11*C46),1)) -> 32 | D48: =MAX(D25,CEILING(D33*D26/(Serving!$C$11*D46),1)) -> 32 | E48: =MAX(E25,CEILING(E33*E26/(Serving!$C$11*E46),1)) -> 32 | F48: =MAX(F25,CEILING(F33*F26/(Serving!$C$11*F46),1)) -> 32 | G48: =MAX(G25,CEILING(G33*G26/(Serving!$C$11*G46),1)) -> 32 | H48: =MAX(H25,CEILING(H33*H26/(Serving!$C$11*H46),1)) -> 32 | I48: =MAX(I25,CEILING(I33*I26/(Serving!$C$11*I46),1)) -> 32
A49: 每 GPU 權重 | B49: GB | C49: =C32*C27/C47+C33*C26/C48 -> 48.046332 | D49: =D32*D27/D47+D33*D26/D48 -> 48.046332 | E49: =E32*E27/E47+E33*E26/E48 -> 48.046332 | F49: =F32*F27/F47+F33*F26/F48 -> 48.046332 | G49: =G32*G27/G47+G33*G26/G48 -> 48.046332 | H49: =H32*H27/H47+H33*H26/H48 -> 48.046332 | I49: =I32*I27/I47+I33*I26/I48 -> 48.046332
A50: 草稿數（無 MTP＝0） | C50: =Serving!$C$6*C13 -> 3 | D50: =Serving!$C$6*D13 -> 3 | E50: =Serving!$C$6*E13 -> 3 | F50: =Serving!$C$6*F13 -> 0 | G50: =Serving!$C$6*G13 -> 0 | H50: =Serving!$C$6*H13 -> 3 | I50: =Serving!$C$6*I13 -> 3
A51: 每步接受 token | C51: =IF(C13=1,Serving!$C$8,1) -> 2.533 | D51: =IF(D13=1,Serving!$C$8,1) -> 2.533 | E51: =IF(E13=1,Serving!$C$8,1) -> 2.533 | F51: =IF(F13=1,Serving!$C$8,1) -> 1 | G51: =IF(G13=1,Serving!$C$8,1) -> 1 | H51: =IF(H13=1,Serving!$C$8,1) -> 2.533 | I51: =IF(I13=1,Serving!$C$8,1) -> 2.533
A52: prefill tok/s/GPU（η_p 基準） | B52: tok/s | C52: =$C$5*C21*1000000000000000/(C45*1000000000) -> 34083.579 | D52: =$C$5*D21*1000000000000000/(D45*1000000000) -> 34083.579 | E52: =$C$5*E21*1000000000000000/(E45*1000000000) -> 34083.579 | F52: =$C$5*F21*1000000000000000/(F45*1000000000) -> 34083.579 | G52: =$C$5*G21*1000000000000000/(G45*1000000000) -> 22722.386 | H52: =$C$5*H21*1000000000000000/(H45*1000000000) -> 22722.386 | I52: =$C$5*I21*1000000000000000/(I45*1000000000) -> 34083.579
A53: 每序列算力時間（η＝1） | B53: ms | C53: =(C50+1)*C42/C21/1000 -> 0.035557235 | D53: =(D50+1)*D42/D21/1000 -> 0.035557235 | E53: =(E50+1)*E42/E21/1000 -> 0.035557235 | F53: =(F50+1)*F42/F21/1000 -> 0.0088893088 | G53: =(G50+1)*G42/G21/1000 -> 0.013333963 | H53: =(H50+1)*H42/H21/1000 -> 0.053335853 | I53: =(I50+1)*I42/I21/1000 -> 0.035557235
A54: 實測反推 decode tok/s（每 decode GPU） | B54: tok/s | C54: =C16/((C15+C16)/C17-C15/C52) -> 1380.6028 | D54: =D16/((D15+D16)/D17-D15/D52) -> 424.44263 | E54: =E16/((E15+E16)/E17-E15/E52) -> 1757.9194 | F54: =F16/((F15+F16)/F17-F15/F52) -> 818.91873 | G54: =G16/((G15+G16)/G17-G15/G52) -> 266.00055 | H54: =H16/((H15+H16)/H17-H15/H52) -> 495.25708 | I54: =I16/((I15+I16)/I17-I15/I52) -> 873.25335 | J54: 只對擬合點有意義；假設 P:D GPU 依工作量配比
A55: 實測反推批次 | B55: 序列/GPU | C55: =C54/C14 -> 19.175039 | D55: =D54/D14 -> 3.2649433 | E55: =E54/E14 -> 35.158388 | F55: =F54/F14 -> 30.330323 | G55: =G54/G14 -> 9.8518722 | H55: =H54/H14 -> 4.502337 | I55: =I54/I14 -> 7.9386669
A57: D. 擬合（擬合點 1、2 聯立；假設兩點皆為算力項綁定，見下列檢查）
A58: η_d：decode 每序列算力效率 | B58: % | C58: =(C55-D55)*C53/(1000*(C51/C14-D51/D14)) -> 0.036042379 | J58: B×c/η＝1000×a/s − 固定延遲；兩點相減消去固定延遲
A59: 每步固定延遲（GB300、Sol、含 MTP） | B59: ms | C59: =1000*C51/C14-C55*C53/C58 -> 16.263619
A60: 每層每次前向固定延遲 | B60: µs | C60: =(C59-C49/C23)*1000/(C29+C50) -> 160.27856 | J60: （固定延遲 − 權重讀取時間）÷（層數＋草稿數）：涵蓋 all-to-all 延遲、kernel 啟動、同步
A61: 檢查：擬合點 1 算力項為綁定 | C61: =IF(C53/C58>=MAX(C34*C40/(C23*Serving!$C$13)/1000000000,(C50+1)*C29*C31*C30*Serving!$C$12/(C24*Serving!$C$14)/1000000000),"成立","不成立") -> 成立
A63: E. 各世代採用參數（GB300＝擬合值；其他世代＝擬合值 × 倍數）
A64: 世代 | C64: =Spec_Rack!C4 -> Hopper H100 | D64: =Spec_Rack!D4 -> GB200 NVL72 | E64: =Spec_Rack!E4 -> GB300 NVL72 | F64: =Spec_Rack!F4 -> VR200 NVL72 | G64: =Spec_Rack!G4 -> Rubin Ultra NVL576
A65: η_d 倍數 | B65: x | C65: 3 | D65: 1 | E65: 1 | F65: 1 | G65: 1 | J65: Hopper：DeepSeek H800 線上 decode 約達 FP8 峰值 18%（S30）＝本擬合 5 倍，取 3 [Analogy，區間 1–5]；GB200、VR200 沿用 GB300 [Analogy]；RU [Assumed]
A66: 每層延遲倍數 | B66: x | C66: 1.5 | D66: 1 | E66: 1 | F66: 1 | G66: 1 | J66: Hopper EP 跨節點走 IB [Assumed 1.5，區間 1–3]
A67: η_p 倍數 | B67: x | C67: 1 | D67: 1 | E67: 1 | F67: 1 | G67: 1
A68: η_d（採用） | B68: % | C68: =$C$58*C65 -> 0.10812714 | D68: =$C$58*D65 -> 0.036042379 | E68: =$C$58*E65 -> 0.036042379 | F68: =$C$58*F65 -> 0.036042379 | G68: =$C$58*G65 -> 0.036042379
A69: 每層延遲（採用） | B69: µs | C69: =$C$60*C66 -> 240.41784 | D69: =$C$60*D66 -> 160.27856 | E69: =$C$60*E66 -> 160.27856 | F69: =$C$60*F66 -> 160.27856 | G69: =$C$60*G66 -> 160.27856
A70: η_p（採用） | B70: % | C70: =$C$5*C67 -> 0.3 | D70: =$C$5*D67 -> 0.3 | E70: =$C$5*E67 -> 0.3 | F70: =$C$5*F67 -> 0.3 | G70: =$C$5*G67 -> 0.3
A72: F. 樣本外驗證（以採用參數重算各點）
A73: η_d（該世代） | B73: % | C73: =INDEX($C$68:$G$68,C10) -> 0.036042379 | D73: =INDEX($C$68:$G$68,D10) -> 0.036042379 | E73: =INDEX($C$68:$G$68,E10) -> 0.036042379 | F73: =INDEX($C$68:$G$68,F10) -> 0.036042379 | G73: =INDEX($C$68:$G$68,G10) -> 0.036042379 | H73: =INDEX($C$68:$G$68,H10) -> 0.036042379 | I73: =INDEX($C$68:$G$68,I10) -> 0.036042379
A74: 每層延遲（該世代） | B74: µs | C74: =INDEX($C$69:$G$69,C10) -> 160.27856 | D74: =INDEX($C$69:$G$69,D10) -> 160.27856 | E74: =INDEX($C$69:$G$69,E10) -> 160.27856 | F74: =INDEX($C$69:$G$69,F10) -> 160.27856 | G74: =INDEX($C$69:$G$69,G10) -> 160.27856 | H74: =INDEX($C$69:$G$69,H10) -> 160.27856 | I74: =INDEX($C$69:$G$69,I10) -> 160.27856
A75: η_p（該世代） | B75: % | C75: =INDEX($C$70:$G$70,C10) -> 0.3 | D75: =INDEX($C$70:$G$70,D10) -> 0.3 | E75: =INDEX($C$70:$G$70,E10) -> 0.3 | F75: =INDEX($C$70:$G$70,F10) -> 0.3 | G75: =INDEX($C$70:$G$70,G10) -> 0.3 | H75: =INDEX($C$70:$G$70,H10) -> 0.3 | I75: =INDEX($C$70:$G$70,I10) -> 0.3
A76: prefill tok/s/GPU | B76: tok/s | C76: =C75*C21*1000000000000000/(C45*1000000000) -> 34083.579 | D76: =D75*D21*1000000000000000/(D45*1000000000) -> 34083.579 | E76: =E75*E21*1000000000000000/(E45*1000000000) -> 34083.579 | F76: =F75*F21*1000000000000000/(F45*1000000000) -> 34083.579 | G76: =G75*G21*1000000000000000/(G45*1000000000) -> 22722.386 | H76: =H75*H21*1000000000000000/(H45*1000000000) -> 22722.386 | I76: =I75*I21*1000000000000000/(I45*1000000000) -> 34083.579
A77: 每步固定延遲 | B77: ms | C77: =C49/C23+(C29+C50)*C74/1000 -> 16.263619 | D77: =D49/D23+(D29+D50)*D74/1000 -> 16.263619 | E77: =E49/E23+(E29+E50)*E74/1000 -> 16.263619 | F77: =F49/F23+(F29+F50)*F74/1000 -> 15.782784 | G77: =G49/G23+(G29+G50)*G74/1000 -> 15.782784 | H77: =H49/H23+(H29+H50)*H74/1000 -> 16.263619 | I77: =I49/I23+(I29+I50)*I74/1000 -> 16.263619
A78: 每序列每步時間 | B78: ms | C78: =MAX(C53/C73,C34*C40/(C23*Serving!$C$13)/1000000000,(C50+1)*C29*C31*C30*Serving!$C$12*(C48-1)/C48/(C24*Serving!$C$14)/1000000000) -> 0.98653962 | D78: =MAX(D53/D73,D34*D40/(D23*Serving!$C$13)/1000000000,(D50+1)*D29*D31*D30*Serving!$C$12*(D48-1)/D48/(D24*Serving!$C$14)/1000000000) -> 0.98653962 | E78: =MAX(E53/E73,E34*E40/(E23*Serving!$C$13)/1000000000,(E50+1)*E29*E31*E30*Serving!$C$12*(E48-1)/E48/(E24*Serving!$C$14)/1000000000) -> 0.98653962 | F78: =MAX(F53/F73,F34*F40/(F23*Serving!$C$13)/1000000000,(F50+1)*F29*F31*F30*Serving!$C$12*(F48-1)/F48/(F24*Serving!$C$14)/1000000000) -> 0.24663491 | G78: =MAX(G53/G73,G34*G40/(G23*Serving!$C$13)/1000000000,(G50+1)*G29*G31*G30*Serving!$C$12*(G48-1)/G48/(G24*Serving!$C$14)/1000000000) -> 0.36995236 | H78: =MAX(H53/H73,H34*H40/(H23*Serving!$C$13)/1000000000,(H50+1)*H29*H31*H30*Serving!$C$12*(H48-1)/H48/(H24*Serving!$C$14)/1000000000) -> 1.4798094 | I78: =MAX(I53/I73,I34*I40/(I23*Serving!$C$13)/1000000000,(I50+1)*I29*I31*I30*Serving!$C$12*(I48-1)/I48/(I24*Serving!$C$14)/1000000000) -> 0.98653962
A79: SLO 批次上限 | B79: 序列 | C79: =(1000*C51/C14-C77)/C78 -> 19.175039 | D79: =(1000*D51/D14-D77)/D78 -> 3.2649433 | E79: =(1000*E51/E14-E77)/E78 -> 34.865686 | F79: =(1000*F51/F14-F77)/F78 -> 86.176988 | G79: =(1000*G51/G14-G77)/G78 -> 57.451325 | H79: =(1000*H51/H14-H77)/H78 -> 4.5706245 | I79: =(1000*I51/I14-I77)/I78 -> 6.8559368
A80: 容量批次上限 | B80: 序列 | C80: =(C46-C49)*1000000000/(C34*C40) -> 6118.3815 | D80: =(D46-D49)*1000000000/(D34*D40) -> 6118.3815 | E80: =(E46-E49)*1000000000/(E34*E40) -> 6118.3815 | F80: =(F46-F49)*1000000000/(F34*F40) -> 6118.3815 | G80: =(G46-G49)*1000000000/(G34*G40) -> 3458.3878 | H80: =(H46-H49)*1000000000/(H34*H40) -> 3458.3878 | I80: =(I46-I49)*1000000000/(I34*I40) -> 6118.3815
A81: B* | B81: 序列 | C81: =MAX(0,MIN(C79,C80)) -> 19.175039 | D81: =MAX(0,MIN(D79,D80)) -> 3.2649433 | E81: =MAX(0,MIN(E79,E80)) -> 34.865686 | F81: =MAX(0,MIN(F79,F80)) -> 86.176988 | G81: =MAX(0,MIN(G79,G80)) -> 57.451325 | H81: =MAX(0,MIN(H79,H80)) -> 4.5706245 | I81: =MAX(0,MIN(I79,I80)) -> 6.8559368
A82: decode tok/s/GPU | B82: tok/s | C82: =IF(C81>0,C81*C51/((C77+C81*C78)/1000),0) -> 1380.6028 | D82: =IF(D81>0,D81*D51/((D77+D81*D78)/1000),0) -> 424.44263 | E82: =IF(E81>0,E81*E51/((E77+E81*E78)/1000),0) -> 1743.2843 | F82: =IF(F81>0,F81*F51/((F77+F81*F78)/1000),0) -> 2326.7787 | G82: =IF(G81>0,G81*G51/((G77+G81*G78)/1000),0) -> 1551.1858 | H82: =IF(H81>0,H81*H51/((H77+H81*H78)/1000),0) -> 502.7687 | I82: =IF(I81>0,I81*I51/((I77+I81*I78)/1000),0) -> 754.15305
A83: 模型 tok/s/GPU（總 token） | B83: tok/s | C83: =IF(C82>0,(C15+C16)/(C15/C76+C16/C82),0) -> 9384.4 | D83: =IF(D82>0,(D15+D16)/(D15/D76+D16/D82),0) -> 3473.9 | E83: =IF(E82>0,(E15+E16)/(E15/E76+E16/E82),0) -> 11133.832 | F83: =IF(F82>0,(F15+F16)/(F15/F76+F16/F82),0) -> 13544.102 | G83: =IF(G82>0,(G15+G16)/(G15/G76+G16/G82),0) -> 9029.4015 | H83: =IF(H82>0,(H15+H16)/(H15/H76+H16/H82),0) -> 3844.4092 | I83: =IF(I82>0,(I15+I16)/(I15/I76+I16/I82),0) -> 5766.6139
A84: 模型 ÷ 實測 | B84: x | C84: =C83/C17 -> 1 | D84: =D83/D17 -> 1 | E84: =E83/E17 -> 0.99409213 | F84: =F83/F17 -> 2.1908933 | G84: =G83/G17 -> 4.1248979 | H84: =H83/H17 -> 1.0128861 | I84: =I83/I17 -> 0.88412453
A85: 判讀 | C85: 擬合點：應為 1.00 | D85: 擬合點：應為 1.00 | E85: 同世代、不同日期與引擎：檢驗前緣形狀 | F85: 舊軟體：模型應高於實測（軟體差距） | G85: 舊軟體＋GB200 記憶體限制配方（S20 說明） | H85: 工作負載標示不明（頁面預設為 agentic） | I85: 同上
A87: G. η_p 敏感度：擬合結果隨 η_p 的變化（η_p 僅影響 prefill／decode GPU 分攤）
A88: η_p | C88: 0.15 | D88: 0.3 | E88: 0.45
A89: 擬合點 1 prefill tok/s | C89: =C88*$C$21*1000000000000000/($C$45*1000000000) -> 17041.789 | D89: =D88*$C$21*1000000000000000/($C$45*1000000000) -> 34083.579 | E89: =E88*$C$21*1000000000000000/($C$45*1000000000) -> 51125.368
A90: 擬合點 2 prefill tok/s | C90: =C88*$D$21*1000000000000000/($D$45*1000000000) -> 17041.789 | D90: =D88*$D$21*1000000000000000/($D$45*1000000000) -> 34083.579 | E90: =E88*$D$21*1000000000000000/($D$45*1000000000) -> 51125.368
A91: 擬合點 1 反推批次 | C91: =$C$16/(($C$15+$C$16)/$C$17-$C$15/C89)/$C$14 -> 28.367589 | D91: =$C$16/(($C$15+$C$16)/$C$17-$C$15/D89)/$C$14 -> 19.175039 | E91: =$C$16/(($C$15+$C$16)/$C$17-$C$15/E89)/$C$14 -> 17.305726
A92: 擬合點 2 反推批次 | C92: =$D$16/(($D$15+$D$16)/$D$17-$D$15/C90)/$D$14 -> 3.6261997 | D92: =$D$16/(($D$15+$D$16)/$D$17-$D$15/D90)/$D$14 -> 3.2649433 | E92: =$D$16/(($D$15+$D$16)/$D$17-$D$15/E90)/$D$14 -> 3.1600059
A93: η_d | C93: =(C91-C92)*$C$53/(1000*($C$51/$C$14-$D$51/$D$14)) -> 0.056048596 | D93: =(D91-D92)*$C$53/(1000*($C$51/$C$14-$D$51/$D$14)) -> 0.036042379 | E93: =(E91-E92)*$C$53/(1000*($C$51/$C$14-$D$51/$D$14)) -> 0.032045401
A94: 每層延遲 µs | C94: =((1000*$C$51/$C$14-C91*$C$53/C93)-$C$49/$C$23)*1000/($C$29+$C$50) -> 174.66191 | D94: =((1000*$C$51/$C$14-D91*$C$53/D93)-$C$49/$C$23)*1000/($C$29+$C$50) -> 160.27856 | E94: =((1000*$C$51/$C$14-E91*$C$53/E93)-$C$49/$C$23)*1000/($C$29+$C$50) -> 155.82055
A96: H. 第二來源驗證：MLPerf Inference DeepSeek-R1（MLCommons 稽核；提交者 NVIDIA 為利害關係方）
A97: R1 架構與工作負載（驗證專用輸入）
A98: 總參數 | B98: B | C98: 671 | J98: Verified：DeepSeek-V3/R1 模型卡；ISL／OSL 800／3,880（MLCommons 2025-09，S33）
A99: 啟用參數 | B99: B | C99: 37
A100: 層數 | C100: 61
A101: d_model | C101: 7168
A102: routed experts | C102: 256
A103: 啟用 experts | C103: 8
A104: shared experts | C104: 1
A105: vocab | C105: 129280
A106: KV bytes/token（MLA 576 × 61 層，FP8） | B106: B | C106: 35136
A107: 注意力 FLOPs／被注意 token（MLA：2×128×192＋2×128×128，× 61） | B107: FLOP | C107: 4997120
...

Sheet Perf
A1: Perf — 每架產出引擎（世代 × 層級；各層級 SLO 與參考任務；100% 利用率）
A2: decode：每步時間＝固定延遲＋B × 每序列時間；在 SLO 下解出批次 B*，再受 HBM 容量限制。prefill 為算力受限。黃底為關鍵輸出
A4: 世代 | C4: =INDEX(Spec_Rack!$C$4:$G$4,C6) -> Hopper H100 | D4: =INDEX(Spec_Rack!$C$4:$G$4,D6) -> Hopper H100 | E4: =INDEX(Spec_Rack!$C$4:$G$4,E6) -> Hopper H100 | F4: =INDEX(Spec_Rack!$C$4:$G$4,F6) -> GB200 NVL72 | G4: =INDEX(Spec_Rack!$C$4:$G$4,G6) -> GB200 NVL72 | H4: =INDEX(Spec_Rack!$C$4:$G$4,H6) -> GB200 NVL72 | I4: =INDEX(Spec_Rack!$C$4:$G$4,I6) -> GB300 NVL72 | J4: =INDEX(Spec_Rack!$C$4:$G$4,J6) -> GB300 NVL72 | ... Q4: =INDEX(Spec_Rack!$C$4:$G$4,Q6) -> Rubin Ultra NVL576
A5: 層級 | C5: =INDEX(Arch!$C$4:$E$4,C7) -> Luna（低層） | D5: =INDEX(Arch!$C$4:$E$4,D7) -> Sol（中層） | E5: =INDEX(Arch!$C$4:$E$4,E7) -> Astra（頂層） | F5: =INDEX(Arch!$C$4:$E$4,F7) -> Luna（低層） | G5: =INDEX(Arch!$C$4:$E$4,G7) -> Sol（中層） | H5: =INDEX(Arch!$C$4:$E$4,H7) -> Astra（頂層） | I5: =INDEX(Arch!$C$4:$E$4,I7) -> Luna（低層） | J5: =INDEX(Arch!$C$4:$E$4,J7) -> Sol（中層） | ... Q5: =INDEX(Arch!$C$4:$E$4,Q7) -> Astra（頂層）
A6: 世代索引 | C6: 1 | D6: 1 | E6: 1 | F6: 2 | G6: 2 | H6: 2 | I6: 3 | J6: 3 | K6: 3 | L6: 4 | M6: 4 | N6: 4 | O6: 5 | P6: 5 | Q6: 5
A7: 層級索引 | C7: 1 | D7: 2 | E7: 3 | F7: 1 | G7: 2 | H7: 3 | I7: 1 | J7: 2 | K7: 3 | L7: 1 | M7: 2 | N7: 3 | O7: 1 | P7: 2 | Q7: 3
A9: A. 規格（連結 Spec_Rack、DC_Cost）
A10: 計算用峰值 | B10: PF/GPU | C10: =INDEX(Spec_Rack!$C$35:$G$35,C$6) -> 0.989 | D10: =INDEX(Spec_Rack!$C$35:$G$35,D$6) -> 0.989 | E10: =INDEX(Spec_Rack!$C$35:$G$35,E$6) -> 0.989 | F10: =INDEX(Spec_Rack!$C$35:$G$35,F$6) -> 10 | G10: =INDEX(Spec_Rack!$C$35:$G$35,G$6) -> 10 | H10: =INDEX(Spec_Rack!$C$35:$G$35,H$6) -> 10 | I10: =INDEX(Spec_Rack!$C$35:$G$35,I$6) -> 15 | J10: =INDEX(Spec_Rack!$C$35:$G$35,J$6) -> 15 | ... Q10: =INDEX(Spec_Rack!$C$35:$G$35,Q$6) -> 73
A11: HBM 容量 | B11: GB/GPU | C11: =INDEX(Spec_Rack!$C$25:$G$25,C$6) -> 80 | D11: =INDEX(Spec_Rack!$C$25:$G$25,D$6) -> 80 | E11: =INDEX(Spec_Rack!$C$25:$G$25,E$6) -> 80 | F11: =INDEX(Spec_Rack!$C$25:$G$25,F$6) -> 186 | G11: =INDEX(Spec_Rack!$C$25:$G$25,G$6) -> 186 | H11: =INDEX(Spec_Rack!$C$25:$G$25,H$6) -> 186 | I11: =INDEX(Spec_Rack!$C$25:$G$25,I$6) -> 288 | J11: =INDEX(Spec_Rack!$C$25:$G$25,J$6) -> 288 | ... Q11: =INDEX(Spec_Rack!$C$25:$G$25,Q$6) -> 1024
A12: HBM 頻寬 | B12: TB/s/GPU | C12: =INDEX(Spec_Rack!$C$26:$G$26,C$6) -> 3.35 | D12: =INDEX(Spec_Rack!$C$26:$G$26,D$6) -> 3.35 | E12: =INDEX(Spec_Rack!$C$26:$G$26,E$6) -> 3.35 | F12: =INDEX(Spec_Rack!$C$26:$G$26,F$6) -> 8 | G12: =INDEX(Spec_Rack!$C$26:$G$26,G$6) -> 8 | H12: =INDEX(Spec_Rack!$C$26:$G$26,H$6) -> 8 | I12: =INDEX(Spec_Rack!$C$26:$G$26,I$6) -> 8 | J12: =INDEX(Spec_Rack!$C$26:$G$26,J$6) -> 8 | ... Q12: =INDEX(Spec_Rack!$C$26:$G$26,Q$6) -> 32
A13: EP 通訊頻寬（單向） | B13: TB/s/GPU | C13: =INDEX(Spec_Rack!$C$27:$G$27,C$6) -> 0.05 | D13: =INDEX(Spec_Rack!$C$27:$G$27,D$6) -> 0.05 | E13: =INDEX(Spec_Rack!$C$27:$G$27,E$6) -> 0.05 | F13: =INDEX(Spec_Rack!$C$27:$G$27,F$6) -> 0.9 | G13: =INDEX(Spec_Rack!$C$27:$G$27,G$6) -> 0.9 | H13: =INDEX(Spec_Rack!$C$27:$G$27,H$6) -> 0.9 | I13: =INDEX(Spec_Rack!$C$27:$G$27,I$6) -> 0.9 | J13: =INDEX(Spec_Rack!$C$27:$G$27,J$6) -> 0.9 | ... Q13: =INDEX(Spec_Rack!$C$27:$G$27,Q$6) -> 1.8
A14: decode EP 基準寬度 | B14: GPU | C14: =INDEX(Spec_Rack!$C$29:$G$29,C$6) -> 64 | D14: =INDEX(Spec_Rack!$C$29:$G$29,D$6) -> 64 | E14: =INDEX(Spec_Rack!$C$29:$G$29,E$6) -> 64 | F14: =INDEX(Spec_Rack!$C$29:$G$29,F$6) -> 32 | G14: =INDEX(Spec_Rack!$C$29:$G$29,G$6) -> 32 | H14: =INDEX(Spec_Rack!$C$29:$G$29,H$6) -> 32 | I14: =INDEX(Spec_Rack!$C$29:$G$29,I$6) -> 32 | J14: =INDEX(Spec_Rack!$C$29:$G$29,J$6) -> 32 | ... Q14: =INDEX(Spec_Rack!$C$29:$G$29,Q$6) -> 64
A15: 專家權重 bytes/param | B15: B | C15: =INDEX(Spec_Rack!$C$30:$G$30,C$6) -> 1 | D15: =INDEX(Spec_Rack!$C$30:$G$30,D$6) -> 1 | E15: =INDEX(Spec_Rack!$C$30:$G$30,E$6) -> 1 | F15: =INDEX(Spec_Rack!$C$30:$G$30,F$6) -> 0.5625 | G15: =INDEX(Spec_Rack!$C$30:$G$30,G$6) -> 0.5625 | H15: =INDEX(Spec_Rack!$C$30:$G$30,H$6) -> 0.5625 | I15: =INDEX(Spec_Rack!$C$30:$G$30,I$6) -> 0.5625 | J15: =INDEX(Spec_Rack!$C$30:$G$30,J$6) -> 0.5625 | ... Q15: =INDEX(Spec_Rack!$C$30:$G$30,Q$6) -> 0.5625
A16: 非專家權重 bytes/param | B16: B | C16: =INDEX(Spec_Rack!$C$31:$G$31,C$6) -> 1 | D16: =INDEX(Spec_Rack!$C$31:$G$31,D$6) -> 1 | E16: =INDEX(Spec_Rack!$C$31:$G$31,E$6) -> 1 | F16: =INDEX(Spec_Rack!$C$31:$G$31,F$6) -> 1 | G16: =INDEX(Spec_Rack!$C$31:$G$31,G$6) -> 1 | H16: =INDEX(Spec_Rack!$C$31:$G$31,H$6) -> 1 | I16: =INDEX(Spec_Rack!$C$31:$G$31,I$6) -> 1 | J16: =INDEX(Spec_Rack!$C$31:$G$31,J$6) -> 1 | ... Q16: =INDEX(Spec_Rack!$C$31:$G$31,Q$6) -> 1
A17: 每 prefill 實例 GPU 數 | B17: GPU | C17: =INDEX(Spec_Rack!$C$32:$G$32,C$6) -> 8 | D17: =INDEX(Spec_Rack!$C$32:$G$32,D$6) -> 8 | E17: =INDEX(Spec_Rack!$C$32:$G$32,E$6) -> 8 | F17: =INDEX(Spec_Rack!$C$32:$G$32,F$6) -> 4 | G17: =INDEX(Spec_Rack!$C$32:$G$32,G$6) -> 4 | H17: =INDEX(Spec_Rack!$C$32:$G$32,H$6) -> 4 | I17: =INDEX(Spec_Rack!$C$32:$G$32,I$6) -> 4 | J17: =INDEX(Spec_Rack!$C$32:$G$32,J$6) -> 4 | ... Q17: =INDEX(Spec_Rack!$C$32:$G$32,Q$6) -> 8
A18: GPU 封裝／架 | B18: 顆 | C18: =INDEX(Spec_Rack!$C$6:$G$6,C$6) -> 32 | D18: =INDEX(Spec_Rack!$C$6:$G$6,D$6) -> 32 | E18: =INDEX(Spec_Rack!$C$6:$G$6,E$6) -> 32 | F18: =INDEX(Spec_Rack!$C$6:$G$6,F$6) -> 72 | G18: =INDEX(Spec_Rack!$C$6:$G$6,G$6) -> 72 | H18: =INDEX(Spec_Rack!$C$6:$G$6,H$6) -> 72 | I18: =INDEX(Spec_Rack!$C$6:$G$6,I$6) -> 72 | J18: =INDEX(Spec_Rack!$C$6:$G$6,J$6) -> 72 | ... Q18: =INDEX(Spec_Rack!$C$6:$G$6,Q$6) -> 144
A19: GPU 功率 | B19: W | C19: =INDEX(Spec_Rack!$C$33:$G$33,C$6) -> 700 | D19: =INDEX(Spec_Rack!$C$33:$G$33,D$6) -> 700 | E19: =INDEX(Spec_Rack!$C$33:$G$33,E$6) -> 700 | F19: =INDEX(Spec_Rack!$C$33:$G$33,F$6) -> 1200 | G19: =INDEX(Spec_Rack!$C$33:$G$33,G$6) -> 1200 | H19: =INDEX(Spec_Rack!$C$33:$G$33,H$6) -> 1200 | I19: =INDEX(Spec_Rack!$C$33:$G$33,I$6) -> 1400 | J19: =INDEX(Spec_Rack!$C$33:$G$33,J$6) -> 1400 | ... Q19: =INDEX(Spec_Rack!$C$33:$G$33,Q$6) -> 3600
A20: HBM 存取能量 | B20: pJ/B | C20: =INDEX(Spec_Rack!$C$34:$G$34,C$6) -> 31 | D20: =INDEX(Spec_Rack!$C$34:$G$34,D$6) -> 31 | E20: =INDEX(Spec_Rack!$C$34:$G$34,E$6) -> 31 | F20: =INDEX(Spec_Rack!$C$34:$G$34,F$6) -> 25 | G20: =INDEX(Spec_Rack!$C$34:$G$34,G$6) -> 25 | H20: =INDEX(Spec_Rack!$C$34:$G$34,H$6) -> 25 | I20: =INDEX(Spec_Rack!$C$34:$G$34,I$6) -> 25 | J20: =INDEX(Spec_Rack!$C$34:$G$34,J$6) -> 25 | ... Q20: =INDEX(Spec_Rack!$C$34:$G$34,Q$6) -> 18
A21: 每 GW 機架數（功率情境） | B21: 架 | C21: =INDEX(DC_Cost!$C$12:$Q$12,3*(C$6-1)+2) -> 22439 | D21: =INDEX(DC_Cost!$C$12:$Q$12,3*(D$6-1)+2) -> 22439 | E21: =INDEX(DC_Cost!$C$12:$Q$12,3*(E$6-1)+2) -> 22439 | F21: =INDEX(DC_Cost!$C$12:$Q$12,3*(F$6-1)+2) -> 7076 | G21: =INDEX(DC_Cost!$C$12:$Q$12,3*(G$6-1)+2) -> 7076 | H21: =INDEX(DC_Cost!$C$12:$Q$12,3*(H$6-1)+2) -> 7076 | I21: =INDEX(DC_Cost!$C$12:$Q$12,3*(I$6-1)+2) -> 6715 | J21: =INDEX(DC_Cost!$C$12:$Q$12,3*(J$6-1)+2) -> 6715 | ... Q21: =INDEX(DC_Cost!$C$12:$Q$12,3*(Q$6-1)+2) -> 1533
A22: 每架配電設計功率 | B22: kW | C22: =INDEX(DC_Cost!$C$11:$Q$11,3*(C$6-1)+2) -> 41 | D22: =INDEX(DC_Cost!$C$11:$Q$11,3*(D$6-1)+2) -> 41 | E22: =INDEX(DC_Cost!$C$11:$Q$11,3*(E$6-1)+2) -> 41 | F22: =INDEX(DC_Cost!$C$11:$Q$11,3*(F$6-1)+2) -> 130 | G22: =INDEX(DC_Cost!$C$11:$Q$11,3*(G$6-1)+2) -> 130 | H22: =INDEX(DC_Cost!$C$11:$Q$11,3*(H$6-1)+2) -> 130 | I22: =INDEX(DC_Cost!$C$11:$Q$11,3*(I$6-1)+2) -> 137 | J22: =INDEX(DC_Cost!$C$11:$Q$11,3*(J$6-1)+2) -> 137 | ... Q22: =INDEX(DC_Cost!$C$11:$Q$11,3*(Q$6-1)+2) -> 600
A23: B. 架構（連結 Arch）
A24: 啟用參數 | B24: B | C24: =INDEX(Arch!$C$7:$E$7,C$7) -> 13 | D24: =INDEX(Arch!$C$7:$E$7,D$7) -> 49 | E24: =INDEX(Arch!$C$7:$E$7,E$7) -> 180 | F24: =INDEX(Arch!$C$7:$E$7,F$7) -> 13 | G24: =INDEX(Arch!$C$7:$E$7,G$7) -> 49 | H24: =INDEX(Arch!$C$7:$E$7,H$7) -> 180 | I24: =INDEX(Arch!$C$7:$E$7,I$7) -> 13 | J24: =INDEX(Arch!$C$7:$E$7,J$7) -> 49 | ... Q24: =INDEX(Arch!$C$7:$E$7,Q$7) -> 180
A25: 層數 | B25: 層 | C25: =INDEX(Arch!$C$8:$E$8,C$7) -> 43 | D25: =INDEX(Arch!$C$8:$E$8,D$7) -> 61 | E25: =INDEX(Arch!$C$8:$E$8,E$7) -> 100 | F25: =INDEX(Arch!$C$8:$E$8,F$7) -> 43 | G25: =INDEX(Arch!$C$8:$E$8,G$7) -> 61 | H25: =INDEX(Arch!$C$8:$E$8,H$7) -> 100 | I25: =INDEX(Arch!$C$8:$E$8,I$7) -> 43 | J25: =INDEX(Arch!$C$8:$E$8,J$7) -> 61 | ... Q25: =INDEX(Arch!$C$8:$E$8,Q$7) -> 100
A26: d_model | C26: =INDEX(Arch!$C$9:$E$9,C$7) -> 4096 | D26: =INDEX(Arch!$C$9:$E$9,D$7) -> 7168 | E26: =INDEX(Arch!$C$9:$E$9,E$7) -> 12288 | F26: =INDEX(Arch!$C$9:$E$9,F$7) -> 4096 | G26: =INDEX(Arch!$C$9:$E$9,G$7) -> 7168 | H26: =INDEX(Arch!$C$9:$E$9,H$7) -> 12288 | I26: =INDEX(Arch!$C$9:$E$9,I$7) -> 4096 | J26: =INDEX(Arch!$C$9:$E$9,J$7) -> 7168 | ... Q26: =INDEX(Arch!$C$9:$E$9,Q$7) -> 12288
A27: 啟用 routed experts | C27: =INDEX(Arch!$C$13:$E$13,C$7) -> 6 | D27: =INDEX(Arch!$C$13:$E$13,D$7) -> 6 | E27: =INDEX(Arch!$C$13:$E$13,E$7) -> 16 | F27: =INDEX(Arch!$C$13:$E$13,F$7) -> 6 | G27: =INDEX(Arch!$C$13:$E$13,G$7) -> 6 | H27: =INDEX(Arch!$C$13:$E$13,H$7) -> 16 | I27: =INDEX(Arch!$C$13:$E$13,I$7) -> 6 | J27: =INDEX(Arch!$C$13:$E$13,J$7) -> 6 | ... Q27: =INDEX(Arch!$C$13:$E$13,Q$7) -> 16
A28: 非專家參數 | B28: B | C28: =INDEX(Arch!$C$28:$E$28,C$7) -> 5.412 | D28: =INDEX(Arch!$C$28:$E$28,D$7) -> 20.277778 | E28: =INDEX(Arch!$C$28:$E$28,E$7) -> 49.072581 | F28: =INDEX(Arch!$C$28:$E$28,F$7) -> 5.412 | G28: =INDEX(Arch!$C$28:$E$28,G$7) -> 20.277778 | H28: =INDEX(Arch!$C$28:$E$28,H$7) -> 49.072581 | I28: =INDEX(Arch!$C$28:$E$28,I$7) -> 5.412 | J28: =INDEX(Arch!$C$28:$E$28,J$7) -> 20.277778 | ... Q28: =INDEX(Arch!$C$28:$E$28,Q$7) -> 49.072581
A29: 專家參數 | B29: B | C29: =INDEX(Arch!$C$29:$E$29,C$7) -> 278.588 | D29: =INDEX(Arch!$C$29:$E$29,D$7) -> 1579.7222 | E29: =INDEX(Arch!$C$29:$E$29,E$7) -> 3950.9274 | F29: =INDEX(Arch!$C$29:$E$29,F$7) -> 278.588 | G29: =INDEX(Arch!$C$29:$E$29,G$7) -> 1579.7222 | H29: =INDEX(Arch!$C$29:$E$29,H$7) -> 3950.9274 | I29: =INDEX(Arch!$C$29:$E$29,I$7) -> 278.588 | J29: =INDEX(Arch!$C$29:$E$29,J$7) -> 1579.7222 | ... Q29: =INDEX(Arch!$C$29:$E$29,Q$7) -> 3950.9274
A30: KV bytes/token | B30: B | C30: =INDEX(Arch!$C$25:$E$25,C$7) -> 2795 | D30: =INDEX(Arch!$C$25:$E$25,D$7) -> 3965 | E30: =INDEX(Arch!$C$25:$E$25,E$7) -> 57600 | F30: =INDEX(Arch!$C$25:$E$25,F$7) -> 2795 | G30: =INDEX(Arch!$C$25:$E$25,G$7) -> 3965 | H30: =INDEX(Arch!$C$25:$E$25,H$7) -> 57600 | I30: =INDEX(Arch!$C$25:$E$25,I$7) -> 2795 | J30: =INDEX(Arch!$C$25:$E$25,J$7) -> 3965 | ... Q30: =INDEX(Arch!$C$25:$E$25,Q$7) -> 57600
A31: 注意力 FLOPs／被注意 token | B31: FLOP | C31: =INDEX(Arch!$C$30:$E$30,C$7) -> 5636096 | D31: =INDEX(Arch!$C$30:$E$30,D$7) -> 15990784 | E31: =INDEX(Arch!$C$30:$E$30,E$7) -> 4915200 | F31: =INDEX(Arch!$C$30:$E$30,F$7) -> 5636096 | G31: =INDEX(Arch!$C$30:$E$30,G$7) -> 15990784 | H31: =INDEX(Arch!$C$30:$E$30,H$7) -> 4915200 | I31: =INDEX(Arch!$C$30:$E$30,I$7) -> 5636096 | J31: =INDEX(Arch!$C$30:$E$30,J$7) -> 15990784 | ... Q31: =INDEX(Arch!$C$30:$E$30,Q$7) -> 4915200
A32: 全注意力層比例 | B32: % | C32: =INDEX(Arch!$C$16:$E$16,C$7) -> 0.5 | D32: =INDEX(Arch!$C$16:$E$16,D$7) -> 0.5 | E32: =INDEX(Arch!$C$16:$E$16,E$7) -> 1 | F32: =INDEX(Arch!$C$16:$E$16,F$7) -> 0.5 | G32: =INDEX(Arch!$C$16:$E$16,G$7) -> 0.5 | H32: =INDEX(Arch!$C$16:$E$16,H$7) -> 1 | I32: =INDEX(Arch!$C$16:$E$16,I$7) -> 0.5 | J32: =INDEX(Arch!$C$16:$E$16,J$7) -> 0.5 | ... Q32: =INDEX(Arch!$C$16:$E$16,Q$7) -> 1
A33: 全注意力跨度上限 | B33: tok | C33: =INDEX(Arch!$C$17:$E$17,C$7) -> 4224 | D33: =INDEX(Arch!$C$17:$E$17,D$7) -> 4224 | E33: =INDEX(Arch!$C$17:$E$17,E$7) -> 0 | F33: =INDEX(Arch!$C$17:$E$17,F$7) -> 4224 | G33: =INDEX(Arch!$C$17:$E$17,G$7) -> 4224 | H33: =INDEX(Arch!$C$17:$E$17,H$7) -> 0 | I33: =INDEX(Arch!$C$17:$E$17,I$7) -> 4224 | J33: =INDEX(Arch!$C$17:$E$17,J$7) -> 4224 | ... Q33: =INDEX(Arch!$C$17:$E$17,Q$7) -> 0
A34: 其他層壓縮比 | B34: x | C34: =INDEX(Arch!$C$18:$E$18,C$7) -> 128 | D34: =INDEX(Arch!$C$18:$E$18,D$7) -> 128 | E34: =INDEX(Arch!$C$18:$E$18,E$7) -> 1 | F34: =INDEX(Arch!$C$18:$E$18,F$7) -> 128 | G34: =INDEX(Arch!$C$18:$E$18,G$7) -> 128 | H34: =INDEX(Arch!$C$18:$E$18,H$7) -> 1 | I34: =INDEX(Arch!$C$18:$E$18,I$7) -> 128 | J34: =INDEX(Arch!$C$18:$E$18,J$7) -> 128 | ... Q34: =INDEX(Arch!$C$18:$E$18,Q$7) -> 1
A35: 其他層滑動窗 | B35: tok | C35: =INDEX(Arch!$C$19:$E$19,C$7) -> 128 | D35: =INDEX(Arch!$C$19:$E$19,D$7) -> 128 | E35: =INDEX(Arch!$C$19:$E$19,E$7) -> 0 | F35: =INDEX(Arch!$C$19:$E$19,F$7) -> 128 | G35: =INDEX(Arch!$C$19:$E$19,G$7) -> 128 | H35: =INDEX(Arch!$C$19:$E$19,H$7) -> 0 | I35: =INDEX(Arch!$C$19:$E$19,I$7) -> 128 | J35: =INDEX(Arch!$C$19:$E$19,J$7) -> 128 | ... Q35: =INDEX(Arch!$C$19:$E$19,Q$7) -> 0
A36: C. 服務、SLO 與校準參數
A37: SLO：每用戶 decode 速度下限 | B37: tok/s | C37: =INDEX(Serving!$C$21:$E$21,C$7) -> 120 | D37: =INDEX(Serving!$C$21:$E$21,D$7) -> 65 | E37: =INDEX(Serving!$C$21:$E$21,E$7) -> 55 | F37: =INDEX(Serving!$C$21:$E$21,F$7) -> 120 | G37: =INDEX(Serving!$C$21:$E$21,G$7) -> 65 | H37: =INDEX(Serving!$C$21:$E$21,H$7) -> 55 | I37: =INDEX(Serving!$C$21:$E$21,I$7) -> 120 | J37: =INDEX(Serving!$C$21:$E$21,J$7) -> 65 | ... Q37: =INDEX(Serving!$C$21:$E$21,Q$7) -> 55
A38: TTFT 上限 | B38: s | C38: =INDEX(Serving!$C$22:$E$22,C$7) -> 2 | D38: =INDEX(Serving!$C$22:$E$22,D$7) -> 3 | E38: =INDEX(Serving!$C$22:$E$22,E$7) -> 5 | F38: =INDEX(Serving!$C$22:$E$22,F$7) -> 2 | G38: =INDEX(Serving!$C$22:$E$22,G$7) -> 3 | H38: =INDEX(Serving!$C$22:$E$22,H$7) -> 5 | I38: =INDEX(Serving!$C$22:$E$22,I$7) -> 2 | J38: =INDEX(Serving!$C$22:$E$22,J$7) -> 3 | ... Q38: =INDEX(Serving!$C$22:$E$22,Q$7) -> 5
A39: 參考 ISL | B39: tok | C39: =INDEX(Serving!$C$23:$E$23,C$7) -> 8192 | D39: =INDEX(Serving!$C$23:$E$23,D$7) -> 16384 | E39: =INDEX(Serving!$C$23:$E$23,E$7) -> 32768 | F39: =INDEX(Serving!$C$23:$E$23,F$7) -> 8192 | G39: =INDEX(Serving!$C$23:$E$23,G$7) -> 16384 | H39: =INDEX(Serving!$C$23:$E$23,H$7) -> 32768 | I39: =INDEX(Serving!$C$23:$E$23,I$7) -> 8192 | J39: =INDEX(Serving!$C$23:$E$23,J$7) -> 16384 | ... Q39: =INDEX(Serving!$C$23:$E$23,Q$7) -> 32768
A40: 參考 OSL（含思考） | B40: tok | C40: =INDEX(Serving!$C$24:$E$24,C$7) -> 1024 | D40: =INDEX(Serving!$C$24:$E$24,D$7) -> 2048 | E40: =INDEX(Serving!$C$24:$E$24,E$7) -> 4096 | F40: =INDEX(Serving!$C$24:$E$24,F$7) -> 1024 | G40: =INDEX(Serving!$C$24:$E$24,G$7) -> 2048 | H40: =INDEX(Serving!$C$24:$E$24,H$7) -> 4096 | I40: =INDEX(Serving!$C$24:$E$24,I$7) -> 1024 | J40: =INDEX(Serving!$C$24:$E$24,J$7) -> 2048 | ... Q40: =INDEX(Serving!$C$24:$E$24,Q$7) -> 4096
A41: decode 平均上下文 | B41: tok | C41: =C39+C40/2 -> 8704 | D41: =D39+D40/2 -> 17408 | E41: =E39+E40/2 -> 34816 | F41: =F39+F40/2 -> 8704 | G41: =G39+G40/2 -> 17408 | H41: =H39+H40/2 -> 34816 | I41: =I39+I40/2 -> 8704 | J41: =J39+J40/2 -> 17408 | ... Q41: =Q39+Q40/2 -> 34816
A42: prefill 平均位置 | B42: tok | C42: =C39/2 -> 4096 | D42: =D39/2 -> 8192 | E42: =E39/2 -> 16384 | F42: =F39/2 -> 4096 | G42: =G39/2 -> 8192 | H42: =H39/2 -> 16384 | I42: =I39/2 -> 4096 | J42: =J39/2 -> 8192 | ... Q42: =Q39/2 -> 16384
A43: MTP 草稿數 | B43: tok | C43: =Serving!$C$6 -> 3 | D43: =Serving!$C$6 -> 3 | E43: =Serving!$C$6 -> 3 | F43: =Serving!$C$6 -> 3 | G43: =Serving!$C$6 -> 3 | H43: =Serving!$C$6 -> 3 | I43: =Serving!$C$6 -> 3 | J43: =Serving!$C$6 -> 3 | ... Q43: =Serving!$C$6 -> 3
A44: 草稿接受率 | B44: % | C44: =Serving!$C$7 -> 0.7 | D44: =Serving!$C$7 -> 0.7 | E44: =Serving!$C$7 -> 0.7 | F44: =Serving!$C$7 -> 0.7 | G44: =Serving!$C$7 -> 0.7 | H44: =Serving!$C$7 -> 0.7 | I44: =Serving!$C$7 -> 0.7 | J44: =Serving!$C$7 -> 0.7 | ... Q44: =Serving!$C$7 -> 0.7
A45: 每步期望接受 token | B45: tok | C45: =(1-C44^(C43+1))/(1-C44) -> 2.533 | D45: =(1-D44^(D43+1))/(1-D44) -> 2.533 | E45: =(1-E44^(E43+1))/(1-E44) -> 2.533 | F45: =(1-F44^(F43+1))/(1-F44) -> 2.533 | G45: =(1-G44^(G43+1))/(1-G44) -> 2.533 | H45: =(1-H44^(H43+1))/(1-H44) -> 2.533 | I45: =(1-I44^(I43+1))/(1-I44) -> 2.533 | J45: =(1-J44^(J43+1))/(1-J44) -> 2.533 | ... Q45: =(1-Q44^(Q43+1))/(1-Q44) -> 2.533
A46: 實測→生產效率折減 | B46: x | C46: =Serving!$C$18 -> 1 | D46: =Serving!$C$18 -> 1 | E46: =Serving!$C$18 -> 1 | F46: =Serving!$C$18 -> 1 | G46: =Serving!$C$18 -> 1 | H46: =Serving!$C$18 -> 1 | I46: =Serving!$C$18 -> 1 | J46: =Serving!$C$18 -> 1 | ... Q46: =Serving!$C$18 -> 1
A47: η_p（prefill 占峰值；含折減） | B47: % | C47: =INDEX(Calib!$C$70:$G$70,C$6)*C46 -> 0.3 | D47: =INDEX(Calib!$C$70:$G$70,D$6)*D46 -> 0.3 | E47: =INDEX(Calib!$C$70:$G$70,E$6)*E46 -> 0.3 | F47: =INDEX(Calib!$C$70:$G$70,F$6)*F46 -> 0.3 | G47: =INDEX(Calib!$C$70:$G$70,G$6)*G46 -> 0.3 | H47: =INDEX(Calib!$C$70:$G$70,H$6)*H46 -> 0.3 | I47: =INDEX(Calib!$C$70:$G$70,I$6)*I46 -> 0.3 | J47: =INDEX(Calib!$C$70:$G$70,J$6)*J46 -> 0.3 | ... Q47: =INDEX(Calib!$C$70:$G$70,Q$6)*Q46 -> 0.3
A48: η_d 情境倍數（基準 1；Sens_Perf 使用） | B48: x | C48: 1 | D48: 1 | E48: 1 | F48: 1 | G48: 1 | H48: 1 | I48: 1 | J48: 1 | K48: 1 | L48: 1 | M48: 1 | N48: 1 | O48: 1 | P48: 1 | Q48: 1
A49: η_d（decode 每序列算力效率；含折減） | B49: % | C49: =INDEX(Calib!$C$68:$G$68,C$6)*C48*C46 -> 0.10812714 | D49: =INDEX(Calib!$C$68:$G$68,D$6)*D48*D46 -> 0.10812714 | E49: =INDEX(Calib!$C$68:$G$68,E$6)*E48*E46 -> 0.10812714 | F49: =INDEX(Calib!$C$68:$G$68,F$6)*F48*F46 -> 0.036042379 | G49: =INDEX(Calib!$C$68:$G$68,G$6)*G48*G46 -> 0.036042379 | H49: =INDEX(Calib!$C$68:$G$68,H$6)*H48*H46 -> 0.036042379 | I49: =INDEX(Calib!$C$68:$G$68,I$6)*I48*I46 -> 0.036042379 | J49: =INDEX(Calib!$C$68:$G$68,J$6)*J48*J46 -> 0.036042379 | ... Q49: =INDEX(Calib!$C$68:$G$68,Q$6)*Q48*Q46 -> 0.036042379
A50: 每層延遲情境倍數（基準 1） | B50: x | C50: 1 | D50: 1 | E50: 1 | F50: 1 | G50: 1 | H50: 1 | I50: 1 | J50: 1 | K50: 1 | L50: 1 | M50: 1 | N50: 1 | O50: 1 | P50: 1 | Q50: 1
A51: 每層每次前向固定延遲（含折減） | B51: µs | C51: =INDEX(Calib!$C$69:$G$69,C$6)*C50/C46 -> 240.41784 | D51: =INDEX(Calib!$C$69:$G$69,D$6)*D50/D46 -> 240.41784 | E51: =INDEX(Calib!$C$69:$G$69,E$6)*E50/E46 -> 240.41784 | F51: =INDEX(Calib!$C$69:$G$69,F$6)*F50/F46 -> 160.27856 | G51: =INDEX(Calib!$C$69:$G$69,G$6)*G50/G46 -> 160.27856 | H51: =INDEX(Calib!$C$69:$G$69,H$6)*H50/H46 -> 160.27856 | I51: =INDEX(Calib!$C$69:$G$69,I$6)*I50/I46 -> 160.27856 | J51: =INDEX(Calib!$C$69:$G$69,J$6)*J50/J46 -> 160.27856 | ... Q51: =INDEX(Calib!$C$69:$G$69,Q$6)*Q50/Q46 -> 160.27856
A52: HBM 保留比例 | B52: % | C52: =Serving!$C$9 -> 0.1 | D52: =Serving!$C$9 -> 0.1 | E52: =Serving!$C$9 -> 0.1 | F52: =Serving!$C$9 -> 0.1 | G52: =Serving!$C$9 -> 0.1 | H52: =Serving!$C$9 -> 0.1 | I52: =Serving!$C$9 -> 0.1 | J52: =Serving!$C$9 -> 0.1 | ... Q52: =Serving!$C$9 -> 0.1
A53: 非專家權重占 HBM 上限 | B53: % | C53: =Serving!$C$10 -> 0.2 | D53: =Serving!$C$10 -> 0.2 | E53: =Serving!$C$10 -> 0.2 | F53: =Serving!$C$10 -> 0.2 | G53: =Serving!$C$10 -> 0.2 | H53: =Serving!$C$10 -> 0.2 | I53: =Serving!$C$10 -> 0.2 | J53: =Serving!$C$10 -> 0.2 | ... Q53: =Serving!$C$10 -> 0.2
A54: 專家權重占 HBM 上限 | B54: % | C54: =Serving!$C$11 -> 0.4 | D54: =Serving!$C$11 -> 0.4 | E54: =Serving!$C$11 -> 0.4 | F54: =Serving!$C$11 -> 0.4 | G54: =Serving!$C$11 -> 0.4 | H54: =Serving!$C$11 -> 0.4 | I54: =Serving!$C$11 -> 0.4 | J54: =Serving!$C$11 -> 0.4 | ... Q54: =Serving!$C$11 -> 0.4
A55: EP 啟用值 bytes/元素 | B55: B | C55: =Serving!$C$12 -> 3 | D55: =Serving!$C$12 -> 3 | E55: =Serving!$C$12 -> 3 | F55: =Serving!$C$12 -> 3 | G55: =Serving!$C$12 -> 3 | H55: =Serving!$C$12 -> 3 | I55: =Serving!$C$12 -> 3 | J55: =Serving!$C$12 -> 3 | ... Q55: =Serving!$C$12 -> 3
A56: KV 讀取效率 | B56: % | C56: =Serving!$C$13 -> 0.7 | D56: =Serving!$C$13 -> 0.7 | E56: =Serving!$C$13 -> 0.7 | F56: =Serving!$C$13 -> 0.7 | G56: =Serving!$C$13 -> 0.7 | H56: =Serving!$C$13 -> 0.7 | I56: =Serving!$C$13 -> 0.7 | J56: =Serving!$C$13 -> 0.7 | ... Q56: =Serving!$C$13 -> 0.7
A57: EP 通訊效率 | B57: % | C57: =Serving!$C$14 -> 0.7 | D57: =Serving!$C$14 -> 0.7 | E57: =Serving!$C$14 -> 0.7 | F57: =Serving!$C$14 -> 0.7 | G57: =Serving!$C$14 -> 0.7 | H57: =Serving!$C$14 -> 0.7 | I57: =Serving!$C$14 -> 0.7 | J57: =Serving!$C$14 -> 0.7 | ... Q57: =Serving!$C$14 -> 0.7
A58: 快取載入頻寬 | B58: TB/s | C58: =Serving!$C$15 -> 0.1 | D58: =Serving!$C$15 -> 0.1 | E58: =Serving!$C$15 -> 0.1 | F58: =Serving!$C$15 -> 0.1 | G58: =Serving!$C$15 -> 0.1 | H58: =Serving!$C$15 -> 0.1 | I58: =Serving!$C$15 -> 0.1 | J58: =Serving!$C$15 -> 0.1 | ... Q58: =Serving!$C$15 -> 0.1
A59: D. 每 token 計算量
A60: decode 被注意 token 數 | B60: tok | C60: =C32*IF(C33=0,C41,MIN(C41,C33))+(1-C32)*(C41/C34+C35) -> 2210 | D60: =D32*IF(D33=0,D41,MIN(D41,D33))+(1-D32)*(D41/D34+D35) -> 2244 | E60: =E32*IF(E33=0,E41,MIN(E41,E33))+(1-E32)*(E41/E34+E35) -> 34816 | F60: =F32*IF(F33=0,F41,MIN(F41,F33))+(1-F32)*(F41/F34+F35) -> 2210 | G60: =G32*IF(G33=0,G41,MIN(G41,G33))+(1-G32)*(G41/G34+G35) -> 2244 | H60: =H32*IF(H33=0,H41,MIN(H41,H33))+(1-H32)*(H41/H34+H35) -> 34816 | I60: =I32*IF(I33=0,I41,MIN(I41,I33))+(1-I32)*(I41/I34+I35) -> 2210 | J60: =J32*IF(J33=0,J41,MIN(J41,J33))+(1-J32)*(J41/J34+J35) -> 2244 | ... Q60: =Q32*IF(Q33=0,Q41,MIN(Q41,Q33))+(1-Q32)*(Q41/Q34+Q35) -> 34816
A61: decode FLOPs/token | B61: GFLOP | C61: =(2*C24*1000000000+C31*C60)/1000000000 -> 38.455772 | D61: =(2*D24*1000000000+D31*D60)/1000000000 -> 133.88332 | E61: =(2*E24*1000000000+E31*E60)/1000000000 -> 531.1276 | F61: =(2*F24*1000000000+F31*F60)/1000000000 -> 38.455772 | G61: =(2*G24*1000000000+G31*G60)/1000000000 -> 133.88332 | H61: =(2*H24*1000000000+H31*H60)/1000000000 -> 531.1276 | I61: =(2*I24*1000000000+I31*I60)/1000000000 -> 38.455772 | J61: =(2*J24*1000000000+J31*J60)/1000000000 -> 133.88332 | ... Q61: =(2*Q24*1000000000+Q31*Q60)/1000000000 -> 531.1276
A62: prefill 被注意 token 數 | B62: tok | C62: =C32*IF(C33=0,C42,MIN(C42,C33))+(1-C32)*(C42/C34+C35) -> 2128 | D62: =D32*IF(D33=0,D42,MIN(D42,D33))+(1-D32)*(D42/D34+D35) -> 2208 | E62: =E32*IF(E33=0,E42,MIN(E42,E33))+(1-E32)*(E42/E34+E35) -> 16384 | F62: =F32*IF(F33=0,F42,MIN(F42,F33))+(1-F32)*(F42/F34+F35) -> 2128 | G62: =G32*IF(G33=0,G42,MIN(G42,G33))+(1-G32)*(G42/G34+G35) -> 2208 | H62: =H32*IF(H33=0,H42,MIN(H42,H33))+(1-H32)*(H42/H34+H35) -> 16384 | I62: =I32*IF(I33=0,I42,MIN(I42,I33))+(1-I32)*(I42/I34+I35) -> 2128 | J62: =J32*IF(J33=0,J42,MIN(J42,J33))+(1-J32)*(J42/J34+J35) -> 2208 | ... Q62: =Q32*IF(Q33=0,Q42,MIN(Q42,Q33))+(1-Q32)*(Q42/Q34+Q35) -> 16384
A63: prefill FLOPs/token | B63: GFLOP | C63: =(2*C24*1000000000+C31*C62)/1000000000 -> 37.993612 | D63: =(2*D24*1000000000+D31*D62)/1000000000 -> 133.30765 | E63: =(2*E24*1000000000+E31*E62)/1000000000 -> 440.53064 | F63: =(2*F24*1000000000+F31*F62)/1000000000 -> 37.993612 | G63: =(2*G24*1000000000+G31*G62)/1000000000 -> 133.30765 | H63: =(2*H24*1000000000+H31*H62)/1000000000 -> 440.53064 | I63: =(2*I24*1000000000+I31*I62)/1000000000 -> 37.993612 | J63: =(2*J24*1000000000+J31*J62)/1000000000 -> 133.30765 | ... Q63: =(2*Q24*1000000000+Q31*Q62)/1000000000 -> 440.53064
A64: E. 記憶體配置（attention DP＋wide EP；每 GPU）
A65: 可用 HBM | B65: GB | C65: =C11*(1-C52) -> 72 | D65: =D11*(1-D52) -> 72 | E65: =E11*(1-E52) -> 72 | F65: =F11*(1-F52) -> 167.4 | G65: =G11*(1-G52) -> 167.4 | H65: =H11*(1-H52) -> 167.4 | I65: =I11*(1-I52) -> 259.2 | J65: =J11*(1-J52) -> 259.2 | ... Q65: =Q11*(1-Q52) -> 921.6
A66: 注意力 TP 度（自動） | C66: =MAX(1,CEILING(C28*C16/(C53*C65),1)) -> 1 | D66: =MAX(1,CEILING(D28*D16/(D53*D65),1)) -> 2 | E66: =MAX(1,CEILING(E28*E16/(E53*E65),1)) -> 4 | F66: =MAX(1,CEILING(F28*F16/(F53*F65),1)) -> 1 | G66: =MAX(1,CEILING(G28*G16/(G53*G65),1)) -> 1 | H66: =MAX(1,CEILING(H28*H16/(H53*H65),1)) -> 2 | I66: =MAX(1,CEILING(I28*I16/(I53*I65),1)) -> 1 | J66: =MAX(1,CEILING(J28*J16/(J53*J65),1)) -> 1 | ... Q66: =MAX(1,CEILING(Q28*Q16/(Q53*Q65),1)) -> 1
A67: decode EP 寬度（自動） | B67: GPU | C67: =MAX(C14,CEILING(C29*C15/(C54*C65),1)) -> 64 | D67: =MAX(D14,CEILING(D29*D15/(D54*D65),1)) -> 64 | E67: =MAX(E14,CEILING(E29*E15/(E54*E65),1)) -> 138 | F67: =MAX(F14,CEILING(F29*F15/(F54*F65),1)) -> 32 | G67: =MAX(G14,CEILING(G29*G15/(G54*G65),1)) -> 32 | H67: =MAX(H14,CEILING(H29*H15/(H54*H65),1)) -> 34 | I67: =MAX(I14,CEILING(I29*I15/(I54*I65),1)) -> 32 | J67: =MAX(J14,CEILING(J29*J15/(J54*J65),1)) -> 32 | ... Q67: =MAX(Q14,CEILING(Q29*Q15/(Q54*Q65),1)) -> 64
A68: 每 GPU 權重 | B68: GB | C68: =C28*C16/C66+C29*C15/C67 -> 9.7649375 | D68: =D28*D16/D66+D29*D15/D67 -> 34.822049 | E68: =E28*E16/E66+E29*E15/E67 -> 40.898054 | F68: =F28*F16/F66+F29*F15/F67 -> 10.309055 | G68: =G28*G16/G66+G29*G15/G67 -> 48.046332 | H68: =H28*H16/H66+H29*H15/H67 -> 89.900898 | I68: =I28*I16/I66+I29*I15/I67 -> 10.309055 | J68: =J28*J16/J66+J29*J15/J67 -> 48.046332 | ... Q68: =Q28*Q16/Q66+Q29*Q15/Q67 -> 83.797529
A69: 權重占可用 HBM | B69: % | C69: =C68/C65 -> 0.13562413 | D69: =D68/D65 -> 0.48363956 | E69: =E68/E65 -> 0.56802853 | F69: =F68/F65 -> 0.061583361 | G69: =G68/G65 -> 0.28701513 | H69: =H68/H65 -> 0.5370424 | I69: =I68/I65 -> 0.039772588 | J69: =J68/J65 -> 0.18536394 | ... Q69: =Q68/Q65 -> 0.090926138
A70: F. Prefill（算力受限）
A71: prefill tok/s（每 prefill GPU） | B71: tok/s | C71: =C47*C10*1000000000000000/(C63*1000000000) -> 7809.2074 | D71: =D47*D10*1000000000000000/(D63*1000000000) -> 2225.6787 | E71: =E47*E10*1000000000000000/(E63*1000000000) -> 673.50594 | F71: =F47*F10*1000000000000000/(F63*1000000000) -> 78960.642 | G71: =G47*G10*1000000000000000/(G63*1000000000) -> 22504.335 | H71: =H47*H10*1000000000000000/(H63*1000000000) -> 6809.969 | I71: =I47*I10*1000000000000000/(I63*1000000000) -> 118440.96 | J71: =J47*J10*1000000000000000/(J63*1000000000) -> 33756.502 | ... Q71: =Q47*Q10*1000000000000000/(Q63*1000000000) -> 49712.774
A72: TTFT（計算部分） | B72: s | C72: =C39*C63*1000000000/(C47*C10*1000000000000000*C17) -> 0.13112726 | D72: =D39*D63*1000000000/(D47*D10*1000000000000000*D17) -> 0.92016875 | E72: =E39*E63*1000000000/(E47*E10*1000000000000000*E17) -> 6.0816093 | F72: =F39*F63*1000000000/(F47*F10*1000000000000000*F17) -> 0.025936973 | G72: =G39*G63*1000000000/(G47*G10*1000000000000000*G17) -> 0.18200938 | H72: =H39*H63*1000000000/(H47*H10*1000000000000000*H17) -> 1.2029423 | I72: =I39*I63*1000000000/(I47*I10*1000000000000000*I17) -> 0.017291315 | J72: =J39*J63*1000000000/(J47*J10*1000000000000000*J17) -> 0.12133959 | ... Q72: =Q39*Q63*1000000000/(Q47*Q10*1000000000000000*Q17) -> 0.08239331
A73: TTFT 符合上限 | C73: =IF(C72<=C38,"是","否") -> 是 | D73: =IF(D72<=D38,"是","否") -> 是 | E73: =IF(E72<=E38,"是","否") -> 否 | F73: =IF(F72<=F38,"是","否") -> 是 | G73: =IF(G72<=G38,"是","否") -> 是 | H73: =IF(H72<=H38,"是","否") -> 是 | I73: =IF(I72<=I38,"是","否") -> 是 | J73: =IF(J72<=J38,"是","否") -> 是 | ... Q73: =IF(Q72<=Q38,"是","否") -> 是
A74: G. Decode：每步時間＝固定延遲＋B × 每序列時間；B* ＝ min(SLO 上限, HBM 容量上限)
A75: 每步固定延遲（權重讀取＋逐層延遲） | B75: ms | C75: =C68/C12+(C25+C43)*C51/1000 -> 13.974127 | D75: =D68/D12+(D25+D43)*D51/1000 -> 25.781383 | E75: =E68/E12+(E25+E43)*E51/1000 -> 36.971412 | F75: =F68/F12+(F25+F43)*F51/1000 -> 8.6614456 | G75: =G68/G12+(G25+G43)*G51/1000 -> 16.263619 | H75: =H68/H12+(H25+H43)*H51/1000 -> 27.746304 | I75: =I68/I12+(I25+I43)*I51/1000 -> 8.6614456 | J75: =J68/J12+(J25+J43)*J51/1000 -> 16.263619 | ... Q75: =Q68/Q12+(Q25+Q43)*Q51/1000 -> 19.127365
A76: 每序列每步 — 算力項 | B76: ms | C76: =(C43+1)*C61/(C10*C49)/1000 -> 1.4384359 | D76: =(D43+1)*D61/(D10*D49)/1000 -> 5.0078978 | E76: =(E43+1)*E61/(E10*E49)/1000 -> 19.866797 | F76: =(F43+1)*F61/(F10*F49)/1000 -> 0.42678394 | G76: =(G43+1)*G61/(G10*G49)/1000 -> 1.4858433 | H76: =(H43+1)*H61/(H10*H49)/1000 -> 5.8944788 | I76: =(I43+1)*I61/(I10*I49)/1000 -> 0.28452263 | J76: =(J43+1)*J61/(J10*J49)/1000 -> 0.99056219 | ... Q76: =(Q43+1)*Q61/(Q10*Q49)/1000 -> 0.80746285
A77: 每序列每步 — KV 讀取項 | B77: ms | C77: =C30*C41/(C12*C56)/1000000000 -> 0.010374277 | D77: =D30*D41/(D12*D56)/1000000000 -> 0.029433996 | E77: =E30*E41/(E12*E56)/1000000000 -> 0.85518192 | F77: =F30*F41/(F12*F56)/1000000000 -> 0.0043442286 | G77: =G30*G41/(G12*G56)/1000000000 -> 0.012325486 | H77: =H30*H41/(H12*H56)/1000000000 -> 0.35810743 | I77: =I30*I41/(I12*I56)/1000000000 -> 0.0043442286 | J77: =J30*J41/(J12*J56)/1000000000 -> 0.012325486 | ... Q77: =Q30*Q41/(Q12*Q56)/1000000000 -> 0.089526857
A78: 每序列每步 — EP 通訊項 | B78: ms | C78: =(C43+1)*C25*C27*C26*C55*(C67-1)/C67/(C13*C57)/1000000000 -> 0.3566592 | D78: =(D43+1)*D25*D27*D26*D55*(D67-1)/D67/(D13*D57)/1000000000 -> 0.8854272 | E78: =(E43+1)*E25*E27*E26*E55*(E67-1)/E67/(E13*E57)/1000000000 -> 6.691999 | F78: =(F43+1)*F25*F27*F26*F55*(F67-1)/F67/(F13*F57)/1000000000 -> 0.019499886 | G78: =(G43+1)*G25*G27*G26*G55*(G67-1)/G67/(G13*G57)/1000000000 -> 0.0484096 | H78: =(H43+1)*H25*H27*H26*H55*(H67-1)/H67/(H13*H57)/1000000000 -> 0.36347697 | I78: =(I43+1)*I25*I27*I26*I55*(I67-1)/I67/(I13*I57)/1000000000 -> 0.019499886 | J78: =(J43+1)*J25*J27*J26*J55*(J67-1)/J67/(J13*J57)/1000000000 -> 0.0484096 | ... Q78: =(Q43+1)*Q25*Q27*Q26*Q55*(Q67-1)/Q67/(Q13*Q57)/1000000000 -> 0.18432
A79: 每序列每步（取最大，假設三者可重疊） | B79: ms | C79: =MAX(C76,C77,C78) -> 1.4384359 | D79: =MAX(D76,D77,D78) -> 5.0078978 | E79: =MAX(E76,E77,E78) -> 19.866797 | F79: =MAX(F76,F77,F78) -> 0.42678394 | G79: =MAX(G76,G77,G78) -> 1.4858433 | H79: =MAX(H76,H77,H78) -> 5.8944788 | I79: =MAX(I76,I77,I78) -> 0.28452263 | J79: =MAX(J76,J77,J78) -> 0.99056219 | ... Q79: =MAX(Q76,Q77,Q78) -> 0.80746285
A80: 每序列綁定項 | C80: =IF(C79=C76,"算力",IF(C79=C77,"KV 頻寬","EP 通訊")) -> 算力 | D80: =IF(D79=D76,"算力",IF(D79=D77,"KV 頻寬","EP 通訊")) -> 算力 | E80: =IF(E79=E76,"算力",IF(E79=E77,"KV 頻寬","EP 通訊")) -> 算力 | F80: =IF(F79=F76,"算力",IF(F79=F77,"KV 頻寬","EP 通訊")) -> 算力 | G80: =IF(G79=G76,"算力",IF(G79=G77,"KV 頻寬","EP 通訊")) -> 算力 | H80: =IF(H79=H76,"算力",IF(H79=H77,"KV 頻寬","EP 通訊")) -> 算力 | I80: =IF(I79=I76,"算力",IF(I79=I77,"KV 頻寬","EP 通訊")) -> 算力 | J80: =IF(J79=J76,"算力",IF(J79=J77,"KV 頻寬","EP 通訊")) -> 算力 | ... Q80: =IF(Q79=Q76,"算力",IF(Q79=Q77,"KV 頻寬","EP 通訊")) -> 算力
A81: SLO 允許的批次上限 | B81: 序列/GPU | C81: =(1000*C45/C37-C75)/C79 -> 4.9596966 | D81: =(1000*D45/D37-D75)/D79 -> 2.6334099 | E81: =(1000*E45/E37-E75)/E79 -> 0.4572017 | F81: =(1000*F45/F37-F75)/F79 -> 29.164377 | G81: =(1000*G45/G37-G75)/G79 -> 15.281296 | H81: =(1000*H45/H37-H75)/H79 -> 3.1059984 | I81: =(1000*I45/I37-I75)/I79 -> 43.746565 | J81: =(1000*J45/J37-J75)/J79 -> 22.921944 | ... Q81: =(1000*Q45/Q37-Q75)/Q79 -> 33.347888
A82: HBM 容量允許的批次上限 | B82: 序列/GPU | C82: =(C65-C68)*1000000000/(C30*C41) -> 2558.1997 | D82: =(D65-D68)*1000000000/(D30*D41) -> 538.63353 | E82: =(E65-E68)*1000000000/(E30*E41) -> 15.509086 | F82: =(F65-F68)*1000000000/(F30*F41) -> 6457.2925 | G82: =(G65-G68)*1000000000/(G30*G41) -> 1729.1939 | H82: =(H65-H68)*1000000000/(H30*H41) -> 38.645178 | I82: =(I65-I68)*1000000000/(I30*I41) -> 10230.772 | J82: =(J65-J68)*1000000000/(J30*J41) -> 3059.1908 | ... Q82: =(Q65-Q68)*1000000000/(Q30*Q41) -> 417.77291
A83: 採用批次 B* | B83: 序列/GPU | C83: =MAX(0,MIN(C81,C82)) -> 4.9596966 | D83: =MAX(0,MIN(D81,D82)) -> 2.6334099 | E83: =MAX(0,MIN(E81,E82)) -> 0.4572017 | F83: =MAX(0,MIN(F81,F82)) -> 29.164377 | G83: =MAX(0,MIN(G81,G82)) -> 15.281296 | H83: =MAX(0,MIN(H81,H82)) -> 3.1059984 | I83: =MAX(0,MIN(I81,I82)) -> 43.746565 | J83: =MAX(0,MIN(J81,J82)) -> 22.921944 | ... Q83: =MAX(0,MIN(Q81,Q82)) -> 33.347888
A84: decode tok/s（每 decode GPU） | B84: tok/s | C84: =IF(C83>0,C83*C45/((C75+C83*C79)/1000),0) -> 595.1636 | D84: =IF(D83>0,D83*D45/((D75+D83*D79)/1000),0) -> 171.17164 | E84: =IF(E83>0,E83*E45/((E75+E83*E79)/1000),0) -> 25.146093 | F84: =IF(F83>0,F83*F45/((F75+F83*F79)/1000),0) -> 3499.7252 | G84: =IF(G83>0,G83*G45/((G75+G83*G79)/1000),0) -> 993.28425 | H84: =IF(H83>0,H83*H45/((H75+H83*H79)/1000),0) -> 170.82991 | I84: =IF(I83>0,I83*I45/((I75+I83*I79)/1000),0) -> 5249.5878 | J84: =IF(J83>0,J83*J45/((J75+J83*J79)/1000),0) -> 1489.9264 | ... Q84: =IF(Q83>0,Q83*Q45/((Q75+Q83*Q79)/1000),0) -> 1834.1339
A85: 實際每用戶速度 | B85: tok/s | C85: =IF(C83>0,C45/((C75+C83*C79)/1000),0) -> 120 | D85: =IF(D83>0,D45/((D75+D83*D79)/1000),0) -> 65 | E85: =IF(E83>0,E45/((E75+E83*E79)/1000),0) -> 55 | F85: =IF(F83>0,F45/((F75+F83*F79)/1000),0) -> 120 | G85: =IF(G83>0,G45/((G75+G83*G79)/1000),0) -> 65 | H85: =IF(H83>0,H45/((H75+H83*H79)/1000),0) -> 55 | I85: =IF(I83>0,I45/((I75+I83*I79)/1000),0) -> 120 | J85: =IF(J83>0,J45/((J75+J83*J79)/1000),0) -> 65 | ... Q85: =IF(Q83>0,Q45/((Q75+Q83*Q79)/1000),0) -> 55
A86: 綁定約束 | C86: =IF(C83<=0,"SLO 不可達",IF(C81<=C82,"SLO（"&C80&"）","HBM 容量")) -> SLO（算力） | D86: =IF(D83<=0,"SLO 不可達",IF(D81<=D82,"SLO（"&D80&"）","HBM 容量")) -> SLO（算力） | E86: =IF(E83<=0,"SLO 不可達",IF(E81<=E82,"SLO（"&E80&"）","HBM 容量")) -> SLO（算力） | F86: =IF(F83<=0,"SLO 不可達",IF(F81<=F82,"SLO（"&F80&"）","HBM 容量")) -> SLO（算力） | G86: =IF(G83<=0,"SLO 不可達",IF(G81<=G82,"SLO（"&G80&"）","HBM 容量")) -> SLO（算力） | H86: =IF(H83<=0,"SLO 不可達",IF(H81<=H82,"SLO（"&H80&"）","HBM 容量")) -> SLO（算力） | I86: =IF(I83<=0,"SLO 不可達",IF(I81<=I82,"SLO（"&I80&"）","HBM 容量")) -> SLO（算力） | J86: =IF(J83<=0,"SLO 不可達",IF(J81<=J82,"SLO（"&J80&"）","HBM 容量")) -> SLO（算力） | ... Q86: =IF(Q83<=0,"SLO 不可達",IF(Q81<=Q82,"SLO（"&Q80&"）","HBM 容量")) -> SLO（算力）
A87: KV 占可用 HBM | B87: % | C87: =C83*C30*C41/1000000000/C65 -> 0.0016758043 | D87: =D83*D30*D41/1000000000/D65 -> 0.0025245154 | E87: =E83*E30*E41/1000000000/E65 -> 0.012734347 | F87: =F83*F30*F41/1000000000/F65 -> 0.004238361 | G87: =G83*G30*G41/1000000000/G65 -> 0.0063008162 | H87: =H83*H30*H41/1000000000/H65 -> 0.037208925 | I87: =I83*I30*I41/1000000000/I65 -> 0.0041059122 | J87: =J83*J30*J41/1000000000/J65 -> 0.0061039156 | ... Q87: =Q83*Q30*Q41/1000000000/Q65 -> 0.072565005
A88: H. 每架與每 GW（參考任務；P:D 依工作量配比；100% 利用率）
A89: 每請求 GPU 秒 | B89: GPU-s | C89: =IF(C84>0,C39/C71+C40/C84,0) -> 2.7695534 | D89: =IF(D84>0,D39/D71+D40/D84,0) -> 19.325949 | E89: =IF(E84>0,E39/E71+E40/E84,0) -> 211.541 | F89: =IF(F84>0,F39/F71+F40/F84,0) -> 0.39634229 | G89: =IF(G84>0,G39/G71+G40/G84,0) -> 2.7898844 | H89: =IF(H84>0,H39/H71+H40/H84,0) -> 28.788835 | I89: =IF(I84>0,I39/I71+I40/I84,0) -> 0.26422819 | J89: =IF(J84>0,J39/J71+J40/J84,0) -> 1.8599229 | ... Q89: =IF(Q84>0,Q39/Q71+Q40/Q84,0) -> 2.8923532
A90: prefill GPU 占比 | B90: % | C90: =IF(C89>0,(C39/C71)/C89,0) -> 0.37876796 | D90: =IF(D89>0,(D39/D71)/D89,0) -> 0.38090497 | E90: =IF(E89>0,(E39/E71)/E89,0) -> 0.22999265 | F90: =IF(F89>0,(F39/F71)/F89,0) -> 0.26176336 | G90: =IF(G89>0,(G39/G71)/G89,0) -> 0.26095616 | H90: =IF(H89>0,(H39/H71)/H89,0) -> 0.16714012 | I90: =IF(I89>0,(I39/I71)/I89,0) -> 0.26176336 | J90: =IF(J89>0,(J39/J71)/J89,0) -> 0.26095616 | ... Q90: =IF(Q89>0,(Q39/Q71)/Q89,0) -> 0.22789281
A91: 每架總 tok/s | B91: tok/s | C91: =IF(C89>0,C18*(C39+C40)/C89,0) -> 106483.59 | D91: =IF(D89>0,D18*(D39+D40)/D89,0) -> 30519.795 | E91: =IF(E89>0,E18*(E39+E40)/E89,0) -> 5576.4509 | F91: =IF(F89>0,F18*(F39+F40)/F89,0) -> 1674189.2 | G91: =IF(G89>0,G18*(G39+G40)/G89,0) -> 475684.23 | H91: =IF(H89>0,H18*(H39+H40)/H89,0) -> 92195.741 | I91: =IF(I89>0,I18*(I39+I40)/I89,0) -> 2511283.9 | J91: =IF(J89>0,J18*(J39+J40)/J89,0) -> 713526.35 | ... Q91: =IF(Q89>0,Q18*(Q39+Q40)/Q89,0) -> 1835327.7
A92: 每架 decode tok/s | B92: tok/s | C92: =C91*C40/(C39+C40) -> 11831.51 | D92: =D91*D40/(D39+D40) -> 3391.0884 | E92: =E91*E40/(E39+E40) -> 619.60566 | F92: =F91*F40/(F39+F40) -> 186021.03 | G92: =G91*G40/(G39+G40) -> 52853.803 | H92: =H91*H40/(H39+H40) -> 10243.971 | I92: =I91*I40/(I39+I40) -> 279031.54 | J92: =J91*J40/(J39+J40) -> 79280.705 | ... Q92: =Q91*Q40/(Q39+Q40) -> 203925.3
A93: 每架 prefill tok/s | B93: tok/s | C93: =C91-C92 -> 94652.082 | D93: =D91-D92 -> 27128.707 | E93: =E91-E92 -> 4956.8452 | F93: =F91-F92 -> 1488168.2 | G93: =G91-G92 -> 422830.43 | H93: =H91-H92 -> 81951.77 | I93: =I91-I92 -> 2232252.3 | J93: =J91-J92 -> 634245.64 | ... Q93: =Q91-Q92 -> 1631402.4
A94: 每 GW 總產出 | B94: M tok/年 | C94: =C91*C21*8760*3600/1000000 -> 7.5351656e+10 | D94: =D91*D21*8760*3600/1000000 -> 2.1596915e+10 | E94: =E91*E21*8760*3600/1000000 -> 3.9460991e+09 | F94: =F91*F21*8760*3600/1000000 -> 3.7359321e+11 | G94: =G91*G21*8760*3600/1000000 -> 1.0614833e+11 | H94: =H91*H21*8760*3600/1000000 -> 2.0573363e+10 | I94: =I91*I21*8760*3600/1000000 -> 5.3180012e+11 | J94: =J91*J21*8760*3600/1000000 -> 1.5109936e+11 | ... Q94: =Q91*Q21*8760*3600/1000000 -> 8.8728347e+10
A95: 每 GW decode 產出 | B95: M tok/年 | C95: =C92*C21*8760*3600/1000000 -> 8.3724062e+09 | D95: =D92*D21*8760*3600/1000000 -> 2.3996572e+09 | E95: =E92*E21*8760*3600/1000000 -> 4.3845546e+08 | F95: =F92*F21*8760*3600/1000000 -> 4.1510357e+10 | G95: =G92*G21*8760*3600/1000000 -> 1.1794259e+10 | H95: =H92*H21*8760*3600/1000000 -> 2.2859292e+09 | I95: =I92*I21*8760*3600/1000000 -> 5.9088902e+10 | J95: =J92*J21*8760*3600/1000000 -> 1.6788818e+10 | ... Q95: =Q92*Q21*8760*3600/1000000 -> 9.8587052e+09
A96: I. 每 M token GPU 秒（供 Unit_Cost）與速覽成本
A97: 新鮮 prefill | B97: GPU-s/M | C97: =1000000/C71 -> 128.05397 | D97: =1000000/D71 -> 449.30115 | E97: =1000000/E71 -> 1484.7679 | F97: =1000000/F71 -> 12.664537 | G97: =1000000/G71 -> 44.435884 | H97: =1000000/H71 -> 146.84355 | I97: =1000000/I71 -> 8.443025 | J97: =1000000/J71 -> 29.623922 | ... Q97: =1000000/Q71 -> 20.115554
A98: 快取命中 prefill（KV 載入） | B98: GPU-s/M | C98: =1000000*C30/(C58*1000000000000) -> 0.02795 | D98: =1000000*D30/(D58*1000000000000) -> 0.03965 | E98: =1000000*E30/(E58*1000000000000) -> 0.576 | F98: =1000000*F30/(F58*1000000000000) -> 0.02795 | G98: =1000000*G30/(G58*1000000000000) -> 0.03965 | H98: =1000000*H30/(H58*1000000000000) -> 0.576 | I98: =1000000*I30/(I58*1000000000000) -> 0.02795 | J98: =1000000*J30/(J58*1000000000000) -> 0.03965 | ... Q98: =1000000*Q30/(Q58*1000000000000) -> 0.576
A99: decode（0＝SLO 不可達） | B99: GPU-s/M | C99: =IF(C84>0,1000000/C84,0) -> 1680.2103 | D99: =IF(D84>0,1000000/D84,0) -> 5842.0892 | E99: =IF(E84>0,1000000/E84,0) -> 39767.609 | F99: =IF(F84>0,1000000/F84,0) -> 285.73672 | G99: =IF(G84>0,1000000/G84,0) -> 1006.7612 | H99: =IF(H84>0,1000000/H84,0) -> 5853.7759 | I99: =IF(I84>0,1000000/I84,0) -> 190.49115 | J99: =IF(J84>0,1000000/J84,0) -> 671.17411 | ... Q99: =IF(Q84>0,1000000/Q84,0) -> 545.21648
A100: 速覽：新鮮 prefill $/M（經濟、基準成本、100%） | B100: $/M | C100: =INDEX(DC_Cost!$C$58:$Q$58,3*(C$6-1)+2)/3600*C97 -> 0.057091768 | D100: =INDEX(DC_Cost!$C$58:$Q$58,3*(D$6-1)+2)/3600*D97 -> 0.20031708 | E100: =INDEX(DC_Cost!$C$58:$Q$58,3*(E$6-1)+2)/3600*E97 -> 0.66197109 | F100: =INDEX(DC_Cost!$C$58:$Q$58,3*(F$6-1)+2)/3600*F97 -> 0.0073059068 | G100: =INDEX(DC_Cost!$C$58:$Q$58,3*(G$6-1)+2)/3600*G97 -> 0.025634132 | H100: =INDEX(DC_Cost!$C$58:$Q$58,3*(H$6-1)+2)/3600*H97 -> 0.084710971 | I100: =INDEX(DC_Cost!$C$58:$Q$58,3*(I$6-1)+2)/3600*I97 -> 0.0070065683 | J100: =INDEX(DC_Cost!$C$58:$Q$58,3*(J$6-1)+2)/3600*J97 -> 0.024583847 | ... Q100: =INDEX(DC_Cost!$C$58:$Q$58,3*(Q$6-1)+2)/3600*Q97 -> 0.048448802
A101: 速覽：decode $/M（經濟、基準成本、100%） | B101: $/M | C101: =IF(C99>0,INDEX(DC_Cost!$C$58:$Q$58,3*(C$6-1)+2)/3600*C99,0) -> 0.74910741 | D101: =IF(D99>0,INDEX(DC_Cost!$C$58:$Q$58,3*(D$6-1)+2)/3600*D99,0) -> 2.6046456 | E101: =IF(E99>0,INDEX(DC_Cost!$C$58:$Q$58,3*(E$6-1)+2)/3600*E99,0) -> 17.730049 | F101: =IF(F99>0,INDEX(DC_Cost!$C$58:$Q$58,3*(F$6-1)+2)/3600*F99,0) -> 0.16483554 | G101: =IF(G99>0,INDEX(DC_Cost!$C$58:$Q$58,3*(G$6-1)+2)/3600*G99,0) -> 0.58077946 | H101: =IF(H99>0,INDEX(DC_Cost!$C$58:$Q$58,3*(H$6-1)+2)/3600*H99,0) -> 3.3769209 | I101: =IF(I99>0,INDEX(DC_Cost!$C$58:$Q$58,3*(I$6-1)+2)/3600*I99,0) -> 0.15808188 | J101: =IF(J99>0,INDEX(DC_Cost!$C$58:$Q$58,3*(J$6-1)+2)/3600*J99,0) -> 0.55698369 | ... Q101: =IF(Q99>0,INDEX(DC_Cost!$C$58:$Q$58,3*(Q$6-1)+2)/3600*Q99,0) -> 1.3131672
A102: J. 能量下限與閉合（能量閉合：物理下限功率 ≤ 機架平均用電）
...

Sheet Sens_Perf
A1: Sens_Perf — VR200 對 GB300 的單變數敏感度（先看敏感度，再看基準）
A2: 每組兩欄：左 VR200、右 GB300。黃底藍字＝該情境改動的輸入。GB300 為校準世代，VR200 的 η_d 與每層延遲為沿用值 [Analogy]，故 VR 專屬情境只動 VR 欄
A3: 情境 | C3: 基準 | E3: VR η_d × 0.5（新世代軟體未成熟） | G3: VR η_d × 1.5 | I3: VR 每層延遲 × 0.7 | K3: VR 每層延遲 × 1.5 | M3: VR 峰值 50 PF（J2 高情境） | O3: SLO 40 tok/s | Q3: SLO 100 tok/s | S3: MTP 接受率 0.60 | U3: MTP 接受率 0.80 | W3: ISL 4K | Y3: ISL 64K | AA3: 生產折減 0.7（兩世代） | AC3: Astra KV 情境 1（混合） | AE3: Astra KV 情境 2（全層 MLA，基準） | AG3: Astra KV 情境 3（GQA-8）
A4: 世代 | C4: =INDEX(Spec_Rack!$C$4:$G$4,C6) -> VR200 NVL72 | D4: =INDEX(Spec_Rack!$C$4:$G$4,D6) -> GB300 NVL72 | E4: =INDEX(Spec_Rack!$C$4:$G$4,E6) -> VR200 NVL72 | F4: =INDEX(Spec_Rack!$C$4:$G$4,F6) -> GB300 NVL72 | G4: =INDEX(Spec_Rack!$C$4:$G$4,G6) -> VR200 NVL72 | H4: =INDEX(Spec_Rack!$C$4:$G$4,H6) -> GB300 NVL72 | I4: =INDEX(Spec_Rack!$C$4:$G$4,I6) -> VR200 NVL72 | J4: =INDEX(Spec_Rack!$C$4:$G$4,J6) -> GB300 NVL72 | ... AH4: =INDEX(Spec_Rack!$C$4:$G$4,AH6) -> GB300 NVL72
A5: 層級 | C5: =INDEX(Arch!$C$4:$E$4,C7) -> Sol（中層） | D5: =INDEX(Arch!$C$4:$E$4,D7) -> Sol（中層） | E5: =INDEX(Arch!$C$4:$E$4,E7) -> Sol（中層） | F5: =INDEX(Arch!$C$4:$E$4,F7) -> Sol（中層） | G5: =INDEX(Arch!$C$4:$E$4,G7) -> Sol（中層） | H5: =INDEX(Arch!$C$4:$E$4,H7) -> Sol（中層） | I5: =INDEX(Arch!$C$4:$E$4,I7) -> Sol（中層） | J5: =INDEX(Arch!$C$4:$E$4,J7) -> Sol（中層） | ... AH5: =INDEX(Arch!$C$4:$E$4,AH7) -> Astra（頂層）
A6: 世代索引 | C6: 4 | D6: 3 | E6: 4 | F6: 3 | G6: 4 | H6: 3 | I6: 4 | J6: 3 | K6: 4 | L6: 3 | M6: 4 | N6: 3 | O6: 4 | P6: 3 | Q6: 4 | R6: 3 | S6: 4 | T6: 3 | U6: 4 | V6: 3 | W6: 4 | X6: 3 | Y6: 4 | Z6: 3 | AA6: 4 | AB6: 3 | AC6: 4 | AD6: 3 | AE6: 4 | AF6: 3 | AG6: 4 | AH6: 3
A7: 層級索引 | C7: 2 | D7: 2 | E7: 2 | F7: 2 | G7: 2 | H7: 2 | I7: 2 | J7: 2 | K7: 2 | L7: 2 | M7: 2 | N7: 2 | O7: 2 | P7: 2 | Q7: 2 | R7: 2 | S7: 2 | T7: 2 | U7: 2 | V7: 2 | W7: 2 | X7: 2 | Y7: 2 | Z7: 2 | AA7: 2 | AB7: 2 | AC7: 3 | AD7: 3 | AE7: 3 | AF7: 3 | AG7: 3 | AH7: 3
A9: A. 規格（連結 Spec_Rack、DC_Cost）
A10: 計算用峰值 | B10: PF/GPU | C10: =INDEX(Spec_Rack!$C$35:$G$35,C$6) -> 35 | D10: =INDEX(Spec_Rack!$C$35:$G$35,D$6) -> 15 | E10: =INDEX(Spec_Rack!$C$35:$G$35,E$6) -> 35 | F10: =INDEX(Spec_Rack!$C$35:$G$35,F$6) -> 15 | G10: =INDEX(Spec_Rack!$C$35:$G$35,G$6) -> 35 | H10: =INDEX(Spec_Rack!$C$35:$G$35,H$6) -> 15 | I10: =INDEX(Spec_Rack!$C$35:$G$35,I$6) -> 35 | J10: =INDEX(Spec_Rack!$C$35:$G$35,J$6) -> 15 | ... L10: =INDEX(Spec_Rack!$C$35:$G$35,L$6) -> 15 | M10: 50 | N10: =INDEX(Spec_Rack!$C$35:$G$35,N$6) -> 15 | O10: =INDEX(Spec_Rack!$C$35:$G$35,O$6) -> 35 | P10: =INDEX(Spec_Rack!$C$35:$G$35,P$6) -> 15 | Q10: =INDEX(Spec_Rack!$C$35:$G$35,Q$6) -> 35 | R10: =INDEX(Spec_Rack!$C$35:$G$35,R$6) -> 15 | S10: =INDEX(Spec_Rack!$C$35:$G$35,S$6) -> 35 | T10: =INDEX(Spec_Rack!$C$35:$G$35,T$6) -> 15 | U10: =INDEX(Spec_Rack!$C$35:$G$35,U$6) -> 35 | ... AH10: =INDEX(Spec_Rack!$C$35:$G$35,AH$6) -> 15
A11: HBM 容量 | B11: GB/GPU | C11: =INDEX(Spec_Rack!$C$25:$G$25,C$6) -> 288 | D11: =INDEX(Spec_Rack!$C$25:$G$25,D$6) -> 288 | E11: =INDEX(Spec_Rack!$C$25:$G$25,E$6) -> 288 | F11: =INDEX(Spec_Rack!$C$25:$G$25,F$6) -> 288 | G11: =INDEX(Spec_Rack!$C$25:$G$25,G$6) -> 288 | H11: =INDEX(Spec_Rack!$C$25:$G$25,H$6) -> 288 | I11: =INDEX(Spec_Rack!$C$25:$G$25,I$6) -> 288 | J11: =INDEX(Spec_Rack!$C$25:$G$25,J$6) -> 288 | ... AH11: =INDEX(Spec_Rack!$C$25:$G$25,AH$6) -> 288
A12: HBM 頻寬 | B12: TB/s/GPU | C12: =INDEX(Spec_Rack!$C$26:$G$26,C$6) -> 22 | D12: =INDEX(Spec_Rack!$C$26:$G$26,D$6) -> 8 | E12: =INDEX(Spec_Rack!$C$26:$G$26,E$6) -> 22 | F12: =INDEX(Spec_Rack!$C$26:$G$26,F$6) -> 8 | G12: =INDEX(Spec_Rack!$C$26:$G$26,G$6) -> 22 | H12: =INDEX(Spec_Rack!$C$26:$G$26,H$6) -> 8 | I12: =INDEX(Spec_Rack!$C$26:$G$26,I$6) -> 22 | J12: =INDEX(Spec_Rack!$C$26:$G$26,J$6) -> 8 | ... AH12: =INDEX(Spec_Rack!$C$26:$G$26,AH$6) -> 8
A13: EP 通訊頻寬（單向） | B13: TB/s/GPU | C13: =INDEX(Spec_Rack!$C$27:$G$27,C$6) -> 1.8 | D13: =INDEX(Spec_Rack!$C$27:$G$27,D$6) -> 0.9 | E13: =INDEX(Spec_Rack!$C$27:$G$27,E$6) -> 1.8 | F13: =INDEX(Spec_Rack!$C$27:$G$27,F$6) -> 0.9 | G13: =INDEX(Spec_Rack!$C$27:$G$27,G$6) -> 1.8 | H13: =INDEX(Spec_Rack!$C$27:$G$27,H$6) -> 0.9 | I13: =INDEX(Spec_Rack!$C$27:$G$27,I$6) -> 1.8 | J13: =INDEX(Spec_Rack!$C$27:$G$27,J$6) -> 0.9 | ... AH13: =INDEX(Spec_Rack!$C$27:$G$27,AH$6) -> 0.9
A14: decode EP 基準寬度 | B14: GPU | C14: =INDEX(Spec_Rack!$C$29:$G$29,C$6) -> 32 | D14: =INDEX(Spec_Rack!$C$29:$G$29,D$6) -> 32 | E14: =INDEX(Spec_Rack!$C$29:$G$29,E$6) -> 32 | F14: =INDEX(Spec_Rack!$C$29:$G$29,F$6) -> 32 | G14: =INDEX(Spec_Rack!$C$29:$G$29,G$6) -> 32 | H14: =INDEX(Spec_Rack!$C$29:$G$29,H$6) -> 32 | I14: =INDEX(Spec_Rack!$C$29:$G$29,I$6) -> 32 | J14: =INDEX(Spec_Rack!$C$29:$G$29,J$6) -> 32 | ... AH14: =INDEX(Spec_Rack!$C$29:$G$29,AH$6) -> 32
A15: 專家權重 bytes/param | B15: B | C15: =INDEX(Spec_Rack!$C$30:$G$30,C$6) -> 0.5625 | D15: =INDEX(Spec_Rack!$C$30:$G$30,D$6) -> 0.5625 | E15: =INDEX(Spec_Rack!$C$30:$G$30,E$6) -> 0.5625 | F15: =INDEX(Spec_Rack!$C$30:$G$30,F$6) -> 0.5625 | G15: =INDEX(Spec_Rack!$C$30:$G$30,G$6) -> 0.5625 | H15: =INDEX(Spec_Rack!$C$30:$G$30,H$6) -> 0.5625 | I15: =INDEX(Spec_Rack!$C$30:$G$30,I$6) -> 0.5625 | J15: =INDEX(Spec_Rack!$C$30:$G$30,J$6) -> 0.5625 | ... AH15: =INDEX(Spec_Rack!$C$30:$G$30,AH$6) -> 0.5625
A16: 非專家權重 bytes/param | B16: B | C16: =INDEX(Spec_Rack!$C$31:$G$31,C$6) -> 1 | D16: =INDEX(Spec_Rack!$C$31:$G$31,D$6) -> 1 | E16: =INDEX(Spec_Rack!$C$31:$G$31,E$6) -> 1 | F16: =INDEX(Spec_Rack!$C$31:$G$31,F$6) -> 1 | G16: =INDEX(Spec_Rack!$C$31:$G$31,G$6) -> 1 | H16: =INDEX(Spec_Rack!$C$31:$G$31,H$6) -> 1 | I16: =INDEX(Spec_Rack!$C$31:$G$31,I$6) -> 1 | J16: =INDEX(Spec_Rack!$C$31:$G$31,J$6) -> 1 | ... AH16: =INDEX(Spec_Rack!$C$31:$G$31,AH$6) -> 1
A17: 每 prefill 實例 GPU 數 | B17: GPU | C17: =INDEX(Spec_Rack!$C$32:$G$32,C$6) -> 4 | D17: =INDEX(Spec_Rack!$C$32:$G$32,D$6) -> 4 | E17: =INDEX(Spec_Rack!$C$32:$G$32,E$6) -> 4 | F17: =INDEX(Spec_Rack!$C$32:$G$32,F$6) -> 4 | G17: =INDEX(Spec_Rack!$C$32:$G$32,G$6) -> 4 | H17: =INDEX(Spec_Rack!$C$32:$G$32,H$6) -> 4 | I17: =INDEX(Spec_Rack!$C$32:$G$32,I$6) -> 4 | J17: =INDEX(Spec_Rack!$C$32:$G$32,J$6) -> 4 | ... AH17: =INDEX(Spec_Rack!$C$32:$G$32,AH$6) -> 4
A18: GPU 封裝／架 | B18: 顆 | C18: =INDEX(Spec_Rack!$C$6:$G$6,C$6) -> 72 | D18: =INDEX(Spec_Rack!$C$6:$G$6,D$6) -> 72 | E18: =INDEX(Spec_Rack!$C$6:$G$6,E$6) -> 72 | F18: =INDEX(Spec_Rack!$C$6:$G$6,F$6) -> 72 | G18: =INDEX(Spec_Rack!$C$6:$G$6,G$6) -> 72 | H18: =INDEX(Spec_Rack!$C$6:$G$6,H$6) -> 72 | I18: =INDEX(Spec_Rack!$C$6:$G$6,I$6) -> 72 | J18: =INDEX(Spec_Rack!$C$6:$G$6,J$6) -> 72 | ... AH18: =INDEX(Spec_Rack!$C$6:$G$6,AH$6) -> 72
A19: GPU 功率 | B19: W | C19: =INDEX(Spec_Rack!$C$33:$G$33,C$6) -> 1800 | D19: =INDEX(Spec_Rack!$C$33:$G$33,D$6) -> 1400 | E19: =INDEX(Spec_Rack!$C$33:$G$33,E$6) -> 1800 | F19: =INDEX(Spec_Rack!$C$33:$G$33,F$6) -> 1400 | G19: =INDEX(Spec_Rack!$C$33:$G$33,G$6) -> 1800 | H19: =INDEX(Spec_Rack!$C$33:$G$33,H$6) -> 1400 | I19: =INDEX(Spec_Rack!$C$33:$G$33,I$6) -> 1800 | J19: =INDEX(Spec_Rack!$C$33:$G$33,J$6) -> 1400 | ... AH19: =INDEX(Spec_Rack!$C$33:$G$33,AH$6) -> 1400
A20: HBM 存取能量 | B20: pJ/B | C20: =INDEX(Spec_Rack!$C$34:$G$34,C$6) -> 20 | D20: =INDEX(Spec_Rack!$C$34:$G$34,D$6) -> 25 | E20: =INDEX(Spec_Rack!$C$34:$G$34,E$6) -> 20 | F20: =INDEX(Spec_Rack!$C$34:$G$34,F$6) -> 25 | G20: =INDEX(Spec_Rack!$C$34:$G$34,G$6) -> 20 | H20: =INDEX(Spec_Rack!$C$34:$G$34,H$6) -> 25 | I20: =INDEX(Spec_Rack!$C$34:$G$34,I$6) -> 20 | J20: =INDEX(Spec_Rack!$C$34:$G$34,J$6) -> 25 | ... AH20: =INDEX(Spec_Rack!$C$34:$G$34,AH$6) -> 25
A21: 每 GW 機架數（功率情境） | B21: 架 | C21: =INDEX(DC_Cost!$C$12:$Q$12,3*(C$6-1)+2) -> 4052 | D21: =INDEX(DC_Cost!$C$12:$Q$12,3*(D$6-1)+2) -> 6715 | E21: =INDEX(DC_Cost!$C$12:$Q$12,3*(E$6-1)+2) -> 4052 | F21: =INDEX(DC_Cost!$C$12:$Q$12,3*(F$6-1)+2) -> 6715 | G21: =INDEX(DC_Cost!$C$12:$Q$12,3*(G$6-1)+2) -> 4052 | H21: =INDEX(DC_Cost!$C$12:$Q$12,3*(H$6-1)+2) -> 6715 | I21: =INDEX(DC_Cost!$C$12:$Q$12,3*(I$6-1)+2) -> 4052 | J21: =INDEX(DC_Cost!$C$12:$Q$12,3*(J$6-1)+2) -> 6715 | ... AH21: =INDEX(DC_Cost!$C$12:$Q$12,3*(AH$6-1)+2) -> 6715
A22: 每架配電設計功率 | B22: kW | C22: =INDEX(DC_Cost!$C$11:$Q$11,3*(C$6-1)+2) -> 227 | D22: =INDEX(DC_Cost!$C$11:$Q$11,3*(D$6-1)+2) -> 137 | E22: =INDEX(DC_Cost!$C$11:$Q$11,3*(E$6-1)+2) -> 227 | F22: =INDEX(DC_Cost!$C$11:$Q$11,3*(F$6-1)+2) -> 137 | G22: =INDEX(DC_Cost!$C$11:$Q$11,3*(G$6-1)+2) -> 227 | H22: =INDEX(DC_Cost!$C$11:$Q$11,3*(H$6-1)+2) -> 137 | I22: =INDEX(DC_Cost!$C$11:$Q$11,3*(I$6-1)+2) -> 227 | J22: =INDEX(DC_Cost!$C$11:$Q$11,3*(J$6-1)+2) -> 137 | ... AH22: =INDEX(DC_Cost!$C$11:$Q$11,3*(AH$6-1)+2) -> 137
A23: B. 架構（連結 Arch）
A24: 啟用參數 | B24: B | C24: =INDEX(Arch!$C$7:$E$7,C$7) -> 49 | D24: =INDEX(Arch!$C$7:$E$7,D$7) -> 49 | E24: =INDEX(Arch!$C$7:$E$7,E$7) -> 49 | F24: =INDEX(Arch!$C$7:$E$7,F$7) -> 49 | G24: =INDEX(Arch!$C$7:$E$7,G$7) -> 49 | H24: =INDEX(Arch!$C$7:$E$7,H$7) -> 49 | I24: =INDEX(Arch!$C$7:$E$7,I$7) -> 49 | J24: =INDEX(Arch!$C$7:$E$7,J$7) -> 49 | ... AH24: =INDEX(Arch!$C$7:$E$7,AH$7) -> 180
A25: 層數 | B25: 層 | C25: =INDEX(Arch!$C$8:$E$8,C$7) -> 61 | D25: =INDEX(Arch!$C$8:$E$8,D$7) -> 61 | E25: =INDEX(Arch!$C$8:$E$8,E$7) -> 61 | F25: =INDEX(Arch!$C$8:$E$8,F$7) -> 61 | G25: =INDEX(Arch!$C$8:$E$8,G$7) -> 61 | H25: =INDEX(Arch!$C$8:$E$8,H$7) -> 61 | I25: =INDEX(Arch!$C$8:$E$8,I$7) -> 61 | J25: =INDEX(Arch!$C$8:$E$8,J$7) -> 61 | ... AH25: =INDEX(Arch!$C$8:$E$8,AH$7) -> 100
A26: d_model | C26: =INDEX(Arch!$C$9:$E$9,C$7) -> 7168 | D26: =INDEX(Arch!$C$9:$E$9,D$7) -> 7168 | E26: =INDEX(Arch!$C$9:$E$9,E$7) -> 7168 | F26: =INDEX(Arch!$C$9:$E$9,F$7) -> 7168 | G26: =INDEX(Arch!$C$9:$E$9,G$7) -> 7168 | H26: =INDEX(Arch!$C$9:$E$9,H$7) -> 7168 | I26: =INDEX(Arch!$C$9:$E$9,I$7) -> 7168 | J26: =INDEX(Arch!$C$9:$E$9,J$7) -> 7168 | ... AH26: =INDEX(Arch!$C$9:$E$9,AH$7) -> 12288
A27: 啟用 routed experts | C27: =INDEX(Arch!$C$13:$E$13,C$7) -> 6 | D27: =INDEX(Arch!$C$13:$E$13,D$7) -> 6 | E27: =INDEX(Arch!$C$13:$E$13,E$7) -> 6 | F27: =INDEX(Arch!$C$13:$E$13,F$7) -> 6 | G27: =INDEX(Arch!$C$13:$E$13,G$7) -> 6 | H27: =INDEX(Arch!$C$13:$E$13,H$7) -> 6 | I27: =INDEX(Arch!$C$13:$E$13,I$7) -> 6 | J27: =INDEX(Arch!$C$13:$E$13,J$7) -> 6 | ... AH27: =INDEX(Arch!$C$13:$E$13,AH$7) -> 16
A28: 非專家參數 | B28: B | C28: =INDEX(Arch!$C$28:$E$28,C$7) -> 20.277778 | D28: =INDEX(Arch!$C$28:$E$28,D$7) -> 20.277778 | E28: =INDEX(Arch!$C$28:$E$28,E$7) -> 20.277778 | F28: =INDEX(Arch!$C$28:$E$28,F$7) -> 20.277778 | G28: =INDEX(Arch!$C$28:$E$28,G$7) -> 20.277778 | H28: =INDEX(Arch!$C$28:$E$28,H$7) -> 20.277778 | I28: =INDEX(Arch!$C$28:$E$28,I$7) -> 20.277778 | J28: =INDEX(Arch!$C$28:$E$28,J$7) -> 20.277778 | ... AH28: =INDEX(Arch!$C$28:$E$28,AH$7) -> 49.072581
A29: 專家參數 | B29: B | C29: =INDEX(Arch!$C$29:$E$29,C$7) -> 1579.7222 | D29: =INDEX(Arch!$C$29:$E$29,D$7) -> 1579.7222 | E29: =INDEX(Arch!$C$29:$E$29,E$7) -> 1579.7222 | F29: =INDEX(Arch!$C$29:$E$29,F$7) -> 1579.7222 | G29: =INDEX(Arch!$C$29:$E$29,G$7) -> 1579.7222 | H29: =INDEX(Arch!$C$29:$E$29,H$7) -> 1579.7222 | I29: =INDEX(Arch!$C$29:$E$29,I$7) -> 1579.7222 | J29: =INDEX(Arch!$C$29:$E$29,J$7) -> 1579.7222 | ... AH29: =INDEX(Arch!$C$29:$E$29,AH$7) -> 3950.9274
A30: KV bytes/token | B30: B | C30: =INDEX(Arch!$C$25:$E$25,C$7) -> 3965 | D30: =INDEX(Arch!$C$25:$E$25,D$7) -> 3965 | E30: =INDEX(Arch!$C$25:$E$25,E$7) -> 3965 | F30: =INDEX(Arch!$C$25:$E$25,F$7) -> 3965 | G30: =INDEX(Arch!$C$25:$E$25,G$7) -> 3965 | H30: =INDEX(Arch!$C$25:$E$25,H$7) -> 3965 | I30: =INDEX(Arch!$C$25:$E$25,I$7) -> 3965 | J30: =INDEX(Arch!$C$25:$E$25,J$7) -> 3965 | ... AB30: =INDEX(Arch!$C$25:$E$25,AB$7) -> 3965 | AC30: =Arch!$E$21 -> 14976 | AD30: =Arch!$E$21 -> 14976 | AE30: =Arch!$E$22 -> 57600 | AF30: =Arch!$E$22 -> 57600 | AG30: =Arch!$E$23 -> 204800 | AH30: =Arch!$E$23 -> 204800
A31: 注意力 FLOPs／被注意 token | B31: FLOP | C31: =INDEX(Arch!$C$30:$E$30,C$7) -> 15990784 | D31: =INDEX(Arch!$C$30:$E$30,D$7) -> 15990784 | E31: =INDEX(Arch!$C$30:$E$30,E$7) -> 15990784 | F31: =INDEX(Arch!$C$30:$E$30,F$7) -> 15990784 | G31: =INDEX(Arch!$C$30:$E$30,G$7) -> 15990784 | H31: =INDEX(Arch!$C$30:$E$30,H$7) -> 15990784 | I31: =INDEX(Arch!$C$30:$E$30,I$7) -> 15990784 | J31: =INDEX(Arch!$C$30:$E$30,J$7) -> 15990784 | ... AH31: =INDEX(Arch!$C$30:$E$30,AH$7) -> 4915200
A32: 全注意力層比例 | B32: % | C32: =INDEX(Arch!$C$16:$E$16,C$7) -> 0.5 | D32: =INDEX(Arch!$C$16:$E$16,D$7) -> 0.5 | E32: =INDEX(Arch!$C$16:$E$16,E$7) -> 0.5 | F32: =INDEX(Arch!$C$16:$E$16,F$7) -> 0.5 | G32: =INDEX(Arch!$C$16:$E$16,G$7) -> 0.5 | H32: =INDEX(Arch!$C$16:$E$16,H$7) -> 0.5 | I32: =INDEX(Arch!$C$16:$E$16,I$7) -> 0.5 | J32: =INDEX(Arch!$C$16:$E$16,J$7) -> 0.5 | ... AH32: =INDEX(Arch!$C$16:$E$16,AH$7) -> 1
A33: 全注意力跨度上限 | B33: tok | C33: =INDEX(Arch!$C$17:$E$17,C$7) -> 4224 | D33: =INDEX(Arch!$C$17:$E$17,D$7) -> 4224 | E33: =INDEX(Arch!$C$17:$E$17,E$7) -> 4224 | F33: =INDEX(Arch!$C$17:$E$17,F$7) -> 4224 | G33: =INDEX(Arch!$C$17:$E$17,G$7) -> 4224 | H33: =INDEX(Arch!$C$17:$E$17,H$7) -> 4224 | I33: =INDEX(Arch!$C$17:$E$17,I$7) -> 4224 | J33: =INDEX(Arch!$C$17:$E$17,J$7) -> 4224 | ... AH33: =INDEX(Arch!$C$17:$E$17,AH$7) -> 0
A34: 其他層壓縮比 | B34: x | C34: =INDEX(Arch!$C$18:$E$18,C$7) -> 128 | D34: =INDEX(Arch!$C$18:$E$18,D$7) -> 128 | E34: =INDEX(Arch!$C$18:$E$18,E$7) -> 128 | F34: =INDEX(Arch!$C$18:$E$18,F$7) -> 128 | G34: =INDEX(Arch!$C$18:$E$18,G$7) -> 128 | H34: =INDEX(Arch!$C$18:$E$18,H$7) -> 128 | I34: =INDEX(Arch!$C$18:$E$18,I$7) -> 128 | J34: =INDEX(Arch!$C$18:$E$18,J$7) -> 128 | ... AH34: =INDEX(Arch!$C$18:$E$18,AH$7) -> 1
A35: 其他層滑動窗 | B35: tok | C35: =INDEX(Arch!$C$19:$E$19,C$7) -> 128 | D35: =INDEX(Arch!$C$19:$E$19,D$7) -> 128 | E35: =INDEX(Arch!$C$19:$E$19,E$7) -> 128 | F35: =INDEX(Arch!$C$19:$E$19,F$7) -> 128 | G35: =INDEX(Arch!$C$19:$E$19,G$7) -> 128 | H35: =INDEX(Arch!$C$19:$E$19,H$7) -> 128 | I35: =INDEX(Arch!$C$19:$E$19,I$7) -> 128 | J35: =INDEX(Arch!$C$19:$E$19,J$7) -> 128 | ... AH35: =INDEX(Arch!$C$19:$E$19,AH$7) -> 0
A36: C. 服務、SLO 與校準參數
A37: SLO：每用戶 decode 速度下限 | B37: tok/s | C37: =INDEX(Serving!$C$21:$E$21,C$7) -> 65 | D37: =INDEX(Serving!$C$21:$E$21,D$7) -> 65 | E37: =INDEX(Serving!$C$21:$E$21,E$7) -> 65 | F37: =INDEX(Serving!$C$21:$E$21,F$7) -> 65 | G37: =INDEX(Serving!$C$21:$E$21,G$7) -> 65 | H37: =INDEX(Serving!$C$21:$E$21,H$7) -> 65 | I37: =INDEX(Serving!$C$21:$E$21,I$7) -> 65 | J37: =INDEX(Serving!$C$21:$E$21,J$7) -> 65 | ... N37: =INDEX(Serving!$C$21:$E$21,N$7) -> 65 | O37: 40 | P37: 40 | Q37: 100 | R37: 100 | S37: =INDEX(Serving!$C$21:$E$21,S$7) -> 65 | T37: =INDEX(Serving!$C$21:$E$21,T$7) -> 65 | U37: =INDEX(Serving!$C$21:$E$21,U$7) -> 65 | V37: =INDEX(Serving!$C$21:$E$21,V$7) -> 65 | W37: =INDEX(Serving!$C$21:$E$21,W$7) -> 65 | X37: =INDEX(Serving!$C$21:$E$21,X$7) -> 65 | Y37: =INDEX(Serving!$C$21:$E$21,Y$7) -> 65 | Z37: =INDEX(Serving!$C$21:$E$21,Z$7) -> 65 | ... AH37: =INDEX(Serving!$C$21:$E$21,AH$7) -> 55
A38: TTFT 上限 | B38: s | C38: =INDEX(Serving!$C$22:$E$22,C$7) -> 3 | D38: =INDEX(Serving!$C$22:$E$22,D$7) -> 3 | E38: =INDEX(Serving!$C$22:$E$22,E$7) -> 3 | F38: =INDEX(Serving!$C$22:$E$22,F$7) -> 3 | G38: =INDEX(Serving!$C$22:$E$22,G$7) -> 3 | H38: =INDEX(Serving!$C$22:$E$22,H$7) -> 3 | I38: =INDEX(Serving!$C$22:$E$22,I$7) -> 3 | J38: =INDEX(Serving!$C$22:$E$22,J$7) -> 3 | ... AH38: =INDEX(Serving!$C$22:$E$22,AH$7) -> 5
A39: 參考 ISL | B39: tok | C39: =INDEX(Serving!$C$23:$E$23,C$7) -> 16384 | D39: =INDEX(Serving!$C$23:$E$23,D$7) -> 16384 | E39: =INDEX(Serving!$C$23:$E$23,E$7) -> 16384 | F39: =INDEX(Serving!$C$23:$E$23,F$7) -> 16384 | G39: =INDEX(Serving!$C$23:$E$23,G$7) -> 16384 | H39: =INDEX(Serving!$C$23:$E$23,H$7) -> 16384 | I39: =INDEX(Serving!$C$23:$E$23,I$7) -> 16384 | J39: =INDEX(Serving!$C$23:$E$23,J$7) -> 16384 | ... V39: =INDEX(Serving!$C$23:$E$23,V$7) -> 16384 | W39: 4096 | X39: 4096 | Y39: 65536 | Z39: 65536 | AA39: =INDEX(Serving!$C$23:$E$23,AA$7) -> 16384 | AB39: =INDEX(Serving!$C$23:$E$23,AB$7) -> 16384 | AC39: =INDEX(Serving!$C$23:$E$23,AC$7) -> 32768 | AD39: =INDEX(Serving!$C$23:$E$23,AD$7) -> 32768 | AE39: =INDEX(Serving!$C$23:$E$23,AE$7) -> 32768 | AF39: =INDEX(Serving!$C$23:$E$23,AF$7) -> 32768 | AG39: =INDEX(Serving!$C$23:$E$23,AG$7) -> 32768 | AH39: =INDEX(Serving!$C$23:$E$23,AH$7) -> 32768
A40: 參考 OSL（含思考） | B40: tok | C40: =INDEX(Serving!$C$24:$E$24,C$7) -> 2048 | D40: =INDEX(Serving!$C$24:$E$24,D$7) -> 2048 | E40: =INDEX(Serving!$C$24:$E$24,E$7) -> 2048 | F40: =INDEX(Serving!$C$24:$E$24,F$7) -> 2048 | G40: =INDEX(Serving!$C$24:$E$24,G$7) -> 2048 | H40: =INDEX(Serving!$C$24:$E$24,H$7) -> 2048 | I40: =INDEX(Serving!$C$24:$E$24,I$7) -> 2048 | J40: =INDEX(Serving!$C$24:$E$24,J$7) -> 2048 | ... AH40: =INDEX(Serving!$C$24:$E$24,AH$7) -> 4096
A41: decode 平均上下文 | B41: tok | C41: =C39+C40/2 -> 17408 | D41: =D39+D40/2 -> 17408 | E41: =E39+E40/2 -> 17408 | F41: =F39+F40/2 -> 17408 | G41: =G39+G40/2 -> 17408 | H41: =H39+H40/2 -> 17408 | I41: =I39+I40/2 -> 17408 | J41: =J39+J40/2 -> 17408 | ... AH41: =AH39+AH40/2 -> 34816
A42: prefill 平均位置 | B42: tok | C42: =C39/2 -> 8192 | D42: =D39/2 -> 8192 | E42: =E39/2 -> 8192 | F42: =F39/2 -> 8192 | G42: =G39/2 -> 8192 | H42: =H39/2 -> 8192 | I42: =I39/2 -> 8192 | J42: =J39/2 -> 8192 | ... AH42: =AH39/2 -> 16384
A43: MTP 草稿數 | B43: tok | C43: =Serving!$C$6 -> 3 | D43: =Serving!$C$6 -> 3 | E43: =Serving!$C$6 -> 3 | F43: =Serving!$C$6 -> 3 | G43: =Serving!$C$6 -> 3 | H43: =Serving!$C$6 -> 3 | I43: =Serving!$C$6 -> 3 | J43: =Serving!$C$6 -> 3 | ... AH43: =Serving!$C$6 -> 3
A44: 草稿接受率 | B44: % | C44: =Serving!$C$7 -> 0.7 | D44: =Serving!$C$7 -> 0.7 | E44: =Serving!$C$7 -> 0.7 | F44: =Serving!$C$7 -> 0.7 | G44: =Serving!$C$7 -> 0.7 | H44: =Serving!$C$7 -> 0.7 | I44: =Serving!$C$7 -> 0.7 | J44: =Serving!$C$7 -> 0.7 | ... R44: =Serving!$C$7 -> 0.7 | S44: 0.6 | T44: 0.6 | U44: 0.8 | V44: 0.8 | W44: =Serving!$C$7 -> 0.7 | X44: =Serving!$C$7 -> 0.7 | Y44: =Serving!$C$7 -> 0.7 | Z44: =Serving!$C$7 -> 0.7 | AA44: =Serving!$C$7 -> 0.7 | AB44: =Serving!$C$7 -> 0.7 | AC44: =Serving!$C$7 -> 0.7 | AD44: =Serving!$C$7 -> 0.7 | ... AH44: =Serving!$C$7 -> 0.7
A45: 每步期望接受 token | B45: tok | C45: =(1-C44^(C43+1))/(1-C44) -> 2.533 | D45: =(1-D44^(D43+1))/(1-D44) -> 2.533 | E45: =(1-E44^(E43+1))/(1-E44) -> 2.533 | F45: =(1-F44^(F43+1))/(1-F44) -> 2.533 | G45: =(1-G44^(G43+1))/(1-G44) -> 2.533 | H45: =(1-H44^(H43+1))/(1-H44) -> 2.533 | I45: =(1-I44^(I43+1))/(1-I44) -> 2.533 | J45: =(1-J44^(J43+1))/(1-J44) -> 2.533 | ... AH45: =(1-AH44^(AH43+1))/(1-AH44) -> 2.533
A46: 實測→生產效率折減 | B46: x | C46: =Serving!$C$18 -> 1 | D46: =Serving!$C$18 -> 1 | E46: =Serving!$C$18 -> 1 | F46: =Serving!$C$18 -> 1 | G46: =Serving!$C$18 -> 1 | H46: =Serving!$C$18 -> 1 | I46: =Serving!$C$18 -> 1 | J46: =Serving!$C$18 -> 1 | ... Z46: =Serving!$C$18 -> 1 | AA46: 0.7 | AB46: 0.7 | AC46: =Serving!$C$18 -> 1 | AD46: =Serving!$C$18 -> 1 | AE46: =Serving!$C$18 -> 1 | AF46: =Serving!$C$18 -> 1 | AG46: =Serving!$C$18 -> 1 | AH46: =Serving!$C$18 -> 1
A47: η_p（prefill 占峰值；含折減） | B47: % | C47: =INDEX(Calib!$C$70:$G$70,C$6)*C46 -> 0.3 | D47: =INDEX(Calib!$C$70:$G$70,D$6)*D46 -> 0.3 | E47: =INDEX(Calib!$C$70:$G$70,E$6)*E46 -> 0.3 | F47: =INDEX(Calib!$C$70:$G$70,F$6)*F46 -> 0.3 | G47: =INDEX(Calib!$C$70:$G$70,G$6)*G46 -> 0.3 | H47: =INDEX(Calib!$C$70:$G$70,H$6)*H46 -> 0.3 | I47: =INDEX(Calib!$C$70:$G$70,I$6)*I46 -> 0.3 | J47: =INDEX(Calib!$C$70:$G$70,J$6)*J46 -> 0.3 | ... AH47: =INDEX(Calib!$C$70:$G$70,AH$6)*AH46 -> 0.3
A48: η_d 情境倍數（基準 1；Sens_Perf 使用） | B48: x | C48: 1 | D48: 1 | E48: 0.5 | F48: 1 | G48: 1.5 | H48: 1 | I48: 1 | J48: 1 | K48: 1 | L48: 1 | M48: 1 | N48: 1 | O48: 1 | P48: 1 | Q48: 1 | R48: 1 | S48: 1 | T48: 1 | U48: 1 | V48: 1 | W48: 1 | X48: 1 | Y48: 1 | Z48: 1 | AA48: 1 | AB48: 1 | AC48: 1 | AD48: 1 | AE48: 1 | AF48: 1 | AG48: 1 | AH48: 1
A49: η_d（decode 每序列算力效率；含折減） | B49: % | C49: =INDEX(Calib!$C$68:$G$68,C$6)*C48*C46 -> 0.036042379 | D49: =INDEX(Calib!$C$68:$G$68,D$6)*D48*D46 -> 0.036042379 | E49: =INDEX(Calib!$C$68:$G$68,E$6)*E48*E46 -> 0.01802119 | F49: =INDEX(Calib!$C$68:$G$68,F$6)*F48*F46 -> 0.036042379 | G49: =INDEX(Calib!$C$68:$G$68,G$6)*G48*G46 -> 0.054063569 | H49: =INDEX(Calib!$C$68:$G$68,H$6)*H48*H46 -> 0.036042379 | I49: =INDEX(Calib!$C$68:$G$68,I$6)*I48*I46 -> 0.036042379 | J49: =INDEX(Calib!$C$68:$G$68,J$6)*J48*J46 -> 0.036042379 | ... AH49: =INDEX(Calib!$C$68:$G$68,AH$6)*AH48*AH46 -> 0.036042379
A50: 每層延遲情境倍數（基準 1） | B50: x | C50: 1 | D50: 1 | E50: 1 | F50: 1 | G50: 1 | H50: 1 | I50: 0.7 | J50: 1 | K50: 1.5 | L50: 1 | M50: 1 | N50: 1 | O50: 1 | P50: 1 | Q50: 1 | R50: 1 | S50: 1 | T50: 1 | U50: 1 | V50: 1 | W50: 1 | X50: 1 | Y50: 1 | Z50: 1 | AA50: 1 | AB50: 1 | AC50: 1 | AD50: 1 | AE50: 1 | AF50: 1 | AG50: 1 | AH50: 1
A51: 每層每次前向固定延遲（含折減） | B51: µs | C51: =INDEX(Calib!$C$69:$G$69,C$6)*C50/C46 -> 160.27856 | D51: =INDEX(Calib!$C$69:$G$69,D$6)*D50/D46 -> 160.27856 | E51: =INDEX(Calib!$C$69:$G$69,E$6)*E50/E46 -> 160.27856 | F51: =INDEX(Calib!$C$69:$G$69,F$6)*F50/F46 -> 160.27856 | G51: =INDEX(Calib!$C$69:$G$69,G$6)*G50/G46 -> 160.27856 | H51: =INDEX(Calib!$C$69:$G$69,H$6)*H50/H46 -> 160.27856 | I51: =INDEX(Calib!$C$69:$G$69,I$6)*I50/I46 -> 112.19499 | J51: =INDEX(Calib!$C$69:$G$69,J$6)*J50/J46 -> 160.27856 | ... AH51: =INDEX(Calib!$C$69:$G$69,AH$6)*AH50/AH46 -> 160.27856
A52: HBM 保留比例 | B52: % | C52: =Serving!$C$9 -> 0.1 | D52: =Serving!$C$9 -> 0.1 | E52: =Serving!$C$9 -> 0.1 | F52: =Serving!$C$9 -> 0.1 | G52: =Serving!$C$9 -> 0.1 | H52: =Serving!$C$9 -> 0.1 | I52: =Serving!$C$9 -> 0.1 | J52: =Serving!$C$9 -> 0.1 | ... AH52: =Serving!$C$9 -> 0.1
A53: 非專家權重占 HBM 上限 | B53: % | C53: =Serving!$C$10 -> 0.2 | D53: =Serving!$C$10 -> 0.2 | E53: =Serving!$C$10 -> 0.2 | F53: =Serving!$C$10 -> 0.2 | G53: =Serving!$C$10 -> 0.2 | H53: =Serving!$C$10 -> 0.2 | I53: =Serving!$C$10 -> 0.2 | J53: =Serving!$C$10 -> 0.2 | ... AH53: =Serving!$C$10 -> 0.2
A54: 專家權重占 HBM 上限 | B54: % | C54: =Serving!$C$11 -> 0.4 | D54: =Serving!$C$11 -> 0.4 | E54: =Serving!$C$11 -> 0.4 | F54: =Serving!$C$11 -> 0.4 | G54: =Serving!$C$11 -> 0.4 | H54: =Serving!$C$11 -> 0.4 | I54: =Serving!$C$11 -> 0.4 | J54: =Serving!$C$11 -> 0.4 | ... AH54: =Serving!$C$11 -> 0.4
A55: EP 啟用值 bytes/元素 | B55: B | C55: =Serving!$C$12 -> 3 | D55: =Serving!$C$12 -> 3 | E55: =Serving!$C$12 -> 3 | F55: =Serving!$C$12 -> 3 | G55: =Serving!$C$12 -> 3 | H55: =Serving!$C$12 -> 3 | I55: =Serving!$C$12 -> 3 | J55: =Serving!$C$12 -> 3 | ... AH55: =Serving!$C$12 -> 3
A56: KV 讀取效率 | B56: % | C56: =Serving!$C$13 -> 0.7 | D56: =Serving!$C$13 -> 0.7 | E56: =Serving!$C$13 -> 0.7 | F56: =Serving!$C$13 -> 0.7 | G56: =Serving!$C$13 -> 0.7 | H56: =Serving!$C$13 -> 0.7 | I56: =Serving!$C$13 -> 0.7 | J56: =Serving!$C$13 -> 0.7 | ... AH56: =Serving!$C$13 -> 0.7
A57: EP 通訊效率 | B57: % | C57: =Serving!$C$14 -> 0.7 | D57: =Serving!$C$14 -> 0.7 | E57: =Serving!$C$14 -> 0.7 | F57: =Serving!$C$14 -> 0.7 | G57: =Serving!$C$14 -> 0.7 | H57: =Serving!$C$14 -> 0.7 | I57: =Serving!$C$14 -> 0.7 | J57: =Serving!$C$14 -> 0.7 | ... AH57: =Serving!$C$14 -> 0.7
A58: 快取載入頻寬 | B58: TB/s | C58: =Serving!$C$15 -> 0.1 | D58: =Serving!$C$15 -> 0.1 | E58: =Serving!$C$15 -> 0.1 | F58: =Serving!$C$15 -> 0.1 | G58: =Serving!$C$15 -> 0.1 | H58: =Serving!$C$15 -> 0.1 | I58: =Serving!$C$15 -> 0.1 | J58: =Serving!$C$15 -> 0.1 | ... AH58: =Serving!$C$15 -> 0.1
A59: D. 每 token 計算量
A60: decode 被注意 token 數 | B60: tok | C60: =C32*IF(C33=0,C41,MIN(C41,C33))+(1-C32)*(C41/C34+C35) -> 2244 | D60: =D32*IF(D33=0,D41,MIN(D41,D33))+(1-D32)*(D41/D34+D35) -> 2244 | E60: =E32*IF(E33=0,E41,MIN(E41,E33))+(1-E32)*(E41/E34+E35) -> 2244 | F60: =F32*IF(F33=0,F41,MIN(F41,F33))+(1-F32)*(F41/F34+F35) -> 2244 | G60: =G32*IF(G33=0,G41,MIN(G41,G33))+(1-G32)*(G41/G34+G35) -> 2244 | H60: =H32*IF(H33=0,H41,MIN(H41,H33))+(1-H32)*(H41/H34+H35) -> 2244 | I60: =I32*IF(I33=0,I41,MIN(I41,I33))+(1-I32)*(I41/I34+I35) -> 2244 | J60: =J32*IF(J33=0,J41,MIN(J41,J33))+(1-J32)*(J41/J34+J35) -> 2244 | ... AH60: =AH32*IF(AH33=0,AH41,MIN(AH41,AH33))+(1-AH32)*(AH41/AH34+AH35) -> 34816
A61: decode FLOPs/token | B61: GFLOP | C61: =(2*C24*1000000000+C31*C60)/1000000000 -> 133.88332 | D61: =(2*D24*1000000000+D31*D60)/1000000000 -> 133.88332 | E61: =(2*E24*1000000000+E31*E60)/1000000000 -> 133.88332 | F61: =(2*F24*1000000000+F31*F60)/1000000000 -> 133.88332 | G61: =(2*G24*1000000000+G31*G60)/1000000000 -> 133.88332 | H61: =(2*H24*1000000000+H31*H60)/1000000000 -> 133.88332 | I61: =(2*I24*1000000000+I31*I60)/1000000000 -> 133.88332 | J61: =(2*J24*1000000000+J31*J60)/1000000000 -> 133.88332 | ... AH61: =(2*AH24*1000000000+AH31*AH60)/1000000000 -> 531.1276
A62: prefill 被注意 token 數 | B62: tok | C62: =C32*IF(C33=0,C42,MIN(C42,C33))+(1-C32)*(C42/C34+C35) -> 2208 | D62: =D32*IF(D33=0,D42,MIN(D42,D33))+(1-D32)*(D42/D34+D35) -> 2208 | E62: =E32*IF(E33=0,E42,MIN(E42,E33))+(1-E32)*(E42/E34+E35) -> 2208 | F62: =F32*IF(F33=0,F42,MIN(F42,F33))+(1-F32)*(F42/F34+F35) -> 2208 | G62: =G32*IF(G33=0,G42,MIN(G42,G33))+(1-G32)*(G42/G34+G35) -> 2208 | H62: =H32*IF(H33=0,H42,MIN(H42,H33))+(1-H32)*(H42/H34+H35) -> 2208 | I62: =I32*IF(I33=0,I42,MIN(I42,I33))+(1-I32)*(I42/I34+I35) -> 2208 | J62: =J32*IF(J33=0,J42,MIN(J42,J33))+(1-J32)*(J42/J34+J35) -> 2208 | ... AH62: =AH32*IF(AH33=0,AH42,MIN(AH42,AH33))+(1-AH32)*(AH42/AH34+AH35) -> 16384
A63: prefill FLOPs/token | B63: GFLOP | C63: =(2*C24*1000000000+C31*C62)/1000000000 -> 133.30765 | D63: =(2*D24*1000000000+D31*D62)/1000000000 -> 133.30765 | E63: =(2*E24*1000000000+E31*E62)/1000000000 -> 133.30765 | F63: =(2*F24*1000000000+F31*F62)/1000000000 -> 133.30765 | G63: =(2*G24*1000000000+G31*G62)/1000000000 -> 133.30765 | H63: =(2*H24*1000000000+H31*H62)/1000000000 -> 133.30765 | I63: =(2*I24*1000000000+I31*I62)/1000000000 -> 133.30765 | J63: =(2*J24*1000000000+J31*J62)/1000000000 -> 133.30765 | ... AH63: =(2*AH24*1000000000+AH31*AH62)/1000000000 -> 440.53064
A64: E. 記憶體配置（attention DP＋wide EP；每 GPU）
A65: 可用 HBM | B65: GB | C65: =C11*(1-C52) -> 259.2 | D65: =D11*(1-D52) -> 259.2 | E65: =E11*(1-E52) -> 259.2 | F65: =F11*(1-F52) -> 259.2 | G65: =G11*(1-G52) -> 259.2 | H65: =H11*(1-H52) -> 259.2 | I65: =I11*(1-I52) -> 259.2 | J65: =J11*(1-J52) -> 259.2 | ... AH65: =AH11*(1-AH52) -> 259.2
A66: 注意力 TP 度（自動） | C66: =MAX(1,CEILING(C28*C16/(C53*C65),1)) -> 1 | D66: =MAX(1,CEILING(D28*D16/(D53*D65),1)) -> 1 | E66: =MAX(1,CEILING(E28*E16/(E53*E65),1)) -> 1 | F66: =MAX(1,CEILING(F28*F16/(F53*F65),1)) -> 1 | G66: =MAX(1,CEILING(G28*G16/(G53*G65),1)) -> 1 | H66: =MAX(1,CEILING(H28*H16/(H53*H65),1)) -> 1 | I66: =MAX(1,CEILING(I28*I16/(I53*I65),1)) -> 1 | J66: =MAX(1,CEILING(J28*J16/(J53*J65),1)) -> 1 | ... AH66: =MAX(1,CEILING(AH28*AH16/(AH53*AH65),1)) -> 1
A67: decode EP 寬度（自動） | B67: GPU | C67: =MAX(C14,CEILING(C29*C15/(C54*C65),1)) -> 32 | D67: =MAX(D14,CEILING(D29*D15/(D54*D65),1)) -> 32 | E67: =MAX(E14,CEILING(E29*E15/(E54*E65),1)) -> 32 | F67: =MAX(F14,CEILING(F29*F15/(F54*F65),1)) -> 32 | G67: =MAX(G14,CEILING(G29*G15/(G54*G65),1)) -> 32 | H67: =MAX(H14,CEILING(H29*H15/(H54*H65),1)) -> 32 | I67: =MAX(I14,CEILING(I29*I15/(I54*I65),1)) -> 32 | J67: =MAX(J14,CEILING(J29*J15/(J54*J65),1)) -> 32 | ... AH67: =MAX(AH14,CEILING(AH29*AH15/(AH54*AH65),1)) -> 32
A68: 每 GPU 權重 | B68: GB | C68: =C28*C16/C66+C29*C15/C67 -> 48.046332 | D68: =D28*D16/D66+D29*D15/D67 -> 48.046332 | E68: =E28*E16/E66+E29*E15/E67 -> 48.046332 | F68: =F28*F16/F66+F29*F15/F67 -> 48.046332 | G68: =G28*G16/G66+G29*G15/G67 -> 48.046332 | H68: =H28*H16/H66+H29*H15/H67 -> 48.046332 | I68: =I28*I16/I66+I29*I15/I67 -> 48.046332 | J68: =J28*J16/J66+J29*J15/J67 -> 48.046332 | ... AH68: =AH28*AH16/AH66+AH29*AH15/AH67 -> 118.52248
A69: 權重占可用 HBM | B69: % | C69: =C68/C65 -> 0.18536394 | D69: =D68/D65 -> 0.18536394 | E69: =E68/E65 -> 0.18536394 | F69: =F68/F65 -> 0.18536394 | G69: =G68/G65 -> 0.18536394 | H69: =H68/H65 -> 0.18536394 | I69: =I68/I65 -> 0.18536394 | J69: =J68/J65 -> 0.18536394 | ... AH69: =AH68/AH65 -> 0.45726264
A70: F. Prefill（算力受限）
A71: prefill tok/s（每 prefill GPU） | B71: tok/s | C71: =C47*C10*1000000000000000/(C63*1000000000) -> 78765.172 | D71: =D47*D10*1000000000000000/(D63*1000000000) -> 33756.502 | E71: =E47*E10*1000000000000000/(E63*1000000000) -> 78765.172 | F71: =F47*F10*1000000000000000/(F63*1000000000) -> 33756.502 | G71: =G47*G10*1000000000000000/(G63*1000000000) -> 78765.172 | H71: =H47*H10*1000000000000000/(H63*1000000000) -> 33756.502 | I71: =I47*I10*1000000000000000/(I63*1000000000) -> 78765.172 | J71: =J47*J10*1000000000000000/(J63*1000000000) -> 33756.502 | ... AH71: =AH47*AH10*1000000000000000/(AH63*1000000000) -> 10214.954
A72: TTFT（計算部分） | B72: s | C72: =C39*C63*1000000000/(C47*C10*1000000000000000*C17) -> 0.05200268 | D72: =D39*D63*1000000000/(D47*D10*1000000000000000*D17) -> 0.12133959 | E72: =E39*E63*1000000000/(E47*E10*1000000000000000*E17) -> 0.05200268 | F72: =F39*F63*1000000000/(F47*F10*1000000000000000*F17) -> 0.12133959 | G72: =G39*G63*1000000000/(G47*G10*1000000000000000*G17) -> 0.05200268 | H72: =H39*H63*1000000000/(H47*H10*1000000000000000*H17) -> 0.12133959 | I72: =I39*I63*1000000000/(I47*I10*1000000000000000*I17) -> 0.05200268 | J72: =J39*J63*1000000000/(J47*J10*1000000000000000*J17) -> 0.12133959 | ... AH72: =AH39*AH63*1000000000/(AH47*AH10*1000000000000000*AH17) -> 0.80196155
A73: TTFT 符合上限 | C73: =IF(C72<=C38,"是","否") -> 是 | D73: =IF(D72<=D38,"是","否") -> 是 | E73: =IF(E72<=E38,"是","否") -> 是 | F73: =IF(F72<=F38,"是","否") -> 是 | G73: =IF(G72<=G38,"是","否") -> 是 | H73: =IF(H72<=H38,"是","否") -> 是 | I73: =IF(I72<=I38,"是","否") -> 是 | J73: =IF(J72<=J38,"是","否") -> 是 | ... AH73: =IF(AH72<=AH38,"是","否") -> 是
A74: G. Decode：每步時間＝固定延遲＋B × 每序列時間；B* ＝ min(SLO 上限, HBM 容量上限)
A75: 每步固定延遲（權重讀取＋逐層延遲） | B75: ms | C75: =C68/C12+(C25+C43)*C51/1000 -> 12.441752 | D75: =D68/D12+(D25+D43)*D51/1000 -> 16.263619 | E75: =E68/E12+(E25+E43)*E51/1000 -> 12.441752 | F75: =F68/F12+(F25+F43)*F51/1000 -> 16.263619 | G75: =G68/G12+(G25+G43)*G51/1000 -> 12.441752 | H75: =H68/H12+(H25+H43)*H51/1000 -> 16.263619 | I75: =I68/I12+(I25+I43)*I51/1000 -> 9.3644037 | J75: =J68/J12+(J25+J43)*J51/1000 -> 16.263619 | ... AH75: =AH68/AH12+(AH25+AH43)*AH51/1000 -> 31.324001
A76: 每序列每步 — 算力項 | B76: ms | C76: =(C43+1)*C61/(C10*C49)/1000 -> 0.42452665 | D76: =(D43+1)*D61/(D10*D49)/1000 -> 0.99056219 | E76: =(E43+1)*E61/(E10*E49)/1000 -> 0.84905331 | F76: =(F43+1)*F61/(F10*F49)/1000 -> 0.99056219 | G76: =(G43+1)*G61/(G10*G49)/1000 -> 0.28301777 | H76: =(H43+1)*H61/(H10*H49)/1000 -> 0.99056219 | I76: =(I43+1)*I61/(I10*I49)/1000 -> 0.42452665 | J76: =(J43+1)*J61/(J10*J49)/1000 -> 0.99056219 | ... AH76: =(AH43+1)*AH61/(AH10*AH49)/1000 -> 3.9296525
A77: 每序列每步 — KV 讀取項 | B77: ms | C77: =C30*C41/(C12*C56)/1000000000 -> 0.0044819948 | D77: =D30*D41/(D12*D56)/1000000000 -> 0.012325486 | E77: =E30*E41/(E12*E56)/1000000000 -> 0.0044819948 | F77: =F30*F41/(F12*F56)/1000000000 -> 0.012325486 | G77: =G30*G41/(G12*G56)/1000000000 -> 0.0044819948 | H77: =H30*H41/(H12*H56)/1000000000 -> 0.012325486 | I77: =I30*I41/(I12*I56)/1000000000 -> 0.0044819948 | J77: =J30*J41/(J12*J56)/1000000000 -> 0.012325486 | ... AH77: =AH30*AH41/(AH12*AH56)/1000000000 -> 1.2732709
A78: 每序列每步 — EP 通訊項 | B78: ms | C78: =(C43+1)*C25*C27*C26*C55*(C67-1)/C67/(C13*C57)/1000000000 -> 0.0242048 | D78: =(D43+1)*D25*D27*D26*D55*(D67-1)/D67/(D13*D57)/1000000000 -> 0.0484096 | E78: =(E43+1)*E25*E27*E26*E55*(E67-1)/E67/(E13*E57)/1000000000 -> 0.0242048 | F78: =(F43+1)*F25*F27*F26*F55*(F67-1)/F67/(F13*F57)/1000000000 -> 0.0484096 | G78: =(G43+1)*G25*G27*G26*G55*(G67-1)/G67/(G13*G57)/1000000000 -> 0.0242048 | H78: =(H43+1)*H25*H27*H26*H55*(H67-1)/H67/(H13*H57)/1000000000 -> 0.0484096 | I78: =(I43+1)*I25*I27*I26*I55*(I67-1)/I67/(I13*I57)/1000000000 -> 0.0242048 | J78: =(J43+1)*J25*J27*J26*J55*(J67-1)/J67/(J13*J57)/1000000000 -> 0.0484096 | ... AH78: =(AH43+1)*AH25*AH27*AH26*AH55*(AH67-1)/AH67/(AH13*AH57)/1000000000 -> 0.36278857
A79: 每序列每步（取最大，假設三者可重疊） | B79: ms | C79: =MAX(C76,C77,C78) -> 0.42452665 | D79: =MAX(D76,D77,D78) -> 0.99056219 | E79: =MAX(E76,E77,E78) -> 0.84905331 | F79: =MAX(F76,F77,F78) -> 0.99056219 | G79: =MAX(G76,G77,G78) -> 0.28301777 | H79: =MAX(H76,H77,H78) -> 0.99056219 | I79: =MAX(I76,I77,I78) -> 0.42452665 | J79: =MAX(J76,J77,J78) -> 0.99056219 | ... AH79: =MAX(AH76,AH77,AH78) -> 3.9296525
A80: 每序列綁定項 | C80: =IF(C79=C76,"算力",IF(C79=C77,"KV 頻寬","EP 通訊")) -> 算力 | D80: =IF(D79=D76,"算力",IF(D79=D77,"KV 頻寬","EP 通訊")) -> 算力 | E80: =IF(E79=E76,"算力",IF(E79=E77,"KV 頻寬","EP 通訊")) -> 算力 | F80: =IF(F79=F76,"算力",IF(F79=F77,"KV 頻寬","EP 通訊")) -> 算力 | G80: =IF(G79=G76,"算力",IF(G79=G77,"KV 頻寬","EP 通訊")) -> 算力 | H80: =IF(H79=H76,"算力",IF(H79=H77,"KV 頻寬","EP 通訊")) -> 算力 | I80: =IF(I79=I76,"算力",IF(I79=I77,"KV 頻寬","EP 通訊")) -> 算力 | J80: =IF(J79=J76,"算力",IF(J79=J77,"KV 頻寬","EP 通訊")) -> 算力 | ... AH80: =IF(AH79=AH76,"算力",IF(AH79=AH77,"KV 頻寬","EP 通訊")) -> 算力
A81: SLO 允許的批次上限 | B81: 序列/GPU | C81: =(1000*C45/C37-C75)/C79 -> 62.487192 | D81: =(1000*D45/D37-D75)/D79 -> 22.921944 | E81: =(1000*E45/E37-E75)/E79 -> 31.243596 | F81: =(1000*F45/F37-F75)/F79 -> 22.921944 | G81: =(1000*G45/G37-G75)/G79 -> 93.730788 | H81: =(1000*H45/H37-H75)/H79 -> 22.921944 | I81: =(1000*I45/I37-I75)/I79 -> 69.736085 | J81: =(1000*J45/J37-J75)/J79 -> 22.921944 | ... AH81: =(1000*AH45/AH37-AH75)/AH79 -> 3.7485615
A82: HBM 容量允許的批次上限 | B82: 序列/GPU | C82: =(C65-C68)*1000000000/(C30*C41) -> 3059.1908 | D82: =(D65-D68)*1000000000/(D30*D41) -> 3059.1908 | E82: =(E65-E68)*1000000000/(E30*E41) -> 3059.1908 | F82: =(F65-F68)*1000000000/(F30*F41) -> 3059.1908 | G82: =(G65-G68)*1000000000/(G30*G41) -> 3059.1908 | H82: =(H65-H68)*1000000000/(H30*H41) -> 3059.1908 | I82: =(I65-I68)*1000000000/(I30*I41) -> 3059.1908 | J82: =(J65-J68)*1000000000/(J30*J41) -> 3059.1908 | ... AH82: =(AH65-AH68)*1000000000/(AH30*AH41) -> 19.729491
A83: 採用批次 B* | B83: 序列/GPU | C83: =MAX(0,MIN(C81,C82)) -> 62.487192 | D83: =MAX(0,MIN(D81,D82)) -> 22.921944 | E83: =MAX(0,MIN(E81,E82)) -> 31.243596 | F83: =MAX(0,MIN(F81,F82)) -> 22.921944 | G83: =MAX(0,MIN(G81,G82)) -> 93.730788 | H83: =MAX(0,MIN(H81,H82)) -> 22.921944 | I83: =MAX(0,MIN(I81,I82)) -> 69.736085 | J83: =MAX(0,MIN(J81,J82)) -> 22.921944 | ... AH83: =MAX(0,MIN(AH81,AH82)) -> 3.7485615
A84: decode tok/s（每 decode GPU） | B84: tok/s | C84: =IF(C83>0,C83*C45/((C75+C83*C79)/1000),0) -> 4061.6675 | D84: =IF(D83>0,D83*D45/((D75+D83*D79)/1000),0) -> 1489.9264 | E84: =IF(E83>0,E83*E45/((E75+E83*E79)/1000),0) -> 2030.8337 | F84: =IF(F83>0,F83*F45/((F75+F83*F79)/1000),0) -> 1489.9264 | G84: =IF(G83>0,G83*G45/((G75+G83*G79)/1000),0) -> 6092.5012 | H84: =IF(H83>0,H83*H45/((H75+H83*H79)/1000),0) -> 1489.9264 | I84: =IF(I83>0,I83*I45/((I75+I83*I79)/1000),0) -> 4532.8456 | J84: =IF(J83>0,J83*J45/((J75+J83*J79)/1000),0) -> 1489.9264 | ... AH84: =IF(AH83>0,AH83*AH45/((AH75+AH83*AH79)/1000),0) -> 206.17088
A85: 實際每用戶速度 | B85: tok/s | C85: =IF(C83>0,C45/((C75+C83*C79)/1000),0) -> 65 | D85: =IF(D83>0,D45/((D75+D83*D79)/1000),0) -> 65 | E85: =IF(E83>0,E45/((E75+E83*E79)/1000),0) -> 65 | F85: =IF(F83>0,F45/((F75+F83*F79)/1000),0) -> 65 | G85: =IF(G83>0,G45/((G75+G83*G79)/1000),0) -> 65 | H85: =IF(H83>0,H45/((H75+H83*H79)/1000),0) -> 65 | I85: =IF(I83>0,I45/((I75+I83*I79)/1000),0) -> 65 | J85: =IF(J83>0,J45/((J75+J83*J79)/1000),0) -> 65 | ... AH85: =IF(AH83>0,AH45/((AH75+AH83*AH79)/1000),0) -> 55
A86: 綁定約束 | C86: =IF(C83<=0,"SLO 不可達",IF(C81<=C82,"SLO（"&C80&"）","HBM 容量")) -> SLO（算力） | D86: =IF(D83<=0,"SLO 不可達",IF(D81<=D82,"SLO（"&D80&"）","HBM 容量")) -> SLO（算力） | E86: =IF(E83<=0,"SLO 不可達",IF(E81<=E82,"SLO（"&E80&"）","HBM 容量")) -> SLO（算力） | F86: =IF(F83<=0,"SLO 不可達",IF(F81<=F82,"SLO（"&F80&"）","HBM 容量")) -> SLO（算力） | G86: =IF(G83<=0,"SLO 不可達",IF(G81<=G82,"SLO（"&G80&"）","HBM 容量")) -> SLO（算力） | H86: =IF(H83<=0,"SLO 不可達",IF(H81<=H82,"SLO（"&H80&"）","HBM 容量")) -> SLO（算力） | I86: =IF(I83<=0,"SLO 不可達",IF(I81<=I82,"SLO（"&I80&"）","HBM 容量")) -> SLO（算力） | J86: =IF(J83<=0,"SLO 不可達",IF(J81<=J82,"SLO（"&J80&"）","HBM 容量")) -> SLO（算力） | ... AH86: =IF(AH83<=0,"SLO 不可達",IF(AH81<=AH82,"SLO（"&AH80&"）","HBM 容量")) -> SLO（算力）
A87: KV 占可用 HBM | B87: % | C87: =C83*C30*C41/1000000000/C65 -> 0.016639799 | D87: =D83*D30*D41/1000000000/D65 -> 0.0061039156 | E87: =E83*E30*E41/1000000000/E65 -> 0.0083198996 | F87: =F83*F30*F41/1000000000/F65 -> 0.0061039156 | G87: =G83*G30*G41/1000000000/G65 -> 0.024959699 | H87: =H83*H30*H41/1000000000/H65 -> 0.0061039156 | I87: =I83*I30*I41/1000000000/I65 -> 0.018570117 | J87: =J83*J30*J41/1000000000/J65 -> 0.0061039156 | ... AH87: =AH83*AH30*AH41/1000000000/AH65 -> 0.10311895
A88: H. 每架與每 GW（參考任務；P:D 依工作量配比；100% 利用率）
A89: 每請求 GPU 秒 | B89: GPU-s | C89: =IF(C84>0,C39/C71+C40/C84,0) -> 0.71223712 | D89: =IF(D84>0,D39/D71+D40/D84,0) -> 1.8599229 | E89: =IF(E84>0,E39/E71+E40/E84,0) -> 1.2164635 | F89: =IF(F84>0,F39/F71+F40/F84,0) -> 1.8599229 | G89: =IF(G84>0,G39/G71+G40/G84,0) -> 0.54416166 | H89: =IF(H84>0,H39/H71+H40/H84,0) -> 1.8599229 | I89: =IF(I84>0,I39/I71+I40/I84,0) -> 0.65982404 | J89: =IF(J84>0,J39/J71+J40/J84,0) -> 1.8599229 | ... AH89: =IF(AH84>0,AH39/AH71+AH40/AH84,0) -> 23.074861
A90: prefill GPU 占比 | B90: % | C90: =IF(C89>0,(C39/C71)/C89,0) -> 0.29205262 | D90: =IF(D89>0,(D39/D71)/D89,0) -> 0.26095616 | E90: =IF(E89>0,(E39/E71)/E89,0) -> 0.17099626 | F90: =IF(F89>0,(F39/F71)/F89,0) -> 0.26095616 | G90: =IF(G89>0,(G39/G71)/G89,0) -> 0.38225905 | H90: =IF(H89>0,(H39/H71)/H89,0) -> 0.26095616 | I90: =IF(I89>0,(I39/I71)/I89,0) -> 0.31525181 | J90: =IF(J89>0,(J39/J71)/J89,0) -> 0.26095616 | ... AH90: =IF(AH89>0,(AH39/AH71)/AH89,0) -> 0.13901909
A91: 每架總 tok/s | B91: tok/s | C91: =IF(C89>0,C18*(C39+C40)/C89,0) -> 1863289.6 | D91: =IF(D89>0,D18*(D39+D40)/D89,0) -> 713526.35 | E91: =IF(E89>0,E18*(E39+E40)/E89,0) -> 1090952.6 | F91: =IF(F89>0,F18*(F39+F40)/F89,0) -> 713526.35 | G91: =IF(G89>0,G18*(G39+G40)/G89,0) -> 2438804.7 | H91: =IF(H89>0,H18*(H39+H40)/H89,0) -> 713526.35 | I91: =IF(I89>0,I18*(I39+I40)/I89,0) -> 2011299.9 | J91: =IF(J89>0,J18*(J39+J40)/J89,0) -> 713526.35 | ... AH91: =IF(AH89>0,AH18*(AH39+AH40)/AH89,0) -> 115025.96
A92: 每架 decode tok/s | B92: tok/s | C92: =C91*C40/(C39+C40) -> 207032.17 | D92: =D91*D40/(D39+D40) -> 79280.705 | E92: =E91*E40/(E39+E40) -> 121216.95 | F92: =F91*F40/(F39+F40) -> 79280.705 | G92: =G91*G40/(G39+G40) -> 270978.3 | H92: =H91*H40/(H39+H40) -> 79280.705 | I92: =I91*I40/(I39+I40) -> 223477.76 | J92: =J91*J40/(J39+J40) -> 79280.705 | ... AH92: =AH91*AH40/(AH39+AH40) -> 12780.662
A93: 每架 prefill tok/s | B93: tok/s | C93: =C91-C92 -> 1656257.4 | D93: =D91-D92 -> 634245.64 | E93: =E91-E92 -> 969735.61 | F93: =F91-F92 -> 634245.64 | G93: =G91-G92 -> 2167826.4 | H93: =H91-H92 -> 634245.64 | I93: =I91-I92 -> 1787822.1 | J93: =J91-J92 -> 634245.64 | ... AH93: =AH91-AH92 -> 102245.3
A94: 每 GW 總產出 | B94: M tok/年 | C94: =C91*C21*8760*3600/1000000 -> 2.3809835e+11 | D94: =D91*D21*8760*3600/1000000 -> 1.5109936e+11 | E94: =E91*E21*8760*3600/1000000 -> 1.3940614e+11 | F94: =F91*F21*8760*3600/1000000 -> 1.5109936e+11 | G94: =G91*G21*8760*3600/1000000 -> 3.1163991e+11 | H94: =H91*H21*8760*3600/1000000 -> 1.5109936e+11 | I94: =I91*I21*8760*3600/1000000 -> 2.5701168e+11 | J94: =J91*J21*8760*3600/1000000 -> 1.5109936e+11 | ... AH94: =AH91*AH21*8760*3600/1000000 -> 2.4358384e+10
A95: 每 GW decode 產出 | B95: M tok/年 | C95: =C92*C21*8760*3600/1000000 -> 2.6455373e+10 | D95: =D92*D21*8760*3600/1000000 -> 1.6788818e+10 | E95: =E92*E21*8760*3600/1000000 -> 1.5489571e+10 | F95: =F92*F21*8760*3600/1000000 -> 1.6788818e+10 | G95: =G92*G21*8760*3600/1000000 -> 3.4626656e+10 | H95: =H92*H21*8760*3600/1000000 -> 1.6788818e+10 | I95: =I92*I21*8760*3600/1000000 -> 2.8556854e+10 | J95: =J92*J21*8760*3600/1000000 -> 1.6788818e+10 | ... AH95: =AH92*AH21*8760*3600/1000000 -> 2.7064872e+09
A96: I. 每 M token GPU 秒（供 Unit_Cost）與速覽成本
A97: 新鮮 prefill | B97: GPU-s/M | C97: =1000000/C71 -> 12.695967 | D97: =1000000/D71 -> 29.623922 | E97: =1000000/E71 -> 12.695967 | F97: =1000000/F71 -> 29.623922 | G97: =1000000/G71 -> 12.695967 | H97: =1000000/H71 -> 29.623922 | I97: =1000000/I71 -> 12.695967 | J97: =1000000/J71 -> 29.623922 | ... AH97: =1000000/AH71 -> 97.895697
A98: 快取命中 prefill（KV 載入） | B98: GPU-s/M | C98: =1000000*C30/(C58*1000000000000) -> 0.03965 | D98: =1000000*D30/(D58*1000000000000) -> 0.03965 | E98: =1000000*E30/(E58*1000000000000) -> 0.03965 | F98: =1000000*F30/(F58*1000000000000) -> 0.03965 | G98: =1000000*G30/(G58*1000000000000) -> 0.03965 | H98: =1000000*H30/(H58*1000000000000) -> 0.03965 | I98: =1000000*I30/(I58*1000000000000) -> 0.03965 | J98: =1000000*J30/(J58*1000000000000) -> 0.03965 | ... AH98: =1000000*AH30/(AH58*1000000000000) -> 2.048
A99: decode（0＝SLO 不可達） | B99: GPU-s/M | C99: =IF(C84>0,1000000/C84,0) -> 246.2043 | D99: =IF(D84>0,1000000/D84,0) -> 671.17411 | E99: =IF(E84>0,1000000/E84,0) -> 492.4086 | F99: =IF(F84>0,1000000/F84,0) -> 671.17411 | G99: =IF(G84>0,1000000/G84,0) -> 164.1362 | H99: =IF(H84>0,1000000/H84,0) -> 671.17411 | I99: =IF(I84>0,1000000/I84,0) -> 220.61197 | J99: =IF(J84>0,1000000/J84,0) -> 671.17411 | ... AH99: =IF(AH84>0,1000000/AH84,0) -> 4850.3455
A100: 速覽：新鮮 prefill $/M（經濟、基準成本、100%） | B100: $/M | C100: =INDEX(DC_Cost!$C$58:$Q$58,3*(C$6-1)+2)/3600*C97 -> 0.016634195 | D100: =INDEX(DC_Cost!$C$58:$Q$58,3*(D$6-1)+2)/3600*D97 -> 0.024583847 | E100: =INDEX(DC_Cost!$C$58:$Q$58,3*(E$6-1)+2)/3600*E97 -> 0.016634195 | F100: =INDEX(DC_Cost!$C$58:$Q$58,3*(F$6-1)+2)/3600*F97 -> 0.024583847 | G100: =INDEX(DC_Cost!$C$58:$Q$58,3*(G$6-1)+2)/3600*G97 -> 0.016634195 | H100: =INDEX(DC_Cost!$C$58:$Q$58,3*(H$6-1)+2)/3600*H97 -> 0.024583847 | I100: =INDEX(DC_Cost!$C$58:$Q$58,3*(I$6-1)+2)/3600*I97 -> 0.016634195 | J100: =INDEX(DC_Cost!$C$58:$Q$58,3*(J$6-1)+2)/3600*J97 -> 0.024583847 | ... AH100: =INDEX(DC_Cost!$C$58:$Q$58,3*(AH$6-1)+2)/3600*AH97 -> 0.081240182
A101: 速覽：decode $/M（經濟、基準成本、100%） | B101: $/M | C101: =IF(C99>0,INDEX(DC_Cost!$C$58:$Q$58,3*(C$6-1)+2)/3600*C99,0) -> 0.3225757 | D101: =IF(D99>0,INDEX(DC_Cost!$C$58:$Q$58,3*(D$6-1)+2)/3600*D99,0) -> 0.55698369 | E101: =IF(E99>0,INDEX(DC_Cost!$C$58:$Q$58,3*(E$6-1)+2)/3600*E99,0) -> 0.64515139 | F101: =IF(F99>0,INDEX(DC_Cost!$C$58:$Q$58,3*(F$6-1)+2)/3600*F99,0) -> 0.55698369 | G101: =IF(G99>0,INDEX(DC_Cost!$C$58:$Q$58,3*(G$6-1)+2)/3600*G99,0) -> 0.21505046 | H101: =IF(H99>0,INDEX(DC_Cost!$C$58:$Q$58,3*(H$6-1)+2)/3600*H99,0) -> 0.55698369 | I101: =IF(I99>0,INDEX(DC_Cost!$C$58:$Q$58,3*(I$6-1)+2)/3600*I99,0) -> 0.28904475 | J101: =IF(J99>0,INDEX(DC_Cost!$C$58:$Q$58,3*(J$6-1)+2)/3600*J99,0) -> 0.55698369 | ... AH101: =IF(AH99>0,INDEX(DC_Cost!$C$58:$Q$58,3*(AH$6-1)+2)/3600*AH99,0) -> 4.0251304
...

Sheet Unit_Cost
A1: Unit_Cost — 每 M token 成本（世代 × 成本情境；依層級分區；新鮮 prefill／快取 prefill／decode）
A2: 成本＝每 GPU 小時持有成本（DC_Cost）× 每 M token GPU 秒（Perf）。100% 為理想上限；基準利用率版＝100% 版 ÷ 利用率。快取命中只計 KV 載入 GPU 時間，未計儲存成本
A4: 世代 | C4: =DC_Cost!C4 -> Hopper H100 | D4: =DC_Cost!D4 -> Hopper H100 | E4: =DC_Cost!E4 -> Hopper H100 | F4: =DC_Cost!F4 -> GB200 NVL72 | G4: =DC_Cost!G4 -> GB200 NVL72 | H4: =DC_Cost!H4 -> GB200 NVL72 | I4: =DC_Cost!I4 -> GB300 NVL72 | J4: =DC_Cost!J4 -> GB300 NVL72 | ... Q4: =DC_Cost!Q4 -> Rubin Ultra NVL576
A5: 成本情境 | C5: =DC_Cost!C5 -> 低成本 | D5: =DC_Cost!D5 -> 基準 | E5: =DC_Cost!E5 -> 高成本 | F5: =DC_Cost!F5 -> 低成本 | G5: =DC_Cost!G5 -> 基準 | H5: =DC_Cost!H5 -> 高成本 | I5: =DC_Cost!I5 -> 低成本 | J5: =DC_Cost!J5 -> 基準 | ... Q5: =DC_Cost!Q5 -> 高成本
A6: 世代索引 | C6: 1 | D6: 1 | E6: 1 | F6: 2 | G6: 2 | H6: 2 | I6: 3 | J6: 3 | K6: 3 | L6: 4 | M6: 4 | N6: 4 | O6: 5 | P6: 5 | Q6: 5
A7: 共用
A8: 每 GPU 小時持有成本 — 經濟 | B8: $/GPU-hr | C8: =DC_Cost!C58 -> 1.1128667 | D8: =DC_Cost!D58 -> 1.6050293 | E8: =DC_Cost!E58 -> 2.767201 | F8: =DC_Cost!F58 -> 1.5435902 | G8: =DC_Cost!G58 -> 2.0767647 | H8: =DC_Cost!H58 -> 3.379614 | I8: =DC_Cost!I58 -> 2.0442466 | J8: =DC_Cost!J58 -> 2.9875129 | ... Q8: =DC_Cost!Q58 -> 15.917013
A9: 每 GPU 小時持有成本 — 會計 | B9: $/GPU-hr | C9: =DC_Cost!C57 -> 0.85832849 | D9: =DC_Cost!D57 -> 1.1918455 | E9: =DC_Cost!E57 -> 2.058675 | F9: =DC_Cost!F57 -> 1.1900066 | G9: =DC_Cost!G57 -> 1.538515 | H9: =DC_Cost!H57 -> 2.4977877 | I9: =DC_Cost!I57 -> 1.5850033 | J9: =DC_Cost!J57 -> 2.230249 | ... Q9: =DC_Cost!Q57 -> 12.060748
A10: 基準利用率 | B10: % | C10: =Serving!$C$17 -> 0.6 | D10: =Serving!$C$17 -> 0.6 | E10: =Serving!$C$17 -> 0.6 | F10: =Serving!$C$17 -> 0.6 | G10: =Serving!$C$17 -> 0.6 | H10: =Serving!$C$17 -> 0.6 | I10: =Serving!$C$17 -> 0.6 | J10: =Serving!$C$17 -> 0.6 | ... Q10: =Serving!$C$17 -> 0.6
A12: Luna（低層）
A13: GPU 秒／M 新鮮 prefill | B13: GPU-s | C13: =INDEX(Perf!$C$97:$Q$97,3*(C$6-1)+1) -> 128.05397 | D13: =INDEX(Perf!$C$97:$Q$97,3*(D$6-1)+1) -> 128.05397 | E13: =INDEX(Perf!$C$97:$Q$97,3*(E$6-1)+1) -> 128.05397 | F13: =INDEX(Perf!$C$97:$Q$97,3*(F$6-1)+1) -> 12.664537 | G13: =INDEX(Perf!$C$97:$Q$97,3*(G$6-1)+1) -> 12.664537 | H13: =INDEX(Perf!$C$97:$Q$97,3*(H$6-1)+1) -> 12.664537 | I13: =INDEX(Perf!$C$97:$Q$97,3*(I$6-1)+1) -> 8.443025 | J13: =INDEX(Perf!$C$97:$Q$97,3*(J$6-1)+1) -> 8.443025 | ... Q13: =INDEX(Perf!$C$97:$Q$97,3*(Q$6-1)+1) -> 1.7348681
A14: GPU 秒／M 快取命中 prefill | B14: GPU-s | C14: =INDEX(Perf!$C$98:$Q$98,3*(C$6-1)+1) -> 0.02795 | D14: =INDEX(Perf!$C$98:$Q$98,3*(D$6-1)+1) -> 0.02795 | E14: =INDEX(Perf!$C$98:$Q$98,3*(E$6-1)+1) -> 0.02795 | F14: =INDEX(Perf!$C$98:$Q$98,3*(F$6-1)+1) -> 0.02795 | G14: =INDEX(Perf!$C$98:$Q$98,3*(G$6-1)+1) -> 0.02795 | H14: =INDEX(Perf!$C$98:$Q$98,3*(H$6-1)+1) -> 0.02795 | I14: =INDEX(Perf!$C$98:$Q$98,3*(I$6-1)+1) -> 0.02795 | J14: =INDEX(Perf!$C$98:$Q$98,3*(J$6-1)+1) -> 0.02795 | ... Q14: =INDEX(Perf!$C$98:$Q$98,3*(Q$6-1)+1) -> 0.02795
A15: GPU 秒／M decode（0＝SLO 不可達） | B15: GPU-s | C15: =INDEX(Perf!$C$99:$Q$99,3*(C$6-1)+1) -> 1680.2103 | D15: =INDEX(Perf!$C$99:$Q$99,3*(D$6-1)+1) -> 1680.2103 | E15: =INDEX(Perf!$C$99:$Q$99,3*(E$6-1)+1) -> 1680.2103 | F15: =INDEX(Perf!$C$99:$Q$99,3*(F$6-1)+1) -> 285.73672 | G15: =INDEX(Perf!$C$99:$Q$99,3*(G$6-1)+1) -> 285.73672 | H15: =INDEX(Perf!$C$99:$Q$99,3*(H$6-1)+1) -> 285.73672 | I15: =INDEX(Perf!$C$99:$Q$99,3*(I$6-1)+1) -> 190.49115 | J15: =INDEX(Perf!$C$99:$Q$99,3*(J$6-1)+1) -> 190.49115 | ... Q15: =INDEX(Perf!$C$99:$Q$99,3*(Q$6-1)+1) -> 36.115692
A16: 新鮮 prefill $/M — 經濟、100% | B16: $/M | C16: =C$8/3600*C13 -> 0.039585277 | D16: =D$8/3600*D13 -> 0.057091768 | E16: =E$8/3600*E13 -> 0.098430851 | F16: =F$8/3600*F13 -> 0.0054302376 | G16: =G$8/3600*G13 -> 0.0073059068 | H16: =H$8/3600*H13 -> 0.011889235 | I16: =I$8/3600*I13 -> 0.0047943402 | J16: =J$8/3600*J13 -> 0.0070065683 | ... Q16: =Q$8/3600*Q13 -> 0.007670533
A17: 快取命中 prefill $/M — 經濟、100% | B17: $/M | C17: =C$8/3600*C14 -> 8.6401733e-06 | D17: =D$8/3600*D14 -> 1.2461269e-05 | E17: =E$8/3600*E14 -> 2.1484241e-05 | F17: =F$8/3600*F14 -> 1.1984263e-05 | G17: =G$8/3600*G14 -> 1.6123771e-05 | H17: =H$8/3600*H14 -> 2.6238947e-05 | I17: =I$8/3600*I14 -> 1.5871303e-05 | J17: =J$8/3600*J14 -> 2.3194718e-05 | ... Q17: =Q$8/3600*Q14 -> 0.00012357792
A18: decode $/M — 經濟、100% | B18: $/M | C18: =IF(C15>0,C$8/3600*C15,"SLO 不可達") -> 0.5194028 | D18: =IF(D15>0,D$8/3600*D15,"SLO 不可達") -> 0.74910741 | E18: =IF(E15>0,E$8/3600*E15,"SLO 不可達") -> 1.2915221 | F18: =IF(F15>0,F$8/3600*F15,"SLO 不可達") -> 0.12251678 | G18: =IF(G15>0,G$8/3600*G15,"SLO 不可達") -> 0.16483554 | H18: =IF(H15>0,H$8/3600*H15,"SLO 不可達") -> 0.26824439 | I18: =IF(I15>0,I$8/3600*I15,"SLO 不可達") -> 0.10816969 | J18: =IF(J15>0,J$8/3600*J15,"SLO 不可達") -> 0.15808188 | ... Q18: =IF(Q15>0,Q$8/3600*Q15,"SLO 不可達") -> 0.15968165
A19: 新鮮 prefill $/M — 經濟、基準利用率 | B19: $/M | C19: =C16/C$10 -> 0.065975461 | D19: =D16/D$10 -> 0.095152947 | E19: =E16/E$10 -> 0.16405142 | F19: =F16/F$10 -> 0.009050396 | G19: =G16/G$10 -> 0.012176511 | H19: =H16/H$10 -> 0.019815392 | I19: =I16/I$10 -> 0.007990567 | J19: =J16/J$10 -> 0.011677614 | ... Q19: =Q16/Q$10 -> 0.012784222
A20: 快取命中 prefill $/M — 經濟、基準利用率 | B20: $/M | C20: =C17/C$10 -> 1.4400289e-05 | D20: =D17/D$10 -> 2.0768781e-05 | E20: =E17/E$10 -> 3.5807068e-05 | F20: =F17/F$10 -> 1.9973771e-05 | G20: =G17/G$10 -> 2.6872951e-05 | H20: =H17/H$10 -> 4.3731579e-05 | I20: =I17/I$10 -> 2.6452172e-05 | J20: =J17/J$10 -> 3.8657863e-05 | ... Q20: =Q17/Q$10 -> 0.0002059632
A21: decode $/M — 經濟、基準利用率 | B21: $/M | C21: =IF(ISNUMBER(C18),C18/C$10,C18) -> 0.86567133 | D21: =IF(ISNUMBER(D18),D18/D$10,D18) -> 1.2485123 | E21: =IF(ISNUMBER(E18),E18/E$10,E18) -> 2.1525368 | F21: =IF(ISNUMBER(F18),F18/F$10,F18) -> 0.20419463 | G21: =IF(ISNUMBER(G18),G18/G$10,G18) -> 0.2747259 | H21: =IF(ISNUMBER(H18),H18/H$10,H18) -> 0.44707399 | I21: =IF(ISNUMBER(I18),I18/I$10,I18) -> 0.18028281 | J21: =IF(ISNUMBER(J18),J18/J$10,J18) -> 0.26346979 | ... Q21: =IF(ISNUMBER(Q18),Q18/Q$10,Q18) -> 0.26613608
A22: decode $/M — 會計、100% | B22: $/M | C22: =IF(C15>0,C$9/3600*C15,"SLO 不可達") -> 0.40060343 | D22: =IF(D15>0,D$9/3600*D15,"SLO 不可達") -> 0.55626418 | E22: =IF(E15>0,E$9/3600*E15,"SLO 不可達") -> 0.96083527 | F22: =IF(F15>0,F$9/3600*F15,"SLO 不可達") -> 0.094452385 | G22: =IF(G15>0,G$9/3600*G15,"SLO 不可達") -> 0.12211396 | H22: =IF(H15>0,H$9/3600*H15,"SLO 不可達") -> 0.19825268 | I22: =IF(I15>0,I$9/3600*I15,"SLO 不可達") -> 0.083869193 | J22: =IF(J15>0,J$9/3600*J15,"SLO 不可達") -> 0.11801186 | ... Q22: =IF(Q15>0,Q$9/3600*Q15,"SLO 不可達") -> 0.12099507
A23: 參考請求混合 $/M 總 token — 經濟、100% | B23: $/M | C23: =IF(ISNUMBER(C18),(Serving!$C$23*C16+Serving!$C$24*C18)/(Serving!$C$23+Serving!$C$24),C18) -> 0.092898334 | D23: =IF(ISNUMBER(D18),(Serving!$C$23*D16+Serving!$C$24*D18)/(Serving!$C$23+Serving!$C$24),D18) -> 0.13398239 | E23: =IF(ISNUMBER(E18),(Serving!$C$23*E16+Serving!$C$24*E18)/(Serving!$C$23+Serving!$C$24),E18) -> 0.23099654 | F23: =IF(ISNUMBER(F18),(Serving!$C$23*F16+Serving!$C$24*F18)/(Serving!$C$23+Serving!$C$24),F18) -> 0.018439853 | G23: =IF(ISNUMBER(G18),(Serving!$C$23*G16+Serving!$C$24*G18)/(Serving!$C$23+Serving!$C$24),G18) -> 0.024809199 | H23: =IF(ISNUMBER(H18),(Serving!$C$23*H16+Serving!$C$24*H18)/(Serving!$C$23+Serving!$C$24),H18) -> 0.040373142 | I23: =IF(ISNUMBER(I18),(Serving!$C$23*I16+Serving!$C$24*I18)/(Serving!$C$23+Serving!$C$24),I18) -> 0.01628049 | J23: =IF(ISNUMBER(J18),(Serving!$C$23*J16+Serving!$C$24*J18)/(Serving!$C$23+Serving!$C$24),J18) -> 0.023792714 | ... Q23: =IF(ISNUMBER(Q18),(Serving!$C$23*Q16+Serving!$C$24*Q18)/(Serving!$C$23+Serving!$C$24),Q18) -> 0.024560657
A25: Sol（中層）
A26: GPU 秒／M 新鮮 prefill | B26: GPU-s | C26: =INDEX(Perf!$C$97:$Q$97,3*(C$6-1)+2) -> 449.30115 | D26: =INDEX(Perf!$C$97:$Q$97,3*(D$6-1)+2) -> 449.30115 | E26: =INDEX(Perf!$C$97:$Q$97,3*(E$6-1)+2) -> 449.30115 | F26: =INDEX(Perf!$C$97:$Q$97,3*(F$6-1)+2) -> 44.435884 | G26: =INDEX(Perf!$C$97:$Q$97,3*(G$6-1)+2) -> 44.435884 | H26: =INDEX(Perf!$C$97:$Q$97,3*(H$6-1)+2) -> 44.435884 | I26: =INDEX(Perf!$C$97:$Q$97,3*(I$6-1)+2) -> 29.623922 | J26: =INDEX(Perf!$C$97:$Q$97,3*(J$6-1)+2) -> 29.623922 | ... Q26: =INDEX(Perf!$C$97:$Q$97,3*(Q$6-1)+2) -> 6.0871074
A27: GPU 秒／M 快取命中 prefill | B27: GPU-s | C27: =INDEX(Perf!$C$98:$Q$98,3*(C$6-1)+2) -> 0.03965 | D27: =INDEX(Perf!$C$98:$Q$98,3*(D$6-1)+2) -> 0.03965 | E27: =INDEX(Perf!$C$98:$Q$98,3*(E$6-1)+2) -> 0.03965 | F27: =INDEX(Perf!$C$98:$Q$98,3*(F$6-1)+2) -> 0.03965 | G27: =INDEX(Perf!$C$98:$Q$98,3*(G$6-1)+2) -> 0.03965 | H27: =INDEX(Perf!$C$98:$Q$98,3*(H$6-1)+2) -> 0.03965 | I27: =INDEX(Perf!$C$98:$Q$98,3*(I$6-1)+2) -> 0.03965 | J27: =INDEX(Perf!$C$98:$Q$98,3*(J$6-1)+2) -> 0.03965 | ... Q27: =INDEX(Perf!$C$98:$Q$98,3*(Q$6-1)+2) -> 0.03965
A28: GPU 秒／M decode（0＝SLO 不可達） | B28: GPU-s | C28: =INDEX(Perf!$C$99:$Q$99,3*(C$6-1)+2) -> 5842.0892 | D28: =INDEX(Perf!$C$99:$Q$99,3*(D$6-1)+2) -> 5842.0892 | E28: =INDEX(Perf!$C$99:$Q$99,3*(E$6-1)+2) -> 5842.0892 | F28: =INDEX(Perf!$C$99:$Q$99,3*(F$6-1)+2) -> 1006.7612 | G28: =INDEX(Perf!$C$99:$Q$99,3*(G$6-1)+2) -> 1006.7612 | H28: =INDEX(Perf!$C$99:$Q$99,3*(H$6-1)+2) -> 1006.7612 | I28: =INDEX(Perf!$C$99:$Q$99,3*(I$6-1)+2) -> 671.17411 | J28: =INDEX(Perf!$C$99:$Q$99,3*(J$6-1)+2) -> 671.17411 | ... Q28: =INDEX(Perf!$C$99:$Q$99,3*(Q$6-1)+2) -> 113.27614
A29: 新鮮 prefill $/M — 經濟、100% | B29: $/M | C29: =C$8/3600*C26 -> 0.1388923 | D29: =D$8/3600*D26 -> 0.20031708 | E29: =E$8/3600*E26 -> 0.34536294 | F29: =F$8/3600*F26 -> 0.019052998 | G29: =G$8/3600*G26 -> 0.025634132 | H29: =H$8/3600*H26 -> 0.041715593 | I29: =I$8/3600*I26 -> 0.016821834 | J29: =J$8/3600*J26 -> 0.024583847 | ... Q29: =Q$8/3600*Q26 -> 0.026913491
A30: 快取命中 prefill $/M — 經濟、100% | B30: $/M | C30: =C$8/3600*C27 -> 1.225699e-05 | D30: =D$8/3600*D27 -> 1.7677614e-05 | E30: =E$8/3600*E27 -> 3.0477644e-05 | F30: =F$8/3600*F27 -> 1.7000931e-05 | G30: =G$8/3600*G27 -> 2.2873256e-05 | H30: =H$8/3600*H27 -> 3.7222693e-05 | I30: =I$8/3600*I27 -> 2.2515104e-05 | J30: =J$8/3600*J27 -> 3.2904135e-05 | ... Q30: =Q$8/3600*Q27 -> 0.00017530821
A31: decode $/M — 經濟、100% | B31: $/M | C31: =IF(C28>0,C$8/3600*C28,"SLO 不可達") -> 1.8059629 | D31: =IF(D28>0,D$8/3600*D28,"SLO 不可達") -> 2.6046456 | E31: =IF(E28>0,E$8/3600*E28,"SLO 不可達") -> 4.4906208 | F31: =IF(F28>0,F$8/3600*F28,"SLO 不可達") -> 0.43167406 | G31: =IF(G28>0,G$8/3600*G28,"SLO 不可達") -> 0.58077946 | H31: =IF(H28>0,H$8/3600*H28,"SLO 不可達") -> 0.94512891 | I31: =IF(I28>0,I$8/3600*I28,"SLO 不可達") -> 0.38112371 | J31: =IF(J28>0,J$8/3600*J28,"SLO 不可達") -> 0.55698369 | ... Q31: =IF(Q28>0,Q$8/3600*Q28,"SLO 不可達") -> 0.50083827
A32: 新鮮 prefill $/M — 經濟、基準利用率 | B32: $/M | C32: =C29/C$10 -> 0.23148717 | D32: =D29/D$10 -> 0.3338618 | E32: =E29/E$10 -> 0.57560489 | F32: =F29/F$10 -> 0.031754997 | G32: =G29/G$10 -> 0.042723554 | H32: =H29/H$10 -> 0.069525988 | I32: =I29/I$10 -> 0.02803639 | J32: =J29/J$10 -> 0.040973079 | ... Q32: =Q29/Q$10 -> 0.044855818
A33: 快取命中 prefill $/M — 經濟、基準利用率 | B33: $/M | C33: =C30/C$10 -> 2.0428317e-05 | D33: =D30/D$10 -> 2.946269e-05 | E33: =E30/E$10 -> 5.0796073e-05 | F33: =F30/F$10 -> 2.8334884e-05 | G33: =G30/G$10 -> 3.8122093e-05 | H33: =H30/H$10 -> 6.2037821e-05 | I33: =I30/I$10 -> 3.7525174e-05 | J33: =J30/J$10 -> 5.4840225e-05 | ... Q33: =Q30/Q$10 -> 0.00029218035
A34: decode $/M — 經濟、基準利用率 | B34: $/M | C34: =IF(ISNUMBER(C31),C31/C$10,C31) -> 3.0099382 | D34: =IF(ISNUMBER(D31),D31/D$10,D31) -> 4.341076 | E34: =IF(ISNUMBER(E31),E31/E$10,E31) -> 7.484368 | F34: =IF(ISNUMBER(F31),F31/F$10,F31) -> 0.71945677 | G34: =IF(ISNUMBER(G31),G31/G$10,G31) -> 0.96796577 | H34: =IF(ISNUMBER(H31),H31/H$10,H31) -> 1.5752148 | I34: =IF(ISNUMBER(I31),I31/I$10,I31) -> 0.63520618 | J34: =IF(ISNUMBER(J31),J31/J$10,J31) -> 0.92830615 | ... Q34: =IF(ISNUMBER(Q31),Q31/Q$10,Q31) -> 0.83473046
A35: decode $/M — 會計、100% | B35: $/M | C35: =IF(C28>0,C$9/3600*C28,"SLO 不可達") -> 1.3928977 | D35: =IF(D28>0,D$9/3600*D28,"SLO 不可達") -> 1.9341299 | E35: =IF(E28>0,E$9/3600*E28,"SLO 不可達") -> 3.3408231 | F35: =IF(F28>0,F$9/3600*F28,"SLO 不可達") -> 0.33279234 | G35: =IF(G28>0,G$9/3600*G28,"SLO 不可達") -> 0.43025477 | H35: =IF(H28>0,H$9/3600*H28,"SLO 不可達") -> 0.698521 | I35: =IF(I28>0,I$9/3600*I28,"SLO 不可達") -> 0.29550366 | J35: =IF(J28>0,J$9/3600*J28,"SLO 不可達") -> 0.4158015 | ... Q35: =IF(Q28>0,Q$9/3600*Q28,"SLO 不可達") -> 0.3794986
A36: 參考請求混合 $/M 總 token — 經濟、100% | B36: $/M | C36: =IF(ISNUMBER(C31),(Serving!$D$23*C29+Serving!$D$24*C31)/(Serving!$D$23+Serving!$D$24),C31) -> 0.32412237 | D36: =IF(ISNUMBER(D31),(Serving!$D$23*D29+Serving!$D$24*D31)/(Serving!$D$23+Serving!$D$24),D31) -> 0.46746469 | E36: =IF(ISNUMBER(E31),(Serving!$D$23*E29+Serving!$D$24*E31)/(Serving!$D$23+Serving!$D$24),E31) -> 0.80594714 | F36: =IF(ISNUMBER(F31),(Serving!$D$23*F29+Serving!$D$24*F31)/(Serving!$D$23+Serving!$D$24),F31) -> 0.064899783 | G36: =IF(ISNUMBER(G31),(Serving!$D$23*G29+Serving!$D$24*G31)/(Serving!$D$23+Serving!$D$24),G31) -> 0.087316947 | H36: =IF(ISNUMBER(H31),(Serving!$D$23*H29+Serving!$D$24*H31)/(Serving!$D$23+Serving!$D$24),H31) -> 0.14209485 | I36: =IF(ISNUMBER(I31),(Serving!$D$23*I29+Serving!$D$24*I31)/(Serving!$D$23+Serving!$D$24),I31) -> 0.05729982 | J36: =IF(ISNUMBER(J31),(Serving!$D$23*J29+Serving!$D$24*J31)/(Serving!$D$23+Serving!$D$24),J31) -> 0.083739385 | ... Q36: =IF(ISNUMBER(Q31),(Serving!$D$23*Q29+Serving!$D$24*Q31)/(Serving!$D$23+Serving!$D$24),Q31) -> 0.0795718
A38: Astra（頂層）
A39: GPU 秒／M 新鮮 prefill | B39: GPU-s | C39: =INDEX(Perf!$C$97:$Q$97,3*(C$6-1)+3) -> 1484.7679 | D39: =INDEX(Perf!$C$97:$Q$97,3*(D$6-1)+3) -> 1484.7679 | E39: =INDEX(Perf!$C$97:$Q$97,3*(E$6-1)+3) -> 1484.7679 | F39: =INDEX(Perf!$C$97:$Q$97,3*(F$6-1)+3) -> 146.84355 | G39: =INDEX(Perf!$C$97:$Q$97,3*(G$6-1)+3) -> 146.84355 | H39: =INDEX(Perf!$C$97:$Q$97,3*(H$6-1)+3) -> 146.84355 | I39: =INDEX(Perf!$C$97:$Q$97,3*(I$6-1)+3) -> 97.895697 | J39: =INDEX(Perf!$C$97:$Q$97,3*(J$6-1)+3) -> 97.895697 | ... Q39: =INDEX(Perf!$C$97:$Q$97,3*(Q$6-1)+3) -> 20.115554
A40: GPU 秒／M 快取命中 prefill | B40: GPU-s | C40: =INDEX(Perf!$C$98:$Q$98,3*(C$6-1)+3) -> 0.576 | D40: =INDEX(Perf!$C$98:$Q$98,3*(D$6-1)+3) -> 0.576 | E40: =INDEX(Perf!$C$98:$Q$98,3*(E$6-1)+3) -> 0.576 | F40: =INDEX(Perf!$C$98:$Q$98,3*(F$6-1)+3) -> 0.576 | G40: =INDEX(Perf!$C$98:$Q$98,3*(G$6-1)+3) -> 0.576 | H40: =INDEX(Perf!$C$98:$Q$98,3*(H$6-1)+3) -> 0.576 | I40: =INDEX(Perf!$C$98:$Q$98,3*(I$6-1)+3) -> 0.576 | J40: =INDEX(Perf!$C$98:$Q$98,3*(J$6-1)+3) -> 0.576 | ... Q40: =INDEX(Perf!$C$98:$Q$98,3*(Q$6-1)+3) -> 0.576
A41: GPU 秒／M decode（0＝SLO 不可達） | B41: GPU-s | C41: =INDEX(Perf!$C$99:$Q$99,3*(C$6-1)+3) -> 39767.609 | D41: =INDEX(Perf!$C$99:$Q$99,3*(D$6-1)+3) -> 39767.609 | E41: =INDEX(Perf!$C$99:$Q$99,3*(E$6-1)+3) -> 39767.609 | F41: =INDEX(Perf!$C$99:$Q$99,3*(F$6-1)+3) -> 5853.7759 | G41: =INDEX(Perf!$C$99:$Q$99,3*(G$6-1)+3) -> 5853.7759 | H41: =INDEX(Perf!$C$99:$Q$99,3*(H$6-1)+3) -> 5853.7759 | I41: =INDEX(Perf!$C$99:$Q$99,3*(I$6-1)+3) -> 4850.3455 | J41: =INDEX(Perf!$C$99:$Q$99,3*(J$6-1)+3) -> 4850.3455 | ... Q41: =INDEX(Perf!$C$99:$Q$99,3*(Q$6-1)+3) -> 545.21648
A42: 新鮮 prefill $/M — 經濟、100% | B42: $/M | C42: =C$8/3600*C39 -> 0.45898576 | D42: =D$8/3600*D39 -> 0.66197109 | E42: =E$8/3600*E39 -> 1.141292 | F42: =F$8/3600*F39 -> 0.062962848 | G42: =G$8/3600*G39 -> 0.084710971 | H42: =H$8/3600*H39 -> 0.13785403 | I42: =I$8/3600*I39 -> 0.055589706 | J42: =J$8/3600*J39 -> 0.081240182 | ... Q42: =Q$8/3600*Q39 -> 0.08893876
A43: 快取命中 prefill $/M — 經濟、100% | B43: $/M | C43: =C$8/3600*C40 -> 0.00017805867 | D43: =D$8/3600*D40 -> 0.00025680468 | E43: =E$8/3600*E40 -> 0.00044275215 | F43: =F$8/3600*F40 -> 0.00024697443 | G43: =G$8/3600*G40 -> 0.00033228236 | H43: =H$8/3600*H40 -> 0.00054073824 | I43: =I$8/3600*I40 -> 0.00032707945 | J43: =J$8/3600*J40 -> 0.00047800206 | ... Q43: =Q$8/3600*Q40 -> 0.0025467221
A44: decode $/M — 經濟、100% | B44: $/M | C44: =IF(C41>0,C$8/3600*C41,"SLO 不可達") -> 12.293346 | D44: =IF(D41>0,D$8/3600*D41,"SLO 不可達") -> 17.730049 | E44: =IF(E41>0,E$8/3600*E41,"SLO 不可達") -> 30.568046 | F44: =IF(F41>0,F$8/3600*F41,"SLO 不可達") -> 2.509953 | G44: =IF(G41>0,G$8/3600*G41,"SLO 不可達") -> 3.3769209 | H44: =IF(H41>0,H$8/3600*H41,"SLO 不可達") -> 5.4954174 | I44: =IF(I41>0,I$8/3600*I41,"SLO 不可達") -> 2.7542506 | J44: =IF(J41>0,J$8/3600*J41,"SLO 不可達") -> 4.0251304 | ... Q44: =IF(Q41>0,Q$8/3600*Q41,"SLO 不可達") -> 2.410616
A45: 新鮮 prefill $/M — 經濟、基準利用率 | B45: $/M | C45: =C42/C$10 -> 0.76497627 | D45: =D42/D$10 -> 1.1032851 | E45: =E42/E$10 -> 1.9021533 | F45: =F42/F$10 -> 0.10493808 | G45: =G42/G$10 -> 0.14118495 | H45: =H42/H$10 -> 0.22975671 | I45: =I42/I$10 -> 0.09264951 | J45: =J42/J$10 -> 0.1354003 | ... Q45: =Q42/Q$10 -> 0.14823127
A46: 快取命中 prefill $/M — 經濟、基準利用率 | B46: $/M | C46: =C43/C$10 -> 0.00029676445 | D46: =D43/D$10 -> 0.0004280078 | E46: =E43/E$10 -> 0.00073792026 | F46: =F43/F$10 -> 0.00041162404 | G46: =G43/G$10 -> 0.00055380393 | H46: =H43/H$10 -> 0.00090123039 | I46: =I43/I$10 -> 0.00054513241 | J46: =J43/J$10 -> 0.0007966701 | ... Q46: =Q43/Q$10 -> 0.0042445368
A47: decode $/M — 經濟、基準利用率 | B47: $/M | C47: =IF(ISNUMBER(C44),C44/C$10,C44) -> 20.488911 | D47: =IF(ISNUMBER(D44),D44/D$10,D44) -> 29.550081 | E47: =IF(ISNUMBER(E44),E44/E$10,E44) -> 50.946743 | F47: =IF(ISNUMBER(F44),F44/F$10,F44) -> 4.183255 | G47: =IF(ISNUMBER(G44),G44/G$10,G44) -> 5.6282015 | H47: =IF(ISNUMBER(H44),H44/H$10,H44) -> 9.159029 | I47: =IF(ISNUMBER(I44),I44/I$10,I44) -> 4.5904176 | J47: =IF(ISNUMBER(J44),J44/J$10,J44) -> 6.7085507 | ... Q47: =IF(ISNUMBER(Q44),Q44/Q$10,Q44) -> 4.0176934
A48: decode $/M — 會計、100% | B48: $/M | C48: =IF(C41>0,C$9/3600*C41,"SLO 不可達") -> 9.4815754 | D48: =IF(D41>0,D$9/3600*D41,"SLO 不可達") -> 13.16579 | E48: =IF(E41>0,E$9/3600*E41,"SLO 不可達") -> 22.741273 | F48: =IF(F41>0,F$9/3600*F41,"SLO 不可達") -> 1.9350089 | G48: =IF(G41>0,G$9/3600*G41,"SLO 不可達") -> 2.5017006 | H48: =IF(H41>0,H$9/3600*H41,"SLO 不可達") -> 4.0615247 | I48: =IF(I41>0,I$9/3600*I41,"SLO 不可達") -> 2.1355038 | J48: =IF(J41>0,J$9/3600*J41,"SLO 不可達") -> 3.004855 | ... Q48: =IF(Q41>0,Q$9/3600*Q41,"SLO 不可達") -> 1.8265884
A49: 參考請求混合 $/M 總 token — 經濟、100% | B49: $/M | C49: =IF(ISNUMBER(C44),(Serving!$E$23*C42+Serving!$E$24*C44)/(Serving!$E$23+Serving!$E$24),C44) -> 1.7739147 | D49: =IF(ISNUMBER(D44),(Serving!$E$23*D42+Serving!$E$24*D44)/(Serving!$E$23+Serving!$E$24),D44) -> 2.5584242 | E49: =IF(ISNUMBER(E44),(Serving!$E$23*E42+Serving!$E$24*E44)/(Serving!$E$23+Serving!$E$24),E44) -> 4.4109313 | F49: =IF(ISNUMBER(F44),(Serving!$E$23*F42+Serving!$E$24*F44)/(Serving!$E$23+Serving!$E$24),F44) -> 0.33485064 | G49: =IF(ISNUMBER(G44),(Serving!$E$23*G42+Serving!$E$24*G44)/(Serving!$E$23+Serving!$E$24),G44) -> 0.45051207 | H49: =IF(ISNUMBER(H44),(Serving!$E$23*H42+Serving!$E$24*H44)/(Serving!$E$23+Serving!$E$24),H44) -> 0.73313885 | I49: =IF(ISNUMBER(I44),(Serving!$E$23*I42+Serving!$E$24*I44)/(Serving!$E$23+Serving!$E$24),I44) -> 0.35544091 | J49: =IF(ISNUMBER(J44),(Serving!$E$23*J42+Serving!$E$24*J44)/(Serving!$E$23+Serving!$E$24),J44) -> 0.51945021 | ... Q49: =IF(ISNUMBER(Q44),(Serving!$E$23*Q42+Serving!$E$24*Q44)/(Serving!$E$23+Serving!$E$24),Q44) -> 0.3469029

Sheet DC_Cost
A1: DC_Cost — 每 GW（IT）資本支出與年持有成本：5 世代 × 3 成本情境
A2: 功率情境由 Inputs!E6 控制；成本情境為角落情境（所有金額輸入同時取低或高）
A4: 世代 | C4: =Spec_Rack!C4 -> Hopper H100 | D4: =Spec_Rack!C4 -> Hopper H100 | E4: =Spec_Rack!C4 -> Hopper H100 | F4: =Spec_Rack!D4 -> GB200 NVL72 | G4: =Spec_Rack!D4 -> GB200 NVL72 | H4: =Spec_Rack!D4 -> GB200 NVL72 | I4: =Spec_Rack!E4 -> GB300 NVL72 | J4: =Spec_Rack!E4 -> GB300 NVL72 | K4: =Spec_Rack!E4 -> GB300 NVL72 | L4: =Spec_Rack!F4 -> VR200 NVL72 | M4: =Spec_Rack!F4 -> VR200 NVL72 | N4: =Spec_Rack!F4 -> VR200 NVL72 | O4: =Spec_Rack!G4 -> Rubin Ultra NVL576 | P4: =Spec_Rack!G4 -> Rubin Ultra NVL576 | Q4: =Spec_Rack!G4 -> Rubin Ultra NVL576
A5: 成本情境 | C5: 低成本 | D5: 基準 | E5: 高成本 | F5: 低成本 | G5: 基準 | H5: 高成本 | I5: 低成本 | J5: 基準 | K5: 高成本 | L5: 低成本 | M5: 基準 | N5: 高成本 | O5: 低成本 | P5: 基準 | Q5: 高成本
A7: A. 規模與電力
A8: IT 電力 | B8: MW | C8: =Inputs!$E$5*1000 -> 1000 | D8: =Inputs!$E$5*1000 -> 1000 | E8: =Inputs!$E$5*1000 -> 1000 | F8: =Inputs!$E$5*1000 -> 1000 | G8: =Inputs!$E$5*1000 -> 1000 | H8: =Inputs!$E$5*1000 -> 1000 | I8: =Inputs!$E$5*1000 -> 1000 | J8: =Inputs!$E$5*1000 -> 1000 | ... Q8: =Inputs!$E$5*1000 -> 1000
A9: 機架外 IT 電力占比 | B9: % | C9: =Inputs!$E$8 -> 0.08 | D9: =Inputs!$E$8 -> 0.08 | E9: =Inputs!$E$8 -> 0.08 | F9: =Inputs!$E$8 -> 0.08 | G9: =Inputs!$E$8 -> 0.08 | H9: =Inputs!$E$8 -> 0.08 | I9: =Inputs!$E$8 -> 0.08 | J9: =Inputs!$E$8 -> 0.08 | ... Q9: =Inputs!$E$8 -> 0.08
A10: 機架可用 IT 電力 | B10: MW | C10: =C8*(1-C9) -> 920 | D10: =D8*(1-D9) -> 920 | E10: =E8*(1-E9) -> 920 | F10: =F8*(1-F9) -> 920 | G10: =G8*(1-G9) -> 920 | H10: =H8*(1-H9) -> 920 | I10: =I8*(1-I9) -> 920 | J10: =J8*(1-J9) -> 920 | ... Q10: =Q8*(1-Q9) -> 920
A11: 每架配電設計功率 | B11: kW | C11: =CHOOSE(Inputs!$E$6,Spec_Rack!C8,Spec_Rack!C9,Spec_Rack!C10) -> 41 | D11: =CHOOSE(Inputs!$E$6,Spec_Rack!C8,Spec_Rack!C9,Spec_Rack!C10) -> 41 | E11: =CHOOSE(Inputs!$E$6,Spec_Rack!C8,Spec_Rack!C9,Spec_Rack!C10) -> 41 | F11: =CHOOSE(Inputs!$E$6,Spec_Rack!D8,Spec_Rack!D9,Spec_Rack!D10) -> 130 | G11: =CHOOSE(Inputs!$E$6,Spec_Rack!D8,Spec_Rack!D9,Spec_Rack!D10) -> 130 | H11: =CHOOSE(Inputs!$E$6,Spec_Rack!D8,Spec_Rack!D9,Spec_Rack!D10) -> 130 | I11: =CHOOSE(Inputs!$E$6,Spec_Rack!E8,Spec_Rack!E9,Spec_Rack!E10) -> 137 | J11: =CHOOSE(Inputs!$E$6,Spec_Rack!E8,Spec_Rack!E9,Spec_Rack!E10) -> 137 | K11: =CHOOSE(Inputs!$E$6,Spec_Rack!E8,Spec_Rack!E9,Spec_Rack!E10) -> 137 | L11: =CHOOSE(Inputs!$E$6,Spec_Rack!F8,Spec_Rack!F9,Spec_Rack!F10) -> 227 | M11: =CHOOSE(Inputs!$E$6,Spec_Rack!F8,Spec_Rack!F9,Spec_Rack!F10) -> 227 | N11: =CHOOSE(Inputs!$E$6,Spec_Rack!F8,Spec_Rack!F9,Spec_Rack!F10) -> 227 | O11: =CHOOSE(Inputs!$E$6,Spec_Rack!G8,Spec_Rack!G9,Spec_Rack!G10) -> 600 | P11: =CHOOSE(Inputs!$E$6,Spec_Rack!G8,Spec_Rack!G9,Spec_Rack!G10) -> 600 | Q11: =CHOOSE(Inputs!$E$6,Spec_Rack!G8,Spec_Rack!G9,Spec_Rack!G10) -> 600
A12: 每 GW 機架數 | B12: 架 | C12: =FLOOR(C10*1000/C11,1) -> 22439 | D12: =FLOOR(D10*1000/D11,1) -> 22439 | E12: =FLOOR(E10*1000/E11,1) -> 22439 | F12: =FLOOR(F10*1000/F11,1) -> 7076 | G12: =FLOOR(G10*1000/G11,1) -> 7076 | H12: =FLOOR(H10*1000/H11,1) -> 7076 | I12: =FLOOR(I10*1000/I11,1) -> 6715 | J12: =FLOOR(J10*1000/J11,1) -> 6715 | ... Q12: =FLOOR(Q10*1000/Q11,1) -> 1533
A13: GPU 封裝／架 | B13: 顆 | C13: =Spec_Rack!C6 -> 32 | D13: =Spec_Rack!C6 -> 32 | E13: =Spec_Rack!C6 -> 32 | F13: =Spec_Rack!D6 -> 72 | G13: =Spec_Rack!D6 -> 72 | H13: =Spec_Rack!D6 -> 72 | I13: =Spec_Rack!E6 -> 72 | J13: =Spec_Rack!E6 -> 72 | K13: =Spec_Rack!E6 -> 72 | L13: =Spec_Rack!F6 -> 72 | M13: =Spec_Rack!F6 -> 72 | N13: =Spec_Rack!F6 -> 72 | O13: =Spec_Rack!G6 -> 144 | P13: =Spec_Rack!G6 -> 144 | Q13: =Spec_Rack!G6 -> 144
A14: 每 GW GPU 數 | B14: 顆 | C14: =C12*C13 -> 718048 | D14: =D12*D13 -> 718048 | E14: =E12*E13 -> 718048 | F14: =F12*F13 -> 509472 | G14: =G12*G13 -> 509472 | H14: =H12*H13 -> 509472 | I14: =I12*I13 -> 483480 | J14: =J12*J13 -> 483480 | ... Q14: =Q12*Q13 -> 220752
A15: PUE | B15: x | C15: =Inputs!D9 -> 1.1 | D15: =Inputs!E9 -> 1.2 | E15: =Inputs!F9 -> 1.3 | F15: =Inputs!D9 -> 1.1 | G15: =Inputs!E9 -> 1.2 | H15: =Inputs!F9 -> 1.3 | I15: =Inputs!D9 -> 1.1 | J15: =Inputs!E9 -> 1.2 | K15: =Inputs!F9 -> 1.3 | L15: =Inputs!D9 -> 1.1 | M15: =Inputs!E9 -> 1.2 | N15: =Inputs!F9 -> 1.3 | O15: =Inputs!D9 -> 1.1 | P15: =Inputs!E9 -> 1.2 | Q15: =Inputs!F9 -> 1.3
A16: 設施電力（IT × PUE） | B16: MW | C16: =C8*C15 -> 1100 | D16: =D8*D15 -> 1200 | E16: =E8*E15 -> 1300 | F16: =F8*F15 -> 1100 | G16: =G8*G15 -> 1200 | H16: =H8*H15 -> 1300 | I16: =I8*I15 -> 1100 | J16: =J8*J15 -> 1200 | ... Q16: =Q8*Q15 -> 1300
A17: B. 資本支出（$B／GW）
A18: 機架單價 | B18: $M | C18: =Spec_Rack!C11 -> 0.9 | D18: =Spec_Rack!C12 -> 1.1 | E18: =Spec_Rack!C13 -> 1.3 | F18: =Spec_Rack!D11 -> 2.8 | G18: =Spec_Rack!D12 -> 3.1 | H18: =Spec_Rack!D13 -> 3.4 | I18: =Spec_Rack!E11 -> 4 | J18: =Spec_Rack!E12 -> 5 | K18: =Spec_Rack!E13 -> 6.5 | L18: =Spec_Rack!F11 -> 6.7 | M18: =Spec_Rack!F12 -> 7.8 | N18: =Spec_Rack!F13 -> 9.1 | O18: =Spec_Rack!G11 -> 23.4 | P18: =Spec_Rack!G12 -> 31.2 | Q18: =Spec_Rack!G13 -> 39
A19: 機架 | B19: $B | C19: =C12*C18/1000 -> 20.1951 | D19: =D12*D18/1000 -> 24.6829 | E19: =E12*E18/1000 -> 29.1707 | F19: =F12*F18/1000 -> 19.8128 | G19: =G12*G18/1000 -> 21.9356 | H19: =H12*H18/1000 -> 24.0584 | I19: =I12*I18/1000 -> 26.86 | J19: =J12*J18/1000 -> 33.575 | ... Q19: =Q12*Q18/1000 -> 59.787
A20: Scale-out 網路 ÷ 機架價格 | B20: % | C20: =Inputs!D13 -> 0.05 | D20: =Inputs!E13 -> 0.1 | E20: =Inputs!F13 -> 0.15 | F20: =Inputs!D13 -> 0.05 | G20: =Inputs!E13 -> 0.1 | H20: =Inputs!F13 -> 0.15 | I20: =Inputs!D13 -> 0.05 | J20: =Inputs!E13 -> 0.1 | K20: =Inputs!F13 -> 0.15 | L20: =Inputs!D13 -> 0.05 | M20: =Inputs!E13 -> 0.1 | N20: =Inputs!F13 -> 0.15 | O20: =Inputs!D13 -> 0.05 | P20: =Inputs!E13 -> 0.1 | Q20: =Inputs!F13 -> 0.15
A21: Scale-out 網路 | B21: $B | C21: =C19*C20 -> 1.009755 | D21: =D19*D20 -> 2.46829 | E21: =E19*E20 -> 4.375605 | F21: =F19*F20 -> 0.99064 | G21: =G19*G20 -> 2.19356 | H21: =H19*H20 -> 3.60876 | I21: =I19*I20 -> 1.343 | J21: =J19*J20 -> 3.3575 | ... Q21: =Q19*Q20 -> 8.96805
A22: 儲存與管理 | B22: $/GPU | C22: =Inputs!D14 -> 300 | D22: =Inputs!E14 -> 500 | E22: =Inputs!F14 -> 800 | F22: =Inputs!D14 -> 300 | G22: =Inputs!E14 -> 500 | H22: =Inputs!F14 -> 800 | I22: =Inputs!D14 -> 300 | J22: =Inputs!E14 -> 500 | K22: =Inputs!F14 -> 800 | L22: =Inputs!D14 -> 300 | M22: =Inputs!E14 -> 500 | N22: =Inputs!F14 -> 800 | O22: =Inputs!D14 -> 300 | P22: =Inputs!E14 -> 500 | Q22: =Inputs!F14 -> 800
A23: 儲存與管理 | B23: $B | C23: =C14*C22/1000000000 -> 0.2154144 | D23: =D14*D22/1000000000 -> 0.359024 | E23: =E14*E22/1000000000 -> 0.5744384 | F23: =F14*F22/1000000000 -> 0.1528416 | G23: =G14*G22/1000000000 -> 0.254736 | H23: =H14*H22/1000000000 -> 0.4075776 | I23: =I14*I22/1000000000 -> 0.145044 | J23: =J14*J22/1000000000 -> 0.24174 | ... Q23: =Q14*Q22/1000000000 -> 0.1766016
A24: IT 設備小計 | B24: $B | C24: =C19+C21+C23 -> 21.420269 | D24: =D19+D21+D23 -> 27.510214 | E24: =E19+E21+E23 -> 34.120743 | F24: =F19+F21+F23 -> 20.956282 | G24: =G19+G21+G23 -> 24.383896 | H24: =H19+H21+H23 -> 28.074738 | I24: =I19+I21+I23 -> 28.348044 | J24: =J19+J21+J23 -> 37.17424 | ... Q24: =Q19+Q21+Q23 -> 68.931652
A25: 土地 | B25: $B | C25: =C8*Inputs!D16/1000 -> 0.02 | D25: =D8*Inputs!E16/1000 -> 0.02 | E25: =E8*Inputs!F16/1000 -> 0.02 | F25: =F8*Inputs!D16/1000 -> 0.02 | G25: =G8*Inputs!E16/1000 -> 0.02 | H25: =H8*Inputs!F16/1000 -> 0.02 | I25: =I8*Inputs!D16/1000 -> 0.02 | J25: =J8*Inputs!E16/1000 -> 0.02 | K25: =K8*Inputs!F16/1000 -> 0.02 | L25: =L8*Inputs!D16/1000 -> 0.02 | M25: =M8*Inputs!E16/1000 -> 0.02 | N25: =N8*Inputs!F16/1000 -> 0.02 | O25: =O8*Inputs!D16/1000 -> 0.02 | P25: =P8*Inputs!E16/1000 -> 0.02 | Q25: =Q8*Inputs!F16/1000 -> 0.02
A26: 建物與基地 | B26: $B | C26: =C8*Inputs!D17/1000 -> 3 | D26: =D8*Inputs!E17/1000 -> 3.6 | E26: =E8*Inputs!F17/1000 -> 4.5 | F26: =F8*Inputs!D17/1000 -> 3 | G26: =G8*Inputs!E17/1000 -> 3.6 | H26: =H8*Inputs!F17/1000 -> 4.5 | I26: =I8*Inputs!D17/1000 -> 3 | J26: =J8*Inputs!E17/1000 -> 3.6 | K26: =K8*Inputs!F17/1000 -> 4.5 | L26: =L8*Inputs!D17/1000 -> 3 | M26: =M8*Inputs!E17/1000 -> 3.6 | N26: =N8*Inputs!F17/1000 -> 4.5 | O26: =O8*Inputs!D17/1000 -> 3 | P26: =P8*Inputs!E17/1000 -> 3.6 | Q26: =Q8*Inputs!F17/1000 -> 4.5
A27: 電力設施 | B27: $B | C27: =C8*Inputs!D18/1000 -> 3.8 | D27: =D8*Inputs!E18/1000 -> 4.5 | E27: =E8*Inputs!F18/1000 -> 5.5 | F27: =F8*Inputs!D18/1000 -> 3.8 | G27: =G8*Inputs!E18/1000 -> 4.5 | H27: =H8*Inputs!F18/1000 -> 5.5 | I27: =I8*Inputs!D18/1000 -> 3.8 | J27: =J8*Inputs!E18/1000 -> 4.5 | K27: =K8*Inputs!F18/1000 -> 5.5 | L27: =L8*Inputs!D18/1000 -> 3.8 | M27: =M8*Inputs!E18/1000 -> 4.5 | N27: =N8*Inputs!F18/1000 -> 5.5 | O27: =O8*Inputs!D18/1000 -> 3.8 | P27: =P8*Inputs!E18/1000 -> 4.5 | Q27: =Q8*Inputs!F18/1000 -> 5.5
A28: 機械與散熱 | B28: $B | C28: =C8*Inputs!D19/1000 -> 2 | D28: =D8*Inputs!E19/1000 -> 2.5 | E28: =E8*Inputs!F19/1000 -> 3.2 | F28: =F8*Inputs!D19/1000 -> 2 | G28: =G8*Inputs!E19/1000 -> 2.5 | H28: =H8*Inputs!F19/1000 -> 3.2 | I28: =I8*Inputs!D19/1000 -> 2 | J28: =J8*Inputs!E19/1000 -> 2.5 | K28: =K8*Inputs!F19/1000 -> 3.2 | L28: =L8*Inputs!D19/1000 -> 2 | M28: =M8*Inputs!E19/1000 -> 2.5 | N28: =N8*Inputs!F19/1000 -> 3.2 | O28: =O8*Inputs!D19/1000 -> 2 | P28: =P8*Inputs!E19/1000 -> 2.5 | Q28: =Q8*Inputs!F19/1000 -> 3.2
A29: 光纖與保全 | B29: $B | C29: =C8*Inputs!D20/1000 -> 0.3 | D29: =D8*Inputs!E20/1000 -> 0.4 | E29: =E8*Inputs!F20/1000 -> 0.5 | F29: =F8*Inputs!D20/1000 -> 0.3 | G29: =G8*Inputs!E20/1000 -> 0.4 | H29: =H8*Inputs!F20/1000 -> 0.5 | I29: =I8*Inputs!D20/1000 -> 0.3 | J29: =J8*Inputs!E20/1000 -> 0.4 | K29: =K8*Inputs!F20/1000 -> 0.5 | L29: =L8*Inputs!D20/1000 -> 0.3 | M29: =M8*Inputs!E20/1000 -> 0.4 | N29: =N8*Inputs!F20/1000 -> 0.5 | O29: =O8*Inputs!D20/1000 -> 0.3 | P29: =P8*Inputs!E20/1000 -> 0.4 | Q29: =Q8*Inputs!F20/1000 -> 0.5
A30: 設計、管理與預備費率 | B30: % | C30: =Inputs!D21 -> 0.12 | D30: =Inputs!E21 -> 0.15 | E30: =Inputs!F21 -> 0.18 | F30: =Inputs!D21 -> 0.12 | G30: =Inputs!E21 -> 0.15 | H30: =Inputs!F21 -> 0.18 | I30: =Inputs!D21 -> 0.12 | J30: =Inputs!E21 -> 0.15 | K30: =Inputs!F21 -> 0.18 | L30: =Inputs!D21 -> 0.12 | M30: =Inputs!E21 -> 0.15 | N30: =Inputs!F21 -> 0.18 | O30: =Inputs!D21 -> 0.12 | P30: =Inputs!E21 -> 0.15 | Q30: =Inputs!F21 -> 0.18
A31: 設計、管理與預備費 | B31: $B | C31: =(C26+C27+C28+C29)*C30 -> 1.092 | D31: =(D26+D27+D28+D29)*D30 -> 1.65 | E31: =(E26+E27+E28+E29)*E30 -> 2.466 | F31: =(F26+F27+F28+F29)*F30 -> 1.092 | G31: =(G26+G27+G28+G29)*G30 -> 1.65 | H31: =(H26+H27+H28+H29)*H30 -> 2.466 | I31: =(I26+I27+I28+I29)*I30 -> 1.092 | J31: =(J26+J27+J28+J29)*J30 -> 1.65 | ... Q31: =(Q26+Q27+Q28+Q29)*Q30 -> 2.466
A32: 廠房小計 | B32: $B | C32: =C25+C26+C27+C28+C29+C31 -> 10.212 | D32: =D25+D26+D27+D28+D29+D31 -> 12.67 | E32: =E25+E26+E27+E28+E29+E31 -> 16.186 | F32: =F25+F26+F27+F28+F29+F31 -> 10.212 | G32: =G25+G26+G27+G28+G29+G31 -> 12.67 | H32: =H25+H26+H27+H28+H29+H31 -> 16.186 | I32: =I25+I26+I27+I28+I29+I31 -> 10.212 | J32: =J25+J26+J27+J28+J29+J31 -> 12.67 | ... Q32: =Q25+Q26+Q27+Q28+Q29+Q31 -> 16.186
A33: 每 GW 總資本支出 | B33: $B | C33: =C24+C32 -> 31.632269 | D33: =D24+D32 -> 40.180214 | E33: =E24+E32 -> 50.306743 | F33: =F24+F32 -> 31.168282 | G33: =G24+G32 -> 37.053896 | H33: =H24+H32 -> 44.260738 | I33: =I24+I32 -> 38.560044 | J33: =J24+J32 -> 49.84424 | ... Q33: =Q24+Q32 -> 85.117652
A34: 每 GPU 資本支出（含廠房） | B34: $K | C34: =C33*1000000/C14 -> 44.05314 | D34: =D33*1000000/D14 -> 55.95756 | E34: =E33*1000000/E14 -> 70.060419 | F34: =F33*1000000/F14 -> 61.177614 | G34: =G33*1000000/G14 -> 72.729995 | H34: =H33*1000000/H14 -> 86.875702 | I34: =I33*1000000/I14 -> 79.7552 | J34: =J33*1000000/J14 -> 103.09473 | ... Q34: =Q33*1000000/Q14 -> 385.58043
A35: 每 MW IT 資本支出 | B35: $M | C35: =C33*1000/C8 -> 31.632269 | D35: =D33*1000/D8 -> 40.180214 | E35: =E33*1000/E8 -> 50.306743 | F35: =F33*1000/F8 -> 31.168282 | G35: =G33*1000/G8 -> 37.053896 | H35: =H33*1000/H8 -> 44.260738 | I35: =I33*1000/I8 -> 38.560044 | J35: =J33*1000/J8 -> 49.84424 | ... Q35: =Q33*1000/Q8 -> 85.117652
A36: 每 MW IT 廠房資本支出 | B36: $M | C36: =C32*1000/C8 -> 10.212 | D36: =D32*1000/D8 -> 12.67 | E36: =E32*1000/E8 -> 16.186 | F36: =F32*1000/F8 -> 10.212 | G36: =G32*1000/G8 -> 12.67 | H36: =H32*1000/H8 -> 16.186 | I36: =I32*1000/I8 -> 10.212 | J36: =J32*1000/J8 -> 12.67 | ... Q36: =Q32*1000/Q8 -> 16.186
A37: C. 年持有成本 — 會計口徑（$B／GW／年）
A38: IT 折舊年限 | B38: 年 | C38: =Inputs!D23 -> 6 | D38: =Inputs!E23 -> 6 | E38: =Inputs!F23 -> 4 | F38: =Inputs!D23 -> 6 | G38: =Inputs!E23 -> 6 | H38: =Inputs!F23 -> 4 | I38: =Inputs!D23 -> 6 | J38: =Inputs!E23 -> 6 | K38: =Inputs!F23 -> 4 | L38: =Inputs!D23 -> 6 | M38: =Inputs!E23 -> 6 | N38: =Inputs!F23 -> 4 | O38: =Inputs!D23 -> 6 | P38: =Inputs!E23 -> 6 | Q38: =Inputs!F23 -> 4
A39: IT 折舊 | B39: $B | C39: =C24/C38 -> 3.5700449 | D39: =D24/D38 -> 4.5850357 | E39: =E24/E38 -> 8.5301859 | F39: =F24/F38 -> 3.4927136 | G39: =G24/G38 -> 4.0639827 | H39: =H24/H38 -> 7.0186844 | I39: =I24/I38 -> 4.724674 | J39: =J24/J38 -> 6.1957067 | ... Q39: =Q24/Q38 -> 17.232913
A40: 廠房折舊（土地不折舊） | B40: $B | C40: =(C26/Inputs!D24+C27/Inputs!D25+C28/Inputs!D26+C29/Inputs!D27)*(1+C30) -> 0.50773333 | D40: =(D26/Inputs!E24+D27/Inputs!E25+D28/Inputs!E26+D29/Inputs!E27)*(1+D30) -> 0.63441667 | E40: =(E26/Inputs!F24+E27/Inputs!F25+E28/Inputs!F26+E29/Inputs!F27)*(1+E30) -> 0.81223333 | F40: =(F26/Inputs!D24+F27/Inputs!D25+F28/Inputs!D26+F29/Inputs!D27)*(1+F30) -> 0.50773333 | G40: =(G26/Inputs!E24+G27/Inputs!E25+G28/Inputs!E26+G29/Inputs!E27)*(1+G30) -> 0.63441667 | H40: =(H26/Inputs!F24+H27/Inputs!F25+H28/Inputs!F26+H29/Inputs!F27)*(1+H30) -> 0.81223333 | I40: =(I26/Inputs!D24+I27/Inputs!D25+I28/Inputs!D26+I29/Inputs!D27)*(1+I30) -> 0.50773333 | J40: =(J26/Inputs!E24+J27/Inputs!E25+J28/Inputs!E26+J29/Inputs!E27)*(1+J30) -> 0.63441667 | K40: =(K26/Inputs!F24+K27/Inputs!F25+K28/Inputs!F26+K29/Inputs!F27)*(1+K30) -> 0.81223333 | L40: =(L26/Inputs!D24+L27/Inputs!D25+L28/Inputs!D26+L29/Inputs!D27)*(1+L30) -> 0.50773333 | M40: =(M26/Inputs!E24+M27/Inputs!E25+M28/Inputs!E26+M29/Inputs!E27)*(1+M30) -> 0.63441667 | N40: =(N26/Inputs!F24+N27/Inputs!F25+N28/Inputs!F26+N29/Inputs!F27)*(1+N30) -> 0.81223333 | O40: =(O26/Inputs!D24+O27/Inputs!D25+O28/Inputs!D26+O29/Inputs!D27)*(1+O30) -> 0.50773333 | P40: =(P26/Inputs!E24+P27/Inputs!E25+P28/Inputs!E26+P29/Inputs!E27)*(1+P30) -> 0.63441667 | Q40: =(Q26/Inputs!F24+Q27/Inputs!F25+Q28/Inputs!F26+Q29/Inputs!F27)*(1+Q30) -> 0.81223333
A41: 平均用電 ÷ 配電設計功率 | B41: % | C41: =Inputs!D10 -> 0.7 | D41: =Inputs!E10 -> 0.8 | E41: =Inputs!F10 -> 0.9 | F41: =Inputs!D10 -> 0.7 | G41: =Inputs!E10 -> 0.8 | H41: =Inputs!F10 -> 0.9 | I41: =Inputs!D10 -> 0.7 | J41: =Inputs!E10 -> 0.8 | K41: =Inputs!F10 -> 0.9 | L41: =Inputs!D10 -> 0.7 | M41: =Inputs!E10 -> 0.8 | N41: =Inputs!F10 -> 0.9 | O41: =Inputs!D10 -> 0.7 | P41: =Inputs!E10 -> 0.8 | Q41: =Inputs!F10 -> 0.9
A42: 電價 | B42: $/kWh | C42: =Inputs!D11 -> 0.06 | D42: =Inputs!E11 -> 0.08 | E42: =Inputs!F11 -> 0.1 | F42: =Inputs!D11 -> 0.06 | G42: =Inputs!E11 -> 0.08 | H42: =Inputs!F11 -> 0.1 | I42: =Inputs!D11 -> 0.06 | J42: =Inputs!E11 -> 0.08 | K42: =Inputs!F11 -> 0.1 | L42: =Inputs!D11 -> 0.06 | M42: =Inputs!E11 -> 0.08 | N42: =Inputs!F11 -> 0.1 | O42: =Inputs!D11 -> 0.06 | P42: =Inputs!E11 -> 0.08 | Q42: =Inputs!F11 -> 0.1
A43: 電費 | B43: $B | C43: =C8*1000*C41*C15*8760*C42/1000000000 -> 0.404712 | D43: =D8*1000*D41*D15*8760*D42/1000000000 -> 0.672768 | E43: =E8*1000*E41*E15*8760*E42/1000000000 -> 1.02492 | F43: =F8*1000*F41*F15*8760*F42/1000000000 -> 0.404712 | G43: =G8*1000*G41*G15*8760*G42/1000000000 -> 0.672768 | H43: =H8*1000*H41*H15*8760*H42/1000000000 -> 1.02492 | I43: =I8*1000*I41*I15*8760*I42/1000000000 -> 0.404712 | J43: =J8*1000*J41*J15*8760*J42/1000000000 -> 0.672768 | ... Q43: =Q8*1000*Q41*Q15*8760*Q42/1000000000 -> 1.02492
A44: IT 維護 | B44: $B | C44: =C24*Inputs!D30 -> 0.42840539 | D44: =D24*Inputs!E30 -> 0.82530642 | E44: =E24*Inputs!F30 -> 1.3648297 | F44: =F24*Inputs!D30 -> 0.41912563 | G44: =G24*Inputs!E30 -> 0.73151688 | H44: =H24*Inputs!F30 -> 1.1229895 | I44: =I24*Inputs!D30 -> 0.56696088 | J44: =J24*Inputs!E30 -> 1.1152272 | K44: =K24*Inputs!F30 -> 2.0232564 | L44: =L24*Inputs!D30 -> 0.57186686 | M44: =M24*Inputs!E30 -> 1.047361 | N44: =N24*Inputs!F30 -> 1.705503 | O44: =O24*Inputs!D30 -> 0.75464071 | P44: =P24*Inputs!E30 -> 1.5816881 | Q44: =Q24*Inputs!F30 -> 2.7572661
A45: 廠房維護 | B45: $B | C45: =C32*Inputs!D31 -> 0.15318 | D45: =D32*Inputs!E31 -> 0.2534 | E45: =E32*Inputs!F31 -> 0.40465 | F45: =F32*Inputs!D31 -> 0.15318 | G45: =G32*Inputs!E31 -> 0.2534 | H45: =H32*Inputs!F31 -> 0.40465 | I45: =I32*Inputs!D31 -> 0.15318 | J45: =J32*Inputs!E31 -> 0.2534 | K45: =K32*Inputs!F31 -> 0.40465 | L45: =L32*Inputs!D31 -> 0.15318 | M45: =M32*Inputs!E31 -> 0.2534 | N45: =N32*Inputs!F31 -> 0.40465 | O45: =O32*Inputs!D31 -> 0.15318 | P45: =P32*Inputs!E31 -> 0.2534 | Q45: =Q32*Inputs!F31 -> 0.40465
A46: 人員、軟體、水與耗材 | B46: $B | C46: =(Inputs!D32*C8/1000+Inputs!D33*C8/1000+Inputs!D34*C8)/1000 -> 0.24 | D46: =(Inputs!E32*D8/1000+Inputs!E33*D8/1000+Inputs!E34*D8)/1000 -> 0.325 | E46: =(Inputs!F32*E8/1000+Inputs!F33*E8/1000+Inputs!F34*E8)/1000 -> 0.41 | F46: =(Inputs!D32*F8/1000+Inputs!D33*F8/1000+Inputs!D34*F8)/1000 -> 0.24 | G46: =(Inputs!E32*G8/1000+Inputs!E33*G8/1000+Inputs!E34*G8)/1000 -> 0.325 | H46: =(Inputs!F32*H8/1000+Inputs!F33*H8/1000+Inputs!F34*H8)/1000 -> 0.41 | I46: =(Inputs!D32*I8/1000+Inputs!D33*I8/1000+Inputs!D34*I8)/1000 -> 0.24 | J46: =(Inputs!E32*J8/1000+Inputs!E33*J8/1000+Inputs!E34*J8)/1000 -> 0.325 | K46: =(Inputs!F32*K8/1000+Inputs!F33*K8/1000+Inputs!F34*K8)/1000 -> 0.41 | L46: =(Inputs!D32*L8/1000+Inputs!D33*L8/1000+Inputs!D34*L8)/1000 -> 0.24 | M46: =(Inputs!E32*M8/1000+Inputs!E33*M8/1000+Inputs!E34*M8)/1000 -> 0.325 | N46: =(Inputs!F32*N8/1000+Inputs!F33*N8/1000+Inputs!F34*N8)/1000 -> 0.41 | O46: =(Inputs!D32*O8/1000+Inputs!D33*O8/1000+Inputs!D34*O8)/1000 -> 0.24 | P46: =(Inputs!E32*P8/1000+Inputs!E33*P8/1000+Inputs!E34*P8)/1000 -> 0.325 | Q46: =(Inputs!F32*Q8/1000+Inputs!F33*Q8/1000+Inputs!F34*Q8)/1000 -> 0.41
A47: 財產稅與保險 | B47: $B | C47: =C33*Inputs!D35 -> 0.094896808 | D47: =D33*Inputs!E35 -> 0.20090107 | E47: =E33*Inputs!F35 -> 0.40245395 | F47: =F33*Inputs!D35 -> 0.093504845 | G47: =G33*Inputs!E35 -> 0.18526948 | H47: =H33*Inputs!F35 -> 0.3540859 | I47: =I33*Inputs!D35 -> 0.11568013 | J47: =J33*Inputs!E35 -> 0.2492212 | K47: =K33*Inputs!F35 -> 0.53413927 | L47: =L33*Inputs!D35 -> 0.11641603 | M47: =M33*Inputs!E35 -> 0.23791016 | N47: =N33*Inputs!F35 -> 0.4705886 | O47: =O33*Inputs!D35 -> 0.14383211 | P47: =P33*Inputs!E35 -> 0.32696468 | Q47: =Q33*Inputs!F35 -> 0.68094121
A48: 營運費用小計（不含折舊） | B48: $B | C48: =C43+C44+C45+C46+C47 -> 1.3211942 | D48: =D43+D44+D45+D46+D47 -> 2.2773755 | E48: =E43+E44+E45+E46+E47 -> 3.6068537 | F48: =F43+F44+F45+F46+F47 -> 1.3105225 | G48: =G43+G44+G45+G46+G47 -> 2.1679544 | H48: =H43+H44+H45+H46+H47 -> 3.3166454 | I48: =I43+I44+I45+I46+I47 -> 1.480533 | J48: =J43+J44+J45+J46+J47 -> 2.6156164 | ... Q48: =Q43+Q44+Q45+Q46+Q47 -> 5.2777773
A49: 年持有成本 — 會計口徑 | B49: $B | C49: =C39+C40+C48 -> 5.3989724 | D49: =D39+D40+D48 -> 7.4968278 | E49: =E39+E40+E48 -> 12.949273 | F49: =F39+F40+F48 -> 5.3109694 | G49: =G39+G40+G48 -> 6.8663537 | H49: =H39+H40+H48 -> 11.147563 | I49: =I39+I40+I48 -> 6.7129403 | J49: =J39+J40+J48 -> 9.4457397 | ... Q49: =Q39+Q40+Q48 -> 23.322924
A50: D. 年持有成本 — 經濟口徑（資本回收年金）
A51: WACC | B51: % | C51: =Inputs!D28 -> 0.08 | D51: =Inputs!E28 -> 0.1 | E51: =Inputs!F28 -> 0.13 | F51: =Inputs!D28 -> 0.08 | G51: =Inputs!E28 -> 0.1 | H51: =Inputs!F28 -> 0.13 | I51: =Inputs!D28 -> 0.08 | J51: =Inputs!E28 -> 0.1 | K51: =Inputs!F28 -> 0.13 | L51: =Inputs!D28 -> 0.08 | M51: =Inputs!E28 -> 0.1 | N51: =Inputs!F28 -> 0.13 | O51: =Inputs!D28 -> 0.08 | P51: =Inputs!E28 -> 0.1 | Q51: =Inputs!F28 -> 0.13
A52: IT 資本回收係數 | B52: x | C52: =C51/(1-(1+C51)^(-C38)) -> 0.21631539 | D52: =D51/(1-(1+D51)^(-D38)) -> 0.22960738 | E52: =E51/(1-(1+E51)^(-E38)) -> 0.3361942 | F52: =F51/(1-(1+F51)^(-F38)) -> 0.21631539 | G52: =G51/(1-(1+G51)^(-G38)) -> 0.22960738 | H52: =H51/(1-(1+H51)^(-H38)) -> 0.3361942 | I52: =I51/(1-(1+I51)^(-I38)) -> 0.21631539 | J52: =J51/(1-(1+J51)^(-J38)) -> 0.22960738 | ... Q52: =Q51/(1-(1+Q51)^(-Q38)) -> 0.3361942
A53: IT 資本回收 | B53: $B | C53: =C24*C52 -> 4.6335338 | D53: =D24*D52 -> 6.3165482 | E53: =E24*E52 -> 11.471196 | F53: =F24*F52 -> 4.5331661 | G53: =G24*G52 -> 5.5987225 | H53: =H24*H52 -> 9.4385639 | I53: =I24*I52 -> 6.1321181 | J53: =J24*J52 -> 8.5354799 | ... Q53: =Q24*Q52 -> 23.174421
A54: 廠房資本回收（土地按 WACC 計機會成本） | B54: $B | C54: =(C26*C51/(1-(1+C51)^(-Inputs!D24))+C27*C51/(1-(1+C51)^(-Inputs!D25))+C28*C51/(1-(1+C51)^(-Inputs!D26))+C29*C51/(1-(1+C51)^(-Inputs!D27)))*(1+C30)+C25*C51 -> 1.0453153 | D54: =(D26*D51/(1-(1+D51)^(-Inputs!E24))+D27*D51/(1-(1+D51)^(-Inputs!E25))+D28*D51/(1-(1+D51)^(-Inputs!E26))+D29*D51/(1-(1+D51)^(-Inputs!E27)))*(1+D30)+D25*D51 -> 1.5018716 | E54: =(E26*E51/(1-(1+E51)^(-Inputs!F24))+E27*E51/(1-(1+E51)^(-Inputs!F25))+E28*E51/(1-(1+E51)^(-Inputs!F26))+E29*E51/(1-(1+E51)^(-Inputs!F27)))*(1+E30)+E25*E51 -> 2.3279224 | F54: =(F26*F51/(1-(1+F51)^(-Inputs!D24))+F27*F51/(1-(1+F51)^(-Inputs!D25))+F28*F51/(1-(1+F51)^(-Inputs!D26))+F29*F51/(1-(1+F51)^(-Inputs!D27)))*(1+F30)+F25*F51 -> 1.0453153 | G54: =(G26*G51/(1-(1+G51)^(-Inputs!E24))+G27*G51/(1-(1+G51)^(-Inputs!E25))+G28*G51/(1-(1+G51)^(-Inputs!E26))+G29*G51/(1-(1+G51)^(-Inputs!E27)))*(1+G30)+G25*G51 -> 1.5018716 | H54: =(H26*H51/(1-(1+H51)^(-Inputs!F24))+H27*H51/(1-(1+H51)^(-Inputs!F25))+H28*H51/(1-(1+H51)^(-Inputs!F26))+H29*H51/(1-(1+H51)^(-Inputs!F27)))*(1+H30)+H25*H51 -> 2.3279224 | I54: =(I26*I51/(1-(1+I51)^(-Inputs!D24))+I27*I51/(1-(1+I51)^(-Inputs!D25))+I28*I51/(1-(1+I51)^(-Inputs!D26))+I29*I51/(1-(1+I51)^(-Inputs!D27)))*(1+I30)+I25*I51 -> 1.0453153 | J54: =(J26*J51/(1-(1+J51)^(-Inputs!E24))+J27*J51/(1-(1+J51)^(-Inputs!E25))+J28*J51/(1-(1+J51)^(-Inputs!E26))+J29*J51/(1-(1+J51)^(-Inputs!E27)))*(1+J30)+J25*J51 -> 1.5018716 | K54: =(K26*K51/(1-(1+K51)^(-Inputs!F24))+K27*K51/(1-(1+K51)^(-Inputs!F25))+K28*K51/(1-(1+K51)^(-Inputs!F26))+K29*K51/(1-(1+K51)^(-Inputs!F27)))*(1+K30)+K25*K51 -> 2.3279224 | L54: =(L26*L51/(1-(1+L51)^(-Inputs!D24))+L27*L51/(1-(1+L51)^(-Inputs!D25))+L28*L51/(1-(1+L51)^(-Inputs!D26))+L29*L51/(1-(1+L51)^(-Inputs!D27)))*(1+L30)+L25*L51 -> 1.0453153 | M54: =(M26*M51/(1-(1+M51)^(-Inputs!E24))+M27*M51/(1-(1+M51)^(-Inputs!E25))+M28*M51/(1-(1+M51)^(-Inputs!E26))+M29*M51/(1-(1+M51)^(-Inputs!E27)))*(1+M30)+M25*M51 -> 1.5018716 | N54: =(N26*N51/(1-(1+N51)^(-Inputs!F24))+N27*N51/(1-(1+N51)^(-Inputs!F25))+N28*N51/(1-(1+N51)^(-Inputs!F26))+N29*N51/(1-(1+N51)^(-Inputs!F27)))*(1+N30)+N25*N51 -> 2.3279224 | O54: =(O26*O51/(1-(1+O51)^(-Inputs!D24))+O27*O51/(1-(1+O51)^(-Inputs!D25))+O28*O51/(1-(1+O51)^(-Inputs!D26))+O29*O51/(1-(1+O51)^(-Inputs!D27)))*(1+O30)+O25*O51 -> 1.0453153 | P54: =(P26*P51/(1-(1+P51)^(-Inputs!E24))+P27*P51/(1-(1+P51)^(-Inputs!E25))+P28*P51/(1-(1+P51)^(-Inputs!E26))+P29*P51/(1-(1+P51)^(-Inputs!E27)))*(1+P30)+P25*P51 -> 1.5018716 | Q54: =(Q26*Q51/(1-(1+Q51)^(-Inputs!F24))+Q27*Q51/(1-(1+Q51)^(-Inputs!F25))+Q28*Q51/(1-(1+Q51)^(-Inputs!F26))+Q29*Q51/(1-(1+Q51)^(-Inputs!F27)))*(1+Q30)+Q25*Q51 -> 2.3279224
A55: 年持有成本 — 經濟口徑 | B55: $B | C55: =C53+C54+C48 -> 7.0000433 | D55: =D53+D54+D48 -> 10.095795 | E55: =E53+E54+E48 -> 17.405972 | F55: =F53+F54+F48 -> 6.8890039 | G55: =G53+G54+G48 -> 9.2685485 | H55: =H53+H54+H48 -> 15.083132 | I55: =I53+I54+I48 -> 8.6579664 | J55: =J53+J54+J48 -> 12.652968 | ... Q55: =Q53+Q54+Q48 -> 30.780121
A56: E. 單位成本與結構
A57: 每 GPU 小時持有成本 — 會計 | B57: $/GPU-hr | C57: =C49*1000000000/(C14*8760) -> 0.85832849 | D57: =D49*1000000000/(D14*8760) -> 1.1918455 | E57: =E49*1000000000/(E14*8760) -> 2.058675 | F57: =F49*1000000000/(F14*8760) -> 1.1900066 | G57: =G49*1000000000/(G14*8760) -> 1.538515 | H57: =H49*1000000000/(H14*8760) -> 2.4977877 | I57: =I49*1000000000/(I14*8760) -> 1.5850033 | J57: =J49*1000000000/(J14*8760) -> 2.230249 | ... Q57: =Q49*1000000000/(Q14*8760) -> 12.060748
A58: 每 GPU 小時持有成本 — 經濟 | B58: $/GPU-hr | C58: =C55*1000000000/(C14*8760) -> 1.1128667 | D58: =D55*1000000000/(D14*8760) -> 1.6050293 | E58: =E55*1000000000/(E14*8760) -> 2.767201 | F58: =F55*1000000000/(F14*8760) -> 1.5435902 | G58: =G55*1000000000/(G14*8760) -> 2.0767647 | H58: =H55*1000000000/(H14*8760) -> 3.379614 | I58: =I55*1000000000/(I14*8760) -> 2.0442466 | J58: =J55*1000000000/(J14*8760) -> 2.9875129 | ... Q58: =Q55*1000000000/(Q14*8760) -> 15.917013
A59: 每架小時持有成本 — 經濟 | B59: $/rack-hr | C59: =C55*1000000000/(C12*8760) -> 35.611734 | D59: =D55*1000000000/(D12*8760) -> 51.360936 | E59: =E55*1000000000/(E12*8760) -> 88.550431 | F59: =F55*1000000000/(F12*8760) -> 111.13849 | G59: =G55*1000000000/(G12*8760) -> 149.52706 | H59: =H55*1000000000/(H12*8760) -> 243.33221 | I59: =I55*1000000000/(I12*8760) -> 147.18575 | J59: =J55*1000000000/(J12*8760) -> 215.10093 | ... Q59: =Q55*1000000000/(Q12*8760) -> 2292.0499
A60: 年用電（設施端） | B60: TWh | C60: =C8*C41*C15*8760/1000000 -> 6.7452 | D60: =D8*D41*D15*8760/1000000 -> 8.4096 | E60: =E8*E41*E15*8760/1000000 -> 10.2492 | F60: =F8*F41*F15*8760/1000000 -> 6.7452 | G60: =G8*G41*G15*8760/1000000 -> 8.4096 | H60: =H8*H41*H15*8760/1000000 -> 10.2492 | I60: =I8*I41*I15*8760/1000000 -> 6.7452 | J60: =J8*J41*J15*8760/1000000 -> 8.4096 | ... Q60: =Q8*Q41*Q15*8760/1000000 -> 10.2492
A61: 資本回收占經濟口徑 | B61: % | C61: =(C53+C54)/C55 -> 0.81125914 | D61: =(D53+D54)/D55 -> 0.77442337 | E61: =(E53+E54)/E55 -> 0.79278068 | F61: =(F53+F54)/F55 -> 0.80976604 | G61: =(G53+G54)/G55 -> 0.76609559 | H61: =(H53+H54)/H55 -> 0.78010897 | I61: =(I53+I54)/I55 -> 0.8289976 | J61: =(J53+J54)/J55 -> 0.7932804 | ... Q61: =(Q53+Q54)/Q55 -> 0.82853293
A62: 電費占經濟口徑 | B62: % | C62: =C43/C55 -> 0.057815642 | D62: =D43/D55 -> 0.066638435 | E62: =E43/E55 -> 0.058883238 | F62: =F43/F55 -> 0.058747535 | G62: =G43/G55 -> 0.072586123 | H62: =H43/H55 -> 0.067951406 | I62: =I43/I55 -> 0.046744464 | J62: =J43/J55 -> 0.053170766 | ... Q62: =Q43/Q55 -> 0.033298115

Sheet Interface
A1: Interface — 下游模型唯一連結點（每 GW＝IT 關鍵電力）
A2: 每一列為一個具名範圍（IF_…），欄＝世代 × 成本情境；Block 2 產出依層級分區（物理量不隨成本情境變動）
A4: 指標 | B4: 單位 | C4: =Spec_Rack!C4 -> Hopper H100 | D4: =Spec_Rack!C4 -> Hopper H100 | E4: =Spec_Rack!C4 -> Hopper H100 | F4: =Spec_Rack!D4 -> GB200 NVL72 | G4: =Spec_Rack!D4 -> GB200 NVL72 | H4: =Spec_Rack!D4 -> GB200 NVL72 | I4: =Spec_Rack!E4 -> GB300 NVL72 | J4: =Spec_Rack!E4 -> GB300 NVL72 | K4: =Spec_Rack!E4 -> GB300 NVL72 | L4: =Spec_Rack!F4 -> VR200 NVL72 | M4: =Spec_Rack!F4 -> VR200 NVL72 | N4: =Spec_Rack!F4 -> VR200 NVL72 | O4: =Spec_Rack!G4 -> Rubin Ultra NVL576 | P4: =Spec_Rack!G4 -> Rubin Ultra NVL576 | Q4: =Spec_Rack!G4 -> Rubin Ultra NVL576
A5: 成本情境 | C5: 低成本 | D5: 基準 | E5: 高成本 | F5: 低成本 | G5: 基準 | H5: 高成本 | I5: 低成本 | J5: 基準 | K5: 高成本 | L5: 低成本 | M5: 基準 | N5: 高成本 | O5: 低成本 | P5: 基準 | Q5: 高成本
A6: 每 GW 機架數 | B6: 架 | C6: =DC_Cost!C12 -> 22439 | D6: =DC_Cost!D12 -> 22439 | E6: =DC_Cost!E12 -> 22439 | F6: =DC_Cost!F12 -> 7076 | G6: =DC_Cost!G12 -> 7076 | H6: =DC_Cost!H12 -> 7076 | I6: =DC_Cost!I12 -> 6715 | J6: =DC_Cost!J12 -> 6715 | ... Q6: =DC_Cost!Q12 -> 1533
A7: 每 GW GPU 數 | B7: 顆 | C7: =DC_Cost!C14 -> 718048 | D7: =DC_Cost!D14 -> 718048 | E7: =DC_Cost!E14 -> 718048 | F7: =DC_Cost!F14 -> 509472 | G7: =DC_Cost!G14 -> 509472 | H7: =DC_Cost!H14 -> 509472 | I7: =DC_Cost!I14 -> 483480 | J7: =DC_Cost!J14 -> 483480 | ... Q7: =DC_Cost!Q14 -> 220752
A8: 每 IT GW 對應設施電力 | B8: GW | C8: =DC_Cost!C16/1000 -> 1.1 | D8: =DC_Cost!D16/1000 -> 1.2 | E8: =DC_Cost!E16/1000 -> 1.3 | F8: =DC_Cost!F16/1000 -> 1.1 | G8: =DC_Cost!G16/1000 -> 1.2 | H8: =DC_Cost!H16/1000 -> 1.3 | I8: =DC_Cost!I16/1000 -> 1.1 | J8: =DC_Cost!J16/1000 -> 1.2 | ... Q8: =DC_Cost!Q16/1000 -> 1.3
A9: 每 GW 資本支出 — IT 設備 | B9: $B | C9: =DC_Cost!C24 -> 21.420269 | D9: =DC_Cost!D24 -> 27.510214 | E9: =DC_Cost!E24 -> 34.120743 | F9: =DC_Cost!F24 -> 20.956282 | G9: =DC_Cost!G24 -> 24.383896 | H9: =DC_Cost!H24 -> 28.074738 | I9: =DC_Cost!I24 -> 28.348044 | J9: =DC_Cost!J24 -> 37.17424 | ... Q9: =DC_Cost!Q24 -> 68.931652
A10: 每 GW 資本支出 — 廠房 | B10: $B | C10: =DC_Cost!C32 -> 10.212 | D10: =DC_Cost!D32 -> 12.67 | E10: =DC_Cost!E32 -> 16.186 | F10: =DC_Cost!F32 -> 10.212 | G10: =DC_Cost!G32 -> 12.67 | H10: =DC_Cost!H32 -> 16.186 | I10: =DC_Cost!I32 -> 10.212 | J10: =DC_Cost!J32 -> 12.67 | ... Q10: =DC_Cost!Q32 -> 16.186
A11: 每 GW 資本支出 — 合計 | B11: $B | C11: =DC_Cost!C33 -> 31.632269 | D11: =DC_Cost!D33 -> 40.180214 | E11: =DC_Cost!E33 -> 50.306743 | F11: =DC_Cost!F33 -> 31.168282 | G11: =DC_Cost!G33 -> 37.053896 | H11: =DC_Cost!H33 -> 44.260738 | I11: =DC_Cost!I33 -> 38.560044 | J11: =DC_Cost!J33 -> 49.84424 | ... Q11: =DC_Cost!Q33 -> 85.117652
A12: 每 GW 年持有成本 — 會計口徑 | B12: $B/年 | C12: =DC_Cost!C49 -> 5.3989724 | D12: =DC_Cost!D49 -> 7.4968278 | E12: =DC_Cost!E49 -> 12.949273 | F12: =DC_Cost!F49 -> 5.3109694 | G12: =DC_Cost!G49 -> 6.8663537 | H12: =DC_Cost!H49 -> 11.147563 | I12: =DC_Cost!I49 -> 6.7129403 | J12: =DC_Cost!J49 -> 9.4457397 | ... Q12: =DC_Cost!Q49 -> 23.322924
A13: 每 GW 年持有成本 — 經濟口徑 | B13: $B/年 | C13: =DC_Cost!C55 -> 7.0000433 | D13: =DC_Cost!D55 -> 10.095795 | E13: =DC_Cost!E55 -> 17.405972 | F13: =DC_Cost!F55 -> 6.8890039 | G13: =DC_Cost!G55 -> 9.2685485 | H13: =DC_Cost!H55 -> 15.083132 | I13: =DC_Cost!I55 -> 8.6579664 | J13: =DC_Cost!J55 -> 12.652968 | ... Q13: =DC_Cost!Q55 -> 30.780121
A14: 每 GPU 小時持有成本 — 經濟 | B14: $/GPU-hr | C14: =DC_Cost!C58 -> 1.1128667 | D14: =DC_Cost!D58 -> 1.6050293 | E14: =DC_Cost!E58 -> 2.767201 | F14: =DC_Cost!F58 -> 1.5435902 | G14: =DC_Cost!G58 -> 2.0767647 | H14: =DC_Cost!H58 -> 3.379614 | I14: =DC_Cost!I58 -> 2.0442466 | J14: =DC_Cost!J58 -> 2.9875129 | ... Q14: =DC_Cost!Q58 -> 15.917013
A15: 其中：每 GW 年電費 | B15: $B/年 | C15: =DC_Cost!C43 -> 0.404712 | D15: =DC_Cost!D43 -> 0.672768 | E15: =DC_Cost!E43 -> 1.02492 | F15: =DC_Cost!F43 -> 0.404712 | G15: =DC_Cost!G43 -> 0.672768 | H15: =DC_Cost!H43 -> 1.02492 | I15: =DC_Cost!I43 -> 0.404712 | J15: =DC_Cost!J43 -> 0.672768 | ... Q15: =DC_Cost!Q43 -> 1.02492
A17: B. Block 2 產出（依層級；100%＝理想上限；下游以自身利用率換算）
A18: Luna（低層）
A19: 每架總 tok/s（參考任務 P:D） [IF_TokRack_Luna] | B19: tok/s | C19: =INDEX(Perf!$C$91:$Q$91,3*(Unit_Cost!C$6-1)+1) -> 106483.59 | D19: =INDEX(Perf!$C$91:$Q$91,3*(Unit_Cost!D$6-1)+1) -> 106483.59 | E19: =INDEX(Perf!$C$91:$Q$91,3*(Unit_Cost!E$6-1)+1) -> 106483.59 | F19: =INDEX(Perf!$C$91:$Q$91,3*(Unit_Cost!F$6-1)+1) -> 1674189.2 | G19: =INDEX(Perf!$C$91:$Q$91,3*(Unit_Cost!G$6-1)+1) -> 1674189.2 | H19: =INDEX(Perf!$C$91:$Q$91,3*(Unit_Cost!H$6-1)+1) -> 1674189.2 | I19: =INDEX(Perf!$C$91:$Q$91,3*(Unit_Cost!I$6-1)+1) -> 2511283.9 | J19: =INDEX(Perf!$C$91:$Q$91,3*(Unit_Cost!J$6-1)+1) -> 2511283.9 | ... Q19: =INDEX(Perf!$C$91:$Q$91,3*(Unit_Cost!Q$6-1)+1) -> 25922780
A20: 每架 decode tok/s [IF_TokRackD_Luna] | B20: tok/s | C20: =INDEX(Perf!$C$92:$Q$92,3*(Unit_Cost!C$6-1)+1) -> 11831.51 | D20: =INDEX(Perf!$C$92:$Q$92,3*(Unit_Cost!D$6-1)+1) -> 11831.51 | E20: =INDEX(Perf!$C$92:$Q$92,3*(Unit_Cost!E$6-1)+1) -> 11831.51 | F20: =INDEX(Perf!$C$92:$Q$92,3*(Unit_Cost!F$6-1)+1) -> 186021.03 | G20: =INDEX(Perf!$C$92:$Q$92,3*(Unit_Cost!G$6-1)+1) -> 186021.03 | H20: =INDEX(Perf!$C$92:$Q$92,3*(Unit_Cost!H$6-1)+1) -> 186021.03 | I20: =INDEX(Perf!$C$92:$Q$92,3*(Unit_Cost!I$6-1)+1) -> 279031.54 | J20: =INDEX(Perf!$C$92:$Q$92,3*(Unit_Cost!J$6-1)+1) -> 279031.54 | ... Q20: =INDEX(Perf!$C$92:$Q$92,3*(Unit_Cost!Q$6-1)+1) -> 2880308.9
A21: 每 GW 總產出（100%） [IF_TokGW_Luna] | B21: M tok/年 | C21: =INDEX(Perf!$C$94:$Q$94,3*(Unit_Cost!C$6-1)+1) -> 7.5351656e+10 | D21: =INDEX(Perf!$C$94:$Q$94,3*(Unit_Cost!D$6-1)+1) -> 7.5351656e+10 | E21: =INDEX(Perf!$C$94:$Q$94,3*(Unit_Cost!E$6-1)+1) -> 7.5351656e+10 | F21: =INDEX(Perf!$C$94:$Q$94,3*(Unit_Cost!F$6-1)+1) -> 3.7359321e+11 | G21: =INDEX(Perf!$C$94:$Q$94,3*(Unit_Cost!G$6-1)+1) -> 3.7359321e+11 | H21: =INDEX(Perf!$C$94:$Q$94,3*(Unit_Cost!H$6-1)+1) -> 3.7359321e+11 | I21: =INDEX(Perf!$C$94:$Q$94,3*(Unit_Cost!I$6-1)+1) -> 5.3180012e+11 | J21: =INDEX(Perf!$C$94:$Q$94,3*(Unit_Cost!J$6-1)+1) -> 5.3180012e+11 | ... Q21: =INDEX(Perf!$C$94:$Q$94,3*(Unit_Cost!Q$6-1)+1) -> 1.2532287e+12
A22: VR-eq 係數（每 GW 產出 ÷ VR200） [IF_VReq_Luna] | B22: x | C22: =INDEX(Perf!$C$116:$Q$116,3*(Unit_Cost!C$6-1)+1) -> 0.096041849 | D22: =INDEX(Perf!$C$116:$Q$116,3*(Unit_Cost!D$6-1)+1) -> 0.096041849 | E22: =INDEX(Perf!$C$116:$Q$116,3*(Unit_Cost!E$6-1)+1) -> 0.096041849 | F22: =INDEX(Perf!$C$116:$Q$116,3*(Unit_Cost!F$6-1)+1) -> 0.47617511 | G22: =INDEX(Perf!$C$116:$Q$116,3*(Unit_Cost!G$6-1)+1) -> 0.47617511 | H22: =INDEX(Perf!$C$116:$Q$116,3*(Unit_Cost!H$6-1)+1) -> 0.47617511 | I22: =INDEX(Perf!$C$116:$Q$116,3*(Unit_Cost!I$6-1)+1) -> 0.67782275 | J22: =INDEX(Perf!$C$116:$Q$116,3*(Unit_Cost!J$6-1)+1) -> 0.67782275 | ... Q22: =INDEX(Perf!$C$116:$Q$116,3*(Unit_Cost!Q$6-1)+1) -> 1.5973425
A23: 新鮮 prefill $/M（經濟、100%） [IF_CostPre_Luna] | B23: $/M | C23: =Unit_Cost!C16 -> 0.039585277 | D23: =Unit_Cost!D16 -> 0.057091768 | E23: =Unit_Cost!E16 -> 0.098430851 | F23: =Unit_Cost!F16 -> 0.0054302376 | G23: =Unit_Cost!G16 -> 0.0073059068 | H23: =Unit_Cost!H16 -> 0.011889235 | I23: =Unit_Cost!I16 -> 0.0047943402 | J23: =Unit_Cost!J16 -> 0.0070065683 | ... Q23: =Unit_Cost!Q16 -> 0.007670533
A24: 快取命中 prefill $/M（經濟、100%） [IF_CostCache_Luna] | B24: $/M | C24: =Unit_Cost!C17 -> 8.6401733e-06 | D24: =Unit_Cost!D17 -> 1.2461269e-05 | E24: =Unit_Cost!E17 -> 2.1484241e-05 | F24: =Unit_Cost!F17 -> 1.1984263e-05 | G24: =Unit_Cost!G17 -> 1.6123771e-05 | H24: =Unit_Cost!H17 -> 2.6238947e-05 | I24: =Unit_Cost!I17 -> 1.5871303e-05 | J24: =Unit_Cost!J17 -> 2.3194718e-05 | ... Q24: =Unit_Cost!Q17 -> 0.00012357792
A25: decode $/M（經濟、100%） [IF_CostDec_Luna] | B25: $/M | C25: =Unit_Cost!C18 -> 0.5194028 | D25: =Unit_Cost!D18 -> 0.74910741 | E25: =Unit_Cost!E18 -> 1.2915221 | F25: =Unit_Cost!F18 -> 0.12251678 | G25: =Unit_Cost!G18 -> 0.16483554 | H25: =Unit_Cost!H18 -> 0.26824439 | I25: =Unit_Cost!I18 -> 0.10816969 | J25: =Unit_Cost!J18 -> 0.15808188 | ... Q25: =Unit_Cost!Q18 -> 0.15968165
A26: decode $/M（會計、100%） [IF_CostDecAcct_Luna] | B26: $/M | C26: =Unit_Cost!C22 -> 0.40060343 | D26: =Unit_Cost!D22 -> 0.55626418 | E26: =Unit_Cost!E22 -> 0.96083527 | F26: =Unit_Cost!F22 -> 0.094452385 | G26: =Unit_Cost!G22 -> 0.12211396 | H26: =Unit_Cost!H22 -> 0.19825268 | I26: =Unit_Cost!I22 -> 0.083869193 | J26: =Unit_Cost!J22 -> 0.11801186 | ... Q26: =Unit_Cost!Q22 -> 0.12099507
A27: tokens／焦耳（平均用電口徑） [IF_TokPerJ_Luna] | B27: tok/J | C27: =INDEX(Perf!$C$113:$Q$113,3*(Unit_Cost!C$6-1)+1) -> 3.246451 | D27: =INDEX(Perf!$C$113:$Q$113,3*(Unit_Cost!D$6-1)+1) -> 3.246451 | E27: =INDEX(Perf!$C$113:$Q$113,3*(Unit_Cost!E$6-1)+1) -> 3.246451 | F27: =INDEX(Perf!$C$113:$Q$113,3*(Unit_Cost!F$6-1)+1) -> 16.097973 | G27: =INDEX(Perf!$C$113:$Q$113,3*(Unit_Cost!G$6-1)+1) -> 16.097973 | H27: =INDEX(Perf!$C$113:$Q$113,3*(Unit_Cost!H$6-1)+1) -> 16.097973 | I27: =INDEX(Perf!$C$113:$Q$113,3*(Unit_Cost!I$6-1)+1) -> 22.913174 | J27: =INDEX(Perf!$C$113:$Q$113,3*(Unit_Cost!J$6-1)+1) -> 22.913174 | ... Q27: =INDEX(Perf!$C$113:$Q$113,3*(Unit_Cost!Q$6-1)+1) -> 54.005792
A28: Sol（中層）
A29: 每架總 tok/s（參考任務 P:D） [IF_TokRack_Sol] | B29: tok/s | C29: =INDEX(Perf!$C$91:$Q$91,3*(Unit_Cost!C$6-1)+2) -> 30519.795 | D29: =INDEX(Perf!$C$91:$Q$91,3*(Unit_Cost!D$6-1)+2) -> 30519.795 | E29: =INDEX(Perf!$C$91:$Q$91,3*(Unit_Cost!E$6-1)+2) -> 30519.795 | F29: =INDEX(Perf!$C$91:$Q$91,3*(Unit_Cost!F$6-1)+2) -> 475684.23 | G29: =INDEX(Perf!$C$91:$Q$91,3*(Unit_Cost!G$6-1)+2) -> 475684.23 | H29: =INDEX(Perf!$C$91:$Q$91,3*(Unit_Cost!H$6-1)+2) -> 475684.23 | I29: =INDEX(Perf!$C$91:$Q$91,3*(Unit_Cost!I$6-1)+2) -> 713526.35 | J29: =INDEX(Perf!$C$91:$Q$91,3*(Unit_Cost!J$6-1)+2) -> 713526.35 | ... Q29: =INDEX(Perf!$C$91:$Q$91,3*(Unit_Cost!Q$6-1)+2) -> 8001333.6
A30: 每架 decode tok/s [IF_TokRackD_Sol] | B30: tok/s | C30: =INDEX(Perf!$C$92:$Q$92,3*(Unit_Cost!C$6-1)+2) -> 3391.0884 | D30: =INDEX(Perf!$C$92:$Q$92,3*(Unit_Cost!D$6-1)+2) -> 3391.0884 | E30: =INDEX(Perf!$C$92:$Q$92,3*(Unit_Cost!E$6-1)+2) -> 3391.0884 | F30: =INDEX(Perf!$C$92:$Q$92,3*(Unit_Cost!F$6-1)+2) -> 52853.803 | G30: =INDEX(Perf!$C$92:$Q$92,3*(Unit_Cost!G$6-1)+2) -> 52853.803 | H30: =INDEX(Perf!$C$92:$Q$92,3*(Unit_Cost!H$6-1)+2) -> 52853.803 | I30: =INDEX(Perf!$C$92:$Q$92,3*(Unit_Cost!I$6-1)+2) -> 79280.705 | J30: =INDEX(Perf!$C$92:$Q$92,3*(Unit_Cost!J$6-1)+2) -> 79280.705 | ... Q30: =INDEX(Perf!$C$92:$Q$92,3*(Unit_Cost!Q$6-1)+2) -> 889037.07
A31: 每 GW 總產出（100%） [IF_TokGW_Sol] | B31: M tok/年 | C31: =INDEX(Perf!$C$94:$Q$94,3*(Unit_Cost!C$6-1)+2) -> 2.1596915e+10 | D31: =INDEX(Perf!$C$94:$Q$94,3*(Unit_Cost!D$6-1)+2) -> 2.1596915e+10 | E31: =INDEX(Perf!$C$94:$Q$94,3*(Unit_Cost!E$6-1)+2) -> 2.1596915e+10 | F31: =INDEX(Perf!$C$94:$Q$94,3*(Unit_Cost!F$6-1)+2) -> 1.0614833e+11 | G31: =INDEX(Perf!$C$94:$Q$94,3*(Unit_Cost!G$6-1)+2) -> 1.0614833e+11 | H31: =INDEX(Perf!$C$94:$Q$94,3*(Unit_Cost!H$6-1)+2) -> 1.0614833e+11 | I31: =INDEX(Perf!$C$94:$Q$94,3*(Unit_Cost!I$6-1)+2) -> 1.5109936e+11 | J31: =INDEX(Perf!$C$94:$Q$94,3*(Unit_Cost!J$6-1)+2) -> 1.5109936e+11 | ... Q31: =INDEX(Perf!$C$94:$Q$94,3*(Unit_Cost!Q$6-1)+2) -> 3.8682198e+11
A32: VR-eq 係數（每 GW 產出 ÷ VR200） [IF_VReq_Sol] | B32: x | C32: =INDEX(Perf!$C$116:$Q$116,3*(Unit_Cost!C$6-1)+2) -> 0.090705856 | D32: =INDEX(Perf!$C$116:$Q$116,3*(Unit_Cost!D$6-1)+2) -> 0.090705856 | E32: =INDEX(Perf!$C$116:$Q$116,3*(Unit_Cost!E$6-1)+2) -> 0.090705856 | F32: =INDEX(Perf!$C$116:$Q$116,3*(Unit_Cost!F$6-1)+2) -> 0.44581717 | G32: =INDEX(Perf!$C$116:$Q$116,3*(Unit_Cost!G$6-1)+2) -> 0.44581717 | H32: =INDEX(Perf!$C$116:$Q$116,3*(Unit_Cost!H$6-1)+2) -> 0.44581717 | I32: =INDEX(Perf!$C$116:$Q$116,3*(Unit_Cost!I$6-1)+2) -> 0.63460902 | J32: =INDEX(Perf!$C$116:$Q$116,3*(Unit_Cost!J$6-1)+2) -> 0.63460902 | ... Q32: =INDEX(Perf!$C$116:$Q$116,3*(Unit_Cost!Q$6-1)+2) -> 1.624631
A33: 新鮮 prefill $/M（經濟、100%） [IF_CostPre_Sol] | B33: $/M | C33: =Unit_Cost!C29 -> 0.1388923 | D33: =Unit_Cost!D29 -> 0.20031708 | E33: =Unit_Cost!E29 -> 0.34536294 | F33: =Unit_Cost!F29 -> 0.019052998 | G33: =Unit_Cost!G29 -> 0.025634132 | H33: =Unit_Cost!H29 -> 0.041715593 | I33: =Unit_Cost!I29 -> 0.016821834 | J33: =Unit_Cost!J29 -> 0.024583847 | ... Q33: =Unit_Cost!Q29 -> 0.026913491
A34: 快取命中 prefill $/M（經濟、100%） [IF_CostCache_Sol] | B34: $/M | C34: =Unit_Cost!C30 -> 1.225699e-05 | D34: =Unit_Cost!D30 -> 1.7677614e-05 | E34: =Unit_Cost!E30 -> 3.0477644e-05 | F34: =Unit_Cost!F30 -> 1.7000931e-05 | G34: =Unit_Cost!G30 -> 2.2873256e-05 | H34: =Unit_Cost!H30 -> 3.7222693e-05 | I34: =Unit_Cost!I30 -> 2.2515104e-05 | J34: =Unit_Cost!J30 -> 3.2904135e-05 | ... Q34: =Unit_Cost!Q30 -> 0.00017530821
A35: decode $/M（經濟、100%） [IF_CostDec_Sol] | B35: $/M | C35: =Unit_Cost!C31 -> 1.8059629 | D35: =Unit_Cost!D31 -> 2.6046456 | E35: =Unit_Cost!E31 -> 4.4906208 | F35: =Unit_Cost!F31 -> 0.43167406 | G35: =Unit_Cost!G31 -> 0.58077946 | H35: =Unit_Cost!H31 -> 0.94512891 | I35: =Unit_Cost!I31 -> 0.38112371 | J35: =Unit_Cost!J31 -> 0.55698369 | ... Q35: =Unit_Cost!Q31 -> 0.50083827
A36: decode $/M（會計、100%） [IF_CostDecAcct_Sol] | B36: $/M | C36: =Unit_Cost!C35 -> 1.3928977 | D36: =Unit_Cost!D35 -> 1.9341299 | E36: =Unit_Cost!E35 -> 3.3408231 | F36: =Unit_Cost!F35 -> 0.33279234 | G36: =Unit_Cost!G35 -> 0.43025477 | H36: =Unit_Cost!H35 -> 0.698521 | I36: =Unit_Cost!I35 -> 0.29550366 | J36: =Unit_Cost!J35 -> 0.4158015 | ... Q36: =Unit_Cost!Q35 -> 0.3794986
A37: tokens／焦耳（平均用電口徑） [IF_TokPerJ_Sol] | B37: tok/J | C37: =INDEX(Perf!$C$113:$Q$113,3*(Unit_Cost!C$6-1)+2) -> 0.93048156 | D37: =INDEX(Perf!$C$113:$Q$113,3*(Unit_Cost!D$6-1)+2) -> 0.93048156 | E37: =INDEX(Perf!$C$113:$Q$113,3*(Unit_Cost!E$6-1)+2) -> 0.93048156 | F37: =INDEX(Perf!$C$113:$Q$113,3*(Unit_Cost!F$6-1)+2) -> 4.5738868 | G37: =INDEX(Perf!$C$113:$Q$113,3*(Unit_Cost!G$6-1)+2) -> 4.5738868 | H37: =INDEX(Perf!$C$113:$Q$113,3*(Unit_Cost!H$6-1)+2) -> 4.5738868 | I37: =INDEX(Perf!$C$113:$Q$113,3*(Unit_Cost!I$6-1)+2) -> 6.5102769 | J37: =INDEX(Perf!$C$113:$Q$113,3*(Unit_Cost!J$6-1)+2) -> 6.5102769 | ... Q37: =INDEX(Perf!$C$113:$Q$113,3*(Unit_Cost!Q$6-1)+2) -> 16.669445
A38: Astra（頂層）
A39: 每架總 tok/s（參考任務 P:D） [IF_TokRack_Astra] | B39: tok/s | C39: =INDEX(Perf!$C$91:$Q$91,3*(Unit_Cost!C$6-1)+3) -> 5576.4509 | D39: =INDEX(Perf!$C$91:$Q$91,3*(Unit_Cost!D$6-1)+3) -> 5576.4509 | E39: =INDEX(Perf!$C$91:$Q$91,3*(Unit_Cost!E$6-1)+3) -> 5576.4509 | F39: =INDEX(Perf!$C$91:$Q$91,3*(Unit_Cost!F$6-1)+3) -> 92195.741 | G39: =INDEX(Perf!$C$91:$Q$91,3*(Unit_Cost!G$6-1)+3) -> 92195.741 | H39: =INDEX(Perf!$C$91:$Q$91,3*(Unit_Cost!H$6-1)+3) -> 92195.741 | I39: =INDEX(Perf!$C$91:$Q$91,3*(Unit_Cost!I$6-1)+3) -> 115025.96 | J39: =INDEX(Perf!$C$91:$Q$91,3*(Unit_Cost!J$6-1)+3) -> 115025.96 | ... Q39: =INDEX(Perf!$C$91:$Q$91,3*(Unit_Cost!Q$6-1)+3) -> 1835327.7
A40: 每架 decode tok/s [IF_TokRackD_Astra] | B40: tok/s | C40: =INDEX(Perf!$C$92:$Q$92,3*(Unit_Cost!C$6-1)+3) -> 619.60566 | D40: =INDEX(Perf!$C$92:$Q$92,3*(Unit_Cost!D$6-1)+3) -> 619.60566 | E40: =INDEX(Perf!$C$92:$Q$92,3*(Unit_Cost!E$6-1)+3) -> 619.60566 | F40: =INDEX(Perf!$C$92:$Q$92,3*(Unit_Cost!F$6-1)+3) -> 10243.971 | G40: =INDEX(Perf!$C$92:$Q$92,3*(Unit_Cost!G$6-1)+3) -> 10243.971 | H40: =INDEX(Perf!$C$92:$Q$92,3*(Unit_Cost!H$6-1)+3) -> 10243.971 | I40: =INDEX(Perf!$C$92:$Q$92,3*(Unit_Cost!I$6-1)+3) -> 12780.662 | J40: =INDEX(Perf!$C$92:$Q$92,3*(Unit_Cost!J$6-1)+3) -> 12780.662 | ... Q40: =INDEX(Perf!$C$92:$Q$92,3*(Unit_Cost!Q$6-1)+3) -> 203925.3
A41: 每 GW 總產出（100%） [IF_TokGW_Astra] | B41: M tok/年 | C41: =INDEX(Perf!$C$94:$Q$94,3*(Unit_Cost!C$6-1)+3) -> 3.9460991e+09 | D41: =INDEX(Perf!$C$94:$Q$94,3*(Unit_Cost!D$6-1)+3) -> 3.9460991e+09 | E41: =INDEX(Perf!$C$94:$Q$94,3*(Unit_Cost!E$6-1)+3) -> 3.9460991e+09 | F41: =INDEX(Perf!$C$94:$Q$94,3*(Unit_Cost!F$6-1)+3) -> 2.0573363e+10 | G41: =INDEX(Perf!$C$94:$Q$94,3*(Unit_Cost!G$6-1)+3) -> 2.0573363e+10 | H41: =INDEX(Perf!$C$94:$Q$94,3*(Unit_Cost!H$6-1)+3) -> 2.0573363e+10 | I41: =INDEX(Perf!$C$94:$Q$94,3*(Unit_Cost!I$6-1)+3) -> 2.4358384e+10 | J41: =INDEX(Perf!$C$94:$Q$94,3*(Unit_Cost!J$6-1)+3) -> 2.4358384e+10 | ... Q41: =INDEX(Perf!$C$94:$Q$94,3*(Unit_Cost!Q$6-1)+3) -> 8.8728347e+10
A42: VR-eq 係數（每 GW 產出 ÷ VR200） [IF_VReq_Astra] | B42: x | C42: =INDEX(Perf!$C$116:$Q$116,3*(Unit_Cost!C$6-1)+3) -> 0.076398866 | D42: =INDEX(Perf!$C$116:$Q$116,3*(Unit_Cost!D$6-1)+3) -> 0.076398866 | E42: =INDEX(Perf!$C$116:$Q$116,3*(Unit_Cost!E$6-1)+3) -> 0.076398866 | F42: =INDEX(Perf!$C$116:$Q$116,3*(Unit_Cost!F$6-1)+3) -> 0.39831275 | G42: =INDEX(Perf!$C$116:$Q$116,3*(Unit_Cost!G$6-1)+3) -> 0.39831275 | H42: =INDEX(Perf!$C$116:$Q$116,3*(Unit_Cost!H$6-1)+3) -> 0.39831275 | I42: =INDEX(Perf!$C$116:$Q$116,3*(Unit_Cost!I$6-1)+3) -> 0.47159306 | J42: =INDEX(Perf!$C$116:$Q$116,3*(Unit_Cost!J$6-1)+3) -> 0.47159306 | ... Q42: =INDEX(Perf!$C$116:$Q$116,3*(Unit_Cost!Q$6-1)+3) -> 1.7178345
A43: 新鮮 prefill $/M（經濟、100%） [IF_CostPre_Astra] | B43: $/M | C43: =Unit_Cost!C42 -> 0.45898576 | D43: =Unit_Cost!D42 -> 0.66197109 | E43: =Unit_Cost!E42 -> 1.141292 | F43: =Unit_Cost!F42 -> 0.062962848 | G43: =Unit_Cost!G42 -> 0.084710971 | H43: =Unit_Cost!H42 -> 0.13785403 | I43: =Unit_Cost!I42 -> 0.055589706 | J43: =Unit_Cost!J42 -> 0.081240182 | ... Q43: =Unit_Cost!Q42 -> 0.08893876
A44: 快取命中 prefill $/M（經濟、100%） [IF_CostCache_Astra] | B44: $/M | C44: =Unit_Cost!C43 -> 0.00017805867 | D44: =Unit_Cost!D43 -> 0.00025680468 | E44: =Unit_Cost!E43 -> 0.00044275215 | F44: =Unit_Cost!F43 -> 0.00024697443 | G44: =Unit_Cost!G43 -> 0.00033228236 | H44: =Unit_Cost!H43 -> 0.00054073824 | I44: =Unit_Cost!I43 -> 0.00032707945 | J44: =Unit_Cost!J43 -> 0.00047800206 | ... Q44: =Unit_Cost!Q43 -> 0.0025467221
A45: decode $/M（經濟、100%） [IF_CostDec_Astra] | B45: $/M | C45: =Unit_Cost!C44 -> 12.293346 | D45: =Unit_Cost!D44 -> 17.730049 | E45: =Unit_Cost!E44 -> 30.568046 | F45: =Unit_Cost!F44 -> 2.509953 | G45: =Unit_Cost!G44 -> 3.3769209 | H45: =Unit_Cost!H44 -> 5.4954174 | I45: =Unit_Cost!I44 -> 2.7542506 | J45: =Unit_Cost!J44 -> 4.0251304 | ... Q45: =Unit_Cost!Q44 -> 2.410616
A46: decode $/M（會計、100%） [IF_CostDecAcct_Astra] | B46: $/M | C46: =Unit_Cost!C48 -> 9.4815754 | D46: =Unit_Cost!D48 -> 13.16579 | E46: =Unit_Cost!E48 -> 22.741273 | F46: =Unit_Cost!F48 -> 1.9350089 | G46: =Unit_Cost!G48 -> 2.5017006 | H46: =Unit_Cost!H48 -> 4.0615247 | I46: =Unit_Cost!I48 -> 2.1355038 | J46: =Unit_Cost!J48 -> 3.004855 | ... Q46: =Unit_Cost!Q48 -> 1.8265884
A47: tokens／焦耳（平均用電口徑） [IF_TokPerJ_Astra] | B47: tok/J | C47: =INDEX(Perf!$C$113:$Q$113,3*(Unit_Cost!C$6-1)+3) -> 0.17001375 | D47: =INDEX(Perf!$C$113:$Q$113,3*(Unit_Cost!D$6-1)+3) -> 0.17001375 | E47: =INDEX(Perf!$C$113:$Q$113,3*(Unit_Cost!E$6-1)+3) -> 0.17001375 | F47: =INDEX(Perf!$C$113:$Q$113,3*(Unit_Cost!F$6-1)+3) -> 0.88649751 | G47: =INDEX(Perf!$C$113:$Q$113,3*(Unit_Cost!G$6-1)+3) -> 0.88649751 | H47: =INDEX(Perf!$C$113:$Q$113,3*(Unit_Cost!H$6-1)+3) -> 0.88649751 | I47: =INDEX(Perf!$C$113:$Q$113,3*(Unit_Cost!I$6-1)+3) -> 1.0495069 | J47: =INDEX(Perf!$C$113:$Q$113,3*(Unit_Cost!J$6-1)+3) -> 1.0495069 | ... Q47: =INDEX(Perf!$C$113:$Q$113,3*(Unit_Cost!Q$6-1)+3) -> 3.8235995
A48: 基準利用率（第 0 層；下游可覆寫） [IF_Util] | B48: % | C48: =Serving!$C$17 -> 0.6
A50: 每 GW 理論營收 | C50: 待 Block 4（Capability、單價前緣）

Sheet Energy
A1: Energy — 逐步能量下限與閉合檢查
A2: 物理下限＝FLOPs × pJ/FLOP ＋ HBM bytes × pJ/byte ＋ EP bytes × pJ/byte；閉合：下限功率 ≤ 機架平均用電（Block 1 輸入 Inputs!E10）
A4: 輸入
A5: GPU 功率中可歸於運算的比例 | B5: % | C5: 0.6 | F5: Assumed：pJ/FLOP＝GPU 功率 × 此比例 ÷ 峰值（滿載上限口徑），區間 0.4–0.8
A6: EP 通訊能量 NVLink | B6: pJ/byte | C6: 10 | F6: Analogy：SerDes＋交換約 1–2 pJ/bit；區間 5–20
A7: EP 通訊能量 IB（Hopper） | B7: pJ/byte | C7: 40 | F7: Analogy：含光模組與網卡；區間 20–80

Sheet NonNV
A1: NonNV — 非 NVIDIA 世代比例列（D2；全部 [Assumed]，以區間表示）
A2: 每 GW 產出比與每 GW 持有成本比皆相對 VR200（同層級、同 SLO）。持有成本比預設接近 1，依 Block 1 結論：每 GW 持有成本幾乎不隨世代改變
A4: 候選 | B4: 產出比 低 | C4: 產出比 基準 | D4: 產出比 高 | E4: 持有比 低 | F4: 持有比 基準 | G4: 持有比 高 | H4: 每 token 成本比 基準 | I4: 最佳角落 | J4: 最差角落 | K4: 標記 | L4: 說明
A5: AMD MI455X（Helios） | B5: 0.5 | C5: 0.7 | D5: 1 | E5: 0.8 | F5: 0.9 | G5: 1 | H5: =F5/C5 -> 1.2857143 | I5: =E5/D5 -> 0.8 | J5: =G5/B5 -> 2 | K5: Assumed | L5: MI355X 在 V4-Pro 上 26 天內吞吐提升 110 倍（S20 所屬部落格），軟體成熟度為主要不確定
A6: Google TPU v7 Ironwood | B6: 0.6 | C6: 0.8 | D6: 1.1 | E6: 0.7 | F6: 0.8 | G6: 1 | H6: =F6/C6 -> 1 | I6: =E6/D6 -> 0.63636364 | J6: =G6/B6 -> 1.6666667 | K6: Assumed | L6: 自用為主，無公開同口徑實測
A7: AWS Trainium3 | B7: 0.3 | C7: 0.5 | D7: 0.8 | E7: 0.6 | F7: 0.7 | G7: 0.9 | H7: =F7/C7 -> 1.4 | I7: =E7/D7 -> 0.75 | J7: =G7/B7 -> 3 | K7: Assumed | L7: OpenAI v0.5 以 2GW Trainium 合約為輸入
A8: Cerebras WSE-3 | B8: 0.2 | C8: 0.4 | D8: 0.8 | E8: 0.8 | F8: 1 | G8: 1.2 | H8: =F8/C8 -> 2.5 | I8: =E8/D8 -> 1 | J8: =G8/B8 -> 6 | K8: Assumed | L8: 高互動性利基；每 GW 吞吐低、單用戶速度高
A9: OpenAI／Broadcom 客製 | B9: 0.4 | C9: 0.6 | D9: 0.9 | E9: 0.7 | F9: 0.8 | G9: 1 | H9: =F9/C9 -> 1.3333333 | I9: =E9/D9 -> 0.77777778 | J9: =G9/B9 -> 2.5 | K9: Assumed | L9: 無公開規格；沿用 v0.5「自研／其他 0.6（0.4–1.0）」

Sheet Sensitivity
A1: Sensitivity — VR200 NVL72 單變數敏感度（其餘輸入取基準、功率取基準）
A2: 先看敏感度再看基準值：哪個輸入在合理範圍內移動，最能改變每 GW 資本支出與持有成本
A4: 情境 | C4: 基準 | D4: 機架價格－低 | E4: 機架價格－高 | F4: 配電設計功率－低 | G4: 配電設計功率－高 | H4: 網路 %－低 | I4: 網路 %－高 | J4: 廠房建物－低 | K4: 廠房建物－高 | L4: 廠房電力設施－低 | M4: 廠房電力設施－高 | N4: IT 折舊年限（7 年對 4 年）－低 | O4: IT 折舊年限（7 年對 4 年）－高 | P4: WACC－低 | Q4: WACC－高 | R4: 電價－低 | S4: 電價－高 | T4: PUE－低 | U4: PUE－高 | V4: 平均用電比－低 | W4: 平均用電比－高 | X4: 機架外 IT 占比（5% 對 12%）－低 | Y4: 機架外 IT 占比（5% 對 12%）－高
A6: A. 規模與電力
A7: IT 電力 | B7: MW | C7: =Inputs!$E$5*1000 -> 1000 | D7: =Inputs!$E$5*1000 -> 1000 | E7: =Inputs!$E$5*1000 -> 1000 | F7: =Inputs!$E$5*1000 -> 1000 | G7: =Inputs!$E$5*1000 -> 1000 | H7: =Inputs!$E$5*1000 -> 1000 | I7: =Inputs!$E$5*1000 -> 1000 | J7: =Inputs!$E$5*1000 -> 1000 | ... Y7: =Inputs!$E$5*1000 -> 1000
A8: 機架外 IT 電力占比 | B8: % | C8: =Inputs!$E$8 -> 0.08 | D8: =Inputs!$E$8 -> 0.08 | E8: =Inputs!$E$8 -> 0.08 | F8: =Inputs!$E$8 -> 0.08 | G8: =Inputs!$E$8 -> 0.08 | H8: =Inputs!$E$8 -> 0.08 | I8: =Inputs!$E$8 -> 0.08 | J8: =Inputs!$E$8 -> 0.08 | ... W8: =Inputs!$E$8 -> 0.08 | X8: =0.05 -> 0.05 | Y8: =0.12 -> 0.12
A9: 機架可用 IT 電力 | B9: MW | C9: =C7*(1-C8) -> 920 | D9: =D7*(1-D8) -> 920 | E9: =E7*(1-E8) -> 920 | F9: =F7*(1-F8) -> 920 | G9: =G7*(1-G8) -> 920 | H9: =H7*(1-H8) -> 920 | I9: =I7*(1-I8) -> 920 | J9: =J7*(1-J8) -> 920 | ... Y9: =Y7*(1-Y8) -> 880
A10: 每架配電設計功率 | B10: kW | C10: =Spec_Rack!F9 -> 227 | D10: =Spec_Rack!F9 -> 227 | E10: =Spec_Rack!F9 -> 227 | F10: =Spec_Rack!F8 -> 190 | G10: =Spec_Rack!F10 -> 230 | H10: =Spec_Rack!F9 -> 227 | I10: =Spec_Rack!F9 -> 227 | J10: =Spec_Rack!F9 -> 227 | K10: =Spec_Rack!F9 -> 227 | L10: =Spec_Rack!F9 -> 227 | M10: =Spec_Rack!F9 -> 227 | N10: =Spec_Rack!F9 -> 227 | O10: =Spec_Rack!F9 -> 227 | P10: =Spec_Rack!F9 -> 227 | Q10: =Spec_Rack!F9 -> 227 | R10: =Spec_Rack!F9 -> 227 | S10: =Spec_Rack!F9 -> 227 | T10: =Spec_Rack!F9 -> 227 | U10: =Spec_Rack!F9 -> 227 | V10: =Spec_Rack!F9 -> 227 | W10: =Spec_Rack!F9 -> 227 | X10: =Spec_Rack!F9 -> 227 | Y10: =Spec_Rack!F9 -> 227
A11: 每 GW 機架數 | B11: 架 | C11: =FLOOR(C9*1000/C10,1) -> 4052 | D11: =FLOOR(D9*1000/D10,1) -> 4052 | E11: =FLOOR(E9*1000/E10,1) -> 4052 | F11: =FLOOR(F9*1000/F10,1) -> 4842 | G11: =FLOOR(G9*1000/G10,1) -> 4000 | H11: =FLOOR(H9*1000/H10,1) -> 4052 | I11: =FLOOR(I9*1000/I10,1) -> 4052 | J11: =FLOOR(J9*1000/J10,1) -> 4052 | ... Y11: =FLOOR(Y9*1000/Y10,1) -> 3876
A12: GPU 封裝／架 | B12: 顆 | C12: =Spec_Rack!F6 -> 72 | D12: =Spec_Rack!F6 -> 72 | E12: =Spec_Rack!F6 -> 72 | F12: =Spec_Rack!F6 -> 72 | G12: =Spec_Rack!F6 -> 72 | H12: =Spec_Rack!F6 -> 72 | I12: =Spec_Rack!F6 -> 72 | J12: =Spec_Rack!F6 -> 72 | K12: =Spec_Rack!F6 -> 72 | L12: =Spec_Rack!F6 -> 72 | M12: =Spec_Rack!F6 -> 72 | N12: =Spec_Rack!F6 -> 72 | O12: =Spec_Rack!F6 -> 72 | P12: =Spec_Rack!F6 -> 72 | Q12: =Spec_Rack!F6 -> 72 | R12: =Spec_Rack!F6 -> 72 | S12: =Spec_Rack!F6 -> 72 | T12: =Spec_Rack!F6 -> 72 | U12: =Spec_Rack!F6 -> 72 | V12: =Spec_Rack!F6 -> 72 | W12: =Spec_Rack!F6 -> 72 | X12: =Spec_Rack!F6 -> 72 | Y12: =Spec_Rack!F6 -> 72
A13: 每 GW GPU 數 | B13: 顆 | C13: =C11*C12 -> 291744 | D13: =D11*D12 -> 291744 | E13: =E11*E12 -> 291744 | F13: =F11*F12 -> 348624 | G13: =G11*G12 -> 288000 | H13: =H11*H12 -> 291744 | I13: =I11*I12 -> 291744 | J13: =J11*J12 -> 291744 | ... Y13: =Y11*Y12 -> 279072
A14: PUE | B14: x | C14: =Inputs!$E$9 -> 1.2 | D14: =Inputs!$E$9 -> 1.2 | E14: =Inputs!$E$9 -> 1.2 | F14: =Inputs!$E$9 -> 1.2 | G14: =Inputs!$E$9 -> 1.2 | H14: =Inputs!$E$9 -> 1.2 | I14: =Inputs!$E$9 -> 1.2 | J14: =Inputs!$E$9 -> 1.2 | ... S14: =Inputs!$E$9 -> 1.2 | T14: =Inputs!$D$9 -> 1.1 | U14: =Inputs!$F$9 -> 1.3 | V14: =Inputs!$E$9 -> 1.2 | W14: =Inputs!$E$9 -> 1.2 | X14: =Inputs!$E$9 -> 1.2 | Y14: =Inputs!$E$9 -> 1.2
A15: 設施電力（IT × PUE） | B15: MW | C15: =C7*C14 -> 1200 | D15: =D7*D14 -> 1200 | E15: =E7*E14 -> 1200 | F15: =F7*F14 -> 1200 | G15: =G7*G14 -> 1200 | H15: =H7*H14 -> 1200 | I15: =I7*I14 -> 1200 | J15: =J7*J14 -> 1200 | ... Y15: =Y7*Y14 -> 1200
A16: B. 資本支出（$B／GW）
A17: 機架單價 | B17: $M | C17: =Spec_Rack!F12 -> 7.8 | D17: =Spec_Rack!F11 -> 6.7 | E17: =Spec_Rack!F13 -> 9.1 | F17: =Spec_Rack!F12 -> 7.8 | G17: =Spec_Rack!F12 -> 7.8 | H17: =Spec_Rack!F12 -> 7.8 | I17: =Spec_Rack!F12 -> 7.8 | J17: =Spec_Rack!F12 -> 7.8 | K17: =Spec_Rack!F12 -> 7.8 | L17: =Spec_Rack!F12 -> 7.8 | M17: =Spec_Rack!F12 -> 7.8 | N17: =Spec_Rack!F12 -> 7.8 | O17: =Spec_Rack!F12 -> 7.8 | P17: =Spec_Rack!F12 -> 7.8 | Q17: =Spec_Rack!F12 -> 7.8 | R17: =Spec_Rack!F12 -> 7.8 | S17: =Spec_Rack!F12 -> 7.8 | T17: =Spec_Rack!F12 -> 7.8 | U17: =Spec_Rack!F12 -> 7.8 | V17: =Spec_Rack!F12 -> 7.8 | W17: =Spec_Rack!F12 -> 7.8 | X17: =Spec_Rack!F12 -> 7.8 | Y17: =Spec_Rack!F12 -> 7.8
A18: 機架 | B18: $B | C18: =C11*C17/1000 -> 31.6056 | D18: =D11*D17/1000 -> 27.1484 | E18: =E11*E17/1000 -> 36.8732 | F18: =F11*F17/1000 -> 37.7676 | G18: =G11*G17/1000 -> 31.2 | H18: =H11*H17/1000 -> 31.6056 | I18: =I11*I17/1000 -> 31.6056 | J18: =J11*J17/1000 -> 31.6056 | ... Y18: =Y11*Y17/1000 -> 30.2328
A19: Scale-out 網路 ÷ 機架價格 | B19: % | C19: =Inputs!$E$13 -> 0.1 | D19: =Inputs!$E$13 -> 0.1 | E19: =Inputs!$E$13 -> 0.1 | F19: =Inputs!$E$13 -> 0.1 | G19: =Inputs!$E$13 -> 0.1 | H19: =Inputs!$D$13 -> 0.05 | I19: =Inputs!$F$13 -> 0.15 | J19: =Inputs!$E$13 -> 0.1 | K19: =Inputs!$E$13 -> 0.1 | L19: =Inputs!$E$13 -> 0.1 | M19: =Inputs!$E$13 -> 0.1 | N19: =Inputs!$E$13 -> 0.1 | O19: =Inputs!$E$13 -> 0.1 | P19: =Inputs!$E$13 -> 0.1 | Q19: =Inputs!$E$13 -> 0.1 | ... Y19: =Inputs!$E$13 -> 0.1
A20: Scale-out 網路 | B20: $B | C20: =C18*C19 -> 3.16056 | D20: =D18*D19 -> 2.71484 | E20: =E18*E19 -> 3.68732 | F20: =F18*F19 -> 3.77676 | G20: =G18*G19 -> 3.12 | H20: =H18*H19 -> 1.58028 | I20: =I18*I19 -> 4.74084 | J20: =J18*J19 -> 3.16056 | ... Y20: =Y18*Y19 -> 3.02328
A21: 儲存與管理 | B21: $/GPU | C21: =Inputs!$E$14 -> 500 | D21: =Inputs!$E$14 -> 500 | E21: =Inputs!$E$14 -> 500 | F21: =Inputs!$E$14 -> 500 | G21: =Inputs!$E$14 -> 500 | H21: =Inputs!$E$14 -> 500 | I21: =Inputs!$E$14 -> 500 | J21: =Inputs!$E$14 -> 500 | ... Y21: =Inputs!$E$14 -> 500
A22: 儲存與管理 | B22: $B | C22: =C13*C21/1000000000 -> 0.145872 | D22: =D13*D21/1000000000 -> 0.145872 | E22: =E13*E21/1000000000 -> 0.145872 | F22: =F13*F21/1000000000 -> 0.174312 | G22: =G13*G21/1000000000 -> 0.144 | H22: =H13*H21/1000000000 -> 0.145872 | I22: =I13*I21/1000000000 -> 0.145872 | J22: =J13*J21/1000000000 -> 0.145872 | ... Y22: =Y13*Y21/1000000000 -> 0.139536
A23: IT 設備小計 | B23: $B | C23: =C18+C20+C22 -> 34.912032 | D23: =D18+D20+D22 -> 30.009112 | E23: =E18+E20+E22 -> 40.706392 | F23: =F18+F20+F22 -> 41.718672 | G23: =G18+G20+G22 -> 34.464 | H23: =H18+H20+H22 -> 33.331752 | I23: =I18+I20+I22 -> 36.492312 | J23: =J18+J20+J22 -> 34.912032 | ... Y23: =Y18+Y20+Y22 -> 33.395616
A24: 土地 | B24: $B | C24: =C7*Inputs!$E$16/1000 -> 0.02 | D24: =D7*Inputs!$E$16/1000 -> 0.02 | E24: =E7*Inputs!$E$16/1000 -> 0.02 | F24: =F7*Inputs!$E$16/1000 -> 0.02 | G24: =G7*Inputs!$E$16/1000 -> 0.02 | H24: =H7*Inputs!$E$16/1000 -> 0.02 | I24: =I7*Inputs!$E$16/1000 -> 0.02 | J24: =J7*Inputs!$E$16/1000 -> 0.02 | ... Y24: =Y7*Inputs!$E$16/1000 -> 0.02
A25: 建物與基地 | B25: $B | C25: =C7*Inputs!$E$17/1000 -> 3.6 | D25: =D7*Inputs!$E$17/1000 -> 3.6 | E25: =E7*Inputs!$E$17/1000 -> 3.6 | F25: =F7*Inputs!$E$17/1000 -> 3.6 | G25: =G7*Inputs!$E$17/1000 -> 3.6 | H25: =H7*Inputs!$E$17/1000 -> 3.6 | I25: =I7*Inputs!$E$17/1000 -> 3.6 | J25: =J7*Inputs!$D$17/1000 -> 3 | K25: =K7*Inputs!$F$17/1000 -> 4.5 | L25: =L7*Inputs!$E$17/1000 -> 3.6 | M25: =M7*Inputs!$E$17/1000 -> 3.6 | N25: =N7*Inputs!$E$17/1000 -> 3.6 | O25: =O7*Inputs!$E$17/1000 -> 3.6 | P25: =P7*Inputs!$E$17/1000 -> 3.6 | Q25: =Q7*Inputs!$E$17/1000 -> 3.6 | R25: =R7*Inputs!$E$17/1000 -> 3.6 | S25: =S7*Inputs!$E$17/1000 -> 3.6 | ... Y25: =Y7*Inputs!$E$17/1000 -> 3.6
A26: 電力設施 | B26: $B | C26: =C7*Inputs!$E$18/1000 -> 4.5 | D26: =D7*Inputs!$E$18/1000 -> 4.5 | E26: =E7*Inputs!$E$18/1000 -> 4.5 | F26: =F7*Inputs!$E$18/1000 -> 4.5 | G26: =G7*Inputs!$E$18/1000 -> 4.5 | H26: =H7*Inputs!$E$18/1000 -> 4.5 | I26: =I7*Inputs!$E$18/1000 -> 4.5 | J26: =J7*Inputs!$E$18/1000 -> 4.5 | K26: =K7*Inputs!$E$18/1000 -> 4.5 | L26: =L7*Inputs!$D$18/1000 -> 3.8 | M26: =M7*Inputs!$F$18/1000 -> 5.5 | N26: =N7*Inputs!$E$18/1000 -> 4.5 | O26: =O7*Inputs!$E$18/1000 -> 4.5 | P26: =P7*Inputs!$E$18/1000 -> 4.5 | Q26: =Q7*Inputs!$E$18/1000 -> 4.5 | R26: =R7*Inputs!$E$18/1000 -> 4.5 | S26: =S7*Inputs!$E$18/1000 -> 4.5 | T26: =T7*Inputs!$E$18/1000 -> 4.5 | U26: =U7*Inputs!$E$18/1000 -> 4.5 | ... Y26: =Y7*Inputs!$E$18/1000 -> 4.5
A27: 機械與散熱 | B27: $B | C27: =C7*Inputs!$E$19/1000 -> 2.5 | D27: =D7*Inputs!$E$19/1000 -> 2.5 | E27: =E7*Inputs!$E$19/1000 -> 2.5 | F27: =F7*Inputs!$E$19/1000 -> 2.5 | G27: =G7*Inputs!$E$19/1000 -> 2.5 | H27: =H7*Inputs!$E$19/1000 -> 2.5 | I27: =I7*Inputs!$E$19/1000 -> 2.5 | J27: =J7*Inputs!$E$19/1000 -> 2.5 | ... Y27: =Y7*Inputs!$E$19/1000 -> 2.5
A28: 光纖與保全 | B28: $B | C28: =C7*Inputs!$E$20/1000 -> 0.4 | D28: =D7*Inputs!$E$20/1000 -> 0.4 | E28: =E7*Inputs!$E$20/1000 -> 0.4 | F28: =F7*Inputs!$E$20/1000 -> 0.4 | G28: =G7*Inputs!$E$20/1000 -> 0.4 | H28: =H7*Inputs!$E$20/1000 -> 0.4 | I28: =I7*Inputs!$E$20/1000 -> 0.4 | J28: =J7*Inputs!$E$20/1000 -> 0.4 | ... Y28: =Y7*Inputs!$E$20/1000 -> 0.4
