Workbook

Sheet Claude Log
A1: Turn # | B1: Date | C1: User Request | D1: Action Taken | E1: Details | F1: Outcome
A2: 1 | B2: 46093 | C2: Re-wire DC_Cost_Model, Revenue_Model, and OpenAI_Sim to pull all inputs from Config sheet instead of hardcoded WP_VR72_1T_1M1000 / TL_VR72_1T_1M1000 scenario sheets. | D2: Updated 11 formula cells across DC_Cost_Model and Revenue_Model to reference Config (and TL_Param for latency). Updated source note annotations. Updated section headers. | E2: DC_Cost_Model: B5→Config!B5/1M, B6→Config!B6, B8→Config!B7, B9→Config!B8, B10→Config!B14. Revenue_Model: B5→Config!B30, B6→Config!B26, B7→Config!B27, B9→Config!B48, B10→Config!B51, B11→TL_Param!E29. OpenAI_Sim already chains through DC_Cost_Model & Revenue_Model — no direct changes needed. | F2: All three sheets now flow from Config. Values updated automatically (e.g., Revenue_Model now uses 1M/1M tokens and 1.5T model from Config vs old 1M/1K & 1T). Full chain: Config → WP_Param/TL_Param → Revenue_Model; Config → DC_Cost_Model → OpenAI_Sim.
A3: 2 | B3: 46093 | C3: Make data precision (FP8) selectable from Config, based on NVIDIA spec tiers (FP4/FP8/FP16). | D3: Added Precision dropdown (B42), Bytes per Parameter (B43), and Inference PFLOPS (B44) to Config. Updated 8 formulas in WP_Param that had hardcoded *1 (FP8) to reference Config!B43. Updated compute time formulas to use Config!B44 for precision-matched PFLOPS. Updated Config!B62 weight memory check. | E3: Config: B42=FP4/FP8/FP16 dropdown, B43=IF(FP4→0.5,FP8→1,FP16→2), B44=selects matching PFLOPS from B19/B21/B22. WP_Param updated: B37 (weight mem), B73 (prefill HBM wt/layer), B126 (decode HBM wt/layer), B143 (NVLink msg), B158 (GQA wt), B168 (batch wt), B68 (prefill compute time), B121 (decode compute time). All notes updated to reference Config Precision. | F3: Precision is now a single dropdown in Config!B42. Changing it cascades through WP_Param → TL_Param → Revenue_Model → OpenAI_Sim. Verified FP8 baseline values unchanged. Full chain: Config Precision → bytes/param + PFLOPS → weight memory, HBM traffic, compute times, latency, throughput, revenue.
A4: 3 | B4: 46093 | C4: Make token pricing correspond to model size automatically. Build market pricing tiers referenced from real API pricing data (Mar 2026). | D4: Built 5-tier pricing lookup table in Config E28:H42 (Nano/Small/Mid/Frontier/Premium). Added MATCH/INDEX formulas to auto-select Input/Output $/M based on Config!B30 parameters. Wired Revenue_Model B32:B33 to Config!F41:F42. | E4: Tiers: Nano <50B ($0.10/$0.40), Small 50-200B ($0.25/$2), Mid 200-500B ($1.25/$10), Frontier 500B-1.5T ($2.50/$10), Premium >1.5T ($5/$25). Sources: OpenAI (GPT-5/4o/Nano), Anthropic (Opus/Sonnet/Haiku), Mar 2026 market data. Used MATCH with approximate match on ascending thresholds. OpenAI_Sim API rates left independent (calibrated to OpenAI's actual pricing, not model-based). | F4: Revenue_Model now auto-prices at $5/$25 for 1.5T model (Premium tier). Changing B30 to e.g. 300B would auto-select Mid tier at $1.25/$10. Full chain: Config B30 → MATCH/INDEX → F41:F42 → Revenue_Model B32:B33 → revenue calcs → OpenAI_Sim.
A5: 4 | B5: 46093 | C5: Make number of racks depend on IT power. Rack count should be derived from Total Power / Power per Rack, not hardcoded. | D5: Added 'Power per Rack (kW)' row to Config rack presets (row 23): VR NVL72 = 132 kW, GB200 NVL72 = 120 kW. Changed F8 and G8 from hardcoded 4386 to =FLOOR(F5/1000/F23,1). B8 auto-selects via existing IF lookup. | E5: VR NVL72: 1GW / 132kW = 7,575 racks. GB200 NVL72: 1GW / 120kW = 8,333 racks. Power per rack values sourced from NVIDIA specs (GPU TDP × 72 + CPU + networking, liquid-cooled). Downstream: DC_Cost_Model racks, total GPUs, CapEx, OpEx, Revenue_Model throughput all update automatically. | F5: Rack count now fully derived from IT power and rack power draw. Changing Total Power (F5/G5) or Power per Rack (F23/G23) automatically recalculates racks. GB200 NVL72 went from 4,386 to 8,333 racks; total GPUs ~600K; CapEx ~$37.5B.
A6: 5 | B6: 46093 | C6: User asked where the '14/GPU B200' FP4 Training figure (G20) comes from. | D6: Researched NVIDIA Blackwell B200 specs. Compared sheet values against HGX B200 datasheet and multiple technical sources. | E6: NVIDIA official: B200 FP4 = 9 dense / 18 sparse PFLOPS/GPU, FP8 = 4.5/9, FP16 = 2.25/4.5. Sheet has 14/10/5 which don't match either tier cleanly. HGX B200 datasheet (8-GPU): FP4=144, FP8=72, FP16=36 PFLOPS (all with sparsity). Confirmed via primeline-solutions.com datasheet PDF, serversimply.com, cudocompute.com, and runpod.io. | F6: Presented discrepancy to user with dense vs sparse comparison table. Awaiting user decision on whether to update to official NVIDIA figures.
A7: 6 | B7: 46093 | C7: Update all NVIDIA PFLOPS specs to dense (no sparsity) values based on official datasheets. | D7: Updated F19:G22 and E19:E22 with dense PFLOPS. GB200: FP4=9/GPU (648/rack), FP8=4.5 (324), FP16=2.25 (162). Vera Rubin: FP4=35/GPU (2520/rack), FP8=16 (1152), FP16=3.6 (259.2). Updated labels to include 'Dense'. Updated WP_Param labels. Added source notes. | E7: Sources: NVIDIA HGX B200 datasheet (sparse values halved for dense), SemiAnalysis (Rubin 35 PFLOPS dense FP4, 3.5× over Blackwell), Tom's Hardware (Rubin ~16 FP8 PFLOPS/GPU). Previous values (14/10/5 per GPU B200) didn't match either dense or sparse tiers. FP4 Training = FP4 Inference for dense (sparsity only differentiates inference marketing numbers). | F7: All PFLOPS now use dense (no sparsity) consistently. Config B45 (precision-selected PFLOPS) correctly picks 324 for FP8 GB200. Full chain verified: Config → WP_Param compute times → TL_Param latency → Revenue_Model throughput.
A8: 7 | B8: 46093 | C8: Sanity check Revenue_Model margins and unit economics. Full review of pricing, throughput, costs, and profitability. | D8: Computed independent verification of all Revenue_Model sections. Ran sensitivity analysis on utilization (50-85%) and I/O ratio (1:1 to 20:1). Cross-referenced margins against industry benchmarks (AWS, NVIDIA, OpenAI). | E8: Key findings: (1) 49.6% operating margin (after depreciation) is plausible but optimistic — driven by 85% utilization assumption. (2) EBITDA margin 85.6% is extremely high because depreciation dominates OpEx. (3) 10:1 I/O ratio compresses blended rate to $3.18/M vs $6.25 at 1:1. (4) Payback 2.82yr is reasonable. (5) At 60% utilization margin drops to 28.6%. (6) No errors found in formulas — all calculations verified. | F8: Revenue_Model is internally consistent. Main risks: utilization assumption (85% is aggressive), I/O ratio sensitivity, and no R&D/SGA/overhead costs beyond DC OpEx. Presented findings to user.
A9: 8 | B9: 46093 | C9: User asked for detailed explanation of the '25-40% realistic margin' statement from the sanity check. | D9: Provided detailed breakdown of two margin compression factors: (1) utilization drag from 85% to 60-70%, (2) non-DC overhead costs (R&D, S&M, G&A, SBC) typically 15-40% of revenue. Cross-referenced OpenAI_Sim actuals for overhead benchmarks. | E9: Explained: 85%→70% util drops DC margin from 49.6% to ~39%. Adding 15% lean overhead gives ~24% net. Adding 25% moderate overhead gives ~9%. OpenAI-like growth overhead (40%) makes it negative. The 25-40% range assumes mature/lean infra provider at 65-70% util with 10-15% overhead. Revenue_Model is correctly scoped as DC-level P&L, not company-level. | F9: No changes made to spreadsheet. Analytical explanation only. User now understands the gap between DC operating margin and company-level margin.
A10: 9 | B10: 46093 | C10: User wants 1T model as the representative default, doesn't want Config more complicated. | D10: Confirmed 1T is already set in Config!B31. Validated it's the right market representative — GPT-4o ($2.50/$10) and Claude Sonnet ($3/$15) are in the 500B-1.5T range and are the highest-volume API models. | E10: No changes needed. Config!B31 = 1T maps to Frontier tier ($2.50/$10). User also adjusted Revenue_Model!B13 utilization from 85% to 70% per previous discussion. | F10: Config unchanged. 1T dense model is the correct representative for current frontier LLM market (GPT-4o, Claude Sonnet, Gemini 2.5 Pro class).
A11: 10 | B11: 46093 | C11: User asked how GPT-5 and Opus 4.6 fit into the pricing/model-size framework. | D11: Analyzed GPT-5 family pricing tiers (base $1.25/$10, 5.2 $1.75/$14, 5.2 Pro $21/$168) and Opus 4.6 ($5/$25). Mapped to model size estimates and existing Config tiers. | E11: GPT-5 base is Mid tier (~200-500B, likely MoE), not a bigger dense model. Opus 4.6 is Premium (>1.5T). GPT-4o/Sonnet 4.6/GPT-5.2 are Frontier class (~500B-1T). 1T dense at Frontier ($2.50/$10) remains the best representative for high-volume API workloads. | F11: No changes made. Confirmed 1T Frontier tier is correct default. GPT-5 base is actually cheaper (efficiency gains, not size), while Opus is premium niche.
A12: 11 | B12: 46093 | C12: User asked what typical/representative input/output token sizes are for the model. | D12: Researched market data on tokens per request by use case. Found current Config (500K/50K) represents extreme long-context, not typical API workload. Typical ranges: chatbots 500/200-1000, enterprise RAG 5K-50K/500-2K, support tickets 3K/400. | E12: Recommended representative default: ~4,000 input / 1,000 output (4:1 ratio, 5K total). Reflects weighted blend of enterprise RAG (majority of API revenue) and consumer chatbot (majority of volume). Median output-to-input pricing ratio is ~4×, suggesting providers design for 3-5:1 I/O. Current 500K/50K is entire-book-per-request territory. | F12: Presented analysis to user. Awaiting confirmation to update Config!B27 and B28 to representative values. Change would significantly affect latency, throughput, and revenue calculations.
A13: 12 | B13: 46093 | C13: User asked what the input/output token sizes of our own conversation look like. | D13: Estimated per-turn and cumulative token counts. Per-turn user messages ~10-30 tokens, but with conversation history the full input grows to ~10K-17K by turn 11. Output responses ~500-1,500 tokens. Session average: ~4K-8K input / ~700-1K output. | E13: Key insight: API input includes full conversation history, not just the latest message. I/O ratio ~5:1 to 8:1 in multi-turn conversation. This aligns with the 4,000/1,000 representative recommendation. Our conversation is a typical frontier model assistant workload. | F13: No changes made. Analysis-only response reinforcing the 4K/1K recommendation as representative.
... A59: 58 | B59: 46100 | C59: Fix 11 errors across physics, finance, and formatting: (1) FP4 Inference 2520→3600, (2) land depreciation GAAP violation, (3) CapEx per GW formula (marginal vs cumulative), (4) fleet efficiency factor (wrong ratio), (5) d_model values for 8B-700B, (6) batching latency fallacy note, (7) OOM warning on 1M/1M, (8) Grok pricing totals (missing fees), (9) Claude I/O ratio formula, (10) 'Onput' typo, (11) dangling data in Section 10C. | D59: Applied all 11 fixes: corrected formulas, added cell notes documenting each error and fix, updated annotations, cleared orphaned data. | E59: Config!F19: 2520→3600 (50/GPU×72). DC_Cost_Model!D67: =(D28-D25)/B67 excludes $20M land. OpenAI_Sim!C96:H96: CapEx÷new GW instead of year-end. C34: tok/s ratio via TL_Param!O34/N34 replacing broken rev/opex ratio; yields 0.271x (was 0.343x). ModelSize D5:E10: reference architectures (e.g., 8B d_model=4096 not 128). TL_Param!B35 note: batching ≠ latency compression. IO_Sensitivity!O21: OOM flag. Input&Output: Grok totals $0.0068/$0.0499; B22=45000/15500; 'Onput'→'Output'. I487:I488 cleared. | F59: All 11 errors corrected. Key downstream impact: fleet efficiency now 0.271x (correctly between H100 0.25x and GB200 0.32x); VR depreciation $140.0M/yr (was $140.67M); CapEx/GW now shows marginal cost ($25B/GW in 2026E vs old $11.4B). d_model fix flagged but latency values for 8B-700B need full pipeline rerun.

Sheet D_Transformer
A1: Vanilla Decode-Only Transformer | D1: Advanced Decode-Only Transformer

Sheet Context Window Evolution
A1: Context Window Evolution: Model-Level Timeline (2023–2026)
A2: Model | B2: Provider | C2: Release | D2: Context Window | E2: Max Output | F2: Primary Use Cases
A3: GPT-3.5 | B3: OpenAI | C3: 2023 | D3: 4K-16K | E3: 4K | F3: Chatbot, Q&A
A4: GPT-4 | B4: OpenAI | C4: 2023 | D4: 8K-32K | E4: 8K | F4: Reasoning, Code
A5: Claude 2 | B5: Anthropic | C5: 2023 | D5: 100K | E5: ~4K | F5: Doc analysis
A6: Gemini 1.0 Pro | B6: Google | C6: 2023 Q4 | D6: 32K | E6: 8K | F6: Multimodal chat
A7: GPT-4 Turbo | B7: OpenAI | C7: 2024 Q1 | D7: 128K | E7: 4K | F7: Long-doc, Code
A8: Claude 3 Opus | B8: Anthropic | C8: 2024 Q1 | D8: 200K | E8: 4K | F8: Research, Legal
A9: Gemini 1.5 Pro | B9: Google | C9: 2024 Q2 | D9: 1M | E9: 8K | F9: Video, Codebase
A10: Llama 3.1 405B | B10: Meta | C10: 2024 Q3 | D10: 128K | E10: 4K | F10: OSS General
A11: GPT-4.1 | B11: OpenAI | C11: 2025 Q2 | D11: 1M | E11: 32K | F11: Agent, Code
A12: Claude 4.5 Sonnet | B12: Anthropic | C12: 2025 Q3 | D12: 200K | E12: 16K | F12: Coding, Agent
A13: Gemini 2.5 Pro | B13: Google | C13: 2025 Q1 | D13: 1M | E13: 64K | F13: Multimodal, Deep
A14: DeepSeek V3 | B14: DeepSeek | C14: 2025 | D14: 128K | E14: 8K | F14: OSS Reasoning
A15: Llama 4 Scout | B15: Meta | C15: 2025 Q2 | D15: 10M | E15: ~8K | F15: Legal discovery
A16: Claude Opus 4.5/4.6 | B16: Anthropic | C16: 2025 Q4 | D16: 200K | E16: 32K | F16: Deep reasoning
A17: GPT-5.2 | B17: OpenAI | C17: 2025 Q4 | D17: 400K | E17: 32K | F17: Abstract reasoning
A18: Gemini 3 Pro | B18: Google | C18: 2025 Q4 | D18: 1M-10M | E18: 64K | F18: Enterprise multimodal
A20: Input-to-Output Token Ratios Across Real-World Scenarios
A21: Scenario | B21: Input (tokens) | C21: Output (tokens) | D21: I:O Ratio | E21: Typical Context | F21: Description & Real-World Examples
A22: Casual Chatbot | B22: 100-500 | C22: 100-400 | D22: ~1:1 | E22: 4K-8K | F22: Customer service, general Q&A; short turns, rapid exchanges
A23: RAG Q&A System | B23: 2K-8K | C23: 200-800 | D23: ~10:1 | E23: 16K-128K | F23: Enterprise knowledge base; retrieved chunks dominate input
A24: Code Generation | B24: 5K-30K | C24: 500-5K | D24: ~5:1 | E24: 128K-1M | F24: Codebase + prompt; entire repo uploaded for 'vibe coding'
A25: Coding Agent (Agentic) | B25: 10K-50K | C25: 1K-10K | D25: ~5:1 | E25: 128K-1M | F25: Multi-step tool-calling, planning, iterative code edits
A26: Document Summarization | B26: 10K-100K | C26: 500-3K | D26: ~30:1 | E26: 128K-1M | F26: Book-length or report-length text compressed to brief summary
A27: Legal Contract Review | B27: 50K-500K | C27: 2K-10K | D27: ~50:1 | E27: 200K-10M | F27: Full contracts, cross-reference clauses, compliance flagging
A28: Medical Record Analysis | B28: 20K-200K | C28: 1K-5K | D28: ~40:1 | E28: 200K-1M | F28: Multi-page patient records, holistic diagnosis support
A29: Financial Report Analysis | B29: 30K-300K | C29: 2K-8K | D29: ~40:1 | E29: 200K-1M | F29: Annual reports, earnings calls, regulatory filings
A30: Creative Writing | B30: 500-5K | C30: 1K-10K | D30: ~1:2 | E30: 32K-200K | F30: Novels, screenplays; output-heavy with narrative consistency
A31: Roleplay / Interactive Fiction | B31: 1K-5K | C31: 200-2K | D31: ~2:1 | E31: 32K-128K | F31: Character-based dialogue; 60% of roleplay tokens on OpenRouter
A32: Multi-turn Research Agent | B32: 20K-100K | C32: 2K-20K | D32: ~5:1 | E32: 200K-1M | F32: Deep research with web search, tool use, iterative refinement
... A34: Multimodal (Image+Text) | B34: 5K-20K | C34: 500-3K | D34: ~7:1 | E34: 128K-1M | F34: Image tokens add to input; output is text-based analysis
A36: Platform-Level Usage Trends (OpenRouter 100T Token Study)
A37: Metric | B37: Early 2024 / Pre-o1 | C37: Late 2025 / Early 2026 | D37: Key Insight
A38: Avg. Prompt Length | B38: ~1,500 tokens | C38: ~6,000+ tokens | D38: ~4x increase; driven by codebase uploads and agent workflows
A39: Avg. Completion Length | B39: ~150 tokens | C39: ~400 tokens | D39: ~2.7x increase; reasoning models produce longer deliberation traces
A40: Programming Prompts | B40: Often >10K tokens | C40: Often >20K tokens | D40: Entire files/repos passed in; largest driver of prompt complexity
A41: Reasoning Model Share | B41: ~0% (pre-o1) | C41: >50% of all tokens | D41: o1 launched Dec 2024; by late 2025 reasoning models dominate
A42: Tool-Calling Usage | B42: Minimal | C42: Central to high-value workflows | D42: Claude Sonnet and Gemini Flash lead tool-enabled traffic
A43: Open-Source Share | B43: ~15% | C43: ~33% | D43: DeepSeek, Qwen, Kimi K2, MiniMax; Chinese OSS near 30% share
A44: Total Weekly Tokens | B44: ~500B-1T | C44: 7T+ (12T+ by Feb 2026) | D44: 12.7x growth year-over-year on OpenRouter platform
A46: Effective vs. Advertised Context: The Fidelity Gap
A47: Model | B47: Advertised Max Tokens | C47: Effective Reliable Range | D47: Retention Rate | E47: Notes
A48: GPT-4.1 | B48: 1000000 | C48: ~500K-800K | D48: 80-85% | E48: Consistent but slows near max; middle-recall drops 10-15%
A49: Claude Opus 4.5 | B49: 200000 | C49: ~170K-190K | D49: 85-95% | E49: <5% accuracy degradation across full window
A50: Gemini 2.5 Pro | B50: 1000000 | C50: ~700K-900K | D50: 90%+ | E50: Best retention at scale; multimodal adds overhead
A51: Llama 4 Scout | B51: 10000000 | C51: ~128K-256K effective | D51: ~15-50% | E51: Physical capacity 10M but reasoning degrades sharply after 256K
A52: DeepSeek V3 | B52: 128000 | C52: ~90K-100K | D52: 75-80% | E52: Competitive for cost; middle-section drop observed
A53: GPT-5.2 | B53: 400000 | C53: ~300K-350K | D53: 80-85% | E53: Strong reasoning; abstract tasks well-suited
A55: Cost Implications by Context Tier
A56: Context Tier | B56: Best Use Cases | C56: Cost Level | D56: Trade-offs | E56: Representative Models
A57: Short Context (<32K) | B57: Chatbots, Simple Q&A | C57: Low | D57: Fastest response, lowest cost per query | E57: GPT-4o mini, Haiku, Gemini Flash
A58: Medium (32K-128K) | B58: RAG, Code Assist | C58: Moderate | D58: Sweet spot for most enterprise apps | E58: GPT-4 Turbo, Claude Sonnet, DeepSeek V3
A59: Long (128K-200K) | B59: Doc analysis, Agents | C59: High | D59: Full document processing; reliable range for most models | E59: Claude Opus 4.5, GPT-4.1
A60: Very Long (200K-1M) | B60: Codebase, Legal review | C60: Very High | D60: Effective but 'lost-in-middle' risk; 2x pricing for >200K on some APIs | E60: Gemini 2.5 Pro, GPT-4.1
A61: Ultra-Long (1M-10M) | B61: Discovery, Repo-scale | C61: Extreme | D61: Reasoning degrades past ~256K; useful for retrieval, less for synthesis | E61: Llama 4 Scout, Gemini 3 Pro

Sheet Input&Output
A1: Claude- 200 token prompt 1 round conversation | G1: Claude- 160 token prompt 1 round conversation
A2: Conversation Link | B2: https://claude.ai/share/a8aedabd-a6df-4461-8d01-713e5a3ea16b | G2: Conversation Link | H2: https://grok.com/share/bGVnYWN5LWNvcHk_97f0b6e6-0e3e-433f-aa46-f5b8332efddb
A4: Component | B4: Category | C4: Tokens | D4: Rate | E4: Cost | G4: Component | H4: Token Category | I4: Price (Grok 4.1 Fast) | J4: Price (Grok 4) | K4: Real-World Example
A5: Your system prompt (custom, ~2K) | B5: Input | C5: 2000 | D5: $5/MTok | E5: 0.01 | G5: System prompt | H5: prompt_tokens | I5: $0.20 / M | J5: $3.00 / M | K5: 900 tokens → $0.00018 or $0.0027
A6: Tool definitions (5 tools) | B6: Input | C6: 3000 | D6: $5/MTok | E6: 0.015 | G6: Your user prompt | H6: prompt_tokens | I6: $0.20 / M | J6: $3.00 / M | K6: 160 tokens → $0.000032 or $0.00048
A7: Your user message | B7: Input | C7: 200 | D7: $5/MTok | E7: 0.001 | G7: Tool/search results | H7: prompt_tokens | I7: $0.20 / M | J7: $3.00 / M | K7: 2,400 tokens + $0.005 invocation
A8: Web search results (6 searches)* | B8: Input | C8: ~36,000 | D8: $5/MTok | E8: 0.18 | G8: Internal thinking | H8: reasoning_tokens | I8: $0.50 / M | J8: $15.00 / M | K8: 800 tokens → $0.0004 or $0.012
A9: Skill file content | B9: Input | C9: ~3,500 | D9: $5/MTok | E9: 0.018 | G9: Visible reply (output) | H9: completion_tokens | I9: $0.50 / M | J9: $15.00 / M | K9: 1,500 tokens → $0.00075 or $0.0225
A10: Bash tool outputs | B10: Input | C10: ~200 | D10: $5/MTok | E10: 0.001 | G10: Total* | H10: — | I10: ~$0.0068 | J10: ~$0.0499 | K10: —
A11: Total Input | C11: ~45,000 | E11: 0.225
A12: Tool call outputs (search requests, code) | B12: Output | C12: ~4,000 | D12: $25/MTok | E12: 0.1
A13: Thinking tokens (if enabled) | B13: Output | C13: ~4,000 | D13: $25/MTok | E13: 0.1
A14: Visible reply text | B14: Output | C14: ~2,500 | D14: $25/MTok | E14: 0.063
A15: Generated code (docx script) | B15: Output | C15: ~5,000 | D15: $25/MTok | E15: 0.125
A16: Total Output | C16: ~15,500 | E16: 0.388
A17: GRAND TOTAL | C17: ~60,500 | E17: ~$0.61
A18: * Tool call (1$10/1000 call) may apply | G18: *Tool invocations fee may apply(e.g., web_search = $5 / 1,000 calls; live search = $25 / 1,000 sources)
A20: Total input/Prompt | B20: =45000/C7 -> 225 | G20: Total input/Prompt | H20: =(900+160+2400)/160 -> 21.625
A21: Total Output/Visible reply | B21: =15500/(2500+5000) -> 2.0666667 | G21: Total Output/Visible reply | H21: =(800+1500)/1500 -> 1.5333333
A22: Total Input/Total Output | B22: =45000/15500 -> 2.9032258 | G22: Total Input/Total Output | H22: =(900+160+2400)/(800+1500) -> 1.5043478

Sheet Flowchart_TL
A2: \\\\\\\\\\\\\\\\\\\\\\\ | B2: Transformer Inference Pipeline — Optimization Flow (VR72 / 1.5T / 1M input, 1M output)
A4: `
B5: ① BASE LINE | D5: 1. Tokenization (CPU) Duration: 0.050s Bottleneck: CPU | I5: 2. Embedding Lookup + Broadcast Duration: 0.001s Bottleneck: Memory (HBM BW) | N5: 3. Prefill + KV Cache Write Duration: 22.85s Bottleneck: Compute (GPU) | S5: 4. Decode First Token Duration: 0.006s Bottleneck: Memory (HBM BW) | X5: 5. Decode All Tokens Duration: 6,428.69s Bottleneck: Memory (HBM BW) | AC5: 6. De-tokenization (CPU) Duration: 0.050s Bottleneck: CPU | AH5: E2E Total 6,451.64s Avg/Token: 0.00645s
H6: → | M6: → | R6: → | W6: → | AB6: → | AG6: →
X9: ▼ 8.4× faster (6,429→768s)
B10: ⬇ Optimization: GQA + Concurrent Requests (Batch Size 50) + Speculative Decoding ⬇
B12: ② GQA+ BATCH+ SPEC | D12: 1. Tokenization (CPU) Duration: 0.050s Bottleneck: CPU | I12: 2. Embedding Lookup + Broadcast Duration: 0.0003s Bottleneck: NVLink | N12: 3. Prefill + KV Cache Write Duration: 1,142.36s Bottleneck: Compute (GPU) | S12: 4. Decode First Token Duration: 0.001s Bottleneck: Memory (HBM BW) | X12: 5. Decode All Tokens Duration: 767.90s Bottleneck: NV Link | AC12: 6. De-tokenization (CPU) Duration: 0.050s Bottleneck: CPU | AH12: E2E Total 1,910.36s Avg/Token: 0.0000382s
H13: → | M13: → | R13: → | W13: → | AB13: → | AG13: →
X16: ▼ 2.9× faster (768→269s)
B17: ⬇ Optimization: + NVLink Optimization ⬇
B19: ③ +NV LINK OPT | D19: 1. Tokenization (CPU) Duration: 0.050s Bottleneck: CPU | I19: 2. Embedding Lookup + Broadcast Duration: 0.0003s Bottleneck: NVLink | N19: 3. Prefill + KV Cache Write Duration: 1,142.36s Bottleneck: Compute (GPU) | S19: 4. Decode First Token Duration: 0.001s Bottleneck: Memory (HBM BW) | X19: 5. Decode All Tokens Duration: 268.60s Bottleneck: Memory (HBM BW) | AC19: 6. De-tokenization (CPU) Duration: 0.050s Bottleneck: CPU | AH19: E2E Total 1,411.06s Avg/Token: 0.0000282s
H20: → | M20: → | R20: → | W20: → | AB20: → | AG20: →
AH23: Total: 4.6× E2E Speedup 229× better per-token latency
B25: Performance Comparison Summary
B27: Configuration | G27: E2E Time (s) | K27: Decode-All (s) | O27: Avg Time/Token (s) | S27: Speedup vs Base | W27: Key Bottleneck | AA27: Primary Optimizations | AG27: Legend
B28: ① Base Line | G28: 6451.64 | K28: 6428.69 | O28: 0.006452 | S28: 1.0× | W28: Decode-All (HBM BW) | AA28: None | AH28: Standard step
B29: ② GQA + Batch + Spec | G29: 1910.36 | K29: 767.9 | O29: 3.82e-05 | S29: 169× | W29: Prefill (Compute), Decode (HBM) | AA29: GQA, Batch=50, Speculative Decoding | AH29: Dominant bottleneck
B30: ③ + NVLink Opt | G30: 1411.06 | K30: 268.6 | O30: 2.82e-05 | S30: 229× | W30: Prefill (Compute), Decode (HBM) | AA30: +@ NVLink Optimization | AH30: Optimized step

Sheet TL_VR72_1.5T_1M1M
B1: Base Line
A2: # | B2: Step(time in s) | C2: Start Time | D2: Duration | E2: End Time | F2: Compute Time | G2: HBM BW Time | H2: NVLink Time | I2: Bottleneck | J2: Dominant Resource | K2: FLOPs Used | L2: HBM Bytes Moved
A3: 1 | B3: Tokenization (CPU) | C3: 0 | D3: 0.05 | E3: =C3+D3 -> 0.05 | F3: N/A(CPU) | G3: N/A | H3: N/A | I3: CPU | J3: CPU | K3: 0 | L3: 0
A4: 2 | B4: Embedding Lookup + Broadcast | C4: =E3 -> 0.05 | D4: =G4+H4 -> 0.00031235999 | E4: =C4+D4 -> 0.05031236 | F4: 0 | G4: ='WP_VR72_1.5T_1M1M'!B28*'WP_VR72_1.5T_1M1M'!B29/('WP_VR72_1.5T_1M1M'!B15*1000000000000) -> 1.6591392e-06 | H4: =2*'WP_VR72_1.5T_1M1M'!B22*'WP_VR72_1.5T_1M1M'!B29*2*(71/72)/('WP_VR72_1.5T_1M1M'!B12*1000000000000) -> 0.00031070085 | I4: Memory | J4: HBM BW | K4: 0 | L4: ='WP_VR72_1.5T_1M1M'!B22*'WP_VR72_1.5T_1M1M'!B29+'WP_VR72_1.5T_1M1M'!B28*'WP_VR72_1.5T_1M1M'!B29 -> 23101440000
A5: 3 | B5: Prefill+KV Cache Write | C5: =E4 -> 0.05031236 | D5: =F5+H5 -> 22.847222 | E5: =C5+D5 -> 22.897535 | F5: ='WP_VR72_1.5T_1M1M'!B70 -> 21.415513 | G5: ='WP_VR72_1.5T_1M1M'!B87 -> 0.01422438 | H5: ='WP_VR72_1.5T_1M1M'!B97 -> 1.4317095 | I5: Compute | J5: GPU | K5: ='WP_VR72_1.5T_1M1M'!B65 -> 1.3491773e+19 | L5: ='WP_VR72_1.5T_1M1M'!B84 -> 22474520000000
A6: 4 | B6: Decode-First Token | C6: =E5 -> 22.897535 | D6: =G6 -> 0.0064286869 | E6: =C6+D6 -> 22.903963 | F6: ='WP_VR72_1.5T_1M1M'!B121 -> 1.4868762e-05 | G6: ='WP_VR72_1.5T_1M1M'!B151 -> 0.0064286869 | H6: - | I6: Memory | J6: HBM BW | K6: ='WP_VR72_1.5T_1M1M'!B117 -> 18734640000000 | L6: ='WP_VR72_1.5T_1M1M'!B135 -> 9367325242880
A7: 5 | B7: Decode-All Tokens | C7: =E6 -> 22.903963 | D7: =G7+H7 -> 6428.6869 | E7: =C7+D7 -> 6451.5908 | F7: ='WP_VR72_1.5T_1M1M'!B122 -> 14.868762 | G7: ='WP_VR72_1.5T_1M1M'!B138*'WP_VR72_1.5T_1M1M'!B23 -> 5928.6869 | H7: ='WP_VR72_1.5T_1M1M'!B149*'WP_VR72_1.5T_1M1M'!B23 -> 500 | I7: Memory | J7: HBM BW | K7: ='WP_VR72_1.5T_1M1M'!B118 -> 1.873464e+19 | L7: ='WP_VR72_1.5T_1M1M'!B135*'WP_VR72_1.5T_1M1M'!B23 -> 9.3673252e+18
A8: 6 | B8: De-tokenization (CPU) | C8: =E7 -> 6451.5908 | D8: 0.05 | E8: =C8+D8 -> 6451.6408 | F8: N/A(CPU) | G8: N/A | H8: N/A | I8: CPU | J8: CPU | K8: 0 | L8: 0
B9: Avg Time per Output Token (s) | E9: =E8/'WP_VR72_1.5T_1M1M'!B23 -> 0.0064516408
B10: Output token per second | E10: =1/E9 -> 154.99933
B12: Optimized-GQA + Concurrent Requests - Batch Size + Speculative Decoding
A13: # | B13: Step(time in s) | C13: Start Time | D13: Duration | E13: End Time | F13: Compute Time | G13: HBM BW Time | H13: NVLink Time | I13: Bottleneck | J13: Dominant Resource | K13: FLOPs Used | L13: HBM Bytes Moved
A14: 1 | B14: Tokenization (CPU) | C14: 0 | D14: 0.05 | E14: =C14+D14 -> 0.05 | F14: N/A(CPU) | G14: N/A | H14: N/A | I14: CPU | J14: CPU | K14: 0 | L14: 0
A15: 2 | B15: Embedding Lookup + Broadcast | C15: =E14 -> 0.05 | D15: =G15+H15 -> 0.00031235999 | E15: =C15+D15 -> 0.05031236 | F15: 0 | G15: ='WP_VR72_1.5T_1M1M'!B28*'WP_VR72_1.5T_1M1M'!B29/('WP_VR72_1.5T_1M1M'!B15*1000000000000) -> 1.6591392e-06 | H15: =2*'WP_VR72_1.5T_1M1M'!B22*'WP_VR72_1.5T_1M1M'!B29*2*(71/72)/('WP_VR72_1.5T_1M1M'!B12*1000000000000) -> 0.00031070085 | I15: NVLink | J15: NVLink | K15: 0 | L15: ='WP_VR72_1.5T_1M1M'!B22*'WP_VR72_1.5T_1M1M'!B29+'WP_VR72_1.5T_1M1M'!B28*'WP_VR72_1.5T_1M1M'!B29 -> 23101440000
A16: 3 | B16: Prefill+KV Cache Write | C16: =E15 -> 0.05031236 | D16: =F16+H16 -> 1142.3611 | E16: =C16+D16 -> 1142.4114 | F16: ='WP_VR72_1.5T_1M1M'!B70*'WP_VR72_1.5T_1M1M'!B169 -> 1070.7756 | G16: ='WP_VR72_1.5T_1M1M'!B87*'WP_VR72_1.5T_1M1M'!B169 -> 0.71121899 | H16: ='WP_VR72_1.5T_1M1M'!B97*'WP_VR72_1.5T_1M1M'!B169 -> 71.585477 | I16: Compute | J16: GPU | K16: ='WP_VR72_1.5T_1M1M'!B65*'WP_VR72_1.5T_1M1M'!B169 -> 6.7458866e+20 | L16: ='WP_VR72_1.5T_1M1M'!B84*'WP_VR72_1.5T_1M1M'!B169 -> 1.123726e+15
A17: 4 | B17: Decode-First Token | C17: =E16 -> 1142.4114 | D17: =G17 -> 0.0012001367 | E17: =C17+D17 -> 1142.4126 | F17: ='WP_VR72_1.5T_1M1M'!B121 -> 1.4868762e-05 | G17: ='WP_VR72_1.5T_1M1M'!B164 -> 0.0012001367 | H17: - | I17: Memory | J17: HBM BW | K17: ='WP_VR72_1.5T_1M1M'!B117 -> 18734640000000 | L17: ='WP_VR72_1.5T_1M1M'!B163 -> 1896216000000
A18: 5 | B18: Decode-All Tokens | C18: =E17 -> 1142.4126 | D18: =G18+H18 -> 767.8962 | E18: =C18+D18 -> 1910.3088 | F18: ='WP_VR72_1.5T_1M1M'!B122 -> 14.868762 | G18: ='WP_VR72_1.5T_1M1M'!B172*'WP_VR72_1.5T_1M1M'!B23 -> 267.8962 | H18: ='WP_VR72_1.5T_1M1M'!B149*'WP_VR72_1.5T_1M1M'!B23 -> 500 | I18: NV Link | J18: NV Link | K18: ='WP_VR72_1.5T_1M1M'!B118 -> 1.873464e+19 | L18: ='WP_VR72_1.5T_1M1M'!B171*'WP_VR72_1.5T_1M1M'!B23 -> 2.11638e+19
A19: 6 | B19: De-tokenization (CPU) | C19: =E18 -> 1910.3088 | D19: 0.05 | E19: =C19+D19 -> 1910.3588 | F19: N/A(CPU) | G19: N/A | H19: N/A | I19: CPU | J19: CPU | K19: 0 | L19: 0
B20: Avg Time per Output Token (s) | E20: =E19/('WP_VR72_1.5T_1M1M'!B169*'WP_VR72_1.5T_1M1M'!B23) -> 3.8207177e-05 | G20: E2E / (Batch * Output) = Total / (50 * 1000000)
B21: Output token per second | E21: =1/E20 -> 26173.093 | F21: =E9/E20 -> 168.8594
B23: Optimized-GQA + Concurrent Requests - Batch Size + Speculative Decoding + NVLink Optimization
A24: # | B24: Step(time in s) | C24: Start Time | D24: Duration | E24: End Time | F24: Compute Time | G24: HBM BW Time | H24: NVLink Time | I24: Bottleneck | J24: Dominant Resource | K24: FLOPs Used | L24: HBM Bytes Moved
A25: 1 | B25: Tokenization (CPU) | C25: 0 | D25: 0.05 | E25: =C25+D25 -> 0.05 | F25: N/A(CPU) | G25: N/A | H25: N/A | I25: CPU | J25: CPU | K25: 0 | L25: 0
A26: 2 | B26: Embedding Lookup + Broadcast | C26: =E25 -> 0.05 | D26: =G26+H26 -> 0.00031235999 | E26: =C26+D26 -> 0.05031236 | F26: 0 | G26: ='WP_VR72_1.5T_1M1M'!B28*'WP_VR72_1.5T_1M1M'!B29/('WP_VR72_1.5T_1M1M'!B15*1000000000000) -> 1.6591392e-06 | H26: =2*'WP_VR72_1.5T_1M1M'!B22*'WP_VR72_1.5T_1M1M'!B29*2*(71/72)/('WP_VR72_1.5T_1M1M'!B12*1000000000000) -> 0.00031070085 | I26: NVLink | J26: NVLink | K26: 0 | L26: ='WP_VR72_1.5T_1M1M'!B22*'WP_VR72_1.5T_1M1M'!B29+'WP_VR72_1.5T_1M1M'!B28*'WP_VR72_1.5T_1M1M'!B29 -> 23101440000
A27: 3 | B27: Prefill+KV Cache Write | C27: =E26 -> 0.05031236 | D27: =F27+H27 -> 1142.3611 | E27: =C27+D27 -> 1142.4114 | F27: ='WP_VR72_1.5T_1M1M'!B70*'WP_VR72_1.5T_1M1M'!B169 -> 1070.7756 | G27: ='WP_VR72_1.5T_1M1M'!B87*'WP_VR72_1.5T_1M1M'!B169 -> 0.71121899 | H27: ='WP_VR72_1.5T_1M1M'!B97*'WP_VR72_1.5T_1M1M'!B169 -> 71.585477 | I27: Compute | J27: GPU | K27: ='WP_VR72_1.5T_1M1M'!B65*'WP_VR72_1.5T_1M1M'!B169 -> 6.7458866e+20 | L27: ='WP_VR72_1.5T_1M1M'!B84*'WP_VR72_1.5T_1M1M'!B169 -> 1.123726e+15
A28: 4 | B28: Decode-First Token | C28: =E27 -> 1142.4114 | D28: =G28 -> 0.0012001367 | E28: =C28+D28 -> 1142.4126 | F28: ='WP_VR72_1.5T_1M1M'!B121 -> 1.4868762e-05 | G28: ='WP_VR72_1.5T_1M1M'!B164 -> 0.0012001367 | H28: - | I28: Memory | J28: HBM BW | K28: ='WP_VR72_1.5T_1M1M'!B117 -> 18734640000000 | L28: ='WP_VR72_1.5T_1M1M'!B163 -> 1896216000000
A29: 5 | B29: Decode-All Tokens | C29: =E28 -> 1142.4126 | D29: =G29+H29 -> 268.60197 | E29: =C29+D29 -> 1411.0146 | F29: ='WP_VR72_1.5T_1M1M'!B122 -> 14.868762 | G29: ='WP_VR72_1.5T_1M1M'!B172*'WP_VR72_1.5T_1M1M'!B23 -> 267.8962 | H29: ='WP_VR72_1.5T_1M1M'!B206 -> 0.70577231 | I29: Memory | J29: HBM BW | K29: ='WP_VR72_1.5T_1M1M'!B118 -> 1.873464e+19 | L29: ='WP_VR72_1.5T_1M1M'!B171*'WP_VR72_1.5T_1M1M'!B23 -> 2.11638e+19
A30: 6 | B30: De-tokenization (CPU) | C30: =E29 -> 1411.0146 | D30: 0.05 | E30: =C30+D30 -> 1411.0646 | F30: N/A(CPU) | G30: N/A | H30: N/A | I30: CPU | J30: CPU | K30: 0 | L30: 0
B31: Avg Time per Output Token (s) | E31: =E30/('WP_VR72_1.5T_1M1M'!B169*'WP_VR72_1.5T_1M1M'!B23) -> 2.8221292e-05 | G31: E2E / (Batch * Output) = Total / (50 * 1000000)
B32: Output token per second | E32: =1/E31 -> 35434.239 | F32: =E9/E31 -> 228.60898

Sheet WP_VR72_1.5T_1M1M
A1: AI DC Spec. | B1: Data | C1: Note
A2: Total power(W) | B2: =1000000000 -> 1000000000
A3: PUE | B3: 1.2
A4: Rack Type | B4: Vera Rubin NVL72
A5: No.of racks | B5: 4386
A7: Rack Spec. | B7: Data | C7: Note
A8: CPU Type | B8: Vera CPU
A9: No. of CPU | B9: 36
A10: GPU Type | B10: Rubin GPU
A11: No. of GPU | B11: 72
A12: NVLink Bandwidth(TB/s) | B12: 260
A13: NVLink-C2C Bandwidth(TB/s) | B13: 65
A14: GPU Memory(TB) | B14: 20.7 | C14: 0.288/GPU
A15: Memory Bandwidth(TB) | B15: 1580 | C15: 22/GPU
A16: NVFP4 Inference(PFLOPS) | B16: 3600 | C16: 50/GPU
A17: NVFP4 Training(PFLOPS) | B17: =72*35 -> 2520 | C17: 35/GPU
A18: FP8/FP16 Training(PFLOPS) | B18: =17.5*72 -> 1260 | C18: 17.5/GPU
A19: FP16/BF16 | B19: =72*4 -> 288 | C19: 4/GPU
A21: Input/Output Tokens Setup | B21: Data | C21: Note
A22: Input Tokens: | B22: 1000000
A23: Output Tokens: | B23: 1000000
A25: Model Spec. | B25: Data | C25: Note
A26: Parameters | B26: 1503000000000 | C26: Given, 1.503T/128=11.744B Per Layer
A27: Type | B27: Dense
A28: vocab size(V) | B28: 128000
A29: Hidden Dimension(d_model) | B29: 20480 | C29: Given
A30: n_layers | B30: 128 | C30: Given
A31: n_heads | B31: 160
A32: d_head | B32: =B29/B31 -> 128
A33: d_ff(SwiGLU) | B33: =(B26/B30-4*B29^2)/(3*B29) -> 163809.67 | C33: derived:1.5 × 10¹² = 128 × (4 × 20,480² + 3 × 20,480 × d_ff)
A34: Parameters per Layer(Att) | B34: =4*B29^2 -> 1677721600 | C34: Q_W+K_W+V_W+O_W=4*20480^2
A35: Parameters per Layer(FFN) | B35: =3*B29*B33 -> 10064465900 | C35: FFN(x) = [SiLU(x · W_gate) ⊙ (x · W_up)] · W_down~= 3 × 20,480 × d_ff
A36: Total Parameters per Layer | B36: =B34+B35 -> 11742187500
A37: Weight Memory(Byte) | B37: =B26*1 -> 1503000000000 | C37: FP8, 1 parameter= 1 Byte
A38: Weight Memory(Byte)/GPU | B38: =B37/B11 -> 20875000000
A39: KV cache @ Begining(Byte) | B39: =2*B29*B22*B30 -> 5242880000000 | C39: K=V=d_model*layer*no.of Input tokens, Total =K+V
A40: KV cache @ End(Byte) | B40: =2*B29*(B22+B23)*B30 -> 10485760000000 | C40: K=V=d_model*layer*no.of (Input +Output tokens, Total =K+V
A41: KV cache per GPU @ End | B41: =B40/B11 -> 1.4563556e+11
A42: Memory required per GPU | B42: =B41+B38 -> 1.6651056e+11 | C42: Need addition memory for Activations
A43: GPU Memory Headroom | B43: =B14/B11*1000000000000-B42 -> 1.2098944e+11 | C43: Check if GPU has enough memory
A45: Parallelism Strategy
A46: Tensor Parallelism (TP) | B46: 72
A48: Prefill Phase
A49: Prefill Flop Per Layer | B49: Data | C49: Note
A50: QKV Projections | B50: =2*B22*B29^2*3 -> 2.5165824e+15 | C50: 2*Input*d_model^2*3
A51: Q × Kᵀ (Attention Scores) | B51: =2*B22^2*B29 -> 4.096e+16 | C51: 2*input*input*d_model
A52: Attention x V | B52: =2*B22^2*B29 -> 4.096e+16 | C52: 2*input*input*d_model
A53: Output Projection | B53: =2*B22*B29^2 -> 838860800000000 | C53: 2*Input*d_model^2
A54: FFN (SwiGLU, 3 matrices) | B54: =2*B22*B29*B33*3 -> 2.0128932e+16 | C54: 2*input*d_model*d_ff*3
A55: Norms / Softmax / Activations | B55: =5*B22*B29 -> 102400000000 | C55: ~O(input × d_model)~=5*input*d_model
A56: Total Prefill Flop Per Layer | B56: =SUM(B50:B55) -> 1.0540448e+17
A58: Prefill Flop All Layers | B58: Data | C58: Note
A59: QKV Projections | B59: =B50*$B$30 -> 3.2212255e+17 | C59: =B59/$B$65 -> 0.023875479
A60: Q × Kᵀ (Attention Scores) | B60: =B51*$B$30 -> 5.24288e+18 | C60: =B60/$B$65 -> 0.38859829
A61: Attention x V | B61: =B52*$B$30 -> 5.24288e+18 | C61: =B61/$B$65 -> 0.38859829
A62: Output Projection | B62: =B53*$B$30 -> 1.0737418e+17 | C62: =B62/$B$65 -> 0.007958493
A63: FFN (SwiGLU, 3 matrices) | B63: =B54*$B$30 -> 2.5765033e+18 | C63: =B63/$B$65 -> 0.19096847
A64: Norms / Softmax / Activations | B64: =B55*$B$30 -> 13107200000000 | C64: =B64/$B$65 -> 9.7149573e-07
A65: Total Prefill Flop | B65: =SUM(B59:B64) -> 1.3491773e+19 | C65: =B65/$B$65 -> 1
A67: Prefill Compute Time(s) | B67: Data | C67: Note
A68: Prefill Compute Time(Theoretical) | B68: =B65/B18/1000000000000000 -> 10.707756
A69: MFU | B69: 0.5 | C69: model FLOPS utilization (MFU)
A70: Prefill Compute Time(50% MFU) | B70: =B68/B69 -> 21.415513
A72: Prefill HBM Traffic per Layer (byte)
A73: model weights | B73: =1*(4*B29^2+3*B29*B33) -> 11742187500 | C73: 1*(4*d_model^2+3*d_model*d)_ff=1 byte * parameters per layer
A74: Activation reads/writes (intermediate tensors) | B74: =4*B22*B29 -> 81920000000 | C74: ~4 activation tensors per layer: input*d_model
A75: KV cache write | B75: =2*B22*B31*B32 -> 40960000000 | C75: 2(K,V)*(input)*n_head*d_head
A76: FlashAttention internal I/O | B76: =2*B22*B29 -> 40960000000 | C76: O(input × d_model × n_layers)~=2*input*d_model*n_layers
A77: Prefill HBM Traffic Per Layer | B77: =SUM(B73:B76) -> 175582187500
A79: Prefill HBM Traffic All (byte)
A80: model weights | B80: =B73*$B$30 -> 1503000000000 | C80: =B80/$B$84 -> 0.066875733
A81: Activation reads/writes (intermediate tensors) | B81: =B74*$B$30 -> 10485760000000 | C81: =B81/$B$84 -> 0.46656213
A82: KV cache write | B82: =B75*$B$30 -> 5242880000000 | C82: =B82/$B$84 -> 0.23328107
A83: FlashAttention internal I/O | B83: =B76*$B$30 -> 5242880000000 | C83: =B83/$B$84 -> 0.23328107
A84: Total Prefill HBM Traffic All | B84: =SUM(B80:B83) -> 22474520000000 | C84: =B84/$B$84 -> 1
A86: Prefill HBM Traffic Time(s)
A87: Prefill HBM Traffic Time(Theoretical) | B87: =B84/B15/1000000000000 -> 0.01422438
A88: Arithmetic intensity check | B88: =B65/B84 -> 600314.18 | C88: total Prefill flop/Total Prefill HBM Traffic(byte)>>797 roofline breakeven
A90: Prefill NVLink Communication (byte)
A91: all-reduce of the output activation size | B91: =B22*B29 -> 20480000000 | C91: input*d_model
A92: Per all-reduce (ring-reduce) | B92: =2*(B11-1)/B11*B22*B29 -> 4.0391111e+10 | C92: 2*(no.of GPU-1)/(no. of GPU)*input*d_model
A93: Count per layer | B93: 2 | C93: all-reduces (one after attention output projection, one after FFN)
A94: Total per Layer | B94: =B92*B93 -> 8.0782222e+10 | C94: Per all-reduce (ring-reduce)*Count per layer
A95: Total NVLink Communication | B95: =B94*B30 -> 1.0340124e+13 | C95: Total per Layer*n_layers
A96: Total NVLink Communication Time(s) | B96: =B95/(B12/B11*1000000000000) -> 2.8634191 | C96: Total NVLink Communication/per-GPU NVLink BW
A97: NVLink Communication Time with Sharp(s) | B97: =B96*0.5 -> 1.4317095 | C97: SHARP in-network reduction (up to 50% traffic reduction)
A99: Total Prefill Time | B99: =B70+B87+B97 -> 22.861447 | C99: Compute Bound
A102: DECODE (1M output tokens, Avg context 1.5M)
A103: Decode Flop Per Layer | B103: Data | C103: Note
A104: QKV Projections (per tok) | B104: =2*1*B29^2*3 -> 2516582400 | C104: 2*1(1token)*d_model^2*3
A105: Q × Kᵀ (per tok, avg) | B105: =2*B29*(B22+0.5*B23) -> 61440000000 | C105: 2*d_model*(input+output/2)
A106: Attention × V (per tok, avg) | B106: =2*B29*(B22+0.5*B23) -> 61440000000 | C106: 2*d_model*(input+output/2)
A107: Output Projection (per tok) | B107: =2*1*B29^2 -> 838860800 | C107: 2*1(1token)*d_model^2
A108: FFN SwiGLU (per tok) | B108: =2*B29*B33*3 -> 20128931800 | C108: 2*d_model*d_ff*3
A109: DECODE per Layer (per tok avg) | B109: =SUM(B104:B108) -> 146364375000
A111: Decode Flop All Layers | B111: Data | C111: Note
A112: QKV Projections (per tok) | B112: =B104*$B$30 -> 322122547200 | C112: 2*1(1token)*d_model^2*3
A113: Q × Kᵀ (per tok, avg) | B113: =B105*$B$30 -> 7864320000000 | C113: 2*d_model*(input+output/2)
A114: Attention × V (per tok, avg) | B114: =B106*$B$30 -> 7864320000000 | C114: 2*d_model*(input+output/2)
A115: Output Projection (per tok) | B115: =B107*$B$30 -> 107374182400 | C115: 2*1(1token)*d_model^2
...

Sheet TL_VR72_1T_1M1000
B1: Base Line
A2: # | B2: Step(time in s) | C2: Start Time | D2: Duration | E2: End Time | F2: Compute Time | G2: HBM BW Time | H2: NVLink Time | I2: Bottleneck | J2: Dominant Resource | K2: FLOPs Used | L2: HBM Bytes Moved
A3: 1 | B3: Tokenization (CPU) | C3: 0 | D3: 0.05 | E3: =C3+D3 -> 0.05 | F3: N/A(CPU) | G3: N/A | H3: N/A | I3: CPU | J3: CPU | K3: 0 | L3: 0
A4: 2 | B4: Embedding Lookup + Broadcast | C4: =E3 -> 0.05 | D4: =G4+H4 -> 0.00031235999 | E4: =C4+D4 -> 0.05031236 | F4: 0 | G4: =WP_VR72_1T_1M1000!B28*WP_VR72_1T_1M1000!B29/(WP_VR72_1T_1M1000!B15*1000000000000) -> 1.6591392e-06 | H4: =2*WP_VR72_1T_1M1000!B22*WP_VR72_1T_1M1000!B29*2*(71/72)/(WP_VR72_1T_1M1000!B12*1000000000000) -> 0.00031070085 | I4: NVLink | J4: NVLink | K4: 0 | L4: =WP_VR72_1T_1M1000!B22*WP_VR72_1T_1M1000!B29+WP_VR72_1T_1M1000!B28*WP_VR72_1T_1M1000!B29 -> 23101440000
A5: 3 | B5: Prefill+KV Cache Write | C5: =E4 -> 0.05031236 | D5: =F5+H5 -> 21.250397 | E5: =C5+D5 -> 21.300709 | F5: =WP_VR72_1T_1M1000!B70 -> 19.818687 | G5: =WP_VR72_1T_1M1000!B87 -> 0.013906025 | H5: =WP_VR72_1T_1M1000!B97 -> 1.4317095 | I5: Compute | J5: GPU | K5: =WP_VR72_1T_1M1000!B65 -> 1.2485773e+19 | L5: =WP_VR72_1T_1M1000!B84 -> 21971520000000
A6: 4 | B6: Decode-First Token | C6: =E5 -> 21.300709 | D6: =G6 -> 0.0044528523 | E6: =C6+D6 -> 21.305162 | F6: =WP_VR72_1T_1M1000!B121 -> 9.9134943e-06 | G6: =WP_VR72_1T_1M1000!B151 -> 0.0044528523 | H6: - | I6: Memory | J6: HBM BW | K6: =WP_VR72_1T_1M1000!B117 -> 12491002880000 | L6: =WP_VR72_1T_1M1000!B135 -> 6245506682880
A7: 5 | B7: Decode-All Tokens | C7: =E6 -> 21.305162 | D7: =G7+H7 -> 4.4528523 | E7: =C7+D7 -> 25.758015 | F7: =WP_VR72_1T_1M1000!B122 -> 0.0099134943 | G7: =WP_VR72_1T_1M1000!B138*WP_VR72_1T_1M1000!B23 -> 3.9528523 | H7: =WP_VR72_1T_1M1000!B149*WP_VR72_1T_1M1000!B23 -> 0.5 | I7: Memory | J7: HBM BW | K7: =WP_VR72_1T_1M1000!B118 -> 1.2491003e+16 | L7: =WP_VR72_1T_1M1000!B135*WP_VR72_1T_1M1000!B23 -> 6.2455067e+15
A8: 6 | B8: De-tokenization (CPU) | C8: =E7 -> 25.758015 | D8: 0.05 | E8: =C8+D8 -> 25.808015 | F8: N/A(CPU) | G8: N/A | H8: N/A | I8: CPU | J8: CPU | K8: 0 | L8: 0
B9: Avg Time per Output Token (s) | D9: =E8/(WP_VR72_1T_1M1000!B23) -> 0.025808015
B11: Optimized-GQA + Concurrent Requests - Batch Size + Speculative Decoding
A12: # | B12: Step(time in s) | C12: Start Time | D12: Duration | E12: End Time | F12: Compute Time | G12: HBM BW Time | H12: NVLink Time | I12: Bottleneck | J12: Dominant Resource | K12: FLOPs Used | L12: HBM Bytes Moved
A13: 1 | B13: Tokenization (CPU) | C13: 0 | D13: 0.05 | E13: =C13+D13 -> 0.05 | F13: N/A(CPU) | G13: N/A | H13: N/A | I13: CPU | J13: CPU | K13: 0 | L13: 0
A14: 2 | B14: Embedding Lookup + Broadcast | C14: =E13 -> 0.05 | D14: =G14+H14 -> 0.00031235999 | E14: =C14+D14 -> 0.05031236 | F14: 0 | G14: =WP_VR72_1T_1M1000!B28*WP_VR72_1T_1M1000!B29/(WP_VR72_1T_1M1000!B15*1000000000000) -> 1.6591392e-06 | H14: =2*WP_VR72_1T_1M1000!B22*WP_VR72_1T_1M1000!B29*2*(71/72)/(WP_VR72_1T_1M1000!B12*1000000000000) -> 0.00031070085 | I14: NVLink | J14: NVLink | K14: 0 | L14: =WP_VR72_1T_1M1000!B22*WP_VR72_1T_1M1000!B29+WP_VR72_1T_1M1000!B28*WP_VR72_1T_1M1000!B29 -> 23101440000
A15: 3 | B15: Prefill+KV Cache Write | C15: =E14 -> 0.05031236 | D15: =F15+H15 -> 1360.0254 | E15: =C15+D15 -> 1360.0757 | F15: =WP_VR72_1T_1M1000!B70*WP_VR72_1T_1M1000!B169 -> 1268.396 | G15: =WP_VR72_1T_1M1000!B87*WP_VR72_1T_1M1000!B169 -> 0.88998562 | H15: =WP_VR72_1T_1M1000!B97*WP_VR72_1T_1M1000!B169 -> 91.62941 | I15: Compute | J15: GPU | K15: =WP_VR72_1T_1M1000!B65*WP_VR72_1T_1M1000!B169 -> 7.9908948e+20 | L15: =WP_VR72_1T_1M1000!B84*WP_VR72_1T_1M1000!B169 -> 1.4061773e+15
A16: 4 | B16: Decode-First Token | C16: =E15 -> 1360.0757 | D16: =G16 -> 0.00079890827 | E16: =C16+D16 -> 1360.0765 | F16: =WP_VR72_1T_1M1000!B121 -> 9.9134943e-06 | G16: =WP_VR72_1T_1M1000!B164 -> 0.00079890827 | H16: - | I16: Memory | J16: HBM BW | K16: =WP_VR72_1T_1M1000!B117 -> 12491002880000 | L16: =WP_VR72_1T_1M1000!B163 -> 1262275072000
A17: 5 | B17: Decode-All Tokens | C17: =E16 -> 1360.0765 | D17: =G17+H17 -> 0.67588612 | E17: =C17+D17 -> 1360.7524 | F17: =WP_VR72_1T_1M1000!B122 -> 0.0099134943 | G17: =WP_VR72_1T_1M1000!B172*WP_VR72_1T_1M1000!B23 -> 0.17588612 | H17: =WP_VR72_1T_1M1000!B149*WP_VR72_1T_1M1000!B23 -> 0.5 | I17: NVLink | J17: NVLink | K17: =WP_VR72_1T_1M1000!B118 -> 1.2491003e+16 | L17: =WP_VR72_1T_1M1000!B171*WP_VR72_1T_1M1000!B23 -> 1.7785605e+16
A18: 6 | B18: De-tokenization (CPU) | C18: =E17 -> 1360.7524 | D18: 0.05 | E18: =C18+D18 -> 1360.8024 | F18: N/A(CPU) | G18: N/A | H18: N/A | I18: CPU | J18: CPU | K18: 0 | L18: 0
B19: Avg Time per Output Token (s) | D19: =E18/(WP_VR72_1T_1M1000!B169*WP_VR72_1T_1M1000!B23) -> 0.021262538 | G19: E2E / (Batch * Output) = Total / (64 * 1000)
A22: Optimized-GQA + Concurrent Requests - Batch Size + Speculative Decoding + NVLink Optimization
A23: # | B23: Step(time in s) | C23: Start Time | D23: Duration | E23: End Time | F23: Compute Time | G23: HBM BW Time | H23: NVLink Time | I23: Bottleneck | J23: Dominant Resource | K23: FLOPs Used | L23: HBM Bytes Moved
A24: 1 | B24: Tokenization (CPU) | C24: 0 | D24: 0.05 | E24: =C24+D24 -> 0.05 | F24: N/A(CPU) | G24: N/A | H24: N/A | I24: CPU | J24: CPU | K24: 0 | L24: 0
A25: 2 | B25: Embedding Lookup + Broadcast | C25: =E24 -> 0.05 | D25: =G25+H25 -> 0.00031235999 | E25: =C25+D25 -> 0.05031236 | F25: 0 | G25: =WP_VR72_1T_1M1000!B28*WP_VR72_1T_1M1000!B29/(WP_VR72_1T_1M1000!B15*1000000000000) -> 1.6591392e-06 | H25: =2*WP_VR72_1T_1M1000!B22*WP_VR72_1T_1M1000!B29*2*(71/72)/(WP_VR72_1T_1M1000!B12*1000000000000) -> 0.00031070085 | I25: NVLink | J25: NVLink | K25: 0 | L25: =WP_VR72_1T_1M1000!B22*WP_VR72_1T_1M1000!B29+WP_VR72_1T_1M1000!B28*WP_VR72_1T_1M1000!B29 -> 23101440000
A26: 3 | B26: Prefill+KV Cache Write | C26: =E25 -> 0.05031236 | D26: =F26+H26 -> 1360.0254 | E26: =C26+D26 -> 1360.0757 | F26: =WP_VR72_1T_1M1000!B70*WP_VR72_1T_1M1000!B169 -> 1268.396 | G26: =WP_VR72_1T_1M1000!B87*WP_VR72_1T_1M1000!B169 -> 0.88998562 | H26: =WP_VR72_1T_1M1000!B97*WP_VR72_1T_1M1000!B169 -> 91.62941 | I26: Compute | J26: GPU | K26: =WP_VR72_1T_1M1000!B65*WP_VR72_1T_1M1000!B169 -> 7.9908948e+20 | L26: =WP_VR72_1T_1M1000!B84*WP_VR72_1T_1M1000!B169 -> 1.4061773e+15
A27: 4 | B27: Decode-First Token | C27: =E26 -> 1360.0757 | D27: =G27 -> 0.00079890827 | E27: =C27+D27 -> 1360.0765 | F27: =WP_VR72_1T_1M1000!B121 -> 9.9134943e-06 | G27: =WP_VR72_1T_1M1000!B164 -> 0.00079890827 | H27: - | I27: Memory | J27: HBM BW | K27: =WP_VR72_1T_1M1000!B117 -> 12491002880000 | L27: =WP_VR72_1T_1M1000!B163 -> 1262275072000
A28: 5 | B28: Decode-All Tokens | C28: =E27 -> 1360.0765 | D28: =G28+H28 -> 0.17659189 | E28: =C28+D28 -> 1360.2531 | F28: =WP_VR72_1T_1M1000!B122 -> 0.0099134943 | G28: =WP_VR72_1T_1M1000!B172*WP_VR72_1T_1M1000!B23 -> 0.17588612 | H28: =WP_VR72_1T_1M1000!B206 -> 0.00070577231 | I28: Memory | J28: HBM BW | K28: =WP_VR72_1T_1M1000!B118 -> 1.2491003e+16 | L28: =WP_VR72_1T_1M1000!B171*WP_VR72_1T_1M1000!B23 -> 1.7785605e+16
A29: 6 | B29: De-tokenization (CPU) | C29: =E28 -> 1360.2531 | D29: 0.05 | E29: =C29+D29 -> 1360.3031 | F29: N/A(CPU) | G29: N/A | H29: N/A | I29: CPU | J29: CPU | K29: 0 | L29: 0
B30: Avg Time per Output Token (s) | D30: =E29/(WP_VR72_1T_1M1000!B169*WP_VR72_1T_1M1000!B23) -> 0.021254736 | G30: E2E / (Batch * Output) = Total / (64 * 1000)

Sheet WP_VR72_1T_1M1000
A1: zzxxxxq21 | B1: Data | C1: Note
A2: Total power(W) | B2: =1000000000 -> 1000000000
A3: PUE | B3: 1.2
A4: Rack Type | B4: Vera Rubin NVL72
A5: No.of racks | B5: 4386
A7: Rack Spec. | B7: Data | C7: Note
A8: CPU Type | B8: Vera CPU
A9: No. of CPU | B9: 36
A10: GPU Type | B10: Rubin GPU
A11: No. of GPU | B11: 72
A12: NVLink Bandwidth(TB/s) | B12: 260
A13: NVLink-C2C Bandwidth(TB/s) | B13: 65
A14: GPU Memory(TB) | B14: 20.7 | C14: 0.288/GPU
A15: Memory Bandwidth(TB) | B15: 1580 | C15: 22/GPU
A16: NVFP4 Inference(PFLOPS) | B16: 3600 | C16: 50/GPU
A17: NVFP4 Training(PFLOPS) | B17: =72*35 -> 2520 | C17: 35/GPU
A18: FP8/FP16 Training(PFLOPS) | B18: =17.5*72 -> 1260 | C18: 17.5/GPU
A19: FP16/BF16 | B19: =72*4 -> 288 | C19: 4/GPU
A21: Input/Output Tokens Setup | B21: Data | C21: Note
A22: Input Tokens: | B22: 1000000
A23: Output Tokens: | B23: 1000
A25: Model Spec. | B25: Data | C25: Note
A26: Parameters | B26: 1000000000000 | C26: Given, 1.503T/128=11.744B Per Layer
A27: Type | B27: Dense
A28: vocab size(V) | B28: 128000
A29: Hidden Dimension(d_model) | B29: =IF(B26<100000000,B26^(1/4),2^11*10^LOG((B26/10^11))) -> 20480 | C29: Given
A30: n_layers | B30: 128 | C30: Given
A31: n_heads | B31: 160
A32: d_head | B32: =B29/B31 -> 128
A33: d_ff(SwiGLU) | B33: =(B26/B30-4*B29^2)/(3*B29) -> 99849.909 | C33: derived:1.5 × 10¹² = 128 × (4 × 20,480² + 3 × 20,480 × d_ff)
A34: Parameters per Layer(Att) | B34: =4*B29^2 -> 1677721600 | C34: Q_W+K_W+V_W+O_W=4*20480^2
A35: Parameters per Layer(FFN) | B35: =3*B29*B33 -> 6134778400 | C35: FFN(x) = [SiLU(x · W_gate) ⊙ (x · W_up)] · W_down~= 3 × 20,480 × d_ff
A36: Total Parameters per Layer | B36: =B34+B35 -> 7812500000
A37: Weight Memory(Byte) | B37: =B26*1 -> 1000000000000 | C37: FP8, 1 parameter= 1 Byte
A38: Weight Memory(Byte)/GPU | B38: =B37/B11 -> 1.3888889e+10
A39: KV cache @ Begining(Byte) | B39: =2*B29*B22*B30 -> 5242880000000 | C39: K=V=d_model*layer*no.of Input tokens, Total =K+V
A40: KV cache @ End(Byte) | B40: =2*B29*(B22+B23)*B30 -> 5248122880000 | C40: K=V=d_model*layer*no.of (Input +Output tokens, Total =K+V
A41: KV cache per GPU @ End | B41: =B40/B11 -> 7.2890596e+10
A42: Memory required per GPU | B42: =B41+B38 -> 8.6779484e+10 | C42: Need addition memory for Activations
A43: GPU Memory Headroom | B43: =B14/B11*1000000000000-B42 -> 2.0072052e+11 | C43: Check if GPU has enough memory
A45: Parallelism Strategy
A46: Tensor Parallelism (TP) | B46: 72
A48: Prefill Phase
A49: Prefill Flop Per Layer | B49: Data | C49: Note
A50: QKV Projections | B50: =2*B22*B29^2*3 -> 2.5165824e+15 | C50: 2*Input*d_model^2*3
A51: Q × Kᵀ (Attention Scores) | B51: =2*B22^2*B29 -> 4.096e+16 | C51: 2*input*input*d_model
A52: Attention x V | B52: =2*B22^2*B29 -> 4.096e+16 | C52: 2*input*input*d_model
A53: Output Projection | B53: =2*B22*B29^2 -> 838860800000000 | C53: 2*Input*d_model^2
A54: FFN (SwiGLU, 3 matrices) | B54: =2*B22*B29*B33*3 -> 1.2269557e+16 | C54: 2*input*d_model*d_ff*3
A55: Norms / Softmax / Activations | B55: =5*B22*B29 -> 102400000000 | C55: ~O(input × d_model)~=5*input*d_model
A56: Total Prefill Flop Per Layer | B56: =SUM(B50:B55) -> 9.7545102e+16
A58: Prefill Flop All Layers | B58: Data | C58: Note
A59: QKV Projections | B59: =B50*$B$30 -> 3.2212255e+17 | C59: =B59/$B$65 -> 0.025799167
A60: Q × Kᵀ (Attention Scores) | B60: =B51*$B$30 -> 5.24288e+18 | C60: =B60/$B$65 -> 0.41990832
A61: Attention x V | B61: =B52*$B$30 -> 5.24288e+18 | C61: =B61/$B$65 -> 0.41990832
A62: Output Projection | B62: =B53*$B$30 -> 1.0737418e+17 | C62: =B62/$B$65 -> 0.0085997224
A63: FFN (SwiGLU, 3 matrices) | B63: =B54*$B$30 -> 1.5705033e+18 | C63: =B63/$B$65 -> 0.12578342
A64: Norms / Softmax / Activations | B64: =B55*$B$30 -> 13107200000000 | C64: =B64/$B$65 -> 1.0497708e-06
A65: Total Prefill Flop | B65: =SUM(B59:B64) -> 1.2485773e+19 | C65: =B65/$B$65 -> 1
A67: Prefill Compute Time(s) | B67: Data | C67: Note
A68: Prefill Compute Time(Theoretical) | B68: =B65/B18/1000000000000000 -> 9.9093437
A69: MFU | B69: 0.5 | C69: model FLOPS utilization (MFU)
A70: Prefill Compute Time(50% MFU) | B70: =B68/B69 -> 19.818687
A72: Prefill HBM Traffic per Layer (byte)
A73: model weights | B73: =1*(4*B29^2+3*B29*B33) -> 7812500000 | C73: 1*(4*d_model^2+3*d_model*d)_ff=1 byte * parameters per layer
A74: Activation reads/writes (intermediate tensors) | B74: =4*B22*B29 -> 81920000000 | C74: ~4 activation tensors per layer: input*d_model
A75: KV cache write | B75: =2*B22*B31*B32 -> 40960000000 | C75: 2(K,V)*(input)*n_head*d_head
A76: FlashAttention internal I/O | B76: =2*B22*B29 -> 40960000000 | C76: O(input × d_model × n_layers)~=2*input*d_model*n_layers
A77: Prefill HBM Traffic Per Layer | B77: =SUM(B73:B76) -> 171652500000
A79: Prefill HBM Traffic All (byte)
A80: model weights | B80: =B73*$B$30 -> 1000000000000 | C80: =B80/$B$84 -> 0.045513465
A81: Activation reads/writes (intermediate tensors) | B81: =B74*$B$30 -> 10485760000000 | C81: =B81/$B$84 -> 0.47724327
A82: KV cache write | B82: =B75*$B$30 -> 5242880000000 | C82: =B82/$B$84 -> 0.23862163
A83: FlashAttention internal I/O | B83: =B76*$B$30 -> 5242880000000 | C83: =B83/$B$84 -> 0.23862163
A84: Total Prefill HBM Traffic All | B84: =SUM(B80:B83) -> 21971520000000 | C84: =B84/$B$84 -> 1
A86: Prefill HBM Traffic Time(s)
A87: Prefill HBM Traffic Time(Theoretical) | B87: =B84/B15/1000000000000 -> 0.013906025
A88: Arithmetic intensity check | B88: =B65/B84 -> 568270.79 | C88: total Prefill flop/Total Prefill HBM Traffic(byte)>>797 roofline breakeven
A90: Prefill NVLink Communication (byte)
A91: all-reduce of the output activation size | B91: =B22*B29 -> 20480000000 | C91: input*d_model
A92: Per all-reduce (ring-reduce) | B92: =2*(B11-1)/B11*B22*B29 -> 4.0391111e+10 | C92: 2*(no.of GPU-1)/(no. of GPU)*input*d_model
A93: Count per layer | B93: 2 | C93: all-reduces (one after attention output projection, one after FFN)
A94: Total per Layer | B94: =B92*B93 -> 8.0782222e+10 | C94: Per all-reduce (ring-reduce)*Count per layer
A95: Total NVLink Communication | B95: =B94*B30 -> 1.0340124e+13 | C95: Total per Layer*n_layers
A96: Total NVLink Communication Time(s) | B96: =B95/(B12/B11*1000000000000) -> 2.8634191 | C96: Total NVLink Communication/per-GPU NVLink BW
A97: NVLink Communication Time with Sharp(s) | B97: =B96*0.5 -> 1.4317095 | C97: SHARP in-network reduction (up to 50% traffic reduction)
A99: Total Prefill Time | B99: =B70+B87+B97 -> 21.264303 | C99: Compute Bound
A102: DECODE (1M output tokens, Avg context 1.5M)
A103: Decode Flop Per Layer | B103: Data | C103: Note
A104: QKV Projections (per tok) | B104: =2*1*B29^2*3 -> 2516582400 | C104: 2*1(1token)*d_model^2*3
A105: Q × Kᵀ (per tok, avg) | B105: =2*B29*(B22+0.5*B23) -> 40980480000 | C105: 2*d_model*(input+output/2)
A106: Attention × V (per tok, avg) | B106: =2*B29*(B22+0.5*B23) -> 40980480000 | C106: 2*d_model*(input+output/2)
A107: Output Projection (per tok) | B107: =2*1*B29^2 -> 838860800 | C107: 2*1(1token)*d_model^2
A108: FFN SwiGLU (per tok) | B108: =2*B29*B33*3 -> 12269556800 | C108: 2*d_model*d_ff*3
A109: DECODE per Layer (per tok avg) | B109: =SUM(B104:B108) -> 97585960000
A111: Decode Flop All Layers | B111: Data | C111: Note
A112: QKV Projections (per tok) | B112: =B104*$B$30 -> 322122547200 | C112: 2*1(1token)*d_model^2*3
A113: Q × Kᵀ (per tok, avg) | B113: =B105*$B$30 -> 5245501440000 | C113: 2*d_model*(input+output/2)
A114: Attention × V (per tok, avg) | B114: =B106*$B$30 -> 5245501440000 | C114: 2*d_model*(input+output/2)
A115: Output Projection (per tok) | B115: =B107*$B$30 -> 107374182400 | C115: 2*1(1token)*d_model^2
...

Sheet Config
A1: PARAMETERIZED TOKEN GENERATION PIPELINE | E1: RACK PRESETS
A2: Change the blue cells below to experiment with different configurations | E2: Copy a column into Column B to switch racks
A4: AI DC Spec. | B4: Data | C4: Note | E4: AI DC Spec. | F4: Vera Rubin NVL72 | G4: GB200 NVL72 | H4: Note
A5: Total power(W) | B5: =IF($B$7=F$4,F5,G5) -> 1000000000 | E5: Total power(W) | F5: 1000000000 | G5: 1000000000
A6: PUE | B6: =IF($B$7=F$4,F6,G6) -> 1.2 | E6: PUE | F6: 1.2 | G6: 1.2
A7: Rack Type | B7: Vera Rubin NVL72 | E7: Rack Type | F7: Vera Rubin NVL72 | G7: GB200 NVL72
A8: No.of racks | B8: =IF($B$7=F$4,F8,G8) -> 5263 | C8: Derived: FLOOR(IT Power / Power per Rack) | E8: No.of racks | F8: =FLOOR(F5/1000/F23,1) -> 5263 | G8: =FLOOR(G5/1000/G23,1) -> 7194 | H8: Derived: FLOOR(Total Power / Power per Rack)
A10: Rack Spec. | B10: Data | C10: Note | E10: Rack Spec. | F10: Vera Rubin NVL72 | G10: GB200 NVL72 | H10: Note
A11: CPU Type | B11: =IF($B$7=F$4,F11,G11) -> Vera CPU | E11: CPU Type | F11: Vera CPU | G11: Grace CPU
A12: No. of CPU | B12: =IF($B$7=F$4,F12,G12) -> 36 | E12: No. of CPU | F12: 36 | G12: 36
A13: GPU Type | B13: =IF($B$7=F$4,F13,G13) -> Rubin GPU | E13: GPU Type | F13: Rubin GPU | G13: Blackwell B200
A14: No. of GPU | B14: =IF($B$7=F$4,F14,G14) -> 72 | C14: per rack | E14: No. of GPU | F14: 72 | G14: 72
A15: NVLink Bandwidth(TB/s) | B15: =IF($B$7=F$4,F15,G15) -> 260 | C15: total per rack | E15: NVLink BW(TB/s) | F15: 260 | G15: 130 | H15: Total per rack
A16: NVLink-C2C Bandwidth(TB/s) | B16: =IF($B$7=F$4,F16,G16) -> 65 | E16: NVLink-C2C BW(TB/s) | F16: 65 | G16: 32.4 | H16: 0.9 TB/s * 36 CPUs
A17: GPU Memory(TB) | B17: =IF($B$7=F$4,F17,G17) -> 20.7 | C17: 0.288/GPU | E17: GPU Memory(TB) | F17: 20.7 | G17: 13.5 | H17: Total per rack (0.1875/GPU for GB200)
A18: Memory Bandwidth(TB) | B18: =IF($B$7=F$4,F18,G18) -> 1580 | C18: 22/GPU | E18: Memory BW(TB) | F18: 1580 | G18: 576 | H18: Total per rack (8/GPU for GB200)
A19: FP4 Dense Inference(PFLOPS) | B19: =IF($B$7=F$4,F19,G19) -> 3600 | C19: 50/GPU | E19: FP4 Dense Inference(PFLOPS) | F19: 3600 | G19: 648 | H19: 50/GPU Rubin = 3600; 9/GPU B200 (dense, no sparsity). Fixed from 2520 (was using 35/GPU training value).
A20: FP4 Dense Training(PFLOPS) | B20: =IF($B$7=F$4,F20,G20) -> 2520 | C20: 35/GPU | E20: FP4 Dense Training(PFLOPS) | F20: 2520 | G20: 648 | H20: Same as inference for dense (sparsity only boosts inference marketing)
A21: FP8 Dense(PFLOPS) | B21: =IF($B$7=F$4,F21,G21) -> 1260 | C21: 17.5/GPU | E21: FP8 Dense(PFLOPS) | F21: 1260 | G21: 324 | H21: 16/GPU Rubin; 4.5/GPU B200 (dense)
A22: FP16/BF16 Dense(PFLOPS) | B22: =IF($B$7=F$4,F22,G22) -> 288 | C22: 4/GPU | E22: FP16/BF16 Dense(PFLOPS) | F22: 288 | G22: 162 | H22: 3.6/GPU Rubin; 2.25/GPU B200 (dense)
A23: Power per Rack (kW) | B23: =IF($B$7=F$4,F23,G23) -> 190 | C23: IT power draw per rack | E23: Power/Rack (kW) | F23: 190 | G23: 139 | H23: IT power only (excl. PUE overhead)
A24: Rack Price ($) | B24: =IF($B$7=F$4,F27,G27) -> 6000000 | C24: Auto-filled from dropdown; edit preset in F26/G26
A26: ▶ KEY INPUTS — Model & Tokens | B26: Data | C26: Note | E26: Pricing | F26: Vera Rubin NVL72 | G26: GB200 NVL72 | H26: Note
A27: Input Tokens | B27: 4000 | C27: ← Change this | E27: Rack Price ($) | F27: 6000000 | G27: 3000000 | H27: Est. $3M GB200; Rubin ~$6M (15-20% premium)
A28: Output Tokens | B28: =B27/4 -> 1000 | C28: ← Change this
E29: ▶ MARKET PRICING TIERS (Mar 2026)
A30: Model Spec. | B30: Data | C30: Note | E30: Auto-selects pricing based on model parameters (Column B30)
A31: Parameters | B31: 1000000000000 | C31: ← Change this (e.g. 500B, 1T, 1.5T) | E31: Tier | F31: Param Threshold | G31: Input $/M | H31: Output $/M
A32: Type | B32: Dense | E32: Nano (<50B) | F32: 0 | G32: 0.1 | H32: 0.4
A33: vocab size(V) | B33: 128000 | E33: Small (50B–200B) | F33: 50000000000 | G33: 0.25 | H33: 2
A34: Hidden Dimension(d_model) | B34: =IF(B31<100000000,B31^(1/4),2^11*10^LOG((B31/10^11))) -> 20480 | C34: Given or adjust for model size | E34: Mid (200B–500B) | F34: 200000000000 | G34: 1.25 | H34: 10
A35: n_layers | B35: 128 | C35: Given or adjust for model size | E35: Frontier (500B–1.5T) | F35: 500000000000 | G35: 2.5 | H35: 10
A36: n_heads | B36: 160 | E36: Premium (>1.5T) | F36: 1500000000000 | G36: 5 | H36: 25
A37: d_head | B37: =B34/B36 -> 128 | C37: d_model / n_heads
A38: d_ff(SwiGLU) | B38: =(B31/B35-4*B34^2)/(3*B34) -> 99849.909 | C38: derived from Parameters = n_layers × (4×d² + 3×d×d_ff) | E38: Sources: | F38: GPT-5 $1.25/$10, GPT-4o $2.50/$10, Opus 4.6 $5/$25, Haiku $1/$5, GPT-5 Nano $0.05/$0.40
A39: Parameters per Layer(Att) | B39: =4*B34^2 -> 1677721600 | C39: Q_W+K_W+V_W+O_W = 4×d_model²
A40: Parameters per Layer(FFN) | B40: =3*B34*B38 -> 6134778400 | C40: 3 × d_model × d_ff | E40: ▶ AUTO-SELECTED PRICING (from B30)
A41: Total Parameters per Layer | B41: =B39+B40 -> 7812500000 | E41: Matched Tier | F41: {=INDEX(E32:E36,MATCH(B31,F32:F36,1))} -> Frontier (500B–1.5T) | H41: Based on Config!B30 parameters
A42: MFU | B42: 0.5 | C42: Model FLOPS Utilization | E42: Input Price ($/M tokens) | F42: {=INDEX(G32:G36,MATCH(B31,F32:F36,1))} -> 2.5
A43: Precision | B43: FP8 | C43: ← Select: FP4, FP8, or FP16 | E43: Output Price ($/M tokens) | F43: {=INDEX(H32:H36,MATCH(B31,F32:F36,1))} -> 10
A44: Bytes per Parameter | B44: =IF(B43="FP4",0.5,IF(B43="FP8",1,IF(B43="FP16",2,"ERR"))) -> 1 | C44: FP4=0.5B, FP8=1B, FP16=2B
A45: Inference PFLOPS (rack) | B45: =IF(B43="FP4",B19,IF(B43="FP8",B21,IF(B43="FP16",B22,"ERR"))) -> 1260 | C45: Auto-selected from rack spec based on precision
A47: Parallelism Strategy | B47: Data | C47: Note
A48: Tensor Parallelism (TP) | B48: 72
A50: ▶ Optimization Parameters | B50: Data | C50: Note
A51: GQA KV heads | B51: 8 | C51: 160→8, 20:1 ratio
A52: Batch Size / tokens per step | B52: 64 | C52: bounded by HBM Size
A53: Speculation window: N | B53: 8 | C53: tokens generated per step
A54: Acceptance rate: a | B54: 0.7
A55: Expected Tokens Accepted | B55: =(1-B54^(B53+1))/(1-B54) -> 3.1988213 | C55: (1-a^(N+1))/(1-a)
A56: NVLink SHARP reduction | B56: 0.5 | C56: SHARP in-network traffic reduction
A57: NVLink time per token with SHARP (s) | B57: 0.0005 | C57: Override: 0.00128×0.5≈0.0005 (partially overlapped)
A58: Compute-Communication Overlap efficiency | B58: 0.5 | C58: 50% of NVLink hidden behind compute
A59: New TP degree (for PP split) | B59: 36 | C59: Split into PP stages × TP GPUs
A60: PP stages | B60: =B14/B59 -> 2 | C60: No. of GPU / New TP degree
A62: Derived Memory Check | B62: Data | C62: Note
A63: Weight Memory(Byte) | B63: =B31*B44 -> 1000000000000 | C63: Parameters × Bytes per Parameter (from Precision)

Sheet TL_Param
B1: Base Line
A2: # | B2: Step(time in s) | C2: Start Time | D2: Duration | E2: End Time | F2: Compute Time | G2: HBM BW Time | H2: NVLink Time | I2: Bottleneck | J2: Dominant Resource | K2: FLOPs Used | L2: HBM Bytes Moved
A3: 1 | B3: Tokenization (CPU) | C3: 0 | D3: 0.05 | E3: =C3+D3 -> 0.05 | F3: N/A(CPU) | G3: N/A | H3: N/A | I3: CPU | J3: CPU | K3: 0 | L3: 0
A4: 2 | B4: Embedding Lookup + Broadcast | C4: =E3 -> 0.05 | D4: =G4+H4 -> 0.0010016591 | E4: =C4+D4 -> 0.051001659 | F4: 0 | G4: =WP_Param!B28*WP_Param!B29/(WP_Param!B15*1000000000000) -> 1.6591392e-06 | H4: 0.001 | I4: Memory | J4: HBM BW | K4: 0 | L4: =WP_Param!B22*WP_Param!B29+WP_Param!B28*WP_Param!B29 -> 2703360000
A5: 3 | B5: Prefill+KV Cache Write | C5: =E4 -> 0.051001659 | D5: =F5+H5 -> 0.018691639 | E5: =C5+D5 -> 0.069693298 | F5: =WP_Param!B70 -> 0.012964801 | G5: =WP_Param!B87 -> 0.00068600385 | H5: =WP_Param!B97 -> 0.0057268382 | I5: Compute | J5: GPU | K5: =WP_Param!B65 -> 8.1678246e+15 | L5: =WP_Param!B84 -> 1083886080000
A6: 4 | B6: Decode-First Token | C6: =E5 -> 0.069693298 | D6: =G6 -> 0.001147847 | E6: =C6+D6 -> 0.070841145 | F6: =WP_Param!B121 -> 1.6247507e-06 | G6: =WP_Param!B151 -> 0.001147847 | H6: - | I6: Memory | J6: HBM BW | K6: =WP_Param!B117 -> 2047185920000 | L6: =WP_Param!B135 -> 1023598202880
A7: 5 | B7: Decode-All Tokens | C7: =E6 -> 0.070841145 | D7: =G7+H7 -> 1.147847 | E7: =C7+D7 -> 1.2186881 | F7: =WP_Param!B122 -> 0.0016247507 | G7: =WP_Param!B138*WP_Param!B23 -> 0.64784696 | H7: =WP_Param!B149*WP_Param!B23 -> 0.5 | I7: Memory | J7: HBM BW | K7: =WP_Param!B118 -> 2.0471859e+15 | L7: =WP_Param!B135*WP_Param!B23 -> 1.0235982e+15
A8: 6 | B8: De-tokenization (CPU) | C8: =E7 -> 1.2186881 | D8: 0.05 | E8: =C8+D8 -> 1.2686881 | F8: N/A(CPU) | G8: N/A | H8: N/A | I8: CPU | J8: CPU | K8: 0 | L8: 0
B9: Avg Time per Output Token (s) | E9: =E8/WP_Param!B23 -> 0.0012686881
B10: Total Output Token(s)/second | E10: =1/E9 -> 788.21579
B13: Optimized-GQA + Concurrent Requests - Batch Size + Speculative Decoding
A14: # | B14: Step(time in s) | C14: Start Time | D14: Duration | E14: End Time | F14: Compute Time | G14: HBM BW Time | H14: NVLink Time | I14: Bottleneck | J14: Dominant Resource | K14: FLOPs Used | L14: HBM Bytes Moved
A15: 1 | B15: Tokenization (CPU) | C15: 0 | D15: 0.05 | E15: =C15+D15 -> 0.05 | F15: N/A(CPU) | G15: N/A | H15: N/A | I15: CPU | J15: CPU | K15: 0 | L15: 0
A16: 2 | B16: Embedding Lookup + Broadcast | C16: =E15 -> 0.05 | D16: =G16+H16 -> 2.9019427e-06 | E16: =C16+D16 -> 0.050002902 | F16: 0 | G16: =WP_Param!B28*WP_Param!B29/(WP_Param!B15*1000000000000) -> 1.6591392e-06 | H16: =2*WP_Param!B22*WP_Param!B29*2*(71/72)/(WP_Param!B12*1000000000000) -> 1.2428034e-06 | I16: NVLink | J16: NVLink | K16: 0 | L16: =WP_Param!B22*WP_Param!B29+WP_Param!B28*WP_Param!B29 -> 2703360000
A17: 3 | B17: Prefill+KV Cache Write | C17: =E16 -> 0.050002902 | D17: =F17+H17 -> 1.1962649 | E17: =C17+D17 -> 1.2462678 | F17: =WP_Param!B70*WP_Param!B169 -> 0.82974726 | G17: =WP_Param!B87*WP_Param!B169 -> 0.043904246 | H17: =WP_Param!B97*WP_Param!B169 -> 0.36651764 | I17: Compute | J17: GPU | K17: =WP_Param!B65*WP_Param!B169 -> 5.2274077e+17 | L17: =WP_Param!B84*WP_Param!B169 -> 69368709120000
A18: 4 | B18: Decode-First Token | C18: =E17 -> 1.2462678 | D18: =G18 -> 0.00063365801 | E18: =C18+D18 -> 1.2469015 | F18: =WP_Param!B121 -> 1.6247507e-06 | G18: =WP_Param!B164 -> 0.00063365801 | H18: - | I18: Memory | J18: HBM BW | K18: =WP_Param!B117 -> 2047185920000 | L18: =WP_Param!B163 -> 1001179648000
A19: 5 | B19: Decode-All Tokens | C19: =E18 -> 1.2469015 | D19: =G19+H19 -> 1.1806946 | E19: =C19+D19 -> 2.4275961 | F19: =WP_Param!B122 -> 0.0016247507 | G19: =WP_Param!B172*WP_Param!B23*WP_Param!B169 -> 0.6806946 | H19: =WP_Param!B149*WP_Param!B23 -> 0.5 | I19: Memory | J19: HBM BW | K19: =WP_Param!B118 -> 2.0471859e+15 | L19: =WP_Param!B171*WP_Param!B23 -> 1.0754975e+15
A20: 6 | B20: De-tokenization (CPU) | C20: =E19 -> 2.4275961 | D20: 0.05 | E20: =C20+D20 -> 2.4775961 | F20: N/A(CPU) | G20: N/A | H20: N/A | I20: CPU | J20: CPU | K20: 0 | L20: 0
B21: Avg Time per Output Token (s) | E21: =E20/(WP_Param!B169*WP_Param!B23) -> 3.8712439e-05 | G21: E2E / (Batch * Output)
B22: Total Output Token(s)/second | E22: =1/E21 -> 25831.491
B25: Optimized-GQA + Concurrent Requests - Batch Size + Speculative Decoding + NVLink Optimization | N25: Rack-Independent Latency Outputs
A26: # | B26: Step(time in s) | C26: Start Time | D26: Duration | E26: End Time | F26: Compute Time | G26: HBM BW Time | H26: NVLink Time | I26: Bottleneck | J26: Dominant Resource | K26: FLOPs Used | L26: HBM Bytes Moved | N26: VR NVL72 E2E (s) | O26: GB200 NVL72 E2E (s)
A27: 1 | B27: Tokenization (CPU) | C27: 0 | D27: 0.05 | E27: =C27+D27 -> 0.05 | F27: N/A(CPU) | G27: N/A | H27: N/A | I27: CPU | J27: CPU | K27: 0 | L27: 0 | N27: =D27 -> 0.05 | O27: =D27 -> 0.05
A28: 2 | B28: Embedding Lookup + Broadcast | C28: =E27 -> 0.05 | D28: =G28+H28 -> 2.9019427e-06 | E28: =C28+D28 -> 0.050002902 | F28: 0 | G28: =WP_Param!B28*WP_Param!B29/(WP_Param!B15*1000000000000) -> 1.6591392e-06 | H28: =2*WP_Param!B22*WP_Param!B29*2*(71/72)/(WP_Param!B12*1000000000000) -> 1.2428034e-06 | I28: NVLink | J28: NVLink | K28: 0 | L28: =WP_Param!B22*WP_Param!B29+WP_Param!B28*WP_Param!B29 -> 2703360000 | N28: =IF(Config!B7="Vera Rubin NVL72", D28, G28*(Config!G18/Config!F18) + H28*(Config!G15/Config!F15)) -> 2.9019427e-06 | O28: =IF(Config!B7="Vera Rubin NVL72", G28*(Config!F18/Config!G18) + H28*(Config!F15/Config!G15), D28) -> 7.0367179e-06
A29: 3 | B29: Prefill+KV Cache Write | C29: =E28 -> 0.050002902 | D29: =F29+H29 -> 1.1962649 | E29: =C29+D29 -> 1.2462678 | F29: =WP_Param!B70*WP_Param!B169 -> 0.82974726 | G29: =WP_Param!B87*WP_Param!B169 -> 0.043904246 | H29: =WP_Param!B97*WP_Param!B169 -> 0.36651764 | I29: Compute | J29: GPU | K29: =WP_Param!B65*WP_Param!B169 -> 5.2274077e+17 | L29: =WP_Param!B84*WP_Param!B169 -> 69368709120000 | N29: =IF(Config!B7="Vera Rubin NVL72", D29, F29*(IF(Config!B43="FP4",Config!G19,IF(Config!B43="FP8",Config!G21,Config!G22))/IF(Config!B43="FP4",Config!F19,IF(Config!B43="FP8",Config!F21,Config!F22))) + H29*(Config!G15/Config!F15)) -> 1.1962649 | O29: =IF(Config!B7="Vera Rubin NVL72", F29*(IF(Config!B43="FP4",Config!F19,IF(Config!B43="FP8",Config!F21,Config!F22))/IF(Config!B43="FP4",Config!G19,IF(Config!B43="FP8",Config!G21,Config!G22))) + H29*(Config!F15/Config!G15), D29) -> 3.9598302
A30: 4 | B30: Decode-First Token | C30: =E29 -> 1.2462678 | D30: =G30 -> 0.00063365801 | E30: =C30+D30 -> 1.2469015 | F30: =WP_Param!B121 -> 1.6247507e-06 | G30: =WP_Param!B164 -> 0.00063365801 | H30: - | I30: Memory | J30: HBM BW | K30: =WP_Param!B117 -> 2047185920000 | L30: =WP_Param!B163 -> 1001179648000 | N30: =IF(Config!B7="Vera Rubin NVL72", D30, G30*(Config!G18/Config!F18)) -> 0.00063365801 | O30: =IF(Config!B7="Vera Rubin NVL72", G30*(Config!F18/Config!G18), D30) -> 0.0017381591
A31: 5 | B31: Decode-All Tokens | C31: =E30 -> 1.2469015 | D31: =G31+H31 -> 0.68140037 | E31: =C31+D31 -> 1.9283018 | F31: =WP_Param!B122 -> 0.0016247507 | G31: =WP_Param!B172*WP_Param!B23*WP_Param!B169 -> 0.6806946 | H31: =WP_Param!B206 -> 0.00070577231 | I31: Memory | J31: HBM BW | K31: =WP_Param!B118 -> 2.0471859e+15 | L31: =WP_Param!B171*WP_Param!B23 -> 1.0754975e+15 | N31: =IF(Config!B7="Vera Rubin NVL72", D31, G31*(Config!G18/Config!F18) + H31*(Config!G15/Config!F15)) -> 0.68140037 | O31: =IF(Config!B7="Vera Rubin NVL72", G31*(Config!F18/Config!G18) + H31*(Config!F15/Config!G15), D31) -> 1.8685947
A32: 6 | B32: De-tokenization (CPU) | C32: =E31 -> 1.9283018 | D32: 0.05 | E32: =C32+D32 -> 1.9783018 | F32: N/A(CPU) | G32: N/A | H32: N/A | I32: CPU | J32: CPU | K32: 0 | L32: 0 | N32: =D32 -> 0.05 | O32: =D32 -> 0.05
B33: Avg Time per Output Token (s) | E33: =E32/(WP_Param!B169*WP_Param!B23) -> 3.0910966e-05 | G33: E2E / (Batch * Output) | N33: =SUM(N27:N32)/(Config!B52*Config!B28) -> 3.0910966e-05 | O33: =SUM(O27:O32)/(Config!B52*Config!B28) -> 9.2658907e-05
B34: Total Output Token(s)/second | E34: =1/E33 -> 32350.978 | N34: =1/N33 -> 32350.978 | O34: =1/O33 -> 10792.271
N35: =SUM(N27:N31) -> 1.9283018 | O35: =SUM(O27:O31) -> 5.88017

Sheet WP_Param
A1: AI DC Spec. | B1: Data | C1: Note
A2: Total power(W) | B2: =Config!B5 -> 1000000000
A3: PUE | B3: =Config!B6 -> 1.2
A4: Rack Type | B4: =Config!B7 -> Vera Rubin NVL72
A5: No.of racks | B5: =Config!B8 -> 5263
A7: Rack Spec. | B7: Data | C7: Note
A8: CPU Type | B8: =Config!B11 -> Vera CPU
A9: No. of CPU | B9: =Config!B12 -> 36
A10: GPU Type | B10: =Config!B13 -> Rubin GPU
A11: No. of GPU | B11: =Config!B14 -> 72
A12: NVLink Bandwidth(TB/s) | B12: =Config!B15 -> 260
A13: NVLink-C2C Bandwidth(TB/s) | B13: =Config!B16 -> 65
A14: GPU Memory(TB) | B14: =Config!B17 -> 20.7 | C14: 0.288/GPU
A15: Memory Bandwidth(TB) | B15: =Config!B18 -> 1580 | C15: 22/GPU
A16: FP4 Dense Inference(PFLOPS) | B16: =Config!B19 -> 3600 | C16: 50/GPU
A17: FP4 Dense Training(PFLOPS) | B17: =Config!B20 -> 2520 | C17: 35/GPU
A18: FP8 Dense(PFLOPS) | B18: =Config!B21 -> 1260 | C18: 17.5/GPU
A19: FP16/BF16 Dense(PFLOPS) | B19: =Config!B22 -> 288 | C19: 4/GPU
A21: Input/Output Tokens Setup | B21: Data | C21: Note
A22: Input Tokens: | B22: =Config!B27 -> 4000
A23: Output Tokens: | B23: =Config!B28 -> 1000
A25: Model Spec. | B25: Data | C25: Note
A26: Parameters | B26: =Config!B31 -> 1000000000000 | C26: From Config sheet
A27: Type | B27: =Config!B32 -> Dense
A28: vocab size(V) | B28: =Config!B33 -> 128000
A29: Hidden Dimension(d_model) | B29: =Config!B34 -> 20480 | C29: Given
A30: n_layers | B30: =Config!B35 -> 128 | C30: Given
A31: n_heads | B31: =Config!B36 -> 160
A32: d_head | B32: =Config!B37 -> 128
A33: d_ff(SwiGLU) | B33: =Config!B38 -> 99849.909 | C33: derived from Parameters
A34: Parameters per Layer(Att) | B34: =Config!B39 -> 1677721600 | C34: Q_W+K_W+V_W+O_W=4*d_model^2
A35: Parameters per Layer(FFN) | B35: =Config!B40 -> 6134778400 | C35: 3 × d_model × d_ff
A36: Total Parameters per Layer | B36: =Config!B41 -> 7812500000
A37: Weight Memory(Byte) | B37: =B26*Config!B44 -> 1000000000000 | C37: Parameters × Bytes/param (from Config Precision)
A38: Weight Memory(Byte)/GPU | B38: =B37/B11 -> 1.3888889e+10
A39: KV cache @ Beginning(Byte) | B39: =2*B29*B22*B30 -> 20971520000 | C39: K=V=d_model*layer*no.of Input tokens, Total =K+V
A40: KV cache @ End(Byte) | B40: =2*B29*(B22+B23)*B30 -> 26214400000 | C40: K=V=d_model*layer*no.of (Input+Output tokens), Total =K+V
A41: KV cache per GPU @ End | B41: =B40/B11 -> 3.6408889e+08
A42: Memory required per GPU | B42: =B41+B38 -> 1.4252978e+10 | C42: Need additional memory for Activations
A43: GPU Memory Headroom | B43: =B14/B11*1000000000000-B42 -> 2.7324702e+11 | C43: Check if GPU has enough memory
A45: Parallelism Strategy
A46: Tensor Parallelism (TP) | B46: =Config!B47 -> Data
A48: Prefill Phase
A49: Prefill Flop Per Layer | B49: Data | C49: Note
A50: QKV Projections | B50: =2*B22*B29^2*3 -> 10066329600000 | C50: 2*Input*d_model^2*3
A51: Q × Kᵀ (Attention Scores) | B51: =2*B22^2*B29 -> 655360000000 | C51: 2*input*input*d_model
A52: Attention x V | B52: =2*B22^2*B29 -> 655360000000 | C52: 2*input*input*d_model
A53: Output Projection | B53: =2*B22*B29^2 -> 3355443200000 | C53: 2*Input*d_model^2
A54: FFN (SwiGLU, 3 matrices) | B54: =2*B22*B29*B33*3 -> 49078227200000 | C54: 2*input*d_model*d_ff*3
A55: Norms / Softmax / Activations | B55: =5*B22*B29 -> 409600000 | C55: ~O(input × d_model)~=5*input*d_model
A56: Total Prefill Flop Per Layer | B56: =SUM(B50:B55) -> 63811129600000
A58: Prefill Flop All Layers | B58: Data | C58: Note
A59: QKV Projections | B59: =B50*$B$30 -> 1.2884902e+15 | C59: =B59/$B$65 -> 0.15775194
A60: Q × Kᵀ (Attention Scores) | B60: =B51*$B$30 -> 83886080000000 | C60: =B60/$B$65 -> 0.010270309
A61: Attention x V | B61: =B52*$B$30 -> 83886080000000 | C61: =B61/$B$65 -> 0.010270309
A62: Output Projection | B62: =B53*$B$30 -> 429496729600000 | C62: =B62/$B$65 -> 0.052583981
A63: FFN (SwiGLU, 3 matrices) | B63: =B54*$B$30 -> 6.2820131e+15 | C63: =B63/$B$65 -> 0.76911704
A64: Norms / Softmax / Activations | B64: =B55*$B$30 -> 52428800000 | C64: =B64/$B$65 -> 6.4189429e-06
A65: Total Prefill Flop | B65: =SUM(B59:B64) -> 8.1678246e+15 | C65: =B65/$B$65 -> 1
A67: Prefill Compute Time(s) | B67: Data | C67: Note
A68: Prefill Compute Time(Theoretical) | B68: =B65/Config!B45/1000000000000000 -> 0.0064824005
A69: MFU | B69: =Config!B42 -> 0.5 | C69: model FLOPS utilization (MFU)
A70: Prefill Compute Time(50% MFU) | B70: =B68/B69 -> 0.012964801
A72: Prefill HBM Traffic per Layer (byte)
A73: model weights | B73: =Config!B44*(4*B29^2+3*B29*B33) -> 7812500000 | C73: Bytes/param × parameters per layer (from Config Precision)
A74: Activation reads/writes (intermediate tensors) | B74: =4*B22*B29 -> 327680000 | C74: ~4 activation tensors per layer: input*d_model
A75: KV cache write | B75: =2*B22*B31*B32 -> 163840000 | C75: 2(K,V)*(input)*n_head*d_head
A76: FlashAttention internal I/O | B76: =2*B22*B29 -> 163840000 | C76: O(input × d_model)~=2*input*d_model
A77: Prefill HBM Traffic Per Layer | B77: =SUM(B73:B76) -> 8467860000
A79: Prefill HBM Traffic All (byte)
A80: model weights | B80: =B73*$B$30 -> 1000000000000 | C80: =B80/$B$84 -> 0.92260618
A81: Activation reads/writes (intermediate tensors) | B81: =B74*$B$30 -> 41943040000 | C81: =B81/$B$84 -> 0.038696908
A82: KV cache write | B82: =B75*$B$30 -> 20971520000 | C82: =B82/$B$84 -> 0.019348454
A83: FlashAttention internal I/O | B83: =B76*$B$30 -> 20971520000 | C83: =B83/$B$84 -> 0.019348454
A84: Total Prefill HBM Traffic All | B84: =SUM(B80:B83) -> 1083886080000 | C84: =B84/$B$84 -> 1
A86: Prefill HBM Traffic Time(s)
A87: Prefill HBM Traffic Time(Theoretical) | B87: =B84/B15/1000000000000 -> 0.00068600385
A88: Arithmetic intensity check | B88: =B65/B84 -> 7535.6855 | C88: total Prefill flop/Total Prefill HBM Traffic(byte)>>797 roofline breakeven
A90: Prefill NVLink Communication (byte)
A91: all-reduce of the output activation size | B91: =B22*B29 -> 81920000 | C91: input*d_model
A92: Per all-reduce (ring-reduce) | B92: =2*(B11-1)/B11*B22*B29 -> 1.6156444e+08 | C92: 2*(no.of GPU-1)/(no. of GPU)*input*d_model
A93: Count per layer | B93: 2 | C93: all-reduces (one after attention output projection, one after FFN)
A94: Total per Layer | B94: =B92*B93 -> 3.2312889e+08 | C94: Per all-reduce * Count per layer
A95: Total NVLink Communication | B95: =B94*B30 -> 4.1360498e+10 | C95: Total per Layer*n_layers
A96: Total NVLink Communication Time(s) | B96: =B95/(B12/B11*1000000000000) -> 0.011453676 | C96: Total NVLink Communication/per-GPU NVLink BW
A97: NVLink Communication Time with Sharp(s) | B97: =B96*0.5 -> 0.0057268382 | C97: SHARP in-network reduction (up to 50% traffic reduction)
A99: Total Prefill Time | B99: =B70+B87+B97 -> 0.019377643 | C99: Compute Bound
A102: DECODE | C102: Avg context = input + output/2
A103: Decode Flop Per Layer | B103: Data | C103: Note
A104: QKV Projections (per tok) | B104: =2*1*B29^2*3 -> 2516582400 | C104: 2*1(1token)*d_model^2*3
A105: Q × Kᵀ (per tok, avg) | B105: =2*B29*(B22+0.5*B23) -> 184320000 | C105: 2*d_model*(input+output/2)
A106: Attention × V (per tok, avg) | B106: =2*B29*(B22+0.5*B23) -> 184320000 | C106: 2*d_model*(input+output/2)
A107: Output Projection (per tok) | B107: =2*1*B29^2 -> 838860800 | C107: 2*1(1token)*d_model^2
A108: FFN SwiGLU (per tok) | B108: =2*B29*B33*3 -> 12269556800 | C108: 2*d_model*d_ff*3
A109: DECODE per Layer (per tok avg) | B109: =SUM(B104:B108) -> 15993640000
A111: Decode Flop All Layers | B111: Data | C111: Note
A112: QKV Projections (per tok) | B112: =B104*$B$30 -> 322122547200 | C112: 2*1(1token)*d_model^2*3
A113: Q × Kᵀ (per tok, avg) | B113: =B105*$B$30 -> 23592960000 | C113: 2*d_model*(input+output/2)
A114: Attention × V (per tok, avg) | B114: =B106*$B$30 -> 23592960000 | C114: 2*d_model*(input+output/2)
A115: Output Projection (per tok) | B115: =B107*$B$30 -> 107374182400 | C115: 2*1(1token)*d_model^2
...

Sheet DC_Cost_Model
A1: Data Center Cost Model — 1 GW Vera Rubin NVL72 Facility
A3: Section 1: Data Center Specifications (from Config)
A4: Item | B4: Value | C4: Unit | E4: Source / Note
A5: Total IT Power | B5: =Config!B5/1000000 -> 1000 | C5: MW | E5: Linked from Config!B5
A6: PUE | B6: =Config!B6 -> 1.2 | E6: Linked from Config!B6
A7: Total Facility Power (IT × PUE) | B7: =B5*B6 -> 1200 | C7: MW | E7: Total electrical load including cooling, lighting, etc.
A8: Rack Type | B8: =Config!B7 -> Vera Rubin NVL72 | E8: Linked from Config!B7
A9: Number of Racks | B9: =Config!B8 -> 5263 | C9: racks | E9: Linked from Config!B8
A10: GPUs per Rack | B10: =Config!B14 -> 72 | C10: GPUs | E10: Linked from Config!B14
A11: Total GPUs | B11: =B9*B10 -> 378936 | C11: GPUs | E11: Racks × GPUs per rack
A12: Power per Rack (est.) | B12: =B5*1000/B9 -> 190.0057 | C12: kW | E12: Total IT Power / Racks
A13: Total Facility Sq. Ft. (est.) | B13: =B9*80 -> 421040 | C13: sq ft | E13: ~80 sq ft per rack (AI liquid-cooled, incl. aisles + support)
A15: Section 2: Capital Expenditure (CapEx) Breakdown
A16: Category | B16: Unit Cost | C16: Quantity / Basis | D16: Total ($M) | E16: Assumption / Source | F16: % of CapEx
A17: 2A. IT Hardware (Servers & GPUs)
A18: =" "&Config!B7&" Racks" -> Vera Rubin NVL72 Racks | B18: =Config!B24 -> 6000000 | C18: =B9 -> 5263 | D18: =B18*C18/1000000 -> 31578 | E18: Est. $3.5M/rack; GB200 NVL72 ~$3M, Rubin gen premium ~15-20% | F18: =D18/$D$54 -> 0.73039455
A19: Scale-out Networking (InfiniBand/Ethernet) | B19: 150000 | C19: =B9 -> 5263 | D19: =B19*C19/1000000 -> 789.45 | E19: Quantum-X800 IB + Spectrum-X Ethernet per-rack allocation | F19: =D19/$D$54 -> 0.018259864
A20: Top-of-Rack & Spine Switches | B20: 35000 | C20: =B9 -> 5263 | D20: =B20*C20/1000000 -> 184.205 | E20: Mgmt network, OOB, storage fabric per-rack allocation | F20: =D20/$D$54 -> 0.0042606349
A21: Storage & Boot Infrastructure | B21: 25000 | C21: =B9 -> 5263 | D21: =B21*C21/1000000 -> 131.575 | E21: NVMe boot drives, shared storage, cabling per rack | F21: =D21/$D$54 -> 0.0030433106
A22: Subtotal IT Hardware | D22: =SUM(D18:D21) -> 32683.23 | F22: =D22/$D$54 -> 0.75595836
A24: 2B. Land, Building & Site Work
A25: Land Acquisition (est. 100 acres) | B25: 200000 | C25: 100 | D25: =B25*C25/1000000 -> 20 | E25: ~100 acres; $200K/acre (semi-rural US, utility-adjacent) | F25: =D25/$D$54 -> 0.00046259709
A26: Building Shell & Core | B26: 3000000 | C26: =B7 -> 1200 | D26: =B26*C26/1000000 -> 3600 | E26: $3M/MW facility power; foundation, structure, envelope | F26: =D26/$D$54 -> 0.083267476
A27: Site Work & Civil (roads, grading, fencing) | B27: 500000 | C27: =B7 -> 1200 | D27: =B27*C27/1000000 -> 600 | E27: $500K/MW facility power; roads, grading, security fence | F27: =D27/$D$54 -> 0.013877913
A28: Subtotal Land & Building | D28: =SUM(D25:D27) -> 4220 | F28: =D28/$D$54 -> 0.097607986
A30: 2C. Electrical Infrastructure
A31: Substation & Grid Interconnection | B31: 1500000 | C31: =B7 -> 1200 | D31: =B31*C31/1000000 -> 1800 | E31: $1.5M/MW; HV substation, transformers, HV switchgear | F31: =D31/$D$54 -> 0.041633738
A32: Medium Voltage Distribution & PDUs | B32: 800000 | C32: =B7 -> 1200 | D32: =B32*C32/1000000 -> 960 | E32: $800K/MW; MV switchgear, busway, rack-level PDUs | F32: =D32/$D$54 -> 0.02220466
A33: Backup Generators (N+1 diesel/gas) | B33: 600000 | C33: =B7 -> 1200 | D33: =B33*C33/1000000 -> 720 | E33: $600K/MW; diesel/gas turbine gen-sets with N+1 redundancy | F33: =D33/$D$54 -> 0.016653495
A34: UPS & Battery Storage | B34: 400000 | C34: =B5 -> 1000 | D34: =B34*C34/1000000 -> 400 | E34: $400K/MW IT; UPS systems + Li-ion BESS for ride-through | F34: =D34/$D$54 -> 0.0092519418
A35: Subtotal Electrical | D35: =SUM(D31:D34) -> 3880 | F35: =D35/$D$54 -> 0.089743836
A37: 2D. Cooling & Mechanical Systems
A38: Liquid Cooling (CDUs, piping, cold plates) | B38: 56000 | C38: =B9 -> 5263 | D38: =B38*C38/1000000 -> 294.728 | E38: ~$56K/rack; Morgan Stanley est. cold plates + CDU piping | F38: =D38/$D$54 -> 0.0068170158
A39: Cooling Towers & Heat Rejection Plant | B39: 300000 | C39: =B7 -> 1200 | D39: =B39*C39/1000000 -> 360 | E39: $300K/MW; cooling towers, chillers, pumps, water treatment | F39: =D39/$D$54 -> 0.0083267476
A40: Fire Suppression & HVAC (non-IT areas) | B40: 100000 | C40: =B7 -> 1200 | D40: =B40*C40/1000000 -> 120 | E40: $100K/MW; clean agent suppression, office HVAC | F40: =D40/$D$54 -> 0.0027755825
A41: Subtotal Cooling & Mechanical | D41: =SUM(D38:D40) -> 774.728 | F41: =D41/$D$54 -> 0.017919346
A43: 2E. Fiber, Cabling & Security
A44: Fiber Optic & Structured Cabling | B44: 200000 | C44: =B7 -> 1200 | D44: =B44*C44/1000000 -> 240 | E44: $200K/MW; intra-campus dark fiber, cable trays, patch panels | F44: =D44/$D$54 -> 0.0055511651
A45: Physical Security & BMS | B45: 50000 | C45: =B7 -> 1200 | D45: =B45*C45/1000000 -> 60 | E45: $50K/MW; CCTV, access control, DCIM, BMS sensors | F45: =D45/$D$54 -> 0.0013877913
A46: Subtotal Fiber, Cabling & Security | D46: =SUM(D44:D45) -> 300 | F46: =D46/$D$54 -> 0.0069389564
A48: 2F. Soft Costs & Contingency
A49: Design, Engineering & Permitting | B49: 0.03 | C49: % of non-IT CapEx | D49: =B49*(D28+D35+D41+D46) -> 275.24184 | E49: 3% of facility CapEx; A&E, environmental, permits | F49: =D49/$D$54 -> 0.0063663037
A50: Project Management & Commissioning | B50: 0.02 | C50: % of non-IT CapEx | D50: =B50*(D28+D35+D41+D46) -> 183.49456 | E50: 2% of facility CapEx; PM, CxA, testing & validation | F50: =D50/$D$54 -> 0.0042442025
A51: Contingency | B51: 0.1 | C51: % of non-IT CapEx | D51: =B51*(D28+D35+D41+D46) -> 917.4728 | E51: 10% contingency on facility/infrastructure CapEx | F51: =D51/$D$54 -> 0.021221012
A52: Subtotal Soft Costs & Contingency | D52: =SUM(D49:D51) -> 1376.2092 | F52: =D52/$D$54 -> 0.031831519
A54: TOTAL CAPEX | D54: =D22+D28+D35+D41+D46+D52 -> 43234.167 | F54: 1
A56: CapEx Composition
A57: IT Hardware share | D57: =D22/D54 -> 0.75595836
A58: Facility Infrastructure share | D58: =(D28+D35+D41+D46)/D54 -> 0.21221012
A59: Soft Costs & Contingency share | D59: =D52/D54 -> 0.031831519
A60: CapEx per MW (IT) | D60: =D54/B5 -> 43.234167 | E60: $/MW of IT power
A61: CapEx per GPU | D61: =D54*1000000/B11 -> 114093.59 | E61: Total CapEx / Total GPUs
A63: Section 3: Annual Operating Expenditure (OpEx)
A64: Category | B64: Assumption | C64: Basis | D64: Annual ($M) | E64: Note / Source | F64: % of OpEx
A65: 3A. Depreciation (GAAP, Straight-Line)
A66: IT Hardware (servers, GPUs, networking) | B66: 5 | C66: years useful life | D66: =D22/B66 -> 6536.646 | E66: ASC 360; 5-yr life per hyperscaler practice (Meta, MSFT) | F66: =D66/$D$88 -> 0.70300298
A67: Building & Shell | B67: 30 | C67: years useful life | D67: =(D28-D25)/B67 -> 140 | E67: ASC 360; 30-yr life. Land ($20M) excluded — indefinite-lived asset per GAAP. | F67: =D67/$D$88 -> 0.015056715
A68: Electrical Infrastructure | B68: 20 | C68: years useful life | D68: =D35/B68 -> 194 | E68: ASC 360; 15-25yr for heavy electrical equipment | F68: =D68/$D$88 -> 0.020864305
A69: Cooling & Mechanical | B69: 15 | C69: years useful life | D69: =D41/B69 -> 51.648533 | E69: ASC 360; 10-20yr for HVAC/mechanical systems | F69: =D69/$D$88 -> 0.0055546947
A70: Fiber, Cabling & Security | B70: 10 | C70: years useful life | D70: =D46/B70 -> 30 | E70: ASC 360; 7-15yr for structured cabling/security | F70: =D70/$D$88 -> 0.003226439
A71: Subtotal Annual Depreciation | D71: =SUM(D66:D70) -> 6952.2945 | F71: =D71/$D$88 -> 0.74770513
A73: 3B. Electricity Cost
A74: Electricity Rate (blended) | B74: 0.06 | C74: $/kWh | E74: US industrial avg $0.05-0.08; PPA-negotiated rate
A75: Annual Energy (facility) | B75: =B7*8760 -> 10512000 | C75: MWh/year | E75: Facility MW × 8,760 hrs (100% utilization assumed)
A76: Annual Electricity Cost | D76: =B75*1000*B74/1000000 -> 630.72 | E76: MWh × 1000 kWh/MWh × $/kWh | F76: =D76/$D$88 -> 0.067832653
A77: Subtotal Electricity | D77: =D76 -> 630.72 | F77: =D77/$D$88 -> 0.067832653
A79: 3C. Maintenance & Operations
A80: IT Hardware Maintenance (spares, repair) | B80: 0.03 | C80: % of IT HW CapEx/yr | D80: =B80*D22 -> 980.4969 | E80: 3% of IT HW CapEx; GPU/NIC failures, spares pool | F80: =D80/$D$88 -> 0.10545045
A81: Facility Maintenance (MEP) | B81: 0.02 | C81: % of facility CapEx/yr | D81: =B81*(D28+D35+D41+D46) -> 183.49456 | E81: 2% of facility CapEx; preventive & corrective maintenance | F81: =D81/$D$88 -> 0.019734467
A82: Staff (DC ops, NOC, security, mgmt) | B82: 500 | C82: headcount (est.) | D82: =B82*150000/1000000 -> 75 | E82: 500 FTEs @ $150K avg loaded cost; ops, NOC, security | F82: =D82/$D$88 -> 0.0080660974
A83: Property Tax & Insurance | B83: 0.005 | C83: % of total CapEx/yr | D83: =B83*D54 -> 216.17084 | E83: 0.5% of total CapEx; property tax + all-risk insurance | F83: =D83/$D$88 -> 0.023248734
A84: Water & Consumables | B84: 50000 | C84: =B7 -> 1200 | D84: =B84*C84/1000000 -> 60 | E84: $50K/MW/yr; cooling water, chemicals, diesel fuel stores | F84: =D84/$D$88 -> 0.0064528779
A85: Software Licenses & Connectivity | B85: 200 | C85: $M/year | D85: 200 | E85: DCIM, NVIDIA AI Enterprise, WAN transit, peering | F85: =D85/$D$88 -> 0.021509593
A86: Subtotal Maintenance & Operations | D86: =SUM(D80:D85) -> 1715.1623 | F86: =D86/$D$88 -> 0.18446222
A88: TOTAL ANNUAL OPEX | D88: =D71+D77+D86 -> 9298.1768 | F88: 1
A90: OpEx Composition
A91: Depreciation share | D91: =D71/D88 -> 0.74770513
A92: Electricity share | D92: =D77/D88 -> 0.067832653
A93: Maintenance & Ops share | D93: =D86/D88 -> 0.18446222
A94: OpEx per GPU per year | D94: =D88*1000000/B11 -> 24537.592 | E94: Annual OpEx / Total GPUs
A97: Data Center Cost Model — 1 GW GB200 NVL72 Facility
A99: Section 1: Data Center Specifications (GB200 NVL72 Preset)
A100: Item | B100: Value | C100: Unit | E100: Source / Note
A101: Total IT Power | B101: =Config!G5/1000000 -> 1000 | C101: MW | E101: From Config GB200 NVL72 preset (Col G)
A102: PUE | B102: =Config!G6 -> 1.2 | E102: From Config GB200 NVL72 preset (Col G)
A103: Total Facility Power (IT × PUE) | B103: =B101*B102 -> 1200 | C103: MW | E103: Total electrical load including cooling, lighting, etc.
A104: Rack Type | B104: =Config!G7 -> GB200 NVL72 | E104: From Config GB200 NVL72 preset (Col G)
A105: Number of Racks | B105: =Config!G8 -> 7194 | C105: racks | E105: From Config GB200 NVL72 preset (Col G)
A106: GPUs per Rack | B106: =Config!G14 -> 72 | C106: GPUs | E106: From Config GB200 NVL72 preset (Col G)
A107: Total GPUs | B107: =B105*B106 -> 517968 | C107: GPUs | E107: Racks × GPUs per rack
A108: Power per Rack (est.) | B108: =B101*1000/B105 -> 139.00473 | C108: kW | E108: Total IT Power / Racks
A109: Total Facility Sq. Ft. (est.) | B109: =B105*80 -> 575520 | C109: sq ft | E109: ~80 sq ft per rack (AI liquid-cooled, incl. aisles + support)
A111: Section 2: Capital Expenditure (CapEx) Breakdown
F112: % of CapEx
A113: 2A. IT Hardware (Servers & GPUs) | B113: Unit Cost | C113: Quantity / Basis | D113: Total ($M) | E113: Assumption / Source
A114: =" "&Config!G7&" Racks" -> GB200 NVL72 Racks | B114: =Config!G27 -> 3000000 | C114: =B105 -> 7194 | D114: =B114*C114/1000000 -> 21582 | E114: Est. $3M/rack; GB200 NVL72 pricing per Config preset | F114: =D114/$D$150 -> 0.63912516
A115: Scale-out Networking (InfiniBand/Ethernet) | B115: 150000 | C115: =B105 -> 7194 | D115: =B115*C115/1000000 -> 1079.1 | E115: Quantum-2 IB + Spectrum-X Ethernet per-rack allocation | F115: =D115/$D$150 -> 0.031956258
A116: Top-of-Rack & Spine Switches | B116: 35000 | C116: =B105 -> 7194 | D116: =B116*C116/1000000 -> 251.79 | E116: Mgmt network, OOB, storage fabric per-rack allocation | F116: =D116/$D$150 -> 0.0074564602
A117: Storage & Boot Infrastructure | B117: 25000 | C117: =B105 -> 7194 | D117: =B117*C117/1000000 -> 179.85 | E117: NVMe boot drives, shared storage, cabling per rack | F117: =D117/$D$150 -> 0.005326043
A118: Subtotal IT Hardware | D118: =SUM(D114:D117) -> 23092.74 | F118: =D118/$D$150 -> 0.68386393
...

Sheet Revenue_Model
A1: Token Generation & Revenue Model — 1 GW Vera Rubin NVL72 Inference Facility
A3: Section 1: Inference Configuration (per Rack) — from Config
A4: Parameter | B4: Value | C4: Unit | E4: Source / Note
A5: Model Parameters | B5: =Config!B31 -> 1000000000000 | C5: params | E5: Linked from Config!B30
A6: Input Tokens per Request | B6: =Config!B27 -> 4000 | C6: tokens | E6: Linked from Config!B26
A7: Output Tokens per Request | B7: =Config!B28 -> 1000 | C7: tokens | E7: Linked from Config!B27
A8: Total Tokens per Request | B8: =B6+B7 -> 5000 | C8: tokens | E8: Input + Output
A9: Batch Size (concurrent requests) | B9: =Config!B52 -> 64 | C9: requests | E9: Linked from Config!B48
A10: Speculative Decoding Gain | B10: =Config!B55 -> 3.1988213 | C10: tokens/step | E10: Expected tokens accepted per step, Config!B51
A11: End-to-End Latency per Request (optimized) | B11: =TL_Param!N35 -> 1.9283018 | C11: seconds | E11: From TL_Param!N35 (VR-specific, dropdown-independent)
A12: Number of Racks | B12: =Config!F8 -> 5263 | C12: racks | E12: Config!F8 (VR rack count, dropdown-independent)
A13: GPU Utilization Rate | B13: 0.7 | E13: Realistic + lean overhead; accounts for maintenance, failures, model swap
A14: Uptime (scheduled) | B14: 0.995 | E14: 99.5% SLA; ~43.8 hrs downtime/year
A15: Effective Annual Seconds per Rack | B15: =8760*3600*B13*B14 -> 21964824 | C15: seconds/yr | E15: 8,760 hrs × 3,600 s/hr × utilization × uptime
A16: Requests per Rack per Year | B16: =FLOOR(B15/B11,1)*B9 -> 729008640 | C16: requests/yr | E16: (Effective seconds / Latency) × Batch Size
A18: Section 2: Annual Token Throughput (Entire DC)
A19: Metric | B19: Value | C19: Unit | E19: Calculation
A20: Total Requests per Year (all racks) | B20: =B16*B12 -> 3836772472320 | C20: requests/yr | E20: Requests/rack/yr × racks
A21: Annual Input Tokens | B21: =B20*B6 -> 1.534709e+16 | C21: tokens/yr | E21: Total requests × input tokens/request
A22: Annual Output Tokens | B22: =B20*B7 -> 3.8367725e+15 | C22: tokens/yr | E22: Total requests × output tokens/request
A23: Annual Total Tokens | B23: =B21+B22 -> 1.9183862e+16 | C23: tokens/yr | E23: Input + Output
A24: Annual Total Tokens (M) | B24: =B23/1000000 -> 1.9183862e+10 | C24: M tokens/yr | E24: Total / 1,000,000
A25: Annual Input Tokens (M) | B25: =B21/1000000 -> 1.534709e+10 | C25: M tokens/yr
A26: Annual Output Tokens (M) | B26: =B22/1000000 -> 3.8367725e+09 | C26: M tokens/yr
A27: Tokens per Second (DC-wide) | B27: =B23/(8760*3600) -> 6.0831628e+08 | C27: tokens/sec | E27: Annual tokens / seconds per year (gross throughput)
A28: Requests per Second (DC-wide) | B28: =B20/(8760*3600) -> 121663.26 | C28: req/sec | E28: Annual requests / seconds per year
A30: Section 3: Market Pricing & Annual Revenue
A31: Pricing Tier | B31: Value | C31: Unit | E31: Source / Note
A32: Market Rate — Input Tokens | B32: =Config!F42 -> 2.5 | C32: $/M input tokens | E32: Auto-selected from Config pricing tiers based on model size
A33: Market Rate — Output Tokens | B33: =Config!F43 -> 10 | C33: $/M output tokens | E33: Auto-selected from Config pricing tiers based on model size
A34: Blended Rate (weighted by I/O mix) | B34: =(B32*B25+B33*B26)/(B25+B26) -> 4 | C34: $/M tokens | E34: (Input rev + Output rev) / Total M tokens
A36: Revenue Calculation
A37: Annual Input Token Revenue | B37: =B25*B32/1000000 -> 38367.725 | C37: $M/year | E37: Input M tokens × $/M input
A38: Annual Output Token Revenue | B38: =B26*B33/1000000 -> 38367.725 | C38: $M/year | E38: Output M tokens × $/M output
A39: TOTAL ANNUAL REVENUE | B39: =B37+B38 -> 76735.449 | C39: $M/year
A41: Revenue Composition
A42: Input token revenue share | B42: =B37/B39 -> 0.5
A43: Output token revenue share | B43: =B38/B39 -> 0.5
A44: Revenue per rack per year | B44: =B39/B12*1000000 -> 14580173 | C44: $/rack/yr
A46: Rrevenue to opex | B46: =B39/DC_Cost_Model!D88 -> 8.2527415
A47: Cost per Mtok | B47: =B34/B46 -> 0.48468742
A49: Token Generation & Revenue Model — 1 GW GB200 NVL72 Inference Facility
A51: Section 1: Inference Configuration (per Rack) — from Config
A52: Parameter | B52: Value | C52: Unit | E52: Source / Note
A53: Model Parameters | B53: =Config!B31 -> 1000000000000 | C53: params | E53: Linked from Config!B30
A54: Input Tokens per Request | B54: =Config!B27 -> 4000 | C54: tokens | E54: Linked from Config!B26
A55: Output Tokens per Request | B55: =Config!B28 -> 1000 | C55: tokens | E55: Linked from Config!B27
A56: Total Tokens per Request | B56: =B54+B55 -> 5000 | C56: tokens | E56: Input + Output
A57: Batch Size (concurrent requests) | B57: =Config!B52 -> 64 | C57: requests | E57: Linked from Config!B48
A58: Speculative Decoding Gain | B58: =Config!B55 -> 3.1988213 | C58: tokens/step | E58: Expected tokens accepted per step, Config!B51
A59: End-to-End Latency per Request (optimized) | B59: =TL_Param!O35 -> 5.88017 | C59: seconds | E59: From TL_Param!O35 (GB200-specific, dropdown-independent)
A60: Number of Racks | B60: =Config!G8 -> 7194 | C60: racks | E60: Config!G8 (GB200 rack count, dropdown-independent)
A61: GPU Utilization Rate | B61: 0.7 | E61: Realistic + lean overhead; accounts for maintenance, failures, model swap
A62: Uptime (scheduled) | B62: 0.995 | E62: 99.5% SLA; ~43.8 hrs downtime/year
A63: Effective Annual Seconds per Rack | B63: =8760*3600*B61*B62 -> 21964824 | C63: seconds/yr | E63: 8,760 hrs × 3,600 s/hr × utilization × uptime
A64: Requests per Rack per Year | B64: =FLOOR(B63/B59,1)*B57 -> 239065984 | C64: requests/yr | E64: (Effective seconds / Latency) × Batch Size
A66: Section 2: Annual Token Throughput (Entire DC)
A67: Metric | B67: Value | C67: Unit | E67: Calculation
A68: Total Requests per Year (all racks) | B68: =B64*B60 -> 1719840688896 | C68: requests/yr | E68: Requests/rack/yr × racks
A69: Annual Input Tokens | B69: =B68*B54 -> 6.8793628e+15 | C69: tokens/yr | E69: Total requests × input tokens/request
A70: Annual Output Tokens | B70: =B68*B55 -> 1.7198407e+15 | C70: tokens/yr | E70: Total requests × output tokens/request
A71: Annual Total Tokens | B71: =B69+B70 -> 8.5992034e+15 | C71: tokens/yr | E71: Input + Output
A72: Annual Total Tokens (M) | B72: =B71/1000000 -> 8.5992034e+09 | C72: M tokens/yr | E72: Total / 1,000,000
A73: Annual Input Tokens (M) | B73: =B69/1000000 -> 6.8793628e+09 | C73: M tokens/yr
A74: Annual Output Tokens (M) | B74: =B70/1000000 -> 1.7198407e+09 | C74: M tokens/yr
A75: Tokens per Second (DC-wide) | B75: =B71/(8760*3600) -> 2.7267895e+08 | C75: tokens/sec | E75: Annual tokens / seconds per year (gross throughput)
A76: Requests per Second (DC-wide) | B76: =B68/(8760*3600) -> 54535.79 | C76: req/sec | E76: Annual requests / seconds per year
A78: Section 3: Market Pricing & Annual Revenue
A79: Pricing Tier | B79: Value | C79: Unit | E79: Source / Note
A80: Market Rate — Input Tokens | B80: =Config!F42 -> 2.5 | C80: $/M input tokens | E80: Auto-selected from Config pricing tiers based on model size
A81: Market Rate — Output Tokens | B81: =Config!F43 -> 10 | C81: $/M output tokens | E81: Auto-selected from Config pricing tiers based on model size
A82: Blended Rate (weighted by I/O mix) | B82: =(B80*B73+B81*B74)/(B73+B74) -> 4 | C82: $/M tokens | E82: (Input rev + Output rev) / Total M tokens
A84: Revenue Calculation
A85: Annual Input Token Revenue | B85: =B73*B80/1000000 -> 17198.407 | C85: $M/year | E85: Input M tokens × $/M input
A86: Annual Output Token Revenue | B86: =B74*B81/1000000 -> 17198.407 | C86: $M/year | E86: Output M tokens × $/M output
A87: TOTAL ANNUAL REVENUE | B87: =B85+B86 -> 34396.814 | C87: $M/year
A89: Revenue Composition
A90: Input token revenue share | B90: =B85/B87 -> 0.5
A91: Output token revenue share | B91: =B86/B87 -> 0.5
A92: Revenue per rack per year | B92: =B87/B60*1000000 -> 4781319.7 | C92: $/rack/yr
A94: Rrevenue to opex | B94: =B87/DC_Cost_Model!D184 -> 4.8759339
A95: Cost per Mtok | B95: =B82/B94 -> 0.82035566

Sheet Graph&Table
A1: (1GW, mn USD) | B1: Capex | C1: Opex | D1: Revenue(理論)
A2: VR NVL72 | B2: =DC_Cost_Model!D54 -> 43234.167 | C2: =DC_Cost_Model!D88 -> 9298.1768 | D2: =Revenue_Model!B39 -> 76735.449 | E2: =D2/C2 -> 8.2527415 | H2: =D2/D3 -> 2.2308883
A3: GB200 NVL 72 | B3: =DC_Cost_Model!D150 -> 33768.034 | C3: =DC_Cost_Model!D184 -> 7054.4052 | D3: =Revenue_Model!B87 -> 34396.814 | E3: =D3/C3 -> 4.8759339 | F3: =E2/E3 -> 1.6925458
E4: =1-1/E2 -> 0.87882814
E5: =1-1/E3 -> 0.79491108 | F5: =E4/E5 -> 1.1055679
A8: Metric | B8: 2025A | C8: 2026E | D8: 2027E | E8: 2028E | F8: 2029E | G8: 2030E
A9: Revenue ($B) | B9: =OpenAI_Sim!C652 -> 13.1 | C9: =OpenAI_Sim!D652 -> 32.75 | D9: =OpenAI_Sim!E652 -> 60.5875 | E9: =OpenAI_Sim!F652 -> 112.08688 | F9: =OpenAI_Sim!G652 -> 179.339 | G9: =OpenAI_Sim!H652 -> 286.9424
A10: YoY Revenue Growth | B10: =OpenAI_Sim!C653 -> 2.5405405 | C10: =OpenAI_Sim!D653 -> 1.5 | D10: =OpenAI_Sim!E653 -> 0.85 | E10: =OpenAI_Sim!F653 -> 0.85 | F10: =OpenAI_Sim!G653 -> 0.6 | G10: =OpenAI_Sim!H653 -> 0.6
A11: Total Customers (M) | B11: =OpenAI_Sim!C654 -> 622.5 | C11: =OpenAI_Sim!D654 -> 1158.5 | D11: =OpenAI_Sim!E654 -> 1599.5 | E11: =OpenAI_Sim!F654 -> 2484 | F11: =OpenAI_Sim!G654 -> 2787 | G11: =OpenAI_Sim!H654 -> 3120
A12: Paid Subscribers (M) | B12: =OpenAI_Sim!C655 -> 21.8 | C12: =OpenAI_Sim!D655 -> 58.5 | D12: =OpenAI_Sim!E655 -> 99.5 | E12: =OpenAI_Sim!F655 -> 184 | F12: =OpenAI_Sim!G655 -> 237 | G12: =OpenAI_Sim!H655 -> 320
A13: Free-to-Paid Conversion Rate | B13: =OpenAI_Sim!C656 -> 0.03502008 | C13: =OpenAI_Sim!D656 -> 0.050496331 | D13: =OpenAI_Sim!E656 -> 0.06220694 | E13: =OpenAI_Sim!F656 -> 0.074074074 | F13: =OpenAI_Sim!G656 -> 0.085037675 | G13: =OpenAI_Sim!H656 -> 0.1025641
A14: Total Customers tokens(Mtok) | B14: =OpenAI_Sim!C657 -> 1355706725 | C14: =OpenAI_Sim!D657 -> 4708500000 | D14: =OpenAI_Sim!E657 -> 8628600000 | E14: =OpenAI_Sim!F657 -> 16727950000 | F14: =OpenAI_Sim!G657 -> 28561250000 | G14: =OpenAI_Sim!H657 -> 44457000000
A15: tok/customer/day | B15: =OpenAI_Sim!C658 -> 5966.6908 | C15: =OpenAI_Sim!D658 -> 11135.088 | D15: =OpenAI_Sim!E658 -> 14779.619 | E15: =OpenAI_Sim!F658 -> 18450.081 | F15: =OpenAI_Sim!G658 -> 28076.785 | G15: =OpenAI_Sim!H658 -> 39038.462
A16: tok/paid customer/day | B16: =OpenAI_Sim!C659 -> 170379.13 | C16: =OpenAI_Sim!D659 -> 220512.82 | D16: =OpenAI_Sim!E659 -> 237587.94 | E16: =OpenAI_Sim!F659 -> 249076.09 | F16: =OpenAI_Sim!G659 -> 330168.78 | G16: =OpenAI_Sim!H659 -> 380625
A17: Consumer Sub Rev ($B) | B17: =OpenAI_Sim!C660 -> 8.448 | C17: =OpenAI_Sim!D660 -> 19.776 | D17: =OpenAI_Sim!E660 -> 33.672 | E17: =OpenAI_Sim!F660 -> 61.008 | F17: =OpenAI_Sim!G660 -> 92.7 | G17: =OpenAI_Sim!H660 -> 142.8
A18: Consumer Sub Price ($/Mtok) | B18: =OpenAI_Sim!C661 -> 6.2314362 | C18: =OpenAI_Sim!D661 -> 4.2000637 | D18: =OpenAI_Sim!E661 -> 3.9023712 | E18: =OpenAI_Sim!F661 -> 3.6470697 | F18: =OpenAI_Sim!G661 -> 3.2456563 | G18: =OpenAI_Sim!H661 -> 3.2120926
A19: API Rev ($B) | B19: =OpenAI_Sim!C662 -> 4.652 | C19: =OpenAI_Sim!D662 -> 12.974 | D19: =OpenAI_Sim!E662 -> 26.9155 | E19: =OpenAI_Sim!F662 -> 51.078875 | F19: =OpenAI_Sim!G662 -> 86.639 | G19: =OpenAI_Sim!H662 -> 144.1424
A20: Total API tokens(Mtok) | B20: =OpenAI_Sim!C663 -> 1.7990194e+09 | C20: =OpenAI_Sim!D663 -> 5.0978012e+09 | D20: =OpenAI_Sim!E663 -> 1.090646e+10 | E20: =OpenAI_Sim!F663 -> 2.1282865e+10 | F20: =OpenAI_Sim!G663 -> 3.7999561e+10 | G20: =OpenAI_Sim!H663 -> 6.7672488e+10
... A22: Consumer % of Rev | B22: =OpenAI_Sim!C665 -> 0.6448855 | C22: =OpenAI_Sim!D665 -> 0.60384733 | D22: =OpenAI_Sim!E665 -> 0.5557582 | E22: =OpenAI_Sim!F665 -> 0.54429209 | F22: =OpenAI_Sim!G665 -> 0.51689816 | G22: =OpenAI_Sim!H665 -> 0.49766085
A24: Total Tokens (T) | B24: =OpenAI_Sim!C670 -> 3154.7261 | C24: =OpenAI_Sim!D670 -> 9806.3012 | D24: =OpenAI_Sim!E670 -> 19535.06 | E24: =OpenAI_Sim!F670 -> 38010.815 | F24: =OpenAI_Sim!G670 -> 66560.811 | G24: =OpenAI_Sim!H670 -> 112129.49
A25: YoY Token Growth | B25: =OpenAI_Sim!C671 -> n/a | C25: =OpenAI_Sim!D671 -> 2.1084477 | D25: =OpenAI_Sim!E671 -> 0.99209264 | E25: =OpenAI_Sim!F671 -> 0.9457741 | F25: =OpenAI_Sim!G671 -> 0.75110195 | G25: =OpenAI_Sim!H671 -> 0.68461721
A26: Blended Eff. Rate ($/M tok) | B26: =OpenAI_Sim!C672 -> 4.1525 | C26: =OpenAI_Sim!D672 -> 3.3396894 | D26: =OpenAI_Sim!E672 -> 3.1014749 | E26: =OpenAI_Sim!F672 -> 2.9488154 | F26: =OpenAI_Sim!G672 -> 2.6943632 | G26: =OpenAI_Sim!H672 -> 2.5590271
A27: Blended ARPU ($/mo) | B27: =OpenAI_Sim!C673 -> 32.293578 | C27: =OpenAI_Sim!D673 -> 28.17094 | D27: =OpenAI_Sim!E673 -> 28.201005 | E27: =OpenAI_Sim!F673 -> 27.630435 | F27: =OpenAI_Sim!G673 -> 32.594937 | G27: =OpenAI_Sim!H673 -> 37.1875

Sheet OpenAI_Sim
A1: OpenAI Financial Simulation — Calibrating 1 GW VR72 DC Model to OpenAI's Disclosed Financials (Feb 2026 Funding Round)
A3: Section 1: OpenAI Disclosed Financials & Operating Metrics (as of Feb 2026)
A4: Metric | B4: 2024A | C4: 2025A | D4: 2026E | E4: 2027E | F4: 2028E | G4: 2029E | H4: 2030E | I4: Source / Note
A5: Revenue ($B) | B5: 3.7 | C5: 13.1 | H5: 280 | I5: CNBC: $13.1B actual 2025; $280B 2030 target
A6: ARR ($B, exit rate) | B6: 6 | C6: 20 | I6: OpenAI CFO blog: $2B (2023) → $6B (2024) → $20B+ (2025)
A7: YoY Revenue Growth | B7: =B5/3.7-1 -> 0 | C7: =C5/B5-1 -> 2.5405405 | I7: Implied from reported revenue figures
A8: Cash Burn ($B) | B8: -5 | C8: -8 | D8: -17 | G8: 2 | I8: The Information: burn $17B (2026), cash flow positive ~2029
A9: Gross Margin | B9: 0.4 | C9: 0.33
A11: Compute Capacity, Year-End (GW) | B11: 0.6 | C11: 1.9 | D11: 3.5 | E11: 4.5 | F11: 5.75 | G11: 7 | H11: 10 | I11: Year-end capacity: 0.6 GW (2024) → 1.9 GW (2025) → 10 GW (2030 Stargate)
A12: Compute Capacity, FY Avg (GW) | B12: =(0.2+B11)/2 -> 0.4 | C12: =(B11+C11)/2 -> 1.25 | D12: =(C11+D11)/2 -> 2.7 | E12: =(D11+E11)/2 -> 4 | F12: =(E11+F11)/2 -> 5.125 | G12: =(F11+G11)/2 -> 6.375 | H12: =(G11+H11)/2 -> 8.5 | I12: FY average = midpoint of prior year-end and current year-end (linear ramp)
A13: Weekly Active Users (M) | C13: 900 | I13: 900M WAU, 50M+ paid subscribers (Feb 2026)
A14: Paid Subscribers (M) | C14: 50 | I14: 50M+ consumer subscribers
A16: Latest Funding Round
A17: Total Raised | B17: $110B | I17: Amazon $50B + Nvidia $30B + SoftBank $30B (Feb 2026)
A18: Pre-Money Valuation | B18: $730B | I18: Pre-money $730B; post-money $840B
A19: Post-Money Valuation | B19: $840B | I19: Largest private funding round in history
A20: Implied Revenue Multiple (on 2025 rev) | B20: =840/C5 -> 64.122137 | I20: Post-money valuation / 2025 actual revenue
A21: Implied Revenue Multiple (on 2030E rev) | B21: =840/F5 -> #DIV/0! | I21: Post-money valuation / 2030E target revenue
A22: Infrastructure Spend Target (by 2030) | B22: $600B | I22: CNBC: revised down from $1.4T to ~$600B by 2030
A23: Stargate Capacity Target | B23: 10 GW | I23: Stargate: $500B / 4 yrs / 10 GW US-based AI infra
A25: Section 2: Infrastructure Calibration — Scaling Our 1 GW VR72 Model to OpenAI's 1.9 GW (2025)
A26: Parameter | B26: Our 1 GW Model | C26: OpenAI 1.9 GW | D26: Unit | I26: Note
A27: IT Power (MW) | B27: =Config!F5/1000000 -> 1000 | C27: =C11*1000 -> 1900 | D27: MW | I27: Config!F5 (VR preset, dropdown-independent); OpenAI from CFO blog
A28: PUE | B28: =Config!F6 -> 1.2 | C28: 1.25 | I28: Mixed fleet PUE slightly higher (H100/A100 legacy + newer)
A29: Total Facility Power (MW) | B29: =B27*B28 -> 1200 | C29: =C27*C28 -> 2375 | D29: MW | I29: IT Power × PUE
A30: Scale Factor (vs our 1 GW model) | B30: 1 | C30: =C27/B27 -> 1.9 | I30: Simple linear scaling of IT power
A32: Hardware Mix Adjustment
A33: Current Fleet (est.) | B33: 100% VR NVL72 | C33: Mixed (H100/GB200/VR) | I33: OpenAI runs mixed generations; our model = next-gen only
A34: Inference Efficiency Factor | B34: 1 | C34: =C100*0.25+C101*(TL_Param!O34/TL_Param!N34)+C102*1 -> 0.27507985 | I34: Fleet-weighted VR-equiv factor: H100=0.25x, GB200=0.32x (TL_Param!O34/N34), VR=1.0x
A35: Effective VR-Equivalent Power (MW) | B35: =B27*B34 -> 1000 | C35: =C27*C34 -> 522.65172 | D35: MW-eq | I35: Reference facility IT power × fleet efficiency factor = VR-equivalent MW
A37: Implied from Financials
A38: Our Model CapEx ($B) | B38: =DC_Cost_Model!D54/1000 -> 43.234167 | I38: From DC_Cost_Model total CapEx
A39: OpenAI Implied CapEx at 1.9 GW ($B) | C39: =B38*C30 -> 82.144918 | I39: Scaled linearly from our 1 GW model
A40: Our Model Annual OpEx ($B) | B40: =DC_Cost_Model!D88/1000 -> 9.2981768 | I40: From DC_Cost_Model total annual OpEx
A41: OpenAI Implied DC OpEx at 1.9 GW ($B) | C41: =B40*C30 -> 17.666536 | I41: DC-only OpEx; does not include R&D, S&M, G&A, SBC
A43: Section 3: OpenAI P&L Simulation — Reverse-Engineering from Disclosed Numbers
A44: Line Item | B44: 2024A ($B) | C44: 2025A ($B) | D44: 2026E ($B) | E44: 2027E ($B) | F44: 2028E ($B) | G44: 2029E ($B) | H44: 2030E ($B) | I44: Assumption / Source
A45: Assumptions
A46: Revenue Growth Rate (YoY) | C46: =C7 -> 2.5405405 | D46: 1.5 | E46: 0.85 | F46: 0.85 | G46: 0.6 | H46: 0.6 | I46: 254% actual (2025); decelerating growth toward $280B 2030 target
A47: Gross Margin | B47: =B9 -> 0.4 | C47: =C9 -> 0.33 | D47: =D61 -> 0.57447116 | E47: =E61 -> 0.62037766 | F47: =F61 -> 0.70380206 | G47: =G61 -> 0.75678609 | H47: =H61 -> 0.79066801 | I47: Now derived from bottom-up DC cost model (row 60); 2024-2025 actual
A48: R&D as % of Revenue | B48: 0.68 | C48: 0.51 | D48: 0.4 | E48: 0.3 | F48: 0.25 | G48: 0.2 | H48: 0.15 | I48: $2.5B (2024); $6.7B H1 2025 → ~$13B ann.
A49: S&M as % of Revenue | B49: 0.27 | C49: 0.15 | D49: 0.12 | E49: 0.1 | F49: 0.08 | G49: 0.065 | H49: 0.05 | I49: ~$2B in H1 2025 → ~$4B ann.; declining with scale
A50: G&A as % of Revenue | B50: 0.08 | C50: 0.06 | D50: 0.05 | E50: 0.045 | F50: 0.04 | G50: 0.035 | H50: 0.03 | I50: Est. corporate overhead; declining leverage with scale
A51: SBC as % of Revenue | B51: 0.68 | C51: 0.19 | D51: 0.12 | E51: 0.09 | F51: 0.06 | G51: 0.045 | H51: 0.03 | I51: ~$2.5B H1 2025 → $5B ann.; dilutes as rev scales
A52: MS Revenue Share % | B52: 0.2 | C52: 0.2 | D52: 0.2 | E52: 0.175 | F52: 0.15 | G52: 0.125 | H52: 0.1 | I52: 20% rev share to MS; may reduce post-PBC conversion
A53: CapEx (infra investment, $B) | B53: 5 | C53: 15 | D53: 40 | E53: 60 | F53: 100 | G53: 125 | H53: 150 | I53: ~$600B cumulative by 2030; ramp accelerates post-2027
A54: Bottom-Up COGS (from DC_Cost_Model fleet economics)
A55: OpEx/GW: Legacy H100 ($B) | B55: 5.631 | C55: 5.631 | D55: 5.631 | E55: 5.631 | F55: 5.631 | G55: 5.631 | H55: 5.631 | I55: Est: $20B CapEx, 5yr depr + $0.63B elec + $1.0B maint
A56: OpEx/GW: GB200 NVL72 ($B) | B56: =DC_Cost_Model!D184/1000 -> 7.0544052 | C56: =DC_Cost_Model!D184/1000 -> 7.0544052 | D56: =DC_Cost_Model!D184/1000 -> 7.0544052 | E56: =DC_Cost_Model!D184/1000 -> 7.0544052 | F56: =DC_Cost_Model!D184/1000 -> 7.0544052 | G56: =DC_Cost_Model!D184/1000 -> 7.0544052 | H56: =DC_Cost_Model!D184/1000 -> 7.0544052 | I56: Linked from DC_Cost_Model GB200 section (D184 / 1GW)
A57: OpEx/GW: VR NVL72 ($B) | B57: =DC_Cost_Model!D88/1000 -> 9.2981768 | C57: =DC_Cost_Model!D88/1000 -> 9.2981768 | D57: =DC_Cost_Model!D88/1000 -> 9.2981768 | E57: =DC_Cost_Model!D88/1000 -> 9.2981768 | F57: =DC_Cost_Model!D88/1000 -> 9.2981768 | G57: =DC_Cost_Model!D88/1000 -> 9.2981768 | H57: =DC_Cost_Model!D88/1000 -> 9.2981768 | I57: Linked from DC_Cost_Model VR section (D88 / 1GW)
A58: Fleet-Weighted DC OpEx ($B) | B58: =B94*(B100*B55+B101*B56+B102*B57) -> 2.2524 | C58: =C94*(C100*C55+C101*C56+C102*C57) -> 7.572527 | D58: =D94*(D100*D55+D101*D56+D102*D57) -> 18.336934 | E58: =E94*(E100*E55+E101*E56+E102*E57) -> 30.263642 | F58: =F94*(F100*F55+F101*F56+F102*F57) -> 43.684081 | G58: =G94*(G100*G55+G101*G56+G102*G57) -> 57.391762 | H58: =H94*(H100*H55+H101*H56+H102*H57) -> 79.034503 | I58: Σ(GW × fleet_share × OpEx/GW) per hardware type
A59: COGS / DC OpEx Ratio | B59: 0.78 | C59: =C68*(1-C9)/C58 -> 1.1590583 | D59: 0.76 | E59: 0.76 | F59: 0.76 | G59: 0.76 | H59: 0.76 | I59: ← Adjustable. Captures inference share + Azure markup + non-compute COGS. Calibrated to 2025 actual.
A60: Bottom-Up COGS ($B) | B60: =B58*B59 -> 1.756872 | C60: =C58*C59 -> 8.777 | D60: =D58*D59 -> 13.93607 | E60: =E58*E59 -> 23.000368 | F60: =F58*F59 -> 33.199902 | G60: =G58*G59 -> 43.617739 | H60: =H58*H59 -> 60.066222 | I60: Fleet DC OpEx × COGS ratio
A61: → Implied Gross Margin | B61: =1-B60/B68 -> 0.52516973 | C61: =1-C60/C68 -> 0.33 | D61: =1-D60/D68 -> 0.57447116 | E61: =1-E60/E68 -> 0.62037766 | F61: =1-F60/F68 -> 0.70380206 | G61: =1-G60/G68 -> 0.75678609 | H61: =1-H60/H68 -> 0.79066801 | I61: 1 - COGS / Gross Revenue (bottom-up)
A67: Income Statement
A68: Revenue (gross) | B68: =B5 -> 3.7 | C68: =C5 -> 13.1 | D68: =C68*(1+D46) -> 32.75 | E68: =D68*(1+E46) -> 60.5875 | F68: =E68*(1+F46) -> 112.08688 | G68: =F68*(1+G46) -> 179.339 | H68: =G68*(1+H46) -> 286.9424 | I68: 2024-2025 actual; 2026+ from growth assumptions
A69: Less: MS Revenue Share | B69: =-B68*B52 -> -0.74 | C69: =-C68*C52 -> -2.62 | D69: =-D68*D52 -> -6.55 | E69: =-E68*E52 -> -10.602813 | F69: =-F68*F52 -> -16.813031 | G69: =-G68*G52 -> -22.417375 | H69: =-H68*H52 -> -28.69424 | I69: Revenue share paid to Microsoft
A70: Net Revenue | B70: =B68+B69 -> 2.96 | C70: =C68+C69 -> 10.48 | D70: =D68+D69 -> 26.2 | E70: =E68+E69 -> 49.984687 | F70: =F68+F69 -> 95.273844 | G70: =G68+G69 -> 156.92163 | H70: =H68+H69 -> 258.24816 | I70: Gross revenue minus MS share
A72: Cost of Revenue (COGS) | B72: =-B60 -> -1.756872 | C72: =-C60 -> -8.777 | D72: =-D60 -> -13.93607 | E72: =-E60 -> -23.000368 | F72: =-F60 -> -33.199902 | G72: =-G60 -> -43.617739 | H72: =-H60 -> -60.066222 | I72: From bottom-up DC cost model (row 59)
A73: Gross Profit | B73: =B70+B72 -> 1.203128 | C73: =C70+C72 -> 1.703 | D73: =D70+D72 -> 12.26393 | E73: =E70+E72 -> 26.984319 | F73: =F70+F72 -> 62.073942 | G73: =G70+G72 -> 113.30389 | H73: =H70+H72 -> 198.18194 | I73: Net Revenue less COGS
A74: Gross Margin | B74: =B73/B70 -> 0.40646216 | C74: =C73/C70 -> 0.1625 | D74: =D73/D70 -> 0.46808894 | E74: =E73/E70 -> 0.53985171 | F74: =F73/F70 -> 0.65153183 | G74: =G73/G70 -> 0.72204125 | H74: =H73/H70 -> 0.7674089 | I74: On NET revenue basis (after MS share); differs from C46 which is on gross revenue
A76: R&D Expense | B76: =-B68*B48 -> -2.516 | C76: =-C68*C48 -> -6.681 | D76: =-D68*D48 -> -13.1 | E76: =-E68*E48 -> -18.17625 | F76: =-F68*F48 -> -28.021719 | G76: =-G68*G48 -> -35.8678 | H76: =-H68*H48 -> -43.04136 | I76: Training compute, research staff, model dev
A77: S&M Expense | B77: =-B68*B49 -> -0.999 | C77: =-C68*C49 -> -1.965 | D77: =-D68*D49 -> -3.93 | E77: =-E68*E49 -> -6.05875 | F77: =-F68*F49 -> -8.96695 | G77: =-G68*G49 -> -11.657035 | H77: =-H68*H49 -> -14.34712 | I77: Sales, marketing, user acquisition
A78: G&A Expense | B78: =-B68*B50 -> -0.296 | C78: =-C68*C50 -> -0.786 | D78: =-D68*D50 -> -1.6375 | E78: =-E68*E50 -> -2.7264375 | F78: =-F68*F50 -> -4.483475 | G78: =-G68*G50 -> -6.276865 | H78: =-H68*H50 -> -8.608272 | I78: Legal, admin, finance, office
A79: SBC Expense | B79: =-B68*B51 -> -2.516 | C79: =-C68*C51 -> -2.489 | D79: =-D68*D51 -> -3.93 | E79: =-E68*E51 -> -5.452875 | F79: =-F68*F51 -> -6.7252125 | G79: =-G68*G51 -> -8.070255 | H79: =-H68*H51 -> -8.608272 | I79: Stock-based compensation
A80: Total OpEx (incl. COGS) | B80: =B72+B76+B77+B78+B79 -> -8.083872 | C80: =C72+C76+C77+C78+C79 -> -20.698 | D80: =D72+D76+D77+D78+D79 -> -36.53357 | E80: =E72+E76+E77+E78+E79 -> -55.414681 | F80: =F72+F76+F77+F78+F79 -> -81.397258 | G80: =G72+G76+G77+G78+G79 -> -105.48969 | H80: =H72+H76+H77+H78+H79 -> -134.67125 | I80: COGS + R&D + S&M + G&A + SBC
A82: Operating Income (Loss) | B82: =B70+B80 -> -5.123872 | C82: =C70+C80 -> -10.218 | D82: =D70+D80 -> -10.33357 | E82: =E70+E80 -> -5.4299933 | F82: =F70+F80 -> 13.876586 | G82: =G70+G80 -> 51.431931 | H82: =H70+H80 -> 123.57691 | I82: Net Revenue less Total OpEx
A83: Operating Margin (on net rev) | B83: =B82/B70 -> -1.7310378 | C83: =C82/C70 -> -0.975 | D83: =D82/D70 -> -0.39441106 | E83: =E82/E70 -> -0.10863313 | F83: =F82/F70 -> 0.14564948 | G83: =G82/G70 -> 0.32775553 | H83: =H82/H70 -> 0.47852002
A85: Disclosed Cash Burn (actual) | B85: =B8 -> -5 | C85: =C8 -> -8 | D85: =D8 -> -17 | G85: =G8 -> 2 | H85: =H8 -> 0 | I85: Actual/projected disclosed cash burn
A86: Cash Burn = OpInc - CapEx + SBC addback | B86: =B82-B53+ABS(B79) -> -7.607872 | C86: =C82-C53+ABS(C79) -> -22.729 | D86: =D82-D53+ABS(D79) -> -46.40357 | E86: =E82-E53+ABS(E79) -> -59.977118 | F86: =F82-F53+ABS(F79) -> -79.398202 | G86: =G82-G53+ABS(G79) -> -65.497814 | H86: =H82-H53+ABS(H79) -> -17.814814 | I86: Modeled: Operating income - CapEx + SBC (non-cash)
A87: Δ vs Disclosed | B87: =B86-B85 -> -2.607872 | C87: =C86-C85 -> -14.729 | D87: =D86-D85 -> -29.40357 | G87: =G86-G85 -> -67.497814 | I87: Variance: model vs disclosed (check)
A89: Section 4: Infrastructure Spend Waterfall & Compute Ramp
A90: Metric | B90: 2024A | C90: 2025A | D90: 2026E | E90: 2027E | F90: 2028E | G90: 2029E | H90: 2030E | I90: Source / Note
A91: Annual CapEx ($B) | B91: =B53 -> 5 | C91: =C53 -> 15 | D91: =D53 -> 40 | E91: =E53 -> 60 | F91: =F53 -> 100 | G91: =G53 -> 125 | H91: =H53 -> 150 | I91: From assumptions; ~$600B cumulative by 2030
A92: Cumulative CapEx ($B) | B92: =B91 -> 5 | C92: =B92+C91 -> 20 | D92: =C92+D91 -> 60 | E92: =D92+E91 -> 120 | F92: =E92+F91 -> 220 | G92: =F92+G91 -> 345 | H92: =G92+H91 -> 495 | I92: Running total of cumulative CapEx
A94: Compute Capacity, FY Avg (GW) | B94: =B12 -> 0.4 | C94: =C12 -> 1.25 | D94: =D12 -> 2.7 | E94: =E12 -> 4 | F94: =F12 -> 5.125 | G94: =G12 -> 6.375 | H94: =H12 -> 8.5 | I94: FY average capacity (from Section 1); used for COGS and revenue-per-GW matching
A95: Compute Capacity, Year-End (GW) | B95: =B11 -> 0.6 | C95: =C11 -> 1.9 | D95: =D11 -> 3.5 | E95: =E11 -> 4.5 | F95: =F11 -> 5.75 | G95: =G11 -> 7 | H95: =H11 -> 10 | I95: Year-end capacity; used for CapEx per GW calculation
A96: CapEx per GW ($B/GW) | B96: =B91/(B95-0) -> 8.3333333 | C96: =C91/(C95-B95) -> 11.538462 | D96: =D91/(D95-C95) -> 25 | E96: =E91/(E95-D95) -> 60 | F96: =F91/(F95-E95) -> 80 | G96: =G91/(G95-F95) -> 100 | H96: =H91/(H95-G95) -> 50 | I96: Marginal CapEx per NEW GW deployed (Annual CapEx / New GW added)
A97: Our 1 GW Model CapEx for reference | C97: =B38 -> 43.234167 | I97: DC_Cost_Model CapEx for 1 GW VR NVL72
A99: Fleet Composition (est.)
A100: Legacy (H100/A100) share | B100: 1 | C100: 0.7 | D100: 0.5 | E100: 0.35 | F100: 0.15 | G100: 0.05 | H100: 0 | I100: Legacy fleet phased out as VR NVL72 ramps
A101: GB200 NVL72 share | B101: 0 | C101: 0.3 | D101: 0.3 | E101: 0.2 | F101: 0.1 | G101: 0.05 | H101: 0 | I101: Blackwell era; deployed mid-2025
A102: Vera Rubin NVL72 share | B102: 0 | C102: 0 | D102: 0.2 | E102: 0.45 | F102: 0.75 | G102: 0.9 | H102: 1 | I102: First VR deployment H2 2026; dominant by 2028+
A103: Effective VR-equiv Capacity (GW) | B103: =B94*(B100*0.25+B101*(TL_Param!O34/TL_Param!N34)+B102*1) -> 0.1 | C103: =C94*(C100*0.25+C101*(TL_Param!O34/TL_Param!N34)+C102*1) -> 0.34384982 | D103: =D94*(D100*0.25+D101*(TL_Param!O34/TL_Param!N34)+D102*1) -> 1.1477156 | E103: =E94*(E100*0.25+E101*(TL_Param!O34/TL_Param!N34)+E102*1) -> 2.4168796 | F103: =F94*(F100*0.25+F101*(TL_Param!O34/TL_Param!N34)+F102*1) -> 4.2069073 | G103: =G94*(G100*0.25+G101*(TL_Param!O34/TL_Param!N34)+G102*1) -> 5.9235223 | H103: =H94*(H100*0.25+H101*(TL_Param!O34/TL_Param!N34)+H102*1) -> 8.5 | I103: Weighted inference eff: H100=0.25x, GB200=0.32x (output tok/s ratio from TL_Param), VR=1.0x
A106: Revenue per GW ($B/GW) | B106: =B68/B94 -> 9.25 | C106: =C68/C94 -> 10.48 | D106: =D68/D94 -> 12.12963 | E106: =E68/E94 -> 15.146875 | F106: =F68/F94 -> 21.87061 | G106: =G68/G94 -> 28.131608 | H106: =H68/H94 -> 33.757929 | I106: Revenue generation efficiency per GW
A107: Revenue per VR-equiv GW ($B/GW-eq) | B107: =IF(B103>0,B68/B103,"-") -> 37 | C107: =IF(C103>0,C68/C103,"-") -> 38.098028 | D107: =IF(D103>0,D68/D103,"-") -> 28.534944 | E107: =IF(E103>0,E68/E103,"-") -> 25.068481 | F107: =IF(F103>0,F68/F103,"-") -> 26.643534 | G107: =IF(G103>0,G68/G103,"-") -> 30.275736 | H107: =IF(H103>0,H68/H103,"-") -> 33.757929 | I107: Normalized for hardware generation efficiency
A108: Our 1 GW Model Revenue ($B) | C108: =Revenue_Model!B39/1000 -> 76.735449 | I108: From Revenue_Model total annual revenue (theoretical max)
A110: Section 5: Valuation Sanity Check & DC-Backed Analysis
A111: Metric | B111: Value | C111: Unit | I111: Note
A112: Valuation Multiples
A113: Post-Money Valuation | B113: 840 | C113: $B | I113: Feb 2026 round: $730B pre + $110B raised
A114: EV / 2025 Revenue | B114: =B113/C68 -> 64.122137 | I114: On actual 2025 revenue ($13.1B)
A115: EV / 2025 ARR (exit rate) | B115: =B113/C6 -> 42 | I115: On $20B exit ARR
A116: EV / 2026E Revenue | B116: =B113/D68 -> 25.648855 | I116: On projected 2026 revenue
A117: EV / 2030E Revenue | B117: =B113/H68 -> 2.9274168 | I117: On projected 2030 revenue
A118: For reference: typical high-growth SaaS | B118: 15-25x | C118: rev | I118: Top-quartile SaaS companies trade 15-25x ARR
A120: Implied 2030 Valuation (at various multiples)
A121: At 10x 2030E Revenue | B121: =H68*10 -> 2869.424 | C121: $B | I121: Conservative multiple for scaled tech
A122: At 15x 2030E Revenue | B122: =H68*15 -> 4304.136 | C122: $B | I122: Moderate growth premium
A123: At 20x 2030E Revenue | B123: =H68*20 -> 5738.848 | C123: $B | I123: High-growth platform premium
...

Sheet IO_Sensitivity
A1: Input/Output Token Sensitivity Analysis — Annual Token Processing & Revenue Impact
A2: 1 GW Vera Rubin NVL72 Facility | 1T Dense Model (FP8) | Batch=64 | 70% GPU Utilization | Pricing: $2.50/M input, $10/M output
A4: # | B4: Input Tokens | C4: Output Tokens | D4: Total Tokens per Request | E4: I/O Ratio | F4: E2E Latency (seconds) | G4: Requests/Year (Billions) | H4: Annual Input Tokens (T) | I4: Annual Output Tokens (T) | J4: Annual Total Tokens (T) | K4: Input Revenue ($M/yr) | L4: Output Revenue ($M/yr) | M4: Theoretical Revenue ($M/yr) | O4: Use Case
A5: 1 | B5: 500 | C5: 200 | D5: =B5+C5 -> 700 | E5: =B5/C5 -> 2.5 | F5: 0.326301 | G5: 22673.7 | H5: 11336.8 | I5: 4534.7 | J5: 15871.6 | K5: 28342.1 | L5: 45347.37 | M5: 73689.47 | O5: Quick chatbot
A6: 2 | B6: 1000 | C6: 500 | D6: =B6+C6 -> 1500 | E6: =B6/C6 -> 2 | F6: 0.669951 | G6: 11043.3 | H6: 11043.3 | I6: 5521.6 | J6: 16564.9 | K6: 27608.21 | L6: 55216.41 | M6: 82824.62 | O6: Standard chat
A7: 3 | B7: 2000 | C7: 500 | D7: =B7+C7 -> 2500 | E7: =B7/C7 -> 4 | F7: 0.973262 | G7: 7601.7 | H7: 15203.4 | I7: 3800.9 | J7: 19004.3 | K7: 38008.57 | L7: 38008.57 | M7: 76017.14 | O7: Q&A / search
A8: 4 | B8: 2000 | C8: 1000 | D8: =B8+C8 -> 3000 | E8: =B8/C8 -> 2 | F8: 1.304671 | G8: 5670.7 | H8: 11341.5 | I8: 5670.7 | J8: 17012.2 | K8: 28353.73 | L8: 56707.46 | M8: 85061.19 | O8: Conversational AI
A9: 5 | B9: 4000 | C9: 1000 | D9: =B9+C9 -> 5000 | E9: =B9/C9 -> 4 | F9: =Revenue_Model!B11 -> 1.9283018 | G9: =Revenue_Model!B20/1000000000 -> 3836.7725 | H9: =Revenue_Model!B25/1000000 -> 15347.09 | I9: =Revenue_Model!B26/1000000 -> 3836.7725 | J9: =Revenue_Model!B24/1000000 -> 19183.862 | K9: =Revenue_Model!B37 -> 38367.725 | L9: =Revenue_Model!B38 -> 38367.725 | M9: =Revenue_Model!B39 -> 76735.449 | O9: ◄ CURRENT CONFIG
A10: 6 | B10: 4000 | C10: 2000 | D10: =B10+C10 -> 6000 | E10: =B10/C10 -> 2 | F10: 2.620321 | G10: 2823.5 | H10: 11294 | I10: 5647 | J10: 16941 | K10: 28234.92 | L10: 56469.85 | M10: 84704.77 | O10: Balanced generation
A11: 7 | B11: 4000 | C11: 4000 | D11: =B11+C11 -> 8000 | E11: =B11/C11 -> 1 | F11: 4.036214 | G11: 1833 | H11: 7332.1 | I11: 7332.1 | J11: 14664.1 | K11: 18330.19 | L11: 73320.74 | M11: 91650.93 | O11: Heavy generation (1:1)
A12: 8 | B12: 8000 | C12: 1000 | D12: =B12+C12 -> 9000 | E12: =B12/C12 -> 8 | F12: 3.20113 | G12: 2311.2 | H12: 18489.6 | I12: 2311.2 | J12: 20800.8 | K12: 46224.03 | L12: 23112.01 | M12: 69336.04 | O12: Long context + short reply
A13: 9 | B13: 8000 | C13: 2000 | D13: =B13+C13 -> 10000 | E13: =B13/C13 -> 4 | F13: 3.935623 | G13: 1879.9 | H13: 15039 | I13: 3759.7 | J13: 18798.7 | K13: 37597.38 | L13: 37597.38 | M13: 75194.77 | O13: Document analysis
A14: 10 | B14: 8000 | C14: 4000 | D14: =B14+C14 -> 12000 | E14: =B14/C14 -> 2 | F14: 5.436464 | G14: 1360.9 | H14: 10887.2 | I14: 5443.6 | J14: 16330.7 | K14: 27217.9 | L14: 54435.79 | M14: 81653.69 | O14: Deep analysis + response
A15: 11 | B15: 16000 | C15: 1000 | D15: =B15+C15 -> 17000 | E15: =B15/C15 -> 16 | F15: 5.849046 | G15: 1264.9 | H15: 20238.4 | I15: 1264.9 | J15: 21503.3 | K15: 50595.98 | L15: 12648.99 | M15: 63244.97 | O15: RAG / long doc short answer
A16: 12 | B16: 16000 | C16: 2000 | D16: =B16+C16 -> 18000 | E16: =B16/C16 -> 8 | F16: 6.668487 | G16: 1109.5 | H16: 17751.4 | I16: 2218.9 | J16: 19970.4 | K16: 44378.61 | L16: 22189.31 | M16: 66567.92 | O16: Long doc summarization
A17: 13 | B17: 16000 | C17: 4000 | D17: =B17+C17 -> 20000 | E17: =B17/C17 -> 4 | F17: 8.339224 | G17: 887.2 | H17: 14195 | I17: 3548.7 | J17: 17743.7 | K17: 35487.5 | L17: 35487.5 | M17: 70975 | O17: Enterprise doc processing
A18: 14 | B18: 4000 | C18: 8000 | D18: =B18+C18 -> 12000 | E18: =B18/C18 -> 0.5 | F18: 6.995423 | G18: 1057.6 | H18: 4230.5 | I18: 8460.9 | J18: 12691.4 | K18: 10576.14 | L18: 84609.1 | M18: 95185.24 | O18: Code generation
A19: 15 | B19: 4000 | C19: 16000 | D19: =B19+C19 -> 20000 | E19: =B19/C19 -> 0.25 | F19: 13.423528 | G19: 551.2 | H19: 2204.6 | I19: 8818.5 | J19: 11023.1 | K19: 5511.56 | L19: 88184.93 | M19: 93696.49 | O19: Long-form writing / reports
A20: 16 | B20: 1000000 | C20: 1000 | D20: =B20+C20 -> 1001000 | E20: =B20/C20 -> 1000 | F20: 1371.334 | G20: 5.4 | H20: 5395.1 | I20: 5.4 | J20: 5400.5 | K20: 13487.7 | L20: 53.95 | M20: 13541.65 | O20: 1M-token context window + short reply
A21: 17 | B21: 1000000 | C21: 1000000 | D21: =B21+C21 -> 2000000 | E21: =B21/C21 -> 1 | F21: 561.935 | G21: 13.17 | H21: 13165.75 | I21: 13165.75 | J21: 26331.5 | K21: =H21*2.5 -> 32914.375 | L21: =I21*10 -> 131657.5 | M21: =K21+L21 -> 164571.88 | O21: ⚠️ OOM: 2M-token context @ batch=64 requires ~33.5 TB KV cache. VR NVL72 has only 20.7 TB HBM4. Batch must be dynamically throttled to ~1-2.
A22: 18 | B22: 1000 | C22: 1000000 | D22: =B22+C22 -> 1001000 | E22: =B22/C22 -> 0.001 | F22: 5953.828 | G22: 1.2 | H22: 1.2 | I22: 1242.6 | J22: 1243.9 | K22: 3.11 | L22: 12426.38 | M22: 12429.49 | O22: Tiny prompt + massive generation (1M output)
A25: Key Insight:
A26: Prefill (input processing) dominates latency (~97% of E2E time). Increasing input tokens has a far larger impact on throughput than increasing output tokens. Output tokens primarily drive revenue via 4× higher output pricing. Calculated on Vera Rubin NVL72 with all optimizations (GQA, batch=64, speculative decoding, NVLink SHARP+overlap+PP).
A29: Chart 1: Annual Token Throughput by I/O Configuration | F29: Chart 2: Revenue by I/O Configuration ($M/yr)
A30: Config (Input:Output) | B30: 11336.8 | C30: 4534.7 | D30: 15871.6 | F30: Config (Input:Output) | G30: 28342.1 | H30: 45347.37 | I30: 73689.47
A31: =B5&":"&C5 -> 500:200 | B31: 11043.3 | C31: 5521.6 | D31: 16564.9 | F31: =A31 -> 500:200 | G31: 27608.21 | H31: 55216.41 | I31: 82824.62
A32: =B6&":"&C6 -> 1000:500 | B32: 15203.4 | C32: 3800.9 | D32: 19004.3 | F32: =A32 -> 1000:500 | G32: 38008.57 | H32: 38008.57 | I32: 76017.14
A33: =B7&":"&C7 -> 2000:500 | B33: 11341.5 | C33: 5670.7 | D33: 17012.2 | F33: =A33 -> 2000:500 | G33: 28353.73 | H33: 56707.46 | I33: 85061.19
A34: =B8&":"&C8 -> 2000:1000 | B34: =H8 -> 11341.5 | C34: =I8 -> 5670.7 | D34: =J8 -> 17012.2 | F34: =A34 -> 2000:1000 | G34: =K8 -> 28353.73 | H34: =L8 -> 56707.46 | I34: =M8 -> 85061.19
A35: =B9&":"&C9 -> 4000:1000 | B35: 11294 | C35: 5647 | D35: 16941 | F35: =A35 -> 4000:1000 | G35: 28234.92 | H35: 56469.85 | I35: 84704.77
A36: =B10&":"&C10 -> 4000:2000 | B36: 7332.1 | C36: 7332.1 | D36: 14664.1 | F36: =A36 -> 4000:2000 | G36: 18330.19 | H36: 73320.74 | I36: 91650.93
A37: =B11&":"&C11 -> 4000:4000 | B37: 18489.6 | C37: 2311.2 | D37: 20800.8 | F37: =A37 -> 4000:4000 | G37: 46224.03 | H37: 23112.01 | I37: 69336.04
A38: =B12&":"&C12 -> 8000:1000 | B38: 15039 | C38: 3759.7 | D38: 18798.7 | F38: =A38 -> 8000:1000 | G38: 37597.38 | H38: 37597.38 | I38: 75194.77
A39: =B13&":"&C13 -> 8000:2000 | B39: 10887.2 | C39: 5443.6 | D39: 16330.7 | F39: =A39 -> 8000:2000 | G39: 27217.9 | H39: 54435.79 | I39: 81653.69
A40: =B14&":"&C14 -> 8000:4000 | B40: 20238.4 | C40: 1264.9 | D40: 21503.3 | F40: =A40 -> 8000:4000 | G40: 50595.98 | H40: 12648.99 | I40: 63244.97
A41: =B15&":"&C15 -> 16000:1000 | B41: 17751.4 | C41: 2218.9 | D41: 19970.4 | F41: =A41 -> 16000:1000 | G41: 44378.61 | H41: 22189.31 | I41: 66567.92
A42: =B16&":"&C16 -> 16000:2000 | B42: 14195 | C42: 3548.7 | D42: 17743.7 | F42: =A42 -> 16000:2000 | G42: 35487.5 | H42: 35487.5 | I42: 70975
A43: =B17&":"&C17 -> 16000:4000 | B43: 4230.5 | C43: 8460.9 | D43: 12691.4 | F43: =A43 -> 16000:4000 | G43: 10576.14 | H43: 84609.1 | I43: 95185.24
A44: =B18&":"&C18 -> 4000:8000 | B44: 2204.6 | C44: 8818.5 | D44: 11023.1 | F44: =A44 -> 4000:8000 | G44: 5511.56 | H44: 88184.93 | I44: 93696.49
A45: =B19&":"&C19 -> 4000:16000 | B45: 5395.1 | C45: 5.4 | D45: 5400.5 | F45: =A45 -> 4000:16000 | G45: 13487.7 | H45: 53.95 | I45: 13541.65
A46: =B20&":"&C20 -> 1000000:1000 | B46: =H20 -> 5395.1 | C46: =I20 -> 5.4 | D46: =J20 -> 5400.5 | F46: =A46 -> 1000000:1000 | G46: =K20 -> 13487.7 | H46: =L20 -> 53.95 | I46: =M20 -> 13541.65
A47: =B21&":"&C21 -> 1000000:1000000 | B47: 1.2 | C47: 1242.6 | D47: 1243.9 | F47: =A47 -> 1000000:1000000 | G47: 3.11 | H47: 12426.38 | I47: 12429.49
A48: =B22&":"&C22 -> 1000:1000000 | B48: =H22 -> 1.2 | C48: =I22 -> 1242.6 | D48: =J22 -> 1243.9 | F48: =A48 -> 1000:1000000 | G48: =K22 -> 3.11 | H48: =L22 -> 12426.38 | I48: =M22 -> 12429.49

Sheet ModelSize_Sensitivity
A1: Model Size Sensitivity Analysis — Annual Token Processing & Revenue
A2: 1 GW Vera Rubin NVL72 Facility | Input: 4,000 / Output: 1,000 tokens | Batch=64 | FP8 | 70% GPU Utilization | All optimizations applied
A4: # | B4: Model Size | C4: Parameters | D4: d_model | E4: Layers | F4: E2E Latency (seconds) | G4: Requests/Year (Billions) | H4: Annual Input Tokens (T) | I4: Annual Output Tokens (T) | J4: Annual Total Tokens (T) | K4: Pricing Tier | L4: Input Price ($/M tok) | M4: Output Price ($/M tok) | N4: Theo Revenue ($M/yr) | O4: Revenue per Token ($/T tok) | P4: Reference Model
A5: 1 | B5: 8B | C5: 8000000000 | D5: 4096 | E5: 32 | F5: 0.09273 | G5: 79784.8 | H5: 319139.3 | I5: 79784.8 | J5: 398924.1 | K5: Nano (<50B) | L5: 0.1 | M5: 0.4 | N5: 63827.85 | O5: =N5/J5 -> 0.15999998 | P5: Llama 3.1 8B / Mistral 7B
A6: 2 | B6: 20B | C6: 20000000000 | D6: 5120 | E6: 44 | F6: 0.128375 | G6: 57631.7 | H6: 230526.9 | I6: 57631.7 | J6: 288158.6 | K6: Nano (<50B) | L6: 0.1 | M6: 0.4 | N6: 46105.38 | O6: =N6/J6 -> 0.16000001 | P6: GPT-5 Nano tier
A7: 3 | B7: 70B | C7: 70000000000 | D7: 8192 | E7: 80 | F7: 0.277171 | G7: 26692.7 | H7: 106770.9 | I7: 26692.7 | J7: 133463.6 | K7: Small (50B-200B) | L7: 0.25 | M7: 2 | N7: 80078.19 | O7: =N7/J7 -> 0.60000022 | P7: Llama 3.1 70B
A8: 4 | B8: 200B | C8: 200000000000 | D8: 12288 | E8: 96 | F8: 0.548011 | G8: 13500.6 | H8: 54002.3 | I8: 13500.6 | J8: 67502.8 | K8: Mid (200B-500B) | L8: 1.25 | M8: 10 | N8: 202508.49 | O8: =N8/J8 -> 3.0000013 | P8: GPT-4 class
A9: 5 | B9: 405B | C9: 405000000000 | D9: 13824 | E9: 126 | F9: 0.938098 | G9: 7886.7 | H9: 31546.6 | I9: 7886.7 | J9: 39433.3 | K9: Mid (200B-500B) | L9: 1.25 | M9: 10 | N9: 118299.77 | O9: =N9/J9 -> 2.9999967 | P9: Llama 3.1 405B
A10: 6 | B10: 700B | C10: 700000000000 | D10: 18432 | E10: 120 | F10: 1.4314 | G10: 5168.7 | H10: 20674.7 | I10: 5168.7 | J10: 25843.4 | K10: Frontier (500B-1.5T) | L10: 2.5 | M10: 10 | N10: 103373.72 | O10: =N10/J10 -> 4.0000046 | P10: Claude 3.5 Sonnet class
A11: 7 | B11: 1T | C11: =Revenue_Model!B5 -> 1000000000000 | D11: 20480 | E11: 128 | F11: =Revenue_Model!B11 -> 1.9283018 | G11: =Revenue_Model!B20/1000000000 -> 3836.7725 | H11: =Revenue_Model!B25/1000000 -> 15347.09 | I11: =Revenue_Model!B26/1000000 -> 3836.7725 | J11: =Revenue_Model!B24/1000000 -> 19183.862 | K11: Frontier (500B-1.5T) | L11: =Revenue_Model!B32 -> 2.5 | M11: =Revenue_Model!B33 -> 10 | N11: =Revenue_Model!B39 -> 76735.449 | O11: =N11/J11 -> 4 | P11: ◄ CURRENT CONFIG
A12: 8 | B12: 1.5T | C12: 1500000000000 | D12: 30720 | E12: 144 | F12: 2.921585 | G12: 2532.3 | H12: 10129.4 | I12: 2532.3 | J12: 12661.7 | K12: Premium (>1.5T) | L12: 7.5 | M12: 37.5 | N12: 170933.17 | O12: =N12/J12 -> 13.500017 | P12: Claude Opus class
A13: 9 | B13: 2T | C13: 2000000000000 | D13: 40960 | E13: 160 | F13: 3.962902 | G13: 1866.9 | H13: 7467.7 | I13: 1866.9 | J13: 9334.6 | K13: Premium (>1.5T) | L13: 10 | M13: 50 | N13: 168023.59 | O13: =N13/J13 -> 18.000085 | P13: Next-gen frontier
A14: 10 | B14: 3T | C14: 3000000000000 | D14: 61440 | E14: 192 | F14: 6.189638 | G14: 1195.3 | H14: 4781.2 | I14: 1195.3 | J14: 5976.5 | K14: Premium (>1.5T) | L14: 15 | M14: 75 | N14: 161365.09 | O14: =N14/J14 -> 26.999931 | P14: Scaling frontier
A16: Key: Throughput drops ~exponentially with model size (prefill FLOPs ∝ params). Revenue peaks at 200B due to the mid-tier pricing sweet spot. d_model values corrected to match reference architectures (Llama 3.1, GPT-4 class). Prior values from the auto-formula were astronomically too small (e.g., d_model=128 for 8B, producing only ~6.3M params instead of 8B).
A17: Chart 1: Annual Token Throughput vs Model Size | E17: Chart 2: Revenue vs Model Size
A18: Model Size | B18: 398924.1 | C18: 63827.85 | E18: Model Size | F18: 63827.85
A19: =B5 -> 8B | B19: 288158.6 | C19: 46105.38 | E19: =A19 -> 8B | F19: 46105.38
A20: =B6 -> 20B | B20: 133463.6 | C20: 80078.19 | E20: =A20 -> 20B | F20: 80078.19
A21: =B7 -> 70B | B21: 67502.8 | C21: 202508.49 | E21: =A21 -> 70B | F21: 202508.49
A22: =B8 -> 200B | B22: 39433.3 | C22: 118299.77 | E22: =A22 -> 200B | F22: 118299.77
A23: =B9 -> 405B | B23: 25843.4 | C23: 103373.72 | E23: =A23 -> 405B | F23: 103373.72
A24: =B10 -> 700B | B24: =J10 -> 25843.4 | C24: =N10 -> 103373.72 | E24: =A24 -> 700B | F24: =C24 -> 103373.72
A25: =B11 -> 1T | B25: 12661.7 | C25: 170933.17 | E25: =A25 -> 1T | F25: 170933.17
A26: =B12 -> 1.5T | B26: 9334.6 | C26: 168023.59 | E26: =A26 -> 1.5T | F26: 168023.59
A27: =B13 -> 2T | B27: 5976.5 | C27: 161365.09 | E27: =A27 -> 2T | F27: 161365.09
A28: =B14 -> 3T | B28: =J14 -> 5976.5 | C28: =N14 -> 161365.09 | E28: =A28 -> 3T | F28: =C28 -> 161365.09
