Workbook

Sheet README
A1: Tokenomics v5.7 — Block 1＋2＋3：機架規格、每 GW 成本、各層級產出與每 token 成本、訓練與研發計畫
A2: 第 0 層規格來源。能力與理論營收於 Block 4 加入。
A4: 用途 | B4: 回答：每 1 GW IT 電力，各世代可容納多少機架、資本支出與持有成本（Block 1）；各層級 SLO 下的產出與依『世代 × 層級 × token 類型』的每 M token 成本（Block 2）；各層級代表模型的訓練與研發計畫需要多少 GPU 小時、成本與 1 GW 年，其中後訓練占多少（Block 3）。不含營收（Block 4）。
A5: 版本 | B5: 20261001_Tokenomics_v5.7（Block 1＋2＋3；v5.2 加第二來源驗證與生產折減；v5.3、v5.4 依 CC 回饋補具名範圍與驗證表；v5.5 加 Block 3：Tech_Registry、Train_In、Perf_Batch、Training、Sens_Train，並更正 Hopper FP8 峰值；v5.6 非同步 RL 併入基準、補 TR_ 與訓練世代具名範圍；v5.7 改為 Excel 優先：輸入值由 Excel 擁有，新增 DB_Evidence 證據登錄表）。v4 的 Config／TL_Param／WP_Param／Revenue_Model 由 Arch、Serving、Workload、Calib、Perf、Unit_Cost 取代。
A6: 電力口徑 | B6: GW＝IT 關鍵電力（Andy 2026-09-30 確認）。設施電力＝IT × PUE，於 DC_Cost 與 Interface 並列。
A7: 工作表 | B7: Inputs → Spec_Rack → Arch → Serving → Workload → Calib → Tech_Registry → Perf → Sens_Perf → Unit_Cost → DC_Cost → Train_In → Perf_Batch → Training → Sens_Train → Interface；Energy、NonNV、Sensitivity、Checks、Sources。
A8: Block 3 推導 | B8: 預訓練：FLOPs＝3 ×（2 × 啟用參數＋注意力 FLOPs × 被注意 token）× token；GPU 小時＝FLOPs ÷（FP8 訓練峰值 × MFU × goodput）。RL、蒸餾、合成資料、評測的推論型運算以 Perf_Batch（與 Perf 同公式，只換速度下限與參考任務）計價；RL 有效 MFU 為推導值。研發計畫＝最終訓練 GPU 小時 × 研發倍數。
A9: Block 3 決策 | B9: J7 訓練精度 FP8（NVFP4 預訓練在 Tech_Registry）；J8 Astra 預訓練與 Arch 一致，前沿錨點列 Checks；J9 RL 由下而上，基準校到 RL÷預訓練 GPU 小時 Luna／Sol 0.3、Astra 1.0；J10 研發倍數 8，家族合計、依最終訓練比例分攤；J11 用途 × 型態只列單一計畫；J12 rollout NVFP4（FP8 為情境）；J13 下游預設 VR200、GB300 並列；J14 主流＝至少兩家實驗室公開採用，可覆寫。
A10: Excel 優先（v5.7） | B10: 藍字＝輸入，由本活頁簿擁有：要改輸入，直接改 Excel。builder 重建 Block 2、3 時會先讀取所有藍字輸入，重建後依『工作表＋欄 A 標籤＋欄位』寫回，程式內的預設值只用於新增的輸入列。公式頁不要手改（重建時會被覆寫）。
A11: DB_Evidence（v5.7） | B11: 證據登錄表：所有比對過的新資訊（含不採納者），記錄主張、來源、標記、對應參數、當時值、新值、判定與處理版本。builder 只在本頁不存在時建立。
A12: Tech_Registry | B12: 每列＝技術 × 作用物理量；有效倍數＝1＋開關 × 採用比例 ×（倍數−1）；已在基準者不套倍數。掛鉤彙總表連到 Perf、Perf_Batch、Training。全部開關為 0 時 Block 2 數值與 v5.4 相同。
A13: Block 2 推導 | B13: prefill：tok/s＝η_p × 峰值 ÷ FLOPs/token。decode：每步時間＝固定延遲（權重讀取＋每層延遲 ×（層數＋草稿數））＋B × 每序列時間；在 SLO 下解出批次 B*，再受 HBM 容量限制。η_d 與每層延遲由 GB300 同一前緣兩點聯立解出（Calib）。
A14: 成本情境 | B14: 低成本／基準／高成本為角落情境。單一變數影響看 Sensitivity（Block 1）與 Sens_Perf（Block 2）。
A15: 功率情境 | B15: Inputs!E6 選 1／2／3，決定每架配電設計功率與每 GW 機架數。
... A21: 未結事項 | B21: (1) VR200 報價是否含網路（S11）。(2) 所有來源待 Andy 查核。(3) Rubin Ultra 為推估。(4) J6 基準利用率暫用 60%、生產折減暫用 1.0，皆待 Andy 給值。(5) VR200 無實測，η_d 與每層延遲沿用 GB300。(6) 交接錨點 6,182 屬舊軟體（vLLM 無 MTP），已改為 GB300 最新前緣兩點校準。(7) 快取命中只計載入時間，未計儲存成本。(8) Hopper 峰值更正為 FP8 1,979 TF，η_d 與 η_p 倍數同步減半以維持產出；S30 口徑待查後重推。(9) Block 3 的 Astra token、RL rollout 量、研發倍數皆為 Analogy／Assumed，看 Sens_Train。(10) v5.6：非同步 RL 併入基準（rollout 效率 0.85），RL rollout token 重校以維持 GPU 小時錨點（J9 (a)）。

Sheet Inputs
A1: Inputs — 全域輸入（藍字可改）
A2: 低成本／基準／高成本為角落情境；單值輸入只填基準欄
A3: 參數 | B3: 單位 | D3: 低成本 | E3: 基準 | F3: 高成本 | G3: 標記 | H3: 來源／說明
A4: 控制
A5: IT 電力規模 | B5: GW | D5: =E5 -> 1 | E5: 1 | F5: =E5 -> 1 | G5: Decision | H5: 口徑：IT 關鍵電力
A6: 功率情境（1 低／2 基準／3 高） | B6: 選擇 | D6: =E6 -> 2 | E6: 2 | F6: =E6 -> 2 | G6: Decision | H6: 決定每架配電設計功率；見 Spec_Rack 第 9–11 列
A7: 規模與電力
A8: 機架外 IT 電力占比 | B8: % | D8: =E8 -> 0.08 | E8: 0.08 | F8: =E8 -> 0.08 | G8: Assumed | H8: 管理、儲存、網路機櫃等；區間 5–12%（見 Sensitivity）。v4 未計
A9: PUE | B9: x | D9: 1.1 | E9: 1.2 | F9: 1.3 | G9: Analogy | H9: 液冷 AI 設施；v4＝1.2。S14
A10: 平均用電 ÷ 配電設計功率 | B10: % | D10: 0.7 | E10: 0.8 | F10: 0.9 | G10: Assumed | H10: Block 2 以逐步能量模型閉合檢查
A11: 電價 | B11: $/kWh | D11: 0.06 | E11: 0.08 | F11: 0.1 | G11: Verified/Analogy | H11: EIA 美國工業電價 2026 年約 8.6–8.7¢（S13）；低端為 PPA（v4＝0.06）
A12: IT 設備（機架以外）
A13: Scale-out 網路 ÷ 機架價格 | B13: % | D13: 0.05 | E13: 0.1 | F13: 0.15 | G13: Analogy | H13: 1,024 GPU 叢集網路約為 GPU BOM 4–8%（S10）；GW 級多一層以上交換，取 5–15%
A14: 儲存與管理設備 | B14: $/GPU | D14: 300 | E14: 500 | F14: 800 | G14: Assumed | H14: v4 約 $350/GPU（$25K/架）
A15: 廠房（每 MW IT，$M）
A16: 土地 | B16: $M/MW | D16: 0.02 | E16: 0.02 | F16: 0.02 | G16: Assumed | H16: v4：100 英畝 × $200K／GW
A17: 建物與基地工程 | B17: $M/MW | D17: 3 | E17: 3.6 | F17: 4.5 | G17: Assumed | H17: 分項為假設；總額以 JLL 校準（S12）
A18: 電力設施（變電、中壓、發電機、UPS） | B18: $M/MW | D18: 3.8 | E18: 4.5 | F18: 5.5 | G18: Assumed | H18: 同上
A19: 機械與散熱（液冷迴路、散熱設備） | B19: $M/MW | D19: 2 | E19: 2.5 | F19: 3.2 | G19: Assumed | H19: 機架內冷板與 manifold 含在機架價格
A20: 光纖、佈線、保全、BMS | B20: $M/MW | D20: 0.3 | E20: 0.4 | F20: 0.5 | G20: Assumed | H20: 同上
A21: 設計、管理與預備費 | B21: % 廠房 | D21: 0.12 | E21: 0.15 | F21: 0.18 | G21: Assumed | H21: v4＝15%
A22: 年限與資金成本
A23: IT 設備折舊年限 | B23: 年 | D23: 6 | E23: 6 | F23: 4 | G23: Verified | H23: CoreWeave 與主要 hyperscaler 6 年；Nebius 4 年、Lambda 5 年（S15）。高成本情境取 4
A24: 建物年限 | B24: 年 | D24: =E24 -> 30 | E24: 30 | F24: =E24 -> 30 | G24: Analogy | H24: v4
A25: 電力設施年限 | B25: 年 | D25: =E25 -> 20 | E25: 20 | F25: =E25 -> 20 | G25: Analogy | H25: v4
A26: 機械與散熱年限 | B26: 年 | D26: =E26 -> 15 | E26: 15 | F26: =E26 -> 15 | G26: Analogy | H26: v4
A27: 光纖與保全年限 | B27: 年 | D27: =E27 -> 10 | E27: 10 | F27: =E27 -> 10 | G27: Analogy | H27: v4
A28: WACC（經濟口徑） | B28: % | D28: 0.08 | E28: 0.1 | F28: 0.13 | G28: Assumed | H28: 與擁有者無關的單一假設；下游公司模型以自身 WACC 覆寫（Andy 2026-09-30 決定）
A29: 營運費用
A30: IT 維護 | B30: % IT 資本/年 | D30: 0.02 | E30: 0.03 | F30: 0.04 | G30: Analogy | H30: v4＝3%
A31: 廠房維護 | B31: % 廠房資本/年 | D31: 0.015 | E31: 0.02 | F31: 0.025 | G31: Analogy | H31: v4＝2%
A32: 人員 | B32: $M/GW/年 | D32: 50 | E32: 75 | F32: 100 | G32: Assumed | H32: v4：500 FTE × $150K
A33: 軟體授權與連線 | B33: $M/GW/年 | D33: 150 | E33: 200 | F33: 250 | G33: Assumed | H33: v4＝$200M
A34: 水與耗材 | B34: $M/MW/年 | D34: 0.04 | E34: 0.05 | F34: 0.06 | G34: Assumed | H34: v4＝$50K/MW
A35: 財產稅與保險 | B35: % 總資本/年 | D35: 0.003 | E35: 0.005 | F35: 0.008 | G35: Analogy | H35: v4＝0.5%

Sheet Spec_Rack
A1: Spec_Rack — 各世代機架規格（Block 1 只含功率與價格；效能規格於 Block 2 加入）
A2: 價格為買方取得價（CSP/hyperscaler 口徑）；Hopper 以 4 台 HGX 構成一架（32 GPU）以便比較
A4: 世代 | C4: Hopper H100 | D4: GB200 NVL72 | E4: GB300 NVL72 | F4: VR200 NVL72 | G4: Rubin Ultra NVL576 | H4: 標記／來源
A5: 平台／出貨 | C5: HGX ×4（32 GPU） | D5: 2024–25 出貨 | E5: 2025–26 主力 | F5: 2026 下半年開始出貨 | G5: 2027 預估（Kyber）
A6: GPU 封裝／架 | C6: 32 | D6: 72 | E6: 72 | F6: 72 | G6: 144
A7: 冷卻 | C7: 氣冷 | D7: 液冷 | E7: 液冷 | F7: 液冷（必須） | G7: 液冷
A8: 配電設計功率 低（kW） | C8: 38 | D8: 120 | E8: 132 | F8: 190 | G8: 550
A9: 配電設計功率 基準（kW） | C9: 41 | D9: 130 | E9: 137 | F9: 227 | G9: 600
A10: 配電設計功率 高（kW） | C10: 44 | D10: 140 | E10: 142 | F10: 230 | G10: 650
A11: 機架價格 低（$M） | C11: 0.9 | D11: 2.8 | E11: 4 | F11: 6.7 | G11: 23.4
A12: 機架價格 基準（$M） | C12: 1.1 | D12: 3.1 | E12: 5 | F12: 7.8 | G12: 31.2
A13: 機架價格 高（$M） | C13: 1.3 | D13: 3.4 | E13: 6.5 | F13: 9.1 | G13: 39
A14: 價格涵蓋範圍 | C14: 8 GPU 伺服器 + CPU、NIC、機內儲存；以部署當時取得價計 | D14: 運算匣＋NVLink 交換匣＋機架內冷卻 | E14: 同上 | F14: 運算匣＋交換匣＋冷卻＋約 $1M NAND；是否含部分網路待查（S11） | G14: 144 封裝；價格＝VR 每 GPU 價 × 1.5／2.0／2.5（推估）
A15: 功率來源 | C15: DGX H100 最大 10.2 kW／8 GPU（S1） | D15: 約 120–130 kW（S3）；v4＝139 | E15: 132–142 kW（S3、S5） | F15: Max-Q 約 190、Max-P 約 230 kW（S7）；Supermicro DLC-2 設計點 227 kW（S8） | G15: 約 600 kW（S7）
A16: 價格來源 | C16: HGX H100 8 GPU 伺服器約 $220–320K（S2，弱證據） | D16: $2.8–3.4M（S4）；Barron's 約 $3M | E16: MS 約 $4M；2026-08 採購單約 $5M；媒體 $6–6.5M（S4、S6） | F16: MS $7.8M（自購記憶體 $6.7M）；Bernstein $9.09M；報價 $5–7M（S9） | G16: 無公開報價；純推估，不進基準比較
A17: 標記 | C17: Analogy | D17: Interested-party | E17: Interested-party | F17: Interested-party | G17: Assumed
A19: 註：GPU 數為封裝數（Rubin Ultra 為 144 封裝，NVIDIA 以 576 die 命名為 NVL576）。
A21: B2. 效能規格（Block 2；藍字＝輸入；每 GPU 封裝）
A22: 服務精度 | C22: FP8 | D22: NVFP4 | E22: NVFP4 | F22: NVFP4 | G22: NVFP4 | H22: Hopper 不支援 FP4，以 FP8 服務
A23: 峰值 dense（基準）PF/GPU | C23: 1.979 | D23: 10 | E23: 15 | F23: 35 | G23: 73 | H23: Interested-party（NVIDIA 規格）：H100 FP8 dense 1,979 TF（v5.5 更正；v5.4 誤填 BF16 的 989）；GB200 FP4 10 PF（HGX B200 為 9）；B300 15；Rubin NVFP4 訓練 35；RU＝104×35/50 推估 [Derived]。S28
A24: 峰值（高情境：NVFP4 推論口徑）PF/GPU | C24: 1.979 | D24: 10 | E24: 15 | F24: 50 | G24: 104 | H24: Rubin 50 PF 含自適應壓縮；RU NVL576 15 EF ÷ 144。J2：只作高情境
A25: HBM 容量 GB/GPU | C25: 80 | D25: 186 | E25: 288 | F25: 288 | G25: 1024 | H25: GB200 NVL72 13.4 TB ÷ 72；InferenceX 以 192 計。RU HBM4e 約 1 TB/封裝。S28
A26: HBM 頻寬 TB/s/GPU | C26: 3.35 | D26: 8 | E26: 8 | F26: 22 | G26: 32 | H26: Rubin 22 TB/s（NVIDIA 2026 上修）；RU 4.6 PB/s ÷ 144。S28
A27: EP 通訊頻寬 TB/s/GPU（單向） | C27: 0.05 | D27: 0.9 | E27: 0.9 | F27: 1.8 | G27: 1.8 | H27: Hopper EP 跨節點走 400G IB；NVLink 5＝900 GB/s；NVLink 6＝1.8 TB/s（InferenceX 規格表 S20）；RU 取同 VR [Assumed]
A28: Scale-up 域 GPU 數 | C28: 8 | D28: 72 | E28: 72 | F28: 72 | G28: 144
A29: decode EP 基準寬度 | C29: 64 | D29: 32 | E29: 32 | F29: 32 | G29: 64 | H29: GB300 公開配方 dep32（S21）；Hopper 跨節點 [Analogy DeepSeek]；RU [Assumed]。權重放不下時自動加寬
A30: 專家權重 bytes/param | C30: 1 | D30: 0.5625 | E30: 0.5625 | F30: 0.5625 | G30: 0.5625 | H30: NVFP4＝4 bit＋每 16 值 8 bit scale＝0.5625 B；Hopper FP8
A31: 非專家權重 bytes/param | C31: 1 | D31: 1 | E31: 1 | F31: 1 | G31: 1 | H31: 注意力、路由、embedding 以 FP8 存放 [Analogy V4]
A32: 每 prefill 實例 GPU 數（算 TTFT） | C32: 8 | D32: 4 | E32: 4 | F32: 4 | G32: 8 | H32: GB300 配方 dep4 prefill（S21）
A33: GPU 功率 W/封裝（能量用） | C33: 700 | D33: 1200 | E33: 1400 | F33: 1800 | G33: 3600 | H33: Interested-party；Rubin 約 1.8 kW、RU 推估。僅用於能量下限估算
A34: HBM 存取能量 pJ/byte | C34: 31 | D34: 25 | E34: 25 | F34: 20 | G34: 18 | H34: Analogy：HBM3 約 3.9 pJ/bit、HBM3e 約 3、HBM4 約 2.5；區間 ±30%（S29）
A35: 計算用峰值 PF/GPU（依 Serving 峰值情境） | C35: =IF(Serving!$C$16=2,C24,C23) -> 1.979 | D35: =IF(Serving!$C$16=2,D24,D23) -> 10 | E35: =IF(Serving!$C$16=2,E24,E23) -> 15 | F35: =IF(Serving!$C$16=2,F24,F23) -> 35 | G35: =IF(Serving!$C$16=2,G24,G23) -> 73
A36: Ridge point（FLOP/byte） | C36: =C35*1000/C26 -> 590.74627 | D36: =D35*1000/D26 -> 1250 | E36: =E35*1000/E26 -> 1875 | F36: =F35*1000/F26 -> 1590.9091 | G36: =G35*1000/G26 -> 2281.25
A38: B3. 訓練峰值（Block 3；dense；每 GPU 封裝；MFU 以 FP8 列為分母，J7）
A39: BF16 dense PF/GPU | C39: 0.989 | D39: 2.5 | E39: 2.5 | F39: 4 | G39: 8 | H39: Interested-party（NVIDIA）：H100 989 TF；GB200／GB300 2.5；VR NVL72 288 PF ÷ 72＝4.0（S36）；RU 取 VR×2 [Assumed]
A40: FP8 dense PF/GPU（訓練基準，J7） | C40: 1.979 | D40: 5 | E40: 5 | F40: 17.5 | G40: 34.7 | H40: Interested-party（NVIDIA）：H100 1,979 TF；GB200／GB300 FP8 5 PF（B300 未提升 FP8）；VR NVL72 1,260 PF ÷ 72＝17.5（S36）；RU NVL576 5 EF ÷ 144 [模型內建知識，待查]
A41: NVFP4 訓練 dense PF/GPU（Tech_Registry 情境） | C41: 1.979 | D41: 10 | E41: 15 | F41: 35 | G41: 73 | H41: Hopper 無 FP4，取 FP8；GB200 10（NVIDIA：Rubin 為 Blackwell 3.5 倍）；GB300 15 [Assumed，區間 10–15]；VR 2,520 PF ÷ 72＝35（S36）；RU＝VR × 104/50 [Derived]

Sheet Arch
A1: Arch — 三層級代表架構（D5：每層級一個代表；參數為公開模型卡或推估）
A2: Luna／Sol 以公開權重模型為物理代表 [Analogy：對應封閉層級]；Astra 為封閉前沿代理，KV 以情境處理（J1）
A4: 參數 | B4: 單位 | C4: Luna（低層） | D4: Sol（中層） | E4: Astra（頂層） | F4: 標記 | G4: 來源／說明
A5: 代表架構 | C5: DeepSeek V4-Flash 類 | D5: DeepSeek V4-Pro 類 | E5: 封閉前沿代理 | F5: Decision | G5: D5；Andy 2026-09-30 確認
A6: 總參數 | B6: B | C6: 284 | D6: 1600 | E6: 4000 | F6: Verified／Assumed | G6: V4-Flash 284B、V4-Pro 1.6T（模型卡，S27）；Astra 4T [Assumed，區間 2–10T]
A7: 啟用參數 | B7: B | C7: 13 | D7: 49 | E7: 180 | F7: Verified／Assumed | G7: V4-Flash 13B、V4-Pro 49B；Astra 180B [Assumed，區間 60–250B]
A8: 層數 | B8: 層 | C8: 43 | D8: 61 | E8: 100 | F8: Verified／Assumed | G8: V4-Pro 61（config.json）；V4-Flash 43（二手）；Astra [Assumed]
A9: d_model | C9: 4096 | D9: 7168 | E9: 12288 | F9: Verified／Derived | G9: V4-Pro 7168；V4-Flash 由專家維度反推；Astra [Assumed]
A10: query heads | C10: 64 | D10: 128 | E10: 96 | F10: Verified／Analogy | G10: V4-Pro 128；V4-Flash 取 Pro 一半 [Analogy]
A11: head_dim | C11: 512 | D11: 512 | E11: 128 | F11: Verified／Assumed | G11: V4 單一 512 維 KV head；Astra 128
A12: routed experts | C12: 256 | D12: 384 | E12: 512 | F12: Verified／Assumed
A13: 每 token 啟用 routed experts | C13: 6 | D13: 6 | E13: 16 | F13: Verified／Assumed
A14: shared experts | C14: 1 | D14: 1 | E14: 1 | F14: Verified
A15: vocab | C15: 129280 | D15: 129280 | E15: 200000 | F15: Verified／Assumed
A16: 全注意力層比例 | B16: % | C16: 0.5 | D16: 0.5 | E16: 1 | F16: Verified／Assumed | G16: V4：CSA 與 HCA 約各半；Astra 全層注意力
A17: 全注意力層跨度上限（0＝全上下文） | B17: tok | C17: 4224 | D17: 4224 | E17: 0 | F17: Derived | G17: V4 CSA：top-k 1,024 壓縮塊 × 4 ＋ 128 窗口
A18: 其他層壓縮比 | B18: x | C18: 128 | D18: 128 | E18: 1 | F18: Verified | G18: V4 HCA 128× 壓縮
A19: 其他層滑動窗 | B19: tok | C19: 128 | D19: 128 | E19: 0 | F19: Verified
A20: Astra KV 情境（1 混合／2 全層 MLA／3 GQA-8） | B20: 選擇 | E20: 2 | F20: Decision | G20: J1：基準 2（Andy 2026-09-30 確認）
A21: KV bytes/token — 情境 1 | B21: B | C21: 2795 | D21: 3965 | E21: 14976 | F21: Derived／Assumed | G21: Luna 65×43、Sol 65×61（v4 推導，FP8 KV）；Astra 混合：26% 層 × 576 × 100 層（類 K3）
A22: KV bytes/token — 情境 2 | B22: B | C22: 2795 | D22: 3965 | E22: 57600 | F22: Derived／Assumed | G22: Astra 全層 MLA：576 × 100
A23: KV bytes/token — 情境 3 | B23: B | C23: 2795 | D23: 3965 | E23: 204800 | F23: Derived／Assumed | G23: Astra GQA-8：8 × 128 × 2 × 100
A24: 導出
A25: KV bytes/token（採用） | B25: B | C25: =CHOOSE(IF(C20="",1,C20),C21,C22,C23) -> 2795 | D25: =CHOOSE(IF(D20="",1,D20),D21,D22,D23) -> 3965 | E25: =CHOOSE(IF(E20="",1,E20),E21,E22,E23) -> 57600
A26: Embedding＋LM head 參數 | B26: B | C26: =C15*C9*2/1000000000 -> 1.0590618 | D26: =D15*D9*2/1000000000 -> 1.8533581 | E26: =E15*E9*2/1000000000 -> 4.9152
A27: 每 routed expert 參數 | B27: B | C27: =(C6-C7)/(C8*(C12-C13)) -> 0.025209302 | D27: =(D6-D7)/(D8*(D12-D13)) -> 0.067265157 | E27: =(E6-E7)/(E8*(E12-E13)) -> 0.077016129 | G27: 由公開總參數與啟用參數反推，確保總數吻合（v4 方法）
A28: 非專家參數（注意力、路由、embedding） | B28: B | C28: =C7-C8*(C13+C14)*C27 -> 5.412 | D28: =D7-D8*(D13+D14)*D27 -> 20.277778 | E28: =E7-E8*(E13+E14)*E27 -> 49.072581
A29: 專家參數 | B29: B | C29: =C6-C28 -> 278.588 | D29: =D6-D28 -> 1579.7222 | E29: =E6-E28 -> 3950.9274
A30: 注意力 FLOPs／每個被注意的 token | B30: FLOP | C30: =4*C10*C11*C8 -> 5636096 | D30: =4*D10*D11*D8 -> 15990784 | E30: =4*E10*E11*E8 -> 4915200
A31: 128K 上下文每序列 KV | B31: GB | C31: =C25*128000/1000000000 -> 0.35776 | D31: =D25*128000/1000000000 -> 0.50752 | E31: =E25*128000/1000000000 -> 7.3728

Sheet Serving
A1: Serving — 服務設定與各層級 SLO（主流：分離式 P/D、wide EP、attention DP、NVFP4、MTP、前綴快取）
A2: 藍字＝輸入。SLO 依 J3 採市場觀測輸出速度（Artificial Analysis 2026-09，S26）
A4: 全域設定 | B4: 單位 | C4: 值 | D4: 標記 | F4: 說明
A5: 服務架構 | C5: 分離式 P/D＋wide EP＋attention DP | D5: Decision | F5: D6 與 Block 2 命題
A6: MTP 草稿數 N | B6: tok | C6: 3 | D6: Analogy | F6: DeepSeek MTP；區間 1–5
A7: 每個草稿 token 接受率 α | B7: % | C7: 0.7 | D7: Verified-measured | F7: SGLang 修正後 0.57→0.70（S21）；區間 0.6–0.8
A8: 每步期望接受 token a | B8: tok | C8: =(1-C7^(C6+1))/(1-C7) -> 2.533 | D8: Derived | F8: (1−α^(N+1))/(1−α)
A9: HBM 保留比例（啟用值、工作區） | B9: % | C9: 0.1 | D9: Assumed | F9: 區間 5–20%
A10: 非專家權重占可用 HBM 上限 | B10: % | C10: 0.2 | D10: Assumed | F10: 超過時自動以注意力 TP 切分
A11: 專家權重占可用 HBM 上限 | B11: % | C11: 0.4 | D11: Assumed | F11: 超過時自動加寬 EP
A12: EP 啟用值 bytes/元素（dispatch＋combine） | B12: B | C12: 3 | D12: Analogy | F12: FP8 dispatch 1 B＋BF16 combine 2 B
A13: KV 讀取頻寬效率 η_mem | B13: % | C13: 0.7 | D13: Analogy | F13: 區間 0.5–0.85
A14: EP 通訊效率 η_link | B14: % | C14: 0.7 | D14: Analogy | F14: 區間 0.5–0.85
A15: 快取命中 KV 載入頻寬 | B15: TB/s/GPU | C15: 0.1 | D15: Assumed | F15: 主機記憶體／SSD 經 NIC 載入；區間 0.05–0.4。未計快取儲存成本
A16: 峰值情境（1＝dense 基準／2＝NVFP4 推論高） | B16: 選擇 | C16: 1 | D16: Decision | F16: J2：基準 1
A17: 基準利用率（第 0 層） | B17: % | C17: 0.6 | D17: Assumed | F17: J6：Andy 尚未給值，暫沿用 OpenAI v0.5 的 60%（區間 40–80%）。Unit_Cost 同時輸出 100% 版
A18: 實測→生產效率折減 | B18: x | C18: 1 | D18: Assumed | F18: 待 Andy 決定。基準測試為固定長度、穩態負載；生產環境另有長度變異、路由不均、故障。1.0＝不折減。作用：η_p、η_d 乘此值，每層延遲除以此值。第二來源（MLPerf、DeepSeek 自揭）目前均高於本模型，見 Calib H 節
A19: 各層級 SLO 與參考任務
A20: 項目 | B20: 單位 | C20: =Arch!C4 -> Luna（低層） | D20: =Arch!D4 -> Sol（中層） | E20: =Arch!E4 -> Astra（頂層） | F20: 說明
A21: SLO：每用戶 decode 速度下限 | B21: tok/s | C21: 120 | D21: 65 | E21: 55 | F21: Verified-measured（市場觀測）：GPT-5.6 Luna 約 120、GPT-5.6 Sol 約 68、GPT-6 Astra 約 52–56、Opus 5 約 54 tok/s（S26）。區間 Luna 100–300、Sol 50–100、Astra 30–75
A22: TTFT 上限（只作檢查） | B22: s | C22: 2 | D22: 3 | E22: 5 | F22: Assumed
A23: 參考 ISL（每次請求輸入） | B23: tok | C23: 8192 | D23: 16384 | E23: 32768 | F23: Assumed：Astra 用於長任務；上下文敏感度見 Sens_Perf
A24: 參考 OSL（含思考） | B24: tok | C24: 1024 | D24: 2048 | E24: 4096 | F24: Assumed
A25: decode 平均上下文 | B25: tok | C25: =C23+C24/2 -> 8704 | D25: =D23+D24/2 -> 17408 | E25: =E23+E24/2 -> 34816 | F25: Derived
A26: prefill 平均位置 | B26: tok | C26: =C23/2 -> 4096 | D26: =D23/2 -> 8192 | E26: =E23/2 -> 16384 | F26: Derived

Sheet Workload
A1: Workload — 任務制工作負載（每任務的 token 結構；思考 token 在物理上屬 decode）
A2: 任務組合權重不在第 0 層（J5）；本頁只定義標準任務。harness token 倍數預設 1.0，Block 5 接手
A4: 參數 | B4: 單位 | C4: 一般聊天 | D4: 推理聊天 | E4: 單代理（工具迴圈） | F4: 多代理研究 | G4: Coding agent（長程） | H4: 說明
A5: 輪數 T | B5: 輪 | C5: 1 | D5: 1 | E5: 4 | F5: 4 | G5: 30 | H5: Assumed
A6: 初始上下文 S（系統提示、歷史、工具定義） | B6: tok | C6: 2000 | D6: 2000 | E6: 3000 | F6: 3000 | G6: 12000 | H6: Assumed
A7: 每輪新輸入 u（使用者或工具結果） | B7: tok | C7: 500 | D7: 500 | E7: 1200 | F7: 1200 | G7: 2000 | H7: Assumed
A8: 每輪思考 token h | B8: tok | C8: 0 | D8: 3000 | E8: 400 | F8: 400 | G8: 600 | H8: Assumed；服務端思考占比待查
A9: 每輪可見輸出 o | B9: tok | C9: 500 | D9: 700 | E9: 200 | F9: 200 | G9: 400 | H9: Assumed
A10: 思考保留於上下文比例 ρ | B10: % | C10: 0 | D10: 0 | E10: 0 | F10: 0 | G10: 0 | H10: Assumed：多數 API 不保留前輪思考
A11: 歷史快取命中率 χ | B11: % | C11: 0.5 | D11: 0.5 | E11: 0.9 | F11: 0.9 | G11: 0.9 | H11: Assumed；代理迴圈前綴重用高
A12: 並行子代理數 m | B12: 個 | C12: 0 | D12: 0 | E12: 0 | F12: 3 | G12: 0 | H12: Assumed：子代理沿用單代理參數
A13: harness token 倍數 | B13: x | C13: 1 | D13: 1 | E13: 1 | F13: 1 | G13: 1 | H13: 預設 1.0（Block 5）
A15: 導出（每任務）
A16: 每輪上下文增量 u＋o＋ρh | B16: tok | C16: =C7+C9+C10*C8 -> 1000 | D16: =D7+D9+D10*D8 -> 1200 | E16: =E7+E9+E10*E8 -> 1400 | F16: =F7+F9+F10*F8 -> 1400 | G16: =G7+G9+G10*G8 -> 2400
A17: 單代理輸入總量 | B17: tok | C17: =C5*(C6+C7)+C16*C5*(C5-1)/2 -> 2500 | D17: =D5*(D6+D7)+D16*D5*(D5-1)/2 -> 2500 | E17: =E5*(E6+E7)+E16*E5*(E5-1)/2 -> 25200 | F17: =F5*(F6+F7)+F16*F5*(F5-1)/2 -> 25200 | G17: =G5*(G6+G7)+G16*G5*(G5-1)/2 -> 1464000
A18: 其中可快取（前綴） | B18: tok | C18: =C11*(C5*C6+C16*C5*(C5-1)/2) -> 1000 | D18: =D11*(D5*D6+D16*D5*(D5-1)/2) -> 1000 | E18: =E11*(E5*E6+E16*E5*(E5-1)/2) -> 18360 | F18: =F11*(F5*F6+F16*F5*(F5-1)/2) -> 18360 | G18: =G11*(G5*G6+G16*G5*(G5-1)/2) -> 1263600
A19: 其中新鮮 | B19: tok | C19: =C17-C18 -> 1500 | D19: =D17-D18 -> 1500 | E19: =E17-E18 -> 6840 | F19: =F17-F18 -> 6840 | G19: =G17-G18 -> 200400
A20: 單代理 decode（思考＋可見） | B20: tok | C20: =C5*(C8+C9) -> 500 | D20: =D5*(D8+D9) -> 3700 | E20: =E5*(E8+E9) -> 2400 | F20: =F5*(F8+F9) -> 2400 | G20: =G5*(G8+G9) -> 30000
A21: 系統倍數（1＋m）× harness | B21: x | C21: =(1+C12)*C13 -> 1 | D21: =(1+D12)*D13 -> 1 | E21: =(1+E12)*E13 -> 1 | F21: =(1+F12)*F13 -> 4 | G21: =(1+G12)*G13 -> 1
A22: 任務新鮮 prefill | B22: tok | C22: =C19*C21 -> 1500 | D22: =D19*D21 -> 1500 | E22: =E19*E21 -> 6840 | F22: =F19*F21 -> 27360 | G22: =G19*G21 -> 200400
A23: 任務快取 prefill | B23: tok | C23: =C18*C21 -> 1000 | D23: =D18*D21 -> 1000 | E23: =E18*E21 -> 18360 | F23: =F18*F21 -> 73440 | G23: =G18*G21 -> 1263600
A24: 任務 decode | B24: tok | C24: =C20*C21 -> 500 | D24: =D20*D21 -> 3700 | E24: =E20*E21 -> 2400 | F24: =F20*F21 -> 9600 | G24: =G20*G21 -> 30000
A25: 任務總 token | B25: tok | C25: =C22+C23+C24 -> 3000 | D25: =D22+D23+D24 -> 6200 | E25: =E22+E23+E24 -> 27600 | F25: =F22+F23+F24 -> 110400 | G25: =G22+G23+G24 -> 1494000
A26: decode 平均上下文 | B26: tok | C26: =C6+C7+(C5-1)/2*C16+(C8+C9)/2 -> 2750 | D26: =D6+D7+(D5-1)/2*D16+(D8+D9)/2 -> 4350 | E26: =E6+E7+(E5-1)/2*E16+(E8+E9)/2 -> 6600 | F26: =F6+F7+(F5-1)/2*F16+(F8+F9)/2 -> 6600 | G26: =G6+G7+(G5-1)/2*G16+(G8+G9)/2 -> 49300 | H26: Unit_Cost 的 decode 成本取各層級參考上下文；本列顯示任務實際上下文，差距大時看 Sens_Perf 的 ISL 情境
A27: 思考占 decode | B27: % | C27: =IF(C8+C9>0,C8/(C8+C9),0) -> 0 | D27: =IF(D8+D9>0,D8/(D8+D9),0) -> 0.81081081 | E27: =IF(E8+E9>0,E8/(E8+E9),0) -> 0.66666667 | F27: =IF(F8+F9>0,F8/(F8+F9),0) -> 0.66666667 | G27: =IF(G8+G9>0,G8/(G8+G9),0) -> 0.6
A28: 總 token ÷ 一般聊天 | B28: x | C28: =C25/$C$25 -> 1 | D28: =D25/$C$25 -> 2.0666667 | E28: =E25/$C$25 -> 9.2 | F28: =F25/$C$25 -> 36.8 | G28: =G25/$C$25 -> 498
A29: 總 token ÷ 推理聊天 | B29: x | C29: =C25/$D$25 -> 0.48387097 | D29: =D25/$D$25 -> 1 | E29: =E25/$D$25 -> 4.4516129 | F29: =F25/$D$25 -> 17.806452 | G29: =G25/$D$25 -> 240.96774
A30: 參照：Anthropic 揭露倍數（相對聊天） | B30: x | C30: 1 | E30: 4 | F30: 15 | H30: Interested-party：Anthropic 2025-06 多代理研究系統文章，agent 約 4 倍、多代理約 15 倍聊天 token（S25）。其『聊天』口徑未說明是否含思考，故兩個倍數並列
A32: 每任務成本（$／任務；經濟口徑、基準成本情境、基準利用率）
A33: VR200 × Luna | B33: $ | C33: =IF(ISNUMBER(Unit_Cost!M21),(C22*Unit_Cost!M19+C23*Unit_Cost!M20+C24*Unit_Cost!M21)/1000000,"SLO 不可達") -> 9.5539556e-05 | D33: =IF(ISNUMBER(Unit_Cost!M21),(D22*Unit_Cost!M19+D23*Unit_Cost!M20+D24*Unit_Cost!M21)/1000000,"SLO 不可達") -> 0.00063074831 | E33: =IF(ISNUMBER(Unit_Cost!M21),(E22*Unit_Cost!M19+E23*Unit_Cost!M20+E24*Unit_Cost!M21)/1000000,"SLO 不可達") -> 0.00045657296 | F33: =IF(ISNUMBER(Unit_Cost!M21),(F22*Unit_Cost!M19+F23*Unit_Cost!M20+F24*Unit_Cost!M21)/1000000,"SLO 不可達") -> 0.0018262919 | G33: =IF(ISNUMBER(Unit_Cost!M21),(G22*Unit_Cost!M19+G23*Unit_Cost!M20+G24*Unit_Cost!M21)/1000000,"SLO 不可達") -> 0.0066781516
A34: VR200 × Sol | B34: $ | C34: =IF(ISNUMBER(Unit_Cost!M34),(C22*Unit_Cost!M32+C23*Unit_Cost!M33+C24*Unit_Cost!M34)/1000000,"SLO 不可達") -> 0.00031048515 | D34: =IF(ISNUMBER(Unit_Cost!M34),(D22*Unit_Cost!M32+D23*Unit_Cost!M33+D24*Unit_Cost!M34)/1000000,"SLO 不可達") -> 0.0020308889 | E34: =IF(ISNUMBER(Unit_Cost!M34),(E22*Unit_Cost!M32+E23*Unit_Cost!M33+E24*Unit_Cost!M34)/1000000,"SLO 不可達") -> 0.0014815223 | F34: =IF(ISNUMBER(Unit_Cost!M34),(F22*Unit_Cost!M32+F23*Unit_Cost!M33+F24*Unit_Cost!M34)/1000000,"SLO 不可達") -> 0.005926089 | G34: =IF(ISNUMBER(Unit_Cost!M34),(G22*Unit_Cost!M32+G23*Unit_Cost!M33+G24*Unit_Cost!M34)/1000000,"SLO 不可達") -> 0.021794011
A35: VR200 × Astra | B35: $ | C35: =IF(ISNUMBER(Unit_Cost!M47),(C22*Unit_Cost!M45+C23*Unit_Cost!M46+C24*Unit_Cost!M47)/1000000,"SLO 不可達") -> 0.001522567 | D35: =IF(ISNUMBER(Unit_Cost!M47),(D22*Unit_Cost!M45+D23*Unit_Cost!M46+D24*Unit_Cost!M47)/1000000,"SLO 不可達") -> 0.010379432 | E35: =IF(ISNUMBER(Unit_Cost!M47),(E22*Unit_Cost!M45+E23*Unit_Cost!M46+E24*Unit_Cost!M47)/1000000,"SLO 不可達") -> 0.0072923954 | F35: =IF(ISNUMBER(Unit_Cost!M47),(F22*Unit_Cost!M45+F23*Unit_Cost!M46+F24*Unit_Cost!M47)/1000000,"SLO 不可達") -> 0.029169582 | G35: =IF(ISNUMBER(Unit_Cost!M47),(G22*Unit_Cost!M45+G23*Unit_Cost!M46+G24*Unit_Cost!M47)/1000000,"SLO 不可達") -> 0.10298231
A36: GB300 × Luna | B36: $ | C36: =IF(ISNUMBER(Unit_Cost!J21),(C22*Unit_Cost!J19+C23*Unit_Cost!J20+C24*Unit_Cost!J21)/1000000,"SLO 不可達") -> 0.00014928998 | D36: =IF(ISNUMBER(Unit_Cost!J21),(D22*Unit_Cost!J19+D23*Unit_Cost!J20+D24*Unit_Cost!J21)/1000000,"SLO 不可達") -> 0.00099239332 | E36: =IF(ISNUMBER(Unit_Cost!J21),(E22*Unit_Cost!J19+E23*Unit_Cost!J20+E24*Unit_Cost!J21)/1000000,"SLO 不可達") -> 0.00071291214 | F36: =IF(ISNUMBER(Unit_Cost!J21),(F22*Unit_Cost!J19+F23*Unit_Cost!J20+F24*Unit_Cost!J21)/1000000,"SLO 不可達") -> 0.0028516486 | G36: =IF(ISNUMBER(Unit_Cost!J21),(G22*Unit_Cost!J19+G23*Unit_Cost!J20+G24*Unit_Cost!J21)/1000000,"SLO 不可達") -> 0.010293136
A37: GB300 × Sol | B37: $ | C37: =IF(ISNUMBER(Unit_Cost!J34),(C22*Unit_Cost!J32+C23*Unit_Cost!J33+C24*Unit_Cost!J34)/1000000,"SLO 不可達") -> 0.00052566753 | D37: =IF(ISNUMBER(Unit_Cost!J34),(D22*Unit_Cost!J32+D23*Unit_Cost!J33+D24*Unit_Cost!J34)/1000000,"SLO 不可達") -> 0.0034962472 | E37: =IF(ISNUMBER(Unit_Cost!J34),(E22*Unit_Cost!J32+E23*Unit_Cost!J33+E24*Unit_Cost!J34)/1000000,"SLO 不可達") -> 0.0025091975 | F37: =IF(ISNUMBER(Unit_Cost!J34),(F22*Unit_Cost!J32+F23*Unit_Cost!J33+F24*Unit_Cost!J34)/1000000,"SLO 不可達") -> 0.01003679 | G37: =IF(ISNUMBER(Unit_Cost!J34),(G22*Unit_Cost!J32+G23*Unit_Cost!J33+G24*Unit_Cost!J34)/1000000,"SLO 不可達") -> 0.036129486
A38: GB300 × Astra | B38: $ | C38: =IF(ISNUMBER(Unit_Cost!J47),(C22*Unit_Cost!J45+C23*Unit_Cost!J46+C24*Unit_Cost!J47)/1000000,"SLO 不可達") -> 0.0035581725 | D38: =IF(ISNUMBER(Unit_Cost!J47),(D22*Unit_Cost!J45+D23*Unit_Cost!J46+D24*Unit_Cost!J47)/1000000,"SLO 不可達") -> 0.025025535 | E38: =IF(ISNUMBER(Unit_Cost!J47),(E22*Unit_Cost!J45+E23*Unit_Cost!J46+E24*Unit_Cost!J47)/1000000,"SLO 不可達") -> 0.017041287 | F38: =IF(ISNUMBER(Unit_Cost!J47),(F22*Unit_Cost!J45+F23*Unit_Cost!J46+F24*Unit_Cost!J47)/1000000,"SLO 不可達") -> 0.068165147 | G38: =IF(ISNUMBER(Unit_Cost!J47),(G22*Unit_Cost!J45+G23*Unit_Cost!J46+G24*Unit_Cost!J47)/1000000,"SLO 不可達") -> 0.22939741

Sheet Calib
A1: Calib — 以實測錨點校準效率係數（實測只校準係數，不取代推導）
A2: 錨點：DeepSeek V4-Pro（＝Sol 代表架構）、FP4、8K/1K、分離式 P/D，tok/s/GPU 為總 token 口徑。GB300 同一前緣上兩點聯立解出 η_d 與每層延遲；其餘各點為樣本外驗證
A4: A. 輸入
A5: η_p：prefill 達成峰值比例 | B5: % | C5: 0.3 | J5: Analogy：DeepSeek H800 線上 prefill 約 0.37（S30，待查）；區間 0.15–0.45。擬合結果對此不敏感（見 G 節）
A7: B. 錨點（每欄一個實測點）
A8: 項目 | B8: 單位
A9: 用途 | C9: 擬合點 1 | D9: 擬合點 2 | E9: 驗證 | F9: 驗證（舊軟體） | G9: 驗證（舊軟體） | H9: 驗證（口徑待查） | I9: 驗證（口徑待查）
A10: 世代索引 | C10: 3 | D10: 3 | E10: 3 | F10: 3 | G10: 2 | H10: 2 | I10: 3
A11: 世代 | C11: =INDEX(Spec_Rack!$C$4:$G$4,C10) -> GB300 NVL72 | D11: =INDEX(Spec_Rack!$C$4:$G$4,D10) -> GB300 NVL72 | E11: =INDEX(Spec_Rack!$C$4:$G$4,E10) -> GB300 NVL72 | F11: =INDEX(Spec_Rack!$C$4:$G$4,F10) -> GB300 NVL72 | G11: =INDEX(Spec_Rack!$C$4:$G$4,G10) -> GB200 NVL72 | H11: =INDEX(Spec_Rack!$C$4:$G$4,H10) -> GB200 NVL72 | I11: =INDEX(Spec_Rack!$C$4:$G$4,I10) -> GB300 NVL72
A12: 軟體／日期 | C12: InferenceX 最佳前緣（約 2026-07） | D12: InferenceX 最佳前緣（約 2026-07） | E12: SGLang＋MTP，2026-06 | F12: vLLM 無 MTP，2026-05-22 | G12: vLLM 無 MTP，2026-05-22 | H12: InferenceX 比較頁（0813） | I12: InferenceX 比較頁（0813）
A13: MTP（1＝有） | C13: 1 | D13: 1 | E13: 1 | F13: 0 | G13: 0 | H13: 1 | I13: 1
A14: 每用戶速度 | B14: tok/s | C14: 72 | D14: 130 | E14: 50 | F14: 27 | G14: 27 | H14: 110 | I14: 110
A15: ISL | B15: tok | C15: 8192 | D15: 8192 | E15: 8192 | F15: 8192 | G15: 8192 | H15: 8192 | I15: 8192
A16: OSL | B16: tok | C16: 1024 | D16: 1024 | E16: 1024 | F16: 1024 | G16: 1024 | H16: 1024 | I16: 1024
A17: 實測 tok/s/GPU（總 token） | B17: tok/s | C17: 9384.4 | D17: 3473.9 | E17: 11200 | F17: 6182 | G17: 2189 | H17: 3795.5 | I17: 6522.4
A18: 來源 | C18: S22 | D18: S22 | E18: S21 | F18: S20 | G18: S20 | H18: S23 | I18: S23
A19: 量測平台（獨立性） | C19: InferenceX（SemiAnalysis） | D19: InferenceX（SemiAnalysis） | E19: InferenceX（SemiAnalysis） | F19: InferenceX（SemiAnalysis） | G19: InferenceX（SemiAnalysis） | H19: InferenceX（SemiAnalysis） | I19: InferenceX（SemiAnalysis） | J19: 七個點全部來自同一平台（S21 為 SGLang 作者轉述 InferenceX 資料，不構成獨立來源）。第二來源見 H 節
A20: 點位標籤（世代｜用途｜速度） | C20: =C11&"｜"&C9&"｜"&TEXT(C14,"0")&" tok/s" -> GB300 NVL72｜擬合點 1｜72 tok/s | D20: =D11&"｜"&D9&"｜"&TEXT(D14,"0")&" tok/s" -> GB300 NVL72｜擬合點 2｜130 tok/s | E20: =E11&"｜"&E9&"｜"&TEXT(E14,"0")&" tok/s" -> GB300 NVL72｜驗證｜50 tok/s | F20: =F11&"｜"&F9&"｜"&TEXT(F14,"0")&" tok/s" -> GB300 NVL72｜驗證（舊軟體）｜27 tok/s | G20: =G11&"｜"&G9&"｜"&TEXT(G14,"0")&" tok/s" -> GB200 NVL72｜驗證（舊軟體）｜27 tok/s | H20: =H11&"｜"&H9&"｜"&TEXT(H14,"0")&" tok/s" -> GB200 NVL72｜驗證（口徑待查）｜110 tok/s | I20: =I11&"｜"&I9&"｜"&TEXT(I14,"0")&" tok/s" -> GB300 NVL72｜驗證（口徑待查）｜110 tok/s
A21: 口徑 | C21: 總 token（輸入＋輸出） | D21: 總 token（輸入＋輸出） | E21: 總 token（輸入＋輸出） | F21: 總 token（輸入＋輸出） | G21: 總 token（輸入＋輸出） | H21: 總 token（輸入＋輸出） | I21: 總 token（輸入＋輸出）
A22: C. 各點的模型量（Sol 架構；與 Perf 同一套公式）
A23: 計算用峰值 | B23: PF/GPU | C23: =INDEX(Spec_Rack!$C$35:$G$35,C10) -> 15 | D23: =INDEX(Spec_Rack!$C$35:$G$35,D10) -> 15 | E23: =INDEX(Spec_Rack!$C$35:$G$35,E10) -> 15 | F23: =INDEX(Spec_Rack!$C$35:$G$35,F10) -> 15 | G23: =INDEX(Spec_Rack!$C$35:$G$35,G10) -> 10 | H23: =INDEX(Spec_Rack!$C$35:$G$35,H10) -> 10 | I23: =INDEX(Spec_Rack!$C$35:$G$35,I10) -> 15
A24: HBM 容量 | B24: GB | C24: =INDEX(Spec_Rack!$C$25:$G$25,C10) -> 288 | D24: =INDEX(Spec_Rack!$C$25:$G$25,D10) -> 288 | E24: =INDEX(Spec_Rack!$C$25:$G$25,E10) -> 288 | F24: =INDEX(Spec_Rack!$C$25:$G$25,F10) -> 288 | G24: =INDEX(Spec_Rack!$C$25:$G$25,G10) -> 186 | H24: =INDEX(Spec_Rack!$C$25:$G$25,H10) -> 186 | I24: =INDEX(Spec_Rack!$C$25:$G$25,I10) -> 288
A25: HBM 頻寬 | B25: TB/s | C25: =INDEX(Spec_Rack!$C$26:$G$26,C10) -> 8 | D25: =INDEX(Spec_Rack!$C$26:$G$26,D10) -> 8 | E25: =INDEX(Spec_Rack!$C$26:$G$26,E10) -> 8 | F25: =INDEX(Spec_Rack!$C$26:$G$26,F10) -> 8 | G25: =INDEX(Spec_Rack!$C$26:$G$26,G10) -> 8 | H25: =INDEX(Spec_Rack!$C$26:$G$26,H10) -> 8 | I25: =INDEX(Spec_Rack!$C$26:$G$26,I10) -> 8
A26: EP 通訊頻寬 | B26: TB/s | C26: =INDEX(Spec_Rack!$C$27:$G$27,C10) -> 0.9 | D26: =INDEX(Spec_Rack!$C$27:$G$27,D10) -> 0.9 | E26: =INDEX(Spec_Rack!$C$27:$G$27,E10) -> 0.9 | F26: =INDEX(Spec_Rack!$C$27:$G$27,F10) -> 0.9 | G26: =INDEX(Spec_Rack!$C$27:$G$27,G10) -> 0.9 | H26: =INDEX(Spec_Rack!$C$27:$G$27,H10) -> 0.9 | I26: =INDEX(Spec_Rack!$C$27:$G$27,I10) -> 0.9
A27: EP 基準寬度 | C27: =INDEX(Spec_Rack!$C$29:$G$29,C10) -> 32 | D27: =INDEX(Spec_Rack!$C$29:$G$29,D10) -> 32 | E27: =INDEX(Spec_Rack!$C$29:$G$29,E10) -> 32 | F27: =INDEX(Spec_Rack!$C$29:$G$29,F10) -> 32 | G27: =INDEX(Spec_Rack!$C$29:$G$29,G10) -> 32 | H27: =INDEX(Spec_Rack!$C$29:$G$29,H10) -> 32 | I27: =INDEX(Spec_Rack!$C$29:$G$29,I10) -> 32
A28: 專家 bytes/param | B28: B | C28: =INDEX(Spec_Rack!$C$30:$G$30,C10) -> 0.5625 | D28: =INDEX(Spec_Rack!$C$30:$G$30,D10) -> 0.5625 | E28: =INDEX(Spec_Rack!$C$30:$G$30,E10) -> 0.5625 | F28: =INDEX(Spec_Rack!$C$30:$G$30,F10) -> 0.5625 | G28: =INDEX(Spec_Rack!$C$30:$G$30,G10) -> 0.5625 | H28: =INDEX(Spec_Rack!$C$30:$G$30,H10) -> 0.5625 | I28: =INDEX(Spec_Rack!$C$30:$G$30,I10) -> 0.5625
A29: 非專家 bytes/param | B29: B | C29: =INDEX(Spec_Rack!$C$31:$G$31,C10) -> 1 | D29: =INDEX(Spec_Rack!$C$31:$G$31,D10) -> 1 | E29: =INDEX(Spec_Rack!$C$31:$G$31,E10) -> 1 | F29: =INDEX(Spec_Rack!$C$31:$G$31,F10) -> 1 | G29: =INDEX(Spec_Rack!$C$31:$G$31,G10) -> 1 | H29: =INDEX(Spec_Rack!$C$31:$G$31,H10) -> 1 | I29: =INDEX(Spec_Rack!$C$31:$G$31,I10) -> 1
A30: 啟用參數 | B30: B | C30: =Arch!$D$7 -> 49 | D30: =Arch!$D$7 -> 49 | E30: =Arch!$D$7 -> 49 | F30: =Arch!$D$7 -> 49 | G30: =Arch!$D$7 -> 49 | H30: =Arch!$D$7 -> 49 | I30: =Arch!$D$7 -> 49
A31: 層數 | C31: =Arch!$D$8 -> 61 | D31: =Arch!$D$8 -> 61 | E31: =Arch!$D$8 -> 61 | F31: =Arch!$D$8 -> 61 | G31: =Arch!$D$8 -> 61 | H31: =Arch!$D$8 -> 61 | I31: =Arch!$D$8 -> 61
A32: d_model | C32: =Arch!$D$9 -> 7168 | D32: =Arch!$D$9 -> 7168 | E32: =Arch!$D$9 -> 7168 | F32: =Arch!$D$9 -> 7168 | G32: =Arch!$D$9 -> 7168 | H32: =Arch!$D$9 -> 7168 | I32: =Arch!$D$9 -> 7168
A33: 啟用專家 | C33: =Arch!$D$13 -> 6 | D33: =Arch!$D$13 -> 6 | E33: =Arch!$D$13 -> 6 | F33: =Arch!$D$13 -> 6 | G33: =Arch!$D$13 -> 6 | H33: =Arch!$D$13 -> 6 | I33: =Arch!$D$13 -> 6
A34: 非專家參數 | B34: B | C34: =Arch!$D$28 -> 20.277778 | D34: =Arch!$D$28 -> 20.277778 | E34: =Arch!$D$28 -> 20.277778 | F34: =Arch!$D$28 -> 20.277778 | G34: =Arch!$D$28 -> 20.277778 | H34: =Arch!$D$28 -> 20.277778 | I34: =Arch!$D$28 -> 20.277778
A35: 專家參數 | B35: B | C35: =Arch!$D$29 -> 1579.7222 | D35: =Arch!$D$29 -> 1579.7222 | E35: =Arch!$D$29 -> 1579.7222 | F35: =Arch!$D$29 -> 1579.7222 | G35: =Arch!$D$29 -> 1579.7222 | H35: =Arch!$D$29 -> 1579.7222 | I35: =Arch!$D$29 -> 1579.7222
A36: KV bytes/token | B36: B | C36: =Arch!$D$25 -> 3965 | D36: =Arch!$D$25 -> 3965 | E36: =Arch!$D$25 -> 3965 | F36: =Arch!$D$25 -> 3965 | G36: =Arch!$D$25 -> 3965 | H36: =Arch!$D$25 -> 3965 | I36: =Arch!$D$25 -> 3965
A37: 注意力 FLOPs／被注意 token | C37: =Arch!$D$30 -> 15990784 | D37: =Arch!$D$30 -> 15990784 | E37: =Arch!$D$30 -> 15990784 | F37: =Arch!$D$30 -> 15990784 | G37: =Arch!$D$30 -> 15990784 | H37: =Arch!$D$30 -> 15990784 | I37: =Arch!$D$30 -> 15990784
A38: 全注意力層比例 | B38: % | C38: =Arch!$D$16 -> 0.5 | D38: =Arch!$D$16 -> 0.5 | E38: =Arch!$D$16 -> 0.5 | F38: =Arch!$D$16 -> 0.5 | G38: =Arch!$D$16 -> 0.5 | H38: =Arch!$D$16 -> 0.5 | I38: =Arch!$D$16 -> 0.5
A39: 跨度上限 | C39: =Arch!$D$17 -> 4224 | D39: =Arch!$D$17 -> 4224 | E39: =Arch!$D$17 -> 4224 | F39: =Arch!$D$17 -> 4224 | G39: =Arch!$D$17 -> 4224 | H39: =Arch!$D$17 -> 4224 | I39: =Arch!$D$17 -> 4224
A40: 壓縮比 | C40: =Arch!$D$18 -> 128 | D40: =Arch!$D$18 -> 128 | E40: =Arch!$D$18 -> 128 | F40: =Arch!$D$18 -> 128 | G40: =Arch!$D$18 -> 128 | H40: =Arch!$D$18 -> 128 | I40: =Arch!$D$18 -> 128
A41: 滑動窗 | C41: =Arch!$D$19 -> 128 | D41: =Arch!$D$19 -> 128 | E41: =Arch!$D$19 -> 128 | F41: =Arch!$D$19 -> 128 | G41: =Arch!$D$19 -> 128 | H41: =Arch!$D$19 -> 128 | I41: =Arch!$D$19 -> 128
A42: decode 平均上下文 | B42: tok | C42: =C15+C16/2 -> 8704 | D42: =D15+D16/2 -> 8704 | E42: =E15+E16/2 -> 8704 | F42: =F15+F16/2 -> 8704 | G42: =G15+G16/2 -> 8704 | H42: =H15+H16/2 -> 8704 | I42: =I15+I16/2 -> 8704
A43: decode 被注意 token | B43: tok | C43: =C38*IF(C39=0,C42,MIN(C42,C39))+(1-C38)*(C42/C40+C41) -> 2210 | D43: =D38*IF(D39=0,D42,MIN(D42,D39))+(1-D38)*(D42/D40+D41) -> 2210 | E43: =E38*IF(E39=0,E42,MIN(E42,E39))+(1-E38)*(E42/E40+E41) -> 2210 | F43: =F38*IF(F39=0,F42,MIN(F42,F39))+(1-F38)*(F42/F40+F41) -> 2210 | G43: =G38*IF(G39=0,G42,MIN(G42,G39))+(1-G38)*(G42/G40+G41) -> 2210 | H43: =H38*IF(H39=0,H42,MIN(H42,H39))+(1-H38)*(H42/H40+H41) -> 2210 | I43: =I38*IF(I39=0,I42,MIN(I42,I39))+(1-I38)*(I42/I40+I41) -> 2210
A44: decode FLOPs/token | B44: GFLOP | C44: =(2*C30*1000000000+C37*C43)/1000000000 -> 133.33963 | D44: =(2*D30*1000000000+D37*D43)/1000000000 -> 133.33963 | E44: =(2*E30*1000000000+E37*E43)/1000000000 -> 133.33963 | F44: =(2*F30*1000000000+F37*F43)/1000000000 -> 133.33963 | G44: =(2*G30*1000000000+G37*G43)/1000000000 -> 133.33963 | H44: =(2*H30*1000000000+H37*H43)/1000000000 -> 133.33963 | I44: =(2*I30*1000000000+I37*I43)/1000000000 -> 133.33963
A45: prefill 平均位置 | B45: tok | C45: =C15/2 -> 4096 | D45: =D15/2 -> 4096 | E45: =E15/2 -> 4096 | F45: =F15/2 -> 4096 | G45: =G15/2 -> 4096 | H45: =H15/2 -> 4096 | I45: =I15/2 -> 4096
A46: prefill 被注意 token | B46: tok | C46: =C38*IF(C39=0,C45,MIN(C45,C39))+(1-C38)*(C45/C40+C41) -> 2128 | D46: =D38*IF(D39=0,D45,MIN(D45,D39))+(1-D38)*(D45/D40+D41) -> 2128 | E46: =E38*IF(E39=0,E45,MIN(E45,E39))+(1-E38)*(E45/E40+E41) -> 2128 | F46: =F38*IF(F39=0,F45,MIN(F45,F39))+(1-F38)*(F45/F40+F41) -> 2128 | G46: =G38*IF(G39=0,G45,MIN(G45,G39))+(1-G38)*(G45/G40+G41) -> 2128 | H46: =H38*IF(H39=0,H45,MIN(H45,H39))+(1-H38)*(H45/H40+H41) -> 2128 | I46: =I38*IF(I39=0,I45,MIN(I45,I39))+(1-I38)*(I45/I40+I41) -> 2128
A47: prefill FLOPs/token | B47: GFLOP | C47: =(2*C30*1000000000+C37*C46)/1000000000 -> 132.02839 | D47: =(2*D30*1000000000+D37*D46)/1000000000 -> 132.02839 | E47: =(2*E30*1000000000+E37*E46)/1000000000 -> 132.02839 | F47: =(2*F30*1000000000+F37*F46)/1000000000 -> 132.02839 | G47: =(2*G30*1000000000+G37*G46)/1000000000 -> 132.02839 | H47: =(2*H30*1000000000+H37*H46)/1000000000 -> 132.02839 | I47: =(2*I30*1000000000+I37*I46)/1000000000 -> 132.02839
A48: 可用 HBM | B48: GB | C48: =C24*(1-Serving!$C$9) -> 259.2 | D48: =D24*(1-Serving!$C$9) -> 259.2 | E48: =E24*(1-Serving!$C$9) -> 259.2 | F48: =F24*(1-Serving!$C$9) -> 259.2 | G48: =G24*(1-Serving!$C$9) -> 167.4 | H48: =H24*(1-Serving!$C$9) -> 167.4 | I48: =I24*(1-Serving!$C$9) -> 259.2
A49: 注意力 TP 度 | C49: =MAX(1,CEILING(C34*C29/(Serving!$C$10*C48),1)) -> 1 | D49: =MAX(1,CEILING(D34*D29/(Serving!$C$10*D48),1)) -> 1 | E49: =MAX(1,CEILING(E34*E29/(Serving!$C$10*E48),1)) -> 1 | F49: =MAX(1,CEILING(F34*F29/(Serving!$C$10*F48),1)) -> 1 | G49: =MAX(1,CEILING(G34*G29/(Serving!$C$10*G48),1)) -> 1 | H49: =MAX(1,CEILING(H34*H29/(Serving!$C$10*H48),1)) -> 1 | I49: =MAX(1,CEILING(I34*I29/(Serving!$C$10*I48),1)) -> 1
A50: EP 寬度 | C50: =MAX(C27,CEILING(C35*C28/(Serving!$C$11*C48),1)) -> 32 | D50: =MAX(D27,CEILING(D35*D28/(Serving!$C$11*D48),1)) -> 32 | E50: =MAX(E27,CEILING(E35*E28/(Serving!$C$11*E48),1)) -> 32 | F50: =MAX(F27,CEILING(F35*F28/(Serving!$C$11*F48),1)) -> 32 | G50: =MAX(G27,CEILING(G35*G28/(Serving!$C$11*G48),1)) -> 32 | H50: =MAX(H27,CEILING(H35*H28/(Serving!$C$11*H48),1)) -> 32 | I50: =MAX(I27,CEILING(I35*I28/(Serving!$C$11*I48),1)) -> 32
A51: 每 GPU 權重 | B51: GB | C51: =C34*C29/C49+C35*C28/C50 -> 48.046332 | D51: =D34*D29/D49+D35*D28/D50 -> 48.046332 | E51: =E34*E29/E49+E35*E28/E50 -> 48.046332 | F51: =F34*F29/F49+F35*F28/F50 -> 48.046332 | G51: =G34*G29/G49+G35*G28/G50 -> 48.046332 | H51: =H34*H29/H49+H35*H28/H50 -> 48.046332 | I51: =I34*I29/I49+I35*I28/I50 -> 48.046332
A52: 草稿數（無 MTP＝0） | C52: =Serving!$C$6*C13 -> 3 | D52: =Serving!$C$6*D13 -> 3 | E52: =Serving!$C$6*E13 -> 3 | F52: =Serving!$C$6*F13 -> 0 | G52: =Serving!$C$6*G13 -> 0 | H52: =Serving!$C$6*H13 -> 3 | I52: =Serving!$C$6*I13 -> 3
A53: 每步接受 token | C53: =IF(C13=1,Serving!$C$8,1) -> 2.533 | D53: =IF(D13=1,Serving!$C$8,1) -> 2.533 | E53: =IF(E13=1,Serving!$C$8,1) -> 2.533 | F53: =IF(F13=1,Serving!$C$8,1) -> 1 | G53: =IF(G13=1,Serving!$C$8,1) -> 1 | H53: =IF(H13=1,Serving!$C$8,1) -> 2.533 | I53: =IF(I13=1,Serving!$C$8,1) -> 2.533
A54: prefill tok/s/GPU（η_p 基準） | B54: tok/s | C54: =$C$5*C23*1000000000000000/(C47*1000000000) -> 34083.579 | D54: =$C$5*D23*1000000000000000/(D47*1000000000) -> 34083.579 | E54: =$C$5*E23*1000000000000000/(E47*1000000000) -> 34083.579 | F54: =$C$5*F23*1000000000000000/(F47*1000000000) -> 34083.579 | G54: =$C$5*G23*1000000000000000/(G47*1000000000) -> 22722.386 | H54: =$C$5*H23*1000000000000000/(H47*1000000000) -> 22722.386 | I54: =$C$5*I23*1000000000000000/(I47*1000000000) -> 34083.579
A55: 每序列算力時間（η＝1） | B55: ms | C55: =(C52+1)*C44/C23/1000 -> 0.035557235 | D55: =(D52+1)*D44/D23/1000 -> 0.035557235 | E55: =(E52+1)*E44/E23/1000 -> 0.035557235 | F55: =(F52+1)*F44/F23/1000 -> 0.0088893088 | G55: =(G52+1)*G44/G23/1000 -> 0.013333963 | H55: =(H52+1)*H44/H23/1000 -> 0.053335853 | I55: =(I52+1)*I44/I23/1000 -> 0.035557235
A56: 實測反推 decode tok/s（每 decode GPU） | B56: tok/s | C56: =C16/((C15+C16)/C17-C15/C54) -> 1380.6028 | D56: =D16/((D15+D16)/D17-D15/D54) -> 424.44263 | E56: =E16/((E15+E16)/E17-E15/E54) -> 1757.9194 | F56: =F16/((F15+F16)/F17-F15/F54) -> 818.91873 | G56: =G16/((G15+G16)/G17-G15/G54) -> 266.00055 | H56: =H16/((H15+H16)/H17-H15/H54) -> 495.25708 | I56: =I16/((I15+I16)/I17-I15/I54) -> 873.25335 | J56: 只對擬合點有意義；假設 P:D GPU 依工作量配比
A57: 實測反推批次 | B57: 序列/GPU | C57: =C56/C14 -> 19.175039 | D57: =D56/D14 -> 3.2649433 | E57: =E56/E14 -> 35.158388 | F57: =F56/F14 -> 30.330323 | G57: =G56/G14 -> 9.8518722 | H57: =H56/H14 -> 4.502337 | I57: =I56/I14 -> 7.9386669
A59: D. 擬合（擬合點 1、2 聯立；假設兩點皆為算力項綁定，見下列檢查）
A60: η_d：decode 每序列算力效率 | B60: % | C60: =(C57-D57)*C55/(1000*(C53/C14-D53/D14)) -> 0.036042379 | J60: B×c/η＝1000×a/s − 固定延遲；兩點相減消去固定延遲
A61: 每步固定延遲（GB300、Sol、含 MTP） | B61: ms | C61: =1000*C53/C14-C57*C55/C60 -> 16.263619
A62: 每層每次前向固定延遲 | B62: µs | C62: =(C61-C51/C25)*1000/(C31+C52) -> 160.27856 | J62: （固定延遲 − 權重讀取時間）÷（層數＋草稿數）：涵蓋 all-to-all 延遲、kernel 啟動、同步
A63: 檢查：擬合點 1 算力項為綁定 | C63: =IF(C55/C60>=MAX(C36*C42/(C25*Serving!$C$13)/1000000000,(C52+1)*C31*C33*C32*Serving!$C$12/(C26*Serving!$C$14)/1000000000),"成立","不成立") -> 成立
A65: E. 各世代採用參數（GB300＝擬合值；其他世代＝擬合值 × 倍數）
A66: 世代 | C66: =Spec_Rack!C4 -> Hopper H100 | D66: =Spec_Rack!D4 -> GB200 NVL72 | E66: =Spec_Rack!E4 -> GB300 NVL72 | F66: =Spec_Rack!F4 -> VR200 NVL72 | G66: =Spec_Rack!G4 -> Rubin Ultra NVL576
A67: η_d 倍數 | B67: x | C67: 1.5 | D67: 1 | E67: 1 | F67: 1 | G67: 1 | J67: Hopper：v5.4 取 3（DeepSeek H800 線上 decode 約達峰值 18%，S30；當時峰值誤用 989 TF）。v5.5 峰值更正為 FP8 1,979 TF，倍數同步減半為 1.5，使 Hopper 產出不變；S30 口徑查核後重推 [Analogy，區間 0.5–2.5]；GB200、VR200 沿用 GB300 [Analogy]；RU [Assumed]
A68: 每層延遲倍數 | B68: x | C68: 1.5 | D68: 1 | E68: 1 | F68: 1 | G68: 1 | J68: Hopper EP 跨節點走 IB [Assumed 1.5，區間 1–3]
A69: η_p 倍數 | B69: x | C69: 0.5 | D69: 1 | E69: 1 | F69: 1 | G69: 1 | J69: Hopper 0.5：v5.5 峰值更正（989→1,979 TF）後維持 prefill 產出不變（誤差 0.05%）；S30 口徑查核後重推
A70: η_d（採用） | B70: % | C70: =$C$60*C67 -> 0.054063569 | D70: =$C$60*D67 -> 0.036042379 | E70: =$C$60*E67 -> 0.036042379 | F70: =$C$60*F67 -> 0.036042379 | G70: =$C$60*G67 -> 0.036042379
A71: 每層延遲（採用） | B71: µs | C71: =$C$62*C68 -> 240.41784 | D71: =$C$62*D68 -> 160.27856 | E71: =$C$62*E68 -> 160.27856 | F71: =$C$62*F68 -> 160.27856 | G71: =$C$62*G68 -> 160.27856
A72: η_p（採用） | B72: % | C72: =$C$5*C69 -> 0.15 | D72: =$C$5*D69 -> 0.3 | E72: =$C$5*E69 -> 0.3 | F72: =$C$5*F69 -> 0.3 | G72: =$C$5*G69 -> 0.3
A74: F. 樣本外驗證（以採用參數重算各點）
A75: η_d（該世代） | B75: % | C75: =INDEX($C$70:$G$70,C10) -> 0.036042379 | D75: =INDEX($C$70:$G$70,D10) -> 0.036042379 | E75: =INDEX($C$70:$G$70,E10) -> 0.036042379 | F75: =INDEX($C$70:$G$70,F10) -> 0.036042379 | G75: =INDEX($C$70:$G$70,G10) -> 0.036042379 | H75: =INDEX($C$70:$G$70,H10) -> 0.036042379 | I75: =INDEX($C$70:$G$70,I10) -> 0.036042379
A76: 每層延遲（該世代） | B76: µs | C76: =INDEX($C$71:$G$71,C10) -> 160.27856 | D76: =INDEX($C$71:$G$71,D10) -> 160.27856 | E76: =INDEX($C$71:$G$71,E10) -> 160.27856 | F76: =INDEX($C$71:$G$71,F10) -> 160.27856 | G76: =INDEX($C$71:$G$71,G10) -> 160.27856 | H76: =INDEX($C$71:$G$71,H10) -> 160.27856 | I76: =INDEX($C$71:$G$71,I10) -> 160.27856
A77: η_p（該世代） | B77: % | C77: =INDEX($C$72:$G$72,C10) -> 0.3 | D77: =INDEX($C$72:$G$72,D10) -> 0.3 | E77: =INDEX($C$72:$G$72,E10) -> 0.3 | F77: =INDEX($C$72:$G$72,F10) -> 0.3 | G77: =INDEX($C$72:$G$72,G10) -> 0.3 | H77: =INDEX($C$72:$G$72,H10) -> 0.3 | I77: =INDEX($C$72:$G$72,I10) -> 0.3
A78: prefill tok/s/GPU | B78: tok/s | C78: =C77*C23*1000000000000000/(C47*1000000000) -> 34083.579 | D78: =D77*D23*1000000000000000/(D47*1000000000) -> 34083.579 | E78: =E77*E23*1000000000000000/(E47*1000000000) -> 34083.579 | F78: =F77*F23*1000000000000000/(F47*1000000000) -> 34083.579 | G78: =G77*G23*1000000000000000/(G47*1000000000) -> 22722.386 | H78: =H77*H23*1000000000000000/(H47*1000000000) -> 22722.386 | I78: =I77*I23*1000000000000000/(I47*1000000000) -> 34083.579
A79: 每步固定延遲 | B79: ms | C79: =C51/C25+(C31+C52)*C76/1000 -> 16.263619 | D79: =D51/D25+(D31+D52)*D76/1000 -> 16.263619 | E79: =E51/E25+(E31+E52)*E76/1000 -> 16.263619 | F79: =F51/F25+(F31+F52)*F76/1000 -> 15.782784 | G79: =G51/G25+(G31+G52)*G76/1000 -> 15.782784 | H79: =H51/H25+(H31+H52)*H76/1000 -> 16.263619 | I79: =I51/I25+(I31+I52)*I76/1000 -> 16.263619
A80: 每序列每步時間 | B80: ms | C80: =MAX(C55/C75,C36*C42/(C25*Serving!$C$13)/1000000000,(C52+1)*C31*C33*C32*Serving!$C$12*(C50-1)/C50/(C26*Serving!$C$14)/1000000000) -> 0.98653962 | D80: =MAX(D55/D75,D36*D42/(D25*Serving!$C$13)/1000000000,(D52+1)*D31*D33*D32*Serving!$C$12*(D50-1)/D50/(D26*Serving!$C$14)/1000000000) -> 0.98653962 | E80: =MAX(E55/E75,E36*E42/(E25*Serving!$C$13)/1000000000,(E52+1)*E31*E33*E32*Serving!$C$12*(E50-1)/E50/(E26*Serving!$C$14)/1000000000) -> 0.98653962 | F80: =MAX(F55/F75,F36*F42/(F25*Serving!$C$13)/1000000000,(F52+1)*F31*F33*F32*Serving!$C$12*(F50-1)/F50/(F26*Serving!$C$14)/1000000000) -> 0.24663491 | G80: =MAX(G55/G75,G36*G42/(G25*Serving!$C$13)/1000000000,(G52+1)*G31*G33*G32*Serving!$C$12*(G50-1)/G50/(G26*Serving!$C$14)/1000000000) -> 0.36995236 | H80: =MAX(H55/H75,H36*H42/(H25*Serving!$C$13)/1000000000,(H52+1)*H31*H33*H32*Serving!$C$12*(H50-1)/H50/(H26*Serving!$C$14)/1000000000) -> 1.4798094 | I80: =MAX(I55/I75,I36*I42/(I25*Serving!$C$13)/1000000000,(I52+1)*I31*I33*I32*Serving!$C$12*(I50-1)/I50/(I26*Serving!$C$14)/1000000000) -> 0.98653962
A81: SLO 批次上限 | B81: 序列 | C81: =(1000*C53/C14-C79)/C80 -> 19.175039 | D81: =(1000*D53/D14-D79)/D80 -> 3.2649433 | E81: =(1000*E53/E14-E79)/E80 -> 34.865686 | F81: =(1000*F53/F14-F79)/F80 -> 86.176988 | G81: =(1000*G53/G14-G79)/G80 -> 57.451325 | H81: =(1000*H53/H14-H79)/H80 -> 4.5706245 | I81: =(1000*I53/I14-I79)/I80 -> 6.8559368
A82: 容量批次上限 | B82: 序列 | C82: =(C48-C51)*1000000000/(C36*C42) -> 6118.3815 | D82: =(D48-D51)*1000000000/(D36*D42) -> 6118.3815 | E82: =(E48-E51)*1000000000/(E36*E42) -> 6118.3815 | F82: =(F48-F51)*1000000000/(F36*F42) -> 6118.3815 | G82: =(G48-G51)*1000000000/(G36*G42) -> 3458.3878 | H82: =(H48-H51)*1000000000/(H36*H42) -> 3458.3878 | I82: =(I48-I51)*1000000000/(I36*I42) -> 6118.3815
A83: B* | B83: 序列 | C83: =MAX(0,MIN(C81,C82)) -> 19.175039 | D83: =MAX(0,MIN(D81,D82)) -> 3.2649433 | E83: =MAX(0,MIN(E81,E82)) -> 34.865686 | F83: =MAX(0,MIN(F81,F82)) -> 86.176988 | G83: =MAX(0,MIN(G81,G82)) -> 57.451325 | H83: =MAX(0,MIN(H81,H82)) -> 4.5706245 | I83: =MAX(0,MIN(I81,I82)) -> 6.8559368
A84: decode tok/s/GPU | B84: tok/s | C84: =IF(C83>0,C83*C53/((C79+C83*C80)/1000),0) -> 1380.6028 | D84: =IF(D83>0,D83*D53/((D79+D83*D80)/1000),0) -> 424.44263 | E84: =IF(E83>0,E83*E53/((E79+E83*E80)/1000),0) -> 1743.2843 | F84: =IF(F83>0,F83*F53/((F79+F83*F80)/1000),0) -> 2326.7787 | G84: =IF(G83>0,G83*G53/((G79+G83*G80)/1000),0) -> 1551.1858 | H84: =IF(H83>0,H83*H53/((H79+H83*H80)/1000),0) -> 502.7687 | I84: =IF(I83>0,I83*I53/((I79+I83*I80)/1000),0) -> 754.15305
A85: 模型 tok/s/GPU（總 token） | B85: tok/s | C85: =IF(C84>0,(C15+C16)/(C15/C78+C16/C84),0) -> 9384.4 | D85: =IF(D84>0,(D15+D16)/(D15/D78+D16/D84),0) -> 3473.9 | E85: =IF(E84>0,(E15+E16)/(E15/E78+E16/E84),0) -> 11133.832 | F85: =IF(F84>0,(F15+F16)/(F15/F78+F16/F84),0) -> 13544.102 | G85: =IF(G84>0,(G15+G16)/(G15/G78+G16/G84),0) -> 9029.4015 | H85: =IF(H84>0,(H15+H16)/(H15/H78+H16/H84),0) -> 3844.4092 | I85: =IF(I84>0,(I15+I16)/(I15/I78+I16/I84),0) -> 5766.6139
A86: 模型 ÷ 實測 | B86: x | C86: =C85/C17 -> 1 | D86: =D85/D17 -> 1 | E86: =E85/E17 -> 0.99409213 | F86: =F85/F17 -> 2.1908933 | G86: =G85/G17 -> 4.1248979 | H86: =H85/H17 -> 1.0128861 | I86: =I85/I17 -> 0.88412453
A87: 判讀 | C87: 擬合點：應為 1.00 | D87: 擬合點：應為 1.00 | E87: 同世代、不同日期與引擎：檢驗前緣形狀 | F87: 舊軟體：模型應高於實測（軟體差距） | G87: 舊軟體＋GB200 記憶體限制配方（S20 說明） | H87: 工作負載標示不明（頁面預設為 agentic） | I87: 同上
A89: G. η_p 敏感度：擬合結果隨 η_p 的變化（η_p 僅影響 prefill／decode GPU 分攤）
A90: η_p | C90: 0.15 | D90: 0.3 | E90: 0.45
A91: 擬合點 1 prefill tok/s | C91: =C90*$C$23*1000000000000000/($C$47*1000000000) -> 17041.789 | D91: =D90*$C$23*1000000000000000/($C$47*1000000000) -> 34083.579 | E91: =E90*$C$23*1000000000000000/($C$47*1000000000) -> 51125.368
A92: 擬合點 2 prefill tok/s | C92: =C90*$D$23*1000000000000000/($D$47*1000000000) -> 17041.789 | D92: =D90*$D$23*1000000000000000/($D$47*1000000000) -> 34083.579 | E92: =E90*$D$23*1000000000000000/($D$47*1000000000) -> 51125.368
A93: 擬合點 1 反推批次 | C93: =$C$16/(($C$15+$C$16)/$C$17-$C$15/C91)/$C$14 -> 28.367589 | D93: =$C$16/(($C$15+$C$16)/$C$17-$C$15/D91)/$C$14 -> 19.175039 | E93: =$C$16/(($C$15+$C$16)/$C$17-$C$15/E91)/$C$14 -> 17.305726
A94: 擬合點 2 反推批次 | C94: =$D$16/(($D$15+$D$16)/$D$17-$D$15/C92)/$D$14 -> 3.6261997 | D94: =$D$16/(($D$15+$D$16)/$D$17-$D$15/D92)/$D$14 -> 3.2649433 | E94: =$D$16/(($D$15+$D$16)/$D$17-$D$15/E92)/$D$14 -> 3.1600059
A95: η_d | C95: =(C93-C94)*$C$55/(1000*($C$53/$C$14-$D$53/$D$14)) -> 0.056048596 | D95: =(D93-D94)*$C$55/(1000*($C$53/$C$14-$D$53/$D$14)) -> 0.036042379 | E95: =(E93-E94)*$C$55/(1000*($C$53/$C$14-$D$53/$D$14)) -> 0.032045401
A96: 每層延遲 µs | C96: =((1000*$C$53/$C$14-C93*$C$55/C95)-$C$51/$C$25)*1000/($C$31+$C$52) -> 174.66191 | D96: =((1000*$C$53/$C$14-D93*$C$55/D95)-$C$51/$C$25)*1000/($C$31+$C$52) -> 160.27856 | E96: =((1000*$C$53/$C$14-E93*$C$55/E95)-$C$51/$C$25)*1000/($C$31+$C$52) -> 155.82055
A98: H. 第二來源驗證：MLPerf Inference DeepSeek-R1（MLCommons 稽核；提交者 NVIDIA 為利害關係方）
A99: R1 架構與工作負載（驗證專用輸入）
A100: 總參數 | B100: B | C100: 671 | J100: Verified：DeepSeek-V3/R1 模型卡；ISL／OSL 800／3,880（MLCommons 2025-09，S33）
A101: 啟用參數 | B101: B | C101: 37
A102: 層數 | C102: 61
A103: d_model | C103: 7168
A104: routed experts | C104: 256
A105: 啟用 experts | C105: 8
A106: shared experts | C106: 1
A107: vocab | C107: 129280
...

Sheet Tech_Registry
A1: Tech_Registry — 新技術登錄與掛鉤（每列＝技術 × 作用物理量；基準值只在『已在基準＝否』且開關＝1 時套用）
A2: 有效倍數＝1＋開關 × 採用比例 ×（所選倍數−1）；已在基準者恆為 1，避免重複計算。主流判定（J14）：至少兩家實驗室公開採用；L 欄可由 Andy 覆寫
A4: ID | B4: 技術 | C4: 掛鉤代碼 | D4: 作用物理量 | E4: 倍數 低 | F4: 倍數 基準 | G4: 倍數 高 | H4: 情境（1／2／3） | I4: 狀態 | J4: 公開採用實驗室數 | K4: 主流判定（J14） | L4: Andy 覆寫 | M4: 已在基準 | N4: 採用比例 | O4: 開關（0／1） | P4: 有效倍數 | Q4: 證據標記 | R4: 來源／說明 | S4: 下次檢查觸發 | T4: 一致性檢查
A5: T01 | B5: MTP 推測解碼 | C5: — | D5: Serving!C6:C8（N、α） | E5: 1 | F5: 1 | G5: 1 | H5: 2 | I5: 主流 | J5: 3 | K5: =IF(J5>=2,"主流","非主流") -> 主流 | M5: 是 | N5: 1 | O5: 1 | P5: =IF(M5="是",1,1+O5*N5*(CHOOSE(H5,E5,F5,G5)-1)) -> 1 | Q5: Verified | R5: DeepSeek V3／V4、GLM-4.5、MiMo 公開採用；已在 Serving 基準 | S5: — | T5: =IF(AND(IF(L5="",K5,L5)="主流",M5="否"),"主流但未入基準：須 Andy 判定",IF(AND(IF(L5="",K5,L5)="非主流",M5="是",I5<>"早期採用"),"非主流卻在基準","一致")) -> 一致
A6: T02 | B6: 壓縮／稀疏注意力（CSA/HCA 類） | C6: — | D6: Arch 列 16–19 | E6: 1 | F6: 1 | G6: 1 | H6: 2 | I6: 主流 | J6: 3 | K6: =IF(J6>=2,"主流","非主流") -> 主流 | M6: 是 | N6: 1 | O6: 1 | P6: =IF(M6="是",1,1+O6*N6*(CHOOSE(H6,E6,F6,G6)-1)) -> 1 | Q6: Verified | R6: DeepSeek V4 CSA/HCA、DeepSeek／GLM 稀疏注意力、Qwen3-Next 混合注意力；Luna／Sol 基準已含（S27、S35） | S6: — | T6: =IF(AND(IF(L6="",K6,L6)="主流",M6="否"),"主流但未入基準：須 Andy 判定",IF(AND(IF(L6="",K6,L6)="非主流",M6="是",I6<>"早期採用"),"非主流卻在基準","一致")) -> 一致
A7: T03 | B7: FP4 權重推論（NVFP4／MXFP4） | C7: — | D7: Spec_Rack 專家 bytes/param | E7: 1 | F7: 1 | G7: 1 | H7: 2 | I7: 主流 | J7: 2 | K7: =IF(J7>=2,"主流","非主流") -> 主流 | M7: 是 | N7: 1 | O7: 1 | P7: =IF(M7="是",1,1+O7*N7*(CHOOSE(H7,E7,F7,G7)-1)) -> 1 | Q7: Verified | R7: DeepSeek V4 原生 FP4 專家權重、OpenAI gpt-oss MXFP4；已在基準 | S7: — | T7: =IF(AND(IF(L7="",K7,L7)="主流",M7="否"),"主流但未入基準：須 Andy 判定",IF(AND(IF(L7="",K7,L7)="非主流",M7="是",I7<>"早期採用"),"非主流卻在基準","一致")) -> 一致
A8: T04 | B8: FP4 量化感知訓練（後訓練） | C8: — | D8: Spec_Rack 專家 bytes/param | E8: 1 | F8: 1 | G8: 1 | H8: 2 | I8: 主流 | J8: 2 | K8: =IF(J8>=2,"主流","非主流") -> 主流 | M8: 是 | N8: 1 | O8: 1 | P8: =IF(M8="是",1,1+O8*N8*(CHOOSE(H8,E8,F8,G8)-1)) -> 1 | Q8: Interested-party | R8: DeepSeek V4：主權重量化到 FP4 再反量化到 FP8 計算，沿用 FP8 訓練框架（S35） | S8: — | T8: =IF(AND(IF(L8="",K8,L8)="主流",M8="否"),"主流但未入基準：須 Andy 判定",IF(AND(IF(L8="",K8,L8)="非主流",M8="是",I8<>"早期採用"),"非主流卻在基準","一致")) -> 一致
A9: T05 | B9: On-policy 蒸餾（多專家整合） | C9: — | D9: Training G 節 | E9: 1 | F9: 1 | G9: 1 | H9: 2 | I9: 主流 | J9: 2 | K9: =IF(J9>=2,"主流","非主流") -> 主流 | M9: 是 | N9: 1 | O9: 1 | P9: =IF(M9="是",1,1+O9*N9*(CHOOSE(H9,E9,F9,G9)-1)) -> 1 | Q9: Interested-party | R9: DeepSeek V4（專家 SFT＋GRPO 後以 on-policy 蒸餾整合，S35）、Qwen3；已在 Training 基準 | S9: — | T9: =IF(AND(IF(L9="",K9,L9)="主流",M9="否"),"主流但未入基準：須 Andy 判定",IF(AND(IF(L9="",K9,L9)="非主流",M9="是",I9<>"早期採用"),"非主流卻在基準","一致")) -> 一致
A10: T06 | B10: Muon 優化器 | C10: H_TOK | D10: 預訓練所需 token | E10: 0.7 | F10: 0.85 | G10: 1 | H10: 2 | I10: 早期採用 | J10: 2 | K10: =IF(J10>=2,"主流","非主流") -> 主流 | M10: 是 | N10: 1 | O10: 0 | P10: =IF(M10="是",1,1+O10*N10*(CHOOSE(H10,E10,F10,G10)-1)) -> 1 | Q10: Interested-party | R10: Moonshot Kimi K2、DeepSeek V4 採用；Luna／Sol 的 token 數為實際值，已隱含其效果，故不套倍數 | S10: 第三家前沿實驗室採用，或公開同品質 token 節省的對照實驗 | T10: =IF(AND(IF(L10="",K10,L10)="主流",M10="否"),"主流但未入基準：須 Andy 判定",IF(AND(IF(L10="",K10,L10)="非主流",M10="是",I10<>"早期採用"),"非主流卻在基準","一致")) -> 一致
A11: T07 | B11: NVFP4 預訓練 | C11: H_TPK | D11: 訓練峰值 | E11: 1.5 | F11: 2 | G11: 3 | H11: 2 | I11: 早期採用 | J11: 1 | K11: =IF(J11>=2,"主流","非主流") -> 非主流 | M11: 否 | N11: 1 | O11: 0 | P11: =IF(M11="是",1,1+O11*N11*(CHOOSE(H11,E11,F11,G11)-1)) -> 1 | Q11: Interested-party | R11: 倍數＝NVFP4 訓練峰值 ÷ FP8（VR 35/17.5＝2；GB300 15/5＝3 [Assumed]）。NVIDIA 公開 12B 模型 10T token NVFP4 預訓練；前沿實驗室未見公開採用。MFU 可能同步下降，未計 | S11: 任一前沿實驗室公開以 FP4 完成主預訓練 | T11: =IF(AND(IF(L11="",K11,L11)="主流",M11="否"),"主流但未入基準：須 Andy 判定",IF(AND(IF(L11="",K11,L11)="非主流",M11="是",I11<>"早期採用"),"非主流卻在基準","一致")) -> 一致
A12: T08 | B12: Looped transformer（權重共享迴圈）— 計算量 | C12: H_FLOP | D12: 每 token FLOPs | E12: 1.5 | F12: 2 | G12: 4 | H12: 2 | I12: 研究 | J12: 0 | K12: =IF(J12>=2,"主流","非主流") -> 非主流 | M12: 否 | N12: 1 | O12: 0 | P12: =IF(M12="是",1,1+O12*N12*(CHOOSE(H12,E12,F12,G12)-1)) -> 1 | Q12: Assumed | R12: 同一組權重迴圈 k 次：FLOPs × k、權重 bytes × 1；能力增量於 Block 4（H_CAP）處理 | S12: 前沿模型卡或技術報告揭露迴圈深度 | T12: =IF(AND(IF(L12="",K12,L12)="主流",M12="否"),"主流但未入基準：須 Andy 判定",IF(AND(IF(L12="",K12,L12)="非主流",M12="是",I12<>"早期採用"),"非主流卻在基準","一致")) -> 一致
A13: T09 | B13: Looped transformer — 每層延遲 | C13: H_TL | D13: 每步逐層延遲 | E13: 1.5 | F13: 2 | G13: 4 | H13: 2 | I13: 研究 | J13: 0 | K13: =IF(J13>=2,"主流","非主流") -> 非主流 | M13: 否 | N13: 1 | O13: 0 | P13: =IF(M13="是",1,1+O13*N13*(CHOOSE(H13,E13,F13,G13)-1)) -> 1 | Q13: Assumed | R13: 迴圈使有效層數 × k，逐層延遲同比增加；與 T08 同時開關 | S13: 同 T08 | T13: =IF(AND(IF(L13="",K13,L13)="主流",M13="否"),"主流但未入基準：須 Andy 判定",IF(AND(IF(L13="",K13,L13)="非主流",M13="是",I13<>"早期採用"),"非主流卻在基準","一致")) -> 一致
A14: T10 | B14: 非同步 RL（rollout 與訓練解耦、部分 rollout） | C14: H_ROLL | D14: rollout 效率 | E14: 1.2 | F14: 1.4 | G14: 1.6 | H14: 2 | I14: 主流 | J14: 4 | K14: =IF(J14>=2,"主流","非主流") -> 主流 | M14: 是 | N14: 1 | O14: 0 | P14: =IF(M14="是",1,1+O14*N14*(CHOOSE(H14,E14,F14,G14)-1)) -> 1 | Q14: Interested-party | R14: 旗艦模型公開採用：DeepSeek V4.1（幾乎全部 RL 與 OPD，S45）、Zhipu GLM-5（slime，S46）、Moonshot Kimi-Researcher（完全非同步 rollout，S47）、Meta Llama 3（LlamaRL，S48）。閉源四家未找到披露。v5.6 起併入基準：Train_In rollout 效率 0.85（Andy 2026-10-01 決定 (a)） | S14: 閉源實驗室披露同步做法，或前沿規模對照實驗顯示 off-policy 偏差抵銷吞吐增益 | T14: =IF(AND(IF(L14="",K14,L14)="主流",M14="否"),"主流但未入基準：須 Andy 判定",IF(AND(IF(L14="",K14,L14)="非主流",M14="是",I14<>"早期採用"),"非主流卻在基準","一致")) -> 一致
A15: T11 | B15: KV 快取壓縮（FP4 KV 等） | C15: H_KV | D15: KV bytes/token | E15: 0.5 | F15: 0.5 | G15: 0.75 | H15: 2 | I15: 早期採用 | J15: 1 | K15: =IF(J15>=2,"主流","非主流") -> 非主流 | M15: 否 | N15: 1 | O15: 0 | P15: =IF(M15="是",1,1+O15*N15*(CHOOSE(H15,E15,F15,G15)-1)) -> 1 | Q15: Assumed | R15: FP8 → FP4 KV：bytes × 0.5；準確率損失待查 | S15: 第二家實驗室在生產服務公開採用 | T15: =IF(AND(IF(L15="",K15,L15)="主流",M15="否"),"主流但未入基準：須 Andy 判定",IF(AND(IF(L15="",K15,L15)="非主流",M15="是",I15<>"早期採用"),"非主流卻在基準","一致")) -> 一致
A16: T12 | B16: Harness（代理框架） | C16: H_HAR | D16: Block 5 占位 | E16: 1 | F16: 1 | G16: 1 | H16: 2 | I16: 追蹤中 | J16: 0 | K16: =IF(J16>=2,"主流","非主流") -> 非主流 | M16: 否 | N16: 1 | O16: 0 | P16: =IF(M16="是",1,1+O16*N16*(CHOOSE(H16,E16,F16,G16)-1)) -> 1 | Q16: Assumed | R16: ARC-AGI-3：GPT-6 Astra 標準 harness 62.7% → Provider Adapter 99.9%；Opus 5 30.2% → Strands 99.95%。Block 5 參數化 | S16: Block 5 | T16: =IF(AND(IF(L16="",K16,L16)="主流",M16="否"),"主流但未入基準：須 Andy 判定",IF(AND(IF(L16="",K16,L16)="非主流",M16="是",I16<>"早期採用"),"非主流卻在基準","一致")) -> 一致
A18: 掛鉤彙總（同一掛鉤多條目時取乘積；Perf、Perf_Batch、Training 連結本表 E 欄）
A19: 代碼 | B19: 意義 | D19: 作用位置 | E19: 倍數
A20: H_ETAD | B20: decode η_d 倍數 | D20: Perf／Perf_Batch：etadm 列 | E20: =EXP(SUMPRODUCT(($C$5:$C$16="H_ETAD")*LN($P$5:$P$16))) -> 1
A21: H_TL | B21: 每層延遲倍數 | D21: Perf／Perf_Batch：tlm 列 | E21: =EXP(SUMPRODUCT(($C$5:$C$16="H_TL")*LN($P$5:$P$16))) -> 1
A22: H_FLOP | B22: 每 token FLOPs 倍數（推論與訓練） | D22: Perf／Perf_Batch：hflop 列；Training：hflop 列 | E22: =EXP(SUMPRODUCT(($C$5:$C$16="H_FLOP")*LN($P$5:$P$16))) -> 1
A23: H_KV | B23: KV bytes/token 倍數 | D23: Perf／Perf_Batch：hkv 列 | E23: =EXP(SUMPRODUCT(($C$5:$C$16="H_KV")*LN($P$5:$P$16))) -> 1
A24: H_WB | B24: 權重 bytes/param 倍數 | D24: Perf／Perf_Batch：hwb 列 | E24: =EXP(SUMPRODUCT(($C$5:$C$16="H_WB")*LN($P$5:$P$16))) -> 1
A25: H_TPK | B25: 訓練峰值倍數 | D25: Training：htpk 列 | E25: =EXP(SUMPRODUCT(($C$5:$C$16="H_TPK")*LN($P$5:$P$16))) -> 1
A26: H_MFU | B26: 訓練 MFU 倍數 | D26: Training：hmfu 列 | E26: =EXP(SUMPRODUCT(($C$5:$C$16="H_MFU")*LN($P$5:$P$16))) -> 1
A27: H_TOK | B27: 達同等預訓練品質所需 token 倍數 | D27: Training：htok 列 | E27: =EXP(SUMPRODUCT(($C$5:$C$16="H_TOK")*LN($P$5:$P$16))) -> 1
A28: H_ROLL | B28: rollout 效率倍數 | D28: Training：hroll 列 | E28: =EXP(SUMPRODUCT(($C$5:$C$16="H_ROLL")*LN($P$5:$P$16))) -> 1
A29: H_CAP | B29: 能力增量（Block 4 占位，尚無作用） | D29: Block 4 | E29: =EXP(SUMPRODUCT(($C$5:$C$16="H_CAP")*LN($P$5:$P$16))) -> 1
A30: H_HAR | B30: harness（Block 5 占位，尚無作用） | D30: Block 5 | E30: =EXP(SUMPRODUCT(($C$5:$C$16="H_HAR")*LN($P$5:$P$16))) -> 1
A32: 注意 | B32: 掛鉤作用於全部世代與層級。新條目：在表中插入一列（範圍內），填倍數、狀態與證據；開關預設 0。Sens_Perf 的 η_d 與每層延遲情境為覆寫值，不受 Registry 影響。

Sheet Perf
A1: Perf — 每架產出引擎（世代 × 層級；各層級 SLO 與參考任務；100% 利用率）
A2: decode：每步時間＝固定延遲＋B × 每序列時間；在 SLO 下解出批次 B*，再受 HBM 容量限制。prefill 為算力受限。黃底為關鍵輸出
A4: 世代 | C4: =INDEX(Spec_Rack!$C$4:$G$4,C6) -> Hopper H100 | D4: =INDEX(Spec_Rack!$C$4:$G$4,D6) -> Hopper H100 | E4: =INDEX(Spec_Rack!$C$4:$G$4,E6) -> Hopper H100 | F4: =INDEX(Spec_Rack!$C$4:$G$4,F6) -> GB200 NVL72 | G4: =INDEX(Spec_Rack!$C$4:$G$4,G6) -> GB200 NVL72 | H4: =INDEX(Spec_Rack!$C$4:$G$4,H6) -> GB200 NVL72 | I4: =INDEX(Spec_Rack!$C$4:$G$4,I6) -> GB300 NVL72 | J4: =INDEX(Spec_Rack!$C$4:$G$4,J6) -> GB300 NVL72 | ... Q4: =INDEX(Spec_Rack!$C$4:$G$4,Q6) -> Rubin Ultra NVL576
A5: 層級 | C5: =INDEX(Arch!$C$4:$E$4,C7) -> Luna（低層） | D5: =INDEX(Arch!$C$4:$E$4,D7) -> Sol（中層） | E5: =INDEX(Arch!$C$4:$E$4,E7) -> Astra（頂層） | F5: =INDEX(Arch!$C$4:$E$4,F7) -> Luna（低層） | G5: =INDEX(Arch!$C$4:$E$4,G7) -> Sol（中層） | H5: =INDEX(Arch!$C$4:$E$4,H7) -> Astra（頂層） | I5: =INDEX(Arch!$C$4:$E$4,I7) -> Luna（低層） | J5: =INDEX(Arch!$C$4:$E$4,J7) -> Sol（中層） | ... Q5: =INDEX(Arch!$C$4:$E$4,Q7) -> Astra（頂層）
A6: 世代索引 | C6: 1 | D6: 1 | E6: 1 | F6: 2 | G6: 2 | H6: 2 | I6: 3 | J6: 3 | K6: 3 | L6: 4 | M6: 4 | N6: 4 | O6: 5 | P6: 5 | Q6: 5
A7: 層級索引 | C7: 1 | D7: 2 | E7: 3 | F7: 1 | G7: 2 | H7: 3 | I7: 1 | J7: 2 | K7: 3 | L7: 1 | M7: 2 | N7: 3 | O7: 1 | P7: 2 | Q7: 3
A9: 0. Tech_Registry 掛鉤（基準＝1；Registry 未啟用任何條目時與 v5.4 相同）
A10: FLOPs/token 倍數（H_FLOP） | B10: x | C10: =Tech_Registry!$E$22 -> 1 | D10: =Tech_Registry!$E$22 -> 1 | E10: =Tech_Registry!$E$22 -> 1 | F10: =Tech_Registry!$E$22 -> 1 | G10: =Tech_Registry!$E$22 -> 1 | H10: =Tech_Registry!$E$22 -> 1 | I10: =Tech_Registry!$E$22 -> 1 | J10: =Tech_Registry!$E$22 -> 1 | ... Q10: =Tech_Registry!$E$22 -> 1
A11: KV bytes/token 倍數（H_KV） | B11: x | C11: =Tech_Registry!$E$23 -> 1 | D11: =Tech_Registry!$E$23 -> 1 | E11: =Tech_Registry!$E$23 -> 1 | F11: =Tech_Registry!$E$23 -> 1 | G11: =Tech_Registry!$E$23 -> 1 | H11: =Tech_Registry!$E$23 -> 1 | I11: =Tech_Registry!$E$23 -> 1 | J11: =Tech_Registry!$E$23 -> 1 | ... Q11: =Tech_Registry!$E$23 -> 1
A12: 權重 bytes/param 倍數（H_WB） | B12: x | C12: =Tech_Registry!$E$24 -> 1 | D12: =Tech_Registry!$E$24 -> 1 | E12: =Tech_Registry!$E$24 -> 1 | F12: =Tech_Registry!$E$24 -> 1 | G12: =Tech_Registry!$E$24 -> 1 | H12: =Tech_Registry!$E$24 -> 1 | I12: =Tech_Registry!$E$24 -> 1 | J12: =Tech_Registry!$E$24 -> 1 | ... Q12: =Tech_Registry!$E$24 -> 1
A13: A. 規格（連結 Spec_Rack、DC_Cost）
A14: 計算用峰值 | B14: PF/GPU | C14: =INDEX(Spec_Rack!$C$35:$G$35,C$6) -> 1.979 | D14: =INDEX(Spec_Rack!$C$35:$G$35,D$6) -> 1.979 | E14: =INDEX(Spec_Rack!$C$35:$G$35,E$6) -> 1.979 | F14: =INDEX(Spec_Rack!$C$35:$G$35,F$6) -> 10 | G14: =INDEX(Spec_Rack!$C$35:$G$35,G$6) -> 10 | H14: =INDEX(Spec_Rack!$C$35:$G$35,H$6) -> 10 | I14: =INDEX(Spec_Rack!$C$35:$G$35,I$6) -> 15 | J14: =INDEX(Spec_Rack!$C$35:$G$35,J$6) -> 15 | ... Q14: =INDEX(Spec_Rack!$C$35:$G$35,Q$6) -> 73
A15: HBM 容量 | B15: GB/GPU | C15: =INDEX(Spec_Rack!$C$25:$G$25,C$6) -> 80 | D15: =INDEX(Spec_Rack!$C$25:$G$25,D$6) -> 80 | E15: =INDEX(Spec_Rack!$C$25:$G$25,E$6) -> 80 | F15: =INDEX(Spec_Rack!$C$25:$G$25,F$6) -> 186 | G15: =INDEX(Spec_Rack!$C$25:$G$25,G$6) -> 186 | H15: =INDEX(Spec_Rack!$C$25:$G$25,H$6) -> 186 | I15: =INDEX(Spec_Rack!$C$25:$G$25,I$6) -> 288 | J15: =INDEX(Spec_Rack!$C$25:$G$25,J$6) -> 288 | ... Q15: =INDEX(Spec_Rack!$C$25:$G$25,Q$6) -> 1024
A16: HBM 頻寬 | B16: TB/s/GPU | C16: =INDEX(Spec_Rack!$C$26:$G$26,C$6) -> 3.35 | D16: =INDEX(Spec_Rack!$C$26:$G$26,D$6) -> 3.35 | E16: =INDEX(Spec_Rack!$C$26:$G$26,E$6) -> 3.35 | F16: =INDEX(Spec_Rack!$C$26:$G$26,F$6) -> 8 | G16: =INDEX(Spec_Rack!$C$26:$G$26,G$6) -> 8 | H16: =INDEX(Spec_Rack!$C$26:$G$26,H$6) -> 8 | I16: =INDEX(Spec_Rack!$C$26:$G$26,I$6) -> 8 | J16: =INDEX(Spec_Rack!$C$26:$G$26,J$6) -> 8 | ... Q16: =INDEX(Spec_Rack!$C$26:$G$26,Q$6) -> 32
A17: EP 通訊頻寬（單向） | B17: TB/s/GPU | C17: =INDEX(Spec_Rack!$C$27:$G$27,C$6) -> 0.05 | D17: =INDEX(Spec_Rack!$C$27:$G$27,D$6) -> 0.05 | E17: =INDEX(Spec_Rack!$C$27:$G$27,E$6) -> 0.05 | F17: =INDEX(Spec_Rack!$C$27:$G$27,F$6) -> 0.9 | G17: =INDEX(Spec_Rack!$C$27:$G$27,G$6) -> 0.9 | H17: =INDEX(Spec_Rack!$C$27:$G$27,H$6) -> 0.9 | I17: =INDEX(Spec_Rack!$C$27:$G$27,I$6) -> 0.9 | J17: =INDEX(Spec_Rack!$C$27:$G$27,J$6) -> 0.9 | ... Q17: =INDEX(Spec_Rack!$C$27:$G$27,Q$6) -> 1.8
A18: decode EP 基準寬度 | B18: GPU | C18: =INDEX(Spec_Rack!$C$29:$G$29,C$6) -> 64 | D18: =INDEX(Spec_Rack!$C$29:$G$29,D$6) -> 64 | E18: =INDEX(Spec_Rack!$C$29:$G$29,E$6) -> 64 | F18: =INDEX(Spec_Rack!$C$29:$G$29,F$6) -> 32 | G18: =INDEX(Spec_Rack!$C$29:$G$29,G$6) -> 32 | H18: =INDEX(Spec_Rack!$C$29:$G$29,H$6) -> 32 | I18: =INDEX(Spec_Rack!$C$29:$G$29,I$6) -> 32 | J18: =INDEX(Spec_Rack!$C$29:$G$29,J$6) -> 32 | ... Q18: =INDEX(Spec_Rack!$C$29:$G$29,Q$6) -> 64
A19: 專家權重 bytes/param（含 H_WB） | B19: B | C19: =INDEX(Spec_Rack!$C$30:$G$30,C$6)*C12 -> 1 | D19: =INDEX(Spec_Rack!$C$30:$G$30,D$6)*D12 -> 1 | E19: =INDEX(Spec_Rack!$C$30:$G$30,E$6)*E12 -> 1 | F19: =INDEX(Spec_Rack!$C$30:$G$30,F$6)*F12 -> 0.5625 | G19: =INDEX(Spec_Rack!$C$30:$G$30,G$6)*G12 -> 0.5625 | H19: =INDEX(Spec_Rack!$C$30:$G$30,H$6)*H12 -> 0.5625 | I19: =INDEX(Spec_Rack!$C$30:$G$30,I$6)*I12 -> 0.5625 | J19: =INDEX(Spec_Rack!$C$30:$G$30,J$6)*J12 -> 0.5625 | ... Q19: =INDEX(Spec_Rack!$C$30:$G$30,Q$6)*Q12 -> 0.5625
A20: 非專家權重 bytes/param（含 H_WB） | B20: B | C20: =INDEX(Spec_Rack!$C$31:$G$31,C$6)*C12 -> 1 | D20: =INDEX(Spec_Rack!$C$31:$G$31,D$6)*D12 -> 1 | E20: =INDEX(Spec_Rack!$C$31:$G$31,E$6)*E12 -> 1 | F20: =INDEX(Spec_Rack!$C$31:$G$31,F$6)*F12 -> 1 | G20: =INDEX(Spec_Rack!$C$31:$G$31,G$6)*G12 -> 1 | H20: =INDEX(Spec_Rack!$C$31:$G$31,H$6)*H12 -> 1 | I20: =INDEX(Spec_Rack!$C$31:$G$31,I$6)*I12 -> 1 | J20: =INDEX(Spec_Rack!$C$31:$G$31,J$6)*J12 -> 1 | ... Q20: =INDEX(Spec_Rack!$C$31:$G$31,Q$6)*Q12 -> 1
A21: 每 prefill 實例 GPU 數 | B21: GPU | C21: =INDEX(Spec_Rack!$C$32:$G$32,C$6) -> 8 | D21: =INDEX(Spec_Rack!$C$32:$G$32,D$6) -> 8 | E21: =INDEX(Spec_Rack!$C$32:$G$32,E$6) -> 8 | F21: =INDEX(Spec_Rack!$C$32:$G$32,F$6) -> 4 | G21: =INDEX(Spec_Rack!$C$32:$G$32,G$6) -> 4 | H21: =INDEX(Spec_Rack!$C$32:$G$32,H$6) -> 4 | I21: =INDEX(Spec_Rack!$C$32:$G$32,I$6) -> 4 | J21: =INDEX(Spec_Rack!$C$32:$G$32,J$6) -> 4 | ... Q21: =INDEX(Spec_Rack!$C$32:$G$32,Q$6) -> 8
A22: GPU 封裝／架 | B22: 顆 | C22: =INDEX(Spec_Rack!$C$6:$G$6,C$6) -> 32 | D22: =INDEX(Spec_Rack!$C$6:$G$6,D$6) -> 32 | E22: =INDEX(Spec_Rack!$C$6:$G$6,E$6) -> 32 | F22: =INDEX(Spec_Rack!$C$6:$G$6,F$6) -> 72 | G22: =INDEX(Spec_Rack!$C$6:$G$6,G$6) -> 72 | H22: =INDEX(Spec_Rack!$C$6:$G$6,H$6) -> 72 | I22: =INDEX(Spec_Rack!$C$6:$G$6,I$6) -> 72 | J22: =INDEX(Spec_Rack!$C$6:$G$6,J$6) -> 72 | ... Q22: =INDEX(Spec_Rack!$C$6:$G$6,Q$6) -> 144
A23: GPU 功率 | B23: W | C23: =INDEX(Spec_Rack!$C$33:$G$33,C$6) -> 700 | D23: =INDEX(Spec_Rack!$C$33:$G$33,D$6) -> 700 | E23: =INDEX(Spec_Rack!$C$33:$G$33,E$6) -> 700 | F23: =INDEX(Spec_Rack!$C$33:$G$33,F$6) -> 1200 | G23: =INDEX(Spec_Rack!$C$33:$G$33,G$6) -> 1200 | H23: =INDEX(Spec_Rack!$C$33:$G$33,H$6) -> 1200 | I23: =INDEX(Spec_Rack!$C$33:$G$33,I$6) -> 1400 | J23: =INDEX(Spec_Rack!$C$33:$G$33,J$6) -> 1400 | ... Q23: =INDEX(Spec_Rack!$C$33:$G$33,Q$6) -> 3600
A24: HBM 存取能量 | B24: pJ/B | C24: =INDEX(Spec_Rack!$C$34:$G$34,C$6) -> 31 | D24: =INDEX(Spec_Rack!$C$34:$G$34,D$6) -> 31 | E24: =INDEX(Spec_Rack!$C$34:$G$34,E$6) -> 31 | F24: =INDEX(Spec_Rack!$C$34:$G$34,F$6) -> 25 | G24: =INDEX(Spec_Rack!$C$34:$G$34,G$6) -> 25 | H24: =INDEX(Spec_Rack!$C$34:$G$34,H$6) -> 25 | I24: =INDEX(Spec_Rack!$C$34:$G$34,I$6) -> 25 | J24: =INDEX(Spec_Rack!$C$34:$G$34,J$6) -> 25 | ... Q24: =INDEX(Spec_Rack!$C$34:$G$34,Q$6) -> 18
A25: 每 GW 機架數（功率情境） | B25: 架 | C25: =INDEX(DC_Cost!$C$12:$Q$12,3*(C$6-1)+2) -> 22439 | D25: =INDEX(DC_Cost!$C$12:$Q$12,3*(D$6-1)+2) -> 22439 | E25: =INDEX(DC_Cost!$C$12:$Q$12,3*(E$6-1)+2) -> 22439 | F25: =INDEX(DC_Cost!$C$12:$Q$12,3*(F$6-1)+2) -> 7076 | G25: =INDEX(DC_Cost!$C$12:$Q$12,3*(G$6-1)+2) -> 7076 | H25: =INDEX(DC_Cost!$C$12:$Q$12,3*(H$6-1)+2) -> 7076 | I25: =INDEX(DC_Cost!$C$12:$Q$12,3*(I$6-1)+2) -> 6715 | J25: =INDEX(DC_Cost!$C$12:$Q$12,3*(J$6-1)+2) -> 6715 | ... Q25: =INDEX(DC_Cost!$C$12:$Q$12,3*(Q$6-1)+2) -> 1533
A26: 每架配電設計功率 | B26: kW | C26: =INDEX(DC_Cost!$C$11:$Q$11,3*(C$6-1)+2) -> 41 | D26: =INDEX(DC_Cost!$C$11:$Q$11,3*(D$6-1)+2) -> 41 | E26: =INDEX(DC_Cost!$C$11:$Q$11,3*(E$6-1)+2) -> 41 | F26: =INDEX(DC_Cost!$C$11:$Q$11,3*(F$6-1)+2) -> 130 | G26: =INDEX(DC_Cost!$C$11:$Q$11,3*(G$6-1)+2) -> 130 | H26: =INDEX(DC_Cost!$C$11:$Q$11,3*(H$6-1)+2) -> 130 | I26: =INDEX(DC_Cost!$C$11:$Q$11,3*(I$6-1)+2) -> 137 | J26: =INDEX(DC_Cost!$C$11:$Q$11,3*(J$6-1)+2) -> 137 | ... Q26: =INDEX(DC_Cost!$C$11:$Q$11,3*(Q$6-1)+2) -> 600
A27: B. 架構（連結 Arch）
A28: 啟用參數 | B28: B | C28: =INDEX(Arch!$C$7:$E$7,C$7) -> 13 | D28: =INDEX(Arch!$C$7:$E$7,D$7) -> 49 | E28: =INDEX(Arch!$C$7:$E$7,E$7) -> 180 | F28: =INDEX(Arch!$C$7:$E$7,F$7) -> 13 | G28: =INDEX(Arch!$C$7:$E$7,G$7) -> 49 | H28: =INDEX(Arch!$C$7:$E$7,H$7) -> 180 | I28: =INDEX(Arch!$C$7:$E$7,I$7) -> 13 | J28: =INDEX(Arch!$C$7:$E$7,J$7) -> 49 | ... Q28: =INDEX(Arch!$C$7:$E$7,Q$7) -> 180
A29: 層數 | B29: 層 | C29: =INDEX(Arch!$C$8:$E$8,C$7) -> 43 | D29: =INDEX(Arch!$C$8:$E$8,D$7) -> 61 | E29: =INDEX(Arch!$C$8:$E$8,E$7) -> 100 | F29: =INDEX(Arch!$C$8:$E$8,F$7) -> 43 | G29: =INDEX(Arch!$C$8:$E$8,G$7) -> 61 | H29: =INDEX(Arch!$C$8:$E$8,H$7) -> 100 | I29: =INDEX(Arch!$C$8:$E$8,I$7) -> 43 | J29: =INDEX(Arch!$C$8:$E$8,J$7) -> 61 | ... Q29: =INDEX(Arch!$C$8:$E$8,Q$7) -> 100
A30: d_model | C30: =INDEX(Arch!$C$9:$E$9,C$7) -> 4096 | D30: =INDEX(Arch!$C$9:$E$9,D$7) -> 7168 | E30: =INDEX(Arch!$C$9:$E$9,E$7) -> 12288 | F30: =INDEX(Arch!$C$9:$E$9,F$7) -> 4096 | G30: =INDEX(Arch!$C$9:$E$9,G$7) -> 7168 | H30: =INDEX(Arch!$C$9:$E$9,H$7) -> 12288 | I30: =INDEX(Arch!$C$9:$E$9,I$7) -> 4096 | J30: =INDEX(Arch!$C$9:$E$9,J$7) -> 7168 | ... Q30: =INDEX(Arch!$C$9:$E$9,Q$7) -> 12288
A31: 啟用 routed experts | C31: =INDEX(Arch!$C$13:$E$13,C$7) -> 6 | D31: =INDEX(Arch!$C$13:$E$13,D$7) -> 6 | E31: =INDEX(Arch!$C$13:$E$13,E$7) -> 16 | F31: =INDEX(Arch!$C$13:$E$13,F$7) -> 6 | G31: =INDEX(Arch!$C$13:$E$13,G$7) -> 6 | H31: =INDEX(Arch!$C$13:$E$13,H$7) -> 16 | I31: =INDEX(Arch!$C$13:$E$13,I$7) -> 6 | J31: =INDEX(Arch!$C$13:$E$13,J$7) -> 6 | ... Q31: =INDEX(Arch!$C$13:$E$13,Q$7) -> 16
A32: 非專家參數 | B32: B | C32: =INDEX(Arch!$C$28:$E$28,C$7) -> 5.412 | D32: =INDEX(Arch!$C$28:$E$28,D$7) -> 20.277778 | E32: =INDEX(Arch!$C$28:$E$28,E$7) -> 49.072581 | F32: =INDEX(Arch!$C$28:$E$28,F$7) -> 5.412 | G32: =INDEX(Arch!$C$28:$E$28,G$7) -> 20.277778 | H32: =INDEX(Arch!$C$28:$E$28,H$7) -> 49.072581 | I32: =INDEX(Arch!$C$28:$E$28,I$7) -> 5.412 | J32: =INDEX(Arch!$C$28:$E$28,J$7) -> 20.277778 | ... Q32: =INDEX(Arch!$C$28:$E$28,Q$7) -> 49.072581
A33: 專家參數 | B33: B | C33: =INDEX(Arch!$C$29:$E$29,C$7) -> 278.588 | D33: =INDEX(Arch!$C$29:$E$29,D$7) -> 1579.7222 | E33: =INDEX(Arch!$C$29:$E$29,E$7) -> 3950.9274 | F33: =INDEX(Arch!$C$29:$E$29,F$7) -> 278.588 | G33: =INDEX(Arch!$C$29:$E$29,G$7) -> 1579.7222 | H33: =INDEX(Arch!$C$29:$E$29,H$7) -> 3950.9274 | I33: =INDEX(Arch!$C$29:$E$29,I$7) -> 278.588 | J33: =INDEX(Arch!$C$29:$E$29,J$7) -> 1579.7222 | ... Q33: =INDEX(Arch!$C$29:$E$29,Q$7) -> 3950.9274
A34: KV bytes/token（含 H_KV） | B34: B | C34: =INDEX(Arch!$C$25:$E$25,C$7)*C11 -> 2795 | D34: =INDEX(Arch!$C$25:$E$25,D$7)*D11 -> 3965 | E34: =INDEX(Arch!$C$25:$E$25,E$7)*E11 -> 57600 | F34: =INDEX(Arch!$C$25:$E$25,F$7)*F11 -> 2795 | G34: =INDEX(Arch!$C$25:$E$25,G$7)*G11 -> 3965 | H34: =INDEX(Arch!$C$25:$E$25,H$7)*H11 -> 57600 | I34: =INDEX(Arch!$C$25:$E$25,I$7)*I11 -> 2795 | J34: =INDEX(Arch!$C$25:$E$25,J$7)*J11 -> 3965 | ... Q34: =INDEX(Arch!$C$25:$E$25,Q$7)*Q11 -> 57600
A35: 注意力 FLOPs／被注意 token | B35: FLOP | C35: =INDEX(Arch!$C$30:$E$30,C$7) -> 5636096 | D35: =INDEX(Arch!$C$30:$E$30,D$7) -> 15990784 | E35: =INDEX(Arch!$C$30:$E$30,E$7) -> 4915200 | F35: =INDEX(Arch!$C$30:$E$30,F$7) -> 5636096 | G35: =INDEX(Arch!$C$30:$E$30,G$7) -> 15990784 | H35: =INDEX(Arch!$C$30:$E$30,H$7) -> 4915200 | I35: =INDEX(Arch!$C$30:$E$30,I$7) -> 5636096 | J35: =INDEX(Arch!$C$30:$E$30,J$7) -> 15990784 | ... Q35: =INDEX(Arch!$C$30:$E$30,Q$7) -> 4915200
A36: 全注意力層比例 | B36: % | C36: =INDEX(Arch!$C$16:$E$16,C$7) -> 0.5 | D36: =INDEX(Arch!$C$16:$E$16,D$7) -> 0.5 | E36: =INDEX(Arch!$C$16:$E$16,E$7) -> 1 | F36: =INDEX(Arch!$C$16:$E$16,F$7) -> 0.5 | G36: =INDEX(Arch!$C$16:$E$16,G$7) -> 0.5 | H36: =INDEX(Arch!$C$16:$E$16,H$7) -> 1 | I36: =INDEX(Arch!$C$16:$E$16,I$7) -> 0.5 | J36: =INDEX(Arch!$C$16:$E$16,J$7) -> 0.5 | ... Q36: =INDEX(Arch!$C$16:$E$16,Q$7) -> 1
A37: 全注意力跨度上限 | B37: tok | C37: =INDEX(Arch!$C$17:$E$17,C$7) -> 4224 | D37: =INDEX(Arch!$C$17:$E$17,D$7) -> 4224 | E37: =INDEX(Arch!$C$17:$E$17,E$7) -> 0 | F37: =INDEX(Arch!$C$17:$E$17,F$7) -> 4224 | G37: =INDEX(Arch!$C$17:$E$17,G$7) -> 4224 | H37: =INDEX(Arch!$C$17:$E$17,H$7) -> 0 | I37: =INDEX(Arch!$C$17:$E$17,I$7) -> 4224 | J37: =INDEX(Arch!$C$17:$E$17,J$7) -> 4224 | ... Q37: =INDEX(Arch!$C$17:$E$17,Q$7) -> 0
A38: 其他層壓縮比 | B38: x | C38: =INDEX(Arch!$C$18:$E$18,C$7) -> 128 | D38: =INDEX(Arch!$C$18:$E$18,D$7) -> 128 | E38: =INDEX(Arch!$C$18:$E$18,E$7) -> 1 | F38: =INDEX(Arch!$C$18:$E$18,F$7) -> 128 | G38: =INDEX(Arch!$C$18:$E$18,G$7) -> 128 | H38: =INDEX(Arch!$C$18:$E$18,H$7) -> 1 | I38: =INDEX(Arch!$C$18:$E$18,I$7) -> 128 | J38: =INDEX(Arch!$C$18:$E$18,J$7) -> 128 | ... Q38: =INDEX(Arch!$C$18:$E$18,Q$7) -> 1
A39: 其他層滑動窗 | B39: tok | C39: =INDEX(Arch!$C$19:$E$19,C$7) -> 128 | D39: =INDEX(Arch!$C$19:$E$19,D$7) -> 128 | E39: =INDEX(Arch!$C$19:$E$19,E$7) -> 0 | F39: =INDEX(Arch!$C$19:$E$19,F$7) -> 128 | G39: =INDEX(Arch!$C$19:$E$19,G$7) -> 128 | H39: =INDEX(Arch!$C$19:$E$19,H$7) -> 0 | I39: =INDEX(Arch!$C$19:$E$19,I$7) -> 128 | J39: =INDEX(Arch!$C$19:$E$19,J$7) -> 128 | ... Q39: =INDEX(Arch!$C$19:$E$19,Q$7) -> 0
A40: C. 服務、SLO 與校準參數
A41: SLO：每用戶 decode 速度下限 | B41: tok/s | C41: =INDEX(Serving!$C$21:$E$21,C$7) -> 120 | D41: =INDEX(Serving!$C$21:$E$21,D$7) -> 65 | E41: =INDEX(Serving!$C$21:$E$21,E$7) -> 55 | F41: =INDEX(Serving!$C$21:$E$21,F$7) -> 120 | G41: =INDEX(Serving!$C$21:$E$21,G$7) -> 65 | H41: =INDEX(Serving!$C$21:$E$21,H$7) -> 55 | I41: =INDEX(Serving!$C$21:$E$21,I$7) -> 120 | J41: =INDEX(Serving!$C$21:$E$21,J$7) -> 65 | ... Q41: =INDEX(Serving!$C$21:$E$21,Q$7) -> 55
A42: TTFT 上限 | B42: s | C42: =INDEX(Serving!$C$22:$E$22,C$7) -> 2 | D42: =INDEX(Serving!$C$22:$E$22,D$7) -> 3 | E42: =INDEX(Serving!$C$22:$E$22,E$7) -> 5 | F42: =INDEX(Serving!$C$22:$E$22,F$7) -> 2 | G42: =INDEX(Serving!$C$22:$E$22,G$7) -> 3 | H42: =INDEX(Serving!$C$22:$E$22,H$7) -> 5 | I42: =INDEX(Serving!$C$22:$E$22,I$7) -> 2 | J42: =INDEX(Serving!$C$22:$E$22,J$7) -> 3 | ... Q42: =INDEX(Serving!$C$22:$E$22,Q$7) -> 5
A43: 參考 ISL | B43: tok | C43: =INDEX(Serving!$C$23:$E$23,C$7) -> 8192 | D43: =INDEX(Serving!$C$23:$E$23,D$7) -> 16384 | E43: =INDEX(Serving!$C$23:$E$23,E$7) -> 32768 | F43: =INDEX(Serving!$C$23:$E$23,F$7) -> 8192 | G43: =INDEX(Serving!$C$23:$E$23,G$7) -> 16384 | H43: =INDEX(Serving!$C$23:$E$23,H$7) -> 32768 | I43: =INDEX(Serving!$C$23:$E$23,I$7) -> 8192 | J43: =INDEX(Serving!$C$23:$E$23,J$7) -> 16384 | ... Q43: =INDEX(Serving!$C$23:$E$23,Q$7) -> 32768
A44: 參考 OSL（含思考） | B44: tok | C44: =INDEX(Serving!$C$24:$E$24,C$7) -> 1024 | D44: =INDEX(Serving!$C$24:$E$24,D$7) -> 2048 | E44: =INDEX(Serving!$C$24:$E$24,E$7) -> 4096 | F44: =INDEX(Serving!$C$24:$E$24,F$7) -> 1024 | G44: =INDEX(Serving!$C$24:$E$24,G$7) -> 2048 | H44: =INDEX(Serving!$C$24:$E$24,H$7) -> 4096 | I44: =INDEX(Serving!$C$24:$E$24,I$7) -> 1024 | J44: =INDEX(Serving!$C$24:$E$24,J$7) -> 2048 | ... Q44: =INDEX(Serving!$C$24:$E$24,Q$7) -> 4096
A45: decode 平均上下文 | B45: tok | C45: =C43+C44/2 -> 8704 | D45: =D43+D44/2 -> 17408 | E45: =E43+E44/2 -> 34816 | F45: =F43+F44/2 -> 8704 | G45: =G43+G44/2 -> 17408 | H45: =H43+H44/2 -> 34816 | I45: =I43+I44/2 -> 8704 | J45: =J43+J44/2 -> 17408 | ... Q45: =Q43+Q44/2 -> 34816
A46: prefill 平均位置 | B46: tok | C46: =C43/2 -> 4096 | D46: =D43/2 -> 8192 | E46: =E43/2 -> 16384 | F46: =F43/2 -> 4096 | G46: =G43/2 -> 8192 | H46: =H43/2 -> 16384 | I46: =I43/2 -> 4096 | J46: =J43/2 -> 8192 | ... Q46: =Q43/2 -> 16384
A47: MTP 草稿數 | B47: tok | C47: =Serving!$C$6 -> 3 | D47: =Serving!$C$6 -> 3 | E47: =Serving!$C$6 -> 3 | F47: =Serving!$C$6 -> 3 | G47: =Serving!$C$6 -> 3 | H47: =Serving!$C$6 -> 3 | I47: =Serving!$C$6 -> 3 | J47: =Serving!$C$6 -> 3 | ... Q47: =Serving!$C$6 -> 3
A48: 草稿接受率 | B48: % | C48: =Serving!$C$7 -> 0.7 | D48: =Serving!$C$7 -> 0.7 | E48: =Serving!$C$7 -> 0.7 | F48: =Serving!$C$7 -> 0.7 | G48: =Serving!$C$7 -> 0.7 | H48: =Serving!$C$7 -> 0.7 | I48: =Serving!$C$7 -> 0.7 | J48: =Serving!$C$7 -> 0.7 | ... Q48: =Serving!$C$7 -> 0.7
A49: 每步期望接受 token | B49: tok | C49: =(1-C48^(C47+1))/(1-C48) -> 2.533 | D49: =(1-D48^(D47+1))/(1-D48) -> 2.533 | E49: =(1-E48^(E47+1))/(1-E48) -> 2.533 | F49: =(1-F48^(F47+1))/(1-F48) -> 2.533 | G49: =(1-G48^(G47+1))/(1-G48) -> 2.533 | H49: =(1-H48^(H47+1))/(1-H48) -> 2.533 | I49: =(1-I48^(I47+1))/(1-I48) -> 2.533 | J49: =(1-J48^(J47+1))/(1-J48) -> 2.533 | ... Q49: =(1-Q48^(Q47+1))/(1-Q48) -> 2.533
A50: 實測→生產效率折減 | B50: x | C50: =Serving!$C$18 -> 1 | D50: =Serving!$C$18 -> 1 | E50: =Serving!$C$18 -> 1 | F50: =Serving!$C$18 -> 1 | G50: =Serving!$C$18 -> 1 | H50: =Serving!$C$18 -> 1 | I50: =Serving!$C$18 -> 1 | J50: =Serving!$C$18 -> 1 | ... Q50: =Serving!$C$18 -> 1
A51: η_p（prefill 占峰值；含折減） | B51: % | C51: =INDEX(Calib!$C$72:$G$72,C$6)*C50 -> 0.15 | D51: =INDEX(Calib!$C$72:$G$72,D$6)*D50 -> 0.15 | E51: =INDEX(Calib!$C$72:$G$72,E$6)*E50 -> 0.15 | F51: =INDEX(Calib!$C$72:$G$72,F$6)*F50 -> 0.3 | G51: =INDEX(Calib!$C$72:$G$72,G$6)*G50 -> 0.3 | H51: =INDEX(Calib!$C$72:$G$72,H$6)*H50 -> 0.3 | I51: =INDEX(Calib!$C$72:$G$72,I$6)*I50 -> 0.3 | J51: =INDEX(Calib!$C$72:$G$72,J$6)*J50 -> 0.3 | ... Q51: =INDEX(Calib!$C$72:$G$72,Q$6)*Q50 -> 0.3
A52: η_d 倍數（Tech_Registry H_ETAD；Sens_Perf 情境覆寫） | B52: x | C52: =Tech_Registry!$E$20 -> 1 | D52: =Tech_Registry!$E$20 -> 1 | E52: =Tech_Registry!$E$20 -> 1 | F52: =Tech_Registry!$E$20 -> 1 | G52: =Tech_Registry!$E$20 -> 1 | H52: =Tech_Registry!$E$20 -> 1 | I52: =Tech_Registry!$E$20 -> 1 | J52: =Tech_Registry!$E$20 -> 1 | ... Q52: =Tech_Registry!$E$20 -> 1
A53: η_d（decode 每序列算力效率；含折減） | B53: % | C53: =INDEX(Calib!$C$70:$G$70,C$6)*C52*C50 -> 0.054063569 | D53: =INDEX(Calib!$C$70:$G$70,D$6)*D52*D50 -> 0.054063569 | E53: =INDEX(Calib!$C$70:$G$70,E$6)*E52*E50 -> 0.054063569 | F53: =INDEX(Calib!$C$70:$G$70,F$6)*F52*F50 -> 0.036042379 | G53: =INDEX(Calib!$C$70:$G$70,G$6)*G52*G50 -> 0.036042379 | H53: =INDEX(Calib!$C$70:$G$70,H$6)*H52*H50 -> 0.036042379 | I53: =INDEX(Calib!$C$70:$G$70,I$6)*I52*I50 -> 0.036042379 | J53: =INDEX(Calib!$C$70:$G$70,J$6)*J52*J50 -> 0.036042379 | ... Q53: =INDEX(Calib!$C$70:$G$70,Q$6)*Q52*Q50 -> 0.036042379
A54: 每層延遲倍數（Tech_Registry H_TL；Sens_Perf 情境覆寫） | B54: x | C54: =Tech_Registry!$E$21 -> 1 | D54: =Tech_Registry!$E$21 -> 1 | E54: =Tech_Registry!$E$21 -> 1 | F54: =Tech_Registry!$E$21 -> 1 | G54: =Tech_Registry!$E$21 -> 1 | H54: =Tech_Registry!$E$21 -> 1 | I54: =Tech_Registry!$E$21 -> 1 | J54: =Tech_Registry!$E$21 -> 1 | ... Q54: =Tech_Registry!$E$21 -> 1
A55: 每層每次前向固定延遲（含折減） | B55: µs | C55: =INDEX(Calib!$C$71:$G$71,C$6)*C54/C50 -> 240.41784 | D55: =INDEX(Calib!$C$71:$G$71,D$6)*D54/D50 -> 240.41784 | E55: =INDEX(Calib!$C$71:$G$71,E$6)*E54/E50 -> 240.41784 | F55: =INDEX(Calib!$C$71:$G$71,F$6)*F54/F50 -> 160.27856 | G55: =INDEX(Calib!$C$71:$G$71,G$6)*G54/G50 -> 160.27856 | H55: =INDEX(Calib!$C$71:$G$71,H$6)*H54/H50 -> 160.27856 | I55: =INDEX(Calib!$C$71:$G$71,I$6)*I54/I50 -> 160.27856 | J55: =INDEX(Calib!$C$71:$G$71,J$6)*J54/J50 -> 160.27856 | ... Q55: =INDEX(Calib!$C$71:$G$71,Q$6)*Q54/Q50 -> 160.27856
A56: HBM 保留比例 | B56: % | C56: =Serving!$C$9 -> 0.1 | D56: =Serving!$C$9 -> 0.1 | E56: =Serving!$C$9 -> 0.1 | F56: =Serving!$C$9 -> 0.1 | G56: =Serving!$C$9 -> 0.1 | H56: =Serving!$C$9 -> 0.1 | I56: =Serving!$C$9 -> 0.1 | J56: =Serving!$C$9 -> 0.1 | ... Q56: =Serving!$C$9 -> 0.1
A57: 非專家權重占 HBM 上限 | B57: % | C57: =Serving!$C$10 -> 0.2 | D57: =Serving!$C$10 -> 0.2 | E57: =Serving!$C$10 -> 0.2 | F57: =Serving!$C$10 -> 0.2 | G57: =Serving!$C$10 -> 0.2 | H57: =Serving!$C$10 -> 0.2 | I57: =Serving!$C$10 -> 0.2 | J57: =Serving!$C$10 -> 0.2 | ... Q57: =Serving!$C$10 -> 0.2
A58: 專家權重占 HBM 上限 | B58: % | C58: =Serving!$C$11 -> 0.4 | D58: =Serving!$C$11 -> 0.4 | E58: =Serving!$C$11 -> 0.4 | F58: =Serving!$C$11 -> 0.4 | G58: =Serving!$C$11 -> 0.4 | H58: =Serving!$C$11 -> 0.4 | I58: =Serving!$C$11 -> 0.4 | J58: =Serving!$C$11 -> 0.4 | ... Q58: =Serving!$C$11 -> 0.4
A59: EP 啟用值 bytes/元素 | B59: B | C59: =Serving!$C$12 -> 3 | D59: =Serving!$C$12 -> 3 | E59: =Serving!$C$12 -> 3 | F59: =Serving!$C$12 -> 3 | G59: =Serving!$C$12 -> 3 | H59: =Serving!$C$12 -> 3 | I59: =Serving!$C$12 -> 3 | J59: =Serving!$C$12 -> 3 | ... Q59: =Serving!$C$12 -> 3
A60: KV 讀取效率 | B60: % | C60: =Serving!$C$13 -> 0.7 | D60: =Serving!$C$13 -> 0.7 | E60: =Serving!$C$13 -> 0.7 | F60: =Serving!$C$13 -> 0.7 | G60: =Serving!$C$13 -> 0.7 | H60: =Serving!$C$13 -> 0.7 | I60: =Serving!$C$13 -> 0.7 | J60: =Serving!$C$13 -> 0.7 | ... Q60: =Serving!$C$13 -> 0.7
A61: EP 通訊效率 | B61: % | C61: =Serving!$C$14 -> 0.7 | D61: =Serving!$C$14 -> 0.7 | E61: =Serving!$C$14 -> 0.7 | F61: =Serving!$C$14 -> 0.7 | G61: =Serving!$C$14 -> 0.7 | H61: =Serving!$C$14 -> 0.7 | I61: =Serving!$C$14 -> 0.7 | J61: =Serving!$C$14 -> 0.7 | ... Q61: =Serving!$C$14 -> 0.7
A62: 快取載入頻寬 | B62: TB/s | C62: =Serving!$C$15 -> 0.1 | D62: =Serving!$C$15 -> 0.1 | E62: =Serving!$C$15 -> 0.1 | F62: =Serving!$C$15 -> 0.1 | G62: =Serving!$C$15 -> 0.1 | H62: =Serving!$C$15 -> 0.1 | I62: =Serving!$C$15 -> 0.1 | J62: =Serving!$C$15 -> 0.1 | ... Q62: =Serving!$C$15 -> 0.1
A63: D. 每 token 計算量
A64: decode 被注意 token 數 | B64: tok | C64: =C36*IF(C37=0,C45,MIN(C45,C37))+(1-C36)*(C45/C38+C39) -> 2210 | D64: =D36*IF(D37=0,D45,MIN(D45,D37))+(1-D36)*(D45/D38+D39) -> 2244 | E64: =E36*IF(E37=0,E45,MIN(E45,E37))+(1-E36)*(E45/E38+E39) -> 34816 | F64: =F36*IF(F37=0,F45,MIN(F45,F37))+(1-F36)*(F45/F38+F39) -> 2210 | G64: =G36*IF(G37=0,G45,MIN(G45,G37))+(1-G36)*(G45/G38+G39) -> 2244 | H64: =H36*IF(H37=0,H45,MIN(H45,H37))+(1-H36)*(H45/H38+H39) -> 34816 | I64: =I36*IF(I37=0,I45,MIN(I45,I37))+(1-I36)*(I45/I38+I39) -> 2210 | J64: =J36*IF(J37=0,J45,MIN(J45,J37))+(1-J36)*(J45/J38+J39) -> 2244 | ... Q64: =Q36*IF(Q37=0,Q45,MIN(Q45,Q37))+(1-Q36)*(Q45/Q38+Q39) -> 34816
A65: decode FLOPs/token | B65: GFLOP | C65: =(2*C28*1000000000+C35*C64)*C10/1000000000 -> 38.455772 | D65: =(2*D28*1000000000+D35*D64)*D10/1000000000 -> 133.88332 | E65: =(2*E28*1000000000+E35*E64)*E10/1000000000 -> 531.1276 | F65: =(2*F28*1000000000+F35*F64)*F10/1000000000 -> 38.455772 | G65: =(2*G28*1000000000+G35*G64)*G10/1000000000 -> 133.88332 | H65: =(2*H28*1000000000+H35*H64)*H10/1000000000 -> 531.1276 | I65: =(2*I28*1000000000+I35*I64)*I10/1000000000 -> 38.455772 | J65: =(2*J28*1000000000+J35*J64)*J10/1000000000 -> 133.88332 | ... Q65: =(2*Q28*1000000000+Q35*Q64)*Q10/1000000000 -> 531.1276
A66: prefill 被注意 token 數 | B66: tok | C66: =C36*IF(C37=0,C46,MIN(C46,C37))+(1-C36)*(C46/C38+C39) -> 2128 | D66: =D36*IF(D37=0,D46,MIN(D46,D37))+(1-D36)*(D46/D38+D39) -> 2208 | E66: =E36*IF(E37=0,E46,MIN(E46,E37))+(1-E36)*(E46/E38+E39) -> 16384 | F66: =F36*IF(F37=0,F46,MIN(F46,F37))+(1-F36)*(F46/F38+F39) -> 2128 | G66: =G36*IF(G37=0,G46,MIN(G46,G37))+(1-G36)*(G46/G38+G39) -> 2208 | H66: =H36*IF(H37=0,H46,MIN(H46,H37))+(1-H36)*(H46/H38+H39) -> 16384 | I66: =I36*IF(I37=0,I46,MIN(I46,I37))+(1-I36)*(I46/I38+I39) -> 2128 | J66: =J36*IF(J37=0,J46,MIN(J46,J37))+(1-J36)*(J46/J38+J39) -> 2208 | ... Q66: =Q36*IF(Q37=0,Q46,MIN(Q46,Q37))+(1-Q36)*(Q46/Q38+Q39) -> 16384
A67: prefill FLOPs/token | B67: GFLOP | C67: =(2*C28*1000000000+C35*C66)*C10/1000000000 -> 37.993612 | D67: =(2*D28*1000000000+D35*D66)*D10/1000000000 -> 133.30765 | E67: =(2*E28*1000000000+E35*E66)*E10/1000000000 -> 440.53064 | F67: =(2*F28*1000000000+F35*F66)*F10/1000000000 -> 37.993612 | G67: =(2*G28*1000000000+G35*G66)*G10/1000000000 -> 133.30765 | H67: =(2*H28*1000000000+H35*H66)*H10/1000000000 -> 440.53064 | I67: =(2*I28*1000000000+I35*I66)*I10/1000000000 -> 37.993612 | J67: =(2*J28*1000000000+J35*J66)*J10/1000000000 -> 133.30765 | ... Q67: =(2*Q28*1000000000+Q35*Q66)*Q10/1000000000 -> 440.53064
A68: E. 記憶體配置（attention DP＋wide EP；每 GPU）
A69: 可用 HBM | B69: GB | C69: =C15*(1-C56) -> 72 | D69: =D15*(1-D56) -> 72 | E69: =E15*(1-E56) -> 72 | F69: =F15*(1-F56) -> 167.4 | G69: =G15*(1-G56) -> 167.4 | H69: =H15*(1-H56) -> 167.4 | I69: =I15*(1-I56) -> 259.2 | J69: =J15*(1-J56) -> 259.2 | ... Q69: =Q15*(1-Q56) -> 921.6
A70: 注意力 TP 度（自動） | C70: =MAX(1,CEILING(C32*C20/(C57*C69),1)) -> 1 | D70: =MAX(1,CEILING(D32*D20/(D57*D69),1)) -> 2 | E70: =MAX(1,CEILING(E32*E20/(E57*E69),1)) -> 4 | F70: =MAX(1,CEILING(F32*F20/(F57*F69),1)) -> 1 | G70: =MAX(1,CEILING(G32*G20/(G57*G69),1)) -> 1 | H70: =MAX(1,CEILING(H32*H20/(H57*H69),1)) -> 2 | I70: =MAX(1,CEILING(I32*I20/(I57*I69),1)) -> 1 | J70: =MAX(1,CEILING(J32*J20/(J57*J69),1)) -> 1 | ... Q70: =MAX(1,CEILING(Q32*Q20/(Q57*Q69),1)) -> 1
A71: decode EP 寬度（自動） | B71: GPU | C71: =MAX(C18,CEILING(C33*C19/(C58*C69),1)) -> 64 | D71: =MAX(D18,CEILING(D33*D19/(D58*D69),1)) -> 64 | E71: =MAX(E18,CEILING(E33*E19/(E58*E69),1)) -> 138 | F71: =MAX(F18,CEILING(F33*F19/(F58*F69),1)) -> 32 | G71: =MAX(G18,CEILING(G33*G19/(G58*G69),1)) -> 32 | H71: =MAX(H18,CEILING(H33*H19/(H58*H69),1)) -> 34 | I71: =MAX(I18,CEILING(I33*I19/(I58*I69),1)) -> 32 | J71: =MAX(J18,CEILING(J33*J19/(J58*J69),1)) -> 32 | ... Q71: =MAX(Q18,CEILING(Q33*Q19/(Q58*Q69),1)) -> 64
A72: 每 GPU 權重 | B72: GB | C72: =C32*C20/C70+C33*C19/C71 -> 9.7649375 | D72: =D32*D20/D70+D33*D19/D71 -> 34.822049 | E72: =E32*E20/E70+E33*E19/E71 -> 40.898054 | F72: =F32*F20/F70+F33*F19/F71 -> 10.309055 | G72: =G32*G20/G70+G33*G19/G71 -> 48.046332 | H72: =H32*H20/H70+H33*H19/H71 -> 89.900898 | I72: =I32*I20/I70+I33*I19/I71 -> 10.309055 | J72: =J32*J20/J70+J33*J19/J71 -> 48.046332 | ... Q72: =Q32*Q20/Q70+Q33*Q19/Q71 -> 83.797529
A73: 權重占可用 HBM | B73: % | C73: =C72/C69 -> 0.13562413 | D73: =D72/D69 -> 0.48363956 | E73: =E72/E69 -> 0.56802853 | F73: =F72/F69 -> 0.061583361 | G73: =G72/G69 -> 0.28701513 | H73: =H72/H69 -> 0.5370424 | I73: =I72/I69 -> 0.039772588 | J73: =J72/J69 -> 0.18536394 | ... Q73: =Q72/Q69 -> 0.090926138
A74: F. Prefill（算力受限）
A75: prefill tok/s（每 prefill GPU） | B75: tok/s | C75: =C51*C14*1000000000000000/(C67*1000000000) -> 7813.1555 | D75: =D51*D14*1000000000000000/(D67*1000000000) -> 2226.8039 | E75: =E51*E14*1000000000000000/(E67*1000000000) -> 673.84644 | F75: =F51*F14*1000000000000000/(F67*1000000000) -> 78960.642 | G75: =G51*G14*1000000000000000/(G67*1000000000) -> 22504.335 | H75: =H51*H14*1000000000000000/(H67*1000000000) -> 6809.969 | I75: =I51*I14*1000000000000000/(I67*1000000000) -> 118440.96 | J75: =J51*J14*1000000000000000/(J67*1000000000) -> 33756.502 | ... Q75: =Q51*Q14*1000000000000000/(Q67*1000000000) -> 49712.774
A76: TTFT（計算部分） | B76: s | C76: =C43*C67*1000000000/(C51*C14*1000000000000000*C21) -> 0.131061 | D76: =D43*D67*1000000000/(D51*D14*1000000000000000*D21) -> 0.91970379 | E76: =E43*E67*1000000000/(E51*E14*1000000000000000*E21) -> 6.0785363 | F76: =F43*F67*1000000000/(F51*F14*1000000000000000*F21) -> 0.025936973 | G76: =G43*G67*1000000000/(G51*G14*1000000000000000*G21) -> 0.18200938 | H76: =H43*H67*1000000000/(H51*H14*1000000000000000*H21) -> 1.2029423 | I76: =I43*I67*1000000000/(I51*I14*1000000000000000*I21) -> 0.017291315 | J76: =J43*J67*1000000000/(J51*J14*1000000000000000*J21) -> 0.12133959 | ... Q76: =Q43*Q67*1000000000/(Q51*Q14*1000000000000000*Q21) -> 0.08239331
A77: TTFT 符合上限 | C77: =IF(C76<=C42,"是","否") -> 是 | D77: =IF(D76<=D42,"是","否") -> 是 | E77: =IF(E76<=E42,"是","否") -> 否 | F77: =IF(F76<=F42,"是","否") -> 是 | G77: =IF(G76<=G42,"是","否") -> 是 | H77: =IF(H76<=H42,"是","否") -> 是 | I77: =IF(I76<=I42,"是","否") -> 是 | J77: =IF(J76<=J42,"是","否") -> 是 | ... Q77: =IF(Q76<=Q42,"是","否") -> 是
A78: G. Decode：每步時間＝固定延遲＋B × 每序列時間；B* ＝ min(SLO 上限, HBM 容量上限)
A79: 每步固定延遲（權重讀取＋逐層延遲） | B79: ms | C79: =C72/C16+(C29+C47)*C55/1000 -> 13.974127 | D79: =D72/D16+(D29+D47)*D55/1000 -> 25.781383 | E79: =E72/E16+(E29+E47)*E55/1000 -> 36.971412 | F79: =F72/F16+(F29+F47)*F55/1000 -> 8.6614456 | G79: =G72/G16+(G29+G47)*G55/1000 -> 16.263619 | H79: =H72/H16+(H29+H47)*H55/1000 -> 27.746304 | I79: =I72/I16+(I29+I47)*I55/1000 -> 8.6614456 | J79: =J72/J16+(J29+J47)*J55/1000 -> 16.263619 | ... Q79: =Q72/Q16+(Q29+Q47)*Q55/1000 -> 19.127365
A80: 每序列每步 — 算力項 | B80: ms | C80: =(C47+1)*C65/(C14*C53)/1000 -> 1.4377091 | D80: =(D47+1)*D65/(D14*D53)/1000 -> 5.0053673 | E80: =(E47+1)*E65/(E14*E53)/1000 -> 19.856759 | F80: =(F47+1)*F65/(F14*F53)/1000 -> 0.42678394 | G80: =(G47+1)*G65/(G14*G53)/1000 -> 1.4858433 | H80: =(H47+1)*H65/(H14*H53)/1000 -> 5.8944788 | I80: =(I47+1)*I65/(I14*I53)/1000 -> 0.28452263 | J80: =(J47+1)*J65/(J14*J53)/1000 -> 0.99056219 | ... Q80: =(Q47+1)*Q65/(Q14*Q53)/1000 -> 0.80746285
A81: 每序列每步 — KV 讀取項 | B81: ms | C81: =C34*C45/(C16*C60)/1000000000 -> 0.010374277 | D81: =D34*D45/(D16*D60)/1000000000 -> 0.029433996 | E81: =E34*E45/(E16*E60)/1000000000 -> 0.85518192 | F81: =F34*F45/(F16*F60)/1000000000 -> 0.0043442286 | G81: =G34*G45/(G16*G60)/1000000000 -> 0.012325486 | H81: =H34*H45/(H16*H60)/1000000000 -> 0.35810743 | I81: =I34*I45/(I16*I60)/1000000000 -> 0.0043442286 | J81: =J34*J45/(J16*J60)/1000000000 -> 0.012325486 | ... Q81: =Q34*Q45/(Q16*Q60)/1000000000 -> 0.089526857
A82: 每序列每步 — EP 通訊項 | B82: ms | C82: =(C47+1)*C29*C31*C30*C59*(C71-1)/C71/(C17*C61)/1000000000 -> 0.3566592 | D82: =(D47+1)*D29*D31*D30*D59*(D71-1)/D71/(D17*D61)/1000000000 -> 0.8854272 | E82: =(E47+1)*E29*E31*E30*E59*(E71-1)/E71/(E17*E61)/1000000000 -> 6.691999 | F82: =(F47+1)*F29*F31*F30*F59*(F71-1)/F71/(F17*F61)/1000000000 -> 0.019499886 | G82: =(G47+1)*G29*G31*G30*G59*(G71-1)/G71/(G17*G61)/1000000000 -> 0.0484096 | H82: =(H47+1)*H29*H31*H30*H59*(H71-1)/H71/(H17*H61)/1000000000 -> 0.36347697 | I82: =(I47+1)*I29*I31*I30*I59*(I71-1)/I71/(I17*I61)/1000000000 -> 0.019499886 | J82: =(J47+1)*J29*J31*J30*J59*(J71-1)/J71/(J17*J61)/1000000000 -> 0.0484096 | ... Q82: =(Q47+1)*Q29*Q31*Q30*Q59*(Q71-1)/Q71/(Q17*Q61)/1000000000 -> 0.18432
A83: 每序列每步（取最大，假設三者可重疊） | B83: ms | C83: =MAX(C80,C81,C82) -> 1.4377091 | D83: =MAX(D80,D81,D82) -> 5.0053673 | E83: =MAX(E80,E81,E82) -> 19.856759 | F83: =MAX(F80,F81,F82) -> 0.42678394 | G83: =MAX(G80,G81,G82) -> 1.4858433 | H83: =MAX(H80,H81,H82) -> 5.8944788 | I83: =MAX(I80,I81,I82) -> 0.28452263 | J83: =MAX(J80,J81,J82) -> 0.99056219 | ... Q83: =MAX(Q80,Q81,Q82) -> 0.80746285
A84: 每序列綁定項 | C84: =IF(C83=C80,"算力",IF(C83=C81,"KV 頻寬","EP 通訊")) -> 算力 | D84: =IF(D83=D80,"算力",IF(D83=D81,"KV 頻寬","EP 通訊")) -> 算力 | E84: =IF(E83=E80,"算力",IF(E83=E81,"KV 頻寬","EP 通訊")) -> 算力 | F84: =IF(F83=F80,"算力",IF(F83=F81,"KV 頻寬","EP 通訊")) -> 算力 | G84: =IF(G83=G80,"算力",IF(G83=G81,"KV 頻寬","EP 通訊")) -> 算力 | H84: =IF(H83=H80,"算力",IF(H83=H81,"KV 頻寬","EP 通訊")) -> 算力 | I84: =IF(I83=I80,"算力",IF(I83=I81,"KV 頻寬","EP 通訊")) -> 算力 | J84: =IF(J83=J80,"算力",IF(J83=J81,"KV 頻寬","EP 通訊")) -> 算力 | ... Q84: =IF(Q83=Q80,"算力",IF(Q83=Q81,"KV 頻寬","EP 通訊")) -> 算力
A85: SLO 允許的批次上限 | B85: 序列/GPU | C85: =(1000*C49/C41-C79)/C83 -> 4.9622041 | D85: =(1000*D49/D41-D79)/D83 -> 2.6347412 | E85: =(1000*E49/E41-E79)/E83 -> 0.45743284 | F85: =(1000*F49/F41-F79)/F83 -> 29.164377 | G85: =(1000*G49/G41-G79)/G83 -> 15.281296 | H85: =(1000*H49/H41-H79)/H83 -> 3.1059984 | I85: =(1000*I49/I41-I79)/I83 -> 43.746565 | J85: =(1000*J49/J41-J79)/J83 -> 22.921944 | ... Q85: =(1000*Q49/Q41-Q79)/Q83 -> 33.347888
A86: HBM 容量允許的批次上限 | B86: 序列/GPU | C86: =(C69-C72)*1000000000/(C34*C45) -> 2558.1997 | D86: =(D69-D72)*1000000000/(D34*D45) -> 538.63353 | E86: =(E69-E72)*1000000000/(E34*E45) -> 15.509086 | F86: =(F69-F72)*1000000000/(F34*F45) -> 6457.2925 | G86: =(G69-G72)*1000000000/(G34*G45) -> 1729.1939 | H86: =(H69-H72)*1000000000/(H34*H45) -> 38.645178 | I86: =(I69-I72)*1000000000/(I34*I45) -> 10230.772 | J86: =(J69-J72)*1000000000/(J34*J45) -> 3059.1908 | ... Q86: =(Q69-Q72)*1000000000/(Q34*Q45) -> 417.77291
A87: 採用批次 B* | B87: 序列/GPU | C87: =MAX(0,MIN(C85,C86)) -> 4.9622041 | D87: =MAX(0,MIN(D85,D86)) -> 2.6347412 | E87: =MAX(0,MIN(E85,E86)) -> 0.45743284 | F87: =MAX(0,MIN(F85,F86)) -> 29.164377 | G87: =MAX(0,MIN(G85,G86)) -> 15.281296 | H87: =MAX(0,MIN(H85,H86)) -> 3.1059984 | I87: =MAX(0,MIN(I85,I86)) -> 43.746565 | J87: =MAX(0,MIN(J85,J86)) -> 22.921944 | ... Q87: =MAX(0,MIN(Q85,Q86)) -> 33.347888
A88: decode tok/s（每 decode GPU） | B88: tok/s | C88: =IF(C87>0,C87*C49/((C79+C87*C83)/1000),0) -> 595.46449 | D88: =IF(D87>0,D87*D49/((D79+D87*D83)/1000),0) -> 171.25818 | E88: =IF(E87>0,E87*E49/((E79+E87*E83)/1000),0) -> 25.158806 | F88: =IF(F87>0,F87*F49/((F79+F87*F83)/1000),0) -> 3499.7252 | G88: =IF(G87>0,G87*G49/((G79+G87*G83)/1000),0) -> 993.28425 | H88: =IF(H87>0,H87*H49/((H79+H87*H83)/1000),0) -> 170.82991 | I88: =IF(I87>0,I87*I49/((I79+I87*I83)/1000),0) -> 5249.5878 | J88: =IF(J87>0,J87*J49/((J79+J87*J83)/1000),0) -> 1489.9264 | ... Q88: =IF(Q87>0,Q87*Q49/((Q79+Q87*Q83)/1000),0) -> 1834.1339
A89: 實際每用戶速度 | B89: tok/s | C89: =IF(C87>0,C49/((C79+C87*C83)/1000),0) -> 120 | D89: =IF(D87>0,D49/((D79+D87*D83)/1000),0) -> 65 | E89: =IF(E87>0,E49/((E79+E87*E83)/1000),0) -> 55 | F89: =IF(F87>0,F49/((F79+F87*F83)/1000),0) -> 120 | G89: =IF(G87>0,G49/((G79+G87*G83)/1000),0) -> 65 | H89: =IF(H87>0,H49/((H79+H87*H83)/1000),0) -> 55 | I89: =IF(I87>0,I49/((I79+I87*I83)/1000),0) -> 120 | J89: =IF(J87>0,J49/((J79+J87*J83)/1000),0) -> 65 | ... Q89: =IF(Q87>0,Q49/((Q79+Q87*Q83)/1000),0) -> 55
A90: 綁定約束 | C90: =IF(C87<=0,"SLO 不可達",IF(C85<=C86,"SLO（"&C84&"）","HBM 容量")) -> SLO（算力） | D90: =IF(D87<=0,"SLO 不可達",IF(D85<=D86,"SLO（"&D84&"）","HBM 容量")) -> SLO（算力） | E90: =IF(E87<=0,"SLO 不可達",IF(E85<=E86,"SLO（"&E84&"）","HBM 容量")) -> SLO（算力） | F90: =IF(F87<=0,"SLO 不可達",IF(F85<=F86,"SLO（"&F84&"）","HBM 容量")) -> SLO（算力） | G90: =IF(G87<=0,"SLO 不可達",IF(G85<=G86,"SLO（"&G84&"）","HBM 容量")) -> SLO（算力） | H90: =IF(H87<=0,"SLO 不可達",IF(H85<=H86,"SLO（"&H84&"）","HBM 容量")) -> SLO（算力） | I90: =IF(I87<=0,"SLO 不可達",IF(I85<=I86,"SLO（"&I84&"）","HBM 容量")) -> SLO（算力） | J90: =IF(J87<=0,"SLO 不可達",IF(J85<=J86,"SLO（"&J84&"）","HBM 容量")) -> SLO（算力） | ... Q90: =IF(Q87<=0,"SLO 不可達",IF(Q85<=Q86,"SLO（"&Q84&"）","HBM 容量")) -> SLO（算力）
A91: KV 占可用 HBM | B91: % | C91: =C87*C34*C45/1000000000/C69 -> 0.0016766516 | D91: =D87*D34*D45/1000000000/D69 -> 0.0025257917 | E91: =E87*E34*E45/1000000000/E69 -> 0.012740785 | F91: =F87*F34*F45/1000000000/F69 -> 0.004238361 | G91: =G87*G34*G45/1000000000/G69 -> 0.0063008162 | H91: =H87*H34*H45/1000000000/H69 -> 0.037208925 | I91: =I87*I34*I45/1000000000/I69 -> 0.0041059122 | J91: =J87*J34*J45/1000000000/J69 -> 0.0061039156 | ... Q91: =Q87*Q34*Q45/1000000000/Q69 -> 0.072565005
A92: H. 每架與每 GW（參考任務；P:D 依工作量配比；100% 利用率）
A93: 每請求 GPU 秒 | B93: GPU-s | C93: =IF(C88>0,C43/C75+C44/C88,0) -> 2.768154 | D93: =IF(D88>0,D43/D75+D44/D88,0) -> 19.316183 | E93: =IF(E88>0,E43/E75+E44/E88,0) -> 211.43411 | F93: =IF(F88>0,F43/F75+F44/F88,0) -> 0.39634229 | G93: =IF(G88>0,G43/G75+G44/G88,0) -> 2.7898844 | H93: =IF(H88>0,H43/H75+H44/H88,0) -> 28.788835 | I93: =IF(I88>0,I43/I75+I44/I88,0) -> 0.26422819 | J93: =IF(J88>0,J43/J75+J44/J88,0) -> 1.8599229 | ... Q93: =IF(Q88>0,Q43/Q75+Q44/Q88,0) -> 2.8923532
A94: prefill GPU 占比 | B94: % | C94: =IF(C93>0,(C43/C75)/C93,0) -> 0.37876796 | D94: =IF(D93>0,(D43/D75)/D93,0) -> 0.38090497 | E94: =IF(E93>0,(E43/E75)/E93,0) -> 0.22999265 | F94: =IF(F93>0,(F43/F75)/F93,0) -> 0.26176336 | G94: =IF(G93>0,(G43/G75)/G93,0) -> 0.26095616 | H94: =IF(H93>0,(H43/H75)/H93,0) -> 0.16714012 | I94: =IF(I93>0,(I43/I75)/I93,0) -> 0.26176336 | J94: =IF(J93>0,(J43/J75)/J93,0) -> 0.26095616 | ... Q94: =IF(Q93>0,(Q43/Q75)/Q93,0) -> 0.22789281
A95: 每架總 tok/s | B95: tok/s | C95: =IF(C93>0,C22*(C43+C44)/C93,0) -> 106537.43 | D95: =IF(D93>0,D22*(D43+D44)/D93,0) -> 30535.225 | E95: =IF(E93>0,E22*(E43+E44)/E93,0) -> 5579.2701 | F95: =IF(F93>0,F22*(F43+F44)/F93,0) -> 1674189.2 | G95: =IF(G93>0,G22*(G43+G44)/G93,0) -> 475684.23 | H95: =IF(H93>0,H22*(H43+H44)/H93,0) -> 92195.741 | I95: =IF(I93>0,I22*(I43+I44)/I93,0) -> 2511283.9 | J95: =IF(J93>0,J22*(J43+J44)/J93,0) -> 713526.35 | ... Q95: =IF(Q93>0,Q22*(Q43+Q44)/Q93,0) -> 1835327.7
A96: 每架 decode tok/s | B96: tok/s | C96: =C95*C44/(C43+C44) -> 11837.492 | D96: =D95*D44/(D43+D44) -> 3392.8028 | E96: =E95*E44/(E43+E44) -> 619.9189 | F96: =F95*F44/(F43+F44) -> 186021.03 | G96: =G95*G44/(G43+G44) -> 52853.803 | H96: =H95*H44/(H43+H44) -> 10243.971 | I96: =I95*I44/(I43+I44) -> 279031.54 | J96: =J95*J44/(J43+J44) -> 79280.705 | ... Q96: =Q95*Q44/(Q43+Q44) -> 203925.3
A97: 每架 prefill tok/s | B97: tok/s | C97: =C95-C96 -> 94699.935 | D97: =D95-D96 -> 27142.422 | E97: =E95-E96 -> 4959.3512 | F97: =F95-F96 -> 1488168.2 | G97: =G95-G96 -> 422830.43 | H97: =H95-H96 -> 81951.77 | I97: =I95-I96 -> 2232252.3 | J97: =J95-J96 -> 634245.64 | ... Q97: =Q95-Q96 -> 1631402.4
A98: 每 GW 總產出 | B98: M tok/年 | C98: =C95*C25*8760*3600/1000000 -> 7.5389751e+10 | D98: =D95*D25*8760*3600/1000000 -> 2.1607834e+10 | E98: =E95*E25*8760*3600/1000000 -> 3.9480941e+09 | F98: =F95*F25*8760*3600/1000000 -> 3.7359321e+11 | G98: =G95*G25*8760*3600/1000000 -> 1.0614833e+11 | H98: =H95*H25*8760*3600/1000000 -> 2.0573363e+10 | I98: =I95*I25*8760*3600/1000000 -> 5.3180012e+11 | J98: =J95*J25*8760*3600/1000000 -> 1.5109936e+11 | ... Q98: =Q95*Q25*8760*3600/1000000 -> 8.8728347e+10
A99: 每 GW decode 產出 | B99: M tok/年 | C99: =C96*C25*8760*3600/1000000 -> 8.376639e+09 | D99: =D96*D25*8760*3600/1000000 -> 2.4008704e+09 | E99: =E96*E25*8760*3600/1000000 -> 4.3867712e+08 | F99: =F96*F25*8760*3600/1000000 -> 4.1510357e+10 | G99: =G96*G25*8760*3600/1000000 -> 1.1794259e+10 | H99: =H96*H25*8760*3600/1000000 -> 2.2859292e+09 | I99: =I96*I25*8760*3600/1000000 -> 5.9088902e+10 | J99: =J96*J25*8760*3600/1000000 -> 1.6788818e+10 | ... Q99: =Q96*Q25*8760*3600/1000000 -> 9.8587052e+09
A100: I. 每 M token GPU 秒（供 Unit_Cost）與速覽成本
A101: 新鮮 prefill | B101: GPU-s/M | C101: =1000000/C75 -> 127.98926 | D101: =1000000/D75 -> 449.07412 | E101: =1000000/E75 -> 1484.0176 | F101: =1000000/F75 -> 12.664537 | G101: =1000000/G75 -> 44.435884 | H101: =1000000/H75 -> 146.84355 | I101: =1000000/I75 -> 8.443025 | J101: =1000000/J75 -> 29.623922 | ... Q101: =1000000/Q75 -> 20.115554
A102: 快取命中 prefill（KV 載入） | B102: GPU-s/M | C102: =1000000*C34/(C62*1000000000000) -> 0.02795 | D102: =1000000*D34/(D62*1000000000000) -> 0.03965 | E102: =1000000*E34/(E62*1000000000000) -> 0.576 | F102: =1000000*F34/(F62*1000000000000) -> 0.02795 | G102: =1000000*G34/(G62*1000000000000) -> 0.03965 | H102: =1000000*H34/(H62*1000000000000) -> 0.576 | I102: =1000000*I34/(I62*1000000000000) -> 0.02795 | J102: =1000000*J34/(J62*1000000000000) -> 0.03965 | ... Q102: =1000000*Q34/(Q62*1000000000000) -> 0.576
...

Sheet Sens_Perf
A1: Sens_Perf — VR200 對 GB300 的單變數敏感度（先看敏感度，再看基準）
A2: 每組兩欄：左 VR200、右 GB300。黃底藍字＝該情境改動的輸入。GB300 為校準世代，VR200 的 η_d 與每層延遲為沿用值 [Analogy]，故 VR 專屬情境只動 VR 欄
A3: 情境 | C3: 基準 | E3: VR η_d × 0.5（新世代軟體未成熟） | G3: VR η_d × 1.5 | I3: VR 每層延遲 × 0.7 | K3: VR 每層延遲 × 1.5 | M3: VR 峰值 50 PF（J2 高情境） | O3: SLO 40 tok/s | Q3: SLO 100 tok/s | S3: MTP 接受率 0.60 | U3: MTP 接受率 0.80 | W3: ISL 4K | Y3: ISL 64K | AA3: 生產折減 0.7（兩世代） | AC3: Astra KV 情境 1（混合） | AE3: Astra KV 情境 2（全層 MLA，基準） | AG3: Astra KV 情境 3（GQA-8）
A4: 世代 | C4: =INDEX(Spec_Rack!$C$4:$G$4,C6) -> VR200 NVL72 | D4: =INDEX(Spec_Rack!$C$4:$G$4,D6) -> GB300 NVL72 | E4: =INDEX(Spec_Rack!$C$4:$G$4,E6) -> VR200 NVL72 | F4: =INDEX(Spec_Rack!$C$4:$G$4,F6) -> GB300 NVL72 | G4: =INDEX(Spec_Rack!$C$4:$G$4,G6) -> VR200 NVL72 | H4: =INDEX(Spec_Rack!$C$4:$G$4,H6) -> GB300 NVL72 | I4: =INDEX(Spec_Rack!$C$4:$G$4,I6) -> VR200 NVL72 | J4: =INDEX(Spec_Rack!$C$4:$G$4,J6) -> GB300 NVL72 | ... AH4: =INDEX(Spec_Rack!$C$4:$G$4,AH6) -> GB300 NVL72
A5: 層級 | C5: =INDEX(Arch!$C$4:$E$4,C7) -> Sol（中層） | D5: =INDEX(Arch!$C$4:$E$4,D7) -> Sol（中層） | E5: =INDEX(Arch!$C$4:$E$4,E7) -> Sol（中層） | F5: =INDEX(Arch!$C$4:$E$4,F7) -> Sol（中層） | G5: =INDEX(Arch!$C$4:$E$4,G7) -> Sol（中層） | H5: =INDEX(Arch!$C$4:$E$4,H7) -> Sol（中層） | I5: =INDEX(Arch!$C$4:$E$4,I7) -> Sol（中層） | J5: =INDEX(Arch!$C$4:$E$4,J7) -> Sol（中層） | ... AH5: =INDEX(Arch!$C$4:$E$4,AH7) -> Astra（頂層）
A6: 世代索引 | C6: 4 | D6: 3 | E6: 4 | F6: 3 | G6: 4 | H6: 3 | I6: 4 | J6: 3 | K6: 4 | L6: 3 | M6: 4 | N6: 3 | O6: 4 | P6: 3 | Q6: 4 | R6: 3 | S6: 4 | T6: 3 | U6: 4 | V6: 3 | W6: 4 | X6: 3 | Y6: 4 | Z6: 3 | AA6: 4 | AB6: 3 | AC6: 4 | AD6: 3 | AE6: 4 | AF6: 3 | AG6: 4 | AH6: 3
A7: 層級索引 | C7: 2 | D7: 2 | E7: 2 | F7: 2 | G7: 2 | H7: 2 | I7: 2 | J7: 2 | K7: 2 | L7: 2 | M7: 2 | N7: 2 | O7: 2 | P7: 2 | Q7: 2 | R7: 2 | S7: 2 | T7: 2 | U7: 2 | V7: 2 | W7: 2 | X7: 2 | Y7: 2 | Z7: 2 | AA7: 2 | AB7: 2 | AC7: 3 | AD7: 3 | AE7: 3 | AF7: 3 | AG7: 3 | AH7: 3
A9: 0. Tech_Registry 掛鉤（基準＝1；Registry 未啟用任何條目時與 v5.4 相同）
A10: FLOPs/token 倍數（H_FLOP） | B10: x | C10: =Tech_Registry!$E$22 -> 1 | D10: =Tech_Registry!$E$22 -> 1 | E10: =Tech_Registry!$E$22 -> 1 | F10: =Tech_Registry!$E$22 -> 1 | G10: =Tech_Registry!$E$22 -> 1 | H10: =Tech_Registry!$E$22 -> 1 | I10: =Tech_Registry!$E$22 -> 1 | J10: =Tech_Registry!$E$22 -> 1 | ... AH10: =Tech_Registry!$E$22 -> 1
A11: KV bytes/token 倍數（H_KV） | B11: x | C11: =Tech_Registry!$E$23 -> 1 | D11: =Tech_Registry!$E$23 -> 1 | E11: =Tech_Registry!$E$23 -> 1 | F11: =Tech_Registry!$E$23 -> 1 | G11: =Tech_Registry!$E$23 -> 1 | H11: =Tech_Registry!$E$23 -> 1 | I11: =Tech_Registry!$E$23 -> 1 | J11: =Tech_Registry!$E$23 -> 1 | ... AH11: =Tech_Registry!$E$23 -> 1
A12: 權重 bytes/param 倍數（H_WB） | B12: x | C12: =Tech_Registry!$E$24 -> 1 | D12: =Tech_Registry!$E$24 -> 1 | E12: =Tech_Registry!$E$24 -> 1 | F12: =Tech_Registry!$E$24 -> 1 | G12: =Tech_Registry!$E$24 -> 1 | H12: =Tech_Registry!$E$24 -> 1 | I12: =Tech_Registry!$E$24 -> 1 | J12: =Tech_Registry!$E$24 -> 1 | ... AH12: =Tech_Registry!$E$24 -> 1
A13: A. 規格（連結 Spec_Rack、DC_Cost）
A14: 計算用峰值 | B14: PF/GPU | C14: =INDEX(Spec_Rack!$C$35:$G$35,C$6) -> 35 | D14: =INDEX(Spec_Rack!$C$35:$G$35,D$6) -> 15 | E14: =INDEX(Spec_Rack!$C$35:$G$35,E$6) -> 35 | F14: =INDEX(Spec_Rack!$C$35:$G$35,F$6) -> 15 | G14: =INDEX(Spec_Rack!$C$35:$G$35,G$6) -> 35 | H14: =INDEX(Spec_Rack!$C$35:$G$35,H$6) -> 15 | I14: =INDEX(Spec_Rack!$C$35:$G$35,I$6) -> 35 | J14: =INDEX(Spec_Rack!$C$35:$G$35,J$6) -> 15 | ... L14: =INDEX(Spec_Rack!$C$35:$G$35,L$6) -> 15 | M14: 50 | N14: =INDEX(Spec_Rack!$C$35:$G$35,N$6) -> 15 | O14: =INDEX(Spec_Rack!$C$35:$G$35,O$6) -> 35 | P14: =INDEX(Spec_Rack!$C$35:$G$35,P$6) -> 15 | Q14: =INDEX(Spec_Rack!$C$35:$G$35,Q$6) -> 35 | R14: =INDEX(Spec_Rack!$C$35:$G$35,R$6) -> 15 | S14: =INDEX(Spec_Rack!$C$35:$G$35,S$6) -> 35 | T14: =INDEX(Spec_Rack!$C$35:$G$35,T$6) -> 15 | U14: =INDEX(Spec_Rack!$C$35:$G$35,U$6) -> 35 | ... AH14: =INDEX(Spec_Rack!$C$35:$G$35,AH$6) -> 15
A15: HBM 容量 | B15: GB/GPU | C15: =INDEX(Spec_Rack!$C$25:$G$25,C$6) -> 288 | D15: =INDEX(Spec_Rack!$C$25:$G$25,D$6) -> 288 | E15: =INDEX(Spec_Rack!$C$25:$G$25,E$6) -> 288 | F15: =INDEX(Spec_Rack!$C$25:$G$25,F$6) -> 288 | G15: =INDEX(Spec_Rack!$C$25:$G$25,G$6) -> 288 | H15: =INDEX(Spec_Rack!$C$25:$G$25,H$6) -> 288 | I15: =INDEX(Spec_Rack!$C$25:$G$25,I$6) -> 288 | J15: =INDEX(Spec_Rack!$C$25:$G$25,J$6) -> 288 | ... AH15: =INDEX(Spec_Rack!$C$25:$G$25,AH$6) -> 288
A16: HBM 頻寬 | B16: TB/s/GPU | C16: =INDEX(Spec_Rack!$C$26:$G$26,C$6) -> 22 | D16: =INDEX(Spec_Rack!$C$26:$G$26,D$6) -> 8 | E16: =INDEX(Spec_Rack!$C$26:$G$26,E$6) -> 22 | F16: =INDEX(Spec_Rack!$C$26:$G$26,F$6) -> 8 | G16: =INDEX(Spec_Rack!$C$26:$G$26,G$6) -> 22 | H16: =INDEX(Spec_Rack!$C$26:$G$26,H$6) -> 8 | I16: =INDEX(Spec_Rack!$C$26:$G$26,I$6) -> 22 | J16: =INDEX(Spec_Rack!$C$26:$G$26,J$6) -> 8 | ... AH16: =INDEX(Spec_Rack!$C$26:$G$26,AH$6) -> 8
A17: EP 通訊頻寬（單向） | B17: TB/s/GPU | C17: =INDEX(Spec_Rack!$C$27:$G$27,C$6) -> 1.8 | D17: =INDEX(Spec_Rack!$C$27:$G$27,D$6) -> 0.9 | E17: =INDEX(Spec_Rack!$C$27:$G$27,E$6) -> 1.8 | F17: =INDEX(Spec_Rack!$C$27:$G$27,F$6) -> 0.9 | G17: =INDEX(Spec_Rack!$C$27:$G$27,G$6) -> 1.8 | H17: =INDEX(Spec_Rack!$C$27:$G$27,H$6) -> 0.9 | I17: =INDEX(Spec_Rack!$C$27:$G$27,I$6) -> 1.8 | J17: =INDEX(Spec_Rack!$C$27:$G$27,J$6) -> 0.9 | ... AH17: =INDEX(Spec_Rack!$C$27:$G$27,AH$6) -> 0.9
A18: decode EP 基準寬度 | B18: GPU | C18: =INDEX(Spec_Rack!$C$29:$G$29,C$6) -> 32 | D18: =INDEX(Spec_Rack!$C$29:$G$29,D$6) -> 32 | E18: =INDEX(Spec_Rack!$C$29:$G$29,E$6) -> 32 | F18: =INDEX(Spec_Rack!$C$29:$G$29,F$6) -> 32 | G18: =INDEX(Spec_Rack!$C$29:$G$29,G$6) -> 32 | H18: =INDEX(Spec_Rack!$C$29:$G$29,H$6) -> 32 | I18: =INDEX(Spec_Rack!$C$29:$G$29,I$6) -> 32 | J18: =INDEX(Spec_Rack!$C$29:$G$29,J$6) -> 32 | ... AH18: =INDEX(Spec_Rack!$C$29:$G$29,AH$6) -> 32
A19: 專家權重 bytes/param（含 H_WB） | B19: B | C19: =INDEX(Spec_Rack!$C$30:$G$30,C$6)*C12 -> 0.5625 | D19: =INDEX(Spec_Rack!$C$30:$G$30,D$6)*D12 -> 0.5625 | E19: =INDEX(Spec_Rack!$C$30:$G$30,E$6)*E12 -> 0.5625 | F19: =INDEX(Spec_Rack!$C$30:$G$30,F$6)*F12 -> 0.5625 | G19: =INDEX(Spec_Rack!$C$30:$G$30,G$6)*G12 -> 0.5625 | H19: =INDEX(Spec_Rack!$C$30:$G$30,H$6)*H12 -> 0.5625 | I19: =INDEX(Spec_Rack!$C$30:$G$30,I$6)*I12 -> 0.5625 | J19: =INDEX(Spec_Rack!$C$30:$G$30,J$6)*J12 -> 0.5625 | ... AH19: =INDEX(Spec_Rack!$C$30:$G$30,AH$6)*AH12 -> 0.5625
A20: 非專家權重 bytes/param（含 H_WB） | B20: B | C20: =INDEX(Spec_Rack!$C$31:$G$31,C$6)*C12 -> 1 | D20: =INDEX(Spec_Rack!$C$31:$G$31,D$6)*D12 -> 1 | E20: =INDEX(Spec_Rack!$C$31:$G$31,E$6)*E12 -> 1 | F20: =INDEX(Spec_Rack!$C$31:$G$31,F$6)*F12 -> 1 | G20: =INDEX(Spec_Rack!$C$31:$G$31,G$6)*G12 -> 1 | H20: =INDEX(Spec_Rack!$C$31:$G$31,H$6)*H12 -> 1 | I20: =INDEX(Spec_Rack!$C$31:$G$31,I$6)*I12 -> 1 | J20: =INDEX(Spec_Rack!$C$31:$G$31,J$6)*J12 -> 1 | ... AH20: =INDEX(Spec_Rack!$C$31:$G$31,AH$6)*AH12 -> 1
A21: 每 prefill 實例 GPU 數 | B21: GPU | C21: =INDEX(Spec_Rack!$C$32:$G$32,C$6) -> 4 | D21: =INDEX(Spec_Rack!$C$32:$G$32,D$6) -> 4 | E21: =INDEX(Spec_Rack!$C$32:$G$32,E$6) -> 4 | F21: =INDEX(Spec_Rack!$C$32:$G$32,F$6) -> 4 | G21: =INDEX(Spec_Rack!$C$32:$G$32,G$6) -> 4 | H21: =INDEX(Spec_Rack!$C$32:$G$32,H$6) -> 4 | I21: =INDEX(Spec_Rack!$C$32:$G$32,I$6) -> 4 | J21: =INDEX(Spec_Rack!$C$32:$G$32,J$6) -> 4 | ... AH21: =INDEX(Spec_Rack!$C$32:$G$32,AH$6) -> 4
A22: GPU 封裝／架 | B22: 顆 | C22: =INDEX(Spec_Rack!$C$6:$G$6,C$6) -> 72 | D22: =INDEX(Spec_Rack!$C$6:$G$6,D$6) -> 72 | E22: =INDEX(Spec_Rack!$C$6:$G$6,E$6) -> 72 | F22: =INDEX(Spec_Rack!$C$6:$G$6,F$6) -> 72 | G22: =INDEX(Spec_Rack!$C$6:$G$6,G$6) -> 72 | H22: =INDEX(Spec_Rack!$C$6:$G$6,H$6) -> 72 | I22: =INDEX(Spec_Rack!$C$6:$G$6,I$6) -> 72 | J22: =INDEX(Spec_Rack!$C$6:$G$6,J$6) -> 72 | ... AH22: =INDEX(Spec_Rack!$C$6:$G$6,AH$6) -> 72
A23: GPU 功率 | B23: W | C23: =INDEX(Spec_Rack!$C$33:$G$33,C$6) -> 1800 | D23: =INDEX(Spec_Rack!$C$33:$G$33,D$6) -> 1400 | E23: =INDEX(Spec_Rack!$C$33:$G$33,E$6) -> 1800 | F23: =INDEX(Spec_Rack!$C$33:$G$33,F$6) -> 1400 | G23: =INDEX(Spec_Rack!$C$33:$G$33,G$6) -> 1800 | H23: =INDEX(Spec_Rack!$C$33:$G$33,H$6) -> 1400 | I23: =INDEX(Spec_Rack!$C$33:$G$33,I$6) -> 1800 | J23: =INDEX(Spec_Rack!$C$33:$G$33,J$6) -> 1400 | ... AH23: =INDEX(Spec_Rack!$C$33:$G$33,AH$6) -> 1400
A24: HBM 存取能量 | B24: pJ/B | C24: =INDEX(Spec_Rack!$C$34:$G$34,C$6) -> 20 | D24: =INDEX(Spec_Rack!$C$34:$G$34,D$6) -> 25 | E24: =INDEX(Spec_Rack!$C$34:$G$34,E$6) -> 20 | F24: =INDEX(Spec_Rack!$C$34:$G$34,F$6) -> 25 | G24: =INDEX(Spec_Rack!$C$34:$G$34,G$6) -> 20 | H24: =INDEX(Spec_Rack!$C$34:$G$34,H$6) -> 25 | I24: =INDEX(Spec_Rack!$C$34:$G$34,I$6) -> 20 | J24: =INDEX(Spec_Rack!$C$34:$G$34,J$6) -> 25 | ... AH24: =INDEX(Spec_Rack!$C$34:$G$34,AH$6) -> 25
A25: 每 GW 機架數（功率情境） | B25: 架 | C25: =INDEX(DC_Cost!$C$12:$Q$12,3*(C$6-1)+2) -> 4052 | D25: =INDEX(DC_Cost!$C$12:$Q$12,3*(D$6-1)+2) -> 6715 | E25: =INDEX(DC_Cost!$C$12:$Q$12,3*(E$6-1)+2) -> 4052 | F25: =INDEX(DC_Cost!$C$12:$Q$12,3*(F$6-1)+2) -> 6715 | G25: =INDEX(DC_Cost!$C$12:$Q$12,3*(G$6-1)+2) -> 4052 | H25: =INDEX(DC_Cost!$C$12:$Q$12,3*(H$6-1)+2) -> 6715 | I25: =INDEX(DC_Cost!$C$12:$Q$12,3*(I$6-1)+2) -> 4052 | J25: =INDEX(DC_Cost!$C$12:$Q$12,3*(J$6-1)+2) -> 6715 | ... AH25: =INDEX(DC_Cost!$C$12:$Q$12,3*(AH$6-1)+2) -> 6715
A26: 每架配電設計功率 | B26: kW | C26: =INDEX(DC_Cost!$C$11:$Q$11,3*(C$6-1)+2) -> 227 | D26: =INDEX(DC_Cost!$C$11:$Q$11,3*(D$6-1)+2) -> 137 | E26: =INDEX(DC_Cost!$C$11:$Q$11,3*(E$6-1)+2) -> 227 | F26: =INDEX(DC_Cost!$C$11:$Q$11,3*(F$6-1)+2) -> 137 | G26: =INDEX(DC_Cost!$C$11:$Q$11,3*(G$6-1)+2) -> 227 | H26: =INDEX(DC_Cost!$C$11:$Q$11,3*(H$6-1)+2) -> 137 | I26: =INDEX(DC_Cost!$C$11:$Q$11,3*(I$6-1)+2) -> 227 | J26: =INDEX(DC_Cost!$C$11:$Q$11,3*(J$6-1)+2) -> 137 | ... AH26: =INDEX(DC_Cost!$C$11:$Q$11,3*(AH$6-1)+2) -> 137
A27: B. 架構（連結 Arch）
A28: 啟用參數 | B28: B | C28: =INDEX(Arch!$C$7:$E$7,C$7) -> 49 | D28: =INDEX(Arch!$C$7:$E$7,D$7) -> 49 | E28: =INDEX(Arch!$C$7:$E$7,E$7) -> 49 | F28: =INDEX(Arch!$C$7:$E$7,F$7) -> 49 | G28: =INDEX(Arch!$C$7:$E$7,G$7) -> 49 | H28: =INDEX(Arch!$C$7:$E$7,H$7) -> 49 | I28: =INDEX(Arch!$C$7:$E$7,I$7) -> 49 | J28: =INDEX(Arch!$C$7:$E$7,J$7) -> 49 | ... AH28: =INDEX(Arch!$C$7:$E$7,AH$7) -> 180
A29: 層數 | B29: 層 | C29: =INDEX(Arch!$C$8:$E$8,C$7) -> 61 | D29: =INDEX(Arch!$C$8:$E$8,D$7) -> 61 | E29: =INDEX(Arch!$C$8:$E$8,E$7) -> 61 | F29: =INDEX(Arch!$C$8:$E$8,F$7) -> 61 | G29: =INDEX(Arch!$C$8:$E$8,G$7) -> 61 | H29: =INDEX(Arch!$C$8:$E$8,H$7) -> 61 | I29: =INDEX(Arch!$C$8:$E$8,I$7) -> 61 | J29: =INDEX(Arch!$C$8:$E$8,J$7) -> 61 | ... AH29: =INDEX(Arch!$C$8:$E$8,AH$7) -> 100
A30: d_model | C30: =INDEX(Arch!$C$9:$E$9,C$7) -> 7168 | D30: =INDEX(Arch!$C$9:$E$9,D$7) -> 7168 | E30: =INDEX(Arch!$C$9:$E$9,E$7) -> 7168 | F30: =INDEX(Arch!$C$9:$E$9,F$7) -> 7168 | G30: =INDEX(Arch!$C$9:$E$9,G$7) -> 7168 | H30: =INDEX(Arch!$C$9:$E$9,H$7) -> 7168 | I30: =INDEX(Arch!$C$9:$E$9,I$7) -> 7168 | J30: =INDEX(Arch!$C$9:$E$9,J$7) -> 7168 | ... AH30: =INDEX(Arch!$C$9:$E$9,AH$7) -> 12288
A31: 啟用 routed experts | C31: =INDEX(Arch!$C$13:$E$13,C$7) -> 6 | D31: =INDEX(Arch!$C$13:$E$13,D$7) -> 6 | E31: =INDEX(Arch!$C$13:$E$13,E$7) -> 6 | F31: =INDEX(Arch!$C$13:$E$13,F$7) -> 6 | G31: =INDEX(Arch!$C$13:$E$13,G$7) -> 6 | H31: =INDEX(Arch!$C$13:$E$13,H$7) -> 6 | I31: =INDEX(Arch!$C$13:$E$13,I$7) -> 6 | J31: =INDEX(Arch!$C$13:$E$13,J$7) -> 6 | ... AH31: =INDEX(Arch!$C$13:$E$13,AH$7) -> 16
A32: 非專家參數 | B32: B | C32: =INDEX(Arch!$C$28:$E$28,C$7) -> 20.277778 | D32: =INDEX(Arch!$C$28:$E$28,D$7) -> 20.277778 | E32: =INDEX(Arch!$C$28:$E$28,E$7) -> 20.277778 | F32: =INDEX(Arch!$C$28:$E$28,F$7) -> 20.277778 | G32: =INDEX(Arch!$C$28:$E$28,G$7) -> 20.277778 | H32: =INDEX(Arch!$C$28:$E$28,H$7) -> 20.277778 | I32: =INDEX(Arch!$C$28:$E$28,I$7) -> 20.277778 | J32: =INDEX(Arch!$C$28:$E$28,J$7) -> 20.277778 | ... AH32: =INDEX(Arch!$C$28:$E$28,AH$7) -> 49.072581
A33: 專家參數 | B33: B | C33: =INDEX(Arch!$C$29:$E$29,C$7) -> 1579.7222 | D33: =INDEX(Arch!$C$29:$E$29,D$7) -> 1579.7222 | E33: =INDEX(Arch!$C$29:$E$29,E$7) -> 1579.7222 | F33: =INDEX(Arch!$C$29:$E$29,F$7) -> 1579.7222 | G33: =INDEX(Arch!$C$29:$E$29,G$7) -> 1579.7222 | H33: =INDEX(Arch!$C$29:$E$29,H$7) -> 1579.7222 | I33: =INDEX(Arch!$C$29:$E$29,I$7) -> 1579.7222 | J33: =INDEX(Arch!$C$29:$E$29,J$7) -> 1579.7222 | ... AH33: =INDEX(Arch!$C$29:$E$29,AH$7) -> 3950.9274
A34: KV bytes/token（含 H_KV） | B34: B | C34: =INDEX(Arch!$C$25:$E$25,C$7)*C11 -> 3965 | D34: =INDEX(Arch!$C$25:$E$25,D$7)*D11 -> 3965 | E34: =INDEX(Arch!$C$25:$E$25,E$7)*E11 -> 3965 | F34: =INDEX(Arch!$C$25:$E$25,F$7)*F11 -> 3965 | G34: =INDEX(Arch!$C$25:$E$25,G$7)*G11 -> 3965 | H34: =INDEX(Arch!$C$25:$E$25,H$7)*H11 -> 3965 | I34: =INDEX(Arch!$C$25:$E$25,I$7)*I11 -> 3965 | J34: =INDEX(Arch!$C$25:$E$25,J$7)*J11 -> 3965 | ... AB34: =INDEX(Arch!$C$25:$E$25,AB$7)*AB11 -> 3965 | AC34: =Arch!$E$21 -> 14976 | AD34: =Arch!$E$21 -> 14976 | AE34: =Arch!$E$22 -> 57600 | AF34: =Arch!$E$22 -> 57600 | AG34: =Arch!$E$23 -> 204800 | AH34: =Arch!$E$23 -> 204800
A35: 注意力 FLOPs／被注意 token | B35: FLOP | C35: =INDEX(Arch!$C$30:$E$30,C$7) -> 15990784 | D35: =INDEX(Arch!$C$30:$E$30,D$7) -> 15990784 | E35: =INDEX(Arch!$C$30:$E$30,E$7) -> 15990784 | F35: =INDEX(Arch!$C$30:$E$30,F$7) -> 15990784 | G35: =INDEX(Arch!$C$30:$E$30,G$7) -> 15990784 | H35: =INDEX(Arch!$C$30:$E$30,H$7) -> 15990784 | I35: =INDEX(Arch!$C$30:$E$30,I$7) -> 15990784 | J35: =INDEX(Arch!$C$30:$E$30,J$7) -> 15990784 | ... AH35: =INDEX(Arch!$C$30:$E$30,AH$7) -> 4915200
A36: 全注意力層比例 | B36: % | C36: =INDEX(Arch!$C$16:$E$16,C$7) -> 0.5 | D36: =INDEX(Arch!$C$16:$E$16,D$7) -> 0.5 | E36: =INDEX(Arch!$C$16:$E$16,E$7) -> 0.5 | F36: =INDEX(Arch!$C$16:$E$16,F$7) -> 0.5 | G36: =INDEX(Arch!$C$16:$E$16,G$7) -> 0.5 | H36: =INDEX(Arch!$C$16:$E$16,H$7) -> 0.5 | I36: =INDEX(Arch!$C$16:$E$16,I$7) -> 0.5 | J36: =INDEX(Arch!$C$16:$E$16,J$7) -> 0.5 | ... AH36: =INDEX(Arch!$C$16:$E$16,AH$7) -> 1
A37: 全注意力跨度上限 | B37: tok | C37: =INDEX(Arch!$C$17:$E$17,C$7) -> 4224 | D37: =INDEX(Arch!$C$17:$E$17,D$7) -> 4224 | E37: =INDEX(Arch!$C$17:$E$17,E$7) -> 4224 | F37: =INDEX(Arch!$C$17:$E$17,F$7) -> 4224 | G37: =INDEX(Arch!$C$17:$E$17,G$7) -> 4224 | H37: =INDEX(Arch!$C$17:$E$17,H$7) -> 4224 | I37: =INDEX(Arch!$C$17:$E$17,I$7) -> 4224 | J37: =INDEX(Arch!$C$17:$E$17,J$7) -> 4224 | ... AH37: =INDEX(Arch!$C$17:$E$17,AH$7) -> 0
A38: 其他層壓縮比 | B38: x | C38: =INDEX(Arch!$C$18:$E$18,C$7) -> 128 | D38: =INDEX(Arch!$C$18:$E$18,D$7) -> 128 | E38: =INDEX(Arch!$C$18:$E$18,E$7) -> 128 | F38: =INDEX(Arch!$C$18:$E$18,F$7) -> 128 | G38: =INDEX(Arch!$C$18:$E$18,G$7) -> 128 | H38: =INDEX(Arch!$C$18:$E$18,H$7) -> 128 | I38: =INDEX(Arch!$C$18:$E$18,I$7) -> 128 | J38: =INDEX(Arch!$C$18:$E$18,J$7) -> 128 | ... AH38: =INDEX(Arch!$C$18:$E$18,AH$7) -> 1
A39: 其他層滑動窗 | B39: tok | C39: =INDEX(Arch!$C$19:$E$19,C$7) -> 128 | D39: =INDEX(Arch!$C$19:$E$19,D$7) -> 128 | E39: =INDEX(Arch!$C$19:$E$19,E$7) -> 128 | F39: =INDEX(Arch!$C$19:$E$19,F$7) -> 128 | G39: =INDEX(Arch!$C$19:$E$19,G$7) -> 128 | H39: =INDEX(Arch!$C$19:$E$19,H$7) -> 128 | I39: =INDEX(Arch!$C$19:$E$19,I$7) -> 128 | J39: =INDEX(Arch!$C$19:$E$19,J$7) -> 128 | ... AH39: =INDEX(Arch!$C$19:$E$19,AH$7) -> 0
A40: C. 服務、SLO 與校準參數
A41: SLO：每用戶 decode 速度下限 | B41: tok/s | C41: =INDEX(Serving!$C$21:$E$21,C$7) -> 65 | D41: =INDEX(Serving!$C$21:$E$21,D$7) -> 65 | E41: =INDEX(Serving!$C$21:$E$21,E$7) -> 65 | F41: =INDEX(Serving!$C$21:$E$21,F$7) -> 65 | G41: =INDEX(Serving!$C$21:$E$21,G$7) -> 65 | H41: =INDEX(Serving!$C$21:$E$21,H$7) -> 65 | I41: =INDEX(Serving!$C$21:$E$21,I$7) -> 65 | J41: =INDEX(Serving!$C$21:$E$21,J$7) -> 65 | ... N41: =INDEX(Serving!$C$21:$E$21,N$7) -> 65 | O41: 40 | P41: 40 | Q41: 100 | R41: 100 | S41: =INDEX(Serving!$C$21:$E$21,S$7) -> 65 | T41: =INDEX(Serving!$C$21:$E$21,T$7) -> 65 | U41: =INDEX(Serving!$C$21:$E$21,U$7) -> 65 | V41: =INDEX(Serving!$C$21:$E$21,V$7) -> 65 | W41: =INDEX(Serving!$C$21:$E$21,W$7) -> 65 | X41: =INDEX(Serving!$C$21:$E$21,X$7) -> 65 | Y41: =INDEX(Serving!$C$21:$E$21,Y$7) -> 65 | Z41: =INDEX(Serving!$C$21:$E$21,Z$7) -> 65 | ... AH41: =INDEX(Serving!$C$21:$E$21,AH$7) -> 55
A42: TTFT 上限 | B42: s | C42: =INDEX(Serving!$C$22:$E$22,C$7) -> 3 | D42: =INDEX(Serving!$C$22:$E$22,D$7) -> 3 | E42: =INDEX(Serving!$C$22:$E$22,E$7) -> 3 | F42: =INDEX(Serving!$C$22:$E$22,F$7) -> 3 | G42: =INDEX(Serving!$C$22:$E$22,G$7) -> 3 | H42: =INDEX(Serving!$C$22:$E$22,H$7) -> 3 | I42: =INDEX(Serving!$C$22:$E$22,I$7) -> 3 | J42: =INDEX(Serving!$C$22:$E$22,J$7) -> 3 | ... AH42: =INDEX(Serving!$C$22:$E$22,AH$7) -> 5
A43: 參考 ISL | B43: tok | C43: =INDEX(Serving!$C$23:$E$23,C$7) -> 16384 | D43: =INDEX(Serving!$C$23:$E$23,D$7) -> 16384 | E43: =INDEX(Serving!$C$23:$E$23,E$7) -> 16384 | F43: =INDEX(Serving!$C$23:$E$23,F$7) -> 16384 | G43: =INDEX(Serving!$C$23:$E$23,G$7) -> 16384 | H43: =INDEX(Serving!$C$23:$E$23,H$7) -> 16384 | I43: =INDEX(Serving!$C$23:$E$23,I$7) -> 16384 | J43: =INDEX(Serving!$C$23:$E$23,J$7) -> 16384 | ... V43: =INDEX(Serving!$C$23:$E$23,V$7) -> 16384 | W43: 4096 | X43: 4096 | Y43: 65536 | Z43: 65536 | AA43: =INDEX(Serving!$C$23:$E$23,AA$7) -> 16384 | AB43: =INDEX(Serving!$C$23:$E$23,AB$7) -> 16384 | AC43: =INDEX(Serving!$C$23:$E$23,AC$7) -> 32768 | AD43: =INDEX(Serving!$C$23:$E$23,AD$7) -> 32768 | AE43: =INDEX(Serving!$C$23:$E$23,AE$7) -> 32768 | AF43: =INDEX(Serving!$C$23:$E$23,AF$7) -> 32768 | AG43: =INDEX(Serving!$C$23:$E$23,AG$7) -> 32768 | AH43: =INDEX(Serving!$C$23:$E$23,AH$7) -> 32768
A44: 參考 OSL（含思考） | B44: tok | C44: =INDEX(Serving!$C$24:$E$24,C$7) -> 2048 | D44: =INDEX(Serving!$C$24:$E$24,D$7) -> 2048 | E44: =INDEX(Serving!$C$24:$E$24,E$7) -> 2048 | F44: =INDEX(Serving!$C$24:$E$24,F$7) -> 2048 | G44: =INDEX(Serving!$C$24:$E$24,G$7) -> 2048 | H44: =INDEX(Serving!$C$24:$E$24,H$7) -> 2048 | I44: =INDEX(Serving!$C$24:$E$24,I$7) -> 2048 | J44: =INDEX(Serving!$C$24:$E$24,J$7) -> 2048 | ... AH44: =INDEX(Serving!$C$24:$E$24,AH$7) -> 4096
A45: decode 平均上下文 | B45: tok | C45: =C43+C44/2 -> 17408 | D45: =D43+D44/2 -> 17408 | E45: =E43+E44/2 -> 17408 | F45: =F43+F44/2 -> 17408 | G45: =G43+G44/2 -> 17408 | H45: =H43+H44/2 -> 17408 | I45: =I43+I44/2 -> 17408 | J45: =J43+J44/2 -> 17408 | ... AH45: =AH43+AH44/2 -> 34816
A46: prefill 平均位置 | B46: tok | C46: =C43/2 -> 8192 | D46: =D43/2 -> 8192 | E46: =E43/2 -> 8192 | F46: =F43/2 -> 8192 | G46: =G43/2 -> 8192 | H46: =H43/2 -> 8192 | I46: =I43/2 -> 8192 | J46: =J43/2 -> 8192 | ... AH46: =AH43/2 -> 16384
A47: MTP 草稿數 | B47: tok | C47: =Serving!$C$6 -> 3 | D47: =Serving!$C$6 -> 3 | E47: =Serving!$C$6 -> 3 | F47: =Serving!$C$6 -> 3 | G47: =Serving!$C$6 -> 3 | H47: =Serving!$C$6 -> 3 | I47: =Serving!$C$6 -> 3 | J47: =Serving!$C$6 -> 3 | ... AH47: =Serving!$C$6 -> 3
A48: 草稿接受率 | B48: % | C48: =Serving!$C$7 -> 0.7 | D48: =Serving!$C$7 -> 0.7 | E48: =Serving!$C$7 -> 0.7 | F48: =Serving!$C$7 -> 0.7 | G48: =Serving!$C$7 -> 0.7 | H48: =Serving!$C$7 -> 0.7 | I48: =Serving!$C$7 -> 0.7 | J48: =Serving!$C$7 -> 0.7 | ... R48: =Serving!$C$7 -> 0.7 | S48: 0.6 | T48: 0.6 | U48: 0.8 | V48: 0.8 | W48: =Serving!$C$7 -> 0.7 | X48: =Serving!$C$7 -> 0.7 | Y48: =Serving!$C$7 -> 0.7 | Z48: =Serving!$C$7 -> 0.7 | AA48: =Serving!$C$7 -> 0.7 | AB48: =Serving!$C$7 -> 0.7 | AC48: =Serving!$C$7 -> 0.7 | AD48: =Serving!$C$7 -> 0.7 | ... AH48: =Serving!$C$7 -> 0.7
A49: 每步期望接受 token | B49: tok | C49: =(1-C48^(C47+1))/(1-C48) -> 2.533 | D49: =(1-D48^(D47+1))/(1-D48) -> 2.533 | E49: =(1-E48^(E47+1))/(1-E48) -> 2.533 | F49: =(1-F48^(F47+1))/(1-F48) -> 2.533 | G49: =(1-G48^(G47+1))/(1-G48) -> 2.533 | H49: =(1-H48^(H47+1))/(1-H48) -> 2.533 | I49: =(1-I48^(I47+1))/(1-I48) -> 2.533 | J49: =(1-J48^(J47+1))/(1-J48) -> 2.533 | ... AH49: =(1-AH48^(AH47+1))/(1-AH48) -> 2.533
A50: 實測→生產效率折減 | B50: x | C50: =Serving!$C$18 -> 1 | D50: =Serving!$C$18 -> 1 | E50: =Serving!$C$18 -> 1 | F50: =Serving!$C$18 -> 1 | G50: =Serving!$C$18 -> 1 | H50: =Serving!$C$18 -> 1 | I50: =Serving!$C$18 -> 1 | J50: =Serving!$C$18 -> 1 | ... Z50: =Serving!$C$18 -> 1 | AA50: 0.7 | AB50: 0.7 | AC50: =Serving!$C$18 -> 1 | AD50: =Serving!$C$18 -> 1 | AE50: =Serving!$C$18 -> 1 | AF50: =Serving!$C$18 -> 1 | AG50: =Serving!$C$18 -> 1 | AH50: =Serving!$C$18 -> 1
A51: η_p（prefill 占峰值；含折減） | B51: % | C51: =INDEX(Calib!$C$72:$G$72,C$6)*C50 -> 0.3 | D51: =INDEX(Calib!$C$72:$G$72,D$6)*D50 -> 0.3 | E51: =INDEX(Calib!$C$72:$G$72,E$6)*E50 -> 0.3 | F51: =INDEX(Calib!$C$72:$G$72,F$6)*F50 -> 0.3 | G51: =INDEX(Calib!$C$72:$G$72,G$6)*G50 -> 0.3 | H51: =INDEX(Calib!$C$72:$G$72,H$6)*H50 -> 0.3 | I51: =INDEX(Calib!$C$72:$G$72,I$6)*I50 -> 0.3 | J51: =INDEX(Calib!$C$72:$G$72,J$6)*J50 -> 0.3 | ... AH51: =INDEX(Calib!$C$72:$G$72,AH$6)*AH50 -> 0.3
A52: η_d 倍數（Tech_Registry H_ETAD；Sens_Perf 情境覆寫） | B52: x | C52: =Tech_Registry!$E$20 -> 1 | D52: =Tech_Registry!$E$20 -> 1 | E52: 0.5 | F52: =Tech_Registry!$E$20 -> 1 | G52: 1.5 | H52: =Tech_Registry!$E$20 -> 1 | I52: =Tech_Registry!$E$20 -> 1 | J52: =Tech_Registry!$E$20 -> 1 | K52: =Tech_Registry!$E$20 -> 1 | L52: =Tech_Registry!$E$20 -> 1 | M52: =Tech_Registry!$E$20 -> 1 | N52: =Tech_Registry!$E$20 -> 1 | O52: =Tech_Registry!$E$20 -> 1 | ... AH52: =Tech_Registry!$E$20 -> 1
A53: η_d（decode 每序列算力效率；含折減） | B53: % | C53: =INDEX(Calib!$C$70:$G$70,C$6)*C52*C50 -> 0.036042379 | D53: =INDEX(Calib!$C$70:$G$70,D$6)*D52*D50 -> 0.036042379 | E53: =INDEX(Calib!$C$70:$G$70,E$6)*E52*E50 -> 0.01802119 | F53: =INDEX(Calib!$C$70:$G$70,F$6)*F52*F50 -> 0.036042379 | G53: =INDEX(Calib!$C$70:$G$70,G$6)*G52*G50 -> 0.054063569 | H53: =INDEX(Calib!$C$70:$G$70,H$6)*H52*H50 -> 0.036042379 | I53: =INDEX(Calib!$C$70:$G$70,I$6)*I52*I50 -> 0.036042379 | J53: =INDEX(Calib!$C$70:$G$70,J$6)*J52*J50 -> 0.036042379 | ... AH53: =INDEX(Calib!$C$70:$G$70,AH$6)*AH52*AH50 -> 0.036042379
A54: 每層延遲倍數（Tech_Registry H_TL；Sens_Perf 情境覆寫） | B54: x | C54: =Tech_Registry!$E$21 -> 1 | D54: =Tech_Registry!$E$21 -> 1 | E54: =Tech_Registry!$E$21 -> 1 | F54: =Tech_Registry!$E$21 -> 1 | G54: =Tech_Registry!$E$21 -> 1 | H54: =Tech_Registry!$E$21 -> 1 | I54: 0.7 | J54: =Tech_Registry!$E$21 -> 1 | K54: 1.5 | L54: =Tech_Registry!$E$21 -> 1 | M54: =Tech_Registry!$E$21 -> 1 | N54: =Tech_Registry!$E$21 -> 1 | O54: =Tech_Registry!$E$21 -> 1 | P54: =Tech_Registry!$E$21 -> 1 | Q54: =Tech_Registry!$E$21 -> 1 | R54: =Tech_Registry!$E$21 -> 1 | S54: =Tech_Registry!$E$21 -> 1 | ... AH54: =Tech_Registry!$E$21 -> 1
A55: 每層每次前向固定延遲（含折減） | B55: µs | C55: =INDEX(Calib!$C$71:$G$71,C$6)*C54/C50 -> 160.27856 | D55: =INDEX(Calib!$C$71:$G$71,D$6)*D54/D50 -> 160.27856 | E55: =INDEX(Calib!$C$71:$G$71,E$6)*E54/E50 -> 160.27856 | F55: =INDEX(Calib!$C$71:$G$71,F$6)*F54/F50 -> 160.27856 | G55: =INDEX(Calib!$C$71:$G$71,G$6)*G54/G50 -> 160.27856 | H55: =INDEX(Calib!$C$71:$G$71,H$6)*H54/H50 -> 160.27856 | I55: =INDEX(Calib!$C$71:$G$71,I$6)*I54/I50 -> 112.19499 | J55: =INDEX(Calib!$C$71:$G$71,J$6)*J54/J50 -> 160.27856 | ... AH55: =INDEX(Calib!$C$71:$G$71,AH$6)*AH54/AH50 -> 160.27856
A56: HBM 保留比例 | B56: % | C56: =Serving!$C$9 -> 0.1 | D56: =Serving!$C$9 -> 0.1 | E56: =Serving!$C$9 -> 0.1 | F56: =Serving!$C$9 -> 0.1 | G56: =Serving!$C$9 -> 0.1 | H56: =Serving!$C$9 -> 0.1 | I56: =Serving!$C$9 -> 0.1 | J56: =Serving!$C$9 -> 0.1 | ... AH56: =Serving!$C$9 -> 0.1
A57: 非專家權重占 HBM 上限 | B57: % | C57: =Serving!$C$10 -> 0.2 | D57: =Serving!$C$10 -> 0.2 | E57: =Serving!$C$10 -> 0.2 | F57: =Serving!$C$10 -> 0.2 | G57: =Serving!$C$10 -> 0.2 | H57: =Serving!$C$10 -> 0.2 | I57: =Serving!$C$10 -> 0.2 | J57: =Serving!$C$10 -> 0.2 | ... AH57: =Serving!$C$10 -> 0.2
A58: 專家權重占 HBM 上限 | B58: % | C58: =Serving!$C$11 -> 0.4 | D58: =Serving!$C$11 -> 0.4 | E58: =Serving!$C$11 -> 0.4 | F58: =Serving!$C$11 -> 0.4 | G58: =Serving!$C$11 -> 0.4 | H58: =Serving!$C$11 -> 0.4 | I58: =Serving!$C$11 -> 0.4 | J58: =Serving!$C$11 -> 0.4 | ... AH58: =Serving!$C$11 -> 0.4
A59: EP 啟用值 bytes/元素 | B59: B | C59: =Serving!$C$12 -> 3 | D59: =Serving!$C$12 -> 3 | E59: =Serving!$C$12 -> 3 | F59: =Serving!$C$12 -> 3 | G59: =Serving!$C$12 -> 3 | H59: =Serving!$C$12 -> 3 | I59: =Serving!$C$12 -> 3 | J59: =Serving!$C$12 -> 3 | ... AH59: =Serving!$C$12 -> 3
A60: KV 讀取效率 | B60: % | C60: =Serving!$C$13 -> 0.7 | D60: =Serving!$C$13 -> 0.7 | E60: =Serving!$C$13 -> 0.7 | F60: =Serving!$C$13 -> 0.7 | G60: =Serving!$C$13 -> 0.7 | H60: =Serving!$C$13 -> 0.7 | I60: =Serving!$C$13 -> 0.7 | J60: =Serving!$C$13 -> 0.7 | ... AH60: =Serving!$C$13 -> 0.7
A61: EP 通訊效率 | B61: % | C61: =Serving!$C$14 -> 0.7 | D61: =Serving!$C$14 -> 0.7 | E61: =Serving!$C$14 -> 0.7 | F61: =Serving!$C$14 -> 0.7 | G61: =Serving!$C$14 -> 0.7 | H61: =Serving!$C$14 -> 0.7 | I61: =Serving!$C$14 -> 0.7 | J61: =Serving!$C$14 -> 0.7 | ... AH61: =Serving!$C$14 -> 0.7
A62: 快取載入頻寬 | B62: TB/s | C62: =Serving!$C$15 -> 0.1 | D62: =Serving!$C$15 -> 0.1 | E62: =Serving!$C$15 -> 0.1 | F62: =Serving!$C$15 -> 0.1 | G62: =Serving!$C$15 -> 0.1 | H62: =Serving!$C$15 -> 0.1 | I62: =Serving!$C$15 -> 0.1 | J62: =Serving!$C$15 -> 0.1 | ... AH62: =Serving!$C$15 -> 0.1
A63: D. 每 token 計算量
A64: decode 被注意 token 數 | B64: tok | C64: =C36*IF(C37=0,C45,MIN(C45,C37))+(1-C36)*(C45/C38+C39) -> 2244 | D64: =D36*IF(D37=0,D45,MIN(D45,D37))+(1-D36)*(D45/D38+D39) -> 2244 | E64: =E36*IF(E37=0,E45,MIN(E45,E37))+(1-E36)*(E45/E38+E39) -> 2244 | F64: =F36*IF(F37=0,F45,MIN(F45,F37))+(1-F36)*(F45/F38+F39) -> 2244 | G64: =G36*IF(G37=0,G45,MIN(G45,G37))+(1-G36)*(G45/G38+G39) -> 2244 | H64: =H36*IF(H37=0,H45,MIN(H45,H37))+(1-H36)*(H45/H38+H39) -> 2244 | I64: =I36*IF(I37=0,I45,MIN(I45,I37))+(1-I36)*(I45/I38+I39) -> 2244 | J64: =J36*IF(J37=0,J45,MIN(J45,J37))+(1-J36)*(J45/J38+J39) -> 2244 | ... AH64: =AH36*IF(AH37=0,AH45,MIN(AH45,AH37))+(1-AH36)*(AH45/AH38+AH39) -> 34816
A65: decode FLOPs/token | B65: GFLOP | C65: =(2*C28*1000000000+C35*C64)*C10/1000000000 -> 133.88332 | D65: =(2*D28*1000000000+D35*D64)*D10/1000000000 -> 133.88332 | E65: =(2*E28*1000000000+E35*E64)*E10/1000000000 -> 133.88332 | F65: =(2*F28*1000000000+F35*F64)*F10/1000000000 -> 133.88332 | G65: =(2*G28*1000000000+G35*G64)*G10/1000000000 -> 133.88332 | H65: =(2*H28*1000000000+H35*H64)*H10/1000000000 -> 133.88332 | I65: =(2*I28*1000000000+I35*I64)*I10/1000000000 -> 133.88332 | J65: =(2*J28*1000000000+J35*J64)*J10/1000000000 -> 133.88332 | ... AH65: =(2*AH28*1000000000+AH35*AH64)*AH10/1000000000 -> 531.1276
A66: prefill 被注意 token 數 | B66: tok | C66: =C36*IF(C37=0,C46,MIN(C46,C37))+(1-C36)*(C46/C38+C39) -> 2208 | D66: =D36*IF(D37=0,D46,MIN(D46,D37))+(1-D36)*(D46/D38+D39) -> 2208 | E66: =E36*IF(E37=0,E46,MIN(E46,E37))+(1-E36)*(E46/E38+E39) -> 2208 | F66: =F36*IF(F37=0,F46,MIN(F46,F37))+(1-F36)*(F46/F38+F39) -> 2208 | G66: =G36*IF(G37=0,G46,MIN(G46,G37))+(1-G36)*(G46/G38+G39) -> 2208 | H66: =H36*IF(H37=0,H46,MIN(H46,H37))+(1-H36)*(H46/H38+H39) -> 2208 | I66: =I36*IF(I37=0,I46,MIN(I46,I37))+(1-I36)*(I46/I38+I39) -> 2208 | J66: =J36*IF(J37=0,J46,MIN(J46,J37))+(1-J36)*(J46/J38+J39) -> 2208 | ... AH66: =AH36*IF(AH37=0,AH46,MIN(AH46,AH37))+(1-AH36)*(AH46/AH38+AH39) -> 16384
A67: prefill FLOPs/token | B67: GFLOP | C67: =(2*C28*1000000000+C35*C66)*C10/1000000000 -> 133.30765 | D67: =(2*D28*1000000000+D35*D66)*D10/1000000000 -> 133.30765 | E67: =(2*E28*1000000000+E35*E66)*E10/1000000000 -> 133.30765 | F67: =(2*F28*1000000000+F35*F66)*F10/1000000000 -> 133.30765 | G67: =(2*G28*1000000000+G35*G66)*G10/1000000000 -> 133.30765 | H67: =(2*H28*1000000000+H35*H66)*H10/1000000000 -> 133.30765 | I67: =(2*I28*1000000000+I35*I66)*I10/1000000000 -> 133.30765 | J67: =(2*J28*1000000000+J35*J66)*J10/1000000000 -> 133.30765 | ... AH67: =(2*AH28*1000000000+AH35*AH66)*AH10/1000000000 -> 440.53064
A68: E. 記憶體配置（attention DP＋wide EP；每 GPU）
A69: 可用 HBM | B69: GB | C69: =C15*(1-C56) -> 259.2 | D69: =D15*(1-D56) -> 259.2 | E69: =E15*(1-E56) -> 259.2 | F69: =F15*(1-F56) -> 259.2 | G69: =G15*(1-G56) -> 259.2 | H69: =H15*(1-H56) -> 259.2 | I69: =I15*(1-I56) -> 259.2 | J69: =J15*(1-J56) -> 259.2 | ... AH69: =AH15*(1-AH56) -> 259.2
A70: 注意力 TP 度（自動） | C70: =MAX(1,CEILING(C32*C20/(C57*C69),1)) -> 1 | D70: =MAX(1,CEILING(D32*D20/(D57*D69),1)) -> 1 | E70: =MAX(1,CEILING(E32*E20/(E57*E69),1)) -> 1 | F70: =MAX(1,CEILING(F32*F20/(F57*F69),1)) -> 1 | G70: =MAX(1,CEILING(G32*G20/(G57*G69),1)) -> 1 | H70: =MAX(1,CEILING(H32*H20/(H57*H69),1)) -> 1 | I70: =MAX(1,CEILING(I32*I20/(I57*I69),1)) -> 1 | J70: =MAX(1,CEILING(J32*J20/(J57*J69),1)) -> 1 | ... AH70: =MAX(1,CEILING(AH32*AH20/(AH57*AH69),1)) -> 1
A71: decode EP 寬度（自動） | B71: GPU | C71: =MAX(C18,CEILING(C33*C19/(C58*C69),1)) -> 32 | D71: =MAX(D18,CEILING(D33*D19/(D58*D69),1)) -> 32 | E71: =MAX(E18,CEILING(E33*E19/(E58*E69),1)) -> 32 | F71: =MAX(F18,CEILING(F33*F19/(F58*F69),1)) -> 32 | G71: =MAX(G18,CEILING(G33*G19/(G58*G69),1)) -> 32 | H71: =MAX(H18,CEILING(H33*H19/(H58*H69),1)) -> 32 | I71: =MAX(I18,CEILING(I33*I19/(I58*I69),1)) -> 32 | J71: =MAX(J18,CEILING(J33*J19/(J58*J69),1)) -> 32 | ... AH71: =MAX(AH18,CEILING(AH33*AH19/(AH58*AH69),1)) -> 32
A72: 每 GPU 權重 | B72: GB | C72: =C32*C20/C70+C33*C19/C71 -> 48.046332 | D72: =D32*D20/D70+D33*D19/D71 -> 48.046332 | E72: =E32*E20/E70+E33*E19/E71 -> 48.046332 | F72: =F32*F20/F70+F33*F19/F71 -> 48.046332 | G72: =G32*G20/G70+G33*G19/G71 -> 48.046332 | H72: =H32*H20/H70+H33*H19/H71 -> 48.046332 | I72: =I32*I20/I70+I33*I19/I71 -> 48.046332 | J72: =J32*J20/J70+J33*J19/J71 -> 48.046332 | ... AH72: =AH32*AH20/AH70+AH33*AH19/AH71 -> 118.52248
A73: 權重占可用 HBM | B73: % | C73: =C72/C69 -> 0.18536394 | D73: =D72/D69 -> 0.18536394 | E73: =E72/E69 -> 0.18536394 | F73: =F72/F69 -> 0.18536394 | G73: =G72/G69 -> 0.18536394 | H73: =H72/H69 -> 0.18536394 | I73: =I72/I69 -> 0.18536394 | J73: =J72/J69 -> 0.18536394 | ... AH73: =AH72/AH69 -> 0.45726264
A74: F. Prefill（算力受限）
A75: prefill tok/s（每 prefill GPU） | B75: tok/s | C75: =C51*C14*1000000000000000/(C67*1000000000) -> 78765.172 | D75: =D51*D14*1000000000000000/(D67*1000000000) -> 33756.502 | E75: =E51*E14*1000000000000000/(E67*1000000000) -> 78765.172 | F75: =F51*F14*1000000000000000/(F67*1000000000) -> 33756.502 | G75: =G51*G14*1000000000000000/(G67*1000000000) -> 78765.172 | H75: =H51*H14*1000000000000000/(H67*1000000000) -> 33756.502 | I75: =I51*I14*1000000000000000/(I67*1000000000) -> 78765.172 | J75: =J51*J14*1000000000000000/(J67*1000000000) -> 33756.502 | ... AH75: =AH51*AH14*1000000000000000/(AH67*1000000000) -> 10214.954
A76: TTFT（計算部分） | B76: s | C76: =C43*C67*1000000000/(C51*C14*1000000000000000*C21) -> 0.05200268 | D76: =D43*D67*1000000000/(D51*D14*1000000000000000*D21) -> 0.12133959 | E76: =E43*E67*1000000000/(E51*E14*1000000000000000*E21) -> 0.05200268 | F76: =F43*F67*1000000000/(F51*F14*1000000000000000*F21) -> 0.12133959 | G76: =G43*G67*1000000000/(G51*G14*1000000000000000*G21) -> 0.05200268 | H76: =H43*H67*1000000000/(H51*H14*1000000000000000*H21) -> 0.12133959 | I76: =I43*I67*1000000000/(I51*I14*1000000000000000*I21) -> 0.05200268 | J76: =J43*J67*1000000000/(J51*J14*1000000000000000*J21) -> 0.12133959 | ... AH76: =AH43*AH67*1000000000/(AH51*AH14*1000000000000000*AH21) -> 0.80196155
A77: TTFT 符合上限 | C77: =IF(C76<=C42,"是","否") -> 是 | D77: =IF(D76<=D42,"是","否") -> 是 | E77: =IF(E76<=E42,"是","否") -> 是 | F77: =IF(F76<=F42,"是","否") -> 是 | G77: =IF(G76<=G42,"是","否") -> 是 | H77: =IF(H76<=H42,"是","否") -> 是 | I77: =IF(I76<=I42,"是","否") -> 是 | J77: =IF(J76<=J42,"是","否") -> 是 | ... AH77: =IF(AH76<=AH42,"是","否") -> 是
A78: G. Decode：每步時間＝固定延遲＋B × 每序列時間；B* ＝ min(SLO 上限, HBM 容量上限)
A79: 每步固定延遲（權重讀取＋逐層延遲） | B79: ms | C79: =C72/C16+(C29+C47)*C55/1000 -> 12.441752 | D79: =D72/D16+(D29+D47)*D55/1000 -> 16.263619 | E79: =E72/E16+(E29+E47)*E55/1000 -> 12.441752 | F79: =F72/F16+(F29+F47)*F55/1000 -> 16.263619 | G79: =G72/G16+(G29+G47)*G55/1000 -> 12.441752 | H79: =H72/H16+(H29+H47)*H55/1000 -> 16.263619 | I79: =I72/I16+(I29+I47)*I55/1000 -> 9.3644037 | J79: =J72/J16+(J29+J47)*J55/1000 -> 16.263619 | ... AH79: =AH72/AH16+(AH29+AH47)*AH55/1000 -> 31.324001
A80: 每序列每步 — 算力項 | B80: ms | C80: =(C47+1)*C65/(C14*C53)/1000 -> 0.42452665 | D80: =(D47+1)*D65/(D14*D53)/1000 -> 0.99056219 | E80: =(E47+1)*E65/(E14*E53)/1000 -> 0.84905331 | F80: =(F47+1)*F65/(F14*F53)/1000 -> 0.99056219 | G80: =(G47+1)*G65/(G14*G53)/1000 -> 0.28301777 | H80: =(H47+1)*H65/(H14*H53)/1000 -> 0.99056219 | I80: =(I47+1)*I65/(I14*I53)/1000 -> 0.42452665 | J80: =(J47+1)*J65/(J14*J53)/1000 -> 0.99056219 | ... AH80: =(AH47+1)*AH65/(AH14*AH53)/1000 -> 3.9296525
A81: 每序列每步 — KV 讀取項 | B81: ms | C81: =C34*C45/(C16*C60)/1000000000 -> 0.0044819948 | D81: =D34*D45/(D16*D60)/1000000000 -> 0.012325486 | E81: =E34*E45/(E16*E60)/1000000000 -> 0.0044819948 | F81: =F34*F45/(F16*F60)/1000000000 -> 0.012325486 | G81: =G34*G45/(G16*G60)/1000000000 -> 0.0044819948 | H81: =H34*H45/(H16*H60)/1000000000 -> 0.012325486 | I81: =I34*I45/(I16*I60)/1000000000 -> 0.0044819948 | J81: =J34*J45/(J16*J60)/1000000000 -> 0.012325486 | ... AH81: =AH34*AH45/(AH16*AH60)/1000000000 -> 1.2732709
A82: 每序列每步 — EP 通訊項 | B82: ms | C82: =(C47+1)*C29*C31*C30*C59*(C71-1)/C71/(C17*C61)/1000000000 -> 0.0242048 | D82: =(D47+1)*D29*D31*D30*D59*(D71-1)/D71/(D17*D61)/1000000000 -> 0.0484096 | E82: =(E47+1)*E29*E31*E30*E59*(E71-1)/E71/(E17*E61)/1000000000 -> 0.0242048 | F82: =(F47+1)*F29*F31*F30*F59*(F71-1)/F71/(F17*F61)/1000000000 -> 0.0484096 | G82: =(G47+1)*G29*G31*G30*G59*(G71-1)/G71/(G17*G61)/1000000000 -> 0.0242048 | H82: =(H47+1)*H29*H31*H30*H59*(H71-1)/H71/(H17*H61)/1000000000 -> 0.0484096 | I82: =(I47+1)*I29*I31*I30*I59*(I71-1)/I71/(I17*I61)/1000000000 -> 0.0242048 | J82: =(J47+1)*J29*J31*J30*J59*(J71-1)/J71/(J17*J61)/1000000000 -> 0.0484096 | ... AH82: =(AH47+1)*AH29*AH31*AH30*AH59*(AH71-1)/AH71/(AH17*AH61)/1000000000 -> 0.36278857
A83: 每序列每步（取最大，假設三者可重疊） | B83: ms | C83: =MAX(C80,C81,C82) -> 0.42452665 | D83: =MAX(D80,D81,D82) -> 0.99056219 | E83: =MAX(E80,E81,E82) -> 0.84905331 | F83: =MAX(F80,F81,F82) -> 0.99056219 | G83: =MAX(G80,G81,G82) -> 0.28301777 | H83: =MAX(H80,H81,H82) -> 0.99056219 | I83: =MAX(I80,I81,I82) -> 0.42452665 | J83: =MAX(J80,J81,J82) -> 0.99056219 | ... AH83: =MAX(AH80,AH81,AH82) -> 3.9296525
A84: 每序列綁定項 | C84: =IF(C83=C80,"算力",IF(C83=C81,"KV 頻寬","EP 通訊")) -> 算力 | D84: =IF(D83=D80,"算力",IF(D83=D81,"KV 頻寬","EP 通訊")) -> 算力 | E84: =IF(E83=E80,"算力",IF(E83=E81,"KV 頻寬","EP 通訊")) -> 算力 | F84: =IF(F83=F80,"算力",IF(F83=F81,"KV 頻寬","EP 通訊")) -> 算力 | G84: =IF(G83=G80,"算力",IF(G83=G81,"KV 頻寬","EP 通訊")) -> 算力 | H84: =IF(H83=H80,"算力",IF(H83=H81,"KV 頻寬","EP 通訊")) -> 算力 | I84: =IF(I83=I80,"算力",IF(I83=I81,"KV 頻寬","EP 通訊")) -> 算力 | J84: =IF(J83=J80,"算力",IF(J83=J81,"KV 頻寬","EP 通訊")) -> 算力 | ... AH84: =IF(AH83=AH80,"算力",IF(AH83=AH81,"KV 頻寬","EP 通訊")) -> 算力
A85: SLO 允許的批次上限 | B85: 序列/GPU | C85: =(1000*C49/C41-C79)/C83 -> 62.487192 | D85: =(1000*D49/D41-D79)/D83 -> 22.921944 | E85: =(1000*E49/E41-E79)/E83 -> 31.243596 | F85: =(1000*F49/F41-F79)/F83 -> 22.921944 | G85: =(1000*G49/G41-G79)/G83 -> 93.730788 | H85: =(1000*H49/H41-H79)/H83 -> 22.921944 | I85: =(1000*I49/I41-I79)/I83 -> 69.736085 | J85: =(1000*J49/J41-J79)/J83 -> 22.921944 | ... AH85: =(1000*AH49/AH41-AH79)/AH83 -> 3.7485615
A86: HBM 容量允許的批次上限 | B86: 序列/GPU | C86: =(C69-C72)*1000000000/(C34*C45) -> 3059.1908 | D86: =(D69-D72)*1000000000/(D34*D45) -> 3059.1908 | E86: =(E69-E72)*1000000000/(E34*E45) -> 3059.1908 | F86: =(F69-F72)*1000000000/(F34*F45) -> 3059.1908 | G86: =(G69-G72)*1000000000/(G34*G45) -> 3059.1908 | H86: =(H69-H72)*1000000000/(H34*H45) -> 3059.1908 | I86: =(I69-I72)*1000000000/(I34*I45) -> 3059.1908 | J86: =(J69-J72)*1000000000/(J34*J45) -> 3059.1908 | ... AH86: =(AH69-AH72)*1000000000/(AH34*AH45) -> 19.729491
A87: 採用批次 B* | B87: 序列/GPU | C87: =MAX(0,MIN(C85,C86)) -> 62.487192 | D87: =MAX(0,MIN(D85,D86)) -> 22.921944 | E87: =MAX(0,MIN(E85,E86)) -> 31.243596 | F87: =MAX(0,MIN(F85,F86)) -> 22.921944 | G87: =MAX(0,MIN(G85,G86)) -> 93.730788 | H87: =MAX(0,MIN(H85,H86)) -> 22.921944 | I87: =MAX(0,MIN(I85,I86)) -> 69.736085 | J87: =MAX(0,MIN(J85,J86)) -> 22.921944 | ... AH87: =MAX(0,MIN(AH85,AH86)) -> 3.7485615
A88: decode tok/s（每 decode GPU） | B88: tok/s | C88: =IF(C87>0,C87*C49/((C79+C87*C83)/1000),0) -> 4061.6675 | D88: =IF(D87>0,D87*D49/((D79+D87*D83)/1000),0) -> 1489.9264 | E88: =IF(E87>0,E87*E49/((E79+E87*E83)/1000),0) -> 2030.8337 | F88: =IF(F87>0,F87*F49/((F79+F87*F83)/1000),0) -> 1489.9264 | G88: =IF(G87>0,G87*G49/((G79+G87*G83)/1000),0) -> 6092.5012 | H88: =IF(H87>0,H87*H49/((H79+H87*H83)/1000),0) -> 1489.9264 | I88: =IF(I87>0,I87*I49/((I79+I87*I83)/1000),0) -> 4532.8456 | J88: =IF(J87>0,J87*J49/((J79+J87*J83)/1000),0) -> 1489.9264 | ... AH88: =IF(AH87>0,AH87*AH49/((AH79+AH87*AH83)/1000),0) -> 206.17088
A89: 實際每用戶速度 | B89: tok/s | C89: =IF(C87>0,C49/((C79+C87*C83)/1000),0) -> 65 | D89: =IF(D87>0,D49/((D79+D87*D83)/1000),0) -> 65 | E89: =IF(E87>0,E49/((E79+E87*E83)/1000),0) -> 65 | F89: =IF(F87>0,F49/((F79+F87*F83)/1000),0) -> 65 | G89: =IF(G87>0,G49/((G79+G87*G83)/1000),0) -> 65 | H89: =IF(H87>0,H49/((H79+H87*H83)/1000),0) -> 65 | I89: =IF(I87>0,I49/((I79+I87*I83)/1000),0) -> 65 | J89: =IF(J87>0,J49/((J79+J87*J83)/1000),0) -> 65 | ... AH89: =IF(AH87>0,AH49/((AH79+AH87*AH83)/1000),0) -> 55
A90: 綁定約束 | C90: =IF(C87<=0,"SLO 不可達",IF(C85<=C86,"SLO（"&C84&"）","HBM 容量")) -> SLO（算力） | D90: =IF(D87<=0,"SLO 不可達",IF(D85<=D86,"SLO（"&D84&"）","HBM 容量")) -> SLO（算力） | E90: =IF(E87<=0,"SLO 不可達",IF(E85<=E86,"SLO（"&E84&"）","HBM 容量")) -> SLO（算力） | F90: =IF(F87<=0,"SLO 不可達",IF(F85<=F86,"SLO（"&F84&"）","HBM 容量")) -> SLO（算力） | G90: =IF(G87<=0,"SLO 不可達",IF(G85<=G86,"SLO（"&G84&"）","HBM 容量")) -> SLO（算力） | H90: =IF(H87<=0,"SLO 不可達",IF(H85<=H86,"SLO（"&H84&"）","HBM 容量")) -> SLO（算力） | I90: =IF(I87<=0,"SLO 不可達",IF(I85<=I86,"SLO（"&I84&"）","HBM 容量")) -> SLO（算力） | J90: =IF(J87<=0,"SLO 不可達",IF(J85<=J86,"SLO（"&J84&"）","HBM 容量")) -> SLO（算力） | ... AH90: =IF(AH87<=0,"SLO 不可達",IF(AH85<=AH86,"SLO（"&AH84&"）","HBM 容量")) -> SLO（算力）
A91: KV 占可用 HBM | B91: % | C91: =C87*C34*C45/1000000000/C69 -> 0.016639799 | D91: =D87*D34*D45/1000000000/D69 -> 0.0061039156 | E91: =E87*E34*E45/1000000000/E69 -> 0.0083198996 | F91: =F87*F34*F45/1000000000/F69 -> 0.0061039156 | G91: =G87*G34*G45/1000000000/G69 -> 0.024959699 | H91: =H87*H34*H45/1000000000/H69 -> 0.0061039156 | I91: =I87*I34*I45/1000000000/I69 -> 0.018570117 | J91: =J87*J34*J45/1000000000/J69 -> 0.0061039156 | ... AH91: =AH87*AH34*AH45/1000000000/AH69 -> 0.10311895
A92: H. 每架與每 GW（參考任務；P:D 依工作量配比；100% 利用率）
A93: 每請求 GPU 秒 | B93: GPU-s | C93: =IF(C88>0,C43/C75+C44/C88,0) -> 0.71223712 | D93: =IF(D88>0,D43/D75+D44/D88,0) -> 1.8599229 | E93: =IF(E88>0,E43/E75+E44/E88,0) -> 1.2164635 | F93: =IF(F88>0,F43/F75+F44/F88,0) -> 1.8599229 | G93: =IF(G88>0,G43/G75+G44/G88,0) -> 0.54416166 | H93: =IF(H88>0,H43/H75+H44/H88,0) -> 1.8599229 | I93: =IF(I88>0,I43/I75+I44/I88,0) -> 0.65982404 | J93: =IF(J88>0,J43/J75+J44/J88,0) -> 1.8599229 | ... AH93: =IF(AH88>0,AH43/AH75+AH44/AH88,0) -> 23.074861
A94: prefill GPU 占比 | B94: % | C94: =IF(C93>0,(C43/C75)/C93,0) -> 0.29205262 | D94: =IF(D93>0,(D43/D75)/D93,0) -> 0.26095616 | E94: =IF(E93>0,(E43/E75)/E93,0) -> 0.17099626 | F94: =IF(F93>0,(F43/F75)/F93,0) -> 0.26095616 | G94: =IF(G93>0,(G43/G75)/G93,0) -> 0.38225905 | H94: =IF(H93>0,(H43/H75)/H93,0) -> 0.26095616 | I94: =IF(I93>0,(I43/I75)/I93,0) -> 0.31525181 | J94: =IF(J93>0,(J43/J75)/J93,0) -> 0.26095616 | ... AH94: =IF(AH93>0,(AH43/AH75)/AH93,0) -> 0.13901909
A95: 每架總 tok/s | B95: tok/s | C95: =IF(C93>0,C22*(C43+C44)/C93,0) -> 1863289.6 | D95: =IF(D93>0,D22*(D43+D44)/D93,0) -> 713526.35 | E95: =IF(E93>0,E22*(E43+E44)/E93,0) -> 1090952.6 | F95: =IF(F93>0,F22*(F43+F44)/F93,0) -> 713526.35 | G95: =IF(G93>0,G22*(G43+G44)/G93,0) -> 2438804.7 | H95: =IF(H93>0,H22*(H43+H44)/H93,0) -> 713526.35 | I95: =IF(I93>0,I22*(I43+I44)/I93,0) -> 2011299.9 | J95: =IF(J93>0,J22*(J43+J44)/J93,0) -> 713526.35 | ... AH95: =IF(AH93>0,AH22*(AH43+AH44)/AH93,0) -> 115025.96
A96: 每架 decode tok/s | B96: tok/s | C96: =C95*C44/(C43+C44) -> 207032.17 | D96: =D95*D44/(D43+D44) -> 79280.705 | E96: =E95*E44/(E43+E44) -> 121216.95 | F96: =F95*F44/(F43+F44) -> 79280.705 | G96: =G95*G44/(G43+G44) -> 270978.3 | H96: =H95*H44/(H43+H44) -> 79280.705 | I96: =I95*I44/(I43+I44) -> 223477.76 | J96: =J95*J44/(J43+J44) -> 79280.705 | ... AH96: =AH95*AH44/(AH43+AH44) -> 12780.662
A97: 每架 prefill tok/s | B97: tok/s | C97: =C95-C96 -> 1656257.4 | D97: =D95-D96 -> 634245.64 | E97: =E95-E96 -> 969735.61 | F97: =F95-F96 -> 634245.64 | G97: =G95-G96 -> 2167826.4 | H97: =H95-H96 -> 634245.64 | I97: =I95-I96 -> 1787822.1 | J97: =J95-J96 -> 634245.64 | ... AH97: =AH95-AH96 -> 102245.3
A98: 每 GW 總產出 | B98: M tok/年 | C98: =C95*C25*8760*3600/1000000 -> 2.3809835e+11 | D98: =D95*D25*8760*3600/1000000 -> 1.5109936e+11 | E98: =E95*E25*8760*3600/1000000 -> 1.3940614e+11 | F98: =F95*F25*8760*3600/1000000 -> 1.5109936e+11 | G98: =G95*G25*8760*3600/1000000 -> 3.1163991e+11 | H98: =H95*H25*8760*3600/1000000 -> 1.5109936e+11 | I98: =I95*I25*8760*3600/1000000 -> 2.5701168e+11 | J98: =J95*J25*8760*3600/1000000 -> 1.5109936e+11 | ... AH98: =AH95*AH25*8760*3600/1000000 -> 2.4358384e+10
A99: 每 GW decode 產出 | B99: M tok/年 | C99: =C96*C25*8760*3600/1000000 -> 2.6455373e+10 | D99: =D96*D25*8760*3600/1000000 -> 1.6788818e+10 | E99: =E96*E25*8760*3600/1000000 -> 1.5489571e+10 | F99: =F96*F25*8760*3600/1000000 -> 1.6788818e+10 | G99: =G96*G25*8760*3600/1000000 -> 3.4626656e+10 | H99: =H96*H25*8760*3600/1000000 -> 1.6788818e+10 | I99: =I96*I25*8760*3600/1000000 -> 2.8556854e+10 | J99: =J96*J25*8760*3600/1000000 -> 1.6788818e+10 | ... AH99: =AH96*AH25*8760*3600/1000000 -> 2.7064872e+09
A100: I. 每 M token GPU 秒（供 Unit_Cost）與速覽成本
A101: 新鮮 prefill | B101: GPU-s/M | C101: =1000000/C75 -> 12.695967 | D101: =1000000/D75 -> 29.623922 | E101: =1000000/E75 -> 12.695967 | F101: =1000000/F75 -> 29.623922 | G101: =1000000/G75 -> 12.695967 | H101: =1000000/H75 -> 29.623922 | I101: =1000000/I75 -> 12.695967 | J101: =1000000/J75 -> 29.623922 | ... AH101: =1000000/AH75 -> 97.895697
...

Sheet Unit_Cost
A1: Unit_Cost — 每 M token 成本（世代 × 成本情境；依層級分區；新鮮 prefill／快取 prefill／decode）
A2: 成本＝每 GPU 小時持有成本（DC_Cost）× 每 M token GPU 秒（Perf）。思考 token 在物理上與可見輸出同為 decode，成本相同，差異只在計費（Block 4）。100% 為理想上限；基準利用率版＝100% 版 ÷ 利用率。快取命中只計 KV 載入 GPU 時間，未計儲存成本
A4: 世代 | C4: =DC_Cost!C4 -> Hopper H100 | D4: =DC_Cost!D4 -> Hopper H100 | E4: =DC_Cost!E4 -> Hopper H100 | F4: =DC_Cost!F4 -> GB200 NVL72 | G4: =DC_Cost!G4 -> GB200 NVL72 | H4: =DC_Cost!H4 -> GB200 NVL72 | I4: =DC_Cost!I4 -> GB300 NVL72 | J4: =DC_Cost!J4 -> GB300 NVL72 | ... Q4: =DC_Cost!Q4 -> Rubin Ultra NVL576
A5: 成本情境 | C5: =DC_Cost!C5 -> 低成本 | D5: =DC_Cost!D5 -> 基準 | E5: =DC_Cost!E5 -> 高成本 | F5: =DC_Cost!F5 -> 低成本 | G5: =DC_Cost!G5 -> 基準 | H5: =DC_Cost!H5 -> 高成本 | I5: =DC_Cost!I5 -> 低成本 | J5: =DC_Cost!J5 -> 基準 | ... Q5: =DC_Cost!Q5 -> 高成本
A6: 世代索引 | C6: 1 | D6: 1 | E6: 1 | F6: 2 | G6: 2 | H6: 2 | I6: 3 | J6: 3 | K6: 3 | L6: 4 | M6: 4 | N6: 4 | O6: 5 | P6: 5 | Q6: 5
A7: 共用
A8: 每 GPU 小時持有成本 — 經濟 | B8: $/GPU-hr | C8: =DC_Cost!C58 -> 1.1128667 | D8: =DC_Cost!D58 -> 1.6050293 | E8: =DC_Cost!E58 -> 2.767201 | F8: =DC_Cost!F58 -> 1.5435902 | G8: =DC_Cost!G58 -> 2.0767647 | H8: =DC_Cost!H58 -> 3.379614 | I8: =DC_Cost!I58 -> 2.0442466 | J8: =DC_Cost!J58 -> 2.9875129 | ... Q8: =DC_Cost!Q58 -> 15.917013
A9: 每 GPU 小時持有成本 — 會計 | B9: $/GPU-hr | C9: =DC_Cost!C57 -> 0.85832849 | D9: =DC_Cost!D57 -> 1.1918455 | E9: =DC_Cost!E57 -> 2.058675 | F9: =DC_Cost!F57 -> 1.1900066 | G9: =DC_Cost!G57 -> 1.538515 | H9: =DC_Cost!H57 -> 2.4977877 | I9: =DC_Cost!I57 -> 1.5850033 | J9: =DC_Cost!J57 -> 2.230249 | ... Q9: =DC_Cost!Q57 -> 12.060748
A10: 基準利用率 | B10: % | C10: =Serving!$C$17 -> 0.6 | D10: =Serving!$C$17 -> 0.6 | E10: =Serving!$C$17 -> 0.6 | F10: =Serving!$C$17 -> 0.6 | G10: =Serving!$C$17 -> 0.6 | H10: =Serving!$C$17 -> 0.6 | I10: =Serving!$C$17 -> 0.6 | J10: =Serving!$C$17 -> 0.6 | ... Q10: =Serving!$C$17 -> 0.6
A12: Luna（低層）
A13: GPU 秒／M 新鮮 prefill | B13: GPU-s | C13: =INDEX(Perf!$C$101:$Q$101,3*(C$6-1)+1) -> 127.98926 | D13: =INDEX(Perf!$C$101:$Q$101,3*(D$6-1)+1) -> 127.98926 | E13: =INDEX(Perf!$C$101:$Q$101,3*(E$6-1)+1) -> 127.98926 | F13: =INDEX(Perf!$C$101:$Q$101,3*(F$6-1)+1) -> 12.664537 | G13: =INDEX(Perf!$C$101:$Q$101,3*(G$6-1)+1) -> 12.664537 | H13: =INDEX(Perf!$C$101:$Q$101,3*(H$6-1)+1) -> 12.664537 | I13: =INDEX(Perf!$C$101:$Q$101,3*(I$6-1)+1) -> 8.443025 | J13: =INDEX(Perf!$C$101:$Q$101,3*(J$6-1)+1) -> 8.443025 | ... Q13: =INDEX(Perf!$C$101:$Q$101,3*(Q$6-1)+1) -> 1.7348681
A14: GPU 秒／M 快取命中 prefill | B14: GPU-s | C14: =INDEX(Perf!$C$102:$Q$102,3*(C$6-1)+1) -> 0.02795 | D14: =INDEX(Perf!$C$102:$Q$102,3*(D$6-1)+1) -> 0.02795 | E14: =INDEX(Perf!$C$102:$Q$102,3*(E$6-1)+1) -> 0.02795 | F14: =INDEX(Perf!$C$102:$Q$102,3*(F$6-1)+1) -> 0.02795 | G14: =INDEX(Perf!$C$102:$Q$102,3*(G$6-1)+1) -> 0.02795 | H14: =INDEX(Perf!$C$102:$Q$102,3*(H$6-1)+1) -> 0.02795 | I14: =INDEX(Perf!$C$102:$Q$102,3*(I$6-1)+1) -> 0.02795 | J14: =INDEX(Perf!$C$102:$Q$102,3*(J$6-1)+1) -> 0.02795 | ... Q14: =INDEX(Perf!$C$102:$Q$102,3*(Q$6-1)+1) -> 0.02795
A15: GPU 秒／M decode（含思考 token；0＝SLO 不可達） | B15: GPU-s | C15: =INDEX(Perf!$C$103:$Q$103,3*(C$6-1)+1) -> 1679.3613 | D15: =INDEX(Perf!$C$103:$Q$103,3*(D$6-1)+1) -> 1679.3613 | E15: =INDEX(Perf!$C$103:$Q$103,3*(E$6-1)+1) -> 1679.3613 | F15: =INDEX(Perf!$C$103:$Q$103,3*(F$6-1)+1) -> 285.73672 | G15: =INDEX(Perf!$C$103:$Q$103,3*(G$6-1)+1) -> 285.73672 | H15: =INDEX(Perf!$C$103:$Q$103,3*(H$6-1)+1) -> 285.73672 | I15: =INDEX(Perf!$C$103:$Q$103,3*(I$6-1)+1) -> 190.49115 | J15: =INDEX(Perf!$C$103:$Q$103,3*(J$6-1)+1) -> 190.49115 | ... Q15: =INDEX(Perf!$C$103:$Q$103,3*(Q$6-1)+1) -> 36.115692
A16: 新鮮 prefill $/M — 經濟、100% | B16: $/M | C16: =C$8/3600*C13 -> 0.039565274 | D16: =D$8/3600*D13 -> 0.057062919 | E16: =E$8/3600*E13 -> 0.098381113 | F16: =F$8/3600*F13 -> 0.0054302376 | G16: =G$8/3600*G13 -> 0.0073059068 | H16: =H$8/3600*H13 -> 0.011889235 | I16: =I$8/3600*I13 -> 0.0047943402 | J16: =J$8/3600*J13 -> 0.0070065683 | ... Q16: =Q$8/3600*Q13 -> 0.007670533
A17: 快取命中 prefill $/M — 經濟、100% | B17: $/M | C17: =C$8/3600*C14 -> 8.6401733e-06 | D17: =D$8/3600*D14 -> 1.2461269e-05 | E17: =E$8/3600*E14 -> 2.1484241e-05 | F17: =F$8/3600*F14 -> 1.1984263e-05 | G17: =G$8/3600*G14 -> 1.6123771e-05 | H17: =H$8/3600*H14 -> 2.6238947e-05 | I17: =I$8/3600*I14 -> 1.5871303e-05 | J17: =J$8/3600*J14 -> 2.3194718e-05 | ... Q17: =Q$8/3600*Q14 -> 0.00012357792
A18: decode（含思考 token）$/M — 經濟、100% | B18: $/M | C18: =IF(C15>0,C$8/3600*C15,"SLO 不可達") -> 0.51914034 | D18: =IF(D15>0,D$8/3600*D15,"SLO 不可達") -> 0.74872888 | E18: =IF(E15>0,E$8/3600*E15,"SLO 不可達") -> 1.2908695 | F18: =IF(F15>0,F$8/3600*F15,"SLO 不可達") -> 0.12251678 | G18: =IF(G15>0,G$8/3600*G15,"SLO 不可達") -> 0.16483554 | H18: =IF(H15>0,H$8/3600*H15,"SLO 不可達") -> 0.26824439 | I18: =IF(I15>0,I$8/3600*I15,"SLO 不可達") -> 0.10816969 | J18: =IF(J15>0,J$8/3600*J15,"SLO 不可達") -> 0.15808188 | ... Q18: =IF(Q15>0,Q$8/3600*Q15,"SLO 不可達") -> 0.15968165
A19: 新鮮 prefill $/M — 經濟、基準利用率 | B19: $/M | C19: =C16/C$10 -> 0.065942123 | D19: =D16/D$10 -> 0.095104865 | E19: =E16/E$10 -> 0.16396852 | F19: =F16/F$10 -> 0.009050396 | G19: =G16/G$10 -> 0.012176511 | H19: =H16/H$10 -> 0.019815392 | I19: =I16/I$10 -> 0.007990567 | J19: =J16/J$10 -> 0.011677614 | ... Q19: =Q16/Q$10 -> 0.012784222
A20: 快取命中 prefill $/M — 經濟、基準利用率 | B20: $/M | C20: =C17/C$10 -> 1.4400289e-05 | D20: =D17/D$10 -> 2.0768781e-05 | E20: =E17/E$10 -> 3.5807068e-05 | F20: =F17/F$10 -> 1.9973771e-05 | G20: =G17/G$10 -> 2.6872951e-05 | H20: =H17/H$10 -> 4.3731579e-05 | I20: =I17/I$10 -> 2.6452172e-05 | J20: =J17/J$10 -> 3.8657863e-05 | ... Q20: =Q17/Q$10 -> 0.0002059632
A21: decode（含思考 token）$/M — 經濟、基準利用率 | B21: $/M | C21: =IF(ISNUMBER(C18),C18/C$10,C18) -> 0.8652339 | D21: =IF(ISNUMBER(D18),D18/D$10,D18) -> 1.2478815 | E21: =IF(ISNUMBER(E18),E18/E$10,E18) -> 2.1514491 | F21: =IF(ISNUMBER(F18),F18/F$10,F18) -> 0.20419463 | G21: =IF(ISNUMBER(G18),G18/G$10,G18) -> 0.2747259 | H21: =IF(ISNUMBER(H18),H18/H$10,H18) -> 0.44707399 | I21: =IF(ISNUMBER(I18),I18/I$10,I18) -> 0.18028281 | J21: =IF(ISNUMBER(J18),J18/J$10,J18) -> 0.26346979 | ... Q21: =IF(ISNUMBER(Q18),Q18/Q$10,Q18) -> 0.26613608
A22: decode（含思考 token）$/M — 會計、100% | B22: $/M | C22: =IF(C15>0,C$9/3600*C15,"SLO 不可達") -> 0.400401 | D22: =IF(D15>0,D$9/3600*D15,"SLO 不可達") -> 0.55598309 | E22: =IF(E15>0,E$9/3600*E15,"SLO 不可達") -> 0.96034976 | F22: =IF(F15>0,F$9/3600*F15,"SLO 不可達") -> 0.094452385 | G22: =IF(G15>0,G$9/3600*G15,"SLO 不可達") -> 0.12211396 | H22: =IF(H15>0,H$9/3600*H15,"SLO 不可達") -> 0.19825268 | I22: =IF(I15>0,I$9/3600*I15,"SLO 不可達") -> 0.083869193 | J22: =IF(J15>0,J$9/3600*J15,"SLO 不可達") -> 0.11801186 | ... Q22: =IF(Q15>0,Q$9/3600*Q15,"SLO 不可達") -> 0.12099507
A23: 參考請求混合 $/M 總 token — 經濟、100% | B23: $/M | C23: =IF(ISNUMBER(C18),(Serving!$C$23*C16+Serving!$C$24*C18)/(Serving!$C$23+Serving!$C$24),C18) -> 0.092851392 | D23: =IF(ISNUMBER(D18),(Serving!$C$23*D16+Serving!$C$24*D18)/(Serving!$C$23+Serving!$C$24),D18) -> 0.13391469 | E23: =IF(ISNUMBER(E18),(Serving!$C$23*E16+Serving!$C$24*E18)/(Serving!$C$23+Serving!$C$24),E18) -> 0.23087982 | F23: =IF(ISNUMBER(F18),(Serving!$C$23*F16+Serving!$C$24*F18)/(Serving!$C$23+Serving!$C$24),F18) -> 0.018439853 | G23: =IF(ISNUMBER(G18),(Serving!$C$23*G16+Serving!$C$24*G18)/(Serving!$C$23+Serving!$C$24),G18) -> 0.024809199 | H23: =IF(ISNUMBER(H18),(Serving!$C$23*H16+Serving!$C$24*H18)/(Serving!$C$23+Serving!$C$24),H18) -> 0.040373142 | I23: =IF(ISNUMBER(I18),(Serving!$C$23*I16+Serving!$C$24*I18)/(Serving!$C$23+Serving!$C$24),I18) -> 0.01628049 | J23: =IF(ISNUMBER(J18),(Serving!$C$23*J16+Serving!$C$24*J18)/(Serving!$C$23+Serving!$C$24),J18) -> 0.023792714 | ... Q23: =IF(ISNUMBER(Q18),(Serving!$C$23*Q16+Serving!$C$24*Q18)/(Serving!$C$23+Serving!$C$24),Q18) -> 0.024560657
A25: Sol（中層）
A26: GPU 秒／M 新鮮 prefill | B26: GPU-s | C26: =INDEX(Perf!$C$101:$Q$101,3*(C$6-1)+2) -> 449.07412 | D26: =INDEX(Perf!$C$101:$Q$101,3*(D$6-1)+2) -> 449.07412 | E26: =INDEX(Perf!$C$101:$Q$101,3*(E$6-1)+2) -> 449.07412 | F26: =INDEX(Perf!$C$101:$Q$101,3*(F$6-1)+2) -> 44.435884 | G26: =INDEX(Perf!$C$101:$Q$101,3*(G$6-1)+2) -> 44.435884 | H26: =INDEX(Perf!$C$101:$Q$101,3*(H$6-1)+2) -> 44.435884 | I26: =INDEX(Perf!$C$101:$Q$101,3*(I$6-1)+2) -> 29.623922 | J26: =INDEX(Perf!$C$101:$Q$101,3*(J$6-1)+2) -> 29.623922 | ... Q26: =INDEX(Perf!$C$101:$Q$101,3*(Q$6-1)+2) -> 6.0871074
A27: GPU 秒／M 快取命中 prefill | B27: GPU-s | C27: =INDEX(Perf!$C$102:$Q$102,3*(C$6-1)+2) -> 0.03965 | D27: =INDEX(Perf!$C$102:$Q$102,3*(D$6-1)+2) -> 0.03965 | E27: =INDEX(Perf!$C$102:$Q$102,3*(E$6-1)+2) -> 0.03965 | F27: =INDEX(Perf!$C$102:$Q$102,3*(F$6-1)+2) -> 0.03965 | G27: =INDEX(Perf!$C$102:$Q$102,3*(G$6-1)+2) -> 0.03965 | H27: =INDEX(Perf!$C$102:$Q$102,3*(H$6-1)+2) -> 0.03965 | I27: =INDEX(Perf!$C$102:$Q$102,3*(I$6-1)+2) -> 0.03965 | J27: =INDEX(Perf!$C$102:$Q$102,3*(J$6-1)+2) -> 0.03965 | ... Q27: =INDEX(Perf!$C$102:$Q$102,3*(Q$6-1)+2) -> 0.03965
A28: GPU 秒／M decode（含思考 token；0＝SLO 不可達） | B28: GPU-s | C28: =INDEX(Perf!$C$103:$Q$103,3*(C$6-1)+2) -> 5839.1372 | D28: =INDEX(Perf!$C$103:$Q$103,3*(D$6-1)+2) -> 5839.1372 | E28: =INDEX(Perf!$C$103:$Q$103,3*(E$6-1)+2) -> 5839.1372 | F28: =INDEX(Perf!$C$103:$Q$103,3*(F$6-1)+2) -> 1006.7612 | G28: =INDEX(Perf!$C$103:$Q$103,3*(G$6-1)+2) -> 1006.7612 | H28: =INDEX(Perf!$C$103:$Q$103,3*(H$6-1)+2) -> 1006.7612 | I28: =INDEX(Perf!$C$103:$Q$103,3*(I$6-1)+2) -> 671.17411 | J28: =INDEX(Perf!$C$103:$Q$103,3*(J$6-1)+2) -> 671.17411 | ... Q28: =INDEX(Perf!$C$103:$Q$103,3*(Q$6-1)+2) -> 113.27614
A29: 新鮮 prefill $/M — 經濟、100% | B29: $/M | C29: =C$8/3600*C26 -> 0.13882212 | D29: =D$8/3600*D26 -> 0.20021586 | E29: =E$8/3600*E26 -> 0.34518842 | F29: =F$8/3600*F26 -> 0.019052998 | G29: =G$8/3600*G26 -> 0.025634132 | H29: =H$8/3600*H26 -> 0.041715593 | I29: =I$8/3600*I26 -> 0.016821834 | J29: =J$8/3600*J26 -> 0.024583847 | ... Q29: =Q$8/3600*Q26 -> 0.026913491
A30: 快取命中 prefill $/M — 經濟、100% | B30: $/M | C30: =C$8/3600*C27 -> 1.225699e-05 | D30: =D$8/3600*D27 -> 1.7677614e-05 | E30: =E$8/3600*E27 -> 3.0477644e-05 | F30: =F$8/3600*F27 -> 1.7000931e-05 | G30: =G$8/3600*G27 -> 2.2873256e-05 | H30: =H$8/3600*H27 -> 3.7222693e-05 | I30: =I$8/3600*I27 -> 2.2515104e-05 | J30: =J$8/3600*J27 -> 3.2904135e-05 | ... Q30: =Q$8/3600*Q27 -> 0.00017530821
A31: decode（含思考 token）$/M — 經濟、100% | B31: $/M | C31: =IF(C28>0,C$8/3600*C28,"SLO 不可達") -> 1.8050504 | D31: =IF(D28>0,D$8/3600*D28,"SLO 不可達") -> 2.6033295 | E31: =IF(E28>0,E$8/3600*E28,"SLO 不可達") -> 4.4883517 | F31: =IF(F28>0,F$8/3600*F28,"SLO 不可達") -> 0.43167406 | G31: =IF(G28>0,G$8/3600*G28,"SLO 不可達") -> 0.58077946 | H31: =IF(H28>0,H$8/3600*H28,"SLO 不可達") -> 0.94512891 | I31: =IF(I28>0,I$8/3600*I28,"SLO 不可達") -> 0.38112371 | J31: =IF(J28>0,J$8/3600*J28,"SLO 不可達") -> 0.55698369 | ... Q31: =IF(Q28>0,Q$8/3600*Q28,"SLO 不可達") -> 0.50083827
A32: 新鮮 prefill $/M — 經濟、基準利用率 | B32: $/M | C32: =C29/C$10 -> 0.2313702 | D32: =D29/D$10 -> 0.3336931 | E32: =E29/E$10 -> 0.57531404 | F32: =F29/F$10 -> 0.031754997 | G32: =G29/G$10 -> 0.042723554 | H32: =H29/H$10 -> 0.069525988 | I32: =I29/I$10 -> 0.02803639 | J32: =J29/J$10 -> 0.040973079 | ... Q32: =Q29/Q$10 -> 0.044855818
A33: 快取命中 prefill $/M — 經濟、基準利用率 | B33: $/M | C33: =C30/C$10 -> 2.0428317e-05 | D33: =D30/D$10 -> 2.946269e-05 | E33: =E30/E$10 -> 5.0796073e-05 | F33: =F30/F$10 -> 2.8334884e-05 | G33: =G30/G$10 -> 3.8122093e-05 | H33: =H30/H$10 -> 6.2037821e-05 | I33: =I30/I$10 -> 3.7525174e-05 | J33: =J30/J$10 -> 5.4840225e-05 | ... Q33: =Q30/Q$10 -> 0.00029218035
A34: decode（含思考 token）$/M — 經濟、基準利用率 | B34: $/M | C34: =IF(ISNUMBER(C31),C31/C$10,C31) -> 3.0084173 | D34: =IF(ISNUMBER(D31),D31/D$10,D31) -> 4.3388824 | E34: =IF(ISNUMBER(E31),E31/E$10,E31) -> 7.4805861 | F34: =IF(ISNUMBER(F31),F31/F$10,F31) -> 0.71945677 | G34: =IF(ISNUMBER(G31),G31/G$10,G31) -> 0.96796577 | H34: =IF(ISNUMBER(H31),H31/H$10,H31) -> 1.5752148 | I34: =IF(ISNUMBER(I31),I31/I$10,I31) -> 0.63520618 | J34: =IF(ISNUMBER(J31),J31/J$10,J31) -> 0.92830615 | ... Q34: =IF(ISNUMBER(Q31),Q31/Q$10,Q31) -> 0.83473046
A35: decode（含思考 token）$/M — 會計、100% | B35: $/M | C35: =IF(C28>0,C$9/3600*C28,"SLO 不可達") -> 1.3921938 | D35: =IF(D28>0,D$9/3600*D28,"SLO 不可達") -> 1.9331526 | E35: =IF(E28>0,E$9/3600*E28,"SLO 不可達") -> 3.339135 | F35: =IF(F28>0,F$9/3600*F28,"SLO 不可達") -> 0.33279234 | G35: =IF(G28>0,G$9/3600*G28,"SLO 不可達") -> 0.43025477 | H35: =IF(H28>0,H$9/3600*H28,"SLO 不可達") -> 0.698521 | I35: =IF(I28>0,I$9/3600*I28,"SLO 不可達") -> 0.29550366 | J35: =IF(J28>0,J$9/3600*J28,"SLO 不可達") -> 0.4158015 | ... Q35: =IF(Q28>0,Q$9/3600*Q28,"SLO 不可達") -> 0.3794986
A36: 參考請求混合 $/M 總 token — 經濟、100% | B36: $/M | C36: =IF(ISNUMBER(C31),(Serving!$D$23*C29+Serving!$D$24*C31)/(Serving!$D$23+Serving!$D$24),C31) -> 0.32395859 | D36: =IF(ISNUMBER(D31),(Serving!$D$23*D29+Serving!$D$24*D31)/(Serving!$D$23+Serving!$D$24),D31) -> 0.46722848 | E36: =IF(ISNUMBER(E31),(Serving!$D$23*E29+Serving!$D$24*E31)/(Serving!$D$23+Serving!$D$24),E31) -> 0.80553989 | F36: =IF(ISNUMBER(F31),(Serving!$D$23*F29+Serving!$D$24*F31)/(Serving!$D$23+Serving!$D$24),F31) -> 0.064899783 | G36: =IF(ISNUMBER(G31),(Serving!$D$23*G29+Serving!$D$24*G31)/(Serving!$D$23+Serving!$D$24),G31) -> 0.087316947 | H36: =IF(ISNUMBER(H31),(Serving!$D$23*H29+Serving!$D$24*H31)/(Serving!$D$23+Serving!$D$24),H31) -> 0.14209485 | I36: =IF(ISNUMBER(I31),(Serving!$D$23*I29+Serving!$D$24*I31)/(Serving!$D$23+Serving!$D$24),I31) -> 0.05729982 | J36: =IF(ISNUMBER(J31),(Serving!$D$23*J29+Serving!$D$24*J31)/(Serving!$D$23+Serving!$D$24),J31) -> 0.083739385 | ... Q36: =IF(ISNUMBER(Q31),(Serving!$D$23*Q29+Serving!$D$24*Q31)/(Serving!$D$23+Serving!$D$24),Q31) -> 0.0795718
A38: Astra（頂層）
A39: GPU 秒／M 新鮮 prefill | B39: GPU-s | C39: =INDEX(Perf!$C$101:$Q$101,3*(C$6-1)+3) -> 1484.0176 | D39: =INDEX(Perf!$C$101:$Q$101,3*(D$6-1)+3) -> 1484.0176 | E39: =INDEX(Perf!$C$101:$Q$101,3*(E$6-1)+3) -> 1484.0176 | F39: =INDEX(Perf!$C$101:$Q$101,3*(F$6-1)+3) -> 146.84355 | G39: =INDEX(Perf!$C$101:$Q$101,3*(G$6-1)+3) -> 146.84355 | H39: =INDEX(Perf!$C$101:$Q$101,3*(H$6-1)+3) -> 146.84355 | I39: =INDEX(Perf!$C$101:$Q$101,3*(I$6-1)+3) -> 97.895697 | J39: =INDEX(Perf!$C$101:$Q$101,3*(J$6-1)+3) -> 97.895697 | ... Q39: =INDEX(Perf!$C$101:$Q$101,3*(Q$6-1)+3) -> 20.115554
A40: GPU 秒／M 快取命中 prefill | B40: GPU-s | C40: =INDEX(Perf!$C$102:$Q$102,3*(C$6-1)+3) -> 0.576 | D40: =INDEX(Perf!$C$102:$Q$102,3*(D$6-1)+3) -> 0.576 | E40: =INDEX(Perf!$C$102:$Q$102,3*(E$6-1)+3) -> 0.576 | F40: =INDEX(Perf!$C$102:$Q$102,3*(F$6-1)+3) -> 0.576 | G40: =INDEX(Perf!$C$102:$Q$102,3*(G$6-1)+3) -> 0.576 | H40: =INDEX(Perf!$C$102:$Q$102,3*(H$6-1)+3) -> 0.576 | I40: =INDEX(Perf!$C$102:$Q$102,3*(I$6-1)+3) -> 0.576 | J40: =INDEX(Perf!$C$102:$Q$102,3*(J$6-1)+3) -> 0.576 | ... Q40: =INDEX(Perf!$C$102:$Q$102,3*(Q$6-1)+3) -> 0.576
A41: GPU 秒／M decode（含思考 token；0＝SLO 不可達） | B41: GPU-s | C41: =INDEX(Perf!$C$103:$Q$103,3*(C$6-1)+3) -> 39747.514 | D41: =INDEX(Perf!$C$103:$Q$103,3*(D$6-1)+3) -> 39747.514 | E41: =INDEX(Perf!$C$103:$Q$103,3*(E$6-1)+3) -> 39747.514 | F41: =INDEX(Perf!$C$103:$Q$103,3*(F$6-1)+3) -> 5853.7759 | G41: =INDEX(Perf!$C$103:$Q$103,3*(G$6-1)+3) -> 5853.7759 | H41: =INDEX(Perf!$C$103:$Q$103,3*(H$6-1)+3) -> 5853.7759 | I41: =INDEX(Perf!$C$103:$Q$103,3*(I$6-1)+3) -> 4850.3455 | J41: =INDEX(Perf!$C$103:$Q$103,3*(J$6-1)+3) -> 4850.3455 | ... Q41: =INDEX(Perf!$C$103:$Q$103,3*(Q$6-1)+3) -> 545.21648
A42: 新鮮 prefill $/M — 經濟、100% | B42: $/M | C42: =C$8/3600*C39 -> 0.45875383 | D42: =D$8/3600*D39 -> 0.66163659 | E42: =E$8/3600*E39 -> 1.1407153 | F42: =F$8/3600*F39 -> 0.062962848 | G42: =G$8/3600*G39 -> 0.084710971 | H42: =H$8/3600*H39 -> 0.13785403 | I42: =I$8/3600*I39 -> 0.055589706 | J42: =J$8/3600*J39 -> 0.081240182 | ... Q42: =Q$8/3600*Q39 -> 0.08893876
A43: 快取命中 prefill $/M — 經濟、100% | B43: $/M | C43: =C$8/3600*C40 -> 0.00017805867 | D43: =D$8/3600*D40 -> 0.00025680468 | E43: =E$8/3600*E40 -> 0.00044275215 | F43: =F$8/3600*F40 -> 0.00024697443 | G43: =G$8/3600*G40 -> 0.00033228236 | H43: =H$8/3600*H40 -> 0.00054073824 | I43: =I$8/3600*I40 -> 0.00032707945 | J43: =J$8/3600*J40 -> 0.00047800206 | ... Q43: =Q$8/3600*Q40 -> 0.0025467221
A44: decode（含思考 token）$/M — 經濟、100% | B44: $/M | C44: =IF(C41>0,C$8/3600*C41,"SLO 不可達") -> 12.287135 | D44: =IF(D41>0,D$8/3600*D41,"SLO 不可達") -> 17.72109 | E44: =IF(E41>0,E$8/3600*E41,"SLO 不可達") -> 30.5526 | F44: =IF(F41>0,F$8/3600*F41,"SLO 不可達") -> 2.509953 | G44: =IF(G41>0,G$8/3600*G41,"SLO 不可達") -> 3.3769209 | H44: =IF(H41>0,H$8/3600*H41,"SLO 不可達") -> 5.4954174 | I44: =IF(I41>0,I$8/3600*I41,"SLO 不可達") -> 2.7542506 | J44: =IF(J41>0,J$8/3600*J41,"SLO 不可達") -> 4.0251304 | ... Q44: =IF(Q41>0,Q$8/3600*Q41,"SLO 不可達") -> 2.410616
A45: 新鮮 prefill $/M — 經濟、基準利用率 | B45: $/M | C45: =C42/C$10 -> 0.76458972 | D45: =D42/D$10 -> 1.1027277 | E45: =E42/E$10 -> 1.9011921 | F45: =F42/F$10 -> 0.10493808 | G45: =G42/G$10 -> 0.14118495 | H45: =H42/H$10 -> 0.22975671 | I45: =I42/I$10 -> 0.09264951 | J45: =J42/J$10 -> 0.1354003 | ... Q45: =Q42/Q$10 -> 0.14823127
A46: 快取命中 prefill $/M — 經濟、基準利用率 | B46: $/M | C46: =C43/C$10 -> 0.00029676445 | D46: =D43/D$10 -> 0.0004280078 | E46: =E43/E$10 -> 0.00073792026 | F46: =F43/F$10 -> 0.00041162404 | G46: =G43/G$10 -> 0.00055380393 | H46: =H43/H$10 -> 0.00090123039 | I46: =I43/I$10 -> 0.00054513241 | J46: =J43/J$10 -> 0.0007966701 | ... Q46: =Q43/Q$10 -> 0.0042445368
A47: decode（含思考 token）$/M — 經濟、基準利用率 | B47: $/M | C47: =IF(ISNUMBER(C44),C44/C$10,C44) -> 20.478558 | D47: =IF(ISNUMBER(D44),D44/D$10,D44) -> 29.535149 | E47: =IF(ISNUMBER(E44),E44/E$10,E44) -> 50.920999 | F47: =IF(ISNUMBER(F44),F44/F$10,F44) -> 4.183255 | G47: =IF(ISNUMBER(G44),G44/G$10,G44) -> 5.6282015 | H47: =IF(ISNUMBER(H44),H44/H$10,H44) -> 9.159029 | I47: =IF(ISNUMBER(I44),I44/I$10,I44) -> 4.5904176 | J47: =IF(ISNUMBER(J44),J44/J$10,J44) -> 6.7085507 | ... Q47: =IF(ISNUMBER(Q44),Q44/Q$10,Q44) -> 4.0176934
A48: decode（含思考 token）$/M — 會計、100% | B48: $/M | C48: =IF(C41>0,C$9/3600*C41,"SLO 不可達") -> 9.4767843 | D48: =IF(D41>0,D$9/3600*D41,"SLO 不可達") -> 13.159137 | E48: =IF(E41>0,E$9/3600*E41,"SLO 不可達") -> 22.729782 | F48: =IF(F41>0,F$9/3600*F41,"SLO 不可達") -> 1.9350089 | G48: =IF(G41>0,G$9/3600*G41,"SLO 不可達") -> 2.5017006 | H48: =IF(H41>0,H$9/3600*H41,"SLO 不可達") -> 4.0615247 | I48: =IF(I41>0,I$9/3600*I41,"SLO 不可達") -> 2.1355038 | J48: =IF(J41>0,J$9/3600*J41,"SLO 不可達") -> 3.004855 | ... Q48: =IF(Q41>0,Q$9/3600*Q41,"SLO 不可達") -> 1.8265884
A49: 參考請求混合 $/M 總 token — 經濟、100% | B49: $/M | C49: =IF(ISNUMBER(C44),(Serving!$E$23*C42+Serving!$E$24*C44)/(Serving!$E$23+Serving!$E$24),C44) -> 1.7730184 | D49: =IF(ISNUMBER(D44),(Serving!$E$23*D42+Serving!$E$24*D44)/(Serving!$E$23+Serving!$E$24),D44) -> 2.5571314 | E49: =IF(ISNUMBER(E44),(Serving!$E$23*E42+Serving!$E$24*E44)/(Serving!$E$23+Serving!$E$24),E44) -> 4.4087024 | F49: =IF(ISNUMBER(F44),(Serving!$E$23*F42+Serving!$E$24*F44)/(Serving!$E$23+Serving!$E$24),F44) -> 0.33485064 | G49: =IF(ISNUMBER(G44),(Serving!$E$23*G42+Serving!$E$24*G44)/(Serving!$E$23+Serving!$E$24),G44) -> 0.45051207 | H49: =IF(ISNUMBER(H44),(Serving!$E$23*H42+Serving!$E$24*H44)/(Serving!$E$23+Serving!$E$24),H44) -> 0.73313885 | I49: =IF(ISNUMBER(I44),(Serving!$E$23*I42+Serving!$E$24*I44)/(Serving!$E$23+Serving!$E$24),I44) -> 0.35544091 | J49: =IF(ISNUMBER(J44),(Serving!$E$23*J42+Serving!$E$24*J44)/(Serving!$E$23+Serving!$E$24),J44) -> 0.51945021 | ... Q49: =IF(ISNUMBER(Q44),(Serving!$E$23*Q42+Serving!$E$24*Q44)/(Serving!$E$23+Serving!$E$24),Q44) -> 0.3469029

Sheet DC_Cost
A1: DC_Cost — 每 GW（IT）資本支出與年持有成本：5 世代 × 3 成本情境
A2: 功率情境由 Inputs!E6 控制；成本情境為角落情境（所有金額輸入同時取低或高）
A4: 世代 | C4: =Spec_Rack!C4 -> Hopper H100 | D4: =Spec_Rack!C4 -> Hopper H100 | E4: =Spec_Rack!C4 -> Hopper H100 | F4: =Spec_Rack!D4 -> GB200 NVL72 | G4: =Spec_Rack!D4 -> GB200 NVL72 | H4: =Spec_Rack!D4 -> GB200 NVL72 | I4: =Spec_Rack!E4 -> GB300 NVL72 | J4: =Spec_Rack!E4 -> GB300 NVL72 | K4: =Spec_Rack!E4 -> GB300 NVL72 | L4: =Spec_Rack!F4 -> VR200 NVL72 | M4: =Spec_Rack!F4 -> VR200 NVL72 | N4: =Spec_Rack!F4 -> VR200 NVL72 | O4: =Spec_Rack!G4 -> Rubin Ultra NVL576 | P4: =Spec_Rack!G4 -> Rubin Ultra NVL576 | Q4: =Spec_Rack!G4 -> Rubin Ultra NVL576
A5: 成本情境 | C5: 低成本 | D5: 基準 | E5: 高成本 | F5: 低成本 | G5: 基準 | H5: 高成本 | I5: 低成本 | J5: 基準 | K5: 高成本 | L5: 低成本 | M5: 基準 | N5: 高成本 | O5: 低成本 | P5: 基準 | Q5: 高成本
A7: A. 規模與電力
A8: IT 電力 | B8: MW | C8: =Inputs!$E$5*1000 -> 1000 | D8: =Inputs!$E$5*1000 -> 1000 | E8: =Inputs!$E$5*1000 -> 1000 | F8: =Inputs!$E$5*1000 -> 1000 | G8: =Inputs!$E$5*1000 -> 1000 | H8: =Inputs!$E$5*1000 -> 1000 | I8: =Inputs!$E$5*1000 -> 1000 | J8: =Inputs!$E$5*1000 -> 1000 | ... Q8: =Inputs!$E$5*1000 -> 1000
A9: 機架外 IT 電力占比 | B9: % | C9: =Inputs!$E$8 -> 0.08 | D9: =Inputs!$E$8 -> 0.08 | E9: =Inputs!$E$8 -> 0.08 | F9: =Inputs!$E$8 -> 0.08 | G9: =Inputs!$E$8 -> 0.08 | H9: =Inputs!$E$8 -> 0.08 | I9: =Inputs!$E$8 -> 0.08 | J9: =Inputs!$E$8 -> 0.08 | ... Q9: =Inputs!$E$8 -> 0.08
A10: 機架可用 IT 電力 | B10: MW | C10: =C8*(1-C9) -> 920 | D10: =D8*(1-D9) -> 920 | E10: =E8*(1-E9) -> 920 | F10: =F8*(1-F9) -> 920 | G10: =G8*(1-G9) -> 920 | H10: =H8*(1-H9) -> 920 | I10: =I8*(1-I9) -> 920 | J10: =J8*(1-J9) -> 920 | ... Q10: =Q8*(1-Q9) -> 920
A11: 每架配電設計功率 | B11: kW | C11: =CHOOSE(Inputs!$E$6,Spec_Rack!C8,Spec_Rack!C9,Spec_Rack!C10) -> 41 | D11: =CHOOSE(Inputs!$E$6,Spec_Rack!C8,Spec_Rack!C9,Spec_Rack!C10) -> 41 | E11: =CHOOSE(Inputs!$E$6,Spec_Rack!C8,Spec_Rack!C9,Spec_Rack!C10) -> 41 | F11: =CHOOSE(Inputs!$E$6,Spec_Rack!D8,Spec_Rack!D9,Spec_Rack!D10) -> 130 | G11: =CHOOSE(Inputs!$E$6,Spec_Rack!D8,Spec_Rack!D9,Spec_Rack!D10) -> 130 | H11: =CHOOSE(Inputs!$E$6,Spec_Rack!D8,Spec_Rack!D9,Spec_Rack!D10) -> 130 | I11: =CHOOSE(Inputs!$E$6,Spec_Rack!E8,Spec_Rack!E9,Spec_Rack!E10) -> 137 | J11: =CHOOSE(Inputs!$E$6,Spec_Rack!E8,Spec_Rack!E9,Spec_Rack!E10) -> 137 | K11: =CHOOSE(Inputs!$E$6,Spec_Rack!E8,Spec_Rack!E9,Spec_Rack!E10) -> 137 | L11: =CHOOSE(Inputs!$E$6,Spec_Rack!F8,Spec_Rack!F9,Spec_Rack!F10) -> 227 | M11: =CHOOSE(Inputs!$E$6,Spec_Rack!F8,Spec_Rack!F9,Spec_Rack!F10) -> 227 | N11: =CHOOSE(Inputs!$E$6,Spec_Rack!F8,Spec_Rack!F9,Spec_Rack!F10) -> 227 | O11: =CHOOSE(Inputs!$E$6,Spec_Rack!G8,Spec_Rack!G9,Spec_Rack!G10) -> 600 | P11: =CHOOSE(Inputs!$E$6,Spec_Rack!G8,Spec_Rack!G9,Spec_Rack!G10) -> 600 | Q11: =CHOOSE(Inputs!$E$6,Spec_Rack!G8,Spec_Rack!G9,Spec_Rack!G10) -> 600
A12: 每 GW 機架數 | B12: 架 | C12: =FLOOR(C10*1000/C11,1) -> 22439 | D12: =FLOOR(D10*1000/D11,1) -> 22439 | E12: =FLOOR(E10*1000/E11,1) -> 22439 | F12: =FLOOR(F10*1000/F11,1) -> 7076 | G12: =FLOOR(G10*1000/G11,1) -> 7076 | H12: =FLOOR(H10*1000/H11,1) -> 7076 | I12: =FLOOR(I10*1000/I11,1) -> 6715 | J12: =FLOOR(J10*1000/J11,1) -> 6715 | ... Q12: =FLOOR(Q10*1000/Q11,1) -> 1533
A13: GPU 封裝／架 | B13: 顆 | C13: =Spec_Rack!C6 -> 32 | D13: =Spec_Rack!C6 -> 32 | E13: =Spec_Rack!C6 -> 32 | F13: =Spec_Rack!D6 -> 72 | G13: =Spec_Rack!D6 -> 72 | H13: =Spec_Rack!D6 -> 72 | I13: =Spec_Rack!E6 -> 72 | J13: =Spec_Rack!E6 -> 72 | K13: =Spec_Rack!E6 -> 72 | L13: =Spec_Rack!F6 -> 72 | M13: =Spec_Rack!F6 -> 72 | N13: =Spec_Rack!F6 -> 72 | O13: =Spec_Rack!G6 -> 144 | P13: =Spec_Rack!G6 -> 144 | Q13: =Spec_Rack!G6 -> 144
A14: 每 GW GPU 數 | B14: 顆 | C14: =C12*C13 -> 718048 | D14: =D12*D13 -> 718048 | E14: =E12*E13 -> 718048 | F14: =F12*F13 -> 509472 | G14: =G12*G13 -> 509472 | H14: =H12*H13 -> 509472 | I14: =I12*I13 -> 483480 | J14: =J12*J13 -> 483480 | ... Q14: =Q12*Q13 -> 220752
A15: PUE | B15: x | C15: =Inputs!D9 -> 1.1 | D15: =Inputs!E9 -> 1.2 | E15: =Inputs!F9 -> 1.3 | F15: =Inputs!D9 -> 1.1 | G15: =Inputs!E9 -> 1.2 | H15: =Inputs!F9 -> 1.3 | I15: =Inputs!D9 -> 1.1 | J15: =Inputs!E9 -> 1.2 | K15: =Inputs!F9 -> 1.3 | L15: =Inputs!D9 -> 1.1 | M15: =Inputs!E9 -> 1.2 | N15: =Inputs!F9 -> 1.3 | O15: =Inputs!D9 -> 1.1 | P15: =Inputs!E9 -> 1.2 | Q15: =Inputs!F9 -> 1.3
A16: 設施電力（IT × PUE） | B16: MW | C16: =C8*C15 -> 1100 | D16: =D8*D15 -> 1200 | E16: =E8*E15 -> 1300 | F16: =F8*F15 -> 1100 | G16: =G8*G15 -> 1200 | H16: =H8*H15 -> 1300 | I16: =I8*I15 -> 1100 | J16: =J8*J15 -> 1200 | ... Q16: =Q8*Q15 -> 1300
A17: B. 資本支出（$B／GW）
A18: 機架單價 | B18: $M | C18: =Spec_Rack!C11 -> 0.9 | D18: =Spec_Rack!C12 -> 1.1 | E18: =Spec_Rack!C13 -> 1.3 | F18: =Spec_Rack!D11 -> 2.8 | G18: =Spec_Rack!D12 -> 3.1 | H18: =Spec_Rack!D13 -> 3.4 | I18: =Spec_Rack!E11 -> 4 | J18: =Spec_Rack!E12 -> 5 | K18: =Spec_Rack!E13 -> 6.5 | L18: =Spec_Rack!F11 -> 6.7 | M18: =Spec_Rack!F12 -> 7.8 | N18: =Spec_Rack!F13 -> 9.1 | O18: =Spec_Rack!G11 -> 23.4 | P18: =Spec_Rack!G12 -> 31.2 | Q18: =Spec_Rack!G13 -> 39
A19: 機架 | B19: $B | C19: =C12*C18/1000 -> 20.1951 | D19: =D12*D18/1000 -> 24.6829 | E19: =E12*E18/1000 -> 29.1707 | F19: =F12*F18/1000 -> 19.8128 | G19: =G12*G18/1000 -> 21.9356 | H19: =H12*H18/1000 -> 24.0584 | I19: =I12*I18/1000 -> 26.86 | J19: =J12*J18/1000 -> 33.575 | ... Q19: =Q12*Q18/1000 -> 59.787
A20: Scale-out 網路 ÷ 機架價格 | B20: % | C20: =Inputs!D13 -> 0.05 | D20: =Inputs!E13 -> 0.1 | E20: =Inputs!F13 -> 0.15 | F20: =Inputs!D13 -> 0.05 | G20: =Inputs!E13 -> 0.1 | H20: =Inputs!F13 -> 0.15 | I20: =Inputs!D13 -> 0.05 | J20: =Inputs!E13 -> 0.1 | K20: =Inputs!F13 -> 0.15 | L20: =Inputs!D13 -> 0.05 | M20: =Inputs!E13 -> 0.1 | N20: =Inputs!F13 -> 0.15 | O20: =Inputs!D13 -> 0.05 | P20: =Inputs!E13 -> 0.1 | Q20: =Inputs!F13 -> 0.15
A21: Scale-out 網路 | B21: $B | C21: =C19*C20 -> 1.009755 | D21: =D19*D20 -> 2.46829 | E21: =E19*E20 -> 4.375605 | F21: =F19*F20 -> 0.99064 | G21: =G19*G20 -> 2.19356 | H21: =H19*H20 -> 3.60876 | I21: =I19*I20 -> 1.343 | J21: =J19*J20 -> 3.3575 | ... Q21: =Q19*Q20 -> 8.96805
A22: 儲存與管理 | B22: $/GPU | C22: =Inputs!D14 -> 300 | D22: =Inputs!E14 -> 500 | E22: =Inputs!F14 -> 800 | F22: =Inputs!D14 -> 300 | G22: =Inputs!E14 -> 500 | H22: =Inputs!F14 -> 800 | I22: =Inputs!D14 -> 300 | J22: =Inputs!E14 -> 500 | K22: =Inputs!F14 -> 800 | L22: =Inputs!D14 -> 300 | M22: =Inputs!E14 -> 500 | N22: =Inputs!F14 -> 800 | O22: =Inputs!D14 -> 300 | P22: =Inputs!E14 -> 500 | Q22: =Inputs!F14 -> 800
A23: 儲存與管理 | B23: $B | C23: =C14*C22/1000000000 -> 0.2154144 | D23: =D14*D22/1000000000 -> 0.359024 | E23: =E14*E22/1000000000 -> 0.5744384 | F23: =F14*F22/1000000000 -> 0.1528416 | G23: =G14*G22/1000000000 -> 0.254736 | H23: =H14*H22/1000000000 -> 0.4075776 | I23: =I14*I22/1000000000 -> 0.145044 | J23: =J14*J22/1000000000 -> 0.24174 | ... Q23: =Q14*Q22/1000000000 -> 0.1766016
A24: IT 設備小計 | B24: $B | C24: =C19+C21+C23 -> 21.420269 | D24: =D19+D21+D23 -> 27.510214 | E24: =E19+E21+E23 -> 34.120743 | F24: =F19+F21+F23 -> 20.956282 | G24: =G19+G21+G23 -> 24.383896 | H24: =H19+H21+H23 -> 28.074738 | I24: =I19+I21+I23 -> 28.348044 | J24: =J19+J21+J23 -> 37.17424 | ... Q24: =Q19+Q21+Q23 -> 68.931652
A25: 土地 | B25: $B | C25: =C8*Inputs!D16/1000 -> 0.02 | D25: =D8*Inputs!E16/1000 -> 0.02 | E25: =E8*Inputs!F16/1000 -> 0.02 | F25: =F8*Inputs!D16/1000 -> 0.02 | G25: =G8*Inputs!E16/1000 -> 0.02 | H25: =H8*Inputs!F16/1000 -> 0.02 | I25: =I8*Inputs!D16/1000 -> 0.02 | J25: =J8*Inputs!E16/1000 -> 0.02 | K25: =K8*Inputs!F16/1000 -> 0.02 | L25: =L8*Inputs!D16/1000 -> 0.02 | M25: =M8*Inputs!E16/1000 -> 0.02 | N25: =N8*Inputs!F16/1000 -> 0.02 | O25: =O8*Inputs!D16/1000 -> 0.02 | P25: =P8*Inputs!E16/1000 -> 0.02 | Q25: =Q8*Inputs!F16/1000 -> 0.02
A26: 建物與基地 | B26: $B | C26: =C8*Inputs!D17/1000 -> 3 | D26: =D8*Inputs!E17/1000 -> 3.6 | E26: =E8*Inputs!F17/1000 -> 4.5 | F26: =F8*Inputs!D17/1000 -> 3 | G26: =G8*Inputs!E17/1000 -> 3.6 | H26: =H8*Inputs!F17/1000 -> 4.5 | I26: =I8*Inputs!D17/1000 -> 3 | J26: =J8*Inputs!E17/1000 -> 3.6 | K26: =K8*Inputs!F17/1000 -> 4.5 | L26: =L8*Inputs!D17/1000 -> 3 | M26: =M8*Inputs!E17/1000 -> 3.6 | N26: =N8*Inputs!F17/1000 -> 4.5 | O26: =O8*Inputs!D17/1000 -> 3 | P26: =P8*Inputs!E17/1000 -> 3.6 | Q26: =Q8*Inputs!F17/1000 -> 4.5
A27: 電力設施 | B27: $B | C27: =C8*Inputs!D18/1000 -> 3.8 | D27: =D8*Inputs!E18/1000 -> 4.5 | E27: =E8*Inputs!F18/1000 -> 5.5 | F27: =F8*Inputs!D18/1000 -> 3.8 | G27: =G8*Inputs!E18/1000 -> 4.5 | H27: =H8*Inputs!F18/1000 -> 5.5 | I27: =I8*Inputs!D18/1000 -> 3.8 | J27: =J8*Inputs!E18/1000 -> 4.5 | K27: =K8*Inputs!F18/1000 -> 5.5 | L27: =L8*Inputs!D18/1000 -> 3.8 | M27: =M8*Inputs!E18/1000 -> 4.5 | N27: =N8*Inputs!F18/1000 -> 5.5 | O27: =O8*Inputs!D18/1000 -> 3.8 | P27: =P8*Inputs!E18/1000 -> 4.5 | Q27: =Q8*Inputs!F18/1000 -> 5.5
A28: 機械與散熱 | B28: $B | C28: =C8*Inputs!D19/1000 -> 2 | D28: =D8*Inputs!E19/1000 -> 2.5 | E28: =E8*Inputs!F19/1000 -> 3.2 | F28: =F8*Inputs!D19/1000 -> 2 | G28: =G8*Inputs!E19/1000 -> 2.5 | H28: =H8*Inputs!F19/1000 -> 3.2 | I28: =I8*Inputs!D19/1000 -> 2 | J28: =J8*Inputs!E19/1000 -> 2.5 | K28: =K8*Inputs!F19/1000 -> 3.2 | L28: =L8*Inputs!D19/1000 -> 2 | M28: =M8*Inputs!E19/1000 -> 2.5 | N28: =N8*Inputs!F19/1000 -> 3.2 | O28: =O8*Inputs!D19/1000 -> 2 | P28: =P8*Inputs!E19/1000 -> 2.5 | Q28: =Q8*Inputs!F19/1000 -> 3.2
A29: 光纖與保全 | B29: $B | C29: =C8*Inputs!D20/1000 -> 0.3 | D29: =D8*Inputs!E20/1000 -> 0.4 | E29: =E8*Inputs!F20/1000 -> 0.5 | F29: =F8*Inputs!D20/1000 -> 0.3 | G29: =G8*Inputs!E20/1000 -> 0.4 | H29: =H8*Inputs!F20/1000 -> 0.5 | I29: =I8*Inputs!D20/1000 -> 0.3 | J29: =J8*Inputs!E20/1000 -> 0.4 | K29: =K8*Inputs!F20/1000 -> 0.5 | L29: =L8*Inputs!D20/1000 -> 0.3 | M29: =M8*Inputs!E20/1000 -> 0.4 | N29: =N8*Inputs!F20/1000 -> 0.5 | O29: =O8*Inputs!D20/1000 -> 0.3 | P29: =P8*Inputs!E20/1000 -> 0.4 | Q29: =Q8*Inputs!F20/1000 -> 0.5
A30: 設計、管理與預備費率 | B30: % | C30: =Inputs!D21 -> 0.12 | D30: =Inputs!E21 -> 0.15 | E30: =Inputs!F21 -> 0.18 | F30: =Inputs!D21 -> 0.12 | G30: =Inputs!E21 -> 0.15 | H30: =Inputs!F21 -> 0.18 | I30: =Inputs!D21 -> 0.12 | J30: =Inputs!E21 -> 0.15 | K30: =Inputs!F21 -> 0.18 | L30: =Inputs!D21 -> 0.12 | M30: =Inputs!E21 -> 0.15 | N30: =Inputs!F21 -> 0.18 | O30: =Inputs!D21 -> 0.12 | P30: =Inputs!E21 -> 0.15 | Q30: =Inputs!F21 -> 0.18
A31: 設計、管理與預備費 | B31: $B | C31: =(C26+C27+C28+C29)*C30 -> 1.092 | D31: =(D26+D27+D28+D29)*D30 -> 1.65 | E31: =(E26+E27+E28+E29)*E30 -> 2.466 | F31: =(F26+F27+F28+F29)*F30 -> 1.092 | G31: =(G26+G27+G28+G29)*G30 -> 1.65 | H31: =(H26+H27+H28+H29)*H30 -> 2.466 | I31: =(I26+I27+I28+I29)*I30 -> 1.092 | J31: =(J26+J27+J28+J29)*J30 -> 1.65 | ... Q31: =(Q26+Q27+Q28+Q29)*Q30 -> 2.466
A32: 廠房小計 | B32: $B | C32: =C25+C26+C27+C28+C29+C31 -> 10.212 | D32: =D25+D26+D27+D28+D29+D31 -> 12.67 | E32: =E25+E26+E27+E28+E29+E31 -> 16.186 | F32: =F25+F26+F27+F28+F29+F31 -> 10.212 | G32: =G25+G26+G27+G28+G29+G31 -> 12.67 | H32: =H25+H26+H27+H28+H29+H31 -> 16.186 | I32: =I25+I26+I27+I28+I29+I31 -> 10.212 | J32: =J25+J26+J27+J28+J29+J31 -> 12.67 | ... Q32: =Q25+Q26+Q27+Q28+Q29+Q31 -> 16.186
A33: 每 GW 總資本支出 | B33: $B | C33: =C24+C32 -> 31.632269 | D33: =D24+D32 -> 40.180214 | E33: =E24+E32 -> 50.306743 | F33: =F24+F32 -> 31.168282 | G33: =G24+G32 -> 37.053896 | H33: =H24+H32 -> 44.260738 | I33: =I24+I32 -> 38.560044 | J33: =J24+J32 -> 49.84424 | ... Q33: =Q24+Q32 -> 85.117652
A34: 每 GPU 資本支出（含廠房） | B34: $K | C34: =C33*1000000/C14 -> 44.05314 | D34: =D33*1000000/D14 -> 55.95756 | E34: =E33*1000000/E14 -> 70.060419 | F34: =F33*1000000/F14 -> 61.177614 | G34: =G33*1000000/G14 -> 72.729995 | H34: =H33*1000000/H14 -> 86.875702 | I34: =I33*1000000/I14 -> 79.7552 | J34: =J33*1000000/J14 -> 103.09473 | ... Q34: =Q33*1000000/Q14 -> 385.58043
A35: 每 MW IT 資本支出 | B35: $M | C35: =C33*1000/C8 -> 31.632269 | D35: =D33*1000/D8 -> 40.180214 | E35: =E33*1000/E8 -> 50.306743 | F35: =F33*1000/F8 -> 31.168282 | G35: =G33*1000/G8 -> 37.053896 | H35: =H33*1000/H8 -> 44.260738 | I35: =I33*1000/I8 -> 38.560044 | J35: =J33*1000/J8 -> 49.84424 | ... Q35: =Q33*1000/Q8 -> 85.117652
A36: 每 MW IT 廠房資本支出 | B36: $M | C36: =C32*1000/C8 -> 10.212 | D36: =D32*1000/D8 -> 12.67 | E36: =E32*1000/E8 -> 16.186 | F36: =F32*1000/F8 -> 10.212 | G36: =G32*1000/G8 -> 12.67 | H36: =H32*1000/H8 -> 16.186 | I36: =I32*1000/I8 -> 10.212 | J36: =J32*1000/J8 -> 12.67 | ... Q36: =Q32*1000/Q8 -> 16.186
A37: C. 年持有成本 — 會計口徑（$B／GW／年）
A38: IT 折舊年限 | B38: 年 | C38: =Inputs!D23 -> 6 | D38: =Inputs!E23 -> 6 | E38: =Inputs!F23 -> 4 | F38: =Inputs!D23 -> 6 | G38: =Inputs!E23 -> 6 | H38: =Inputs!F23 -> 4 | I38: =Inputs!D23 -> 6 | J38: =Inputs!E23 -> 6 | K38: =Inputs!F23 -> 4 | L38: =Inputs!D23 -> 6 | M38: =Inputs!E23 -> 6 | N38: =Inputs!F23 -> 4 | O38: =Inputs!D23 -> 6 | P38: =Inputs!E23 -> 6 | Q38: =Inputs!F23 -> 4
A39: IT 折舊 | B39: $B | C39: =C24/C38 -> 3.5700449 | D39: =D24/D38 -> 4.5850357 | E39: =E24/E38 -> 8.5301859 | F39: =F24/F38 -> 3.4927136 | G39: =G24/G38 -> 4.0639827 | H39: =H24/H38 -> 7.0186844 | I39: =I24/I38 -> 4.724674 | J39: =J24/J38 -> 6.1957067 | ... Q39: =Q24/Q38 -> 17.232913
A40: 廠房折舊（土地不折舊） | B40: $B | C40: =(C26/Inputs!D24+C27/Inputs!D25+C28/Inputs!D26+C29/Inputs!D27)*(1+C30) -> 0.50773333 | D40: =(D26/Inputs!E24+D27/Inputs!E25+D28/Inputs!E26+D29/Inputs!E27)*(1+D30) -> 0.63441667 | E40: =(E26/Inputs!F24+E27/Inputs!F25+E28/Inputs!F26+E29/Inputs!F27)*(1+E30) -> 0.81223333 | F40: =(F26/Inputs!D24+F27/Inputs!D25+F28/Inputs!D26+F29/Inputs!D27)*(1+F30) -> 0.50773333 | G40: =(G26/Inputs!E24+G27/Inputs!E25+G28/Inputs!E26+G29/Inputs!E27)*(1+G30) -> 0.63441667 | H40: =(H26/Inputs!F24+H27/Inputs!F25+H28/Inputs!F26+H29/Inputs!F27)*(1+H30) -> 0.81223333 | I40: =(I26/Inputs!D24+I27/Inputs!D25+I28/Inputs!D26+I29/Inputs!D27)*(1+I30) -> 0.50773333 | J40: =(J26/Inputs!E24+J27/Inputs!E25+J28/Inputs!E26+J29/Inputs!E27)*(1+J30) -> 0.63441667 | K40: =(K26/Inputs!F24+K27/Inputs!F25+K28/Inputs!F26+K29/Inputs!F27)*(1+K30) -> 0.81223333 | L40: =(L26/Inputs!D24+L27/Inputs!D25+L28/Inputs!D26+L29/Inputs!D27)*(1+L30) -> 0.50773333 | M40: =(M26/Inputs!E24+M27/Inputs!E25+M28/Inputs!E26+M29/Inputs!E27)*(1+M30) -> 0.63441667 | N40: =(N26/Inputs!F24+N27/Inputs!F25+N28/Inputs!F26+N29/Inputs!F27)*(1+N30) -> 0.81223333 | O40: =(O26/Inputs!D24+O27/Inputs!D25+O28/Inputs!D26+O29/Inputs!D27)*(1+O30) -> 0.50773333 | P40: =(P26/Inputs!E24+P27/Inputs!E25+P28/Inputs!E26+P29/Inputs!E27)*(1+P30) -> 0.63441667 | Q40: =(Q26/Inputs!F24+Q27/Inputs!F25+Q28/Inputs!F26+Q29/Inputs!F27)*(1+Q30) -> 0.81223333
A41: 平均用電 ÷ 配電設計功率 | B41: % | C41: =Inputs!D10 -> 0.7 | D41: =Inputs!E10 -> 0.8 | E41: =Inputs!F10 -> 0.9 | F41: =Inputs!D10 -> 0.7 | G41: =Inputs!E10 -> 0.8 | H41: =Inputs!F10 -> 0.9 | I41: =Inputs!D10 -> 0.7 | J41: =Inputs!E10 -> 0.8 | K41: =Inputs!F10 -> 0.9 | L41: =Inputs!D10 -> 0.7 | M41: =Inputs!E10 -> 0.8 | N41: =Inputs!F10 -> 0.9 | O41: =Inputs!D10 -> 0.7 | P41: =Inputs!E10 -> 0.8 | Q41: =Inputs!F10 -> 0.9
A42: 電價 | B42: $/kWh | C42: =Inputs!D11 -> 0.06 | D42: =Inputs!E11 -> 0.08 | E42: =Inputs!F11 -> 0.1 | F42: =Inputs!D11 -> 0.06 | G42: =Inputs!E11 -> 0.08 | H42: =Inputs!F11 -> 0.1 | I42: =Inputs!D11 -> 0.06 | J42: =Inputs!E11 -> 0.08 | K42: =Inputs!F11 -> 0.1 | L42: =Inputs!D11 -> 0.06 | M42: =Inputs!E11 -> 0.08 | N42: =Inputs!F11 -> 0.1 | O42: =Inputs!D11 -> 0.06 | P42: =Inputs!E11 -> 0.08 | Q42: =Inputs!F11 -> 0.1
A43: 電費 | B43: $B | C43: =C8*1000*C41*C15*8760*C42/1000000000 -> 0.404712 | D43: =D8*1000*D41*D15*8760*D42/1000000000 -> 0.672768 | E43: =E8*1000*E41*E15*8760*E42/1000000000 -> 1.02492 | F43: =F8*1000*F41*F15*8760*F42/1000000000 -> 0.404712 | G43: =G8*1000*G41*G15*8760*G42/1000000000 -> 0.672768 | H43: =H8*1000*H41*H15*8760*H42/1000000000 -> 1.02492 | I43: =I8*1000*I41*I15*8760*I42/1000000000 -> 0.404712 | J43: =J8*1000*J41*J15*8760*J42/1000000000 -> 0.672768 | ... Q43: =Q8*1000*Q41*Q15*8760*Q42/1000000000 -> 1.02492
A44: IT 維護 | B44: $B | C44: =C24*Inputs!D30 -> 0.42840539 | D44: =D24*Inputs!E30 -> 0.82530642 | E44: =E24*Inputs!F30 -> 1.3648297 | F44: =F24*Inputs!D30 -> 0.41912563 | G44: =G24*Inputs!E30 -> 0.73151688 | H44: =H24*Inputs!F30 -> 1.1229895 | I44: =I24*Inputs!D30 -> 0.56696088 | J44: =J24*Inputs!E30 -> 1.1152272 | K44: =K24*Inputs!F30 -> 2.0232564 | L44: =L24*Inputs!D30 -> 0.57186686 | M44: =M24*Inputs!E30 -> 1.047361 | N44: =N24*Inputs!F30 -> 1.705503 | O44: =O24*Inputs!D30 -> 0.75464071 | P44: =P24*Inputs!E30 -> 1.5816881 | Q44: =Q24*Inputs!F30 -> 2.7572661
A45: 廠房維護 | B45: $B | C45: =C32*Inputs!D31 -> 0.15318 | D45: =D32*Inputs!E31 -> 0.2534 | E45: =E32*Inputs!F31 -> 0.40465 | F45: =F32*Inputs!D31 -> 0.15318 | G45: =G32*Inputs!E31 -> 0.2534 | H45: =H32*Inputs!F31 -> 0.40465 | I45: =I32*Inputs!D31 -> 0.15318 | J45: =J32*Inputs!E31 -> 0.2534 | K45: =K32*Inputs!F31 -> 0.40465 | L45: =L32*Inputs!D31 -> 0.15318 | M45: =M32*Inputs!E31 -> 0.2534 | N45: =N32*Inputs!F31 -> 0.40465 | O45: =O32*Inputs!D31 -> 0.15318 | P45: =P32*Inputs!E31 -> 0.2534 | Q45: =Q32*Inputs!F31 -> 0.40465
A46: 人員、軟體、水與耗材 | B46: $B | C46: =(Inputs!D32*C8/1000+Inputs!D33*C8/1000+Inputs!D34*C8)/1000 -> 0.24 | D46: =(Inputs!E32*D8/1000+Inputs!E33*D8/1000+Inputs!E34*D8)/1000 -> 0.325 | E46: =(Inputs!F32*E8/1000+Inputs!F33*E8/1000+Inputs!F34*E8)/1000 -> 0.41 | F46: =(Inputs!D32*F8/1000+Inputs!D33*F8/1000+Inputs!D34*F8)/1000 -> 0.24 | G46: =(Inputs!E32*G8/1000+Inputs!E33*G8/1000+Inputs!E34*G8)/1000 -> 0.325 | H46: =(Inputs!F32*H8/1000+Inputs!F33*H8/1000+Inputs!F34*H8)/1000 -> 0.41 | I46: =(Inputs!D32*I8/1000+Inputs!D33*I8/1000+Inputs!D34*I8)/1000 -> 0.24 | J46: =(Inputs!E32*J8/1000+Inputs!E33*J8/1000+Inputs!E34*J8)/1000 -> 0.325 | K46: =(Inputs!F32*K8/1000+Inputs!F33*K8/1000+Inputs!F34*K8)/1000 -> 0.41 | L46: =(Inputs!D32*L8/1000+Inputs!D33*L8/1000+Inputs!D34*L8)/1000 -> 0.24 | M46: =(Inputs!E32*M8/1000+Inputs!E33*M8/1000+Inputs!E34*M8)/1000 -> 0.325 | N46: =(Inputs!F32*N8/1000+Inputs!F33*N8/1000+Inputs!F34*N8)/1000 -> 0.41 | O46: =(Inputs!D32*O8/1000+Inputs!D33*O8/1000+Inputs!D34*O8)/1000 -> 0.24 | P46: =(Inputs!E32*P8/1000+Inputs!E33*P8/1000+Inputs!E34*P8)/1000 -> 0.325 | Q46: =(Inputs!F32*Q8/1000+Inputs!F33*Q8/1000+Inputs!F34*Q8)/1000 -> 0.41
A47: 財產稅與保險 | B47: $B | C47: =C33*Inputs!D35 -> 0.094896808 | D47: =D33*Inputs!E35 -> 0.20090107 | E47: =E33*Inputs!F35 -> 0.40245395 | F47: =F33*Inputs!D35 -> 0.093504845 | G47: =G33*Inputs!E35 -> 0.18526948 | H47: =H33*Inputs!F35 -> 0.3540859 | I47: =I33*Inputs!D35 -> 0.11568013 | J47: =J33*Inputs!E35 -> 0.2492212 | K47: =K33*Inputs!F35 -> 0.53413927 | L47: =L33*Inputs!D35 -> 0.11641603 | M47: =M33*Inputs!E35 -> 0.23791016 | N47: =N33*Inputs!F35 -> 0.4705886 | O47: =O33*Inputs!D35 -> 0.14383211 | P47: =P33*Inputs!E35 -> 0.32696468 | Q47: =Q33*Inputs!F35 -> 0.68094121
A48: 營運費用小計（不含折舊） | B48: $B | C48: =C43+C44+C45+C46+C47 -> 1.3211942 | D48: =D43+D44+D45+D46+D47 -> 2.2773755 | E48: =E43+E44+E45+E46+E47 -> 3.6068537 | F48: =F43+F44+F45+F46+F47 -> 1.3105225 | G48: =G43+G44+G45+G46+G47 -> 2.1679544 | H48: =H43+H44+H45+H46+H47 -> 3.3166454 | I48: =I43+I44+I45+I46+I47 -> 1.480533 | J48: =J43+J44+J45+J46+J47 -> 2.6156164 | ... Q48: =Q43+Q44+Q45+Q46+Q47 -> 5.2777773
A49: 年持有成本 — 會計口徑 | B49: $B | C49: =C39+C40+C48 -> 5.3989724 | D49: =D39+D40+D48 -> 7.4968278 | E49: =E39+E40+E48 -> 12.949273 | F49: =F39+F40+F48 -> 5.3109694 | G49: =G39+G40+G48 -> 6.8663537 | H49: =H39+H40+H48 -> 11.147563 | I49: =I39+I40+I48 -> 6.7129403 | J49: =J39+J40+J48 -> 9.4457397 | ... Q49: =Q39+Q40+Q48 -> 23.322924
A50: D. 年持有成本 — 經濟口徑（資本回收年金）
A51: WACC | B51: % | C51: =Inputs!D28 -> 0.08 | D51: =Inputs!E28 -> 0.1 | E51: =Inputs!F28 -> 0.13 | F51: =Inputs!D28 -> 0.08 | G51: =Inputs!E28 -> 0.1 | H51: =Inputs!F28 -> 0.13 | I51: =Inputs!D28 -> 0.08 | J51: =Inputs!E28 -> 0.1 | K51: =Inputs!F28 -> 0.13 | L51: =Inputs!D28 -> 0.08 | M51: =Inputs!E28 -> 0.1 | N51: =Inputs!F28 -> 0.13 | O51: =Inputs!D28 -> 0.08 | P51: =Inputs!E28 -> 0.1 | Q51: =Inputs!F28 -> 0.13
A52: IT 資本回收係數 | B52: x | C52: =C51/(1-(1+C51)^(-C38)) -> 0.21631539 | D52: =D51/(1-(1+D51)^(-D38)) -> 0.22960738 | E52: =E51/(1-(1+E51)^(-E38)) -> 0.3361942 | F52: =F51/(1-(1+F51)^(-F38)) -> 0.21631539 | G52: =G51/(1-(1+G51)^(-G38)) -> 0.22960738 | H52: =H51/(1-(1+H51)^(-H38)) -> 0.3361942 | I52: =I51/(1-(1+I51)^(-I38)) -> 0.21631539 | J52: =J51/(1-(1+J51)^(-J38)) -> 0.22960738 | ... Q52: =Q51/(1-(1+Q51)^(-Q38)) -> 0.3361942
A53: IT 資本回收 | B53: $B | C53: =C24*C52 -> 4.6335338 | D53: =D24*D52 -> 6.3165482 | E53: =E24*E52 -> 11.471196 | F53: =F24*F52 -> 4.5331661 | G53: =G24*G52 -> 5.5987225 | H53: =H24*H52 -> 9.4385639 | I53: =I24*I52 -> 6.1321181 | J53: =J24*J52 -> 8.5354799 | ... Q53: =Q24*Q52 -> 23.174421
A54: 廠房資本回收（土地按 WACC 計機會成本） | B54: $B | C54: =(C26*C51/(1-(1+C51)^(-Inputs!D24))+C27*C51/(1-(1+C51)^(-Inputs!D25))+C28*C51/(1-(1+C51)^(-Inputs!D26))+C29*C51/(1-(1+C51)^(-Inputs!D27)))*(1+C30)+C25*C51 -> 1.0453153 | D54: =(D26*D51/(1-(1+D51)^(-Inputs!E24))+D27*D51/(1-(1+D51)^(-Inputs!E25))+D28*D51/(1-(1+D51)^(-Inputs!E26))+D29*D51/(1-(1+D51)^(-Inputs!E27)))*(1+D30)+D25*D51 -> 1.5018716 | E54: =(E26*E51/(1-(1+E51)^(-Inputs!F24))+E27*E51/(1-(1+E51)^(-Inputs!F25))+E28*E51/(1-(1+E51)^(-Inputs!F26))+E29*E51/(1-(1+E51)^(-Inputs!F27)))*(1+E30)+E25*E51 -> 2.3279224 | F54: =(F26*F51/(1-(1+F51)^(-Inputs!D24))+F27*F51/(1-(1+F51)^(-Inputs!D25))+F28*F51/(1-(1+F51)^(-Inputs!D26))+F29*F51/(1-(1+F51)^(-Inputs!D27)))*(1+F30)+F25*F51 -> 1.0453153 | G54: =(G26*G51/(1-(1+G51)^(-Inputs!E24))+G27*G51/(1-(1+G51)^(-Inputs!E25))+G28*G51/(1-(1+G51)^(-Inputs!E26))+G29*G51/(1-(1+G51)^(-Inputs!E27)))*(1+G30)+G25*G51 -> 1.5018716 | H54: =(H26*H51/(1-(1+H51)^(-Inputs!F24))+H27*H51/(1-(1+H51)^(-Inputs!F25))+H28*H51/(1-(1+H51)^(-Inputs!F26))+H29*H51/(1-(1+H51)^(-Inputs!F27)))*(1+H30)+H25*H51 -> 2.3279224 | I54: =(I26*I51/(1-(1+I51)^(-Inputs!D24))+I27*I51/(1-(1+I51)^(-Inputs!D25))+I28*I51/(1-(1+I51)^(-Inputs!D26))+I29*I51/(1-(1+I51)^(-Inputs!D27)))*(1+I30)+I25*I51 -> 1.0453153 | J54: =(J26*J51/(1-(1+J51)^(-Inputs!E24))+J27*J51/(1-(1+J51)^(-Inputs!E25))+J28*J51/(1-(1+J51)^(-Inputs!E26))+J29*J51/(1-(1+J51)^(-Inputs!E27)))*(1+J30)+J25*J51 -> 1.5018716 | K54: =(K26*K51/(1-(1+K51)^(-Inputs!F24))+K27*K51/(1-(1+K51)^(-Inputs!F25))+K28*K51/(1-(1+K51)^(-Inputs!F26))+K29*K51/(1-(1+K51)^(-Inputs!F27)))*(1+K30)+K25*K51 -> 2.3279224 | L54: =(L26*L51/(1-(1+L51)^(-Inputs!D24))+L27*L51/(1-(1+L51)^(-Inputs!D25))+L28*L51/(1-(1+L51)^(-Inputs!D26))+L29*L51/(1-(1+L51)^(-Inputs!D27)))*(1+L30)+L25*L51 -> 1.0453153 | M54: =(M26*M51/(1-(1+M51)^(-Inputs!E24))+M27*M51/(1-(1+M51)^(-Inputs!E25))+M28*M51/(1-(1+M51)^(-Inputs!E26))+M29*M51/(1-(1+M51)^(-Inputs!E27)))*(1+M30)+M25*M51 -> 1.5018716 | N54: =(N26*N51/(1-(1+N51)^(-Inputs!F24))+N27*N51/(1-(1+N51)^(-Inputs!F25))+N28*N51/(1-(1+N51)^(-Inputs!F26))+N29*N51/(1-(1+N51)^(-Inputs!F27)))*(1+N30)+N25*N51 -> 2.3279224 | O54: =(O26*O51/(1-(1+O51)^(-Inputs!D24))+O27*O51/(1-(1+O51)^(-Inputs!D25))+O28*O51/(1-(1+O51)^(-Inputs!D26))+O29*O51/(1-(1+O51)^(-Inputs!D27)))*(1+O30)+O25*O51 -> 1.0453153 | P54: =(P26*P51/(1-(1+P51)^(-Inputs!E24))+P27*P51/(1-(1+P51)^(-Inputs!E25))+P28*P51/(1-(1+P51)^(-Inputs!E26))+P29*P51/(1-(1+P51)^(-Inputs!E27)))*(1+P30)+P25*P51 -> 1.5018716 | Q54: =(Q26*Q51/(1-(1+Q51)^(-Inputs!F24))+Q27*Q51/(1-(1+Q51)^(-Inputs!F25))+Q28*Q51/(1-(1+Q51)^(-Inputs!F26))+Q29*Q51/(1-(1+Q51)^(-Inputs!F27)))*(1+Q30)+Q25*Q51 -> 2.3279224
A55: 年持有成本 — 經濟口徑 | B55: $B | C55: =C53+C54+C48 -> 7.0000433 | D55: =D53+D54+D48 -> 10.095795 | E55: =E53+E54+E48 -> 17.405972 | F55: =F53+F54+F48 -> 6.8890039 | G55: =G53+G54+G48 -> 9.2685485 | H55: =H53+H54+H48 -> 15.083132 | I55: =I53+I54+I48 -> 8.6579664 | J55: =J53+J54+J48 -> 12.652968 | ... Q55: =Q53+Q54+Q48 -> 30.780121
A56: E. 單位成本與結構
A57: 每 GPU 小時持有成本 — 會計 | B57: $/GPU-hr | C57: =C49*1000000000/(C14*8760) -> 0.85832849 | D57: =D49*1000000000/(D14*8760) -> 1.1918455 | E57: =E49*1000000000/(E14*8760) -> 2.058675 | F57: =F49*1000000000/(F14*8760) -> 1.1900066 | G57: =G49*1000000000/(G14*8760) -> 1.538515 | H57: =H49*1000000000/(H14*8760) -> 2.4977877 | I57: =I49*1000000000/(I14*8760) -> 1.5850033 | J57: =J49*1000000000/(J14*8760) -> 2.230249 | ... Q57: =Q49*1000000000/(Q14*8760) -> 12.060748
A58: 每 GPU 小時持有成本 — 經濟 | B58: $/GPU-hr | C58: =C55*1000000000/(C14*8760) -> 1.1128667 | D58: =D55*1000000000/(D14*8760) -> 1.6050293 | E58: =E55*1000000000/(E14*8760) -> 2.767201 | F58: =F55*1000000000/(F14*8760) -> 1.5435902 | G58: =G55*1000000000/(G14*8760) -> 2.0767647 | H58: =H55*1000000000/(H14*8760) -> 3.379614 | I58: =I55*1000000000/(I14*8760) -> 2.0442466 | J58: =J55*1000000000/(J14*8760) -> 2.9875129 | ... Q58: =Q55*1000000000/(Q14*8760) -> 15.917013
A59: 每架小時持有成本 — 經濟 | B59: $/rack-hr | C59: =C55*1000000000/(C12*8760) -> 35.611734 | D59: =D55*1000000000/(D12*8760) -> 51.360936 | E59: =E55*1000000000/(E12*8760) -> 88.550431 | F59: =F55*1000000000/(F12*8760) -> 111.13849 | G59: =G55*1000000000/(G12*8760) -> 149.52706 | H59: =H55*1000000000/(H12*8760) -> 243.33221 | I59: =I55*1000000000/(I12*8760) -> 147.18575 | J59: =J55*1000000000/(J12*8760) -> 215.10093 | ... Q59: =Q55*1000000000/(Q12*8760) -> 2292.0499
A60: 年用電（設施端） | B60: TWh | C60: =C8*C41*C15*8760/1000000 -> 6.7452 | D60: =D8*D41*D15*8760/1000000 -> 8.4096 | E60: =E8*E41*E15*8760/1000000 -> 10.2492 | F60: =F8*F41*F15*8760/1000000 -> 6.7452 | G60: =G8*G41*G15*8760/1000000 -> 8.4096 | H60: =H8*H41*H15*8760/1000000 -> 10.2492 | I60: =I8*I41*I15*8760/1000000 -> 6.7452 | J60: =J8*J41*J15*8760/1000000 -> 8.4096 | ... Q60: =Q8*Q41*Q15*8760/1000000 -> 10.2492
A61: 資本回收占經濟口徑 | B61: % | C61: =(C53+C54)/C55 -> 0.81125914 | D61: =(D53+D54)/D55 -> 0.77442337 | E61: =(E53+E54)/E55 -> 0.79278068 | F61: =(F53+F54)/F55 -> 0.80976604 | G61: =(G53+G54)/G55 -> 0.76609559 | H61: =(H53+H54)/H55 -> 0.78010897 | I61: =(I53+I54)/I55 -> 0.8289976 | J61: =(J53+J54)/J55 -> 0.7932804 | ... Q61: =(Q53+Q54)/Q55 -> 0.82853293
A62: 電費占經濟口徑 | B62: % | C62: =C43/C55 -> 0.057815642 | D62: =D43/D55 -> 0.066638435 | E62: =E43/E55 -> 0.058883238 | F62: =F43/F55 -> 0.058747535 | G62: =G43/G55 -> 0.072586123 | H62: =H43/H55 -> 0.067951406 | I62: =I43/I55 -> 0.046744464 | J62: =J43/J55 -> 0.053170766 | ... Q62: =Q43/Q55 -> 0.033298115

Sheet Train_In
A1: Train_In — 訓練輸入（藍字＝輸入；Analogy／Assumed 一律附區間）
A2: Block 3 命題：各層級代表模型從預訓練到可發布、以及含研發實驗的整個計畫，需要多少 GPU 小時、美元與 1 GW 年。決策 J7–J14 見 README
A4: 全域設定 | B4: 單位 | C4: 值 | D4: 標記 | H4: 說明
A5: 訓練精度（MFU 分母） | C5: FP8 dense | D5: Decision | H5: J7：基準 FP8（DeepSeek V4 以 FP8 計算＋FP4 QAT，S35）；NVFP4 預訓練列於 Tech_Registry T07
A6: 預訓練 MFU 基準（FP8 分母；GB200／GB300） | B6: % | C6: 0.25 | D6: Analogy | H6: DeepSeek V3 推導 H800 FP8 口徑約 20%（Checks）；Llama 3 405B BF16 口徑 38–43%＝FP8 口徑約 19–22%（S37，待查）；NVL72 域大、EP 通訊較佳取 0.25。區間 0.15–0.40
A7: goodput（扣除故障、重啟、checkpoint 的有效時間比） | B7: % | C7: 0.9 | D7: Analogy | H7: Meta Llama 3：有效訓練時間 >90%（S37，待查）；區間 0.80–0.95
A8: SFT MFU 係數（× 預訓練 MFU） | B8: x | C8: 0.8 | D8: Assumed | H8: 較短批次、較多變長序列；區間 0.6–1.0
A9: RL trainer MFU 係數（× 預訓練 MFU） | B9: x | C9: 0.6 | D9: Assumed | H9: 長序列、小批次、與 rollout 交替；區間 0.4–0.9。蒸餾學生更新沿用
A10: 參考模型前向（KL 懲罰；0＝無、1＝有） | B10: 選擇 | C10: 0 | D10: Assumed | H10: GRPO 原版含 KL；DAPO 等後續做法移除。取 0，區間 0–1
A11: rollout 效率（長尾等待、權重同步、閒置） | B11: % | C11: 0.85 | D11: Analogy | H11: v5.6：非同步 RL 已屬主流（Tech_Registry T10）。各家報告非同步增益 1.5–2.7 倍（S45–S49）；同步約 0.4–0.5 → 非同步 0.85，區間 0.7–0.95。v5.5 為 0.6（混合）
A12: GRPO 每題取樣數（共用 prompt，prefill 只算一次） | B12: 個 | C12: 16 | D12: Analogy | H12: DeepSeekMath／R1 GRPO 群組 16；區間 8–64
A13: 研發倍數（研發總 GPU 小時 ÷ 最終訓練） | B13: x | C13: 8 | D13: Analogy | H13: J10。Epoch：最終訓練占研發支出 OpenAI 9.6%、MiniMax 22.6%、Z.ai 12.3%（S38）＝4.4–10.4 倍；取 8。以支出為口徑，已含實驗的低利用率，故乘在 GPU 小時上
A14: 研發歸屬 | C14: 家族合計乘一次，依最終訓練 GPU 小時比例分攤 | D14: Decision | H14: J10。比例分攤下，各層級分得＝該層級最終訓練 × 倍數；Training J 節另列家族合計
A15: 合成資料生成層級（1 Luna／2 Sol／3 Astra） | B15: 選擇 | C15: 3 | D15: Assumed | H15: 以頂層模型生成；區間 2–3
A16: 下游預設訓練世代（世代索引） | B16: 索引 | C16: 4 | D16: Decision | E16: =INDEX(Spec_Rack!$C$4:$G$4,$C$16) -> VR200 NVL72 | H16: J13：Andy 2026-09-30 決定 VR200（索引 4）；具名範圍 IF_TrainGenDefault
A17: 並列訓練世代（世代索引） | B17: 索引 | C17: 3 | D17: Decision | E17: =INDEX(Spec_Rack!$C$4:$G$4,$C$17) -> GB300 NVL72 | H17: J13：GB300（索引 3）並列；具名範圍 IF_TrainGenAlt
A19: 各世代
A20: 世代 | C20: =Spec_Rack!C4 -> Hopper H100 | D20: =Spec_Rack!D4 -> GB200 NVL72 | E20: =Spec_Rack!E4 -> GB300 NVL72 | F20: =Spec_Rack!F4 -> VR200 NVL72 | G20: =Spec_Rack!G4 -> Rubin Ultra NVL576
A21: 預訓練 MFU 世代倍數 | B21: x | C21: 0.8 | D21: 1 | E21: 1 | F21: 0.9 | G21: 0.9 | H21: Hopper 0.8 使 MFU＝20%，對應 V3 推導值 [Derived]；VR200 峰值 3.5 倍而 HBM 頻寬 2.75 倍，取 0.9 [Assumed，區間 0.7–1.1]；RU 同 VR [Assumed]
A23: 各層級
A24: 項目 | B24: 單位 | C24: =Arch!C4 -> Luna（低層） | D24: =Arch!D4 -> Sol（中層） | E24: =Arch!E4 -> Astra（頂層） | H24: 說明
A25: 預訓練 token | B25: T | C25: 32 | D25: 33 | E25: 60 | H25: Verified：V4-Flash 32T、V4-Pro 33T（S35）；Astra [Assumed，區間 30–100T；J8 以 Arch 一致為基準，前沿錨點見 Checks]
A26: 預訓練序列長（dense 注意力） | B26: tok | C26: 4096 | D26: 4096 | E26: 8192 | H26: V4：4K → 16K 漸增，其間以 dense 注意力訓練（S35）；多數 token 在 4K [Assumed，區間 4K–16K]
A27: 長上下文延伸 token | B27: T | C27: 1 | D27: 1 | E27: 2 | H27: Assumed，區間 0.3–3T（V4 未揭露）
A28: 長上下文延伸序列長（稀疏注意力路徑） | B28: tok | C28: 131072 | D28: 131072 | E28: 131072 | H28: Assumed
A29: SFT token | B29: T | C29: 0.05 | D29: 0.05 | E29: 0.1 | H29: Assumed，區間 0.01–0.3T
A30: SFT 序列長 | B30: tok | C30: 16384 | D30: 16384 | E30: 16384 | H30: Assumed
A31: 批次推論速度下限（rollout、合成、評測） | B31: tok/s | C31: 20 | D31: 20 | E31: 20 | H31: 取代互動 SLO；過低時長尾拉長牆鐘時間 [Assumed，區間 10–40]
A32: rollout 參考輸入（prompt＋工具結果） | B32: tok | C32: 4096 | D32: 8192 | E32: 16384 | H32: Assumed
A33: rollout 參考輸出（含思考） | B33: tok | C33: 8192 | D33: 16384 | E33: 32768 | H33: Assumed：推理與代理任務的長輸出
A34: RL rollout 輸出 token（含各領域專家） | B34: T | C34: 2.36 | D34: 2.36 | E34: 9.6 | H34: J9：由下而上輸入；基準值校到 VR200 上 RL ÷ 預訓練 GPU 小時約 Luna／Sol 0.3、Astra 1.0（結果見 Training rlH 列與 Checks）；v5.6 因 rollout 效率 0.6→0.85 由 2／2／8 上調為 2.36／2.36／9.6，GPU 小時不變（Andy 決定 (a)）。外部點：R1 約 5%、Grok 4 約 1 倍（S40、S42；GPU 小時或預算口徑）。區間：Luna／Sol 0.3–6T、Astra 2.5–25T
A35: On-policy 蒸餾：學生 rollout 輸出 token | B35: T | C35: 0.2 | D35: 0.2 | E35: 0.2 | H35: Assumed，區間 0.05–1T
A36: 蒸餾教師層級（1／2／3） | B36: 選擇 | C36: 1 | D36: 2 | E36: 3 | H36: V4 做法：同尺寸各領域專家為教師 [Interested-party，S35]
... A38: 評測 token | B38: T | C38: 0.02 | D38: 0.05 | E38: 0.1 | H38: Assumed
A40: 外部錨點（Checks 用；不進推導）
A41: DeepSeek V3 預訓練 token | B41: T | C41: 14.8 | H41: Interested-party：DeepSeek V3 技術報告（S44）
A42: DeepSeek V3 預訓練 H800 GPU 小時 | B42: M | C42: 2.664 | H42: S44（全部 2.788M，含長上下文 0.119M、後訓練 0.005M）
A43: DeepSeek V3 預訓練序列長 | B43: tok | C43: 4096 | H43: S44
A44: DeepSeek R1 RL GPU 小時 ÷ V3 預訓練 | B44: x | C44: 0.055 | H44: 147K ÷ 2.664M（S40，Lambert 轉述；GPU 小時口徑）
A45: Grok 4 RL ÷ 預訓練（宣稱） | B45: x | C45: 1 | H45: Interested-party：xAI『預訓練規模』（S42）；口徑不明
A46: 前沿預訓練錨點 低 | B46: FLOP | C46: 2e+26 | H46: Analogy：Epoch 估計（Grok-3 約 4.6e26，S39）；誤差 2–5 倍
A47: 前沿預訓練錨點 中 | B47: FLOP | C47: 5e+26 | H47: 同上
A48: 前沿預訓練錨點 高 | B48: FLOP | C48: 2e+27 | H48: 同上

Sheet Perf_Batch
A1: Perf_Batch — 批次推論引擎（RL rollout、蒸餾、合成資料、評測）：與 Perf 同一套公式，只換速度下限與參考任務
A2: C–Q 欄＝世代 × 層級基準；R、S 欄＝VR200 以 FP8 rollout 的情境（J12 替代）。綠字＝連結 Train_In（非情境改動）；黃底＝情境改動
A3: 欄位 | R3: 情境：FP8 rollout | S3: 情境：FP8 rollout
A4: 世代 | C4: =INDEX(Spec_Rack!$C$4:$G$4,C6) -> Hopper H100 | D4: =INDEX(Spec_Rack!$C$4:$G$4,D6) -> Hopper H100 | E4: =INDEX(Spec_Rack!$C$4:$G$4,E6) -> Hopper H100 | F4: =INDEX(Spec_Rack!$C$4:$G$4,F6) -> GB200 NVL72 | G4: =INDEX(Spec_Rack!$C$4:$G$4,G6) -> GB200 NVL72 | H4: =INDEX(Spec_Rack!$C$4:$G$4,H6) -> GB200 NVL72 | I4: =INDEX(Spec_Rack!$C$4:$G$4,I6) -> GB300 NVL72 | J4: =INDEX(Spec_Rack!$C$4:$G$4,J6) -> GB300 NVL72 | ... S4: =INDEX(Spec_Rack!$C$4:$G$4,S6) -> VR200 NVL72
A5: 層級 | C5: =INDEX(Arch!$C$4:$E$4,C7) -> Luna（低層） | D5: =INDEX(Arch!$C$4:$E$4,D7) -> Sol（中層） | E5: =INDEX(Arch!$C$4:$E$4,E7) -> Astra（頂層） | F5: =INDEX(Arch!$C$4:$E$4,F7) -> Luna（低層） | G5: =INDEX(Arch!$C$4:$E$4,G7) -> Sol（中層） | H5: =INDEX(Arch!$C$4:$E$4,H7) -> Astra（頂層） | I5: =INDEX(Arch!$C$4:$E$4,I7) -> Luna（低層） | J5: =INDEX(Arch!$C$4:$E$4,J7) -> Sol（中層） | ... S5: =INDEX(Arch!$C$4:$E$4,S7) -> Astra（頂層）
A6: 世代索引 | C6: 1 | D6: 1 | E6: 1 | F6: 2 | G6: 2 | H6: 2 | I6: 3 | J6: 3 | K6: 3 | L6: 4 | M6: 4 | N6: 4 | O6: 5 | P6: 5 | Q6: 5 | R6: 4 | S6: 4
A7: 層級索引 | C7: 1 | D7: 2 | E7: 3 | F7: 1 | G7: 2 | H7: 3 | I7: 1 | J7: 2 | K7: 3 | L7: 1 | M7: 2 | N7: 3 | O7: 1 | P7: 2 | Q7: 3 | R7: 2 | S7: 3
A9: 0. Tech_Registry 掛鉤（基準＝1；Registry 未啟用任何條目時與 v5.4 相同）
A10: FLOPs/token 倍數（H_FLOP） | B10: x | C10: =Tech_Registry!$E$22 -> 1 | D10: =Tech_Registry!$E$22 -> 1 | E10: =Tech_Registry!$E$22 -> 1 | F10: =Tech_Registry!$E$22 -> 1 | G10: =Tech_Registry!$E$22 -> 1 | H10: =Tech_Registry!$E$22 -> 1 | I10: =Tech_Registry!$E$22 -> 1 | J10: =Tech_Registry!$E$22 -> 1 | ... S10: =Tech_Registry!$E$22 -> 1
A11: KV bytes/token 倍數（H_KV） | B11: x | C11: =Tech_Registry!$E$23 -> 1 | D11: =Tech_Registry!$E$23 -> 1 | E11: =Tech_Registry!$E$23 -> 1 | F11: =Tech_Registry!$E$23 -> 1 | G11: =Tech_Registry!$E$23 -> 1 | H11: =Tech_Registry!$E$23 -> 1 | I11: =Tech_Registry!$E$23 -> 1 | J11: =Tech_Registry!$E$23 -> 1 | ... S11: =Tech_Registry!$E$23 -> 1
A12: 權重 bytes/param 倍數（H_WB） | B12: x | C12: =Tech_Registry!$E$24 -> 1 | D12: =Tech_Registry!$E$24 -> 1 | E12: =Tech_Registry!$E$24 -> 1 | F12: =Tech_Registry!$E$24 -> 1 | G12: =Tech_Registry!$E$24 -> 1 | H12: =Tech_Registry!$E$24 -> 1 | I12: =Tech_Registry!$E$24 -> 1 | J12: =Tech_Registry!$E$24 -> 1 | ... S12: =Tech_Registry!$E$24 -> 1
A13: A. 規格（連結 Spec_Rack、DC_Cost）
A14: 計算用峰值 | B14: PF/GPU | C14: =INDEX(Spec_Rack!$C$35:$G$35,C$6) -> 1.979 | D14: =INDEX(Spec_Rack!$C$35:$G$35,D$6) -> 1.979 | E14: =INDEX(Spec_Rack!$C$35:$G$35,E$6) -> 1.979 | F14: =INDEX(Spec_Rack!$C$35:$G$35,F$6) -> 10 | G14: =INDEX(Spec_Rack!$C$35:$G$35,G$6) -> 10 | H14: =INDEX(Spec_Rack!$C$35:$G$35,H$6) -> 10 | I14: =INDEX(Spec_Rack!$C$35:$G$35,I$6) -> 15 | J14: =INDEX(Spec_Rack!$C$35:$G$35,J$6) -> 15 | ... Q14: =INDEX(Spec_Rack!$C$35:$G$35,Q$6) -> 73 | R14: =Spec_Rack!$F$40 -> 17.5 | S14: =Spec_Rack!$F$40 -> 17.5
A15: HBM 容量 | B15: GB/GPU | C15: =INDEX(Spec_Rack!$C$25:$G$25,C$6) -> 80 | D15: =INDEX(Spec_Rack!$C$25:$G$25,D$6) -> 80 | E15: =INDEX(Spec_Rack!$C$25:$G$25,E$6) -> 80 | F15: =INDEX(Spec_Rack!$C$25:$G$25,F$6) -> 186 | G15: =INDEX(Spec_Rack!$C$25:$G$25,G$6) -> 186 | H15: =INDEX(Spec_Rack!$C$25:$G$25,H$6) -> 186 | I15: =INDEX(Spec_Rack!$C$25:$G$25,I$6) -> 288 | J15: =INDEX(Spec_Rack!$C$25:$G$25,J$6) -> 288 | ... S15: =INDEX(Spec_Rack!$C$25:$G$25,S$6) -> 288
A16: HBM 頻寬 | B16: TB/s/GPU | C16: =INDEX(Spec_Rack!$C$26:$G$26,C$6) -> 3.35 | D16: =INDEX(Spec_Rack!$C$26:$G$26,D$6) -> 3.35 | E16: =INDEX(Spec_Rack!$C$26:$G$26,E$6) -> 3.35 | F16: =INDEX(Spec_Rack!$C$26:$G$26,F$6) -> 8 | G16: =INDEX(Spec_Rack!$C$26:$G$26,G$6) -> 8 | H16: =INDEX(Spec_Rack!$C$26:$G$26,H$6) -> 8 | I16: =INDEX(Spec_Rack!$C$26:$G$26,I$6) -> 8 | J16: =INDEX(Spec_Rack!$C$26:$G$26,J$6) -> 8 | ... S16: =INDEX(Spec_Rack!$C$26:$G$26,S$6) -> 22
A17: EP 通訊頻寬（單向） | B17: TB/s/GPU | C17: =INDEX(Spec_Rack!$C$27:$G$27,C$6) -> 0.05 | D17: =INDEX(Spec_Rack!$C$27:$G$27,D$6) -> 0.05 | E17: =INDEX(Spec_Rack!$C$27:$G$27,E$6) -> 0.05 | F17: =INDEX(Spec_Rack!$C$27:$G$27,F$6) -> 0.9 | G17: =INDEX(Spec_Rack!$C$27:$G$27,G$6) -> 0.9 | H17: =INDEX(Spec_Rack!$C$27:$G$27,H$6) -> 0.9 | I17: =INDEX(Spec_Rack!$C$27:$G$27,I$6) -> 0.9 | J17: =INDEX(Spec_Rack!$C$27:$G$27,J$6) -> 0.9 | ... S17: =INDEX(Spec_Rack!$C$27:$G$27,S$6) -> 1.8
A18: decode EP 基準寬度 | B18: GPU | C18: =INDEX(Spec_Rack!$C$29:$G$29,C$6) -> 64 | D18: =INDEX(Spec_Rack!$C$29:$G$29,D$6) -> 64 | E18: =INDEX(Spec_Rack!$C$29:$G$29,E$6) -> 64 | F18: =INDEX(Spec_Rack!$C$29:$G$29,F$6) -> 32 | G18: =INDEX(Spec_Rack!$C$29:$G$29,G$6) -> 32 | H18: =INDEX(Spec_Rack!$C$29:$G$29,H$6) -> 32 | I18: =INDEX(Spec_Rack!$C$29:$G$29,I$6) -> 32 | J18: =INDEX(Spec_Rack!$C$29:$G$29,J$6) -> 32 | ... S18: =INDEX(Spec_Rack!$C$29:$G$29,S$6) -> 32
A19: 專家權重 bytes/param（含 H_WB） | B19: B | C19: =INDEX(Spec_Rack!$C$30:$G$30,C$6)*C12 -> 1 | D19: =INDEX(Spec_Rack!$C$30:$G$30,D$6)*D12 -> 1 | E19: =INDEX(Spec_Rack!$C$30:$G$30,E$6)*E12 -> 1 | F19: =INDEX(Spec_Rack!$C$30:$G$30,F$6)*F12 -> 0.5625 | G19: =INDEX(Spec_Rack!$C$30:$G$30,G$6)*G12 -> 0.5625 | H19: =INDEX(Spec_Rack!$C$30:$G$30,H$6)*H12 -> 0.5625 | I19: =INDEX(Spec_Rack!$C$30:$G$30,I$6)*I12 -> 0.5625 | J19: =INDEX(Spec_Rack!$C$30:$G$30,J$6)*J12 -> 0.5625 | ... Q19: =INDEX(Spec_Rack!$C$30:$G$30,Q$6)*Q12 -> 0.5625 | R19: 1 | S19: 1
A20: 非專家權重 bytes/param（含 H_WB） | B20: B | C20: =INDEX(Spec_Rack!$C$31:$G$31,C$6)*C12 -> 1 | D20: =INDEX(Spec_Rack!$C$31:$G$31,D$6)*D12 -> 1 | E20: =INDEX(Spec_Rack!$C$31:$G$31,E$6)*E12 -> 1 | F20: =INDEX(Spec_Rack!$C$31:$G$31,F$6)*F12 -> 1 | G20: =INDEX(Spec_Rack!$C$31:$G$31,G$6)*G12 -> 1 | H20: =INDEX(Spec_Rack!$C$31:$G$31,H$6)*H12 -> 1 | I20: =INDEX(Spec_Rack!$C$31:$G$31,I$6)*I12 -> 1 | J20: =INDEX(Spec_Rack!$C$31:$G$31,J$6)*J12 -> 1 | ... Q20: =INDEX(Spec_Rack!$C$31:$G$31,Q$6)*Q12 -> 1 | R20: 1 | S20: 1
A21: 每 prefill 實例 GPU 數 | B21: GPU | C21: =INDEX(Spec_Rack!$C$32:$G$32,C$6) -> 8 | D21: =INDEX(Spec_Rack!$C$32:$G$32,D$6) -> 8 | E21: =INDEX(Spec_Rack!$C$32:$G$32,E$6) -> 8 | F21: =INDEX(Spec_Rack!$C$32:$G$32,F$6) -> 4 | G21: =INDEX(Spec_Rack!$C$32:$G$32,G$6) -> 4 | H21: =INDEX(Spec_Rack!$C$32:$G$32,H$6) -> 4 | I21: =INDEX(Spec_Rack!$C$32:$G$32,I$6) -> 4 | J21: =INDEX(Spec_Rack!$C$32:$G$32,J$6) -> 4 | ... S21: =INDEX(Spec_Rack!$C$32:$G$32,S$6) -> 4
A22: GPU 封裝／架 | B22: 顆 | C22: =INDEX(Spec_Rack!$C$6:$G$6,C$6) -> 32 | D22: =INDEX(Spec_Rack!$C$6:$G$6,D$6) -> 32 | E22: =INDEX(Spec_Rack!$C$6:$G$6,E$6) -> 32 | F22: =INDEX(Spec_Rack!$C$6:$G$6,F$6) -> 72 | G22: =INDEX(Spec_Rack!$C$6:$G$6,G$6) -> 72 | H22: =INDEX(Spec_Rack!$C$6:$G$6,H$6) -> 72 | I22: =INDEX(Spec_Rack!$C$6:$G$6,I$6) -> 72 | J22: =INDEX(Spec_Rack!$C$6:$G$6,J$6) -> 72 | ... S22: =INDEX(Spec_Rack!$C$6:$G$6,S$6) -> 72
A23: GPU 功率 | B23: W | C23: =INDEX(Spec_Rack!$C$33:$G$33,C$6) -> 700 | D23: =INDEX(Spec_Rack!$C$33:$G$33,D$6) -> 700 | E23: =INDEX(Spec_Rack!$C$33:$G$33,E$6) -> 700 | F23: =INDEX(Spec_Rack!$C$33:$G$33,F$6) -> 1200 | G23: =INDEX(Spec_Rack!$C$33:$G$33,G$6) -> 1200 | H23: =INDEX(Spec_Rack!$C$33:$G$33,H$6) -> 1200 | I23: =INDEX(Spec_Rack!$C$33:$G$33,I$6) -> 1400 | J23: =INDEX(Spec_Rack!$C$33:$G$33,J$6) -> 1400 | ... S23: =INDEX(Spec_Rack!$C$33:$G$33,S$6) -> 1800
A24: HBM 存取能量 | B24: pJ/B | C24: =INDEX(Spec_Rack!$C$34:$G$34,C$6) -> 31 | D24: =INDEX(Spec_Rack!$C$34:$G$34,D$6) -> 31 | E24: =INDEX(Spec_Rack!$C$34:$G$34,E$6) -> 31 | F24: =INDEX(Spec_Rack!$C$34:$G$34,F$6) -> 25 | G24: =INDEX(Spec_Rack!$C$34:$G$34,G$6) -> 25 | H24: =INDEX(Spec_Rack!$C$34:$G$34,H$6) -> 25 | I24: =INDEX(Spec_Rack!$C$34:$G$34,I$6) -> 25 | J24: =INDEX(Spec_Rack!$C$34:$G$34,J$6) -> 25 | ... S24: =INDEX(Spec_Rack!$C$34:$G$34,S$6) -> 20
A25: 每 GW 機架數（功率情境） | B25: 架 | C25: =INDEX(DC_Cost!$C$12:$Q$12,3*(C$6-1)+2) -> 22439 | D25: =INDEX(DC_Cost!$C$12:$Q$12,3*(D$6-1)+2) -> 22439 | E25: =INDEX(DC_Cost!$C$12:$Q$12,3*(E$6-1)+2) -> 22439 | F25: =INDEX(DC_Cost!$C$12:$Q$12,3*(F$6-1)+2) -> 7076 | G25: =INDEX(DC_Cost!$C$12:$Q$12,3*(G$6-1)+2) -> 7076 | H25: =INDEX(DC_Cost!$C$12:$Q$12,3*(H$6-1)+2) -> 7076 | I25: =INDEX(DC_Cost!$C$12:$Q$12,3*(I$6-1)+2) -> 6715 | J25: =INDEX(DC_Cost!$C$12:$Q$12,3*(J$6-1)+2) -> 6715 | ... S25: =INDEX(DC_Cost!$C$12:$Q$12,3*(S$6-1)+2) -> 4052
A26: 每架配電設計功率 | B26: kW | C26: =INDEX(DC_Cost!$C$11:$Q$11,3*(C$6-1)+2) -> 41 | D26: =INDEX(DC_Cost!$C$11:$Q$11,3*(D$6-1)+2) -> 41 | E26: =INDEX(DC_Cost!$C$11:$Q$11,3*(E$6-1)+2) -> 41 | F26: =INDEX(DC_Cost!$C$11:$Q$11,3*(F$6-1)+2) -> 130 | G26: =INDEX(DC_Cost!$C$11:$Q$11,3*(G$6-1)+2) -> 130 | H26: =INDEX(DC_Cost!$C$11:$Q$11,3*(H$6-1)+2) -> 130 | I26: =INDEX(DC_Cost!$C$11:$Q$11,3*(I$6-1)+2) -> 137 | J26: =INDEX(DC_Cost!$C$11:$Q$11,3*(J$6-1)+2) -> 137 | ... S26: =INDEX(DC_Cost!$C$11:$Q$11,3*(S$6-1)+2) -> 227
A27: B. 架構（連結 Arch）
A28: 啟用參數 | B28: B | C28: =INDEX(Arch!$C$7:$E$7,C$7) -> 13 | D28: =INDEX(Arch!$C$7:$E$7,D$7) -> 49 | E28: =INDEX(Arch!$C$7:$E$7,E$7) -> 180 | F28: =INDEX(Arch!$C$7:$E$7,F$7) -> 13 | G28: =INDEX(Arch!$C$7:$E$7,G$7) -> 49 | H28: =INDEX(Arch!$C$7:$E$7,H$7) -> 180 | I28: =INDEX(Arch!$C$7:$E$7,I$7) -> 13 | J28: =INDEX(Arch!$C$7:$E$7,J$7) -> 49 | ... S28: =INDEX(Arch!$C$7:$E$7,S$7) -> 180
A29: 層數 | B29: 層 | C29: =INDEX(Arch!$C$8:$E$8,C$7) -> 43 | D29: =INDEX(Arch!$C$8:$E$8,D$7) -> 61 | E29: =INDEX(Arch!$C$8:$E$8,E$7) -> 100 | F29: =INDEX(Arch!$C$8:$E$8,F$7) -> 43 | G29: =INDEX(Arch!$C$8:$E$8,G$7) -> 61 | H29: =INDEX(Arch!$C$8:$E$8,H$7) -> 100 | I29: =INDEX(Arch!$C$8:$E$8,I$7) -> 43 | J29: =INDEX(Arch!$C$8:$E$8,J$7) -> 61 | ... S29: =INDEX(Arch!$C$8:$E$8,S$7) -> 100
A30: d_model | C30: =INDEX(Arch!$C$9:$E$9,C$7) -> 4096 | D30: =INDEX(Arch!$C$9:$E$9,D$7) -> 7168 | E30: =INDEX(Arch!$C$9:$E$9,E$7) -> 12288 | F30: =INDEX(Arch!$C$9:$E$9,F$7) -> 4096 | G30: =INDEX(Arch!$C$9:$E$9,G$7) -> 7168 | H30: =INDEX(Arch!$C$9:$E$9,H$7) -> 12288 | I30: =INDEX(Arch!$C$9:$E$9,I$7) -> 4096 | J30: =INDEX(Arch!$C$9:$E$9,J$7) -> 7168 | ... S30: =INDEX(Arch!$C$9:$E$9,S$7) -> 12288
A31: 啟用 routed experts | C31: =INDEX(Arch!$C$13:$E$13,C$7) -> 6 | D31: =INDEX(Arch!$C$13:$E$13,D$7) -> 6 | E31: =INDEX(Arch!$C$13:$E$13,E$7) -> 16 | F31: =INDEX(Arch!$C$13:$E$13,F$7) -> 6 | G31: =INDEX(Arch!$C$13:$E$13,G$7) -> 6 | H31: =INDEX(Arch!$C$13:$E$13,H$7) -> 16 | I31: =INDEX(Arch!$C$13:$E$13,I$7) -> 6 | J31: =INDEX(Arch!$C$13:$E$13,J$7) -> 6 | ... S31: =INDEX(Arch!$C$13:$E$13,S$7) -> 16
A32: 非專家參數 | B32: B | C32: =INDEX(Arch!$C$28:$E$28,C$7) -> 5.412 | D32: =INDEX(Arch!$C$28:$E$28,D$7) -> 20.277778 | E32: =INDEX(Arch!$C$28:$E$28,E$7) -> 49.072581 | F32: =INDEX(Arch!$C$28:$E$28,F$7) -> 5.412 | G32: =INDEX(Arch!$C$28:$E$28,G$7) -> 20.277778 | H32: =INDEX(Arch!$C$28:$E$28,H$7) -> 49.072581 | I32: =INDEX(Arch!$C$28:$E$28,I$7) -> 5.412 | J32: =INDEX(Arch!$C$28:$E$28,J$7) -> 20.277778 | ... S32: =INDEX(Arch!$C$28:$E$28,S$7) -> 49.072581
A33: 專家參數 | B33: B | C33: =INDEX(Arch!$C$29:$E$29,C$7) -> 278.588 | D33: =INDEX(Arch!$C$29:$E$29,D$7) -> 1579.7222 | E33: =INDEX(Arch!$C$29:$E$29,E$7) -> 3950.9274 | F33: =INDEX(Arch!$C$29:$E$29,F$7) -> 278.588 | G33: =INDEX(Arch!$C$29:$E$29,G$7) -> 1579.7222 | H33: =INDEX(Arch!$C$29:$E$29,H$7) -> 3950.9274 | I33: =INDEX(Arch!$C$29:$E$29,I$7) -> 278.588 | J33: =INDEX(Arch!$C$29:$E$29,J$7) -> 1579.7222 | ... S33: =INDEX(Arch!$C$29:$E$29,S$7) -> 3950.9274
A34: KV bytes/token（含 H_KV） | B34: B | C34: =INDEX(Arch!$C$25:$E$25,C$7)*C11 -> 2795 | D34: =INDEX(Arch!$C$25:$E$25,D$7)*D11 -> 3965 | E34: =INDEX(Arch!$C$25:$E$25,E$7)*E11 -> 57600 | F34: =INDEX(Arch!$C$25:$E$25,F$7)*F11 -> 2795 | G34: =INDEX(Arch!$C$25:$E$25,G$7)*G11 -> 3965 | H34: =INDEX(Arch!$C$25:$E$25,H$7)*H11 -> 57600 | I34: =INDEX(Arch!$C$25:$E$25,I$7)*I11 -> 2795 | J34: =INDEX(Arch!$C$25:$E$25,J$7)*J11 -> 3965 | ... S34: =INDEX(Arch!$C$25:$E$25,S$7)*S11 -> 57600
A35: 注意力 FLOPs／被注意 token | B35: FLOP | C35: =INDEX(Arch!$C$30:$E$30,C$7) -> 5636096 | D35: =INDEX(Arch!$C$30:$E$30,D$7) -> 15990784 | E35: =INDEX(Arch!$C$30:$E$30,E$7) -> 4915200 | F35: =INDEX(Arch!$C$30:$E$30,F$7) -> 5636096 | G35: =INDEX(Arch!$C$30:$E$30,G$7) -> 15990784 | H35: =INDEX(Arch!$C$30:$E$30,H$7) -> 4915200 | I35: =INDEX(Arch!$C$30:$E$30,I$7) -> 5636096 | J35: =INDEX(Arch!$C$30:$E$30,J$7) -> 15990784 | ... S35: =INDEX(Arch!$C$30:$E$30,S$7) -> 4915200
A36: 全注意力層比例 | B36: % | C36: =INDEX(Arch!$C$16:$E$16,C$7) -> 0.5 | D36: =INDEX(Arch!$C$16:$E$16,D$7) -> 0.5 | E36: =INDEX(Arch!$C$16:$E$16,E$7) -> 1 | F36: =INDEX(Arch!$C$16:$E$16,F$7) -> 0.5 | G36: =INDEX(Arch!$C$16:$E$16,G$7) -> 0.5 | H36: =INDEX(Arch!$C$16:$E$16,H$7) -> 1 | I36: =INDEX(Arch!$C$16:$E$16,I$7) -> 0.5 | J36: =INDEX(Arch!$C$16:$E$16,J$7) -> 0.5 | ... S36: =INDEX(Arch!$C$16:$E$16,S$7) -> 1
A37: 全注意力跨度上限 | B37: tok | C37: =INDEX(Arch!$C$17:$E$17,C$7) -> 4224 | D37: =INDEX(Arch!$C$17:$E$17,D$7) -> 4224 | E37: =INDEX(Arch!$C$17:$E$17,E$7) -> 0 | F37: =INDEX(Arch!$C$17:$E$17,F$7) -> 4224 | G37: =INDEX(Arch!$C$17:$E$17,G$7) -> 4224 | H37: =INDEX(Arch!$C$17:$E$17,H$7) -> 0 | I37: =INDEX(Arch!$C$17:$E$17,I$7) -> 4224 | J37: =INDEX(Arch!$C$17:$E$17,J$7) -> 4224 | ... S37: =INDEX(Arch!$C$17:$E$17,S$7) -> 0
A38: 其他層壓縮比 | B38: x | C38: =INDEX(Arch!$C$18:$E$18,C$7) -> 128 | D38: =INDEX(Arch!$C$18:$E$18,D$7) -> 128 | E38: =INDEX(Arch!$C$18:$E$18,E$7) -> 1 | F38: =INDEX(Arch!$C$18:$E$18,F$7) -> 128 | G38: =INDEX(Arch!$C$18:$E$18,G$7) -> 128 | H38: =INDEX(Arch!$C$18:$E$18,H$7) -> 1 | I38: =INDEX(Arch!$C$18:$E$18,I$7) -> 128 | J38: =INDEX(Arch!$C$18:$E$18,J$7) -> 128 | ... S38: =INDEX(Arch!$C$18:$E$18,S$7) -> 1
A39: 其他層滑動窗 | B39: tok | C39: =INDEX(Arch!$C$19:$E$19,C$7) -> 128 | D39: =INDEX(Arch!$C$19:$E$19,D$7) -> 128 | E39: =INDEX(Arch!$C$19:$E$19,E$7) -> 0 | F39: =INDEX(Arch!$C$19:$E$19,F$7) -> 128 | G39: =INDEX(Arch!$C$19:$E$19,G$7) -> 128 | H39: =INDEX(Arch!$C$19:$E$19,H$7) -> 0 | I39: =INDEX(Arch!$C$19:$E$19,I$7) -> 128 | J39: =INDEX(Arch!$C$19:$E$19,J$7) -> 128 | ... S39: =INDEX(Arch!$C$19:$E$19,S$7) -> 0
A40: C. 服務、SLO 與校準參數
A41: SLO：每用戶 decode 速度下限 | B41: tok/s | C41: =INDEX(Train_In!$C$31:$E$31,C$7) -> 20 | D41: =INDEX(Train_In!$C$31:$E$31,D$7) -> 20 | E41: =INDEX(Train_In!$C$31:$E$31,E$7) -> 20 | F41: =INDEX(Train_In!$C$31:$E$31,F$7) -> 20 | G41: =INDEX(Train_In!$C$31:$E$31,G$7) -> 20 | H41: =INDEX(Train_In!$C$31:$E$31,H$7) -> 20 | I41: =INDEX(Train_In!$C$31:$E$31,I$7) -> 20 | J41: =INDEX(Train_In!$C$31:$E$31,J$7) -> 20 | ... S41: =INDEX(Train_In!$C$31:$E$31,S$7) -> 20
A42: TTFT 上限 | B42: s | C42: =INDEX(Serving!$C$22:$E$22,C$7) -> 2 | D42: =INDEX(Serving!$C$22:$E$22,D$7) -> 3 | E42: =INDEX(Serving!$C$22:$E$22,E$7) -> 5 | F42: =INDEX(Serving!$C$22:$E$22,F$7) -> 2 | G42: =INDEX(Serving!$C$22:$E$22,G$7) -> 3 | H42: =INDEX(Serving!$C$22:$E$22,H$7) -> 5 | I42: =INDEX(Serving!$C$22:$E$22,I$7) -> 2 | J42: =INDEX(Serving!$C$22:$E$22,J$7) -> 3 | ... S42: =INDEX(Serving!$C$22:$E$22,S$7) -> 5
A43: 參考 ISL | B43: tok | C43: =INDEX(Train_In!$C$32:$E$32,C$7) -> 4096 | D43: =INDEX(Train_In!$C$32:$E$32,D$7) -> 8192 | E43: =INDEX(Train_In!$C$32:$E$32,E$7) -> 16384 | F43: =INDEX(Train_In!$C$32:$E$32,F$7) -> 4096 | G43: =INDEX(Train_In!$C$32:$E$32,G$7) -> 8192 | H43: =INDEX(Train_In!$C$32:$E$32,H$7) -> 16384 | I43: =INDEX(Train_In!$C$32:$E$32,I$7) -> 4096 | J43: =INDEX(Train_In!$C$32:$E$32,J$7) -> 8192 | ... S43: =INDEX(Train_In!$C$32:$E$32,S$7) -> 16384
