Workbook

Sheet Config
A1: PARAMETERIZED TOKEN GENERATION PIPELINE — v4 (frontier MoE presets, Sep 2026) | E1: RACK PRESETS
A2: Change the blue cells below to experiment with different configurations | E2: Copy a column into Column B to switch racks
A4: AI DC Spec. | B4: Data | C4: Note | E4: AI DC Spec. | F4: Vera Rubin NVL72 | G4: GB200 NVL72 | H4: Note
A5: Total power(W) | B5: =IF($B$7=F$4,F5,G5) -> 1000000000 | E5: Total power(W) | F5: 1000000000 | G5: 1000000000
A6: PUE | B6: =IF($B$7=F$4,F6,G6) -> 1.2 | E6: PUE | F6: 1.2 | G6: 1.2
A7: Rack Type | B7: Vera Rubin NVL72 | E7: Rack Type | F7: Vera Rubin NVL72 | G7: GB200 NVL72
A8: No.of racks | B8: =IF($B$7=F$4,F8,G8) -> 5263 | C8: Derived: FLOOR(IT Power / Power per Rack) | E8: No.of racks | F8: =FLOOR(F5/1000/F23,1) -> 5263 | G8: =FLOOR(G5/1000/G23,1) -> 7194 | H8: Derived: FLOOR(Total Power / Power per Rack)
A10: Rack Spec. | B10: Data | C10: Note | E10: Rack Spec. | F10: Vera Rubin NVL72 | G10: GB200 NVL72 | H10: Note
A11: CPU Type | B11: =IF($B$7=F$4,F11,G11) -> Vera CPU | E11: CPU Type | F11: Vera CPU | G11: Grace CPU
A12: No. of CPU | B12: =IF($B$7=F$4,F12,G12) -> 36 | E12: No. of CPU | F12: 36 | G12: 36
A13: GPU Type | B13: =IF($B$7=F$4,F13,G13) -> Rubin GPU | E13: GPU Type | F13: Rubin GPU | G13: Blackwell B200
A14: No. of GPU | B14: =IF($B$7=F$4,F14,G14) -> 72 | C14: per rack | E14: No. of GPU | F14: 72 | G14: 72
A15: NVLink Bandwidth(TB/s) | B15: =IF($B$7=F$4,F15,G15) -> 260 | C15: total per rack | E15: NVLink BW(TB/s) | F15: 260 | G15: 130 | H15: Total per rack
A16: NVLink-C2C Bandwidth(TB/s) | B16: =IF($B$7=F$4,F16,G16) -> 65 | E16: NVLink-C2C BW(TB/s) | F16: 65 | G16: 32.4 | H16: 0.9 TB/s * 36 CPUs
A17: GPU Memory(TB) | B17: =IF($B$7=F$4,F17,G17) -> 20.7 | C17: 0.288/GPU | E17: GPU Memory(TB) | F17: 20.7 | G17: 13.5 | H17: Total per rack (0.1875/GPU for GB200)
A18: Memory Bandwidth(TB) | B18: =IF($B$7=F$4,F18,G18) -> 1580 | C18: 22/GPU | E18: Memory BW(TB) | F18: 1580 | G18: 576 | H18: Total per rack (8/GPU for GB200)
A19: FP4 Dense Inference(PFLOPS) | B19: =IF($B$7=F$4,F19,G19) -> 3600 | C19: 50/GPU | E19: FP4 Dense Inference(PFLOPS) | F19: 3600 | G19: 648 | H19: 50/GPU Rubin = 3600; 9/GPU B200 (dense, no sparsity). Fixed from 2520 (was using 35/GPU training value).
A20: FP4 Dense Training(PFLOPS) | B20: =IF($B$7=F$4,F20,G20) -> 2520 | C20: 35/GPU | E20: FP4 Dense Training(PFLOPS) | F20: 2520 | G20: 648 | H20: 35 PFLOPS/GPU Rubin = 2520; 9 PFLOPS/GPU B200 = 648 (dense training)
A21: FP8 Dense(PFLOPS) | B21: =IF($B$7=F$4,F21,G21) -> 1152 | C21: 16/GPU (was 17.5) | E21: FP8 Dense(PFLOPS) | F21: 1152 | G21: 324 | H21: 16/GPU Rubin; 4.5/GPU B200 (dense)
A22: FP16/BF16 Dense(PFLOPS) | B22: =IF($B$7=F$4,F22,G22) -> 288 | C22: 4/GPU | E22: FP16/BF16 Dense(PFLOPS) | F22: 288 | G22: 162 | H22: 3.6/GPU Rubin; 2.25/GPU B200 (dense)
A23: Power per Rack (kW) | B23: =IF($B$7=F$4,F23,G23) -> 190 | C23: IT power draw per rack | E23: Power/Rack (kW) | F23: 190 | G23: 139 | H23: IT power only (excl. PUE overhead)
A24: Rack Price ($) | B24: =IF($B$7=F$4,F27,G27) -> 6000000 | C24: Auto-filled from dropdown; edit preset in F27/G27
A26: ▶ KEY INPUTS — Model & Tokens | B26: Data | C26: Note | E26: Pricing | F26: Vera Rubin NVL72 | G26: GB200 NVL72 | H26: Note | J26: ▶ FRONTIER MODEL PRESETS (Sep 2026) — select in B29; column K feeds column B
A27: Input Tokens | B27: 16000 | C27: [Analogy] agentic/coding mix: OpenRouter avg prompt >6K (Nov-2025), programming >20K; range 6K–32K | E27: Rack Price ($) | F27: 6000000 | G27: 3000000 | H27: Est. $3M GB200; Rubin ~$6M (15-20% premium) | J27: Blue = published/assumed input · black = derived. Tags in column Q. Published = vendor model card / config.json.
A28: Output Tokens | B28: 1000 | C28: [Analogy] avg completion ~400 (Nov-2025) rising with reasoning; range 400–2,000. Link =B27/4 removed (I:O now ~16:1) | J28: Parameter | K28: ▶ Selected | L28: DeepSeek V4-Pro | M28: Kimi K3 | N28: DeepSeek V4-Flash | O28: Closed-frontier proxy | P28: Legacy 1T Dense (v3) | Q28: Source / Tag
A29: Model Preset | B29: DeepSeek V4-Pro | C29: ← Select frontier architecture (table J26:Q55); feeds B31–B48, B55 | E29: ▶ MARKET PRICING TIERS (Sep 2026) | J29: Total parameters (published) | K29: =IF(INDEX($L29:$P29,MATCH($B$29,$L$28:$P$28,0))="","",INDEX($L29:$P29,MATCH($B$29,$L$28:$P$28,0))) -> 1600000000000 | L29: 1600000000000 | M29: 2800000000000 | N29: 284000000000 | O29: 4000000000000 | P29: 1000000000000 | Q29: V4-Pro 1.6T (preview; GA-0813 card 1.7T incl. DSpark) [Verified: HF card]; K3 2.8T [Verified: model card]; V4-Flash 284B [Verified: arXiv 2606.19348]; proxy [Assumed, range 2–10T]; legacy = v3 default
A30: Model Spec. | B30: Data | C30: Note | E30: Select tier in F41 (independent of architecture preset) | J30: Active parameters / token (published) | K30: =IF(INDEX($L30:$P30,MATCH($B$29,$L$28:$P$28,0))="","",INDEX($L30:$P30,MATCH($B$29,$L$28:$P$28,0))) -> 49000000000 | L30: 49000000000 | M30: 104000000000 | N30: 13000000000 | O30: 180000000000 | P30: 1000000000000 | Q30: V4-Pro 49B, K3 104B, V4-Flash 13B [Verified]; proxy [Assumed, range 60–250B]
A31: Parameters | B31: =K29 -> 1600000000000 | C31: Total params (from preset K29) | E31: Tier | F31: Representative models (list $/M in/out) | G31: Input $/M | H31: Output $/M | J31: Type | K31: =IF(INDEX($L31:$P31,MATCH($B$29,$L$28:$P$28,0))="","",INDEX($L31:$P31,MATCH($B$29,$L$28:$P$28,0))) -> MoE | L31: MoE | M31: MoE | N31: MoE | O31: MoE | P31: Dense
A32: Type | B32: =K31 -> MoE | C32: Dense / MoE (from preset; overwrite to test) | E32: Nano | F32: Qwen3.7 Flash $0.03/$0.13; Nova Micro $0.035/$0.14 | G32: 0.035 | H32: 0.14 | J32: n_layers (blank = auto-scale) | K32: =IF(INDEX($L32:$P32,MATCH($B$29,$L$28:$P$28,0))="","",INDEX($L32:$P32,MATCH($B$29,$L$28:$P$28,0))) -> 61 | L32: 61 | M32: 93 | N32: 43 | O32: 100 | Q32: V4-Pro 61 (config.json); K3 93 = 24 Gated-MLA + 69 KDA; V4-Flash 43 [secondary: clore.ai]; proxy [Assumed]
A33: Total Experts | B33: =N(K36) -> 384 | C33: Routed experts (from preset) | E33: Small / Flash | F33: GPT-5.6 Luna $0.20/$1.20; DeepSeek V4-Flash $0.44/$1.32; Gemini 3.8 Flash $0.75/$3.75 (median) | G33: 0.44 | H33: 1.32 | J33: d_model (blank = auto-scale) | K33: =IF(INDEX($L33:$P33,MATCH($B$29,$L$28:$P$28,0))="","",INDEX($L33:$P33,MATCH($B$29,$L$28:$P$28,0))) -> 7168 | L33: 7168 | M33: 7168 | N33: =N55 -> 4096 | O33: 12288 | Q33: V4-Pro/K3 hidden 7168 [Verified]; V4-Flash derived in row 55; proxy [Assumed]
A34: Active Experts | B34: =N(K37) -> 6 | C34: Active routed experts (from preset) | E34: Open-weight frontier | F34: DeepSeek V4-Pro $1.32/$3.96 (peak); GLM-5.3 $1.40/$4.40 (mean) | G34: 1.36 | H34: 4.18 | J34: Attention heads (query) | K34: =IF(INDEX($L34:$P34,MATCH($B$29,$L$28:$P$28,0))="","",INDEX($L34:$P34,MATCH($B$29,$L$28:$P$28,0))) -> 128 | L34: 128 | M34: 96 | N34: 64 | O34: 96 | Q34: V4-Pro 128; K3 96 [Verified]; V4-Flash 64 [Analogy: half of Pro]; proxy [Assumed]
A35: FFN Compute Ratio | B35: =IF(B32="Dense",1,(B34+N(K38))/(B33+N(K38))) -> 0.018181818 | C35: Dense=1; MoE=(active+shared)/(routed+shared) | E35: Mid | F35: Claude Sonnet 5 $3/$15; Kimi K3 $3/$15; Gemini 3.1 Pro $2/$12 (median) | G35: 3 | H35: 15 | J35: Attention head dim (for QK/AV FLOPs) | K35: =IF(INDEX($L35:$P35,MATCH($B$29,$L$28:$P$28,0))="","",INDEX($L35:$P35,MATCH($B$29,$L$28:$P$28,0))) -> 512 | L35: 512 | M35: 128 | N35: 512 | O35: 128 | P35: 128 | Q35: V4-Pro head_dim 512 [Verified]; K3 128 [Analogy: K2 MLA v-head]; V4-Flash [Analogy: Pro]
A36: Active Parameters | B36: =IF(B32="Dense",B31,B39*(B43+B44*B35)+K40) -> 49000000000 | C36: MoE = layers×(non-expert + FFN×ratio) + embeddings; ties to published active | E36: Frontier (closed) | F36: Claude Opus 5 $5/$25; Opus 4.8 $5/$25; GPT-5.6 Sol $5/$30 list, $4/$20 promo (median) | G36: 5 | H36: 25 | J36: Routed experts | K36: =IF(INDEX($L36:$P36,MATCH($B$29,$L$28:$P$28,0))="","",INDEX($L36:$P36,MATCH($B$29,$L$28:$P$28,0))) -> 384 | L36: 384 | M36: 896 | N36: 256 | O36: 512 | P36: 0 | Q36: V4-Pro 384 (config.json); K3 896; V4-Flash 256 [Verified]; proxy [Assumed]
A37: vocab size(V) | B37: =K39 -> 129280 | C37: From preset | E37: Premium | F37: Claude Fable 5.1 $10/$50 | G37: 10 | H37: 50 | J37: Active routed experts / token | K37: =IF(INDEX($L37:$P37,MATCH($B$29,$L$28:$P$28,0))="","",INDEX($L37:$P37,MATCH($B$29,$L$28:$P$28,0))) -> 6 | L37: 6 | M37: 16 | N37: 6 | O37: 16 | P37: 0 | Q37: V4-Pro 6, K3 16, V4-Flash 6 [Verified]
A38: Hidden Dimension(d_model) | B38: =IF(N(K33)>0,K33,MROUND(160*B39,128)) -> 7168 | C38: Preset value; blank → auto (aspect 160) | E38: Sources: | F38: Vendor list prices via price trackers checked 2026-08-19 to 2026-09-18 (CloudZero, Morph, Layer3, BenchLM, Spheron). [Verified-secondary]; promo and off-peak rates noted, not used. | J38: Shared experts | K38: =IF(INDEX($L38:$P38,MATCH($B$29,$L$28:$P$28,0))="","",INDEX($L38:$P38,MATCH($B$29,$L$28:$P$28,0))) -> 1 | L38: 1 | M38: 2 | N38: 1 | O38: 1 | P38: 0 | Q38: V4-Pro 1, K3 2, V4-Flash 1 [Verified]
A39: n_layers | B39: =IF(N(K32)>0,K32,ROUND((B31/(12*160^2))^(1/3),0)) -> 61 | C39: Preset value; blank → auto (P/(12r²))^(1/3) | J39: Vocab size | K39: =IF(INDEX($L39:$P39,MATCH($B$29,$L$28:$P$28,0))="","",INDEX($L39:$P39,MATCH($B$29,$L$28:$P$28,0))) -> 129280 | L39: 129280 | M39: 163840 | N39: 129280 | O39: 200000 | P39: 128000 | Q39: V4 129,280; K3 163,840 [Verified]; proxy [Assumed]
A40: n_heads | B40: =IF(N(K34)>0,K34,B38/B41) -> 128 | C40: Query heads (preset; else d_model/d_head) | E40: ▶ SELECTED PRICING | J40: Embedding + LM-head params [Derived] | K40: =INDEX($L40:$P40,MATCH($B$29,$L$28:$P$28,0)) -> 1853358080 | L40: =L39*IF(N(L33)>0,L33,$B$38)*2 -> 1853358080 | M40: =M39*IF(N(M33)>0,M33,$B$38)*2 -> 2348810240 | N40: =N39*IF(N(N33)>0,N33,$B$38)*2 -> 1059061760 | O40: =O39*IF(N(O33)>0,O33,$B$38)*2 -> 4915200000 | P40: =P39*IF(N(P33)>0,P33,$B$38)*2 -> 1835008000 | Q40: vocab × d_model × 2 (untied input embedding + output head)
A41: d_head | B41: =IF(N(K35)>0,K35,128) -> 512 | C41: Attention head dim (preset; else 128) | E41: Pricing Tier | F41: Frontier (closed) | H41: ← Dropdown. Default = closed-frontier list price (lab monetization view); choose "Open-weight frontier" to price the preset at its own API rate | J41: Params per routed expert [Derived] | K41: =IF(INDEX($L41:$P41,MATCH($B$29,$L$28:$P$28,0))="","",INDEX($L41:$P41,MATCH($B$29,$L$28:$P$28,0))) -> 67265157 | L41: =IF(L31="MoE",(L29-L30)/(L32*(L36-L37)),"") -> 67265157 | M41: =IF(M31="MoE",(M29-M30)/(M32*(M36-M37)),"") -> 32942326 | N41: =IF(N31="MoE",(N29-N30)/(N32*(N36-N37)),"") -> 25209302 | O41: =IF(O31="MoE",(O29-O30)/(O32*(O36-O37)),"") -> 77016129 | P41: =IF(P31="MoE",(P29-P30)/(P32*(P36-P37)),"") | Q41: (total − active) / (layers × (routed − active)); ties exactly to published totals. V4-Pro gives 67.3M vs 66.1M from config (3×7168×3072), −1.8%
A42: d_ff(SwiGLU) | B42: =IF(B32="MoE",K43,(B31/B39-4*B38^2)/(3*B38)) -> 1204291.6 | C42: MoE: effective d_ff of all experts (K43); Dense: derived from params | E42: Input Price ($/M tokens) | F42: =INDEX(G32:G37,MATCH(F41,E32:E37,0)) -> 5 | J42: Non-expert params per layer (attn, router, norms) [Derived] | K42: =IF(INDEX($L42:$P42,MATCH($B$29,$L$28:$P$28,0))="","",INDEX($L42:$P42,MATCH($B$29,$L$28:$P$28,0))) -> 3.0203967e+08 | L42: =IF(L31="MoE",(L30-L40-L32*(L37+L38)*L41)/L32,"") -> 3.0203967e+08 | M42: =IF(M31="MoE",(M30-M40-M32*(M37+M38)*M41)/M32,"") -> 5.0006167e+08 | N42: =IF(N31="MoE",(N30-N40-N32*(N37+N38)*N41)/N32,"") -> 1.0123112e+08 | O42: =IF(O31="MoE",(O30-O40-O32*(O37+O38)*O41)/O32,"") -> 4.4157381e+08 | P42: =IF(P31="MoE",(P30-P40-P32*(P37+P38)*P41)/P32,"") | Q42: (active − embed − layers × (active+shared) × expert) / layers. Includes attention, indexer, mHC, router
A43: Parameters per Layer(Att) | B43: =IF(B32="MoE",K42,4*B38^2) -> 3.0203967e+08 | C43: MoE: non-expert params/layer (K42); Dense: 4×d² | E43: Output Price ($/M tokens) | F43: =INDEX(H32:H37,MATCH(F41,E32:E37,0)) -> 25 | J43: Effective FFN intermediate d_ff (all experts, in d_model units) [Derived] | K43: =IF(INDEX($L43:$P43,MATCH($B$29,$L$28:$P$28,0))="","",INDEX($L43:$P43,MATCH($B$29,$L$28:$P$28,0))) -> 1204291.6 | L43: =IF(L31="MoE",(L36+L38)*L41/(3*IF(N(L33)>0,L33,$B$38)),"") -> 1204291.6 | M43: =IF(M31="MoE",(M36+M38)*M41/(3*IF(N(M33)>0,M33,$B$38)),"") -> 1375660.8 | N43: =IF(N31="MoE",(N36+N38)*N41/(3*IF(N(N33)>0,N33,$B$38)),"") -> 527245.34 | O43: =IF(O31="MoE",(O36+O38)*O41/(3*IF(N(O33)>0,O33,$B$38)),"") -> 1071757.7 | P43: =IF(P31="MoE",(P36+P38)*P41/(3*IF(N(P33)>0,P33,$B$38)),"") | Q43: (routed+shared) × expert params / (3 × d_model) → keeps 3·d·d_ff = total FFN params in WP_Param formulas
A44: Parameters per Layer(FFN) | B44: =3*B38*B42 -> 2.5897086e+10 | C44: 3 × d_model × d_ff | J44: Check: implied total params [Derived] | K44: =IF(INDEX($L44:$P44,MATCH($B$29,$L$28:$P$28,0))="","",INDEX($L44:$P44,MATCH($B$29,$L$28:$P$28,0))) -> 1600000000000 | L44: =IF(L31="MoE",L32*(L42+(L36+L38)*L41)+L40,"") -> 1600000000000 | M44: =IF(M31="MoE",M32*(M42+(M36+M38)*M41)+M40,"") -> 2800000000000 | N44: =IF(N31="MoE",N32*(N42+(N36+N38)*N41)+N40,"") -> 284000000000 | O44: =IF(O31="MoE",O32*(O42+(O36+O38)*O41)+O40,"") -> 4000000000000 | P44: =IF(P31="MoE",P32*(P42+(P36+P38)*P41)+P40,"") | Q44: Should equal row 29 (by construction ≈ equal; small gap = embeddings rounding)
A45: Total Parameters per Layer | B45: =B43+B44 -> 2.6199125e+10 | J45: KV elements / token / layer (effective avg) | K45: =IF(INDEX($L45:$P45,MATCH($B$29,$L$28:$P$28,0))="","",INDEX($L45:$P45,MATCH($B$29,$L$28:$P$28,0))) -> 65 | L45: 65 | M45: 149 | N45: 65 | O45: 2048 | P45: 2048 | Q45: [Derived] V4-Pro: 512-dim single KV head; CSA (≈½ layers) 4× + HCA (≈½) 128× compression → 512×(0.5×¼+0.5×1/128)≈65; cross-check: card says 10% of V3.2 KV (576×10%≈58). K3: 24/93 MLA layers × 576 = 149 (KDA recurrent state omitted). V4-Flash [Analogy: Pro]. Proxy/legacy: GQA 8 heads × 128 × 2 = 2048 [Assumed]
A46: MFU | B46: 0.35 | C46: [Analogy] inference MFU range 0.25–0.50; was 0.50 (Mar-2026 audit flagged as high) | J46: KV cache bytes / element | K46: =IF(INDEX($L46:$P46,MATCH($B$29,$L$28:$P$28,0))="","",INDEX($L46:$P46,MATCH($B$29,$L$28:$P$28,0))) -> 1 | L46: 1 | M46: 1 | N46: 1 | O46: 1 | P46: 1 | Q46: FP8 KV cache = 1 byte [Assumed; industry default on Blackwell/Rubin]
A47: Precision | B47: =K51 -> FP4 | C47: Compute precision from preset (FP4/FP8/FP16); overwrite to force | J47: Full-attention layer fraction | K47: =IF(INDEX($L47:$P47,MATCH($B$29,$L$28:$P$28,0))="","",INDEX($L47:$P47,MATCH($B$29,$L$28:$P$28,0))) -> 0.5 | L47: 0.5 | M47: 0.25806452 | N47: 0.5 | O47: 1 | P47: 1 | Q47: V4: CSA layers ≈ ½ (alternating CSA/HCA) [Verified structure]; K3: 24 of 93 layers full MLA [Verified]; dense = 1
A48: Bytes per Parameter | B48: =IF(N(K50)>0,K50,IF(B47="FP4",0.5,IF(B47="FP8",1,IF(B47="FP16",2,"ERR")))) -> 0.507 | C48: Effective weight bytes (mixed precision from preset; else by B47) | J48: Full-attention span cap (tokens; 0 = none) | K48: =IF(INDEX($L48:$P48,MATCH($B$29,$L$28:$P$28,0))="","",INDEX($L48:$P48,MATCH($B$29,$L$28:$P$28,0))) -> 4224 | L48: 4224 | M48: 0 | N48: 4224 | O48: 0 | P48: 0 | Q48: V4 CSA: index_topk 1024 compressed blocks × 4 tokens + 128 sliding window = 4,224 [Derived]; 0 = attends full context
A49: Inference PFLOPS (rack) | B49: =IF(B47="FP4",B19,IF(B47="FP8",B21,IF(B47="FP16",B22,"ERR"))) -> 3600 | C49: Auto-selected from rack spec based on precision | J49: Tokens attended in other (compressed / linear) layers | K49: =IF(INDEX($L49:$P49,MATCH($B$29,$L$28:$P$28,0))="","",INDEX($L49:$P49,MATCH($B$29,$L$28:$P$28,0))) -> 256 | L49: 256 | M49: 128 | N49: 256 | O49: 0 | P49: 0 | Q49: V4 HCA: ctx/128 + 128 window ≈ 256 at 16K ctx [Derived]; K3 KDA linear layers ≈ constant cost, 128-token equivalent [Assumed]
J50: Effective weight bytes / param (blank = by precision) | K50: =IF(INDEX($L50:$P50,MATCH($B$29,$L$28:$P$28,0))="","",INDEX($L50:$P50,MATCH($B$29,$L$28:$P$28,0))) -> 0.507 | L50: 0.507 | M50: 0.53 | N50: 0.51 | O50: 0.53 | Q50: V4-Pro: experts FP4 (0.5 B) + non-expert FP8 (1 B) weighted → 0.507 [Derived]; K3 native MXFP4 incl. scales ≈ 0.53 [Derived]; blank → from B47
A51: Parallelism Strategy | B51: Data | C51: Note | J51: Compute precision (feeds B47) | K51: =IF(INDEX($L51:$P51,MATCH($B$29,$L$28:$P$28,0))="","",INDEX($L51:$P51,MATCH($B$29,$L$28:$P$28,0))) -> FP4 | L51: FP4 | M51: FP4 | N51: FP4 | O51: FP4 | P51: FP8 | Q51: Native serving precision: V4 FP4 experts/FP8 dense; K3 MXFP4 QAT [Verified]; compute on dominant (expert) path
A52: Tensor Parallelism (TP) | B52: 72 | J52: Reference API list price in / out ($/M) | K52: =IF(INDEX($L52:$P52,MATCH($B$29,$L$28:$P$28,0))="","",INDEX($L52:$P52,MATCH($B$29,$L$28:$P$28,0))) -> $1.32/$3.96 peak ($0.66/$1.98 off-peak) | L52: $1.32/$3.96 peak ($0.66/$1.98 off-peak) | M52: $3/$15 | N52: $0.44/$1.32 peak ($0.22/$0.66 off-peak) | O52: n/a (see tier Frontier (closed)) | P52: v3: $2.50/$10 (Mar-2026 tier) | Q52: Vendor list prices, Sep-2026 [Verified: DeepSeek API / Moonshot; via secondary price trackers]
J53: Release / checkpoint | K53: =IF(INDEX($L53:$P53,MATCH($B$29,$L$28:$P$28,0))="","",INDEX($L53:$P53,MATCH($B$29,$L$28:$P$28,0))) -> Apr-24-2026 preview; GA 0813 | L53: Apr-24-2026 preview; GA 0813 | M53: Jul-16-2026; weights Jul-27 | N53: GA 0731 | O53: Assumed composite of GPT-5.6 Sol / Claude Opus 5 / Gemini 3.1 Pro class | P53: Retained for comparison
A54: ▶ Optimization Parameters | B54: Data | C54: Note
A55: KV heads (GQA-equivalent) | B55: =K45/(2*B41) -> 0.063476562 | C55: GQA-equivalent KV heads = KV elements per token per layer / (2×d_head); fractional for compressed attention | J55: V4-Flash d_model [Derived] | N55: =MROUND((N29-N30)/(N32*(N36-N37))/(3*2048),128) -> 4096 | Q55: Expert intermediate 2048 [Verified] → d ≈ expert params / (3×2048); rounded to 128. Written to N33 via formula
A56: Batch Size / tokens per step | B56: 64 | C56: bounded by HBM Size
A57: Speculation window: N | B57: 5 | C57: [Analogy] DSpark block size 5 (V4-Pro-0813); MTP-style drafts 3–5; was 8
A58: Acceptance rate: a | B58: 0.7
A59: Expected Tokens Accepted | B59: =(1-B58^(B57+1))/(1-B58) -> 2.94117 | C59: (1-a^(N+1))/(1-a)
A60: NVLink SHARP reduction | B60: 0.5 | C60: SHARP in-network traffic reduction
A61: NVLink time per token with SHARP (s) | B61: 0.0005 | C61: Override: 0.00128×0.5≈0.0005 (partially overlapped)
A62: Compute-Communication Overlap efficiency | B62: 0.5 | C62: 50% of NVLink hidden behind compute
A63: New TP degree (for PP split) | B63: 36 | C63: Split into PP stages × TP GPUs
A64: PP stages | B64: =B14/B63 -> 2 | C64: No. of GPU / New TP degree
A66: Derived Memory Check | B66: Data | C66: Note
A67: Weight Memory(Byte) | B67: =B31*B48 -> 811200000000 | C67: Parameters × Bytes per Parameter (from Precision)
A69: ▶ Inter-Rack Network Fabric | B69: Data | C69: Note | E69: Inter-Rack Network Fabric | F69: Vera Rubin NVL72 | G69: GB200 NVL72 | H69: Note
A70: Network Fabric Type | B70: InfiniBand XDR | C70: IB XDR (Quantum-X800) / Spectrum-X800 / Std Ethernet | E70: Network Fabric Type | F70: InfiniBand XDR | G70: InfiniBand XDR | H70: Quantum-X800 for both
A71: NIC Type | B71: ConnectX-9 SuperNIC | C71: 1.6 Tb/s per GPU; PCIe Gen6 (VR NVL72) | E71: NIC Type | F71: ConnectX-9 SuperNIC | G71: ConnectX-8 | H71: VR NVL72: ConnectX-9 1.6 Tb/s; GB200: ConnectX-8 800 Gb/s
A72: NIC BW per GPU (Gb/s) | B72: 1600 | C72: 1600 Gb/s = 0.2 TB/s per GPU | E72: NIC BW per GPU (Gb/s) | F72: 1600 | G72: 800 | H72: Per GPU
A73: NIC BW per GPU (TB/s) | B73: =B72/8/1000 -> 0.2 | C73: Gb/s → TB/s (divide by 8 for bits→bytes, /1000 for G→T) | E73: NIC BW per GPU (TB/s) | F73: =F72/8/1000 -> 0.2 | G73: =G72/8/1000 -> 0.1
A74: Total Inter-Rack BW per Rack (TB/s) | B74: =B73*B14 -> 14.4 | C74: NIC BW/GPU × GPUs per rack | E74: Total Inter-Rack BW/Rack (TB/s) | F74: =F73*F14 -> 14.4 | G74: =G73*G14 -> 7.2
A75: Switch Type (Leaf/Spine) | B75: Quantum-X800 Q3400 | C75: 144-port 800 Gb/s XDR switch | E75: Switch Type | F75: Quantum-X800 Q3400 | G75: Quantum-X800 Q3400 | H75: 144 ports × 800 Gb/s
A76: Switch Port-to-Port Latency (μs) | B76: 0.1 | C76: Sub-100 ns per hop (IB XDR); ~0.5 μs Ethernet | E76: Switch Latency (μs) | F76: 0.1 | G76: 0.1 | H76: Sub-100 ns for IB XDR
A77: Network Hops (leaf-spine-leaf) | B77: 3 | C77: 2-tier fat-tree: leaf→spine→leaf = 3 hops | E77: Network Hops | F77: 3 | G77: 3 | H77: 2-tier fat-tree topology
A78: Network Oversubscription Ratio | B78: 2 | C78: 2:1 typical; 1:1 = full bisection bandwidth | E78: Oversubscription | F78: 2 | G78: 2 | H78: 2:1 oversubscription
A79: Effective Inter-Rack BW per GPU (TB/s) | B79: =B73/B78 -> 0.1 | C79: NIC BW / oversubscription ratio | E79: Eff. Inter-Rack BW/GPU (TB/s) | F79: =F73/F78 -> 0.1 | G79: =G73/G78 -> 0.05
A80: Inter-Rack Latency per Hop (s) | B80: =B76/1000000 -> 1e-07 | C80: μs → seconds | E80: Inter-Rack Latency/Hop (s) | F80: =F76/1000000 -> 1e-07 | G80: =G76/1000000 -> 1e-07
A81: Inter-Rack One-Way Latency (s) | B81: =B80*B77 -> 3e-07 | C81: Latency/hop × hops | E81: One-Way Latency (s) | F81: =F80*F77 -> 3e-07 | G81: =G80*G77 -> 3e-07
A82: SHARP v4 Inter-Rack Reduction | B82: 0.5 | C82: In-network all-reduce traffic reduction (SHARP v4) | E82: SHARP v4 Reduction | F82: 0.5 | G82: 0.5 | H82: SHARP v4: 9x in-network compute vs NDR
A84: Multi-Rack Parallelism | B84: Data | C84: Note
A85: DP Replicas (racks) | B85: =B8 -> 5263 | C85: All racks run DP replicas (model fits in 1 rack)
A86: Inter-Rack Comm Overlap (Inference) | B86: 0.8 | C86: 80% inter-rack comm overlaps with compute in inference
A87: KV Cache Transfer per Request (bytes) | B87: =K45*B39*K46*(B27+B28) -> 67405000 | C87: KV elements/token/layer × layers × KV bytes × (input+output)
A88: KV Cache Transfer Time (s) | B88: =B87/(B79*1000000000000) -> 0.00067405 | C88: KV cache / effective inter-rack BW
A89: Disaggregated Prefill-Decode Overhead (s) | B89: =B88+B81 -> 0.00067435 | C89: KV transfer + one-way network latency

Sheet TL_Param
B1: Base Line
A2: # | B2: Step(time in s) | C2: Start Time | D2: Duration | E2: End Time | F2: Compute Time | G2: HBM BW Time | H2: NVLink Time | I2: Inter-Rack Time | J2: Bottleneck | K2: Dominant Resource | L2: FLOPs Used | M2: HBM Bytes Moved
A3: 1 | B3: Tokenization (CPU) | C3: 0 | D3: 0.05 | E3: =C3+D3 -> 0.05 | F3: N/A(CPU) | G3: N/A | H3: N/A | I3: N/A | J3: CPU | K3: CPU | L3: 0 | M3: 0
A4: 2 | B4: Embedding Lookup + Broadcast | C4: =E3 -> 0.05 | D4: =G4+H4+I4 -> 2.6264305e-06 | E4: =C4+D4 -> 0.050002626 | F4: 0 | G4: =WP_Param!B28*WP_Param!B29/(WP_Param!B15*1000000000000) -> 5.8650572e-07 | H4: =H17 -> 1.7399248e-06 | I4: =WP_Param!B293 -> 3e-07 | J4: =IF(MAX(F4,G4,H4,I4)=0,"N/A",IF(AND(MAX(F4,G4)>=H4,MAX(F4,G4)>=I4),"Memory",IF(H4>=I4,"NVLink","Inter-Rack"))) -> NVLink | K4: =IF(MAX(F4,G4,H4,I4)=0,"N/A",IF(AND(G4>=F4,G4>=H4,G4>=I4),"HBM BW",IF(AND(F4>=G4,F4>=H4,F4>=I4),"GPU",IF(H4>=I4,"NVLink","Inter-Rack")))) -> NVLink | L4: 0 | M4: =WP_Param!B22*WP_Param!B29+WP_Param!B28*WP_Param!B29 -> 1041367040
A5: 3 | B5: Prefill+KV Cache Write | C5: =E4 -> 0.050002626 | D5: =MAX(F5,G5)+H5+I5 -> 0.0092940014 | E5: =C5+D5 -> 0.059296628 | F5: =WP_Param!B70 -> 0.0016522518 | G5: =WP_Param!B87 -> 0.00053943012 | H5: =WP_Param!B96 -> 0.0076417497 | I5: =WP_Param!B294 -> 0 | J5: =IF(F5>=MAX(G5,H5,I5),"Compute",IF(G5>=MAX(H5,I5),"Memory",IF(H5>=I5,"NVLink","Inter-Rack"))) -> NVLink | K5: =IF(F5>=MAX(G5,H5,I5),"GPU",IF(G5>=MAX(H5,I5),"HBM BW",IF(H5>=I5,"NVLink","Inter-Rack"))) -> NVLink | L5: =WP_Param!B65 -> 2.0818372e+15 | M5: =WP_Param!B84 -> 8.522996e+11
A6: 4 | B6: Decode-First Token | C6: =E5 -> 0.059296628 | D6: =MAX(F6,G6) -> 1.517011e-05 | E6: =C6+D6 -> 0.059311798 | F6: =WP_Param!B121 -> 3.61424e-08 | G6: =WP_Param!B138 -> 1.517011e-05 | H6: - | I6: - | J6: =IF(F6>=MAX(G6,H6,I6),"Compute",IF(G6>=MAX(H6,I6),"Memory",IF(H6>=I6,"NVLink","Inter-Rack"))) -> Memory | K6: =IF(F6>=MAX(G6,H6,I6),"GPU",IF(G6>=MAX(H6,I6),"HBM BW",IF(H6>=I6,"NVLink","Inter-Rack"))) -> HBM BW | L6: =WP_Param!B117 -> 130112640000 | M6: =WP_Param!B135 -> 2.3968774e+10
A7: 5 | B7: Decode-All Tokens | C7: =E6 -> 0.059311798 | D7: =MAX(F7,G7)+H7+I7 -> 0.26000555 | E7: =C7+D7 -> 0.31931735 | F7: =WP_Param!B122 -> 3.61424e-05 | G7: =WP_Param!B138*WP_Param!B23 -> 0.01517011 | H7: =WP_Param!$B$149*WP_Param!$B$23+WP_Param!$B$200*WP_Param!$B$23 -> 0.24423544 | I7: =WP_Param!B295 -> 0.0006 | J7: =IF(F7>=MAX(G7,H7,I7),"Compute",IF(G7>=MAX(H7,I7),"Memory",IF(H7>=I7,"NVLink","Inter-Rack"))) -> NVLink | K7: =IF(F7>=MAX(G7,H7,I7),"GPU",IF(G7>=MAX(H7,I7),"HBM BW",IF(H7>=I7,"NVLink","Inter-Rack"))) -> NVLink | L7: =WP_Param!B118 -> 130112640000000 | M7: =WP_Param!B135*WP_Param!B23 -> 23968773918440
A8: 6 | B8: De-tokenization (CPU) | C8: =E7 -> 0.31931735 | D8: 0.05 | E8: =C8+D8 -> 0.36931735 | F8: N/A(CPU) | G8: N/A | H8: N/A | I8: N/A | J8: CPU | K8: CPU | L8: 0 | M8: 0
B9: Avg Time per Output Token (s) | E9: =E8/WP_Param!B23 -> 0.00036931735
B10: Total Output Token(s)/second | E10: =1/E9 -> 2707.6984
B14: Optimized — architecture KV + Concurrent Batch + Speculative Decoding + NVLink Optimization (v4: MoE-aware)
A15: # | B15: Step(time in s) | C15: Start Time | D15: Duration | E15: End Time | F15: Compute Time | G15: HBM BW Time | H15: NVLink Time | I15: Inter-Rack Time | J15: Bottleneck | K15: Dominant Resource | L15: FLOPs Used | M15: HBM Bytes Moved
A16: 1 | B16: Tokenization (CPU) | C16: 0 | D16: 0.05 | E16: =C16+D16 -> 0.05 | F16: N/A(CPU) | G16: N/A | H16: N/A | I16: N/A | J16: CPU | K16: CPU | L16: 0 | M16: 0
A17: 2 | B17: Embedding Lookup + Broadcast | C17: =E16 -> 0.05 | D17: =G17+H17+I17 -> 2.6264305e-06 | E17: =C17+D17 -> 0.050002626 | F17: 0 | G17: =WP_Param!B28*WP_Param!B29/(WP_Param!B15*1000000000000) -> 5.8650572e-07 | H17: =2*WP_Param!B22*WP_Param!B29*2*(71/72)/(WP_Param!B12*1000000000000) -> 1.7399248e-06 | I17: =WP_Param!B297 -> 3e-07 | J17: =IF(MAX(F17,G17,H17,I17)=0,"N/A",IF(AND(MAX(F17,G17)>=H17,MAX(F17,G17)>=I17),"Memory",IF(H17>=I17,"NVLink","Inter-Rack"))) -> NVLink | K17: =IF(MAX(F17,G17,H17,I17)=0,"N/A",IF(AND(G17>=F17,G17>=H17,G17>=I17),"HBM BW",IF(AND(F17>=G17,F17>=H17,F17>=I17),"GPU",IF(H17>=I17,"NVLink","Inter-Rack")))) -> NVLink | L17: 0 | M17: =WP_Param!B22*WP_Param!B29+WP_Param!B28*WP_Param!B29 -> 1041367040
A18: 3 | B18: Prefill+KV Cache Write | C18: =E17 -> 0.050002626 | D18: =MAX(F18,G18)+H18+I18 -> 0.3502801 | E18: =C18+D18 -> 0.40028273 | F18: =WP_Param!B70*WP_Param!B169 -> 0.10574411 | G18: =WP_Param!B87*WP_Param!B169 -> 0.034523528 | H18: =WP_Param!B97*WP_Param!B169 -> 0.24453599 | I18: =WP_Param!B294 -> 0 | J18: =IF(F18>=MAX(G18,H18,I18),"Compute",IF(G18>=MAX(H18,I18),"Memory",IF(H18>=I18,"NVLink","Inter-Rack"))) -> NVLink | K18: =IF(F18>=MAX(G18,H18,I18),"GPU",IF(G18>=MAX(H18,I18),"HBM BW",IF(H18>=I18,"NVLink","Inter-Rack"))) -> NVLink | L18: =WP_Param!B65*WP_Param!B169 -> 1.3323758e+17 | M18: =WP_Param!B84*WP_Param!B169 -> 5.4547174e+13
A19: 4 | B19: Decode-First Token | C19: =E18 -> 0.40028273 | D19: =MAX(F19,G19) -> 1.5170108e-05 | E19: =C19+D19 -> 0.4002979 | F19: =WP_Param!B121 -> 3.61424e-08 | G19: =WP_Param!B164 -> 1.5170108e-05 | H19: - | I19: - | J19: =IF(F19>=MAX(G19,H19,I19),"Compute",IF(G19>=MAX(H19,I19),"Memory",IF(H19>=I19,"NVLink","Inter-Rack"))) -> Memory | K19: =IF(F19>=MAX(G19,H19,I19),"GPU",IF(G19>=MAX(H19,I19),"HBM BW",IF(H19>=I19,"NVLink","Inter-Rack"))) -> HBM BW | L19: =WP_Param!B117 -> 130112640000 | M19: =WP_Param!B163 -> 2.396877e+10
A20: 5 | B20: Decode-All Tokens | C20: =E19 -> 0.4002979 | D20: =MAX(F20,G20)+H20+I20 -> 0.15678195 | E20: =C20+D20 -> 0.55707985 | F20: =WP_Param!B122*WP_Param!B169*(Config!B57+1)/Config!B59/Config!B46 -> 0.013482178 | G20: =WP_Param!B172*WP_Param!B23*WP_Param!B169/WP_Param!B178 -> 0.11262025 | H20: =(WP_Param!$B$205*WP_Param!$B$169+WP_Param!B206)*WP_Param!$B$23/WP_Param!$B$178 -> 0.044041697 | I20: =WP_Param!B296 -> 0.00012 | J20: =IF(F20>=MAX(G20,H20,I20),"Compute",IF(G20>=MAX(H20,I20),"Memory",IF(H20>=I20,"NVLink","Inter-Rack"))) -> Memory | K20: =IF(F20>=MAX(G20,H20,I20),"GPU",IF(G20>=MAX(H20,I20),"HBM BW",IF(H20>=I20,"NVLink","Inter-Rack"))) -> HBM BW | L20: =WP_Param!B118 -> 130112640000000 | M20: =WP_Param!B171*WP_Param!B23 -> 523351795827173 | N20: F20 fix (v4): decode compute × batch × (draft N+1)/accepted ÷ MFU; v3 ignored batch
A21: 6 | B21: De-tokenization (CPU) | C21: =E20 -> 0.55707985 | D21: 0.05 | E21: =C21+D21 -> 0.60707985 | F21: N/A(CPU) | G21: N/A | H21: N/A | I21: N/A | J21: CPU | K21: CPU | L21: 0 | M21: 0
B22: Avg Time per Output Token (s) | E22: =E21/(WP_Param!B169*WP_Param!B23) -> 9.4856227e-06 | G22: E2E / (Batch * Output)
B23: Total Output Token(s)/second | E23: =1/E22 -> 105422.71
B28: Rack-Independent Latency Outputs (with Inter-Rack Network)
C29: VR NVL72 E2E (s) | D29: GB200 NVL72 E2E (s)
C30: =D16 -> 0.05 | D30: =D16 -> 0.05
C31: =IF(Config!B7="Vera Rubin NVL72", D17, G17*(Config!G18/Config!F18) + H17*(Config!G15/Config!F15) + I17) -> 2.6264305e-06 | D31: =IF(Config!B7="Vera Rubin NVL72", G17*(Config!F18/Config!G18) + H17*(Config!F15/Config!G15) + I17, D17) -> 5.3886674e-06
C32: =IF(Config!B7="Vera Rubin NVL72", D18, F18*(IF(Config!B47="FP4",Config!G19,IF(Config!B47="FP8",Config!G21,Config!G22))/IF(Config!B47="FP4",Config!F19,IF(Config!B47="FP8",Config!F21,Config!F22))) + H18*(Config!G15/Config!F15) + I18) -> 0.3502801 | D32: =IF(Config!B7="Vera Rubin NVL72", F18*(IF(Config!B47="FP4",Config!F19,IF(Config!B47="FP8",Config!F21,Config!F22))/IF(Config!B47="FP4",Config!G19,IF(Config!B47="FP8",Config!G21,Config!G22))) + H18*(Config!F15/Config!G15) + I18, D18) -> 1.0765393
C33: =IF(Config!B7="Vera Rubin NVL72", D19, G19*(Config!G18/Config!F18)) -> 1.5170108e-05 | D33: =IF(Config!B7="Vera Rubin NVL72", G19*(Config!F18/Config!G18), D19) -> 4.1612448e-05
C34: =IF(Config!B7="Vera Rubin NVL72", D20, G20*(Config!G18/Config!F18) + H20*(Config!G15/Config!F15) + I20) -> 0.15678195 | D34: =IF(Config!B7="Vera Rubin NVL72", G20*(Config!F18/Config!G18) + H20*(Config!F15/Config!G15) + I20, D20) -> 0.39712701
C35: =D21 -> 0.05 | D35: =D21 -> 0.05
B36: Avg Time/Output Token (s) | C36: =SUM(C30:C35)/(Config!B56*Config!B28) -> 9.4856227e-06 | D36: =SUM(D30:D35)/(Config!B56*Config!B28) -> 2.458927e-05
B37: Tokens/sec per Rack | C37: =1/C36 -> 105422.71 | D37: =1/D36 -> 40668.145
B38: E2E Latency (s) | C38: =SUM(C30:C35) -> 0.60707985 | D38: =SUM(D30:D35) -> 1.5737133
B39: Inter-Rack Overhead % | C39: =(I17+I18+I20)/C38 -> 0.00019816174 | D39: =(I17+I18+I20)/D38 -> 7.6443404e-05
B42: ▶ INTER-RACK STRESS TEST — Scenario Comparison (VR NVL72)
B44: Parameter / Metric | C44: Current (IB XDR, Colocated) | D44: Scenario A Std Ethernet | E44: Scenario B Disaggregated | F44: Scenario C 16:1 Oversub | G44: Scenario D Ethernet + Disagg | H44: Scenario E All Worst-Case
B45: Network Assumptions
B46: Fabric Type | C46: IB XDR | D46: Std Ethernet | E46: IB XDR | F46: IB XDR | G46: Std Ethernet | H46: Std Ethernet
B47: Switch Latency (μs/hop) | C47: =Config!B76 -> 0.1 | D47: 5 | E47: =C47 -> 0.1 | F47: =C47 -> 0.1 | G47: =D47 -> 5 | H47: =D47 -> 5
B48: Network Hops | C48: =Config!B77 -> 3 | D48: =C48 -> 3 | E48: =C48 -> 3 | F48: =C48 -> 3 | G48: =C48 -> 3 | H48: 5
B49: One-Way Latency (s) | C49: =C47*C48/1000000 -> 3e-07 | D49: =D47*D48/1000000 -> 1.5e-05 | E49: =E47*E48/1000000 -> 3e-07 | F49: =F47*F48/1000000 -> 3e-07 | G49: =G47*G48/1000000 -> 1.5e-05 | H49: =H47*H48/1000000 -> 2.5e-05
B50: Oversubscription Ratio | C50: =Config!B78 -> 2 | D50: =C50 -> 2 | E50: =C50 -> 2 | F50: 16 | G50: =C50 -> 2 | H50: =F50 -> 16
B51: Eff. BW per GPU (TB/s) | C51: =Config!B73/C50 -> 0.1 | D51: =Config!B73/D50 -> 0.1 | E51: =Config!B73/E50 -> 0.1 | F51: =Config!B73/F50 -> 0.0125 | G51: =Config!B73/G50 -> 0.1 | H51: =Config!B73/H50 -> 0.0125
B52: Disaggregated Inference? | C52: No | D52: No | E52: Yes | F52: No | G52: Yes | H52: Yes
B53: Comm Overlap (Inference) | C53: =Config!B86 -> 0.8 | D53: =C53 -> 0.8 | E53: =C53 -> 0.8 | F53: =C53 -> 0.8 | G53: 0.5 | H53: 0.3
B55: Computed Inter-Rack Overhead
B56: Step 2: LB Routing (s) | C56: =C49 -> 3e-07 | D56: =D49 -> 1.5e-05 | E56: =E49 -> 3e-07 | F56: =F49 -> 3e-07 | G56: =G49 -> 1.5e-05 | H56: =H49 -> 2.5e-05
B57: Step 3: KV Cache Transfer (s) | C57: 0 | D57: 0 | E57: =WP_Param!B227/(E51*1000000000000)+E49 -> 0.00067435 | F57: 0 | G57: =WP_Param!B227/(G51*1000000000000)+G49 -> 0.00068905 | H57: =WP_Param!B227/(H51*1000000000000)+H49 -> 0.0054174
B58: Step 5: Token Streaming (s) | C58: =2*C49*Config!B28*(1-C53) -> 0.00012 | D58: =2*D49*Config!B28*(1-D53) -> 0.006 | E58: =2*E49*Config!B28*(1-E53) -> 0.00012 | F58: =2*F49*Config!B28*(1-F53) -> 0.00012 | G58: =2*G49*Config!B28*(1-G53) -> 0.015 | H58: =2*H49*Config!B28*(1-H53) -> 0.035
B59: Total Inter-Rack Overhead (s) | C59: =C56+C57+C58 -> 0.0001203 | D59: =D56+D57+D58 -> 0.006015 | E59: =E56+E57+E58 -> 0.00079465 | F59: =F56+F57+F58 -> 0.0001203 | G59: =G56+G57+G58 -> 0.01570405 | H59: =H56+H57+H58 -> 0.0404424
B61: Throughput Impact
B62: Intra-Rack E2E (s) | C62: =C38-SUM(I17,I18,I20) -> 0.60695955 | D62: =C62 -> 0.60695955 | E62: =C62 -> 0.60695955 | F62: =C62 -> 0.60695955 | G62: =C62 -> 0.60695955 | H62: =C62 -> 0.60695955
B63: Adjusted E2E (s) | C63: =C62+C59 -> 0.60707985 | D63: =D62+D59 -> 0.61297455 | E63: =E62+E59 -> 0.6077542 | F63: =F62+F59 -> 0.60707985 | G63: =G62+G59 -> 0.6226636 | H63: =H62+H59 -> 0.64740195
B64: Tokens/sec per Rack | C64: =1/(C63/(Config!B56*Config!B28)) -> 105422.71 | D64: =1/(D63/(Config!B56*Config!B28)) -> 104408.9 | E64: =1/(E63/(Config!B56*Config!B28)) -> 105305.73 | F64: =1/(F63/(Config!B56*Config!B28)) -> 105422.71 | G64: =1/(G63/(Config!B56*Config!B28)) -> 102784.23 | H64: =1/(H63/(Config!B56*Config!B28)) -> 98856.669
B65: Throughput Loss % | C65: =1-C64/$C$64 -> 0 | D65: =1-D64/$C$64 -> 0.0096165493 | E65: =1-E64/$C$64 -> 0.0011095769 | F65: =1-F64/$C$64 -> 0 | G65: =1-G64/$C$64 -> 0.025027559 | H65: =1-H64/$C$64 -> 0.062282945
B67: Annual Revenue Impact ($M) | C67: - | D67: =D65*Revenue_Model!B39 -> 12305.629 | E67: =E65*Revenue_Model!B39 -> 1419.8483 | F67: =F65*Revenue_Model!B39 -> 0 | G67: =G65*Revenue_Model!B39 -> 32026.025 | H67: =H65*Revenue_Model!B39 -> 79699.148
B68: Key Bottleneck | C68: Negligible | D68: Streaming latency | E68: KV cache transfer | F68: Negligible | G68: KV + streaming | H68: KV @ low BW

Sheet WP_Param
A1: AI DC Spec. | B1: Data | C1: Note
A2: Total power(W) | B2: =Config!B5 -> 1000000000
A3: PUE | B3: =Config!B6 -> 1.2
A4: Rack Type | B4: =Config!B7 -> Vera Rubin NVL72
A5: No.of racks | B5: =Config!B8 -> 5263
A7: Rack Spec. | B7: Data | C7: Note
A8: CPU Type | B8: =Config!B11 -> Vera CPU
A9: No. of CPU | B9: =Config!B12 -> 36
A10: GPU Type | B10: =Config!B13 -> Rubin GPU
A11: No. of GPU | B11: =Config!B14 -> 72
A12: NVLink Bandwidth(TB/s) | B12: =Config!B15 -> 260
A13: NVLink-C2C Bandwidth(TB/s) | B13: =Config!B16 -> 65
A14: GPU Memory(TB) | B14: =Config!B17 -> 20.7 | C14: 0.288/GPU
A15: Memory Bandwidth(TB) | B15: =Config!B18 -> 1580 | C15: 22/GPU
A16: FP4 Dense Inference(PFLOPS) | B16: =Config!B19 -> 3600 | C16: 50 PFLOPS/GPU (FP4 dense inference)
A17: FP4 Dense Training(PFLOPS) | B17: =Config!B20 -> 2520 | C17: 35/GPU
A18: FP8 Dense(PFLOPS) | B18: =Config!B21 -> 1152 | C18: 16 PFLOPS/GPU (FP8 dense)
A19: FP16/BF16 Dense(PFLOPS) | B19: =Config!B22 -> 288 | C19: 4/GPU
A21: Input/Output Tokens Setup | B21: Data | C21: Note
A22: Input Tokens: | B22: =Config!B27 -> 16000
A23: Output Tokens: | B23: =Config!B28 -> 1000
A25: Model Spec. | B25: Data | C25: Note
A26: Parameters | B26: =Config!B31 -> 1600000000000 | C26: From Config sheet
A27: Type | B27: =Config!B32 -> MoE
A28: vocab size(V) | B28: =Config!B37 -> 129280
A29: Hidden Dimension(d_model) | B29: =Config!B38 -> 7168 | C29: Given
A30: n_layers | B30: =Config!B39 -> 61 | C30: Given
A31: n_heads | B31: =Config!B40 -> 128
A32: d_head | B32: =Config!B41 -> 512
A33: d_ff(SwiGLU) | B33: =Config!B42 -> 1204291.6 | C33: derived from Parameters
A34: Parameters per Layer(Att) | B34: =Config!B43 -> 3.0203967e+08 | C34: Q_W+K_W+V_W+O_W=4*d_model^2
A35: Parameters per Layer(FFN) | B35: =Config!B44 -> 2.5897086e+10 | C35: 3 × d_model × d_ff
A36: Total Parameters per Layer | B36: =Config!B45 -> 2.6199125e+10
A37: Weight Memory(Byte) | B37: =B26*Config!B48 -> 811200000000 | C37: Parameters × Bytes/param (from Config Precision)
A38: Weight Memory(Byte)/GPU | B38: =B37/B11 -> 1.1266667e+10
A39: KV cache @ Beginning(Byte) | B39: =B161*B22*B30*Config!$K$46 -> 63440000 | C39: Architecture KV (MLA/CSA/GQA) × input × layers × KV bytes
A40: KV cache @ End(Byte) | B40: =B161*(B22+B23)*B30*Config!$K$46 -> 67405000 | C40: Architecture KV × (input+output) × layers × KV bytes
A41: KV cache per GPU @ End | B41: =B40/B11 -> 936180.56
A42: Memory required per GPU | B42: =B41*B169+B38 -> 1.1326582e+10 | C42: KV/GPU × Batch_Size + Weights/GPU (production serving)
A43: GPU Memory Headroom | B43: =B14/B11*1000000000000-B42 -> 2.7617342e+11 | C43: Check if GPU has enough memory
A45: Parallelism Strategy
A46: Tensor Parallelism (TP) | B46: =Config!B52 -> 72 | C46: TP degree (was linked to header cell Config!B51)
A48: Prefill Phase
A49: Prefill Flop Per Layer | B49: Data | C49: Note
A50: QKV Projections | B50: =2*B22*B34*0.75 -> 7.248952e+12 | C50: 2×input×(attn params/layer)×¾ — generalized from 2·in·3d²
A51: Q × Kᵀ (Attention Scores) | B51: =2*B22*(Config!$K$47*IF(Config!$K$48>0,MIN(B22,Config!$K$48),B22)+(1-Config!$K$47)*MIN(B22,Config!$K$49))*B31*B32 -> 4697620480000 | C51: 2×input×attended tokens×(heads×head_dim); attended = full-attn fraction × min(ctx,cap) + rest × compressed span
A52: Attention x V | B52: =2*B22*(Config!$K$47*IF(Config!$K$48>0,MIN(B22,Config!$K$48),B22)+(1-Config!$K$47)*MIN(B22,Config!$K$49))*B31*B32 -> 4697620480000 | C52: same as Q×Kᵀ
A53: Output Projection | B53: =2*B22*B34*0.25 -> 2.4163173e+12 | C53: 2×input×(attn params/layer)×¼
A54: FFN (SwiGLU, 3 matrices) | B54: =2*B22*B29*B33*3*Config!B35 -> 1.5067395e+13 | C54: 2*input*d_model*d_ff*3
A55: Norms / Softmax / Activations | B55: =5*B22*B29 -> 573440000 | C55: ~O(input × d_model)~=5*input*d_model
A56: Total Prefill Flop Per Layer | B56: =SUM(B50:B55) -> 3.4128479e+13
A58: Prefill Flop All Layers | B58: Data | C58: Note
A59: QKV Projections | B59: =B50*$B$30 -> 442186072746667 | C59: =B59/$B$65 -> 0.21240185
A60: Q × Kᵀ (Attention Scores) | B60: =B51*$B$30 -> 286554849280000 | C60: =B60/$B$65 -> 0.13764518
A61: Attention x V | B61: =B52*$B$30 -> 286554849280000 | C61: =B61/$B$65 -> 0.13764518
A62: Output Projection | B62: =B53*$B$30 -> 147395357582222 | C62: =B62/$B$65 -> 0.070800616
A63: FFN (SwiGLU, 3 matrices) | B63: =B54*$B$30 -> 919111111111111 | C63: =B63/$B$65 -> 0.44149038
A64: Norms / Softmax / Activations | B64: =B55*$B$30 -> 34979840000 | C64: =B64/$B$65 -> 1.680239e-05
A65: Total Prefill Flop | B65: =SUM(B59:B64) -> 2.0818372e+15 | C65: =B65/$B$65 -> 1
A67: Prefill Compute Time(s) | B67: Data | C67: Note
A68: Prefill Compute Time(Theoretical) | B68: =B65/Config!B49/1000000000000000 -> 0.00057828812
A69: MFU | B69: =Config!B46 -> 0.35 | C69: model FLOPS utilization (MFU)
A70: Prefill Compute Time(50% MFU) | B70: =B68/B69 -> 0.0016522518
A72: Prefill HBM Traffic per Layer (byte)
A73: model weights | B73: =Config!B48*(B34+B35) -> 1.3282957e+10 | C73: Bytes/param × (non-expert + all-expert params) per layer
A74: Activation reads/writes (intermediate tensors) | B74: =4*B22*B29 -> 458752000 | C74: ~4 activation tensors per layer: input*d_model
A75: KV cache write | B75: =B22*B161*Config!$K$46 -> 1040000 | C75: Architecture KV write: input × KV elements/token/layer × KV bytes
A76: FlashAttention internal I/O | B76: =2*B22*B29 -> 229376000 | C76: O(input × d_model)~=2*input*d_model
A77: Prefill HBM Traffic Per Layer | B77: =SUM(B73:B76) -> 1.3972125e+10
A79: Prefill HBM Traffic All (byte)
A80: model weights | B80: =B73*$B$30 -> 8.1026035e+11
A81: Activation reads/writes (intermediate tensors) | B81: =B74*$B$30 -> 27983872000
A82: KV cache write | B82: =B75*$B$30 -> 63440000
A83: FlashAttention internal I/O | B83: =B76*$B$30 -> 13991936000
A84: Total Prefill HBM Traffic All | B84: =SUM(B80:B83) -> 8.522996e+11
A86: Prefill HBM Traffic Time(s)
A87: Prefill HBM Traffic Time(Theoretical) | B87: =B84/B15/1000000000000 -> 0.00053943012
A88: Arithmetic intensity check | B88: =B65/B84 -> 2442.612 | C88: total Prefill flop/Total Prefill HBM Traffic(byte)>>797 roofline breakeven
A90: Prefill NVLink Communication (byte)
A91: all-reduce of the output activation size | B91: =B22*B29 -> 114688000 | C91: input*d_model
A92: Per all-reduce (ring-reduce) | B92: =2*(B11-1)/B11*B22*B29 -> 2.2619022e+08 | C92: 2*(no.of GPU-1)/(no. of GPU)*input*d_model
A93: Count per layer | B93: 2 | C93: all-reduces (one after attention output projection, one after FFN)
A94: Total per Layer | B94: =B92*B93 -> 4.5238044e+08 | C94: Per all-reduce * Count per layer
A95: Total NVLink Communication | B95: =B94*B30 -> 2.7595207e+10 | C95: Total per Layer*n_layers
A96: Total NVLink Communication Time(s) | B96: =B95/(B12/B11*1000000000000) -> 0.0076417497 | C96: Total NVLink Communication/per-GPU NVLink BW
A97: NVLink Communication Time with Sharp(s) | B97: =B96*0.5 -> 0.0038208748 | C97: SHARP in-network reduction (up to 50% traffic reduction)
A99: Total Prefill Time | B99: =B70+B87+B97 -> 0.0060125567 | C99: Compute Bound
A102: DECODE | C102: Avg context = input + output/2
A103: Decode Flop Per Layer | B103: Data | C103: Note
A104: QKV Projections (per tok) | B104: =2*B34*0.75 -> 4.530595e+08 | C104: 2×(attn params/layer)×¾ per token
A105: Q × Kᵀ (per tok, avg) | B105: =2*B31*B32*(Config!$K$47*IF(Config!$K$48>0,MIN((B22+0.5*B23),Config!$K$48),(B22+0.5*B23))+(1-Config!$K$47)*MIN((B22+0.5*B23),Config!$K$49)) -> 293601280 | C105: 2×(heads×head_dim)×attended tokens (avg ctx = input + output/2)
A106: Attention × V (per tok, avg) | B106: =2*B31*B32*(Config!$K$47*IF(Config!$K$48>0,MIN((B22+0.5*B23),Config!$K$48),(B22+0.5*B23))+(1-Config!$K$47)*MIN((B22+0.5*B23),Config!$K$49)) -> 293601280 | C106: same as Q×Kᵀ
A107: Output Projection (per tok) | B107: =2*B34*0.25 -> 1.5101983e+08 | C107: 2×(attn params/layer)×¼ per token
A108: FFN SwiGLU (per tok) | B108: =2*B29*B33*3*Config!B35 -> 9.417122e+08 | C108: 2*d_model*d_ff*3
A109: DECODE per Layer (per tok avg) | B109: =SUM(B104:B108) -> 2.1329941e+09
A111: Decode Flop All Layers | B111: Data | C111: Note
A112: QKV Projections (per tok) | B112: =B104*$B$30 -> 2.763663e+10 | C112: 2*1(1token)*d_model^2*3
A113: Q × Kᵀ (per tok, avg) | B113: =B105*$B$30 -> 17909678080 | C113: 2*d_model*(input+output/2)
A114: Attention × V (per tok, avg) | B114: =B106*$B$30 -> 17909678080 | C114: 2*d_model*(input+output/2)
A115: Output Projection (per tok) | B115: =B107*$B$30 -> 9.2122098e+09 | C115: 2*1(1token)*d_model^2
...

Sheet DC_Cost_Model
A1: Data Center Cost Model — 1 GW Vera Rubin NVL72 Facility
A3: Section 1: Data Center Specifications (from Config)
A4: Item | B4: Value | C4: Unit | E4: Source / Note
A5: Total IT Power | B5: =Config!F5/1000000 -> 1000 | C5: MW | E5: Config!F5 (VR preset, dropdown-independent)
A6: PUE | B6: =Config!F6 -> 1.2 | E6: Config!F6 (VR preset, dropdown-independent)
A7: Total Facility Power (IT × PUE) | B7: =B5*B6 -> 1200 | C7: MW | E7: Total electrical load including cooling, lighting, etc.
A8: Rack Type | B8: =Config!F7 -> Vera Rubin NVL72 | E8: Config!F7 (VR preset, dropdown-independent)
A9: Number of Racks | B9: =Config!F8 -> 5263 | C9: racks | E9: Config!F8 (VR preset, dropdown-independent)
A10: GPUs per Rack | B10: =Config!F14 -> 72 | C10: GPUs | E10: Config!F14 (VR preset, dropdown-independent)
A11: Total GPUs | B11: =B9*B10 -> 378936 | C11: GPUs | E11: Racks × GPUs per rack
A12: Power per Rack (est.) | B12: =B5*1000/B9 -> 190.0057 | C12: kW | E12: Total IT Power / Racks
A13: Total Facility Sq. Ft. (est.) | B13: =B9*80 -> 421040 | C13: sq ft | E13: ~80 sq ft per rack (AI liquid-cooled, incl. aisles + support)
A15: Section 2: Capital Expenditure (CapEx) Breakdown
A16: Category | B16: Unit Cost | C16: Quantity / Basis | D16: Total ($M) | E16: Assumption / Source | F16: % of CapEx
A17: 2A. IT Hardware (Servers & GPUs)
A18: =" "&Config!F7&" Racks" -> Vera Rubin NVL72 Racks | B18: =Config!F27 -> 6000000 | C18: =B9 -> 5263 | D18: =B18*C18/1000000 -> 31578 | E18: Est. $6M/rack per Config VR preset (F27); GB200 ~$3M, Rubin gen premium ~15-20% | F18: =D18/$D$54 -> 0.73039455
A19: Scale-out Networking (InfiniBand/Ethernet) | B19: 150000 | C19: =B9 -> 5263 | D19: =B19*C19/1000000 -> 789.45 | E19: Quantum-X800 IB + Spectrum-X Ethernet per-rack allocation | F19: =D19/$D$54 -> 0.018259864
A20: Top-of-Rack & Spine Switches | B20: 35000 | C20: =B9 -> 5263 | D20: =B20*C20/1000000 -> 184.205 | E20: Mgmt network, OOB, storage fabric per-rack allocation | F20: =D20/$D$54 -> 0.0042606349
A21: Storage & Boot Infrastructure | B21: 25000 | C21: =B9 -> 5263 | D21: =B21*C21/1000000 -> 131.575 | E21: NVMe boot drives, shared storage, cabling per rack | F21: =D21/$D$54 -> 0.0030433106
A22: Subtotal IT Hardware | D22: =SUM(D18:D21) -> 32683.23 | F22: =D22/$D$54 -> 0.75595836
A24: 2B. Land, Building & Site Work
A25: Land Acquisition (est. 100 acres) | B25: 200000 | C25: 100 | D25: =B25*C25/1000000 -> 20 | E25: ~100 acres; $200K/acre (semi-rural US, utility-adjacent) | F25: =D25/$D$54 -> 0.00046259709
A26: Building Shell & Core | B26: 3000000 | C26: =B7 -> 1200 | D26: =B26*C26/1000000 -> 3600 | E26: $3M/MW facility power; foundation, structure, envelope | F26: =D26/$D$54 -> 0.083267476
A27: Site Work & Civil (roads, grading, fencing) | B27: 500000 | C27: =B7 -> 1200 | D27: =B27*C27/1000000 -> 600 | E27: $500K/MW facility power; roads, grading, security fence | F27: =D27/$D$54 -> 0.013877913
A28: Subtotal Land & Building | D28: =SUM(D25:D27) -> 4220 | F28: =D28/$D$54 -> 0.097607986
A30: 2C. Electrical Infrastructure
A31: Substation & Grid Interconnection | B31: 1500000 | C31: =B7 -> 1200 | D31: =B31*C31/1000000 -> 1800 | E31: $1.5M/MW; HV substation, transformers, HV switchgear | F31: =D31/$D$54 -> 0.041633738
A32: Medium Voltage Distribution & PDUs | B32: 800000 | C32: =B7 -> 1200 | D32: =B32*C32/1000000 -> 960 | E32: $800K/MW; MV switchgear, busway, rack-level PDUs | F32: =D32/$D$54 -> 0.02220466
A33: Backup Generators (N+1 diesel/gas) | B33: 600000 | C33: =B7 -> 1200 | D33: =B33*C33/1000000 -> 720 | E33: $600K/MW; diesel/gas turbine gen-sets with N+1 redundancy | F33: =D33/$D$54 -> 0.016653495
A34: UPS & Battery Storage | B34: 400000 | C34: =B5 -> 1000 | D34: =B34*C34/1000000 -> 400 | E34: $400K/MW IT; UPS systems + Li-ion BESS for ride-through | F34: =D34/$D$54 -> 0.0092519418
A35: Subtotal Electrical | D35: =SUM(D31:D34) -> 3880 | F35: =D35/$D$54 -> 0.089743836
A37: 2D. Cooling & Mechanical Systems
A38: Liquid Cooling (CDUs, piping, cold plates) | B38: 56000 | C38: =B9 -> 5263 | D38: =B38*C38/1000000 -> 294.728 | E38: ~$56K/rack; Morgan Stanley est. cold plates + CDU piping | F38: =D38/$D$54 -> 0.0068170158
A39: Cooling Towers & Heat Rejection Plant | B39: 300000 | C39: =B7 -> 1200 | D39: =B39*C39/1000000 -> 360 | E39: $300K/MW; cooling towers, chillers, pumps, water treatment | F39: =D39/$D$54 -> 0.0083267476
A40: Fire Suppression & HVAC (non-IT areas) | B40: 100000 | C40: =B7 -> 1200 | D40: =B40*C40/1000000 -> 120 | E40: $100K/MW; clean agent suppression, office HVAC | F40: =D40/$D$54 -> 0.0027755825
A41: Subtotal Cooling & Mechanical | D41: =SUM(D38:D40) -> 774.728 | F41: =D41/$D$54 -> 0.017919346
A43: 2E. Fiber, Cabling & Security
A44: Fiber Optic & Structured Cabling | B44: 200000 | C44: =B7 -> 1200 | D44: =B44*C44/1000000 -> 240 | E44: $200K/MW; intra-campus dark fiber, cable trays, patch panels | F44: =D44/$D$54 -> 0.0055511651
A45: Physical Security & BMS | B45: 50000 | C45: =B7 -> 1200 | D45: =B45*C45/1000000 -> 60 | E45: $50K/MW; CCTV, access control, DCIM, BMS sensors | F45: =D45/$D$54 -> 0.0013877913
A46: Subtotal Fiber, Cabling & Security | D46: =SUM(D44:D45) -> 300 | F46: =D46/$D$54 -> 0.0069389564
A48: 2F. Soft Costs & Contingency
A49: Design, Engineering & Permitting | B49: 0.03 | C49: % of non-IT CapEx | D49: =B49*(D28+D35+D41+D46) -> 275.24184 | E49: 3% of facility CapEx; A&E, environmental, permits | F49: =D49/$D$54 -> 0.0063663037
A50: Project Management & Commissioning | B50: 0.02 | C50: % of non-IT CapEx | D50: =B50*(D28+D35+D41+D46) -> 183.49456 | E50: 2% of facility CapEx; PM, CxA, testing & validation | F50: =D50/$D$54 -> 0.0042442025
A51: Contingency | B51: 0.1 | C51: % of non-IT CapEx | D51: =B51*(D28+D35+D41+D46) -> 917.4728 | E51: 10% contingency on facility/infrastructure CapEx | F51: =D51/$D$54 -> 0.021221012
A52: Subtotal Soft Costs & Contingency | D52: =SUM(D49:D51) -> 1376.2092 | F52: =D52/$D$54 -> 0.031831519
A54: TOTAL CAPEX | D54: =D22+D28+D35+D41+D46+D52 -> 43234.167 | F54: 1
A56: CapEx Composition
A57: IT Hardware share | D57: =D22/D54 -> 0.75595836
A58: Facility Infrastructure share | D58: =(D28+D35+D41+D46)/D54 -> 0.21221012
A59: Soft Costs & Contingency share | D59: =D52/D54 -> 0.031831519
A60: CapEx per MW (IT) | D60: =D54/B5 -> 43.234167 | E60: $/MW of IT power
A61: CapEx per GPU | D61: =D54*1000000/B11 -> 114093.59 | E61: Total CapEx / Total GPUs
A63: Section 3: Annual Operating Expenditure (OpEx)
A64: Category | B64: Assumption | C64: Basis | D64: Annual ($M) | E64: Note / Source | F64: % of OpEx
A65: 3A. Depreciation (GAAP, Straight-Line)
A66: IT Hardware (servers, GPUs, networking) | B66: 5 | C66: years useful life | D66: =D22/B66 -> 6536.646 | E66: ASC 360; 5-yr life per hyperscaler practice (Meta, MSFT) | F66: =D66/$D$88 -> 0.70300298
A67: Building & Shell | B67: 30 | C67: years useful life | D67: =(D28-D25)/B67 -> 140 | E67: ASC 360; 30-yr life. Land ($20M) excluded — indefinite-lived asset per GAAP. | F67: =D67/$D$88 -> 0.015056715
A68: Electrical Infrastructure | B68: 20 | C68: years useful life | D68: =D35/B68 -> 194 | E68: ASC 360; 15-25yr for heavy electrical equipment | F68: =D68/$D$88 -> 0.020864305
A69: Cooling & Mechanical | B69: 15 | C69: years useful life | D69: =D41/B69 -> 51.648533 | E69: ASC 360; 10-20yr for HVAC/mechanical systems | F69: =D69/$D$88 -> 0.0055546947
A70: Fiber, Cabling & Security | B70: 10 | C70: years useful life | D70: =D46/B70 -> 30 | E70: ASC 360; 7-15yr for structured cabling/security | F70: =D70/$D$88 -> 0.003226439
A71: Subtotal Annual Depreciation | D71: =SUM(D66:D70) -> 6952.2945 | F71: =D71/$D$88 -> 0.74770513
A73: 3B. Electricity Cost
A74: Electricity Rate (blended) | B74: 0.06 | C74: $/kWh | E74: US industrial avg $0.05-0.08; PPA-negotiated rate
A75: Annual Energy (facility) | B75: =B7*8760 -> 10512000 | C75: MWh/year | E75: Facility MW × 8,760 hrs (100% utilization assumed)
A76: Annual Electricity Cost | D76: =B75*1000*B74/1000000 -> 630.72 | E76: MWh × 1000 kWh/MWh × $/kWh | F76: =D76/$D$88 -> 0.067832653
A77: Subtotal Electricity | D77: =D76 -> 630.72 | F77: =D77/$D$88 -> 0.067832653
A79: 3C. Maintenance & Operations
A80: IT Hardware Maintenance (spares, repair) | B80: 0.03 | C80: % of IT HW CapEx/yr | D80: =B80*D22 -> 980.4969 | E80: 3% of IT HW CapEx; GPU/NIC failures, spares pool | F80: =D80/$D$88 -> 0.10545045
A81: Facility Maintenance (MEP) | B81: 0.02 | C81: % of facility CapEx/yr | D81: =B81*(D28+D35+D41+D46) -> 183.49456 | E81: 2% of facility CapEx; preventive & corrective maintenance | F81: =D81/$D$88 -> 0.019734467
A82: Staff (DC ops, NOC, security, mgmt) | B82: 500 | C82: headcount (est.) | D82: =B82*150000/1000000 -> 75 | E82: 500 FTEs @ $150K avg loaded cost; ops, NOC, security | F82: =D82/$D$88 -> 0.0080660974
A83: Property Tax & Insurance | B83: 0.005 | C83: % of total CapEx/yr | D83: =B83*D54 -> 216.17084 | E83: 0.5% of total CapEx; property tax + all-risk insurance | F83: =D83/$D$88 -> 0.023248734
A84: Water & Consumables | B84: 50000 | C84: =B7 -> 1200 | D84: =B84*C84/1000000 -> 60 | E84: $50K/MW/yr; cooling water, chemicals, diesel fuel stores | F84: =D84/$D$88 -> 0.0064528779
A85: Software Licenses & Connectivity | B85: 200 | C85: $M/year | D85: 200 | E85: DCIM, NVIDIA AI Enterprise, WAN transit, peering | F85: =D85/$D$88 -> 0.021509593
A86: Subtotal Maintenance & Operations | D86: =SUM(D80:D85) -> 1715.1623 | F86: =D86/$D$88 -> 0.18446222
A88: TOTAL ANNUAL OPEX | D88: =D71+D77+D86 -> 9298.1768 | F88: 1
A90: OpEx Composition
A91: Depreciation share | D91: =D71/D88 -> 0.74770513
A92: Electricity share | D92: =D77/D88 -> 0.067832653
A93: Maintenance & Ops share | D93: =D86/D88 -> 0.18446222
A94: OpEx per GPU per year | D94: =D88*1000000/B11 -> 24537.592 | E94: Annual OpEx / Total GPUs
A97: Data Center Cost Model — 1 GW GB200 NVL72 Facility
A99: Section 1: Data Center Specifications (GB200 NVL72 Preset)
A100: Item | B100: Value | C100: Unit | E100: Source / Note
A101: Total IT Power | B101: =Config!G5/1000000 -> 1000 | C101: MW | E101: From Config GB200 NVL72 preset (Col G)
A102: PUE | B102: =Config!G6 -> 1.2 | E102: From Config GB200 NVL72 preset (Col G)
A103: Total Facility Power (IT × PUE) | B103: =B101*B102 -> 1200 | C103: MW | E103: Total electrical load including cooling, lighting, etc.
A104: Rack Type | B104: =Config!G7 -> GB200 NVL72 | E104: From Config GB200 NVL72 preset (Col G)
A105: Number of Racks | B105: =Config!G8 -> 7194 | C105: racks | E105: From Config GB200 NVL72 preset (Col G)
A106: GPUs per Rack | B106: =Config!G14 -> 72 | C106: GPUs | E106: From Config GB200 NVL72 preset (Col G)
A107: Total GPUs | B107: =B105*B106 -> 517968 | C107: GPUs | E107: Racks × GPUs per rack
A108: Power per Rack (est.) | B108: =B101*1000/B105 -> 139.00473 | C108: kW | E108: Total IT Power / Racks
A109: Total Facility Sq. Ft. (est.) | B109: =B105*80 -> 575520 | C109: sq ft | E109: ~80 sq ft per rack (AI liquid-cooled, incl. aisles + support)
A111: Section 2: Capital Expenditure (CapEx) Breakdown
F112: % of CapEx
A113: 2A. IT Hardware (Servers & GPUs) | B113: Unit Cost | C113: Quantity / Basis | D113: Total ($M) | E113: Assumption / Source
A114: =" "&Config!G7&" Racks" -> GB200 NVL72 Racks | B114: =Config!G27 -> 3000000 | C114: =B105 -> 7194 | D114: =B114*C114/1000000 -> 21582 | E114: Est. $3M/rack; GB200 NVL72 pricing per Config preset | F114: =D114/$D$150 -> 0.63912516
A115: Scale-out Networking (InfiniBand/Ethernet) | B115: 150000 | C115: =B105 -> 7194 | D115: =B115*C115/1000000 -> 1079.1 | E115: Quantum-2 IB + Spectrum-X Ethernet per-rack allocation | F115: =D115/$D$150 -> 0.031956258
A116: Top-of-Rack & Spine Switches | B116: 35000 | C116: =B105 -> 7194 | D116: =B116*C116/1000000 -> 251.79 | E116: Mgmt network, OOB, storage fabric per-rack allocation | F116: =D116/$D$150 -> 0.0074564602
A117: Storage & Boot Infrastructure | B117: 25000 | C117: =B105 -> 7194 | D117: =B117*C117/1000000 -> 179.85 | E117: NVMe boot drives, shared storage, cabling per rack | F117: =D117/$D$150 -> 0.005326043
A118: Subtotal IT Hardware | D118: =SUM(D114:D117) -> 23092.74 | F118: =D118/$D$150 -> 0.68386393
...

Sheet Revenue_Model
A1: Token Generation & Revenue Model — 1 GW Vera Rubin NVL72 Inference Facility
A3: Section 1: Inference Configuration (per Rack) — from Config
A4: Parameter | B4: Value | C4: Unit | E4: Source / Note
A5: Model Parameters | B5: =Config!B31 -> 1600000000000 | C5: params | E5: Linked from Config!B30
A6: Input Tokens per Request | B6: =Config!B27 -> 16000 | C6: tokens | E6: Linked from Config!B26
A7: Output Tokens per Request | B7: =Config!B28 -> 1000 | C7: tokens | E7: Linked from Config!B27
A8: Total Tokens per Request | B8: =B6+B7 -> 17000 | C8: tokens | E8: Input + Output
A9: Batch Size (concurrent requests) | B9: =Config!B56 -> 64 | C9: requests | E9: Linked from Config!B48
A10: Speculative Decoding Gain | B10: =Config!B59 -> 2.94117 | C10: tokens/step | E10: Expected tokens accepted per step, Config!B51
A11: End-to-End Latency per Request (optimized) | B11: =TL_Param!C38 -> 0.60707985 | C11: seconds | E11: From TL_Param!C38 (VR-specific, dropdown-independent)
A12: Number of Racks | B12: =Config!F8 -> 5263 | C12: racks | E12: Config!F8 (VR rack count, dropdown-independent)
A13: GPU Utilization Rate | B13: 0.7 | E13: Realistic + lean overhead; accounts for maintenance, failures, model swap
A14: Uptime (scheduled) | B14: 0.995 | E14: 99.5% SLA; ~43.8 hrs downtime/year
A15: Effective Annual Seconds per Rack | B15: =8760*3600*B13*B14 -> 21964824 | C15: seconds/yr | E15: 8,760 hrs × 3,600 s/hr × utilization × uptime
A16: Requests per Rack per Year | B16: =FLOOR(B15/B11,1)*B9 -> 2315591104 | C16: requests/yr | E16: (Effective seconds / Latency) × Batch Size
A18: Section 2: Annual Token Throughput (Entire DC)
A19: Metric | B19: Value | C19: Unit | E19: Calculation
A20: Total Requests per Year (all racks) | B20: =B16*B12 -> 12186955980352 | C20: requests/yr | E20: Requests/rack/yr × racks
A21: Annual Input Tokens | B21: =B20*B6 -> 1.949913e+17 | C21: tokens/yr | E21: Total requests × input tokens/request
A22: Annual Output Tokens | B22: =B20*B7 -> 1.2186956e+16 | C22: tokens/yr | E22: Total requests × output tokens/request
A23: Annual Total Tokens | B23: =B21+B22 -> 2.0717825e+17 | C23: tokens/yr | E23: Input + Output
A24: Annual Total Tokens (M) | B24: =B23/1000000 -> 2.0717825e+11 | C24: M tokens/yr | E24: Total / 1,000,000
A25: Annual Input Tokens (M) | B25: =B21/1000000 -> 1.949913e+11 | C25: M tokens/yr
A26: Annual Output Tokens (M) | B26: =B22/1000000 -> 1.2186956e+10 | C26: M tokens/yr
A27: Tokens per Second (DC-wide) | B27: =B23/(8760*3600) -> 6.5695793e+09 | C27: tokens/sec | E27: Annual tokens / seconds per year (gross throughput)
A28: Requests per Second (DC-wide) | B28: =B20/(8760*3600) -> 386445.84 | C28: req/sec | E28: Annual requests / seconds per year
A30: Section 3: Market Pricing & Annual Revenue
A31: Pricing Tier | B31: Value | C31: Unit | E31: Source / Note
A32: Market Rate — Input Tokens | B32: =Config!F42 -> 5 | C32: $/M input tokens | E32: Auto-selected from Config pricing tiers based on model size
A33: Market Rate — Output Tokens | B33: =Config!F43 -> 25 | C33: $/M output tokens | E33: Auto-selected from Config pricing tiers based on model size
A34: Blended Rate (weighted by I/O mix) | B34: =(B32*B25+B33*B26)/(B25+B26) -> 6.1764706 | C34: $/M tokens | E34: (Input rev + Output rev) / Total M tokens
A36: Revenue Calculation
A37: Annual Input Token Revenue | B37: =B25*B32/1000000 -> 974956.48 | C37: $M/year | E37: Input M tokens × $/M input
A38: Annual Output Token Revenue | B38: =B26*B33/1000000 -> 304673.9 | C38: $M/year | E38: Output M tokens × $/M output
A39: TOTAL ANNUAL REVENUE | B39: =B37+B38 -> 1279630.4 | C39: $M/year
A41: Revenue Composition
A42: Input token revenue share | B42: =B37/B39 -> 0.76190476
A43: Output token revenue share | B43: =B38/B39 -> 0.23809524
A44: Revenue per rack per year | B44: =B39/B12*1000000 -> 2.4313707e+08 | C44: $/rack/yr
A46: Rrevenue to opex | B46: =B39/DC_Cost_Model!D88 -> 137.62164
A47: Cost per Mtok | B47: =B34/B46 -> 0.044880082
A49: Token Generation & Revenue Model — 1 GW GB200 NVL72 Inference Facility
A51: Section 1: Inference Configuration (per Rack) — from Config
A52: Parameter | B52: Value | C52: Unit | E52: Source / Note
A53: Model Parameters | B53: =Config!B31 -> 1600000000000 | C53: params | E53: Linked from Config!B30
A54: Input Tokens per Request | B54: =Config!B27 -> 16000 | C54: tokens | E54: Linked from Config!B26
A55: Output Tokens per Request | B55: =Config!B28 -> 1000 | C55: tokens | E55: Linked from Config!B27
A56: Total Tokens per Request | B56: =B54+B55 -> 17000 | C56: tokens | E56: Input + Output
A57: Batch Size (concurrent requests) | B57: =Config!B56 -> 64 | C57: requests | E57: Linked from Config!B48
A58: Speculative Decoding Gain | B58: =Config!B59 -> 2.94117 | C58: tokens/step | E58: Expected tokens accepted per step, Config!B51
A59: End-to-End Latency per Request (optimized) | B59: =TL_Param!D38 -> 1.5737133 | C59: seconds | E59: From TL_Param!D38 (GB200-specific, dropdown-independent)
A60: Number of Racks | B60: =Config!G8 -> 7194 | C60: racks | E60: Config!G8 (GB200 rack count, dropdown-independent)
A61: GPU Utilization Rate | B61: 0.7 | E61: Realistic + lean overhead; accounts for maintenance, failures, model swap
A62: Uptime (scheduled) | B62: 0.995 | E62: 99.5% SLA; ~43.8 hrs downtime/year
A63: Effective Annual Seconds per Rack | B63: =8760*3600*B61*B62 -> 21964824 | C63: seconds/yr | E63: 8,760 hrs × 3,600 s/hr × utilization × uptime
A64: Requests per Rack per Year | B64: =FLOOR(B63/B59,1)*B57 -> 893268608 | C64: requests/yr | E64: (Effective seconds / Latency) × Batch Size
A66: Section 2: Annual Token Throughput (Entire DC)
A67: Metric | B67: Value | C67: Unit | E67: Calculation
A68: Total Requests per Year (all racks) | B68: =B64*B60 -> 6426174365952 | C68: requests/yr | E68: Requests/rack/yr × racks
A69: Annual Input Tokens | B69: =B68*B54 -> 1.0281879e+17 | C69: tokens/yr | E69: Total requests × input tokens/request
A70: Annual Output Tokens | B70: =B68*B55 -> 6.4261744e+15 | C70: tokens/yr | E70: Total requests × output tokens/request
A71: Annual Total Tokens | B71: =B69+B70 -> 1.0924496e+17 | C71: tokens/yr | E71: Input + Output
A72: Annual Total Tokens (M) | B72: =B71/1000000 -> 1.0924496e+11 | C72: M tokens/yr | E72: Total / 1,000,000
A73: Annual Input Tokens (M) | B73: =B69/1000000 -> 1.0281879e+11 | C73: M tokens/yr
A74: Annual Output Tokens (M) | B74: =B70/1000000 -> 6.4261744e+09 | C74: M tokens/yr
A75: Tokens per Second (DC-wide) | B75: =B71/(8760*3600) -> 3.4641351e+09 | C75: tokens/sec | E75: Annual tokens / seconds per year (gross throughput)
A76: Requests per Second (DC-wide) | B76: =B68/(8760*3600) -> 203772.65 | C76: req/sec | E76: Annual requests / seconds per year
A78: Section 3: Market Pricing & Annual Revenue
A79: Pricing Tier | B79: Value | C79: Unit | E79: Source / Note
A80: Market Rate — Input Tokens | B80: =Config!F42 -> 5 | C80: $/M input tokens | E80: Auto-selected from Config pricing tiers based on model size
A81: Market Rate — Output Tokens | B81: =Config!F43 -> 25 | C81: $/M output tokens | E81: Auto-selected from Config pricing tiers based on model size
A82: Blended Rate (weighted by I/O mix) | B82: =(B80*B73+B81*B74)/(B73+B74) -> 6.1764706 | C82: $/M tokens | E82: (Input rev + Output rev) / Total M tokens
A84: Revenue Calculation
A85: Annual Input Token Revenue | B85: =B73*B80/1000000 -> 514093.95 | C85: $M/year | E85: Input M tokens × $/M input
A86: Annual Output Token Revenue | B86: =B74*B81/1000000 -> 160654.36 | C86: $M/year | E86: Output M tokens × $/M output
A87: TOTAL ANNUAL REVENUE | B87: =B85+B86 -> 674748.31 | C87: $M/year
A89: Revenue Composition
A90: Input token revenue share | B90: =B85/B87 -> 0.76190476
A91: Output token revenue share | B91: =B86/B87 -> 0.23809524
A92: Revenue per rack per year | B92: =B87/B60*1000000 -> 93793204 | C92: $/rack/yr
A94: Rrevenue to opex | B94: =B87/DC_Cost_Model!D184 -> 95.649213
A95: Cost per Mtok | B95: =B82/B94 -> 0.064574192

Sheet OpenAI_Sim
A1: OpenAI Financial Simulation — Calibrating 1 GW VR72 DC Model to OpenAI's Disclosed Financials (Feb 2026 Funding Round)
A3: Section 1: OpenAI Disclosed Financials & Operating Metrics (Feb-2026 base; Sep-2026 FT update applied — see FT_Sep2026)
A4: Metric | B4: 2024A | C4: 2025A | D4: 2026E | E4: 2027E | F4: 2028E | G4: 2029E | H4: 2030E | I4: Source / Note
A5: Revenue ($B) | B5: 3.7 | C5: 13.1 | D5: =FT_Sep2026!E6 -> 36 | H5: =FT_Sep2026!E8 -> 350 | I5: 2025A $13.1B (CNBC). 2026E $36B / 2030E $350B: Jul-2026 deck per FT 2026-09-18 [Interested-party]; prior 2030 target $280B (Feb-2026)
A6: ARR ($B, exit rate) | B6: 6 | C6: 20 | I6: OpenAI CFO blog: $2B (2023) → $6B (2024) → $20B+ (2025)
A7: YoY Revenue Growth | B7: =B5/3.7-1 -> 0 | C7: =C5/B5-1 -> 2.5405405 | I7: Implied from reported revenue figures
A8: Cash Burn ($B) | B8: -5 | C8: -8 | D8: -25 | E8: -57 | H8: 39 | I8: Feb-2026 vintage (The Information): 2026 −$25B, 2027 −$57B, 2026–29 cum −$218B (2028–29 not split), 2030 +$39B. Jul-2026 vintage: 2026–30 cum −$278B (FT) → FT_Sep2026
A9: Gross Margin | B9: 0.4 | C9: 0.33
A11: Compute Capacity, Year-End (GW) | B11: 0.6 | C11: 1.9 | D11: 3.5 | E11: 4.5 | F11: 5.75 | G11: 7 | H11: 10 | I11: Year-end capacity: 0.6 GW (2024) → 1.9 GW (2025) → 10 GW (2030 Stargate)
A12: Compute Capacity, FY Avg (GW) | B12: =(0.2+B11)/2 -> 0.4 | C12: =(B11+C11)/2 -> 1.25 | D12: =(C11+D11)/2 -> 2.7 | E12: =(D11+E11)/2 -> 4 | F12: =(E11+F11)/2 -> 5.125 | G12: =(F11+G11)/2 -> 6.375 | H12: =(G11+H11)/2 -> 8.5 | I12: FY average = midpoint of prior year-end and current year-end (linear ramp)
A13: Weekly Active Users (M) | C13: 900 | I13: 900M WAU, 50M+ paid subscribers (Feb 2026)
A14: Paid Subscribers (M) | C14: 50 | I14: 50M+ consumer subscribers
A16: Latest Funding Round
A17: Total Raised | B17: $122B | I17: Closed 2026-03-31: $122B committed (Amazon / Nvidia / SoftBank anchor) [Verified]
A18: Pre-Money Valuation | B18: $730B | I18: Pre-money $730B; post-money $852B
A19: Post-Money Valuation | B19: $852B | I19: Largest private funding round in history
A20: Implied Revenue Multiple (on 2025 rev) | B20: =B113/C5 -> 65.038168 | I20: Post-money valuation / 2025 actual revenue
A21: Implied Revenue Multiple (on 2030E rev) | B21: =B113/H5 -> 2.4342857 | I21: Post-money valuation / 2030E target revenue
A22: Infrastructure Spend Target (by 2030) | B22: $856B | I22: Jul-2026 deck: ~$856B compute & infrastructure through 2030 (Feb-2026: ~$600B "compute"; category may differ)
A23: Stargate Capacity Target | B23: 10 GW | I23: Stargate: $500B / 4 yrs / 10 GW US-based AI infra
A24: New Round Talks (Sep 2026, valuation ≥) | B24: =FT_Sep2026!E19 -> 1200 | I24: FT/Bloomberg: investors discussed ≥$1.2T; OpenAI seeking higher [Interested-party]
A25: Section 2: Infrastructure Calibration — Scaling Our 1 GW VR72 Model to OpenAI's 1.9 GW (2025)
A26: Parameter | B26: Our 1 GW Model | C26: OpenAI 1.9 GW | D26: Unit | I26: Note
A27: IT Power (MW) | B27: =Config!F5/1000000 -> 1000 | C27: =C11*1000 -> 1900 | D27: MW | I27: Config!F5 (VR preset, dropdown-independent); OpenAI from CFO blog
A28: PUE | B28: =Config!F6 -> 1.2 | C28: 1.25 | I28: Mixed fleet PUE slightly higher (H100/A100 legacy + newer)
A29: Total Facility Power (MW) | B29: =B27*B28 -> 1200 | C29: =C27*C28 -> 2375 | D29: MW | I29: IT Power × PUE
A30: Scale Factor (vs our 1 GW model) | B30: 1 | C30: =C27/B27 -> 1.9 | I30: Simple linear scaling of IT power
A32: Hardware Mix Adjustment
A33: Current Fleet (est.) | B33: 100% VR NVL72 | C33: Mixed (H100/GB200/VR) | I33: OpenAI runs mixed generations; our model = next-gen only
A34: Inference Efficiency Factor | B34: 1 | C34: =C100*0.25+C101*(TL_Param!D37/TL_Param!C37)+C102*1 -> 0.2907288 | I34: Fleet-weighted VR-equiv factor: H100=0.25x, GB200≈0.39x (TL_Param!D37/C37), VR=1.0x
A35: Effective VR-Equivalent Power (MW) | B35: =B27*B34 -> 1000 | C35: =C27*C34 -> 552.38473 | D35: MW-eq | I35: Reference facility IT power × fleet efficiency factor = VR-equivalent MW
A37: Implied from Financials
A38: Our Model CapEx ($B) | B38: =DC_Cost_Model!D54/1000 -> 43.234167 | I38: From DC_Cost_Model total CapEx
A39: OpenAI Implied CapEx at 1.9 GW ($B) | C39: =B38*C30 -> 82.144918 | I39: Scaled linearly from our 1 GW model
A40: Our Model Annual OpEx ($B) | B40: =DC_Cost_Model!D88/1000 -> 9.2981768 | I40: From DC_Cost_Model total annual OpEx
A41: OpenAI Implied DC OpEx at 1.9 GW ($B) | C41: =B40*C30 -> 17.666536 | I41: DC-only OpEx; does not include R&D, S&M, G&A, SBC
A43: Section 3: OpenAI P&L Simulation — Reverse-Engineering from Disclosed Numbers
A44: Line Item | B44: 2024A ($B) | C44: 2025A ($B) | D44: 2026E ($B) | E44: 2027E ($B) | F44: 2028E ($B) | G44: 2029E ($B) | H44: 2030E ($B) | I44: Assumption / Source
A45: Assumptions
A46: Revenue Growth Rate (YoY) | C46: =C7 -> 2.5405405 | D46: =FT_Sep2026!B25 -> 1.7480916 | E46: =FT_Sep2026!C25 -> 1.0861111 | F46: =FT_Sep2026!D25 -> 0.88415446 | G46: =FT_Sep2026!E25 -> 0.67773852 | H46: =FT_Sep2026!F25 -> 0.47430497 | I46: 2025 actual 254%; 2026–30 from FT_Sep2026 row 25 (Jul-2026 deck path: $36B → $350B, Σ $840B)
A47: Gross Margin | B47: =B9 -> 0.4 | C47: =C9 -> 0.33 | D47: =D61 -> 0.61288695 | E47: =E61 -> 0.69373677 | F47: =F61 -> 0.76537172 | G47: =G61 -> 0.816269 | H47: =H61 -> 0.82838222 | I47: Now derived from bottom-up DC cost model (row 60); 2024-2025 actual
A48: R&D as % of Revenue | B48: 0.68 | C48: 0.51 | D48: 0.4 | E48: 0.3 | F48: 0.25 | G48: 0.2 | H48: 0.15 | I48: $2.5B (2024); $6.7B H1 2025 → ~$13B ann.
A49: S&M as % of Revenue | B49: 0.27 | C49: 0.15 | D49: 0.12 | E49: 0.1 | F49: 0.08 | G49: 0.065 | H49: 0.05 | I49: ~$2B in H1 2025 → ~$4B ann.; declining with scale
A50: G&A as % of Revenue | B50: 0.08 | C50: 0.06 | D50: 0.05 | E50: 0.045 | F50: 0.04 | G50: 0.035 | H50: 0.03 | I50: Est. corporate overhead; declining leverage with scale
A51: SBC as % of Revenue | B51: 0.68 | C51: 0.19 | D51: 0.12 | E51: 0.09 | F51: 0.06 | G51: 0.045 | H51: 0.03 | I51: ~$2.5B H1 2025 → $5B ann.; dilutes as rev scales
A52: MS Revenue Share % | B52: 0.2 | C52: 0.2 | D52: 0.2 | E52: 0.175 | F52: 0.15 | G52: 0.125 | H52: 0.1 | I52: 20% rev share to MS; may reduce post-PBC conversion
A53: CapEx (infra investment, $B) | B53: 5 | C53: 15 | D53: 40 | E53: 60 | F53: 100 | G53: 125 | H53: 150 | I53: Owned (balance-sheet) CapEx [Assumed, v2 path]; total compute & infra $856B incl. leased → FT_Sep2026 rows 39–41
A54: Bottom-Up COGS (from DC_Cost_Model fleet economics)
A55: OpEx/GW: Legacy H100 ($B) | B55: 5.631 | C55: 5.631 | D55: 5.631 | E55: 5.631 | F55: 5.631 | G55: 5.631 | H55: 5.631 | I55: Est: $20B CapEx, 5yr depr + $0.63B elec + $1.0B maint
A56: OpEx/GW: GB200 NVL72 ($B) | B56: =DC_Cost_Model!D184/1000 -> 7.0544052 | C56: =DC_Cost_Model!D184/1000 -> 7.0544052 | D56: =DC_Cost_Model!D184/1000 -> 7.0544052 | E56: =DC_Cost_Model!D184/1000 -> 7.0544052 | F56: =DC_Cost_Model!D184/1000 -> 7.0544052 | G56: =DC_Cost_Model!D184/1000 -> 7.0544052 | H56: =DC_Cost_Model!D184/1000 -> 7.0544052 | I56: Linked from DC_Cost_Model GB200 section (D184 / 1GW)
A57: OpEx/GW: VR NVL72 ($B) | B57: =DC_Cost_Model!D88/1000 -> 9.2981768 | C57: =DC_Cost_Model!D88/1000 -> 9.2981768 | D57: =DC_Cost_Model!D88/1000 -> 9.2981768 | E57: =DC_Cost_Model!D88/1000 -> 9.2981768 | F57: =DC_Cost_Model!D88/1000 -> 9.2981768 | G57: =DC_Cost_Model!D88/1000 -> 9.2981768 | H57: =DC_Cost_Model!D88/1000 -> 9.2981768 | I57: Linked from DC_Cost_Model VR section (D88 / 1GW)
A58: Fleet-Weighted DC OpEx ($B) | B58: =B94*(B100*B55+B101*B56+B102*B57) -> 2.2524 | C58: =C94*(C100*C55+C101*C56+C102*C57) -> 7.572527 | D58: =D94*(D100*D55+D101*D56+D102*D57) -> 18.336934 | E58: =E94*(E100*E55+E101*E56+E102*E57) -> 30.263642 | F58: =F94*(F100*F55+F101*F56+F102*F57) -> 43.684081 | G58: =G94*(G100*G55+G101*G56+G102*G57) -> 57.391762 | H58: =H94*(H100*H55+H101*H56+H102*H57) -> 79.034503 | I58: Σ(GW × fleet_share × OpEx/GW) per hardware type
A59: COGS / DC OpEx Ratio | B59: 0.78 | C59: =C68*(1-C9)/C58 -> 1.1590583 | D59: 0.76 | E59: 0.76 | F59: 0.76 | G59: 0.76 | H59: 0.76 | I59: ← Adjustable. Captures inference share + Azure markup + non-compute COGS. Calibrated to 2025 actual.
A60: Bottom-Up COGS ($B) | B60: =B58*B59 -> 1.756872 | C60: =C58*C59 -> 8.777 | D60: =D58*D59 -> 13.93607 | E60: =E58*E59 -> 23.000368 | F60: =F58*F59 -> 33.199902 | G60: =G58*G59 -> 43.617739 | H60: =H58*H59 -> 60.066222 | I60: Fleet DC OpEx × COGS ratio
A61: → Implied Gross Margin | B61: =1-B60/B68 -> 0.52516973 | C61: =1-C60/C68 -> 0.33 | D61: =1-D60/D68 -> 0.61288695 | E61: =1-E60/E68 -> 0.69373677 | F61: =1-F60/F68 -> 0.76537172 | G61: =1-G60/G68 -> 0.816269 | H61: =1-H60/H68 -> 0.82838222 | I61: 1 - COGS / Gross Revenue (bottom-up)
A67: Income Statement
A68: Revenue (gross) | B68: =B5 -> 3.7 | C68: =C5 -> 13.1 | D68: =C68*(1+D46) -> 36 | E68: =D68*(1+E46) -> 75.1 | F68: =E68*(1+F46) -> 141.5 | G68: =F68*(1+G46) -> 237.4 | H68: =G68*(1+H46) -> 350 | I68: 2024-2025 actual; 2026+ from growth assumptions
A69: Less: MS Revenue Share | B69: =-B68*B52 -> -0.74 | C69: =-C68*C52 -> -2.62 | D69: =-D68*D52 -> -7.2 | E69: =-E68*E52 -> -13.1425 | F69: =-F68*F52 -> -21.225 | G69: =-G68*G52 -> -29.675 | H69: =-H68*H52 -> -35 | I69: Revenue share paid to Microsoft
A70: Net Revenue | B70: =B68+B69 -> 2.96 | C70: =C68+C69 -> 10.48 | D70: =D68+D69 -> 28.8 | E70: =E68+E69 -> 61.9575 | F70: =F68+F69 -> 120.275 | G70: =G68+G69 -> 207.725 | H70: =H68+H69 -> 315 | I70: Gross revenue minus MS share
A72: Cost of Revenue (COGS) | B72: =-B60 -> -1.756872 | C72: =-C60 -> -8.777 | D72: =-D60 -> -13.93607 | E72: =-E60 -> -23.000368 | F72: =-F60 -> -33.199902 | G72: =-G60 -> -43.617739 | H72: =-H60 -> -60.066222 | I72: From bottom-up DC cost model (row 59)
A73: Gross Profit | B73: =B70+B72 -> 1.203128 | C73: =C70+C72 -> 1.703 | D73: =D70+D72 -> 14.86393 | E73: =E70+E72 -> 38.957132 | F73: =F70+F72 -> 87.075098 | G73: =G70+G72 -> 164.10726 | H73: =H70+H72 -> 254.93378 | I73: Net Revenue less COGS
A74: Gross Margin | B74: =B73/B70 -> 0.40646216 | C74: =C73/C70 -> 0.1625 | D74: =D73/D70 -> 0.51610869 | E74: =E73/E70 -> 0.62877185 | F74: =F73/F70 -> 0.72396673 | G74: =G73/G70 -> 0.79002171 | H74: =H73/H70 -> 0.80931358 | I74: On NET revenue basis (after MS share); differs from C46 which is on gross revenue
A76: R&D Expense | B76: =-B68*B48 -> -2.516 | C76: =-C68*C48 -> -6.681 | D76: =-D68*D48 -> -14.4 | E76: =-E68*E48 -> -22.53 | F76: =-F68*F48 -> -35.375 | G76: =-G68*G48 -> -47.48 | H76: =-H68*H48 -> -52.5 | I76: Training compute, research staff, model dev
A77: S&M Expense | B77: =-B68*B49 -> -0.999 | C77: =-C68*C49 -> -1.965 | D77: =-D68*D49 -> -4.32 | E77: =-E68*E49 -> -7.51 | F77: =-F68*F49 -> -11.32 | G77: =-G68*G49 -> -15.431 | H77: =-H68*H49 -> -17.5 | I77: Sales, marketing, user acquisition
A78: G&A Expense | B78: =-B68*B50 -> -0.296 | C78: =-C68*C50 -> -0.786 | D78: =-D68*D50 -> -1.8 | E78: =-E68*E50 -> -3.3795 | F78: =-F68*F50 -> -5.66 | G78: =-G68*G50 -> -8.309 | H78: =-H68*H50 -> -10.5 | I78: Legal, admin, finance, office
A79: SBC Expense | B79: =-B68*B51 -> -2.516 | C79: =-C68*C51 -> -2.489 | D79: =-D68*D51 -> -4.32 | E79: =-E68*E51 -> -6.759 | F79: =-F68*F51 -> -8.49 | G79: =-G68*G51 -> -10.683 | H79: =-H68*H51 -> -10.5 | I79: Stock-based compensation
A80: Total OpEx (incl. COGS) | B80: =B72+B76+B77+B78+B79 -> -8.083872 | C80: =C72+C76+C77+C78+C79 -> -20.698 | D80: =D72+D76+D77+D78+D79 -> -38.77607 | E80: =E72+E76+E77+E78+E79 -> -63.178868 | F80: =F72+F76+F77+F78+F79 -> -94.044902 | G80: =G72+G76+G77+G78+G79 -> -125.52074 | H80: =H72+H76+H77+H78+H79 -> -151.06622 | I80: COGS + R&D + S&M + G&A + SBC
A82: Operating Income (Loss) | B82: =B70+B80 -> -5.123872 | C82: =C70+C80 -> -10.218 | D82: =D70+D80 -> -9.9760696 | E82: =E70+E80 -> -1.2213683 | F82: =F70+F80 -> 26.230098 | G82: =G70+G80 -> 82.204261 | H82: =H70+H80 -> 163.93378 | I82: Net Revenue less Total OpEx
A83: Operating Margin (on net rev) | B83: =B82/B70 -> -1.7310378 | C83: =C82/C70 -> -0.975 | D83: =D82/D70 -> -0.34639131 | E83: =E82/E70 -> -0.019713002 | F83: =F82/F70 -> 0.21808438 | G83: =G82/G70 -> 0.395736 | H83: =H82/H70 -> 0.52042469
A85: Disclosed Cash Burn (actual) | B85: =B8 -> -5 | C85: =C8 -> -8 | D85: =D8 -> -25 | E85: =E8 -> -57 | H85: =H8 -> 39 | I85: Actual/projected disclosed cash burn
A86: Free Cash Flow — 2024-25: legacy formula; 2026-30: v3 cash bridge (FT_Sep2026 row 46) | B86: =B82-B53+ABS(B79) -> -7.607872 | C86: =C82-C53+ABS(C79) -> -22.729 | D86: =FT_Sep2026!B46 -> -55.164211 | E86: =FT_Sep2026!C46 -> -66.070316 | F86: =FT_Sep2026!D46 -> -91.065526 | G86: =FT_Sep2026!E46 -> -60.270158 | H86: =FT_Sep2026!F46 -> -4.3157895 | I86: v3: cash basis (no depreciation double count) with full $856B compute & infra; 2024–25 keep legacy OpInc−CapEx+SBC (historical, not re-based)
A87: Δ vs Disclosed | B87: =B86-B85 -> -2.607872 | C87: =C86-C85 -> -14.729 | D87: =D86-D85 -> -30.164211 | E87: =E86-E85 -> -9.0703158 | H87: =H86-H85 -> -43.315789 | I87: Variance vs Feb-2026 vintage (only years disclosed individually)
A88: Cum. FCF 2026–30: v3 vs Jul-2026 deck (−$278B) | B88: =FT_Sep2026!G46 -> -276.886 | C88: =FT_Sep2026!G54 -> 1.114 | I88: B = v3 cumulative; C = v3 minus deck (+ = v3 less negative)
A89: Section 4: Infrastructure Spend Waterfall & Compute Ramp
A90: Metric | B90: 2024A | C90: 2025A | D90: 2026E | E90: 2027E | F90: 2028E | G90: 2029E | H90: 2030E | I90: Source / Note
A91: Annual CapEx ($B) | B91: =B53 -> 5 | C91: =C53 -> 15 | D91: =D53 -> 40 | E91: =E53 -> 60 | F91: =F53 -> 100 | G91: =G53 -> 125 | H91: =H53 -> 150 | I91: From assumptions; ~$600B cumulative by 2030
A92: Cumulative CapEx ($B) | B92: =B91 -> 5 | C92: =B92+C91 -> 20 | D92: =C92+D91 -> 60 | E92: =D92+E91 -> 120 | F92: =E92+F91 -> 220 | G92: =F92+G91 -> 345 | H92: =G92+H91 -> 495 | I92: Running total of cumulative CapEx
A94: Compute Capacity, FY Avg (GW) | B94: =B12 -> 0.4 | C94: =C12 -> 1.25 | D94: =D12 -> 2.7 | E94: =E12 -> 4 | F94: =F12 -> 5.125 | G94: =G12 -> 6.375 | H94: =H12 -> 8.5 | I94: FY average capacity (from Section 1); used for COGS and revenue-per-GW matching
A95: Compute Capacity, Year-End (GW) | B95: =B11 -> 0.6 | C95: =C11 -> 1.9 | D95: =D11 -> 3.5 | E95: =E11 -> 4.5 | F95: =F11 -> 5.75 | G95: =G11 -> 7 | H95: =H11 -> 10 | I95: Year-end capacity; used for CapEx per GW calculation
A96: CapEx per GW ($B/GW) | B96: =B91/(B95-0) -> 8.3333333 | C96: =C91/(C95-B95) -> 11.538462 | D96: =D91/(D95-C95) -> 25 | E96: =E91/(E95-D95) -> 60 | F96: =F91/(F95-E95) -> 80 | G96: =G91/(G95-F95) -> 100 | H96: =H91/(H95-G95) -> 50 | I96: Marginal CapEx per NEW GW deployed (Annual CapEx / New GW added)
A97: Our 1 GW Model CapEx for reference | C97: =B38 -> 43.234167 | I97: DC_Cost_Model CapEx for 1 GW VR NVL72
A99: Fleet Composition (est.)
A100: Legacy (H100/A100) share | B100: 1 | C100: 0.7 | D100: 0.5 | E100: 0.35 | F100: 0.15 | G100: 0.05 | H100: 0 | I100: Legacy fleet phased out as VR NVL72 ramps
A101: GB200 NVL72 share | B101: 0 | C101: 0.3 | D101: 0.3 | E101: 0.2 | F101: 0.1 | G101: 0.05 | H101: 0 | I101: Blackwell era; deployed mid-2025
A102: Vera Rubin NVL72 share | B102: 0 | C102: 0 | D102: 0.2 | E102: 0.45 | F102: 0.75 | G102: 0.9 | H102: 1 | I102: First VR deployment H2 2026; dominant by 2028+
A103: Effective VR-equiv Capacity (GW) | B103: =B94*(B100*0.25+B101*(TL_Param!D37/TL_Param!C37)+B102*1) -> 0.1 | C103: =C94*(C100*0.25+C101*(TL_Param!D37/TL_Param!C37)+C102*1) -> 0.363411 | D103: =D94*(D100*0.25+D101*(TL_Param!D37/TL_Param!C37)+D102*1) -> 1.1899678 | E103: =E94*(E100*0.25+E101*(TL_Param!D37/TL_Param!C37)+E102*1) -> 2.4586101 | F103: =F94*(F100*0.25+F101*(TL_Param!D37/TL_Param!C37)+F102*1) -> 4.2336409 | G103: =G94*(G100*0.25+G101*(TL_Param!D37/TL_Param!C37)+G102*1) -> 5.9401494 | H103: =H94*(H100*0.25+H101*(TL_Param!D37/TL_Param!C37)+H102*1) -> 8.5 | I103: Weighted inference eff: H100=0.25x, GB200≈0.39x (output tok/s ratio from TL_Param), VR=1.0x
A106: Revenue per GW ($B/GW) | B106: =B68/B94 -> 9.25 | C106: =C68/C94 -> 10.48 | D106: =D68/D94 -> 13.333333 | E106: =E68/E94 -> 18.775 | F106: =F68/F94 -> 27.609756 | G106: =G68/G94 -> 37.239216 | H106: =H68/H94 -> 41.176471 | I106: Revenue generation efficiency per GW
A107: Revenue per VR-equiv GW ($B/GW-eq) | B107: =IF(B103>0,B68/B103,"-") -> 37 | C107: =IF(C103>0,C68/C103,"-") -> 36.04734 | D107: =IF(D103>0,D68/D103,"-") -> 30.25292 | E107: =IF(E103>0,E68/E103,"-") -> 30.545713 | F107: =IF(F103>0,F68/F103,"-") -> 33.422769 | G107: =IF(G103>0,G68/G103,"-") -> 39.965325 | H107: =IF(H103>0,H68/H103,"-") -> 41.176471 | I107: Normalized for hardware generation efficiency
A108: Our 1 GW Model Revenue ($B) | C108: =Revenue_Model!B39/1000 -> 1279.6304 | I108: From Revenue_Model total annual revenue (theoretical max)
A110: Section 5: Valuation Sanity Check & DC-Backed Analysis
A111: Metric | B111: Value | C111: Unit | I111: Note
A112: Valuation Multiples
A113: Post-Money Valuation | B113: 852 | C113: $B | I113: Mar-2026 close: $730B pre + $122B raised
A114: EV / 2025 Revenue | B114: =B113/C68 -> 65.038168 | I114: On actual 2025 revenue ($13.1B)
A115: EV / 2025 ARR (exit rate) | B115: =B113/C6 -> 42.6 | I115: On $20B exit ARR
A116: EV / 2026E Revenue | B116: =B113/D68 -> 23.666667 | I116: On projected 2026 revenue
A117: EV / 2030E Revenue | B117: =B113/H68 -> 2.4342857 | I117: On projected 2030 revenue
A118: For reference: typical high-growth SaaS | B118: 15-25x | C118: rev | I118: Top-quartile SaaS companies trade 15-25x ARR
A119: EV / 2030E Revenue at new-round talks | B119: =B24/H68 -> 3.4285714 | I119: ≥$1.2T / 2030E revenue
A120: Implied 2030 Valuation (at various multiples)
...

Sheet FT_Sep2026
A1: FT Update (2026-09-18 report on OpenAI July-2026 deck) — Vintages, Revenue Path, Cash Bridge v3, Runway, Capacity Tension
A2: Legend: blue = hardcoded input / lever · black = formula · green = link to another sheet · yellow fill = key assumption. Tags in column H: [Verified] [Interested-party] [Analogy] [Assumed] [Derived].
A4: Section A: OpenAI projection vintages ($B) — as reported
A5: Metric | B5: Sep-2025 | C5: Feb-2026 | D5: May-2026 | E5: Jul-2026 | H5: Source / Tag
A6: Revenue 2026E | C6: 30 | E6: 36 | H6: Feb: The Information via the-decoder (2026-02-21); Jul: FT 2026-09-18. [Interested-party: OpenAI; Jul deck prepared for a compute deal amid ≥$1.2T round talks]
A7: Revenue 2027E | C7: 62 | H7: Feb: The Information (~$62B). Jul: not disclosed
A8: Revenue 2030E | C8: 280 | E8: 350 | H8: Feb: $280B target; Jul: FT
A9: Cumulative revenue 2026–30 | E9: 840 | H9: FT: "$840bn between now and the end of 2030" — reading assumed = FY2026–FY2030 (see note row 20)
A10: FCF 2026E | B10: -17 | C10: -25 | H10: Sep-25: The Information via CNBC 2025-09-06; Feb: The Information
A11: FCF 2027E | B11: -35 | C11: -57 | H11: same
A12: FCF 2028E | B12: -45 | H12: Sep-25 only; Feb gives 2026–29 cumulative only
A13: Cumulative FCF 2026–29 | C13: -218 | H13: Feb: The Information / Sherwood 2026-02-23
A14: FCF 2030E | C14: 39 | H14: Feb: first positive year 2030 (+$39B)
A15: Cumulative FCF 2026–30 | C15: =C13+C14 -> -179 | D15: -305 | E15: -278 | H15: Feb [Derived]=−218+39; May & Jul: FT
A16: Compute / infra spend through 2030 | C16: 600 | E16: 856 | H16: Feb: ~$600B "compute"; Jul: ~$856B "computing power and infrastructure" — category may differ
A17: Latest round raised | E17: 122 | H17: OpenAI 2026-03-31: $122B committed [Verified]
A18: Post-money valuation | E18: 852 | H18: OpenAI 2026-03-31 [Verified]
A19: New round talks (valuation, ≥) | E19: 1200 | H19: FT/Bloomberg Sep-2026; OpenAI pushing higher [Interested-party]
A20: Note: "$840bn between now and end of 2030" admits two readings: (a) FY2026–30 (adopted); (b) from report date. Reading (b) implies an even more front-loaded path.
A22: Section B: v3 revenue path — drives OpenAI_Sim!D46:H46
A23: Metric | B23: 2026E | C23: 2027E | D23: 2028E | E23: 2029E | F23: 2030E | G23: Total 26–30 | H23: Source / Tag
A24: Revenue anchors / inputs ($B) | B24: =E6 -> 36 | C24: 75.1 | D24: 141.5 | E24: =E9-B24-C24-D24-F24 -> 237.4 | F24: =E8 -> 350 | G24: =SUM(B24:F24) -> 840 | H24: 2026/2030 = Jul deck. 2027–28 [Derived]: fitted path with linearly decelerating growth that closes $36B→$350B and Σ=$840B. 2029 = residual so Σ ties to $840B exactly.
A25: YoY growth | B25: =B24/OpenAI_Sim!C68-1 -> 1.7480916 | C25: =C24/B24-1 -> 1.0861111 | D25: =D24/C24-1 -> 0.88415446 | E25: =E24/D24-1 -> 0.67773852 | F25: =F24/E24-1 -> 0.47430497 | H25: Linked into OpenAI_Sim row 46 (2026 vs 2025A actual)
A26: v2 path (July model) for reference | B26: 32.75 | C26: 60.5875 | D26: 112.0869 | E26: 179.339 | F26: 286.9424 | G26: =SUM(B26:F26) -> 671.7058 | H26: Frozen v2 values (20260715_Tokenomics_v2 OpenAI_Sim D68:H68)
A27: v3 vs v2 | B27: =B24/B26-1 -> 0.099236641 | C27: =C24/C26-1 -> 0.23952961 | D27: =D24/D26-1 -> 0.26241336 | E27: =E24/E26-1 -> 0.32374999 | F27: =F24/F26-1 -> 0.219757 | G27: =G24/G26-1 -> 0.25054749
A28: Check: equal-growth path Σ (36→350) | G28: =SUMPRODUCT(B24*((F24/B24)^({0,1,2,3,4}/4))) -> 760.029 | H28: If Σ(equal-growth) < $840B, the deck implies a front-loaded path (faster 2027–28)
A30: Section C: Free-cash-flow bridge v3 (cash basis; replaces v2 row-86 formula for 2026–30)
A31: Line ($B) | B31: 2026E | C31: 2027E | D31: 2028E | E31: 2029E | F31: 2030E | G31: Total 26–30 | H31: Logic / Tag
A32: Lever: compute & infra total 2026–30 | B32: =E16 -> 856 | H32: Jul deck $856B [Interested-party]. Allocation across years uses row 34 key.
A33: Lever: R&D share that is compute (inside row 32) | B33: 0.6 | H33: [Assumed] range 40–80%. Prevents counting training compute twice (R&D line + compute line).
A34: Allocation key: owned CapEx path (OpenAI_Sim row 53) | B34: =OpenAI_Sim!D53 -> 40 | C34: =OpenAI_Sim!E53 -> 60 | D34: =OpenAI_Sim!F53 -> 100 | E34: =OpenAI_Sim!G53 -> 125 | F34: =OpenAI_Sim!H53 -> 150 | G34: =SUM(B34:F34) -> 475 | H34: [Assumed] v2 CapEx path = balance-sheet (owned) portion; also used as timing key for total spend
A35: Lever: partner-financed share of compute (off OAI FCF) | B35: 0 | H35: [Assumed] 0% base. >0% if partners fund build outside OpenAI cash flow; raises off-balance-sheet commitments instead.
A37: Gross revenue | B37: =OpenAI_Sim!D68 -> 36 | C37: =OpenAI_Sim!E68 -> 75.1 | D37: =OpenAI_Sim!F68 -> 141.5 | E37: =OpenAI_Sim!G68 -> 237.4 | F37: =OpenAI_Sim!H68 -> 350 | G37: =SUM(B37:F37) -> 840 | H37: OpenAI_Sim row 68 (now v3 path)
A38: Less: Microsoft revenue share | B38: =OpenAI_Sim!D69 -> -7.2 | C38: =OpenAI_Sim!E69 -> -13.1425 | D38: =OpenAI_Sim!F69 -> -21.225 | E38: =OpenAI_Sim!G69 -> -29.675 | F38: =OpenAI_Sim!H69 -> -35 | G38: =SUM(B38:F38) -> -106.2425 | H38: OpenAI_Sim row 69
A39: Compute & infra spend (total) | B39: =-$B$32*B34/$G$34 -> -72.084211 | C39: =-$B$32*C34/$G$34 -> -108.12632 | D39: =-$B$32*D34/$G$34 -> -180.21053 | E39: =-$B$32*E34/$G$34 -> -225.26316 | F39: =-$B$32*F34/$G$34 -> -270.31579 | G39: =SUM(B39:F39) -> -856 | H39: Total × timing key
A40: of which owned (balance-sheet CapEx) | B40: =-B34 -> -40 | C40: =-C34 -> -60 | D40: =-D34 -> -100 | E40: =-E34 -> -125 | F40: =-F34 -> -150 | G40: =SUM(B40:F40) -> -475 | H40: Split item 4: owned
A41: of which leased / contracted (cash opex) | B41: =B39-B40 -> -32.084211 | C41: =C39-C40 -> -48.126316 | D41: =D39-D40 -> -80.210526 | E41: =E39-E40 -> -100.26316 | F41: =F39-F40 -> -120.31579 | G41: =SUM(B41:F41) -> -381 | H41: Split item 4: leased = total − owned
A42: Add back: partner-financed portion | B42: =-B39*$B$35 -> 0 | C42: =-C39*$B$35 -> 0 | D42: =-D39*$B$35 -> 0 | E42: =-E39*$B$35 -> 0 | F42: =-F39*$B$35 -> 0 | G42: =SUM(B42:F42) -> 0 | H42: Excluded from OAI FCF
A43: R&D excl. compute (cash) | B43: =OpenAI_Sim!D76*(1-$B$33) -> -5.76 | C43: =OpenAI_Sim!E76*(1-$B$33) -> -9.012 | D43: =OpenAI_Sim!F76*(1-$B$33) -> -14.15 | E43: =OpenAI_Sim!G76*(1-$B$33) -> -18.992 | F43: =OpenAI_Sim!H76*(1-$B$33) -> -21 | G43: =SUM(B43:F43) -> -68.914 | H43: OpenAI_Sim row 76 × (1 − compute share)
A44: S&M (cash) | B44: =OpenAI_Sim!D77 -> -4.32 | C44: =OpenAI_Sim!E77 -> -7.51 | D44: =OpenAI_Sim!F77 -> -11.32 | E44: =OpenAI_Sim!G77 -> -15.431 | F44: =OpenAI_Sim!H77 -> -17.5 | G44: =SUM(B44:F44) -> -56.081 | H44: OpenAI_Sim row 77
A45: G&A (cash) | B45: =OpenAI_Sim!D78 -> -1.8 | C45: =OpenAI_Sim!E78 -> -3.3795 | D45: =OpenAI_Sim!F78 -> -5.66 | E45: =OpenAI_Sim!G78 -> -8.309 | F45: =OpenAI_Sim!H78 -> -10.5 | G45: =SUM(B45:F45) -> -29.6485 | H45: OpenAI_Sim row 78
A46: Free cash flow v3 | B46: =SUM(B37:B39)+SUM(B42:B45) -> -55.164211 | C46: =SUM(C37:C39)+SUM(C42:C45) -> -66.070316 | D46: =SUM(D37:D39)+SUM(D42:D45) -> -91.065526 | E46: =SUM(E37:E39)+SUM(E42:E45) -> -60.270158 | F46: =SUM(F37:F39)+SUM(F42:F45) -> -4.3157895 | G46: =SUM(B46:F46) -> -276.886 | H46: SBC excluded (non-cash). Depreciation NOT deducted — cash basis removes the v2 double count (Audit_Report row 78).
A47: Cumulative FCF v3 | B47: =B46 -> -55.164211 | C47: =B47+C46 -> -121.23453 | D47: =C47+D46 -> -212.30005 | E47: =D47+E46 -> -272.57021 | F47: =E47+F46 -> -276.886 | H47: Running total
A48: FCF / gross revenue | B48: =B46/B37 -> -1.5323392 | C48: =C46/C37 -> -0.87976452 | D48: =D46/D37 -> -0.64357262 | E48: =E46/E37 -> -0.25387598 | F48: =F46/F37 -> -0.012330827 | G48: =G46/G37 -> -0.32962619
A50: Legacy v2 formula (OpInc − CapEx + SBC), reference only | B50: =OpenAI_Sim!D82-OpenAI_Sim!D53+ABS(OpenAI_Sim!D79) -> -45.65607 | C50: =OpenAI_Sim!E82-OpenAI_Sim!E53+ABS(OpenAI_Sim!E79) -> -54.462368 | D50: =OpenAI_Sim!F82-OpenAI_Sim!F53+ABS(OpenAI_Sim!F79) -> -65.279902 | E50: =OpenAI_Sim!G82-OpenAI_Sim!G53+ABS(OpenAI_Sim!G79) -> -32.112739 | F50: =OpenAI_Sim!H82-OpenAI_Sim!H53+ABS(OpenAI_Sim!H79) -> 24.433778 | G50: =SUM(B50:F50) -> -173.0773 | H50: Double-counts depreciation embedded in COGS and omits leased compute — do not use
A52: Reconciliation to Jul deck
A53: Jul deck cumulative FCF 2026–30 | G53: =E15 -> -278
A54: v3 minus deck (+ = v3 less negative) | G54: =G46-G53 -> 1.114
A55: Implied non-compute cash cost in deck | G55: =E9-E16-E15 -> 262 | H55: [Derived] 840 − 856 + 278; compare with v3 −(G38+G43+G44+G45)
A56: v3 non-compute cash cost | G56: =-(G38+G43+G44+G45) -> 260.886
A57: Legacy v2 vs deck (shows the offsetting-error coincidence) | G57: =G50-G53 -> 104.9227
A59: Section C2: Sensitivity — cumulative FCF 2026–30 ($B)
A60: R&D compute share ↓ / partner-financed → | B60: 0 | C60: 0.1 | D60: 0.2 | E60: 0.3 | H60: Formula recomputes Σ bridge; base case boxed by row 33/35 levers
A61: 0.4 | B61: =$G$37+$G$38+$G$39*(1-B$60)+SUM(OpenAI_Sim!$D$76:$H$76)*(1-$A61)+$G$44+$G$45 -> -311.343 | C61: =$G$37+$G$38+$G$39*(1-C$60)+SUM(OpenAI_Sim!$D$76:$H$76)*(1-$A61)+$G$44+$G$45 -> -225.743 | D61: =$G$37+$G$38+$G$39*(1-D$60)+SUM(OpenAI_Sim!$D$76:$H$76)*(1-$A61)+$G$44+$G$45 -> -140.143 | E61: =$G$37+$G$38+$G$39*(1-E$60)+SUM(OpenAI_Sim!$D$76:$H$76)*(1-$A61)+$G$44+$G$45 -> -54.543
A62: 0.5 | B62: =$G$37+$G$38+$G$39*(1-B$60)+SUM(OpenAI_Sim!$D$76:$H$76)*(1-$A62)+$G$44+$G$45 -> -294.1145 | C62: =$G$37+$G$38+$G$39*(1-C$60)+SUM(OpenAI_Sim!$D$76:$H$76)*(1-$A62)+$G$44+$G$45 -> -208.5145 | D62: =$G$37+$G$38+$G$39*(1-D$60)+SUM(OpenAI_Sim!$D$76:$H$76)*(1-$A62)+$G$44+$G$45 -> -122.9145 | E62: =$G$37+$G$38+$G$39*(1-E$60)+SUM(OpenAI_Sim!$D$76:$H$76)*(1-$A62)+$G$44+$G$45 -> -37.3145
A63: 0.6 | B63: =$G$37+$G$38+$G$39*(1-B$60)+SUM(OpenAI_Sim!$D$76:$H$76)*(1-$A63)+$G$44+$G$45 -> -276.886 | C63: =$G$37+$G$38+$G$39*(1-C$60)+SUM(OpenAI_Sim!$D$76:$H$76)*(1-$A63)+$G$44+$G$45 -> -191.286 | D63: =$G$37+$G$38+$G$39*(1-D$60)+SUM(OpenAI_Sim!$D$76:$H$76)*(1-$A63)+$G$44+$G$45 -> -105.686 | E63: =$G$37+$G$38+$G$39*(1-E$60)+SUM(OpenAI_Sim!$D$76:$H$76)*(1-$A63)+$G$44+$G$45 -> -20.086
A64: 0.7 | B64: =$G$37+$G$38+$G$39*(1-B$60)+SUM(OpenAI_Sim!$D$76:$H$76)*(1-$A64)+$G$44+$G$45 -> -259.6575 | C64: =$G$37+$G$38+$G$39*(1-C$60)+SUM(OpenAI_Sim!$D$76:$H$76)*(1-$A64)+$G$44+$G$45 -> -174.0575 | D64: =$G$37+$G$38+$G$39*(1-D$60)+SUM(OpenAI_Sim!$D$76:$H$76)*(1-$A64)+$G$44+$G$45 -> -88.4575 | E64: =$G$37+$G$38+$G$39*(1-E$60)+SUM(OpenAI_Sim!$D$76:$H$76)*(1-$A64)+$G$44+$G$45 -> -2.8575
A65: 0.8 | B65: =$G$37+$G$38+$G$39*(1-B$60)+SUM(OpenAI_Sim!$D$76:$H$76)*(1-$A65)+$G$44+$G$45 -> -242.429 | C65: =$G$37+$G$38+$G$39*(1-C$60)+SUM(OpenAI_Sim!$D$76:$H$76)*(1-$A65)+$G$44+$G$45 -> -156.829 | D65: =$G$37+$G$38+$G$39*(1-D$60)+SUM(OpenAI_Sim!$D$76:$H$76)*(1-$A65)+$G$44+$G$45 -> -71.229 | E65: =$G$37+$G$38+$G$39*(1-E$60)+SUM(OpenAI_Sim!$D$76:$H$76)*(1-$A65)+$G$44+$G$45 -> 14.371
A67: Section D: Funding runway ($B)
A68: Line | B68: 2026E | C68: 2027E | D68: 2028E | E68: 2029E | F68: 2030E | H68: Logic / Tag
A69: Lever: cash before March-2026 round | B69: 40 | H69: [Interested-party, secondary aggregator ~ $40B, Feb-2026] — weak input; test ±$15B
A70: Round proceeds (March 2026) | B70: =E17 -> 122
A71: Year-end cash before new funding | B71: =B69+B70+B46 -> 106.83579 | C71: =B71+C46 -> 40.765474 | D71: =C71+D46 -> -50.300053 | E71: =D71+E46 -> -110.57021 | F71: =E71+F46 -> -114.886 | H71: Assumes full $122B received in 2026 and no debt / partner draws
A72: Cumulative external funding need | B72: =MAX(0,-B71) -> 0 | C72: =MAX(0,-C71) -> 0 | D72: =MAX(0,-D71) -> 50.300053 | E72: =MAX(0,-E71) -> 110.57021 | F72: =MAX(0,-F71) -> 114.886
A73: First year cash < 0 | B73: =IFERROR(INDEX($B$23:$F$23,MATCH(TRUE(),INDEX($B$71:$F$71<0,0),0)),"none ≤2030") -> 2028E | H73: FT: deck indicates March capital could be exhausted ~2028
A75: Section E: Capacity tension (item 6) — capacity inputs NOT raised; tension flagged
A76: Line | B76: 2026E | C76: 2027E | D76: 2028E | E76: 2029E | F76: 2030E | H76: Logic / Tag
A77: Realized % of theoretical tokens (OpenAI_Sim row 669) | B77: =OpenAI_Sim!D669 -> 0.059152942 | C77: =OpenAI_Sim!E669 -> 0.065652978 | D77: =OpenAI_Sim!F669 -> 0.075405844 | E77: =OpenAI_Sim!G669 -> 0.098391185 | F77: =OpenAI_Sim!H669 -> 0.10590034
A78: Year-end capacity in model (GW) | B78: =OpenAI_Sim!D95 -> 3.5 | C78: =OpenAI_Sim!E95 -> 4.5 | D78: =OpenAI_Sim!F95 -> 5.75 | E78: =OpenAI_Sim!G95 -> 7 | F78: =OpenAI_Sim!H95 -> 10
A79: Year-end GW needed for Realized% = 100% (approx.) | B79: =B78*MAX(1,B77) -> 3.5 | C79: =C78*MAX(1,C77) -> 4.5 | D79: =D78*MAX(1,D77) -> 5.75 | E79: =E78*MAX(1,E77) -> 7 | F79: =F78*MAX(1,F77) -> 10 | H79: [Derived] linear in capacity at fixed fleet mix; ignores FY-avg lag
A80: Scenario: capacity scaled by Jul/Feb compute ratio (GW) | F80: =OpenAI_Sim!H11*E16/C16 -> 14.266667 | H80: [Derived] 10 GW × 856/600; assumes constant $/GW and identical spend category — upper-bound illustration
A81: Realized % 2030 under scaled capacity | F81: =F77*OpenAI_Sim!H11/F80 -> 0.074229209
A82: Flag | B82: =IF(MAX(B77:F77)>1,"⚠ Token projection exceeds theoretical fleet capacity in "&INDEX(B23:F23,MATCH(MAX(B77:F77),B77:F77,0))&" — revenue path needs more GW or higher $/token","OK: within capacity") -> OK: within capacity

Sheet Claude Log
A1: Turn # | B1: Date | C1: User Request | D1: Action Taken | E1: Details | F1: Outcome
A2: 1 | B2: 46106 | C2: Expand model with inter-rack networking (InfiniBand XDR, Spectrum-X, Ethernet) across Config, TL_Param, and WP_Param sheets to make token/revenue calculations more realistic. | D2: Added inter-rack network fabric section to Config (rows 65-85), inter-rack network analysis to WP_Param (rows 208-270), and inter-rack adjusted E2E latency section to TL_Param (rows 26-33). | E2: Config: Added NIC specs (ConnectX-8 800Gb/s), switch specs (Quantum-X800 Q3400 144-port), latency (sub-100ns/hop IB XDR), oversubscription (2:1), SHARP v4 reduction (50%), multi-rack parallelism (DP replicas, KV cache transfer for disaggregated inference). WP_Param: 3 sub-sections—DP all-reduce, KV cache transfer, decode overhead—plus combined E2E impact for colocated vs disaggregated scenarios. TL_Param: Added rows 26-33 showing network-adjusted E2E for both VR NVL72 and GB200 NVL72. | F2: Colocated inference: ~0.04% overhead (negligible). Disaggregated inference: ~24.7% throughput reduction due to KV cache transfer across racks. All values dynamically linked to Config blue-cell inputs.
A3: 2 | B3: 46106 | C3: Integrate inter-rack network overhead into each of the 6 steps of the token generation pipeline in TL_Param, just like how NVLink time is integrated. | D3: Added column M 'Inter-Rack Time' to the optimized pipeline in TL_Param. Updated Duration formulas (D17, D18, D20) to include inter-rack. Rebuilt Rack-Independent outputs (O26:P38) with inter-rack. Fixed Revenue_Model linkage. | E3: Step 1 (Tokenization): N/A. Step 2 (Embedding): +3.0E-7s (LB routing latency). Step 3 (Prefill): 0 for colocated. Step 4 (Decode-First): N/A. Step 5 (Decode-All): +0.00012s (token streaming, 80% overlapped). Step 6 (De-tokenization): N/A. Token streaming uses (1-overlap) factor from Config!B82. Cleaned up old separate inter-rack section (rows 26-33) and replaced with integrated approach. | F3: VR NVL72: 39,901 tok/s (0.008% inter-rack overhead). GB200 NVL72: 13,240 tok/s (0.002% overhead). Inter-rack is negligible for colocated inference with IB XDR. Revenue_Model auto-updates via TL_Param!O36/P36 references.
A4: 3 | B4: 46106 | C4: Add Inter-Rack Time column to the Baseline section and reposition it right next to NVLink (column I) in both Baseline and Optimized sections. | D4: Inserted column I between NVLink (H) and Bottleneck (J). Populated Inter-Rack Time for both Baseline and Optimized pipelines. Updated all Duration formulas (D4, D7, D17, D18, D20). Migrated Rack-Independent formulas (O/P) from old col N to col I. Deleted orphan column N. Verified Revenue_Model auto-shifted to O36/P36. | E4: Baseline Inter-Rack: Step 2 = 3E-7s (routing), Step 5 = 0.0006s (full streaming, no overlap since baseline has no optimizations). Optimized Inter-Rack: Step 2 = 3E-7s, Step 5 = 0.00012s (80% overlapped). Column order now: Compute | HBM BW | NVLink | Inter-Rack | Bottleneck | Dominant | FLOPs | HBM Bytes. | F4: Baseline: 777 tok/s (was 777.4 without inter-rack). Optimized: 39,901 tok/s (unchanged). Both sections now have consistent 8-resource-column layout. Revenue_Model correctly references O36/P36 for VR/GB200 E2E.
A5: 4 | B5: 46106 | C5: User asked if I23 was doing anything; confirmed it was a redundant duplicate of E23 and cleared it. | D5: Cleared TL_Param!I23 (was =1/E22, duplicate of E23). | E5: I23 was not referenced by any downstream formula. | F5: Cell cleared. No impact on model.
A6: 5 | B6: 46106 | C6: User surprised inter-rack overhead is so small. Asked for walkthrough of main reasons. | D6: Provided analysis-only explanation. No spreadsheet changes. | E6: 3 reasons: (1) 1T model fits in 1 rack (20.7TB >> 1TB), no cross-rack compute traffic. (2) IB XDR = 0.3μs one-way, 6 orders of magnitude below decode bottleneck. (3) Only last-mile routing+streaming crosses fabric. Also noted when it would matter: disaggregated (~25% hit), multi-rack TP, or Ethernet. | F6: Key numbers: Inter-rack step 5 = 0.00012s vs HBM 0.213s (710,000× gap). Model fits in rack = no TP/PP across fabric.
A7: 6 | B7: 46106 | C7: Make Bottleneck (J) and Dominant Resource (K) columns dynamic instead of hardcoded, for both Baseline and Optimized. | D7: Replaced hardcoded text with IF/MAX formulas comparing F (Compute), G (HBM), H (NVLink), I (Inter-Rack). Steps 1 & 6 remain 'CPU' (hardcoded, always CPU). Steps 2-5 use nested IF(MAX(...)) logic. | E7: Bottleneck (J): returns Compute/Memory/NVLink/Inter-Rack based on which time column is largest. Dominant (K): returns GPU/HBM BW/NVLink/Inter-Rack. Step 2 Optimized corrected from hardcoded 'NVLink' to formula-derived 'Memory/HBM BW' (HBM 1.66E-6 > NVLink 1.24E-6). | F7: All 8 formula cells verified against actual time values. Results auto-update when Config parameters change (e.g., switching to Ethernet could flip Step 2 to Inter-Rack bottleneck).
A8: 7 | B8: 46106 | C8: User asked how to stress test inter-rack overhead. Built side-by-side scenario comparison table with 5 scenarios. | D8: Created stress test table at TL_Param rows 42-68 with 6 columns: Current + 5 scenarios (Std Ethernet, Disaggregated, 16:1 Oversub, Ethernet+Disagg, All Worst-Case). Each scenario independently varies fabric latency, oversubscription, disaggregation, and overlap. | E8: All formulas are self-contained — scenario parameters feed into Step 2/3/5 overhead calculations, then into adjusted E2E, tok/s, throughput loss %, and annual revenue impact ($M) linked to Revenue_Model!B38. | F8: Results: A=0.37% loss ($169M), B=24.6% ($11.4B), C=0% ($0), D=25.2% ($11.6B), E=72.5% ($33.4B). Disaggregation is the dominant factor; Ethernet alone is minor; 16:1 oversubscription alone is negligible; combined worst-case is devastating.
A10: 9 | B10: 46106 | C10: User changed model size 1T→10T, asked why inter-rack numbers don't change | D10: Traced formula chain from TL_Param I7/I20 → WP_Param B235 → Config B77; diagnosed root cause | E10: Inter-rack formulas depend on network latency × output_tokens, NOT model size. Model size affects compute/HBM but not token streaming overhead. DP all-reduce (WP_Param B221-B228) DOES scale with model size but isn't wired into pipeline steps. | F10: Explained to user; offered to add model-size-dependent inter-rack component (DP all-reduce) into pipeline
A11: 10 | B11: 46106 | C11: d_ff goes negative when model size increases from 1E12 to 1E13 | D11: Replaced d_model and n_layers with auto-scaling formulas; fixed circular ref in n_heads/d_head | E11: Root cause: d_model formula scaled linearly with P (10× params → 10× d), causing 4d² to exceed P/n_layers. Fix: n_layers = (P/(12×160²))^(1/3), d_model = MROUND(160×n_layers, 128). d_head fixed at 128. B34-B36 changed from blue (input) to black (formula). Verified at 1E12 and 1E13. | F11: All model specs now auto-scale correctly: 1E12→(n=148,d=23680), 1E13→(n=319,d=51072), d_ff positive at all sizes. B31 restored to 1E12.
A12: 11 | B12: 46106 | C12: At 1E14, model exceeds 1 rack memory but inter-rack numbers don't change | D12: Built multi-rack TP section (WP_Param B272:C297); rewired TL_Param I4:I20 to use model-size-aware inter-rack formulas; fixed D5 missing +I5 | E12: When B43<0 (model won't fit), auto-computes racks needed for TP, cross-rack activation transfer per layer (decode + prefill), total overhead. At 1E14: 5 racks needed, prefill adds 1.68s inter-rack, decode adds 0.42s (baseline) / 0.08s (optimized). At 1E12: all multi-rack terms =0 (model fits in 1 rack). Bottleneck column now shows 'Inter-Rack' for Step 3 prefill at 1E14. | F12: Model is now fully model-size-aware for inter-rack. B31 left at 1E14 per user's testing.
A13: 12 | B13: 46106 | C13: User asked if it's common for advanced models not to fit in one rack | D13: Provided industry context: MoE architectures, NVLink domain scaling (NVL72→NVL576), quantization (FP4), and multi-rack TP reality | E13: Explained that dense >20T models exceed NVL72 rack capacity (20.7 TB HBM). Industry uses MoE (sparse activation), larger NVLink domains (Rubin Ultra NVL576 ~150+ TB), and FP4 quantization. Mentioned GPT-5, Claude Opus, Gemini Ultra as likely multi-rack models. Noted user's 1E14 model is realistic for 2027-2028 era. | F13: Q&A turn — no spreadsheet modifications. User's model at 1E14 correctly shows inter-rack as prefill bottleneck.
A14: 13 | B14: 46106 | C14: User challenged: 10T model fits in rack, why is multi-rack common? | D14: Explained production reality: KV cache × batch_size is the real memory pressure, not just weights. Offered to extend B42/B43 to include batch-aware KV cache. | E14: Current B42 = weight/GPU + KV_end/GPU for 1 request. In production with batch=64 concurrent requests, KV cache alone can be 10+ TB for a 10T model at 5K context. Long-context (1M tokens) makes it worse. Also noted latency SLA reasons for multi-rack TP. User's model only accounts for single-request KV. | F14: Q&A — offered to make memory headroom batch-aware. Awaiting user decision.
... A33: 33 | B33: 46287 | C33: 以主流前沿模型 (Sep 2026) 更新 Config / TL_Param / WP_Param。 | D33: Config: 新增前沿模型預設表 J26:Q55 (DeepSeek V4-Pro、Kimi K3、DeepSeek V4-Flash、閉源前沿代理[Assumed]、舊 1T Dense), B29 選單; B31–B48/B55/B87 改由預設驅動; 定價層級改為 Sep-2026 六層並以 F41 選單選擇; 輸入/輸出 16K/1K; MFU 0.35; 推測解碼 N=5; F71/F72 改 CX-9; 修正 B32:B36 資料驗證範圍。WP: 注意力 FLOPs/參數泛化 (heads×head_dim、稀疏/壓縮注意力跨度)、KV 改架構實際 (MLA/CSA/HCA/GQA) 並計 KV bytes、批次解碼權重讀取改 MoE 命中機率、B46 TP 連結錯誤修正、B143 啟動值位元組。TL: F20 解碼運算乘上批次與推測驗證、除以 MFU。 | E33: 預設 V4-Pro + Frontier (closed) 定價: VR 機櫃 105K output tok/s, 1GW 年營收 $1.28T (v3: 34.9K tok/s, $80.8B)。主因: 49B active vs 1T dense、FP4、壓縮 KV、定價 $5/$25。Legacy 預設在新工作負載下為 7.5K tok/s。 | F33: 重算後公式零新錯誤。Revenue_Model 未納入 prompt caching 折價 — 營收為上限值。詳 Audit_Report 第 97 列起。

Sheet Audit_Report
A1: Workbook Formula, Linkage & Dynamic-Response Audit
A3: Audit date | B3: 46218
A4: Workbook | B4: 20260715_Tokenomics_inter-rack_energy.xlsx
A5: Scope | B5: All 7 original worksheets; formulas, cross-sheet links, recalculation errors, and parameter sensitivity.
A7: Executive conclusion | B7: 2026-07-15 複核版: 全簿 1,805 個公式重算零錯誤; 8 項參數敏感度實測全數連動。本次複核另發現並修正 4 項重大語意缺陷 (GQA KV 傳輸、營收衝擊基底、2027-2030 I/O 拆分、DC VR 專區下拉依賴) 及 2 項動態性缺陷 (all-reduce 數硬編 256、Overhead% 漏項)。詳見第 58 列起之複核修正表與未結事項。
A9: Worksheet | B9: Role | C9: Formula cells | D9: Cross-sheet formulas | E9: Recalc status | F9: Dynamic status | G9: Risk | H9: Key conclusion
A10: Claude Log | B10: Change log | C10: 0 | D10: 0 | E10: Pass | F10: N/A | G10: Low | H10: Narrative log only; no calculation role.
A11: Config | B11: Inputs & presets | C11: 56 | D11: 0 | E11: Pass | F11: Pass after fix | G11: Medium | H11: Rack/model/network controls feed downstream sheets. MoE active-parameter formula corrected.
A12: TL_Param | B12: Pipeline latency | C12: 193 | D12: 82 | E12: Pass after fix | F12: Pass after fix | G12: High | H12: Three optimized duration formulas now respect changing bottlenecks; stress-test base no longer double-counts current network overhead.
A13: WP_Param | B13: Workload mechanics | C13: 211 | D13: 67 | E13: Pass after fix | F13: Pass after fix | G13: High | H13: Network comparison no longer double-counts integrated routing/streaming terms.
A14: DC_Cost_Model | B14: CapEx/OpEx | C14: 236 | D14: 14 | E14: Pass | F14: Pass | G14: Medium | H14: Derived totals are formula-driven; unit-cost and operating assumptions are intentionally hardcoded inputs.
A15: Revenue_Model | B15: Throughput/revenue | C15: 60 | D15: 20 | E15: Pass | F15: Pass | G15: Medium | H15: VR and GB200 sections link to independent latency/rack outputs; utilization and uptime are explicit assumptions.
A16: OpenAI_Sim | B16: Financial scenarios | C16: 1049 | D16: 39 | E16: Pass after fix | F16: Partial by design | G16: High | H16: 2030 valuation multiple error corrected. Forecast assumptions and segment scenarios intentionally contain many hardcoded controls.
A19: Corrections applied
A20: Sheet | B20: Cell | C20: Previous formula/value | D20: Corrected formula/value | E20: Reason
A21: TL_Param | B21: D18 | C21: '=F18+H18+I18 | D21: '=MAX(F18,G18)+H18+I18 | E21: Optimized prefill duration omitted HBM time when HBM becomes slower than compute.
A22: TL_Param | B22: D19 | C22: '=G19 | D22: '=MAX(F19,G19) | E22: Optimized first-token duration was hard-linked to HBM only and ignored a possible compute bottleneck.
A23: TL_Param | B23: D20 | C23: '=G20+H20+I20 | D23: '=MAX(F20,G20)+H20+I20 | E23: Optimized decode-all duration omitted compute time when compute becomes slower than HBM.
A24: OpenAI_Sim | B24: B21 | C24: '=840/F5 | D24: '=840/H5 | E24: 2030 valuation multiple referenced blank F5 instead of 2030 target in H5, causing #DIV/0!.
A25: Config | B25: B36 | C25: '=IF(B32="Dense",B31,B31*B35) | D25: '=IF(B32="Dense",B31,B39*(B43+B44*B35)) | E25: MoE active parameters must retain shared attention parameters and scale only expert FFN parameters.
A26: Config | B26: C36 | C26: Dense=total, MoE=total×ratio | D26: Dense=total; MoE=n_layers×(attention + FFN×active/total) | E26: Clarified corrected MoE active-parameter definition.
A27: TL_Param | B27: C62 | C27: '=C38 | D27: '=C38-SUM(I17,I18,I20) | E27: Intra-rack base must exclude inter-rack overhead already integrated into C38 before scenario overhead is added.
A28: WP_Param | B28: B240 | C28: '=TL_Param!E21 | D28: '=TL_Param!E21-SUM(TL_Param!I17,TL_Param!I18,TL_Param!I20) | E28: Base latency should exclude integrated network terms.
A29: WP_Param | B29: C240 | C29: From TL_Param (now includes inter-rack in steps 2,5) | D29: TL optimized E2E less integrated inter-rack terms | E29: Updated description to match formula.
A30: WP_Param | B30: A241 | C30: Load Balancer + Return Overhead (s) | D30: Load Balancer Routing Overhead (s) | E30: Clarified that only one-way routing is added here.
A31: WP_Param | B31: B241 | C31: '=B233+B234 | D31: '=B233 | E31: Use the same one-way routing term integrated in TL_Param.
... A40: WP_Param | B40: C16 | C40: 50/GPU | D40: 16 PFLOPS/GPU | E40: Corrected stale note after FP8 rack performance audit.
A42: Dynamic-response tests
A43: Control changed | B43: Baseline | C43: Test value | D43: Observed downstream response | E43: Result
A44: Config!B27 Input Tokens | B44: 4000 | C44: 8000 | D44: TL E2E 1.819s→3.621s; throughput and revenue changed. | H44: Pass
A45: Config!B31 Parameters | B45: 1000000000000 | C45: 2000000000000 | D45: TL E2E 1.819s→3.230s; memory, throughput, pricing/revenue changed. | H45: Pass
A46: Config!B32 Type | B46: Dense | C46: MoE | D46: Dense→MoE: active params 1.0T→0.415T; E2E 1.819s→1.299s. | H46: Pass
A47: Config!B46 MFU | B47: 0.5 | C47: 0.8 | D47: MFU 0.5→0.8: E2E 1.819s→1.476s; revenue changed. | H47: Pass
A48: Config!B56 Batch Size | B48: 64 | C48: 32 | D48: Batch 64→32: memory headroom, throughput and revenue changed. | H48: Pass
A49: Config!B76 Switch latency | B49: 0.1 | C49: 5 | D49: 0.1→5 μs: E2E 1.819s→1.825s; throughput/revenue changed. | H49: Pass
A50: Config!B7 Rack Type | B50: Vera Rubin NVL72 | C50: GB200 NVL72 | D50: Downstream selected-rack cost/workload changed, but VR independent output moved ~2.2%. | H50: Partial
A52: Hardcoded-cell assessment
A53: Acceptable controls | B53: Config presets and blue input cells; DC unit costs; Revenue utilization/uptime; TL stress-scenario assumptions; OpenAI forecast assumptions. These are scenario drivers and should remain hardcoded/editable.
A54: Derived outputs | B54: Core latency, throughput, rack count, CapEx/OpEx totals, revenue, and P&L subtotal/output rows are formula-driven after corrections.
A55: Caution | B55: OpenAI_Sim is a scenario model, not a fully endogenous forecast. Customer counts, prices, fleet shares, growth, margins, and token-use assumptions are intentionally hardcoded and must be reviewed as an assumption block.
A56: Structural limitation | B56: VR-vs-GB200 rack-independent comparison rescales the currently selected rack calculation. Rack dropdown testing moved the nominal VR output by ~2.2%, so it is not fully rack-independent. For investment use, build separate full WP/TL calculation blocks for each rack instead of ratio scaling.
A58: 2026-07-15 複核修正 (Re-audit, corrections applied)
A59: Sheet | B59: Cell | C59: Previous formula/value | D59: Corrected formula/value | E59: Reason
A60: Config | B60: B87 | C60: '=2*B38*B39*B48*(B27+B28) | D60: '=2*B41*B55*B39*B48*(B27+B28) | E60: M1: KV cache 傳輸原用全 MHA (2×d_model), 與 decode 路徑之 GQA (B55=8 KV heads) 不一致; 高估 23.1×。修正後 KV=1.52GB/request。
A61: WP_Param | B61: B227 | C61: '=2*B29*B30*Config!B48*(B22+B23) | D61: '=2*B32*B159*B30*Config!B48*(B22+B23) | E61: M1 同步: 分離式 P→D 傳輸的是 GQA 壓縮後 KV。Disaggregated 吞吐損失 32.2%→1.98%; Scenario E 79.4%→17.2%。
A62: TL_Param | B62: D67:H67 | C62: '=X65*Revenue_Model!B38 | D62: '=X65*Revenue_Model!B39 | E62: M2: 吞吐損失等比例壓縮 input+output 營收, 基底應為總營收 B39 而非僅 output 營收 B38 (原低估 2×)。
A63: OpenAI_Sim | B63: B433/C433 | C63: ...C369... (input 單價) | D63: ...C371... (I:O 比) | E63: M3: 2027E API I/O 拆分誤用單價列。修正後 input 8.48T/output 2.42T, 與分層加總 E428/F428 一致。
A64: OpenAI_Sim | B64: B503/C503 | C64: ...C442... | D64: ...C444... | E64: M3 同步 (2028E)。
A65: OpenAI_Sim | B65: B574/C574 | C65: ...C512... | D65: ...C514... | E65: M3 同步 (2029E)。
A66: OpenAI_Sim | B66: B645/C645 | C66: ...C583... | D66: ...C585... | E66: M3 同步 (2030E): 原 in/out 恰完全顛倒; 修正後 in 45.11T/out 22.56T = 分層加總 E639/F639。
A67: DC_Cost_Model | B67: B5,B6,B8,B9,B10,B18,A18 | C67: '=Config!B5/B6/B7/B8/B14/B24 (跟隨下拉) | D67: '=Config!F5/F6/F7/F8/F14/F27 (釘選 vr 預設) | E67: M4: VR Facility 專區原跟隨下拉選單, 選 GB200 時整區變 GB200 成本卻掛 VR 標題, 汙染 OpenAI_Sim B38/B57。實測修正後切換下拉 D54/D88 不動。
A68: WP_Param | B68: B149 | C68: '=2*Config!$B$64*256*Config!$B$60/1000000 | D68: '=2*Config!$B$64*$B$145*Config!$B$60/1000000 | E68: 動態性: all-reduce 數 256 為舊 128 層模型遺留, 改引 B145 (=2×n_layers, 現 296) 隨模型深度縮放。
A69: WP_Param | B69: B206 | C69: '=1*Config!$B$64*256*Config!$B$60/1000000 | D69: '=1*Config!$B$64*$B$145*Config!$B$60/1000000 | E69: 同上 (optimized 路徑)。
A70: TL_Param | B70: C39/D39 | C70: '=(I17+I20)/X38 | D70: '=(I17+I18+I20)/X38 | E70: Overhead% 漏加 prefill inter-rack 項 I18 (多機櫃 TP 時會低估)。
A71: (多處) | B71: 註記更新 | C71: 過期註記 | D71: 已更新 | E71: 含: Config C28 (B28 為公式非輸入), Revenue E11/E59 (TL 座標), DC E5-E18 (釘選說明+單價), OpenAI I34/I103/I144 (GB200≈0.39x), I288 (2025 推導值 48%), I127/I130 (使用率已內含警語), Sec.10/12 標題營收數字, WP C16/C18 (PFLOPS 註記歸位)。
A72: 修正後關鍵值變化
C73: Optimized tok/s per rack | D73: 21,661 → 21,301 (-1.7%) | E73: NVLink latency 項由 256→296 all-reduces。
C74: VR 年營收 ($M) | D74: 50,082 → 49,248 | E74: 同上連動。
C75: Disaggregated 吞吐損失 | D75: 32.2% → 1.98% | E75: M1。分離式推論在 IB XDR + GQA 下代價輕微 — 先前結論反轉。
C76: Scenario E (全惡化) 損失 | D76: 79.4% → 17.2% ($8.48B/yr) | E76: M1+M2 綜合。
A77: 未結事項 (需建模決策, 未修改)
A78: OpenAI_Sim | B78: row 86 | E78: 現金消耗 = OpInc-CapEx+SBC 未加回 COGS 內含折舊 (~75%), 基建成本雙重計入; 語意取決於自建 vs 租賃假設。
A79: OpenAI_Sim | B79: B130 | E79: 使用率重複折減 (B127 已含 70%, 再除 0.6); 已加警語註記, 公式保留待決。
A80: OpenAI_Sim | B80: 10C-12C | E80: 分層費率欄與 I 欄註記錯位且被 Assumed Blended Rate 繞過; 三年度架構不一致, 屬情境區塊重整範疇。
A81: OpenAI_Sim | B81: row 668-669 | E81: Realized% 2029=118%/2030=139% >100%: token 投射超出艦隊理論容量, 為實質可行性張力, 建議正式標記於研究結論。
A82: TL/Revenue | B82: 結構性 | E82: 機櫃比例縮放比較 (C30:D39) 非完全獨立 (下拉切換漂移約 ±5.7%); 投資級使用應為兩機櫃各建完整計算塊。
A84: 2026-09-22 v3 更新 (FT Sep-2026)
A85: Sheet | B85: Cell | C85: Previous | D85: New | E85: Reason
A86: OpenAI_Sim | B86: D8/E8/H8, G8 | C86: -17 / — / — ; +2 | D86: -25 / -57 / +39 ; 清空 | E86: 揭露列原為 Sep-2025 版, 更新至 Feb-2026 版; 2028-29 未分年揭露
A87: OpenAI_Sim | B87: D46:H46 | C87: 1.5/0.85/0.85/0.6/0.6 (硬編) | D87: '=FT_Sep2026!B25:F25 | E87: 營收路徑改依七月簡報 ($36B→$350B, Σ$840B)
A88: OpenAI_Sim | B88: D86:H86 | C88: '=OpInc−CapEx+SBC | D88: '=FT_Sep2026!B46:F46 | E88: 修正折舊雙計並納入完整算力 (項目 4+5 同步)
A89: OpenAI_Sim | B89: B17/B19/B113, B20/B21 | C89: $110B/$840B/840, =840/… | D89: $122B/$852B/852, =B113/… | E89: 3 月實際交割; 移除硬編 840
A90: OpenAI_Sim | B90: B129/B133/B153 | C90: 硬編 280 | D90: '=B128 / =H5 | E90: 2030 目標隨版本連動
A91: OpenAI_Sim | B91: row 675-676, CF C669:H669 | C91: — | D91: 旗標 + 所需 GW | E91: 項目 6: 容量張力明確標示 (未上調 H11/H95)
A92: FT_Sep2026 | B92: 全表 | C92: — | D92: 新增 | E92: 版本表、v3 營收路徑、現金橋、敏感度、資金跑道、容量張力
A93: 未結 | B93: OpenAI_Sim row 60-83 | E93: P&L 之 COGS 仍以 DC 模型推算, 未反映 $856B 算力口徑; 營業利益僅供參考, 現金以 FT_Sep2026 為準
A94: 未結 | B94: OpenAI_Sim 8C-12C | E94: 營收上調使 API 目標營收上升, 分層客戶數/token 量依原校準機制放大; Realized% 見旗標
A97: 2026-09-22 v4 更新 (前沿模型)
A98: Sheet | B98: Cell | C98: Previous | D98: New | E98: Reason
A99: Config | B99: J26:Q55, B29 | C99: — | D99: 前沿 MoE 預設表 + 選單 | E99: 以公開 config.json/模型卡建模; 專家大小與非專家參數由公開總/活躍參數反推, 精確閉合
A100: Config | B100: B31–B43 | C100: 自動縮放 (aspect 160) | D100: 預設驅動; Dense 仍可自動 | E100: MoE 總參數不應決定寬度/層數 (v3 對 1T MoE 推出 148 層×23,680, 與實際 61×7,168 不符)
A101: Config | B101: B55, B87 | C101: GQA 8 heads; KV 以權重位元組計 | D101: KV 元素/token/層 (K45) × KV bytes (K46) | E101: MLA/CSA/HCA 壓縮 KV; 權重位元組 (FP4) 不應套用於 KV
A102: Config | B102: E29:H43 | C102: 依參數門檻自動選層 (Mar-2026) | D102: 六層 Sep-2026 定價, F41 選單 | E102: MoE 總參數選價失真 (1.6T 會落入 Premium)
A103: Config | B103: B27/B28, B46, B57 | C103: 4000/=B27/4, 0.5, 8 | D103: 16000/1000, 0.35, 5 | E103: 代理式工作負載 (OpenRouter); MFU 稽核建議; DSpark block 5
A104: Config | B104: DV B32:B36 | C104: Dense/MoE 清單套用至數值格 | D104: 僅 B32 | E104: 資料驗證範圍錯誤
A105: WP_Param | B105: B46 | C105: '=Config!B51 | D105: '=Config!B52 | E105: 原連到標題格 "Data"
A106: WP_Param | B106: B50–B53, B104–B107 | C106: 4d² / 2·in²·d | D106: attn params 與 heads×head_dim×有效跨度 | E106: 泛化至 MLA/稀疏注意力; Dense 預設結果不變
A107: WP_Param | B107: B39/B40/B75/B127/B128/B162/B227 | C107: 全 MHA KV, 無 bytes | D107: 架構 KV × KV bytes | E107: 記憶體與頻寬以實際壓縮 KV 計
A108: WP_Param | B108: B158, B168 | C108: 全模型權重 | D108: 單請求=活躍; 批次=非專家+共享+路由×命中機率 | E108: MoE 批次解碼權重讀取
A109: TL_Param | B109: F20 | C109: '=WP_Param!B122 | D109: '=B122×batch×(N+1)/E[accepted]/MFU | E109: v3 解碼運算未乘批次
A110: 未結 | B110: TL/WP NVLink | E110: 仍以 TP all-reduce 建模; MoE 實務為 EP all-to-all, 預填 NVLink 可能高估
A111: 未結 | B111: Revenue_Model | E111: 未含 prompt caching 折價與使用率需求上限; 前沿 MoE 下營收為理論上限
A112: 未結 | B112: OpenAI_Sim Realized% | E112: 隨架構預設大幅變動 (V4-Pro 10.6% vs Legacy 149%); FT_Sep2026 容量旗標依賴此假設
