Workbook

Sheet README
A1: Tokenomics v5.0 — Block 1：機架規格、每 GW 資本支出與持有成本
A2: 第 0 層規格來源。本版只含 Block 1（供給面）；推論產出（Block 2）完成前，推論計算仍以 v4 為準。
A4: 用途 | B4: 回答：每 1 GW IT 電力，各世代可容納多少機架、需要多少資本支出、每年持有成本多少。不含產出與營收（Block 2 起）。
A5: 版本 | B5: 20260930_Tokenomics_v5.0（Block 1）。v4 的 OpenAI_Sim、FT_Sep2026 已依決議移除；Config/TL/WP/Revenue 將於 Block 2 重建後退場。
A6: 電力口徑 | B6: GW＝IT 關鍵電力（Andy 2026-09-30 確認）。設施電力＝IT × PUE，於 DC_Cost 與 Interface 並列。
A7: 工作表 | B7: Inputs（全域輸入與情境）→ Spec_Rack（各世代機架）→ DC_Cost（每 GW 計算，5 世代 × 3 成本情境）→ Interface（下游唯一連結點）；Sensitivity（VR200 單變數敏感度）；Checks（交叉檢查）；Sources（來源與查核狀態）。
A8: 成本情境 | B8: 低成本／基準／高成本：所有金額類輸入同時取低或高端，為『角落情境』，用來框出範圍，不代表機率。單一變數的影響看 Sensitivity。
A9: 功率情境 | B9: Inputs!E6 選 1／2／3（低功率／基準／高功率），決定每架配電設計功率，進而決定每 GW 機架數。這是物理設定，不混入成本情境。
A10: 顏色 | B10: 藍字＝輸入；黑字＝公式；綠字＝跨頁連結；黃底＝關鍵輸出。
A11: 來源標記 | B11: Verified／Interested-party／Analogy／Assumed／Derived。Analogy 與 Assumed 一律給區間。
A12: 網站同步 | B12: 本檔為事實來源；repo 以公式引擎直接計算本檔，parity 測試比對 Interface 全部格。
A13: 未結事項 | B13: (1) VR200 報價是否已含部分網路設備：若含，網路 % 會重複計算（見 Sources S11）。(2) Rubin Ultra 價格為推估，不進任何基準比較。(3) 非 NVIDIA 世代於 Block 2 以產出比例列加入。(4) 平均用電比將於 Block 2 以逐步能量模型做閉合檢查。

Sheet Inputs
A1: Inputs — 全域輸入（藍字可改）
A2: 低成本／基準／高成本為角落情境；單值輸入只填基準欄
A3: 參數 | B3: 單位 | D3: 低成本 | E3: 基準 | F3: 高成本 | G3: 標記 | H3: 來源／說明
A4: 控制
A5: IT 電力規模 | B5: GW | D5: =E5 -> 1 | E5: 1 | F5: =E5 -> 1 | G5: Decision | H5: 口徑：IT 關鍵電力
A6: 功率情境（1 低／2 基準／3 高） | B6: 選擇 | D6: =E6 -> 2 | E6: 2 | F6: =E6 -> 2 | G6: Decision | H6: 決定每架配電設計功率；見 Spec_Rack 第 9–11 列
A7: 規模與電力
A8: 機架外 IT 電力占比 | B8: % | D8: =E8 -> 0.08 | E8: 0.08 | F8: =E8 -> 0.08 | G8: Assumed | H8: 管理、儲存、網路機櫃等；區間 5–12%（見 Sensitivity）。v4 未計
A9: PUE | B9: x | D9: 1.1 | E9: 1.2 | F9: 1.3 | G9: Analogy | H9: 液冷 AI 設施；v4＝1.2。S14
A10: 平均用電 ÷ 配電設計功率 | B10: % | D10: 0.7 | E10: 0.8 | F10: 0.9 | G10: Assumed | H10: Block 2 以逐步能量模型閉合檢查
A11: 電價 | B11: $/kWh | D11: 0.06 | E11: 0.08 | F11: 0.1 | G11: Verified/Analogy | H11: EIA 美國工業電價 2026 年約 8.6–8.7¢（S13）；低端為 PPA（v4＝0.06）
A12: IT 設備（機架以外）
A13: Scale-out 網路 ÷ 機架價格 | B13: % | D13: 0.05 | E13: 0.1 | F13: 0.15 | G13: Analogy | H13: 1,024 GPU 叢集網路約為 GPU BOM 4–8%（S10）；GW 級多一層以上交換，取 5–15%
A14: 儲存與管理設備 | B14: $/GPU | D14: 300 | E14: 500 | F14: 800 | G14: Assumed | H14: v4 約 $350/GPU（$25K/架）
A15: 廠房（每 MW IT，$M）
A16: 土地 | B16: $M/MW | D16: 0.02 | E16: 0.02 | F16: 0.02 | G16: Assumed | H16: v4：100 英畝 × $200K／GW
A17: 建物與基地工程 | B17: $M/MW | D17: 3 | E17: 3.6 | F17: 4.5 | G17: Assumed | H17: 分項為假設；總額以 JLL 校準（S12）
A18: 電力設施（變電、中壓、發電機、UPS） | B18: $M/MW | D18: 3.8 | E18: 4.5 | F18: 5.5 | G18: Assumed | H18: 同上
A19: 機械與散熱（液冷迴路、散熱設備） | B19: $M/MW | D19: 2 | E19: 2.5 | F19: 3.2 | G19: Assumed | H19: 機架內冷板與 manifold 含在機架價格
A20: 光纖、佈線、保全、BMS | B20: $M/MW | D20: 0.3 | E20: 0.4 | F20: 0.5 | G20: Assumed | H20: 同上
A21: 設計、管理與預備費 | B21: % 廠房 | D21: 0.12 | E21: 0.15 | F21: 0.18 | G21: Assumed | H21: v4＝15%
A22: 年限與資金成本
A23: IT 設備折舊年限 | B23: 年 | D23: 6 | E23: 6 | F23: 4 | G23: Verified | H23: CoreWeave 與主要 hyperscaler 6 年；Nebius 4 年、Lambda 5 年（S15）。高成本情境取 4
A24: 建物年限 | B24: 年 | D24: =E24 -> 30 | E24: 30 | F24: =E24 -> 30 | G24: Analogy | H24: v4
A25: 電力設施年限 | B25: 年 | D25: =E25 -> 20 | E25: 20 | F25: =E25 -> 20 | G25: Analogy | H25: v4
A26: 機械與散熱年限 | B26: 年 | D26: =E26 -> 15 | E26: 15 | F26: =E26 -> 15 | G26: Analogy | H26: v4
A27: 光纖與保全年限 | B27: 年 | D27: =E27 -> 10 | E27: 10 | F27: =E27 -> 10 | G27: Analogy | H27: v4
A28: WACC（經濟口徑） | B28: % | D28: 0.08 | E28: 0.1 | F28: 0.13 | G28: Assumed | H28: 與擁有者無關的單一假設；下游公司模型以自身 WACC 覆寫（Andy 2026-09-30 決定）
A29: 營運費用
A30: IT 維護 | B30: % IT 資本/年 | D30: 0.02 | E30: 0.03 | F30: 0.04 | G30: Analogy | H30: v4＝3%
A31: 廠房維護 | B31: % 廠房資本/年 | D31: 0.015 | E31: 0.02 | F31: 0.025 | G31: Analogy | H31: v4＝2%
A32: 人員 | B32: $M/GW/年 | D32: 50 | E32: 75 | F32: 100 | G32: Assumed | H32: v4：500 FTE × $150K
A33: 軟體授權與連線 | B33: $M/GW/年 | D33: 150 | E33: 200 | F33: 250 | G33: Assumed | H33: v4＝$200M
A34: 水與耗材 | B34: $M/MW/年 | D34: 0.04 | E34: 0.05 | F34: 0.06 | G34: Assumed | H34: v4＝$50K/MW
A35: 財產稅與保險 | B35: % 總資本/年 | D35: 0.003 | E35: 0.005 | F35: 0.008 | G35: Analogy | H35: v4＝0.5%

Sheet Spec_Rack
A1: Spec_Rack — 各世代機架規格（Block 1 只含功率與價格；效能規格於 Block 2 加入）
A2: 價格為買方取得價（CSP/hyperscaler 口徑）；Hopper 以 4 台 HGX 構成一架（32 GPU）以便比較
A4: 世代 | C4: Hopper H100 | D4: GB200 NVL72 | E4: GB300 NVL72 | F4: VR200 NVL72 | G4: Rubin Ultra NVL576
A5: 平台／出貨 | C5: HGX ×4（32 GPU） | D5: 2024–25 出貨 | E5: 2025–26 主力 | F5: 2026 下半年開始出貨 | G5: 2027 預估（Kyber）
A6: GPU 封裝／架 | C6: 32 | D6: 72 | E6: 72 | F6: 72 | G6: 144
A7: 冷卻 | C7: 氣冷 | D7: 液冷 | E7: 液冷 | F7: 液冷（必須） | G7: 液冷
A8: 配電設計功率 低（kW） | C8: 38 | D8: 120 | E8: 132 | F8: 190 | G8: 550
A9: 配電設計功率 基準（kW） | C9: 41 | D9: 130 | E9: 137 | F9: 227 | G9: 600
A10: 配電設計功率 高（kW） | C10: 44 | D10: 140 | E10: 142 | F10: 230 | G10: 650
A11: 機架價格 低（$M） | C11: 0.9 | D11: 2.8 | E11: 4 | F11: 6.7 | G11: 23.4
A12: 機架價格 基準（$M） | C12: 1.1 | D12: 3.1 | E12: 5 | F12: 7.8 | G12: 31.2
A13: 機架價格 高（$M） | C13: 1.3 | D13: 3.4 | E13: 6.5 | F13: 9.1 | G13: 39
A14: 價格涵蓋範圍 | C14: 8 GPU 伺服器 + CPU、NIC、機內儲存；以部署當時取得價計 | D14: 運算匣＋NVLink 交換匣＋機架內冷卻 | E14: 同上 | F14: 運算匣＋交換匣＋冷卻＋約 $1M NAND；是否含部分網路待查（S11） | G14: 144 封裝；價格＝VR 每 GPU 價 × 1.5／2.0／2.5（推估）
A15: 功率來源 | C15: DGX H100 最大 10.2 kW／8 GPU（S1） | D15: 約 120–130 kW（S3）；v4＝139 | E15: 132–142 kW（S3、S5） | F15: Max-Q 約 190、Max-P 約 230 kW（S7）；Supermicro DLC-2 設計點 227 kW（S8） | G15: 約 600 kW（S7）
A16: 價格來源 | C16: HGX H100 8 GPU 伺服器約 $220–320K（S2，弱證據） | D16: $2.8–3.4M（S4）；Barron's 約 $3M | E16: MS 約 $4M；2026-08 採購單約 $5M；媒體 $6–6.5M（S4、S6） | F16: MS $7.8M（自購記憶體 $6.7M）；Bernstein $9.09M；報價 $5–7M（S9） | G16: 無公開報價；純推估，不進基準比較
A17: 標記 | C17: Analogy | D17: Interested-party | E17: Interested-party | F17: Interested-party | G17: Assumed
A19: 註：GPU 數為封裝數（Rubin Ultra 為 144 封裝，NVIDIA 以 576 die 命名為 NVL576）。

Sheet DC_Cost
A1: DC_Cost — 每 GW（IT）資本支出與年持有成本：5 世代 × 3 成本情境
A2: 功率情境由 Inputs!E6 控制；成本情境為角落情境（所有金額輸入同時取低或高）
A4: 世代 | C4: =Spec_Rack!C4 -> Hopper H100 | D4: =Spec_Rack!C4 -> Hopper H100 | E4: =Spec_Rack!C4 -> Hopper H100 | F4: =Spec_Rack!D4 -> GB200 NVL72 | G4: =Spec_Rack!D4 -> GB200 NVL72 | H4: =Spec_Rack!D4 -> GB200 NVL72 | I4: =Spec_Rack!E4 -> GB300 NVL72 | J4: =Spec_Rack!E4 -> GB300 NVL72 | K4: =Spec_Rack!E4 -> GB300 NVL72 | L4: =Spec_Rack!F4 -> VR200 NVL72 | M4: =Spec_Rack!F4 -> VR200 NVL72 | N4: =Spec_Rack!F4 -> VR200 NVL72 | O4: =Spec_Rack!G4 -> Rubin Ultra NVL576 | P4: =Spec_Rack!G4 -> Rubin Ultra NVL576 | Q4: =Spec_Rack!G4 -> Rubin Ultra NVL576
A5: 成本情境 | C5: 低成本 | D5: 基準 | E5: 高成本 | F5: 低成本 | G5: 基準 | H5: 高成本 | I5: 低成本 | J5: 基準 | K5: 高成本 | L5: 低成本 | M5: 基準 | N5: 高成本 | O5: 低成本 | P5: 基準 | Q5: 高成本
A7: A. 規模與電力
A8: IT 電力 | B8: MW | C8: =Inputs!$E$5*1000 -> 1000 | D8: =Inputs!$E$5*1000 -> 1000 | E8: =Inputs!$E$5*1000 -> 1000 | F8: =Inputs!$E$5*1000 -> 1000 | G8: =Inputs!$E$5*1000 -> 1000 | H8: =Inputs!$E$5*1000 -> 1000 | I8: =Inputs!$E$5*1000 -> 1000 | J8: =Inputs!$E$5*1000 -> 1000 | ... Q8: =Inputs!$E$5*1000 -> 1000
A9: 機架外 IT 電力占比 | B9: % | C9: =Inputs!$E$8 -> 0.08 | D9: =Inputs!$E$8 -> 0.08 | E9: =Inputs!$E$8 -> 0.08 | F9: =Inputs!$E$8 -> 0.08 | G9: =Inputs!$E$8 -> 0.08 | H9: =Inputs!$E$8 -> 0.08 | I9: =Inputs!$E$8 -> 0.08 | J9: =Inputs!$E$8 -> 0.08 | ... Q9: =Inputs!$E$8 -> 0.08
A10: 機架可用 IT 電力 | B10: MW | C10: =C8*(1-C9) -> 920 | D10: =D8*(1-D9) -> 920 | E10: =E8*(1-E9) -> 920 | F10: =F8*(1-F9) -> 920 | G10: =G8*(1-G9) -> 920 | H10: =H8*(1-H9) -> 920 | I10: =I8*(1-I9) -> 920 | J10: =J8*(1-J9) -> 920 | ... Q10: =Q8*(1-Q9) -> 920
A11: 每架配電設計功率 | B11: kW | C11: =CHOOSE(Inputs!$E$6,Spec_Rack!C8,Spec_Rack!C9,Spec_Rack!C10) -> 41 | D11: =CHOOSE(Inputs!$E$6,Spec_Rack!C8,Spec_Rack!C9,Spec_Rack!C10) -> 41 | E11: =CHOOSE(Inputs!$E$6,Spec_Rack!C8,Spec_Rack!C9,Spec_Rack!C10) -> 41 | F11: =CHOOSE(Inputs!$E$6,Spec_Rack!D8,Spec_Rack!D9,Spec_Rack!D10) -> 130 | G11: =CHOOSE(Inputs!$E$6,Spec_Rack!D8,Spec_Rack!D9,Spec_Rack!D10) -> 130 | H11: =CHOOSE(Inputs!$E$6,Spec_Rack!D8,Spec_Rack!D9,Spec_Rack!D10) -> 130 | I11: =CHOOSE(Inputs!$E$6,Spec_Rack!E8,Spec_Rack!E9,Spec_Rack!E10) -> 137 | J11: =CHOOSE(Inputs!$E$6,Spec_Rack!E8,Spec_Rack!E9,Spec_Rack!E10) -> 137 | K11: =CHOOSE(Inputs!$E$6,Spec_Rack!E8,Spec_Rack!E9,Spec_Rack!E10) -> 137 | L11: =CHOOSE(Inputs!$E$6,Spec_Rack!F8,Spec_Rack!F9,Spec_Rack!F10) -> 227 | M11: =CHOOSE(Inputs!$E$6,Spec_Rack!F8,Spec_Rack!F9,Spec_Rack!F10) -> 227 | N11: =CHOOSE(Inputs!$E$6,Spec_Rack!F8,Spec_Rack!F9,Spec_Rack!F10) -> 227 | O11: =CHOOSE(Inputs!$E$6,Spec_Rack!G8,Spec_Rack!G9,Spec_Rack!G10) -> 600 | P11: =CHOOSE(Inputs!$E$6,Spec_Rack!G8,Spec_Rack!G9,Spec_Rack!G10) -> 600 | Q11: =CHOOSE(Inputs!$E$6,Spec_Rack!G8,Spec_Rack!G9,Spec_Rack!G10) -> 600
A12: 每 GW 機架數 | B12: 架 | C12: =FLOOR(C10*1000/C11,1) -> 22439 | D12: =FLOOR(D10*1000/D11,1) -> 22439 | E12: =FLOOR(E10*1000/E11,1) -> 22439 | F12: =FLOOR(F10*1000/F11,1) -> 7076 | G12: =FLOOR(G10*1000/G11,1) -> 7076 | H12: =FLOOR(H10*1000/H11,1) -> 7076 | I12: =FLOOR(I10*1000/I11,1) -> 6715 | J12: =FLOOR(J10*1000/J11,1) -> 6715 | ... Q12: =FLOOR(Q10*1000/Q11,1) -> 1533
A13: GPU 封裝／架 | B13: 顆 | C13: =Spec_Rack!C6 -> 32 | D13: =Spec_Rack!C6 -> 32 | E13: =Spec_Rack!C6 -> 32 | F13: =Spec_Rack!D6 -> 72 | G13: =Spec_Rack!D6 -> 72 | H13: =Spec_Rack!D6 -> 72 | I13: =Spec_Rack!E6 -> 72 | J13: =Spec_Rack!E6 -> 72 | K13: =Spec_Rack!E6 -> 72 | L13: =Spec_Rack!F6 -> 72 | M13: =Spec_Rack!F6 -> 72 | N13: =Spec_Rack!F6 -> 72 | O13: =Spec_Rack!G6 -> 144 | P13: =Spec_Rack!G6 -> 144 | Q13: =Spec_Rack!G6 -> 144
A14: 每 GW GPU 數 | B14: 顆 | C14: =C12*C13 -> 718048 | D14: =D12*D13 -> 718048 | E14: =E12*E13 -> 718048 | F14: =F12*F13 -> 509472 | G14: =G12*G13 -> 509472 | H14: =H12*H13 -> 509472 | I14: =I12*I13 -> 483480 | J14: =J12*J13 -> 483480 | ... Q14: =Q12*Q13 -> 220752
A15: PUE | B15: x | C15: =Inputs!D9 -> 1.1 | D15: =Inputs!E9 -> 1.2 | E15: =Inputs!F9 -> 1.3 | F15: =Inputs!D9 -> 1.1 | G15: =Inputs!E9 -> 1.2 | H15: =Inputs!F9 -> 1.3 | I15: =Inputs!D9 -> 1.1 | J15: =Inputs!E9 -> 1.2 | K15: =Inputs!F9 -> 1.3 | L15: =Inputs!D9 -> 1.1 | M15: =Inputs!E9 -> 1.2 | N15: =Inputs!F9 -> 1.3 | O15: =Inputs!D9 -> 1.1 | P15: =Inputs!E9 -> 1.2 | Q15: =Inputs!F9 -> 1.3
A16: 設施電力（IT × PUE） | B16: MW | C16: =C8*C15 -> 1100 | D16: =D8*D15 -> 1200 | E16: =E8*E15 -> 1300 | F16: =F8*F15 -> 1100 | G16: =G8*G15 -> 1200 | H16: =H8*H15 -> 1300 | I16: =I8*I15 -> 1100 | J16: =J8*J15 -> 1200 | ... Q16: =Q8*Q15 -> 1300
A17: B. 資本支出（$B／GW）
A18: 機架單價 | B18: $M | C18: =Spec_Rack!C11 -> 0.9 | D18: =Spec_Rack!C12 -> 1.1 | E18: =Spec_Rack!C13 -> 1.3 | F18: =Spec_Rack!D11 -> 2.8 | G18: =Spec_Rack!D12 -> 3.1 | H18: =Spec_Rack!D13 -> 3.4 | I18: =Spec_Rack!E11 -> 4 | J18: =Spec_Rack!E12 -> 5 | K18: =Spec_Rack!E13 -> 6.5 | L18: =Spec_Rack!F11 -> 6.7 | M18: =Spec_Rack!F12 -> 7.8 | N18: =Spec_Rack!F13 -> 9.1 | O18: =Spec_Rack!G11 -> 23.4 | P18: =Spec_Rack!G12 -> 31.2 | Q18: =Spec_Rack!G13 -> 39
A19: 機架 | B19: $B | C19: =C12*C18/1000 -> 20.1951 | D19: =D12*D18/1000 -> 24.6829 | E19: =E12*E18/1000 -> 29.1707 | F19: =F12*F18/1000 -> 19.8128 | G19: =G12*G18/1000 -> 21.9356 | H19: =H12*H18/1000 -> 24.0584 | I19: =I12*I18/1000 -> 26.86 | J19: =J12*J18/1000 -> 33.575 | ... Q19: =Q12*Q18/1000 -> 59.787
A20: Scale-out 網路 ÷ 機架價格 | B20: % | C20: =Inputs!D13 -> 0.05 | D20: =Inputs!E13 -> 0.1 | E20: =Inputs!F13 -> 0.15 | F20: =Inputs!D13 -> 0.05 | G20: =Inputs!E13 -> 0.1 | H20: =Inputs!F13 -> 0.15 | I20: =Inputs!D13 -> 0.05 | J20: =Inputs!E13 -> 0.1 | K20: =Inputs!F13 -> 0.15 | L20: =Inputs!D13 -> 0.05 | M20: =Inputs!E13 -> 0.1 | N20: =Inputs!F13 -> 0.15 | O20: =Inputs!D13 -> 0.05 | P20: =Inputs!E13 -> 0.1 | Q20: =Inputs!F13 -> 0.15
A21: Scale-out 網路 | B21: $B | C21: =C19*C20 -> 1.009755 | D21: =D19*D20 -> 2.46829 | E21: =E19*E20 -> 4.375605 | F21: =F19*F20 -> 0.99064 | G21: =G19*G20 -> 2.19356 | H21: =H19*H20 -> 3.60876 | I21: =I19*I20 -> 1.343 | J21: =J19*J20 -> 3.3575 | ... Q21: =Q19*Q20 -> 8.96805
A22: 儲存與管理 | B22: $/GPU | C22: =Inputs!D14 -> 300 | D22: =Inputs!E14 -> 500 | E22: =Inputs!F14 -> 800 | F22: =Inputs!D14 -> 300 | G22: =Inputs!E14 -> 500 | H22: =Inputs!F14 -> 800 | I22: =Inputs!D14 -> 300 | J22: =Inputs!E14 -> 500 | K22: =Inputs!F14 -> 800 | L22: =Inputs!D14 -> 300 | M22: =Inputs!E14 -> 500 | N22: =Inputs!F14 -> 800 | O22: =Inputs!D14 -> 300 | P22: =Inputs!E14 -> 500 | Q22: =Inputs!F14 -> 800
A23: 儲存與管理 | B23: $B | C23: =C14*C22/1000000000 -> 0.2154144 | D23: =D14*D22/1000000000 -> 0.359024 | E23: =E14*E22/1000000000 -> 0.5744384 | F23: =F14*F22/1000000000 -> 0.1528416 | G23: =G14*G22/1000000000 -> 0.254736 | H23: =H14*H22/1000000000 -> 0.4075776 | I23: =I14*I22/1000000000 -> 0.145044 | J23: =J14*J22/1000000000 -> 0.24174 | ... Q23: =Q14*Q22/1000000000 -> 0.1766016
A24: IT 設備小計 | B24: $B | C24: =C19+C21+C23 -> 21.420269 | D24: =D19+D21+D23 -> 27.510214 | E24: =E19+E21+E23 -> 34.120743 | F24: =F19+F21+F23 -> 20.956282 | G24: =G19+G21+G23 -> 24.383896 | H24: =H19+H21+H23 -> 28.074738 | I24: =I19+I21+I23 -> 28.348044 | J24: =J19+J21+J23 -> 37.17424 | ... Q24: =Q19+Q21+Q23 -> 68.931652
A25: 土地 | B25: $B | C25: =C8*Inputs!D16/1000 -> 0.02 | D25: =D8*Inputs!E16/1000 -> 0.02 | E25: =E8*Inputs!F16/1000 -> 0.02 | F25: =F8*Inputs!D16/1000 -> 0.02 | G25: =G8*Inputs!E16/1000 -> 0.02 | H25: =H8*Inputs!F16/1000 -> 0.02 | I25: =I8*Inputs!D16/1000 -> 0.02 | J25: =J8*Inputs!E16/1000 -> 0.02 | K25: =K8*Inputs!F16/1000 -> 0.02 | L25: =L8*Inputs!D16/1000 -> 0.02 | M25: =M8*Inputs!E16/1000 -> 0.02 | N25: =N8*Inputs!F16/1000 -> 0.02 | O25: =O8*Inputs!D16/1000 -> 0.02 | P25: =P8*Inputs!E16/1000 -> 0.02 | Q25: =Q8*Inputs!F16/1000 -> 0.02
A26: 建物與基地 | B26: $B | C26: =C8*Inputs!D17/1000 -> 3 | D26: =D8*Inputs!E17/1000 -> 3.6 | E26: =E8*Inputs!F17/1000 -> 4.5 | F26: =F8*Inputs!D17/1000 -> 3 | G26: =G8*Inputs!E17/1000 -> 3.6 | H26: =H8*Inputs!F17/1000 -> 4.5 | I26: =I8*Inputs!D17/1000 -> 3 | J26: =J8*Inputs!E17/1000 -> 3.6 | K26: =K8*Inputs!F17/1000 -> 4.5 | L26: =L8*Inputs!D17/1000 -> 3 | M26: =M8*Inputs!E17/1000 -> 3.6 | N26: =N8*Inputs!F17/1000 -> 4.5 | O26: =O8*Inputs!D17/1000 -> 3 | P26: =P8*Inputs!E17/1000 -> 3.6 | Q26: =Q8*Inputs!F17/1000 -> 4.5
A27: 電力設施 | B27: $B | C27: =C8*Inputs!D18/1000 -> 3.8 | D27: =D8*Inputs!E18/1000 -> 4.5 | E27: =E8*Inputs!F18/1000 -> 5.5 | F27: =F8*Inputs!D18/1000 -> 3.8 | G27: =G8*Inputs!E18/1000 -> 4.5 | H27: =H8*Inputs!F18/1000 -> 5.5 | I27: =I8*Inputs!D18/1000 -> 3.8 | J27: =J8*Inputs!E18/1000 -> 4.5 | K27: =K8*Inputs!F18/1000 -> 5.5 | L27: =L8*Inputs!D18/1000 -> 3.8 | M27: =M8*Inputs!E18/1000 -> 4.5 | N27: =N8*Inputs!F18/1000 -> 5.5 | O27: =O8*Inputs!D18/1000 -> 3.8 | P27: =P8*Inputs!E18/1000 -> 4.5 | Q27: =Q8*Inputs!F18/1000 -> 5.5
A28: 機械與散熱 | B28: $B | C28: =C8*Inputs!D19/1000 -> 2 | D28: =D8*Inputs!E19/1000 -> 2.5 | E28: =E8*Inputs!F19/1000 -> 3.2 | F28: =F8*Inputs!D19/1000 -> 2 | G28: =G8*Inputs!E19/1000 -> 2.5 | H28: =H8*Inputs!F19/1000 -> 3.2 | I28: =I8*Inputs!D19/1000 -> 2 | J28: =J8*Inputs!E19/1000 -> 2.5 | K28: =K8*Inputs!F19/1000 -> 3.2 | L28: =L8*Inputs!D19/1000 -> 2 | M28: =M8*Inputs!E19/1000 -> 2.5 | N28: =N8*Inputs!F19/1000 -> 3.2 | O28: =O8*Inputs!D19/1000 -> 2 | P28: =P8*Inputs!E19/1000 -> 2.5 | Q28: =Q8*Inputs!F19/1000 -> 3.2
A29: 光纖與保全 | B29: $B | C29: =C8*Inputs!D20/1000 -> 0.3 | D29: =D8*Inputs!E20/1000 -> 0.4 | E29: =E8*Inputs!F20/1000 -> 0.5 | F29: =F8*Inputs!D20/1000 -> 0.3 | G29: =G8*Inputs!E20/1000 -> 0.4 | H29: =H8*Inputs!F20/1000 -> 0.5 | I29: =I8*Inputs!D20/1000 -> 0.3 | J29: =J8*Inputs!E20/1000 -> 0.4 | K29: =K8*Inputs!F20/1000 -> 0.5 | L29: =L8*Inputs!D20/1000 -> 0.3 | M29: =M8*Inputs!E20/1000 -> 0.4 | N29: =N8*Inputs!F20/1000 -> 0.5 | O29: =O8*Inputs!D20/1000 -> 0.3 | P29: =P8*Inputs!E20/1000 -> 0.4 | Q29: =Q8*Inputs!F20/1000 -> 0.5
A30: 設計、管理與預備費率 | B30: % | C30: =Inputs!D21 -> 0.12 | D30: =Inputs!E21 -> 0.15 | E30: =Inputs!F21 -> 0.18 | F30: =Inputs!D21 -> 0.12 | G30: =Inputs!E21 -> 0.15 | H30: =Inputs!F21 -> 0.18 | I30: =Inputs!D21 -> 0.12 | J30: =Inputs!E21 -> 0.15 | K30: =Inputs!F21 -> 0.18 | L30: =Inputs!D21 -> 0.12 | M30: =Inputs!E21 -> 0.15 | N30: =Inputs!F21 -> 0.18 | O30: =Inputs!D21 -> 0.12 | P30: =Inputs!E21 -> 0.15 | Q30: =Inputs!F21 -> 0.18
A31: 設計、管理與預備費 | B31: $B | C31: =(C26+C27+C28+C29)*C30 -> 1.092 | D31: =(D26+D27+D28+D29)*D30 -> 1.65 | E31: =(E26+E27+E28+E29)*E30 -> 2.466 | F31: =(F26+F27+F28+F29)*F30 -> 1.092 | G31: =(G26+G27+G28+G29)*G30 -> 1.65 | H31: =(H26+H27+H28+H29)*H30 -> 2.466 | I31: =(I26+I27+I28+I29)*I30 -> 1.092 | J31: =(J26+J27+J28+J29)*J30 -> 1.65 | ... Q31: =(Q26+Q27+Q28+Q29)*Q30 -> 2.466
A32: 廠房小計 | B32: $B | C32: =C25+C26+C27+C28+C29+C31 -> 10.212 | D32: =D25+D26+D27+D28+D29+D31 -> 12.67 | E32: =E25+E26+E27+E28+E29+E31 -> 16.186 | F32: =F25+F26+F27+F28+F29+F31 -> 10.212 | G32: =G25+G26+G27+G28+G29+G31 -> 12.67 | H32: =H25+H26+H27+H28+H29+H31 -> 16.186 | I32: =I25+I26+I27+I28+I29+I31 -> 10.212 | J32: =J25+J26+J27+J28+J29+J31 -> 12.67 | ... Q32: =Q25+Q26+Q27+Q28+Q29+Q31 -> 16.186
A33: 每 GW 總資本支出 | B33: $B | C33: =C24+C32 -> 31.632269 | D33: =D24+D32 -> 40.180214 | E33: =E24+E32 -> 50.306743 | F33: =F24+F32 -> 31.168282 | G33: =G24+G32 -> 37.053896 | H33: =H24+H32 -> 44.260738 | I33: =I24+I32 -> 38.560044 | J33: =J24+J32 -> 49.84424 | ... Q33: =Q24+Q32 -> 85.117652
A34: 每 GPU 資本支出（含廠房） | B34: $K | C34: =C33*1000000/C14 -> 44.05314 | D34: =D33*1000000/D14 -> 55.95756 | E34: =E33*1000000/E14 -> 70.060419 | F34: =F33*1000000/F14 -> 61.177614 | G34: =G33*1000000/G14 -> 72.729995 | H34: =H33*1000000/H14 -> 86.875702 | I34: =I33*1000000/I14 -> 79.7552 | J34: =J33*1000000/J14 -> 103.09473 | ... Q34: =Q33*1000000/Q14 -> 385.58043
A35: 每 MW IT 資本支出 | B35: $M | C35: =C33*1000/C8 -> 31.632269 | D35: =D33*1000/D8 -> 40.180214 | E35: =E33*1000/E8 -> 50.306743 | F35: =F33*1000/F8 -> 31.168282 | G35: =G33*1000/G8 -> 37.053896 | H35: =H33*1000/H8 -> 44.260738 | I35: =I33*1000/I8 -> 38.560044 | J35: =J33*1000/J8 -> 49.84424 | ... Q35: =Q33*1000/Q8 -> 85.117652
A36: 每 MW IT 廠房資本支出 | B36: $M | C36: =C32*1000/C8 -> 10.212 | D36: =D32*1000/D8 -> 12.67 | E36: =E32*1000/E8 -> 16.186 | F36: =F32*1000/F8 -> 10.212 | G36: =G32*1000/G8 -> 12.67 | H36: =H32*1000/H8 -> 16.186 | I36: =I32*1000/I8 -> 10.212 | J36: =J32*1000/J8 -> 12.67 | ... Q36: =Q32*1000/Q8 -> 16.186
A37: C. 年持有成本 — 會計口徑（$B／GW／年）
A38: IT 折舊年限 | B38: 年 | C38: =Inputs!D23 -> 6 | D38: =Inputs!E23 -> 6 | E38: =Inputs!F23 -> 4 | F38: =Inputs!D23 -> 6 | G38: =Inputs!E23 -> 6 | H38: =Inputs!F23 -> 4 | I38: =Inputs!D23 -> 6 | J38: =Inputs!E23 -> 6 | K38: =Inputs!F23 -> 4 | L38: =Inputs!D23 -> 6 | M38: =Inputs!E23 -> 6 | N38: =Inputs!F23 -> 4 | O38: =Inputs!D23 -> 6 | P38: =Inputs!E23 -> 6 | Q38: =Inputs!F23 -> 4
A39: IT 折舊 | B39: $B | C39: =C24/C38 -> 3.5700449 | D39: =D24/D38 -> 4.5850357 | E39: =E24/E38 -> 8.5301859 | F39: =F24/F38 -> 3.4927136 | G39: =G24/G38 -> 4.0639827 | H39: =H24/H38 -> 7.0186844 | I39: =I24/I38 -> 4.724674 | J39: =J24/J38 -> 6.1957067 | ... Q39: =Q24/Q38 -> 17.232913
A40: 廠房折舊（土地不折舊） | B40: $B | C40: =(C26/Inputs!D24+C27/Inputs!D25+C28/Inputs!D26+C29/Inputs!D27)*(1+C30) -> 0.50773333 | D40: =(D26/Inputs!E24+D27/Inputs!E25+D28/Inputs!E26+D29/Inputs!E27)*(1+D30) -> 0.63441667 | E40: =(E26/Inputs!F24+E27/Inputs!F25+E28/Inputs!F26+E29/Inputs!F27)*(1+E30) -> 0.81223333 | F40: =(F26/Inputs!D24+F27/Inputs!D25+F28/Inputs!D26+F29/Inputs!D27)*(1+F30) -> 0.50773333 | G40: =(G26/Inputs!E24+G27/Inputs!E25+G28/Inputs!E26+G29/Inputs!E27)*(1+G30) -> 0.63441667 | H40: =(H26/Inputs!F24+H27/Inputs!F25+H28/Inputs!F26+H29/Inputs!F27)*(1+H30) -> 0.81223333 | I40: =(I26/Inputs!D24+I27/Inputs!D25+I28/Inputs!D26+I29/Inputs!D27)*(1+I30) -> 0.50773333 | J40: =(J26/Inputs!E24+J27/Inputs!E25+J28/Inputs!E26+J29/Inputs!E27)*(1+J30) -> 0.63441667 | K40: =(K26/Inputs!F24+K27/Inputs!F25+K28/Inputs!F26+K29/Inputs!F27)*(1+K30) -> 0.81223333 | L40: =(L26/Inputs!D24+L27/Inputs!D25+L28/Inputs!D26+L29/Inputs!D27)*(1+L30) -> 0.50773333 | M40: =(M26/Inputs!E24+M27/Inputs!E25+M28/Inputs!E26+M29/Inputs!E27)*(1+M30) -> 0.63441667 | N40: =(N26/Inputs!F24+N27/Inputs!F25+N28/Inputs!F26+N29/Inputs!F27)*(1+N30) -> 0.81223333 | O40: =(O26/Inputs!D24+O27/Inputs!D25+O28/Inputs!D26+O29/Inputs!D27)*(1+O30) -> 0.50773333 | P40: =(P26/Inputs!E24+P27/Inputs!E25+P28/Inputs!E26+P29/Inputs!E27)*(1+P30) -> 0.63441667 | Q40: =(Q26/Inputs!F24+Q27/Inputs!F25+Q28/Inputs!F26+Q29/Inputs!F27)*(1+Q30) -> 0.81223333
A41: 平均用電 ÷ 配電設計功率 | B41: % | C41: =Inputs!D10 -> 0.7 | D41: =Inputs!E10 -> 0.8 | E41: =Inputs!F10 -> 0.9 | F41: =Inputs!D10 -> 0.7 | G41: =Inputs!E10 -> 0.8 | H41: =Inputs!F10 -> 0.9 | I41: =Inputs!D10 -> 0.7 | J41: =Inputs!E10 -> 0.8 | K41: =Inputs!F10 -> 0.9 | L41: =Inputs!D10 -> 0.7 | M41: =Inputs!E10 -> 0.8 | N41: =Inputs!F10 -> 0.9 | O41: =Inputs!D10 -> 0.7 | P41: =Inputs!E10 -> 0.8 | Q41: =Inputs!F10 -> 0.9
A42: 電價 | B42: $/kWh | C42: =Inputs!D11 -> 0.06 | D42: =Inputs!E11 -> 0.08 | E42: =Inputs!F11 -> 0.1 | F42: =Inputs!D11 -> 0.06 | G42: =Inputs!E11 -> 0.08 | H42: =Inputs!F11 -> 0.1 | I42: =Inputs!D11 -> 0.06 | J42: =Inputs!E11 -> 0.08 | K42: =Inputs!F11 -> 0.1 | L42: =Inputs!D11 -> 0.06 | M42: =Inputs!E11 -> 0.08 | N42: =Inputs!F11 -> 0.1 | O42: =Inputs!D11 -> 0.06 | P42: =Inputs!E11 -> 0.08 | Q42: =Inputs!F11 -> 0.1
A43: 電費 | B43: $B | C43: =C8*1000*C41*C15*8760*C42/1000000000 -> 0.404712 | D43: =D8*1000*D41*D15*8760*D42/1000000000 -> 0.672768 | E43: =E8*1000*E41*E15*8760*E42/1000000000 -> 1.02492 | F43: =F8*1000*F41*F15*8760*F42/1000000000 -> 0.404712 | G43: =G8*1000*G41*G15*8760*G42/1000000000 -> 0.672768 | H43: =H8*1000*H41*H15*8760*H42/1000000000 -> 1.02492 | I43: =I8*1000*I41*I15*8760*I42/1000000000 -> 0.404712 | J43: =J8*1000*J41*J15*8760*J42/1000000000 -> 0.672768 | ... Q43: =Q8*1000*Q41*Q15*8760*Q42/1000000000 -> 1.02492
A44: IT 維護 | B44: $B | C44: =C24*Inputs!D30 -> 0.42840539 | D44: =D24*Inputs!E30 -> 0.82530642 | E44: =E24*Inputs!F30 -> 1.3648297 | F44: =F24*Inputs!D30 -> 0.41912563 | G44: =G24*Inputs!E30 -> 0.73151688 | H44: =H24*Inputs!F30 -> 1.1229895 | I44: =I24*Inputs!D30 -> 0.56696088 | J44: =J24*Inputs!E30 -> 1.1152272 | K44: =K24*Inputs!F30 -> 2.0232564 | L44: =L24*Inputs!D30 -> 0.57186686 | M44: =M24*Inputs!E30 -> 1.047361 | N44: =N24*Inputs!F30 -> 1.705503 | O44: =O24*Inputs!D30 -> 0.75464071 | P44: =P24*Inputs!E30 -> 1.5816881 | Q44: =Q24*Inputs!F30 -> 2.7572661
A45: 廠房維護 | B45: $B | C45: =C32*Inputs!D31 -> 0.15318 | D45: =D32*Inputs!E31 -> 0.2534 | E45: =E32*Inputs!F31 -> 0.40465 | F45: =F32*Inputs!D31 -> 0.15318 | G45: =G32*Inputs!E31 -> 0.2534 | H45: =H32*Inputs!F31 -> 0.40465 | I45: =I32*Inputs!D31 -> 0.15318 | J45: =J32*Inputs!E31 -> 0.2534 | K45: =K32*Inputs!F31 -> 0.40465 | L45: =L32*Inputs!D31 -> 0.15318 | M45: =M32*Inputs!E31 -> 0.2534 | N45: =N32*Inputs!F31 -> 0.40465 | O45: =O32*Inputs!D31 -> 0.15318 | P45: =P32*Inputs!E31 -> 0.2534 | Q45: =Q32*Inputs!F31 -> 0.40465
A46: 人員、軟體、水與耗材 | B46: $B | C46: =(Inputs!D32*C8/1000+Inputs!D33*C8/1000+Inputs!D34*C8)/1000 -> 0.24 | D46: =(Inputs!E32*D8/1000+Inputs!E33*D8/1000+Inputs!E34*D8)/1000 -> 0.325 | E46: =(Inputs!F32*E8/1000+Inputs!F33*E8/1000+Inputs!F34*E8)/1000 -> 0.41 | F46: =(Inputs!D32*F8/1000+Inputs!D33*F8/1000+Inputs!D34*F8)/1000 -> 0.24 | G46: =(Inputs!E32*G8/1000+Inputs!E33*G8/1000+Inputs!E34*G8)/1000 -> 0.325 | H46: =(Inputs!F32*H8/1000+Inputs!F33*H8/1000+Inputs!F34*H8)/1000 -> 0.41 | I46: =(Inputs!D32*I8/1000+Inputs!D33*I8/1000+Inputs!D34*I8)/1000 -> 0.24 | J46: =(Inputs!E32*J8/1000+Inputs!E33*J8/1000+Inputs!E34*J8)/1000 -> 0.325 | K46: =(Inputs!F32*K8/1000+Inputs!F33*K8/1000+Inputs!F34*K8)/1000 -> 0.41 | L46: =(Inputs!D32*L8/1000+Inputs!D33*L8/1000+Inputs!D34*L8)/1000 -> 0.24 | M46: =(Inputs!E32*M8/1000+Inputs!E33*M8/1000+Inputs!E34*M8)/1000 -> 0.325 | N46: =(Inputs!F32*N8/1000+Inputs!F33*N8/1000+Inputs!F34*N8)/1000 -> 0.41 | O46: =(Inputs!D32*O8/1000+Inputs!D33*O8/1000+Inputs!D34*O8)/1000 -> 0.24 | P46: =(Inputs!E32*P8/1000+Inputs!E33*P8/1000+Inputs!E34*P8)/1000 -> 0.325 | Q46: =(Inputs!F32*Q8/1000+Inputs!F33*Q8/1000+Inputs!F34*Q8)/1000 -> 0.41
A47: 財產稅與保險 | B47: $B | C47: =C33*Inputs!D35 -> 0.094896808 | D47: =D33*Inputs!E35 -> 0.20090107 | E47: =E33*Inputs!F35 -> 0.40245395 | F47: =F33*Inputs!D35 -> 0.093504845 | G47: =G33*Inputs!E35 -> 0.18526948 | H47: =H33*Inputs!F35 -> 0.3540859 | I47: =I33*Inputs!D35 -> 0.11568013 | J47: =J33*Inputs!E35 -> 0.2492212 | K47: =K33*Inputs!F35 -> 0.53413927 | L47: =L33*Inputs!D35 -> 0.11641603 | M47: =M33*Inputs!E35 -> 0.23791016 | N47: =N33*Inputs!F35 -> 0.4705886 | O47: =O33*Inputs!D35 -> 0.14383211 | P47: =P33*Inputs!E35 -> 0.32696468 | Q47: =Q33*Inputs!F35 -> 0.68094121
A48: 營運費用小計（不含折舊） | B48: $B | C48: =C43+C44+C45+C46+C47 -> 1.3211942 | D48: =D43+D44+D45+D46+D47 -> 2.2773755 | E48: =E43+E44+E45+E46+E47 -> 3.6068537 | F48: =F43+F44+F45+F46+F47 -> 1.3105225 | G48: =G43+G44+G45+G46+G47 -> 2.1679544 | H48: =H43+H44+H45+H46+H47 -> 3.3166454 | I48: =I43+I44+I45+I46+I47 -> 1.480533 | J48: =J43+J44+J45+J46+J47 -> 2.6156164 | ... Q48: =Q43+Q44+Q45+Q46+Q47 -> 5.2777773
A49: 年持有成本 — 會計口徑 | B49: $B | C49: =C39+C40+C48 -> 5.3989724 | D49: =D39+D40+D48 -> 7.4968278 | E49: =E39+E40+E48 -> 12.949273 | F49: =F39+F40+F48 -> 5.3109694 | G49: =G39+G40+G48 -> 6.8663537 | H49: =H39+H40+H48 -> 11.147563 | I49: =I39+I40+I48 -> 6.7129403 | J49: =J39+J40+J48 -> 9.4457397 | ... Q49: =Q39+Q40+Q48 -> 23.322924
A50: D. 年持有成本 — 經濟口徑（資本回收年金）
A51: WACC | B51: % | C51: =Inputs!D28 -> 0.08 | D51: =Inputs!E28 -> 0.1 | E51: =Inputs!F28 -> 0.13 | F51: =Inputs!D28 -> 0.08 | G51: =Inputs!E28 -> 0.1 | H51: =Inputs!F28 -> 0.13 | I51: =Inputs!D28 -> 0.08 | J51: =Inputs!E28 -> 0.1 | K51: =Inputs!F28 -> 0.13 | L51: =Inputs!D28 -> 0.08 | M51: =Inputs!E28 -> 0.1 | N51: =Inputs!F28 -> 0.13 | O51: =Inputs!D28 -> 0.08 | P51: =Inputs!E28 -> 0.1 | Q51: =Inputs!F28 -> 0.13
A52: IT 資本回收係數 | B52: x | C52: =C51/(1-(1+C51)^(-C38)) -> 0.21631539 | D52: =D51/(1-(1+D51)^(-D38)) -> 0.22960738 | E52: =E51/(1-(1+E51)^(-E38)) -> 0.3361942 | F52: =F51/(1-(1+F51)^(-F38)) -> 0.21631539 | G52: =G51/(1-(1+G51)^(-G38)) -> 0.22960738 | H52: =H51/(1-(1+H51)^(-H38)) -> 0.3361942 | I52: =I51/(1-(1+I51)^(-I38)) -> 0.21631539 | J52: =J51/(1-(1+J51)^(-J38)) -> 0.22960738 | ... Q52: =Q51/(1-(1+Q51)^(-Q38)) -> 0.3361942
A53: IT 資本回收 | B53: $B | C53: =C24*C52 -> 4.6335338 | D53: =D24*D52 -> 6.3165482 | E53: =E24*E52 -> 11.471196 | F53: =F24*F52 -> 4.5331661 | G53: =G24*G52 -> 5.5987225 | H53: =H24*H52 -> 9.4385639 | I53: =I24*I52 -> 6.1321181 | J53: =J24*J52 -> 8.5354799 | ... Q53: =Q24*Q52 -> 23.174421
A54: 廠房資本回收（土地按 WACC 計機會成本） | B54: $B | C54: =(C26*C51/(1-(1+C51)^(-Inputs!D24))+C27*C51/(1-(1+C51)^(-Inputs!D25))+C28*C51/(1-(1+C51)^(-Inputs!D26))+C29*C51/(1-(1+C51)^(-Inputs!D27)))*(1+C30)+C25*C51 -> 1.0453153 | D54: =(D26*D51/(1-(1+D51)^(-Inputs!E24))+D27*D51/(1-(1+D51)^(-Inputs!E25))+D28*D51/(1-(1+D51)^(-Inputs!E26))+D29*D51/(1-(1+D51)^(-Inputs!E27)))*(1+D30)+D25*D51 -> 1.5018716 | E54: =(E26*E51/(1-(1+E51)^(-Inputs!F24))+E27*E51/(1-(1+E51)^(-Inputs!F25))+E28*E51/(1-(1+E51)^(-Inputs!F26))+E29*E51/(1-(1+E51)^(-Inputs!F27)))*(1+E30)+E25*E51 -> 2.3279224 | F54: =(F26*F51/(1-(1+F51)^(-Inputs!D24))+F27*F51/(1-(1+F51)^(-Inputs!D25))+F28*F51/(1-(1+F51)^(-Inputs!D26))+F29*F51/(1-(1+F51)^(-Inputs!D27)))*(1+F30)+F25*F51 -> 1.0453153 | G54: =(G26*G51/(1-(1+G51)^(-Inputs!E24))+G27*G51/(1-(1+G51)^(-Inputs!E25))+G28*G51/(1-(1+G51)^(-Inputs!E26))+G29*G51/(1-(1+G51)^(-Inputs!E27)))*(1+G30)+G25*G51 -> 1.5018716 | H54: =(H26*H51/(1-(1+H51)^(-Inputs!F24))+H27*H51/(1-(1+H51)^(-Inputs!F25))+H28*H51/(1-(1+H51)^(-Inputs!F26))+H29*H51/(1-(1+H51)^(-Inputs!F27)))*(1+H30)+H25*H51 -> 2.3279224 | I54: =(I26*I51/(1-(1+I51)^(-Inputs!D24))+I27*I51/(1-(1+I51)^(-Inputs!D25))+I28*I51/(1-(1+I51)^(-Inputs!D26))+I29*I51/(1-(1+I51)^(-Inputs!D27)))*(1+I30)+I25*I51 -> 1.0453153 | J54: =(J26*J51/(1-(1+J51)^(-Inputs!E24))+J27*J51/(1-(1+J51)^(-Inputs!E25))+J28*J51/(1-(1+J51)^(-Inputs!E26))+J29*J51/(1-(1+J51)^(-Inputs!E27)))*(1+J30)+J25*J51 -> 1.5018716 | K54: =(K26*K51/(1-(1+K51)^(-Inputs!F24))+K27*K51/(1-(1+K51)^(-Inputs!F25))+K28*K51/(1-(1+K51)^(-Inputs!F26))+K29*K51/(1-(1+K51)^(-Inputs!F27)))*(1+K30)+K25*K51 -> 2.3279224 | L54: =(L26*L51/(1-(1+L51)^(-Inputs!D24))+L27*L51/(1-(1+L51)^(-Inputs!D25))+L28*L51/(1-(1+L51)^(-Inputs!D26))+L29*L51/(1-(1+L51)^(-Inputs!D27)))*(1+L30)+L25*L51 -> 1.0453153 | M54: =(M26*M51/(1-(1+M51)^(-Inputs!E24))+M27*M51/(1-(1+M51)^(-Inputs!E25))+M28*M51/(1-(1+M51)^(-Inputs!E26))+M29*M51/(1-(1+M51)^(-Inputs!E27)))*(1+M30)+M25*M51 -> 1.5018716 | N54: =(N26*N51/(1-(1+N51)^(-Inputs!F24))+N27*N51/(1-(1+N51)^(-Inputs!F25))+N28*N51/(1-(1+N51)^(-Inputs!F26))+N29*N51/(1-(1+N51)^(-Inputs!F27)))*(1+N30)+N25*N51 -> 2.3279224 | O54: =(O26*O51/(1-(1+O51)^(-Inputs!D24))+O27*O51/(1-(1+O51)^(-Inputs!D25))+O28*O51/(1-(1+O51)^(-Inputs!D26))+O29*O51/(1-(1+O51)^(-Inputs!D27)))*(1+O30)+O25*O51 -> 1.0453153 | P54: =(P26*P51/(1-(1+P51)^(-Inputs!E24))+P27*P51/(1-(1+P51)^(-Inputs!E25))+P28*P51/(1-(1+P51)^(-Inputs!E26))+P29*P51/(1-(1+P51)^(-Inputs!E27)))*(1+P30)+P25*P51 -> 1.5018716 | Q54: =(Q26*Q51/(1-(1+Q51)^(-Inputs!F24))+Q27*Q51/(1-(1+Q51)^(-Inputs!F25))+Q28*Q51/(1-(1+Q51)^(-Inputs!F26))+Q29*Q51/(1-(1+Q51)^(-Inputs!F27)))*(1+Q30)+Q25*Q51 -> 2.3279224
A55: 年持有成本 — 經濟口徑 | B55: $B | C55: =C53+C54+C48 -> 7.0000433 | D55: =D53+D54+D48 -> 10.095795 | E55: =E53+E54+E48 -> 17.405972 | F55: =F53+F54+F48 -> 6.8890039 | G55: =G53+G54+G48 -> 9.2685485 | H55: =H53+H54+H48 -> 15.083132 | I55: =I53+I54+I48 -> 8.6579664 | J55: =J53+J54+J48 -> 12.652968 | ... Q55: =Q53+Q54+Q48 -> 30.780121
A56: E. 單位成本與結構
A57: 每 GPU 小時持有成本 — 會計 | B57: $/GPU-hr | C57: =C49*1000000000/(C14*8760) -> 0.85832849 | D57: =D49*1000000000/(D14*8760) -> 1.1918455 | E57: =E49*1000000000/(E14*8760) -> 2.058675 | F57: =F49*1000000000/(F14*8760) -> 1.1900066 | G57: =G49*1000000000/(G14*8760) -> 1.538515 | H57: =H49*1000000000/(H14*8760) -> 2.4977877 | I57: =I49*1000000000/(I14*8760) -> 1.5850033 | J57: =J49*1000000000/(J14*8760) -> 2.230249 | ... Q57: =Q49*1000000000/(Q14*8760) -> 12.060748
A58: 每 GPU 小時持有成本 — 經濟 | B58: $/GPU-hr | C58: =C55*1000000000/(C14*8760) -> 1.1128667 | D58: =D55*1000000000/(D14*8760) -> 1.6050293 | E58: =E55*1000000000/(E14*8760) -> 2.767201 | F58: =F55*1000000000/(F14*8760) -> 1.5435902 | G58: =G55*1000000000/(G14*8760) -> 2.0767647 | H58: =H55*1000000000/(H14*8760) -> 3.379614 | I58: =I55*1000000000/(I14*8760) -> 2.0442466 | J58: =J55*1000000000/(J14*8760) -> 2.9875129 | ... Q58: =Q55*1000000000/(Q14*8760) -> 15.917013
A59: 每架小時持有成本 — 經濟 | B59: $/rack-hr | C59: =C55*1000000000/(C12*8760) -> 35.611734 | D59: =D55*1000000000/(D12*8760) -> 51.360936 | E59: =E55*1000000000/(E12*8760) -> 88.550431 | F59: =F55*1000000000/(F12*8760) -> 111.13849 | G59: =G55*1000000000/(G12*8760) -> 149.52706 | H59: =H55*1000000000/(H12*8760) -> 243.33221 | I59: =I55*1000000000/(I12*8760) -> 147.18575 | J59: =J55*1000000000/(J12*8760) -> 215.10093 | ... Q59: =Q55*1000000000/(Q12*8760) -> 2292.0499
A60: 年用電（設施端） | B60: TWh | C60: =C8*C41*C15*8760/1000000 -> 6.7452 | D60: =D8*D41*D15*8760/1000000 -> 8.4096 | E60: =E8*E41*E15*8760/1000000 -> 10.2492 | F60: =F8*F41*F15*8760/1000000 -> 6.7452 | G60: =G8*G41*G15*8760/1000000 -> 8.4096 | H60: =H8*H41*H15*8760/1000000 -> 10.2492 | I60: =I8*I41*I15*8760/1000000 -> 6.7452 | J60: =J8*J41*J15*8760/1000000 -> 8.4096 | ... Q60: =Q8*Q41*Q15*8760/1000000 -> 10.2492
A61: 資本回收占經濟口徑 | B61: % | C61: =(C53+C54)/C55 -> 0.81125914 | D61: =(D53+D54)/D55 -> 0.77442337 | E61: =(E53+E54)/E55 -> 0.79278068 | F61: =(F53+F54)/F55 -> 0.80976604 | G61: =(G53+G54)/G55 -> 0.76609559 | H61: =(H53+H54)/H55 -> 0.78010897 | I61: =(I53+I54)/I55 -> 0.8289976 | J61: =(J53+J54)/J55 -> 0.7932804 | ... Q61: =(Q53+Q54)/Q55 -> 0.82853293
A62: 電費占經濟口徑 | B62: % | C62: =C43/C55 -> 0.057815642 | D62: =D43/D55 -> 0.066638435 | E62: =E43/E55 -> 0.058883238 | F62: =F43/F55 -> 0.058747535 | G62: =G43/G55 -> 0.072586123 | H62: =H43/H55 -> 0.067951406 | I62: =I43/I55 -> 0.046744464 | J62: =J43/J55 -> 0.053170766 | ... Q62: =Q43/Q55 -> 0.033298115

Sheet Sensitivity
A1: Sensitivity — VR200 NVL72 單變數敏感度（其餘輸入取基準、功率取基準）
A2: 先看敏感度再看基準值：哪個輸入在合理範圍內移動，最能改變每 GW 資本支出與持有成本
A4: 情境 | C4: 基準 | D4: 機架價格－低 | E4: 機架價格－高 | F4: 配電設計功率－低 | G4: 配電設計功率－高 | H4: 網路 %－低 | I4: 網路 %－高 | J4: 廠房建物－低 | K4: 廠房建物－高 | L4: 廠房電力設施－低 | M4: 廠房電力設施－高 | N4: IT 折舊年限（7 年對 4 年）－低 | O4: IT 折舊年限（7 年對 4 年）－高 | P4: WACC－低 | Q4: WACC－高 | R4: 電價－低 | S4: 電價－高 | T4: PUE－低 | U4: PUE－高 | V4: 平均用電比－低 | W4: 平均用電比－高 | X4: 機架外 IT 占比（5% 對 12%）－低 | Y4: 機架外 IT 占比（5% 對 12%）－高
A6: A. 規模與電力
A7: IT 電力 | B7: MW | C7: =Inputs!$E$5*1000 -> 1000 | D7: =Inputs!$E$5*1000 -> 1000 | E7: =Inputs!$E$5*1000 -> 1000 | F7: =Inputs!$E$5*1000 -> 1000 | G7: =Inputs!$E$5*1000 -> 1000 | H7: =Inputs!$E$5*1000 -> 1000 | I7: =Inputs!$E$5*1000 -> 1000 | J7: =Inputs!$E$5*1000 -> 1000 | ... Y7: =Inputs!$E$5*1000 -> 1000
A8: 機架外 IT 電力占比 | B8: % | C8: =Inputs!$E$8 -> 0.08 | D8: =Inputs!$E$8 -> 0.08 | E8: =Inputs!$E$8 -> 0.08 | F8: =Inputs!$E$8 -> 0.08 | G8: =Inputs!$E$8 -> 0.08 | H8: =Inputs!$E$8 -> 0.08 | I8: =Inputs!$E$8 -> 0.08 | J8: =Inputs!$E$8 -> 0.08 | ... W8: =Inputs!$E$8 -> 0.08 | X8: =0.05 -> 0.05 | Y8: =0.12 -> 0.12
A9: 機架可用 IT 電力 | B9: MW | C9: =C7*(1-C8) -> 920 | D9: =D7*(1-D8) -> 920 | E9: =E7*(1-E8) -> 920 | F9: =F7*(1-F8) -> 920 | G9: =G7*(1-G8) -> 920 | H9: =H7*(1-H8) -> 920 | I9: =I7*(1-I8) -> 920 | J9: =J7*(1-J8) -> 920 | ... Y9: =Y7*(1-Y8) -> 880
A10: 每架配電設計功率 | B10: kW | C10: =Spec_Rack!F9 -> 227 | D10: =Spec_Rack!F9 -> 227 | E10: =Spec_Rack!F9 -> 227 | F10: =Spec_Rack!F8 -> 190 | G10: =Spec_Rack!F10 -> 230 | H10: =Spec_Rack!F9 -> 227 | I10: =Spec_Rack!F9 -> 227 | J10: =Spec_Rack!F9 -> 227 | K10: =Spec_Rack!F9 -> 227 | L10: =Spec_Rack!F9 -> 227 | M10: =Spec_Rack!F9 -> 227 | N10: =Spec_Rack!F9 -> 227 | O10: =Spec_Rack!F9 -> 227 | P10: =Spec_Rack!F9 -> 227 | Q10: =Spec_Rack!F9 -> 227 | R10: =Spec_Rack!F9 -> 227 | S10: =Spec_Rack!F9 -> 227 | T10: =Spec_Rack!F9 -> 227 | U10: =Spec_Rack!F9 -> 227 | V10: =Spec_Rack!F9 -> 227 | W10: =Spec_Rack!F9 -> 227 | X10: =Spec_Rack!F9 -> 227 | Y10: =Spec_Rack!F9 -> 227
A11: 每 GW 機架數 | B11: 架 | C11: =FLOOR(C9*1000/C10,1) -> 4052 | D11: =FLOOR(D9*1000/D10,1) -> 4052 | E11: =FLOOR(E9*1000/E10,1) -> 4052 | F11: =FLOOR(F9*1000/F10,1) -> 4842 | G11: =FLOOR(G9*1000/G10,1) -> 4000 | H11: =FLOOR(H9*1000/H10,1) -> 4052 | I11: =FLOOR(I9*1000/I10,1) -> 4052 | J11: =FLOOR(J9*1000/J10,1) -> 4052 | ... Y11: =FLOOR(Y9*1000/Y10,1) -> 3876
A12: GPU 封裝／架 | B12: 顆 | C12: =Spec_Rack!F6 -> 72 | D12: =Spec_Rack!F6 -> 72 | E12: =Spec_Rack!F6 -> 72 | F12: =Spec_Rack!F6 -> 72 | G12: =Spec_Rack!F6 -> 72 | H12: =Spec_Rack!F6 -> 72 | I12: =Spec_Rack!F6 -> 72 | J12: =Spec_Rack!F6 -> 72 | K12: =Spec_Rack!F6 -> 72 | L12: =Spec_Rack!F6 -> 72 | M12: =Spec_Rack!F6 -> 72 | N12: =Spec_Rack!F6 -> 72 | O12: =Spec_Rack!F6 -> 72 | P12: =Spec_Rack!F6 -> 72 | Q12: =Spec_Rack!F6 -> 72 | R12: =Spec_Rack!F6 -> 72 | S12: =Spec_Rack!F6 -> 72 | T12: =Spec_Rack!F6 -> 72 | U12: =Spec_Rack!F6 -> 72 | V12: =Spec_Rack!F6 -> 72 | W12: =Spec_Rack!F6 -> 72 | X12: =Spec_Rack!F6 -> 72 | Y12: =Spec_Rack!F6 -> 72
A13: 每 GW GPU 數 | B13: 顆 | C13: =C11*C12 -> 291744 | D13: =D11*D12 -> 291744 | E13: =E11*E12 -> 291744 | F13: =F11*F12 -> 348624 | G13: =G11*G12 -> 288000 | H13: =H11*H12 -> 291744 | I13: =I11*I12 -> 291744 | J13: =J11*J12 -> 291744 | ... Y13: =Y11*Y12 -> 279072
A14: PUE | B14: x | C14: =Inputs!$E$9 -> 1.2 | D14: =Inputs!$E$9 -> 1.2 | E14: =Inputs!$E$9 -> 1.2 | F14: =Inputs!$E$9 -> 1.2 | G14: =Inputs!$E$9 -> 1.2 | H14: =Inputs!$E$9 -> 1.2 | I14: =Inputs!$E$9 -> 1.2 | J14: =Inputs!$E$9 -> 1.2 | ... S14: =Inputs!$E$9 -> 1.2 | T14: =Inputs!$D$9 -> 1.1 | U14: =Inputs!$F$9 -> 1.3 | V14: =Inputs!$E$9 -> 1.2 | W14: =Inputs!$E$9 -> 1.2 | X14: =Inputs!$E$9 -> 1.2 | Y14: =Inputs!$E$9 -> 1.2
A15: 設施電力（IT × PUE） | B15: MW | C15: =C7*C14 -> 1200 | D15: =D7*D14 -> 1200 | E15: =E7*E14 -> 1200 | F15: =F7*F14 -> 1200 | G15: =G7*G14 -> 1200 | H15: =H7*H14 -> 1200 | I15: =I7*I14 -> 1200 | J15: =J7*J14 -> 1200 | ... Y15: =Y7*Y14 -> 1200
A16: B. 資本支出（$B／GW）
A17: 機架單價 | B17: $M | C17: =Spec_Rack!F12 -> 7.8 | D17: =Spec_Rack!F11 -> 6.7 | E17: =Spec_Rack!F13 -> 9.1 | F17: =Spec_Rack!F12 -> 7.8 | G17: =Spec_Rack!F12 -> 7.8 | H17: =Spec_Rack!F12 -> 7.8 | I17: =Spec_Rack!F12 -> 7.8 | J17: =Spec_Rack!F12 -> 7.8 | K17: =Spec_Rack!F12 -> 7.8 | L17: =Spec_Rack!F12 -> 7.8 | M17: =Spec_Rack!F12 -> 7.8 | N17: =Spec_Rack!F12 -> 7.8 | O17: =Spec_Rack!F12 -> 7.8 | P17: =Spec_Rack!F12 -> 7.8 | Q17: =Spec_Rack!F12 -> 7.8 | R17: =Spec_Rack!F12 -> 7.8 | S17: =Spec_Rack!F12 -> 7.8 | T17: =Spec_Rack!F12 -> 7.8 | U17: =Spec_Rack!F12 -> 7.8 | V17: =Spec_Rack!F12 -> 7.8 | W17: =Spec_Rack!F12 -> 7.8 | X17: =Spec_Rack!F12 -> 7.8 | Y17: =Spec_Rack!F12 -> 7.8
A18: 機架 | B18: $B | C18: =C11*C17/1000 -> 31.6056 | D18: =D11*D17/1000 -> 27.1484 | E18: =E11*E17/1000 -> 36.8732 | F18: =F11*F17/1000 -> 37.7676 | G18: =G11*G17/1000 -> 31.2 | H18: =H11*H17/1000 -> 31.6056 | I18: =I11*I17/1000 -> 31.6056 | J18: =J11*J17/1000 -> 31.6056 | ... Y18: =Y11*Y17/1000 -> 30.2328
A19: Scale-out 網路 ÷ 機架價格 | B19: % | C19: =Inputs!$E$13 -> 0.1 | D19: =Inputs!$E$13 -> 0.1 | E19: =Inputs!$E$13 -> 0.1 | F19: =Inputs!$E$13 -> 0.1 | G19: =Inputs!$E$13 -> 0.1 | H19: =Inputs!$D$13 -> 0.05 | I19: =Inputs!$F$13 -> 0.15 | J19: =Inputs!$E$13 -> 0.1 | K19: =Inputs!$E$13 -> 0.1 | L19: =Inputs!$E$13 -> 0.1 | M19: =Inputs!$E$13 -> 0.1 | N19: =Inputs!$E$13 -> 0.1 | O19: =Inputs!$E$13 -> 0.1 | P19: =Inputs!$E$13 -> 0.1 | Q19: =Inputs!$E$13 -> 0.1 | ... Y19: =Inputs!$E$13 -> 0.1
A20: Scale-out 網路 | B20: $B | C20: =C18*C19 -> 3.16056 | D20: =D18*D19 -> 2.71484 | E20: =E18*E19 -> 3.68732 | F20: =F18*F19 -> 3.77676 | G20: =G18*G19 -> 3.12 | H20: =H18*H19 -> 1.58028 | I20: =I18*I19 -> 4.74084 | J20: =J18*J19 -> 3.16056 | ... Y20: =Y18*Y19 -> 3.02328
A21: 儲存與管理 | B21: $/GPU | C21: =Inputs!$E$14 -> 500 | D21: =Inputs!$E$14 -> 500 | E21: =Inputs!$E$14 -> 500 | F21: =Inputs!$E$14 -> 500 | G21: =Inputs!$E$14 -> 500 | H21: =Inputs!$E$14 -> 500 | I21: =Inputs!$E$14 -> 500 | J21: =Inputs!$E$14 -> 500 | ... Y21: =Inputs!$E$14 -> 500
A22: 儲存與管理 | B22: $B | C22: =C13*C21/1000000000 -> 0.145872 | D22: =D13*D21/1000000000 -> 0.145872 | E22: =E13*E21/1000000000 -> 0.145872 | F22: =F13*F21/1000000000 -> 0.174312 | G22: =G13*G21/1000000000 -> 0.144 | H22: =H13*H21/1000000000 -> 0.145872 | I22: =I13*I21/1000000000 -> 0.145872 | J22: =J13*J21/1000000000 -> 0.145872 | ... Y22: =Y13*Y21/1000000000 -> 0.139536
A23: IT 設備小計 | B23: $B | C23: =C18+C20+C22 -> 34.912032 | D23: =D18+D20+D22 -> 30.009112 | E23: =E18+E20+E22 -> 40.706392 | F23: =F18+F20+F22 -> 41.718672 | G23: =G18+G20+G22 -> 34.464 | H23: =H18+H20+H22 -> 33.331752 | I23: =I18+I20+I22 -> 36.492312 | J23: =J18+J20+J22 -> 34.912032 | ... Y23: =Y18+Y20+Y22 -> 33.395616
A24: 土地 | B24: $B | C24: =C7*Inputs!$E$16/1000 -> 0.02 | D24: =D7*Inputs!$E$16/1000 -> 0.02 | E24: =E7*Inputs!$E$16/1000 -> 0.02 | F24: =F7*Inputs!$E$16/1000 -> 0.02 | G24: =G7*Inputs!$E$16/1000 -> 0.02 | H24: =H7*Inputs!$E$16/1000 -> 0.02 | I24: =I7*Inputs!$E$16/1000 -> 0.02 | J24: =J7*Inputs!$E$16/1000 -> 0.02 | ... Y24: =Y7*Inputs!$E$16/1000 -> 0.02
A25: 建物與基地 | B25: $B | C25: =C7*Inputs!$E$17/1000 -> 3.6 | D25: =D7*Inputs!$E$17/1000 -> 3.6 | E25: =E7*Inputs!$E$17/1000 -> 3.6 | F25: =F7*Inputs!$E$17/1000 -> 3.6 | G25: =G7*Inputs!$E$17/1000 -> 3.6 | H25: =H7*Inputs!$E$17/1000 -> 3.6 | I25: =I7*Inputs!$E$17/1000 -> 3.6 | J25: =J7*Inputs!$D$17/1000 -> 3 | K25: =K7*Inputs!$F$17/1000 -> 4.5 | L25: =L7*Inputs!$E$17/1000 -> 3.6 | M25: =M7*Inputs!$E$17/1000 -> 3.6 | N25: =N7*Inputs!$E$17/1000 -> 3.6 | O25: =O7*Inputs!$E$17/1000 -> 3.6 | P25: =P7*Inputs!$E$17/1000 -> 3.6 | Q25: =Q7*Inputs!$E$17/1000 -> 3.6 | R25: =R7*Inputs!$E$17/1000 -> 3.6 | S25: =S7*Inputs!$E$17/1000 -> 3.6 | ... Y25: =Y7*Inputs!$E$17/1000 -> 3.6
A26: 電力設施 | B26: $B | C26: =C7*Inputs!$E$18/1000 -> 4.5 | D26: =D7*Inputs!$E$18/1000 -> 4.5 | E26: =E7*Inputs!$E$18/1000 -> 4.5 | F26: =F7*Inputs!$E$18/1000 -> 4.5 | G26: =G7*Inputs!$E$18/1000 -> 4.5 | H26: =H7*Inputs!$E$18/1000 -> 4.5 | I26: =I7*Inputs!$E$18/1000 -> 4.5 | J26: =J7*Inputs!$E$18/1000 -> 4.5 | K26: =K7*Inputs!$E$18/1000 -> 4.5 | L26: =L7*Inputs!$D$18/1000 -> 3.8 | M26: =M7*Inputs!$F$18/1000 -> 5.5 | N26: =N7*Inputs!$E$18/1000 -> 4.5 | O26: =O7*Inputs!$E$18/1000 -> 4.5 | P26: =P7*Inputs!$E$18/1000 -> 4.5 | Q26: =Q7*Inputs!$E$18/1000 -> 4.5 | R26: =R7*Inputs!$E$18/1000 -> 4.5 | S26: =S7*Inputs!$E$18/1000 -> 4.5 | T26: =T7*Inputs!$E$18/1000 -> 4.5 | U26: =U7*Inputs!$E$18/1000 -> 4.5 | ... Y26: =Y7*Inputs!$E$18/1000 -> 4.5
A27: 機械與散熱 | B27: $B | C27: =C7*Inputs!$E$19/1000 -> 2.5 | D27: =D7*Inputs!$E$19/1000 -> 2.5 | E27: =E7*Inputs!$E$19/1000 -> 2.5 | F27: =F7*Inputs!$E$19/1000 -> 2.5 | G27: =G7*Inputs!$E$19/1000 -> 2.5 | H27: =H7*Inputs!$E$19/1000 -> 2.5 | I27: =I7*Inputs!$E$19/1000 -> 2.5 | J27: =J7*Inputs!$E$19/1000 -> 2.5 | ... Y27: =Y7*Inputs!$E$19/1000 -> 2.5
A28: 光纖與保全 | B28: $B | C28: =C7*Inputs!$E$20/1000 -> 0.4 | D28: =D7*Inputs!$E$20/1000 -> 0.4 | E28: =E7*Inputs!$E$20/1000 -> 0.4 | F28: =F7*Inputs!$E$20/1000 -> 0.4 | G28: =G7*Inputs!$E$20/1000 -> 0.4 | H28: =H7*Inputs!$E$20/1000 -> 0.4 | I28: =I7*Inputs!$E$20/1000 -> 0.4 | J28: =J7*Inputs!$E$20/1000 -> 0.4 | ... Y28: =Y7*Inputs!$E$20/1000 -> 0.4
A29: 設計、管理與預備費率 | B29: % | C29: =Inputs!$E$21 -> 0.15 | D29: =Inputs!$E$21 -> 0.15 | E29: =Inputs!$E$21 -> 0.15 | F29: =Inputs!$E$21 -> 0.15 | G29: =Inputs!$E$21 -> 0.15 | H29: =Inputs!$E$21 -> 0.15 | I29: =Inputs!$E$21 -> 0.15 | J29: =Inputs!$E$21 -> 0.15 | ... Y29: =Inputs!$E$21 -> 0.15
A30: 設計、管理與預備費 | B30: $B | C30: =(C25+C26+C27+C28)*C29 -> 1.65 | D30: =(D25+D26+D27+D28)*D29 -> 1.65 | E30: =(E25+E26+E27+E28)*E29 -> 1.65 | F30: =(F25+F26+F27+F28)*F29 -> 1.65 | G30: =(G25+G26+G27+G28)*G29 -> 1.65 | H30: =(H25+H26+H27+H28)*H29 -> 1.65 | I30: =(I25+I26+I27+I28)*I29 -> 1.65 | J30: =(J25+J26+J27+J28)*J29 -> 1.56 | ... Y30: =(Y25+Y26+Y27+Y28)*Y29 -> 1.65
A31: 廠房小計 | B31: $B | C31: =C24+C25+C26+C27+C28+C30 -> 12.67 | D31: =D24+D25+D26+D27+D28+D30 -> 12.67 | E31: =E24+E25+E26+E27+E28+E30 -> 12.67 | F31: =F24+F25+F26+F27+F28+F30 -> 12.67 | G31: =G24+G25+G26+G27+G28+G30 -> 12.67 | H31: =H24+H25+H26+H27+H28+H30 -> 12.67 | I31: =I24+I25+I26+I27+I28+I30 -> 12.67 | J31: =J24+J25+J26+J27+J28+J30 -> 11.98 | ... Y31: =Y24+Y25+Y26+Y27+Y28+Y30 -> 12.67
A32: 每 GW 總資本支出 | B32: $B | C32: =C23+C31 -> 47.582032 | D32: =D23+D31 -> 42.679112 | E32: =E23+E31 -> 53.376392 | F32: =F23+F31 -> 54.388672 | G32: =G23+G31 -> 47.134 | H32: =H23+H31 -> 46.001752 | I32: =I23+I31 -> 49.162312 | J32: =J23+J31 -> 46.892032 | ... Y32: =Y23+Y31 -> 46.065616
A33: 每 GPU 資本支出（含廠房） | B33: $K | C33: =C32*1000000/C13 -> 163.09515 | D33: =D32*1000000/D13 -> 146.2896 | E33: =E32*1000000/E13 -> 182.95626 | F33: =F32*1000000/F13 -> 156.00955 | G33: =G32*1000000/G13 -> 163.65972 | H33: =H32*1000000/H13 -> 157.67849 | I33: =I32*1000000/I13 -> 168.51182 | J33: =J32*1000000/J13 -> 160.73006 | ... Y33: =Y32*1000000/Y13 -> 165.06714
A34: 每 MW IT 資本支出 | B34: $M | C34: =C32*1000/C7 -> 47.582032 | D34: =D32*1000/D7 -> 42.679112 | E34: =E32*1000/E7 -> 53.376392 | F34: =F32*1000/F7 -> 54.388672 | G34: =G32*1000/G7 -> 47.134 | H34: =H32*1000/H7 -> 46.001752 | I34: =I32*1000/I7 -> 49.162312 | J34: =J32*1000/J7 -> 46.892032 | ... Y34: =Y32*1000/Y7 -> 46.065616
A35: 每 MW IT 廠房資本支出 | B35: $M | C35: =C31*1000/C7 -> 12.67 | D35: =D31*1000/D7 -> 12.67 | E35: =E31*1000/E7 -> 12.67 | F35: =F31*1000/F7 -> 12.67 | G35: =G31*1000/G7 -> 12.67 | H35: =H31*1000/H7 -> 12.67 | I35: =I31*1000/I7 -> 12.67 | J35: =J31*1000/J7 -> 11.98 | ... Y35: =Y31*1000/Y7 -> 12.67
A36: C. 年持有成本 — 會計口徑（$B／GW／年）
A37: IT 折舊年限 | B37: 年 | C37: =Inputs!$E$23 -> 6 | D37: =Inputs!$E$23 -> 6 | E37: =Inputs!$E$23 -> 6 | F37: =Inputs!$E$23 -> 6 | G37: =Inputs!$E$23 -> 6 | H37: =Inputs!$E$23 -> 6 | I37: =Inputs!$E$23 -> 6 | J37: =Inputs!$E$23 -> 6 | ... M37: =Inputs!$E$23 -> 6 | N37: =7 -> 7 | O37: =Inputs!$F$23 -> 4 | P37: =Inputs!$E$23 -> 6 | Q37: =Inputs!$E$23 -> 6 | R37: =Inputs!$E$23 -> 6 | S37: =Inputs!$E$23 -> 6 | T37: =Inputs!$E$23 -> 6 | U37: =Inputs!$E$23 -> 6 | V37: =Inputs!$E$23 -> 6 | W37: =Inputs!$E$23 -> 6 | ... Y37: =Inputs!$E$23 -> 6
A38: IT 折舊 | B38: $B | C38: =C23/C37 -> 5.818672 | D38: =D23/D37 -> 5.0015187 | E38: =E23/E37 -> 6.7843987 | F38: =F23/F37 -> 6.953112 | G38: =G23/G37 -> 5.744 | H38: =H23/H37 -> 5.555292 | I38: =I23/I37 -> 6.082052 | J38: =J23/J37 -> 5.818672 | ... Y38: =Y23/Y37 -> 5.565936
A39: 廠房折舊（土地不折舊） | B39: $B | C39: =(C25/Inputs!$E$24+C26/Inputs!$E$25+C27/Inputs!$E$26+C28/Inputs!$E$27)*(1+C29) -> 0.63441667 | D39: =(D25/Inputs!$E$24+D26/Inputs!$E$25+D27/Inputs!$E$26+D28/Inputs!$E$27)*(1+D29) -> 0.63441667 | E39: =(E25/Inputs!$E$24+E26/Inputs!$E$25+E27/Inputs!$E$26+E28/Inputs!$E$27)*(1+E29) -> 0.63441667 | F39: =(F25/Inputs!$E$24+F26/Inputs!$E$25+F27/Inputs!$E$26+F28/Inputs!$E$27)*(1+F29) -> 0.63441667 | G39: =(G25/Inputs!$E$24+G26/Inputs!$E$25+G27/Inputs!$E$26+G28/Inputs!$E$27)*(1+G29) -> 0.63441667 | H39: =(H25/Inputs!$E$24+H26/Inputs!$E$25+H27/Inputs!$E$26+H28/Inputs!$E$27)*(1+H29) -> 0.63441667 | I39: =(I25/Inputs!$E$24+I26/Inputs!$E$25+I27/Inputs!$E$26+I28/Inputs!$E$27)*(1+I29) -> 0.63441667 | J39: =(J25/Inputs!$E$24+J26/Inputs!$E$25+J27/Inputs!$E$26+J28/Inputs!$E$27)*(1+J29) -> 0.61141667 | ... Y39: =(Y25/Inputs!$E$24+Y26/Inputs!$E$25+Y27/Inputs!$E$26+Y28/Inputs!$E$27)*(1+Y29) -> 0.63441667
A40: 平均用電 ÷ 配電設計功率 | B40: % | C40: =Inputs!$E$10 -> 0.8 | D40: =Inputs!$E$10 -> 0.8 | E40: =Inputs!$E$10 -> 0.8 | F40: =Inputs!$E$10 -> 0.8 | G40: =Inputs!$E$10 -> 0.8 | H40: =Inputs!$E$10 -> 0.8 | I40: =Inputs!$E$10 -> 0.8 | J40: =Inputs!$E$10 -> 0.8 | ... U40: =Inputs!$E$10 -> 0.8 | V40: =Inputs!$D$10 -> 0.7 | W40: =Inputs!$F$10 -> 0.9 | X40: =Inputs!$E$10 -> 0.8 | Y40: =Inputs!$E$10 -> 0.8
A41: 電價 | B41: $/kWh | C41: =Inputs!$E$11 -> 0.08 | D41: =Inputs!$E$11 -> 0.08 | E41: =Inputs!$E$11 -> 0.08 | F41: =Inputs!$E$11 -> 0.08 | G41: =Inputs!$E$11 -> 0.08 | H41: =Inputs!$E$11 -> 0.08 | I41: =Inputs!$E$11 -> 0.08 | J41: =Inputs!$E$11 -> 0.08 | ... Q41: =Inputs!$E$11 -> 0.08 | R41: =Inputs!$D$11 -> 0.06 | S41: =Inputs!$F$11 -> 0.1 | T41: =Inputs!$E$11 -> 0.08 | U41: =Inputs!$E$11 -> 0.08 | V41: =Inputs!$E$11 -> 0.08 | W41: =Inputs!$E$11 -> 0.08 | X41: =Inputs!$E$11 -> 0.08 | Y41: =Inputs!$E$11 -> 0.08
A42: 電費 | B42: $B | C42: =C7*1000*C40*C14*8760*C41/1000000000 -> 0.672768 | D42: =D7*1000*D40*D14*8760*D41/1000000000 -> 0.672768 | E42: =E7*1000*E40*E14*8760*E41/1000000000 -> 0.672768 | F42: =F7*1000*F40*F14*8760*F41/1000000000 -> 0.672768 | G42: =G7*1000*G40*G14*8760*G41/1000000000 -> 0.672768 | H42: =H7*1000*H40*H14*8760*H41/1000000000 -> 0.672768 | I42: =I7*1000*I40*I14*8760*I41/1000000000 -> 0.672768 | J42: =J7*1000*J40*J14*8760*J41/1000000000 -> 0.672768 | ... Y42: =Y7*1000*Y40*Y14*8760*Y41/1000000000 -> 0.672768
A43: IT 維護 | B43: $B | C43: =C23*Inputs!$E$30 -> 1.047361 | D43: =D23*Inputs!$E$30 -> 0.90027336 | E43: =E23*Inputs!$E$30 -> 1.2211918 | F43: =F23*Inputs!$E$30 -> 1.2515602 | G43: =G23*Inputs!$E$30 -> 1.03392 | H43: =H23*Inputs!$E$30 -> 0.99995256 | I43: =I23*Inputs!$E$30 -> 1.0947694 | J43: =J23*Inputs!$E$30 -> 1.047361 | ... Y43: =Y23*Inputs!$E$30 -> 1.0018685
A44: 廠房維護 | B44: $B | C44: =C31*Inputs!$E$31 -> 0.2534 | D44: =D31*Inputs!$E$31 -> 0.2534 | E44: =E31*Inputs!$E$31 -> 0.2534 | F44: =F31*Inputs!$E$31 -> 0.2534 | G44: =G31*Inputs!$E$31 -> 0.2534 | H44: =H31*Inputs!$E$31 -> 0.2534 | I44: =I31*Inputs!$E$31 -> 0.2534 | J44: =J31*Inputs!$E$31 -> 0.2396 | ... Y44: =Y31*Inputs!$E$31 -> 0.2534
A45: 人員、軟體、水與耗材 | B45: $B | C45: =(Inputs!$E$32*C7/1000+Inputs!$E$33*C7/1000+Inputs!$E$34*C7)/1000 -> 0.325 | D45: =(Inputs!$E$32*D7/1000+Inputs!$E$33*D7/1000+Inputs!$E$34*D7)/1000 -> 0.325 | E45: =(Inputs!$E$32*E7/1000+Inputs!$E$33*E7/1000+Inputs!$E$34*E7)/1000 -> 0.325 | F45: =(Inputs!$E$32*F7/1000+Inputs!$E$33*F7/1000+Inputs!$E$34*F7)/1000 -> 0.325 | G45: =(Inputs!$E$32*G7/1000+Inputs!$E$33*G7/1000+Inputs!$E$34*G7)/1000 -> 0.325 | H45: =(Inputs!$E$32*H7/1000+Inputs!$E$33*H7/1000+Inputs!$E$34*H7)/1000 -> 0.325 | I45: =(Inputs!$E$32*I7/1000+Inputs!$E$33*I7/1000+Inputs!$E$34*I7)/1000 -> 0.325 | J45: =(Inputs!$E$32*J7/1000+Inputs!$E$33*J7/1000+Inputs!$E$34*J7)/1000 -> 0.325 | ... Y45: =(Inputs!$E$32*Y7/1000+Inputs!$E$33*Y7/1000+Inputs!$E$34*Y7)/1000 -> 0.325
A46: 財產稅與保險 | B46: $B | C46: =C32*Inputs!$E$35 -> 0.23791016 | D46: =D32*Inputs!$E$35 -> 0.21339556 | E46: =E32*Inputs!$E$35 -> 0.26688196 | F46: =F32*Inputs!$E$35 -> 0.27194336 | G46: =G32*Inputs!$E$35 -> 0.23567 | H46: =H32*Inputs!$E$35 -> 0.23000876 | I46: =I32*Inputs!$E$35 -> 0.24581156 | J46: =J32*Inputs!$E$35 -> 0.23446016 | ... Y46: =Y32*Inputs!$E$35 -> 0.23032808
A47: 營運費用小計（不含折舊） | B47: $B | C47: =C42+C43+C44+C45+C46 -> 2.5364391 | D47: =D42+D43+D44+D45+D46 -> 2.3648369 | E47: =E42+E43+E44+E45+E46 -> 2.7392417 | F47: =F42+F43+F44+F45+F46 -> 2.7746715 | G47: =G42+G43+G44+G45+G46 -> 2.520758 | H47: =H42+H43+H44+H45+H46 -> 2.4811293 | I47: =I42+I43+I44+I45+I46 -> 2.5917489 | J47: =J42+J43+J44+J45+J46 -> 2.5191891 | ... Y47: =Y42+Y43+Y44+Y45+Y46 -> 2.4833646
A48: 年持有成本 — 會計口徑 | B48: $B | C48: =C38+C39+C47 -> 8.9895278 | D48: =D38+D39+D47 -> 8.0007723 | E48: =E38+E39+E47 -> 10.158057 | F48: =F38+F39+F47 -> 10.3622 | G48: =G38+G39+G47 -> 8.8991747 | H48: =H38+H39+H47 -> 8.670838 | I48: =I38+I39+I47 -> 9.3082176 | J48: =J38+J39+J47 -> 8.9492778 | ... Y48: =Y38+Y39+Y47 -> 8.6837172
A49: D. 年持有成本 — 經濟口徑（資本回收年金）
A50: WACC | B50: % | C50: =Inputs!$E$28 -> 0.1 | D50: =Inputs!$E$28 -> 0.1 | E50: =Inputs!$E$28 -> 0.1 | F50: =Inputs!$E$28 -> 0.1 | G50: =Inputs!$E$28 -> 0.1 | H50: =Inputs!$E$28 -> 0.1 | I50: =Inputs!$E$28 -> 0.1 | J50: =Inputs!$E$28 -> 0.1 | ... O50: =Inputs!$E$28 -> 0.1 | P50: =Inputs!$D$28 -> 0.08 | Q50: =Inputs!$F$28 -> 0.13 | R50: =Inputs!$E$28 -> 0.1 | S50: =Inputs!$E$28 -> 0.1 | T50: =Inputs!$E$28 -> 0.1 | U50: =Inputs!$E$28 -> 0.1 | V50: =Inputs!$E$28 -> 0.1 | W50: =Inputs!$E$28 -> 0.1 | X50: =Inputs!$E$28 -> 0.1 | Y50: =Inputs!$E$28 -> 0.1
A51: IT 資本回收係數 | B51: x | C51: =C50/(1-(1+C50)^(-C37)) -> 0.22960738 | D51: =D50/(1-(1+D50)^(-D37)) -> 0.22960738 | E51: =E50/(1-(1+E50)^(-E37)) -> 0.22960738 | F51: =F50/(1-(1+F50)^(-F37)) -> 0.22960738 | G51: =G50/(1-(1+G50)^(-G37)) -> 0.22960738 | H51: =H50/(1-(1+H50)^(-H37)) -> 0.22960738 | I51: =I50/(1-(1+I50)^(-I37)) -> 0.22960738 | J51: =J50/(1-(1+J50)^(-J37)) -> 0.22960738 | ... Y51: =Y50/(1-(1+Y50)^(-Y37)) -> 0.22960738
A52: IT 資本回收 | B52: $B | C52: =C23*C51 -> 8.0160602 | D52: =D23*D51 -> 6.8903136 | E52: =E23*E51 -> 9.346488 | F52: =F23*F51 -> 9.578915 | G52: =G23*G51 -> 7.9131888 | H52: =H23*H51 -> 7.6532163 | I52: =I23*I51 -> 8.3789042 | J52: =J23*J51 -> 8.0160602 | ... Y52: =Y23*Y51 -> 7.6678799
A53: 廠房資本回收（土地按 WACC 計機會成本） | B53: $B | C53: =(C25*C50/(1-(1+C50)^(-Inputs!$E$24))+C26*C50/(1-(1+C50)^(-Inputs!$E$25))+C27*C50/(1-(1+C50)^(-Inputs!$E$26))+C28*C50/(1-(1+C50)^(-Inputs!$E$27)))*(1+C29)+C24*C50 -> 1.5018716 | D53: =(D25*D50/(1-(1+D50)^(-Inputs!$E$24))+D26*D50/(1-(1+D50)^(-Inputs!$E$25))+D27*D50/(1-(1+D50)^(-Inputs!$E$26))+D28*D50/(1-(1+D50)^(-Inputs!$E$27)))*(1+D29)+D24*D50 -> 1.5018716 | E53: =(E25*E50/(1-(1+E50)^(-Inputs!$E$24))+E26*E50/(1-(1+E50)^(-Inputs!$E$25))+E27*E50/(1-(1+E50)^(-Inputs!$E$26))+E28*E50/(1-(1+E50)^(-Inputs!$E$27)))*(1+E29)+E24*E50 -> 1.5018716 | F53: =(F25*F50/(1-(1+F50)^(-Inputs!$E$24))+F26*F50/(1-(1+F50)^(-Inputs!$E$25))+F27*F50/(1-(1+F50)^(-Inputs!$E$26))+F28*F50/(1-(1+F50)^(-Inputs!$E$27)))*(1+F29)+F24*F50 -> 1.5018716 | G53: =(G25*G50/(1-(1+G50)^(-Inputs!$E$24))+G26*G50/(1-(1+G50)^(-Inputs!$E$25))+G27*G50/(1-(1+G50)^(-Inputs!$E$26))+G28*G50/(1-(1+G50)^(-Inputs!$E$27)))*(1+G29)+G24*G50 -> 1.5018716 | H53: =(H25*H50/(1-(1+H50)^(-Inputs!$E$24))+H26*H50/(1-(1+H50)^(-Inputs!$E$25))+H27*H50/(1-(1+H50)^(-Inputs!$E$26))+H28*H50/(1-(1+H50)^(-Inputs!$E$27)))*(1+H29)+H24*H50 -> 1.5018716 | I53: =(I25*I50/(1-(1+I50)^(-Inputs!$E$24))+I26*I50/(1-(1+I50)^(-Inputs!$E$25))+I27*I50/(1-(1+I50)^(-Inputs!$E$26))+I28*I50/(1-(1+I50)^(-Inputs!$E$27)))*(1+I29)+I24*I50 -> 1.5018716 | J53: =(J25*J50/(1-(1+J50)^(-Inputs!$E$24))+J26*J50/(1-(1+J50)^(-Inputs!$E$25))+J27*J50/(1-(1+J50)^(-Inputs!$E$26))+J28*J50/(1-(1+J50)^(-Inputs!$E$27)))*(1+J29)+J24*J50 -> 1.428677 | ... Y53: =(Y25*Y50/(1-(1+Y50)^(-Inputs!$E$24))+Y26*Y50/(1-(1+Y50)^(-Inputs!$E$25))+Y27*Y50/(1-(1+Y50)^(-Inputs!$E$26))+Y28*Y50/(1-(1+Y50)^(-Inputs!$E$27)))*(1+Y29)+Y24*Y50 -> 1.5018716
A54: 年持有成本 — 經濟口徑 | B54: $B | C54: =C52+C53+C47 -> 12.054371 | D54: =D52+D53+D47 -> 10.757022 | E54: =E52+E53+E47 -> 13.587601 | F54: =F52+F53+F47 -> 13.855458 | G54: =G52+G53+G47 -> 11.935818 | H54: =H52+H53+H47 -> 11.636217 | I54: =I52+I53+I47 -> 12.472525 | J54: =J52+J53+J47 -> 11.963926 | ... Y54: =Y52+Y53+Y47 -> 11.653116
A55: E. 單位成本與結構
A56: 每 GPU 小時持有成本 — 會計 | B56: $/GPU-hr | C56: =C48*1000000000/(C13*8760) -> 3.5174735 | D56: =D48*1000000000/(D13*8760) -> 3.1305877 | E56: =E48*1000000000/(E13*8760) -> 3.9747023 | F56: =F48*1000000000/(F13*8760) -> 3.3930526 | G56: =G48*1000000000/(G13*8760) -> 3.5273872 | H56: =H48*1000000000/(H13*8760) -> 3.3927748 | I56: =I48*1000000000/(I13*8760) -> 3.6421723 | J56: =J48*1000000000/(J13*8760) -> 3.5017243 | ... Y56: =Y48*1000000000/(Y13*8760) -> 3.552101
A57: 每 GPU 小時持有成本 — 經濟 | B57: $/GPU-hr | C57: =C54*1000000000/(C13*8760) -> 4.7167028 | D57: =D54*1000000000/(D13*8760) -> 4.2090688 | E57: =E54*1000000000/(E13*8760) -> 5.3166339 | F57: =F54*1000000000/(F13*8760) -> 4.5369031 | G57: =G54*1000000000/(G13*8760) -> 4.731029 | H57: =H54*1000000000/(H13*8760) -> 4.5530852 | I57: =I54*1000000000/(I13*8760) -> 4.8803204 | J57: =J54*1000000000/(J13*8760) -> 4.6813131 | ... Y57: =Y54*1000000000/(Y13*8760) -> 4.7667426
A58: 每架小時持有成本 — 經濟 | B58: $/rack-hr | C58: =C54*1000000000/(C11*8760) -> 339.6026 | D58: =D54*1000000000/(D11*8760) -> 303.05295 | E58: =E54*1000000000/(E11*8760) -> 382.79764 | F58: =F54*1000000000/(F11*8760) -> 326.65702 | G58: =G54*1000000000/(G11*8760) -> 340.63409 | H58: =H54*1000000000/(H11*8760) -> 327.82214 | I58: =I54*1000000000/(I11*8760) -> 351.38307 | J58: =J54*1000000000/(J11*8760) -> 337.05454 | ... Y58: =Y54*1000000000/(Y11*8760) -> 343.20547
A59: 年用電（設施端） | B59: TWh | C59: =C7*C40*C14*8760/1000000 -> 8.4096 | D59: =D7*D40*D14*8760/1000000 -> 8.4096 | E59: =E7*E40*E14*8760/1000000 -> 8.4096 | F59: =F7*F40*F14*8760/1000000 -> 8.4096 | G59: =G7*G40*G14*8760/1000000 -> 8.4096 | H59: =H7*H40*H14*8760/1000000 -> 8.4096 | I59: =I7*I40*I14*8760/1000000 -> 8.4096 | J59: =J7*J40*J14*8760/1000000 -> 8.4096 | ... Y59: =Y7*Y40*Y14*8760/1000000 -> 8.4096
A60: 資本回收占經濟口徑 | B60: % | C60: =(C52+C53)/C54 -> 0.78958345 | D60: =(D52+D53)/D54 -> 0.78015878 | E60: =(E52+E53)/E54 -> 0.79840138 | F60: =(F52+F53)/F54 -> 0.79974163 | G60: =(G52+G53)/G54 -> 0.78880728 | H60: =(H52+H53)/H54 -> 0.78677527 | I60: =(I52+I53)/I54 -> 0.79220334 | J60: =(J52+J53)/J54 -> 0.78943458 | ... Y60: =(Y52+Y53)/Y54 -> 0.78689266
A61: 電費占經濟口徑 | B61: % | C61: =C42/C54 -> 0.055811125 | D61: =D42/D54 -> 0.062542216 | E61: =E42/E54 -> 0.049513375 | F61: =F42/F54 -> 0.048556171 | G61: =G42/G54 -> 0.056365469 | H61: =H42/H54 -> 0.057816728 | I61: =I42/I54 -> 0.053940001 | J61: =J42/J54 -> 0.056233045 | ... Y61: =Y42/Y54 -> 0.057732884
A64: 摘要（依擺幅判讀；擺幅＝高減低的絕對值）
A65: 變數 | C65: 資本支出（變數取低） | D65: 資本支出（變數取高） | E65: 擺幅 $B | F65: 經濟持有成本（變數取低） | G65: 經濟持有成本（變數取高） | H65: 擺幅 $B/年 | I65: $/GPU-hr（變數取低） | J65: $/GPU-hr（變數取高）
A66: 基準 | C66: =C32 -> 47.582032 | F66: =C54 -> 12.054371 | I66: =C57 -> 4.7167028
A67: 機架價格 | C67: =D32 -> 42.679112 | D67: =E32 -> 53.376392 | E67: =ABS(D67-C67) -> 10.69728 | F67: =D54 -> 10.757022 | G67: =E54 -> 13.587601 | H67: =ABS(G67-F67) -> 2.8305792 | I67: =D57 -> 4.2090688 | J67: =E57 -> 5.3166339
A68: 配電設計功率 | C68: =F32 -> 54.388672 | D68: =G32 -> 47.134 | E68: =ABS(D68-C68) -> 7.254672 | F68: =F54 -> 13.855458 | G68: =G54 -> 11.935818 | H68: =ABS(G68-F68) -> 1.9196398 | I68: =F57 -> 4.5369031 | J68: =G57 -> 4.731029
A69: 網路 % | C69: =H32 -> 46.001752 | D69: =I32 -> 49.162312 | E69: =ABS(D69-C69) -> 3.16056 | F69: =H54 -> 11.636217 | G69: =I54 -> 12.472525 | H69: =ABS(G69-F69) -> 0.8363075 | I69: =H57 -> 4.5530852 | J69: =I57 -> 4.8803204
A70: 廠房建物 | C70: =J32 -> 46.892032 | D70: =K32 -> 48.617032 | E70: =ABS(D70-C70) -> 1.725 | F70: =J54 -> 11.963926 | G70: =K54 -> 12.190038 | H70: =ABS(G70-F70) -> 0.2261117 | I70: =J57 -> 4.6813131 | J70: =K57 -> 4.7697874
A71: 廠房電力設施 | C71: =L32 -> 46.777032 | D71: =M32 -> 48.732032 | E71: =ABS(D71-C71) -> 1.955 | F71: =L54 -> 11.939691 | G71: =M54 -> 12.2182 | H71: =ABS(G71-F71) -> 0.27850857 | I71: =L57 -> 4.6718302 | J71: =M57 -> 4.7808066
A72: IT 折舊年限（7 年對 4 年） | C72: =N32 -> 47.582032 | D72: =O32 -> 47.582032 | E72: =ABS(D72-C72) -> 0 | F72: =N54 -> 11.209434 | G72: =O54 -> 15.052038 | H72: =ABS(G72-F72) -> 3.8426034 | I72: =N57 -> 4.3860911 | J72: =O57 -> 5.8896468
A73: WACC | C73: =P32 -> 47.582032 | D73: =Q32 -> 47.582032 | E73: =ABS(D73-C73) -> 0 | F73: =P54 -> 11.389318 | G73: =Q54 -> 13.091054 | H73: =ABS(G73-F73) -> 1.7017355 | I73: =P57 -> 4.4564771 | J73: =Q57 -> 5.1223419
A74: 電價 | C74: =R32 -> 47.582032 | D74: =S32 -> 47.582032 | E74: =ABS(D74-C74) -> 0 | F74: =R54 -> 11.886179 | G74: =S54 -> 12.222563 | H74: =ABS(G74-F74) -> 0.336384 | I74: =R57 -> 4.6508917 | J74: =S57 -> 4.7825139
A75: PUE | C75: =T32 -> 47.582032 | D75: =U32 -> 47.582032 | E75: =ABS(D75-C75) -> 0 | F75: =T54 -> 11.998307 | G75: =U54 -> 12.110435 | H75: =ABS(G75-F75) -> 0.112128 | I75: =T57 -> 4.6947658 | J75: =U57 -> 4.7386399
A76: 平均用電比 | C76: =V32 -> 47.582032 | D76: =W32 -> 47.582032 | E76: =ABS(D76-C76) -> 0 | F76: =V54 -> 11.970275 | G76: =W54 -> 12.138467 | H76: =ABS(G76-F76) -> 0.168192 | I76: =V57 -> 4.6837973 | J76: =W57 -> 4.7496084
A77: 機架外 IT 占比（5% 對 12%） | C77: =X32 -> 48.72796 | D77: =Y32 -> 46.065616 | E77: =ABS(D77-C77) -> 2.662344 | F77: =X54 -> 12.357592 | G77: =Y54 -> 11.653116 | H77: =ABS(G77-F77) -> 0.70447587 | I77: =X57 -> 4.6816807 | J77: =Y57 -> 4.7667426

Sheet Checks
A1: Checks — 交叉檢查（外部數字多為利害關係方或第三方估計，只作方向驗證）
A3: 項目 | B3: 本模型（基準） | C3: 外部參照 | D3: 單位 | E3: 判讀 | F3: 來源
A4: VR200 每 GW 總資本支出 | B4: =DC_Cost!M33 -> 47.582032 | C4: 50–60 | D4: $B/GW | E4: =IF(AND(B4>=50,B4<=60),"落在區間",IF(B4<50,"低於參照","高於參照")) -> 低於參照 | F4: 黃仁勳 2025-08：每 GW $50–60B（S16，Interested-party；口徑未明）
A5: VR200 每 GW NVIDIA 內容（機架） | B5: =DC_Cost!M19 -> 31.6056 | C5: 約 35 | D5: $B/GW | E5: =IF(ABS(B5-35)/35<=0.2,"±20% 內","差距 >20%") -> ±20% 內 | F5: 同上：其中約 $35B 為 NVIDIA 晶片與系統
A6: 每 MW IT 廠房資本支出 | B6: =DC_Cost!M36 -> 12.67 | C6: 11.3 × 1.07–1.10 | D6: $M/MW | E6: =IF(AND(B6>=11.3*1.07*0.9,B6<=11.3*1.1*1.3),"合理區間","需檢查") -> 合理區間 | F6: JLL 2026 全球平均建物與核心 $11.3M/MW；液冷溢價 7–10%（S12）
A7: GB200 經濟口徑 $/GPU-hr | B7: =DC_Cost!G58 -> 2.0767647 | C7: 2.21 | D7: $/GPU-hr | E7: =IF(B7>2.21,"高於參照（參照假設未知）","低於參照") -> 低於參照 | F7: SemiAnalysis AI Cloud TCO（經 InferenceX 引用，S17）
A8: GB300 經濟口徑 $/GPU-hr | B8: =DC_Cost!J58 -> 2.9875129 | C8: 2.65 | D8: $/GPU-hr | E8: =IF(B8>2.65,"高於參照（參照假設未知）","低於參照") -> 高於參照（參照假設未知） | F8: 同上
A9: GB200 市場牌價對照 | B9: =DC_Cost!G58 -> 2.0767647 | C9: 10.50 | D9: $/GPU-hr | E9: ="牌價 ÷ 持有成本＝"&TEXT(10.5/B9,"0.0")&" 倍" -> 牌價 ÷ 持有成本＝5.1 倍 | F9: CoreWeave 公開價 4-GPU GB200 $42/hr（2026-05，S18）；隨需牌價非合約價
A10: 新雲損益兩平參照 | B10: =DC_Cost!J58 -> 2.9875129 | C10: 3.57 | D10: $/GPU-hr | E10: ="參照 ÷ 本模型＝"&TEXT(3.57/B10,"0.00") -> 參照 ÷ 本模型＝1.19 | F10: 第三方以 85% 利用率、9.12% 資金成本、6 年回收推算之每 GPU 小時租金門檻（S19；機型未明）

Sheet Interface
A1: Interface — 下游模型唯一連結點（每 GW＝IT 關鍵電力）
A2: 每一列為一個具名範圍（IF_…），欄＝世代 × 成本情境；Block 2 起加入產出列
A4: 指標 | B4: 單位 | C4: =Spec_Rack!C4 -> Hopper H100 | D4: =Spec_Rack!C4 -> Hopper H100 | E4: =Spec_Rack!C4 -> Hopper H100 | F4: =Spec_Rack!D4 -> GB200 NVL72 | G4: =Spec_Rack!D4 -> GB200 NVL72 | H4: =Spec_Rack!D4 -> GB200 NVL72 | I4: =Spec_Rack!E4 -> GB300 NVL72 | J4: =Spec_Rack!E4 -> GB300 NVL72 | K4: =Spec_Rack!E4 -> GB300 NVL72 | L4: =Spec_Rack!F4 -> VR200 NVL72 | M4: =Spec_Rack!F4 -> VR200 NVL72 | N4: =Spec_Rack!F4 -> VR200 NVL72 | O4: =Spec_Rack!G4 -> Rubin Ultra NVL576 | P4: =Spec_Rack!G4 -> Rubin Ultra NVL576 | Q4: =Spec_Rack!G4 -> Rubin Ultra NVL576
A5: 成本情境 | C5: 低成本 | D5: 基準 | E5: 高成本 | F5: 低成本 | G5: 基準 | H5: 高成本 | I5: 低成本 | J5: 基準 | K5: 高成本 | L5: 低成本 | M5: 基準 | N5: 高成本 | O5: 低成本 | P5: 基準 | Q5: 高成本
A6: 每 GW 機架數 | B6: 架 | C6: =DC_Cost!C12 -> 22439 | D6: =DC_Cost!D12 -> 22439 | E6: =DC_Cost!E12 -> 22439 | F6: =DC_Cost!F12 -> 7076 | G6: =DC_Cost!G12 -> 7076 | H6: =DC_Cost!H12 -> 7076 | I6: =DC_Cost!I12 -> 6715 | J6: =DC_Cost!J12 -> 6715 | ... Q6: =DC_Cost!Q12 -> 1533
A7: 每 GW GPU 數 | B7: 顆 | C7: =DC_Cost!C14 -> 718048 | D7: =DC_Cost!D14 -> 718048 | E7: =DC_Cost!E14 -> 718048 | F7: =DC_Cost!F14 -> 509472 | G7: =DC_Cost!G14 -> 509472 | H7: =DC_Cost!H14 -> 509472 | I7: =DC_Cost!I14 -> 483480 | J7: =DC_Cost!J14 -> 483480 | ... Q7: =DC_Cost!Q14 -> 220752
A8: 每 IT GW 對應設施電力 | B8: GW | C8: =DC_Cost!C16/1000 -> 1.1 | D8: =DC_Cost!D16/1000 -> 1.2 | E8: =DC_Cost!E16/1000 -> 1.3 | F8: =DC_Cost!F16/1000 -> 1.1 | G8: =DC_Cost!G16/1000 -> 1.2 | H8: =DC_Cost!H16/1000 -> 1.3 | I8: =DC_Cost!I16/1000 -> 1.1 | J8: =DC_Cost!J16/1000 -> 1.2 | ... Q8: =DC_Cost!Q16/1000 -> 1.3
A9: 每 GW 資本支出 — IT 設備 | B9: $B | C9: =DC_Cost!C24 -> 21.420269 | D9: =DC_Cost!D24 -> 27.510214 | E9: =DC_Cost!E24 -> 34.120743 | F9: =DC_Cost!F24 -> 20.956282 | G9: =DC_Cost!G24 -> 24.383896 | H9: =DC_Cost!H24 -> 28.074738 | I9: =DC_Cost!I24 -> 28.348044 | J9: =DC_Cost!J24 -> 37.17424 | ... Q9: =DC_Cost!Q24 -> 68.931652
A10: 每 GW 資本支出 — 廠房 | B10: $B | C10: =DC_Cost!C32 -> 10.212 | D10: =DC_Cost!D32 -> 12.67 | E10: =DC_Cost!E32 -> 16.186 | F10: =DC_Cost!F32 -> 10.212 | G10: =DC_Cost!G32 -> 12.67 | H10: =DC_Cost!H32 -> 16.186 | I10: =DC_Cost!I32 -> 10.212 | J10: =DC_Cost!J32 -> 12.67 | ... Q10: =DC_Cost!Q32 -> 16.186
A11: 每 GW 資本支出 — 合計 | B11: $B | C11: =DC_Cost!C33 -> 31.632269 | D11: =DC_Cost!D33 -> 40.180214 | E11: =DC_Cost!E33 -> 50.306743 | F11: =DC_Cost!F33 -> 31.168282 | G11: =DC_Cost!G33 -> 37.053896 | H11: =DC_Cost!H33 -> 44.260738 | I11: =DC_Cost!I33 -> 38.560044 | J11: =DC_Cost!J33 -> 49.84424 | ... Q11: =DC_Cost!Q33 -> 85.117652
A12: 每 GW 年持有成本 — 會計口徑 | B12: $B/年 | C12: =DC_Cost!C49 -> 5.3989724 | D12: =DC_Cost!D49 -> 7.4968278 | E12: =DC_Cost!E49 -> 12.949273 | F12: =DC_Cost!F49 -> 5.3109694 | G12: =DC_Cost!G49 -> 6.8663537 | H12: =DC_Cost!H49 -> 11.147563 | I12: =DC_Cost!I49 -> 6.7129403 | J12: =DC_Cost!J49 -> 9.4457397 | ... Q12: =DC_Cost!Q49 -> 23.322924
A13: 每 GW 年持有成本 — 經濟口徑 | B13: $B/年 | C13: =DC_Cost!C55 -> 7.0000433 | D13: =DC_Cost!D55 -> 10.095795 | E13: =DC_Cost!E55 -> 17.405972 | F13: =DC_Cost!F55 -> 6.8890039 | G13: =DC_Cost!G55 -> 9.2685485 | H13: =DC_Cost!H55 -> 15.083132 | I13: =DC_Cost!I55 -> 8.6579664 | J13: =DC_Cost!J55 -> 12.652968 | ... Q13: =DC_Cost!Q55 -> 30.780121
A14: 每 GPU 小時持有成本 — 經濟 | B14: $/GPU-hr | C14: =DC_Cost!C58 -> 1.1128667 | D14: =DC_Cost!D58 -> 1.6050293 | E14: =DC_Cost!E58 -> 2.767201 | F14: =DC_Cost!F58 -> 1.5435902 | G14: =DC_Cost!G58 -> 2.0767647 | H14: =DC_Cost!H58 -> 3.379614 | I14: =DC_Cost!I58 -> 2.0442466 | J14: =DC_Cost!J58 -> 2.9875129 | ... Q14: =DC_Cost!Q58 -> 15.917013
A15: 其中：每 GW 年電費 | B15: $B/年 | C15: =DC_Cost!C43 -> 0.404712 | D15: =DC_Cost!D43 -> 0.672768 | E15: =DC_Cost!E43 -> 1.02492 | F15: =DC_Cost!F43 -> 0.404712 | G15: =DC_Cost!G43 -> 0.672768 | H15: =DC_Cost!H43 -> 1.02492 | I15: =DC_Cost!I43 -> 0.404712 | J15: =DC_Cost!J43 -> 0.672768 | ... Q15: =DC_Cost!Q43 -> 1.02492
A17: Block 2 起填入（保留列位）
A18: 每架產出 tok/s（世代 × 層級 × SLO） | C18: 待 Block 2／4
A19: 每 GW 產出 M tok/年 | C19: 待 Block 2／4
A20: 每 token 完整成本（依層級） | C20: 待 Block 2／4
A21: 每 GW 理論營收 | C21: 待 Block 2／4
A22: VR-eq 係數 | C22: 待 Block 2／4

Sheet Sources
A1: Sources — 來源與查核狀態（Andy 審閱前均視為待查核）
A3: ID | B3: 項目 | C3: 內容摘要 | D3: 標記 | E3: 日期 | F3: 來源 | G3: 查核狀態
A4: S1 | B4: DGX H100 功率 | C4: 最大約 10.2 kW／8 GPU | D4: Verified | E4: 2023 | F4: NVIDIA DGX H100 規格（模型內建知識，待以原始規格表核對） | G4: 待查核
A5: S2 | B5: HGX H100 價格 | C5: 約 $30K／GPU；8 GPU 伺服器約 $220–320K | D5: Analogy | E5: 2026 | F5: clusterbid.com（低品質來源）；取區間 | G5: 待查核
A6: S3 | B6: GB200／GB300 機架功率 | C6: Blackwell 約 120–130 kW；GB300 NVL72 約 132–142 kW | D6: Interested-party | E6: 2026-06 | F6: moduledge.com；hashrateindex.com | G6: 待查核
A7: S4 | B7: GB200／GB300／VR200 價格 | C7: GB200 $2.8–3.4M；GB300 $6–6.5M；VR200 $5–7M（含約 $1M NAND） | D7: Interested-party | E7: 2026-03 | F7: Tom's Hardware（經 Yahoo Finance） | G7: 待查核
A8: S5 | B8: GB300 機架功率 | C8: Supermicro GB300 NVL72 132–140 kW | D8: Interested-party | E8: 2026-08 | F8: Supermicro 規格（經 wing.vc 引用） | G8: 待查核
A9: S6 | B9: GB300 採購單價 | C9: 2026-08 採購單約 $5M／架 | D9: Interested-party | E9: 2026-08 | F9: Data Gravity（經 wing.vc） | G9: 待查核
A10: S7 | B10: VR200 與 Rubin Ultra 功率 | C10: VR200 Max-Q 約 190、Max-P 約 230 kW（郭明錤）；Rubin Ultra NVL576 約 600 kW | D10: Interested-party | E10: 2026 | F10: spheron.network；thundercompute.com | G10: 待查核
A11: S8 | B11: Supermicro VR NVL72 散熱設計點 | C11: DLC-2 按每架 227 kW 設計；2026-09-23 開始出貨 | D11: Interested-party | E11: 2026-09 | F11: windowsforum.com 轉述 Supermicro | G11: 待查核
A12: S9 | B12: VR200 機架成本估計 | C12: Morgan Stanley $7.8M（自購記憶體 $6.7M）；Bernstein $9.09M | D12: Interested-party | E12: 2026-05／06 | F12: PC Gamer、BigGo Finance 轉述 MS；Futu 轉述 Bernstein | G12: 待查核
A13: S10 | B13: 網路資本支出占比 | C13: 1,024 GPU 叢集網路約為 GPU BOM 4–8%；JPM 假設網路占 AI 支出 15% | D13: Analogy | E13: 2026 | F13: hedgehog.cloud；J.P. Morgan AM Eye on the Market | G13: 待查核
A14: S11 | B14: VR200 報價是否含網路 | C14: 有來源稱報價中約 $1M 與網路設備有關；與 S4 的 NAND 說法可能重疊 | D14: Interested-party | E14: 2026 | F14: originalpricing.com | G14: 未解：可能重複計算
... A22: S19 | B22: 新雲損益兩平租金 | C22: 85% 利用率、9.12% 資金成本、6 年：$3.57／GPU-hr | D22: Derived | E22: 2026-09 | F22: capefearadvisors.substack.com | G22: 機型未明
