Workbook

Sheet 0_說明
B1: m 閱讀版（Tokenomics v21.2）
B2: 建立：2026-10-24（依 Andy 2026-10-21 新定義重做）。用途：讓 Andy 讀懂 m（付費服務 token 的有效牌價變現率）從總覽到最細的推導。本簿每個取自 Tokenomics 的數字都已對 Tokenomics v21.2（master 45ce1ca）逐格核對。
B4: 定義（Andy 原話，2026-10-21）
B5: 14:17「我認為m要定義成『付費服務token的有效牌價(1-折扣20%)變現率』。」 14:37「…m的定義和計算就不要牽涉到免費了…m單純只看收費業務token有效牌價變現率。」 15:39「我認知的m是有效牌價的進一步打折程度，跟營收有關，跟成本無關。」 15:59「那個(1-20%)的20%是預設折扣，不要寫死，要可以調整」「當然要拆，m本來就只有收入面」。
B6: → m＝實收單價 ÷ 有效牌價；有效牌價＝表列牌價 ×（1 − d），d＝預設折扣（Tokenomics B4_Disc，預設 0.20，可調，本簿 2_輸入 的 IN_Disc）。只有收入面。
B8: 分頁
B9: 1_總覽：m 的一句話定義、2025／2026 Q1／Q2／FY2026 的 m 與區間、分路線、2025→2026 Q2 變化的三因子拆解、與 token 帳診斷的區別、最不確定的輸入。
B10: 1A_需求公式樹：從營收與付費 token 出發，逐層（L0–L5）推到 m，含 d 可調驗證與「m＝1 必須為真」。建議先讀本頁，細節再看 3–5 頁。
B11: 2_輸入：全部葉輸入（藍字，可改）。黃底＝不確定度高且對 m 影響大。每列附標記、區間、Tokenomics 位置與說明。
B12: 3_m重算：m 的逐步計算（S1–S14，四欄＝2025／2026 Q1／Q2／FY2026；另有層級單價展開表與區間端點表），每步附白話說明、原活頁簿位置、原值、差異。
B13: 4_分路線：m_API／m_消費訂閱／m_商用席次（營收三分 × token 三分）。
B14: 5_敏感度：2026 Q2 的 m 對每個有 Tokenomics 區間的輸入的單變數擺動。
... B33: 本簿是 Tokenomics v21.2 的版本快照，不會隨基準模型自動同步。姊妹檔：20261020_L閱讀版_v17.0.xlsx（L 閱讀版另行維護）。

Sheet 1_總覽
B1: m（付費服務 token 的有效牌價變現率）總覽
B2: Tokenomics v21.2（20261023_Tokenomics_v21.2.xlsx，master 45ce1ca）。本頁數字全部連結到 3、4 頁，改 2_輸入 會一起變。
B4: 一句話
B5: m ＝ 實收單價 ÷ 有效牌價。實收單價＝付費業務（扣廣告）的營收 ÷ 付費 token（API ＋ ChatGPT 付費）；有效牌價＝表列牌價 ×（1 − d），d 預設 20%、可調。只有收入面：免費服務與訓練研發算力不產生營收，不進 m；也不經成本鏈反推。m＞1 表示每個付費 token 平均實收高於有效牌價，主要來自定額訂閱。
B7: 項目 | C7: 2025 | D7: 2026 Q1 | E7: 2026 Q2（主口徑） | F7: FY2026 | G7: 單位 | H7: 怎麼算（細節頁）
B8: m | C8: =3_m重算!F21 -> 2.5135467 | D8: =3_m重算!G21 -> 1.1923391 | E8: =3_m重算!H21 -> 1.3432012 | F8: =3_m重算!I21 -> 1.4316985 | G8: 倍 | H8: ＝實收單價 ÷ 有效牌價（3_m重算 S13）
B9: m 分子營收（營收 − 廣告） | C9: =3_m重算!F8 -> 13.07 | D9: =3_m重算!G8 -> 22.8 | E9: =3_m重算!H8 -> 26.3 | F9: =3_m重算!I8 -> 35 | G9: $B | H9: 營收年化 − 廣告（S1–S3）
B10: 需求面付費 token | C10: =3_m重算!F15 -> 3825200000 | D10: =3_m重算!G15 -> 9752800000 | E10: =3_m重算!H15 -> 9986400000 | F10: =3_m重算!I15 -> 12468400000 | G10: M tok/年 | H10: API ＋ ChatGPT 付費（S4–S9）
B11: 實收單價 | C11: =3_m重算!F20 -> 3.4168148 | D11: =3_m重算!G20 -> 2.3377902 | E11: =3_m重算!H20 -> 2.6335817 | F11: =3_m重算!I20 -> 2.8070963 | G11: $/M tok | H11: 分子營收 ÷ 付費 token（S12）
B12: 有效牌價（混合有效單價） | C12: =3_m重算!F17 -> 1.35936 | D12: =3_m重算!G17 -> 1.9606756 | E12: =3_m重算!H17 -> 1.9606756 | F12: =3_m重算!I17 -> 1.9606756 | G12: $/M tok | H12: Σ 層級占比 × 層級有效單價 × κ（S10）
B13: 表列混合牌價（未折扣） | C13: =3_m重算!F18 -> 1.6992 | D13: =3_m重算!G18 -> 2.4508444 | E13: =3_m重算!H18 -> 2.4508444 | F13: =3_m重算!I18 -> 2.4508444 | G13: $/M tok | H13: 有效牌價 ÷（1 − d）（S11）
B15: 區間（Tokenomics 的 L1_M 區間；低端＝token 取高、高端＝token 取低）
C16: 低 | D16: 基準 | E16: 高 | H16: 說明
B17: 2025（L1_M_2025） | C17: =3_m重算!F51 -> 1.0851034 | D17: =3_m重算!F21 -> 2.5135467 | E17: =3_m重算!G51 -> 4.2596975 | H17: 每則 token、免費占比、API 全年比例同向取端點（最寬情形，不是機率區間）。
B18: 2026 Q2（L1_M，主口徑） | C18: =3_m重算!H51 -> 0.81018482 | D18: =3_m重算!H21 -> 1.3432012 | E18: =3_m重算!I51 -> 1.5950514 | H18: 每則 token、免費占比同向取端點；營收、API token、單價、每日訊息數不變。
B19: 2026 Q1、FY2026 | C19: 無區間 | H19: Tokenomics 的 L1_M_2026Q1、L1_M_FY2026 區間欄為「無區間」：2026 欄的輸入是 Assumed 單值，區間待補（單值原因＝無 SRC 區間）。
B21: 分路線（細節見 4_分路線）
B22: 路線 | C22: 2025 | D22: 2026 Q1 | E22: 2026 Q2 | F22: FY2026 | G22: 單位 | H22: 讀法
B23: m_API | C23: =4_分路線!F21 -> 0.81302374 | D23: =4_分路線!G21 -> 0.29499353 | E23: =4_分路線!H21 -> 0.34027763 | F23: =4_分路線!I21 -> 0.34833919 | G23: 倍 | H23: API 按量計費：實收約為有效牌價的三分之一（2026 Q2），因為 2026 的 API token 用的是 2026-03 時點值、營收份額 0.20 是餘額。
B24: m_消費訂閱 | C24: =4_分路線!F22 -> 6.1464595 | D24: =4_分路線!G22 -> 5.7438644 | E24: =4_分路線!H22 -> 5.3986354 | F24: =4_分路線!I22 -> 5.5688436 | G24: 倍 | H24: 定額月費：每個 token 實收是有效牌價的 5 倍以上，是整體 m＞1 的主因。
B25: m_商用席次 | C25: =4_分路線!F23 -> 2.6341969 | D25: =4_分路線!G23 -> 3.5557256 | E25: =4_分路線!H23 -> 4.5572896 | F25: =4_分路線!I23 -> 8.0438852 | G25: 倍 | H25: 席次定額收費，同上，倍數較小。
B27: m 從 2025 到 2026 Q2 為什麼變：三個因子
B28: 因子 | C28: 2025 | D28: 2026 Q2 | E28: 倍數（Q2 ÷ 2025） | H28: 怎麼讀
B29: 分子：m 分子營收（$B） | C29: =3_m重算!F8 -> 13.07 | D29: =3_m重算!H8 -> 26.3 | E29: =D29/C29 -> 2.0122418 | H29: 營收成長：m 的分子變大，m 變大。
B30: 分母之一：付費 token（M tok/年） | C30: =3_m重算!F15 -> 3825200000 | D30: =3_m重算!H15 -> 9986400000 | E30: =D30/C30 -> 2.610687 | H30: token 增加：分母變大，m 變小。2026 的 API token 與每日訊息數都明顯增加。
B31: 分母之二：有效牌價（$/M tok） | C31: =3_m重算!F17 -> 1.35936 | D31: =3_m重算!H17 -> 1.9606756 | E31: =D31/C31 -> 1.442352 | H31: 牌價基準不同（2025 年度層級單價對 2026-09 GPT-6 牌價）：分母變大，m 變小。
B32: m 倍數＝分子倍數 ÷（token 倍數 × 有效牌價倍數） | E32: =E29/(E30*E31) -> 0.53438481 | H32: ="應等於 m 的 Q2 ÷ 2025："&TEXT(D8/C8,"0.000")&"；差 "&TEXT(E32-D8/C8,"0.0E+00") -> 應等於 m 的 Q2 ÷ 2025：0.474；差 6.0E-02
B34: 與 token 帳診斷的區別（以下三項不是 m）
B35: 名稱 | C35: Tokenomics 原值 | G35: 單位 | H35: 一句話
B36: L1_MFleet（2025） | C36: 0.94780425 | G36: 倍 | H36: 舊的「機隊 m」：成本鏈（推論支出 → 持有成本 → GW → token）推出的付費 token 當分母。＝m ×（真實 token ÷ 模型 token），混有 token 帳誤差，不是 m。
B37: L1_TokLedger（2025） | C37: 2.6519682 | G37: 倍 | H37: 模型付費 token ÷ 需求面付費 token（＝L1_M_2025 ÷ L1_MFleet）。token 帳係數，歸數量 Q 側。
B38: L1_TokLedger_2026Q2 | C38: 3.0194726 | G38: 倍 | H38: 同上，2026 Q2。
B40: 驗證
B41: 3_m重算 的 m ÷ Tokenomics 原值 − 1（四欄最大絕對值） | C41: =MAX(ABS(3_m重算!N21),ABS(3_m重算!O21),ABS(3_m重算!P21),ABS(3_m重算!Q21)) -> 0
B42: 4_分路線 三路線合計 − 整體 m（四欄最大絕對值） | C42: =MAX(ABS(4_分路線!F25),ABS(4_分路線!G25),ABS(4_分路線!H25),ABS(4_分路線!I25)) -> 0
B44: 最不確定的輸入（依 5_敏感度 擺動；細節見 6 頁）
B45: 輸入 | C45: 擺動 | D45: 承重度
B46: =5_敏感度!B7 -> 每則 token τ | C46: =5_敏感度!L7 -> 0.38687783 | D46: =5_敏感度!K7 -> -0.24923518
B47: =5_敏感度!B9 -> 有效折扣 d | C47: =5_敏感度!L9 -> 0.44444444 | D47: =5_敏感度!K9 -> 0.29248125
B48: =5_敏感度!B10 -> 請求形狀 κ | C48: =5_敏感度!L10 -> 0.70512821 | D48: =5_敏感度!K10 -> -1
B49: =5_敏感度!B13 -> Astra 層級占比 | C49: =5_敏感度!L13 -> 0.57636863 | D49: =5_敏感度!K13 -> -0.58016387
B50: =5_敏感度!B11 -> 快取命中 χ | C50: =5_敏感度!L11 -> 0.35552534 | D50: =5_敏感度!K11 -> 0.38753502
B51: =5_敏感度!B8 -> ChatGPT 免費占比 | C51: =5_敏感度!L8 -> 0.21288515 | D51: =5_敏感度!K8 -> 0.30485458
B52: =5_敏感度!B15 -> Sol 參考輸入長度 ISL | C52: =5_敏感度!L15 -> 0.28421555 | D52: =5_敏感度!K15 -> 0.13329761
B53: =5_敏感度!B18 -> Sol 參考輸出長度 OSL | C53: =5_敏感度!L18 -> 0.22241295 | D53: =5_敏感度!K18 -> -0.1638704

Sheet 1A_需求公式樹
A1: m 的需求公式樹：從「誰付錢、誰用 token」推到 m（付費服務 token 的有效牌價變現率）
A2: 讀法：由上往下，每一層把上一層的一個量拆開。全部是公式，連到 2_輸入（藍字）、3_m重算、4_分路線；改輸入，本頁一起變。左邊兩欄值＝2025 與 2026 Q2（主口徑）；Q1、FY2026 在 3_m重算。H／I 欄＝Tokenomics v21.2 原值（貼上），J／K 欄＝差異。
A3: token 單位一律為「兆 token/年」（10¹² token；3_m重算 的 M tok ÷ 10⁶）。單價一律為「$/M token」（每百萬 token 美元）。m 的定義（Andy 2026-10-21）：m＝實收單價 ÷ 有效牌價；有效牌價＝表列牌價 ×（1 − d），d 預設 20%、可調；m 只有收入面，免費與成本都不進 m。
A5: 層 | B5: 項目 | C5: 值 2025 | D5: 值 2026 Q2 | E5: 單位 | F5: 怎麼算（白話＋公式） | G5: 標記 | H5: 原值 2025 | I5: 原值 2026 Q2 | J5: 差異 2025 | K5: 差異 2026 Q2
A6: L0 m 是什麼：每個付費 token 實收多少，除以有效牌價
B7: m 分子營收（營收 − 廣告） | C7: =3_m重算!F8 -> 13.07 | D7: =3_m重算!H8 -> 26.3 | E7: $B | F7: 付費服務實際收到的錢（毛額、不含廣告）。 | G7: Interested-party | H7: 13.07 | I7: 26.3 | J7: =IF(H7=0,C7-H7,C7/H7-1) -> 0 | K7: =IF(I7=0,D7-I7,D7/I7-1) -> 0
B8: 需求面付費 token | C8: =3_m重算!F15/1000000 -> 3825.2 | D8: =3_m重算!H15/1000000 -> 9986.4 | E8: 兆 token/年 | F8: API token ＋ ChatGPT 付費 token（L3 加總）。免費 token 不進 m。 | G8: Derived | H8: 3825.2 | I8: 9986.4 | J8: =IF(H8=0,C8-H8,C8/H8-1) -> 0 | K8: =IF(I8=0,D8-I8,D8/I8-1) -> 0
B9: 實收單價（每百萬付費 token 實收） | C9: =3_m重算!F20 -> 3.4168148 | D9: =3_m重算!H20 -> 2.6335817 | E9: $/M token | F9: ＝m 分子營收 × 1000 ÷ 付費 token（兆）。 | G9: Derived
B10: 表列混合牌價（未折扣） | C10: =3_m重算!F18 -> 1.6992 | D10: =3_m重算!H18 -> 2.4508444 | E10: $/M token | F10: ＝有效牌價 ÷（1 − d）。層級組合加權的 OpenAI 官方牌價。 | G10: Derived | I10: 2.4508444 | K10: =IF(I10=0,D10-I10,D10/I10-1) -> 0
B11: d：預設折扣（可調） | C11: =IN_Disc -> 0.2 | D11: =IN_Disc -> 0.2 | E11: % | F11: Batch／Flex 半價＋企業議價的加權；Assumed，區間 0.1–0.4。改 2_輸入 的 IN_Disc 即可。 | G11: Assumed | H11: 0.2 | I11: 0.2 | J11: =IF(H11=0,C11-H11,C11/H11-1) -> 0 | K11: =IF(I11=0,D11-I11,D11/I11-1) -> 0
B12: 有效牌價 | C12: =3_m重算!F17 -> 1.35936 | D12: =3_m重算!H17 -> 1.9606756 | E12: $/M token | F12: ＝表列牌價 ×（1 − d）；L4 展開。2025 與 2026 的牌價基準不同（2025 用 2025 年度層級單價，2026 用 2026-09 的 GPT-6 牌價）。 | G12: Derived | H12: 1.35936 | I12: 1.9606756 | J12: =IF(H12=0,C12-H12,C12/H12-1) -> 0 | K12: =IF(I12=0,D12-I12,D12/I12-1) -> 0
B13: m ＝ 實收單價 ÷ 有效牌價 | C13: =3_m重算!F21 -> 2.5135467 | D13: =3_m重算!H21 -> 1.3432012 | E13: 倍 | F13: m＞1：付費 token 平均實收高於有效牌價（主要來自定額訂閱）；m＜1：實收低於有效牌價。 | G13: Derived | H13: 2.5135467 | I13: 1.3432012 | J13: =IF(H13=0,C13-H13,C13/H13-1) -> 0 | K13: =IF(I13=0,D13-I13,D13/I13-1) -> 0
A14: L1 分子與分母：m ＝ 分子營收 ÷（付費 token × 有效單價）
B15: 營收（年化） | C15: =3_m重算!F6 -> 13.07 | D15: =3_m重算!H6 -> 26.8 | E15: $B | F15: 2025 全年；2026 Q2＝季營收 × 4。 | G15: Interested-party | H15: 13.07 | I15: 26.8 | J15: =IF(H15=0,C15-H15,C15/H15-1) -> 0 | K15: =IF(I15=0,D15-I15,D15/I15-1) -> 0
B16: 廣告營收（年化） | C16: =3_m重算!F7 -> 0 | D16: =3_m重算!H7 -> 0.5 | E16: $B | F16: 不進分子（Andy：m 單純看收費業務）。2025 無廣告。 | G16: Assumed | H16: 0 | I16: 0.5 | J16: =IF(H16=0,C16-H16,C16/H16-1) -> 0 | K16: =IF(I16=0,D16-I16,D16/I16-1) -> 0
B17: 分子：m 分子營收 | C17: =3_m重算!F8 -> 13.07 | D17: =3_m重算!H8 -> 26.3 | E17: $B | F17: ＝營收 − 廣告。 | G17: Derived | H17: 13.07 | I17: 26.3 | J17: =IF(H17=0,C17-H17,C17/H17-1) -> 0 | K17: =IF(I17=0,D17-I17,D17/I17-1) -> 0
B18: 分母：付費 token 按有效牌價折算的營收 | C18: =3_m重算!F15*3_m重算!F17/1000000000 -> 5.1998239 | D18: =3_m重算!H15*3_m重算!H17/1000000000 -> 19.58009 | E18: $B | F18: ＝付費 token × 有效單價：如果每個付費 token 都照有效牌價收費，營收會是這麼多。 | G18: Derived
B19: 檢查：分子 ÷ 分母 | C19: =C17/C18 -> 2.5135467 | D19: =D17/D18 -> 1.3432012 | E19: 倍 | F19: 應等於 L0 的 m（恆等式）。 | G19: Derived
A20: L2 營收從哪裡來：三條收費路線，各自的 m（分子拆開；細節見 4_分路線）
B21: API 營收 | C21: =4_分路線!F12 -> 2.614 | D21: =4_分路線!H12 -> 5.26 | E21: $B | F21: ＝m 分子營收 × API 份額（餘額）。 | G21: Derived | H21: 2.614 | I21: 5.26 | J21: =IF(H21=0,C21-H21,C21/H21-1) -> 0 | K21: =IF(I21=0,D21-I21,D21/I21-1) -> 0
B22: 消費訂閱營收 | C22: =4_分路線!F10 -> 9.149 | D22: =4_分路線!H10 -> 14.465 | E22: $B | F22: ＝m 分子營收 × 消費訂閱份額（2025 約 70%；2026 Q2 0.55）。 | G22: Derived／Assumed | H22: 9.149 | I22: 14.465 | J22: =IF(H22=0,C22-H22,C22/H22-1) -> 0 | K22: =IF(I22=0,D22-I22,D22/I22-1) -> 0
B23: 商用席次營收 | C23: =4_分路線!F11 -> 1.307 | D23: =4_分路線!H11 -> 6.575 | E23: $B | F23: ＝m 分子營收 × 商用席次份額（2025 0.10；2026 Q2 0.25，Assumed）。 | G23: Assumed | H23: 1.307 | I23: 6.575 | J23: =IF(H23=0,C23-H23,C23/H23-1) -> 0 | K23: =IF(I23=0,D23-I23,D23/I23-1) -> 0
B24: m_API | C24: =4_分路線!F21 -> 0.81302374 | D24: =4_分路線!H21 -> 0.34027763 | E24: 倍 | F24: 按量計費路線：實收低於有效牌價。 | G24: Derived | H24: 0.81302374 | I24: 0.34027763 | J24: =IF(H24=0,C24-H24,C24/H24-1) -> 0 | K24: =IF(I24=0,D24-I24,D24/I24-1) -> 0
B25: m_消費訂閱 | C25: =4_分路線!F22 -> 6.1464595 | D25: =4_分路線!H22 -> 5.3986354 | E25: 倍 | F25: 定額月費 ÷ 實際用量：遠大於 1，是整體 m 偏高的主因。 | G25: Derived | H25: 6.1464595 | I25: 5.3986354 | J25: =IF(H25=0,C25-H25,C25/H25-1) -> 0 | K25: =IF(I25=0,D25-I25,D25/I25-1) -> 0
B26: m_商用席次 | C26: =4_分路線!F23 -> 2.6341969 | D26: =4_分路線!H23 -> 4.5572896 | E26: 倍 | F26: 按席次定額收費，同上。 | G26: Derived | H26: 2.6341969 | I26: 4.5572896 | J26: =IF(H26=0,C26-H26,C26/H26-1) -> 0 | K26: =IF(I26=0,D26-I26,D26/I26-1) -> 0
A27: L3 付費 token 由誰用：API 與 ChatGPT 付費（二分）；ChatGPT 付費再分消費訂閱／商用席次
B28: API 每分鐘 token | C28: =IN_APItpm -> 6 | D28: =IN_APItpm26 -> 15 | E28: 十億 token/分鐘 | F28: 2025：OpenAI 2025-10-06 公告 60 億；2026：2026-03-31 融資公告「超過」150 億（Q2 當期值未找到）。 | G28: Interested-party | H28: 6 | I28: 15 | J28: =IF(H28=0,C28-H28,C28/H28-1) -> 0 | K28: =IF(I28=0,D28-I28,D28/I28-1) -> 0
B29: API 全年平均 ÷ 時點值 | C29: =IN_APIratio -> 0.75 | E29: 倍 | F29: 只 2025 欄：把 10 月時點值換成全年平均（Assumed 0.6–0.9）；2026 Q1／Q2 不打折，FY2026 另乘 1.3。 | G29: Assumed | H29: 0.75 | J29: =IF(H29=0,C29-H29,C29/H29-1) -> 0
B30: → API token | C30: =3_m重算!F10/1000000 -> 2365.2 | D30: =3_m重算!H10/1000000 -> 7884 | E30: 兆 token/年 | F30: ＝每分鐘 token × 525,600 分鐘 ×（2025：年均比例；2026：1）。 | G30: Derived | H30: 2365.2 | I30: 7884 | J30: =IF(H30=0,C30-H30,C30/H30-1) -> 0 | K30: =IF(I30=0,D30-I30,D30/I30-1) -> 0
B31: ChatGPT 每日訊息數 | C31: =IN_Prompts -> 2.5 | D31: =IN_Prompts_Q2 -> 3.6 | E31: 十億則/日 | F31: 2025：OpenAI 自述 25 億；2026 Q2：3.6（週活比例放大，Assumed）。 | G31: Interested-party／Assumed | H31: 2.5 | I31: 3.6 | J31: =IF(H31=0,C31-H31,C31/H31-1) -> 0 | K31: =IF(I31=0,D31-I31,D31/I31-1) -> 0
B32: 每則訊息 token 數 τ | C32: =IN_Tau -> 4000 | D32: =IN_Tau -> 4000 | E32: token/則 | F32: 含輸入、輸出、思考；無公開數字（Assumed 2,000–11,000）。 | G32: Assumed | H32: 4000 | I32: 4000 | J32: =IF(H32=0,C32-H32,C32/H32-1) -> 0 | K32: =IF(I32=0,D32-I32,D32/I32-1) -> 0
B33: 免費用戶占 ChatGPT token 比 | C33: =IN_FreeShare -> 0.6 | D33: =IN_FreeShare -> 0.6 | E33: % | F33: token 口徑（Assumed 0.4–0.8）。只用來把 ChatGPT 總量扣成付費部分；免費服務本身不進 m。 | G33: Assumed | H33: 0.6 | I33: 0.6 | J33: =IF(H33=0,C33-H33,C33/H33-1) -> 0 | K33: =IF(I33=0,D33-I33,D33/I33-1) -> 0
B34: ChatGPT token 總量 | C34: =3_m重算!F12/1000000 -> 3650 | D34: =3_m重算!H12/1000000 -> 5256 | E34: 兆 token/年 | F34: ＝每日訊息 × τ × 365。 | G34: Derived | H34: 3650 | I34: 5256 | J34: =IF(H34=0,C34-H34,C34/H34-1) -> 0 | K34: =IF(I34=0,D34-I34,D34/I34-1) -> 0
B35: 其中免費 token（扣除，不進 m） | C35: =3_m重算!F13/1000000 -> 2190 | D35: =3_m重算!H13/1000000 -> 3153.6 | E35: 兆 token/年 | F35: ＝總量 × 免費占比。 | G35: Derived | H35: 2190 | I35: 3153.6 | J35: =IF(H35=0,C35-H35,C35/H35-1) -> 0 | K35: =IF(I35=0,D35-I35,D35/I35-1) -> 0
B36: → ChatGPT 付費 token | C36: =3_m重算!F14/1000000 -> 1460 | D36: =3_m重算!H14/1000000 -> 2102.4 | E36: 兆 token/年 | F36: ＝總量 × （1 − 免費占比）。 | G36: Derived | H36: 1460 | I36: 2102.4 | J36: =IF(H36=0,C36-H36,C36/H36-1) -> 0 | K36: =IF(I36=0,D36-I36,D36/I36-1) -> 0
B37: 消費訂閱 token | C37: =4_分路線!F17/1000000 -> 1095 | D37: =4_分路線!H17/1000000 -> 1366.56 | E37: 兆 token/年 | F37: ＝ChatGPT 付費 × 消費份額（2025 0.75；2026 0.65，Assumed）。 | G37: Assumed（份額） | H37: 1095 | I37: 1366.56 | J37: =IF(H37=0,C37-H37,C37/H37-1) -> 0 | K37: =IF(I37=0,D37-I37,D37/I37-1) -> 0
B38: 商用席次 token | C38: =4_分路線!F18/1000000 -> 365 | D38: =4_分路線!H18/1000000 -> 735.84 | E38: 兆 token/年 | F38: ＝ChatGPT 付費 ×（1 − 消費份額）。 | G38: Assumed（份額） | H38: 365 | I38: 735.84 | J38: =IF(H38=0,C38-H38,C38/H38-1) -> 0 | K38: =IF(I38=0,D38-I38,D38/I38-1) -> 0
B39: 需求面付費 token 合計 | C39: =3_m重算!F15/1000000 -> 3825.2 | D39: =3_m重算!H15/1000000 -> 9986.4 | E39: 兆 token/年 | F39: ＝API ＋ ChatGPT 付費。 | G39: Derived | H39: 3825.2 | I39: 9986.4 | J39: =IF(H39=0,C39-H39,C39/H39-1) -> 0 | K39: =IF(I39=0,D39-I39,D39/I39-1) -> 0
A40: L4 有效單價：Σ 層級占比 × 層級有效單價 × κ；層級有效單價 ＝ 表列牌價 × 請求形狀 ×（1 − d）× 能力倍數
B41: Luna 付費 token 占比 | C41: =3_m重算!F37 -> 0.4 | D41: =3_m重算!F37 -> 0.4 | E41: % | F41: Assumed（Cap_In 第 31 列）；2025、2026 用同一組。 | G41: Assumed | H41: 0.4 | I41: 0.4 | J41: =IF(H41=0,C41-H41,C41/H41-1) -> 0 | K41: =IF(I41=0,D41-I41,D41/I41-1) -> 0
B42: Sol 付費 token 占比 | C42: =3_m重算!G37 -> 0.45 | D42: =3_m重算!G37 -> 0.45 | E42: % | F42: Assumed（Cap_In 第 31 列）；2025、2026 用同一組。 | G42: Assumed | H42: 0.45 | I42: 0.45 | J42: =IF(H42=0,C42-H42,C42/H42-1) -> 0 | K42: =IF(I42=0,D42-I42,D42/I42-1) -> 0
B43: Astra 付費 token 占比 | C43: =3_m重算!H37 -> 0.15 | D43: =3_m重算!H37 -> 0.15 | E43: % | F43: Assumed（Cap_In 第 31 列）；2025、2026 用同一組。 | G43: Assumed | H43: 0.15 | I43: 0.15 | J43: =IF(H43=0,C43-H43,C43/H43-1) -> 0 | K43: =IF(I43=0,D43-I43,D43/I43-1) -> 0
B44: Luna 層級有效單價 | C44: =3_m重算!F38 -> 0.0828 | D44: =3_m重算!F36 -> 0.080355556 | E44: $/M token | F44: 2025＝2025 年度表列單價 ×（1 − d）。2026＝[ISL ×（（1 − χ）× 新鮮 ＋ χ × 快取）＋ OSL × 輸出] ÷（ISL ＋ OSL）×（1 − d）× 能力倍數（現值 1）。展開見 3_m重算 下方。 | G44: Derived | I44: 0.080355556 | K44: =IF(I44=0,D44-I44,D44/I44-1) -> 0
B45: Sol 層級有效單價 | C45: =3_m重算!G38 -> 1.7472 | D45: =3_m重算!G36 -> 1.6071111 | E45: $/M token | F45: 2025＝2025 年度表列單價 ×（1 − d）。2026＝[ISL ×（（1 − χ）× 新鮮 ＋ χ × 快取）＋ OSL × 輸出] ÷（ISL ＋ OSL）×（1 − d）× 能力倍數（現值 1）。展開見 3_m重算 下方。 | G45: Derived | I45: 1.6071111 | K45: =IF(I45=0,D45-I45,D45/I45-1) -> 0
B46: Astra 層級有效單價 | C46: =3_m重算!H38 -> 3.6 | D46: =3_m重算!H36 -> 8.0355556 | E46: $/M token | F46: 2025＝2025 年度表列單價 ×（1 − d）。2026＝[ISL ×（（1 − χ）× 新鮮 ＋ χ × 快取）＋ OSL × 輸出] ÷（ISL ＋ OSL）×（1 − d）× 能力倍數（現值 1）。展開見 3_m重算 下方。 | G46: Derived | I46: 8.0355556 | K46: =IF(I46=0,D46-I46,D46/I46-1) -> 0
B47: κ：請求形狀修正 | C47: =IN_Kappa -> 1 | D47: =IN_Kappa -> 1 | E47: 倍 | F47: 實際流量每 GPU 秒總 token ÷ 參考請求（Derived 0.65–1.2）；乘入混合有效單價。 | G47: Derived | H47: 1 | I47: 1 | J47: =IF(H47=0,C47-H47,C47/H47-1) -> 0 | K47: =IF(I47=0,D47-I47,D47/I47-1) -> 0
B48: → 混合有效單價 ＝ Σ 占比 × 層級單價 × κ | C48: =3_m重算!F17 -> 1.35936 | D48: =3_m重算!H17 -> 1.9606756 | E48: $/M token | F48: ＝L0 的有效牌價。 | G48: Derived | H48: 1.35936 | I48: 1.9606756 | J48: =IF(H48=0,C48-H48,C48/H48-1) -> 0 | K48: =IF(I48=0,D48-I48,D48/I48-1) -> 0
B49: 試算用 d（2_輸入 IN_DTest，可改） | C49: =IN_DTest -> 0.3 | D49: =IN_DTest -> 0.3 | E49: % | F49: 只用在下兩列；不影響其他頁。 | G49: 本簿試算
B50: d 改成試算值後的 m | C50: =3_m重算!F8*1000000000/(3_m重算!F15*(IN_Kappa*(1-IN_DTest)*(IN_MixP_L*IN_Px_L+IN_MixP_S*IN_Px_S+IN_MixP_A*IN_Px_A))) -> 2.8726248 | D50: =(IN_RevQ2*4-IN_Ad_Q2)*1000000000/((IN_APItpm26*1000000000*525600/1000000+IN_Prompts_Q2*1000000000*IN_Tau*365/1000000*(1-IN_FreeShare))*(IN_Kappa*(1-IN_DTest)*((IN_MixP_L)*IN_CapMult_L*(IN_ISL_L*((1-IN_Chi)*IN_PIn_L+IN_Chi*IN_PCache_L)+IN_OSL_L*IN_POut_L)/(IN_ISL_L+IN_OSL_L)+(IN_MixP_S)*IN_CapMult_S*(IN_ISL_S*((1-IN_Chi)*IN_PIn_S+IN_Chi*IN_PCache_S)+IN_OSL_S*IN_POut_S)/(IN_ISL_S+IN_OSL_S)+(IN_MixP_A)*IN_CapMult_A*(IN_ISL_A*((1-IN_Chi)*IN_PIn_A+IN_Chi*IN_PCache_A)+IN_OSL_A*IN_POut_A)/(IN_ISL_A+IN_OSL_A)))) -> 1.535087 | E50: 倍 | F50: 用同一組輸入、只把 d 換成試算值，整套有效單價重算（營收與 token 是觀測值，不隨 d 動）。 | G50: Derived
B51: m 變動倍數（試算 ÷ 基準） | C51: =C50/C13 -> 1.1428571 | D51: =D50/D13 -> 1.1428571 | E51: 倍 | F51: ＝(1 − 基準 d) ÷ (1 − 試算 d)。 | G51: Derived
B52: 不變的是 m ×（1 − d） | C52: =C13*(1-IN_Disc) -> 2.0108373 | D52: =D13*(1-IN_Disc) -> 1.0745609 | E52: 倍 | F52: ＝實收單價 ÷ 表列牌價。d 只是改「用哪個價當基準」，營收不變，所以不變的是實收對表列牌價的比，不是 m。 | G52: Derived
A53: L5 必須為真：m＝1（實收＝有效牌價）需要什麼（每次只動一個假設，其他不動）
B54: (a) 每則 token τ 要多大 | C54: =(3_m重算!F8*1000000000/3_m重算!F17-3_m重算!F10)/(3_m重算!F11*1000000000*365/1000000*(1-IN_FreeShare)) -> 19861.969 | D54: =(3_m重算!H8*1000000000/3_m重算!H17-3_m重算!H10)/(3_m重算!H11*1000000000*365/1000000*(1-IN_FreeShare)) -> 10520.822 | E54: token/則 | F54: 令 ChatGPT 付費 token ＝（營收 ÷ 有效單價）− API token，反解 τ。現值 4,000，Tokenomics 區間 2,000–11,000。 | G54: Derived
B55: (b) 付費 token 要多少 | C55: =3_m重算!F8*1000000000/3_m重算!F17/1000000 -> 9614.8187 | D55: =3_m重算!H8*1000000000/3_m重算!H17/1000000 -> 13413.744 | E55: 兆 token/年 | F55: ＝m 分子營收 ÷ 有效單價。 | G55: Derived
B56: 相對現有付費 token 的倍數 | C56: =C55/C8 -> 2.5135467 | D56: =D55/D8 -> 1.3432012 | E56: 倍 | F56: ＝m（因為 m ＝ 營收折算 token ÷ 實際付費 token）。 | G56: Derived
B57: (c) d 要是多少 | C57: =1-(1-IN_Disc)*C13 -> -1.0108373 | D57: =1-(1-IN_Disc)*D13 -> -0.074560924 | E57: % | F57: 令有效牌價＝實收單價，反解 d＝1 −（1 − d）× m。負值代表連不打折的表列牌價都低於實收，d 不可能解釋 m＞1。 | G57: Derived
A58: 下鑽
B59: 牌價與有效單價（L0、L4）→ 3_m重算 S10–S11 與層級單價展開表
B60: 付費 token（L3）→ 3_m重算 S4–S9
B61: 分路線 m（L2）→ 4_分路線
B62: 各輸入的區間與擺動 → 5_敏感度；要找的證據 → 6_不確定與證據
B63: 本頁每個原值與 Tokenomics 的對應 → 9_核對對照
B65: d 可調驗證（一句話） | C65: ="把 d 從 "&TEXT(IN_Disc,"0.00")&" 改成 "&TEXT(IN_DTest,"0.00")&" 重算：2026 Q2 的 m 由 "&TEXT(D13,"0.000")&" 變成 "&TEXT(D50,"0.000")&"（×"&TEXT(D50/D13,"0.000")&"）；2025 由 "&TEXT(C13,"0.000")&" 變成 "&TEXT(C50,"0.000")&"。m 會變：營收與 token 是觀測值，d 只改有效牌價的基準，所以 m 隨 1/(1 − d) 變；不變的是 m ×（1 − d）＝實收單價 ÷ 表列牌價。" -> 把 d 從 0.20 改成 0.30 重算：2026 Q2 的 m 由 1.343 變成 1.535（×1.143）；2025 由 2.514 變成 2.873。m 會變：營收與 token 是觀測值，d 只改有效牌價的基準，所以 m 隨 1/(1 − d) 變；不變的是 m ×（1 − d）＝實收單價 ÷ 表列牌價。

Sheet 2_輸入
A1: m 推導的全部輸入（藍字＝輸入值，可改；改動後 3、4、5 頁與 1A 會自動重算）
A2: 值取自 Tokenomics v21.2（20261023_Tokenomics_v21.2.xlsx，master 45ce1ca）。標記與區間取自該簿 Gov_Map 或 Cap_In 的低／高欄；「—」＝Tokenomics 無此登錄。黃底＝不確定度高且對 m 影響大（見 5_敏感度）。每格與 Tokenomics 的對應登錄在 9_核對對照。
A4: ID | B4: 群組 | C4: 項目 | D4: 值 | E4: 單位 | F4: 標記（Gov_Map／SRC） | G4: 區間低 | H4: 區間高 | I4: Tokenomics 位置 | J4: 說明與來源 | K4: 不確定度
A5: A. 營收與廣告（OpenAI；m 的分子）
A6: IN_Rev | B6: A | C6: 2025 全年營收（毛額） | D6: 13.07 | E6: $B | F6: Interested-party（SRC_DEM_007） | G6: — | H6: — | I6: SRC_DEM_007（Cap_In 以此為源） | J6: Cap_In!C69；SRC_DEM_007，2025 查核財報營收 130.7 億美元（外流、FT 核實）。2025 無廣告，分子＝營收。 | K6: 低
A7: IN_RevQ1 | B7: A | C7: 2026 Q1 季營收 | D7: 5.7 | E7: $B | F7: Interested-party（SRC_DEM_069） | G7: — | H7: — | I7: SRC_DEM_069（Cap_In 以此為源） | J7: Cap_In!D185 = 本格 × 4（年化）。The Information 2026-05-22（二手）。 | K7: 中
A8: IN_RevQ2 | B8: A | C8: 2026 Q2 季營收 | D8: 6.7 | E8: $B | F8: Interested-party（SRC_DEM_042） | G8: — | H8: — | I8: SRC_DEM_042（Cap_In 以此為源） | J8: Cap_In!E185 = 本格 × 4（年化）。WSJ 2026-08-18（經 CryptoBriefing 轉述）。主口徑 L1_M 用本格。 | K8: 中
A9: IN_RevFY | B9: A | C9: FY2026 全年營收（內部預測） | D9: 36 | E9: $B | F9: Assumed（Gov_Map GM624，單值） | G9: — | H9: — | I9: Cap_In!F185 | J9: 藍字常數 36，內部預測，不登 SRC；Tokenomics 無區間。 | K9: 中
A10: IN_Ad_Q1 | B10: A | C10: 2026 Q1 廣告營收（年化；從分子扣除） | D10: 0 | E10: $B | F10: Assumed（Gov_Map GM640） | G10: 0 | H10: 0.2 | I10: Cap_In!D186 | J10: Andy 定義：m 只看收費業務；廣告不進分子（Tokenomics J23）。2025 為 0（常數，非輸入）。 | K10: 低
A11: IN_Ad_Q2 | B11: A | C11: 2026 Q2 廣告營收（年化；從分子扣除） | D11: 0.5 | E11: $B | F11: Assumed（Gov_Map GM641） | G11: 0.3 | H11: 0.8 | I11: Cap_In!E186 | J11: 依據 SRC_DEM_072（2026-08 廣告年化達 $1B）；Q2 取 0.5。 | K11: 低
A12: IN_Ad_FY | B12: A | C12: FY2026 廣告營收（年化；從分子扣除） | D12: 1 | E12: $B | F12: Assumed（Gov_Map GM642） | G12: 0.5 | H12: 1.5 | I12: Cap_In!F186 | J12: FY2026 取 1.0。 | K12: 低
A13: B. 營收份額（只用在 4_分路線；不影響整體 m）
A14: IN_SubShare | B14: B | C14: 2025 營收中消費訂閱占比 | D14: 0.7 | E14: % | F14: Derived（N10；SRC_DEM_039 FT 約 70%） | G14: 0.61208875 | H14: 0.82 | I14: Cap_In!C70 | J14: 低端＝SRC_DEM_041（8）÷ SRC_DEM_007＝0.612；高端 0.82＝A 段 N10 區間上緣（Tokenomics 未追溯到單一 SRC）。 | K14: 中
A15: IN_SeatShare | B15: B | C15: 2025 營收中商用席次占比 | D15: 0.1 | E15: % | F15: Assumed（Gov_Map GM614） | G15: 0.05 | H15: 0.15 | I15: Cap_In!C131 | J15: 基準 0.10、區間 0.05–0.15（J18）；API 營收＝1 − 消費訂閱 − 商用席次（餘額，SRC_DEM_071 Sacra 15–20%）。 | K15: 中
A16: IN_SubShare_Q1 | B16: B | C16: 2026 Q1 營收份額：消費訂閱 | D16: 0.6 | E16: % | F16: Assumed（Gov_Map GM625，單值） | G16: — | H16: — | I16: Cap_In!D188 | J16: 2026-03 OpenAI：消費約 60%、企業 >40%（SRC_DEM_023）；Tokenomics 無區間。 | K16: 高
A17: IN_SubShare_Q2 | B17: B | C17: 2026 Q2 營收份額：消費訂閱 | D17: 0.55 | E17: % | F17: Assumed（Gov_Map GM625，單值） | G17: — | H17: — | I17: Cap_In!E188 | J17: Tokenomics 無區間。 | K17: 高
A18: IN_SubShare_FY | B18: B | C18: FY2026 營收份額：消費訂閱 | D18: 0.45 | E18: % | F18: Assumed（Gov_Map GM625，單值） | G18: — | H18: — | I18: Cap_In!F188 | J18: 企業 2026-07 超過消費、7–9 月翻倍（N05）。Tokenomics 無區間。 | K18: 高
A19: IN_SeatShare_Q1 | B19: B | C19: 2026 Q1 營收份額：商用席次 | D19: 0.2 | E19: % | F19: Assumed（Gov_Map GM626，單值） | G19: — | H19: — | I19: Cap_In!D189 | J19: 企業增量歸席次；API 份額＝餘額（各欄 0.20）。Tokenomics 無區間。 | K19: 高
A20: IN_SeatShare_Q2 | B20: B | C20: 2026 Q2 營收份額：商用席次 | D20: 0.25 | E20: % | F20: Assumed（Gov_Map GM626，單值） | G20: — | H20: — | I20: Cap_In!E189 | J20: Tokenomics 無區間。 | K20: 高
A21: IN_SeatShare_FY | B21: B | C21: FY2026 營收份額：商用席次 | D21: 0.35 | E21: % | F21: Assumed（Gov_Map GM626，單值） | G21: — | H21: — | I21: Cap_In!F189 | J21: Tokenomics 無區間。 | K21: 高
A22: C. 付費 token（m 的分母之一；免費 token 不進 m，只在算付費占比時扣除）
A23: IN_APItpm | B23: C | C23: API 處理量（2025-10 時點） | D23: 6 | E23: 十億 tok/分鐘 | F23: Interested-party（SRC_DEM_010） | G23: — | H23: — | I23: SRC_DEM_010（Cap_In 以此為源） | J23: Cap_In 以 Alloc 第 5 列使用：OpenAI 2025-10-06 公告 60 億 token／分鐘。 | K23: 低
A24: IN_APIratio | B24: C | C24: 2025 API 全年平均 ÷ 10 月時點值 | D24: 0.75 | E24: x | F24: Assumed（Gov_Map GM584） | G24: 0.6 | H24: 0.9 | I24: Alloc_In!C14 | J24: 把 10 月時點值換成全年平均（成長中，所以＜1）。 | K24: 中
A25: IN_APItpm26 | B25: C | C25: API 處理量（2026-03 時點；2026 Q1／Q2 共用） | D25: 15 | E25: 十億 tok/分鐘 | F25: Interested-party（SRC_DEM_011） | G25: — | H25: — | I25: SRC_DEM_011（Cap_In 以此為源） | J25: OpenAI 融資公告（2026-03-31）「超過」15 B tok/min；Q2 當期值已搜尋，未找到（DB_Evidence E399）。 | K25: 中
A26: IN_APImultFY | B26: C | C26: FY2026 API token ÷ 2026 Q2 時點值（年均倍數） | D26: 1.3 | E26: x | F26: Assumed（Gov_Map GM627，單值） | G26: — | H26: — | I26: Cap_In!F195 | J26: FY2026 API token＝Q2 時點值年化 × 1.3；Tokenomics 無區間。 | K26: 中
A27: IN_Prompts | B27: C | C27: 2025 ChatGPT 每日訊息數 | D27: 2.5 | E27: B 則/日 | F27: Interested-party（SRC_DEM_012） | G27: — | H27: — | I27: SRC_DEM_012（Cap_In 以此為源） | J27: OpenAI 告知 Axios（2025-07-21）：25 億則／日。 | K27: 低
A28: IN_Prompts_Q1 | B28: C | C28: 2026 Q1 ChatGPT 每日訊息數 | D28: 3.2 | E28: B 則/日 | F28: Assumed（Gov_Map GM628，單值） | G28: — | H28: — | I28: Cap_In!D197 | J28: 由週活比例放大推得；Tokenomics 無區間。 | K28: 高
A29: IN_Prompts_Q2 | B29: C | C29: 2026 Q2 ChatGPT 每日訊息數 | D29: 3.6 | E29: B 則/日 | F29: Assumed（Gov_Map GM628，單值） | G29: — | H29: — | I29: Cap_In!E197 | J29: 2.5 × 1.0 B ÷ 0.7 B 週活 ≈ 3.6；Tokenomics 無區間。主口徑 L1_M 用本格。 | K29: 高
A30: IN_Prompts_FY | B30: C | C30: FY2026 ChatGPT 每日訊息數 | D30: 3.8 | E30: B 則/日 | F30: Assumed（Gov_Map GM628，單值） | G30: — | H30: — | I30: Cap_In!F197 | J30: Tokenomics 無區間。 | K30: 高
A31: IN_Tau | B31: C | C31: 每則訊息 token 數 τ | D31: 4000 | E31: tok/則 | F31: Assumed（Gov_Map GM586） | G31: 2000 | H31: 11000 | I31: Alloc_In!C15 | J31: 含輸入、上下文、推理與輸出；無公開數字。2025、2026 共用。 | K31: 高
A32: IN_FreeShare | B32: C | C32: ChatGPT token 中免費用戶占比 | D32: 0.6 | E32: % | F32: Assumed（Gov_Map GM588） | G32: 0.4 | H32: 0.8 | I32: Alloc_In!C16 | J32: token 口徑（不是用戶數口徑，也不是支出口徑）。2025、2026 共用。 | K32: 高
A33: IN_SubTokShare | B33: C | C33: 2025 消費訂閱占 ChatGPT 付費 token 份額 | D33: 0.75 | E33: % | F33: Assumed（Gov_Map GM616） | G33: 0.6 | H33: 0.9 | I33: Cap_In!C132 | J33: 只用在 4_分路線；商用席次 token＝餘額。 | K33: 高
A34: IN_SubTokShare26 | B34: C | C34: 2026 消費訂閱占 ChatGPT 付費 token 份額 | D34: 0.65 | E34: % | F34: Assumed（Gov_Map GM643，單值） | G34: 0.5 | H34: 0.8 | I34: Cap_In!D200 | J34: 2026 三欄共用 0.65（Q2、FY 連結 Q1）；2026 企業席次增加後消費份額應低於 2025。 | K34: 高
A35: D. 牌價與有效單價（m 的分母之二）
A36: IN_PIn_L | B36: D | C36: Luna 新鮮輸入 表列牌價 | D36: 0.1 | E36: $/M | F36: Verified（SRC_PRC_003） | G36: — | H36: — | I36: Cap_In!C6 | J36: GPT-6 Luna；Standard、短上下文，2026-09-25。 | K36: 低
A37: IN_PIn_S | B37: D | C37: Sol 新鮮輸入 表列牌價 | D37: 2 | E37: $/M | F37: Verified（SRC_PRC_006） | G37: — | H37: — | I37: Cap_In!D6 | J37: GPT-6 Sol。 | K37: 低
A38: IN_PIn_A | B38: D | C38: Astra 新鮮輸入 表列牌價 | D38: 10 | E38: $/M | F38: Verified（SRC_PRC_009） | G38: — | H38: — | I38: Cap_In!E6 | J38: GPT-6 Astra。 | K38: 低
A39: IN_PCache_L | B39: D | C39: Luna 快取輸入 表列牌價 | D39: 0.01 | E39: $/M | F39: Verified（SRC_PRC_004） | G39: — | H39: — | I39: Cap_In!C7 | J39: ＝輸入價 10%。 | K39: 低
A40: IN_PCache_S | B40: D | C40: Sol 快取輸入 表列牌價 | D40: 0.2 | E40: $/M | F40: Verified（SRC_PRC_007） | G40: — | H40: — | I40: Cap_In!D7 | K40: 低
A41: IN_PCache_A | B41: D | C41: Astra 快取輸入 表列牌價 | D41: 1 | E41: $/M | F41: Verified（SRC_PRC_010） | G41: — | H41: — | I41: Cap_In!E7 | K41: 低
A42: IN_POut_L | B42: D | C42: Luna 輸出（含思考）表列牌價 | D42: 0.5 | E42: $/M | F42: Verified（SRC_PRC_005） | G42: — | H42: — | I42: Cap_In!C8 | J42: 思考 token 依輸出價計費。 | K42: 低
A43: IN_POut_S | B43: D | C43: Sol 輸出（含思考）表列牌價 | D43: 10 | E43: $/M | F43: Verified（SRC_PRC_008） | G43: — | H43: — | I43: Cap_In!D8 | K43: 低
A44: IN_POut_A | B44: D | C44: Astra 輸出（含思考）表列牌價 | D44: 50 | E44: $/M | F44: Verified（SRC_PRC_011） | G44: — | H44: — | I44: Cap_In!E8 | K44: 低
A45: IN_ISL_L | B45: D | C45: Luna 參考請求輸入長度 ISL | D45: 8192 | E45: tok | F45: Assumed（Gov_Map GM245） | G45: 4096 | H45: 16384 | I45: Serving!C23 | J45: 決定「新鮮輸入／快取輸入／輸出」三種價在混合價裡的權重。 | K45: 中
A46: IN_ISL_S | B46: D | C46: Sol 參考請求輸入長度 ISL | D46: 16384 | E46: tok | F46: Assumed（Gov_Map GM246） | G46: 8192 | H46: 68000 | I46: Serving!D23 | K46: 高
A47: IN_ISL_A | B47: D | C47: Astra 參考請求輸入長度 ISL | D47: 32768 | E47: tok | F47: Assumed（Gov_Map GM247） | G47: 16384 | H47: 68000 | I47: Serving!E23 | K47: 高
A48: IN_OSL_L | B48: D | C48: Luna 參考請求輸出長度 OSL（含思考） | D48: 1024 | E48: tok | F48: Assumed（Gov_Map GM248） | G48: 400 | H48: 2048 | I48: Serving!C24 | K48: 中
A49: IN_OSL_S | B49: D | C49: Sol 參考請求輸出長度 OSL（含思考） | D49: 2048 | E49: tok | F49: Assumed（Gov_Map GM249） | G49: 1024 | H49: 4096 | I49: Serving!D24 | K49: 高
A50: IN_OSL_A | B50: D | C50: Astra 參考請求輸出長度 OSL（含思考） | D50: 4096 | E50: tok | F50: Assumed（Gov_Map GM250） | G50: 2048 | H50: 8192 | I50: Serving!E24 | K50: 高
A51: IN_Chi | B51: D | C51: 參考請求快取命中率 χ（輸入中屬快取命中的比例） | D51: 0.55 | E51: % | F51: Assumed（Gov_Map GM443） | G51: 0.3 | H51: 0.75 | I51: Cap_In!C13 | J51: DeepSeek 2025-03 為 56.3%；2026 agent 流量約 88%。成本與營收用同一 χ。 | K51: 高
A52: IN_CapMult_L | B52: D | C52: Luna 能力單價倍數 | D52: 1 | E52: x | F52: Decision（ε＝0，Gov_Map GM445） | G52: — | H52: — | I52: Price_Frontier!C38 | J52: ＝（H_CAP × 有效訓練算力倍數）^ε；基準 ε＝0，倍數恆為 1。本簿只列原值，不展開。 | K52: 低
A53: IN_CapMult_S | B53: D | C53: Sol 能力單價倍數 | D53: 1 | E53: x | F53: Decision（ε＝0，Gov_Map GM445） | G53: — | H53: — | I53: Price_Frontier!D38 | J53: 同上。 | K53: 低
A54: IN_CapMult_A | B54: D | C54: Astra 能力單價倍數 | D54: 1 | E54: x | F54: Decision（ε＝0，Gov_Map GM445） | G54: — | H54: — | I54: Price_Frontier!E38 | J54: 同上。 | K54: 低
A55: IN_Disc | B55: D | C55: 有效折扣 d（預設折扣；Batch／Flex 半價＋企業議價，加權） | D55: 0.2 | E55: % | F55: Assumed（Gov_Map GM441） | G55: 0.1 | H55: 0.4 | I55: Cap_In!C12 | J55: 【可調輸入，不得寫死】有效牌價＝表列牌價 ×（1 − d）。Batch 半價為牌價事實，占比與企業折扣找不到（DB_Evidence E359）。 | K55: 高
A56: IN_Kappa | B56: D | C56: 請求形狀修正 κ | D56: 1 | E56: x | F56: Derived（Gov_Map GM644） | G56: 0.65 | H56: 1.2 | I56: Alloc_In!C26 | J56: 實際流量每 GPU 秒總 token ÷ 參考請求；乘入混合有效單價（Tokenomics v9.0 M3）。 | K56: 高
A57: IN_MixP_L | B57: D | C57: 付費 token 層級組合：Luna | D57: 0.4 | E57: % | F57: Assumed（Gov_Map GM457，群組） | G57: — | H57: — | I57: Cap_In!C31 | J57: OpenAI 模型 v0.5 tokenMix；三者合計須為 1。 | K57: 中
A58: IN_MixP_S | B58: D | C58: 付費 token 層級組合：Sol | D58: 0.45 | E58: % | F58: Assumed（Gov_Map GM457，群組） | G58: — | H58: — | I58: Cap_In!D31 | K58: 中
A59: IN_MixP_A | B59: D | C59: 付費 token 層級組合：Astra | D59: 0.15 | E59: % | F59: Assumed（Gov_Map GM457，群組） | G59: 0.1 | H59: 0.3 | I59: Cap_In!E31 | J59: 區間 0.10–0.30 只寫在 Gov_Map GM457 理由欄文字（v15.2 B6：Luna 與 Sol 依 0.4:0.45 補足），不是儲存格值；本簿手填。 | K59: 高
A60: IN_Px_L | B60: D | C60: 2025 年度層級單價：Luna（表列，未折扣） | D60: 0.1035 | E60: $/M | F60: Derived（Gov_Map GM665） | G60: 0.0669 | H60: 0.3026 | I60: Cap_In!C278 | J60: 參考請求混合單價，在售天數加權；只用在 2025 欄。 | K60: 低
A61: IN_Px_S | B61: D | C61: 2025 年度層級單價：Sol（表列，未折扣） | D61: 2.184 | E61: $/M | F61: Derived（Gov_Map GM667） | G61: 1.672 | H61: 2.338 | I61: Cap_In!C279 | K61: 中
A62: IN_Px_A | B62: D | C62: 2025 年度層級單價：Astra（表列，未折扣） | D62: 4.5 | E62: $/M | F62: Derived（Gov_Map GM669） | G62: 3.3 | H62: 5.9 | I62: Cap_In!C280 | J62: 用量加權（v15.2 B2），各模型 token 占比未公開。 | K62: 高
A63: E. 本簿試算用（不是 Tokenomics 的值，不影響 3、4、5 頁）
A64: IN_DTest | B64: E | C64: 試算：把 d 改成多少看 m（1A 第 L4 層使用） | D64: 0.3 | E64: % | F64: 本簿試算 | G64: — | H64: — | I64: — | J64: 預設 0.30。只用在 1A_需求公式樹 的「d 可調驗證」兩列；改它不會動其他頁。 | K64: —

Sheet 3_m重算
A1: m 的逐步重算（全部為公式；改 2_輸入 的藍字即可看到每一步怎麼變）
A2: m（付費服務 token 的有效牌價變現率）＝ 實收單價 ÷ 有效牌價 ＝ m 分子營收 ÷（需求面付費 token × 混合有效單價）。只有收入面，不經成本鏈。每一步列出對應的 Tokenomics 格與原值，最後三組欄為原值與差異。四欄＝2025 年度、2026 Q1 年化、2026 Q2 年化（主口徑）、FY2026 預測。
A4: 步驟 | B4: 項目 | C4: 白話說明與公式 | D4: 單位 | E4: 原活頁簿位置 | F4: 值 2025 | G4: 值 2026 Q1 | H4: 值 2026 Q2 | I4: 值 FY2026 | J4: Tokenomics 原值 2025 | K4: Tokenomics 原值 2026 Q1 | L4: Tokenomics 原值 2026 Q2 | M4: Tokenomics 原值 FY2026 | N4: 差異 2025 | O4: 差異 2026 Q1 | P4: 差異 2026 Q2 | Q4: 差異 FY2026
A5: 第 A 組：分子——m 分子營收（營收 − 廣告）
A6: S1 | B6: 營收（年化） | C6: 2025＝全年營收；2026 Q1／Q2＝季營收 × 4；FY2026＝內部預測。毛額，不扣 Microsoft 分潤。 | D6: $B | E6: Cap_In 第 69 列 C；第 185 列 D–F | F6: =IN_Rev -> 13.07 | G6: =IN_RevQ1*4 -> 22.8 | H6: =IN_RevQ2*4 -> 26.8 | I6: =IN_RevFY -> 36 | J6: 13.07 | K6: 22.8 | L6: 26.8 | M6: 36 | N6: =IF(J6=0,F6-J6,F6/J6-1) -> 0 | O6: =IF(K6=0,G6-K6,G6/K6-1) -> 0 | P6: =IF(L6=0,H6-L6,H6/L6-1) -> 0 | Q6: =IF(M6=0,I6-M6,I6/M6-1) -> 0
A7: S2 | B7: 廣告營收（年化） | C7: Andy 定義：m 單純看收費業務，廣告不進分子。2025 沒有廣告（Tokenomics 的常數 0）。 | D7: $B | E7: Cap_In 第 186 列 C–F | F7: 0 | G7: =IN_Ad_Q1 -> 0 | H7: =IN_Ad_Q2 -> 0.5 | I7: =IN_Ad_FY -> 1 | J7: 0 | K7: 0 | L7: 0.5 | M7: 1 | N7: =IF(J7=0,F7-J7,F7/J7-1) -> 0 | O7: =IF(K7=0,G7-K7,G7/K7-1) -> 0 | P7: =IF(L7=0,H7-L7,H7/L7-1) -> 0 | Q7: =IF(M7=0,I7-M7,I7/M7-1) -> 0
A8: S3 | B8: m 分子營收 | C8: ＝S1 − S2。這是「付費服務實際收到的錢」。 | D8: $B | E8: Cap_In 第 187 列 D–F（2025 為第 69 列） | F8: =F6-F7 -> 13.07 | G8: =G6-G7 -> 22.8 | H8: =H6-H7 -> 26.3 | I8: =I6-I7 -> 35 | J8: 13.07 | K8: 22.8 | L8: 26.3 | M8: 35 | N8: =IF(J8=0,F8-J8,F8/J8-1) -> 0 | O8: =IF(K8=0,G8-K8,G8/K8-1) -> 0 | P8: =IF(L8=0,H8-L8,H8/L8-1) -> 0 | Q8: =IF(M8=0,I8-M8,I8/M8-1) -> 0
A9: 第 B 組：分母之一——需求面付費 token（API ＋ ChatGPT 付費；免費不進 m）
A10: S4 | B10: API token（全年） | C10: 2025＝每分鐘 token × 525,600 分鐘 × 全年平均比例；2026 Q1／Q2＝2026-03 時點值 × 525,600（不打折）；FY2026＝Q2 × 年均倍數 1.3。 | D10: M tok/年 | E10: Alloc 第 5 列（AL_DAPI）；Cap_In 第 196 列 | F10: =IN_APItpm*1000000000*525600*IN_APIratio/1000000 -> 2365200000 | G10: =IN_APItpm26*1000000000*525600/1000000 -> 7884000000 | H10: =IN_APItpm26*1000000000*525600/1000000 -> 7884000000 | I10: =H10*IN_APImultFY -> 10249200000 | J10: 2365200000 | K10: 7884000000 | L10: 7884000000 | M10: 10249200000 | N10: =IF(J10=0,F10-J10,F10/J10-1) -> 0 | O10: =IF(K10=0,G10-K10,G10/K10-1) -> 0 | P10: =IF(L10=0,H10-L10,H10/L10-1) -> 0 | Q10: =IF(M10=0,I10-M10,I10/M10-1) -> 0
A11: S5 | B11: ChatGPT 每日訊息數 | C11: 2025 取 OpenAI 自述 25 億；2026 由週活比例放大（Assumed）。 | D11: B 則/日 | E11: SRC_DEM_012；Cap_In 第 197 列 | F11: =IN_Prompts -> 2.5 | G11: =IN_Prompts_Q1 -> 3.2 | H11: =IN_Prompts_Q2 -> 3.6 | I11: =IN_Prompts_FY -> 3.8 | J11: 2.5 | K11: 3.2 | L11: 3.6 | M11: 3.8 | N11: =IF(J11=0,F11-J11,F11/J11-1) -> 0 | O11: =IF(K11=0,G11-K11,G11/K11-1) -> 0 | P11: =IF(L11=0,H11-L11,H11/L11-1) -> 0 | Q11: =IF(M11=0,I11-M11,I11/M11-1) -> 0
A12: S6 | B12: ChatGPT token 總量（含免費） | C12: ＝每日訊息數 × 10⁹ × 每則 token τ × 365 ÷ 10⁶。τ 沒有公開數字（Assumed 4,000）。 | D12: M tok/年 | E12: Alloc 第 6 列；Cap_In 第 198＋199 列 | F12: =F11*1000000000*IN_Tau*365/1000000 -> 3650000000 | G12: =G11*1000000000*IN_Tau*365/1000000 -> 4672000000 | H12: =H11*1000000000*IN_Tau*365/1000000 -> 5256000000 | I12: =I11*1000000000*IN_Tau*365/1000000 -> 5548000000 | J12: 3650000000 | K12: 4672000000 | L12: 5256000000 | M12: 5548000000 | N12: =IF(J12=0,F12-J12,F12/J12-1) -> 0 | O12: =IF(K12=0,G12-K12,G12/K12-1) -> 0 | P12: =IF(L12=0,H12-L12,H12/L12-1) -> 0 | Q12: =IF(M12=0,I12-M12,I12/M12-1) -> 0
A13: S7 | B13: ChatGPT 免費 token | C13: ＝S6 × 免費占比。這部分不產生營收，計入管理費用，不進 m（Andy 10-21 14:37）；這裡只是為了從總量扣掉。 | D13: M tok/年 | E13: Alloc 第 7 列；Cap_In 第 199 列 | F13: =F12*IN_FreeShare -> 2190000000 | G13: =G12*IN_FreeShare -> 2803200000 | H13: =H12*IN_FreeShare -> 3153600000 | I13: =I12*IN_FreeShare -> 3328800000 | J13: 2190000000 | K13: 2803200000 | L13: 3153600000 | M13: 3328800000 | N13: =IF(J13=0,F13-J13,F13/J13-1) -> 0 | O13: =IF(K13=0,G13-K13,G13/K13-1) -> 0 | P13: =IF(L13=0,H13-L13,H13/L13-1) -> 0 | Q13: =IF(M13=0,I13-M13,I13/M13-1) -> 0
A14: S8 | B14: ChatGPT 付費 token | C14: ＝S6 − S7＝S6 ×（1 − 免費占比）。 | D14: M tok/年 | E14: Alloc 第 8 列；Cap_In 第 198 列 | F14: =F12-F13 -> 1460000000 | G14: =G12-G13 -> 1868800000 | H14: =H12-H13 -> 2102400000 | I14: =I12-I13 -> 2219200000 | J14: 1460000000 | K14: 1868800000 | L14: 2102400000 | M14: 2219200000 | N14: =IF(J14=0,F14-J14,F14/J14-1) -> 0 | O14: =IF(K14=0,G14-K14,G14/K14-1) -> 0 | P14: =IF(L14=0,H14-L14,H14/L14-1) -> 0 | Q14: =IF(M14=0,I14-M14,I14/M14-1) -> 0
A15: S9 | B15: 需求面付費 token 合計 | C15: ＝S4 ＋ S8。m 的分母用的 token 數量。 | D15: M tok/年 | E15: Cap_In 第 83 列 C；第 196＋198 列 | F15: =F10+F14 -> 3825200000 | G15: =G10+G14 -> 9752800000 | H15: =H10+H14 -> 9986400000 | I15: =I10+I14 -> 12468400000 | J15: 3825200000 | K15: 9752800000 | L15: 9986400000 | M15: 12468400000 | N15: =IF(J15=0,F15-J15,F15/J15-1) -> 0 | O15: =IF(K15=0,G15-K15,G15/K15-1) -> 0 | P15: =IF(L15=0,H15-L15,H15/L15-1) -> 0 | Q15: =IF(M15=0,I15-M15,I15/M15-1) -> 0
A16: 第 C 組：分母之二——混合有效單價（有效牌價；細節見本頁下方「層級單價展開表」）
A17: S10 | B17: 付費 token 混合有效單價 | C17: ＝Σ（層級占比 × 層級有效單價）× κ。2025 的層級有效單價＝2025 年度表列單價 ×（1 − d）；2026 的層級有效單價＝IF_PriceRef（表列牌價 × 請求形狀 ×（1 − d）× 能力倍數）。 | D17: $/M tok | E17: CAP_Price25Mix（Cap_In C281）；Cap_In 第 205 列 | F17: =(F37*F38+G37*G38+H37*H38)*IN_Kappa -> 1.35936 | G17: =(F37*F36+G37*G36+H37*H36)*IN_Kappa -> 1.9606756 | H17: =(F37*F36+G37*G36+H37*H36)*IN_Kappa -> 1.9606756 | I17: =(F37*F36+G37*G36+H37*H36)*IN_Kappa -> 1.9606756 | J17: 1.35936 | K17: 1.9606756 | L17: 1.9606756 | M17: 1.9606756 | N17: =IF(J17=0,F17-J17,F17/J17-1) -> 0 | O17: =IF(K17=0,G17-K17,G17/K17-1) -> 0 | P17: =IF(L17=0,H17-L17,H17/L17-1) -> 0 | Q17: =IF(M17=0,I17-M17,I17/M17-1) -> 0
A18: S11 | B18: 混合表列牌價（未折扣） | C18: ＝S10 ÷（1 − d）。與 d 無關：d 變動時有效單價同比例變動，表列牌價不動。2025 欄 Tokenomics 沒有對應名稱。 | D18: $/M tok | E18: L1_PxList_2026（L1 D126） | F18: =F17/(1-IN_Disc) -> 1.6992 | G18: =G17/(1-IN_Disc) -> 2.4508444 | H18: =H17/(1-IN_Disc) -> 2.4508444 | I18: =I17/(1-IN_Disc) -> 2.4508444 | K18: 2.4508444 | L18: 2.4508444 | M18: 2.4508444 | O18: =IF(K18=0,G18-K18,G18/K18-1) -> 0 | P18: =IF(L18=0,H18-L18,H18/L18-1) -> 0 | Q18: =IF(M18=0,I18-M18,I18/M18-1) -> 0
A19: 第 D 組：m ＝ 實收單價 ÷ 有效牌價
A20: S12 | B20: 實收單價（每百萬付費 token 實收） | C20: ＝S3 × 10⁹ ÷ S9。付費服務每賣出 100 萬個 token，實際收到多少錢。Tokenomics 沒有這一格，本簿新增。 | D20: $/M tok | E20: （本簿新增） | F20: =F8*1000000000/F15 -> 3.4168148 | G20: =G8*1000000000/G15 -> 2.3377902 | H20: =H8*1000000000/H15 -> 2.6335817 | I20: =I8*1000000000/I15 -> 2.8070963
A21: S13 | B21: m（付費 token 的有效牌價變現率） | C21: ＝S12 ÷ S10。m＞1：實收高於有效牌價（訂閱定額月費遠超用量的牌價等值）；m＜1：實收低於有效牌價。 | D21: x | E21: Cap_In 第 209 列 C–F（m_整體） | F21: =F20/F17 -> 2.5135467 | G21: =G20/G17 -> 1.1923391 | H21: =H20/H17 -> 1.3432012 | I21: =I20/I17 -> 1.4316985 | J21: 2.5135467 | K21: 1.1923391 | L21: 1.3432012 | M21: 1.4316985 | N21: =IF(J21=0,F21-J21,F21/J21-1) -> 0 | O21: =IF(K21=0,G21-K21,G21/K21-1) -> 0 | P21: =IF(L21=0,H21-L21,H21/L21-1) -> 0 | Q21: =IF(M21=0,I21-M21,I21/M21-1) -> 0
A22: S14 | B22: 檢查：另一種寫法的 m | C22: ＝S3 × 10⁹ ÷（S9 × S10）。應與 S13 完全相同（恆等式）。 | D22: x | F22: =F8*1000000000/(F15*F17) -> 2.5135467 | G22: =G8*1000000000/(G15*G17) -> 1.1923391 | H22: =H8*1000000000/(H15*H17) -> 1.3432012 | I22: =I8*1000000000/(I15*I17) -> 1.4316985
A23: L1 | B23: 對照 L1 名稱 L1_M_2025／_2026Q1／_2026Q2／_FY2026 | C23: Tokenomics 的 L1 頁輸出名稱（下游契約）；與 S13 同值。 | D23: x | E23: L1 D117、D118、D119、D120 | F23: =F21 -> 2.5135467 | G23: =G21 -> 1.1923391 | H23: =H21 -> 1.3432012 | I23: =I21 -> 1.4316985 | J23: 2.5135467 | K23: 1.1923391 | L23: 1.3432012 | M23: 1.4316985 | N23: =IF(J23=0,F23-J23,F23/J23-1) -> 0 | O23: =IF(K23=0,G23-K23,G23/K23-1) -> 0 | P23: =IF(L23=0,H23-L23,H23/L23-1) -> 0 | Q23: =IF(M23=0,I23-M23,I23/M23-1) -> 0
A24: L2 | B24: 主口徑 L1_M（＝2026 Q2） | C24: Tokenomics 的主口徑 m＝2026 Q2 年化（J1）；FY2026 待 Andy 提供「市場預估 360 億」出處再議。 | D24: x | E24: L1 D121 | H24: =H21 -> 1.3432012 | L24: 1.3432012 | P24: =IF(L24=0,H24-L24,H24/L24-1) -> 0
A25: 層級單價展開表（S10 的細項；欄 F／G／H＝Luna／Sol／Astra，不是期間）
A26: T1 | B26: 新鮮輸入 表列牌價 | C26: 輸入：OpenAI 官方牌價（2_輸入 D 組）。 | D26: $/M | E26: Cap_In 第 6 列 C–E | F26: =IN_PIn_L -> 0.1 | G26: =IN_PIn_S -> 2 | H26: =IN_PIn_A -> 10 | J26: 0.1 | K26: 2 | L26: 10 | N26: =IF(J26=0,F26-J26,F26/J26-1) -> 0 | O26: =IF(K26=0,G26-K26,G26/K26-1) -> 0 | P26: =IF(L26=0,H26-L26,H26/L26-1) -> 0
A27: T2 | B27: 快取輸入 表列牌價 | C27: 輸入。 | D27: $/M | E27: Cap_In 第 7 列 C–E | F27: =IN_PCache_L -> 0.01 | G27: =IN_PCache_S -> 0.2 | H27: =IN_PCache_A -> 1 | J27: 0.01 | K27: 0.2 | L27: 1 | N27: =IF(J27=0,F27-J27,F27/J27-1) -> 0 | O27: =IF(K27=0,G27-K27,G27/K27-1) -> 0 | P27: =IF(L27=0,H27-L27,H27/L27-1) -> 0
A28: T3 | B28: 輸出（含思考）表列牌價 | C28: 輸入。思考 token 依輸出價計費。 | D28: $/M | E28: Cap_In 第 8 列 C–E | F28: =IN_POut_L -> 0.5 | G28: =IN_POut_S -> 10 | H28: =IN_POut_A -> 50 | J28: 0.5 | K28: 10 | L28: 50 | N28: =IF(J28=0,F28-J28,F28/J28-1) -> 0 | O28: =IF(K28=0,G28-K28,G28/K28-1) -> 0 | P28: =IF(L28=0,H28-L28,H28/L28-1) -> 0
A29: T4 | B29: 能力單價倍數 | C29: ＝（H_CAP × 有效訓練算力倍數）^ε。基準 ε＝0，所以恆為 1（本簿只列原值，不展開）。 | D29: x | E29: Price_Frontier 第 38 列 C–E | F29: =IN_CapMult_L -> 1 | G29: =IN_CapMult_S -> 1 | H29: =IN_CapMult_A -> 1 | J29: 1 | K29: 1 | L29: 1 | N29: =IF(J29=0,F29-J29,F29/J29-1) -> 0 | O29: =IF(K29=0,G29-K29,G29/K29-1) -> 0 | P29: =IF(L29=0,H29-L29,H29/L29-1) -> 0
A30: T5 | B30: 參考請求輸入長度 ISL | C30: 輸入。 | D30: tok | E30: Serving 第 23 列 C–E | F30: =IN_ISL_L -> 8192 | G30: =IN_ISL_S -> 16384 | H30: =IN_ISL_A -> 32768 | J30: 8192 | K30: 16384 | L30: 32768 | N30: =IF(J30=0,F30-J30,F30/J30-1) -> 0 | O30: =IF(K30=0,G30-K30,G30/K30-1) -> 0 | P30: =IF(L30=0,H30-L30,H30/L30-1) -> 0
A31: T6 | B31: 參考請求輸出長度 OSL（含思考） | C31: 輸入。 | D31: tok | E31: Serving 第 24 列 C–E | F31: =IN_OSL_L -> 1024 | G31: =IN_OSL_S -> 2048 | H31: =IN_OSL_A -> 4096 | J31: 1024 | K31: 2048 | L31: 4096 | N31: =IF(J31=0,F31-J31,F31/J31-1) -> 0 | O31: =IF(K31=0,G31-K31,G31/K31-1) -> 0 | P31: =IF(L31=0,H31-L31,H31/L31-1) -> 0
A32: T7 | B32: 快取命中率 χ | C32: 輸入（三層共用）。 | D32: % | E32: Cap_In C13 | F32: =IN_Chi -> 0.55 | G32: =IN_Chi -> 0.55 | H32: =IN_Chi -> 0.55 | J32: 0.55 | K32: 0.55 | L32: 0.55 | N32: =IF(J32=0,F32-J32,F32/J32-1) -> 0 | O32: =IF(K32=0,G32-K32,G32/K32-1) -> 0 | P32: =IF(L32=0,H32-L32,H32/L32-1) -> 0
A33: T8 | B33: 新鮮輸入 有效價 | C33: ＝T1 ×（1 − d）× T4。 | D33: $/M | E33: Price_Frontier 第 41 列 C–E | F33: =F26*(1-IN_Disc)*F29 -> 0.08 | G33: =G26*(1-IN_Disc)*G29 -> 1.6 | H33: =H26*(1-IN_Disc)*H29 -> 8 | J33: 0.08 | K33: 1.6 | L33: 8 | N33: =IF(J33=0,F33-J33,F33/J33-1) -> 0 | O33: =IF(K33=0,G33-K33,G33/K33-1) -> 0 | P33: =IF(L33=0,H33-L33,H33/L33-1) -> 0
A34: T9 | B34: 快取輸入 有效價 | C34: ＝T2 ×（1 − d）× T4。 | D34: $/M | E34: Price_Frontier 第 42 列 C–E | F34: =F27*(1-IN_Disc)*F29 -> 0.008 | G34: =G27*(1-IN_Disc)*G29 -> 0.16 | H34: =H27*(1-IN_Disc)*H29 -> 0.8 | J34: 0.008 | K34: 0.16 | L34: 0.8 | N34: =IF(J34=0,F34-J34,F34/J34-1) -> 0 | O34: =IF(K34=0,G34-K34,G34/K34-1) -> 0 | P34: =IF(L34=0,H34-L34,H34/L34-1) -> 0
A35: T10 | B35: 輸出 有效價 | C35: ＝T3 ×（1 − d）× T4。 | D35: $/M | E35: Price_Frontier 第 44 列 C–E | F35: =F28*(1-IN_Disc)*F29 -> 0.4 | G35: =G28*(1-IN_Disc)*G29 -> 8 | H35: =H28*(1-IN_Disc)*H29 -> 40 | J35: 0.4 | K35: 8 | L35: 40 | N35: =IF(J35=0,F35-J35,F35/J35-1) -> 0 | O35: =IF(K35=0,G35-K35,G35/K35-1) -> 0 | P35: =IF(L35=0,H35-L35,H35/L35-1) -> 0
A36: T11 | B36: 參考請求混合有效價（IF_PriceRef_*） | C36: ＝[ISL ×（（1 − χ）× T8 ＋ χ × T9）＋ OSL × T10] ÷（ISL ＋ OSL）。每 1 個 token（輸入加輸出）的平均有效價。 | D36: $/M | E36: Price_Frontier 第 45 列；IF_PriceRef_Luna／Sol／Astra | F36: =(F30*((1-F32)*F33+F32*F34)+F31*F35)/(F30+F31) -> 0.080355556 | G36: =(G30*((1-G32)*G33+G32*G34)+G31*G35)/(G30+G31) -> 1.6071111 | H36: =(H30*((1-H32)*H33+H32*H34)+H31*H35)/(H30+H31) -> 8.0355556 | J36: 0.080355556 | K36: 1.6071111 | L36: 8.0355556 | N36: =IF(J36=0,F36-J36,F36/J36-1) -> 0 | O36: =IF(K36=0,G36-K36,G36/K36-1) -> 0 | P36: =IF(L36=0,H36-L36,H36/L36-1) -> 0
A37: T12 | B37: 付費 token 層級占比 | C37: 輸入（Assumed）。三者合計＝1。 | D37: % | E37: Cap_In 第 31 列 C–E（B4_MixPaid） | F37: =IN_MixP_L -> 0.4 | G37: =IN_MixP_S -> 0.45 | H37: =IN_MixP_A -> 0.15 | J37: 0.4 | K37: 0.45 | L37: 0.15 | N37: =IF(J37=0,F37-J37,F37/J37-1) -> 0 | O37: =IF(K37=0,G37-K37,G37/K37-1) -> 0 | P37: =IF(L37=0,H37-L37,H37/L37-1) -> 0
A38: T13 | B38: 2025 層級有效單價 | C38: ＝2025 年度層級表列單價（輸入）×（1 − d）。2025 不再乘能力倍數（2025 價格對應 2025 年的模型）。S10 的 2025 欄用本列。 | D38: $/M | E38: Cap_In 第 278–280 列 C（表列） | F38: =IN_Px_L*(1-IN_Disc) -> 0.0828 | G38: =IN_Px_S*(1-IN_Disc) -> 1.7472 | H38: =IN_Px_A*(1-IN_Disc) -> 3.6
A39: T14 | B39: 其中 2025 年度層級單價（表列，未折扣） | C39: 輸入的原值。 | D39: $/M | E39: Cap_In 第 278–280 列 C | F39: =IN_Px_L -> 0.1035 | G39: =IN_Px_S -> 2.184 | H39: =IN_Px_A -> 4.5 | J39: 0.1035 | K39: 2.184 | L39: 4.5 | N39: =IF(J39=0,F39-J39,F39/J39-1) -> 0 | O39: =IF(K39=0,G39-K39,G39/K39-1) -> 0 | P39: =IF(L39=0,H39-L39,H39/L39-1) -> 0
A41: 步驟 | B41: 項目 | C41: 白話說明與公式 | D41: 單位 | E41: 原活頁簿位置 | F41: 值 2025 低端 | G41: 值 2025 高端 | H41: 值 2026 Q2 低端 | I41: 值 2026 Q2 高端 | J41: Tokenomics 原值 2025 低端 | K41: 2025 高端 | L41: 2026 Q2 低端 | M41: 2026 Q2 高端 | N41: 差異 2025 低端 | O41: 2025 高端 | P41: 2026 Q2 低端 | Q41: 2026 Q2 高端
A42: 區間端點（低端＝token 取高、m 取低；高端＝token 取低、m 取高。營收與單價取基準，價格區間不交——與 Tokenomics 寫法相同）
A43: E1 | B43: 每則 token τ | C43: 低端取區間上緣（τ 大→付費 token 多→m 小）；高端取下緣。 | D43: tok | E43: Alloc_In D15／E15 | F43: =IN_Tau_Hi -> 11000 | G43: =IN_Tau_Lo -> 2000 | H43: =IN_Tau_Hi -> 11000 | I43: =IN_Tau_Lo -> 2000 | J43: 11000 | K43: 2000 | L43: 11000 | M43: 2000 | N43: =IF(J43=0,F43-J43,F43/J43-1) -> 0 | O43: =IF(K43=0,G43-K43,G43/K43-1) -> 0 | P43: =IF(L43=0,H43-L43,H43/L43-1) -> 0 | Q43: =IF(M43=0,I43-M43,I43/M43-1) -> 0
A44: E2 | B44: ChatGPT 免費占比 | C44: 低端取區間下緣（免費少→付費 token 多）；高端取上緣。 | D44: % | E44: Alloc_In D16／E16 | F44: =IN_FreeShare_Lo -> 0.4 | G44: =IN_FreeShare_Hi -> 0.8 | H44: =IN_FreeShare_Lo -> 0.4 | I44: =IN_FreeShare_Hi -> 0.8 | J44: 0.4 | K44: 0.8 | L44: 0.4 | M44: 0.8 | N44: =IF(J44=0,F44-J44,F44/J44-1) -> 0 | O44: =IF(K44=0,G44-K44,G44/K44-1) -> 0 | P44: =IF(L44=0,H44-L44,H44/L44-1) -> 0 | Q44: =IF(M44=0,I44-M44,I44/M44-1) -> 0
A45: E3 | B45: API 全年平均比例（只 2025） | C45: 低端取上緣、高端取下緣；2026 欄用時點值，不適用。 | D45: x | E45: Alloc_In D14／E14 | F45: =IN_APIratio_Hi -> 0.9 | G45: =IN_APIratio_Lo -> 0.6 | J45: 0.9 | K45: 0.6 | N45: =IF(J45=0,F45-J45,F45/J45-1) -> 0 | O45: =IF(K45=0,G45-K45,G45/K45-1) -> 0
A46: E4 | B46: API token | C46: 2025 依 E3 重算；2026 Q2 與基準相同。 | D46: M tok/年 | E46: Cap_In 第 82 列 D／E | F46: =IN_APItpm*1000000000*525600*F45/1000000 -> 2838240000 | G46: =IN_APItpm*1000000000*525600*G45/1000000 -> 1892160000 | H46: =$H$10 -> 7884000000 | I46: =$H$10 -> 7884000000 | J46: 2838240000 | K46: 1892160000 | N46: =IF(J46=0,F46-J46,F46/J46-1) -> 0 | O46: =IF(K46=0,G46-K46,G46/K46-1) -> 0
A47: E5 | B47: ChatGPT 付費 token | C47: ＝每日訊息數 × 10⁹ × τ × 365 ÷ 10⁶ ×（1 − 免費占比），用端點的 τ 與免費占比。 | D47: M tok/年 | E47: Cap_In 第 81 列 D／E | F47: =IN_Prompts*1000000000*F43*365/1000000*(1-F44) -> 6022500000 | G47: =IN_Prompts*1000000000*G43*365/1000000*(1-G44) -> 365000000 | H47: =IN_Prompts_Q2*1000000000*H43*365/1000000*(1-H44) -> 8672400000 | I47: =IN_Prompts_Q2*1000000000*I43*365/1000000*(1-I44) -> 525600000 | J47: 6022500000 | K47: 365000000 | N47: =IF(J47=0,F47-J47,F47/J47-1) -> 0 | O47: =IF(K47=0,G47-K47,G47/K47-1) -> 0
A48: E6 | B48: 需求面付費 token 合計 | C48: ＝E4 ＋ E5。 | D48: M tok/年 | E48: Cap_In 第 83 列 D／E | F48: =F46+F47 -> 8860740000 | G48: =G46+G47 -> 2257160000 | H48: =H46+H47 -> 16556400000 | I48: =I46+I47 -> 8409600000 | J48: 8860740000 | K48: 2257160000 | N48: =IF(J48=0,F48-J48,F48/J48-1) -> 0 | O48: =IF(K48=0,G48-K48,G48/K48-1) -> 0
A49: E7 | B49: m 分子營收（取基準） | C49: 連結 S3。 | D49: $B | F49: =$F$8 -> 13.07 | G49: =$F$8 -> 13.07 | H49: =$H$8 -> 26.3 | I49: =$H$8 -> 26.3
A50: E8 | B50: 混合有效單價（取基準） | C50: 連結 S10。 | D50: $/M tok | F50: =$F$17 -> 1.35936 | G50: =$F$17 -> 1.35936 | H50: =$H$17 -> 1.9606756 | I50: =$H$17 -> 1.9606756
A51: E9 | B51: m 端點 | C51: ＝E7 × 10⁹ ÷（E6 × E8）。 | D51: x | E51: L1_M_2025_Lo／_Hi（L1 E117／F117）；L1_M_2026Q2_Lo／_Hi（L1 E119／F119） | F51: =F49*1000000000/(F48*F50) -> 1.0851034 | G51: =G49*1000000000/(G48*G50) -> 4.2596975 | H51: =H49*1000000000/(H48*H50) -> 0.81018482 | I51: =I49*1000000000/(I48*I50) -> 1.5950514 | J51: 1.0851034 | K51: 4.2596975 | L51: 0.81018482 | M51: 1.5950514 | N51: =IF(J51=0,F51-J51,F51/J51-1) -> 0 | O51: =IF(K51=0,G51-K51,G51/K51-1) -> 0 | P51: =IF(L51=0,H51-L51,H51/L51-1) -> 0 | Q51: =IF(M51=0,I51-M51,I51/M51-1) -> 0

Sheet 4_分路線
A1: m 按收費模式拆開：API／消費訂閱／商用席次（營收三分 × token 三分）
A2: 每條路線的 m＝該路線營收 ÷（該路線 token × 混合有效單價）。三條路線共用同一個有效單價，所以差別全在「每個 token 實收多少」。主口徑看 2026 Q2 欄；2025 欄取 Tokenomics 的 2025 三分法。營收份額與消費訂閱 token 份額是 Assumed，只影響分路線，不影響整體 m。
A4: 步驟 | B4: 項目 | C4: 白話說明與公式 | D4: 單位 | E4: 原活頁簿位置 | F4: 值 2025 | G4: 值 2026 Q1 | H4: 值 2026 Q2 | I4: 值 FY2026 | J4: Tokenomics 原值 2025 | K4: Tokenomics 原值 2026 Q1 | L4: Tokenomics 原值 2026 Q2 | M4: Tokenomics 原值 FY2026 | N4: 差異 2025 | O4: 差異 2026 Q1 | P4: 差異 2026 Q2 | Q4: 差異 FY2026
A5: 營收三分（$B）
A6: R1 | B6: m 分子營收 | C6: 連結 3_m重算 S3。 | D6: $B | E6: Cap_In 第 69 列 C；第 187 列 D–F | F6: =3_m重算!F8 -> 13.07 | G6: =3_m重算!G8 -> 22.8 | H6: =3_m重算!H8 -> 26.3 | I6: =3_m重算!I8 -> 35 | J6: 13.07 | K6: 22.8 | L6: 26.3 | M6: 35 | N6: =IF(J6=0,F6-J6,F6/J6-1) -> 0 | O6: =IF(K6=0,G6-K6,G6/K6-1) -> 0 | P6: =IF(L6=0,H6-L6,H6/L6-1) -> 0 | Q6: =IF(M6=0,I6-M6,I6/M6-1) -> 0
A7: R2 | B7: 營收份額：消費訂閱 | C7: 輸入。2025 約 70%（FT）；2026 逐期下降（企業成長）。 | D7: % | E7: Cap_In C70；第 188 列 D–F | F7: =IN_SubShare -> 0.7 | G7: =IN_SubShare_Q1 -> 0.6 | H7: =IN_SubShare_Q2 -> 0.55 | I7: =IN_SubShare_FY -> 0.45 | J7: 0.7 | K7: 0.6 | L7: 0.55 | M7: 0.45 | N7: =IF(J7=0,F7-J7,F7/J7-1) -> 0 | O7: =IF(K7=0,G7-K7,G7/K7-1) -> 0 | P7: =IF(L7=0,H7-L7,H7/L7-1) -> 0 | Q7: =IF(M7=0,I7-M7,I7/M7-1) -> 0
A8: R3 | B8: 營收份額：商用席次 | C8: 輸入（Assumed）。 | D8: % | E8: Cap_In C131；第 189 列 D–F | F8: =IN_SeatShare -> 0.1 | G8: =IN_SeatShare_Q1 -> 0.2 | H8: =IN_SeatShare_Q2 -> 0.25 | I8: =IN_SeatShare_FY -> 0.35 | J8: 0.1 | K8: 0.2 | L8: 0.25 | M8: 0.35 | N8: =IF(J8=0,F8-J8,F8/J8-1) -> 0 | O8: =IF(K8=0,G8-K8,G8/K8-1) -> 0 | P8: =IF(L8=0,H8-L8,H8/L8-1) -> 0 | Q8: =IF(M8=0,I8-M8,I8/M8-1) -> 0
A9: R4 | B9: 營收份額：API | C9: ＝1 − 消費訂閱 − 商用席次（餘額；前兩項的誤差全落在這裡）。 | D9: % | E9: Cap_In C137÷C69；第 190 列 D–F | F9: =1-F7-F8 -> 0.2 | G9: =1-G7-G8 -> 0.2 | H9: =1-H7-H8 -> 0.2 | I9: =1-I7-I8 -> 0.2 | J9: 0.2 | K9: 0.2 | L9: 0.2 | M9: 0.2 | N9: =IF(J9=0,F9-J9,F9/J9-1) -> 0 | O9: =IF(K9=0,G9-K9,G9/K9-1) -> 0 | P9: =IF(L9=0,H9-L9,H9/L9-1) -> 0 | Q9: =IF(M9=0,I9-M9,I9/M9-1) -> 0
A10: R5 | B10: 消費訂閱營收 | C10: ＝R1 × R2。 | D10: $B | E10: Cap_In 第 135 列 C；第 191 列 D–F | F10: =F6*F7 -> 9.149 | G10: =G6*G7 -> 13.68 | H10: =H6*H7 -> 14.465 | I10: =I6*I7 -> 15.75 | J10: 9.149 | K10: 13.68 | L10: 14.465 | M10: 15.75 | N10: =IF(J10=0,F10-J10,F10/J10-1) -> 0 | O10: =IF(K10=0,G10-K10,G10/K10-1) -> 0 | P10: =IF(L10=0,H10-L10,H10/L10-1) -> 0 | Q10: =IF(M10=0,I10-M10,I10/M10-1) -> 0
A11: R6 | B11: 商用席次營收 | C11: ＝R1 × R3。 | D11: $B | E11: Cap_In 第 136 列 C；第 192 列 D–F | F11: =F6*F8 -> 1.307 | G11: =G6*G8 -> 4.56 | H11: =H6*H8 -> 6.575 | I11: =I6*I8 -> 12.25 | J11: 1.307 | K11: 4.56 | L11: 6.575 | M11: 12.25 | N11: =IF(J11=0,F11-J11,F11/J11-1) -> 0 | O11: =IF(K11=0,G11-K11,G11/K11-1) -> 0 | P11: =IF(L11=0,H11-L11,H11/L11-1) -> 0 | Q11: =IF(M11=0,I11-M11,I11/M11-1) -> 0
A12: R7 | B12: API 營收 | C12: ＝R1 × R4。 | D12: $B | E12: Cap_In 第 137 列 C；第 193 列 D–F | F12: =F6*F9 -> 2.614 | G12: =G6*G9 -> 4.56 | H12: =H6*H9 -> 5.26 | I12: =I6*I9 -> 7 | J12: 2.614 | K12: 4.56 | L12: 5.26 | M12: 7 | N12: =IF(J12=0,F12-J12,F12/J12-1) -> 0 | O12: =IF(K12=0,G12-K12,G12/K12-1) -> 0 | P12: =IF(L12=0,H12-L12,H12/L12-1) -> 0 | Q12: =IF(M12=0,I12-M12,I12/M12-1) -> 0
A13: 付費 token 三分（M tok/年）
A14: R8 | B14: API token | C14: 連結 3_m重算 S4。 | D14: M tok/年 | E14: Cap_In 第 140 列 C；第 196 列 D–F | F14: =3_m重算!F10 -> 2365200000 | G14: =3_m重算!G10 -> 7884000000 | H14: =3_m重算!H10 -> 7884000000 | I14: =3_m重算!I10 -> 10249200000 | J14: 2365200000 | K14: 7884000000 | L14: 7884000000 | M14: 10249200000 | N14: =IF(J14=0,F14-J14,F14/J14-1) -> 0 | O14: =IF(K14=0,G14-K14,G14/K14-1) -> 0 | P14: =IF(L14=0,H14-L14,H14/L14-1) -> 0 | Q14: =IF(M14=0,I14-M14,I14/M14-1) -> 0
A15: R9 | B15: ChatGPT 付費 token | C15: 連結 3_m重算 S8。 | D15: M tok/年 | E15: Cap_In 第 81 列 C；第 198 列 D–F | F15: =3_m重算!F14 -> 1460000000 | G15: =3_m重算!G14 -> 1868800000 | H15: =3_m重算!H14 -> 2102400000 | I15: =3_m重算!I14 -> 2219200000 | J15: 1460000000 | K15: 1868800000 | L15: 2102400000 | M15: 2219200000 | N15: =IF(J15=0,F15-J15,F15/J15-1) -> 0 | O15: =IF(K15=0,G15-K15,G15/K15-1) -> 0 | P15: =IF(L15=0,H15-L15,H15/L15-1) -> 0 | Q15: =IF(M15=0,I15-M15,I15/M15-1) -> 0
A16: R10 | B16: 消費訂閱占 ChatGPT 付費 token 份額 | C16: 輸入（Assumed）。2026 三欄共用 0.65。 | D16: % | E16: Cap_In C132；第 200 列 D–F | F16: =IN_SubTokShare -> 0.75 | G16: =IN_SubTokShare26 -> 0.65 | H16: =IN_SubTokShare26 -> 0.65 | I16: =IN_SubTokShare26 -> 0.65 | J16: 0.75 | K16: 0.65 | L16: 0.65 | M16: 0.65 | N16: =IF(J16=0,F16-J16,F16/J16-1) -> 0 | O16: =IF(K16=0,G16-K16,G16/K16-1) -> 0 | P16: =IF(L16=0,H16-L16,H16/L16-1) -> 0 | Q16: =IF(M16=0,I16-M16,I16/M16-1) -> 0
A17: R11 | B17: 消費訂閱 token | C17: ＝R9 × R10。 | D17: M tok/年 | E17: Cap_In 第 141 列 C；第 201 列 D–F | F17: =F15*F16 -> 1095000000 | G17: =G15*G16 -> 1214720000 | H17: =H15*H16 -> 1366560000 | I17: =I15*I16 -> 1442480000 | J17: 1095000000 | K17: 1214720000 | L17: 1366560000 | M17: 1442480000 | N17: =IF(J17=0,F17-J17,F17/J17-1) -> 0 | O17: =IF(K17=0,G17-K17,G17/K17-1) -> 0 | P17: =IF(L17=0,H17-L17,H17/L17-1) -> 0 | Q17: =IF(M17=0,I17-M17,I17/M17-1) -> 0
A18: R12 | B18: 商用席次 token | C18: ＝R9 ×（1 − R10）。 | D18: M tok/年 | E18: Cap_In 第 142 列 C；第 202 列 D–F | F18: =F15*(1-F16) -> 365000000 | G18: =G15*(1-G16) -> 654080000 | H18: =H15*(1-H16) -> 735840000 | I18: =I15*(1-I16) -> 776720000 | J18: 365000000 | K18: 654080000 | L18: 735840000 | M18: 776720000 | N18: =IF(J18=0,F18-J18,F18/J18-1) -> 0 | O18: =IF(K18=0,G18-K18,G18/K18-1) -> 0 | P18: =IF(L18=0,H18-L18,H18/L18-1) -> 0 | Q18: =IF(M18=0,I18-M18,I18/M18-1) -> 0
A19: 各路線 m
A20: R13 | B20: 混合有效單價（三路線共用） | C20: 連結 3_m重算 S10。 | D20: $/M tok | E20: CAP_Price25Mix；Cap_In 第 205 列 | F20: =3_m重算!F17 -> 1.35936 | G20: =3_m重算!G17 -> 1.9606756 | H20: =3_m重算!H17 -> 1.9606756 | I20: =3_m重算!I17 -> 1.9606756 | J20: 1.35936 | K20: 1.9606756 | L20: 1.9606756 | M20: 1.9606756 | N20: =IF(J20=0,F20-J20,F20/J20-1) -> 0 | O20: =IF(K20=0,G20-K20,G20/K20-1) -> 0 | P20: =IF(L20=0,H20-L20,H20/L20-1) -> 0 | Q20: =IF(M20=0,I20-M20,I20/M20-1) -> 0
A21: R14 | B21: m_API | C21: ＝R7 × 10⁹ ÷（R8 × R13）。按量計費；實收低於有效牌價。 | D21: x | E21: L1_MAPI（2025）；Cap_In 第 206 列；L1_M_API（Q2） | F21: =F12*1000000000/(F14*F20) -> 0.81302374 | G21: =G12*1000000000/(G14*G20) -> 0.29499353 | H21: =H12*1000000000/(H14*H20) -> 0.34027763 | I21: =I12*1000000000/(I14*I20) -> 0.34833919 | J21: 0.81302374 | K21: 0.29499353 | L21: 0.34027763 | M21: 0.34833919 | N21: =IF(J21=0,F21-J21,F21/J21-1) -> 0 | O21: =IF(K21=0,G21-K21,G21/K21-1) -> 0 | P21: =IF(L21=0,H21-L21,H21/L21-1) -> 0 | Q21: =IF(M21=0,I21-M21,I21/M21-1) -> 0
A22: R15 | B22: m_消費訂閱 | C22: ＝R5 × 10⁹ ÷（R11 × R13）。定額月費 ÷ 實際用量：遠大於 1，表示訂閱用戶付的錢遠超過用掉 token 的有效牌價等值（或 token 數被低估）。 | D22: x | E22: L1_MSub（2025）；Cap_In 第 207 列；L1_M_Sub（Q2） | F22: =F10*1000000000/(F17*F20) -> 6.1464595 | G22: =G10*1000000000/(G17*G20) -> 5.7438644 | H22: =H10*1000000000/(H17*H20) -> 5.3986354 | I22: =I10*1000000000/(I17*I20) -> 5.5688436 | J22: 6.1464595 | K22: 5.7438644 | L22: 5.3986354 | M22: 5.5688436 | N22: =IF(J22=0,F22-J22,F22/J22-1) -> 0 | O22: =IF(K22=0,G22-K22,G22/K22-1) -> 0 | P22: =IF(L22=0,H22-L22,H22/L22-1) -> 0 | Q22: =IF(M22=0,I22-M22,I22/M22-1) -> 0
A23: R16 | B23: m_商用席次 | C23: ＝R6 × 10⁹ ÷（R12 × R13）。按席次定額收費，同上。 | D23: x | E23: L1_MSeat（2025）；Cap_In 第 208 列；L1_M_Seat（Q2） | F23: =F11*1000000000/(F18*F20) -> 2.6341969 | G23: =G11*1000000000/(G18*G20) -> 3.5557256 | H23: =H11*1000000000/(H18*H20) -> 4.5572896 | I23: =I11*1000000000/(I18*I20) -> 8.0438852 | J23: 2.6341969 | K23: 3.5557256 | L23: 4.5572896 | M23: 8.0438852 | N23: =IF(J23=0,F23-J23,F23/J23-1) -> 0 | O23: =IF(K23=0,G23-K23,G23/K23-1) -> 0 | P23: =IF(L23=0,H23-L23,H23/L23-1) -> 0 | Q23: =IF(M23=0,I23-M23,I23/M23-1) -> 0
A24: R17 | B24: 三路線合計的 m | C24: ＝（R5＋R6＋R7）× 10⁹ ÷（（R8＋R11＋R12）× R13）。三分只是把同一分子、同一分母拆開，必須等於整體 m。 | D24: x | E24: Cap_In 第 147 列 C；第 209 列 D–F | F24: =(F10+F11+F12)*1000000000/((F14+F17+F18)*F20) -> 2.5135467 | G24: =(G10+G11+G12)*1000000000/((G14+G17+G18)*G20) -> 1.1923391 | H24: =(H10+H11+H12)*1000000000/((H14+H17+H18)*H20) -> 1.3432012 | I24: =(I10+I11+I12)*1000000000/((I14+I17+I18)*I20) -> 1.4316985 | J24: 2.5135467 | K24: 1.1923391 | L24: 1.3432012 | M24: 1.4316985 | N24: =IF(J24=0,F24-J24,F24/J24-1) -> 0 | O24: =IF(K24=0,G24-K24,G24/K24-1) -> 0 | P24: =IF(L24=0,H24-L24,H24/L24-1) -> 0 | Q24: =IF(M24=0,I24-M24,I24/M24-1) -> 0
A25: R18 | B25: 檢查：R17 − 3_m重算 S13 | C25: 應為 0。 | D25: x | F25: =F24-3_m重算!F21 -> 0 | G25: =G24-3_m重算!G21 -> 0 | H25: =H24-3_m重算!H21 -> 0 | I25: =I24-3_m重算!I21 -> 0
A26: R19 | B26: 每百萬 token 實收：API | C26: ＝R7 × 10⁹ ÷ R8。 | D26: $/M tok | E26: （本簿新增） | F26: =F12*1000000000/F14 -> 1.1051919 | G26: =G12*1000000000/G14 -> 0.57838661 | H26: =H12*1000000000/H14 -> 0.66717402 | I26: =I12*1000000000/I14 -> 0.68298014
A27: R20 | B27: 每百萬 token 實收：消費訂閱 | C27: ＝R5 × 10⁹ ÷ R11。 | D27: $/M tok | E27: （本簿新增） | F27: =F10*1000000000/F17 -> 8.3552511 | G27: =G10*1000000000/G17 -> 11.261855 | H27: =H10*1000000000/H17 -> 10.584972 | I27: =I10*1000000000/I17 -> 10.918696
A28: R21 | B28: 每百萬 token 實收：商用席次 | C28: ＝R6 × 10⁹ ÷ R12。 | D28: $/M tok | E28: （本簿新增） | F28: =F11*1000000000/F18 -> 3.5808219 | G28: =G11*1000000000/G18 -> 6.9716243 | H28: =H11*1000000000/H18 -> 8.9353664 | I28: =I11*1000000000/I18 -> 15.771449

Sheet 5_敏感度
A1: L1_M（2026 Q2，主口徑）的單變數敏感度
A2: 每個有 Tokenomics 區間的輸入，各取低端與高端，其餘不動，用本簿公式重算 m（m 是乘除式，直接寫出）。承重度＝弧彈性 ln(m高/m低) ÷ ln(輸入高/輸入低)；擺動＝|m高 − m低| ÷ m 基準。只測單一變數，未測交互作用。Tokenomics 沒有區間的輸入寫「TK 無區間」，不自訂區間。
A4: # | B4: 輸入 | C4: 怎麼擺動 | D4: Tokenomics 位置 | E4: 低值 | F4: 高值 | G4: m（低值） | H4: m（高值） | I4: 相對變化（低） | J4: 相對變化（高） | K4: 承重度 | L4: 擺動 | M4: 排名 | N4: 說明
B5: m 基準（2026 Q2） | G5: =3_m重算!H21 -> 1.3432012
B6: 檢查：公式在基準值重算 − 基準 | G6: =(IN_RevQ2*4-IN_Ad_Q2)*1000000000/((IN_APItpm26*1000000000*525600/1000000+IN_Prompts_Q2*1000000000*IN_Tau*365/1000000*(1-IN_FreeShare))*(IN_Kappa*(1-IN_Disc)*((IN_MixP_L)*IN_CapMult_L*(IN_ISL_L*((1-IN_Chi)*IN_PIn_L+IN_Chi*IN_PCache_L)+IN_OSL_L*IN_POut_L)/(IN_ISL_L+IN_OSL_L)+(IN_MixP_S)*IN_CapMult_S*(IN_ISL_S*((1-IN_Chi)*IN_PIn_S+IN_Chi*IN_PCache_S)+IN_OSL_S*IN_POut_S)/(IN_ISL_S+IN_OSL_S)+(IN_MixP_A)*IN_CapMult_A*(IN_ISL_A*((1-IN_Chi)*IN_PIn_A+IN_Chi*IN_PCache_A)+IN_OSL_A*IN_POut_A)/(IN_ISL_A+IN_OSL_A))))-G5 -> 0
A7: 1 | B7: 每則 token τ | C7: IN_Tau 取 IN_Tau_Lo／IN_Tau_Hi | D7: Alloc_In C15 | E7: =IN_Tau_Lo -> 2000 | F7: =IN_Tau_Hi -> 11000 | G7: =(IN_RevQ2*4-IN_Ad_Q2)*1000000000/((IN_APItpm26*1000000000*525600/1000000+IN_Prompts_Q2*1000000000*IN_Tau_Lo*365/1000000*(1-IN_FreeShare))*(IN_Kappa*(1-IN_Disc)*((IN_MixP_L)*IN_CapMult_L*(IN_ISL_L*((1-IN_Chi)*IN_PIn_L+IN_Chi*IN_PCache_L)+IN_OSL_L*IN_POut_L)/(IN_ISL_L+IN_OSL_L)+(IN_MixP_S)*IN_CapMult_S*(IN_ISL_S*((1-IN_Chi)*IN_PIn_S+IN_Chi*IN_PCache_S)+IN_OSL_S*IN_POut_S)/(IN_ISL_S+IN_OSL_S)+(IN_MixP_A)*IN_CapMult_A*(IN_ISL_A*((1-IN_Chi)*IN_PIn_A+IN_Chi*IN_PCache_A)+IN_OSL_A*IN_POut_A)/(IN_ISL_A+IN_OSL_A)))) -> 1.5012248 | H7: =(IN_RevQ2*4-IN_Ad_Q2)*1000000000/((IN_APItpm26*1000000000*525600/1000000+IN_Prompts_Q2*1000000000*IN_Tau_Hi*365/1000000*(1-IN_FreeShare))*(IN_Kappa*(1-IN_Disc)*((IN_MixP_L)*IN_CapMult_L*(IN_ISL_L*((1-IN_Chi)*IN_PIn_L+IN_Chi*IN_PCache_L)+IN_OSL_L*IN_POut_L)/(IN_ISL_L+IN_OSL_L)+(IN_MixP_S)*IN_CapMult_S*(IN_ISL_S*((1-IN_Chi)*IN_PIn_S+IN_Chi*IN_PCache_S)+IN_OSL_S*IN_POut_S)/(IN_ISL_S+IN_OSL_S)+(IN_MixP_A)*IN_CapMult_A*(IN_ISL_A*((1-IN_Chi)*IN_PIn_A+IN_Chi*IN_PCache_A)+IN_OSL_A*IN_POut_A)/(IN_ISL_A+IN_OSL_A)))) -> 0.98157007 | I7: =G7/$G$5-1 -> 0.11764706 | J7: =H7/$G$5-1 -> -0.26923077 | K7: =IF(OR(E7<=0,F7<=0,G7<=0,H7<=0),"—",LN(H7/G7)/LN(F7/E7)) -> -0.24923518 | L7: =ABS(H7-G7)/$G$5 -> 0.38687783 | M7: =RANK(L7,$L$7:$L$19) -> 4 | N7: τ 大→付費 token 多→m 小。
A8: 2 | B8: ChatGPT 免費占比 | C8: IN_FreeShare 取 IN_FreeShare_Lo／IN_FreeShare_Hi | D8: Alloc_In C16 | E8: =IN_FreeShare_Lo -> 0.4 | F8: =IN_FreeShare_Hi -> 0.8 | G8: =(IN_RevQ2*4-IN_Ad_Q2)*1000000000/((IN_APItpm26*1000000000*525600/1000000+IN_Prompts_Q2*1000000000*IN_Tau*365/1000000*(1-IN_FreeShare_Lo))*(IN_Kappa*(1-IN_Disc)*((IN_MixP_L)*IN_CapMult_L*(IN_ISL_L*((1-IN_Chi)*IN_PIn_L+IN_Chi*IN_PCache_L)+IN_OSL_L*IN_POut_L)/(IN_ISL_L+IN_OSL_L)+(IN_MixP_S)*IN_CapMult_S*(IN_ISL_S*((1-IN_Chi)*IN_PIn_S+IN_Chi*IN_PCache_S)+IN_OSL_S*IN_POut_S)/(IN_ISL_S+IN_OSL_S)+(IN_MixP_A)*IN_CapMult_A*(IN_ISL_A*((1-IN_Chi)*IN_PIn_A+IN_Chi*IN_PCache_A)+IN_OSL_A*IN_POut_A)/(IN_ISL_A+IN_OSL_A)))) -> 1.2152772 | H8: =(IN_RevQ2*4-IN_Ad_Q2)*1000000000/((IN_APItpm26*1000000000*525600/1000000+IN_Prompts_Q2*1000000000*IN_Tau*365/1000000*(1-IN_FreeShare_Hi))*(IN_Kappa*(1-IN_Disc)*((IN_MixP_L)*IN_CapMult_L*(IN_ISL_L*((1-IN_Chi)*IN_PIn_L+IN_Chi*IN_PCache_L)+IN_OSL_L*IN_POut_L)/(IN_ISL_L+IN_OSL_L)+(IN_MixP_S)*IN_CapMult_S*(IN_ISL_S*((1-IN_Chi)*IN_PIn_S+IN_Chi*IN_PCache_S)+IN_OSL_S*IN_POut_S)/(IN_ISL_S+IN_OSL_S)+(IN_MixP_A)*IN_CapMult_A*(IN_ISL_A*((1-IN_Chi)*IN_PIn_A+IN_Chi*IN_PCache_A)+IN_OSL_A*IN_POut_A)/(IN_ISL_A+IN_OSL_A)))) -> 1.5012248 | I8: =G8/$G$5-1 -> -0.095238095 | J8: =H8/$G$5-1 -> 0.11764706 | K8: =IF(OR(E8<=0,F8<=0,G8<=0,H8<=0),"—",LN(H8/G8)/LN(F8/E8)) -> 0.30485458 | L8: =ABS(H8-G8)/$G$5 -> 0.21288515 | M8: =RANK(L8,$L$7:$L$19) -> 10 | N8: 免費占比大→付費 token 少→m 大。
A9: 3 | B9: 有效折扣 d | C9: IN_Disc 取 IN_Disc_Lo／IN_Disc_Hi | D9: Cap_In C12 | E9: =IN_Disc_Lo -> 0.1 | F9: =IN_Disc_Hi -> 0.4 | G9: =(IN_RevQ2*4-IN_Ad_Q2)*1000000000/((IN_APItpm26*1000000000*525600/1000000+IN_Prompts_Q2*1000000000*IN_Tau*365/1000000*(1-IN_FreeShare))*(IN_Kappa*(1-IN_Disc_Lo)*((IN_MixP_L)*IN_CapMult_L*(IN_ISL_L*((1-IN_Chi)*IN_PIn_L+IN_Chi*IN_PCache_L)+IN_OSL_L*IN_POut_L)/(IN_ISL_L+IN_OSL_L)+(IN_MixP_S)*IN_CapMult_S*(IN_ISL_S*((1-IN_Chi)*IN_PIn_S+IN_Chi*IN_PCache_S)+IN_OSL_S*IN_POut_S)/(IN_ISL_S+IN_OSL_S)+(IN_MixP_A)*IN_CapMult_A*(IN_ISL_A*((1-IN_Chi)*IN_PIn_A+IN_Chi*IN_PCache_A)+IN_OSL_A*IN_POut_A)/(IN_ISL_A+IN_OSL_A)))) -> 1.1939566 | H9: =(IN_RevQ2*4-IN_Ad_Q2)*1000000000/((IN_APItpm26*1000000000*525600/1000000+IN_Prompts_Q2*1000000000*IN_Tau*365/1000000*(1-IN_FreeShare))*(IN_Kappa*(1-IN_Disc_Hi)*((IN_MixP_L)*IN_CapMult_L*(IN_ISL_L*((1-IN_Chi)*IN_PIn_L+IN_Chi*IN_PCache_L)+IN_OSL_L*IN_POut_L)/(IN_ISL_L+IN_OSL_L)+(IN_MixP_S)*IN_CapMult_S*(IN_ISL_S*((1-IN_Chi)*IN_PIn_S+IN_Chi*IN_PCache_S)+IN_OSL_S*IN_POut_S)/(IN_ISL_S+IN_OSL_S)+(IN_MixP_A)*IN_CapMult_A*(IN_ISL_A*((1-IN_Chi)*IN_PIn_A+IN_Chi*IN_PCache_A)+IN_OSL_A*IN_POut_A)/(IN_ISL_A+IN_OSL_A)))) -> 1.7909349 | I9: =G9/$G$5-1 -> -0.11111111 | J9: =H9/$G$5-1 -> 0.33333333 | K9: =IF(OR(E9<=0,F9<=0,G9<=0,H9<=0),"—",LN(H9/G9)/LN(F9/E9)) -> 0.29248125 | L9: =ABS(H9-G9)/$G$5 -> 0.44444444 | M9: =RANK(L9,$L$7:$L$19) -> 3 | N9: d 大→有效牌價低→m 大（m×(1 − d) 不變）。
A10: 4 | B10: 請求形狀 κ | C10: IN_Kappa 取 IN_Kappa_Lo／IN_Kappa_Hi | D10: Alloc_In C26 | E10: =IN_Kappa_Lo -> 0.65 | F10: =IN_Kappa_Hi -> 1.2 | G10: =(IN_RevQ2*4-IN_Ad_Q2)*1000000000/((IN_APItpm26*1000000000*525600/1000000+IN_Prompts_Q2*1000000000*IN_Tau*365/1000000*(1-IN_FreeShare))*(IN_Kappa_Lo*(1-IN_Disc)*((IN_MixP_L)*IN_CapMult_L*(IN_ISL_L*((1-IN_Chi)*IN_PIn_L+IN_Chi*IN_PCache_L)+IN_OSL_L*IN_POut_L)/(IN_ISL_L+IN_OSL_L)+(IN_MixP_S)*IN_CapMult_S*(IN_ISL_S*((1-IN_Chi)*IN_PIn_S+IN_Chi*IN_PCache_S)+IN_OSL_S*IN_POut_S)/(IN_ISL_S+IN_OSL_S)+(IN_MixP_A)*IN_CapMult_A*(IN_ISL_A*((1-IN_Chi)*IN_PIn_A+IN_Chi*IN_PCache_A)+IN_OSL_A*IN_POut_A)/(IN_ISL_A+IN_OSL_A)))) -> 2.0664633 | H10: =(IN_RevQ2*4-IN_Ad_Q2)*1000000000/((IN_APItpm26*1000000000*525600/1000000+IN_Prompts_Q2*1000000000*IN_Tau*365/1000000*(1-IN_FreeShare))*(IN_Kappa_Hi*(1-IN_Disc)*((IN_MixP_L)*IN_CapMult_L*(IN_ISL_L*((1-IN_Chi)*IN_PIn_L+IN_Chi*IN_PCache_L)+IN_OSL_L*IN_POut_L)/(IN_ISL_L+IN_OSL_L)+(IN_MixP_S)*IN_CapMult_S*(IN_ISL_S*((1-IN_Chi)*IN_PIn_S+IN_Chi*IN_PCache_S)+IN_OSL_S*IN_POut_S)/(IN_ISL_S+IN_OSL_S)+(IN_MixP_A)*IN_CapMult_A*(IN_ISL_A*((1-IN_Chi)*IN_PIn_A+IN_Chi*IN_PCache_A)+IN_OSL_A*IN_POut_A)/(IN_ISL_A+IN_OSL_A)))) -> 1.1193343 | I10: =G10/$G$5-1 -> 0.53846154 | J10: =H10/$G$5-1 -> -0.16666667 | K10: =IF(OR(E10<=0,F10<=0,G10<=0,H10<=0),"—",LN(H10/G10)/LN(F10/E10)) -> -1 | L10: =ABS(H10-G10)/$G$5 -> 0.70512821 | M10: =RANK(L10,$L$7:$L$19) -> 1 | N10: κ 乘進有效單價，m 與 κ 成反比。
A11: 5 | B11: 快取命中 χ | C11: IN_Chi 取 IN_Chi_Lo／IN_Chi_Hi | D11: Cap_In C13 | E11: =IN_Chi_Lo -> 0.3 | F11: =IN_Chi_Hi -> 0.75 | G11: =(IN_RevQ2*4-IN_Ad_Q2)*1000000000/((IN_APItpm26*1000000000*525600/1000000+IN_Prompts_Q2*1000000000*IN_Tau*365/1000000*(1-IN_FreeShare))*(IN_Kappa*(1-IN_Disc)*((IN_MixP_L)*IN_CapMult_L*(IN_ISL_L*((1-IN_Chi_Lo)*IN_PIn_L+IN_Chi_Lo*IN_PCache_L)+IN_OSL_L*IN_POut_L)/(IN_ISL_L+IN_OSL_L)+(IN_MixP_S)*IN_CapMult_S*(IN_ISL_S*((1-IN_Chi_Lo)*IN_PIn_S+IN_Chi_Lo*IN_PCache_S)+IN_OSL_S*IN_POut_S)/(IN_ISL_S+IN_OSL_S)+(IN_MixP_A)*IN_CapMult_A*(IN_ISL_A*((1-IN_Chi_Lo)*IN_PIn_A+IN_Chi_Lo*IN_PCache_A)+IN_OSL_A*IN_POut_A)/(IN_ISL_A+IN_OSL_A)))) -> 1.1201604 | H11: =(IN_RevQ2*4-IN_Ad_Q2)*1000000000/((IN_APItpm26*1000000000*525600/1000000+IN_Prompts_Q2*1000000000*IN_Tau*365/1000000*(1-IN_FreeShare))*(IN_Kappa*(1-IN_Disc)*((IN_MixP_L)*IN_CapMult_L*(IN_ISL_L*((1-IN_Chi_Hi)*IN_PIn_L+IN_Chi_Hi*IN_PCache_L)+IN_OSL_L*IN_POut_L)/(IN_ISL_L+IN_OSL_L)+(IN_MixP_S)*IN_CapMult_S*(IN_ISL_S*((1-IN_Chi_Hi)*IN_PIn_S+IN_Chi_Hi*IN_PCache_S)+IN_OSL_S*IN_POut_S)/(IN_ISL_S+IN_OSL_S)+(IN_MixP_A)*IN_CapMult_A*(IN_ISL_A*((1-IN_Chi_Hi)*IN_PIn_A+IN_Chi_Hi*IN_PCache_A)+IN_OSL_A*IN_POut_A)/(IN_ISL_A+IN_OSL_A)))) -> 1.5977024 | I11: =G11/$G$5-1 -> -0.16605166 | J11: =H11/$G$5-1 -> 0.18947368 | K11: =IF(OR(E11<=0,F11<=0,G11<=0,H11<=0),"—",LN(H11/G11)/LN(F11/E11)) -> 0.38753502 | L11: =ABS(H11-G11)/$G$5 -> 0.35552534 | M11: =RANK(L11,$L$7:$L$19) -> 7 | N11: χ 大→輸入多按便宜的快取價→有效單價低→m 大。
A12: 6 | B12: 2026 Q2 廣告營收（年化） | C12: IN_Ad_Q2 取 IN_Ad_Q2_Lo／IN_Ad_Q2_Hi | D12: Cap_In E186 | E12: =IN_Ad_Q2_Lo -> 0.3 | F12: =IN_Ad_Q2_Hi -> 0.8 | G12: =(IN_RevQ2*4-IN_Ad_Q2_Lo)*1000000000/((IN_APItpm26*1000000000*525600/1000000+IN_Prompts_Q2*1000000000*IN_Tau*365/1000000*(1-IN_FreeShare))*(IN_Kappa*(1-IN_Disc)*((IN_MixP_L)*IN_CapMult_L*(IN_ISL_L*((1-IN_Chi)*IN_PIn_L+IN_Chi*IN_PCache_L)+IN_OSL_L*IN_POut_L)/(IN_ISL_L+IN_OSL_L)+(IN_MixP_S)*IN_CapMult_S*(IN_ISL_S*((1-IN_Chi)*IN_PIn_S+IN_Chi*IN_PCache_S)+IN_OSL_S*IN_POut_S)/(IN_ISL_S+IN_OSL_S)+(IN_MixP_A)*IN_CapMult_A*(IN_ISL_A*((1-IN_Chi)*IN_PIn_A+IN_Chi*IN_PCache_A)+IN_OSL_A*IN_POut_A)/(IN_ISL_A+IN_OSL_A)))) -> 1.3534156 | H12: =(IN_RevQ2*4-IN_Ad_Q2_Hi)*1000000000/((IN_APItpm26*1000000000*525600/1000000+IN_Prompts_Q2*1000000000*IN_Tau*365/1000000*(1-IN_FreeShare))*(IN_Kappa*(1-IN_Disc)*((IN_MixP_L)*IN_CapMult_L*(IN_ISL_L*((1-IN_Chi)*IN_PIn_L+IN_Chi*IN_PCache_L)+IN_OSL_L*IN_POut_L)/(IN_ISL_L+IN_OSL_L)+(IN_MixP_S)*IN_CapMult_S*(IN_ISL_S*((1-IN_Chi)*IN_PIn_S+IN_Chi*IN_PCache_S)+IN_OSL_S*IN_POut_S)/(IN_ISL_S+IN_OSL_S)+(IN_MixP_A)*IN_CapMult_A*(IN_ISL_A*((1-IN_Chi)*IN_PIn_A+IN_Chi*IN_PCache_A)+IN_OSL_A*IN_POut_A)/(IN_ISL_A+IN_OSL_A)))) -> 1.3278795 | I12: =G12/$G$5-1 -> 0.0076045627 | J12: =H12/$G$5-1 -> -0.011406844 | K12: =IF(OR(E12<=0,F12<=0,G12<=0,H12<=0),"—",LN(H12/G12)/LN(F12/E12)) -> -0.0194205 | L12: =ABS(H12-G12)/$G$5 -> 0.019011407 | M12: =RANK(L12,$L$7:$L$19) -> 11 | N12: 廣告從分子扣除；影響小。
A13: 7 | B13: Astra 層級占比 | C13: IN_MixP_A 取 IN_MixP_A_Lo／IN_MixP_A_Hi | D13: Cap_In E31（區間來自 Gov_Map GM457 文字） | E13: =IN_MixP_A_Lo -> 0.1 | F13: =IN_MixP_A_Hi -> 0.3 | G13: =(IN_RevQ2*4-IN_Ad_Q2)*1000000000/((IN_APItpm26*1000000000*525600/1000000+IN_Prompts_Q2*1000000000*IN_Tau*365/1000000*(1-IN_FreeShare))*(IN_Kappa*(1-IN_Disc)*(((1-IN_MixP_A_Lo)*IN_MixP_L/(IN_MixP_L+IN_MixP_S))*IN_CapMult_L*(IN_ISL_L*((1-IN_Chi)*IN_PIn_L+IN_Chi*IN_PCache_L)+IN_OSL_L*IN_POut_L)/(IN_ISL_L+IN_OSL_L)+((1-IN_MixP_A_Lo)*IN_MixP_S/(IN_MixP_L+IN_MixP_S))*IN_CapMult_S*(IN_ISL_S*((1-IN_Chi)*IN_PIn_S+IN_Chi*IN_PCache_S)+IN_OSL_S*IN_POut_S)/(IN_ISL_S+IN_OSL_S)+(IN_MixP_A_Lo)*IN_CapMult_A*(IN_ISL_A*((1-IN_Chi)*IN_PIn_A+IN_Chi*IN_PCache_A)+IN_OSL_A*IN_POut_A)/(IN_ISL_A+IN_OSL_A)))) -> 1.6425703 | H13: =(IN_RevQ2*4-IN_Ad_Q2)*1000000000/((IN_APItpm26*1000000000*525600/1000000+IN_Prompts_Q2*1000000000*IN_Tau*365/1000000*(1-IN_FreeShare))*(IN_Kappa*(1-IN_Disc)*(((1-IN_MixP_A_Hi)*IN_MixP_L/(IN_MixP_L+IN_MixP_S))*IN_CapMult_L*(IN_ISL_L*((1-IN_Chi)*IN_PIn_L+IN_Chi*IN_PCache_L)+IN_OSL_L*IN_POut_L)/(IN_ISL_L+IN_OSL_L)+((1-IN_MixP_A_Hi)*IN_MixP_S/(IN_MixP_L+IN_MixP_S))*IN_CapMult_S*(IN_ISL_S*((1-IN_Chi)*IN_PIn_S+IN_Chi*IN_PCache_S)+IN_OSL_S*IN_POut_S)/(IN_ISL_S+IN_OSL_S)+(IN_MixP_A_Hi)*IN_CapMult_A*(IN_ISL_A*((1-IN_Chi)*IN_PIn_A+IN_Chi*IN_PCache_A)+IN_OSL_A*IN_POut_A)/(IN_ISL_A+IN_OSL_A)))) -> 0.86839127 | I13: =G13/$G$5-1 -> 0.22287736 | J13: =H13/$G$5-1 -> -0.35349127 | K13: =IF(OR(E13<=0,F13<=0,G13<=0,H13<=0),"—",LN(H13/G13)/LN(F13/E13)) -> -0.58016387 | L13: =ABS(H13-G13)/$G$5 -> 0.57636863 | M13: =RANK(L13,$L$7:$L$19) -> 2 | N13: Luna 與 Sol 依 0.40：0.45 補足；Astra 貴，占比大→有效單價高→m 小。
A14: 8 | B14: Luna 參考輸入長度 ISL | C14: IN_ISL_L 取 IN_ISL_L_Lo／IN_ISL_L_Hi | D14: Serving C23 | E14: =IN_ISL_L_Lo -> 4096 | F14: =IN_ISL_L_Hi -> 16384 | G14: =(IN_RevQ2*4-IN_Ad_Q2)*1000000000/((IN_APItpm26*1000000000*525600/1000000+IN_Prompts_Q2*1000000000*IN_Tau*365/1000000*(1-IN_FreeShare))*(IN_Kappa*(1-IN_Disc)*((IN_MixP_L)*IN_CapMult_L*(IN_ISL_L_Lo*((1-IN_Chi)*IN_PIn_L+IN_Chi*IN_PCache_L)+IN_OSL_L*IN_POut_L)/(IN_ISL_L_Lo+IN_OSL_L)+(IN_MixP_S)*IN_CapMult_S*(IN_ISL_S*((1-IN_Chi)*IN_PIn_S+IN_Chi*IN_PCache_S)+IN_OSL_S*IN_POut_S)/(IN_ISL_S+IN_OSL_S)+(IN_MixP_A)*IN_CapMult_A*(IN_ISL_A*((1-IN_Chi)*IN_PIn_A+IN_Chi*IN_PCache_A)+IN_OSL_A*IN_POut_A)/(IN_ISL_A+IN_OSL_A)))) -> 1.3344987 | H14: =(IN_RevQ2*4-IN_Ad_Q2)*1000000000/((IN_APItpm26*1000000000*525600/1000000+IN_Prompts_Q2*1000000000*IN_Tau*365/1000000*(1-IN_FreeShare))*(IN_Kappa*(1-IN_Disc)*((IN_MixP_L)*IN_CapMult_L*(IN_ISL_L_Hi*((1-IN_Chi)*IN_PIn_L+IN_Chi*IN_PCache_L)+IN_OSL_L*IN_POut_L)/(IN_ISL_L_Hi+IN_OSL_L)+(IN_MixP_S)*IN_CapMult_S*(IN_ISL_S*((1-IN_Chi)*IN_PIn_S+IN_Chi*IN_PCache_S)+IN_OSL_S*IN_POut_S)/(IN_ISL_S+IN_OSL_S)+(IN_MixP_A)*IN_CapMult_A*(IN_ISL_A*((1-IN_Chi)*IN_PIn_A+IN_Chi*IN_PCache_A)+IN_OSL_A*IN_POut_A)/(IN_ISL_A+IN_OSL_A)))) -> 1.3483734 | I14: =G14/$G$5-1 -> -0.006478859 | J14: =H14/$G$5-1 -> 0.0038507172 | K14: =IF(OR(E14<=0,F14<=0,G14<=0,H14<=0),"—",LN(H14/G14)/LN(F14/E14)) -> 0.0074610851 | L14: =ABS(H14-G14)/$G$5 -> 0.010329576 | M14: =RANK(L14,$L$7:$L$19) -> 13
A15: 9 | B15: Sol 參考輸入長度 ISL | C15: IN_ISL_S 取 IN_ISL_S_Lo／IN_ISL_S_Hi | D15: Serving D23 | E15: =IN_ISL_S_Lo -> 8192 | F15: =IN_ISL_S_Hi -> 68000 | G15: =(IN_RevQ2*4-IN_Ad_Q2)*1000000000/((IN_APItpm26*1000000000*525600/1000000+IN_Prompts_Q2*1000000000*IN_Tau*365/1000000*(1-IN_FreeShare))*(IN_Kappa*(1-IN_Disc)*((IN_MixP_L)*IN_CapMult_L*(IN_ISL_L*((1-IN_Chi)*IN_PIn_L+IN_Chi*IN_PCache_L)+IN_OSL_L*IN_POut_L)/(IN_ISL_L+IN_OSL_L)+(IN_MixP_S)*IN_CapMult_S*(IN_ISL_S_Lo*((1-IN_Chi)*IN_PIn_S+IN_Chi*IN_PCache_S)+IN_OSL_S*IN_POut_S)/(IN_ISL_S_Lo+IN_OSL_S)+(IN_MixP_A)*IN_CapMult_A*(IN_ISL_A*((1-IN_Chi)*IN_PIn_A+IN_Chi*IN_PCache_A)+IN_OSL_A*IN_POut_A)/(IN_ISL_A+IN_OSL_A)))) -> 1.1713368 | H15: =(IN_RevQ2*4-IN_Ad_Q2)*1000000000/((IN_APItpm26*1000000000*525600/1000000+IN_Prompts_Q2*1000000000*IN_Tau*365/1000000*(1-IN_FreeShare))*(IN_Kappa*(1-IN_Disc)*((IN_MixP_L)*IN_CapMult_L*(IN_ISL_L*((1-IN_Chi)*IN_PIn_L+IN_Chi*IN_PCache_L)+IN_OSL_L*IN_POut_L)/(IN_ISL_L+IN_OSL_L)+(IN_MixP_S)*IN_CapMult_S*(IN_ISL_S_Hi*((1-IN_Chi)*IN_PIn_S+IN_Chi*IN_PCache_S)+IN_OSL_S*IN_POut_S)/(IN_ISL_S_Hi+IN_OSL_S)+(IN_MixP_A)*IN_CapMult_A*(IN_ISL_A*((1-IN_Chi)*IN_PIn_A+IN_Chi*IN_PCache_A)+IN_OSL_A*IN_POut_A)/(IN_ISL_A+IN_OSL_A)))) -> 1.5530955 | I15: =G15/$G$5-1 -> -0.12795129 | J15: =H15/$G$5-1 -> 0.15626426 | K15: =IF(OR(E15<=0,F15<=0,G15<=0,H15<=0),"—",LN(H15/G15)/LN(F15/E15)) -> 0.13329761 | L15: =ABS(H15-G15)/$G$5 -> 0.28421555 | M15: =RANK(L15,$L$7:$L$19) -> 8 | N15: ISL 長→新鮮／快取輸入價權重大→Sol 有效價低。
A16: 10 | B16: Astra 參考輸入長度 ISL | C16: IN_ISL_A 取 IN_ISL_A_Lo／IN_ISL_A_Hi | D16: Serving E23 | E16: =IN_ISL_A_Lo -> 16384 | F16: =IN_ISL_A_Hi -> 68000 | G16: =(IN_RevQ2*4-IN_Ad_Q2)*1000000000/((IN_APItpm26*1000000000*525600/1000000+IN_Prompts_Q2*1000000000*IN_Tau*365/1000000*(1-IN_FreeShare))*(IN_Kappa*(1-IN_Disc)*((IN_MixP_L)*IN_CapMult_L*(IN_ISL_L*((1-IN_Chi)*IN_PIn_L+IN_Chi*IN_PCache_L)+IN_OSL_L*IN_POut_L)/(IN_ISL_L+IN_OSL_L)+(IN_MixP_S)*IN_CapMult_S*(IN_ISL_S*((1-IN_Chi)*IN_PIn_S+IN_Chi*IN_PCache_S)+IN_OSL_S*IN_POut_S)/(IN_ISL_S+IN_OSL_S)+(IN_MixP_A)*IN_CapMult_A*(IN_ISL_A_Lo*((1-IN_Chi)*IN_PIn_A+IN_Chi*IN_PCache_A)+IN_OSL_A*IN_POut_A)/(IN_ISL_A_Lo+IN_OSL_A)))) -> 1.0792738 | H16: =(IN_RevQ2*4-IN_Ad_Q2)*1000000000/((IN_APItpm26*1000000000*525600/1000000+IN_Prompts_Q2*1000000000*IN_Tau*365/1000000*(1-IN_FreeShare))*(IN_Kappa*(1-IN_Disc)*((IN_MixP_L)*IN_CapMult_L*(IN_ISL_L*((1-IN_Chi)*IN_PIn_L+IN_Chi*IN_PCache_L)+IN_OSL_L*IN_POut_L)/(IN_ISL_L+IN_OSL_L)+(IN_MixP_S)*IN_CapMult_S*(IN_ISL_S*((1-IN_Chi)*IN_PIn_S+IN_Chi*IN_PCache_S)+IN_OSL_S*IN_POut_S)/(IN_ISL_S+IN_OSL_S)+(IN_MixP_A)*IN_CapMult_A*(IN_ISL_A_Hi*((1-IN_Chi)*IN_PIn_A+IN_Chi*IN_PCache_A)+IN_OSL_A*IN_POut_A)/(IN_ISL_A_Hi+IN_OSL_A)))) -> 1.5790825 | I16: =G16/$G$5-1 -> -0.19649128 | J16: =H16/$G$5-1 -> 0.17561136 | K16: =IF(OR(E16<=0,F16<=0,G16<=0,H16<=0),"—",LN(H16/G16)/LN(F16/E16)) -> 0.26739383 | L16: =ABS(H16-G16)/$G$5 -> 0.37210264 | M16: =RANK(L16,$L$7:$L$19) -> 5
A17: 11 | B17: Luna 參考輸出長度 OSL | C17: IN_OSL_L 取 IN_OSL_L_Lo／IN_OSL_L_Hi | D17: Serving C24 | E17: =IN_OSL_L_Lo -> 400 | F17: =IN_OSL_L_Hi -> 2048 | G17: =(IN_RevQ2*4-IN_Ad_Q2)*1000000000/((IN_APItpm26*1000000000*525600/1000000+IN_Prompts_Q2*1000000000*IN_Tau*365/1000000*(1-IN_FreeShare))*(IN_Kappa*(1-IN_Disc)*((IN_MixP_L)*IN_CapMult_L*(IN_ISL_L*((1-IN_Chi)*IN_PIn_L+IN_Chi*IN_PCache_L)+IN_OSL_L_Lo*IN_POut_L)/(IN_ISL_L+IN_OSL_L_Lo)+(IN_MixP_S)*IN_CapMult_S*(IN_ISL_S*((1-IN_Chi)*IN_PIn_S+IN_Chi*IN_PCache_S)+IN_OSL_S*IN_POut_S)/(IN_ISL_S+IN_OSL_S)+(IN_MixP_A)*IN_CapMult_A*(IN_ISL_A*((1-IN_Chi)*IN_PIn_A+IN_Chi*IN_PCache_A)+IN_OSL_A*IN_POut_A)/(IN_ISL_A+IN_OSL_A)))) -> 1.3495928 | H17: =(IN_RevQ2*4-IN_Ad_Q2)*1000000000/((IN_APItpm26*1000000000*525600/1000000+IN_Prompts_Q2*1000000000*IN_Tau*365/1000000*(1-IN_FreeShare))*(IN_Kappa*(1-IN_Disc)*((IN_MixP_L)*IN_CapMult_L*(IN_ISL_L*((1-IN_Chi)*IN_PIn_L+IN_Chi*IN_PCache_L)+IN_OSL_L_Hi*IN_POut_L)/(IN_ISL_L+IN_OSL_L_Hi)+(IN_MixP_S)*IN_CapMult_S*(IN_ISL_S*((1-IN_Chi)*IN_PIn_S+IN_Chi*IN_PCache_S)+IN_OSL_S*IN_POut_S)/(IN_ISL_S+IN_OSL_S)+(IN_MixP_A)*IN_CapMult_A*(IN_ISL_A*((1-IN_Chi)*IN_PIn_A+IN_Chi*IN_PCache_A)+IN_OSL_A*IN_POut_A)/(IN_ISL_A+IN_OSL_A)))) -> 1.3344987 | I17: =G17/$G$5-1 -> 0.0047585369 | J17: =H17/$G$5-1 -> -0.006478859 | K17: =IF(OR(E17<=0,F17<=0,G17<=0,H17<=0),"—",LN(H17/G17)/LN(F17/E17)) -> -0.0068867883 | L17: =ABS(H17-G17)/$G$5 -> 0.011237396 | M17: =RANK(L17,$L$7:$L$19) -> 12
A18: 12 | B18: Sol 參考輸出長度 OSL | C18: IN_OSL_S 取 IN_OSL_S_Lo／IN_OSL_S_Hi | D18: Serving D24 | E18: =IN_OSL_S_Lo -> 1024 | F18: =IN_OSL_S_Hi -> 4096 | G18: =(IN_RevQ2*4-IN_Ad_Q2)*1000000000/((IN_APItpm26*1000000000*525600/1000000+IN_Prompts_Q2*1000000000*IN_Tau*365/1000000*(1-IN_FreeShare))*(IN_Kappa*(1-IN_Disc)*((IN_MixP_L)*IN_CapMult_L*(IN_ISL_L*((1-IN_Chi)*IN_PIn_L+IN_Chi*IN_PCache_L)+IN_OSL_L*IN_POut_L)/(IN_ISL_L+IN_OSL_L)+(IN_MixP_S)*IN_CapMult_S*(IN_ISL_S*((1-IN_Chi)*IN_PIn_S+IN_Chi*IN_PCache_S)+IN_OSL_S_Lo*IN_POut_S)/(IN_ISL_S+IN_OSL_S_Lo)+(IN_MixP_A)*IN_CapMult_A*(IN_ISL_A*((1-IN_Chi)*IN_PIn_A+IN_Chi*IN_PCache_A)+IN_OSL_A*IN_POut_A)/(IN_ISL_A+IN_OSL_A)))) -> 1.4700822 | H18: =(IN_RevQ2*4-IN_Ad_Q2)*1000000000/((IN_APItpm26*1000000000*525600/1000000+IN_Prompts_Q2*1000000000*IN_Tau*365/1000000*(1-IN_FreeShare))*(IN_Kappa*(1-IN_Disc)*((IN_MixP_L)*IN_CapMult_L*(IN_ISL_L*((1-IN_Chi)*IN_PIn_L+IN_Chi*IN_PCache_L)+IN_OSL_L*IN_POut_L)/(IN_ISL_L+IN_OSL_L)+(IN_MixP_S)*IN_CapMult_S*(IN_ISL_S*((1-IN_Chi)*IN_PIn_S+IN_Chi*IN_PCache_S)+IN_OSL_S_Hi*IN_POut_S)/(IN_ISL_S+IN_OSL_S_Hi)+(IN_MixP_A)*IN_CapMult_A*(IN_ISL_A*((1-IN_Chi)*IN_PIn_A+IN_Chi*IN_PCache_A)+IN_OSL_A*IN_POut_A)/(IN_ISL_A+IN_OSL_A)))) -> 1.1713368 | I18: =G18/$G$5-1 -> 0.094461658 | J18: =H18/$G$5-1 -> -0.12795129 | K18: =IF(OR(E18<=0,F18<=0,G18<=0,H18<=0),"—",LN(H18/G18)/LN(F18/E18)) -> -0.1638704 | L18: =ABS(H18-G18)/$G$5 -> 0.22241295 | M18: =RANK(L18,$L$7:$L$19) -> 9 | N18: OSL 長→貴的輸出價權重大→有效價高→m 小。
A19: 13 | B19: Astra 參考輸出長度 OSL | C19: IN_OSL_A 取 IN_OSL_A_Lo／IN_OSL_A_Hi | D19: Serving E24 | E19: =IN_OSL_A_Lo -> 2048 | F19: =IN_OSL_A_Hi -> 8192 | G19: =(IN_RevQ2*4-IN_Ad_Q2)*1000000000/((IN_APItpm26*1000000000*525600/1000000+IN_Prompts_Q2*1000000000*IN_Tau*365/1000000*(1-IN_FreeShare))*(IN_Kappa*(1-IN_Disc)*((IN_MixP_L)*IN_CapMult_L*(IN_ISL_L*((1-IN_Chi)*IN_PIn_L+IN_Chi*IN_PCache_L)+IN_OSL_L*IN_POut_L)/(IN_ISL_L+IN_OSL_L)+(IN_MixP_S)*IN_CapMult_S*(IN_ISL_S*((1-IN_Chi)*IN_PIn_S+IN_Chi*IN_PCache_S)+IN_OSL_S*IN_POut_S)/(IN_ISL_S+IN_OSL_S)+(IN_MixP_A)*IN_CapMult_A*(IN_ISL_A*((1-IN_Chi)*IN_PIn_A+IN_Chi*IN_PCache_A)+IN_OSL_A_Lo*IN_POut_A)/(IN_ISL_A+IN_OSL_A_Lo)))) -> 1.5688816 | H19: =(IN_RevQ2*4-IN_Ad_Q2)*1000000000/((IN_APItpm26*1000000000*525600/1000000+IN_Prompts_Q2*1000000000*IN_Tau*365/1000000*(1-IN_FreeShare))*(IN_Kappa*(1-IN_Disc)*((IN_MixP_L)*IN_CapMult_L*(IN_ISL_L*((1-IN_Chi)*IN_PIn_L+IN_Chi*IN_PCache_L)+IN_OSL_L*IN_POut_L)/(IN_ISL_L+IN_OSL_L)+(IN_MixP_S)*IN_CapMult_S*(IN_ISL_S*((1-IN_Chi)*IN_PIn_S+IN_Chi*IN_PCache_S)+IN_OSL_S*IN_POut_S)/(IN_ISL_S+IN_OSL_S)+(IN_MixP_A)*IN_CapMult_A*(IN_ISL_A*((1-IN_Chi)*IN_PIn_A+IN_Chi*IN_PCache_A)+IN_OSL_A_Hi*IN_POut_A)/(IN_ISL_A+IN_OSL_A_Hi)))) -> 1.0792738 | I19: =G19/$G$5-1 -> 0.16801687 | J19: =H19/$G$5-1 -> -0.19649128 | K19: =IF(OR(E19<=0,F19<=0,G19<=0,H19<=0),"—",LN(H19/G19)/LN(F19/E19)) -> -0.26983776 | L19: =ABS(H19-G19)/$G$5 -> 0.36450814 | M19: =RANK(L19,$L$7:$L$19) -> 6
B21: 對照：τ 與免費占比同向取端點（Tokenomics 的 L1_M_2026Q2 區間） | G21: =3_m重算!H51 -> 0.81018482 | H21: =3_m重算!I51 -> 1.5950514 | N21: 兩個輸入同時取端點的包絡（最寬情形），不是機率區間；連結 3_m重算 E9。
A23: Tokenomics 無區間的 Assumed／單值輸入（不自訂區間，不計算擺動）
B24: 2026 Q2 季營收 | E24: =IN_RevQ2 -> 6.7 | F24: TK 無區間 | N24: Interested-party 單值（WSJ 轉述）；m 近似與營收成正比（扣廣告後）。
B25: 2026 API 每分鐘 token | E25: =IN_APItpm26 -> 15 | F25: TK 無區間 | N25: 2026-03 時點值，Q2 當期值未找到（E399）。
B26: 2026 Q2 ChatGPT 每日訊息數 | E26: =IN_Prompts_Q2 -> 3.6 | F26: TK 無區間 | N26: Assumed，週活比例放大；TK 無區間。
B27: 2026 營收份額、消費訂閱 token 份額 | E27: =IN_SubShare_Q2 -> 0.55 | F27: TK 無區間 | N27: 只影響分路線 m，不影響整體 m。
B28: 能力單價倍數 ε | E28: =IN_CapMult_S -> 1 | F28: 不影響 | N28: ε 的區間 0–0.5 存在，但倍數＝(H_CAP × 算力倍數)^ε，現值兩者皆為 1，ε 怎麼動倍數都是 1，m 不受影響。

Sheet 6_不確定與證據
A1: 最不確定的輸入：為什麼不確定、要找什麼證據、找到後 m 往哪個方向動
A2: 排序依據：5_敏感度 的擺動 × 證據取得難度。分工：C＝chat 端可在公開網路找；A線上＝Andy 在付費牆或需登入的來源找；A線下＝Andy 線下調研。另列 Tokenomics 交接檔「證據 (4) m」三項（2026 API token 當期值、訂閱用量分布、企業折扣）；交接檔本文本次未能讀取，三項名稱引自工作單。
A4: 優先 | B4: 輸入 | C4: 現值（區間） | D4: 擺動 | E4: 承重度 | F4: 為什麼不確定 | G4: 要找的證據（找到就能定案的口徑）／可直接用的問題 | H4: 建議管道 | I4: 對 m 的影響方向 | J4: 找到後要改的格 | K4: 分工
A5: 一、可以「搜尋」解決
A6: 1 | B6: 每則訊息 token τ | C6: 4,000（2,000–11,000） | D6: TK 無區間 | E6: — | F6: 無公開數字；含輸入、上下文、推理與輸出，agent 與長文件使用會大幅拉高。 | G6: ChatGPT 每則對話（含推理）的平均 token；付費與免費用戶分開。 | H6: OpenRouter《State of AI》（每請求 token 代理值）；NBER《How people use ChatGPT》（訊息數、無 token）；OpenAI DevDay。本串已搜尋：ChatGPT token 長度未找到。 | I6: τ↑→付費 token↑→m↓。 | J6: Alloc_In C15 → 3_m重算 S6 | K6: C
A7: 2 | B7: ChatGPT 免費占比（token 口徑） | C7: 0.6（0.4–0.8） | D7: =5_敏感度!L8 -> 0.21288515 | E7: =5_敏感度!K8 -> 0.30485458 | F7: token 口徑與支出口徑混用過；Tokenomics 另有 2026 投資人資料的免費算力占比預估（L1_FreeShare_2026 0.34，算力口徑，Interested-party），口徑不同、未進 m。 | G7: 免費與付費用戶各自的 token 占比（不是用戶數、不是算力支出）。 | H7: OpenAI 投資人資料（The Information）；招股文件若 IPO；第三方流量統計。 | I7: 免費占比↑→付費 token↓→m↑。 | J7: Alloc_In C16 → S7 | K7: A線上＋C
A8: 3 | B8: 2026 每日訊息數 | C8: 3.2／3.6／3.8 十億則/日（TK 無區間） | D8: TK 無區間 | E8: — | F8: 2026 值是由週活比例放大推得（Assumed），沒有 OpenAI 對 2026 訊息數的直接揭露。 | G8: ChatGPT 2026 每日提示數或每週活躍用戶的官方更新。 | H8: OpenAI 公告、Axios／TechCrunch 轉述。 | I8: 訊息數↑→付費 token↑→m↓（近似反比，因 API token 是固定部分）。 | J8: Cap_In 第 197 列 → S5 | K8: C
A9: 4 | B9: 2026 API token 當期值 | C9: 15 B tok/分鐘（2026-03 時點；Q2 沿用） | D9: TK 無區間 | E9: — | F9: Q2、Q3 當期值已搜尋，未找到（DB_Evidence E399）；時點值「超過」15B，年化後不打折，可能高估或低估全年。Tokenomics 交接檔證據 (4) 項。 | G9: OpenAI 2026 Q2／Q3 API 每分鐘 token 的最新揭露。 | H9: OpenAI 官方部落格、DevDay 2026、第三方統計頁。 | I9: API token↑→付費 token↑→m↓。 | J9: Cap_In 第 196 列 → S4 | K9: C
A10: 5 | B10: 層級組合（Astra 占比） | C10: Luna 0.40／Sol 0.45／Astra 0.15（Astra 0.10–0.30） | D10: =5_敏感度!L13 -> 0.57636863 | E10: =5_敏感度!K13 -> -0.58016387 | F10: 各模型 token 占比未公開；Assumed。Astra 單價約為 Sol 的 5 倍，占比對有效單價影響大。 | G10: 付費 token 在 Luna／Sol／Astra（及舊模型）的占比，按季。 | H10: The Information、FT；OpenRouter 模型排行（代理值）；OpenAI 官方數字。 | I10: Astra↑→有效單價↑→m↓。 | J10: Cap_In 第 31 列 → T12 | K10: A線上＋C
A11: 6 | B11: 快取命中率 χ 與請求形狀（ISL／OSL） | C11: χ 0.55（0.3–0.75）；Sol ISL 16,384／OSL 2,048 | D11: =5_敏感度!L11 -> 0.35552534 | E11: =5_敏感度!K11 -> 0.38753502 | F11: 決定新鮮輸入、快取輸入、輸出三種價在混合價裡的權重；2026 agent 流量快取約 88%，高於現值。 | G11: 各類流量（API、ChatGPT、agent）的平均輸入／輸出長度與快取命中率。 | H11: OpenRouter（prompt 1.5K→6K、completion 150→400、agent 快取約 88%）；OpenAI DevDay。 | I11: χ↑→有效單價↓→m↑；輸出越長→有效單價↑→m↓。 | J11: Cap_In C13；Serving 第 23–24 列 → T5–T7 | K11: C
A12: 7 | B12: 廣告營收 | C12: 2026 Q2 0.5 $B（0.3–0.8） | D12: =5_敏感度!L12 -> 0.019011407 | E12: =5_敏感度!K12 -> -0.0194205 | F12: 依據 SRC_DEM_072（2026-08 廣告年化達 $1B）；Q2 年化值為推定。 | G12: 廣告營收的季度揭露。 | H12: OpenAI／媒體報導。 | I12: 廣告↑→分子↓→m↓（影響小）。 | J12: Cap_In E186 → S2 | K12: C
A13: 二、需要「實地調研」或付費資料
A14: 8 | B14: 有效折扣 d（Batch／Flex 占比與企業折扣） | C14: 0.20（0.1–0.4） | D14: =5_敏感度!L9 -> 0.44444444 | E14: =5_敏感度!K9 -> 0.29248125 | F14: Batch 半價是公開牌價，但占比與企業議價找不到（DB_Evidence E359：三輪搜尋未找到）。Tokenomics 交接檔證據 (4) 項「企業折扣」。 | G14: 問：API 用量中 Batch／Flex 的占比？大型企業承諾用量合約相對牌價的平均折扣？優先處理溢價與快取計價如何影響實收？ | H14: API 大客戶（企業、新創）；OpenAI 業務；雲端市集（Azure）。 | I14: d↑→有效牌價↓→m↑；但 m×(1 − d) 不變（見 1A 的 d 可調驗證）。 | J14: Cap_In C12 → IN_Disc | K14: A線下
A15: 9 | B15: 訂閱用量分布（重度與輕度用戶） | C15: 消費訂閱占 ChatGPT 付費 token 0.75（2025）／0.65（2026）（0.5–0.9） | D15: TK 無區間 | E15: — | F15: m_消費訂閱＞1 的根本原因是定額月費遠高於多數用戶的 token 用量等值；但用量分布（重度用戶人數與比例）沒有揭露。Tokenomics 交接檔證據 (4) 項。 | G15: 問：Plus／Pro 用戶 token 用量的分布（中位數、p90、p99）？重度用戶占訂閱人數與占 token 的比例？方案上限（速率限制）實際觸頂比例？ | H15: 前員工與業者訪談；第三方用量調查；OpenAI 研究報告（用戶行為）。 | I15: 不影響整體 m（只影響訂閱與席次的分路線 m）；整體 m 的訂閱貢獻要靠 τ 與免費占比。 | J15: Cap_In C132、D200 → 4_分路線 R10 | K15: A線下
A16: 10 | B16: 商用席次定價與實際用量 | C16: 席次營收份額 2026 Q2 0.25（Assumed） | D16: TK 無區間 | E16: — | F16: 「企業」口徑 OpenAI 未定義（席次＋API？）；席次實際用量只有 p95／中位數（SRC_DEM_045）。 | G16: 企業席次單價、席次數、企業年約折扣、承諾用量。 | H16: 企業客戶採購人員；OpenAI 業務；雲端市集。 | I16: 只影響分路線 m_商用席次與 m_API 的分攤。 | J16: Cap_In E189 → 4_分路線 | K16: A線下
A17: 11 | B17: 其他收入面變數（尚未進模型） | C17: README 列出，Tokenomics 未量化 | D17: TK 無區間 | E17: — | F17: 訂閱方案用量上限與速率限制、年繳與月繳折扣、促銷與試用額度、區域定價、經雲端市集或合作夥伴的營收分成（毛額與淨額口徑）、退款與壞帳。 | G17: 各項對實收營收（m 分子）的調整幅度。 | H17: 財報附註；招股文件若 IPO；業者訪談。 | I17: 多為分子（實收）調整：實收↓→m↓。 | J17: — | K17: A線下

Sheet 9_核對對照
A1: 核對對照：本簿貼上的 Tokenomics 數字 ↔ Tokenomics 位置
A2: 類型：輸入／區間低／區間高／原值＝貼上自 Tokenomics v21.2，tools/reading_workbooks/check_reading_m.py 逐格比對（相對容差 1e-9）；差異＝須 ≤ 1e-9 的差異格。閱讀時可略過本頁。
A4: 本簿頁 | B4: 本簿格 | C4: Tokenomics 位置（具名範圍或 頁!格；可為四則運算） | D4: 類型
A5: 2_輸入 | B5: D6 | C5: SRC_DEM_007 | D5: 輸入
A6: 2_輸入 | B6: D7 | C6: SRC_DEM_069 | D6: 輸入
A7: 2_輸入 | B7: D8 | C7: SRC_DEM_042 | D7: 輸入
A8: 2_輸入 | B8: D9 | C8: Cap_In!F185 | D8: 輸入
A9: 2_輸入 | B9: D10 | C9: Cap_In!D186 | D9: 輸入
A10: 2_輸入 | B10: G10 | C10: Gov_Map!K644 | D10: 區間低
A11: 2_輸入 | B11: H10 | C11: Gov_Map!L644 | D11: 區間高
A12: 2_輸入 | B12: D11 | C12: Cap_In!E186 | D12: 輸入
A13: 2_輸入 | B13: G11 | C13: Gov_Map!K645 | D13: 區間低
A14: 2_輸入 | B14: H11 | C14: Gov_Map!L645 | D14: 區間高
A15: 2_輸入 | B15: D12 | C15: Cap_In!F186 | D15: 輸入
... A103: 3_m重算 | B103: J6 | C103: Cap_In!C69 | D103: 原值
A104: 3_m重算 | B104: N6 | D104: 差異
A105: 3_m重算 | B105: K6 | C105: Cap_In!D185 | D105: 原值
A106: 3_m重算 | B106: O6 | D106: 差異
A107: 3_m重算 | B107: L6 | C107: Cap_In!E185 | D107: 原值
A108: 3_m重算 | B108: P6 | D108: 差異
A109: 3_m重算 | B109: M6 | C109: Cap_In!F185 | D109: 原值
A110: 3_m重算 | B110: Q6 | D110: 差異
A111: 3_m重算 | B111: J7 | C111: Cap_In!C186 | D111: 原值
A112: 3_m重算 | B112: N7 | D112: 差異
A113: 3_m重算 | B113: K7 | C113: Cap_In!D186 | D113: 原值
A114: 3_m重算 | B114: O7 | D114: 差異
A115: 3_m重算 | B115: L7 | C115: Cap_In!E186 | D115: 原值
A116: 3_m重算 | B116: P7 | D116: 差異
A117: 3_m重算 | B117: M7 | C117: Cap_In!F186 | D117: 原值
A118: 3_m重算 | B118: Q7 | D118: 差異
A119: 3_m重算 | B119: J8 | C119: Cap_In!C69 | D119: 原值
A120: 3_m重算 | B120: N8 | D120: 差異
A121: 3_m重算 | B121: K8 | C121: Cap_In!D187 | D121: 原值
A122: 3_m重算 | B122: O8 | D122: 差異
A123: 3_m重算 | B123: L8 | C123: Cap_In!E187 | D123: 原值
A124: 3_m重算 | B124: P8 | D124: 差異
A125: 3_m重算 | B125: M8 | C125: Cap_In!F187 | D125: 原值
A126: 3_m重算 | B126: Q8 | D126: 差異
A127: 3_m重算 | B127: J10 | C127: AL_DAPI | D127: 原值
A128: 3_m重算 | B128: N10 | D128: 差異
A129: 3_m重算 | B129: K10 | C129: Cap_In!D196 | D129: 原值
A130: 3_m重算 | B130: O10 | D130: 差異
A131: 3_m重算 | B131: L10 | C131: Cap_In!E196 | D131: 原值
A132: 3_m重算 | B132: P10 | D132: 差異
A133: 3_m重算 | B133: M10 | C133: Cap_In!F196 | D133: 原值
A134: 3_m重算 | B134: Q10 | D134: 差異
A135: 3_m重算 | B135: J11 | C135: SRC_DEM_012 | D135: 原值
A136: 3_m重算 | B136: N11 | D136: 差異
A137: 3_m重算 | B137: K11 | C137: Cap_In!D197 | D137: 原值
A138: 3_m重算 | B138: O11 | D138: 差異
A139: 3_m重算 | B139: L11 | C139: Cap_In!E197 | D139: 原值
A140: 3_m重算 | B140: P11 | D140: 差異
A141: 3_m重算 | B141: M11 | C141: Cap_In!F197 | D141: 原值
A142: 3_m重算 | B142: Q11 | D142: 差異
A143: 3_m重算 | B143: J12 | C143: AL_DChat | D143: 原值
A144: 3_m重算 | B144: N12 | D144: 差異
A145: 3_m重算 | B145: K12 | C145: Cap_In!D198+Cap_In!D199 | D145: 原值
A146: 3_m重算 | B146: O12 | D146: 差異
A147: 3_m重算 | B147: L12 | C147: Cap_In!E198+Cap_In!E199 | D147: 原值
A148: 3_m重算 | B148: P12 | D148: 差異
A149: 3_m重算 | B149: M12 | C149: Cap_In!F198+Cap_In!F199 | D149: 原值
A150: 3_m重算 | B150: Q12 | D150: 差異
A151: 3_m重算 | B151: J13 | C151: AL_DChatFree | D151: 原值
A152: 3_m重算 | B152: N13 | D152: 差異
A153: 3_m重算 | B153: K13 | C153: Cap_In!D199 | D153: 原值
A154: 3_m重算 | B154: O13 | D154: 差異
A155: 3_m重算 | B155: L13 | C155: Cap_In!E199 | D155: 原值
A156: 3_m重算 | B156: P13 | D156: 差異
A157: 3_m重算 | B157: M13 | C157: Cap_In!F199 | D157: 原值
A158: 3_m重算 | B158: Q13 | D158: 差異
A159: 3_m重算 | B159: J14 | C159: AL_DChatPaid | D159: 原值
A160: 3_m重算 | B160: N14 | D160: 差異
A161: 3_m重算 | B161: K14 | C161: Cap_In!D198 | D161: 原值
A162: 3_m重算 | B162: O14 | D162: 差異
A163: 3_m重算 | B163: L14 | C163: Cap_In!E198 | D163: 原值
A164: 3_m重算 | B164: P14 | D164: 差異
A165: 3_m重算 | B165: M14 | C165: Cap_In!F198 | D165: 原值
A166: 3_m重算 | B166: Q14 | D166: 差異
A167: 3_m重算 | B167: J15 | C167: Cap_In!C83 | D167: 原值
A168: 3_m重算 | B168: N15 | D168: 差異
A169: 3_m重算 | B169: K15 | C169: Cap_In!D196+Cap_In!D198 | D169: 原值
A170: 3_m重算 | B170: O15 | D170: 差異
A171: 3_m重算 | B171: L15 | C171: Cap_In!E196+Cap_In!E198 | D171: 原值
A172: 3_m重算 | B172: P15 | D172: 差異
A173: 3_m重算 | B173: M15 | C173: Cap_In!F196+Cap_In!F198 | D173: 原值
A174: 3_m重算 | B174: Q15 | D174: 差異
A175: 3_m重算 | B175: J17 | C175: CAP_Price25Mix | D175: 原值
A176: 3_m重算 | B176: N17 | D176: 差異
A177: 3_m重算 | B177: K17 | C177: Cap_In!D205 | D177: 原值
A178: 3_m重算 | B178: O17 | D178: 差異
A179: 3_m重算 | B179: L17 | C179: Cap_In!E205 | D179: 原值
A180: 3_m重算 | B180: P17 | D180: 差異
A181: 3_m重算 | B181: M17 | C181: Cap_In!F205 | D181: 原值
A182: 3_m重算 | B182: Q17 | D182: 差異
A183: 3_m重算 | B183: K18 | C183: L1_PxList_2026 | D183: 原值
A184: 3_m重算 | B184: O18 | D184: 差異
A185: 3_m重算 | B185: L18 | C185: L1_PxList_2026 | D185: 原值
A186: 3_m重算 | B186: P18 | D186: 差異
A187: 3_m重算 | B187: M18 | C187: L1_PxList_2026 | D187: 原值
A188: 3_m重算 | B188: Q18 | D188: 差異
...
