Workbook

Sheet 0_說明
B1: m 閱讀版（Tokenomics v17.0）
B2: 建立：2026-10-18，chat 端（Claude）；2026-10-20 升 v17.0。用途：讓 Andy 讀懂 m 從總覽到最細的推導。本簿每個取自 Tokenomics 的數字都已對 Tokenomics v17.0（master 5ef0f7e）逐格核對。
B4: 分頁
B5: 1_總覽：m 的一句話定義、五層結構、閉式解（IF_Util 約掉）、彈性、驗證、最不確定的五項。
B6: 1A_需求公式樹：從營收三分、token 四分出發，逐層推到 m（m＝m_需求 × 需求覆蓋率），附「必須為真」。建議先讀本頁，細節再看 3–5 頁。
B7: 2_輸入：全部輸入（藍字，可改）。黃底＝不確定度「高」。每列附標記（Gov_Map）、區間、原活頁簿位置與說明。
B8: 3_m重算：m 的逐步計算（S1–S19 → m），每步附白話說明、原活頁簿格與原值、差異。
B9: 4_持有成本：每 GW 年經濟持有成本（Hopper、GB200），資本回收年金＋營運費用。
B10: 5_每GW產出：roofline——由規格、架構、SLO 與校準係數推出每 GW 年 token 產出（6 個案例）。
B11: 6_敏感度：27 個輸入的單變數敏感度（在 v15.3 執行；m 在 Tokenomics 的 2,993 個前置格 v15.3 與 v17.0 逐格相同，所以結果仍適用）。
B12: 7_不確定_搜尋：可以搜尋（公開或付費）解決的最不確定假設，附要找的證據與來源。
B13: 8_不確定_實地調研：需要訪談或供應鏈查核的假設，附可直接使用的訪談問題。
... B28: 本簿是 Tokenomics v17.0 的版本快照，不會隨基準模型自動同步。姊妹檔：20261020_L閱讀版_v17.0.xlsx。

Sheet 1_總覽
B1: m（機隊變現率）推導總覽
B2: Tokenomics v17.0（master 5ef0f7e；m 自 v15.2 起未變）。本頁數字全部連結到 3_m重算，改 2_輸入 會一起變。
B4: 一句話
B5: m ＝ OpenAI 2025 營收能「買到」的 token（按 2025 牌價扣折扣）÷ OpenAI 機隊實際產出的付費 token。m < 1 表示機隊產出的付費 token 比營收按牌價折算的多——每個 token 實收低於牌價（訂閱、免費額度、折扣），或模型高估了機隊產出。
B7: 層級與項目 | C7: 值 | D7: 單位 | E7: 怎麼算（細節頁）
B8: 第 0 層：m | C8: =3_m重算!D28 -> 0.46000311 | D8: x | E8: ＝ 營收 ÷（機隊付費 token × 混合有效單價）（3_m重算 步驟 m）
B9: 營收 | C9: =IN_Rev -> 13.07 | D9: $B | E9: SRC_DEM_007，查核財報
B10: 營收折合的 token | C10: =3_m重算!D27 -> 9.6148187e+09 | D10: M tok/年 | E10: 營收 ÷ 混合有效單價（步驟 S19）
B11: 機隊付費 token | C11: =3_m重算!D23 -> 2.0901639e+10 | D11: M tok/年 | E11: 有效服務 GW × 利用率修正 ÷（1/付費產能 ＋ r/免費產能）（步驟 S16）
B12: 第 1 層：單價 | C12: =3_m重算!D26 -> 1.35936 | D12: $/M tok | E12: 付費層級組合 × 2025 層級單價 ×（1 − 折扣）（步驟 S17–S18）
B13: 第 2 層：有效服務 GW | C13: =3_m重算!D21 -> 1.0565837 | D13: GW | E13: 推論支出 ÷ 每 GW 持有成本 ÷ 計價倍數 × κ（步驟 S12–S14；持有成本見 4_持有成本）
B14: 推論支出 | C14: =IN_Spend -> 8.4 | D14: $B | E14: SRC_DEM_004（主口徑 84 億；126 億為對照）
B15: 機隊每 GW 年持有成本 | C15: =3_m重算!D19 -> 9.3531186 | D15: $B/GW·年 | E15: 資本回收年金＋營運費用（4_持有成本）
B16: 利用率修正 | C16: =3_m重算!D22 -> 0.58083333 | D16: x | E16: 實際利用率 × 生產折減 ÷ IF_Util（步驟 S15）
B17: 第 3 層：免費 ÷ 付費 token 比 r | C17: =3_m重算!D17 -> 0.57251908 | D17: x | E17: ChatGPT 免費 token ÷（API ＋ ChatGPT 付費）（步驟 S7–S11）
B18: 第 4 層：機隊每 GW 年產能（付費） | C18: =3_m重算!D10 -> 3.9539922e+10 | D18: M tok/年 | E18: 世代加權的調和平均（步驟 S1–S6）
B19: 機隊每 GW 年產能（免費） | C19: =3_m重算!D11 -> 1.4065445e+11 | D19: M tok/年 | E19: 同上
B20: 第 5 層：每 GW 年產出（roofline） | C20: =5_每GW產出!H67 -> 1.6371585e+11 | D20: M tok/年 | E20: 例：GB200 Sol。每請求 GPU 秒 ← prefill（算力）＋ decode（SLO 下的批次 B*）（5_每GW產出）
B22: 閉式解（IF_Util 會約掉）
B23: m ＝ 營收 × 持有成本 × 計價倍數 ×（1/C付 ＋ r/C免）÷（推論支出 × κ × 實際利用率 × 生產折減 × 單價）
B24: C付、C免＝100% 利用率下的每 GW 年產能（＝S5、S6 ÷ IF_Util）。IF_Util 同時出現在利用率修正的分母與產能的分子，所以 m 與它無關。
B25: 閉式解計算的 m | C25: =IN_Rev*3_m重算!D19*IN_SpendBasis*(1/(3_m重算!D10/IN_Util)+3_m重算!D17/(3_m重算!D11/IN_Util))/(IN_Spend*IN_Kappa*IN_UtilAct*IN_ProdDerate*3_m重算!D26)*1000000000 -> 0.46000311 | E25: 應等於第 0 層的 m（單位：營收 $B × 持有成本 $B/GW ÷ 支出 $B → 只剩 $/token 與 token 的比）
B26: 差異 | C26: =C25/C8-1 -> 0
B28: 彈性（m 對各輸入，閉式解直接可讀）
B29: 營收、持有成本、計價倍數 | C29: +1
B30: 推論支出、κ、實際利用率、生產折減、單價 | C30: −1
B31: 每 GW 產能（付費與免費一起放大時） | C31: −1
B32: IF_Util | C32: 0（約掉）
B33: 免費 ÷ 付費 token 比 r | C33: ＋（r 越大，留給付費的產能越少，m 越高）
B35: 驗證
B36: 3_m重算 的 m ÷ Tokenomics 原值 − 1 | C36: =3_m重算!H28 -> 0
B37: 5_每GW產出 六個案例的最大絕對差異 | C37: =MAX(ABS(5_每GW產出!D69),ABS(5_每GW產出!E69),ABS(5_每GW產出!F69),ABS(5_每GW產出!G69),ABS(5_每GW產出!H69),ABS(5_每GW產出!I69)) -> 5.9952043e-15
B38: 4_持有成本 兩個世代的最大絕對差異 | C38: =MAX(ABS(4_持有成本!D36),ABS(4_持有成本!E36)) -> 0
B40: 最不確定的八項（依 6_敏感度 擺動排序；細節見 7、8 頁）
B41: 輸入 | C41: 擺動 | D41: 承重度 | E41: 去哪裡解決
B42: =6_敏感度!B8 -> 請求形狀 κ | C42: =6_敏感度!I8 -> 0.70512821 | D42: =6_敏感度!H8 -> -1 | E42: 7_不確定_搜尋 第 1 項
B43: =6_敏感度!B9 -> 實際利用率 | C43: =6_敏感度!I9 -> 0.62939364 | D43: =6_敏感度!H9 -> -0.79821488 | E43: 8_不確定_實地調研 第 1 項
B44: =6_敏感度!B10 -> 計價倍數 | C44: =6_敏感度!I10 -> 0.51764706 | D44: =6_敏感度!H10 -> 1 | E44: 7_不確定_搜尋 第 2 項
B45: =6_敏感度!B12 -> 有效折扣 | C45: =6_敏感度!I12 -> 0.44444444 | D45: =6_敏感度!H12 -> 0.29248125 | E45: 8_不確定_實地調研 第 2 項
B46: =6_敏感度!B11 -> Astra 啟用參數 | C46: =6_敏感度!I11 -> 0.44345692 | D46: =6_敏感度!H11 -> 0.34385124 | E46: 7_不確定_搜尋 第 3 項
B47: =6_敏感度!B13 -> Sol 參考 ISL | C47: =6_敏感度!I13 -> 0.39389614 | D47: =6_敏感度!H13 -> -0.18701762 | E47: 7_不確定_搜尋 第 1 項（流量形狀）
B48: =6_敏感度!B14 -> 生產折減 | C48: =6_敏感度!I14 -> 0.36428571 | D48: =6_敏感度!H14 -> -1 | E48: 8_不確定_實地調研 第 3 項
B49: =6_敏感度!B16 -> 服務世代組合 Hopper | C49: =6_敏感度!I16 -> 0.33185559 | D49: =6_敏感度!H16 -> — | E49: 8_不確定_實地調研 第 4 項

Sheet 1A_需求公式樹
A1: m 的需求角度公式樹：從「誰付錢、誰用 token」推到 m
A2: 讀法：由上往下，每一層都把上一層的一個量拆開。全部是公式，連到 2_輸入（藍字）與 3_m重算；改輸入，本頁一起變。G 欄＝Tokenomics v17.0 原值（貼上），H 欄＝差異。
A3: token 單位一律為「兆 token/年」（10¹² token；3_m重算 的 M tok ÷ 10⁶）。單價一律為「$/M token」（每百萬 token 美元）。
A5: 層 | B5: 項目 | C5: 值 | D5: 單位 | E5: 怎麼算（白話＋公式） | F5: 標記 | G5: Tokenomics 原值 | H5: 差異
A6: L0 | B6: m 是什麼：每個付費 token 實收多少，除以牌價（扣折扣後）
B7: 實際營收 | C7: =IN_Rev -> 13.07 | D7: $B | E7: OpenAI 2025 全年營收（毛額） | F7: Verified（SRC_DEM_007） | G7: 13.07 | H7: =IF(G7=0,C7-G7,C7/G7-1) -> 0
B8: 機隊產出的付費 token | C8: =3_m重算!D23/1000000 -> 20901.639 | D8: 兆 token/年 | E8: OpenAI 推論機隊一年實際產出、屬於付費用戶的 token（供給面算出，L5–L6 展開） | F8: Derived | G8: 20901.639 | H8: =IF(G8=0,C8-G8,C8/G8-1) -> 0
B9: 每百萬付費 token 實收 | C9: =C7*1000/C8 -> 0.62530982 | D9: $/M token | E9: ＝營收 ÷ 機隊付費 token。機隊每產出 100 萬個付費 token，OpenAI 實際收到多少錢 | F9: Derived
B10: 每百萬付費 token 的牌價（扣折扣） | C10: =3_m重算!D26 -> 1.35936 | D10: $/M token | E10: 付費 token 層級組合（Luna／Sol／Astra）× 2025 牌價 ×（1 − 有效折扣）；細節見 3_m重算 S17–S18 | F10: Derived | G10: 1.35936 | H10: =IF(G10=0,C10-G10,C10/G10-1) -> 0
B11: m＝實收 ÷ 牌價 | C11: =C9/C10 -> 0.46000311 | D11: 倍 | E11: m＜1：機隊產出的付費 token，平均每個收到的錢低於牌價。m 只用營收「總額」與機隊「總產出」，需求面只透過免費比 r 進來（L4） | F11: Derived | G11: 0.46000311 | H11: =IF(G11=0,C11-G11,C11/G11-1) -> 0
A13: L1 | B13: 把 m 拆成兩個因子：需求面變現率 × 需求覆蓋率
B14: 需求面數到的付費 token | C14: =3_m重算!D16/1000000 -> 3825.2 | D14: 兆 token/年 | E14: API token ＋ ChatGPT 付費 token（L3 加總；由公開的 API 吞吐與每日訊息數推得） | F14: Derived | G14: 3825.2 | H14: =IF(G14=0,C14-G14,C14/G14-1) -> 0
B15: m_需求：按需求面 token 算的變現率 | C15: =C7*1000/(C14*C10) -> 2.5135467 | D15: 倍 | E15: ＝營收 ÷（需求面付費 token × 牌價）。如果需求面的 token 數是對的，m 就是這個數 | F15: Derived | G15: 2.5135467 | H15: =IF(G15=0,C15-G15,C15/G15-1) -> 0
B16: 需求覆蓋率：需求面 token ÷ 機隊付費 token | C16: =C14/C8 -> 0.18300957 | D16: 倍 | E16: 機隊產出的付費 token，只有這個比例能在需求面數據裡「看到」 | F16: Derived | G16: 0.18300957 | H16: =IF(G16=0,C16-G16,C16/G16-1) -> 0
B17: 檢查：m_需求 × 覆蓋率 | C17: =C15*C16 -> 0.46000311 | D17: 倍 | E17: 應等於 L0 的 m（恆等式：m＝營收 ÷（S × P）＝[營收 ÷（D × P）] ×（D ÷ S）） | F17: — | G17: 0.46000311 | H17: =IF(G17=0,C17-G17,C17/G17-1) -> 0
B18: 兩邊 token 數相差 | C18: =1/C16 -> 5.464195 | D18: 倍 | E18: 機隊付費 token ÷ 需求面付費 token。這個缺口就是 m 最大的不確定來源（見 L8） | F18: Derived
A20: L2 | B20: 營收從哪裡來：營收三分（本層只拆分子，不改變 m 總值）
B21: 消費訂閱營收 | C21: =IN_Rev*IN_SubShare -> 9.149 | D21: $B | E21: ＝營收 × 消費訂閱占比（約 70%，OpenAI 自述） | F21: Derived（N10；OpenAI 自述約 70%） | G21: 9.149 | H21: =IF(G21=0,C21-G21,C21/G21-1) -> 0
B22: 商用席次營收 | C22: =IN_Rev*IN_SeatShare -> 1.307 | D22: $B | E22: ＝營收 × 商用席次占比（10%，假設） | F22: Assumed | G22: 1.307 | H22: =IF(G22=0,C22-G22,C22/G22-1) -> 0
B23: API 營收 | C23: =C7-C21-C22 -> 2.614 | D23: $B | E23: ＝營收 − 消費訂閱 − 商用席次（餘額）。前兩項的誤差全部落在這裡 | F23: Derived | G23: 2.614 | H23: =IF(G23=0,C23-G23,C23/G23-1) -> 0
B24: 占比：消費訂閱／商用席次／API | C24: =TEXT(C21/C7,"0%")&"／"&TEXT(C22/C7,"0%")&"／"&TEXT(C23/C7,"0%") -> 70%／10%／20% | E24: 約七成營收來自定額訂閱：訂閱收入不隨 token 用量變動，這是 m 偏離 1 的根本原因之一 | F24: —
A26: L3 | B26: token 由誰使用：token 四分（需求面）
B27: API token | C27: =3_m重算!D13/1000000 -> 2365.2 | D27: 兆 token/年 | E27: 開發者與企業透過 API 使用；按 token 計費 | F27: Derived | G27: 2365.2 | H27: =IF(G27=0,C27-G27,C27/G27-1) -> 0
B28: ChatGPT 消費訂閱 token | C28: =(3_m重算!D14-3_m重算!D15)*IN_SubTokShare/1000000 -> 1095 | D28: 兆 token/年 | E28: ＝ChatGPT 付費 token × 消費訂閱份額（75%，假設） | F28: Assumed（份額） | G28: 1095 | H28: =IF(G28=0,C28-G28,C28/G28-1) -> 0
B29: ChatGPT 商用席次 token | C29: =(3_m重算!D14-3_m重算!D15)*(1-IN_SubTokShare)/1000000 -> 365 | D29: 兆 token/年 | E29: ＝ChatGPT 付費 token ×（1 − 消費訂閱份額） | F29: Assumed（份額） | G29: 365 | H29: =IF(G29=0,C29-G29,C29/G29-1) -> 0
B30: ChatGPT 免費 token | C30: =3_m重算!D15/1000000 -> 2190 | D30: 兆 token/年 | E30: 免費用戶；沒有直接營收，但同樣占用機隊時間 | F30: Derived | G30: 2190 | H30: =IF(G30=0,C30-G30,C30/G30-1) -> 0
B31: 需求面 token 合計 | C31: =C27+C28+C29+C30 -> 6015.2 | D31: 兆 token/年 | E31: 四類合計；其中付費＝API＋消費訂閱＋商用席次＝L1 的需求面付費 token | F31: Derived | G31: 6015.2 | H31: =IF(G31=0,C31-G31,C31/G31-1) -> 0
A33: L3′ | B33: 各收費模式「每個 token 實收多少」：營收（L2）÷ token（L3）
B34: API：每百萬 token 實收 | C34: =C23*1000/C27 -> 1.1051919 | D34: $/M token | E34: API 營收 ÷ API token | F34: Derived
B35: m_API | C35: =C34/C10 -> 0.81302374 | D35: 倍 | E35: 按量計費，接近牌價（＜1 反映 Batch、企業折扣以外的組合差異） | F35: Derived | G35: 0.81302374 | H35: =IF(G35=0,C35-G35,C35/G35-1) -> 0
B36: 消費訂閱：每百萬 token 實收 | C36: =C21*1000/C28 -> 8.3552511 | D36: $/M token | E36: 消費訂閱營收 ÷ 消費訂閱 token | F36: Derived
B37: m_消費訂閱 | C37: =C36/C10 -> 6.1464595 | D37: 倍 | E37: 定額月費 ÷ 實際用量；遠大於 1，表示每位訂閱用戶付的錢遠超過他用掉 token 的牌價等值（或需求面低估了他的 token） | F37: Derived | G37: 6.1464595 | H37: =IF(G37=0,C37-G37,C37/G37-1) -> 0
B38: 商用席次：每百萬 token 實收 | C38: =C22*1000/C29 -> 3.5808219 | D38: $/M token | E38: 商用席次營收 ÷ 商用席次 token | F38: Derived
B39: m_商用席次 | C39: =C38/C10 -> 2.6341969 | D39: 倍 | E39: 同上，按席次定額收費 | F39: Derived | G39: 2.6341969 | H39: =IF(G39=0,C39-G39,C39/G39-1) -> 0
B40: m_需求（token 加權） | C40: =(C35*C27+C37*C28+C39*C29)/(C27+C28+C29) -> 2.5135467 | D40: 倍 | E40: 三段 m 以 token 加權＝L1 的 m_需求。免費 token 不進這裡，它在 L5 透過 r 壓縮付費產能 | F40: Derived | G40: 2.5135467 | H40: =IF(G40=0,C40-G40,C40/G40-1) -> 0
A42: L4 | B42: 需求面 token 怎麼推出來
B43: API 每分鐘 token（2025-10 時點） | C43: =IN_APItpm -> 6 | D43: 十億 token/分鐘 | E43: OpenAI 2025-10-06 公告 60 億 token／分鐘 | F43: Interested-party | G43: 6 | H43: =IF(G43=0,C43-G43,C43/G43-1) -> 0
B44: API 全年平均 ÷ 10 月時點 | C44: =IN_APIratio -> 0.75 | D44: 倍 | E44: 把 10 月的時點值換成全年平均（成長中，所以＜1） | F44: Assumed（0.6–0.9） | G44: 0.75 | H44: =IF(G44=0,C44-G44,C44/G44-1) -> 0
B45: → API token | C45: =C27 -> 2365.2 | D45: 兆 token/年 | E45: ＝每分鐘 token × 525,600 分鐘 × 全年平均比 | F45: Derived | G45: 2365.2 | H45: =IF(G45=0,C45-G45,C45/G45-1) -> 0
B46: ChatGPT 每日訊息數 | C46: =IN_Prompts -> 2.5 | D46: 十億則/日 | E46: OpenAI 自述 25 億則／日 | F46: Interested-party | G46: 2.5 | H46: =IF(G46=0,C46-G46,C46/G46-1) -> 0
B47: 每則訊息 token 數 τ | C47: =IN_Tau -> 4000 | D47: token/則 | E47: 含輸入、輸出、思考；無公開數字 | F47: Assumed（2,000–11,000） | G47: 4000 | H47: =IF(G47=0,C47-G47,C47/G47-1) -> 0
B48: 免費用戶占 ChatGPT token 比 | C48: =IN_FreeShare -> 0.6 | D48: % | E48: token 口徑（不是用戶數口徑，也不是支出口徑） | F48: Assumed（40%–80%） | G48: 0.6 | H48: =IF(G48=0,C48-G48,C48/G48-1) -> 0
B49: → ChatGPT token | C49: =C28+C29+C30 -> 3650 | D49: 兆 token/年 | E49: ＝每日訊息 × τ × 365 | F49: Derived | G49: 3650 | H49: =IF(G49=0,C49-G49,C49/G49-1) -> 0
B50: 免費 ÷ 付費 token 比 r | C50: =3_m重算!D17 -> 0.57251908 | D50: 倍 | E50: ＝免費 token ÷（API ＋ ChatGPT 付費）。每產出 1 個付費 token，機隊同時要產出 r 個免費 token | F50: Derived | G50: 0.57251908 | H50: =IF(G50=0,C50-G50,C50/G50-1) -> 0
A52: L5 | B52: 機隊供給：付費 token 是怎麼從 GW 算出來的（覆蓋率的分母）
B53: 有效服務 GW | C53: =3_m重算!D21 -> 1.0565837 | D53: GW | E53: L6 展開：推論支出能買到多少 GW 的服務能力 | F53: Derived | G53: 1.0565837 | H53: =IF(G53=0,C53-G53,C53/G53-1) -> 0
B54: 利用率修正 | C54: =3_m重算!D22 -> 0.58083333 | D54: 倍 | E54: ＝實際利用率 41% × 生產折減 0.85 ÷ 基準利用率 IF_Util 60% | F54: Derived | G54: 0.58083333 | H54: =IF(G54=0,C54-G54,C54/G54-1) -> 0
B55: 每 GW·年付費產能（基準利用率） | C55: =3_m重算!D10/1000000 -> 39539.922 | D55: 兆 token/(GW·年) | E55: 由硬體、模型架構、SLO、請求形狀推得（3_m重算 S1–S6、5_每GW產出） | F55: Derived | G55: 39539.922 | H55: =IF(G55=0,C55-G55,C55/G55-1) -> 0
B56: 每 GW·年免費產能（基準利用率） | C56: =3_m重算!D11/1000000 -> 140654.45 | D56: 兆 token/(GW·年) | E56: 免費用戶多用小模型（Luna 90%），每 GW 產出較多 | F56: Derived | G56: 140654.45 | H56: =IF(G56=0,C56-G56,C56/G56-1) -> 0
B57: 每個付費 token 連同其 r 個免費 token 占用的 GW·年 | C57: =1/C55+C50/C56 -> 2.9361289e-05 | D57: GW·年/兆 token | E57: ＝1 ÷ 付費產能 ＋ r ÷ 免費產能 | F57: Derived
B58: → 機隊付費 token | C58: =C53*C54/(1/C55+C50/C56) -> 20901.639 | D58: 兆 token/年 | E58: ＝有效服務 GW × 利用率修正 ÷ 上一列（GW·年守恆） | F58: Derived | G58: 20901.639 | H58: =IF(G58=0,C58-G58,C58/G58-1) -> 0
A60: L6 | B60: 有效服務 GW：推論支出能買到多少機隊
B61: 推論支出 | C61: =IN_Spend -> 8.4 | D61: $B | E61: OpenAI 2025 花在服務用戶推論的錢（所有供應商） | F61: Interested-party（區間 7.5–8.8） | G61: 8.4 | H61: =IF(G61=0,C61-G61,C61/G61-1) -> 0
B62: 每 GW·年持有成本（世代加權） | C62: =3_m重算!D19 -> 9.3531186 | D62: $B/(GW·年) | E62: 資本回收年金＋營運費用（4_持有成本） | F62: Derived
B63: 計價倍數（支出 ÷ 持有成本） | C63: =IN_SpendBasis -> 0.85 | D63: 倍 | E63: ＜1：同樣的錢買到比自建更多的 GW；Microsoft 對 OpenAI 的實際計價未找到 | F63: Derived（0.73–1.17） | G63: 0.85 | H63: =IF(G63=0,C63-G63,C63/G63-1) -> 0
B64: 請求形狀修正 κ | C64: =IN_Kappa -> 1 | D64: 倍 | E64: 實際流量每 GPU 秒的 token ÷ 參考請求 | F64: Derived（0.65–1.2） | G64: 1 | H64: =IF(G64=0,C64-G64,C64/G64-1) -> 0
B65: → 有效服務 GW | C65: =IN_Spend/3_m重算!D19/IN_SpendBasis*IN_Kappa -> 1.0565837 | D65: GW | E65: ＝推論支出 ÷ 持有成本 ÷ 計價倍數 × κ | F65: Derived | G65: 1.0565837 | H65: =IF(G65=0,C65-G65,C65/G65-1) -> 0
A67: L7 | B67: 閉式解（需求角度寫法）
B68: m ＝ m_需求 × 需求覆蓋率
B69: m_需求 ＝ 營收 ÷（需求面付費 token × 牌價）
B70: 需求覆蓋率 ＝ 需求面付費 token × 持有成本 × 計價倍數 ×（1/C付 ＋ r/C免）÷（推論支出 × κ × 實際利用率 × 生產折減）
B71: 合起來：需求面付費 token 約掉，回到 1_總覽 的閉式解：m ＝ 營收 × 持有成本 × 計價倍數 ×（1/C付 ＋ r/C免）÷（推論支出 × κ × 實際利用率 × 生產折減 × 牌價）。C付、C免＝100% 利用率產能；IF_Util 在點估計內約掉
B72: 閉式解計算的 m | C72: =IN_Rev*3_m重算!D19*IN_SpendBasis*(1/(3_m重算!D10/IN_Util)+3_m重算!D17/(3_m重算!D11/IN_Util))/(IN_Spend*IN_Kappa*IN_UtilAct*IN_ProdDerate*3_m重算!D26)*1000000000 -> 0.46000311 | D72: 倍 | E72: 應等於 L0 的 m | F72: Derived | G72: 0.46000311 | H72: =IF(G72=0,C72-G72,C72/G72-1) -> 0
B73: 適用條件：物理下限未綁定 | C73: =IF(IN_UtilAct*IN_ProdDerate/IN_Util>0.787813074077515,"下限綁定：m＝下限 0.339，閉式解不適用","未綁定：閉式解適用") -> 未綁定：閉式解適用 | E73: 實際利用率 × 生產折減 ÷ IF_Util ＞ 0.788（Tokenomics Cap_In!C115，付費產能比）時，Tokenomics 輸出改用下限。基準下＝0.581，未綁定；實際利用率＞0.556 或 IF_Util＜0.442 時綁定 | F73: —
A75: L8 | B75: 必須為真：兩邊 token 數要對得上，各需要什麼
B76: 需求面 token 比機隊少了 | C76: =C18 -> 5.464195 | D76: 倍 | E76: 任選一個單一假設來補齊缺口（其他不動）： | F76: —
B77: (a) τ 要多大，需求才填滿機隊 | C77: =(3_m重算!D21*3_m重算!D22-3_m重算!D13/3_m重算!D10)/((1-IN_FreeShare)/3_m重算!D10+IN_FreeShare/3_m重算!D11)*1000000/(IN_Prompts*1000000000*365) -> 42204.657 | D77: token/則 | E77: 現值 4,000（假設 2,000–11,000）；需要的值落在區間外 | F77: Derived（L1_TokPerPromptClose） | G77: 42204.657 | H77: =IF(G77=0,C77-G77,C77/G77-1) -> 0
B78: 此時的 m | C78: =IN_Rev*1000000000/((3_m重算!D13+(1-IN_FreeShare)*C77*IN_Prompts*1000000000*365/1000000)*3_m重算!D26) -> 0.54107332 | D78: 倍 | E78: 需求面 token 多出來，免費比 r 也跟著上升（訊息數不變、每則變長），所以 m 從 0.46 小幅升到這個值 | F78: Derived
B79: (b) 實際利用率要多低，機隊才只產出需求面的量 | C79: =IN_UtilAct*C16 -> 0.075033925 | D79: % | E79: 現值 41%（假設 30%–65%） | F79: Derived
B80: 此時的 m | C80: =C15 -> 2.5135467 | D80: 倍 | E80: 機隊產出縮到等於需求面，m＝m_需求 | F80: Derived | G80: 2.5135467 | H80: =IF(G80=0,C80-G80,C80/G80-1) -> 0
B81: (c) 推論支出要多少，機隊才只產出需求面的量 | C81: =IN_Spend*C16 -> 1.5372804 | D81: $B | E81: 現值 84 億（區間 75–88 億） | F81: Derived
B82: 此時的 m | C82: =C15 -> 2.5135467 | D82: 倍 | E82: 同 (b) | F82: Derived | G82: 2.5135467 | H82: =IF(G82=0,C82-G82,C82/G82-1) -> 0
B83: 讀法 | E83: m 落在 0.46（相信機隊面的 token 數）到 2.51（相信需求面的 token 數）之間，看缺口由哪一邊吸收。(a) 需要 τ 是現值的 10 倍，(b)(c) 需要利用率或支出只剩現值的兩成，三者都在各自區間外，所以缺口目前無法由單一假設解釋，很可能是多項同時偏離。 | F83: —
A85: 注意 | B85: 另一個口徑選擇
B86: r 改用支出口徑時的 m | C86: 0.73376346 | D86: 倍 | E86: 免費占比若是「支出」口徑而非 token 口徑，r＝3.03 而非 0.57，m＝0.734（Tokenomics Cap_In!C120；Decisions SL46-28）。這是定義選擇，單變數敏感度測不到 | F86: Derived（貼上值） | G86: 0.73376346 | H86: =IF(G86=0,C86-G86,C86/G86-1) -> 0
A88: 下鑽 | B88: 本頁每一層對應的細節頁
B89: 牌價（L0）→ 3_m重算 S17–S18
B90: 需求 token 與 r（L3–L4）→ 3_m重算 S7–S11
B91: 付費與免費產能 C付、C免（L5）→ 3_m重算 S1–S6、5_每GW產出（roofline）
B92: 持有成本（L6）→ 4_持有成本
B93: 各輸入的區間與擺動 → 6_敏感度；要找的證據 → 7、8 頁

Sheet 2_輸入
A1: m 推導的全部輸入（藍字＝輸入值，可改；改動後 3_m重算、4、5 頁會自動重算）
A2: 值取自 Tokenomics v17.0（20261020_Tokenomics_v17.0.xlsx，master 5ef0f7e）。標記與區間取自該簿 Gov_Map；「—」＝Gov_Map 無此格的登錄（多為硬體規格或模型架構的原始數據）。
A4: ID | B4: 群組 | C4: 項目 | D4: 值 | E4: 單位 | F4: 標記（Gov_Map） | G4: 區間低 | H4: 區間高 | I4: 原活頁簿位置 | J4: 說明與來源 | K4: 不確定度
A5: A. 營收與推論支出（OpenAI 2025）
A6: IN_Rev | B6: A | C6: OpenAI 2025 營收 | D6: 13.07 | E6: $B | F6: — | I6: SRC_Demand!C11 | J6: SRC_DEM_007；2025 查核財報營收 130.7 億美元（外流、FT 核實） | K6: 低
A7: IN_Spend | B7: A | C7: OpenAI 2025 推論支出（服務用戶，所有供應商） | D7: 8.4 | E7: $B | F7: — | G7: 7.5 | H7: 8.8 | I7: SRC_Demand!C8 | J7: SRC_DEM_004；OpenAI 投資人資料（經 The Information）；低 7.5＝查核營業成本、高 8.8＝調整後毛利率 33% 換算。Microsoft 端 126 億為對照（含研究推論），不採（調和分析 2026-10-17） | K7: 中
A8: B. 機隊配置與利用率
A9: IN_ShareH | B9: B | C9: 2025 服務世代組合：Hopper（GW 占比） | D9: 0.6 | E9: % | F9: — | G9: 0.5 | H9: 0.7 | I9: Alloc_In!C9 | J9: 無公開數字；chat 端暫設區間 0.5–0.7。Andy 線上／線下調研項 | K9: 高
A10: IN_ShareG | B10: B | C10: 2025 服務世代組合：GB200（GW 占比） | D10: 0.4 | E10: % | F10: — | G10: 0.25 | H10: 0.4 | I10: Alloc_In!C10 | J10: ＝1 − Hopper（GB300、VR200 在 2025 為 0）；Tokenomics 獨立區間 0.25–0.4（Alloc_In D10:E10）。6_敏感度 的世代組合測試用 GB200＝1 − Hopper（0.5／0.3），不是這個區間 | K10: 高
A11: IN_SpendBasis | B11: B | C11: 計價倍數＝推論支出 ÷ 持有成本 | D11: 0.85 | E11: x | F11: Derived | G11: 0.73 | H11: 1.17 | I11: Alloc_In!C23 | J11: 經濟口徑：價格 ÷ 會計成本 1.16 × 會計 ÷ 經濟持有成本 0.73；Microsoft 對 OpenAI 的實際計價未找到 | K11: 高
A12: IN_Kappa | B12: B | C12: 請求形狀修正 κ（實際流量每 GPU 秒 token ÷ 參考請求） | D12: 1 | E12: x | F12: Derived | G12: 0.65 | H12: 1.2 | I12: Alloc_In!C26 | J12: 證據範圍 0.67–1.05（2025 流量形狀，A 段第 3 節）；重算值 0.852（Alloc_In 第 41 列）；v15.3 敏感度擺動第一名 | K12: 高
A13: IN_UtilAct | B13: B | C13: 實際利用率（純；平均 token 吞吐 ÷ 容量） | D13: 0.41 | E13: % | F13: Assumed | G13: 0.3 | H13: 0.65 | I13: Alloc_In!C24 | J13: 無實測；上端 DeepSeek 2025-02 單一模型代理值 0.54–0.65 | K13: 高
A14: IN_ProdDerate | B14: B | C14: 生產折減（SLO 預留、故障、重啟） | D14: 0.85 | E14: x | F14: Assumed | G14: 0.7 | H14: 1 | I14: Serving!C28 | J14: 情境值，非估計值；只有訓練端公開論文可類比 | K14: 高
A15: IN_Util | B15: B | C15: 基準利用率 IF_Util（模型內部的每 GW 產能口徑） | D15: 0.6 | E15: % | F15: Assumed | G15: 0.4 | H15: 0.8 | I15: Serving!C17 | J15: 在 m 中會約掉（服務 GW 的利用率修正 ÷ IF_Util，產能 × IF_Util）；見 1_總覽 | K15: 低（約掉）
A16: C. 2025 價格與層級組合
A17: IN_Px_L | B17: C | C17: 2025 年度單價：Luna（參考請求混合價，表列） | D17: 0.1035 | E17: $/M | F17: Derived | G17: 0.0669 | H17: 0.3026 | I17: Cap_In!C278 | J17: nano 線在售天數加權；牌價 Verified | K17: 低
A18: IN_Px_S | B18: C | C18: 2025 年度單價：Sol | D18: 2.184 | E18: $/M | F18: Derived | G18: 1.672 | H18: 2.338 | I18: Cap_In!C279 | J18: API 主力與 ChatGPT 預設按付費 token 加權 | K18: 中
A19: IN_Px_A | B19: C | C19: 2025 年度單價：Astra（推理旗艦） | D19: 4.5 | E19: $/M | F19: Derived | G19: 3.3 | H19: 5.9 | I19: Cap_In!C280 | J19: v15.2 B2：用量加權 4.5（Azure 季別量指數 × GPT-5 後推理占比 ×2）；各模型 token 占比未公開 | K19: 高
A20: IN_Disc | B20: C | C20: 有效折扣（Batch／Flex 半價＋企業議價，加權） | D20: 0.2 | E20: % | F20: Assumed | G20: 0.1 | H20: 0.4 | I20: Cap_In!C12 | J20: Batch 半價 Verified；占比與企業折扣找不到 | K20: 高
A21: IN_MixP_L | B21: C | C21: 付費 token 層級組合：Luna | D21: 0.4 | E21: % | F21: — | I21: Cap_In!C31 | J21: OpenAI 模型 v0.5 tokenMix（Assumed）；三者合計 1 | K21: 中
A22: IN_MixP_S | B22: C | C22: 付費 token 層級組合：Sol | D22: 0.45 | E22: % | F22: — | I22: Cap_In!D31 | J22: 同上 | K22: 中
A23: IN_MixP_A | B23: C | C23: 付費 token 層級組合：Astra | D23: 0.15 | E23: % | F23: — | I23: Cap_In!E31 | J23: 同上；v15.2 B6 區間 0.10–0.30 | K23: 中
A24: IN_MixF_L | B24: C | C24: 免費 token 層級組合：Luna | D24: 0.9 | E24: % | F24: — | I24: Cap_In!C32 | J24: OpenAI 模型 v0.5 免費方案組合（Assumed） | K24: 中
A25: IN_MixF_S | B25: C | C25: 免費 token 層級組合：Sol | D25: 0.1 | E25: % | F25: — | I25: Cap_In!D32 | J25: 同上 | K25: 中
A26: IN_MixF_A | B26: C | C26: 免費 token 層級組合：Astra | D26: 0 | E26: % | F26: — | I26: Cap_In!E32 | J26: 同上 | K26: 低
A27: D. 需求 token（決定免費 ÷ 付費 token 比 r）
A28: IN_APItpm | B28: D | C28: API token 吞吐（2025-10 時點） | D28: 6 | E28: B tok/分 | F28: — | I28: SRC_Demand!C14 | J28: SRC_DEM_010；OpenAI 2025-10-06 公告 60 億 token／分（Interested-party） | K28: 低
A29: IN_APIratio | B29: D | C29: API 全年平均 ÷ 10 月時點值 | D29: 0.75 | E29: x | F29: Assumed | G29: 0.6 | H29: 0.9 | I29: Alloc_In!C14 | J29: Assumed | K29: 中
A30: IN_Prompts | B30: D | C30: ChatGPT 每日訊息數 | D30: 2.5 | E30: B 則/日 | F30: — | I30: SRC_Demand!C16 | J30: SRC_DEM_012；OpenAI 自述 25 億則／日 | K30: 低
A31: IN_Tau | B31: D | C31: 每則提示 token 數 τ | D31: 4000 | E31: tok | F31: Assumed | G31: 2000 | H31: 11000 | I31: Alloc_In!C15 | J31: Assumed；閉合解遠高於區間（L1_TokPerPromptClose） | K31: 中
A32: IN_FreeShare | B32: D | C32: ChatGPT token 中免費用戶占比 | D32: 0.6 | E32: % | F32: Assumed | G32: 0.4 | H32: 0.8 | I32: Alloc_In!C16 | J32: Assumed；token 口徑與支出口徑混用（Decisions SL46-28） | K32: 中
A33: E. 服務與快取參數（全層級共用）
A34: IN_Chi | B34: E | C34: 參考請求快取命中率 χ | D34: 0.55 | E34: % | F34: Assumed | G34: 0.3 | H34: 0.75 | I34: Cap_In!C13 | J34: Assumed；DeepSeek 2025-03 為 56.3%；2026 agent 流量約 88% | K34: 中
A35: IN_MTP_N | B35: E | C35: MTP 草稿數 N | D35: 3 | E35: tok | F35: Analogy | G35: 1 | H35: 5 | I35: Serving!C6 | J35: 原始數據 | K35: 低
A36: IN_MTP_a | B36: E | C36: 草稿 token 接受率 α | D36: 0.7 | E36: % | F36: 原始數據 | I36: Serving!C7 | J36: 原始數據 | K36: 低
A37: IN_HBMres | B37: E | C37: HBM 保留比例 | D37: 0.1 | E37: % | F37: Assumed | G37: 0.05 | H37: 0.2 | I37: Serving!C9 | K37: 低
A38: IN_NEcap | B38: E | C38: 非專家權重占可用 HBM 上限 | D38: 0.2 | E38: % | F38: Assumed | G38: 0.1 | H38: 0.3 | I38: Serving!C10 | K38: 低
A39: IN_Ecap | B39: E | C39: 專家權重占可用 HBM 上限 | D39: 0.4 | E39: % | F39: Assumed | G39: 0.3 | H39: 0.5 | I39: Serving!C11 | K39: 低
A40: IN_EPbytes | B40: E | C40: EP 啟用值 bytes／元素 | D40: 3 | E40: B | F40: Assumed | G40: 2 | H40: 4 | I40: Serving!C12 | K40: 低
A41: IN_KVeff | B41: E | C41: KV 讀取頻寬效率 | D41: 0.7 | E41: % | F41: Assumed | G41: 0.5 | H41: 0.85 | I41: Serving!C13 | K41: 低
A42: IN_EPeff | B42: E | C42: EP 通訊效率 | D42: 0.7 | E42: % | F42: Assumed | G42: 0.5 | H42: 0.85 | I42: Serving!C14 | K42: 低
A43: F. 校準係數（Calib 頁以 GB300 實測擬合；Hopper／GB200 以倍數換算）
A44: IN_EtaD0 | B44: F | C44: η_d 擬合值（GB300，decode 每序列算力效率） | D44: 0.035755033 | E44: % | F44: — | I44: Calib!C60 | J44: 以 InferenceX GB300 兩個實測點聯立解出（SemiAnalysis，Interested-party） | K44: 中
A45: IN_Lat0 | B45: F | C45: 每層每次前向固定延遲擬合值（GB300） | D45: 161.18534 | E45: µs | F45: — | I45: Calib!C62 | J45: 同上 | K45: 中
A46: IN_EtaP0 | B46: F | C46: η_p：prefill 達成峰值比例（基準） | D46: 0.3 | E46: % | F46: Analogy | G46: 0.15 | H46: 0.45 | I46: Calib!C5 | J46: Analogy | K46: 中
A47: IN_EtaDm_H | B47: F | C47: η_d 倍數：Hopper | D47: 1.2 | E47: x | F47: Derived | G47: 0.8 | H47: 1.6 | I47: Calib!C67 | J47: 吞吐為保守下界（獨立對照約實測 0.26–0.27 倍） | K47: 高
A48: IN_EtaDm_G | B48: F | C48: η_d 倍數：GB200 | D48: 1.15 | E48: x | F48: Derived | G48: 0.9 | H48: 1.45 | I48: Calib!D67 | J48: v15.2 B3：MLPerf v6.0 同軟體配對 1.13–1.27 | K48: 中
A49: IN_Latm_H | B49: F | C49: 每層延遲倍數：Hopper | D49: 1.5 | E49: x | F49: Assumed | G49: 1 | H49: 1.5 | I49: Calib!C68 | J49: Assumed | K49: 中
A50: IN_Latm_G | B50: F | C50: 每層延遲倍數：GB200 | D50: 1 | E50: x | F50: Assumed | G50: 1 | H50: 1.5 | I50: Calib!D68 | J50: 沿用 GB300 | K50: 中
A51: IN_EtaPm_H | B51: F | C51: η_p 倍數：Hopper（＝SRC_HW_019 ÷ SRC_HW_040） | D51: 0.49974735 | E51: x | F51: Derived（公式） | I51: Calib!C69 | J51: 原為公式（規格比），此處以值輸入 | K51: 低
A52: IN_EtaPm_G | B52: F | C52: η_p 倍數：GB200 | D52: 1 | E52: x | F52: Assumed | G52: 0.5 | H52: 1.5 | I52: Calib!D69 | K52: 低
A53: G. 硬體規格（Spec_Rack；H＝Hopper H100、G＝GB200 NVL72）
A54: IN_Peak_H | B54: G | C54: 計算用峰值：Hopper | D54: 1.979 | E54: PF/GPU | F54: — | I54: Spec_Rack!C35 | J54: 原始數據（規格表；NVIDIA 為利害關係方） | K54: 低
A55: IN_Peak_G | B55: G | C55: 計算用峰值：GB200 | D55: 10 | E55: PF/GPU | F55: — | I55: Spec_Rack!D35 | J55: 原始數據（規格表；NVIDIA 為利害關係方） | K55: 低
A56: IN_HBM_H | B56: G | C56: HBM 容量：Hopper | D56: 80 | E56: GB/GPU | F56: 原始數據 | I56: Spec_Rack!C25 | J56: 原始數據（規格表；NVIDIA 為利害關係方） | K56: 低
A57: IN_HBM_G | B57: G | C57: HBM 容量：GB200 | D57: 186 | E57: GB/GPU | F57: 原始數據（G0-2 保留） | I57: Spec_Rack!D25 | J57: 原始數據（規格表；NVIDIA 為利害關係方） | K57: 低
A58: IN_BW_H | B58: G | C58: HBM 頻寬：Hopper | D58: 3.35 | E58: TB/s/GPU | F58: 原始數據 | I58: Spec_Rack!C26 | J58: 原始數據（規格表；NVIDIA 為利害關係方） | K58: 低
A59: IN_BW_G | B59: G | C59: HBM 頻寬：GB200 | D59: 8 | E59: TB/s/GPU | F59: 原始數據 | I59: Spec_Rack!D26 | J59: 原始數據（規格表；NVIDIA 為利害關係方） | K59: 低
A60: IN_EPBW_H | B60: G | C60: EP 通訊頻寬（單向）：Hopper | D60: 0.05 | E60: TB/s/GPU | F60: 原始數據 | I60: Spec_Rack!C27 | J60: 原始數據（規格表；NVIDIA 為利害關係方） | K60: 低
A61: IN_EPBW_G | B61: G | C61: EP 通訊頻寬（單向）：GB200 | D61: 0.9 | E61: TB/s/GPU | F61: 原始數據 | I61: Spec_Rack!D27 | J61: 原始數據（規格表；NVIDIA 為利害關係方） | K61: 低
A62: IN_EPW_H | B62: G | C62: decode EP 基準寬度：Hopper | D62: 64 | E62: GPU | F62: Analogy | G62: 32 | H62: 144 | I62: Spec_Rack!C29 | J62: 原始數據（規格表；NVIDIA 為利害關係方） | K62: 低
A63: IN_EPW_G | B63: G | C63: decode EP 基準寬度：GB200 | D63: 32 | E63: GPU | F63: Analogy | G63: 16 | H63: 72 | I63: Spec_Rack!D29 | J63: 原始數據（規格表；NVIDIA 為利害關係方） | K63: 低
A64: IN_EB_H | B64: G | C64: 專家權重 bytes/param：Hopper | D64: 1 | E64: B | F64: 原始數據 | I64: Spec_Rack!C30 | J64: 原始數據（規格表；NVIDIA 為利害關係方） | K64: 低
A65: IN_EB_G | B65: G | C65: 專家權重 bytes/param：GB200 | D65: 0.5625 | E65: B | F65: 原始數據 | I65: Spec_Rack!D30 | J65: 原始數據（規格表；NVIDIA 為利害關係方） | K65: 低
A66: IN_NEB_H | B66: G | C66: 非專家權重 bytes/param：Hopper | D66: 1 | E66: B | F66: Assumed | G66: 1 | H66: 2 | I66: Spec_Rack!C31 | J66: 原始數據（規格表；NVIDIA 為利害關係方） | K66: 低
A67: IN_NEB_G | B67: G | C67: 非專家權重 bytes/param：GB200 | D67: 1 | E67: B | F67: Assumed | G67: 1 | H67: 2 | I67: Spec_Rack!D31 | J67: 原始數據（規格表；NVIDIA 為利害關係方） | K67: 低
A68: IN_PFG_H | B68: G | C68: 每 prefill 實例 GPU 數：Hopper | D68: 8 | E68: GPU | F68: Assumed | G68: 4 | H68: 16 | I68: Spec_Rack!C32 | J68: 原始數據（規格表；NVIDIA 為利害關係方） | K68: 低
A69: IN_PFG_G | B69: G | C69: 每 prefill 實例 GPU 數：GB200 | D69: 4 | E69: GPU | F69: Analogy | G69: 2 | H69: 8 | I69: Spec_Rack!D32 | J69: 原始數據（規格表；NVIDIA 為利害關係方） | K69: 低
A70: IN_GPR_H | B70: G | C70: GPU 封裝／架：Hopper | D70: 32 | E70: 顆 | F70: Decision | I70: Spec_Rack!C6 | J70: 原始數據（規格表；NVIDIA 為利害關係方） | K70: 低
A71: IN_GPR_G | B71: G | C71: GPU 封裝／架：GB200 | D71: 72 | E71: 顆 | F71: 原始數據 | I71: Spec_Rack!D6 | J71: 原始數據（規格表；NVIDIA 為利害關係方） | K71: 低
A72: IN_RackKW_H | B72: G | C72: 每架配電設計功率（基準）：Hopper | D72: 41 | E72: kW | F72: 原始數據（G0-2 保留） | G72: 38 | H72: 44 | I72: Spec_Rack!C9 | J72: 原始數據（規格表；NVIDIA 為利害關係方） | K72: 低
A73: IN_RackKW_G | B73: G | C73: 每架配電設計功率（基準）：GB200 | D73: 132 | E73: kW | F73: 原始數據 | G73: 120 | H73: 140 | I73: Spec_Rack!D9 | J73: 原始數據（規格表；NVIDIA 為利害關係方） | K73: 低
A74: IN_RackPx_H | B74: G | C74: 機架價格（基準）：Hopper | D74: 1.1 | E74: $M | F74: 原始數據（G0-2 保留） | G74: 0.9 | H74: 1.3 | I74: Spec_Rack!C12 | J74: 機架價格：產業報導與 ODM 報價區間（利害關係方） | K74: 高
A75: IN_RackPx_G | B75: G | C75: 機架價格（基準）：GB200 | D75: 3.1 | E75: $M | F75: 原始數據（G0-2 保留） | G75: 2.8 | H75: 3.4 | I75: Spec_Rack!D12 | J75: 機架價格：產業報導與 ODM 報價區間（利害關係方） | K75: 高
A76: H. 模型架構（Arch；L＝Luna、S＝Sol、A＝Astra）——頂層模型參數未揭露
A77: IN_Act_L | B77: H | C77: 啟用參數：Luna | D77: 13 | E77: B | F77: — | I77: Perf!C28 | J77: 代表架構（Sol＝DeepSeek V4-Pro 型）；Astra 啟用參數 180B 為 Assumed（60–250B） | K77: 中
A78: IN_Act_S | B78: H | C78: 啟用參數：Sol | D78: 49 | E78: B | F78: — | I78: Perf!D28 | J78: 代表架構（Sol＝DeepSeek V4-Pro 型）；Astra 啟用參數 180B 為 Assumed（60–250B） | K78: 中
A79: IN_Act_A | B79: H | C79: 啟用參數：Astra | D79: 180 | E79: B | F79: — | I79: Perf!E28 | J79: 代表架構（Sol＝DeepSeek V4-Pro 型）；Astra 啟用參數 180B 為 Assumed（60–250B） | K79: 高
A80: IN_Lay_L | B80: H | C80: 層數：Luna | D80: 43 | E80: 層 | F80: — | I80: Perf!C29 | J80: 代表架構參數（Arch 頁） | K80: 中
A81: IN_Lay_S | B81: H | C81: 層數：Sol | D81: 61 | E81: 層 | F81: — | I81: Perf!D29 | J81: 代表架構參數（Arch 頁） | K81: 中
A82: IN_Lay_A | B82: H | C82: 層數：Astra | D82: 100 | E82: 層 | F82: — | I82: Perf!E29 | J82: 代表架構參數（Arch 頁） | K82: 中
A83: IN_Dm_L | B83: H | C83: d_model：Luna | D83: 4096 | F83: — | I83: Perf!C30 | J83: 代表架構參數（Arch 頁） | K83: 中
A84: IN_Dm_S | B84: H | C84: d_model：Sol | D84: 7168 | F84: — | I84: Perf!D30 | J84: 代表架構參數（Arch 頁） | K84: 中
A85: IN_Dm_A | B85: H | C85: d_model：Astra | D85: 12288 | F85: — | I85: Perf!E30 | J85: 代表架構參數（Arch 頁） | K85: 中
A86: IN_Exp_L | B86: H | C86: 啟用 routed experts：Luna | D86: 6 | F86: — | I86: Perf!C31 | J86: 代表架構參數（Arch 頁） | K86: 中
A87: IN_Exp_S | B87: H | C87: 啟用 routed experts：Sol | D87: 6 | F87: — | I87: Perf!D31 | J87: 代表架構參數（Arch 頁） | K87: 中
A88: IN_Exp_A | B88: H | C88: 啟用 routed experts：Astra | D88: 16 | F88: — | I88: Perf!E31 | J88: 代表架構參數（Arch 頁） | K88: 中
A89: IN_NEP_L | B89: H | C89: 非專家參數：Luna | D89: 5.412 | E89: B | F89: — | I89: Perf!C32 | J89: 代表架構參數（Arch 頁） | K89: 中
A90: IN_NEP_S | B90: H | C90: 非專家參數：Sol | D90: 20.277778 | E90: B | F90: — | I90: Perf!D32 | J90: 代表架構參數（Arch 頁） | K90: 中
A91: IN_NEP_A | B91: H | C91: 非專家參數：Astra | D91: 49.072581 | E91: B | F91: — | I91: Perf!E32 | J91: 代表架構參數（Arch 頁） | K91: 高
A92: IN_EP_L | B92: H | C92: 專家參數：Luna | D92: 278.588 | E92: B | F92: — | I92: Perf!C33 | J92: 代表架構參數（Arch 頁） | K92: 中
A93: IN_EP_S | B93: H | C93: 專家參數：Sol | D93: 1579.7222 | E93: B | F93: — | I93: Perf!D33 | J93: 代表架構參數（Arch 頁） | K93: 中
A94: IN_EP_A | B94: H | C94: 專家參數：Astra | D94: 3950.9274 | E94: B | F94: — | I94: Perf!E33 | J94: 代表架構參數（Arch 頁） | K94: 高
A95: IN_KV_L | B95: H | C95: KV bytes/token：Luna | D95: 2795 | E95: B | F95: — | I95: Perf!C34 | J95: 代表架構參數（Arch 頁） | K95: 中
A96: IN_KV_S | B96: H | C96: KV bytes/token：Sol | D96: 3965 | E96: B | F96: — | I96: Perf!D34 | J96: 代表架構參數（Arch 頁） | K96: 中
A97: IN_KV_A | B97: H | C97: KV bytes/token：Astra | D97: 57600 | E97: B | F97: — | I97: Perf!E34 | J97: 代表架構參數（Arch 頁） | K97: 中
A98: IN_AF_L | B98: H | C98: 注意力 FLOPs／被注意 token：Luna | D98: 5636096 | E98: FLOP | F98: — | I98: Perf!C35 | J98: 代表架構參數（Arch 頁） | K98: 中
A99: IN_AF_S | B99: H | C99: 注意力 FLOPs／被注意 token：Sol | D99: 15990784 | E99: FLOP | F99: — | I99: Perf!D35 | J99: 代表架構參數（Arch 頁） | K99: 中
A100: IN_AF_A | B100: H | C100: 注意力 FLOPs／被注意 token：Astra | D100: 4915200 | E100: FLOP | F100: — | I100: Perf!E35 | J100: 代表架構參數（Arch 頁） | K100: 中
... A112: IN_Win_A | B112: H | C112: 其他層滑動窗：Astra | D112: 0 | E112: tok | F112: — | I112: Perf!E39 | J112: 代表架構參數（Arch 頁） | K112: 中
...

Sheet 3_m重算
A1: m 的逐步重算（全部為公式；改 2_輸入 的藍字即可看到每一步怎麼變）
A2: m（L1_MFleet，機隊變現率）＝ OpenAI 2025 營收 ÷（機隊付費 token × 2025 機隊口徑單價）。每一步列出對應的 Tokenomics 格與原值，最後一欄為差異。
A4: 步驟 | B4: 項目 | C4: 白話說明與公式 | D4: 值 | E4: 單位 | F4: 原活頁簿位置 | G4: 原活頁簿值 | H4: 差異
A5: 第 4 層：每 GW 產能（由 5_每GW產出 的 roofline 結果組合）
A6: S1 | B6: Hopper 每 GW 年產能（付費，基準利用率） | C6: ＝IF_Util ÷ Σ（付費層級組合 ÷ 該層級每 GW 產出）。調和平均：每 GW 時間按層級組合分給 Luna／Sol／Astra，大模型每 token 耗時多。 | D6: =IN_Util/(IN_MixP_L/5_每GW產出!D$67+IN_MixP_S/5_每GW產出!E$67+IN_MixP_A/5_每GW產出!F$67) -> 1.5395391e+10 | E6: M tok/年 | F6: Alloc!C29 | G6: 1.5395391e+10 | H6: =IF(G6=0,D6-G6,D6/G6-1) -> 0
A7: S2 | B7: GB200 每 GW 年產能（付費） | C7: 同上，GB200 欄 | D7: =IN_Util/(IN_MixP_L/5_每GW產出!G$67+IN_MixP_S/5_每GW產出!H$67+IN_MixP_A/5_每GW產出!I$67) -> 7.5756719e+10 | E7: M tok/年 | F7: Alloc!D29 | G7: 7.5756719e+10 | H7: =IF(G7=0,D7-G7,D7/G7-1) -> 0
A8: S3 | B8: Hopper 每 GW 年產能（免費） | C8: 同上，用免費層級組合（Luna 0.9、Sol 0.1） | D8: =IN_Util/(IN_MixF_L/5_每GW產出!D$67+IN_MixF_S/5_每GW產出!E$67+IN_MixF_A/5_每GW產出!F$67) -> 5.4582805e+10 | E8: M tok/年 | F8: Alloc!C30 | G8: 5.4582805e+10 | H8: =IF(G8=0,D8-G8,D8/G8-1) -> 0
A9: S4 | B9: GB200 每 GW 年產能（免費） | C9: 同上 | D9: =IN_Util/(IN_MixF_L/5_每GW產出!G$67+IN_MixF_S/5_每GW產出!H$67+IN_MixF_A/5_每GW產出!I$67) -> 2.6976193e+11 | E9: M tok/年 | F9: Alloc!D30 | G9: 2.6976193e+11 | H9: =IF(G9=0,D9-G9,D9/G9-1) -> 0
A10: S5 | B10: 機隊每 GW 年產能（付費） | C10: ＝Σ 世代 GW 占比 × 各世代產能（Hopper 0.6、GB200 0.4） | D10: =(IN_ShareH*D6+IN_ShareG*D7)/(IN_ShareH+IN_ShareG) -> 3.9539922e+10 | E10: M tok/年 | F10: Alloc!C33 | G10: 3.9539922e+10 | H10: =IF(G10=0,D10-G10,D10/G10-1) -> 0
A11: S6 | B11: 機隊每 GW 年產能（免費） | C11: 同上 | D11: =(IN_ShareH*D8+IN_ShareG*D9)/(IN_ShareH+IN_ShareG) -> 1.4065445e+11 | E11: M tok/年 | F11: Alloc!C34 | G11: 1.4065445e+11 | H11: =IF(G11=0,D11-G11,D11/G11-1) -> 0
A12: 第 3 層：免費 ÷ 付費 token 比 r（需求面）
A13: S7 | B13: API 需求 token（全年） | C13: ＝API 每分鐘 token × 525,600 分鐘 × 全年平均比 | D13: =IN_APItpm*1000000000*525600*IN_APIratio/1000000 -> 2365200000 | E13: M tok/年 | F13: Alloc!C5 | G13: 2365200000 | H13: =IF(G13=0,D13-G13,D13/G13-1) -> 0
A14: S8 | B14: ChatGPT 需求 token（全年） | C14: ＝每日訊息數 × 每則 token τ × 365 | D14: =IN_Prompts*1000000000*IN_Tau*365/1000000 -> 3650000000 | E14: M tok/年 | F14: Alloc!C6 | G14: 3650000000 | H14: =IF(G14=0,D14-G14,D14/G14-1) -> 0
A15: S9 | B15: ChatGPT 免費 token | C15: ＝ChatGPT token × 免費占比 | D15: =D14*IN_FreeShare -> 2190000000 | E15: M tok/年 | F15: Alloc!C7 | G15: 2190000000 | H15: =IF(G15=0,D15-G15,D15/G15-1) -> 0
A16: S10 | B16: 付費 token（API＋ChatGPT 付費） | C16: ＝API ＋ ChatGPT − 免費 | D16: =D13+D14-D15 -> 3825200000 | E16: M tok/年 | F16: Alloc!C9 | G16: 3825200000 | H16: =IF(G16=0,D16-G16,D16/G16-1) -> 0
A17: S11 | B17: 免費 ÷ 付費 token 比 r | C17: 機隊產能要先扣掉服務免費用戶的部分；r 越大，留給付費 token 的產能越少 | D17: =D15/D16 -> 0.57251908 | E17: x | F17: Cap_In!C112 | G17: 0.57251908 | H17: =IF(G17=0,D17-G17,D17/G17-1) -> 0
A18: 第 2 層：服務 GW（支出路線）與利用率
A19: S12 | B19: 機隊每 GW 年持有成本（世代加權） | C19: ＝Σ 世代占比 × 各世代每 GW 年經濟持有成本（4_持有成本） | D19: =(IN_ShareH*4_持有成本!D$34+IN_ShareG*4_持有成本!E$34)/(IN_ShareH+IN_ShareG) -> 9.3531186 | E19: $B/GW·年
A20: S13 | B20: 支出路線服務 GW | C20: ＝推論支出 ÷ 每 GW 年持有成本：OpenAI 花在服務推論的錢，等於擁有多少 GW 的持有成本 | D20: =IN_Spend/D19 -> 0.89809617 | E20: GW | F20: Alloc!C70 | G20: 0.89809617 | H20: =IF(G20=0,D20-G20,D20/G20-1) -> 0
A21: S14 | B21: 有效服務 GW（經計價倍數與 κ） | C21: ＝服務 GW ÷ 計價倍數 × κ。計價倍數 <1 表示 Azure 計價低於經濟持有成本，所以同樣的錢買到更多 GW | D21: =D20/IN_SpendBasis*IN_Kappa -> 1.0565837 | E21: GW | F21: Cap_In!C109 | G21: 1.0565837 | H21: =IF(G21=0,D21-G21,D21/G21-1) -> 0
A22: S15 | B22: 利用率修正 | C22: ＝實際利用率 × 生產折減 ÷ IF_Util（把每 GW 產能的「基準利用率」口徑換成實際） | D22: =IN_UtilAct*IN_ProdDerate/IN_Util -> 0.58083333 | E22: x | F22: Cap_In!C114 | G22: 0.58083333 | H22: =IF(G22=0,D22-G22,D22/G22-1) -> 0
A23: S16 | B23: 機隊付費 token | C23: ＝有效服務 GW × 利用率修正 ÷（1 ÷ 付費產能 ＋ r ÷ 免費產能）。分母：每產出 1 個付費 token，同時要產出 r 個免費 token，各自耗用 GW 年 | D23: =D21*D22/(1/D10+D17/D11) -> 2.0901639e+10 | E23: M tok/年 | F23: Cap_In!C116 | G23: 2.0901639e+10 | H23: =IF(G23=0,D23-G23,D23/G23-1) -> 0
A24: 第 1 層：單價、token 與 m
A25: S17 | B25: 各世代付費 token 2025 混合有效單價 | C25: ＝Σ 付費層級組合 × 2025 層級單價 ×（1 − 有效折扣） | D25: =(IN_MixP_L*IN_Px_L+IN_MixP_S*IN_Px_S+IN_MixP_A*IN_Px_A)*(1-IN_Disc) -> 1.35936 | E25: $/M tok | F25: Alloc!C148 | G25: 1.35936 | H25: =IF(G25=0,D25-G25,D25/G25-1) -> 0
A26: S18 | B26: 機隊口徑 2025 混合有效單價 | C26: ＝以各世代付費產能加權的 S17（所有層級皆可達時，各世代同值） | D26: =(IN_ShareH*D6*D25+IN_ShareG*D7*D25)/(IN_ShareH*D6+IN_ShareG*D7) -> 1.35936 | E26: $/M tok | F26: Alloc!C151 | G26: 1.35936 | H26: =IF(G26=0,D26-G26,D26/G26-1) -> 0
A27: S19 | B27: 營收折合的 token（按 2025 牌價扣折扣） | C27: ＝營收 ÷ 混合有效單價：如果每個 token 都照牌價收費，營收只買得到這麼多 token | D27: =IN_Rev*1000000000/D26 -> 9.6148187e+09 | E27: M tok/年
A28: m | B28: m（機隊變現率） | C28: ＝營收 ÷（機隊付費 token × 混合有效單價）＝ S19 ÷ S16 | D28: =IN_Rev*1000000000/(D23*D26) -> 0.46000311 | E28: x | F28: Cap_In!C119 | G28: 0.46000311 | H28: =IF(G28=0,D28-G28,D28/G28-1) -> 0
A29: floor | B29: 對照：m 的物理下限（機隊付費 token 上限讀法） | C29: Tokenomics 以 MAX(m, 下限) 輸出；基準下 m 高於下限，所以下限不綁定 | D29: =G29 -> 0.33914788 | E29: x | F29: Cap_In!C121 | G29: 0.33914788 | H29: =IF(G29=0,D29-G29,D29/G29-1) -> 0
A30: L1 | B30: 對照：L1 頁 L1_MFleet | D30: =D28 -> 0.46000311 | E30: x | F30: L1!D78 | G30: 0.46000311 | H30: =IF(G30=0,D30-G30,D30/G30-1) -> 0

Sheet 4_持有成本
A1: 每 GW 年經濟持有成本（資本回收年金＋營運費用）
A2: 公式與 Tokenomics DC_Cost 頁（基準成本欄）相同；1 GW IT 電力。
A4: 列 | B4: 項目 | C4: 單位 | D4: Hopper H100 | E4: GB200 NVL72 | F4: 公式說明
A5: A. 規模
A6: mw | B6: IT 電力 | C6: MW | D6: =1000 -> 1000 | E6: =1000 -> 1000 | F6: 1 GW
A7: rmw | B7: 機架可用 IT 電力 | C7: MW | D7: =D6*(1-IN_ITout) -> 920 | E7: =E6*(1-IN_ITout) -> 920 | F7: 扣除機架外 IT 電力
A8: racks | B8: 機架數 | C8: 架 | D8: =FLOOR(D7*1000/IN_RackKW_H,1) -> 22439 | E8: =FLOOR(E7*1000/IN_RackKW_G,1) -> 6969 | F8: 可用 IT 電力 ÷ 每架功率，取整
A9: gpus | B9: GPU 數 | C9: 顆 | D9: =D8*IN_GPR_H -> 718048 | E9: =E8*IN_GPR_G -> 501768
A10: B. 資本支出
A11: rack | B11: 機架 | C11: $B | D11: =D8*IN_RackPx_H/1000 -> 24.6829 | E11: =E8*IN_RackPx_G/1000 -> 21.6039 | F11: 機架數 × 機架單價
A12: net | B12: Scale-out 網路 | C12: $B | D12: =D11*IN_Net -> 2.46829 | E12: =E11*IN_Net -> 2.16039
A13: stor | B13: 儲存與管理 | C13: $B | D13: =D9*IN_Stor/1000000000 -> 0.359024 | E13: =E9*IN_Stor/1000000000 -> 0.250884
A14: it | B14: IT 設備小計 | C14: $B | D14: =D11+D12+D13 -> 27.510214 | E14: =E11+E12+E13 -> 24.015174
A15: land | B15: 土地 | C15: $B | D15: =D6*IN_Land/1000 -> 0.02 | E15: =E6*IN_Land/1000 -> 0.02
A16: bldg | B16: 建物與基地 | C16: $B | D16: =D6*IN_Bldg/1000 -> 3.6 | E16: =E6*IN_Bldg/1000 -> 3.6
A17: pwr | B17: 電力設施 | C17: $B | D17: =D6*IN_Pwr/1000 -> 4.5 | E17: =E6*IN_Pwr/1000 -> 4.5
A18: mech | B18: 機械與散熱 | C18: $B | D18: =D6*IN_Mech/1000 -> 2.5 | E18: =E6*IN_Mech/1000 -> 2.5
A19: fib | B19: 光纖與保全 | C19: $B | D19: =D6*IN_Fib/1000 -> 0.4 | E19: =E6*IN_Fib/1000 -> 0.4
A20: soft | B20: 設計、管理與預備費 | C20: $B | D20: =(D16+D17+D18+D19)*IN_Soft -> 1.65 | E20: =(E16+E17+E18+E19)*IN_Soft -> 1.65
A21: fac | B21: 廠房小計 | C21: $B | D21: =D15+D16+D17+D18+D19+D20 -> 12.67 | E21: =E15+E16+E17+E18+E19+E20 -> 12.67
A22: capex | B22: 總資本支出 | C22: $B | D22: =D14+D21 -> 40.180214 | E22: =E14+E21 -> 36.685174
A23: C. 營運費用（年）
A24: elec | B24: 電費 | C24: $B | D24: =D6*1000*IN_Load*IN_PUE*8760*IN_Elec/1000000000 -> 0.672768 | E24: =E6*1000*IN_Load*IN_PUE*8760*IN_Elec/1000000000 -> 0.672768 | F24: IT 電力 × 平均負載 × PUE × 8760 × 電價
A25: itm | B25: IT 維護 | C25: $B | D25: =D14*IN_ITmaint -> 0.43259841 | E25: =E14*IN_ITmaint -> 0.37763887
A26: fm | B26: 廠房維護 | C26: $B | D26: =D21*IN_Fmaint -> 0.2534 | E26: =E21*IN_Fmaint -> 0.2534
A27: ops | B27: 人員、軟體、水與耗材 | C27: $B | D27: =(IN_Staff*D6/1000+IN_SW*D6/1000+IN_Water*D6)/1000 -> 0.325 | E27: =(IN_Staff*E6/1000+IN_SW*E6/1000+IN_Water*E6)/1000 -> 0.325
A28: tax | B28: 財產稅與保險 | C28: $B | D28: =D22*IN_Tax -> 0.20090107 | E28: =E22*IN_Tax -> 0.18342587
A29: opex | B29: 營運費用小計 | C29: $B | D29: =D24+D25+D26+D27+D28 -> 1.8846675 | E29: =E24+E25+E26+E27+E28 -> 1.8122327
A30: D. 經濟口徑年持有成本
A31: crf | B31: IT 資本回收係數 | C31: x | D31: =IN_WACC/(1-(1+IN_WACC)^(-IN_ITlife)) -> 0.22960738 | E31: =IN_WACC/(1-(1+IN_WACC)^(-IN_ITlife)) -> 0.22960738 | F31: WACC ÷（1 −（1＋WACC）^−年限）：把 IT 資本攤成等額年金
A32: itrec | B32: IT 資本回收 | C32: $B | D32: =D14*D31 -> 6.3165482 | E32: =E14*E31 -> 5.5140612
A33: facrec | B33: 廠房資本回收（土地按 WACC 計機會成本） | C33: $B | D33: =(D16*IN_WACC/(1-(1+IN_WACC)^(-IN_L_bldg))+D17*IN_WACC/(1-(1+IN_WACC)^(-IN_L_pwr))+D18*IN_WACC/(1-(1+IN_WACC)^(-IN_L_mech))+D19*IN_WACC/(1-(1+IN_WACC)^(-IN_L_fib)))*(1+IN_Soft)+D15*IN_WACC -> 1.5018716 | E33: =(E16*IN_WACC/(1-(1+IN_WACC)^(-IN_L_bldg))+E17*IN_WACC/(1-(1+IN_WACC)^(-IN_L_pwr))+E18*IN_WACC/(1-(1+IN_WACC)^(-IN_L_mech))+E19*IN_WACC/(1-(1+IN_WACC)^(-IN_L_fib)))*(1+IN_Soft)+E15*IN_WACC -> 1.5018716
A34: hold | B34: 每 GW 年經濟持有成本 | C34: $B/GW·年 | D34: =D32+D33+D29 -> 9.7030873 | E34: =E32+E33+E29 -> 8.8281656 | F34: ＝ Tokenomics 的 IF_HoldEcon（AL_HoldGen）
B35: 對照：Tokenomics v17.0 原值（Alloc 第 39 列） | D35: 9.7030873 | E35: 8.8281656
B36: 差異（本頁 ÷ 原值 − 1） | D36: =D34/D35-1 -> 0 | E36: =E34/E35-1 -> 0

Sheet 5_每GW產出
A1: 每 GW 年產出（roofline）：每請求 GPU 秒 → 每架 tok/s → 每 GW M tok/年（100% 利用率）
A2: 六個案例＝Hopper／GB200 × Luna／Sol／Astra。公式與 Tokenomics Perf 頁逐列相同；最後兩列與原活頁簿比對。綠字＝連結 2_輸入；黑字＝本頁公式。
A4: 列 | B4: 項目 | C4: 單位 | D4: Hopper Luna | E4: Hopper Sol | F4: Hopper Astra | G4: GB200 Luna | H4: GB200 Sol | I4: GB200 Astra | J4: 公式說明（物理意義）
A5: A. 規格（每 GPU）
A6: peak | B6: 計算用峰值 | C6: PF/GPU | D6: =IN_Peak_H -> 1.979 | E6: =IN_Peak_H -> 1.979 | F6: =IN_Peak_H -> 1.979 | G6: =IN_Peak_G -> 10 | H6: =IN_Peak_G -> 10 | I6: =IN_Peak_G -> 10
A7: hbm | B7: HBM 容量 | C7: GB | D7: =IN_HBM_H -> 80 | E7: =IN_HBM_H -> 80 | F7: =IN_HBM_H -> 80 | G7: =IN_HBM_G -> 186 | H7: =IN_HBM_G -> 186 | I7: =IN_HBM_G -> 186
A8: bw | B8: HBM 頻寬 | C8: TB/s | D8: =IN_BW_H -> 3.35 | E8: =IN_BW_H -> 3.35 | F8: =IN_BW_H -> 3.35 | G8: =IN_BW_G -> 8 | H8: =IN_BW_G -> 8 | I8: =IN_BW_G -> 8
A9: epbw | B9: EP 通訊頻寬 | C9: TB/s | D9: =IN_EPBW_H -> 0.05 | E9: =IN_EPBW_H -> 0.05 | F9: =IN_EPBW_H -> 0.05 | G9: =IN_EPBW_G -> 0.9 | H9: =IN_EPBW_G -> 0.9 | I9: =IN_EPBW_G -> 0.9
A10: epw | B10: decode EP 基準寬度 | C10: GPU | D10: =IN_EPW_H -> 64 | E10: =IN_EPW_H -> 64 | F10: =IN_EPW_H -> 64 | G10: =IN_EPW_G -> 32 | H10: =IN_EPW_G -> 32 | I10: =IN_EPW_G -> 32
A11: eb | B11: 專家權重 bytes/param | C11: B | D11: =IN_EB_H -> 1 | E11: =IN_EB_H -> 1 | F11: =IN_EB_H -> 1 | G11: =IN_EB_G -> 0.5625 | H11: =IN_EB_G -> 0.5625 | I11: =IN_EB_G -> 0.5625
A12: neb | B12: 非專家權重 bytes/param | C12: B | D12: =IN_NEB_H -> 1 | E12: =IN_NEB_H -> 1 | F12: =IN_NEB_H -> 1 | G12: =IN_NEB_G -> 1 | H12: =IN_NEB_G -> 1 | I12: =IN_NEB_G -> 1
A13: pfg | B13: 每 prefill 實例 GPU 數 | C13: GPU | D13: =IN_PFG_H -> 8 | E13: =IN_PFG_H -> 8 | F13: =IN_PFG_H -> 8 | G13: =IN_PFG_G -> 4 | H13: =IN_PFG_G -> 4 | I13: =IN_PFG_G -> 4
A14: gpr | B14: GPU 封裝／架 | C14: 顆 | D14: =IN_GPR_H -> 32 | E14: =IN_GPR_H -> 32 | F14: =IN_GPR_H -> 32 | G14: =IN_GPR_G -> 72 | H14: =IN_GPR_G -> 72 | I14: =IN_GPR_G -> 72
A15: rpg | B15: 每 GW 機架數 | C15: 架 | D15: =4_持有成本!D$8 -> 22439 | E15: =4_持有成本!D$8 -> 22439 | F15: =4_持有成本!D$8 -> 22439 | G15: =4_持有成本!E$8 -> 6969 | H15: =4_持有成本!E$8 -> 6969 | I15: =4_持有成本!E$8 -> 6969 | J15: 來自 4_持有成本（機架可用 IT 電力 ÷ 每架功率，取整）
A16: B. 架構
A17: act | B17: 啟用參數 | C17: B | D17: =IN_Act_L -> 13 | E17: =IN_Act_S -> 49 | F17: =IN_Act_A -> 180 | G17: =IN_Act_L -> 13 | H17: =IN_Act_S -> 49 | I17: =IN_Act_A -> 180
A18: lay | B18: 層數 | C18: 層 | D18: =IN_Lay_L -> 43 | E18: =IN_Lay_S -> 61 | F18: =IN_Lay_A -> 100 | G18: =IN_Lay_L -> 43 | H18: =IN_Lay_S -> 61 | I18: =IN_Lay_A -> 100
A19: dm | B19: d_model | D19: =IN_Dm_L -> 4096 | E19: =IN_Dm_S -> 7168 | F19: =IN_Dm_A -> 12288 | G19: =IN_Dm_L -> 4096 | H19: =IN_Dm_S -> 7168 | I19: =IN_Dm_A -> 12288
A20: exp | B20: 啟用 routed experts | D20: =IN_Exp_L -> 6 | E20: =IN_Exp_S -> 6 | F20: =IN_Exp_A -> 16 | G20: =IN_Exp_L -> 6 | H20: =IN_Exp_S -> 6 | I20: =IN_Exp_A -> 16
A21: nep | B21: 非專家參數 | C21: B | D21: =IN_NEP_L -> 5.412 | E21: =IN_NEP_S -> 20.277778 | F21: =IN_NEP_A -> 49.072581 | G21: =IN_NEP_L -> 5.412 | H21: =IN_NEP_S -> 20.277778 | I21: =IN_NEP_A -> 49.072581
A22: ep | B22: 專家參數 | C22: B | D22: =IN_EP_L -> 278.588 | E22: =IN_EP_S -> 1579.7222 | F22: =IN_EP_A -> 3950.9274 | G22: =IN_EP_L -> 278.588 | H22: =IN_EP_S -> 1579.7222 | I22: =IN_EP_A -> 3950.9274
A23: kv | B23: KV bytes/token | C23: B | D23: =IN_KV_L -> 2795 | E23: =IN_KV_S -> 3965 | F23: =IN_KV_A -> 57600 | G23: =IN_KV_L -> 2795 | H23: =IN_KV_S -> 3965 | I23: =IN_KV_A -> 57600
A24: af | B24: 注意力 FLOPs／被注意 token | C24: FLOP | D24: =IN_AF_L -> 5636096 | E24: =IN_AF_S -> 15990784 | F24: =IN_AF_A -> 4915200 | G24: =IN_AF_L -> 5636096 | H24: =IN_AF_S -> 15990784 | I24: =IN_AF_A -> 4915200
A25: fa | B25: 全注意力層比例 | C25: % | D25: =IN_FA_L -> 0.512 | E25: =IN_FA_S -> 0.492 | F25: =IN_FA_A -> 1 | G25: =IN_FA_L -> 0.512 | H25: =IN_FA_S -> 0.492 | I25: =IN_FA_A -> 1
A26: span | B26: 全注意力跨度上限 | C26: tok | D26: =IN_Span_L -> 4224 | E26: =IN_Span_S -> 4224 | F26: =IN_Span_A -> 0 | G26: =IN_Span_L -> 4224 | H26: =IN_Span_S -> 4224 | I26: =IN_Span_A -> 0
A27: cmp | B27: 其他層壓縮比 | C27: x | D27: =IN_Cmp_L -> 128 | E27: =IN_Cmp_S -> 128 | F27: =IN_Cmp_A -> 1 | G27: =IN_Cmp_L -> 128 | H27: =IN_Cmp_S -> 128 | I27: =IN_Cmp_A -> 1
A28: win | B28: 其他層滑動窗 | C28: tok | D28: =IN_Win_L -> 128 | E28: =IN_Win_S -> 128 | F28: =IN_Win_A -> 0 | G28: =IN_Win_L -> 128 | H28: =IN_Win_S -> 128 | I28: =IN_Win_A -> 0
A29: C. 服務等級、參考請求、校準
A30: slo | B30: SLO 每用戶 decode 速度下限 | C30: tok/s | D30: =IN_SLO_L -> 84.300059 | E30: =IN_SLO_S -> 43.311661 | F30: =IN_SLO_A -> 40.83136 | G30: =IN_SLO_L -> 84.300059 | H30: =IN_SLO_S -> 43.311661 | I30: =IN_SLO_A -> 40.83136
A31: ttft | B31: TTFT 上限 | C31: s | D31: =IN_TTFT_L -> 2 | E31: =IN_TTFT_S -> 3 | F31: =IN_TTFT_A -> 5 | G31: =IN_TTFT_L -> 2 | H31: =IN_TTFT_S -> 3 | I31: =IN_TTFT_A -> 5
A32: isl | B32: 參考 ISL | C32: tok | D32: =IN_ISL_L -> 8192 | E32: =IN_ISL_S -> 16384 | F32: =IN_ISL_A -> 32768 | G32: =IN_ISL_L -> 8192 | H32: =IN_ISL_S -> 16384 | I32: =IN_ISL_A -> 32768
A33: osl | B33: 參考 OSL（含思考） | C33: tok | D33: =IN_OSL_L -> 1024 | E33: =IN_OSL_S -> 2048 | F33: =IN_OSL_A -> 4096 | G33: =IN_OSL_L -> 1024 | H33: =IN_OSL_S -> 2048 | I33: =IN_OSL_A -> 4096
A34: ctx | B34: decode 平均上下文 | C34: tok | D34: =D32+D33/2 -> 8704 | E34: =E32+E33/2 -> 17408 | F34: =F32+F33/2 -> 34816 | G34: =G32+G33/2 -> 8704 | H34: =H32+H33/2 -> 17408 | I34: =I32+I33/2 -> 34816 | J34: ISL ＋ OSL ÷ 2（輸出過程中上下文由 ISL 長到 ISL＋OSL）
A35: ppos | B35: prefill 平均位置 | C35: tok | D35: =D32/2 -> 4096 | E35: =E32/2 -> 8192 | F35: =F32/2 -> 16384 | G35: =G32/2 -> 4096 | H35: =H32/2 -> 8192 | I35: =I32/2 -> 16384 | J35: ISL ÷ 2
A36: acc | B36: 每步期望接受 token a | C36: tok | D36: =(1-IN_MTP_a^(IN_MTP_N+1))/(1-IN_MTP_a) -> 2.533 | E36: =(1-IN_MTP_a^(IN_MTP_N+1))/(1-IN_MTP_a) -> 2.533 | F36: =(1-IN_MTP_a^(IN_MTP_N+1))/(1-IN_MTP_a) -> 2.533 | G36: =(1-IN_MTP_a^(IN_MTP_N+1))/(1-IN_MTP_a) -> 2.533 | H36: =(1-IN_MTP_a^(IN_MTP_N+1))/(1-IN_MTP_a) -> 2.533 | I36: =(1-IN_MTP_a^(IN_MTP_N+1))/(1-IN_MTP_a) -> 2.533 | J36: MTP 推測解碼：(1 − α^(N+1)) ÷ (1 − α)
A37: etap | B37: η_p（prefill 占峰值） | C37: % | D37: =IN_EtaP0*IN_EtaPm_H -> 0.1499242 | E37: =IN_EtaP0*IN_EtaPm_H -> 0.1499242 | F37: =IN_EtaP0*IN_EtaPm_H -> 0.1499242 | G37: =IN_EtaP0*IN_EtaPm_G -> 0.3 | H37: =IN_EtaP0*IN_EtaPm_G -> 0.3 | I37: =IN_EtaP0*IN_EtaPm_G -> 0.3 | J37: η_p 基準 × 世代倍數（生產折減在本頁＝1，另於 3_m重算乘入）
A38: etad | B38: η_d（decode 每序列算力效率） | C38: % | D38: =IN_EtaD0*IN_EtaDm_H -> 0.04290604 | E38: =IN_EtaD0*IN_EtaDm_H -> 0.04290604 | F38: =IN_EtaD0*IN_EtaDm_H -> 0.04290604 | G38: =IN_EtaD0*IN_EtaDm_G -> 0.041118289 | H38: =IN_EtaD0*IN_EtaDm_G -> 0.041118289 | I38: =IN_EtaD0*IN_EtaDm_G -> 0.041118289 | J38: GB300 擬合值 × 世代倍數（GB200＝Calib D67）
A39: lat | B39: 每層每次前向固定延遲 | C39: µs | D39: =IN_Lat0*IN_Latm_H -> 241.77801 | E39: =IN_Lat0*IN_Latm_H -> 241.77801 | F39: =IN_Lat0*IN_Latm_H -> 241.77801 | G39: =IN_Lat0*IN_Latm_G -> 161.18534 | H39: =IN_Lat0*IN_Latm_G -> 161.18534 | I39: =IN_Lat0*IN_Latm_G -> 161.18534 | J39: GB300 擬合值 × 世代倍數
A40: D. 每 token 計算量
A41: dat | B41: decode 被注意 token 數 | C41: tok | D41: =D25*IF(D26=0,D34,MIN(D34,D26))+(1-D25)*(D34/D27+D28) -> 2258.336 | E41: =E25*IF(E26=0,E34,MIN(E34,E26))+(1-E25)*(E34/E27+E28) -> 2212.32 | F41: =F25*IF(F26=0,F34,MIN(F34,F26))+(1-F25)*(F34/F27+F28) -> 34816 | G41: =G25*IF(G26=0,G34,MIN(G34,G26))+(1-G25)*(G34/G27+G28) -> 2258.336 | H41: =H25*IF(H26=0,H34,MIN(H34,H26))+(1-H25)*(H34/H27+H28) -> 2212.32 | I41: =I25*IF(I26=0,I34,MIN(I34,I26))+(1-I25)*(I34/I27+I28) -> 34816 | J41: 全注意力層看 min(上下文, 跨度上限)；其他層看 上下文 ÷ 壓縮比 ＋ 滑動窗
A42: dfl | B42: decode FLOPs/token | C42: GFLOP | D42: =(2*D17*1000000000+D24*D41)/1000000000 -> 38.728198 | E42: =(2*E17*1000000000+E24*E41)/1000000000 -> 133.37673 | F42: =(2*F17*1000000000+F24*F41)/1000000000 -> 531.1276 | G42: =(2*G17*1000000000+G24*G41)/1000000000 -> 38.728198 | H42: =(2*H17*1000000000+H24*H41)/1000000000 -> 133.37673 | I42: =(2*I17*1000000000+I24*I41)/1000000000 -> 531.1276 | J42: 2 × 啟用參數（矩陣乘）＋ 注意力 FLOPs × 被注意 token
A43: pat | B43: prefill 被注意 token 數 | C43: tok | D43: =D25*IF(D26=0,D35,MIN(D35,D26))+(1-D25)*(D35/D27+D28) -> 2175.232 | E43: =E25*IF(E26=0,E35,MIN(E35,E26))+(1-E25)*(E35/E27+E28) -> 2175.744 | F43: =F25*IF(F26=0,F35,MIN(F35,F26))+(1-F25)*(F35/F27+F28) -> 16384 | G43: =G25*IF(G26=0,G35,MIN(G35,G26))+(1-G25)*(G35/G27+G28) -> 2175.232 | H43: =H25*IF(H26=0,H35,MIN(H35,H26))+(1-H25)*(H35/H27+H28) -> 2175.744 | I43: =I25*IF(I26=0,I35,MIN(I35,I26))+(1-I25)*(I35/I27+I28) -> 16384 | J43: 同上，以 prefill 平均位置計
A44: pfl | B44: prefill FLOPs/token | C44: GFLOP | D44: =(2*D17*1000000000+D24*D43)/1000000000 -> 38.259816 | E44: =(2*E17*1000000000+E24*E43)/1000000000 -> 132.79185 | F44: =(2*F17*1000000000+F24*F43)/1000000000 -> 440.53064 | G44: =(2*G17*1000000000+G24*G43)/1000000000 -> 38.259816 | H44: =(2*H17*1000000000+H24*H43)/1000000000 -> 132.79185 | I44: =(2*I17*1000000000+I24*I43)/1000000000 -> 440.53064
A45: E. 記憶體配置（每 GPU）
A46: hbmu | B46: 可用 HBM | C46: GB | D46: =D7*(1-IN_HBMres) -> 72 | E46: =E7*(1-IN_HBMres) -> 72 | F46: =F7*(1-IN_HBMres) -> 72 | G46: =G7*(1-IN_HBMres) -> 167.4 | H46: =H7*(1-IN_HBMres) -> 167.4 | I46: =I7*(1-IN_HBMres) -> 167.4 | J46: HBM 容量 ×（1 − 保留比例）
A47: tp | B47: 注意力 TP 度 | D47: =MAX(1,CEILING(D21*D12/(IN_NEcap*D46),1)) -> 1 | E47: =MAX(1,CEILING(E21*E12/(IN_NEcap*E46),1)) -> 2 | F47: =MAX(1,CEILING(F21*F12/(IN_NEcap*F46),1)) -> 4 | G47: =MAX(1,CEILING(G21*G12/(IN_NEcap*G46),1)) -> 1 | H47: =MAX(1,CEILING(H21*H12/(IN_NEcap*H46),1)) -> 1 | I47: =MAX(1,CEILING(I21*I12/(IN_NEcap*I46),1)) -> 2 | J47: 非專家權重放得下所需的最小切分數
A48: epx | B48: decode EP 寬度 | C48: GPU | D48: =MAX(D10,CEILING(D22*D11/(IN_Ecap*D46),1)) -> 64 | E48: =MAX(E10,CEILING(E22*E11/(IN_Ecap*E46),1)) -> 64 | F48: =MAX(F10,CEILING(F22*F11/(IN_Ecap*F46),1)) -> 138 | G48: =MAX(G10,CEILING(G22*G11/(IN_Ecap*G46),1)) -> 32 | H48: =MAX(H10,CEILING(H22*H11/(IN_Ecap*H46),1)) -> 32 | I48: =MAX(I10,CEILING(I22*I11/(IN_Ecap*I46),1)) -> 34 | J48: 專家權重放得下所需的最小 EP 寬度，不低於基準寬度
A49: wpg | B49: 每 GPU 權重 | C49: GB | D49: =D21*D12/D47+D22*D11/D48 -> 9.7649375 | E49: =E21*E12/E47+E22*E11/E48 -> 34.822049 | F49: =F21*F12/F47+F22*F11/F48 -> 40.898054 | G49: =G21*G12/G47+G22*G11/G48 -> 10.309055 | H49: =H21*H12/H47+H22*H11/H48 -> 48.046332 | I49: =I21*I12/I47+I22*I11/I48 -> 89.900898
A50: F. Prefill
A51: ptok | B51: prefill tok/s（每 prefill GPU） | C51: tok/s | D51: =D37*D6*1000000000000000/(D44*1000000000) -> 7754.8726 | E51: =E37*E6*1000000000000000/(E44*1000000000) -> 2234.3238 | F51: =F37*F6*1000000000000000/(F44*1000000000) -> 673.50594 | G51: =G37*G6*1000000000000000/(G44*1000000000) -> 78411.249 | H51: =H37*H6*1000000000000000/(H44*1000000000) -> 22591.748 | I51: =I37*I6*1000000000000000/(I44*1000000000) -> 6809.969 | J51: η_p × 峰值 ÷ 每 token FLOPs（prefill 為算力受限）
A52: ttftv | B52: TTFT（只計新鮮輸入） | C52: s | D52: =(D32*(1-IN_Chi))*D44*1000000000/(D37*D6*1000000000000000*D13) -> 0.059420706 | E52: =(E32*(1-IN_Chi))*E44*1000000000/(E37*E6*1000000000000000*E13) -> 0.41247378 | F52: =(F32*(1-IN_Chi))*F44*1000000000/(F37*F6*1000000000000000*F13) -> 2.7367242 | G52: =(G32*(1-IN_Chi))*G44*1000000000/(G37*G6*1000000000000000*G13) -> 0.011753416 | H52: =(H32*(1-IN_Chi))*H44*1000000000/(H37*H6*1000000000000000*H13) -> 0.081587314 | I52: =(I32*(1-IN_Chi))*I44*1000000000/(I37*I6*1000000000000000*I13) -> 0.54132405 | J52: ISL ×（1 − χ）× FLOPs ÷（η_p × 峰值 × prefill 實例 GPU 數）
A53: ttok | B53: TTFT 符合上限 | D53: =IF(D52<=D31,"是","否") -> 是 | E53: =IF(E52<=E31,"是","否") -> 是 | F53: =IF(F52<=F31,"是","否") -> 是 | G53: =IF(G52<=G31,"是","否") -> 是 | H53: =IF(H52<=H31,"是","否") -> 是 | I53: =IF(I52<=I31,"是","否") -> 是
A54: G. Decode：每步時間＝固定延遲 ＋ B ×每序列時間；在 SLO 下解出批次 B*
A55: fix | B55: 每步固定延遲（權重讀取＋逐層延遲） | C55: ms | D55: =D49/D8+(D18+IN_MTP_N)*D39/1000 -> 14.036695 | E55: =E49/E8+(E18+IN_MTP_N)*E39/1000 -> 25.868434 | F55: =F49/F8+(F18+IN_MTP_N)*F39/1000 -> 37.111509 | G55: =G49/G8+(G18+IN_MTP_N)*G39/1000 -> 8.7031574 | H55: =H49/H8+(H18+IN_MTP_N)*H39/1000 -> 16.321653 | I55: =I49/I8+(I18+IN_MTP_N)*I39/1000 -> 27.839702 | J55: 每 GPU 權重 ÷ HBM 頻寬 ＋（層數 ＋ 草稿數）× 每層延遲
A56: sc | B56: 每序列每步：算力項 | C56: ms | D56: =(IN_MTP_N+1)*D42/(D6*D38)/1000 -> 1.8244126 | E56: =(IN_MTP_N+1)*E42/(E6*E38)/1000 -> 6.2831269 | F56: =(IN_MTP_N+1)*F42/(F6*F38)/1000 -> 25.020422 | G56: =(IN_MTP_N+1)*G42/(G6*G38)/1000 -> 0.37674913 | H56: =(IN_MTP_N+1)*H42/(H6*H38)/1000 -> 1.297493 | I56: =(IN_MTP_N+1)*I42/(I6*I38)/1000 -> 5.166826 | J56: （N＋1）× decode FLOPs ÷（峰值 × η_d）——η_d 在這裡起作用
A57: skv | B57: 每序列每步：KV 讀取項 | C57: ms | D57: =D23*D34/(D8*IN_KVeff)/1000000000 -> 0.010374277 | E57: =E23*E34/(E8*IN_KVeff)/1000000000 -> 0.029433996 | F57: =F23*F34/(F8*IN_KVeff)/1000000000 -> 0.85518192 | G57: =G23*G34/(G8*IN_KVeff)/1000000000 -> 0.0043442286 | H57: =H23*H34/(H8*IN_KVeff)/1000000000 -> 0.012325486 | I57: =I23*I34/(I8*IN_KVeff)/1000000000 -> 0.35810743 | J57: KV bytes × 上下文 ÷（頻寬 × 效率）
A58: sep | B58: 每序列每步：EP 通訊項 | C58: ms | D58: =(IN_MTP_N+1)*D18*D20*D19*IN_EPbytes*(D48-1)/D48/(D9*IN_EPeff)/1000000000 -> 0.3566592 | E58: =(IN_MTP_N+1)*E18*E20*E19*IN_EPbytes*(E48-1)/E48/(E9*IN_EPeff)/1000000000 -> 0.8854272 | F58: =(IN_MTP_N+1)*F18*F20*F19*IN_EPbytes*(F48-1)/F48/(F9*IN_EPeff)/1000000000 -> 6.691999 | G58: =(IN_MTP_N+1)*G18*G20*G19*IN_EPbytes*(G48-1)/G48/(G9*IN_EPeff)/1000000000 -> 0.019499886 | H58: =(IN_MTP_N+1)*H18*H20*H19*IN_EPbytes*(H48-1)/H48/(H9*IN_EPeff)/1000000000 -> 0.0484096 | I58: =(IN_MTP_N+1)*I18*I20*I19*IN_EPbytes*(I48-1)/I48/(I9*IN_EPeff)/1000000000 -> 0.36347697
A59: sq | B59: 每序列每步（三者取最大，假設可重疊） | C59: ms | D59: =MAX(D56,D57,D58) -> 1.8244126 | E59: =MAX(E56,E57,E58) -> 6.2831269 | F59: =MAX(F56,F57,F58) -> 25.020422 | G59: =MAX(G56,G57,G58) -> 0.37674913 | H59: =MAX(H56,H57,H58) -> 1.297493 | I59: =MAX(I56,I57,I58) -> 5.166826
A60: bslo | B60: SLO 允許的批次上限 | C60: 序列/GPU | D60: =(1000*D36/D30-D55)/D59 -> 8.7758293 | E60: =(1000*E36/E30-E55)/E59 -> 5.1908328 | F60: =(1000*F36/F30-F55)/F59 -> 0.9961519 | G60: =(1000*G36/G30-G55)/G59 -> 56.653803 | H60: =(1000*H36/H30-H55)/H59 -> 32.494542 | I60: =(1000*I36/I30-I55)/I59 -> 6.6183665 | J60: 每用戶速度 ≥ SLO：a ÷（固定＋B×每序列）≥ SLO → B ≤（1000a/SLO − 固定）÷ 每序列
A61: bhbm | B61: HBM 容量允許的批次上限 | C61: 序列/GPU | D61: =(D46-D49)*1000000000/(D23*D34) -> 2558.1997 | E61: =(E46-E49)*1000000000/(E23*E34) -> 538.63353 | F61: =(F46-F49)*1000000000/(F23*F34) -> 15.509086 | G61: =(G46-G49)*1000000000/(G23*G34) -> 6457.2925 | H61: =(H46-H49)*1000000000/(H23*H34) -> 1729.1939 | I61: =(I46-I49)*1000000000/(I23*I34) -> 38.645178 | J61: （可用 HBM − 權重）÷ 每序列 KV
A62: bst | B62: 採用批次 B* | C62: 序列/GPU | D62: =MAX(0,MIN(D60,D61)) -> 8.7758293 | E62: =MAX(0,MIN(E60,E61)) -> 5.1908328 | F62: =MAX(0,MIN(F60,F61)) -> 0.9961519 | G62: =MAX(0,MIN(G60,G61)) -> 56.653803 | H62: =MAX(0,MIN(H60,H61)) -> 32.494542 | I62: =MAX(0,MIN(I60,I61)) -> 6.6183665
A63: dtok | B63: decode tok/s（每 decode GPU） | C63: tok/s | D63: =IF(D62>0,D62*D36/((D55+D62*D59)/1000),0) -> 739.80293 | E63: =IF(E62>0,E62*E36/((E55+E62*E59)/1000),0) -> 224.82359 | F63: =IF(F62>0,F62*F36/((F55+F62*F59)/1000),0) -> 40.674237 | G63: =IF(G62>0,G62*G36/((G55+G62*G59)/1000),0) -> 4775.919 | H63: =IF(H62>0,H62*H36/((H55+H62*H59)/1000),0) -> 1407.3926 | I63: =IF(I62>0,I62*I36/((I55+I62*I59)/1000),0) -> 270.23691 | J63: B* × a ÷ 每步時間
A64: H. 每架與每 GW（100% 利用率）
A65: gps | B65: 每請求 GPU 秒 | C65: GPU-s | D65: =(D32*(1-IN_Chi))/D51+D33/D63 -> 1.859518 | E65: =(E32*(1-IN_Chi))/E51+E33/E63 -> 12.409155 | F65: =(F32*(1-IN_Chi))/F51+F33/F63 -> 122.59636 | G65: =(G32*(1-IN_Chi))/G51+G33/G63 -> 0.26142266 | H65: =(H32*(1-IN_Chi))/H51+H33/H63 -> 1.7815225 | I65: =(I32*(1-IN_Chi))/I51+I33/I63 -> 17.322367 | J65: 新鮮輸入 ÷ prefill 速度 ＋ 輸出 ÷ decode 速度（快取命中的輸入不計 prefill）
A66: rack | B66: 每架總 tok/s（輸入＋輸出） | C66: tok/s | D66: =D14*(D32+D33)/D65 -> 158595.93 | E66: =E14*(E32+E33)/E65 -> 47531.361 | F66: =F14*(F32+F33)/F65 -> 9622.2108 | G66: =G14*(G32+G33)/G65 -> 2538234.4 | H66: =H14*(H32+H33)/H65 -> 744926.9 | I66: =I14*(I32+I33)/I65 -> 153224.32 | J66: GPU 數 ×（ISL＋OSL）÷ 每請求 GPU 秒
A67: tokgw | B67: 每 GW 年總產出（100% 利用率） | C67: M tok/年 | D67: =D66*D15*8760*3600/1000000 -> 1.1222824e+11 | E67: =E66*E15*8760*3600/1000000 -> 3.3634916e+10 | F67: =F66*F15*8760*3600/1000000 -> 6.8090257e+09 | G67: =G66*G15*8760*3600/1000000 -> 5.5783891e+11 | H67: =H66*H15*8760*3600/1000000 -> 1.6371585e+11 | I67: =I66*I15*8760*3600/1000000 -> 3.3674782e+10 | J67: 每架 tok/s × 每 GW 機架數 × 一年秒數 ÷ 10^6 → 即 Tokenomics 的 IF_TokGW_*
B68: 對照：Tokenomics v17.0 原值（Perf 第 98 列） | D68: 1.1222824e+11 | E68: 3.3634916e+10 | F68: 6.8090257e+09 | G68: 5.5783891e+11 | H68: 1.6371585e+11 | I68: 3.3674782e+10
B69: 差異（本頁 ÷ 原值 − 1） | D69: =D67/D68-1 -> -5.9952043e-15 | E69: =E67/E68-1 -> 0 | F69: =F67/F68-1 -> 0 | G69: =G67/G68-1 -> 0 | H69: =H67/H68-1 -> -3.7747583e-15 | I69: =I67/I68-1 -> 0

Sheet 6_敏感度
A1: m 的單變數敏感度（在 v15.3 執行；m 的 2,993 個前置格 v17.0 與 v15.3 逐格相同，結果仍適用。每個輸入改到 Gov_Map 低端與高端，各以 LibreOffice 重算整本 Tokenomics 一次）
A2: 藍字＝重算結果（數值）；承重度＝弧彈性 ln(m高/m低) ÷ ln(輸入高/輸入低)；擺動＝|m高 − m低| ÷ m 基準。只測單一變數，未測交互作用。
A4: # | B4: 輸入 | C4: 活頁簿位置 | D4: 低值 | E4: 高值 | F4: m（低值） | G4: m（高值） | H4: 承重度 | I4: 擺動 | J4: 排名 | K4: 說明
B5: m 基準（v15.3 重算重現；＝v17.0 值） | F5: 0.46000311
A6: 1 | B6: Astra 2025 單價 | C6: Cap_In!C280 | D6: 3.3 | E6: 5.9 | F6: 0.51450584 | G6: 0.40940566 | H6: =IF(OR(D6<=0,E6<=0,F6<=0,G6<=0),"—",LN(G6/F6)/LN(E6/D6)) -> -0.39326794 | I6: =ABS(G6-F6)/$F$5 -> 0.22847713 | J6: =RANK(I6,$I$6:$I$32) -> 11 | K6: 用量加權（B2）；推理占比曲線為 Assumed
A7: 2 | B7: GB200 η_d 倍數 | C7: Calib!D67 | D7: 0.9 | E7: 1.45 | F7: 0.5385147 | G7: 0.39568964 | H7: =IF(OR(D7<=0,E7<=0,F7<=0,G7<=0),"—",LN(G7/F7)/LN(E7/D7)) -> -0.64619225 | I7: =ABS(G7-F7)/$F$5 -> 0.31048718 | J7: =RANK(I7,$I$6:$I$32) -> 10 | K7: MLPerf v6.0 同軟體配對（B3）
A8: 3 | B8: 請求形狀 κ | C8: Alloc_In!C26 | D8: 0.65 | E8: 1.2 | F8: 0.70769709 | G8: 0.38333592 | H8: =IF(OR(D8<=0,E8<=0,F8<=0,G8<=0),"—",LN(G8/F8)/LN(E8/D8)) -> -1 | I8: =ABS(G8-F8)/$F$5 -> 0.70512821 | J8: =RANK(I8,$I$6:$I$32) -> 1 | K8: 證據範圍 0.67–1.05
A9: 4 | B9: 實際利用率 | C9: Alloc_In!C24 | D9: 0.3 | E9: 0.65 | F9: 0.62867091 | G9: 0.33914788 | H9: =IF(OR(D9<=0,E9<=0,F9<=0,G9<=0),"—",LN(G9/F9)/LN(E9/D9)) -> -0.79821488 | I9: =ABS(G9-F9)/$F$5 -> 0.62939364 | J9: =RANK(I9,$I$6:$I$32) -> 2 | K9: 無實測
A10: 5 | B10: 計價倍數 | C10: Alloc_In!C23 | D10: 0.73 | E10: 1.17 | F10: 0.39506149 | G10: 0.63318075 | H10: =IF(OR(D10<=0,E10<=0,F10<=0,G10<=0),"—",LN(G10/F10)/LN(E10/D10)) -> 1 | I10: =ABS(G10-F10)/$F$5 -> 0.51764706 | J10: =RANK(I10,$I$6:$I$32) -> 3 | K10: Microsoft 對 OpenAI 計價未找到
A11: 6 | B11: Astra 啟用參數 | C11: Arch!E7 | D11: 60 | E11: 250 | F11: 0.32201486 | G11: 0.52600642 | H11: =IF(OR(D11<=0,E11<=0,F11<=0,G11<=0),"—",LN(G11/F11)/LN(E11/D11)) -> 0.34385124 | I11: =ABS(G11-F11)/$F$5 -> 0.44345692 | J11: =RANK(I11,$I$6:$I$32) -> 5 | K11: 頂層模型參數未揭露
A12: 7 | B12: 有效折扣 | C12: Cap_In!C12 | D12: 0.1 | E12: 0.4 | F12: 0.40889165 | G12: 0.61333747 | H12: =IF(OR(D12<=0,E12<=0,F12<=0,G12<=0),"—",LN(G12/F12)/LN(E12/D12)) -> 0.29248125 | I12: =ABS(G12-F12)/$F$5 -> 0.44444444 | J12: =RANK(I12,$I$6:$I$32) -> 4 | K12: Batch 半價為牌價；占比與企業折扣找不到
A13: 8 | B13: Sol 參考 ISL | C13: Serving!D23 | D13: 8192 | E13: 68000 | F13: 0.55435404 | G13: 0.37316059 | H13: =IF(OR(D13<=0,E13<=0,F13<=0,G13<=0),"—",LN(G13/F13)/LN(E13/D13)) -> -0.18701762 | I13: =ABS(G13-F13)/$F$5 -> 0.39389614 | J13: =RANK(I13,$I$6:$I$32) -> 6 | K13: Sol 參考請求輸入長度；與 κ 同屬流量形狀（7 頁第 1 項）
A14: 9 | B14: 生產折減 | C14: Serving!C28 | D14: 0.7 | E14: 1 | F14: 0.5585752 | G14: 0.39100264 | H14: =IF(OR(D14<=0,E14<=0,F14<=0,G14<=0),"—",LN(G14/F14)/LN(E14/D14)) -> -1 | I14: =ABS(G14-F14)/$F$5 -> 0.36428571 | J14: =RANK(I14,$I$6:$I$32) -> 7 | K14: 情境值，非估計值
A15: 10 | B15: Sol 參考 OSL | C15: Serving!D24 | D15: 1024 | E15: 4096 | F15: 0.40376534 | G15: 0.55559624 | H15: =IF(OR(D15<=0,E15<=0,F15<=0,G15<=0),"—",LN(G15/F15)/LN(E15/D15)) -> 0.23025988 | I15: =ABS(G15-F15)/$F$5 -> 0.33006495 | J15: =RANK(I15,$I$6:$I$32) -> 9 | K15: 同上（輸出長度）
A16: 11 | B16: 服務世代組合 Hopper | C16: Alloc_In!C9；Alloc_In!C10 | D16: 0.5；0.5 | E16: 0.7；0.3 | F16: 0.39533131 | G16: 0.54798592 | H16: — | I16: =ABS(G16-F16)/$F$5 -> 0.33185559 | J16: =RANK(I16,$I$6:$I$32) -> 8 | K16: 無區間；chat 端暫設 0.5–0.7，不算彈性
A17: 12 | B17: 推論支出 SRC_DEM_004 | C17: SRC_Demand!C8 | D17: 7.5 | E17: 8.8 | F17: 0.51520348 | G17: 0.43909387 | H17: =IF(OR(D17<=0,E17<=0,F17<=0,G17<=0),"—",LN(G17/F17)/LN(E17/D17)) -> -1 | I17: =ABS(G17-F17)/$F$5 -> 0.16545455 | J17: =RANK(I17,$I$6:$I$32) -> 15 | K17: 查核營業成本 7.5～投資人文件 8.8
A18: 13 | B18: 快取命中 χ | C18: Cap_In!C13 | D18: 0.3 | E18: 0.75 | F18: 0.50336469 | G18: 0.42515025 | H18: =IF(OR(D18<=0,E18<=0,F18<=0,G18<=0),"—",LN(G18/F18)/LN(E18/D18)) -> -0.18429991 | I18: =ABS(G18-F18)/$F$5 -> 0.17003024 | J18: =RANK(I18,$I$6:$I$32) -> 14
A19: 14 | B19: Sol 2025 單價 | C19: Cap_In!C279 | D19: 1.672 | E19: 2.338 | F19: 0.53216046 | G19: 0.44197754 | H19: =IF(OR(D19<=0,E19<=0,F19<=0,G19<=0),"—",LN(G19/F19)/LN(E19/D19)) -> -0.55383132 | I19: =ABS(G19-F19)/$F$5 -> 0.1960485 | J19: =RANK(I19,$I$6:$I$32) -> 12
A20: 15 | B20: 免費占 ChatGPT token | C20: Alloc_In!C16 | D20: 0.4 | E20: 0.8 | F20: 0.43193304 | G20: 0.50131378 | H20: =IF(OR(D20<=0,E20<=0,F20<=0,G20<=0),"—",LN(G20/F20)/LN(E20/D20)) -> 0.21490621 | I20: =ABS(G20-F20)/$F$5 -> 0.15082668 | J20: =RANK(I20,$I$6:$I$32) -> 17
A21: 16 | B21: WACC | C21: Inputs!E28 | D21: 0.08 | E21: 0.13 | F21: 0.4334818 | G21: 0.50146604 | H21: =IF(OR(D21<=0,E21<=0,F21<=0,G21<=0),"—",LN(G21/F21)/LN(E21/D21)) -> 0.30006949 | I21: =ABS(G21-F21)/$F$5 -> 0.14779083 | J21: =RANK(I21,$I$6:$I$32) -> 18
A22: 17 | B22: η_p | C22: Calib!C5 | D22: 0.15 | E22: 0.45 | F22: 0.39700084 | G22: 0.475461 | H22: =IF(OR(D22<=0,E22<=0,F22<=0,G22<=0),"—",LN(G22/F22)/LN(E22/D22)) -> 0.16415842 | I22: =ABS(G22-F22)/$F$5 -> 0.17056441 | J22: =RANK(I22,$I$6:$I$32) -> 13
A23: 18 | B23: 每則提示 token τ | C23: Alloc_In!C15 | D23: 2000 | E23: 11000 | F23: 0.43563783 | G23: 0.50137389 | H23: =IF(OR(D23<=0,E23<=0,F23<=0,G23<=0),"—",LN(G23/F23)/LN(E23/D23)) -> 0.082440844 | I23: =ABS(G23-F23)/$F$5 -> 0.14290351 | J23: =RANK(I23,$I$6:$I$32) -> 19
A24: 19 | B24: Hopper η_d 倍數 | C24: Calib!C67 | D24: 0.8 | E24: 1.6 | F24: 0.49220351 | G24: 0.43543125 | H24: =IF(OR(D24<=0,E24<=0,F24<=0,G24<=0),"—",LN(G24/F24)/LN(E24/D24)) -> -0.17680999 | I24: =ABS(G24-F24)/$F$5 -> 0.12341712 | J24: =RANK(I24,$I$6:$I$32) -> 20
A25: 20 | B25: 基準利用率 IF_Util | C25: Serving!C17 | D25: 0.4 | E25: 0.8 | F25: 0.50872183 | G25: 0.46000311 | H25: =IF(OR(D25<=0,E25<=0,F25<=0,G25<=0),"—",LN(G25/F25)/LN(E25/D25)) -> -0.14523339 | I25: =ABS(G25-F25)/$F$5 -> 0.10590955 | J25: =RANK(I25,$I$6:$I$32) -> 21 | K25: 點估計不變（IF_Util 約掉）；低端 0.4 時 Tokenomics 的物理下限（上限讀法）0.509 高於點估計而綁定（m＝MAX(點估計, 下限)）
A26: 21 | B26: 付費層級組合 | C26: Cap_In!C31；Cap_In!D31；Cap_In!E31 | D26: 0.5；0.4；0.1 | E26: 0.3；0.5；0.2 | F26: 0.46871433 | G26: 0.45408085 | H26: — | I26: =ABS(G26-F26)/$F$5 -> 0.031811699 | J26: =RANK(I26,$I$6:$I$32) -> 26 | K26: 無正式區間；暫設，不算彈性
A27: 22 | B27: Hopper 每層延遲倍數 | C27: Calib!C68 | D27: 1 | E27: 1.5 | F27: 0.44060515 | G27: 0.46000311 | H27: =IF(OR(D27<=0,E27<=0,F27<=0,G27<=0),"—",LN(G27/F27)/LN(E27/D27)) -> 0.10625853 | I27: =ABS(G27-F27)/$F$5 -> 0.042169194 | J27: =RANK(I27,$I$6:$I$32) -> 24
A28: 23 | B28: Luna 2025 單價 | C28: Cap_In!C278 | D28: 0.0669 | E28: 0.3026 | F28: 0.46400085 | G28: 0.43940842 | H28: =IF(OR(D28<=0,E28<=0,F28<=0,G28<=0),"—",LN(G28/F28)/LN(E28/D28)) -> -0.036083091 | I28: =ABS(G28-F28)/$F$5 -> 0.053461446 | J28: =RANK(I28,$I$6:$I$32) -> 22
A29: 24 | B29: Hopper 機架單價 | C29: Spec_Rack!C12 | D29: 0.9 | E29: 1.3 | F29: 0.42353621 | G29: 0.49647 | H29: =IF(OR(D29<=0,E29<=0,F29<=0,G29<=0),"—",LN(G29/F29)/LN(E29/D29)) -> 0.43207328 | I29: =ABS(G29-F29)/$F$5 -> 0.15855065 | J29: =RANK(I29,$I$6:$I$32) -> 16
A30: 25 | B30: GB200 機架單價 | C30: Spec_Rack!D12 | D30: 2.8 | E30: 3.4 | F30: 0.44867739 | G30: 0.47132882 | H30: =IF(OR(D30<=0,E30<=0,F30<=0,G30<=0),"—",LN(G30/F30)/LN(E30/D30)) -> 0.25367165 | I30: =ABS(G30-F30)/$F$5 -> 0.049241922 | J30: =RANK(I30,$I$6:$I$32) -> 23
A31: 26 | B31: API 全年平均比 | C31: Alloc_In!C14 | D31: 0.6 | E31: 0.9 | F31: 0.46900213 | G31: 0.45298485 | H31: =IF(OR(D31<=0,E31<=0,F31<=0,G31<=0),"—",LN(G31/F31)/LN(E31/D31)) -> -0.085700658 | I31: =ABS(G31-F31)/$F$5 -> 0.034819936 | J31: =RANK(I31,$I$6:$I$32) -> 25
A32: 27 | B32: GB200 批次 η_d（不進機隊） | C32: Calib!D156 | D32: 1.59 | E32: 2.64 | F32: 0.46000311 | G32: 0.46000311 | H32: =IF(OR(D32<=0,E32<=0,F32<=0,G32<=0),"—",LN(G32/F32)/LN(E32/D32)) -> 0 | I32: =ABS(G32-F32)/$F$5 -> 0 | J32: =RANK(I32,$I$6:$I$32) -> 27 | K32: 批次口徑不進機隊產能

Sheet 7_不確定_搜尋
A1: 最不確定、可以「搜尋」解決的假設（公開資料或付費報導）
A2: 排序依據：對 m 的擺動 × 證據強度。分工：C＝chat 端可在公開網路找到；A線上＝Andy 在付費牆或需登入的來源找。擺動與承重度連結 6_敏感度。
A4: 優先 | B4: 假設 | C4: 現值（區間） | D4: 擺動 | E4: 承重度 | F4: 為什麼不確定 | G4: 要找的證據（找到就能定案的口徑） | H4: 可能來源與管道 | I4: 本串已做過的搜尋 | J4: 找到後要改的格 | K4: 分工
A5: 1 | B5: 請求形狀 κ 與實際流量形狀（含參考 ISL／OSL、快取命中） | C5: κ 1.0（0.65–1.2）；Sol ISL 16,384、OSL 2,048；χ 0.55 | D5: =6_敏感度!I8 -> 0.70512821 | E5: =6_敏感度!H8 -> -1 | F5: 擺動前五中的第一名。κ 由各類流量的 ISL／OSL／快取命中與 token 占比決定；API 與 ChatGPT 的 token 占比、agent 型流量比重都沒有一手數字 | G5: OpenAI 2025 年 API 與 ChatGPT 的 token 占比；各類請求平均輸入／輸出長度與快取命中率 | H5: OpenRouter《State of AI》與週報（代理值）；OpenAI DevDay；Anthropic Economic Index；NBER《How people use ChatGPT》 | I5: OpenRouter：prompt 1.5K→6K、completion 150→400、agent 快取約 88%（2026）；ChatGPT token 長度：已搜尋，未找到 | J5: Alloc_In C26（另有結構題：κ 與單價須同一流量形狀） | K5: C
A6: 2 | B6: 計價倍數（推論支出 ÷ 持有成本） | C6: 0.85（0.73–1.17） | D6: =6_敏感度!I10 -> 0.51764706 | E6: =6_敏感度!H10 -> 1 | F6: Microsoft 對 OpenAI 的實際計價（牌價、折扣或成本加成）未公開；現值由 Oracle 出租毛利 14% 與經濟／會計成本比推得 | G6: Microsoft 對 OpenAI 的 GPU 時價或折扣、Azure AI 毛利；OpenAI–Oracle、OpenAI–CoreWeave 合約的每 GW 年單價 | H6: The Information、FT（付費）；Microsoft 10-K／法說會（Azure 毛利）；Oracle RPO 揭露；CoreWeave 10-K | I6: 只找到 Zitron 文件與 The Register 轉述；計價條款在付費報導 | J6: Alloc_In C23 | K6: A線上
A7: 3 | B7: Astra 啟用參數 | C7: 180B（60–250B） | D7: =6_敏感度!I11 -> 0.44345692 | E7: =6_敏感度!H11 -> 0.34385124 | F7: 頂層模型參數從未揭露 | G7: 第三方對 GPT-5／GPT-6 級頂層模型啟用參數的估計，或延遲／價格反推 | H7: Epoch AI；學術估計；推理速度反推 | I7: Epoch 1.0e27 FLOP（叢集總算力上限）；啟用參數：只有第三方估計 | J7: Arch E7（Perf Astra 欄） | K7: C（專家意見）
A8: 4 | B8: Astra 2025 單價（用量加權） | C8: 4.5（3.3–5.9）$/M | D8: =6_敏感度!I6 -> 0.22847713 | E8: =6_敏感度!H6 -> -0.39326794 | F8: 各模型 token 占比完全未公開；目前以 Azure 季別支出當量指數、再假設 GPT-5 後推理占比 ×2 | G8: 2025 年 OpenAI API 與 ChatGPT 中 o1／o3／GPT-5 thinking 對 4o／4.1／GPT-5 的 token 或訊息占比，按月或按季 | H8: The Information、FT、SemiAnalysis（付費；後者不可單獨使用）；OpenRouter 模型排行歷史（代理值）；OpenAI 官方部落格與 DevDay 數字 | I8: Altman 2025-08 推理模型日用比例（用戶比例，非 token）；OpenRouter 推理模型占比年初≈0→年底 >50%；各模型 token 占比：已搜尋，未找到 | J8: Cap_In C280／D280／E280 | K8: A線上＋C
A9: 5 | B9: Sol 2025 單價的加權 | C9: 2.184（1.672–2.338）$/M | D9: =6_敏感度!I19 -> 0.1960485 | E9: =6_敏感度!H19 -> -0.55383132 | F9: ChatGPT 預設與 API 主力的 token 比例是 Assumed（2,365：1,460） | G9: 2025 年 ChatGPT 付費 token 對 API token 的比例 | H9: 同第 1、3 項 | I9: 同第 1 項 | J9: Cap_In C279 | K9: C
A10: 6 | B10: 推論支出的記帳口徑 | C10: 8.4（7.5–8.8）$B | D10: =6_敏感度!I17 -> 0.16545455 | E10: =6_敏感度!H17 -> -1 | F10: 營收分成記在營業成本或營收減項不明；免費推論是否在營業成本外不明 | G10: OpenAI 營收分成的會計處理；營業成本組成；免費用戶推論的科目 | H10: OpenAI 若 IPO 的招股文件；FT／The Information 對查核財報的後續報導；Microsoft 10-K 附註 | I10: 查核財報分項（付 Microsoft 172 億）已取得；營收分成記帳位置：已搜尋，未找到 | J10: SRC_Demand C8（SRC_DEM_004） | K10: A線上
A11: 7 | B11: Hopper η_d 倍數 | C11: 1.2（0.8–1.6） | D11: =6_敏感度!I24 -> 0.12341712 | E11: =6_敏感度!H24 -> -0.17680999 | F11: Hopper 吞吐被判為保守下界（獨立對照約實測 0.26–0.27 倍）；MLPerf closed 組沒有 DeepSeek-R1 的 H100／H200 提交 | G11: 同模型、同軟體的 H100／H200 對 GB200 decode 實測（中段互動性） | H11: MLPerf 下一輪；vLLM／SGLang 部落格；InferenceX（不可單獨使用） | I11: MLPerf closed 組確認無 H100／H200 DSR1 提交；405B 跨精度推算 1.3–1.8 | J11: Calib C67 | K11: C
A12: 8 | B12: 每則提示 token τ 與免費占比 | C12: τ 4,000（2,000–11,000）；免費 0.6（0.4–0.8） | D12: =6_敏感度!I23 -> 0.14290351 | E12: =6_敏感度!H23 -> 0.082440844 | F12: τ 只影響 r（免費 ÷ 付費 token 比）；token 口徑的免費占比與支出口徑 46% 混用 | G12: ChatGPT 每則對話的平均 token（含推理）；免費用戶 token 占比 | H12: NBER《How people use ChatGPT》（訊息數，無 token）；OpenAI 官方；WildChat 類比 | I12: WildChat 每回合約 296 入／441 出（類比）；ChatGPT token 長度：已搜尋，未找到 | J12: Alloc_In C15、C16 | K12: C

Sheet 8_不確定_實地調研
A1: 最不確定、需要「實地調研」的假設（業者訪談、供應鏈查核；公開資料找不到）
A2: A線下＝Andy 線下調研。資料放 Drive 02-算力收支/Tokenomics/inbox/，chat 端直接讀。
A4: 優先 | B4: 假設 | C4: 現值（區間） | D4: 擺動 | E4: 承重度 | F4: 為什麼不確定 | G4: 要問的問題（可直接用於訪談） | H4: 訪談或查核對象 | I4: 找到後要改的格 | J4: 分工
A5: 1 | B5: 實際利用率（純） | C5: 0.41（0.30–0.65） | D5: =6_敏感度!I9 -> 0.62939364 | E5: =6_敏感度!H9 -> -0.79821488 | F5: 沒有任何實驗室公開「token 吞吐 ÷ 容量」實測；上端只有 DeepSeek 2025-02 單一模型代理值 | G5: 大型推論叢集的平均 GPU 利用率（以 token 吞吐 ÷ 理論容量計，不是 GPU busy%）？日夜與尖離峰差多少？多模型部署時下降多少？ | H5: 雲端或 neocloud 營運人員（CoreWeave、Nebius、Azure、Oracle）；推論平台（Fireworks、Together、Baseten）；台灣雲端業者 | I5: Alloc_In C24 | J5: A線下
A6: 2 | B6: Batch／Flex 占比與企業折扣 | C6: 有效折扣 0.2（0.1–0.4） | D6: =6_敏感度!I12 -> 0.44444444 | E6: =6_敏感度!H12 -> 0.29248125 | F6: Batch 半價是公開牌價，但占比與企業議價找不到 | G6: API 用量中 Batch／Flex 的占比？大型企業合約相對牌價的平均折扣？ | H6: API 大客戶（企業、新創）；OpenAI 業務；雲端市集 | I6: Cap_In C12 | J6: A線下
A7: 3 | B7: 生產折減（SLO 預留、故障、重啟） | C7: 0.85（0.70–1.00） | D7: =6_敏感度!I14 -> 0.36428571 | E7: =6_敏感度!H14 -> -1 | F7: 情境值，非估計值；只有訓練端的公開可靠度論文可類比 | G7: 推論叢集為了守住 SLO 預留多少容量？節點故障、重啟、升級造成的產能損失約多少？ | H7: 雲端 SRE／推論平台營運；GPU 雲業者 | I7: Serving C28 | J7: A線下
A8: 4 | B8: 2025 服務世代組合（Hopper／GB200） | C8: Hopper 0.6／GB200 0.4（暫設 0.5–0.7） | D8: =6_敏感度!I16 -> 0.33185559 | E8: =6_敏感度!H16 -> — | F8: 無公開數字；GB200 在 2025 年各季的上線量與 OpenAI 分到的比例都不明 | G8: Microsoft、Oracle、CoreWeave 為 OpenAI 部署的 GB200 機櫃在 2025 年各季的出貨與上線數？同期 Hopper 機隊規模？ | H8: 台灣 ODM／機櫃供應鏈（廣達、緯穎、鴻海）；機房業者；SemiAnalysis 付費報告（不可單獨使用） | I8: Alloc_In C9、C10 | J8: A線下＋A線上
A9: 5 | B9: 機架價格（GB200 NVL72、H100） | C9: H100 1.1（0.9–1.3）$M；GB200 3.1（2.8–3.4）$M（擺動欄為 H100） | D9: =6_敏感度!I29 -> 0.15855065 | E9: =6_敏感度!H29 -> 0.43207328 | F9: 產業報導與 ODM 報價差異大；直接決定每 GW 持有成本（m 對持有成本彈性 +1） | G9: 2025 年 GB200 NVL72 整櫃成交價（含 NVLink、液冷）？大客戶折扣？ | H9: ODM、通路與系統整合商；伺服器採購人員 | I9: Spec_Rack C12、D12 | J9: A線下
A10: 6 | B10: Hopper 實際 decode 效率 | C10: η_d 倍數 1.2（0.8–1.6） | D10: =6_敏感度!I24 -> 0.12341712 | E10: =6_敏感度!H24 -> -0.17680999 | F10: 模型 Hopper 吞吐約為獨立實測的 0.26–0.27 倍（保守下界） | G10: 同一模型在 H100／H200 與 GB200 上，生產環境的 decode tok/s/GPU 比？ | H10: 推論平台工程師；雲端效能團隊 | I10: Calib C67 | J10: A線下
